Workbook
Name маг: NA()

Sheet Ялта, Ленина, 18
B1: =TODAY()-1 -> 46171
B2: (отчетная дата)
C3: Осталось до выполнения плана!!! | I3: =График!B3 -> ул. Набережная Ленина, 18
C4: =I8-D56 -> 698754.6 | E4: =IF(I8<>0, C4/I8, 0) -> 0.28416607
D5: =C4/(I14-J14) -> #DIV/0!
F6: Целевые показатели
F7: Показатель | I7: План | J7: Факт | K7: % выполнения | L7: Прогноз выполнения | M7: % выполнения по прогнозу | N7: Отклонение | O7: Факт аналогичного месяца прошлого года | P7: Отклонение LFL
F8: Выручка | I8: =I11*I12*I13 -> 2458965.6 | J8: =D56 -> 1760211 | K8: =IF(AND(I8<>"",I8<>0,J8<>""),J8/I8,"") -> 0.71583393 | L8: =IF(SUMIF($D$25:$D$55,">=0",$U$25:$U$55)<>0,I8*D56/SUMIF($D$25:$D$55,">=0",$U$25:$U$55),0) -> 1760211 | M8: =IF(AND(I8<>"", I8<>0, L8<>"", L8<>0), L8/I8, "") -> 0.71583393 | N8: =IF(AND(J8<>0, J8<>"", I8<>0, I8<>""), L8-I8, "") -> -698754.6 | O8: 2068738.6 | P8: =IF(AND(O8<>"", O8<>0, L8<>"", L8<>0), -O8+L8, "") -> -308527.6 | Q8: =IF(AND(P8<>"",P8<>0,O8<>0,O8<>""),P8/O8,"") -> -0.14913803
F9: Кол-во изделий | I9: =I8/I11 -> 353.808 | J9: =E56 -> 230 | K9: =IF(AND(I9<>"", I9<>0, J9<>""), J9/I9, "") -> 0.65007009 | L9: =IF(SUMIF($E$25:$E$55,">=0",$V$25:$V$55)<>0,I9*E56/SUMIF($E$25:$E$55,">=0",$V$25:$V$55),0) -> 230 | M9: =IF(AND(I9<>"", I9<>0, L9<>"", L9<>0), L9/I9, "") -> 0.65007009 | N9: =IF(AND(J9<>0, J9<>"", I9<>0, I9<>""), L9-I9, "") -> -123.808 | O9: 390 | P9: =IF(AND(O9<>"", O9<>0, L9<>"", L9<>0), -O9+L9, "") -> -160 | Q9: =IF(AND(P9<>"",P9<>0,O9<>0,O9<>""),P9/O9,"") -> -0.41025641
F10: Средний чек | I10: =I11*I12 -> 12649 | J10: =H56 -> 13234.669 | K10: =IF(AND(I10<>"", I10<>0, J10<>""), J10/I10, "") -> 1.0463016 | L10: =J10 -> 13234.669 | M10: =IF(AND(I10<>"", I10<>0, L10<>"", L10<>0), L10/I10, "") -> 1.0463016 | N10: =IF(AND(J10<>0, J10<>"", I10<>0, I10<>""), L10-I10, "") -> 585.66917 | O10: 10608.916 | P10: =IF(AND(O10<>"", O10<>0, L10<>"", L10<>0), -O10+L10, "") -> 2625.7533 | Q10: =IF(AND(P10<>"",P10<>0,O10<>0,O10<>""),P10/O10,"") -> 0.24750439
F11: Средняя стоимость изделия | I11: 6950 | J11: =F56 -> 7653.0913 | K11: =IF(AND(I11<>"", I11<>0, J11<>""), J11/I11, "") -> 1.1011642 | L11: =IF(L9>0, L8/L9, "") -> 7653.0913 | M11: =IF(AND(I11<>"", I11<>0, L11<>"", L11<>0), L11/I11, "") -> 1.1011642 | N11: =IF(AND(J11<>0, J11<>"", I11<>0, I11<>""), L11-I11, "") -> 703.0913 | O11: 5304.4579 | P11: =IF(AND(O11<>"", O11<>0, L11<>"", L11<>0), -O11+L11, "") -> 2348.6334 | Q11: =IF(AND(P11<>"",P11<>0,O11<>0,O11<>""),P11/O11,"") -> 0.44276595
F12: Длина чека | I12: 1.82 | J12: =J56 -> 1.7293233 | K12: =IF(AND(I12<>"", I12<>0, J12<>""), J12/I12, "") -> 0.95017764 | L12: =J12 -> 1.7293233 | M12: =IF(AND(I12<>"", I12<>0, L12<>"", L12<>0), L12/I12, "") -> 0.95017764 | N12: =IF(AND(J12<>0, J12<>"", I12<>0, I12<>""), L12-I12, "") -> -0.090676692 | O12: 2 | P12: =IF(AND(O12<>"", O12<>0, L12<>"", L12<>0), -O12+L12, "") -> -0.27067669 | Q12: =IF(AND(P12<>"",P12<>0,O12<>0,O12<>""),P12/O12,"") -> -0.13533835
F13: Кол-во чеков | I13: =I17*I20 -> 194.4 | J13: =G56 -> 133 | K13: =IF(AND(I13<>"", I13<>0, J13<>""), J13/I13, "") -> 0.68415638 | L13: =IF(SUMIF($G$25:$G$55,">=0",$W$25:$W$55)<>0,I13*G56/SUMIF($G$25:$G$55,">=0",$W$25:$W$55),"") -> 133 | M13: =IF(AND(I13<>"", I13<>0, L13<>"", L13<>0), L13/I13, "") -> 0.68415638 | N13: =IF(AND(J13<>0, J13<>"", I13<>0, I13<>""), L13-I13, "") -> -61.4 | O13: 195 | P13: =IF(AND(O13<>"", O13<>0, L13<>"", L13<>0), -O13+L13, "") -> -62 | Q13: =IF(AND(P13<>"",P13<>0,O13<>0,O13<>""),P13/O13,"") -> -0.31794872
F14: Кол-во смен | I14: =График!AK6 -> 30 | J14: 30 | K14: =IF(AND(I14<>"", I14<>0, J14<>""), J14/I14, "") -> 1 | L14: =I14 -> 30 | M14: =IF(AND(I14<>"", I14<>0, L14<>"", L14<>0), L14/I14, "") -> 1 | N14: =IF(AND(J14<>0, J14<>"", I14<>0, I14<>""), L14-I14, "") -> 0 | O14: 30 | P14: =IF(AND(O14<>"", O14<>0, L14<>"", L14<>0), -O14+L14, "") -> 0 | Q14: =IF(AND(P14<>"",P14<>0,O14<>0,O14<>""),P14/O14,"")
F15: Средние продажи в смену | I15: =I8/I14 -> 81965.52 | J15: =J8/J14 -> 58673.7 | K15: =IF(AND(I15<>"", I15<>0, J15<>""), J15/I15, "") -> 0.71583393 | L15: =J15 -> 58673.7 | M15: =IF(AND(I15<>"", I15<>0, L15<>"", L15<>0), L15/I15, "") -> 0.71583393 | N15: =IF(AND(J15<>0, J15<>"", I15<>0, I15<>""), L15-I15, "") -> -23291.82 | O15: 68957.953 | P15: =IF(AND(O15<>"", O15<>0, L15<>"", L15<>0), -O15+L15, "") -> -10284.253 | Q15: =IF(AND(P15<>"",P15<>0,O15<>0,O15<>""),P15/O15,"") -> -0.14913803
F16: Отставание/Перевыполнение | J16: =J8-I15*J14 -> -698754.6 | K16: =IF(AND(I16<>"", I16<>0, J16<>""), J16/I16, "") | L16: =J16 -> -698754.6 | M16: =IF(AND(I16<>"", I16<>0, L16<>"", L16<>0), L16/I16, "") | N16: =IF(AND(J16<>0, J16<>"", I16<>0, I16<>""), L16-I16, "") | O16: -519369.56 | P16: =IF(AND(O16<>"", O16<>0, L16<>"", L16<>0), -O16+L16, "") -> -179385.04 | Q16: =IF(AND(P16<>"",P16<>0,O16<>0,O16<>""),P16/O16,"") -> 0.34538998
F17: Трафик | I17: 1800 | J17: =I56 -> 1591.2 | K17: =IF(AND(I17<>"", I17<>0, J17<>""), J17/I17, "") -> 0.884 | L17: =J17/J14*I14 -> 1591.2 | M17: =IF(AND(I17<>"", I17<>0, L17<>"", L17<>0), L17/I17, "") -> 0.884 | N17: =IF(AND(J17<>0, J17<>"", I17<>0, I17<>""), L17-I17, "") -> -208.8 | O17: 893 | P17: =IF(AND(O17<>"", O17<>0, L17<>"", L17<>0), -O17+L17, "") -> 698.2 | Q17: =IF(AND(P17<>"",P17<>0,O17<>0,O17<>""),P17/O17,"") -> 0.7818589
F18: Выручка на вошедшего | I18: =I8/I17 -> 1366.092 | J18: =J8/J17 -> 1106.2161 | K18: =IF(AND(I18<>"", I18<>0, J18<>""), J18/I18, "") -> 0.80976688 | L18: =J18 -> 1106.2161 | M18: =IF(AND(I18<>"", I18<>0, L18<>"", L18<>0), L18/I18, "") -> 0.80976688 | N18: =IF(AND(J18<>0, J18<>"", I18<>0, I18<>""), L18-I18, "") -> -259.87594 | P18: =IF(AND(O18<>"", O18<>0, L18<>"", L18<>0), -O18+L18, "") | Q18: =IF(AND(P18<>"",P18<>0,O18<>0,O18<>""),P18/O18,"")
K19: =IF(AND(I19<>"", I19<>0, J19<>""), J19/I19, "") | L19: =J19 -> 0 | M19: =IF(AND(I19<>"", I19<>0, L19<>"", L19<>0), L19/I19, "") | N19: =IF(AND(J19<>0, J19<>"", I19<>0, I19<>""), L19-I19, "") | O19: 0 | P19: =IF(AND(O19<>"", O19<>0, L19<>"", L19<>0), -O19+L19, "") | Q19: =IF(AND(P19<>"",P19<>0,O19<>0,O19<>""),P19/O19,"")
F20: Конверсия план/факт | I20: 0.108 | J20: =S56 -> 0.083584716 | K20: =J20/I20 -> 0.77393255 | L20: =IF(AND(K8<>0,I14<>0,I56<>0),(I56*S56+(I56/K8-I56)*I20)/(I56/K8),0) -> 0.090522711 | M20: =IF(AND(I20<>"", I20<>0, L20<>"", L20<>0), L20/I20, "") -> 0.83817325 | N20: =IF(AND(J20<>0, J20<>"", I20<>0, I20<>""), L20-I20, "") -> -0.017477289 | O20: 0.21836506 | P20: =IF(AND(O20<>"", O20<>0, L20<>"", L20<>0), -O20+L20, "") -> -0.12784235 | Q20: =IF(AND(P20<>"",P20<>0,O20<>0,O20<>""),P20/O20,"") -> -0.5854524
A22: Факт продаж за месяц | T22: % выполнения дневного плана | U22: Раcпределение плана по дням
A23: Сотрудник | B23: Дата | C23: День недели | D23: Выручка (руб) | E23: Кол-во единиц (шт.) | F23: Средняя стоимость изделия (руб.) | G23: Количество чеков (шт.) | H23: Средняя сумма чека (руб.) | I23: Трафик | J23: Длина чека (шт.) | K23: UNOde50 | L23: IS | M23: Agafi | N23: Kalliope | O23: Raganella | P23: CC/MP | Q23: Antyra | R23: SALE | S23: Конверсия | U23: выручка, план | V23: кол-во ед, план | W23: Кол-во чеков, план | X23: выручка, скорректир.план | Y23: кол-во ед, скорр. план | Z23: кол-во чеков, скорр. план | AA23: Коэфф. Дня Недели | AB23: Специфика месяца
B24: 1 | C24: 2 | D24: 3 | E24: 4 | F24: 5 | G24: 6 | H24: 7 | I24: 8 | J24: 9 | K24: 10 | L24: 11 | M24: 12 | N24: 13 | O24: 14 | P24: 15 | Q24: 16 | R24: 17 | S24: 17 | U24: 1 | V24: 2 | W24: 3 | X24: 4 | Y24: 5 | Z24: 6 | AA24: 10 | AB24: 11
A25: Рогалевич,Уразгильдеева | B25: 46113 | C25: ср | D25: 125962 | E25: 13 | F25: =IF(AND(E25<>"",E25<>0),D25/E25,"") -> 9689.3846 | G25: 6 | H25: =IF(AND(G25<>"",G25<>0),D25/G25,"") -> 20993.667 | I25: 74 | J25: =IF(AND(G25<>"",G25<>0),E25/G25,"") -> 2.1666667 | K25: 24291 | N25: 34542 | Q25: 21343 | S25: =IF(AND(I25<>"",I25<>0),G25/I25,"") -> 0.081081081 | T25: =D25/U25 -> 0.87086174 | U25: =$I$8*AA25*AB25/SUMPRODUCT($AB$25:$AB$55,$AA$25:$AA$55) -> 144640.64 | V25: =$I$9*AA25*AB25/SUMPRODUCT($AB$25:$AB$55,$AA$25:$AA$55) -> 20.811603 | W25: =IF($I$12="","",V25/$I$12) -> 11.434947 | X25: =IF(D25<>"",D25,U25) -> 125962 | Y25: =IF(E25<>"",E25,V25) -> 13 | Z25: =IF(G25<>"",G25,W25) -> 6 | AA25: 1 | AB25: 1.51
A26: Рогалевич,Уразгильдеева | B26: 46114 | C26: чт | D26: 19644 | E26: 4 | F26: =IF(AND(E26<>"",E26<>0),D26/E26,"") -> 4911 | G26: 2 | H26: =IF(AND(G26<>"",G26<>0),D26/G26,"") -> 9822 | I26: 39 | J26: =IF(AND(G26<>"",G26<>0),E26/G26,"") -> 2 | S26: =IF(AND(I26<>"",I26<>0),G26/I26,"") -> 0.051282051 | T26: =D26/U26 -> 0.89163826 | U26: =$I$8*AA26*AB26/SUMPRODUCT($AB$25:$AB$55,$AA$25:$AA$55) -> 22031.356 | V26: =$I$9*AA26*AB26/SUMPRODUCT($AB$25:$AB$55,$AA$25:$AA$55) -> 3.1699793 | W26: =IF($I$12="","",V26/$I$12) -> 1.7417469 | X26: =IF(AB26<>"",IF(D26<>"",D26,($I$8-SUM($X$25:X25))*AA26*AB26/SUMPRODUCT($AB26:$AB$55,$AA26:$AA$55)),"") -> 19644 | Y26: =IF(AB26<>"",IF(E26<>"",E26,($I$9-SUM($Y$25:Y25))*AA26*AB26/SUMPRODUCT($AB26:$AB$55,$AA26:$AA$55)),"") -> 4 | Z26: =IF(AB26<>"",IF(E26<>"",E26,($I$9-SUM($Y$25:Y25))*AA26*AB26/SUMPRODUCT($AB26:$AB$55,$AA26:$AA$55)),"") -> 4 | AA26: 1 | AB26: 0.23
A27: Рогалевич.Самошкина | B27: 46115 | C27: пт | D27: 25357 | E27: 6 | F27: =IF(AND(E27<>"",E27<>0),D27/E27,"") -> 4226.1667 | G27: 3 | H27: =IF(AND(G27<>"",G27<>0),D27/G27,"") -> 8452.3333 | I27: 53 | J27: =IF(AND(G27<>"",G27<>0),E27/G27,"") -> 2 | R27: 3795 | S27: =IF(AND(I27<>"",I27<>0),G27/I27,"") -> 0.056603774 | T27: =D27/U27 -> 0.88239538 | U27: =$I$8*AA27*AB27/SUMPRODUCT($AB$25:$AB$55,$AA$25:$AA$55) -> 28736.551 | V27: =$I$9*AA27*AB27/SUMPRODUCT($AB$25:$AB$55,$AA$25:$AA$55) -> 4.1347556 | W27: =IF($I$12="","",V27/$I$12) -> 2.2718437 | X27: =IF(AB27<>"",IF(D27<>"",D27,($I$8-SUM($X$25:X26))*AA27*AB27/SUMPRODUCT($AB27:$AB$55,$AA27:$AA$55)),"") -> 25357 | Y27: =IF(AB27<>"",IF(E27<>"",E27,($I$9-SUM($Y$25:Y26))*AA27*AB27/SUMPRODUCT($AB27:$AB$55,$AA27:$AA$55)),"") -> 6 | Z27: =IF(AB27<>"",IF(E27<>"",E27,($I$9-SUM($Y$25:Y26))*AA27*AB27/SUMPRODUCT($AB27:$AB$55,$AA27:$AA$55)),"") -> 6 | AA27: 1 | AB27: 0.3
A28: Рогалевич,Самошкина | B28: 46116 | C28: сб | D28: 29169 | E28: 4 | F28: 7292 | G28: 3 | H28: 9723 | I28: 53 | J28: =IF(AND(G28<>"",G28<>0),E28/G28,"") -> 1.3333333 | Q28: 14093 | S28: =IF(AND(I28<>"",I28<>0),G28/I28,"") -> 0.056603774 | T28: =D28/U28 -> 0.55366295 | U28: =$I$8*AA28*AB28/SUMPRODUCT($AB$25:$AB$55,$AA$25:$AA$55) -> 52683.677 | V28: =$I$9*AA28*AB28/SUMPRODUCT($AB$25:$AB$55,$AA$25:$AA$55) -> 7.5803852 | W28: =IF($I$12="","",V28/$I$12) -> 4.1650468 | X28: =IF(AB28<>"",IF(D28<>"",D28,($I$8-SUM($X$25:X27))*AA28*AB28/SUMPRODUCT($AB28:$AB$55,$AA28:$AA$55)),"") -> 29169 | Y28: =IF(AB28<>"",IF(E28<>"",E28,($I$9-SUM($Y$25:Y27))*AA28*AB28/SUMPRODUCT($AB28:$AB$55,$AA28:$AA$55)),"") -> 4 | Z28: =IF(AB28<>"",IF(E28<>"",E28,($I$9-SUM($Y$25:Y27))*AA28*AB28/SUMPRODUCT($AB28:$AB$55,$AA28:$AA$55)),"") -> 4 | AA28: 1 | AB28: 0.55
A29: Рогалевич.Уразгильеева | B29: 46117 | C29: вс | D29: 92463 | E29: 16 | F29: =IF(AND(E29<>"",E29<>0),D29/E29,"") -> 5778.9375 | G29: 6 | H29: =IF(AND(G29<>"",G29<>0),D29/G29,"") -> 15410.5 | I29: 69 | J29: =IF(AND(G29<>"",G29<>0),E29/G29,"") -> 2.6666667 | K29: 12293 | N29: 33570 | R29: =7380+6490 -> 13870 | S29: =IF(AND(I29<>"",I29<>0),G29/I29,"") -> 0.086956522 | T29: =D29/U29 -> 0.99513695 | U29: =$I$8*AA29*AB29/SUMPRODUCT($AB$25:$AB$55,$AA$25:$AA$55) -> 92914.849 | V29: =$I$9*AA29*AB29/SUMPRODUCT($AB$25:$AB$55,$AA$25:$AA$55) -> 13.369043 | W29: =IF($I$12="","",V29/$I$12) -> 7.345628 | X29: =IF(AB29<>"",IF(D29<>"",D29,($I$8-SUM($X$25:X28))*AA29*AB29/SUMPRODUCT($AB29:$AB$55,$AA29:$AA$55)),"") -> 92463 | Y29: =IF(AB29<>"",IF(E29<>"",E29,($I$9-SUM($Y$25:Y28))*AA29*AB29/SUMPRODUCT($AB29:$AB$55,$AA29:$AA$55)),"") -> 16 | Z29: =IF(AB29<>"",IF(E29<>"",E29,($I$9-SUM($Y$25:Y28))*AA29*AB29/SUMPRODUCT($AB29:$AB$55,$AA29:$AA$55)),"") -> 16 | AA29: 1 | AB29: 0.97
A30: Уразгильдеева | B30: 46118 | C30: пн | D30: 31933 | E30: 8 | F30: =IF(AND(E30<>"",E30<>0),D30/E30,"") -> 3991.625 | G30: 6 | H30: =IF(AND(G30<>"",G30<>0),D30/G30,"") -> 5322.1667 | I30: 53 | J30: =IF(AND(G30<>"",G30<>0),E30/G30,"") -> 1.3333333 | S30: =IF(AND(I30<>"",I30<>0),G30/I30,"") -> 0.11320755 | T30: =D30/U30 -> 1.1306329 | U30: =$I$8*AA30*AB30/SUMPRODUCT($AB$25:$AB$55,$AA$25:$AA$55) -> 28243.474 | V30: =$I$9*AA30*AB30/SUMPRODUCT($AB$25:$AB$55,$AA$25:$AA$55) -> 4.0638092 | W30: =IF($I$12="","",V30/$I$12) -> 2.2328622 | X30: =IF(AB30<>"",IF(D30<>"",D30,($I$8-SUM($X$25:X29))*AA30*AB30/SUMPRODUCT($AB30:$AB$55,$AA30:$AA$55)),"") -> 31933 | Y30: =IF(AB30<>"",IF(E30<>"",E30,($I$9-SUM($Y$25:Y29))*AA30*AB30/SUMPRODUCT($AB30:$AB$55,$AA30:$AA$55)),"") -> 8 | Z30: =IF(AB30<>"",IF(E30<>"",E30,($I$9-SUM($Y$25:Y29))*AA30*AB30/SUMPRODUCT($AB30:$AB$55,$AA30:$AA$55)),"") -> 8 | AA30: 1 | AB30: 0.29485244
A31: Самошкина | B31: 46119 | C31: вт | D31: 10534 | E31: 2 | F31: =IF(AND(E31<>"",E31<>0),D31/E31,"") -> 5267 | G31: 1 | H31: =IF(AND(G31<>"",G31<>0),D31/G31,"") -> 10534 | I31: 30 | J31: =IF(AND(G31<>"",G31<>0),E31/G31,"") -> 2 | S31: =IF(AND(I31<>"",I31<>0),G31/I31,"") -> 0.033333333 | T31: =D31/U31 -> 1.7303057 | U31: =$I$8*AA31*AB31/SUMPRODUCT($AB$25:$AB$55,$AA$25:$AA$55) -> 6087.9415 | V31: =$I$9*AA31*AB31/SUMPRODUCT($AB$25:$AB$55,$AA$25:$AA$55) -> 0.87596281 | W31: =IF($I$12="","",V31/$I$12) -> 0.48129824 | X31: =IF(AB31<>"",IF(D31<>"",D31,($I$8-SUM($X$25:X30))*AA31*AB31/SUMPRODUCT($AB31:$AB$55,$AA31:$AA$55)),"") -> 10534 | Y31: =IF(AB31<>"",IF(E31<>"",E31,($I$9-SUM($Y$25:Y30))*AA31*AB31/SUMPRODUCT($AB31:$AB$55,$AA31:$AA$55)),"") -> 2 | Z31: =IF(AB31<>"",IF(E31<>"",E31,($I$9-SUM($Y$25:Y30))*AA31*AB31/SUMPRODUCT($AB31:$AB$55,$AA31:$AA$55)),"") -> 2 | AA31: 1 | AB31: 0.063556076
A32: Самошкина | B32: 46120 | C32: ср | D32: 47300 | E32: 8 | F32: =IF(AND(E32<>"",E32<>0),D32/E32,"") -> 5912.5 | G32: 6 | H32: =IF(AND(G32<>"",G32<>0),D32/G32,"") -> 7883.3333 | I32: 52 | J32: =IF(AND(G32<>"",G32<>0),E32/G32,"") -> 1.3333333 | R32: 3514 | S32: =IF(AND(I32<>"",I32<>0),G32/I32,"") -> 0.11538462 | T32: =D32/U32 -> 11.23416 | U32: =$I$8*AA32*AB32/SUMPRODUCT($AB$25:$AB$55,$AA$25:$AA$55) -> 4210.3728 | V32: =$I$9*AA32*AB32/SUMPRODUCT($AB$25:$AB$55,$AA$25:$AA$55) -> 0.60580904 | W32: =IF($I$12="","",V32/$I$12) -> 0.33286211 | X32: =IF(AB32<>"",IF(D32<>"",D32,($I$8-SUM($X$25:X31))*AA32*AB32/SUMPRODUCT($AB32:$AB$55,$AA32:$AA$55)),"") -> 47300 | Y32: =IF(AB32<>"",IF(E32<>"",E32,($I$9-SUM($Y$25:Y31))*AA32*AB32/SUMPRODUCT($AB32:$AB$55,$AA32:$AA$55)),"") -> 8 | Z32: =IF(AB32<>"",IF(E32<>"",E32,($I$9-SUM($Y$25:Y31))*AA32*AB32/SUMPRODUCT($AB32:$AB$55,$AA32:$AA$55)),"") -> 8 | AA32: 1 | AB32: 0.043954886
A33: Уразгильдеева | B33: 46121 | C33: чт | D33: 50991 | E33: 7 | F33: =IF(AND(E33<>"",E33<>0),D33/E33,"") -> 7284.4286 | G33: 2 | H33: =IF(AND(G33<>"",G33<>0),D33/G33,"") -> 25495.5 | I33: 28 | J33: =IF(AND(G33<>"",G33<>0),E33/G33,"") -> 3.5 | R33: 5130 | S33: =IF(AND(I33<>"",I33<>0),G33/I33,"") -> 0.071428571 | T33: =D33/U33 -> 0.47529376 | U33: =$I$8*AA33*AB33/SUMPRODUCT($AB$25:$AB$55,$AA$25:$AA$55) -> 107283.12 | V33: =$I$9*AA33*AB33/SUMPRODUCT($AB$25:$AB$55,$AA$25:$AA$55) -> 15.436421 | W33: =IF($I$12="","",V33/$I$12) -> 8.4815499 | X33: =IF(AB33<>"",IF(D33<>"",D33,($I$8-SUM($X$25:X32))*AA33*AB33/SUMPRODUCT($AB33:$AB$55,$AA33:$AA$55)),"") -> 50991 | Y33: =IF(AB33<>"",IF(E33<>"",E33,($I$9-SUM($Y$25:Y32))*AA33*AB33/SUMPRODUCT($AB33:$AB$55,$AA33:$AA$55)),"") -> 7 | Z33: =IF(AB33<>"",IF(E33<>"",E33,($I$9-SUM($Y$25:Y32))*AA33*AB33/SUMPRODUCT($AB33:$AB$55,$AA33:$AA$55)),"") -> 7 | AA33: 1 | AB33: 1.12
A34: Уразгильдеева | B34: 46122 | C34: пт | D34: 4693 | E34: 1 | F34: =IF(AND(E34<>"",E34<>0),D34/E34,"") -> 4693 | G34: 1 | H34: =IF(AND(G34<>"",G34<>0),D34/G34,"") -> 4693 | I34: 27 | J34: =IF(AND(G34<>"",G34<>0),E34/G34,"") -> 1 | S34: =IF(AND(I34<>"",I34<>0),G34/I34,"") -> 0.037037037 | T34: =D34/U34 -> 0.029337337 | U34: =$I$8*AA34*AB34/SUMPRODUCT($AB$25:$AB$55,$AA$25:$AA$55) -> 159966.8 | V34: =$I$9*AA34*AB34/SUMPRODUCT($AB$25:$AB$55,$AA$25:$AA$55) -> 23.016806 | W34: =IF($I$12="","",V34/$I$12) -> 12.646597 | X34: =IF(AB34<>"",IF(D34<>"",D34,($I$8-SUM($X$25:X33))*AA34*AB34/SUMPRODUCT($AB34:$AB$55,$AA34:$AA$55)),"") -> 4693 | Y34: =IF(AB34<>"",IF(E34<>"",E34,($I$9-SUM($Y$25:Y33))*AA34*AB34/SUMPRODUCT($AB34:$AB$55,$AA34:$AA$55)),"") -> 1 | Z34: =IF(AB34<>"",IF(E34<>"",E34,($I$9-SUM($Y$25:Y33))*AA34*AB34/SUMPRODUCT($AB34:$AB$55,$AA34:$AA$55)),"") -> 1 | AA34: 1 | AB34: 1.67
A35: Рогалевич.Самошкина | B35: 46123 | C35: сб | D35: 68315 | E35: 10 | F35: =IF(AND(E35<>"",E35<>0),D35/E35,"") -> 6831.5 | G35: 3 | H35: =IF(AND(G35<>"",G35<>0),D35/G35,"") -> 22771.667 | I35: 44 | J35: =IF(AND(G35<>"",G35<>0),E35/G35,"") -> 3.3333333 | P35: 11893 | Q35: 20780 | R35: 7980 | S35: =IF(AND(I35<>"",I35<>0),G35/I35,"") -> 0.068181818 | T35: =D35/U35 -> 0.40066617 | U35: =$I$8*AA35*AB35/SUMPRODUCT($AB$25:$AB$55,$AA$25:$AA$55) -> 170503.54 | V35: =$I$9*AA35*AB35/SUMPRODUCT($AB$25:$AB$55,$AA$25:$AA$55) -> 24.532883 | W35: =IF($I$12="","",V35/$I$12) -> 13.479606 | X35: =IF(AB35<>"",IF(D35<>"",D35,($I$8-SUM($X$25:X34))*AA35*AB35/SUMPRODUCT($AB35:$AB$55,$AA35:$AA$55)),"") -> 68315 | Y35: =IF(AB35<>"",IF(E35<>"",E35,($I$9-SUM($Y$25:Y34))*AA35*AB35/SUMPRODUCT($AB35:$AB$55,$AA35:$AA$55)),"") -> 10 | Z35: =IF(AB35<>"",IF(E35<>"",E35,($I$9-SUM($Y$25:Y34))*AA35*AB35/SUMPRODUCT($AB35:$AB$55,$AA35:$AA$55)),"") -> 10 | AA35: 1 | AB35: 1.78
A36: Рогалевич,Самошкина | B36: 46124 | C36: вс | D36: =65297+L36 -> 110299 | E36: 9 | F36: =IF(AND(E36<>"",E36<>0),D36/E36,"") -> 12255.444 | G36: 5 | H36: =IF(AND(G36<>"",G36<>0),D36/G36,"") -> 22059.8 | I36: 51 | J36: =IF(AND(G36<>"",G36<>0),E36/G36,"") -> 1.8 | K36: 22931 | L36: 45002 | S36: =IF(AND(I36<>"",I36<>0),G36/I36,"") -> 0.098039216 | T36: =D36/U36 -> 0.75755574 | U36: =$I$8*AA36*AB36/SUMPRODUCT($AB$25:$AB$55,$AA$25:$AA$55) -> 145598.53 | V36: =$I$9*AA36*AB36/SUMPRODUCT($AB$25:$AB$55,$AA$25:$AA$55) -> 20.949428 | W36: =IF($I$12="","",V36/$I$12) -> 11.510675 | X36: =IF(AB36<>"",IF(D36<>"",D36,($I$8-SUM($X$25:X35))*AA36*AB36/SUMPRODUCT($AB36:$AB$55,$AA36:$AA$55)),"") -> 110299 | Y36: =IF(AB36<>"",IF(E36<>"",E36,($I$9-SUM($Y$25:Y35))*AA36*AB36/SUMPRODUCT($AB36:$AB$55,$AA36:$AA$55)),"") -> 9 | Z36: =IF(AB36<>"",IF(E36<>"",E36,($I$9-SUM($Y$25:Y35))*AA36*AB36/SUMPRODUCT($AB36:$AB$55,$AA36:$AA$55)),"") -> 9 | AA36: 1 | AB36: 1.52
A37: Рогалевич,Уразгильдеева | B37: 46125 | C37: пн | D37: 65616 | E37: 10 | F37: =IF(AND(E37<>"",E37<>0),D37/E37,"") -> 6561.6 | G37: 7 | H37: =IF(AND(G37<>"",G37<>0),D37/G37,"") -> 9373.7143 | I37: 75 | J37: =IF(AND(G37<>"",G37<>0),E37/G37,"") -> 1.4285714 | K37: 31984 | R37: 3245 | S37: =IF(AND(I37<>"",I37<>0),G37/I37,"") -> 0.093333333 | T37: =D37/U37 -> 0.73656896 | U37: =$I$8*AA37*AB37/SUMPRODUCT($AB$25:$AB$55,$AA$25:$AA$55) -> 89083.309 | V37: =$I$9*AA37*AB37/SUMPRODUCT($AB$25:$AB$55,$AA$25:$AA$55) -> 12.817742 | W37: =IF($I$12="","",V37/$I$12) -> 7.0427155 | X37: =IF(AB37<>"",IF(D37<>"",D37,($I$8-SUM($X$25:X36))*AA37*AB37/SUMPRODUCT($AB37:$AB$55,$AA37:$AA$55)),"") -> 65616 | Y37: =IF(AB37<>"",IF(E37<>"",E37,($I$9-SUM($Y$25:Y36))*AA37*AB37/SUMPRODUCT($AB37:$AB$55,$AA37:$AA$55)),"") -> 10 | Z37: =IF(AB37<>"",IF(E37<>"",E37,($I$9-SUM($Y$25:Y36))*AA37*AB37/SUMPRODUCT($AB37:$AB$55,$AA37:$AA$55)),"") -> 10 | AA37: 1 | AB37: 0.93
A38: Рогалевич.Уразгильдеева | B38: 46126 | C38: вт | D38: 49181 | E38: 8 | F38: =IF(AND(E38<>"",E38<>0),D38/E38,"") -> 6147.625 | G38: 7 | H38: =IF(AND(G38<>"",G38<>0),D38/G38,"") -> 7025.8571 | I38: 66 | J38: =IF(AND(G38<>"",G38<>0),E38/G38,"") -> 1.1428571 | K38: 11592 | S38: =IF(AND(I38<>"",I38<>0),G38/I38,"") -> 0.10606061 | T38: =D38/U38 -> 0.74333798 | U38: =$I$8*AA38*AB38/SUMPRODUCT($AB$25:$AB$55,$AA$25:$AA$55) -> 66162.367 | V38: =$I$9*AA38*AB38/SUMPRODUCT($AB$25:$AB$55,$AA$25:$AA$55) -> 9.519765 | W38: =IF($I$12="","",V38/$I$12) -> 5.2306401 | X38: =IF(AB38<>"",IF(D38<>"",D38,($I$8-SUM($X$25:X37))*AA38*AB38/SUMPRODUCT($AB38:$AB$55,$AA38:$AA$55)),"") -> 49181 | Y38: =IF(AB38<>"",IF(E38<>"",E38,($I$9-SUM($Y$25:Y37))*AA38*AB38/SUMPRODUCT($AB38:$AB$55,$AA38:$AA$55)),"") -> 8 | Z38: =IF(AB38<>"",IF(E38<>"",E38,($I$9-SUM($Y$25:Y37))*AA38*AB38/SUMPRODUCT($AB38:$AB$55,$AA38:$AA$55)),"") -> 8 | AA38: 1 | AB38: 0.69071302
A39: Самошкина,Уразгильдеева | B39: 46127 | C39: ср | D39: 61823 | E39: 9 | F39: =IF(AND(E39<>"",E39<>0),D39/E39,"") -> 6869.2222 | G39: 6 | H39: =IF(AND(G39<>"",G39<>0),D39/G39,"") -> 10303.833 | I39: 69 | J39: =IF(AND(G39<>"",G39<>0),E39/G39,"") -> 1.5 | Q39: 26072 | R39: 2095 | S39: =IF(AND(I39<>"",I39<>0),G39/I39,"") -> 0.086956522 | T39: =D39/U39 -> 1.3599351 | U39: =$I$8*AA39*AB39/SUMPRODUCT($AB$25:$AB$55,$AA$25:$AA$55) -> 45460.257 | V39: =$I$9*AA39*AB39/SUMPRODUCT($AB$25:$AB$55,$AA$25:$AA$55) -> 6.5410442 | W39: =IF($I$12="","",V39/$I$12) -> 3.5939803 | X39: =IF(AB39<>"",IF(D39<>"",D39,($I$8-SUM($X$25:X38))*AA39*AB39/SUMPRODUCT($AB39:$AB$55,$AA39:$AA$55)),"") -> 61823 | Y39: =IF(AB39<>"",IF(E39<>"",E39,($I$9-SUM($Y$25:Y38))*AA39*AB39/SUMPRODUCT($AB39:$AB$55,$AA39:$AA$55)),"") -> 9 | Z39: =IF(AB39<>"",IF(E39<>"",E39,($I$9-SUM($Y$25:Y38))*AA39*AB39/SUMPRODUCT($AB39:$AB$55,$AA39:$AA$55)),"") -> 9 | AA39: 1 | AB39: 0.4745899
A40: Рогалевич,Самошкина | B40: 46128 | C40: чт | D40: =154905+L40 -> 172712 | E40: 14 | F40: =IF(AND(E40<>"",E40<>0),D40/E40,"") -> 12336.571 | G40: 7 | H40: =IF(AND(G40<>"",G40<>0),D40/G40,"") -> 24673.143 | I40: 56 | J40: =IF(AND(G40<>"",G40<>0),E40/G40,"") -> 2 | K40: =37294+8792 -> 46086 | L40: 17807 | P40: 37998 | Q40: 57515 | R40: 5890 | S40: =IF(AND(I40<>"",I40<>0),G40/I40,"") -> 0.125 | T40: =D40/U40 -> 1.6162225 | U40: =$I$8*AA40*AB40/SUMPRODUCT($AB$25:$AB$55,$AA$25:$AA$55) -> 106861.53 | V40: =$I$9*AA40*AB40/SUMPRODUCT($AB$25:$AB$55,$AA$25:$AA$55) -> 15.375759 | W40: =IF($I$12="","",V40/$I$12) -> 8.4482194 | X40: =IF(AB40<>"",IF(D40<>"",D40,($I$8-SUM($X$25:X39))*AA40*AB40/SUMPRODUCT($AB40:$AB$55,$AA40:$AA$55)),"") -> 172712 | Y40: =IF(AB40<>"",IF(E40<>"",E40,($I$9-SUM($Y$25:Y39))*AA40*AB40/SUMPRODUCT($AB40:$AB$55,$AA40:$AA$55)),"") -> 14 | Z40: =IF(AB40<>"",IF(E40<>"",E40,($I$9-SUM($Y$25:Y39))*AA40*AB40/SUMPRODUCT($AB40:$AB$55,$AA40:$AA$55)),"") -> 14 | AA40: 1 | AB40: 1.1155987
A41: Рогалевич,Уразгильдеева | B41: 46129 | C41: пт | D41: 51060 | E41: 5 | F41: =IF(AND(E41<>"",E41<>0),D41/E41,"") -> 10212 | G41: 4 | H41: =IF(AND(G41<>"",G41<>0),D41/G41,"") -> 12765 | I41: 64 | J41: =IF(AND(G41<>"",G41<>0),E41/G41,"") -> 1.25 | K41: 8992 | P41: 32284 | R41: 5490 | S41: =IF(AND(I41<>"",I41<>0),G41/I41,"") -> 0.0625 | T41: =D41/U41 -> 0.31852433 | U41: =$I$8*AA41*AB41/SUMPRODUCT($AB$25:$AB$55,$AA$25:$AA$55) -> 160301.73 | V41: =$I$9*AA41*AB41/SUMPRODUCT($AB$25:$AB$55,$AA$25:$AA$55) -> 23.064997 | W41: =IF($I$12="","",V41/$I$12) -> 12.673075 | X41: =IF(AB41<>"",IF(D41<>"",D41,($I$8-SUM($X$25:X40))*AA41*AB41/SUMPRODUCT($AB41:$AB$55,$AA41:$AA$55)),"") -> 51060 | Y41: =IF(AB41<>"",IF(E41<>"",E41,($I$9-SUM($Y$25:Y40))*AA41*AB41/SUMPRODUCT($AB41:$AB$55,$AA41:$AA$55)),"") -> 5 | Z41: =IF(AB41<>"",IF(E41<>"",E41,($I$9-SUM($Y$25:Y40))*AA41*AB41/SUMPRODUCT($AB41:$AB$55,$AA41:$AA$55)),"") -> 5 | AA41: 1 | AB41: 1.6734965
A42: Рогалевич,Уразгильдеева | B42: 46130 | C42: сб | D42: =109190+L42 -> 117892 | E42: 15 | F42: =IF(AND(E42<>"",E42<>0),D42/E42,"") -> 7859.4667 | G42: 7 | H42: =IF(AND(G42<>"",G42<>0),D42/G42,"") -> 16841.714 | I42: 102 | J42: =IF(AND(G42<>"",G42<>0),E42/G42,"") -> 2.1428571 | K42: 15990 | L42: 8702 | P42: 17390 | R42: 5890 | S42: =IF(AND(I42<>"",I42<>0),G42/I42,"") -> 0.068627451 | T42: =D42/U42 -> 1.5863474 | U42: =$I$8*AA42*AB42/SUMPRODUCT($AB$25:$AB$55,$AA$25:$AA$55) -> 74316.633 | V42: =$I$9*AA42*AB42/SUMPRODUCT($AB$25:$AB$55,$AA$25:$AA$55) -> 10.693041 | W42: =IF($I$12="","",V42/$I$12) -> 5.8752971 | X42: =IF(AB42<>"",IF(D42<>"",D42,($I$8-SUM($X$25:X41))*AA42*AB42/SUMPRODUCT($AB42:$AB$55,$AA42:$AA$55)),"") -> 117892 | Y42: =IF(AB42<>"",IF(E42<>"",E42,($I$9-SUM($Y$25:Y41))*AA42*AB42/SUMPRODUCT($AB42:$AB$55,$AA42:$AA$55)),"") -> 15 | Z42: =IF(AB42<>"",IF(E42<>"",E42,($I$9-SUM($Y$25:Y41))*AA42*AB42/SUMPRODUCT($AB42:$AB$55,$AA42:$AA$55)),"") -> 15 | AA42: 1 | AB42: 0.77584084
A43: Рогалевич | B43: 46131 | C43: вс | D43: =60666+L43 -> 89569 | E43: 16 | F43: =IF(AND(E43<>"",E43<>0),D43/E43,"") -> 5598.0625 | G43: 8 | H43: =IF(AND(G43<>"",G43<>0),D43/G43,"") -> 11196.125 | I43: 82 | J43: =IF(AND(G43<>"",G43<>0),E43/G43,"") -> 2 | L43: 28903 | P43: -17390 | Q43: 36786 | R43: 5990 | S43: =IF(AND(I43<>"",I43<>0),G43/I43,"") -> 0.097560976 | T43: =D43/U43 -> 0.61527089 | U43: =$I$8*AA43*AB43/SUMPRODUCT($AB$25:$AB$55,$AA$25:$AA$55) -> 145576.53 | V43: =$I$9*AA43*AB43/SUMPRODUCT($AB$25:$AB$55,$AA$25:$AA$55) -> 20.946263 | W43: =IF($I$12="","",V43/$I$12) -> 11.508936 | X43: =IF(AB43<>"",IF(D43<>"",D43,($I$8-SUM($X$25:X42))*AA43*AB43/SUMPRODUCT($AB43:$AB$55,$AA43:$AA$55)),"") -> 89569 | Y43: =IF(AB43<>"",IF(E43<>"",E43,($I$9-SUM($Y$25:Y42))*AA43*AB43/SUMPRODUCT($AB43:$AB$55,$AA43:$AA$55)),"") -> 16 | Z43: =IF(AB43<>"",IF(E43<>"",E43,($I$9-SUM($Y$25:Y42))*AA43*AB43/SUMPRODUCT($AB43:$AB$55,$AA43:$AA$55)),"") -> 16 | AA43: 1 | AB43: 1.5197703
A44: Уразгильдеева | B44: 46132 | C44: пн | D44: 38213 | E44: 8 | F44: =IF(AND(E44<>"",E44<>0),D44/E44,"") -> 4776.625 | G44: 5 | H44: =IF(AND(G44<>"",G44<>0),D44/G44,"") -> 7642.6 | I44: 86 | J44: =IF(AND(G44<>"",G44<>0),E44/G44,"") -> 1.6 | R44: 11647 | S44: =IF(AND(I44<>"",I44<>0),G44/I44,"") -> 0.058139535 | T44: =D44/U44 -> 0.42895802 | U44: =$I$8*AA44*AB44/SUMPRODUCT($AB$25:$AB$55,$AA$25:$AA$55) -> 89083.309 | V44: =$I$9*AA44*AB44/SUMPRODUCT($AB$25:$AB$55,$AA$25:$AA$55) -> 12.817742 | W44: =IF($I$12="","",V44/$I$12) -> 7.0427155 | X44: =IF(AB44<>"",IF(D44<>"",D44,($I$8-SUM($X$25:X43))*AA44*AB44/SUMPRODUCT($AB44:$AB$55,$AA44:$AA$55)),"") -> 38213 | Y44: =IF(AB44<>"",IF(E44<>"",E44,($I$9-SUM($Y$25:Y43))*AA44*AB44/SUMPRODUCT($AB44:$AB$55,$AA44:$AA$55)),"") -> 8 | Z44: =IF(AB44<>"",IF(E44<>"",E44,($I$9-SUM($Y$25:Y43))*AA44*AB44/SUMPRODUCT($AB44:$AB$55,$AA44:$AA$55)),"") -> 8 | AA44: 1 | AB44: 0.93
A45: Уразгильдеева | B45: 46133 | C45: вт | D45: =35652+L45 -> 61152 | E45: 8 | F45: =IF(AND(E45<>"",E45<>0),D45/E45,"") -> 7644 | G45: 6 | H45: =IF(AND(G45<>"",G45<>0),D45/G45,"") -> 10192 | I45: 64 | J45: =IF(AND(G45<>"",G45<>0),E45/G45,"") -> 1.3333333 | L45: 25500 | R45: 2595 | S45: =IF(AND(I45<>"",I45<>0),G45/I45,"") -> 0.09375 | T45: =D45/U45 -> 1.7246665 | U45: =$I$8*AA45*AB45/SUMPRODUCT($AB$25:$AB$55,$AA$25:$AA$55) -> 35457.29 | V45: =$I$9*AA45*AB45/SUMPRODUCT($AB$25:$AB$55,$AA$25:$AA$55) -> 5.1017684 | W45: =IF($I$12="","",V45/$I$12) -> 2.8031695 | X45: =IF(AB45<>"",IF(D45<>"",D45,($I$8-SUM($X$25:X44))*AA45*AB45/SUMPRODUCT($AB45:$AB$55,$AA45:$AA$55)),"") -> 61152 | Y45: =IF(AB45<>"",IF(E45<>"",E45,($I$9-SUM($Y$25:Y44))*AA45*AB45/SUMPRODUCT($AB45:$AB$55,$AA45:$AA$55)),"") -> 8 | Z45: =IF(AB45<>"",IF(E45<>"",E45,($I$9-SUM($Y$25:Y44))*AA45*AB45/SUMPRODUCT($AB45:$AB$55,$AA45:$AA$55)),"") -> 8 | AA45: 1 | AB45: 0.37016227
A46: Уразгильдеева | B46: 46134 | C46: ср | D46: 66152 | E46: 9 | F46: =IF(AND(E46<>"",E46<>0),D46/E46,"") -> 7350.2222 | G46: 6 | H46: =IF(AND(G46<>"",G46<>0),D46/G46,"") -> 11025.333 | I46: 60 | J46: =IF(AND(G46<>"",G46<>0),E46/G46,"") -> 1.5 | K46: 20284 | R46: 4392 | S46: =IF(AND(I46<>"",I46<>0),G46/I46,"") -> 0.1 | T46: =D46/U46 -> 3.2290208 | U46: =$I$8*AA46*AB46/SUMPRODUCT($AB$25:$AB$55,$AA$25:$AA$55) -> 20486.706 | V46: =$I$9*AA46*AB46/SUMPRODUCT($AB$25:$AB$55,$AA$25:$AA$55) -> 2.9477275 | W46: =IF($I$12="","",V46/$I$12) -> 1.6196305 | X46: =IF(AB46<>"",IF(D46<>"",D46,($I$8-SUM($X$25:X45))*AA46*AB46/SUMPRODUCT($AB46:$AB$55,$AA46:$AA$55)),"") -> 66152 | Y46: =IF(AB46<>"",IF(E46<>"",E46,($I$9-SUM($Y$25:Y45))*AA46*AB46/SUMPRODUCT($AB46:$AB$55,$AA46:$AA$55)),"") -> 9 | Z46: =IF(AB46<>"",IF(E46<>"",E46,($I$9-SUM($Y$25:Y45))*AA46*AB46/SUMPRODUCT($AB46:$AB$55,$AA46:$AA$55)),"") -> 9 | AA46: 1 | AB46: 0.21387437
A47: Уразгильдеева | B47: 46135 | C47: чт | D47: 8688 | E47: 2 | F47: =IF(AND(E47<>"",E47<>0),D47/E47,"") -> 4344 | G47: 2 | H47: =IF(AND(G47<>"",G47<>0),D47/G47,"") -> 4344 | I47: 33 | J47: =IF(AND(G47<>"",G47<>0),E47/G47,"") -> 1 | R47: 4392 | S47: =IF(AND(I47<>"",I47<>0),G47/I47,"") -> 0.060606061 | T47: =D47/U47 -> 0.072160928 | U47: =$I$8*AA47*AB47/SUMPRODUCT($AB$25:$AB$55,$AA$25:$AA$55) -> 120397.56 | V47: =$I$9*AA47*AB47/SUMPRODUCT($AB$25:$AB$55,$AA$25:$AA$55) -> 17.323391 | W47: =IF($I$12="","",V47/$I$12) -> 9.5183465 | X47: =IF(AB47<>"",IF(D47<>"",D47,($I$8-SUM($X$25:X46))*AA47*AB47/SUMPRODUCT($AB47:$AB$55,$AA47:$AA$55)),"") -> 8688 | Y47: =IF(AB47<>"",IF(E47<>"",E47,($I$9-SUM($Y$25:Y46))*AA47*AB47/SUMPRODUCT($AB47:$AB$55,$AA47:$AA$55)),"") -> 2 | Z47: =IF(AB47<>"",IF(E47<>"",E47,($I$9-SUM($Y$25:Y46))*AA47*AB47/SUMPRODUCT($AB47:$AB$55,$AA47:$AA$55)),"") -> 2 | AA47: 1 | AB47: 1.2569104
A48: Рогалевич | B48: 46136 | C48: пт | D48: 0 | E48: 0 | F48: 0 | G48: 0 | H48: =IF(AND(G48<>"",G48<>0),D48/G48,"") | I48: 62 | J48: =IF(AND(G48<>"",G48<>0),E48/G48,"") | S48: =IF(AND(I48<>"",I48<>0),G48/I48,"") -> 0 | T48: =D48/U48 -> 0 | U48: =$I$8*AA48*AB48/SUMPRODUCT($AB$25:$AB$55,$AA$25:$AA$55) -> 66121.285 | V48: =$I$9*AA48*AB48/SUMPRODUCT($AB$25:$AB$55,$AA$25:$AA$55) -> 9.5138539 | W48: =IF($I$12="","",V48/$I$12) -> 5.2273923 | X48: =IF(AB48<>"",IF(D48<>"",D48,($I$8-SUM($X$25:X47))*AA48*AB48/SUMPRODUCT($AB48:$AB$55,$AA48:$AA$55)),"") -> 0 | Y48: =IF(AB48<>"",IF(E48<>"",E48,($I$9-SUM($Y$25:Y47))*AA48*AB48/SUMPRODUCT($AB48:$AB$55,$AA48:$AA$55)),"") -> 0 | Z48: =IF(AB48<>"",IF(E48<>"",E48,($I$9-SUM($Y$25:Y47))*AA48*AB48/SUMPRODUCT($AB48:$AB$55,$AA48:$AA$55)),"") -> 0 | AA48: 1 | AB48: 0.69028413
A49: Рогалевич,Уразгильдеева | B49: 46137 | C49: сб | D49: =27346+L49 -> 64153 | E49: 5 | F49: =IF(AND(E49<>"",E49<>0),D49/E49,"") -> 12830.6 | G49: 5 | H49: =IF(AND(G49<>"",G49<>0),D49/G49,"") -> 12830.6 | I49: 91 | J49: =IF(AND(G49<>"",G49<>0),E49/G49,"") -> 1 | L49: =29904+6903 -> 36807 | M49: 12893 | S49: =IF(AND(I49<>"",I49<>0),G49/I49,"") -> 0.054945055 | T49: =D49/U49 -> 0.49103344 | U49: =$I$8*AA49*AB49/SUMPRODUCT($AB$25:$AB$55,$AA$25:$AA$55) -> 130648.94 | V49: =$I$9*AA49*AB49/SUMPRODUCT($AB$25:$AB$55,$AA$25:$AA$55) -> 18.798409 | W49: =IF($I$12="","",V49/$I$12) -> 10.328796 | X49: =IF(AB49<>"",IF(D49<>"",D49,($I$8-SUM($X$25:X48))*AA49*AB49/SUMPRODUCT($AB49:$AB$55,$AA49:$AA$55)),"") -> 64153 | Y49: =IF(AB49<>"",IF(E49<>"",E49,($I$9-SUM($Y$25:Y48))*AA49*AB49/SUMPRODUCT($AB49:$AB$55,$AA49:$AA$55)),"") -> 5 | Z49: =IF(AB49<>"",IF(E49<>"",E49,($I$9-SUM($Y$25:Y48))*AA49*AB49/SUMPRODUCT($AB49:$AB$55,$AA49:$AA$55)),"") -> 5 | AA49: 1 | AB49: 1.3639313
A50: Рогалевич,Уразгильдеева | B50: 46138 | C50: вс | D50: 28740 | E50: 5 | F50: =IF(AND(E50<>"",E50<>0),D50/E50,"") -> 5748 | G50: 4 | H50: =IF(AND(G50<>"",G50<>0),D50/G50,"") -> 7185 | I50: 61 | J50: =IF(AND(G50<>"",G50<>0),E50/G50,"") -> 1.25 | S50: =IF(AND(I50<>"",I50<>0),G50/I50,"") -> 0.06557377 | T50: =D50/U50 -> 0.1980867 | U50: =$I$8*AA50*AB50/SUMPRODUCT($AB$25:$AB$55,$AA$25:$AA$55) -> 145087.98 | V50: =$I$9*AA50*AB50/SUMPRODUCT($AB$25:$AB$55,$AA$25:$AA$55) -> 20.875969 | W50: =IF($I$12="","",V50/$I$12) -> 11.470312 | X50: =IF(AB50<>"",IF(D50<>"",D50,($I$8-SUM($X$25:X49))*AA50*AB50/SUMPRODUCT($AB50:$AB$55,$AA50:$AA$55)),"") -> 28740 | Y50: =IF(AB50<>"",IF(E50<>"",E50,($I$9-SUM($Y$25:Y49))*AA50*AB50/SUMPRODUCT($AB50:$AB$55,$AA50:$AA$55)),"") -> 5 | Z50: =IF(AB50<>"",IF(E50<>"",E50,($I$9-SUM($Y$25:Y49))*AA50*AB50/SUMPRODUCT($AB50:$AB$55,$AA50:$AA$55)),"") -> 5 | AA50: 1 | AB50: 1.5146701
A51: Рогалевич | B51: 46139 | C51: пн | D51: =4393+L51 -> 16296 | E51: 2 | F51: =IF(AND(E51<>"",E51<>0),D51/E51,"") -> 8148 | G51: 2 | H51: =IF(AND(G51<>"",G51<>0),D51/G51,"") -> 8148 | I51: 46 | J51: =IF(AND(G51<>"",G51<>0),E51/G51,"") -> 1 | L51: 11903 | S51: =IF(AND(I51<>"",I51<>0),G51/I51,"") -> 0.043478261 | T51: =D51/U51 -> 0.25055419 | U51: =$I$8*AA51*AB51/SUMPRODUCT($AB$25:$AB$55,$AA$25:$AA$55) -> 65039.823 | V51: =$I$9*AA51*AB51/SUMPRODUCT($AB$25:$AB$55,$AA$25:$AA$55) -> 9.3582479 | W51: =IF($I$12="","",V51/$I$12) -> 5.1418945 | X51: =IF(AB51<>"",IF(D51<>"",D51,($I$8-SUM($X$25:X50))*AA51*AB51/SUMPRODUCT($AB51:$AB$55,$AA51:$AA$55)),"") -> 16296 | Y51: =IF(AB51<>"",IF(E51<>"",E51,($I$9-SUM($Y$25:Y50))*AA51*AB51/SUMPRODUCT($AB51:$AB$55,$AA51:$AA$55)),"") -> 2 | Z51: =IF(AB51<>"",IF(E51<>"",E51,($I$9-SUM($Y$25:Y50))*AA51*AB51/SUMPRODUCT($AB51:$AB$55,$AA51:$AA$55)),"") -> 2 | AA51: 1 | AB51: 0.67899403
A52: Рогалевич,Уразгильдеева | B52: 46140 | C52: вт | D52: =6239+L52 -> 44848 | E52: 6 | F52: =IF(AND(E52<>"",E52<>0),D52/E52,"") -> 7474.6667 | G52: 4 | H52: =IF(AND(G52<>"",G52<>0),D52/G52,"") -> 11212 | I52: 54 | J52: =IF(AND(G52<>"",G52<>0),E52/G52,"") -> 1.5 | L52: 38609 | R52: 6235 | S52: =IF(AND(I52<>"",I52<>0),G52/I52,"") -> 0.074074074 | T52: =D52/U52 -> 1.4205881 | U52: =$I$8*AA52*AB52/SUMPRODUCT($AB$25:$AB$55,$AA$25:$AA$55) -> 31570.024 | V52: =$I$9*AA52*AB52/SUMPRODUCT($AB$25:$AB$55,$AA$25:$AA$55) -> 4.5424495 | W52: =IF($I$12="","",V52/$I$12) -> 2.4958514 | X52: =IF(AB52<>"",IF(D52<>"",D52,($I$8-SUM($X$25:X51))*AA52*AB52/SUMPRODUCT($AB52:$AB$55,$AA52:$AA$55)),"") -> 44848 | Y52: =IF(AB52<>"",IF(E52<>"",E52,($I$9-SUM($Y$25:Y51))*AA52*AB52/SUMPRODUCT($AB52:$AB$55,$AA52:$AA$55)),"") -> 6 | Z52: =IF(AB52<>"",IF(E52<>"",E52,($I$9-SUM($Y$25:Y51))*AA52*AB52/SUMPRODUCT($AB52:$AB$55,$AA52:$AA$55)),"") -> 6 | AA52: 1 | AB52: 0.32958051
A53: Рогалевич,Уразгильдеева | B53: 46141 | C53: ср | D53: 37553 | E53: 7 | F53: =IF(AND(E53<>"",E53<>0),D53/E53,"") -> 5364.7143 | G53: 3 | H53: =IF(AND(G53<>"",G53<>0),D53/G53,"") -> 12517.667 | I53: 54 | J53: =IF(AND(G53<>"",G53<>0),E53/G53,"") -> 2.3333333 | R53: 3500 | S53: =IF(AND(I53<>"",I53<>0),G53/I53,"") -> 0.055555556 | T53: =D53/U53 -> 0.80008323 | U53: =$I$8*AA53*AB53/SUMPRODUCT($AB$25:$AB$55,$AA$25:$AA$55) -> 46936.367 | V53: =$I$9*AA53*AB53/SUMPRODUCT($AB$25:$AB$55,$AA$25:$AA$55) -> 6.7534341 | W53: =IF($I$12="","",V53/$I$12) -> 3.7106781 | X53: =IF(AB53<>"",IF(D53<>"",D53,($I$8-SUM($X$25:X52))*AA53*AB53/SUMPRODUCT($AB53:$AB$55,$AA53:$AA$55)),"") -> 37553 | Y53: =IF(AB53<>"",IF(E53<>"",E53,($I$9-SUM($Y$25:Y52))*AA53*AB53/SUMPRODUCT($AB53:$AB$55,$AA53:$AA$55)),"") -> 7 | Z53: =IF(AB53<>"",IF(E53<>"",E53,($I$9-SUM($Y$25:Y52))*AA53*AB53/SUMPRODUCT($AB53:$AB$55,$AA53:$AA$55)),"") -> 7 | AA53: 1 | AB53: 0.49
A54: Уразгильдеева | B54: 46142 | C54: чт | D54: =143203+L54 -> 169903 | E54: 13 | F54: =IF(AND(E54<>"",E54<>0),D54/E54,"") -> 13069.462 | G54: 6 | H54: =IF(AND(G54<>"",G54<>0),D54/G54,"") -> 28317.167 | I54: 70 | J54: =IF(AND(G54<>"",G54<>0),E54/G54,"") -> 2.1666667 | K54: 29984 | L54: 26700 | O54: 87458 | R54: 6490 | S54: =IF(AND(I54<>"",I54<>0),G54/I54,"") -> 0.085714286 | T54: =D54/U54 -> 2.9562176 | U54: =$I$8*AA54*AB54/SUMPRODUCT($AB$25:$AB$55,$AA$25:$AA$55) -> 57473.103 | V54: =$I$9*AA54*AB54/SUMPRODUCT($AB$25:$AB$55,$AA$25:$AA$55) -> 8.2695112 | W54: =IF($I$12="","",V54/$I$12) -> 4.5436875 | X54: =IF(AB54<>"",IF(D54<>"",D54,($I$8-SUM($X$25:X53))*AA54*AB54/SUMPRODUCT($AB54:$AB$55,$AA54:$AA$55)),"") -> 169903 | Y54: =IF(AB54<>"",IF(E54<>"",E54,($I$9-SUM($Y$25:Y53))*AA54*AB54/SUMPRODUCT($AB54:$AB$55,$AA54:$AA$55)),"") -> 13 | Z54: =IF(AB54<>"",IF(E54<>"",E54,($I$9-SUM($Y$25:Y53))*AA54*AB54/SUMPRODUCT($AB54:$AB$55,$AA54:$AA$55)),"") -> 13 | AA54: 1 | AB54: 0.6
F55: =IF(AND(E55<>"",E55<>0),D55/E55,"") | H55: =IF(AND(G55<>"",G55<>0),D55/G55,"") | J55: =IF(AND(G55<>"",G55<>0),E55/G55,"") | S55: =IF(AND(I55<>"",I55<>0),G55/I55,"") | T55: =D55/U55 -> #DIV/0! | U55: =$I$8*AA55*AB55/SUMPRODUCT($AB$25:$AB$55,$AA$25:$AA$55) -> 0 | V55: =$I$9*AA55*AB55/SUMPRODUCT($AB$25:$AB$55,$AA$25:$AA$55) -> 0 | W55: =IF($I$12="","",V55/$I$12) -> 0 | X55: =IF(AB55<>"",IF(D55<>"",D55,($I$8-SUM($X$25:X54))*AA55*AB55/SUMPRODUCT($AB55:$AB$55,$AA55:$AA$55)),"") | Y55: =IF(AB55<>"",IF(E55<>"",E55,($I$9-SUM($Y$25:Y54))*AA55*AB55/SUMPRODUCT($AB55:$AB$55,$AA55:$AA$55)),"") | Z55: =IF(AB55<>"",IF(E55<>"",E55,($I$9-SUM($Y$25:Y54))*AA55*AB55/SUMPRODUCT($AB55:$AB$55,$AA55:$AA$55)),"")
B56: итого | D56: =SUM(D25:D55) -> 1760211 | E56: =SUM(E25:E55) -> 230 | F56: =IF(AND(E56<>"", E56<>0), D56/E56, "") -> 7653.0913 | G56: =SUM(G25:G55) -> 133 | H56: =IF(AND(G56<>"",G56<>0),D56/G56,"") -> 13234.669 | I56: =SUM(I25:I55)*0.9 -> 1591.2 | J56: =E56/G56 -> 1.7293233 | K56: =SUM(K25:K55) -> 224427 | L56: =SUM(L25:L55) -> 239933 | M56: =SUM(M25:M55) -> 12893 | N56: =SUM(N25:N55) -> 68112 | O56: =SUM(O25:O55) -> 87458 | P56: =SUM(P25:P55) -> 82175 | Q56: =SUM(Q25:Q55) -> 176589 | R56: =SUM(R25:R55) -> 102140 | S56: =IF(AND(I56<>"", I56<>0), G56/I56, "") -> 0.083584716 | T56: =D56/U56 -> 0.71583393 | U56: =SUM(U25:U55) -> 2458965.6 | V56: =SUM(V25:V55) -> 353.808 | W56: =SUM(W25:W55) -> 194.4 | X56: =SUM(X25:X55) -> 1760211 | Y56: =SUM(Y25:Y55) -> 230 | Z56: =SUM(Z25:Z55) -> 223
D57: =SUMIF(D25:D55,"",U25:U55)+D56 -> 1760211 | I57: =I56/J14 -> 53.04
D58: =Рогалевич!D56+Самошкина!D57+Уразгильдеева!D57 -> 1760211 | E58: =Рогалевич!E56+Уразгильдеева!E57+Самошкина!E57 -> 230 | G58: =Рогалевич!G56+Уразгильдеева!G57+Самошкина!G57 -> 132 | I58: =Рогалевич!I56+Уразгильдеева!I57+Самошкина!I57 -> 1674 | K58: =Рогалевич!K56+Уразгильдеева!K57+Самошкина!K57 -> 224427 | L58: =Рогалевич!L56+Уразгильдеева!L57 -> 239933 | M58: =Рогалевич!M56+Уразгильдеева!M57 -> 12893 | N58: =Рогалевич!N56+Уразгильдеева!N57+Самошкина!N57 -> 68112 | O58: =Уразгильдеева!O57+Рогалевич!O56 -> 87458 | P58: =Рогалевич!P56+Уразгильдеева!P57+Самошкина!P57 -> 82175 | Q58: =Рогалевич!Q56+Уразгильдеева!Q57+Самошкина!Q57 -> 176589 | R58: =Рогалевич!R56+Уразгильдеева!R57+Самошкина!R57 -> 102139.58

Sheet Св. по пок.
A2: Показатель | D2: ='Ялта, Ленина, 18'!I3 -> ул. Набережная Ленина, 18 | G2: =График!B28 -> Рогалевич Ирина | J2: =График!B27 -> Уразгильдеева Екатерина | M2: =График!B26 -> Самошкина Алина
D3: Факт | F3: Прогноз | G3: Факт | I3: Прогноз | J3: Факт | L3: Прогноз | M3: Факт | O3: Прогноз
A4: Выручка | D4: ='Ялта, Ленина, 18'!K8 -> 0.71583393 | E4: ='Ялта, Ленина, 18'!J8 -> 1760211 | F4: ='Ялта, Ленина, 18'!M8 -> 0.71583393 | G4: =Рогалевич!N8 -> 0.87196753 | H4: =Рогалевич!M8 -> 792102 | I4: =Рогалевич!P8 -> 0.87196753 | J4: =Уразгильдеева!N8 -> 0.7155404 | K4: =Уразгильдеева!M8 -> 780750 | L4: =Уразгильдеева!P8 -> 0.7155404 | M4: =Самошкина!N8 -> 0.40781232 | N4: =Самошкина!M8 -> 187359 | O4: =Самошкина!P8 -> 0.81562464
A5: Кол-во изделий | D5: ='Ялта, Ленина, 18'!K9 -> 0.65007009 | E5: ='Ялта, Ленина, 18'!J9 -> 230 | F5: ='Ялта, Ленина, 18'!M9 -> 0.65007009 | G5: =Рогалевич!N9 -> 0.6885675 | H5: =Рогалевич!M9 -> 90 | I5: =Рогалевич!P9 -> 0.6885675 | J5: =Уразгильдеева!N9 -> 0.68153906 | K5: =Уразгильдеева!M9 -> 107 | L5: =Уразгильдеева!P9 -> 0.68153906 | M5: =Самошкина!N9 -> 0.49921144 | N5: =Самошкина!M9 -> 33 | O5: =Самошкина!P9 -> 0.99842287
A6: Средний чек | D6: ='Ялта, Ленина, 18'!K10 -> 1.0463016 | E6: ='Ялта, Ленина, 18'!J10 -> 13234.669 | F6: ='Ялта, Ленина, 18'!M10 -> 1.0463016 | G6: =Рогалевич!N10 -> 1.2042636 | H6: =Рогалевич!M10 -> 15232.731 | I6: =Рогалевич!P10 -> 1.2042636 | J6: =Уразгильдеева!N10 -> 0.97974995 | K6: =Уразгильдеева!M10 -> 12392.857 | L6: =Уразгильдеева!P10 -> 0.97974995 | M6: =Самошкина!N10 -> 0.87130347 | N6: =Самошкина!M10 -> 11021.118 | O6: =Самошкина!P10 -> 0.87130347
A7: Средняя стоимость изделия | D7: ='Ялта, Ленина, 18'!K11 -> 1.1011642 | E7: ='Ялта, Ленина, 18'!J11 -> 7653.0913 | F7: ='Ялта, Ленина, 18'!M11 -> 1.1011642 | G7: =Рогалевич!N11 -> 1.2663501 | H7: =Рогалевич!M11 -> 8801.1333 | I7: =Рогалевич!P11 -> 1.2663501 | J7: =Уразгильдеева!N11 -> 1.0498891 | K7: =Уразгильдеева!M11 -> 7296.729 | L7: =Уразгильдеева!P11 -> 1.0498891 | M7: =Самошкина!N11 -> 0.81691302 | N7: =Самошкина!M11 -> 5677.5455 | O7: =Самошкина!P11 -> 0.81691302
A8: Длина чека | D8: ='Ялта, Ленина, 18'!K12 -> 0.95017764 | E8: ='Ялта, Ленина, 18'!J12 -> 1.7293233 | F8: ='Ялта, Ленина, 18'!M12 -> 0.95017764 | G8: =Рогалевич!N12 -> 0.9509721 | H8: =Рогалевич!M12 -> 1.7307692 | I8: =Рогалевич!P12 -> 0.9509721 | J8: =Уразгильдеева!N12 -> 0.93319379 | K8: =Уразгильдеева!M12 -> 1.6984127 | L8: =Уразгильдеева!P12 -> 0.93319379 | M8: =Самошкина!N12 -> 1.0665805 | N8: =Самошкина!M12 -> 1.9411765 | O8: =Самошкина!P12 -> 1.0665805
A9: Кол-во чеков | D9: ='Ялта, Ленина, 18'!K13 -> 0.68415638 | E9: ='Ялта, Ленина, 18'!J13 -> 133 | F9: ='Ялта, Ленина, 18'!M13 -> 0.68415638 | G9: =Рогалевич!N13 -> 0.72406698 | H9: =Рогалевич!M13 -> 52 | I9: =Рогалевич!P13 -> 0.72406698 | J9: =Уразгильдеева!N13 -> 0.73032961 | K9: =Уразгильдеева!M13 -> 63 | L9: =Уразгильдеева!P13 -> 0.73032961 | M9: =Самошкина!N13 -> 0.46804854 | N9: =Самошкина!M13 -> 17 | O9: =Самошкина!P13 -> 0.93609708
A10: Кол-во смен план/отработано | D10: ='Ялта, Ленина, 18'!K14 -> 1 | E10: ='Ялта, Ленина, 18'!J14 -> 30 | G10: =Рогалевич!N14 -> 1 | H10: =Рогалевич!M14 -> 19 | I10: =Рогалевич!P14 -> 1 | J10: =Уразгильдеева!N14 -> 0.95 | K10: =Уразгильдеева!M14 -> 19 | M10: =Самошкина!N14 -> 1 | N10: =Самошкина!M14 -> 8 | O10: =Самошкина!P14 -> 1
A11: Средние продажи в смену | D11: ='Ялта, Ленина, 18'!K15 -> 0.71583393 | E11: ='Ялта, Ленина, 18'!J15 -> 58673.7 | F11: ='Ялта, Ленина, 18'!M15 -> 0.71583393 | G11: =Рогалевич!N15 -> 0.50862337 | H11: =Рогалевич!M15 -> 41689.579 | I11: =Рогалевич!P15 -> 0.50862337 | J11: =Уразгильдеева!N15 -> 0.50133404 | K11: =Уразгильдеева!M15 -> 41092.105 | L11: =Уразгильдеева!P15 -> 0.50133404 | M11: =Самошкина!N15 -> 0.28572838 | N11: =Самошкина!M15 -> 23419.875 | O11: =Самошкина!P15 -> 0.28572838
A12: Трафик | D12: ='Ялта, Ленина, 18'!K17 -> 0.884 | E12: ='Ялта, Ленина, 18'!J17 -> 1591.2 | F12: ='Ялта, Ленина, 18'!M17 -> 0.884 | G12: =Рогалевич!N17 -> 0.89778736 | H12: =Рогалевич!M17 -> 597 | I12: =Рогалевич!P17 -> 0.89778736 | J12: =Уразгильдеева!N17 -> 1.0003429 | K12: =Уразгильдеева!M17 -> 799 | L12: =Уразгильдеева!P17 -> 1.0529925 | M12: =Самошкина!N17 -> 0.82662879 | N12: =Самошкина!M17 -> 278 | O12: =Самошкина!P17 -> 0.82662879
A13: ='Ялта, Ленина, 18'!F18 -> Выручка на вошедшего | D13: ='Ялта, Ленина, 18'!K18 -> 0.80976688 | E13: ='Ялта, Ленина, 18'!J18 -> 1106.2161 | F13: ='Ялта, Ленина, 18'!M18 -> 0.80976688 | G13: =Рогалевич!N18 -> 0.9712406 | H13: =Рогалевич!M18 -> 1326.804 | I13: =Рогалевич!P18 -> 0.9712406 | J13: =Уразгильдеева!N18 -> 0.71529513 | K13: =Уразгильдеева!M18 -> 977.15895 | L13: =Уразгильдеева!P18 -> 0.71529513 | M13: =Самошкина!N18 -> 0.49334396 | N13: =Самошкина!M18 -> 673.95324 | O13: =Самошкина!P18 -> 0.49334396
A14: ='Ялта, Ленина, 18'!F20 -> Конверсия план/факт | D14: ='Ялта, Ленина, 18'!K20 -> 0.77393255 | E14: ='Ялта, Ленина, 18'!J20 -> 0.083584716 | G14: =Рогалевич!N20 -> 0.80650164 | H14: =Рогалевич!M20 -> 0.087102178 | J14: =Уразгильдеева!N20 -> 0.73007927 | K14: =Уразгильдеева!M20 -> 0.078848561 | L14: =Уразгильдеева!T13 -> 1.3333333 | M14: =Самошкина!N20 -> 0.5662137 | N14: =Самошкина!M20 -> 0.061151079
A15: Доп. KPI | D15: ='Ялта, Ленина, 18'!R56 -> 102140 | G15: =Рогалевич!R56 -> 30605 | J15: =Уразгильдеева!R57 -> 48260.58 | M15: =Самошкина!R57 -> 23274

Sheet План на день
A1: Выручка | B1: 73000
A2: Кол-во изделий | B2: =B1/B4 -> 10.503597
A3: Средний чек | B3: =B4*B5 -> 12649
A4: Средняя стоимость изделия | B4: ='Ялта, Ленина, 18'!I11 -> 6950
A5: Длина чека | B5: ='Ялта, Ленина, 18'!I12 -> 1.82
A6: Кол-во чеков | B6: =IF(B5<>0,B2/B5,"") -> 5.7712072
A7: Конверсия | B7: ='Ялта, Ленина, 18'!I20 -> 0.108
A8: IS | B8: =('Ялта, Ленина, 18'!R12-'Ялта, Ленина, 18'!S12)/('Ялта, Ленина, 18'!I14-'Ялта, Ленина, 18'!J14) -> #DIV/0!
A9: UNOde50 | B9: =('Ялта, Ленина, 18'!R18-'Ялта, Ленина, 18'!S18)/('Ялта, Ленина, 18'!I14-'Ялта, Ленина, 18'!J14) -> #DIV/0!
A10: ='Ялта, Ленина, 18'!M23 -> Agafi | B10: =('Ялта, Ленина, 18'!U12-'Ялта, Ленина, 18'!V12)/('Ялта, Ленина, 18'!I14-'Ялта, Ленина, 18'!J14) -> #DIV/0!

Sheet Рогалевич
B2: (отчетная дата) | J2: ЕЖЕДНЕВНЫЙ ОТЧЕТ О ПРОДАЖАХ
B3: Осталось до выполнения плана!!! | J3: =График!B28 -> Рогалевич Ирина
C4: =L8-D56 -> 116305.67 | E4: =IF(L8<>0,C4/L8,0) -> 0.12803247
I6: Целевые показатели
I7: Показатель | L7: План | M7: Факт | N7: % выполнения | O7: Прогноз выполнения | P7: % выполнения по прогнозу | Q7: Отклонение | R7: Факт аналогичного месяца прошлого года | S7: Отклонение LFL
I8: Выручка | L8: ='Ялта, Ленина, 18'!I8/График!AJ29*График!AJ28 -> 908407.67 | M8: =D56 -> 792102 | N8: =IF(AND(L8<>"",L8<>0,M8<>""),M8/L8,"") -> 0.87196753 | O8: =IF(SUMIF($D$25:$D$55,">=0",$U$24:$U$55)<>0,L8*D56/SUMIF($D$25:$D$55,">=0",$U$24:$U$55),0) -> 792102 | P8: =IF(AND(L8<>"",L8<>0,O8<>"",O8<>0),O8/L8,"") -> 0.87196753 | Q8: =IF(AND(M8<>0,M8<>"",L8<>0,L8<>""),O8-L8,"") -> -116305.67 | R8: 1663026 | S8: =IF(AND(R8<>"",R8<>0,O8<>"",O8<>0),-R8+O8,"") -> -870924 | T8: =IF(AND(S8<>"",S8<>0,R8<>0,R8<>""),S8/R8,"") -> -0.52369837
I9: Кол-во изделий | L9: =L8/L11 -> 130.70614 | M9: =E56 -> 90 | N9: =IF(AND(L9<>"",L9<>0,M9<>""),M9/L9,"") -> 0.6885675 | O9: =IF(SUMIF($E$25:$E$53,">=0",$V$24:$V$53)<>0,L9*E56/SUMIF($E$25:$E$53,">=0",$V$24:$V$53),0) -> 90 | P9: =IF(AND(L9<>"",L9<>0,O9<>"",O9<>0),O9/L9,"") -> 0.6885675 | Q9: =IF(AND(M9<>0,M9<>"",L9<>0,L9<>""),O9-L9,"") -> -40.70614 | R9: 315 | S9: =IF(AND(R9<>"",R9<>0,O9<>"",O9<>0),-R9+O9,"") -> -225 | T9: =IF(AND(S9<>"",S9<>0,R9<>0,R9<>""),S9/R9,"") -> -0.71428571
I10: Средний чек | L10: =L11*L12 -> 12649 | M10: =H56 -> 15232.731 | N10: =IF(AND(L10<>"",L10<>0,M10<>""),M10/L10,"") -> 1.2042636 | O10: =M10 -> 15232.731 | P10: =IF(AND(L10<>"",L10<>0,O10<>"",O10<>0),O10/L10,"") -> 1.2042636 | Q10: =IF(AND(M10<>0,M10<>"",L10<>0,L10<>""),O10-L10,"") -> 2583.7308 | R10: 10869.451 | S10: =IF(AND(R10<>"",R10<>0,O10<>"",O10<>0),-R10+O10,"") -> 4363.2798 | T10: =IF(AND(S10<>"",S10<>0,R10<>0,R10<>""),S10/R10,"") -> 0.40142596
I11: Средняя стоимость изделия | L11: ='Ялта, Ленина, 18'!I11 -> 6950 | M11: =F56 -> 8801.1333 | N11: =IF(AND(L11<>"",L11<>0,M11<>""),M11/L11,"") -> 1.2663501 | O11: =IF(O9>0,O8/O9,"") -> 8801.1333 | P11: =IF(AND(L11<>"",L11<>0,O11<>"",O11<>0),O11/L11,"") -> 1.2663501 | Q11: =IF(AND(M11<>0,M11<>"",L11<>0,L11<>""),O11-L11,"") -> 1851.1333 | R11: 5279.4476 | S11: =IF(AND(R11<>"",R11<>0,O11<>"",O11<>0),-R11+O11,"") -> 3521.6857 | T11: =IF(AND(S12<>"",S12<>0,R12<>0,R12<>""),S12/R12,"") -> -0.15934066
I12: Длина чека | L12: ='Ялта, Ленина, 18'!I12 -> 1.82 | M12: =J56 -> 1.7307692 | N12: =IF(AND(L12<>"",L12<>0,M12<>""),M12/L12,"") -> 0.9509721 | O12: =M12 -> 1.7307692 | P12: =IF(AND(L12<>"",L12<>0,O12<>"",O12<>0),O12/L12,"") -> 0.9509721 | Q12: =IF(AND(M12<>0,M12<>"",L12<>0,L12<>""),O12-L12,"") -> -0.089230769 | R12: 2.0588235 | S12: =IF(AND(R12<>"",R12<>0,O12<>"",O12<>0),-R12+O12,"") -> -0.3280543
I13: Кол-во чеков | L13: =IF(L12<>0,L9/L12,"") -> 71.816561 | M13: =G56 -> 52 | N13: =IF(AND(L13<>"",L13<>0,M13<>""),M13/L13,"") -> 0.72406698 | O13: =IF(SUMIF($G$25:$G$53,">=0",$W$24:$W$53)<>0,L13*G56/SUMIF($G$25:$G$53,">=0",$W$24:$W$53),"") -> 52 | P13: =IF(AND(L13<>"",L13<>0,O13<>"",O13<>0),O13/L13,"") -> 0.72406698 | Q13: =IF(AND(M13<>0,M13<>"",L13<>0,L13<>""),O13-L13,"") -> -19.816561 | R13: 153 | S13: =IF(AND(R13<>"",R13<>0,O13<>"",O13<>0),-R13+O13,"") -> -101 | T13: =IF(AND(S14<>"",S14<>0,R14<>0,R14<>""),S14/R14,"") -> -0.34482759
I14: Кол-во смен план/отработано | L14: =График!AI28 -> 19 | M14: 19 | N14: =IF(AND(L14<>"",L14<>0,M14<>""),M14/L14,"") -> 1 | O14: =L14 -> 19 | P14: =IF(AND(L14<>"",L14<>0,O14<>"",O14<>0),O14/L14,"") -> 1 | Q14: =IF(AND(M14<>0,M14<>"",L14<>0,L14<>""),O14-L14,"") -> 0 | R14: 29 | S14: =IF(AND(R14<>"",R14<>0,O14<>"",O14<>0),-R14+O14,"") -> -10 | T14: =IF(AND(S15<>"",S15<>0,R15<>0,R15<>""),S15/R15,"") -> -0.2730133
I15: Средние продажи в смену | L15: ='Ялта, Ленина, 18'!I15 -> 81965.52 | M15: =M8/M14 -> 41689.579 | N15: =IF(AND(L15<>"",L15<>0,M15<>""),M15/L15,"") -> 0.50862337 | O15: =M15 -> 41689.579 | P15: =IF(AND(L15<>"",L15<>0,O15<>"",O15<>0),O15/L15,"") -> 0.50862337 | Q15: =IF(AND(M15<>0,M15<>"",L15<>0,L15<>""),O15-L15,"") -> -40275.941 | R15: 57345.724 | S15: =IF(AND(R15<>"",R15<>0,O15<>"",O15<>0),-R15+O15,"") -> -15656.145 | T15: =IF(AND(S16<>"",S16<>0,R16<>0,R16<>""),S16/R16,"")
I16: Отставание/Перевыполнение | N16: =IF(AND(L16<>"",L16<>0,M16<>""),M16/L16,"") | O16: =M16 -> 0 | P16: =IF(AND(L16<>"",L16<>0,O16<>"",O16<>0),O16/L16,"") | Q16: =IF(AND(M16<>0,M16<>"",L16<>0,L16<>""),O16-L16,"") | R16: -838811.89 | S16: =IF(AND(R16<>"",R16<>0,O16<>"",O16<>0),-R16+O16,"") | T16: =IF(AND(S17<>"",S17<>0,R17<>0,R17<>""),S17/R17,"") -> -0.0671875
I17: Трафик | L17: ='Ялта, Ленина, 18'!I17/График!AJ29*График!AJ28 -> 664.96815 | M17: =I56 -> 597 | N17: =IF(AND(L17<>"",L17<>0,M17<>""),M17/L17,"") -> 0.89778736 | O17: =M17/M14*L14 -> 597 | P17: =IF(AND(L17<>"",L17<>0,O17<>"",O17<>0),O17/L17,"") -> 0.89778736 | Q17: =IF(AND(M17<>0,M17<>"",L17<>0,L17<>""),O17-L17,"") -> -67.968153 | R17: 640 | S17: =IF(AND(R17<>"",R17<>0,O17<>"",O17<>0),-R17+O17,"") -> -43 | T17: =IF(AND(S18<>"",S18<>0,R18<>0,R18<>""),S18/R18,"")
I18: Выручка на вошедшего | L18: =L8/L17 -> 1366.092 | M18: =M8/M17 -> 1326.804 | N18: =IF(AND(L18<>"", L18<>0, M18<>""), M18/L18, "") -> 0.9712406 | O18: =M18 -> 1326.804 | P18: =IF(AND(L18<>"", L18<>0, O18<>"", O18<>0), O18/L18, "") -> 0.9712406 | Q18: =IF(AND(M18<>0, M18<>"", L18<>0, L18<>""), O18-L18, "") -> -39.28798 | S18: =IF(AND(R18<>"",R18<>0,O18<>"",O18<>0),-R18+O18,"") | T18: =IF(AND(S19<>"",S19<>0,R19<>0,R19<>""),S19/R19,"")
N19: =IF(AND(L19<>"",L19<>0,M19<>""),M19/L19,"") | O19: =M19 -> 0 | P19: =IF(AND(L19<>"",L19<>0,O19<>"",O19<>0),O19/L19,"") | Q19: =IF(AND(M19<>0,M19<>"",L19<>0,L19<>""),O19-L19,"") | R19: 0 | S19: =IF(AND(R19<>"",R19<>0,O19<>"",O19<>0),-R19+O19,"") | T19: =IF(AND(S20<>"",S20<>0,R20<>0,R20<>""),S20/R20,"") -> -0.62445897
I20: Конверсия план/факт | L20: ='Ялта, Ленина, 18'!I20 -> 0.108 | M20: =S56 -> 0.087102178 | N20: =M20/L20 -> 0.80650164 | O20: =IF(AND(N8<>0,L14<>0,I56<>0),(I56*S56+(I56/N8-I56)*L20)/(I56/N8),0) -> 0.089777777 | P20: =IF(AND(L20<>"",L20<>0,O20<>"",O20<>0),O20/L20,"") -> 0.83127572 | Q20: =IF(AND(M20<>0,M20<>"",L20<>0,L20<>""),O20-L20,"") -> -0.018222223 | R20: 0.2390625 | S20: =IF(AND(R20<>"",R20<>0,O20<>"",O20<>0),-R20+O20,"") -> -0.14928472
T21: % выполнения дневного плана | U21: Раcпределение плана по дням
B22: Факт продаж за месяц | U22: выручка, план | V22: кол-во ед, план | W22: Кол-во чеков, план | X22: выручка, скорректир.план | Y22: кол-во ед, скорр. план | Z22: кол-во чеков, скорр. план | AA22: Коэфф. Дня Недели | AB22: Специфика месяца
B23: Дата | C23: День недели | D23: Выручка (руб) | E23: Кол-во единиц (шт.) | F23: Средняя стоимость изделия (руб.) | G23: Количество чеков (шт.) | H23: Средняя сумма чека (руб.) | I23: Трафик | J23: Длина чека (шт.) | K23: UNOde50 | L23: IS | M23: Agafi | N23: Kalliope | O23: Raganella | P23: CC\MP | Q23: Antura | R23: SALE | S23: Конверсия (%) | U23: 1 | V23: 2 | W23: 3 | X23: 4 | Y23: 5 | Z23: 6 | AA23: 10 | AB23: 11
A24: 1 | B24: 1 | C24: 2 | D24: 3 | E24: 4 | F24: 5 | G24: 6 | H24: 7 | I24: 8 | J24: 9 | K24: 10 | L24: 11 | M24: 12 | N24: 13 | O24: 14 | Q24: 15 | R24: 16 | S24: 17 | T24: =D25/U24 -> 1.2568641 | U24: =$L$8*AA24*AB24/SUMPRODUCT($AB$24:$AB$55,$AA$24:$AA$55) -> 82582.516 | V24: =$L$9*AA24*AB24/SUMPRODUCT($AB$24:$AB$55,$AA$24:$AA$55) -> 11.882376 | W24: =IF($L$12="","",V24/$L$12) -> 6.5287782 | X24: =IF(D25<>"",D25,U24) -> 103795 | Y24: =IF(E25<>"",E25,V24) -> 9 | Z24: =IF(G25<>"",G25,W24) -> 4 | AA24: 1 | AB24: 1
A25: 2 | B25: 46113 | C25: ср | D25: =4393+85786+6723+6893 -> 103795 | E25: 9 | F25: =IF(AND(E25<>"",E25<>0),D25/E25,"") -> 11532.778 | G25: 4 | H25: =IF(AND(G25<>"",G25<>0),D25/G25,"") -> 25948.75 | I25: 37 | J25: =IF(AND(G25<>"",G25<>0),E25/G25,"") -> 2.25 | K25: 24291 | N25: 34542 | Q25: 21343 | S25: =IF(AND(I25<>"",I25<>0),G25/I25,"") -> 0.10810811 | T25: =D26/U25 -> 0.11605362 | U25: =$L$8*AA25*AB25/SUMPRODUCT($AB$24:$AB$55,$AA$24:$AA$55) -> 82582.516 | V25: =$L$9*AA25*AB25/SUMPRODUCT($AB$24:$AB$57,$AA$24:$AA$57) -> 11.882376 | W25: =IF($L$12="","",V25/$L$12) -> 6.5287782 | X25: =IF(AB25<>"",IF(D26<>"",D26,($L$8-SUM($X$24:X24))*AA25*AB25/SUMPRODUCT($AB25:$AB$55,$AA25:$AA$55)),"") -> 9584 | Y25: =IF(AB25<>"",IF(E26<>"",E26,($L$9-SUM($Y$24:Y24))*AA25*AB25/SUMPRODUCT($AB25:$AB$57,$AA25:$AA$57)),"") -> 2 | Z25: =IF(AB25<>"",IF($L$12<>"",IF(G26<>"",G26,($L$9/$L$12-SUM($Z$24:Z24))*AA25*AB25/SUMPRODUCT($AB25:$AB$57,$AA25:$AA$57)),""),"") -> 1 | AA25: 1 | AB25: 1
A26: 3 | B26: 46114 | C26: чт | D26: 9584 | E26: 2 | F26: =IF(AND(E26<>"",E26<>0),D26/E26,"") -> 4792 | G26: 1 | H26: =IF(AND(G26<>"",G26<>0),D26/G26,"") -> 9584 | I26: 15 | J26: =IF(AND(G26<>"",G26<>0),E26/G26,"") -> 2 | S26: =IF(AND(I26<>"",I26<>0),G26/I26,"") -> 0.066666667 | T26: =D27/U26 -> 0.053195279 | U26: =$L$8*AA26*AB26/SUMPRODUCT($AB$24:$AB$55,$AA$24:$AA$55) -> 82582.516 | V26: =$L$9*AA26*AB26/SUMPRODUCT($AB$24:$AB$57,$AA$24:$AA$57) -> 11.882376 | W26: =IF($L$12="","",V26/$L$12) -> 6.5287782 | X26: =IF(AB26<>"",IF(D27<>"",D27,($L$8-SUM($X$24:X25))*AA26*AB26/SUMPRODUCT($AB26:$AB$57,$AA26:$AA$57)),"") -> 4393 | Y26: =IF(AB26<>"",IF(E27<>"",E27,($L$9-SUM($Y$24:Y25))*AA26*AB26/SUMPRODUCT($AB26:$AB$57,$AA26:$AA$57)),"") -> 1 | Z26: =IF(AB26<>"",IF($L$12<>"",IF(G27<>"",G27,($L$9/$L$12-SUM($Z$24:Z25))*AA26*AB26/SUMPRODUCT($AB26:$AB$57,$AA26:$AA$57)),""),"") -> 1 | AA26: 1 | AB26: 1
A27: 4 | B27: 46115 | C27: пт | D27: 4393 | E27: 1 | F27: 4393 | G27: 1 | H27: =IF(AND(G27<>"",G27<>0),D27/G27,"") -> 4393 | I27: 20 | J27: =IF(AND(G27<>"",G27<>0),E27/G27,"") -> 1 | S27: =IF(AND(I27<>"",I27<>0),G27/I27,"") -> 0.05 | T27: =D28/U27 -> 0.22746946 | U27: =$L$8*AA27*AB27/SUMPRODUCT($AB$24:$AB$55,$AA$24:$AA$55) -> 82582.516 | V27: =$L$9*AA27*AB27/SUMPRODUCT($AB$24:$AB$57,$AA$24:$AA$57) -> 11.882376 | W27: =IF($L$12="","",V27/$L$12) -> 6.5287782 | X27: =IF(AB27<>"",IF(D28<>"",D28,($L$8-SUM($X$24:X26))*AA27*AB27/SUMPRODUCT($AB27:$AB$57,$AA27:$AA$57)),"") -> 18785 | Y27: =IF(AB27<>"",IF(E28<>"",E28,($L$9-SUM($Y$24:Y26))*AA27*AB27/SUMPRODUCT($AB27:$AB$57,$AA27:$AA$57)),"") -> 2 | Z27: =IF(AB27<>"",IF($L$12<>"",IF(G28<>"",G28,($L$9/$L$12-SUM($Z$24:Z26))*AA27*AB27/SUMPRODUCT($AB27:$AB$57,$AA27:$AA$57)),""),"") -> 2 | AA27: 1 | AB27: 1
A28: 5 | B28: 46116 | C28: сб | D28: 18785 | E28: 2 | F28: 9392 | G28: 2 | H28: 9392 | I28: 23 | J28: =IF(AND(G28<>"",G28<>0),E28/G28,"") -> 1 | Q28: 14093 | S28: =IF(AND(I28<>"",I28<>0),G28/I28,"") -> 0.086956522 | T28: =D29/U28 -> 0.78619547 | U28: =$L$8*AA28*AB28/SUMPRODUCT($AB$24:$AB$55,$AA$24:$AA$55) -> 82582.516 | V28: =$L$9*AA28*AB28/SUMPRODUCT($AB$24:$AB$57,$AA$24:$AA$57) -> 11.882376 | W28: =IF($L$12="","",V28/$L$12) -> 6.5287782 | X28: =IF(AB28<>"",IF(D29<>"",D29,($L$8-SUM($X$24:X27))*AA28*AB28/SUMPRODUCT($AB28:$AB$57,$AA28:$AA$57)),"") -> 64926 | Y28: =IF(AB28<>"",IF(E29<>"",E29,($L$9-SUM($Y$24:Y27))*AA28*AB28/SUMPRODUCT($AB28:$AB$57,$AA28:$AA$57)),"") -> 10 | Z28: =IF(AB28<>"",IF($L$12<>"",IF(G29<>"",G29,($L$9/$L$12-SUM($Z$24:Z27))*AA28*AB28/SUMPRODUCT($AB28:$AB$57,$AA28:$AA$57)),""),"") -> 3 | AA28: 1 | AB28: 1
A29: 6 | B29: 46117 | C29: вс | D29: 64926 | E29: 10 | F29: =IF(AND(E29<>"",E29<>0),D29/E29,"") -> 6492.6 | G29: 3 | H29: =IF(AND(G29<>"",G29<>0),D29/G29,"") -> 21642 | I29: 30 | J29: =IF(AND(G29<>"",G29<>0),E29/G29,"") -> 3.3333333 | N29: 33570 | R29: 6490 | S29: =IF(AND(I29<>"",I29<>0),G29/I29,"") -> 0.1 | T29: =D30/U29 -> 0.34477032 | U29: =$L$8*AA29*AB29/SUMPRODUCT($AB$24:$AB$55,$AA$24:$AA$55) -> 82582.516 | V29: =$L$9*AA29*AB29/SUMPRODUCT($AB$24:$AB$57,$AA$24:$AA$57) -> 11.882376 | W29: =IF($L$12="","",V29/$L$12) -> 6.5287782 | X29: =IF(AB29<>"",IF(D30<>"",D30,($L$8-SUM($X$24:X28))*AA29*AB29/SUMPRODUCT($AB29:$AB$57,$AA29:$AA$57)),"") -> 28472 | Y29: =IF(AB29<>"",IF(E30<>"",E30,($L$9-SUM($Y$24:Y28))*AA29*AB29/SUMPRODUCT($AB29:$AB$57,$AA29:$AA$57)),"") -> 3 | Z29: =IF(AB29<>"",IF($L$12<>"",IF(G30<>"",G30,($L$9/$L$12-SUM($Z$24:Z28))*AA29*AB29/SUMPRODUCT($AB29:$AB$57,$AA29:$AA$57)),""),"") -> 1 | AA29: 1 | AB29: 1
A30: 7 | B30: 46123 | C30: сб | D30: 28472 | E30: 3 | F30: =IF(AND(E30<>"",E30<>0),D30/E30,"") -> 9490.6667 | G30: 1 | H30: =IF(AND(G30<>"",G30<>0),D30/G30,"") -> 28472 | I30: 15 | J30: =IF(AND(G30<>"",G30<>0),E30/G30,"") -> 3 | Q30: 20780 | S30: =IF(AND(I30<>"",I30<>0),G30/I30,"") -> 0.066666667 | T30: =D31/U30 -> 1.3356217 | U30: =$L$8*AA30*AB30/SUMPRODUCT($AB$24:$AB$55,$AA$24:$AA$55) -> 82582.516 | V30: =$L$9*AA30*AB30/SUMPRODUCT($AB$24:$AB$57,$AA$24:$AA$57) -> 11.882376 | W30: =IF($L$12="","",V30/$L$12) -> 6.5287782 | X30: =IF(AB30<>"",IF(D31<>"",D31,($L$8-SUM($X$24:X29))*AA30*AB30/SUMPRODUCT($AB30:$AB$57,$AA30:$AA$57)),"") -> 110299 | Y30: =IF(AB30<>"",IF(E31<>"",E31,($L$9-SUM($Y$24:Y29))*AA30*AB30/SUMPRODUCT($AB30:$AB$57,$AA30:$AA$57)),"") -> 9 | Z30: =IF(AB30<>"",IF($L$12<>"",IF(G31<>"",G31,($L$9/$L$12-SUM($Z$24:Z29))*AA30*AB30/SUMPRODUCT($AB30:$AB$57,$AA30:$AA$57)),""),"") -> 5 | AA30: 1 | AB30: 1
A31: 8 | B31: 46124 | C31: вс | D31: 110299 | E31: 9 | F31: =IF(AND(E31<>"",E31<>0),D31/E31,"") -> 12255.444 | G31: 5 | H31: =IF(AND(G31<>"",G31<>0),D31/G31,"") -> 22059.8 | I31: 15 | J31: =IF(AND(G31<>"",G31<>0),E31/G31,"") -> 1.8 | K31: 22931 | L31: 45002 | S31: =IF(AND(I31<>"",I31<>0),G31/I31,"") -> 0.33333333 | T31: =D32/U31 -> 0.653177 | U31: =$L$8*AA31*AB31/SUMPRODUCT($AB$24:$AB$55,$AA$24:$AA$55) -> 82582.516 | V31: =$L$9*AA31*AB31/SUMPRODUCT($AB$24:$AB$57,$AA$24:$AA$57) -> 11.882376 | W31: =IF($L$12="","",V31/$L$12) -> 6.5287782 | X31: =IF(AB31<>"",IF(D32<>"",D32,($L$8-SUM($X$24:X30))*AA31*AB31/SUMPRODUCT($AB31:$AB$57,$AA31:$AA$57)),"") -> 53941 | Y31: =IF(AB31<>"",IF(E32<>"",E32,($L$9-SUM($Y$24:Y30))*AA31*AB31/SUMPRODUCT($AB31:$AB$57,$AA31:$AA$57)),"") -> 7 | Z31: =IF(AB31<>"",IF($L$12<>"",IF(G32<>"",G32,($L$9/$L$12-SUM($Z$24:Z30))*AA31*AB31/SUMPRODUCT($AB31:$AB$57,$AA31:$AA$57)),""),"") -> 5 | AA31: 1 | AB31: 1
A32: 9 | B32: 46125 | C32: пн | D32: 53941 | E32: 7 | F32: =IF(AND(E32<>"",E32<>0),D32/E32,"") -> 7705.8571 | G32: 5 | H32: =IF(AND(G32<>"",G32<>0),D32/G32,"") -> 10788.2 | I32: 25 | J32: =IF(AND(G32<>"",G32<>0),E32/G32,"") -> 1.4 | K32: 31984 | R32: 3245 | S32: =IF(AND(I32<>"",I32<>0),G32/I32,"") -> 0.2 | T32: =D33/U32 -> 0.3380982 | U32: =$L$8*AA32*AB32/SUMPRODUCT($AB$24:$AB$55,$AA$24:$AA$55) -> 82582.516 | V32: =$L$9*AA32*AB32/SUMPRODUCT($AB$24:$AB$57,$AA$24:$AA$57) -> 11.882376 | W32: =IF($L$12="","",V32/$L$12) -> 6.5287782 | X32: =IF(AB32<>"",IF(D33<>"",D33,($L$8-SUM($X$24:X31))*AA32*AB32/SUMPRODUCT($AB32:$AB$57,$AA32:$AA$57)),"") -> 27921 | Y32: =IF(AB32<>"",IF(E33<>"",E33,($L$9-SUM($Y$24:Y31))*AA32*AB32/SUMPRODUCT($AB32:$AB$57,$AA32:$AA$57)),"") -> 3 | Z32: =IF(AB32<>"",IF($L$12<>"",IF(G33<>"",G33,($L$9/$L$12-SUM($Z$24:Z31))*AA32*AB32/SUMPRODUCT($AB32:$AB$57,$AA32:$AA$57)),""),"") -> 3 | AA32: 1 | AB32: 1
A33: 10 | B33: 46126 | C33: вт | D33: 27921 | E33: 3 | F33: 9307 | G33: 3 | H33: =IF(AND(G33<>"",G33<>0),D33/G33,"") -> 9307 | I33: 33 | J33: =IF(AND(G33<>"",G33<>0),E33/G33,"") -> 1 | K33: 11592 | S33: =IF(AND(I33<>"",I33<>0),G33/I33,"") -> 0.090909091 | T33: =D34/U33 -> 1.7067293 | U33: =$L$8*AA33*AB33/SUMPRODUCT($AB$24:$AB$55,$AA$24:$AA$55) -> 82582.516 | V33: =$L$9*AA33*AB33/SUMPRODUCT($AB$24:$AB$57,$AA$24:$AA$57) -> 11.882376 | W33: =IF($L$12="","",V33/$L$12) -> 6.5287782 | X33: =IF(AB33<>"",IF(D34<>"",D34,($L$8-SUM($X$24:X32))*AA33*AB33/SUMPRODUCT($AB33:$AB$57,$AA33:$AA$57)),"") -> 140946 | Y33: =IF(AB33<>"",IF(E34<>"",E34,($L$9-SUM($Y$24:Y32))*AA33*AB33/SUMPRODUCT($AB33:$AB$57,$AA33:$AA$57)),"") -> 10 | Z33: =IF(AB33<>"",IF($L$12<>"",IF(G34<>"",G34,($L$9/$L$12-SUM($Z$24:Z32))*AA33*AB33/SUMPRODUCT($AB33:$AB$57,$AA33:$AA$57)),""),"") -> 6 | AA33: 1 | AB33: 1
A34: 11 | B34: 46128 | C34: чт | D34: 140946 | E34: 10 | F34: =IF(AND(E34<>"",E34<>0),D34/E34,"") -> 14094.6 | G34: 6 | H34: =IF(AND(G34<>"",G34<>0),D34/G34,"") -> 23491 | I34: 28 | J34: =IF(AND(G34<>"",G34<>0),E34/G34,"") -> 1.6666667 | K34: 46086 | L34: 17807 | P34: 37998 | Q34: 35635 | S34: =IF(AND(I34<>"",I34<>0),G34/I34,"") -> 0.21428571 | T34: =D35/U34 -> 0.066503181 | U34: =$L$8*AA34*AB34/SUMPRODUCT($AB$24:$AB$55,$AA$24:$AA$55) -> 82582.516 | V34: =$L$9*AA34*AB34/SUMPRODUCT($AB$24:$AB$57,$AA$24:$AA$57) -> 11.882376 | W34: =IF($L$12="","",V34/$L$12) -> 6.5287782 | X34: =IF(AB34<>"",IF(D35<>"",D35,($L$8-SUM($X$24:X33))*AA34*AB34/SUMPRODUCT($AB34:$AB$57,$AA34:$AA$57)),"") -> 5492 | Y34: =IF(AB34<>"",IF(E34<>"",E34,($L$9-SUM($Y$24:Y33))*AA34*AB34/SUMPRODUCT($AB34:$AB$57,$AA34:$AA$57)),"") -> 10 | Z34: =IF(AB34<>"",IF($L$12<>"",IF(G35<>"",G35,($L$9/$L$12-SUM($Z$24:Z33))*AA34*AB34/SUMPRODUCT($AB34:$AB$57,$AA34:$AA$57)),""),"") -> 1 | AA34: 1 | AB34: 1
A35: 12 | B35: 46129 | C35: пт | D35: 5492 | E35: 1 | F35: =IF(AND(E35<>"",E35<>0),D35/E35,"") -> 5492 | G35: 1 | H35: =IF(AND(G35<>"",G35<>0),D35/G35,"") -> 5492 | I35: 32 | J35: =IF(AND(G35<>"",G35<>0),E35/G35,"") -> 1 | R35: 5490 | S35: =IF(AND(I35<>"",I35<>0),G35/I35,"") -> 0.03125 | T35: =D36/U35 -> #DIV/0! | U35: =$L$8*AA35*AB35/SUMPRODUCT($AB$24:$AB$55,$AA$24:$AA$55) -> 0 | V35: =$L$9*AA35*AB35/SUMPRODUCT($AB$24:$AB$57,$AA$24:$AA$57) -> 0 | W35: =IF($L$12="","",V35/$L$12) -> 0 | X35: =IF(AB35<>"",IF(D36<>"",D36,($L$8-SUM($X$24:X34))*AA35*AB35/SUMPRODUCT($AB35:$AB$57,$AA35:$AA$57)),"") | Y35: =IF(AB35<>"",IF(E35<>"",E35,($L$9-SUM($Y$24:Y34))*AA35*AB35/SUMPRODUCT($AB35:$AB$57,$AA35:$AA$57)),"") | Z35: =IF(AB35<>"",IF($L$12<>"",IF(G36<>"",G36,($L$9/$L$12-SUM($Z$24:Z34))*AA35*AB35/SUMPRODUCT($AB35:$AB$57,$AA35:$AA$57)),""),"")
A36: 13 | B36: 46130 | C36: сб | D36: 64469 | E36: 7 | F36: =IF(AND(E36<>"",E36<>0),D36/E36,"") -> 9209.8571 | G36: 4 | H36: =IF(AND(G36<>"",G36<>0),D36/G36,"") -> 16117.25 | I36: 51 | J36: =IF(AND(G36<>"",G36<>0),E36/G36,"") -> 1.75 | L36: 8702 | P36: 17390 | R36: 5890 | S36: =IF(AND(I36<>"",I36<>0),G36/I36,"") -> 0.078431373 | T36: =D37/U36 -> #DIV/0! | U36: =$L$8*AA36*AB36/SUMPRODUCT($AB$24:$AB$55,$AA$24:$AA$55) -> 0 | V36: =$L$9*AA36*AB36/SUMPRODUCT($AB$24:$AB$57,$AA$24:$AA$57) -> 0 | W36: =IF($L$12="","",V36/$L$12) -> 0 | X36: =IF(AB36<>"",IF(D37<>"",D37,($L$8-SUM($X$24:X35))*AA36*AB36/SUMPRODUCT($AB36:$AB$57,$AA36:$AA$57)),"") | Y36: =IF(AB36<>"",IF(E37<>"",E37,($L$9-SUM($Y$24:Y35))*AA36*AB36/SUMPRODUCT($AB36:$AB$57,$AA36:$AA$57)),"") | Z36: =IF(AB36<>"",IF($L$12<>"",IF(G37<>"",G37,($L$9/$L$12-SUM($Z$24:Z35))*AA36*AB36/SUMPRODUCT($AB36:$AB$57,$AA36:$AA$57)),""),"")
A37: .22 | B37: 46131 | C37: вс | D37: 89569 | E37: 16 | F37: =IF(AND(E37<>"",E37<>0),D37/E37,"") -> 5598.0625 | G37: 8 | H37: =IF(AND(G37<>"",G37<>0),D37/G37,"") -> 11196.125 | I37: 82 | J37: =IF(AND(G37<>"",G37<>0),E37/G37,"") -> 2 | L37: 28903 | P37: -17390 | Q37: 36786 | R37: 5990 | S37: =IF(AND(I37<>"",I37<>0),G37/I37,"") -> 0.097560976 | T37: =D38/U37 -> #DIV/0! | U37: =$L$8*AA37*AB37/SUMPRODUCT($AB$24:$AB$55,$AA$24:$AA$55) -> 0 | V37: =$L$9*AA37*AB37/SUMPRODUCT($AB$24:$AB$57,$AA$24:$AA$57) -> 0 | W37: =IF($L$12="","",V37/$L$12) -> 0 | X37: =IF(AB37<>"",IF(D38<>"",D38,($L$8-SUM($X$24:X36))*AA37*AB37/SUMPRODUCT($AB37:$AB$57,$AA37:$AA$57)),"") | Y37: =IF(AB37<>"",IF(E38<>"",E38,($L$9-SUM($Y$24:Y36))*AA37*AB37/SUMPRODUCT($AB37:$AB$57,$AA37:$AA$57)),"") | Z37: =IF(AB37<>"",IF($L$12<>"",IF(G38<>"",G38,($L$9/$L$12-SUM($Z$24:Z36))*AA37*AB37/SUMPRODUCT($AB37:$AB$57,$AA37:$AA$57)),""),"")
A38: 15 | B38: 46136 | C38: пт | D38: 0 | E38: 0 | F38: 0 | G38: 0 | H38: 0 | I38: 62 | J38: =IF(AND(G38<>"",G38<>0),E38/G38,"") | S38: =IF(AND(I38<>"",I38<>0),G38/I38,"") -> 0 | T38: =#REF!/U38 -> #REF! | U38: =$L$8*AA38*AB38/SUMPRODUCT($AB$24:$AB$55,$AA$24:$AA$55) -> 0 | V38: =$L$9*AA38*AB38/SUMPRODUCT($AB$24:$AB$57,$AA$24:$AA$57) -> 0 | W38: =IF($L$12="","",V38/$L$12) -> 0 | X38: =IF(AB38<>"",IF(#REF!<>"",#REF!,($L$8-SUM($X$24:X37))*AA38*AB38/SUMPRODUCT($AB38:$AB$57,$AA38:$AA$57)),"") | Y38: =IF(AB38<>"",IF(#REF!<>"",#REF!,($L$9-SUM($Y$24:Y37))*AA38*AB38/SUMPRODUCT($AB38:$AB$57,$AA38:$AA$57)),"") -> #REF! | Z38: =IF(AB38<>"",IF($L$12<>"",IF(#REF!<>"",#REF!,($L$9/$L$12-SUM($Z$24:Z37))*AA38*AB38/SUMPRODUCT($AB38:$AB$57,$AA38:$AA$57)),""),"") -> #REF!
A39: 16 | B39: 46137 | C39: сб | D39: =7693+6760 -> 14453 | E39: 2 | F39: =IF(AND(E39<>"",E39<>0),D39/E39,"") -> 7226.5 | G39: 2 | H39: =IF(AND(G39<>"",G39<>0),D39/G39,"") -> 7226.5 | I39: 20 | J39: =IF(AND(G39<>"",G39<>0),E39/G39,"") -> 1 | S39: =IF(AND(I39<>"",I39<>0),G39/I39,"") -> 0.1 | T39: =D39/U39 -> #DIV/0! | U39: =$L$8*AA39*AB39/SUMPRODUCT($AB$24:$AB$55,$AA$24:$AA$55) -> 0 | V39: =$L$9*AA39*AB39/SUMPRODUCT($AB$24:$AB$57,$AA$24:$AA$57) -> 0 | W39: =IF($L$12="","",V39/$L$12) -> 0 | X39: =IF(AB39<>"",IF(D39<>"",D39,($L$8-SUM($X$24:X38))*AA39*AB39/SUMPRODUCT($AB39:$AB$57,$AA39:$AA$57)),"") | Y39: =IF(AB39<>"",IF(#REF!<>"",#REF!,($L$9-SUM($Y$24:Y38))*AA39*AB39/SUMPRODUCT($AB39:$AB$57,$AA39:$AA$57)),"") -> #REF! | Z39: =IF(AB39<>"",IF($L$12<>"",IF(G39<>"",G39,($L$9/$L$12-SUM($Z$24:Z38))*AA39*AB39/SUMPRODUCT($AB39:$AB$57,$AA39:$AA$57)),""),"")
A40: 17 | B40: 46138 | C40: вс | D40: 18455 | E40: 3 | F40: =IF(AND(E40<>"",E40<>0),D40/E40,"") -> 6151.6667 | G40: 2 | H40: =IF(AND(G40<>"",G40<>0),D40/G40,"") -> 9227.5 | I40: 18 | J40: =IF(AND(G40<>"",G40<>0),E40/G40,"") -> 1.5 | S40: =IF(AND(I40<>"",I40<>0),G40/I40,"") -> 0.11111111 | T40: =D40/U40 -> #DIV/0! | U40: =$L$8*AA40*AB40/SUMPRODUCT($AB$24:$AB$55,$AA$24:$AA$55) -> 0 | V40: =$L$9*AA40*AB40/SUMPRODUCT($AB$24:$AB$57,$AA$24:$AA$57) -> 0 | W40: =IF($L$12="","",V40/$L$12) -> 0 | X40: =IF(AB40<>"",IF(D40<>"",D40,($L$8-SUM($X$24:X39))*AA40*AB40/SUMPRODUCT($AB40:$AB$57,$AA40:$AA$57)),"") | Y40: =IF(AB40<>"",IF(E39<>"",E39,($L$9-SUM($Y$24:Y39))*AA40*AB40/SUMPRODUCT($AB40:$AB$57,$AA40:$AA$57)),"") | Z40: =IF(AB40<>"",IF($L$12<>"",IF(G40<>"",G40,($L$9/$L$12-SUM($Z$24:Z39))*AA40*AB40/SUMPRODUCT($AB40:$AB$57,$AA40:$AA$57)),""),"")
A41: 18 | B41: 46139 | C41: пн | D41: =11903+4393 -> 16296 | E41: 2 | F41: =IF(AND(E41<>"",E41<>0),D41/E41,"") -> 8148 | G41: 2 | H41: =IF(AND(G41<>"",G41<>0),D41/G41,"") -> 8148 | I41: 46 | J41: =IF(AND(G41<>"",G41<>0),E41/G41,"") -> 1 | L41: 11903 | S41: =IF(AND(I41<>"",I41<>0),G41/I41,"") -> 0.043478261 | T41: =D41/U41 -> #DIV/0! | U41: =$L$8*AA41*AB41/SUMPRODUCT($AB$24:$AB$55,$AA$24:$AA$55) -> 0 | V41: =$L$9*AA41*AB41/SUMPRODUCT($AB$24:$AB$57,$AA$24:$AA$57) -> 0 | W41: =IF($L$12="","",V41/$L$12) -> 0 | X41: =IF(AB41<>"",IF(D41<>"",D41,($L$8-SUM($X$24:X40))*AA41*AB41/SUMPRODUCT($AB41:$AB$57,$AA41:$AA$57)),"") | Y41: =IF(AB41<>"",IF(E41<>"",E41,($L$9-SUM($Y$24:Y40))*AA41*AB41/SUMPRODUCT($AB41:$AB$57,$AA41:$AA$57)),"") | Z41: =IF(AB41<>"",IF($L$12<>"",IF(G41<>"",G41,($L$9/$L$12-SUM($Z$24:Z40))*AA41*AB41/SUMPRODUCT($AB41:$AB$57,$AA41:$AA$57)),""),"")
A42: 19 | B42: 46140 | C42: вт | D42: 16803 | E42: 2 | F42: 7011 | G42: 1 | H42: 9348 | I42: 18 | J42: =IF(AND(G42<>"",G42<>0),E42/G42,"") -> 2 | L42: 16803 | S42: =IF(AND(I42<>"",I42<>0),G42/I42,"") -> 0.055555556 | T42: =D42/U42 -> #DIV/0! | U42: =$L$8*AA42*AB42/SUMPRODUCT($AB$24:$AB$55,$AA$24:$AA$55) -> 0 | V42: =$L$9*AA42*AB42/SUMPRODUCT($AB$24:$AB$57,$AA$24:$AA$57) -> 0 | W42: =IF($L$12="","",V42/$L$12) -> 0 | X42: =IF(AB42<>"",IF(D42<>"",D42,($L$8-SUM($X$24:X41))*AA42*AB42/SUMPRODUCT($AB42:$AB$57,$AA42:$AA$57)),"") | Y42: =IF(AB42<>"",IF(E42<>"",E42,($L$9-SUM($Y$24:Y41))*AA42*AB42/SUMPRODUCT($AB42:$AB$57,$AA42:$AA$57)),"") | Z42: =IF(AB42<>"",IF($L$12<>"",IF(G42<>"",G42,($L$9/$L$12-SUM($Z$24:Z41))*AA42*AB42/SUMPRODUCT($AB42:$AB$57,$AA42:$AA$57)),""),"")
A43: 20 | B43: 46141 | C43: ср | D43: 3503 | E43: 1 | F43: 3503 | G43: 1 | H43: 3503 | I43: 27 | J43: =IF(AND(G43<>"",G43<>0),E43/G43,"") -> 1 | R43: 3500 | S43: =IF(AND(I43<>"",I43<>0),G43/I43,"") -> 0.037037037 | T43: =D43/U43 -> #DIV/0! | U43: =$L$8*AA43*AB43/SUMPRODUCT($AB$24:$AB$55,$AA$24:$AA$55) -> 0 | V43: =$L$9*AA43*AB43/SUMPRODUCT($AB$24:$AB$57,$AA$24:$AA$57) -> 0 | W43: =IF($L$12="","",V43/$L$12) -> 0 | X43: =IF(AB43<>"",IF(D43<>"",D43,($L$8-SUM($X$24:X42))*AA43*AB43/SUMPRODUCT($AB43:$AB$57,$AA43:$AA$57)),"") | Y43: =IF(AB43<>"",IF(E43<>"",E43,($L$9-SUM($Y$24:Y42))*AA43*AB43/SUMPRODUCT($AB43:$AB$57,$AA43:$AA$57)),"") | Z43: =IF(AB43<>"",IF($L$12<>"",IF(G43<>"",G43,($L$9/$L$12-SUM($Z$24:Z42))*AA43*AB43/SUMPRODUCT($AB43:$AB$57,$AA43:$AA$57)),""),"")
A44: 21 | J44: =IF(AND(G44<>"",G44<>0),E44/G44,"") | S44: =IF(AND(I44<>"",I44<>0),G44/I44,"") | T44: =D44/U44 -> #DIV/0! | U44: =$L$8*AA44*AB44/SUMPRODUCT($AB$24:$AB$55,$AA$24:$AA$55) -> 0 | V44: =$L$9*AA44*AB44/SUMPRODUCT($AB$24:$AB$57,$AA$24:$AA$57) -> 0 | W44: =IF($L$12="","",V44/$L$12) -> 0 | X44: =IF(AB44<>"",IF(D44<>"",D44,($L$8-SUM($X$24:X43))*AA44*AB44/SUMPRODUCT($AB44:$AB$57,$AA44:$AA$57)),"") | Y44: =IF(AB44<>"",IF(E44<>"",E44,($L$9-SUM($Y$24:Y43))*AA44*AB44/SUMPRODUCT($AB44:$AB$57,$AA44:$AA$57)),"") | Z44: =IF(AB44<>"",IF($L$12<>"",IF(G44<>"",G44,($L$9/$L$12-SUM($Z$24:Z43))*AA44*AB44/SUMPRODUCT($AB44:$AB$57,$AA44:$AA$57)),""),"")
A45: 22 | F45: =IF(AND(E45<>"",E45<>0),D45/E45,"") | H45: =IF(AND(G45<>"",G45<>0),D45/G45,"") | J45: =IF(AND(G45<>"",G45<>0),E45/G45,"") | S45: =IF(AND(I45<>"",I45<>0),G45/I45,"") | T45: =D45/U45 -> #DIV/0! | U45: =$L$8*AA45*AB45/SUMPRODUCT($AB$24:$AB$55,$AA$24:$AA$55) -> 0 | V45: =$L$9*AA45*AB45/SUMPRODUCT($AB$24:$AB$57,$AA$24:$AA$57) -> 0 | W45: =IF($L$12="","",V45/$L$12) -> 0 | X45: =IF(AB45<>"",IF(D45<>"",D45,($L$8-SUM($X$24:X44))*AA45*AB45/SUMPRODUCT($AB45:$AB$57,$AA45:$AA$57)),"") | Y45: =IF(AB45<>"",IF(E45<>"",E45,($L$9-SUM($Y$24:Y44))*AA45*AB45/SUMPRODUCT($AB45:$AB$57,$AA45:$AA$57)),"") | Z45: =IF(AB45<>"",IF($L$12<>"",IF(G45<>"",G45,($L$9/$L$12-SUM($Z$24:Z44))*AA45*AB45/SUMPRODUCT($AB45:$AB$57,$AA45:$AA$57)),""),"")
A46: 23 | F46: =IF(AND(E46<>"",E46<>0),D46/E46,"") | H46: =IF(AND(G46<>"",G46<>0),D46/G46,"") | J46: =IF(AND(G46<>"",G46<>0),E46/G46,"") | S46: =IF(AND(I46<>"",I46<>0),G46/I46,"") | T46: =D46/U46 -> #DIV/0! | U46: =$L$8*AA46*AB46/SUMPRODUCT($AB$24:$AB$55,$AA$24:$AA$55) -> 0 | V46: =$L$9*AA46*AB46/SUMPRODUCT($AB$24:$AB$57,$AA$24:$AA$57) -> 0 | W46: =IF($L$12="","",V46/$L$12) -> 0 | X46: =IF(AB46<>"",IF(D46<>"",D46,($L$8-SUM($X$24:X45))*AA46*AB46/SUMPRODUCT($AB46:$AB$57,$AA46:$AA$57)),"") | Y46: =IF(AB46<>"",IF(E46<>"",E46,($L$9-SUM($Y$24:Y45))*AA46*AB46/SUMPRODUCT($AB46:$AB$57,$AA46:$AA$57)),"") | Z46: =IF(AB46<>"",IF($L$12<>"",IF(G46<>"",G46,($L$9/$L$12-SUM($Z$24:Z45))*AA46*AB46/SUMPRODUCT($AB46:$AB$57,$AA46:$AA$57)),""),"")
A47: 24 | F47: =IF(AND(E47<>"",E47<>0),D47/E47,"") | H47: =IF(AND(G47<>"",G47<>0),D47/G47,"") | J47: =IF(AND(G47<>"",G47<>0),E47/G47,"") | S47: =IF(AND(I47<>"",I47<>0),G47/I47,"") | T47: =D47/U47 -> #DIV/0! | U47: =$L$8*AA47*AB47/SUMPRODUCT($AB$24:$AB$55,$AA$24:$AA$55) -> 0 | V47: =$L$9*AA47*AB47/SUMPRODUCT($AB$24:$AB$57,$AA$24:$AA$57) -> 0 | W47: =IF($L$12="","",V47/$L$12) -> 0 | X47: =IF(AB47<>"",IF(D47<>"",D47,($L$8-SUM($X$24:X46))*AA47*AB47/SUMPRODUCT($AB47:$AB$57,$AA47:$AA$57)),"") | Y47: =IF(AB47<>"",IF(E47<>"",E47,($L$9-SUM($Y$24:Y46))*AA47*AB47/SUMPRODUCT($AB47:$AB$57,$AA47:$AA$57)),"") | Z47: =IF(AB47<>"",IF($L$12<>"",IF(G47<>"",G47,($L$9/$L$12-SUM($Z$24:Z46))*AA47*AB47/SUMPRODUCT($AB47:$AB$57,$AA47:$AA$57)),""),"")
A48: 25 | F48: =IF(AND(E48<>"",E48<>0),D48/E48,"") | H48: =IF(AND(G48<>"",G48<>0),D48/G48,"") | J48: =IF(AND(G48<>"",G48<>0),E48/G48,"") | S48: =IF(AND(I48<>"",I48<>0),G48/I48,"") | T48: =D48/U48 -> #DIV/0! | U48: =$L$8*AA48*AB48/SUMPRODUCT($AB$24:$AB$55,$AA$24:$AA$55) -> 0 | V48: =$L$9*AA48*AB48/SUMPRODUCT($AB$24:$AB$57,$AA$24:$AA$57) -> 0 | W48: =IF($L$12="","",V48/$L$12) -> 0 | X48: =IF(AB48<>"",IF(D48<>"",D48,($L$8-SUM($X$24:X47))*AA48*AB48/SUMPRODUCT($AB48:$AB$57,$AA48:$AA$57)),"") | Y48: =IF(AB48<>"",IF(E48<>"",E48,($L$9-SUM($Y$24:Y47))*AA48*AB48/SUMPRODUCT($AB48:$AB$57,$AA48:$AA$57)),"") | Z48: =IF(AB48<>"",IF($L$12<>"",IF(G48<>"",G48,($L$9/$L$12-SUM($Z$24:Z47))*AA48*AB48/SUMPRODUCT($AB48:$AB$57,$AA48:$AA$57)),""),"")
A49: 26 | F49: =IF(AND(E49<>"",E49<>0),D49/E49,"") | H49: =IF(AND(G49<>"",G49<>0),D49/G49,"") | J49: =IF(AND(G49<>"",G49<>0),E49/G49,"") | S49: =IF(AND(I49<>"",I49<>0),G49/I49,"") | T49: =D49/U49 -> #DIV/0! | U49: =$L$8*AA49*AB49/SUMPRODUCT($AB$24:$AB$55,$AA$24:$AA$55) -> 0 | V49: =$L$9*AA49*AB49/SUMPRODUCT($AB$24:$AB$57,$AA$24:$AA$57) -> 0 | W49: =IF($L$12="","",V49/$L$12) -> 0 | X49: =IF(AB49<>"",IF(D49<>"",D49,($L$8-SUM($X$24:X48))*AA49*AB49/SUMPRODUCT($AB49:$AB$57,$AA49:$AA$57)),"") | Y49: =IF(AB49<>"",IF(E49<>"",E49,($L$9-SUM($Y$24:Y48))*AA49*AB49/SUMPRODUCT($AB49:$AB$57,$AA49:$AA$57)),"") | Z49: =IF(AB49<>"",IF($L$12<>"",IF(G49<>"",G49,($L$9/$L$12-SUM($Z$24:Z48))*AA49*AB49/SUMPRODUCT($AB49:$AB$57,$AA49:$AA$57)),""),"")
A50: 27 | F50: =IF(AND(E50<>"",E50<>0),D50/E50,"") | H50: =IF(AND(G50<>"",G50<>0),D50/G50,"") | J50: =IF(AND(G50<>"",G50<>0),E50/G50,"") | S50: =IF(AND(I50<>"",I50<>0),G50/I50,"") | T50: =D50/U50 -> #DIV/0! | U50: =$L$8*AA50*AB50/SUMPRODUCT($AB$24:$AB$55,$AA$24:$AA$55) -> 0 | V50: =$L$9*AA50*AB50/SUMPRODUCT($AB$24:$AB$57,$AA$24:$AA$57) -> 0 | W50: =IF($L$12="","",V50/$L$12) -> 0 | X50: =IF(AB50<>"",IF(D50<>"",D50,($L$8-SUM($X$24:X49))*AA50*AB50/SUMPRODUCT($AB50:$AB$57,$AA50:$AA$57)),"") | Y50: =IF(AB50<>"",IF(E50<>"",E50,($L$9-SUM($Y$24:Y49))*AA50*AB50/SUMPRODUCT($AB50:$AB$57,$AA50:$AA$57)),"") | Z50: =IF(AB50<>"",IF($L$12<>"",IF(G50<>"",G50,($L$9/$L$12-SUM($Z$24:Z49))*AA50*AB50/SUMPRODUCT($AB50:$AB$57,$AA50:$AA$57)),""),"")
A51: 28 | F51: =IF(AND(E51<>"",E51<>0),D51/E51,"") | H51: =IF(AND(G51<>"",G51<>0),D51/G51,"") | J51: =IF(AND(G51<>"",G51<>0),E51/G51,"") | S51: =IF(AND(I51<>"",I51<>0),G51/I51,"") | T51: =D51/U51 -> #DIV/0! | U51: =$L$8*AA51*AB51/SUMPRODUCT($AB$24:$AB$55,$AA$24:$AA$55) -> 0 | V51: =$L$9*AA51*AB51/SUMPRODUCT($AB$24:$AB$57,$AA$24:$AA$57) -> 0 | W51: =IF($L$12="","",V51/$L$12) -> 0 | X51: =IF(AB51<>"",IF(D51<>"",D51,($L$8-SUM($X$24:X50))*AA51*AB51/SUMPRODUCT($AB51:$AB$57,$AA51:$AA$57)),"") | Y51: =IF(AB51<>"",IF(E51<>"",E51,($L$9-SUM($Y$24:Y50))*AA51*AB51/SUMPRODUCT($AB51:$AB$57,$AA51:$AA$57)),"") | Z51: =IF(AB51<>"",IF($L$12<>"",IF(G51<>"",G51,($L$9/$L$12-SUM($Z$24:Z50))*AA51*AB51/SUMPRODUCT($AB51:$AB$57,$AA51:$AA$57)),""),"")
A52: 29 | F52: =IF(AND(E52<>"",E52<>0),D52/E52,"") | H52: =IF(AND(G52<>"",G52<>0),D52/G52,"") | J52: =IF(AND(G52<>"",G52<>0),E52/G52,"") | S52: =IF(AND(I52<>"",I52<>0),G52/I52,"") | T52: =D52/U52 -> #DIV/0! | U52: =$L$8*AA52*AB52/SUMPRODUCT($AB$24:$AB$55,$AA$24:$AA$55) -> 0 | V52: =$L$9*AA52*AB52/SUMPRODUCT($AB$24:$AB$57,$AA$24:$AA$57) -> 0 | W52: =IF($L$12="","",V52/$L$12) -> 0 | X52: =IF(AB52<>"",IF(D52<>"",D52,($L$8-SUM($X$24:X51))*AA52*AB52/SUMPRODUCT($AB52:$AB$57,$AA52:$AA$57)),"") | Y52: =IF(AB52<>"",IF(E52<>"",E52,($L$9-SUM($Y$24:Y51))*AA52*AB52/SUMPRODUCT($AB52:$AB$57,$AA52:$AA$57)),"") | Z52: =IF(AB52<>"",IF($L$12<>"",IF(G52<>"",G52,($L$9/$L$12-SUM($Z$24:Z51))*AA52*AB52/SUMPRODUCT($AB52:$AB$57,$AA52:$AA$57)),""),"")
F53: =IF(AND(E53<>"",E53<>0),D53/E53,"") | H53: =IF(AND(G53<>"",G53<>0),D53/G53,"") | J53: =IF(AND(G53<>"",G53<>0),E53/G53,"") | S53: =IF(AND(I53<>"",I53<>0),G53/I53,"") | T53: =D53/U53 -> #DIV/0! | U53: =$L$8*AA53*AB53/SUMPRODUCT($AB$24:$AB$55,$AA$24:$AA$55) -> 0 | V53: =$L$9*AA53*AB53/SUMPRODUCT($AB$24:$AB$57,$AA$24:$AA$57) -> 0 | W53: =IF($L$12="","",V53/$L$12) -> 0 | X53: =IF(AB53<>"",IF(D53<>"",D53,($L$8-SUM($X$24:X49))*AA53*AB53/SUMPRODUCT($AB53:$AB$57,$AA53:$AA$57)),"") | Y53: =IF(AB53<>"",IF(E53<>"",E53,($L$9-SUM($Y$24:Y49))*AA53*AB53/SUMPRODUCT($AB53:$AB$57,$AA53:$AA$57)),"") | Z53: =IF(AB53<>"",IF($L$12<>"",IF(G53<>"",G53,($L$9/$L$12-SUM($Z$24:Z49))*AA53*AB53/SUMPRODUCT($AB53:$AB$57,$AA53:$AA$57)),""),"")
F54: =IF(AND(E54<>"",E54<>0),D54/E54,"") | H54: =IF(AND(G54<>"",G54<>0),D54/G54,"") | J54: =IF(AND(G54<>"",G54<>0),E54/G54,"") | S54: =IF(AND(I54<>"",I54<>0),G54/I54,"") | T54: =D54/U54 -> #DIV/0! | U54: =$L$8*AA54*AB54/SUMPRODUCT($AB$24:$AB$55,$AA$24:$AA$55) -> 0 | V54: =$L$9*AA54*AB54/SUMPRODUCT($AB$24:$AB$57,$AA$24:$AA$57) -> 0 | W54: =IF($L$12="","",V54/$L$12) -> 0 | X54: =IF(AB54<>"",IF(D54<>"",D54,($L$8-SUM($X$24:X53))*AA54*AB54/SUMPRODUCT($AB54:$AB$57,$AA54:$AA$57)),"") | Y54: =IF(AB54<>"",IF(E54<>"",E54,($L$9-SUM($Y$24:Y53))*AA54*AB54/SUMPRODUCT($AB54:$AB$57,$AA54:$AA$57)),"") | Z54: =IF(AB54<>"",IF($L$12<>"",IF(G54<>"",G54,($L$9/$L$12-SUM($Z$24:Z53))*AA54*AB54/SUMPRODUCT($AB54:$AB$57,$AA54:$AA$57)),""),"")
F55: =IF(AND(E55<>"",E55<>0),D55/E55,"") | H55: =IF(AND(G55<>"",G55<>0),D55/G55,"") | J55: =IF(AND(G55<>"",G55<>0),E55/G55,"") | S55: =IF(AND(I55<>"",I55<>0),G55/I55,"") | T55: =D55/U55 -> #DIV/0! | U55: =$L$8*AA55*AB55/SUMPRODUCT($AB$24:$AB$55,$AA$24:$AA$55) -> 0 | V55: =$L$9*AA55*AB55/SUMPRODUCT($AB$24:$AB$57,$AA$24:$AA$57) -> 0 | W55: =IF($L$12="","",V55/$L$12) -> 0 | X55: =IF(AB55<>"",IF(D55<>"",D55,($L$8-SUM($X$24:X54))*AA55*AB55/SUMPRODUCT($AB55:$AB$57,$AA55:$AA$57)),"") | Y55: =IF(AB55<>"",IF(E55<>"",E55,($L$9-SUM($Y$24:Y54))*AA55*AB55/SUMPRODUCT($AB55:$AB$57,$AA55:$AA$57)),"") | Z55: =IF(AB55<>"",IF($L$12<>"",IF(G55<>"",G55,($L$9/$L$12-SUM($Z$24:Z54))*AA55*AB55/SUMPRODUCT($AB55:$AB$57,$AA55:$AA$57)),""),"")
D56: =SUM(D25:D55) -> 792102 | E56: =SUM(E25:E55) -> 90 | F56: =IF(AND(E56<>"",E56<>0),D56/E56,"") -> 8801.1333 | G56: =SUM(G25:G55) -> 52 | H56: =IF(AND(G56<>"",G56<>0),D56/G56,"") -> 15232.731 | I56: =SUM(I25:I55) -> 597 | J56: =IF(AND(G56<>"",G56<>0),E56/G56,"") -> 1.7307692 | K56: =SUM(K25:K55) -> 136884 | L56: =SUM(L25:L55) -> 129120 | M56: =SUM(M25:M55) -> 0 | N56: =SUM(N25:N55) -> 68112 | O56: =SUM(O25:O55) -> 0 | P56: =SUM(P25:P55) -> 37998 | Q56: =SUM(Q25:Q55) -> 128637 | R56: =SUM(R25:R55) -> 30605 | S56: =IF(AND(I56<>"",I56<>0),G56/I56,"") -> 0.087102178 | T56: =D56/U56 -> 0.87196753 | U56: =SUM(U24:U55) -> 908407.67 | V56: =SUM(V24:V54) -> 130.70614 | W56: =SUM(W24:W54) -> 71.816561 | X56: =SUM(X24:X55) -> 568554 | Y56: =SUM(Y24:Y54) -> #REF! | Z56: =SUM(Z24:Z54) -> #REF!
D57: =SUMIF(D25:D53,"",U24:U53)+D56 -> 792102

Sheet Уразгильдеева
B1: =TODAY()-1 -> 46171
B2: (отчетная дата) | J2: ЕЖЕДНЕВНЫЙ ОТЧЕТ О ПРОДАЖАХ
B3: Осталось до выполнения плана!!! | J3: =График!B27 -> Уразгильдеева Екатерина
C4: =L8-D50 -> 1091133.4 | E4: =IF(L8<>0,C4/L8,0) -> 1
I6: Целевые показатели
I7: Показатель | L7: План | M7: Факт | N7: % выполнения | O7: Прогноз выполнения | P7: % выполнения по прогнозу | Q7: Отклонение | R7: Факт аналогичного месяца прошлого года | S7: Отклонение LFL
I8: Выручка | L8: ='Ялта, Ленина, 18'!I8/График!AJ29*График!AJ27 -> 1091133.4 | M8: =D57 -> 780750 | N8: =IF(AND(L8<>"",L8<>0,M8<>""),M8/L8,"") -> 0.7155404 | O8: =IF(SUMIF($D$25:$D$56,">=0",$U$25:$U$56)<>0,L8*D57/SUMIF($D$25:$D$56,">=0",$U$25:$U$56),0) -> 780750 | P8: =IF(AND(L8<>"",L8<>0,O8<>"",O8<>0),O8/L8,"") -> 0.7155404 | Q8: =IF(AND(M8<>0,M8<>"",L8<>0,L8<>""),O8-L8,"") -> -310383.36 | R8: 240775 | S8: =IF(AND(R8<>"",R8<>0,O8<>"",O8<>0),-R8+O8,"") -> 539975 | T8: =IF(AND(S8<>"",S8<>0,R8<>0,R8<>""),S8/R8,"") -> 2.2426539
I9: Кол-во изделий | L9: =L8/L11 -> 156.99761 | M9: =E57 -> 107 | N9: =IF(AND(L9<>"",L9<>0,M9<>""),M9/L9,"") -> 0.68153906 | O9: =IF(SUMIF($E$25:$E$54,">=0",$V$25:$V$54)<>0,L9*E57/SUMIF($E$25:$E$54,">=0",$V$25:$V$54),0) -> 107 | P9: =IF(AND(L9<>"",L9<>0,O9<>"",O9<>0),O9/L9,"") -> 0.68153906 | Q9: =IF(AND(M9<>0,M9<>"",L9<>0,L9<>""),O9-L9,"") -> -49.997605 | R9: 51 | S9: =IF(AND(R9<>"",R9<>0,O9<>"",O9<>0),-R9+O9,"") -> 56 | T9: =IF(AND(S9<>"",S9<>0,R9<>0,R9<>""),S9/R9,"") -> 1.0980392
I10: Средний чек | L10: =L11*L12 -> 12649 | M10: =H57 -> 12392.857 | N10: =IF(AND(L10<>"",L10<>0,M10<>""),M10/L10,"") -> 0.97974995 | O10: =M10 -> 12392.857 | P10: =IF(AND(L10<>"",L10<>0,O10<>"",O10<>0),O10/L10,"") -> 0.97974995 | Q10: =IF(AND(M10<>0,M10<>"",L10<>0,L10<>""),O10-L10,"") -> -256.14286 | R10: 8917.5926 | S10: =IF(AND(R10<>"",R10<>0,O10<>"",O10<>0),-R10+O10,"") -> 3475.2646 | T10: =IF(AND(S10<>"",S10<>0,R10<>0,R10<>""),S10/R10,"") -> 0.38970883
I11: Средняя стоимость изделия | L11: ='Ялта, Ленина, 18'!I11 -> 6950 | M11: =F57 -> 7296.729 | N11: =IF(AND(L11<>"",L11<>0,M11<>""),M11/L11,"") -> 1.0498891 | O11: =IF(O9>0,O8/O9,"") -> 7296.729 | P11: =IF(AND(L11<>"",L11<>0,O11<>"",O11<>0),O11/L11,"") -> 1.0498891 | Q11: =IF(AND(M11<>0,M11<>"",L11<>0,L11<>""),O11-L11,"") -> 346.72897 | R11: 4721.0784 | S11: =IF(AND(R11<>"",R11<>0,O11<>"",O11<>0),-R11+O11,"") -> 2575.6505 | T11: =IF(AND(S11<>"",S11<>0,R11<>0,R11<>""),S11/R11,"") -> 0.54556402
I12: Длина чека | L12: ='Ялта, Ленина, 18'!I12 -> 1.82 | M12: =J57 -> 1.6984127 | N12: =IF(AND(L12<>"",L12<>0,M12<>""),M12/L12,"") -> 0.93319379 | O12: =M12 -> 1.6984127 | P12: =IF(AND(L12<>"",L12<>0,O12<>"",O12<>0),O12/L12,"") -> 0.93319379 | Q12: =IF(AND(M12<>0,M12<>"",L12<>0,L12<>""),O12-L12,"") -> -0.1215873 | R12: 1.8888889 | S12: =IF(AND(R12<>"",R12<>0,O12<>"",O12<>0),-R12+O12,"") -> -0.19047619 | T12: =IF(AND(S12<>"",S12<>0,R12<>0,R12<>""),S12/R12,"") -> -0.10084034
I13: Кол-во чеков | L13: =IF(L12<>0,L9/L12,"") -> 86.26242 | M13: =G57 -> 63 | N13: =IF(AND(L13<>"",L13<>0,M13<>""),M13/L13,"") -> 0.73032961 | O13: =IF(SUMIF($G$25:$G$54,">=0",$W$25:$W$54)<>0,L13*G57/SUMIF($G$25:$G$54,">=0",$W$25:$W$54),"") -> 63 | P13: =IF(AND(L13<>"",L13<>0,O13<>"",O13<>0),O13/L13,"") -> 0.73032961 | Q13: =IF(AND(M13<>0,M13<>"",L13<>0,L13<>""),O13-L13,"") -> -23.26242 | R13: 27 | S13: =IF(AND(R13<>"",R13<>0,O13<>"",O13<>0),-R13+O13,"") -> 36 | T13: =IF(AND(S13<>"",S13<>0,R13<>0,R13<>""),S13/R13,"") -> 1.3333333
I14: Кол-во смен план/отработано | L14: =График!AI27 -> 20 | M14: 19 | N14: =IF(AND(L14<>"",L14<>0,M14<>""),M14/L14,"") -> 0.95 | O14: =L14 -> 20 | P14: =IF(AND(L14<>"",L14<>0,O14<>"",O14<>0),O14/L14,"") -> 1 | Q14: =IF(AND(M14<>0,M14<>"",L14<>0,L14<>""),O14-L14,"") -> 0 | R14: 8 | S14: =IF(AND(R14<>"",R14<>0,O14<>"",O14<>0),-R14+O14,"") -> 12 | T14: =IF(AND(S14<>"",S14<>0,R14<>0,R14<>""),S14/R14,"") -> 1.5
I15: Средние продажи в смену | L15: ='Ялта, Ленина, 18'!I15 -> 81965.52 | M15: =M8/M14 -> 41092.105 | N15: =IF(AND(L15<>"",L15<>0,M15<>""),M15/L15,"") -> 0.50133404 | O15: =M15 -> 41092.105 | P15: =IF(AND(L15<>"",L15<>0,O15<>"",O15<>0),O15/L15,"") -> 0.50133404 | Q15: =IF(AND(M15<>0,M15<>"",L15<>0,L15<>""),O15-L15,"") -> -40873.415 | R15: 30096.875 | S15: =IF(AND(R15<>"",R15<>0,O15<>"",O15<>0),-R15+O15,"") -> 10995.23 | T15: =IF(AND(S15<>"",S15<>0,R15<>0,R15<>""),S15/R15,"") -> 0.36532797
I16: Отставание/Перевыполнение | M16: =M8-L15*M14 -> -776594.88 | N16: =IF(AND(L16<>"",L16<>0,M16<>""),M16/L16,"") | O16: =M16 -> -776594.88 | P16: =IF(AND(L16<>"",L16<>0,O16<>"",O16<>0),O16/L16,"") | Q16: =IF(AND(M16<>0,M16<>"",L16<>0,L16<>""),O16-L16,"") | R16: -449387.18 | S16: =IF(AND(R16<>"",R16<>0,O16<>"",O16<>0),-R16+O16,"") -> -327207.7 | T16: =IF(AND(S16<>"",S16<>0,R16<>0,R16<>""),S16/R16,"") -> 0.72811981
I17: Трафик | L17: ='Ялта, Ленина, 18'!I17/График!AJ29*График!AJ27 -> 798.72611 | M17: =I57 -> 799 | N17: =IF(AND(L17<>"",L17<>0,M17<>""),M17/L17,"") -> 1.0003429 | O17: =M17/M14*L14 -> 841.05263 | P17: =IF(AND(L17<>"",L17<>0,O17<>"",O17<>0),O17/L17,"") -> 1.0529925 | Q17: =IF(AND(M17<>0,M17<>"",L17<>0,L17<>""),O17-L17,"") -> 42.326517 | R17: 160 | S17: =IF(AND(R17<>"",R17<>0,O17<>"",O17<>0),-R17+O17,"") -> 681.05263 | T17: =IF(AND(S17<>"",S17<>0,R17<>0,R17<>""),S17/R17,"") -> 4.2565789
I18: Выручка на вошедшего | L18: =L8/L17 -> 1366.092 | M18: =M8/M17 -> 977.15895 | N18: =IF(AND(L18<>"", L18<>0, M18<>""), M18/L18, "") -> 0.71529513 | O18: =M18 -> 977.15895 | P18: =IF(AND(L18<>"", L18<>0, O18<>"", O18<>0), O18/L18, "") -> 0.71529513 | Q18: =IF(AND(M18<>0, M18<>"", L18<>0, L18<>""), O18-L18, "") -> -388.93305 | S18: =IF(AND(R18<>"",R18<>0,O18<>"",O18<>0),-R18+O18,"") | T18: =IF(AND(S18<>"",S18<>0,R18<>0,R18<>""),S18/R18,"")
N19: =IF(AND(L19<>"",L19<>0,M19<>""),M19/L19,"") | O19: =M19 -> 0 | P19: =IF(AND(L19<>"",L19<>0,O19<>"",O19<>0),O19/L19,"") | Q19: =IF(AND(M19<>0,M19<>"",L19<>0,L19<>""),O19-L19,"") | R19: 0 | S19: =IF(AND(R19<>"",R19<>0,O19<>"",O19<>0),-R19+O19,"") | T19: =IF(AND(S19<>"",S19<>0,R19<>0,R19<>""),S19/R19,"")
I20: Конверсия план/факт | L20: ='Ялта, Ленина, 18'!I20 -> 0.108 | M20: =S57 -> 0.078848561 | N20: =M20/L20 -> 0.73007927 | O20: =IF(AND(N8<>0,L14<>0,I57<>0),(I57*S57+(I57/N8-I57)*L20)/(I57/N8),0) -> 0.087140967 | P20: =IF(AND(L20<>"",L20<>0,O20<>"",O20<>0),O20/L20,"") -> 0.80686081 | Q20: =IF(AND(M20<>0,M20<>"",L20<>0,L20<>""),O20-L20,"") -> -0.020859033 | R20: 0.16875 | S20: =IF(AND(R20<>"",R20<>0,O20<>"",O20<>0),-R20+O20,"") -> -0.081609033 | T20: =IF(AND(S20<>"",S20<>0,R20<>0,R20<>""),S20/R20,"") -> -0.48360908
B22: Факт продаж за месяц | T22: % выполнения дневного плана | U22: Раcпределение плана по дням
B23: Дата | C23: День недели | D23: Выручка (руб) | E23: Кол-во единиц (шт.) | F23: Средняя стоимость изделия (руб.) | G23: Количество чеков (шт.) | H23: Средняя сумма чека (руб.) | I23: Трафик | J23: Длина чека (шт.) | K23: UNOde50 | L23: IS | M23: Agafi | N23: Kalliope | O23: Raganella | P23: CC/MP | Q23: Antura | R23: SALE | S23: Конверсия (%) | U23: выручка, план | V23: кол-во ед, план | W23: Кол-во чеков, план | X23: выручка, скорректир.план | Y23: кол-во ед, скорр. план | Z23: кол-во чеков, скорр. план | AA23: Коэфф. Дня Недели | AB23: Специфика месяца
B24: 1 | C24: 2 | D24: 3 | E24: в | F24: 5 | G24: 6 | H24: 7 | I24: 8 | J24: 9 | K24: 10 | L24: 11 | M24: 12 | N24: 13 | P24: 14 | Q24: 15 | R24: 16 | S24: 17 | U24: 1 | V24: 2 | W24: 3 | X24: 4 | Y24: 5 | Z24: 6 | AA24: 10 | AB24: 11
A25: 1 | B25: 46113 | C25: ср | D25: =4392+17775 -> 22167 | E25: 4 | F25: 5542 | G25: 2 | H25: =IF(AND(G25<>"",G25<>0),D25/G25,"") -> 11083.5 | I25: 37 | J25: =IF(AND(G25<>"",G25<>0),E25/G25,"") -> 2 | S25: =IF(AND(I25<>"",I25<>0),G25/I25,"") -> 0.054054054 | T25: =D25/U25 -> 0.32504918 | U25: =$L$8*AA25*AB25/SUMPRODUCT($AB$25:$AB$56,$AA$25:$AA$56) -> 68195.835 | V25: =$L$9*AA25*AB25/SUMPRODUCT($AB$25:$AB$56,$AA$25:$AA$56) -> 9.8123503 | W25: =IF($L$12="","",V25/$L$12) -> 5.3914013 | X25: =IF(D25<>"",D25,U25) -> 22167 | Y25: =IF(E25<>"",E25,V25) -> 4 | Z25: =IF(G25<>"",G25,W25) -> 2 | AA25: 1 | AB25: 1
A26: 2 | B26: 46114 | C26: чт | D26: 10060 | E26: 2 | F26: 5030 | G26: 1 | H26: 10060 | I26: 24 | J26: =IF(AND(G26<>"",G26<>0),E26/G26,"") -> 2 | S26: =IF(AND(I26<>"",I26<>0),G26/I26,"") -> 0.041666667 | T26: =D26/U26 -> 0.14751634 | U26: =$L$8*AA26*AB26/SUMPRODUCT($AB$25:$AB$56,$AA$25:$AA$56) -> 68195.835 | V26: =$L$9*AA26*AB26/SUMPRODUCT($AB$25:$AB$58,$AA$25:$AA$58) -> 9.8123503 | W26: =IF($L$12="","",V26/$L$12) -> 5.3914013 | X26: =IF(AB26<>"",IF(D26<>"",D26,($L$8-SUM($X$25:X25))*AA26*AB26/SUMPRODUCT($AB26:$AB$56,$AA26:$AA$56)),"") -> 10060 | Y26: =IF(AB26<>"",IF(E26<>"",E26,($L$9-SUM($Y$25:Y25))*AA26*AB26/SUMPRODUCT($AB26:$AB$55,$AA26:$AA$55)),"") -> 2 | Z26: =IF(AB26<>"",IF($L$12<>"",IF(G26<>"",G26,($L$9/$L$12-SUM($Z$25:Z25))*AA26*AB26/SUMPRODUCT($AB26:$AB$55,$AA26:$AA$55)),""),"") -> 1 | AA26: 1 | AB26: 1
A27: 3 | B27: 46117 | C27: вс | D27: 27537 | E27: 6 | F27: =IF(AND(E27<>"",E27<>0),D27/E27,"") -> 4589.5 | G27: 3 | H27: =IF(AND(G27<>"",G27<>0),D27/G27,"") -> 9179 | I27: 39 | J27: =IF(AND(G27<>"",G27<>0),E27/G27,"") -> 2 | K27: 12293 | R27: 7379.58 | S27: =IF(AND(I27<>"",I27<>0),G27/I27,"") -> 0.076923077 | T27: =D27/U27 -> 0.40379299 | U27: =$L$8*AA27*AB27/SUMPRODUCT($AB$25:$AB$56,$AA$25:$AA$56) -> 68195.835 | V27: =$L$9*AA27*AB27/SUMPRODUCT($AB$25:$AB$58,$AA$25:$AA$58) -> 9.8123503 | W27: =IF($L$12="","",V27/$L$12) -> 5.3914013 | X27: =IF(AB27<>"",IF(D27<>"",D27,($L$8-SUM($X$25:X26))*AA27*AB27/SUMPRODUCT($AB27:$AB$58,$AA27:$AA$58)),"") -> 27537 | Y27: =IF(AB27<>"",IF(E27<>"",E27,($L$9-SUM($Y$25:Y26))*AA27*AB27/SUMPRODUCT($AB27:$AB$55,$AA27:$AA$55)),"") -> 6 | Z27: =IF(AB27<>"",IF($L$12<>"",IF(G27<>"",G27,($L$9/$L$12-SUM($Z$25:Z26))*AA27*AB27/SUMPRODUCT($AB27:$AB$55,$AA27:$AA$55)),""),"") -> 3 | AA27: 1 | AB27: 1
A28: 4 | B28: 46118 | C28: пн | D28: 31933 | E28: 8 | F28: =IF(AND(E28<>"",E28<>0),D28/E28,"") -> 3991.625 | G28: 5 | H28: =IF(AND(G28<>"",G28<>0),D28/G28,"") -> 6386.6 | I28: 53 | J28: =IF(AND(G28<>"",G28<>0),E28/G28,"") -> 1.6 | S28: =IF(AND(I28<>"",I28<>0),G28/I28,"") -> 0.094339623 | T28: =D28/U28 -> 0.4682544 | U28: =$L$8*AA28*AB28/SUMPRODUCT($AB$25:$AB$56,$AA$25:$AA$56) -> 68195.835 | V28: =$L$9*AA28*AB28/SUMPRODUCT($AB$25:$AB$58,$AA$25:$AA$58) -> 9.8123503 | W28: =IF($L$12="","",V28/$L$12) -> 5.3914013 | X28: =IF(AB28<>"",IF(D28<>"",D28,($L$8-SUM($X$25:X27))*AA28*AB28/SUMPRODUCT($AB28:$AB$58,$AA28:$AA$58)),"") -> 31933 | Y28: =IF(AB28<>"",IF(E28<>"",E28,($L$9-SUM($Y$25:Y27))*AA28*AB28/SUMPRODUCT($AB28:$AB$58,$AA28:$AA$58)),"") -> 8 | Z28: =IF(AB28<>"",IF($L$12<>"",IF(G28<>"",G28,($L$9/$L$12-SUM($Z$25:Z27))*AA28*AB28/SUMPRODUCT($AB28:$AB$58,$AA28:$AA$58)),""),"") -> 5 | AA28: 1 | AB28: 1
A29: 5 | B29: 46121 | C29: чт | D29: 50991 | E29: 7 | F29: =IF(AND(E29<>"",E29<>0),D29/E29,"") -> 7284.4286 | G29: 2 | H29: =IF(AND(G29<>"",G29<>0),D29/G29,"") -> 25495.5 | I29: 28 | J29: =IF(AND(G29<>"",G29<>0),E29/G29,"") -> 3.5 | R29: 5130 | S29: =IF(AND(I29<>"",I29<>0),G29/I29,"") -> 0.071428571 | T29: =D29/U29 -> 0.74771429 | U29: =$L$8*AA29*AB29/SUMPRODUCT($AB$25:$AB$56,$AA$25:$AA$56) -> 68195.835 | V29: =$L$9*AA29*AB29/SUMPRODUCT($AB$25:$AB$58,$AA$25:$AA$58) -> 9.8123503 | W29: =IF($L$12="","",V29/$L$12) -> 5.3914013 | X29: =IF(AB29<>"",IF(D29<>"",D29,($L$8-SUM($X$25:X28))*AA29*AB29/SUMPRODUCT($AB29:$AB$58,$AA29:$AA$58)),"") -> 50991 | Y29: =IF(AB29<>"",IF(E29<>"",E29,($L$9-SUM($Y$25:Y28))*AA29*AB29/SUMPRODUCT($AB29:$AB$58,$AA29:$AA$58)),"") -> 7 | Z29: =IF(AB29<>"",IF($L$12<>"",IF(G29<>"",G29,($L$9/$L$12-SUM($Z$25:Z28))*AA29*AB29/SUMPRODUCT($AB29:$AB$58,$AA29:$AA$58)),""),"") -> 2 | AA29: 1 | AB29: 1
A30: 6 | B30: 46122 | C30: пт | D30: 4693 | E30: 1 | F30: =IF(AND(E30<>"",E30<>0),D30/E30,"") -> 4693 | G30: 1 | H30: =IF(AND(G30<>"",G30<>0),D30/G30,"") -> 4693 | I30: 27 | J30: =IF(AND(G30<>"",G30<>0),E30/G30,"") -> 1 | S30: =IF(AND(I30<>"",I30<>0),G30/I30,"") -> 0.037037037 | T30: =D30/U30 -> 0.06881652 | U30: =$L$8*AA30*AB30/SUMPRODUCT($AB$25:$AB$56,$AA$25:$AA$56) -> 68195.835 | V30: =$L$9*AA30*AB30/SUMPRODUCT($AB$25:$AB$58,$AA$25:$AA$58) -> 9.8123503 | W30: =IF($L$12="","",V30/$L$12) -> 5.3914013 | X30: =IF(AB30<>"",IF(D30<>"",D30,($L$8-SUM($X$25:X29))*AA30*AB30/SUMPRODUCT($AB30:$AB$58,$AA30:$AA$58)),"") -> 4693 | Y30: =IF(AB30<>"",IF(E30<>"",E30,($L$9-SUM($Y$25:Y29))*AA30*AB30/SUMPRODUCT($AB30:$AB$58,$AA30:$AA$58)),"") -> 1 | Z30: =IF(AB30<>"",IF($L$12<>"",IF(G30<>"",G30,($L$9/$L$12-SUM($Z$25:Z29))*AA30*AB30/SUMPRODUCT($AB30:$AB$58,$AA30:$AA$58)),""),"") -> 1 | AA30: 1 | AB30: 1
A31: 7 | B31: 46125 | C31: пн | D31: 11675 | E31: 3 | F31: 3892 | G31: 2 | H31: =IF(AND(G31<>"",G31<>0),D31/G31,"") -> 5837.5 | I31: 50 | J31: =IF(AND(G31<>"",G31<>0),E31/G31,"") -> 1.5 | S31: =IF(AND(I31<>"",I31<>0),G31/I31,"") -> 0.04 | T31: =D31/U31 -> 0.17119814 | U31: =$L$8*AA31*AB31/SUMPRODUCT($AB$25:$AB$56,$AA$25:$AA$56) -> 68195.835 | V31: =$L$9*AA31*AB31/SUMPRODUCT($AB$25:$AB$58,$AA$25:$AA$58) -> 9.8123503 | W31: =IF($L$12="","",V31/$L$12) -> 5.3914013 | X31: =IF(AB31<>"",IF(D31<>"",D31,($L$8-SUM($X$25:X30))*AA31*AB31/SUMPRODUCT($AB31:$AB$58,$AA31:$AA$58)),"") -> 11675 | Y31: =IF(AB31<>"",IF(E31<>"",E31,($L$9-SUM($Y$25:Y30))*AA31*AB31/SUMPRODUCT($AB31:$AB$58,$AA31:$AA$58)),"") -> 3 | Z31: =IF(AB31<>"",IF($L$12<>"",IF(G31<>"",G31,($L$9/$L$12-SUM($Z$25:Z30))*AA31*AB31/SUMPRODUCT($AB31:$AB$58,$AA31:$AA$58)),""),"") -> 2 | AA31: 1 | AB31: 1
A32: 8 | B32: 46126 | C32: вт | D32: 21260 | E32: 5 | F32: =IF(AND(E32<>"",E32<>0),D32/E32,"") -> 4252 | G32: 4 | H32: =IF(AND(G32<>"",G32<>0),D32/G32,"") -> 5315 | I32: 33 | J32: =IF(AND(G32<>"",G32<>0),E32/G32,"") -> 1.25 | S32: =IF(AND(I32<>"",I32<>0),G32/I32,"") -> 0.12121212 | T32: =D32/U32 -> 0.31174925 | U32: =$L$8*AA32*AB32/SUMPRODUCT($AB$25:$AB$56,$AA$25:$AA$56) -> 68195.835 | V32: =$L$9*AA32*AB32/SUMPRODUCT($AB$25:$AB$58,$AA$25:$AA$58) -> 9.8123503 | W32: =IF($L$12="","",V32/$L$12) -> 5.3914013 | X32: =IF(AB32<>"",IF(D32<>"",D32,($L$8-SUM($X$25:X31))*AA32*AB32/SUMPRODUCT($AB32:$AB$58,$AA32:$AA$58)),"") -> 21260 | Y32: =IF(AB32<>"",IF(E32<>"",E32,($L$9-SUM($Y$25:Y31))*AA32*AB32/SUMPRODUCT($AB32:$AB$58,$AA32:$AA$58)),"") -> 5 | Z32: =IF(AB32<>"",IF($L$12<>"",IF(G32<>"",G32,($L$9/$L$12-SUM($Z$25:Z31))*AA32*AB32/SUMPRODUCT($AB32:$AB$58,$AA32:$AA$58)),""),"") -> 4 | AA32: 1 | AB32: 1
A33: 9 | B33: 46127 | C33: ср | D33: 35255 | E33: 4 | F33: =IF(AND(E33<>"",E33<>0),D33/E33,"") -> 8813.75 | G33: 2 | H33: =IF(AND(G33<>"",G33<>0),D33/G33,"") -> 17627.5 | I33: 29 | J33: =IF(AND(G33<>"",G33<>0),E33/G33,"") -> 2 | Q33: 26072 | S33: =IF(AND(I33<>"",I33<>0),G33/I33,"") -> 0.068965517 | T33: =D33/U33 -> 0.51696706 | U33: =$L$8*AA33*AB33/SUMPRODUCT($AB$25:$AB$56,$AA$25:$AA$56) -> 68195.835 | V33: =$L$9*AA33*AB33/SUMPRODUCT($AB$25:$AB$58,$AA$25:$AA$58) -> 9.8123503 | W33: =IF($L$12="","",V33/$L$12) -> 5.3914013 | X33: =IF(AB33<>"",IF(D33<>"",D33,($L$8-SUM($X$25:X32))*AA33*AB33/SUMPRODUCT($AB33:$AB$58,$AA33:$AA$58)),"") -> 35255 | Y33: =IF(AB33<>"",IF(E33<>"",E33,($L$9-SUM($Y$25:Y32))*AA33*AB33/SUMPRODUCT($AB33:$AB$58,$AA33:$AA$58)),"") -> 4 | Z33: =IF(AB33<>"",IF($L$12<>"",IF(G33<>"",G33,($L$9/$L$12-SUM($Z$25:Z32))*AA33*AB33/SUMPRODUCT($AB33:$AB$58,$AA33:$AA$58)),""),"") -> 2 | AA33: 1 | AB33: 1
A34: 10 | B34: 46129 | C34: пт | D34: 45568 | E34: 4 | F34: =IF(AND(E34<>"",E34<>0),D34/E34,"") -> 11392 | G34: 3 | H34: =IF(AND(G34<>"",G34<>0),D34/G34,"") -> 15189.333 | I34: 32 | J34: =IF(AND(G34<>"",G34<>0),E34/G34,"") -> 1.3333333 | K34: 8992 | P34: 32284 | S34: =IF(AND(I34<>"",I34<>0),G34/I34,"") -> 0.09375 | T34: =D34/U34 -> 0.6681933 | U34: =$L$8*AA34*AB34/SUMPRODUCT($AB$25:$AB$56,$AA$25:$AA$56) -> 68195.835 | V34: =$L$9*AA34*AB34/SUMPRODUCT($AB$25:$AB$58,$AA$25:$AA$58) -> 9.8123503 | W34: =IF($L$12="","",V34/$L$12) -> 5.3914013 | X34: =IF(AB34<>"",IF(D34<>"",D34,($L$8-SUM($X$25:X33))*AA34*AB34/SUMPRODUCT($AB34:$AB$58,$AA34:$AA$58)),"") -> 45568 | Y34: =IF(AB34<>"",IF(E34<>"",E34,($L$9-SUM($Y$25:Y33))*AA34*AB34/SUMPRODUCT($AB34:$AB$58,$AA34:$AA$58)),"") -> 4 | Z34: =IF(AB34<>"",IF($L$12<>"",IF(G34<>"",G34,($L$9/$L$12-SUM($Z$25:Z33))*AA34*AB34/SUMPRODUCT($AB34:$AB$58,$AA34:$AA$58)),""),"") -> 3 | AA34: 1 | AB34: 1
A35: 11 | B35: 46130 | C35: сб | D35: 53423 | E35: 8 | F35: =IF(AND(E35<>"",E35<>0),D35/E35,"") -> 6677.875 | G35: 3 | H35: =IF(AND(G35<>"",G35<>0),D35/G35,"") -> 17807.667 | I35: 51 | J35: =IF(AND(G35<>"",G35<>0),E35/G35,"") -> 2.6666667 | K35: 15990 | S35: =IF(AND(I35<>"",I35<>0),G35/I35,"") -> 0.058823529 | T35: =D35/U35 -> 0.78337629 | U35: =$L$8*AA35*AB35/SUMPRODUCT($AB$25:$AB$56,$AA$25:$AA$56) -> 68195.835 | V35: =$L$9*AA35*AB35/SUMPRODUCT($AB$25:$AB$58,$AA$25:$AA$58) -> 9.8123503 | W35: =IF($L$12="","",V35/$L$12) -> 5.3914013 | X35: =IF(AB35<>"",IF(D35<>"",D35,($L$8-SUM($X$25:X34))*AA35*AB35/SUMPRODUCT($AB35:$AB$58,$AA35:$AA$58)),"") -> 53423 | Y35: =IF(AB35<>"",IF(E34<>"",E34,($L$9-SUM($Y$25:Y34))*AA35*AB35/SUMPRODUCT($AB35:$AB$58,$AA35:$AA$58)),"") -> 4 | Z35: =IF(AB35<>"",IF($L$12<>"",IF(G35<>"",G35,($L$9/$L$12-SUM($Z$25:Z34))*AA35*AB35/SUMPRODUCT($AB35:$AB$58,$AA35:$AA$58)),""),"") -> 3 | AA35: 1 | AB35: 1
A36: 11 | B36: 46132 | C36: пн | D36: 38213 | E36: 8 | F36: 4777 | G36: 5 | H36: 7643 | I36: 86 | J36: =IF(AND(G36<>"",G36<>0),E36/G36,"") -> 1.6 | R36: 11647 | S36: =IF(AND(I36<>"",I36<>0),G36/I36,"") -> 0.058139535 | T36: =D36/U36 -> 0.56034214 | U36: =$L$8*AA36*AB36/SUMPRODUCT($AB$25:$AB$56,$AA$25:$AA$56) -> 68195.835 | V36: =$L$9*AA36*AB36/SUMPRODUCT($AB$25:$AB$58,$AA$25:$AA$58) -> 9.8123503 | W36: =IF($L$12="","",V36/$L$12) -> 5.3914013 | X36: =IF(AB36<>"",IF(D36<>"",D36,($L$8-SUM($X$25:X35))*AA36*AB36/SUMPRODUCT($AB36:$AB$58,$AA36:$AA$58)),"") -> 38213 | Y36: =IF(AB36<>"",IF(E35<>"",E35,($L$9-SUM($Y$25:Y35))*AA36*AB36/SUMPRODUCT($AB36:$AB$58,$AA36:$AA$58)),"") -> 8 | Z36: =IF(AB36<>"",IF($L$12<>"",IF(G36<>"",G36,($L$9/$L$12-SUM($Z$25:Z35))*AA36*AB36/SUMPRODUCT($AB36:$AB$58,$AA36:$AA$58)),""),"") -> 5 | AA36: 1 | AB36: 1
A37: 13 | B37: 46133 | C37: вт | D37: 61152 | E37: 8 | F37: =IF(AND(E37<>"",E37<>0),D37/E37,"") -> 7644 | G37: 6 | H37: =IF(AND(G37<>"",G37<>0),D37/G37,"") -> 10192 | I37: 64 | J37: =IF(AND(G37<>"",G37<>0),E37/G37,"") -> 1.3333333 | L37: 25500 | R37: 2595 | S37: =IF(AND(I37<>"",I37<>0),G37/I37,"") -> 0.09375 | T37: =D37/U37 -> 0.89671166 | U37: =$L$8*AA37*AB37/SUMPRODUCT($AB$25:$AB$56,$AA$25:$AA$56) -> 68195.835 | V37: =$L$9*AA37*AB37/SUMPRODUCT($AB$25:$AB$58,$AA$25:$AA$58) -> 9.8123503 | W37: =IF($L$12="","",V37/$L$12) -> 5.3914013 | X37: =IF(AB37<>"",IF(D37<>"",D37,($L$8-SUM($X$25:X36))*AA37*AB37/SUMPRODUCT($AB37:$AB$58,$AA37:$AA$58)),"") -> 61152 | Y37: =IF(AB37<>"",IF(E37<>"",E37,($L$9-SUM($Y$25:Y36))*AA37*AB37/SUMPRODUCT($AB37:$AB$58,$AA37:$AA$58)),"") -> 8 | Z37: =IF(AB37<>"",IF($L$12<>"",IF(G37<>"",G37,($L$9/$L$12-SUM($Z$25:Z36))*AA37*AB37/SUMPRODUCT($AB37:$AB$58,$AA37:$AA$58)),""),"") -> 6 | AA37: 1 | AB37: 1
A38: 14 | B38: 46134 | C38: ср | D38: 66152 | E38: 9 | F38: =IF(AND(E38<>"",E38<>0),D38/E38,"") -> 7350.2222 | G38: 6 | H38: =IF(AND(G38<>"",G38<>0),D38/G38,"") -> 11025.333 | I38: 60 | J38: =IF(AND(G38<>"",G38<>0),E38/G38,"") -> 1.5 | K38: 20284 | R38: 4392 | S38: =IF(AND(I38<>"",I38<>0),G38/I38,"") -> 0.1 | T38: =D38/U38 -> 0.97002992 | U38: =$L$8*AA38*AB38/SUMPRODUCT($AB$25:$AB$56,$AA$25:$AA$56) -> 68195.835 | V38: =$L$9*AA38*AB38/SUMPRODUCT($AB$25:$AB$58,$AA$25:$AA$58) -> 9.8123503 | W38: =IF($L$12="","",V38/$L$12) -> 5.3914013 | X38: =IF(AB38<>"",IF(D38<>"",D38,($L$8-SUM($X$25:X37))*AA38*AB38/SUMPRODUCT($AB38:$AB$58,$AA38:$AA$58)),"") -> 66152 | Y38: =IF(AB38<>"",IF(E38<>"",E38,($L$9-SUM($Y$25:Y37))*AA38*AB38/SUMPRODUCT($AB38:$AB$58,$AA38:$AA$58)),"") -> 9 | Z38: =IF(AB38<>"",IF($L$12<>"",IF(G38<>"",G38,($L$9/$L$12-SUM($Z$25:Z37))*AA38*AB38/SUMPRODUCT($AB38:$AB$58,$AA38:$AA$58)),""),"") -> 6 | AA38: 1 | AB38: 1
A39: 15 | B39: 46135 | C39: чт | D39: 8688 | E39: 2 | F39: =IF(AND(E39<>"",E39<>0),D39/E39,"") -> 4344 | G39: 2 | H39: =IF(AND(G39<>"",G39<>0),D39/G39,"") -> 4344 | I39: 33 | J39: =IF(AND(G39<>"",G39<>0),E39/G39,"") -> 1 | R39: 4392 | S39: =IF(AND(I39<>"",I39<>0),G39/I39,"") -> 0.060606061 | T39: =D39/U39 -> 0.12739781 | U39: =$L$8*AA39*AB39/SUMPRODUCT($AB$25:$AB$56,$AA$25:$AA$56) -> 68195.835 | V39: =$L$9*AA39*AB39/SUMPRODUCT($AB$25:$AB$58,$AA$25:$AA$58) -> 9.8123503 | W39: =IF($L$12="","",V39/$L$12) -> 5.3914013 | X39: =IF(AB39<>"",IF(D39<>"",D39,($L$8-SUM($X$25:X38))*AA39*AB39/SUMPRODUCT($AB39:$AB$58,$AA39:$AA$58)),"") -> 8688 | Y39: =IF(AB39<>"",IF(E39<>"",E39,($L$9-SUM($Y$25:Y38))*AA39*AB39/SUMPRODUCT($AB39:$AB$58,$AA39:$AA$58)),"") -> 2 | Z39: =IF(AB39<>"",IF($L$12<>"",IF(G39<>"",G39,($L$9/$L$12-SUM($Z$25:Z38))*AA39*AB39/SUMPRODUCT($AB39:$AB$58,$AA39:$AA$58)),""),"") -> 2 | AA39: 1 | AB39: 1
A40: 16 | B40: 46137 | C40: сб | D40: =12893+29904+6903 -> 49700 | E40: 3 | F40: =IF(AND(E40<>"",E40<>0),D40/E40,"") -> 16566.667 | G40: 3 | H40: =IF(AND(G40<>"",G40<>0),D40/G40,"") -> 16566.667 | I40: 20 | J40: =IF(AND(G40<>"",G40<>0),E40/G40,"") -> 1 | L40: =29904+6903 -> 36807 | M40: 12893 | S40: =IF(AND(I40<>"",I40<>0),G40/I40,"") -> 0.15 | T40: =D40/U40 -> 0.72878351 | U40: =$L$8*AA40*AB40/SUMPRODUCT($AB$25:$AB$56,$AA$25:$AA$56) -> 68195.835 | V40: =$L$9*AA40*AB40/SUMPRODUCT($AB$25:$AB$58,$AA$25:$AA$58) -> 9.8123503 | W40: =IF($L$12="","",V40/$L$12) -> 5.3914013 | X40: =IF(AB40<>"",IF(D40<>"",D40,($L$8-SUM($X$25:X39))*AA40*AB40/SUMPRODUCT($AB40:$AB$58,$AA40:$AA$58)),"") -> 49700 | Y40: =IF(AB40<>"",IF(E40<>"",E40,($L$9-SUM($Y$25:Y39))*AA40*AB40/SUMPRODUCT($AB40:$AB$58,$AA40:$AA$58)),"") -> 3 | Z40: =IF(AB40<>"",IF($L$12<>"",IF(G40<>"",G40,($L$9/$L$12-SUM($Z$25:Z39))*AA40*AB40/SUMPRODUCT($AB40:$AB$58,$AA40:$AA$58)),""),"") -> 3 | AA40: 1 | AB40: 1
A41: 17 | B41: 46138 | C41: вс | D41: 10285 | E41: 2 | F41: =IF(AND(E41<>"",E41<>0),D41/E41,"") -> 5142.5 | G41: 2 | H41: =IF(AND(G41<>"",G41<>0),D41/G41,"") -> 5142.5 | I41: 18 | J41: =IF(AND(G41<>"",G41<>0),E41/G41,"") -> 1 | S41: =IF(AND(I41<>"",I41<>0),G41/I41,"") -> 0.11111111 | T41: =D41/U41 -> #DIV/0! | U41: =$L$8*AA41*AB41/SUMPRODUCT($AB$25:$AB$56,$AA$25:$AA$56) -> 0 | V41: =$L$9*AA41*AB41/SUMPRODUCT($AB$25:$AB$58,$AA$25:$AA$58) -> 0 | W41: =IF($L$12="","",V41/$L$12) -> 0 | X41: =IF(AB41<>"",IF(D41<>"",D41,($L$8-SUM($X$25:X40))*AA41*AB41/SUMPRODUCT($AB41:$AB$58,$AA41:$AA$58)),"") | Y41: =IF(AB41<>"",IF(E41<>"",E41,($L$9-SUM($Y$25:Y40))*AA41*AB41/SUMPRODUCT($AB41:$AB$58,$AA41:$AA$58)),"") | Z41: =IF(AB41<>"",IF($L$12<>"",IF(G41<>"",G41,($L$9/$L$12-SUM($Z$25:Z40))*AA41*AB41/SUMPRODUCT($AB41:$AB$58,$AA41:$AA$58)),""),"")
A42: 18 | B42: 46140 | C42: вт | D42: =21806+6239 -> 28045 | E42: 4 | F42: =IF(AND(E42<>"",E42<>0),D42/E42,"") -> 7011.25 | G42: 3 | H42: =IF(AND(G42<>"",G42<>0),D42/G42,"") -> 9348.3333 | I42: 18 | J42: =IF(AND(G42<>"",G42<>0),E42/G42,"") -> 1.3333333 | L42: 21806 | R42: 6235 | S42: =IF(AND(I42<>"",I42<>0),G42/I42,"") -> 0.16666667 | T42: =D42/U42 -> #DIV/0! | U42: =$L$8*AA42*AB42/SUMPRODUCT($AB$25:$AB$56,$AA$25:$AA$56) -> 0 | V42: =$L$9*AA42*AB42/SUMPRODUCT($AB$25:$AB$58,$AA$25:$AA$58) -> 0 | W42: =IF($L$12="","",V42/$L$12) -> 0 | X42: =IF(AB42<>"",IF(D42<>"",D42,($L$8-SUM($X$25:X41))*AA42*AB42/SUMPRODUCT($AB42:$AB$58,$AA42:$AA$58)),"") | Y42: =IF(AB42<>"",IF(E42<>"",E42,($L$9-SUM($Y$25:Y41))*AA42*AB42/SUMPRODUCT($AB42:$AB$58,$AA42:$AA$58)),"") | Z42: =IF(AB42<>"",IF($L$12<>"",IF(G42<>"",G42,($L$9/$L$12-SUM($Z$25:Z41))*AA42*AB42/SUMPRODUCT($AB42:$AB$58,$AA42:$AA$58)),""),"")
A43: 18 | B43: 46141 | C43: ср | D43: 34050 | E43: 6 | F43: =IF(AND(E43<>"",E43<>0),D43/E43,"") -> 5675 | G43: 2 | H43: =IF(AND(G43<>"",G43<>0),D43/G43,"") -> 17025 | I43: 27 | J43: =IF(AND(G43<>"",G43<>0),E43/G43,"") -> 3 | S43: =IF(AND(I43<>"",I43<>0),G43/I43,"") -> 0.074074074 | T43: =D43/U43 -> #DIV/0! | U43: =$L$8*AA43*AB43/SUMPRODUCT($AB$25:$AB$56,$AA$25:$AA$56) -> 0 | V43: =$L$9*AA43*AB43/SUMPRODUCT($AB$25:$AB$58,$AA$25:$AA$58) -> 0 | W43: =IF($L$12="","",V43/$L$12) -> 0 | X43: =IF(AB43<>"",IF(D43<>"",D43,($L$8-SUM($X$25:X42))*AA43*AB43/SUMPRODUCT($AB43:$AB$58,$AA43:$AA$58)),"") | Y43: =IF(AB43<>"",IF(E43<>"",E43,($L$9-SUM($Y$25:Y42))*AA43*AB43/SUMPRODUCT($AB43:$AB$58,$AA43:$AA$58)),"") | Z43: =IF(AB43<>"",IF($L$12<>"",IF(G43<>"",G43,($L$9/$L$12-SUM($Z$25:Z42))*AA43*AB43/SUMPRODUCT($AB43:$AB$58,$AA43:$AA$58)),""),"")
A44: 19 | B44: 46142 | C44: чт | D44: =143203+L44 -> 169903 | E44: 13 | F44: =IF(AND(E44<>"",E44<>0),D44/E44,"") -> 13069.462 | G44: 6 | H44: =IF(AND(G44<>"",G44<>0),D44/G44,"") -> 28317.167 | I44: 70 | J44: =IF(AND(G44<>"",G44<>0),E44/G44,"") -> 2.1666667 | K44: 29984 | L44: 26700 | O44: 87458 | R44: 6490 | S44: =IF(AND(I44<>"",I44<>0),G44/I44,"") -> 0.085714286 | T44: =D44/U44 -> #DIV/0! | U44: =$L$8*AA44*AB44/SUMPRODUCT($AB$25:$AB$56,$AA$25:$AA$56) -> 0 | V44: =$L$9*AA44*AB44/SUMPRODUCT($AB$25:$AB$58,$AA$25:$AA$58) -> 0 | W44: =IF($L$12="","",V44/$L$12) -> 0 | X44: =IF(AB44<>"",IF(D44<>"",D44,($L$8-SUM($X$25:X43))*AA44*AB44/SUMPRODUCT($AB44:$AB$58,$AA44:$AA$58)),"") | Y44: =IF(AB44<>"",IF(E44<>"",E44,($L$9-SUM($Y$25:Y43))*AA44*AB44/SUMPRODUCT($AB44:$AB$58,$AA44:$AA$58)),"") | Z44: =IF(AB44<>"",IF($L$12<>"",IF(G44<>"",G44,($L$9/$L$12-SUM($Z$25:Z43))*AA44*AB44/SUMPRODUCT($AB44:$AB$58,$AA44:$AA$58)),""),"")
A45: 20 | F45: =IF(AND(E45<>"",E45<>0),D45/E45,"") | H45: =IF(AND(G45<>"",G45<>0),D45/G45,"") | J45: =IF(AND(G45<>"",G45<>0),E45/G45,"") | S45: =IF(AND(I45<>"",I45<>0),G45/I45,"") | T45: =D45/U45 -> #DIV/0! | U45: =$L$8*AA45*AB45/SUMPRODUCT($AB$25:$AB$56,$AA$25:$AA$56) -> 0 | V45: =$L$9*AA45*AB45/SUMPRODUCT($AB$25:$AB$58,$AA$25:$AA$58) -> 0 | W45: =IF($L$12="","",V45/$L$12) -> 0 | X45: =IF(AB45<>"",IF(D45<>"",D45,($L$8-SUM($X$25:X44))*AA45*AB45/SUMPRODUCT($AB45:$AB$58,$AA45:$AA$58)),"") | Y45: =IF(AB45<>"",IF(E45<>"",E45,($L$9-SUM($Y$25:Y44))*AA45*AB45/SUMPRODUCT($AB45:$AB$58,$AA45:$AA$58)),"") | Z45: =IF(AB45<>"",IF($L$12<>"",IF(G45<>"",G45,($L$9/$L$12-SUM($Z$25:Z44))*AA45*AB45/SUMPRODUCT($AB45:$AB$58,$AA45:$AA$58)),""),"")
A46: 21 | F46: =IF(AND(E46<>"",E46<>0),D46/E46,"") | H46: =IF(AND(G46<>"",G46<>0),D46/G46,"") | J46: =IF(AND(G46<>"",G46<>0),E46/G46,"") | S46: =IF(AND(I46<>"",I46<>0),G46/I46,"") | T46: =D46/U46 -> #DIV/0! | U46: =$L$8*AA46*AB46/SUMPRODUCT($AB$25:$AB$56,$AA$25:$AA$56) -> 0 | V46: =$L$9*AA46*AB46/SUMPRODUCT($AB$25:$AB$58,$AA$25:$AA$58) -> 0 | W46: =IF($L$12="","",V46/$L$12) -> 0 | X46: =IF(AB46<>"",IF(D46<>"",D46,($L$8-SUM($X$25:X45))*AA46*AB46/SUMPRODUCT($AB46:$AB$58,$AA46:$AA$58)),"") | Y46: =IF(AB46<>"",IF(E46<>"",E46,($L$9-SUM($Y$25:Y45))*AA46*AB46/SUMPRODUCT($AB46:$AB$58,$AA46:$AA$58)),"") | Z46: =IF(AB46<>"",IF($L$12<>"",IF(G46<>"",G46,($L$9/$L$12-SUM($Z$25:Z45))*AA46*AB46/SUMPRODUCT($AB46:$AB$58,$AA46:$AA$58)),""),"")
A47: 22 | F47: =IF(AND(E47<>"",E47<>0),D47/E47,"") | H47: =IF(AND(G47<>"",G47<>0),D47/G47,"") | J47: =IF(AND(G47<>"",G47<>0),E47/G47,"") | S47: =IF(AND(I47<>"",I47<>0),G47/I47,"") | T47: =D47/U47 -> #DIV/0! | U47: =$L$8*AA47*AB47/SUMPRODUCT($AB$25:$AB$56,$AA$25:$AA$56) -> 0 | V47: =$L$9*AA47*AB47/SUMPRODUCT($AB$25:$AB$58,$AA$25:$AA$58) -> 0 | W47: =IF($L$12="","",V47/$L$12) -> 0 | X47: =IF(AB47<>"",IF(D47<>"",D47,($L$8-SUM($X$25:X46))*AA47*AB47/SUMPRODUCT($AB47:$AB$58,$AA47:$AA$58)),"") | Y47: =IF(AB47<>"",IF(E47<>"",E47,($L$9-SUM($Y$25:Y46))*AA47*AB47/SUMPRODUCT($AB47:$AB$58,$AA47:$AA$58)),"") | Z47: =IF(AB47<>"",IF($L$12<>"",IF(G47<>"",G47,($L$9/$L$12-SUM($Z$25:Z46))*AA47*AB47/SUMPRODUCT($AB47:$AB$58,$AA47:$AA$58)),""),"")
A48: 23 | F48: =IF(AND(E48<>"",E48<>0),D48/E48,"") | H48: =IF(AND(G48<>"",G48<>0),D48/G48,"") | J48: =IF(AND(G48<>"",G48<>0),E48/G48,"") | S48: =IF(AND(I48<>"",I48<>0),G48/I48,"") | T48: =D48/U48 -> #DIV/0! | U48: =$L$8*AA48*AB48/SUMPRODUCT($AB$25:$AB$56,$AA$25:$AA$56) -> 0 | V48: =$L$9*AA48*AB48/SUMPRODUCT($AB$25:$AB$58,$AA$25:$AA$58) -> 0 | W48: =IF($L$12="","",V48/$L$12) -> 0 | X48: =IF(AB48<>"",IF(D48<>"",D48,($L$8-SUM($X$25:X47))*AA48*AB48/SUMPRODUCT($AB48:$AB$58,$AA48:$AA$58)),"") | Y48: =IF(AB48<>"",IF(E48<>"",E48,($L$9-SUM($Y$25:Y47))*AA48*AB48/SUMPRODUCT($AB48:$AB$58,$AA48:$AA$58)),"") | Z48: =IF(AB48<>"",IF($L$12<>"",IF(G48<>"",G48,($L$9/$L$12-SUM($Z$25:Z47))*AA48*AB48/SUMPRODUCT($AB48:$AB$58,$AA48:$AA$58)),""),"")
A49: 24 | H49: =IF(AND(G49<>"",G49<>0),D49/G49,"") | J49: =IF(AND(G49<>"",G49<>0),E49/G49,"") | S49: =IF(AND(I49<>"",I49<>0),G49/I49,"") | T49: =D49/U49 -> #DIV/0! | U49: =$L$8*AA49*AB49/SUMPRODUCT($AB$25:$AB$56,$AA$25:$AA$56) -> 0 | V49: =$L$9*AA49*AB49/SUMPRODUCT($AB$25:$AB$58,$AA$25:$AA$58) -> 0 | W49: =IF($L$12="","",V49/$L$12) -> 0 | X49: =IF(AB49<>"",IF(D49<>"",D49,($L$8-SUM($X$25:X48))*AA49*AB49/SUMPRODUCT($AB49:$AB$58,$AA49:$AA$58)),"") | Y49: =IF(AB49<>"",IF(E49<>"",E49,($L$9-SUM($Y$25:Y48))*AA49*AB49/SUMPRODUCT($AB49:$AB$58,$AA49:$AA$58)),"") | Z49: =IF(AB49<>"",IF($L$12<>"",IF(G49<>"",G49,($L$9/$L$12-SUM($Z$25:Z48))*AA49*AB49/SUMPRODUCT($AB49:$AB$58,$AA49:$AA$58)),""),"")
F50: =IF(AND(E50<>"",E50<>0),D50/E50,"") | H50: =IF(AND(G50<>"",G50<>0),D50/G50,"") | J50: =IF(AND(G50<>"",G50<>0),E50/G50,"") | S50: =IF(AND(I50<>"",I50<>0),G50/I50,"") | T50: =D50/U50 -> #DIV/0! | U50: =$L$8*AA50*AB50/SUMPRODUCT($AB$25:$AB$56,$AA$25:$AA$56) -> 0 | V50: =$L$9*AA50*AB50/SUMPRODUCT($AB$25:$AB$58,$AA$25:$AA$58) -> 0 | W50: =IF($L$12="","",V50/$L$12) -> 0 | X50: =IF(AB50<>"",IF(D50<>"",D50,($L$8-SUM($X$25:X49))*AA50*AB50/SUMPRODUCT($AB50:$AB$58,$AA50:$AA$58)),"") | Y50: =IF(AB50<>"",IF(E50<>"",E50,($L$9-SUM($Y$25:Y49))*AA50*AB50/SUMPRODUCT($AB50:$AB$58,$AA50:$AA$58)),"") | Z50: =IF(AB50<>"",IF($L$12<>"",IF(G50<>"",G50,($L$9/$L$12-SUM($Z$25:Z49))*AA50*AB50/SUMPRODUCT($AB50:$AB$58,$AA50:$AA$58)),""),"")
F51: =IF(AND(E51<>"",E51<>0),D51/E51,"") | H51: =IF(AND(G51<>"",G51<>0),D51/G51,"") | J51: =IF(AND(G51<>"",G51<>0),E51/G51,"") | S51: =IF(AND(I51<>"",I51<>0),G51/I51,"") | T51: =D51/U51 -> #DIV/0! | U51: =$L$8*AA51*AB51/SUMPRODUCT($AB$25:$AB$56,$AA$25:$AA$56) -> 0 | V51: =$L$9*AA51*AB51/SUMPRODUCT($AB$25:$AB$58,$AA$25:$AA$58) -> 0 | W51: =IF($L$12="","",V51/$L$12) -> 0 | X51: =IF(AB51<>"",IF(D51<>"",D51,($L$8-SUM($X$25:X50))*AA51*AB51/SUMPRODUCT($AB51:$AB$58,$AA51:$AA$58)),"") | Y51: =IF(AB51<>"",IF(E51<>"",E51,($L$9-SUM($Y$25:Y50))*AA51*AB51/SUMPRODUCT($AB51:$AB$58,$AA51:$AA$58)),"") | Z51: =IF(AB51<>"",IF($L$12<>"",IF(G51<>"",G51,($L$9/$L$12-SUM($Z$25:Z50))*AA51*AB51/SUMPRODUCT($AB51:$AB$58,$AA51:$AA$58)),""),"")
F52: =IF(AND(E52<>"",E52<>0),D52/E52,"") | H52: =IF(AND(G52<>"",G52<>0),D52/G52,"") | J52: =IF(AND(G52<>"",G52<>0),E52/G52,"") | S52: =IF(AND(I52<>"",I52<>0),G52/I52,"") | T52: =D52/U52 -> #DIV/0! | U52: =$L$8*AA52*AB52/SUMPRODUCT($AB$25:$AB$56,$AA$25:$AA$56) -> 0 | V52: =$L$9*AA52*AB52/SUMPRODUCT($AB$25:$AB$58,$AA$25:$AA$58) -> 0 | W52: =IF($L$12="","",V52/$L$12) -> 0 | X52: =IF(AB52<>"",IF(D52<>"",D52,($L$8-SUM($X$25:X51))*AA52*AB52/SUMPRODUCT($AB52:$AB$58,$AA52:$AA$58)),"") | Y52: =IF(AB52<>"",IF(E52<>"",E52,($L$9-SUM($Y$25:Y51))*AA52*AB52/SUMPRODUCT($AB52:$AB$58,$AA52:$AA$58)),"") | Z52: =IF(AB52<>"",IF($L$12<>"",IF(G52<>"",G52,($L$9/$L$12-SUM($Z$25:Z51))*AA52*AB52/SUMPRODUCT($AB52:$AB$58,$AA52:$AA$58)),""),"")
F53: =IF(AND(E53<>"",E53<>0),D53/E53,"") | H53: =IF(AND(G53<>"",G53<>0),D53/G53,"") | J53: =IF(AND(G53<>"",G53<>0),E53/G53,"") | S53: =IF(AND(I53<>"",I53<>0),G53/I53,"") | T53: =D53/U53 -> #DIV/0! | U53: =$L$8*AA53*AB53/SUMPRODUCT($AB$25:$AB$56,$AA$25:$AA$56) -> 0 | V53: =$L$9*AA53*AB53/SUMPRODUCT($AB$25:$AB$58,$AA$25:$AA$58) -> 0 | W53: =IF($L$12="","",V53/$L$12) -> 0 | X53: =IF(AB53<>"",IF(D53<>"",D53,($L$8-SUM($X$25:X52))*AA53*AB53/SUMPRODUCT($AB53:$AB$58,$AA53:$AA$58)),"") | Y53: =IF(AB53<>"",IF(E53<>"",E53,($L$9-SUM($Y$25:Y52))*AA53*AB53/SUMPRODUCT($AB53:$AB$58,$AA53:$AA$58)),"") | Z53: =IF(AB53<>"",IF($L$12<>"",IF(G53<>"",G53,($L$9/$L$12-SUM($Z$25:Z52))*AA53*AB53/SUMPRODUCT($AB53:$AB$58,$AA53:$AA$58)),""),"")
F54: =IF(AND(E54<>"",E54<>0),D54/E54,"") | H54: =IF(AND(G54<>"",G54<>0),D54/G54,"") | J54: =IF(AND(G54<>"",G54<>0),E54/G54,"") | S54: =IF(AND(I54<>"",I54<>0),G54/I54,"") | T54: =D54/U54 -> #DIV/0! | U54: =$L$8*AA54*AB54/SUMPRODUCT($AB$25:$AB$56,$AA$25:$AA$56) -> 0 | V54: =$L$9*AA54*AB54/SUMPRODUCT($AB$25:$AB$58,$AA$25:$AA$58) -> 0 | W54: =IF($L$12="","",V54/$L$12) -> 0 | X54: =IF(AB54<>"",IF(D54<>"",D54,($L$8-SUM($X$25:X50))*AA54*AB54/SUMPRODUCT($AB54:$AB$58,$AA54:$AA$58)),"") | Y54: =IF(AB54<>"",IF(E54<>"",E54,($L$9-SUM($Y$25:Y50))*AA54*AB54/SUMPRODUCT($AB54:$AB$58,$AA54:$AA$58)),"") | Z54: =IF(AB54<>"",IF($L$12<>"",IF(G54<>"",G54,($L$9/$L$12-SUM($Z$25:Z50))*AA54*AB54/SUMPRODUCT($AB54:$AB$58,$AA54:$AA$58)),""),"")
F55: =IF(AND(E55<>"",E55<>0),D55/E55,"") | H55: =IF(AND(G55<>"",G55<>0),D55/G55,"") | J55: =IF(AND(G55<>"",G55<>0),E55/G55,"") | S55: =IF(AND(I55<>"",I55<>0),G55/I55,"") | T55: =D55/U55 -> #DIV/0! | U55: =$L$8*AA55*AB55/SUMPRODUCT($AB$25:$AB$56,$AA$25:$AA$56) -> 0 | V55: =$L$9*AA55*AB55/SUMPRODUCT($AB$25:$AB$58,$AA$25:$AA$58) -> 0 | W55: =IF($L$12="","",V55/$L$12) -> 0 | X55: =IF(AB55<>"",IF(D55<>"",D55,($L$8-SUM($X$25:X54))*AA55*AB55/SUMPRODUCT($AB55:$AB$58,$AA55:$AA$58)),"") | Y55: =IF(AB55<>"",IF(E55<>"",E55,($L$9-SUM($Y$25:Y54))*AA55*AB55/SUMPRODUCT($AB55:$AB$58,$AA55:$AA$58)),"") | Z55: =IF(AB55<>"",IF($L$12<>"",IF(G55<>"",G55,($L$9/$L$12-SUM($Z$25:Z54))*AA55*AB55/SUMPRODUCT($AB55:$AB$58,$AA55:$AA$58)),""),"")
F56: =IF(AND(E56<>"",E56<>0),D56/E56,"") | H56: =IF(AND(G56<>"",G56<>0),D56/G56,"") | J56: =IF(AND(G56<>"",G56<>0),E56/G56,"") | S56: =IF(AND(I56<>"",I56<>0),G56/I56,"") | T56: =D56/U56 -> #DIV/0! | U56: =$L$8*AA56*AB56/SUMPRODUCT($AB$25:$AB$56,$AA$25:$AA$56) -> 0 | V56: =$L$9*AA56*AB56/SUMPRODUCT($AB$25:$AB$58,$AA$25:$AA$58) -> 0 | W56: =IF($L$12="","",V56/$L$12) -> 0 | X56: =IF(AB56<>"",IF(D56<>"",D56,($L$8-SUM($X$25:X55))*AA56*AB56/SUMPRODUCT($AB56:$AB$58,$AA56:$AA$58)),"") | Y56: =IF(AB56<>"",IF(E56<>"",E56,($L$9-SUM($Y$25:Y55))*AA56*AB56/SUMPRODUCT($AB56:$AB$58,$AA56:$AA$58)),"") | Z56: =IF(AB56<>"",IF($L$12<>"",IF(G56<>"",G56,($L$9/$L$12-SUM($Z$25:Z55))*AA56*AB56/SUMPRODUCT($AB56:$AB$58,$AA56:$AA$58)),""),"")
D57: =SUM(D25:D56) -> 780750 | E57: =SUM(E25:E56) -> 107 | F57: =IF(AND(E57<>"",E57<>0),D57/E57,"") -> 7296.729 | G57: =SUM(G25:G56) -> 63 | H57: =IF(AND(G57<>"",G57<>0),D57/G57,"") -> 12392.857 | I57: =SUM(I25:I56) -> 799 | J57: =IF(AND(G57<>"",G57<>0),E57/G57,"") -> 1.6984127 | K57: =SUM(K25:K56) -> 87543 | L57: =SUM(L25:L56) -> 110813 | M57: =SUM(M25:M56) -> 12893 | N57: =SUM(N25:N56) -> 0 | O57: =SUM(O25:O56) -> 87458 | P57: =SUM(P25:P56) -> 32284 | Q57: =SUM(Q25:Q56) -> 26072 | R57: =SUM(R25:R56) -> 48260.58 | S57: =IF(AND(I57<>"",I57<>0),G57/I57,"") -> 0.078848561 | T57: =D57/U57 -> 0.7155404 | U57: =SUM(U25:U56) -> 1091133.4 | V57: =SUM(V25:V55) -> 156.99761 | W57: =SUM(W25:W55) -> 86.26242 | X57: =SUM(X25:X56) -> 538467 | Y57: =SUM(Y25:Y55) -> 78 | Z57: =SUM(Z25:Z55) -> 50

Sheet Самошкина
B1: =TODAY()-1 -> 46171
B2: (отчетная дата) | J2: ЕЖЕДНЕВНЫЙ ОТЧЕТ О ПРОДАЖАХ
B3: Осталось до выполнения плана!!! | J3: =График!B26 -> Самошкина Алина
C4: =L8-D50 -> 459424.57 | E4: =IF(L8<>0,C4/L8,0) -> 1
I6: Целевые показатели
I7: Показатель | L7: План | M7: Факт | N7: % выполнения | O7: Прогноз выполнения | P7: % выполнения по прогнозу | Q7: Отклонение | R7: Факт аналогичного месяца прошлого года | S7: Отклонение LFL
I8: Выручка | L8: ='Ялта, Ленина, 18'!I8/График!AJ29*График!AJ26 -> 459424.57 | M8: =D57 -> 187359 | N8: =IF(AND(L8<>"",L8<>0,M8<>""),M8/L8,"") -> 0.40781232 | O8: =IF(SUMIF($D$25:$D$56,">=0",$U$25:$U$56)<>0,L8*D57/SUMIF($D$25:$D$56,">=0",$U$25:$U$56),0) -> 374718 | P8: =IF(AND(L8<>"",L8<>0,O8<>"",O8<>0),O8/L8,"") -> 0.81562464 | Q8: =IF(AND(M8<>0,M8<>"",L8<>0,L8<>""),O8-L8,"") -> -84706.571 | S8: =IF(AND(R8<>"",R8<>0,O8<>"",O8<>0),-R8+O8,"") | T8: =IF(AND(S8<>"",S8<>0,R8<>0,R8<>""),S8/R8,"")
I9: Кол-во изделий | L9: =L8/L11 -> 66.104255 | M9: =E57 -> 33 | N9: =IF(AND(L9<>"",L9<>0,M9<>""),M9/L9,"") -> 0.49921144 | O9: =IF(SUMIF($E$25:$E$54,">=0",$V$25:$V$54)<>0,L9*E57/SUMIF($E$25:$E$54,">=0",$V$25:$V$54),0) -> 66 | P9: =IF(AND(L9<>"",L9<>0,O9<>"",O9<>0),O9/L9,"") -> 0.99842287 | Q9: =IF(AND(M9<>0,M9<>"",L9<>0,L9<>""),O9-L9,"") -> -0.10425478 | R9: =R8/R11 -> #DIV/0! | S9: =IF(AND(R9<>"",R9<>0,O9<>"",O9<>0),-R9+O9,"") -> #DIV/0! | T9: =IF(AND(S9<>"",S9<>0,R9<>0,R9<>""),S9/R9,"") -> #DIV/0!
I10: Средний чек | L10: =L11*L12 -> 12649 | M10: =H57 -> 11021.118 | N10: =IF(AND(L10<>"",L10<>0,M10<>""),M10/L10,"") -> 0.87130347 | O10: =M10 -> 11021.118 | P10: =IF(AND(L10<>"",L10<>0,O10<>"",O10<>0),O10/L10,"") -> 0.87130347 | Q10: =IF(AND(M10<>0,M10<>"",L10<>0,L10<>""),O10-L10,"") -> -1627.8824 | R10: =R11*R12 -> 0 | S10: =IF(AND(R10<>"",R10<>0,O10<>"",O10<>0),-R10+O10,"") | T10: =IF(AND(S10<>"",S10<>0,R10<>0,R10<>""),S10/R10,"")
I11: Средняя стоимость изделия | L11: ='Ялта, Ленина, 18'!I11 -> 6950 | M11: =F57 -> 5677.5455 | N11: =IF(AND(L11<>"",L11<>0,M11<>""),M11/L11,"") -> 0.81691302 | O11: =IF(O9>0,O8/O9,"") -> 5677.5455 | P11: =IF(AND(L11<>"",L11<>0,O11<>"",O11<>0),O11/L11,"") -> 0.81691302 | Q11: =IF(AND(M11<>0,M11<>"",L11<>0,L11<>""),O11-L11,"") -> -1272.4545 | S11: =IF(AND(R11<>"",R11<>0,O11<>"",O11<>0),-R11+O11,"") | T11: =IF(AND(S11<>"",S11<>0,R11<>0,R11<>""),S11/R11,"")
I12: Длина чека | L12: ='Ялта, Ленина, 18'!I12 -> 1.82 | M12: =J57 -> 1.9411765 | N12: =IF(AND(L12<>"",L12<>0,M12<>""),M12/L12,"") -> 1.0665805 | O12: =M12 -> 1.9411765 | P12: =IF(AND(L12<>"",L12<>0,O12<>"",O12<>0),O12/L12,"") -> 1.0665805 | Q12: =IF(AND(M12<>0,M12<>"",L12<>0,L12<>""),O12-L12,"") -> 0.12117647 | S12: =IF(AND(R12<>"",R12<>0,O12<>"",O12<>0),-R12+O12,"") | T12: =IF(AND(S12<>"",S12<>0,R12<>0,R12<>""),S12/R12,"") | W12: =U12-V12 -> 0
I13: Кол-во чеков | L13: =IF(L12<>0,L9/L12,"") -> 36.321019 | M13: =G57 -> 17 | N13: =IF(AND(L13<>"",L13<>0,M13<>""),M13/L13,"") -> 0.46804854 | O13: =IF(SUMIF($G$25:$G$54,">=0",$W$25:$W$54)<>0,L13*G57/SUMIF($G$25:$G$54,">=0",$W$25:$W$54),"") -> 34 | P13: =IF(AND(L13<>"",L13<>0,O13<>"",O13<>0),O13/L13,"") -> 0.93609708 | Q13: =IF(AND(M13<>0,M13<>"",L13<>0,L13<>""),O13-L13,"") -> -2.3210191 | S13: =IF(AND(R13<>"",R13<>0,O13<>"",O13<>0),-R13+O13,"") | T13: =IF(AND(S13<>"",S13<>0,R13<>0,R13<>""),S13/R13,"")
I14: Кол-во смен план/отработано | L14: =График!AI26 -> 8 | M14: 8 | N14: =IF(AND(L14<>"",L14<>0,M14<>""),M14/L14,"") -> 1 | O14: =L14 -> 8 | P14: =IF(AND(L14<>"",L14<>0,O14<>"",O14<>0),O14/L14,"") -> 1 | Q14: =IF(AND(M14<>0,M14<>"",L14<>0,L14<>""),O14-L14,"") -> 0 | S14: =IF(AND(R14<>"",R14<>0,O14<>"",O14<>0),-R14+O14,"") | T14: =IF(AND(S14<>"",S14<>0,R14<>0,R14<>""),S14/R14,"")
I15: Средние продажи в смену | L15: ='Ялта, Ленина, 18'!I15 -> 81965.52 | M15: =M8/M14 -> 23419.875 | N15: =IF(AND(L15<>"",L15<>0,M15<>""),M15/L15,"") -> 0.28572838 | O15: =M15 -> 23419.875 | P15: =IF(AND(L15<>"",L15<>0,O15<>"",O15<>0),O15/L15,"") -> 0.28572838 | Q15: =IF(AND(M15<>0,M15<>"",L15<>0,L15<>""),O15-L15,"") -> -58545.645 | S15: =IF(AND(R15<>"",R15<>0,O15<>"",O15<>0),-R15+O15,"") | T15: =IF(AND(S15<>"",S15<>0,R15<>0,R15<>""),S15/R15,"")
I16: Отставание/Перевыполнение | M16: =M8-L15*M14 -> -468365.16 | N16: =IF(AND(L16<>"",L16<>0,M16<>""),M16/L16,"") | O16: =M16 -> -468365.16 | P16: =IF(AND(L16<>"",L16<>0,O16<>"",O16<>0),O16/L16,"") | Q16: =IF(AND(M16<>0,M16<>"",L16<>0,L16<>""),O16-L16,"") | S16: =IF(AND(R16<>"",R16<>0,O16<>"",O16<>0),-R16+O16,"") | T16: =IF(AND(S16<>"",S16<>0,R16<>0,R16<>""),S16/R16,"")
I17: Трафик | L17: ='Ялта, Ленина, 18'!I17/График!AJ29*График!AJ26 -> 336.30573 | M17: =I57 -> 278 | N17: =IF(AND(L17<>"",L17<>0,M17<>""),M17/L17,"") -> 0.82662879 | O17: =M17/M14*L14 -> 278 | P17: =IF(AND(L17<>"",L17<>0,O17<>"",O17<>0),O17/L17,"") -> 0.82662879 | Q17: =IF(AND(M17<>0,M17<>"",L17<>0,L17<>""),O17-L17,"") -> -58.305732 | S17: =IF(AND(R17<>"",R17<>0,O17<>"",O17<>0),-R17+O17,"") | T17: =IF(AND(S17<>"",S17<>0,R17<>0,R17<>""),S17/R17,"")
I18: Выручка на вошедшего | L18: =L8/L17 -> 1366.092 | M18: =M8/M17 -> 673.95324 | N18: =IF(AND(L18<>"", L18<>0, M18<>""), M18/L18, "") -> 0.49334396 | O18: =M18 -> 673.95324 | P18: =IF(AND(L18<>"", L18<>0, O18<>"", O18<>0), O18/L18, "") -> 0.49334396 | Q18: =IF(AND(M18<>0, M18<>"", L18<>0, L18<>""), O18-L18, "") -> -692.13876 | R18: 0 | S18: =IF(AND(R18<>"",R18<>0,O18<>"",O18<>0),-R18+O18,"") | T18: =IF(AND(S18<>"",S18<>0,R18<>0,R18<>""),S18/R18,"")
N19: =IF(AND(L19<>"",L19<>0,M19<>""),M19/L19,"") | O19: =M19 -> 0 | P19: =IF(AND(L19<>"",L19<>0,O19<>"",O19<>0),O19/L19,"") | Q19: =IF(AND(M19<>0,M19<>"",L19<>0,L19<>""),O19-L19,"") | R19: 0 | S19: =IF(AND(R19<>"",R19<>0,O19<>"",O19<>0),-R19+O19,"") | T19: =IF(AND(S19<>"",S19<>0,R19<>0,R19<>""),S19/R19,"")
I20: Конверсия план/факт | L20: ='Ялта, Ленина, 18'!I20 -> 0.108 | M20: =S57 -> 0.061151079 | N20: =M20/L20 -> 0.5662137 | O20: =IF(AND(N8<>0,L14<>0,I57<>0),(I57*S57+(I57/N8-I57)*L20)/(I57/N8),0) -> 0.088894433 | P20: =IF(AND(L20<>"",L20<>0,O20<>"",O20<>0),O20/L20,"") -> 0.8230966 | Q20: =IF(AND(M20<>0,M20<>"",L20<>0,L20<>""),O20-L20,"") -> -0.019105567 | S20: =IF(AND(R20<>"",R20<>0,O20<>"",O20<>0),-R20+O20,"") | T20: =IF(AND(S20<>"",S20<>0,R20<>0,R20<>""),S20/R20,"")
B22: Факт продаж за месяц | T22: % выполнения дневного плана | U22: Раcпределение плана по дням
B23: Дата | C23: День недели | D23: Выручка (руб) | E23: Кол-во единиц (шт.) | F23: Средняя стоимость изделия (руб.) | G23: Количество чеков (шт.) | H23: Средняя сумма чека (руб.) | I23: Трафик | J23: Длина чека (шт.) | K23: UNOde50 | L23: IS | M23: Agafi | N23: Kalliope | O23: Raganella | P23: CC/MP | Q23: Antura | R23: SALE | S23: Конверсия (%) | U23: выручка, план | V23: кол-во ед, план | W23: Кол-во чеков, план | X23: выручка, скорректир.план | Y23: кол-во ед, скорр. план | Z23: кол-во чеков, скорр. план | AA23: Коэфф. Дня Недели | AB23: Специфика месяца
B24: 1 | C24: 2 | D24: 3 | E24: в | F24: 5 | G24: 6 | H24: 7 | I24: 8 | J24: 9 | K24: 10 | L24: 11 | M24: 12 | N24: 13 | P24: 14 | Q24: 15 | R24: 16 | S24: 17 | U24: 1 | V24: 2 | W24: 3 | X24: 4 | Y24: 5 | Z24: 6 | AA24: 10 | AB24: 11
A25: 1 | B25: 46115 | C25: пт | D25: 20964 | E25: 5 | F25: =IF(AND(E25<>"",E25<>0),D25/E25,"") -> 4192.8 | G25: 2 | H25: =IF(AND(G25<>"",G25<>0),D25/G25,"") -> 10482 | I25: 33 | J25: =IF(AND(G25<>"",G25<>0),E25/G25,"") -> 2.5 | R25: 3795 | S25: =IF(AND(I25<>"",I25<>0),G25/I25,"") -> 0.060606061 | T25: =D25/U25 -> 0.73009591 | U25: =$L$8*AA25*AB25/SUMPRODUCT($AB$25:$AB$56,$AA$25:$AA$56) -> 28714.036 | V25: =$L$9*AA25*AB25/SUMPRODUCT($AB$25:$AB$56,$AA$25:$AA$56) -> 4.1315159 | W25: =IF($L$12="","",V25/$L$12) -> 2.2700637 | X25: =IF(D25<>"",D25,U25) -> 20964 | Y25: =IF(E25<>"",E25,V25) -> 5 | Z25: =IF(G25<>"",G25,W25) -> 2 | AA25: 1 | AB25: 1
A26: 2 | B26: 46116 | C26: сб | D26: 10384 | E26: 2 | F26: =IF(AND(E26<>"",E26<>0),D26/E26,"") -> 5192 | G26: 1 | H26: =IF(AND(G26<>"",G26<>0),D26/G26,"") -> 10384 | I26: 30 | J26: =IF(AND(G26<>"",G26<>0),E26/G26,"") -> 2 | S26: =IF(AND(I26<>"",I26<>0),G26/I26,"") -> 0.033333333 | T26: =D26/U26 -> 0.36163499 | U26: =$L$8*AA26*AB26/SUMPRODUCT($AB$25:$AB$56,$AA$25:$AA$56) -> 28714.036 | V26: =$L$9*AA26*AB26/SUMPRODUCT($AB$25:$AB$58,$AA$25:$AA$58) -> 4.1315159 | W26: =IF($L$12="","",V26/$L$12) -> 2.2700637 | X26: =IF(AB26<>"",IF(D26<>"",D26,($L$8-SUM($X$25:X25))*AA26*AB26/SUMPRODUCT($AB26:$AB$56,$AA26:$AA$56)),"") -> 10384 | Y26: =IF(AB26<>"",IF(E26<>"",E26,($L$9-SUM($Y$25:Y25))*AA26*AB26/SUMPRODUCT($AB26:$AB$58,$AA26:$AA$58)),"") -> 2 | Z26: =IF(AB26<>"",IF($L$12<>"",IF(G26<>"",G26,($L$9/$L$12-SUM($Z$25:Z25))*AA26*AB26/SUMPRODUCT($AB26:$AB$58,$AA26:$AA$58)),""),"") -> 1 | AA26: 1 | AB26: 1
A27: 3 | B27: 46119 | C27: вт | D27: 10534 | E27: 2 | F27: 5267 | G27: 1 | H27: 10534 | I27: 30 | J27: =IF(AND(G27<>"",G27<>0),E27/G27,"") -> 2 | S27: =IF(AND(I27<>"",I27<>0),G27/I27,"") -> 0.033333333 | T27: =I27/U27 -> 0.0010447852 | U27: =$L$8*AA27*AB27/SUMPRODUCT($AB$25:$AB$56,$AA$25:$AA$56) -> 28714.036 | V27: =$L$9*AA27*AB27/SUMPRODUCT($AB$25:$AB$58,$AA$25:$AA$58) -> 4.1315159 | W27: =IF($L$12="","",V27/$L$12) -> 2.2700637 | X27: =IF(AB27<>"",IF(D27<>"",D27,($L$8-SUM($X$25:X26))*AA27*AB27/SUMPRODUCT($AB27:$AB$58,$AA27:$AA$58)),"") -> 10534 | Y27: =IF(AB27<>"",IF(E27<>"",E27,($L$9-SUM($Y$25:Y26))*AA27*AB27/SUMPRODUCT($AB27:$AB$58,$AA27:$AA$58)),"") -> 2 | Z27: =IF(AB27<>"",IF($L$12<>"",IF(G27<>"",G27,($L$9/$L$12-SUM($Z$25:Z26))*AA27*AB27/SUMPRODUCT($AB27:$AB$58,$AA27:$AA$58)),""),"") -> 1 | AA27: 1 | AB27: 1
A28: 4 | B28: 46120 | C28: ср | D28: 47300 | E28: 8 | F28: 5912 | G28: 6 | H28: 7883 | I28: 52 | J28: =IF(AND(G28<>"",G28<>0),E28/G28,"") -> 1.3333333 | R28: 3514 | S28: =IF(AND(I28<>"",I28<>0),G28/I28,"") -> 0.11538462 | T28: =I28/U28 -> 0.001810961 | U28: =$L$8*AA28*AB28/SUMPRODUCT($AB$25:$AB$56,$AA$25:$AA$56) -> 28714.036 | V28: =$L$9*AA28*AB28/SUMPRODUCT($AB$25:$AB$58,$AA$25:$AA$58) -> 4.1315159 | W28: =IF($L$12="","",V28/$L$12) -> 2.2700637 | X28: =IF(AB28<>"",IF(D28<>"",D28,($L$8-SUM($X$25:X27))*AA28*AB28/SUMPRODUCT($AB28:$AB$58,$AA28:$AA$58)),"") -> 47300 | Y28: =IF(AB28<>"",IF(E28<>"",E28,($L$9-SUM($Y$25:Y27))*AA28*AB28/SUMPRODUCT($AB28:$AB$58,$AA28:$AA$58)),"") -> 8 | Z28: =IF(AB28<>"",IF($L$12<>"",IF(G28<>"",G28,($L$9/$L$12-SUM($Z$25:Z27))*AA28*AB28/SUMPRODUCT($AB28:$AB$58,$AA28:$AA$58)),""),"") -> 6 | AA28: 1 | AB28: 1
A29: 5 | B29: 46123 | C29: сб | D29: 39843 | E29: 7 | F29: =IF(AND(E29<>"",E29<>0),D29/E29,"") -> 5691.8571 | G29: 2 | H29: =IF(AND(G29<>"",G29<>0),D29/G29,"") -> 19921.5 | I29: 29 | J29: =IF(AND(G29<>"",G29<>0),E29/G29,"") -> 3.5 | P29: 11893 | R29: 7980 | S29: =IF(AND(I29<>"",I29<>0),G29/I29,"") -> 0.068965517 | T29: =I29/U29 -> 0.001009959 | U29: =$L$8*AA29*AB29/SUMPRODUCT($AB$25:$AB$56,$AA$25:$AA$56) -> 28714.036 | V29: =$L$9*AA29*AB29/SUMPRODUCT($AB$25:$AB$58,$AA$25:$AA$58) -> 4.1315159 | W29: =IF($L$12="","",V29/$L$12) -> 2.2700637 | X29: =IF(AB29<>"",IF(D29<>"",D29,($L$8-SUM($X$25:X28))*AA29*AB29/SUMPRODUCT($AB29:$AB$58,$AA29:$AA$58)),"") -> 39843 | Y29: =IF(AB29<>"",IF(E29<>"",E29,($L$9-SUM($Y$25:Y28))*AA29*AB29/SUMPRODUCT($AB29:$AB$58,$AA29:$AA$58)),"") -> 7 | Z29: =IF(AB29<>"",IF($L$12<>"",IF(G29<>"",G29,($L$9/$L$12-SUM($Z$25:Z28))*AA29*AB29/SUMPRODUCT($AB29:$AB$58,$AA29:$AA$58)),""),"") -> 2 | AA29: 1 | AB29: 1
A30: 6 | B30: 46124 | C30: вс | D30: 0 | E30: 0 | F30: 0 | G30: 0 | H30: 0 | I30: 36 | J30: =IF(AND(G30<>"",G30<>0),E30/G30,"") | S30: =IF(AND(I30<>"",I30<>0),G30/I30,"") -> 0 | T30: =I30/U30 -> 0.0012537423 | U30: =$L$8*AA30*AB30/SUMPRODUCT($AB$25:$AB$56,$AA$25:$AA$56) -> 28714.036 | V30: =$L$9*AA30*AB30/SUMPRODUCT($AB$25:$AB$58,$AA$25:$AA$58) -> 4.1315159 | W30: =IF($L$12="","",V30/$L$12) -> 2.2700637 | X30: =IF(AB30<>"",IF(D30<>"",D30,($L$8-SUM($X$25:X29))*AA30*AB30/SUMPRODUCT($AB30:$AB$58,$AA30:$AA$58)),"") -> 0 | Y30: =IF(AB30<>"",IF(E30<>"",E30,($L$9-SUM($Y$25:Y29))*AA30*AB30/SUMPRODUCT($AB30:$AB$58,$AA30:$AA$58)),"") -> 0 | Z30: =IF(AB30<>"",IF($L$12<>"",IF(G30<>"",G30,($L$9/$L$12-SUM($Z$25:Z29))*AA30*AB30/SUMPRODUCT($AB30:$AB$58,$AA30:$AA$58)),""),"") -> 0 | AA30: 1 | AB30: 1
A31: 7 | B31: 46127 | C31: ср | D31: 26568 | E31: 5 | F31: =IF(AND(E31<>"",E31<>0),D31/E31,"") -> 5313.6 | G31: 4 | H31: =IF(AND(G31<>"",G31<>0),D31/G31,"") -> 6642 | I31: 40 | J31: =IF(AND(G31<>"",G31<>0),E31/G31,"") -> 1.25 | R31: 2095 | S31: =IF(AND(I31<>"",I31<>0),G31/I31,"") -> 0.1 | T31: =I31/U31 -> 0.001393047 | U31: =$L$8*AA31*AB31/SUMPRODUCT($AB$25:$AB$56,$AA$25:$AA$56) -> 28714.036 | V31: =$L$9*AA31*AB31/SUMPRODUCT($AB$25:$AB$58,$AA$25:$AA$58) -> 4.1315159 | W31: =IF($L$12="","",V31/$L$12) -> 2.2700637 | X31: =IF(AB31<>"",IF(D31<>"",D31,($L$8-SUM($X$25:X30))*AA31*AB31/SUMPRODUCT($AB31:$AB$58,$AA31:$AA$58)),"") -> 26568 | Y31: =IF(AB31<>"",IF(E31<>"",E31,($L$9-SUM($Y$25:Y30))*AA31*AB31/SUMPRODUCT($AB31:$AB$58,$AA31:$AA$58)),"") -> 5 | Z31: =IF(AB31<>"",IF($L$12<>"",IF(G31<>"",G31,($L$9/$L$12-SUM($Z$25:Z30))*AA31*AB31/SUMPRODUCT($AB31:$AB$58,$AA31:$AA$58)),""),"") -> 4 | AA31: 1 | AB31: 1
A32: 8 | B32: 46128 | C32: чт | D32: 31766 | E32: 4 | F32: =IF(AND(E32<>"",E32<>0),D32/E32,"") -> 7941.5 | G32: 1 | H32: =IF(AND(G32<>"",G32<>0),D32/G32,"") -> 31766 | I32: 28 | J32: =IF(AND(G32<>"",G32<>0),E32/G32,"") -> 4 | Q32: 21880 | R32: 5890 | S32: =IF(AND(I32<>"",I32<>0),G32/I32,"") -> 0.035714286 | T32: =I32/U32 -> 0.00097513287 | U32: =$L$8*AA32*AB32/SUMPRODUCT($AB$25:$AB$56,$AA$25:$AA$56) -> 28714.036 | V32: =$L$9*AA32*AB32/SUMPRODUCT($AB$25:$AB$58,$AA$25:$AA$58) -> 4.1315159 | W32: =IF($L$12="","",V32/$L$12) -> 2.2700637 | X32: =IF(AB32<>"",IF(D32<>"",D32,($L$8-SUM($X$25:X31))*AA32*AB32/SUMPRODUCT($AB32:$AB$58,$AA32:$AA$58)),"") -> 31766 | Y32: =IF(AB32<>"",IF(E32<>"",E32,($L$9-SUM($Y$25:Y31))*AA32*AB32/SUMPRODUCT($AB32:$AB$58,$AA32:$AA$58)),"") -> 4 | Z32: =IF(AB32<>"",IF($L$12<>"",IF(G32<>"",G32,($L$9/$L$12-SUM($Z$25:Z31))*AA32*AB32/SUMPRODUCT($AB32:$AB$58,$AA32:$AA$58)),""),"") -> 1 | AA32: 1 | AB32: 1
F33: =IF(AND(E33<>"",E33<>0),D33/E33,"") | H33: =IF(AND(G33<>"",G33<>0),D33/G33,"") | J33: =IF(AND(G33<>"",G33<>0),E33/G33,"") | S33: =IF(AND(I33<>"",I33<>0),G33/I33,"") | T33: =I33/U33 -> 0 | U33: =$L$8*AA33*AB33/SUMPRODUCT($AB$25:$AB$56,$AA$25:$AA$56) -> 28714.036 | V33: =$L$9*AA33*AB33/SUMPRODUCT($AB$25:$AB$58,$AA$25:$AA$58) -> 4.1315159 | W33: =IF($L$12="","",V33/$L$12) -> 2.2700637 | X33: =IF(AB33<>"",IF(D33<>"",D33,($L$8-SUM($X$25:X32))*AA33*AB33/SUMPRODUCT($AB33:$AB$58,$AA33:$AA$58)),"") -> 34008.196 | Y33: =IF(AB33<>"",IF(E33<>"",E33,($L$9-SUM($Y$25:Y32))*AA33*AB33/SUMPRODUCT($AB33:$AB$58,$AA33:$AA$58)),"") -> 4.1380318 | Z33: =IF(AB33<>"",IF($L$12<>"",IF(G33<>"",G33,($L$9/$L$12-SUM($Z$25:Z32))*AA33*AB33/SUMPRODUCT($AB33:$AB$58,$AA33:$AA$58)),""),"") -> 2.4151274 | AA33: 1 | AB33: 1
F34: =IF(AND(E34<>"",E34<>0),D34/E34,"") | H34: =IF(AND(G34<>"",G34<>0),D34/G34,"") | J34: =IF(AND(G34<>"",G34<>0),E34/G34,"") | S34: =IF(AND(I34<>"",I34<>0),G34/I34,"") | T34: =I34/U34 -> 0 | U34: =$L$8*AA34*AB34/SUMPRODUCT($AB$25:$AB$56,$AA$25:$AA$56) -> 28714.036 | V34: =$L$9*AA34*AB34/SUMPRODUCT($AB$25:$AB$58,$AA$25:$AA$58) -> 4.1315159 | W34: =IF($L$12="","",V34/$L$12) -> 2.2700637 | X34: =IF(AB34<>"",IF(D34<>"",D34,($L$8-SUM($X$25:X33))*AA34*AB34/SUMPRODUCT($AB34:$AB$58,$AA34:$AA$58)),"") -> 34008.196 | Y34: =IF(AB34<>"",IF(E34<>"",E34,($L$9-SUM($Y$25:Y33))*AA34*AB34/SUMPRODUCT($AB34:$AB$58,$AA34:$AA$58)),"") -> 4.1380318 | Z34: =IF(AB34<>"",IF($L$12<>"",IF(G34<>"",G34,($L$9/$L$12-SUM($Z$25:Z33))*AA34*AB34/SUMPRODUCT($AB34:$AB$58,$AA34:$AA$58)),""),"") -> 2.4151274 | AA34: 1 | AB34: 1
F35: =IF(AND(E35<>"",E35<>0),D35/E35,"") | H35: =IF(AND(G35<>"",G35<>0),D35/G35,"") | J35: =IF(AND(G35<>"",G35<>0),E35/G35,"") | S35: =IF(AND(I35<>"",I35<>0),G35/I35,"") | T35: =I35/U35 -> 0 | U35: =$L$8*AA35*AB35/SUMPRODUCT($AB$25:$AB$56,$AA$25:$AA$56) -> 28714.036 | V35: =$L$9*AA35*AB35/SUMPRODUCT($AB$25:$AB$58,$AA$25:$AA$58) -> 4.1315159 | W35: =IF($L$12="","",V35/$L$12) -> 2.2700637 | X35: =IF(AB35<>"",IF(D35<>"",D35,($L$8-SUM($X$25:X34))*AA35*AB35/SUMPRODUCT($AB35:$AB$58,$AA35:$AA$58)),"") -> 34008.196 | Y35: =IF(AB35<>"",IF(E35<>"",E35,($L$9-SUM($Y$25:Y34))*AA35*AB35/SUMPRODUCT($AB35:$AB$58,$AA35:$AA$58)),"") -> 4.1380318 | Z35: =IF(AB35<>"",IF($L$12<>"",IF(G35<>"",G35,($L$9/$L$12-SUM($Z$25:Z34))*AA35*AB35/SUMPRODUCT($AB35:$AB$58,$AA35:$AA$58)),""),"") -> 2.4151274 | AA35: 1 | AB35: 1
F36: =IF(AND(E36<>"",E36<>0),D36/E36,"") | H36: =IF(AND(G36<>"",G36<>0),D36/G36,"") | J36: =IF(AND(G36<>"",G36<>0),E36/G36,"") | S36: =IF(AND(I36<>"",I36<>0),G36/I36,"") | T36: =I36/U36 -> 0 | U36: =$L$8*AA36*AB36/SUMPRODUCT($AB$25:$AB$56,$AA$25:$AA$56) -> 28714.036 | V36: =$L$9*AA36*AB36/SUMPRODUCT($AB$25:$AB$58,$AA$25:$AA$58) -> 4.1315159 | W36: =IF($L$12="","",V36/$L$12) -> 2.2700637 | X36: =IF(AB36<>"",IF(D36<>"",D36,($L$8-SUM($X$25:X35))*AA36*AB36/SUMPRODUCT($AB36:$AB$58,$AA36:$AA$58)),"") -> 34008.196 | Y36: =IF(AB36<>"",IF(E36<>"",E36,($L$9-SUM($Y$25:Y35))*AA36*AB36/SUMPRODUCT($AB36:$AB$58,$AA36:$AA$58)),"") -> 4.1380318 | Z36: =IF(AB36<>"",IF($L$12<>"",IF(G36<>"",G36,($L$9/$L$12-SUM($Z$25:Z35))*AA36*AB36/SUMPRODUCT($AB36:$AB$58,$AA36:$AA$58)),""),"") -> 2.4151274 | AA36: 1 | AB36: 1
F37: =IF(AND(E37<>"",E37<>0),D37/E37,"") | H37: =IF(AND(G37<>"",G37<>0),D37/G37,"") | J37: =IF(AND(G37<>"",G37<>0),E37/G37,"") | S37: =IF(AND(I37<>"",I37<>0),G37/I37,"") | T37: =I37/U37 -> 0 | U37: =$L$8*AA37*AB37/SUMPRODUCT($AB$25:$AB$56,$AA$25:$AA$56) -> 28714.036 | V37: =$L$9*AA37*AB37/SUMPRODUCT($AB$25:$AB$58,$AA$25:$AA$58) -> 4.1315159 | W37: =IF($L$12="","",V37/$L$12) -> 2.2700637 | X37: =IF(AB37<>"",IF(D37<>"",D37,($L$8-SUM($X$25:X36))*AA37*AB37/SUMPRODUCT($AB37:$AB$58,$AA37:$AA$58)),"") -> 34008.196 | Y37: =IF(AB37<>"",IF(E37<>"",E37,($L$9-SUM($Y$25:Y36))*AA37*AB37/SUMPRODUCT($AB37:$AB$58,$AA37:$AA$58)),"") -> 4.1380318 | Z37: =IF(AB37<>"",IF($L$12<>"",IF(G37<>"",G37,($L$9/$L$12-SUM($Z$25:Z36))*AA37*AB37/SUMPRODUCT($AB37:$AB$58,$AA37:$AA$58)),""),"") -> 2.4151274 | AA37: 1 | AB37: 1
F38: =IF(AND(E38<>"",E38<>0),D38/E38,"") | H38: =IF(AND(G38<>"",G38<>0),D38/G38,"") | J38: =IF(AND(G38<>"",G38<>0),E38/G38,"") | S38: =IF(AND(I38<>"",I38<>0),G38/I38,"") | T38: =I38/U38 -> 0 | U38: =$L$8*AA38*AB38/SUMPRODUCT($AB$25:$AB$56,$AA$25:$AA$56) -> 28714.036 | V38: =$L$9*AA38*AB38/SUMPRODUCT($AB$25:$AB$58,$AA$25:$AA$58) -> 4.1315159 | W38: =IF($L$12="","",V38/$L$12) -> 2.2700637 | X38: =IF(AB38<>"",IF(D38<>"",D38,($L$8-SUM($X$25:X37))*AA38*AB38/SUMPRODUCT($AB38:$AB$58,$AA38:$AA$58)),"") -> 34008.196 | Y38: =IF(AB38<>"",IF(E38<>"",E38,($L$9-SUM($Y$25:Y37))*AA38*AB38/SUMPRODUCT($AB38:$AB$58,$AA38:$AA$58)),"") -> 4.1380318 | Z38: =IF(AB38<>"",IF($L$12<>"",IF(G38<>"",G38,($L$9/$L$12-SUM($Z$25:Z37))*AA38*AB38/SUMPRODUCT($AB38:$AB$58,$AA38:$AA$58)),""),"") -> 2.4151274 | AA38: 1 | AB38: 1
F39: =IF(AND(E39<>"",E39<>0),D39/E39,"") | H39: =IF(AND(G39<>"",G39<>0),D39/G39,"") | J39: =IF(AND(G39<>"",G39<>0),E39/G39,"") | S39: =IF(AND(I39<>"",I39<>0),G39/I39,"") | T39: =I39/U39 -> 0 | U39: =$L$8*AA39*AB39/SUMPRODUCT($AB$25:$AB$56,$AA$25:$AA$56) -> 28714.036 | V39: =$L$9*AA39*AB39/SUMPRODUCT($AB$25:$AB$58,$AA$25:$AA$58) -> 4.1315159 | W39: =IF($L$12="","",V39/$L$12) -> 2.2700637 | X39: =IF(AB39<>"",IF(D39<>"",D39,($L$8-SUM($X$25:X38))*AA39*AB39/SUMPRODUCT($AB39:$AB$58,$AA39:$AA$58)),"") -> 34008.196 | Y39: =IF(AB39<>"",IF(E39<>"",E39,($L$9-SUM($Y$25:Y38))*AA39*AB39/SUMPRODUCT($AB39:$AB$58,$AA39:$AA$58)),"") -> 4.1380318 | Z39: =IF(AB39<>"",IF($L$12<>"",IF(G39<>"",G39,($L$9/$L$12-SUM($Z$25:Z38))*AA39*AB39/SUMPRODUCT($AB39:$AB$58,$AA39:$AA$58)),""),"") -> 2.4151274 | AA39: 1 | AB39: 1
F40: =IF(AND(E40<>"",E40<>0),D40/E40,"") | H40: =IF(AND(G40<>"",G40<>0),D40/G40,"") | J40: =IF(AND(G40<>"",G40<>0),E40/G40,"") | S40: =IF(AND(I40<>"",I40<>0),G40/I40,"") | T40: =I40/U40 -> 0 | U40: =$L$8*AA40*AB40/SUMPRODUCT($AB$25:$AB$56,$AA$25:$AA$56) -> 28714.036 | V40: =$L$9*AA40*AB40/SUMPRODUCT($AB$25:$AB$58,$AA$25:$AA$58) -> 4.1315159 | W40: =IF($L$12="","",V40/$L$12) -> 2.2700637 | X40: =IF(AB40<>"",IF(D40<>"",D40,($L$8-SUM($X$25:X39))*AA40*AB40/SUMPRODUCT($AB40:$AB$58,$AA40:$AA$58)),"") -> 34008.196 | Y40: =IF(AB40<>"",IF(E40<>"",E40,($L$9-SUM($Y$25:Y39))*AA40*AB40/SUMPRODUCT($AB40:$AB$58,$AA40:$AA$58)),"") -> 4.1380318 | Z40: =IF(AB40<>"",IF($L$12<>"",IF(G40<>"",G40,($L$9/$L$12-SUM($Z$25:Z39))*AA40*AB40/SUMPRODUCT($AB40:$AB$58,$AA40:$AA$58)),""),"") -> 2.4151274 | AA40: 1 | AB40: 1
F41: =IF(AND(E41<>"",E41<>0),D41/E41,"") | H41: =IF(AND(G41<>"",G41<>0),D41/G41,"") | J41: =IF(AND(G41<>"",G41<>0),E41/G41,"") | S41: =IF(AND(I41<>"",I41<>0),G41/I41,"") | T41: =I41/U41 -> #DIV/0! | U41: =$L$8*AA41*AB41/SUMPRODUCT($AB$25:$AB$56,$AA$25:$AA$56) -> 0 | V41: =$L$9*AA41*AB41/SUMPRODUCT($AB$25:$AB$58,$AA$25:$AA$58) -> 0 | W41: =IF($L$12="","",V41/$L$12) -> 0 | X41: =IF(AB41<>"",IF(D41<>"",D41,($L$8-SUM($X$25:X40))*AA41*AB41/SUMPRODUCT($AB41:$AB$58,$AA41:$AA$58)),"") | Y41: =IF(AB41<>"",IF(E41<>"",E41,($L$9-SUM($Y$25:Y40))*AA41*AB41/SUMPRODUCT($AB41:$AB$58,$AA41:$AA$58)),"") | Z41: =IF(AB41<>"",IF($L$12<>"",IF(G41<>"",G41,($L$9/$L$12-SUM($Z$25:Z40))*AA41*AB41/SUMPRODUCT($AB41:$AB$58,$AA41:$AA$58)),""),"")
F42: =IF(AND(E42<>"",E42<>0),D42/E42,"") | H42: =IF(AND(G42<>"",G42<>0),D42/G42,"") | J42: =IF(AND(G42<>"",G42<>0),E42/G42,"") | S42: =IF(AND(I42<>"",I42<>0),G42/I42,"") | T42: =I42/U42 -> #DIV/0! | U42: =$L$8*AA42*AB42/SUMPRODUCT($AB$25:$AB$56,$AA$25:$AA$56) -> 0 | V42: =$L$9*AA42*AB42/SUMPRODUCT($AB$25:$AB$58,$AA$25:$AA$58) -> 0 | W42: =IF($L$12="","",V42/$L$12) -> 0 | X42: =IF(AB42<>"",IF(D42<>"",D42,($L$8-SUM($X$25:X41))*AA42*AB42/SUMPRODUCT($AB42:$AB$58,$AA42:$AA$58)),"") | Y42: =IF(AB42<>"",IF(E42<>"",E42,($L$9-SUM($Y$25:Y41))*AA42*AB42/SUMPRODUCT($AB42:$AB$58,$AA42:$AA$58)),"") | Z42: =IF(AB42<>"",IF($L$12<>"",IF(G42<>"",G42,($L$9/$L$12-SUM($Z$25:Z41))*AA42*AB42/SUMPRODUCT($AB42:$AB$58,$AA42:$AA$58)),""),"")
F43: =IF(AND(E43<>"",E43<>0),D43/E43,"") | H43: =IF(AND(G43<>"",G43<>0),D43/G43,"") | J43: =IF(AND(G43<>"",G43<>0),E43/G43,"") | S43: =IF(AND(I43<>"",I43<>0),G43/I43,"") | T43: =I43/U43 -> #DIV/0! | U43: =$L$8*AA43*AB43/SUMPRODUCT($AB$25:$AB$56,$AA$25:$AA$56) -> 0 | V43: =$L$9*AA43*AB43/SUMPRODUCT($AB$25:$AB$58,$AA$25:$AA$58) -> 0 | W43: =IF($L$12="","",V43/$L$12) -> 0 | X43: =IF(AB43<>"",IF(D43<>"",D43,($L$8-SUM($X$25:X42))*AA43*AB43/SUMPRODUCT($AB43:$AB$58,$AA43:$AA$58)),"") | Y43: =IF(AB43<>"",IF(E43<>"",E43,($L$9-SUM($Y$25:Y42))*AA43*AB43/SUMPRODUCT($AB43:$AB$58,$AA43:$AA$58)),"") | Z43: =IF(AB43<>"",IF($L$12<>"",IF(G43<>"",G43,($L$9/$L$12-SUM($Z$25:Z42))*AA43*AB43/SUMPRODUCT($AB43:$AB$58,$AA43:$AA$58)),""),"")
F44: =IF(AND(E44<>"",E44<>0),D44/E44,"") | H44: =IF(AND(G44<>"",G44<>0),D44/G44,"") | J44: =IF(AND(G44<>"",G44<>0),E44/G44,"") | S44: =IF(AND(I44<>"",I44<>0),G44/I44,"") | T44: =I44/U44 -> #DIV/0! | U44: =$L$8*AA44*AB44/SUMPRODUCT($AB$25:$AB$56,$AA$25:$AA$56) -> 0 | V44: =$L$9*AA44*AB44/SUMPRODUCT($AB$25:$AB$58,$AA$25:$AA$58) -> 0 | W44: =IF($L$12="","",V44/$L$12) -> 0 | X44: =IF(AB44<>"",IF(D44<>"",D44,($L$8-SUM($X$25:X43))*AA44*AB44/SUMPRODUCT($AB44:$AB$58,$AA44:$AA$58)),"") | Y44: =IF(AB44<>"",IF(E44<>"",E44,($L$9-SUM($Y$25:Y43))*AA44*AB44/SUMPRODUCT($AB44:$AB$58,$AA44:$AA$58)),"") | Z44: =IF(AB44<>"",IF($L$12<>"",IF(G44<>"",G44,($L$9/$L$12-SUM($Z$25:Z43))*AA44*AB44/SUMPRODUCT($AB44:$AB$58,$AA44:$AA$58)),""),"")
F45: =IF(AND(E45<>"",E45<>0),D45/E45,"") | H45: =IF(AND(G45<>"",G45<>0),D45/G45,"") | J45: =IF(AND(G45<>"",G45<>0),E45/G45,"") | S45: =IF(AND(I45<>"",I45<>0),G45/I45,"") | T45: =I45/U45 -> #DIV/0! | U45: =$L$8*AA45*AB45/SUMPRODUCT($AB$25:$AB$56,$AA$25:$AA$56) -> 0 | V45: =$L$9*AA45*AB45/SUMPRODUCT($AB$25:$AB$58,$AA$25:$AA$58) -> 0 | W45: =IF($L$12="","",V45/$L$12) -> 0 | X45: =IF(AB45<>"",IF(D45<>"",D45,($L$8-SUM($X$25:X44))*AA45*AB45/SUMPRODUCT($AB45:$AB$58,$AA45:$AA$58)),"") | Y45: =IF(AB45<>"",IF(E45<>"",E45,($L$9-SUM($Y$25:Y44))*AA45*AB45/SUMPRODUCT($AB45:$AB$58,$AA45:$AA$58)),"") | Z45: =IF(AB45<>"",IF($L$12<>"",IF(G45<>"",G45,($L$9/$L$12-SUM($Z$25:Z44))*AA45*AB45/SUMPRODUCT($AB45:$AB$58,$AA45:$AA$58)),""),"")
F46: =IF(AND(E46<>"",E46<>0),D46/E46,"") | H46: =IF(AND(G46<>"",G46<>0),D46/G46,"") | J46: =IF(AND(G46<>"",G46<>0),E46/G46,"") | S46: =IF(AND(I46<>"",I46<>0),G46/I46,"") | T46: =I46/U46 -> #DIV/0! | U46: =$L$8*AA46*AB46/SUMPRODUCT($AB$25:$AB$56,$AA$25:$AA$56) -> 0 | V46: =$L$9*AA46*AB46/SUMPRODUCT($AB$25:$AB$58,$AA$25:$AA$58) -> 0 | W46: =IF($L$12="","",V46/$L$12) -> 0 | X46: =IF(AB46<>"",IF(D46<>"",D46,($L$8-SUM($X$25:X45))*AA46*AB46/SUMPRODUCT($AB46:$AB$58,$AA46:$AA$58)),"") | Y46: =IF(AB46<>"",IF(E46<>"",E46,($L$9-SUM($Y$25:Y45))*AA46*AB46/SUMPRODUCT($AB46:$AB$58,$AA46:$AA$58)),"") | Z46: =IF(AB46<>"",IF($L$12<>"",IF(G46<>"",G46,($L$9/$L$12-SUM($Z$25:Z45))*AA46*AB46/SUMPRODUCT($AB46:$AB$58,$AA46:$AA$58)),""),"")
F47: =IF(AND(E47<>"",E47<>0),D47/E47,"") | H47: =IF(AND(G47<>"",G47<>0),D47/G47,"") | J47: =IF(AND(G47<>"",G47<>0),E47/G47,"") | S47: =IF(AND(I47<>"",I47<>0),G47/I47,"") | T47: =I47/U47 -> #DIV/0! | U47: =$L$8*AA47*AB47/SUMPRODUCT($AB$25:$AB$56,$AA$25:$AA$56) -> 0 | V47: =$L$9*AA47*AB47/SUMPRODUCT($AB$25:$AB$58,$AA$25:$AA$58) -> 0 | W47: =IF($L$12="","",V47/$L$12) -> 0 | X47: =IF(AB47<>"",IF(D47<>"",D47,($L$8-SUM($X$25:X46))*AA47*AB47/SUMPRODUCT($AB47:$AB$58,$AA47:$AA$58)),"") | Y47: =IF(AB47<>"",IF(E47<>"",E47,($L$9-SUM($Y$25:Y46))*AA47*AB47/SUMPRODUCT($AB47:$AB$58,$AA47:$AA$58)),"") | Z47: =IF(AB47<>"",IF($L$12<>"",IF(G47<>"",G47,($L$9/$L$12-SUM($Z$25:Z46))*AA47*AB47/SUMPRODUCT($AB47:$AB$58,$AA47:$AA$58)),""),"")
F48: =IF(AND(E48<>"",E48<>0),D48/E48,"") | H48: =IF(AND(G48<>"",G48<>0),D48/G48,"") | J48: =IF(AND(G48<>"",G48<>0),E48/G48,"") | S48: =IF(AND(I48<>"",I48<>0),G48/I48,"") | T48: =I48/U48 -> #DIV/0! | U48: =$L$8*AA48*AB48/SUMPRODUCT($AB$25:$AB$56,$AA$25:$AA$56) -> 0 | V48: =$L$9*AA48*AB48/SUMPRODUCT($AB$25:$AB$58,$AA$25:$AA$58) -> 0 | W48: =IF($L$12="","",V48/$L$12) -> 0 | X48: =IF(AB48<>"",IF(D48<>"",D48,($L$8-SUM($X$25:X47))*AA48*AB48/SUMPRODUCT($AB48:$AB$58,$AA48:$AA$58)),"") | Y48: =IF(AB48<>"",IF(E48<>"",E48,($L$9-SUM($Y$25:Y47))*AA48*AB48/SUMPRODUCT($AB48:$AB$58,$AA48:$AA$58)),"") | Z48: =IF(AB48<>"",IF($L$12<>"",IF(G48<>"",G48,($L$9/$L$12-SUM($Z$25:Z47))*AA48*AB48/SUMPRODUCT($AB48:$AB$58,$AA48:$AA$58)),""),"")
H49: =IF(AND(G49<>"",G49<>0),D49/G49,"") | J49: =IF(AND(G49<>"",G49<>0),E49/G49,"") | S49: =IF(AND(I49<>"",I49<>0),G49/I49,"") | T49: =I49/U49 -> #DIV/0! | U49: =$L$8*AA49*AB49/SUMPRODUCT($AB$25:$AB$56,$AA$25:$AA$56) -> 0 | V49: =$L$9*AA49*AB49/SUMPRODUCT($AB$25:$AB$58,$AA$25:$AA$58) -> 0 | W49: =IF($L$12="","",V49/$L$12) -> 0 | X49: =IF(AB49<>"",IF(D49<>"",D49,($L$8-SUM($X$25:X48))*AA49*AB49/SUMPRODUCT($AB49:$AB$58,$AA49:$AA$58)),"") | Y49: =IF(AB49<>"",IF(E49<>"",E49,($L$9-SUM($Y$25:Y48))*AA49*AB49/SUMPRODUCT($AB49:$AB$58,$AA49:$AA$58)),"") | Z49: =IF(AB49<>"",IF($L$12<>"",IF(G49<>"",G49,($L$9/$L$12-SUM($Z$25:Z48))*AA49*AB49/SUMPRODUCT($AB49:$AB$58,$AA49:$AA$58)),""),"")
F50: =IF(AND(E50<>"",E50<>0),D50/E50,"") | H50: =IF(AND(G50<>"",G50<>0),D50/G50,"") | J50: =IF(AND(G50<>"",G50<>0),E50/G50,"") | S50: =IF(AND(I50<>"",I50<>0),G50/I50,"") | T50: =I50/U50 -> #DIV/0! | U50: =$L$8*AA50*AB50/SUMPRODUCT($AB$25:$AB$56,$AA$25:$AA$56) -> 0 | V50: =$L$9*AA50*AB50/SUMPRODUCT($AB$25:$AB$58,$AA$25:$AA$58) -> 0 | W50: =IF($L$12="","",V50/$L$12) -> 0 | X50: =IF(AB50<>"",IF(D50<>"",D50,($L$8-SUM($X$25:X49))*AA50*AB50/SUMPRODUCT($AB50:$AB$58,$AA50:$AA$58)),"") | Y50: =IF(AB50<>"",IF(E50<>"",E50,($L$9-SUM($Y$25:Y49))*AA50*AB50/SUMPRODUCT($AB50:$AB$58,$AA50:$AA$58)),"") | Z50: =IF(AB50<>"",IF($L$12<>"",IF(G50<>"",G50,($L$9/$L$12-SUM($Z$25:Z49))*AA50*AB50/SUMPRODUCT($AB50:$AB$58,$AA50:$AA$58)),""),"")
F51: =IF(AND(E51<>"",E51<>0),D51/E51,"") | H51: =IF(AND(G51<>"",G51<>0),D51/G51,"") | J51: =IF(AND(G51<>"",G51<>0),E51/G51,"") | S51: =IF(AND(I51<>"",I51<>0),G51/I51,"") | T51: =I51/U51 -> #DIV/0! | U51: =$L$8*AA51*AB51/SUMPRODUCT($AB$25:$AB$56,$AA$25:$AA$56) -> 0 | V51: =$L$9*AA51*AB51/SUMPRODUCT($AB$25:$AB$58,$AA$25:$AA$58) -> 0 | W51: =IF($L$12="","",V51/$L$12) -> 0 | X51: =IF(AB51<>"",IF(D51<>"",D51,($L$8-SUM($X$25:X50))*AA51*AB51/SUMPRODUCT($AB51:$AB$58,$AA51:$AA$58)),"") | Y51: =IF(AB51<>"",IF(E51<>"",E51,($L$9-SUM($Y$25:Y50))*AA51*AB51/SUMPRODUCT($AB51:$AB$58,$AA51:$AA$58)),"") | Z51: =IF(AB51<>"",IF($L$12<>"",IF(G51<>"",G51,($L$9/$L$12-SUM($Z$25:Z50))*AA51*AB51/SUMPRODUCT($AB51:$AB$58,$AA51:$AA$58)),""),"")
F52: =IF(AND(E52<>"",E52<>0),D52/E52,"") | H52: =IF(AND(G52<>"",G52<>0),D52/G52,"") | J52: =IF(AND(G52<>"",G52<>0),E52/G52,"") | S52: =IF(AND(I52<>"",I52<>0),G52/I52,"") | T52: =I52/U52 -> #DIV/0! | U52: =$L$8*AA52*AB52/SUMPRODUCT($AB$25:$AB$56,$AA$25:$AA$56) -> 0 | V52: =$L$9*AA52*AB52/SUMPRODUCT($AB$25:$AB$58,$AA$25:$AA$58) -> 0 | W52: =IF($L$12="","",V52/$L$12) -> 0 | X52: =IF(AB52<>"",IF(D52<>"",D52,($L$8-SUM($X$25:X51))*AA52*AB52/SUMPRODUCT($AB52:$AB$58,$AA52:$AA$58)),"") | Y52: =IF(AB52<>"",IF(E52<>"",E52,($L$9-SUM($Y$25:Y51))*AA52*AB52/SUMPRODUCT($AB52:$AB$58,$AA52:$AA$58)),"") | Z52: =IF(AB52<>"",IF($L$12<>"",IF(G52<>"",G52,($L$9/$L$12-SUM($Z$25:Z51))*AA52*AB52/SUMPRODUCT($AB52:$AB$58,$AA52:$AA$58)),""),"")
F53: =IF(AND(E53<>"",E53<>0),D53/E53,"") | H53: =IF(AND(G53<>"",G53<>0),D53/G53,"") | J53: =IF(AND(G53<>"",G53<>0),E53/G53,"") | S53: =IF(AND(I53<>"",I53<>0),G53/I53,"") | T53: =I53/U53 -> #DIV/0! | U53: =$L$8*AA53*AB53/SUMPRODUCT($AB$25:$AB$56,$AA$25:$AA$56) -> 0 | V53: =$L$9*AA53*AB53/SUMPRODUCT($AB$25:$AB$58,$AA$25:$AA$58) -> 0 | W53: =IF($L$12="","",V53/$L$12) -> 0 | X53: =IF(AB53<>"",IF(D53<>"",D53,($L$8-SUM($X$25:X52))*AA53*AB53/SUMPRODUCT($AB53:$AB$58,$AA53:$AA$58)),"") | Y53: =IF(AB53<>"",IF(E53<>"",E53,($L$9-SUM($Y$25:Y52))*AA53*AB53/SUMPRODUCT($AB53:$AB$58,$AA53:$AA$58)),"") | Z53: =IF(AB53<>"",IF($L$12<>"",IF(G53<>"",G53,($L$9/$L$12-SUM($Z$25:Z52))*AA53*AB53/SUMPRODUCT($AB53:$AB$58,$AA53:$AA$58)),""),"")
F54: =IF(AND(E54<>"",E54<>0),D54/E54,"") | H54: =IF(AND(G54<>"",G54<>0),D54/G54,"") | J54: =IF(AND(G54<>"",G54<>0),E54/G54,"") | S54: =IF(AND(I54<>"",I54<>0),G54/I54,"") | T54: =I54/U54 -> #DIV/0! | U54: =$L$8*AA54*AB54/SUMPRODUCT($AB$25:$AB$56,$AA$25:$AA$56) -> 0 | V54: =$L$9*AA54*AB54/SUMPRODUCT($AB$25:$AB$58,$AA$25:$AA$58) -> 0 | W54: =IF($L$12="","",V54/$L$12) -> 0 | X54: =IF(AB54<>"",IF(D54<>"",D54,($L$8-SUM($X$25:X53))*AA54*AB54/SUMPRODUCT($AB54:$AB$58,$AA54:$AA$58)),"") | Y54: =IF(AB54<>"",IF(E54<>"",E54,($L$9-SUM($Y$25:Y53))*AA54*AB54/SUMPRODUCT($AB54:$AB$58,$AA54:$AA$58)),"") | Z54: =IF(AB54<>"",IF($L$12<>"",IF(G54<>"",G54,($L$9/$L$12-SUM($Z$25:Z53))*AA54*AB54/SUMPRODUCT($AB54:$AB$58,$AA54:$AA$58)),""),"")
F55: =IF(AND(E55<>"",E55<>0),D55/E55,"") | H55: =IF(AND(G55<>"",G55<>0),D55/G55,"") | J55: =IF(AND(G55<>"",G55<>0),E55/G55,"") | S55: =IF(AND(I55<>"",I55<>0),G55/I55,"") | T55: =I55/U55 -> #DIV/0! | U55: =$L$8*AA55*AB55/SUMPRODUCT($AB$25:$AB$56,$AA$25:$AA$56) -> 0 | V55: =$L$9*AA55*AB55/SUMPRODUCT($AB$25:$AB$58,$AA$25:$AA$58) -> 0 | W55: =IF($L$12="","",V55/$L$12) -> 0 | X55: =IF(AB55<>"",IF(D55<>"",D55,($L$8-SUM($X$25:X54))*AA55*AB55/SUMPRODUCT($AB55:$AB$58,$AA55:$AA$58)),"") | Y55: =IF(AB55<>"",IF(E55<>"",E55,($L$9-SUM($Y$25:Y54))*AA55*AB55/SUMPRODUCT($AB55:$AB$58,$AA55:$AA$58)),"") | Z55: =IF(AB55<>"",IF($L$12<>"",IF(G55<>"",G55,($L$9/$L$12-SUM($Z$25:Z54))*AA55*AB55/SUMPRODUCT($AB55:$AB$58,$AA55:$AA$58)),""),"")
F56: =IF(AND(E56<>"",E56<>0),D56/E56,"") | H56: =IF(AND(G56<>"",G56<>0),D56/G56,"") | J56: =IF(AND(G56<>"",G56<>0),E56/G56,"") | S56: =IF(AND(I56<>"",I56<>0),G56/I56,"") | T56: =I56/U56 -> #DIV/0! | U56: =$L$8*AA56*AB56/SUMPRODUCT($AB$25:$AB$56,$AA$25:$AA$56) -> 0 | V56: =$L$9*AA56*AB56/SUMPRODUCT($AB$25:$AB$58,$AA$25:$AA$58) -> 0 | W56: =IF($L$12="","",V56/$L$12) -> 0 | X56: =IF(AB56<>"",IF(D56<>"",D56,($L$8-SUM($X$25:X55))*AA56*AB56/SUMPRODUCT($AB56:$AB$58,$AA56:$AA$58)),"") | Y56: =IF(AB56<>"",IF(E56<>"",E56,($L$9-SUM($Y$25:Y55))*AA56*AB56/SUMPRODUCT($AB56:$AB$58,$AA56:$AA$58)),"") | Z56: =IF(AB56<>"",IF($L$12<>"",IF(G56<>"",G56,($L$9/$L$12-SUM($Z$25:Z55))*AA56*AB56/SUMPRODUCT($AB56:$AB$58,$AA56:$AA$58)),""),"")
D57: =SUM(D25:D56) -> 187359 | E57: =SUM(E25:E56) -> 33 | F57: =IF(AND(E57<>"",E57<>0),D57/E57,"") -> 5677.5455 | G57: =SUM(G25:G56) -> 17 | H57: =IF(AND(G57<>"",G57<>0),D57/G57,"") -> 11021.118 | I57: =SUM(I25:I56) -> 278 | J57: =IF(AND(G57<>"",G57<>0),E57/G57,"") -> 1.9411765 | K57: =SUM(K25:K56) -> 0 | L57: =SUM(L25:L56) -> 0 | M57: =SUM(M25:M56) -> 0 | N57: =SUM(N25:N56) -> 0 | O57: =SUM(O25:O56) -> 0 | P57: =SUM(P25:P56) -> 11893 | Q57: =SUM(Q25:Q56) -> 21880 | R57: =SUM(R25:R56) -> 23274 | S57: =IF(AND(I57<>"",I57<>0),G57/I57,"") -> 0.061151079 | T57: =I57/U57 -> 0.00060510477 | U57: =SUM(U25:U56) -> 459424.57 | V57: =SUM(V25:V55) -> 66.104255 | W57: =SUM(W25:W55) -> 36.321019 | X57: =SUM(X25:X56) -> 459424.57 | Y57: =SUM(Y25:Y55) -> 66.104255 | Z57: =SUM(Z25:Z55) -> 36.321019

Sheet Вед-ть Рогалевич
A1: =График!B1 -> Апрель, 2026
A2: =График!B3 -> ул. Набережная Ленина, 18 | D2: =[1]График!B4 -> GL-0004
A3: Сотрудник | D3: Выплачено на карту | E3: Выплачено наличными по платежной ведомости | F3: Оклад | G3: Бонус от личных продаж по категории товара | H3: Бонусная часть от общих продаж | I3: Дополнительные начисления, доплаты | J3: Итого: | K3: Вычеты | L3: Итого к выдаче с учетом авансов и вычетов
A4: =График!B28 -> Рогалевич Ирина | D4: =44000-J22 -> 38280 | F4: =G7 -> 17400 | G4: =G14 -> 47591.35 | H4: =G20 -> 10477.962 | I4: =L14 -> 17602.11 | J4: =G4+F4+I4+H4 -> 93071.422 | K4: =L20 -> 5720 | L4: =J4-K4-D4-E4 -> 49071.422
B7: Оклад: | G7: =G9+G10 -> 17400
B8: Дней | C8: Магазин | D8: Должность | E8: Зачислено часов | F8: Ставка за час, руб | G8: Начислено за день, руб | I8: КВП | J8: % выполнения
B9: =График!AI28 -> 19 | C9: =A2 -> ул. Набережная Ленина, 18 | D9: УМ | E9: =График!AJ28 -> 174 | F9: 100 | G9: =E9*F9 -> 17400 | I9: Магазин | J9: ='Ялта, Ленина, 18'!K8 -> 0.71583393
I10: Личный | J10: =Рогалевич!N8 -> 0.87196753
B14: Бонус от личных продаж по категории товара | G14: =G16+G17 -> 47591.35 | I14: Доп начисления | L14: =J16+J17+J18 -> 17602.11
B15: Категория товара | C15: Магазин | E15: Процент от продажи | F15: Продано на сумму, руб | G15: Начисленный бонус от продаж, руб | I15: Дата | J15: Сумма | K15: Описание
B16: Категория A | C16: =A2 -> ул. Набережная Ленина, 18 | E16: 0.05 | F16: =Рогалевич!M8-'Вед-ть Рогалевич'!F17 -> 632377 | G16: =F16*E16 -> 31618.85 | I16: 46142 | J16: 0 | K16: % наличного оборота ( > < 60%)
B17: Категория N (SALE, IS) | C17: =A2 -> ул. Набережная Ленина, 18 | E17: 0.1 | F17: =Рогалевич!L56+Рогалевич!R56 -> 159725 | G17: =F17*E17 -> 15972.5 | I17: 46142 | J17: ='Ялта, Ленина, 18'!J8*0.01 -> 17602.11 | K17: Административный %
F18: =F16+F17 -> 792102 | I18: 46142 | J18: 0 | K18: Чек-лист
B20: Бонус от общих продаж | G20: =G22+G23 -> 10477.962 | I20: Вычеты | L20: =J22+J23+J24 -> 5720
B21: Сотрудник | C21: Магазин | D21: Кол-во отработанных личных часов | E21: Кол-во отработанных общих часов | F21: Процент от продажи | G21: Начисленный бонус от продаж, руб | I21: Дата | J21: Сумма | K21: Описание
B22: =A4 -> Рогалевич Ирина | C22: =C16 -> ул. Набережная Ленина, 18 | D22: =E9 -> 174 | E22: =График!AJ29 -> 471 | F22: 0.02 | G22: =('Ялта, Ленина, 18'!J8-'Ялта, Ленина, 18'!L56-'Ялта, Ленина, 18'!R56)*F22*D22/E22 -> 10477.962 | I22: 46142 | J22: 5720 | K22: НДФЛ

Sheet Вед-ть Уразгильдеева
A1: =График!B1 -> Апрель, 2026
A2: =График!B3 -> ул. Набережная Ленина, 18 | D2: =[1]График!B4 -> GL-0004
A3: Сотрудник | D3: Выплачено на карту | E3: Выплачено наличными по платежной ведомости | F3: Оклад | G3: Бонус от личных продаж по категории товара | H3: Бонусная часть от общих продаж | I3: Дополнительные начисления, доплаты | J3: Итого: | K3: Вычеты | L3: Итого к выдаче с учетом авансов и вычетов
A4: =График!B27 -> Уразгильдеева Екатерина | D4: =40000-J22 -> 34800 | F4: =G7 -> 20900 | G4: =G14 -> 46991.179 | H4: =G20 -> 12585.598 | I4: =L14 -> 0 | J4: =G4+F4+I4+H4 -> 80476.777 | K4: =L20 -> 5200 | L4: =J4-K4-D4-E4 -> 40476.777
B7: Оклад: | G7: =G9+G10 -> 20900
B8: Дней | C8: Магазин | D8: Должность | E8: Зачислено часов | F8: Ставка за час, руб | G8: Начислено за день, руб | I8: КВП | J8: % выполнения
B9: =График!AI27 -> 20 | C9: =A2 -> ул. Набережная Ленина, 18 | D9: ПК | E9: =График!AJ27 -> 209 | F9: 100 | G9: =E9*F9 -> 20900 | I9: Магазин | J9: ='Ялта, Ленина, 18'!K8 -> 0.71583393
I10: Личный | J10: =Уразгильдеева!N8 -> 0.7155404
B14: Бонус от личных продаж по категории товара | G14: =G16+G17 -> 46991.179 | I14: Доп начисления | L14: =J16+J17+J18 -> 0
B15: Категория товара | C15: Магазин | E15: Процент от продажи | F15: Продано на сумму, руб | G15: Начисленный бонус от продаж, руб | I15: Дата | J15: Сумма | K15: Описание
B16: Категория A | C16: =A2 -> ул. Набережная Ленина, 18 | E16: 0.05 | F16: =Уразгильдеева!M8-'Вед-ть Уразгильдеева'!F17 -> 621676.42 | G16: =F16*E16 -> 31083.821 | I16: 46142 | J16: 0 | K16: Чек-лист
B17: Категория N (SALE, IS) | C17: =A2 -> ул. Набережная Ленина, 18 | E17: 0.1 | F17: =Уразгильдеева!L57+Уразгильдеева!R57 -> 159073.58 | G17: =F17*E17 -> 15907.358
F18: =F16+F17 -> 780750
B20: Бонус от общих продаж | G20: =G22+G23 -> 12585.598 | I20: Вычеты | L20: =J22+J23+J24 -> 5200
B21: Сотрудник | C21: Магазин | D21: Кол-во отработанных личных часов | E21: Кол-во отработанных общих часов | F21: Процент от продажи | G21: Начисленный бонус от продаж, руб | I21: Дата | J21: Сумма | K21: Описание
B22: =A4 -> Уразгильдеева Екатерина | C22: =C16 -> ул. Набережная Ленина, 18 | D22: =E9 -> 209 | E22: =График!AJ29 -> 471 | F22: 0.02 | G22: =('Ялта, Ленина, 18'!J8-'Ялта, Ленина, 18'!L56-'Ялта, Ленина, 18'!R56)*F22*D22/E22 -> 12585.598 | I22: 46142 | J22: 5200 | K22: НДФЛ

Sheet Вед-ть Самошкина
A1: =График!B1 -> Апрель, 2026
A2: =График!B3 -> ул. Набережная Ленина, 18 | D2: =[1]График!B4 -> GL-0004
A3: Сотрудник | D3: Выплачено на карту | E3: Выплачено наличными по платежной ведомости | F3: Оклад | G3: Бонус от личных продаж по категории товара | H3: Бонусная часть от общих продаж | I3: Дополнительные начисления, доплаты | J3: Итого: | K3: Вычеты | L3: Итого к выдаче с учетом авансов и вычетов
A4: =График!B26 -> Самошкина Алина | D4: 15019.65 | F4: =G7 -> 8800 | G4: =G14 -> 10531.65 | H4: =G20 -> 5299.1993 | I4: =L14 -> 2718.2 | J4: =G4+F4+I4+H4 -> 27349.049 | K4: =L20 -> 9444 | L4: =J4-K4-D4-E4 -> 2885.3993
B7: Оклад: | G7: =G9+G10 -> 8800
B8: Дней | C8: Магазин | D8: Должность | E8: Зачислено часов | F8: Ставка за час, руб | G8: Начислено за день, руб | I8: КВП | J8: % выполнения
B9: =График!AI26 -> 8 | C9: =A2 -> ул. Набережная Ленина, 18 | D9: ПК | E9: =График!AJ26 -> 88 | F9: 100 | G9: =E9*F9 -> 8800 | I9: Магазин | J9: ='Ялта, Ленина, 18'!K8 -> 0.71583393
I10: Личный | J10: =Самошкина!N8 -> 0.40781232
B14: Бонус от личных продаж по категории товара | G14: =G16+G17 -> 10531.65 | I14: Доп начисления | L14: =J16+J17+J18 -> 2718.2
B15: Категория товара | C15: Магазин | E15: Процент от продажи | F15: Продано на сумму, руб | G15: Начисленный бонус от продаж, руб | I15: Дата | J15: Сумма | K15: Описание
B16: Категория A | C16: =A2 -> ул. Набережная Ленина, 18 | E16: 0.05 | F16: =Самошкина!M8-'Вед-ть Самошкина'!F17 -> 164085 | G16: =F16*E16 -> 8204.25 | I16: 46127 | J16: 0 | K16: Чек-лист
B17: Категория N (SALE, IS) | C17: =A2 -> ул. Набережная Ленина, 18 | E17: 0.1 | F17: =Самошкина!L57+Самошкина!R57 -> 23274 | G17: =F17*E17 -> 2327.4 | I17: 46128 | J17: 2718.2 | K17: Компенсация отпуска при увольнении
F18: =F16+F17 -> 187359
B20: Бонус от общих продаж | G20: =G22+G23 -> 5299.1993 | I20: Вычеты | L20: =J22+J23+J24 -> 9444
B21: Сотрудник | C21: Магазин | D21: Кол-во отработанных личных часов | E21: Кол-во отработанных общих часов | F21: Процент от продажи | G21: Начисленный бонус от продаж, руб | I21: Дата | J21: Сумма | K21: Описание
B22: =A4 -> Самошкина Алина | C22: =C16 -> ул. Набережная Ленина, 18 | D22: =E9 -> 88 | E22: =График!AJ29 -> 471 | F22: 0.02 | G22: =('Ялта, Ленина, 18'!J8-'Ялта, Ленина, 18'!L56-'Ялта, Ленина, 18'!R56)*F22*D22/E22 -> 5299.1993 | I22: 46128 | J22: 2244 | K22: НДФЛ
I23: 46128 | J23: 7200 | K23: Вычет за стажировку (72 часа)

Sheet Конкурс
A2: Личный ежедневный КВП, %
A4: Сотруник | B4: 45282 | C4: 45283 | D4: 45284 | E4: 45285 | F4: 45286 | G4: 45287 | H4: 45288 | I4: 45289 | J4: 45290 | K4: 45291 | L4: Итого:
A5: Рогалевич Ирина | E5: 0.57 | F5: 0.73 | G5: 0.88 | H5: 0.98 | I5: 0.69 | J5: 1.82 | K5: 2.89
A6: Арапова Анна | C6: 0 | D6: 0 | E6: 0 | F6: 0 | G6: 0.83 | H6: 0 | I6: 0.28 | J6: 0.46 | K6: 0.89
A7: Уразгильдеева Екатерина | B7: 0.39 | C7: 0 | E7: 0 | F7: 0.49 | G7: 1.19 | H7: 0.69 | J7: 1.63 | K7: 0.81
A9: Личный КВП, баллы
A11: Сотруник | B11: 45282 | C11: 45283 | D11: 45284 | E11: 45285 | F11: 45286 | G11: 45287 | H11: 45288 | I11: 45289 | J11: 45290 | K11: 45291 | L11: Итого:
A12: Рогалевич Ирина | E12: 1 | F12: 1 | G12: 1 | H12: 1 | I12: 1 | J12: 2 | K12: 3 | L12: =SUM(B12:K12) -> 10
A13: Арапова Анна | L13: =SUM(B13:K13) -> 0
A14: Уразгильдеева Екатерина | B14: 1 | F14: 1 | G14: 2 | H14: 1 | J14: 1 | L14: =SUM(B14:K14) -> 6

Sheet График
B1: Апрель, 2026 | T1: в
B2: г. Ялта | C2: Симферополь
B3: ул. Набережная Ленина, 18
B4: GL-0005
B5: 10.00-21.00
B6: ФОТ | C6: Кол-во дней в месяц | AK6: 30
B7: =BT29*100/BH29 -> #DIV/0!
D8: ср | E8: чт | F8: пт | G8: сб | H8: вс | I8: пн | J8: вт | K8: ср | L8: чт | M8: пт | N8: сб | O8: вс | P8: пн | Q8: вт | R8: ср | S8: чт | T8: пт | U8: сб | V8: вс | W8: пн | X8: вт | Y8: ср | Z8: чт | AA8: пт | AB8: сб | AC8: вс | AD8: пн | AE8: вт | AF8: ср | AG8: чт | AJ8: Часы | AK8: Выходные | AL8: Отпуск | AM8: Больничный (официальный) | AN8: Дни стажировки
A9: № | B9: ФИО | C9: Должность | D9: 1 | E9: 2 | F9: 3 | G9: 4 | H9: 5 | I9: 6 | J9: 7 | K9: 8 | L9: 9 | M9: 10 | N9: 11 | O9: 12 | P9: 13 | Q9: 14 | R9: 15 | S9: 16 | T9: 17 | U9: 18 | V9: 19 | W9: 20 | X9: 21 | Y9: 22 | Z9: 23 | AA9: 24 | AB9: 25 | AC9: 26 | AD9: 27 | AE9: 28 | AF9: 29 | AG9: 30 | AI9: Дни
A10: 19 | AI10: 0 | AJ10: 0 | AK10: 0 | AL10: 0 | AM10: 0 | AN10: 0
A11: 18 | AI11: 0 | AJ11: 0 | AK11: 0 | AL11: 0 | AM11: 0 | AN11: 0
A12: 17 | AI12: 0 | AJ12: 0 | AK12: 0 | AL12: 0 | AM12: 0 | AN12: 0
A13: 16 | AI13: 0 | AJ13: 0 | AK13: 0 | AL13: 0 | AM13: 0 | AN13: 0
A14: 15 | AI14: 0 | AJ14: 0 | AK14: 0 | AL14: 0 | AM14: 0 | AN14: 0
A15: 14 | AI15: 0 | AJ15: 0 | AK15: 0 | AL15: 0 | AM15: 0 | AN15: 0
A16: 13 | AI16: 0 | AJ16: 0 | AK16: 0 | AL16: 0 | AM16: 0 | AN16: 0
A17: 12 | AI17: 0 | AJ17: 0 | AK17: 0 | AL17: 0 | AM17: 0 | AN17: 0
A18: 11 | AI18: 0 | AJ18: 0 | AK18: 0 | AL18: 0 | AM18: 0 | AN18: 0
A19: 10 | AI19: 0 | AJ19: 0 | AK19: 0 | AL19: 0 | AM19: 0 | AN19: 0
A20: 9 | AI20: 0 | AJ20: 0 | AK20: 0 | AL20: 0 | AM20: 0 | AN20: 0
A21: 8 | AI21: =COUNTIF(D21:AH21, ">0") -> 0 | AJ21: 0 | AK21: 0 | AL21: 0 | AM21: 0 | AN21: 0
A22: 7 | AI22: =COUNTIF(D22:AH22, ">0") -> 0 | AJ22: 0 | AK22: 0 | AL22: 0 | AM22: 0 | AN22: 0
A23: 6 | AI23: =COUNTIF(D23:AH23, ">0") -> 0 | AJ23: 0 | AK23: 0 | AL23: 0 | AM23: 0 | AN23: 0
A24: 5 | AI24: =COUNTIF(D24:AH24,">0") -> 0 | AJ24: =SUMIF(D24:AH24,">0") -> 0 | AK24: =COUNTIF(D24:AH24,"В") -> 0 | AL24: =COUNTIF(E24:AI24,"о") -> 0 | AM24: =COUNTIF(F24:AJ24,"б") -> 0 | AN24: 0
A25: 4 | B25: Максимычева Евгения | AA25: 8с | AB25: в | AC25: 11с | AD25: в | AE25: 11с | AF25: в | AG25: в | AI25: =COUNTIF(D25:AH25, ">0") -> 0 | AJ25: =SUMIF(D25:AH25,">0") -> 0 | AK25: =COUNTIF(D25:AH25, "В") -> 4 | AL25: 0 | AM25: 0 | AN25: 0
A26: 3 | B26: Самошкина Алина | C26: ПК | D26: в | E26: в | F26: 11 | G26: 11 | H26: в | I26: в | J26: 11 | K26: 11 | L26: в | M26: в | N26: 11 | O26: 11 | P26: в | Q26: в | R26: 11 | S26: 11 | T26: у | U26: у | V26: у | W26: у | X26: у | Y26: у | Z26: у | AA26: у | AB26: у | AC26: у | AD26: у | AE26: у | AF26: у | AG26: у | AI26: =COUNTIF(D26:AH26,">0") -> 8 | AJ26: =SUMIF(D26:AH26,">0") -> 88 | AK26: =COUNTIF(D26:AH26,"В") -> 8 | AL26: =COUNTIF(E26:AI26,"о") -> 0 | AM26: =COUNTIF(F26:AJ26,"б") -> 0 | AN26: 0
A27: 2 | B27: Уразгильдеева Екатерина | C27: ПК | D27: 11 | E27: 11 | F27: в | G27: в | H27: 11 | I27: 11 | J27: в | K27: в | L27: 11 | M27: 11 | N27: в | O27: в | P27: 11 | Q27: 11 | R27: 6 | S27: в | T27: 11 | U27: 11 | V27: в | W27: 11 | X27: 11 | Y27: 11 | Z27: 11 | AA27: в | AB27: 5 | AC27: 11 | AD27: в | AE27: 11 | AF27: 11 | AG27: 11 | AI27: =COUNTIF(D27:AH27,">0") -> 20 | AJ27: =SUMIF(D27:AH27,">0") -> 209 | AK27: =COUNTIF(D27:AH27,"В") -> 10 | AL27: =COUNTIF(E27:AI27,"о") -> 0 | AM27: =COUNTIF(F27:AJ27,"б") -> 0 | AN27: 0
A28: 1 | B28: Рогалевич Ирина | C28: УМ | D28: 9 | E28: 9 | F28: 9 | G28: 9 | H28: 9 | I28: с | J28: с | K28: с | L28: с | M28: с | N28: 9 | O28: 9 | P28: 9 | Q28: 9 | R28: в | S28: 9 | T28: 9 | U28: 10 | V28: 11 | W28: с | X28: с | Y28: с | Z28: с | AA28: 11 | AB28: 9 | AC28: 9 | AD28: 11 | AE28: 8 | AF28: 6 | AG28: с | AI28: =COUNTIF(D28:AH28,">0") -> 19 | AJ28: =SUMIF(D28:AH28,">0") -> 174 | AK28: =COUNTIF(D28:AH28,"В") -> 1 | AL28: =COUNTIF(E28:AI28,"о") -> 0 | AM28: =COUNTIF(F28:AJ28,"б") -> 0 | AN28: 0
B29: Итого магазин | D29: =COUNTIF(D10:D28, ">0") -> 2 | E29: =COUNTIF(E10:E28, ">0") -> 2 | F29: =COUNTIF(F10:F28, ">0") -> 2 | G29: =COUNTIF(G10:G28, ">0") -> 2 | H29: =COUNTIF(H10:H28, ">0") -> 2 | I29: =COUNTIF(I10:I28, ">0") -> 1 | J29: =COUNTIF(J10:J28, ">0") -> 1 | K29: =COUNTIF(K10:K28, ">0") -> 1 | ... AH29: =COUNTIF(AH10:AH28, ">0") -> 0 | AI29: =SUM(AI10:AI28) -> 47 | AJ29: =SUM(AJ10:AJ28) -> 471 | AK29: =SUM(AK10:AK28) -> 23 | AL29: =SUM(AL10:AL28) -> 0 | AM29: =SUM(AM10:AM28) -> 0 | AN29: =SUM(AN10:AN28) -> 0
