Workbook
Name маг: NA()

Sheet Ялта, Ленина, 18
B1: =TODAY()-1 -> 46000
B2: (отчетная дата)
C3: Осталось до выполнения плана!!! | I3: =График!B3 -> ул. Набережная Ленина, 18
C4: =I8-D56 -> 946704 | E4: =IF(I8<>0, C4/I8, 0) -> 0.45815278
D5: =C4/(I14-J14) -> #DIV/0!
F6: Целевые показатели
F7: Показатель | I7: План | J7: Факт | K7: % выполнения | L7: Прогноз выполнения | M7: % выполнения по прогнозу | N7: Отклонение | O7: Факт аналогичного месяца прошлого года | P7: Отклонение LFL
F8: Выручка | I8: =I11*I12*I13 -> 2066350 | J8: =D56 -> 1119646 | K8: =IF(AND(I8<>"",I8<>0,J8<>""),J8/I8,"") -> 0.54184722 | L8: =IF(SUMIF($D$25:$D$55,">=0",$P$25:$P$55)<>0,I8*D56/SUMIF($D$25:$D$55,">=0",$P$25:$P$55),0) -> 1181910.8 | M8: =IF(AND(I8<>"", I8<>0, L8<>"", L8<>0), L8/I8, "") -> 0.57197998 | N8: =IF(AND(J8<>0, J8<>"", I8<>0, I8<>""), L8-I8, "") -> -884439.17 | P8: =IF(AND(O8<>"", O8<>0, L8<>"", L8<>0), -O8+L8, "") | Q8: =IF(AND(P8<>"", P8<>0, O8<>0, O8<>""), P8/O8, "")
F9: Кол-во изделий | I9: =I8/I11 -> 317.9 | J9: =E56 -> 152 | K9: =IF(AND(I9<>"", I9<>0, J9<>""), J9/I9, "") -> 0.47813778 | L9: =IF(SUMIF($E$25:$E$55, ">=0", $Q$25:$Q$55)<>0, I9*E56/SUMIF($E$25:$E$55, ">=0", $Q$25:$Q$55), 0) -> 171.28476 | M9: =IF(AND(I9<>"", I9<>0, L9<>"", L9<>0), L9/I9, "") -> 0.53880075 | N9: =IF(AND(J9<>0, J9<>"", I9<>0, I9<>""), L9-I9, "") -> -146.61524 | O9: =O8/O11 -> #DIV/0! | P9: =IF(AND(O9<>"", O9<>0, L9<>"", L9<>0), -O9+L9, "") -> #DIV/0! | Q9: =IF(AND(P9<>"", P9<>0, O9<>0, O9<>""), P9/O9, "") -> #DIV/0!
F10: Средний чек | I10: =I11*I12 -> 11050 | J10: =H56 -> 11542.742 | K10: =IF(AND(I10<>"", I10<>0, J10<>""), J10/I10, "") -> 1.0445921 | L10: =J10 -> 11542.742 | M10: =IF(AND(I10<>"", I10<>0, L10<>"", L10<>0), L10/I10, "") -> 1.0445921 | N10: =IF(AND(J10<>0, J10<>"", I10<>0, I10<>""), L10-I10, "") -> 492.74227 | O10: =O11*O12 -> 0 | P10: =IF(AND(O10<>"", O10<>0, L10<>"", L10<>0), -O10+L10, "") | Q10: =IF(AND(P10<>"", P10<>0, O10<>0, O10<>""), P10/O10, "") | S10: =L23 -> IS | V10: =M23 -> Agafi
F11: Средняя стоимость изделия | I11: 6500 | J11: =F56 -> 7366.0921 | K11: =IF(AND(I11<>"", I11<>0, J11<>""), J11/I11, "") -> 1.1332449 | L11: =IF(L9>0, L8/L9, "") -> 6900.2685 | M11: =IF(AND(I11<>"", I11<>0, L11<>"", L11<>0), L11/I11, "") -> 1.0615798 | N11: =IF(AND(J11<>0, J11<>"", I11<>0, I11<>""), L11-I11, "") -> 400.26851 | P11: =IF(AND(O11<>"", O11<>0, L11<>"", L11<>0), -O11+L11, "") | Q11: =IF(AND(P11<>"", P11<>0, O11<>0, O11<>""), P11/O11, "")
F12: Длина чека | I12: 1.7 | J12: =J56 -> 1.5670103 | K12: =IF(AND(I12<>"", I12<>0, J12<>""), J12/I12, "") -> 0.92177077 | L12: =J12 -> 1.5670103 | M12: =IF(AND(I12<>"", I12<>0, L12<>"", L12<>0), L12/I12, "") -> 0.92177077 | N12: =IF(AND(J12<>0, J12<>"", I12<>0, I12<>""), L12-I12, "") -> -0.13298969 | P12: =IF(AND(O12<>"", O12<>0, L12<>"", L12<>0), -O12+L12, "") | Q12: =IF(AND(P12<>"", P12<>0, O12<>0, O12<>""), P12/O12, "") | S12: 510000 | T12: =L56 -> 46449 | V12: 480000 | W12: =M56 -> 72847
F13: Кол-во чеков | I13: =I17*I20 -> 187 | J13: =G56 -> 97 | K13: =IF(AND(I13<>"", I13<>0, J13<>""), J13/I13, "") -> 0.51871658 | L13: =IF(SUMIF($G$25:$G$55, ">=0", $R$25:$R$55)<>0, I13*G56/SUMIF($G$25:$G$55, ">=0", $R$25:$R$55), "") -> 109.30672 | M13: =IF(AND(I13<>"", I13<>0, L13<>"", L13<>0), L13/I13, "") -> 0.58452792 | N13: =IF(AND(J13<>0, J13<>"", I13<>0, I13<>""), L13-I13, "") -> -77.693279 | P13: =IF(AND(O13<>"", O13<>0, L13<>"", L13<>0), -O13+L13, "") | Q13: =IF(AND(P13<>"", P13<>0, O13<>0, O13<>""), P13/O13, "") | S13: =T12/S12 -> 0.091076471 | T13: =S13/J14*I14 -> 0.091076471 | V13: =W12/V12 -> 0.15176458 | W13: =V13/J14*I14 -> 0.15176458
F14: Кол-во смен | I14: 30 | J14: 30 | K14: =IF(AND(I14<>"", I14<>0, J14<>""), J14/I14, "") -> 1 | L14: =I14 -> 30 | M14: =IF(AND(I14<>"", I14<>0, L14<>"", L14<>0), L14/I14, "") -> 1 | N14: =IF(AND(J14<>0, J14<>"", I14<>0, I14<>""), L14-I14, "") -> 0 | P14: =IF(AND(O14<>"", O14<>0, L14<>"", L14<>0), -O14+L14, "") | Q14: =IF(AND(P14<>"", P14<>0, O14<>0, O14<>""), P14/O14, "")
F15: Средние продажи в смену | I15: =I8/I14 -> 68878.333 | J15: =J8/J14 -> 37321.533 | K15: =IF(AND(I15<>"", I15<>0, J15<>""), J15/I15, "") -> 0.54184722 | L15: =J15 -> 37321.533 | M15: =IF(AND(I15<>"", I15<>0, L15<>"", L15<>0), L15/I15, "") -> 0.54184722 | N15: =IF(AND(J15<>0, J15<>"", I15<>0, I15<>""), L15-I15, "") -> -31556.8 | P15: =IF(AND(O15<>"", O15<>0, L15<>"", L15<>0), -O15+L15, "") | Q15: =IF(AND(P15<>"", P15<>0, O15<>0, O15<>""), P15/O15, "")
F16: Отставание/Перевыполнение | J16: =J8-I15*J14 -> -946704 | K16: =IF(AND(I16<>"", I16<>0, J16<>""), J16/I16, "") | L16: =J16 -> -946704 | M16: =IF(AND(I16<>"", I16<>0, L16<>"", L16<>0), L16/I16, "") | N16: =IF(AND(J16<>0, J16<>"", I16<>0, I16<>""), L16-I16, "") | P16: =IF(AND(O16<>"", O16<>0, L16<>"", L16<>0), -O16+L16, "") | Q16: =IF(AND(P16<>"", P16<>0, O16<>0, O16<>""), P16/O16, "") | S16: =K23 -> UNOde50
F17: Трафик | I17: 1700 | J17: =I56 -> 1555.2 | K17: =IF(AND(I17<>"", I17<>0, J17<>""), J17/I17, "") -> 0.91482353 | L17: =J17/J14*I14 -> 1555.2 | M17: =IF(AND(I17<>"", I17<>0, L17<>"", L17<>0), L17/I17, "") -> 0.91482353 | N17: =IF(AND(J17<>0, J17<>"", I17<>0, I17<>""), L17-I17, "") -> -144.8 | P17: =IF(AND(O17<>"", O17<>0, L17<>"", L17<>0), -O17+L17, "") | Q17: =IF(AND(P17<>"", P17<>0, O17<>0, O17<>""), P17/O17, "")
K18: =IF(AND(I18<>"", I18<>0, J18<>""), J18/I18, "") | L18: =J18 -> 0 | M18: =IF(AND(I18<>"", I18<>0, L18<>"", L18<>0), L18/I18, "") | N18: =IF(AND(J18<>0, J18<>"", I18<>0, I18<>""), L18-I18, "") | O18: 0 | P18: =IF(AND(O18<>"", O18<>0, L18<>"", L18<>0), -O18+L18, "") | Q18: =IF(AND(P18<>"", P18<>0, O18<>0, O18<>""), P18/O18, "") | S18: 1020000 | T18: =K56 -> 416418
K19: =IF(AND(I19<>"", I19<>0, J19<>""), J19/I19, "") | L19: =J19 -> 0 | M19: =IF(AND(I19<>"", I19<>0, L19<>"", L19<>0), L19/I19, "") | N19: =IF(AND(J19<>0, J19<>"", I19<>0, I19<>""), L19-I19, "") | O19: 0 | P19: =IF(AND(O19<>"", O19<>0, L19<>"", L19<>0), -O19+L19, "") | Q19: =IF(AND(P19<>"", P19<>0, O19<>0, O19<>""), P19/O19, "") | S19: =T18/S18 -> 0.40825294 | T19: =S19/J14*I14 -> 0.40825294
F20: Конверсия план/факт | I20: 0.11 | J20: =N56 -> 0.062371399 | K20: =J20/I20 -> 0.56701272 | L20: =IF(AND(K8<>0, I14<>0, I56<>0), (I56*N56+(I56/K8-I56)*I20)/(I56/K8), 0) -> 0.084192575 | M20: =IF(AND(I20<>"", I20<>0, L20<>"", L20<>0), L20/I20, "") -> 0.76538705 | N20: =IF(AND(J20<>0, J20<>"", I20<>0, I20<>""), L20-I20, "") -> -0.025807425 | P20: =IF(AND(O20<>"", O20<>0, L20<>"", L20<>0), -O20+L20, "") | Q20: =IF(AND(P20<>"", P20<>0, O20<>0, O20<>""), P20/O20, "")
A22: Факт продаж за месяц | O22: % выполнения дневного плана | P22: Раcпределение плана по дням
A23: Сотрудник | B23: Дата | C23: День недели | D23: Выручка (руб) | E23: Кол-во единиц (шт.) | F23: Средняя стоимость изделия (руб.) | G23: Количество чеков (шт.) | H23: Средняя сумма чека (руб.) | I23: Трафик | J23: Длина чека (шт.) | K23: UNOde50 | L23: IS | M23: Agafi | N23: Конверсия (%) | P23: выручка, план | Q23: кол-во ед, план | R23: Кол-во чеков, план | S23: выручка, скорректир.план | T23: кол-во ед, скорр. план | U23: кол-во чеков, скорр. план | V23: Коэфф. Дня Недели | W23: Специфика месяца
B24: 1 | C24: 2 | D24: 3 | E24: 4 | F24: 5 | G24: 6 | H24: 7 | I24: 8 | J24: 9 | K24: 10 | L24: 11 | M24: 12 | N24: 13 | P24: 1 | Q24: 2 | R24: 3 | S24: 4 | T24: 5 | U24: 6 | V24: 10 | W24: 11
A25: Рогалевич,Уразгильдеева,Арапова | B25: 45962 | C25: сб | D25: =29951+10268+6992+20506 -> 67717 | E25: 12 | F25: =IF(AND(E25<>"",E25<>0),D25/E25,"") -> 5643.0833 | G25: 9 | H25: =IF(AND(G25<>"",G25<>0),D25/G25,"") -> 7524.1111 | I25: 103 | J25: =IF(AND(G25<>"",G25<>0),E25/G25,"") -> 1.3333333 | K25: 10268 | L25: 20506 | M25: 6992 | N25: =IF(AND(I25<>"",I25<>0),G25/I25,"") -> 0.087378641 | O25: =D25/P25 -> 0.89835134 | P25: =$I$8*V25*W25/SUMPRODUCT($W$25:$W$55,$V$25:$V$55) -> 75379.194 | Q25: =$I$9*V25*W25/SUMPRODUCT($W$25:$W$55,$V$25:$V$55) -> 11.596799 | R25: =IF($I$12="","",Q25/$I$12) -> 6.8216465 | S25: =IF(D25<>"",D25,P25) -> 67717 | T25: =IF(E25<>"",E25,Q25) -> 12 | U25: =IF(G25<>"",G25,R25) -> 9 | V25: 0.9414554 | W25: 0.9414554
A26: Рогалевич,Уразгильдеева | B26: 45963 | C26: вс | D26: 147496 | E26: 19 | F26: =IF(AND(E26<>"",E26<>0),D26/E26,"") -> 7762.9474 | G26: 11 | H26: =IF(AND(G26<>"",G26<>0),D26/G26,"") -> 13408.727 | I26: 131 | J26: =IF(AND(G26<>"",G26<>0),E26/G26,"") -> 1.7272727 | K26: 63254 | M26: 31287 | N26: =IF(AND(I26<>"",I26<>0),G26/I26,"") -> 0.083969466 | O26: =D26/P26 -> 2.3830107 | P26: =$I$8*V26*W26/SUMPRODUCT($W$25:$W$55,$V$25:$V$55) -> 61894.812 | Q26: =$I$9*V26*W26/SUMPRODUCT($W$25:$W$55,$V$25:$V$55) -> 9.5222788 | R26: =IF($I$12="","",Q26/$I$12) -> 5.6013404 | S26: =IF(W26<>"",IF(D26<>"",D26,($I$8-SUM($S$25:S25))*V26*W26/SUMPRODUCT($W26:$W$55,$V26:$V$55)),"") -> 147496 | T26: =IF(W26<>"",IF(E26<>"",E26,($I$9-SUM($T$25:T25))*V26*W26/SUMPRODUCT($W26:$W$55,$V26:$V$55)),"") -> 19 | U26: =IF(W26<>"",IF(E26<>"",E26,($I$9-SUM($T$25:T25))*V26*W26/SUMPRODUCT($W26:$W$55,$V26:$V$55)),"") -> 19 | V26: 0.85310234 | W26: 0.85310234
A27: Рогалевич,Арапова | B27: 45964 | C27: пн | D27: 8692 | E27: 1 | F27: =IF(AND(E27<>"",E27<>0),D27/E27,"") -> 8692 | G27: 1 | H27: =IF(AND(G27<>"",G27<>0),D27/G27,"") -> 8692 | I27: 81 | J27: =IF(AND(G27<>"",G27<>0),E27/G27,"") -> 1 | K27: 8692 | N27: =IF(AND(I27<>"",I27<>0),G27/I27,"") -> 0.012345679 | O27: =D27/P27 -> 0.1404318 | P27: =$I$8*V27*W27/SUMPRODUCT($W$25:$W$55,$V$25:$V$55) -> 61894.812 | Q27: =$I$9*V27*W27/SUMPRODUCT($W$25:$W$55,$V$25:$V$55) -> 9.5222788 | R27: =IF($I$12="","",Q27/$I$12) -> 5.6013404 | S27: =IF(W27<>"",IF(D27<>"",D27,($I$8-SUM($S$25:S26))*V27*W27/SUMPRODUCT($W27:$W$55,$V27:$V$55)),"") -> 8692 | T27: =IF(W27<>"",IF(E27<>"",E27,($I$9-SUM($T$25:T26))*V27*W27/SUMPRODUCT($W27:$W$55,$V27:$V$55)),"") -> 1 | U27: =IF(W27<>"",IF(E27<>"",E27,($I$9-SUM($T$25:T26))*V27*W27/SUMPRODUCT($W27:$W$55,$V27:$V$55)),"") -> 1 | V27: 0.85310234 | W27: 0.85310234
A28: Рогалевич,Арапова | B28: 45965 | C28: вт | D28: 30422 | E28: 4 | F28: =IF(AND(E28<>"",E28<>0),D28/E28,"") -> 7605.5 | G28: 3 | H28: =IF(AND(G28<>"",G28<>0),D28/G28,"") -> 10140.667 | I28: 92 | J28: =IF(AND(G28<>"",G28<>0),E28/G28,"") -> 1.3333333 | K28: 16490 | N28: =IF(AND(I28<>"",I28<>0),G28/I28,"") -> 0.032608696 | O28: =D28/P28 -> 0.49151131 | P28: =$I$8*V28*W28/SUMPRODUCT($W$25:$W$55,$V$25:$V$55) -> 61894.812 | Q28: =$I$9*V28*W28/SUMPRODUCT($W$25:$W$55,$V$25:$V$55) -> 9.5222788 | R28: =IF($I$12="","",Q28/$I$12) -> 5.6013404 | S28: =IF(W28<>"",IF(D28<>"",D28,($I$8-SUM($S$25:S27))*V28*W28/SUMPRODUCT($W28:$W$55,$V28:$V$55)),"") -> 30422 | T28: =IF(W28<>"",IF(E28<>"",E28,($I$9-SUM($T$25:T27))*V28*W28/SUMPRODUCT($W28:$W$55,$V28:$V$55)),"") -> 4 | U28: =IF(W28<>"",IF(E28<>"",E28,($I$9-SUM($T$25:T27))*V28*W28/SUMPRODUCT($W28:$W$55,$V28:$V$55)),"") -> 4 | V28: 0.85310234 | W28: 0.85310234
A29: Рогалевич | B29: 45966 | C29: ср | D29: 28069 | E29: 6 | F29: =IF(AND(E29<>"",E29<>0),D29/E29,"") -> 4678.1667 | G29: 2 | H29: =IF(AND(G29<>"",G29<>0),D29/G29,"") -> 14034.5 | I29: 46 | J29: =IF(AND(G29<>"",G29<>0),E29/G29,"") -> 3 | N29: =IF(AND(I29<>"",I29<>0),G29/I29,"") -> 0.043478261 | O29: =D29/P29 -> 0.45681158 | P29: =$I$8*V29*W29/SUMPRODUCT($W$25:$W$55,$V$25:$V$55) -> 61445.465 | Q29: =$I$9*V29*W29/SUMPRODUCT($W$25:$W$55,$V$25:$V$55) -> 9.4531485 | R29: =IF($I$12="","",Q29/$I$12) -> 5.5606756 | S29: =IF(W29<>"",IF(D29<>"",D29,($I$8-SUM($S$25:S28))*V29*W29/SUMPRODUCT($W29:$W$55,$V29:$V$55)),"") -> 28069 | T29: =IF(W29<>"",IF(E29<>"",E29,($I$9-SUM($T$25:T28))*V29*W29/SUMPRODUCT($W29:$W$55,$V29:$V$55)),"") -> 6 | U29: =IF(W29<>"",IF(E29<>"",E29,($I$9-SUM($T$25:T28))*V29*W29/SUMPRODUCT($W29:$W$55,$V29:$V$55)),"") -> 6 | V29: 0.85 | W29: 0.85
A30: Рогалевич,Арапова | B30: 45967 | C30: чт | D30: 14400 | E30: 4 | F30: =IF(AND(E30<>"",E30<>0),D30/E30,"") -> 3600 | G30: 2 | H30: =IF(AND(G30<>"",G30<>0),D30/G30,"") -> 7200 | I30: 49 | J30: =IF(AND(G30<>"",G30<>0),E30/G30,"") -> 2 | N30: =IF(AND(I30<>"",I30<>0),G30/I30,"") -> 0.040816327 | O30: =D30/P30 -> 0.16932088 | P30: =$I$8*V30*W30/SUMPRODUCT($W$25:$W$55,$V$25:$V$55) -> 85045.626 | Q30: =$I$9*V30*W30/SUMPRODUCT($W$25:$W$55,$V$25:$V$55) -> 13.083943 | R30: =IF($I$12="","",Q30/$I$12) -> 7.6964368 | S30: =IF(W30<>"",IF(D30<>"",D30,($I$8-SUM($S$25:S29))*V30*W30/SUMPRODUCT($W30:$W$55,$V30:$V$55)),"") -> 14400 | T30: =IF(W30<>"",IF(E30<>"",E30,($I$9-SUM($T$25:T29))*V30*W30/SUMPRODUCT($W30:$W$55,$V30:$V$55)),"") -> 4 | U30: =IF(W30<>"",IF(E30<>"",E30,($I$9-SUM($T$25:T29))*V30*W30/SUMPRODUCT($W30:$W$55,$V30:$V$55)),"") -> 4 | V30: 1 | W30: 1
A31: Рогалевич,Арапова | B31: 45968 | C31: пт | D31: 40625 | E31: 9 | F31: =IF(AND(E31<>"",E31<>0),D31/E31,"") -> 4513.8889 | G31: 6 | H31: =IF(AND(G31<>"",G31<>0),D31/G31,"") -> 6770.8333 | I31: 64 | J31: =IF(AND(G31<>"",G31<>0),E31/G31,"") -> 1.5 | N31: =IF(AND(I31<>"",I31<>0),G31/I31,"") -> 0.09375 | O31: =D31/P31 -> 0.47768476 | P31: =$I$8*V31*W31/SUMPRODUCT($W$25:$W$55,$V$25:$V$55) -> 85045.626 | Q31: =$I$9*V31*W31/SUMPRODUCT($W$25:$W$55,$V$25:$V$55) -> 13.083943 | R31: =IF($I$12="","",Q31/$I$12) -> 7.6964368 | S31: =IF(W31<>"",IF(D31<>"",D31,($I$8-SUM($S$25:S30))*V31*W31/SUMPRODUCT($W31:$W$55,$V31:$V$55)),"") -> 40625 | T31: =IF(W31<>"",IF(E31<>"",E31,($I$9-SUM($T$25:T30))*V31*W31/SUMPRODUCT($W31:$W$55,$V31:$V$55)),"") -> 9 | U31: =IF(W31<>"",IF(E31<>"",E31,($I$9-SUM($T$25:T30))*V31*W31/SUMPRODUCT($W31:$W$55,$V31:$V$55)),"") -> 9 | V31: 1 | W31: 1
A32: Рогалевич,Арапова | B32: 45969 | C32: сб | D32: 46958 | E32: 8 | F32: =IF(AND(E32<>"",E32<>0),D32/E32,"") -> 5869.75 | G32: 6 | H32: =IF(AND(G32<>"",G32<>0),D32/G32,"") -> 7826.3333 | I32: 101 | J32: =IF(AND(G32<>"",G32<>0),E32/G32,"") -> 1.3333333 | K32: 20809 | N32: =IF(AND(I32<>"",I32<>0),G32/I32,"") -> 0.059405941 | O32: =D32/P32 -> 0.75867425 | P32: =$I$8*V32*W32/SUMPRODUCT($W$25:$W$55,$V$25:$V$55) -> 61894.812 | Q32: =$I$9*V32*W32/SUMPRODUCT($W$25:$W$55,$V$25:$V$55) -> 9.5222788 | R32: =IF($I$12="","",Q32/$I$12) -> 5.6013404 | S32: =IF(W32<>"",IF(D32<>"",D32,($I$8-SUM($S$25:S31))*V32*W32/SUMPRODUCT($W32:$W$55,$V32:$V$55)),"") -> 46958 | T32: =IF(W32<>"",IF(E32<>"",E32,($I$9-SUM($T$25:T31))*V32*W32/SUMPRODUCT($W32:$W$55,$V32:$V$55)),"") -> 8 | U32: =IF(W32<>"",IF(E32<>"",E32,($I$9-SUM($T$25:T31))*V32*W32/SUMPRODUCT($W32:$W$55,$V32:$V$55)),"") -> 8 | V32: 0.85310234 | W32: 0.85310234
A33: Рогалевич | B33: 45970 | C33: вс | D33: 6992 | E33: 1 | F33: =IF(AND(E33<>"",E33<>0),D33/E33,"") -> 6992 | G33: 1 | H33: =IF(AND(G33<>"",G33<>0),D33/G33,"") -> 6992 | I33: 84 | J33: =IF(AND(G33<>"",G33<>0),E33/G33,"") -> 1 | M33: 6992 | N33: =IF(AND(I33<>"",I33<>0),G33/I33,"") -> 0.011904762 | O33: =D33/P33 -> 0.11296585 | P33: =$I$8*V33*W33/SUMPRODUCT($W$25:$W$55,$V$25:$V$55) -> 61894.812 | Q33: =$I$9*V33*W33/SUMPRODUCT($W$25:$W$55,$V$25:$V$55) -> 9.5222788 | R33: =IF($I$12="","",Q33/$I$12) -> 5.6013404 | S33: =IF(W33<>"",IF(D33<>"",D33,($I$8-SUM($S$25:S32))*V33*W33/SUMPRODUCT($W33:$W$55,$V33:$V$55)),"") -> 6992 | T33: =IF(W33<>"",IF(E33<>"",E33,($I$9-SUM($T$25:T32))*V33*W33/SUMPRODUCT($W33:$W$55,$V33:$V$55)),"") -> 1 | U33: =IF(W33<>"",IF(E33<>"",E33,($I$9-SUM($T$25:T32))*V33*W33/SUMPRODUCT($W33:$W$55,$V33:$V$55)),"") -> 1 | V33: 0.85310234 | W33: 0.85310234
A34: Рогалевич | B34: 45971 | C34: пн | D34: 30575 | E34: 3 | F34: =IF(AND(E34<>"",E34<>0),D34/E34,"") -> 10191.667 | G34: 2 | H34: =IF(AND(G34<>"",G34<>0),D34/G34,"") -> 15287.5 | I34: 58 | J34: =IF(AND(G34<>"",G34<>0),E34/G34,"") -> 1.5 | K34: 15292 | N34: =IF(AND(I34<>"",I34<>0),G34/I34,"") -> 0.034482759 | O34: =D34/P34 -> 0.49398324 | P34: =$I$8*V34*W34/SUMPRODUCT($W$25:$W$55,$V$25:$V$55) -> 61894.812 | Q34: =$I$9*V34*W34/SUMPRODUCT($W$25:$W$55,$V$25:$V$55) -> 9.5222788 | R34: =IF($I$12="","",Q34/$I$12) -> 5.6013404 | S34: =IF(W34<>"",IF(D34<>"",D34,($I$8-SUM($S$25:S33))*V34*W34/SUMPRODUCT($W34:$W$55,$V34:$V$55)),"") -> 30575 | T34: =IF(W34<>"",IF(E34<>"",E34,($I$9-SUM($T$25:T33))*V34*W34/SUMPRODUCT($W34:$W$55,$V34:$V$55)),"") -> 3 | U34: =IF(W34<>"",IF(E34<>"",E34,($I$9-SUM($T$25:T33))*V34*W34/SUMPRODUCT($W34:$W$55,$V34:$V$55)),"") -> 3 | V34: 0.85310234 | W34: 0.85310234
A35: Рогалевич,Арапова | B35: 45972 | C35: вт | D35: 71465 | E35: 4 | F35: =IF(AND(E35<>"",E35<>0),D35/E35,"") -> 17866.25 | G35: 2 | H35: =IF(AND(G35<>"",G35<>0),D35/G35,"") -> 35732.5 | I35: 64 | J35: =IF(AND(G35<>"",G35<>0),E35/G35,"") -> 2 | K35: 68170 | N35: =IF(AND(I35<>"",I35<>0),G35/I35,"") -> 0.03125 | O35: =D35/P35 -> 0.58355114 | P35: =$I$8*V35*W35/SUMPRODUCT($W$25:$W$55,$V$25:$V$55) -> 122465.7 | Q35: =$I$9*V35*W35/SUMPRODUCT($W$25:$W$55,$V$25:$V$55) -> 18.840877 | R35: =IF($I$12="","",Q35/$I$12) -> 11.082869 | S35: =IF(W35<>"",IF(D35<>"",D35,($I$8-SUM($S$25:S34))*V35*W35/SUMPRODUCT($W35:$W$55,$V35:$V$55)),"") -> 71465 | T35: =IF(W35<>"",IF(E35<>"",E35,($I$9-SUM($T$25:T34))*V35*W35/SUMPRODUCT($W35:$W$55,$V35:$V$55)),"") -> 4 | U35: =IF(W35<>"",IF(E35<>"",E35,($I$9-SUM($T$25:T34))*V35*W35/SUMPRODUCT($W35:$W$55,$V35:$V$55)),"") -> 4 | V35: 1.2 | W35: 1.2
A36: Рогалевич,Арапова | B36: 45973 | C36: ср | D36: 56481 | E36: 5 | F36: =IF(AND(E36<>"",E36<>0),D36/E36,"") -> 11296.2 | G36: 3 | H36: =IF(AND(G36<>"",G36<>0),D36/G36,"") -> 18827 | I36: 69 | J36: =IF(AND(G36<>"",G36<>0),E36/G36,"") -> 1.6666667 | K36: 36977 | L36: 16902 | N36: =IF(AND(I36<>"",I36<>0),G36/I36,"") -> 0.043478261 | O36: =D36/P36 -> 0.91253206 | P36: =$I$8*V36*W36/SUMPRODUCT($W$25:$W$55,$V$25:$V$55) -> 61894.812 | Q36: =$I$9*V36*W36/SUMPRODUCT($W$25:$W$55,$V$25:$V$55) -> 9.5222788 | R36: =IF($I$12="","",Q36/$I$12) -> 5.6013404 | S36: =IF(W36<>"",IF(D36<>"",D36,($I$8-SUM($S$25:S35))*V36*W36/SUMPRODUCT($W36:$W$55,$V36:$V$55)),"") -> 56481 | T36: =IF(W36<>"",IF(E36<>"",E36,($I$9-SUM($T$25:T35))*V36*W36/SUMPRODUCT($W36:$W$55,$V36:$V$55)),"") -> 5 | U36: =IF(W36<>"",IF(E36<>"",E36,($I$9-SUM($T$25:T35))*V36*W36/SUMPRODUCT($W36:$W$55,$V36:$V$55)),"") -> 5 | V36: 0.85310234 | W36: 0.85310234
A37: Рогалевич | B37: 45974 | C37: чт | D37: 0 | H37: 0 | I37: 50 | J37: =IF(AND(G37<>"",G37<>0),E37/G37,"") | N37: =IF(AND(I37<>"",I37<>0),G37/I37,"") -> 0 | O37: =D37/P37 -> 0 | P37: =$I$8*V37*W37/SUMPRODUCT($W$25:$W$55,$V$25:$V$55) -> 61894.812 | Q37: =$I$9*V37*W37/SUMPRODUCT($W$25:$W$55,$V$25:$V$55) -> 9.5222788 | R37: =IF($I$12="","",Q37/$I$12) -> 5.6013404 | S37: =IF(W37<>"",IF(D37<>"",D37,($I$8-SUM($S$25:S36))*V37*W37/SUMPRODUCT($W37:$W$55,$V37:$V$55)),"") -> 0 | T37: =IF(W37<>"",IF(E37<>"",E37,($I$9-SUM($T$25:T36))*V37*W37/SUMPRODUCT($W37:$W$55,$V37:$V$55)),"") -> 12.438562 | U37: =IF(W37<>"",IF(E37<>"",E37,($I$9-SUM($T$25:T36))*V37*W37/SUMPRODUCT($W37:$W$55,$V37:$V$55)),"") -> 12.438562 | V37: 0.85310234 | W37: 0.85310234
A38: Рогалевич,Арапова | B38: 45975 | C38: пт | D38: 56141 | E38: 7 | F38: =IF(AND(E38<>"",E38<>0),D38/E38,"") -> 8020.1429 | G38: 4 | H38: =IF(AND(G38<>"",G38<>0),D38/G38,"") -> 14035.25 | I38: 72 | J38: =IF(AND(G38<>"",G38<>0),E38/G38,"") -> 1.75 | M38: 19883 | N38: =IF(AND(I38<>"",I38<>0),G38/I38,"") -> 0.055555556 | O38: =D38/P38 -> 0.81497285 | P38: =$I$8*V38*W38/SUMPRODUCT($W$25:$W$55,$V$25:$V$55) -> 68886.957 | Q38: =$I$9*V38*W38/SUMPRODUCT($W$25:$W$55,$V$25:$V$55) -> 10.597993 | R38: =IF($I$12="","",Q38/$I$12) -> 6.2341138 | S38: =IF(W38<>"",IF(D38<>"",D38,($I$8-SUM($S$25:S37))*V38*W38/SUMPRODUCT($W38:$W$55,$V38:$V$55)),"") -> 56141 | T38: =IF(W38<>"",IF(E38<>"",E38,($I$9-SUM($T$25:T37))*V38*W38/SUMPRODUCT($W38:$W$55,$V38:$V$55)),"") -> 7 | U38: =IF(W38<>"",IF(E38<>"",E38,($I$9-SUM($T$25:T37))*V38*W38/SUMPRODUCT($W38:$W$55,$V38:$V$55)),"") -> 7 | V38: 0.9 | W38: 0.9
A39: Рогалевич,Уразгильдеева | B39: 45976 | C39: сб | D39: 32254 | E39: 4 | F39: =IF(AND(E39<>"",E39<>0),D39/E39,"") -> 8063.5 | G39: 2 | H39: =IF(AND(G39<>"",G39<>0),D39/G39,"") -> 16127 | I39: 66 | J39: =IF(AND(G39<>"",G39<>0),E39/G39,"") -> 2 | K39: 19147 | N39: =IF(AND(I39<>"",I39<>0),G39/I39,"") -> 0.03030303 | O39: =D39/P39 -> 0.31343409 | P39: =$I$8*V39*W39/SUMPRODUCT($W$25:$W$55,$V$25:$V$55) -> 102905.21 | Q39: =$I$9*V39*W39/SUMPRODUCT($W$25:$W$55,$V$25:$V$55) -> 15.83157 | R39: =IF($I$12="","",Q39/$I$12) -> 9.3126885 | S39: =IF(W39<>"",IF(D39<>"",D39,($I$8-SUM($S$25:S38))*V39*W39/SUMPRODUCT($W39:$W$55,$V39:$V$55)),"") -> 32254 | T39: =IF(W39<>"",IF(E39<>"",E39,($I$9-SUM($T$25:T38))*V39*W39/SUMPRODUCT($W39:$W$55,$V39:$V$55)),"") -> 4 | U39: =IF(W39<>"",IF(E39<>"",E39,($I$9-SUM($T$25:T38))*V39*W39/SUMPRODUCT($W39:$W$55,$V39:$V$55)),"") -> 4 | V39: 1.1 | W39: 1.1
A40: Уразгильдеева,Арапова | B40: 45977 | C40: вс | D40: 25235 | E40: 5 | F40: =IF(AND(E40<>"",E40<>0),D40/E40,"") -> 5047 | G40: 4 | H40: =IF(AND(G40<>"",G40<>0),D40/G40,"") -> 6308.75 | I40: 70 | J40: =IF(AND(G40<>"",G40<>0),E40/G40,"") -> 1.25 | N40: =IF(AND(I40<>"",I40<>0),G40/I40,"") -> 0.057142857 | O40: =D40/P40 -> 0.29672308 | P40: =$I$8*V40*W40/SUMPRODUCT($W$25:$W$55,$V$25:$V$55) -> 85045.626 | Q40: =$I$9*V40*W40/SUMPRODUCT($W$25:$W$55,$V$25:$V$55) -> 13.083943 | R40: =IF($I$12="","",Q40/$I$12) -> 7.6964368 | S40: =IF(W40<>"",IF(D40<>"",D40,($I$8-SUM($S$25:S39))*V40*W40/SUMPRODUCT($W40:$W$55,$V40:$V$55)),"") -> 25235 | T40: =IF(W40<>"",IF(E40<>"",E40,($I$9-SUM($T$25:T39))*V40*W40/SUMPRODUCT($W40:$W$55,$V40:$V$55)),"") -> 5 | U40: =IF(W40<>"",IF(E40<>"",E40,($I$9-SUM($T$25:T39))*V40*W40/SUMPRODUCT($W40:$W$55,$V40:$V$55)),"") -> 5 | V40: 1 | W40: 1
A41: Уразгильдеева,Арапова | B41: 45978 | C41: пн | D41: 76121 | E41: 8 | F41: =IF(AND(E41<>"",E41<>0),D41/E41,"") -> 9515.125 | G41: 2 | H41: =IF(AND(G41<>"",G41<>0),D41/G41,"") -> 38060.5 | I41: 51 | J41: =IF(AND(G41<>"",G41<>0),E41/G41,"") -> 4 | K41: 45170 | N41: =IF(AND(I41<>"",I41<>0),G41/I41,"") -> 0.039215686 | O41: =D41/P41 -> 1.2298446 | P41: =$I$8*V41*W41/SUMPRODUCT($W$25:$W$55,$V$25:$V$55) -> 61894.812 | Q41: =$I$9*V41*W41/SUMPRODUCT($W$25:$W$55,$V$25:$V$55) -> 9.5222788 | R41: =IF($I$12="","",Q41/$I$12) -> 5.6013404 | S41: =IF(W41<>"",IF(D41<>"",D41,($I$8-SUM($S$25:S40))*V41*W41/SUMPRODUCT($W41:$W$55,$V41:$V$55)),"") -> 76121 | T41: =IF(W41<>"",IF(E41<>"",E41,($I$9-SUM($T$25:T40))*V41*W41/SUMPRODUCT($W41:$W$55,$V41:$V$55)),"") -> 8 | U41: =IF(W41<>"",IF(E41<>"",E41,($I$9-SUM($T$25:T40))*V41*W41/SUMPRODUCT($W41:$W$55,$V41:$V$55)),"") -> 8 | V41: 0.85310234 | W41: 0.85310234
A42: Рогалевич,Арапова | B42: 45979 | C42: вт | D42: 25769 | E42: 4 | F42: =IF(AND(E42<>"",E42<>0),D42/E42,"") -> 6442.25 | G42: 3 | H42: =IF(AND(G42<>"",G42<>0),D42/G42,"") -> 8589.6667 | I42: 43 | J42: =IF(AND(G42<>"",G42<>0),E42/G42,"") -> 1.3333333 | K42: 6890 | N42: =IF(AND(I42<>"",I42<>0),G42/I42,"") -> 0.069767442 | O42: =D42/P42 -> 0.41633538 | P42: =$I$8*V42*W42/SUMPRODUCT($W$25:$W$55,$V$25:$V$55) -> 61894.812 | Q42: =$I$9*V42*W42/SUMPRODUCT($W$25:$W$55,$V$25:$V$55) -> 9.5222788 | R42: =IF($I$12="","",Q42/$I$12) -> 5.6013404 | S42: =IF(W42<>"",IF(D42<>"",D42,($I$8-SUM($S$25:S41))*V42*W42/SUMPRODUCT($W42:$W$55,$V42:$V$55)),"") -> 25769 | T42: =IF(W42<>"",IF(E42<>"",E42,($I$9-SUM($T$25:T41))*V42*W42/SUMPRODUCT($W42:$W$55,$V42:$V$55)),"") -> 4 | U42: =IF(W42<>"",IF(E42<>"",E42,($I$9-SUM($T$25:T41))*V42*W42/SUMPRODUCT($W42:$W$55,$V42:$V$55)),"") -> 4 | V42: 0.85310234 | W42: 0.85310234
A43: Рогалевич,Уразгильдеева | B43: 45980 | C43: ср | D43: 34562 | E43: 5 | F43: =IF(AND(E43<>"",E43<>0),D43/E43,"") -> 6912.4 | G43: 4 | H43: =IF(AND(G43<>"",G43<>0),D43/G43,"") -> 8640.5 | I43: 52 | J43: =IF(AND(G43<>"",G43<>0),E43/G43,"") -> 1.25 | K43: 6993 | N43: =IF(AND(I43<>"",I43<>0),G43/I43,"") -> 0.076923077 | O43: =D43/P43 -> 0.56248252 | P43: =$I$8*V43*W43/SUMPRODUCT($W$25:$W$55,$V$25:$V$55) -> 61445.465 | Q43: =$I$9*V43*W43/SUMPRODUCT($W$25:$W$55,$V$25:$V$55) -> 9.4531485 | R43: =IF($I$12="","",Q43/$I$12) -> 5.5606756 | S43: =IF(W43<>"",IF(D43<>"",D43,($I$8-SUM($S$25:S42))*V43*W43/SUMPRODUCT($W43:$W$55,$V43:$V$55)),"") -> 34562 | T43: =IF(W43<>"",IF(E43<>"",E43,($I$9-SUM($T$25:T42))*V43*W43/SUMPRODUCT($W43:$W$55,$V43:$V$55)),"") -> 5 | U43: =IF(W43<>"",IF(E43<>"",E43,($I$9-SUM($T$25:T42))*V43*W43/SUMPRODUCT($W43:$W$55,$V43:$V$55)),"") -> 5 | V43: 0.85 | W43: 0.85
A44: Рогалевич,Уразгильдеева | B44: 45981 | C44: чт | D44: 0 | F44: =IF(AND(E44<>"",E44<>0),D44/E44,"") | H44: =IF(AND(G44<>"",G44<>0),D44/G44,"") | I44: 39 | J44: =IF(AND(G44<>"",G44<>0),E44/G44,"") | N44: =IF(AND(I44<>"",I44<>0),G44/I44,"") -> 0 | O44: =D44/P44 -> 0 | P44: =$I$8*V44*W44/SUMPRODUCT($W$25:$W$55,$V$25:$V$55) -> 61894.812 | Q44: =$I$9*V44*W44/SUMPRODUCT($W$25:$W$55,$V$25:$V$55) -> 9.5222788 | R44: =IF($I$12="","",Q44/$I$12) -> 5.6013404 | S44: =IF(W44<>"",IF(D44<>"",D44,($I$8-SUM($S$25:S43))*V44*W44/SUMPRODUCT($W44:$W$55,$V44:$V$55)),"") -> 0 | T44: =IF(W44<>"",IF(E44<>"",E44,($I$9-SUM($T$25:T43))*V44*W44/SUMPRODUCT($W44:$W$55,$V44:$V$55)),"") -> 17.377877 | U44: =IF(W44<>"",IF(E44<>"",E44,($I$9-SUM($T$25:T43))*V44*W44/SUMPRODUCT($W44:$W$55,$V44:$V$55)),"") -> 17.377877 | V44: 0.85310234 | W44: 0.85310234
A45: Рогалевич,Арапова | B45: 45982 | C45: пт | D45: 12506 | E45: 2 | F45: =IF(AND(E45<>"",E45<>0),D45/E45,"") -> 6253 | G45: 3 | H45: =IF(AND(G45<>"",G45<>0),D45/G45,"") -> 4168.6667 | I45: 84 | J45: =IF(AND(G45<>"",G45<>0),E45/G45,"") -> 0.66666667 | L45: 220 | N45: =IF(AND(I45<>"",I45<>0),G45/I45,"") -> 0.035714286 | O45: =D45/P45 -> 0.1815438 | P45: =$I$8*V45*W45/SUMPRODUCT($W$25:$W$55,$V$25:$V$55) -> 68886.957 | Q45: =$I$9*V45*W45/SUMPRODUCT($W$25:$W$55,$V$25:$V$55) -> 10.597993 | R45: =IF($I$12="","",Q45/$I$12) -> 6.2341138 | S45: =IF(W45<>"",IF(D45<>"",D45,($I$8-SUM($S$25:S44))*V45*W45/SUMPRODUCT($W45:$W$55,$V45:$V$55)),"") -> 12506 | T45: =IF(W45<>"",IF(E45<>"",E45,($I$9-SUM($T$25:T44))*V45*W45/SUMPRODUCT($W45:$W$55,$V45:$V$55)),"") -> 2 | U45: =IF(W45<>"",IF(E45<>"",E45,($I$9-SUM($T$25:T44))*V45*W45/SUMPRODUCT($W45:$W$55,$V45:$V$55)),"") -> 2 | V45: 0.9 | W45: 0.9
A46: Рогалевич,Арапова | B46: 45983 | C46: сб | D46: 89607 | E46: 11 | F46: =IF(AND(E46<>"",E46<>0),D46/E46,"") -> 8146.0909 | G46: 6 | H46: =IF(AND(G46<>"",G46<>0),D46/G46,"") -> 14934.5 | I46: 97 | J46: =IF(AND(G46<>"",G46<>0),E46/G46,"") -> 1.8333333 | K46: 32577 | N46: =IF(AND(I46<>"",I46<>0),G46/I46,"") -> 0.06185567 | O46: =D46/P46 -> 0.87077225 | P46: =$I$8*V46*W46/SUMPRODUCT($W$25:$W$55,$V$25:$V$55) -> 102905.21 | Q46: =$I$9*V46*W46/SUMPRODUCT($W$25:$W$55,$V$25:$V$55) -> 15.83157 | R46: =IF($I$12="","",Q46/$I$12) -> 9.3126885 | S46: =IF(W46<>"",IF(D46<>"",D46,($I$8-SUM($S$25:S45))*V46*W46/SUMPRODUCT($W46:$W$55,$V46:$V$55)),"") -> 89607 | T46: =IF(W46<>"",IF(E46<>"",E46,($I$9-SUM($T$25:T45))*V46*W46/SUMPRODUCT($W46:$W$55,$V46:$V$55)),"") -> 11 | U46: =IF(W46<>"",IF(E46<>"",E46,($I$9-SUM($T$25:T45))*V46*W46/SUMPRODUCT($W46:$W$55,$V46:$V$55)),"") -> 11 | V46: 1.1 | W46: 1.1
A47: Рогалевич,Уразгильдеева | B47: 45984 | C47: вс | D47: 86009 | E47: 9 | F47: =IF(AND(E47<>"",E47<>0),D47/E47,"") -> 9556.5556 | G47: 8 | H47: =IF(AND(G47<>"",G47<>0),D47/G47,"") -> 10751.125 | I47: 63 | J47: =IF(AND(G47<>"",G47<>0),E47/G47,"") -> 1.125 | K47: 58696 | N47: =IF(AND(I47<>"",I47<>0),G47/I47,"") -> 0.12698413 | O47: =D47/P47 -> 1.0113277 | P47: =$I$8*V47*W47/SUMPRODUCT($W$25:$W$55,$V$25:$V$55) -> 85045.626 | Q47: =$I$9*V47*W47/SUMPRODUCT($W$25:$W$55,$V$25:$V$55) -> 13.083943 | R47: =IF($I$12="","",Q47/$I$12) -> 7.6964368 | S47: =IF(W47<>"",IF(D47<>"",D47,($I$8-SUM($S$25:S46))*V47*W47/SUMPRODUCT($W47:$W$55,$V47:$V$55)),"") -> 86009 | T47: =IF(W47<>"",IF(E47<>"",E47,($I$9-SUM($T$25:T46))*V47*W47/SUMPRODUCT($W47:$W$55,$V47:$V$55)),"") -> 9 | U47: =IF(W47<>"",IF(E47<>"",E47,($I$9-SUM($T$25:T46))*V47*W47/SUMPRODUCT($W47:$W$55,$V47:$V$55)),"") -> 9 | V47: 1 | W47: 1
A48: Уразгильдеева,Арапова | B48: 45985 | C48: пн | D48: 29111 | E48: 4 | F48: =IF(AND(E48<>"",E48<>0),D48/E48,"") -> 7277.75 | G48: 2 | H48: =IF(AND(G48<>"",G48<>0),D48/G48,"") -> 14555.5 | I48: 38 | J48: =IF(AND(G48<>"",G48<>0),E48/G48,"") -> 2 | N48: =IF(AND(I48<>"",I48<>0),G48/I48,"") -> 0.052631579 | O48: =D48/P48 -> 0.53484158 | P48: =$I$8*V48*W48/SUMPRODUCT($W$25:$W$55,$V$25:$V$55) -> 54429.201 | Q48: =$I$9*V48*W48/SUMPRODUCT($W$25:$W$55,$V$25:$V$55) -> 8.3737232 | R48: =IF($I$12="","",Q48/$I$12) -> 4.9257195 | S48: =IF(W48<>"",IF(D48<>"",D48,($I$8-SUM($S$25:S47))*V48*W48/SUMPRODUCT($W48:$W$55,$V48:$V$55)),"") -> 29111 | T48: =IF(W48<>"",IF(E48<>"",E48,($I$9-SUM($T$25:T47))*V48*W48/SUMPRODUCT($W48:$W$55,$V48:$V$55)),"") -> 4 | U48: =IF(W48<>"",IF(E48<>"",E48,($I$9-SUM($T$25:T47))*V48*W48/SUMPRODUCT($W48:$W$55,$V48:$V$55)),"") -> 4 | V48: 0.8 | W48: 0.8
A49: Рогалевич,Арапова | B49: 45986 | C49: вт | D49: 12714 | E49: 2 | F49: =IF(AND(E49<>"",E49<>0),D49/E49,"") -> 6357 | G49: 2 | H49: =IF(AND(G49<>"",G49<>0),D49/G49,"") -> 6357 | I49: 41 | J49: =IF(AND(G49<>"",G49<>0),E49/G49,"") -> 1 | L49: 8821 | N49: =IF(AND(I49<>"",I49<>0),G49/I49,"") -> 0.048780488 | O49: =D49/P49 -> 0.23358785 | P49: =$I$8*V49*W49/SUMPRODUCT($W$25:$W$55,$V$25:$V$55) -> 54429.201 | Q49: =$I$9*V49*W49/SUMPRODUCT($W$25:$W$55,$V$25:$V$55) -> 8.3737232 | R49: =IF($I$12="","",Q49/$I$12) -> 4.9257195 | S49: =IF(W49<>"",IF(D49<>"",D49,($I$8-SUM($S$25:S48))*V49*W49/SUMPRODUCT($W49:$W$55,$V49:$V$55)),"") -> 12714 | T49: =IF(W49<>"",IF(E49<>"",E49,($I$9-SUM($T$25:T48))*V49*W49/SUMPRODUCT($W49:$W$55,$V49:$V$55)),"") -> 2 | U49: =IF(W49<>"",IF(E49<>"",E49,($I$9-SUM($T$25:T48))*V49*W49/SUMPRODUCT($W49:$W$55,$V49:$V$55)),"") -> 2 | V49: 0.8 | W49: 0.8
A50: Рогалевич,Уразгильдеева | B50: 45987 | C50: ср | F50: =IF(AND(E50<>"",E50<>0),D50/E50,"") | H50: =IF(AND(G50<>"",G50<>0),D50/G50,"") | I50: 44 | J50: =IF(AND(G50<>"",G50<>0),E50/G50,"") | N50: =IF(AND(I50<>"",I50<>0),G50/I50,"") -> 0 | O50: =D50/P50 -> 0 | P50: =$I$8*V50*W50/SUMPRODUCT($W$25:$W$55,$V$25:$V$55) -> 54429.201 | Q50: =$I$9*V50*W50/SUMPRODUCT($W$25:$W$55,$V$25:$V$55) -> 8.3737232 | R50: =IF($I$12="","",Q50/$I$12) -> 4.9257195 | S50: =IF(W50<>"",IF(D50<>"",D50,($I$8-SUM($S$25:S49))*V50*W50/SUMPRODUCT($W50:$W$55,$V50:$V$55)),"") -> 207285.8 | T50: =IF(W50<>"",IF(E50<>"",E50,($I$9-SUM($T$25:T49))*V50*W50/SUMPRODUCT($W50:$W$55,$V50:$V$55)),"") -> 30.216712 | U50: =IF(W50<>"",IF(E50<>"",E50,($I$9-SUM($T$25:T49))*V50*W50/SUMPRODUCT($W50:$W$55,$V50:$V$55)),"") -> 30.216712 | V50: 0.8 | W50: 0.8
A51: Рогалевич,Уразгильдеева | B51: 45988 | C51: чт | D51: 17908 | E51: 3 | F51: =IF(AND(E51<>"",E51<>0),D51/E51,"") -> 5969.3333 | G51: 2 | H51: =IF(AND(G51<>"",G51<>0),D51/G51,"") -> 8954 | I51: 51 | J51: =IF(AND(G51<>"",G51<>0),E51/G51,"") -> 1.5 | N51: =IF(AND(I51<>"",I51<>0),G51/I51,"") -> 0.039215686 | O51: =D51/P51 -> 0.32901457 | P51: =$I$8*V51*W51/SUMPRODUCT($W$25:$W$55,$V$25:$V$55) -> 54429.201 | Q51: =$I$9*V51*W51/SUMPRODUCT($W$25:$W$55,$V$25:$V$55) -> 8.3737232 | R51: =IF($I$12="","",Q51/$I$12) -> 4.9257195 | S51: =IF(W51<>"",IF(D51<>"",D51,($I$8-SUM($S$25:S50))*V51*W51/SUMPRODUCT($W51:$W$55,$V51:$V$55)),"") -> 17908 | T51: =IF(W51<>"",IF(E51<>"",E51,($I$9-SUM($T$25:T50))*V51*W51/SUMPRODUCT($W51:$W$55,$V51:$V$55)),"") -> 3 | U51: =IF(W51<>"",IF(E51<>"",E51,($I$9-SUM($T$25:T50))*V51*W51/SUMPRODUCT($W51:$W$55,$V51:$V$55)),"") -> 3 | V51: 0.8 | W51: 0.8
A52: Рогалевич,Арапова | B52: 45989 | C52: пт | D52: 34481 | E52: 4 | F52: =IF(AND(E52<>"",E52<>0),D52/E52,"") -> 8620.25 | G52: 3 | H52: =IF(AND(G52<>"",G52<>0),D52/G52,"") -> 11493.667 | I52: 47 | J52: =IF(AND(G52<>"",G52<>0),E52/G52,"") -> 1.3333333 | K52: 6993 | M52: 7693 | N52: =IF(AND(I52<>"",I52<>0),G52/I52,"") -> 0.063829787 | O52: =D52/P52 -> 0.63350186 | P52: =$I$8*V52*W52/SUMPRODUCT($W$25:$W$55,$V$25:$V$55) -> 54429.201 | Q52: =$I$9*V52*W52/SUMPRODUCT($W$25:$W$55,$V$25:$V$55) -> 8.3737232 | R52: =IF($I$12="","",Q52/$I$12) -> 4.9257195 | S52: =IF(W52<>"",IF(D52<>"",D52,($I$8-SUM($S$25:S51))*V52*W52/SUMPRODUCT($W52:$W$55,$V52:$V$55)),"") -> 34481 | T52: =IF(W52<>"",IF(E52<>"",E52,($I$9-SUM($T$25:T51))*V52*W52/SUMPRODUCT($W52:$W$55,$V52:$V$55)),"") -> 4 | U52: =IF(W52<>"",IF(E52<>"",E52,($I$9-SUM($T$25:T51))*V52*W52/SUMPRODUCT($W52:$W$55,$V52:$V$55)),"") -> 4 | V52: 0.8 | W52: 0.8
A53: Уразгильдеева,Арапова | B53: 45990 | C53: сб | D53: 37336 | E53: 8 | F53: =IF(AND(E53<>"",E53<>0),D53/E53,"") -> 4667 | G53: 4 | H53: =IF(AND(G53<>"",G53<>0),D53/G53,"") -> 9334 | I53: 64 | J53: =IF(AND(G53<>"",G53<>0),E53/G53,"") -> 2 | N53: =IF(AND(I53<>"",I53<>0),G53/I53,"") -> 0.0625 | O53: =D53/P53 -> 0.68595532 | P53: =$I$8*V53*W53/SUMPRODUCT($W$25:$W$55,$V$25:$V$55) -> 54429.201 | Q53: =$I$9*V53*W53/SUMPRODUCT($W$25:$W$55,$V$25:$V$55) -> 8.3737232 | R53: =IF($I$12="","",Q53/$I$12) -> 4.9257195 | S53: =IF(W53<>"",IF(D53<>"",D53,($I$8-SUM($S$25:S52))*V53*W53/SUMPRODUCT($W53:$W$55,$V53:$V$55)),"") -> 37336 | T53: =IF(W53<>"",IF(E53<>"",E53,($I$9-SUM($T$25:T52))*V53*W53/SUMPRODUCT($W53:$W$55,$V53:$V$55)),"") -> 8 | U53: =IF(W53<>"",IF(E53<>"",E53,($I$9-SUM($T$25:T52))*V53*W53/SUMPRODUCT($W53:$W$55,$V53:$V$55)),"") -> 8 | V53: 0.8 | W53: 0.8
A54: Уразгильдеева,Арапова | B54: 45991 | C54: вс | F54: =IF(AND(E54<>"",E54<>0),D54/E54,"") | H54: =IF(AND(G54<>"",G54<>0),D54/G54,"") | I54: 30 | J54: =IF(AND(G54<>"",G54<>0),E54/G54,"") | N54: =IF(AND(I54<>"",I54<>0),G54/I54,"") -> 0 | O54: =D54/P54 -> 0 | P54: =$I$8*V54*W54/SUMPRODUCT($W$25:$W$55,$V$25:$V$55) -> 54429.201 | Q54: =$I$9*V54*W54/SUMPRODUCT($W$25:$W$55,$V$25:$V$55) -> 8.3737232 | R54: =IF($I$12="","",Q54/$I$12) -> 4.9257195 | S54: =IF(W54<>"",IF(D54<>"",D54,($I$8-SUM($S$25:S53))*V54*W54/SUMPRODUCT($W54:$W$55,$V54:$V$55)),"") -> 739418.2 | T54: =IF(W54<>"",IF(E54<>"",E54,($I$9-SUM($T$25:T53))*V54*W54/SUMPRODUCT($W54:$W$55,$V54:$V$55)),"") -> 105.86685 | U54: =IF(W54<>"",IF(E54<>"",E54,($I$9-SUM($T$25:T53))*V54*W54/SUMPRODUCT($W54:$W$55,$V54:$V$55)),"") -> 105.86685 | V54: 0.8 | W54: 0.8
F55: =IF(AND(E55<>"",E55<>0),D55/E55,"") | H55: =IF(AND(G55<>"",G55<>0),D55/G55,"") | J55: =IF(AND(G55<>"",G55<>0),E55/G55,"") | N55: =IF(AND(I55<>"",I55<>0),G55/I55,"") | O55: =D55/P55 -> #DIV/0! | P55: =$I$8*V55*W55/SUMPRODUCT($W$25:$W$55,$V$25:$V$55) -> 0 | Q55: =$I$9*V55*W55/SUMPRODUCT($W$25:$W$55,$V$25:$V$55) -> 0 | R55: =IF($I$12="","",Q55/$I$12) -> 0 | S55: =IF(W55<>"",IF(D55<>"",D55,($I$8-SUM($S$25:S54))*V55*W55/SUMPRODUCT($W55:$W$55,$V55:$V$55)),"") | T55: =IF(W55<>"",IF(E55<>"",E55,($I$9-SUM($T$25:T54))*V55*W55/SUMPRODUCT($W55:$W$55,$V55:$V$55)),"") | U55: =IF(W55<>"",IF(E55<>"",E55,($I$9-SUM($T$25:T54))*V55*W55/SUMPRODUCT($W55:$W$55,$V55:$V$55)),"")
B56: итого | D56: =SUM(D25:D55) -> 1119646 | E56: =SUM(E25:E55) -> 152 | F56: =IF(AND(E56<>"", E56<>0), D56/E56, "") -> 7366.0921 | G56: =SUM(G25:G55) -> 97 | H56: =IF(AND(G56<>"", G56<>0), D56/G56, "") -> 11542.742 | I56: =SUM(I25:I55)*0.8 -> 1555.2 | J56: =E56/G56 -> 1.5670103 | K56: =SUM(K25:K55) -> 416418 | L56: =SUM(L25:L55) -> 46449 | M56: =SUM(M25:M55) -> 72847 | N56: =IF(AND(I56<>"", I56<>0), G56/I56, "") -> 0.062371399 | O56: =D56/P56 -> 0.54184722 | P56: =SUM(P25:P55) -> 2066350 | Q56: =SUM(Q25:Q55) -> 317.9 | R56: =SUM(R25:R55) -> 187 | S56: =SUM(S25:S55) -> 2066350 | T56: =SUM(T25:T55) -> 317.9 | U56: =SUM(U25:U55) -> 314.9
D57: =SUMIF(D25:D55,"",P25:P55)+D56 -> 1228504.4 | I57: =I56/J14 -> 51.84
D58: ='Рогалевич И. Е. '!J8+'Уразгильдеева Е. Р. '!J8+'Арапова А. В.'!J8+'Доп сотрудник'!D57 -> 1119646 | E58: ='Рогалевич И. Е. '!E57+'Уразгильдеева Е. Р. '!E57+'Арапова А. В.'!E57+'Доп сотрудник'!E57 -> 152 | G58: ='Рогалевич И. Е. '!G57+'Уразгильдеева Е. Р. '!G57+'Арапова А. В.'!G57+'Доп сотрудник'!G57 -> 98 | I58: ='Рогалевич И. Е. '!I57+'Уразгильдеева Е. Р. '!I57 -> 744 | K58: ='Рогалевич И. Е. '!K57+'Уразгильдеева Е. Р. '!K57+'Арапова А. В.'!K57 -> 416418 | L58: ='Рогалевич И. Е. '!L57+'Уразгильдеева Е. Р. '!L57+'Арапова А. В.'!L57 -> 46449 | M58: ='Рогалевич И. Е. '!M57+'Уразгильдеева Е. Р. '!M57 -> 72847

Sheet Конкурс
A1: Сотрудник | B1: Длина чека | C1: КВП
D2: 9 | E2: 10 | F2: 11 | G2: 12 | H2: 13 | I2: 14 | J2: 15 | K2: 16 | L2: 17 | M2: 18 | N2: 19 | O2: 20 | P2: 21 | Q2: 22 | R2: 23 | S2: 24 | T2: 25 | U2: 26 | V2: 27 | W2: 28 | X2: 29 | Y2: 30 | Z2: Итого
A3: =График!B29 -> Рогалевич Ирина | B3: ='Рогалевич И. Е. '!J12 -> 1.62 | C3: ='Рогалевич И. Е. '!K8 -> 0.76619217 | Z3: =SUM(D3:Y3) -> 0
A4: =График!B28 -> Уразгильдеева Екатерина | B4: ='Уразгильдеева Е. Р. '!J12 -> 1.6818182 | C4: ='Уразгильдеева Е. Р. '!K8 -> 0.56110975 | Z4: =SUM(D4:Y4) -> 0
A5: =График!B27 -> Арапова Анна-Мария | B5: ='[1]Яковенко А. К'!J12 -> #REF! | C5: ='[1]Яковенко А. К'!K8 -> #REF! | Z5: =SUM(D5:Y5) -> 0

Sheet Св. по пок.
A1: 1-20.08
A2: Показатель | D2: ='Ялта, Ленина, 18'!I3 -> ул. Набережная Ленина, 18 | G2: =График!B29 -> Рогалевич Ирина | J2: =График!B28 -> Уразгильдеева Екатерина | M2: =График!B27 -> Арапова Анна-Мария
D3: Факт | F3: Прогноз | G3: Факт | I3: Прогноз | J3: Факт | L3: Прогноз | M3: Факт | O3: Прогноз
A4: Выручка | D4: ='Ялта, Ленина, 18'!K8 -> 0.54184722 | E4: ='Ялта, Ленина, 18'!J8 -> 1119646 | F4: ='Ялта, Ленина, 18'!M8 -> 0.57197998 | G4: ='Рогалевич И. Е. '!K8 -> 0.76619217 | H4: ='Рогалевич И. Е. '!J8 -> 641915 | I4: ='Рогалевич И. Е. '!M8 -> 1.0081476 | J4: ='Уразгильдеева Е. Р. '!K8 -> 0.56110975 | K4: ='Уразгильдеева Е. Р. '!J8 -> 263849 | L4: ='Уразгильдеева Е. Р. '!M8 -> 0.72944267 | M4: ='[1]Яковенко А. К'!K8 -> #REF! | N4: ='[1]Яковенко А. К'!J8 -> #REF! | O4: ='[1]Яковенко А. К'!M8 -> #REF!
A5: Кол-во изделий | D5: ='Ялта, Ленина, 18'!K9 -> 0.47813778 | E5: ='Ялта, Ленина, 18'!J9 -> 152 | F5: ='Ялта, Ленина, 18'!M9 -> 0.53880075 | G5: ='Рогалевич И. Е. '!K9 -> 0.62843239 | H5: ='Рогалевич И. Е. '!J9 -> 81 | I5: ='Рогалевич И. Е. '!M9 -> 0.82688472 | J5: ='Уразгильдеева Е. Р. '!K9 -> 0.51145502 | K5: ='Уразгильдеева Е. Р. '!J9 -> 37 | L5: ='Уразгильдеева Е. Р. '!M9 -> 0.66489152 | M5: ='[1]Яковенко А. К'!K9 -> #REF! | N5: ='[1]Яковенко А. К'!J9 -> #REF! | O5: ='[1]Яковенко А. К'!M9 -> #REF!
A6: Средний чек | D6: ='Ялта, Ленина, 18'!K10 -> 1.0445921 | E6: ='Ялта, Ленина, 18'!J10 -> 11542.742 | F6: ='Ялта, Ленина, 18'!M10 -> 1.0445921 | G6: ='Рогалевич И. Е. '!K10 -> 1.1618371 | H6: ='Рогалевич И. Е. '!J10 -> 12838.3 | I6: ='Рогалевич И. Е. '!M10 -> 1.1618371 | J6: ='Уразгильдеева Е. Р. '!K10 -> 1.0853517 | K6: ='Уразгильдеева Е. Р. '!J10 -> 11993.136 | L6: ='Уразгильдеева Е. Р. '!M10 -> 1.0853517 | M6: ='[1]Яковенко А. К'!K10 -> #REF! | N6: ='[1]Яковенко А. К'!J10 -> #REF! | O6: ='[1]Яковенко А. К'!M10 -> #REF!
A7: Средняя стоимость изделия | D7: ='Ялта, Ленина, 18'!K11 -> 1.1332449 | E7: ='Ялта, Ленина, 18'!J11 -> 7366.0921 | F7: ='Ялта, Ленина, 18'!M11 -> 1.0615798 | G7: ='Рогалевич И. Е. '!K11 -> 1.2192118 | H7: ='Рогалевич И. Е. '!J11 -> 7924.8765 | I7: ='Рогалевич И. Е. '!M11 -> 1.2192118 | J7: ='Уразгильдеева Е. Р. '!K11 -> 1.0970852 | K7: ='Уразгильдеева Е. Р. '!J11 -> 7131.0541 | L7: ='Уразгильдеева Е. Р. '!M11 -> 1.0970852 | M7: ='[1]Яковенко А. К'!K11 -> #REF! | N7: ='[1]Яковенко А. К'!J11 -> #REF! | O7: ='[1]Яковенко А. К'!M11 -> #REF!
A8: Длина чека | D8: ='Ялта, Ленина, 18'!K12 -> 0.92177077 | E8: ='Ялта, Ленина, 18'!J12 -> 1.5670103 | F8: ='Ялта, Ленина, 18'!M12 -> 0.92177077 | G8: ='Рогалевич И. Е. '!K12 -> 0.95294118 | H8: ='Рогалевич И. Е. '!J12 -> 1.62 | I8: ='Рогалевич И. Е. '!M12 -> 0.95294118 | J8: ='Уразгильдеева Е. Р. '!K12 -> 0.98930481 | K8: ='Уразгильдеева Е. Р. '!J12 -> 1.6818182 | L8: ='Уразгильдеева Е. Р. '!M12 -> 0.98930481 | M8: ='[1]Яковенко А. К'!K12 -> #REF! | N8: ='[1]Яковенко А. К'!J12 -> #REF! | O8: ='[1]Яковенко А. К'!M12 -> #REF!
A9: Кол-во чеков | D9: ='Ялта, Ленина, 18'!K13 -> 0.51871658 | E9: ='Ялта, Ленина, 18'!J13 -> 97 | F9: ='Ялта, Ленина, 18'!M13 -> 0.58452792 | G9: ='Рогалевич И. Е. '!K13 -> 0.65946609 | H9: ='Рогалевич И. Е. '!J13 -> 50 | I9: ='Рогалевич И. Е. '!M13 -> 0.86771853 | J9: ='Уразгильдеева Е. Р. '!K13 -> 0.51698426 | K9: ='Уразгильдеева Е. Р. '!J13 -> 22 | L9: ='Уразгильдеева Е. Р. '!M13 -> 0.67207954 | M9: ='[1]Яковенко А. К'!K13 -> #REF! | N9: ='[1]Яковенко А. К'!J13 -> #REF! | O9: ='[1]Яковенко А. К'!M13 -> #REF!
A10: Кол-во смен план/отработано | D10: ='Ялта, Ленина, 18'!K14 -> 1 | E10: ='Ялта, Ленина, 18'!J14 -> 30 | G10: ='Рогалевич И. Е. '!K14 -> 1 | H10: ='Рогалевич И. Е. '!J14 -> 25 | J10: ='Уразгильдеева Е. Р. '!K14 -> 1 | K10: ='Уразгильдеева Е. Р. '!J14 -> 13 | M10: ='[1]Яковенко А. К'!K14 -> #REF! | N10: ='[1]Яковенко А. К'!J14 -> #REF!
A11: Средние продажи в смену | D11: ='Ялта, Ленина, 18'!K15 -> 0.54184722 | E11: ='Ялта, Ленина, 18'!J15 -> 37321.533 | F11: ='Ялта, Ленина, 18'!M15 -> 0.54184722 | G11: ='Рогалевич И. Е. '!K15 -> 0.37278196 | H11: ='Рогалевич И. Е. '!J15 -> 25676.6 | I11: ='Рогалевич И. Е. '!M15 -> 0.37278196 | J11: ='Уразгильдеева Е. Р. '!K15 -> 0.29466562 | K11: ='Уразгильдеева Е. Р. '!J15 -> 20296.077 | L11: ='Уразгильдеева Е. Р. '!M15 -> 0.29466562 | M11: ='[1]Яковенко А. К'!K15 -> #REF! | N11: ='[1]Яковенко А. К'!J15 -> #REF! | O11: ='[1]Яковенко А. К'!M15 -> #REF!
A12: Трафик | D12: ='Ялта, Ленина, 18'!K17 -> 0.91482353 | E12: ='Ялта, Ленина, 18'!J17 -> 1555.2 | F12: ='Ялта, Ленина, 18'!M17 -> 0.91482353 | G12: ='Рогалевич И. Е. '!K17 -> 0.73556847 | H12: ='Рогалевич И. Е. '!J17 -> 507 | I12: ='Рогалевич И. Е. '!M17 -> 0.73556847 | J12: ='Уразгильдеева Е. Р. '!K17 -> 0.61262635 | K12: ='Уразгильдеева Е. Р. '!J17 -> 237 | L12: ='Уразгильдеева Е. Р. '!M17 -> 0.61262635 | M12: ='[1]Яковенко А. К'!K17 -> #REF! | N12: ='[1]Яковенко А. К'!J17 -> #REF! | O12: ='[1]Яковенко А. К'!M17 -> #REF!
A13: UNOde50 | D13: ='Ялта, Ленина, 18'!S19 -> 0.40825294 | E13: ='Ялта, Ленина, 18'!T18 -> 416418 | F13: ='Ялта, Ленина, 18'!T19 -> 0.40825294 | G13: ='Рогалевич И. Е. '!S19 -> 0.71370212 | H13: ='Рогалевич И. Е. '!T18 -> 295157 | I13: ='Рогалевич И. Е. '!T19 -> 0.71370212 | J13: ='Уразгильдеева Е. Р. '!S19 -> 0.39326993 | K13: ='Уразгильдеева Е. Р. '!T18 -> 91284 | L13: ='Уразгильдеева Е. Р. '!T19 -> 0.39326993 | M13: ='[1]Яковенко А. К'!S19 -> #REF! | N13: ='[1]Яковенко А. К'!T18 -> #REF! | O13: ='[1]Яковенко А. К'!T19 -> #REF!
A14: IS | D14: ='Ялта, Ленина, 18'!S13 -> 0.091076471 | E14: ='Ялта, Ленина, 18'!T12 -> 46449 | F14: ='Ялта, Ленина, 18'!T13 -> 0.091076471 | G14: ='Рогалевич И. Е. '!S13 -> 0.058531132 | H14: ='Рогалевич И. Е. '!T12 -> 12103 | I14: ='Рогалевич И. Е. '!T13 -> 0.058531132 | J14: ='Уразгильдеева Е. Р. '!S13 -> 0 | K14: ='Уразгильдеева Е. Р. '!T12 -> 0 | L14: ='Уразгильдеева Е. Р. '!T13 -> 0 | M14: ='[1]Яковенко А. К'!S13 -> #REF! | N14: ='[1]Яковенко А. К'!T12 -> #REF! | O14: ='[1]Яковенко А. К'!T13 -> #REF!
A15: ='Ялта, Ленина, 18'!M23 -> Agafi | D15: ='Ялта, Ленина, 18'!V13 -> 0.15176458 | E15: ='Ялта, Ленина, 18'!W12 -> 72847 | F15: ='Ялта, Ленина, 18'!W13 -> 0.15176458 | G15: ='Рогалевич И. Е. '!V13 -> 0.37431265 | H15: ='Рогалевич И. Е. '!W12 -> 72847 | I15: ='Рогалевич И. Е. '!W13 -> 0.37431265 | J15: ='Уразгильдеева Е. Р. '!V13 -> 0 | K15: ='Уразгильдеева Е. Р. '!W12 -> 0 | L15: ='Уразгильдеева Е. Р. '!W13 -> 0 | M15: ='[1]Яковенко А. К'!V13 -> #REF! | N15: ='[1]Яковенко А. К'!W12 -> #REF! | O15: ='[1]Яковенко А. К'!W13 -> #REF!
A16: Отклонение от плана | D16: ='Ялта, Ленина, 18'!J16 -> -946704 | G16: ='Рогалевич И. Е. '!N8 -> 6826.0417 | J16: ='Уразгильдеева Е. Р. '!N8 -> -127223.38 | M16: ='[1]Яковенко А. К'!N8 -> #REF!

Sheet План на день
A1: Выручка | D1: 85046
A2: Кол-во изделий | D2: =D1/D4 -> 13.084
A3: Средний чек | D3: =D4*D5 -> 11050
A4: Средняя стоимость изделия | D4: ='Ялта, Ленина, 18'!I11 -> 6500
A5: Длина чека | D5: ='Ялта, Ленина, 18'!I12 -> 1.7
A6: Кол-во чеков | D6: =IF(D5<>0,D2/D5,"") -> 7.6964706
A7: Конверсия | D7: ='Ялта, Ленина, 18'!I20 -> 0.11
A8: IS | D8: =('Ялта, Ленина, 18'!S12-'Ялта, Ленина, 18'!T12)/('Ялта, Ленина, 18'!I14-'Ялта, Ленина, 18'!J14) -> #DIV/0!
A9: UNOde50 | D9: =('Ялта, Ленина, 18'!S18-'Ялта, Ленина, 18'!T18)/('Ялта, Ленина, 18'!I14-'Ялта, Ленина, 18'!J14) -> #DIV/0!
A10: ='Ялта, Ленина, 18'!M23 -> Agafi | D10: =('Ялта, Ленина, 18'!V12-'Ялта, Ленина, 18'!W12)/('Ялта, Ленина, 18'!I14-'Ялта, Ленина, 18'!J14) -> #DIV/0!

Sheet Рогалевич И. Е. 
B1: =TODAY()-1 -> 46000
B2: (отчетная дата) | J2: ЕЖЕДНЕВНЫЙ ОТЧЕТ О ПРОДАЖАХ
B3: Осталось до выполнения плана!!! | J3: =График!B29 -> Рогалевич Ирина
C4: =I8-D57 -> 195883.96 | E4: =IF(I8<>0,C4/I8,0) -> 0.23380783
F6: Целевые показатели
F7: Показатель | I7: План | J7: Факт | K7: % выполнения | L7: Прогноз выполнения | M7: % выполнения по прогнозу | N7: Отклонение | O7: Факт аналогичного месяца прошлого года | P7: Отклонение LFL
F8: Выручка | I8: ='Ялта, Ленина, 18'!I8/График!AJ31*График!AJ29 -> 837798.96 | J8: =D57 -> 641915 | K8: =IF(AND(I8<>"",I8<>0,J8<>""),J8/I8,"") -> 0.76619217 | L8: =IF(SUMIF($D$25:$D$56,">=0",$P$25:$P$56)<>0,I8*D57/SUMIF($D$25:$D$56,">=0",$P$25:$P$56),0) -> 844625 | M8: =IF(AND(I8<>"",I8<>0,L8<>"",L8<>0),L8/I8,"") -> 1.0081476 | N8: =IF(AND(J8<>0,J8<>"",I8<>0,I8<>""),L8-I8,"") -> 6826.0417 | P8: =IF(AND(O8<>"",O8<>0,L8<>"",L8<>0),-O8+L8,"") | Q8: =IF(AND(P8<>"",P8<>0,O8<>0,O8<>""),P8/O8,"")
F9: Кол-во изделий | I9: =I8/I11 -> 128.89215 | J9: =E57 -> 81 | K9: =IF(AND(I9<>"",I9<>0,J9<>""),J9/I9,"") -> 0.62843239 | L9: =IF(SUMIF($E$25:$E$54,">=0",$Q$25:$Q$54)<>0,I9*E57/SUMIF($E$25:$E$54,">=0",$Q$25:$Q$54),0) -> 106.57895 | M9: =IF(AND(I9<>"",I9<>0,L9<>"",L9<>0),L9/I9,"") -> 0.82688472 | N9: =IF(AND(J9<>0,J9<>"",I9<>0,I9<>""),L9-I9,"") -> -22.3132 | O9: =O8/O11 -> #DIV/0! | P9: =IF(AND(O9<>"",O9<>0,L9<>"",L9<>0),-O9+L9,"") -> #DIV/0! | Q9: =IF(AND(P9<>"",P9<>0,O9<>0,O9<>""),P9/O9,"") -> #DIV/0!
F10: Средний чек | I10: =I11*I12 -> 11050 | J10: =H57 -> 12838.3 | K10: =IF(AND(I10<>"",I10<>0,J10<>""),J10/I10,"") -> 1.1618371 | L10: =J10 -> 12838.3 | M10: =IF(AND(I10<>"",I10<>0,L10<>"",L10<>0),L10/I10,"") -> 1.1618371 | N10: =IF(AND(J10<>0,J10<>"",I10<>0,I10<>""),L10-I10,"") -> 1788.3 | O10: =O11*O12 -> 0 | P10: =IF(AND(O10<>"",O10<>0,L10<>"",L10<>0),-O10+L10,"") | Q10: =IF(AND(P10<>"",P10<>0,O10<>0,O10<>""),P10/O10,"") | S10: IS | V10: =M23 -> Agafi
F11: Средняя стоимость изделия | I11: ='Ялта, Ленина, 18'!I11 -> 6500 | J11: =F57 -> 7924.8765 | K11: =IF(AND(I11<>"",I11<>0,J11<>""),J11/I11,"") -> 1.2192118 | L11: =IF(L9>0,L8/L9,"") -> 7924.8765 | M11: =IF(AND(I11<>"",I11<>0,L11<>"",L11<>0),L11/I11,"") -> 1.2192118 | N11: =IF(AND(J11<>0,J11<>"",I11<>0,I11<>""),L11-I11,"") -> 1424.8765 | P11: =IF(AND(O11<>"",O11<>0,L11<>"",L11<>0),-O11+L11,"") | Q11: =IF(AND(P11<>"",P11<>0,O11<>0,O11<>""),P11/O11,"")
F12: Длина чека | I12: ='Ялта, Ленина, 18'!I12 -> 1.7 | J12: =J57 -> 1.62 | K12: =IF(AND(I12<>"",I12<>0,J12<>""),J12/I12,"") -> 0.95294118 | L12: =J12 -> 1.62 | M12: =IF(AND(I12<>"",I12<>0,L12<>"",L12<>0),L12/I12,"") -> 0.95294118 | N12: =IF(AND(J12<>0,J12<>"",I12<>0,I12<>""),L12-I12,"") -> -0.08 | P12: =IF(AND(O12<>"",O12<>0,L12<>"",L12<>0),-O12+L12,"") | Q12: =IF(AND(P12<>"",P12<>0,O12<>0,O12<>""),P12/O12,"") | S12: ='Ялта, Ленина, 18'!S12*График!AJ29/График!AJ31 -> 206778.85 | T12: =L57 -> 12103 | V12: ='Ялта, Ленина, 18'!V12/График!AJ31*График!AJ29 -> 194615.38 | W12: =M57 -> 72847
F13: Кол-во чеков | I13: =IF(I12<>0,I9/I12,"") -> 75.81891 | J13: =G57 -> 50 | K13: =IF(AND(I13<>"",I13<>0,J13<>""),J13/I13,"") -> 0.65946609 | L13: =IF(SUMIF($G$25:$G$54,">=0",$R$25:$R$54)<>0,I13*G57/SUMIF($G$25:$G$54,">=0",$R$25:$R$54),"") -> 65.789474 | M13: =IF(AND(I13<>"",I13<>0,L13<>"",L13<>0),L13/I13,"") -> 0.86771853 | N13: =IF(AND(J13<>0,J13<>"",I13<>0,I13<>""),L13-I13,"") -> -10.029437 | P13: =IF(AND(O13<>"",O13<>0,L13<>"",L13<>0),-O13+L13,"") | Q13: =IF(AND(P13<>"",P13<>0,O13<>0,O13<>""),P13/O13,"") | S13: =T12/S12 -> 0.058531132 | T13: =S13/J14*I14 -> 0.058531132 | V13: =W12/V12 -> 0.37431265 | W13: =V13/J14*I14 -> 0.37431265
F14: Кол-во смен план/отработано | I14: =График!AI29 -> 25 | J14: 25 | K14: =IF(AND(I14<>"",I14<>0,J14<>""),J14/I14,"") -> 1 | L14: =I14 -> 25 | M14: =IF(AND(I14<>"",I14<>0,L14<>"",L14<>0),L14/I14,"") -> 1 | N14: =IF(AND(J14<>0,J14<>"",I14<>0,I14<>""),L14-I14,"") -> 0 | P14: =IF(AND(O14<>"",O14<>0,L14<>"",L14<>0),-O14+L14,"") | Q14: =IF(AND(P14<>"",P14<>0,O14<>0,O14<>""),P14/O14,"")
F15: Средние продажи в смену | I15: ='Ялта, Ленина, 18'!I15 -> 68878.333 | J15: =J8/J14 -> 25676.6 | K15: =IF(AND(I15<>"",I15<>0,J15<>""),J15/I15,"") -> 0.37278196 | L15: =J15 -> 25676.6 | M15: =IF(AND(I15<>"",I15<>0,L15<>"",L15<>0),L15/I15,"") -> 0.37278196 | N15: =IF(AND(J15<>0,J15<>"",I15<>0,I15<>""),L15-I15,"") -> -43201.733 | P15: =IF(AND(O15<>"",O15<>0,L15<>"",L15<>0),-O15+L15,"") | Q15: =IF(AND(P15<>"",P15<>0,O15<>0,O15<>""),P15/O15,"")
F16: Отставание/Перевыполнение | J16: =J8-I15*J14 -> -1080043.3 | K16: =IF(AND(I16<>"",I16<>0,J16<>""),J16/I16,"") | L16: =J16 -> -1080043.3 | M16: =IF(AND(I16<>"",I16<>0,L16<>"",L16<>0),L16/I16,"") | N16: =IF(AND(J16<>0,J16<>"",I16<>0,I16<>""),L16-I16,"") | P16: =IF(AND(O16<>"",O16<>0,L16<>"",L16<>0),-O16+L16,"") | Q16: =IF(AND(P16<>"",P16<>0,O16<>0,O16<>""),P16/O16,"") | S16: UNOde50
F17: Трафик | I17: ='Ялта, Ленина, 18'!I17/График!AJ31*График!AJ29 -> 689.26282 | J17: =I57 -> 507 | K17: =IF(AND(I17<>"",I17<>0,J17<>""),J17/I17,"") -> 0.73556847 | L17: =J17/J14*I14 -> 507 | M17: =IF(AND(I17<>"",I17<>0,L17<>"",L17<>0),L17/I17,"") -> 0.73556847 | N17: =IF(AND(J17<>0,J17<>"",I17<>0,I17<>""),L17-I17,"") -> -182.26282 | P17: =IF(AND(O17<>"",O17<>0,L17<>"",L17<>0),-O17+L17,"") | Q17: =IF(AND(P17<>"",P17<>0,O17<>0,O17<>""),P17/O17,"")
K18: =IF(AND(I18<>"",I18<>0,J18<>""),J18/I18,"") | L18: =J18 -> 0 | M18: =IF(AND(I18<>"",I18<>0,L18<>"",L18<>0),L18/I18,"") | N18: =IF(AND(J18<>0,J18<>"",I18<>0,I18<>""),L18-I18,"") | O18: 0 | P18: =IF(AND(O18<>"",O18<>0,L18<>"",L18<>0),-O18+L18,"") | Q18: =IF(AND(P18<>"",P18<>0,O18<>0,O18<>""),P18/O18,"") | S18: ='Ялта, Ленина, 18'!S18*График!AJ29/График!AJ31 -> 413557.69 | T18: =K57 -> 295157
K19: =IF(AND(I19<>"",I19<>0,J19<>""),J19/I19,"") | L19: =J19 -> 0 | M19: =IF(AND(I19<>"",I19<>0,L19<>"",L19<>0),L19/I19,"") | N19: =IF(AND(J19<>0,J19<>"",I19<>0,I19<>""),L19-I19,"") | O19: 0 | P19: =IF(AND(O19<>"",O19<>0,L19<>"",L19<>0),-O19+L19,"") | Q19: =IF(AND(P19<>"",P19<>0,O19<>0,O19<>""),P19/O19,"") | S19: =T18/S18 -> 0.71370212 | T19: =S19/J14*I14 -> 0.71370212
F20: Конверсия план/факт | I20: ='Ялта, Ленина, 18'!I20 -> 0.11 | J20: =N57 -> 0.098619329 | K20: =J20/I20 -> 0.89653936 | L20: =IF(AND(K8<>0,I14<>0,I57<>0),(I57*N57+(I57/K8-I57)*I20)/(I57/K8),0) -> 0.10128022 | M20: =IF(AND(I20<>"",I20<>0,L20<>"",L20<>0),L20/I20,"") -> 0.92072927 | N20: =IF(AND(J20<>0,J20<>"",I20<>0,I20<>""),L20-I20,"") -> -0.0087197807 | P20: =IF(AND(O20<>"",O20<>0,L20<>"",L20<>0),-O20+L20,"") | Q20: =IF(AND(P20<>"",P20<>0,O20<>0,O20<>""),P20/O20,"")
B22: Факт продаж за месяц | O22: % выполнения дневного плана | P22: Раcпределение плана по дням
B23: Дата | C23: День недели | D23: Выручка (руб) | E23: Кол-во единиц (шт.) | F23: Средняя стоимость изделия (руб.) | G23: Количество чеков (шт.) | H23: Средняя сумма чека (руб.) | I23: Трафик | J23: Длина чека (шт.) | K23: UNOde50 | L23: IS | M23: Agafi | N23: Конверсия (%) | P23: выручка, план | Q23: кол-во ед, план | R23: Кол-во чеков, план | S23: выручка, скорректир.план | T23: кол-во ед, скорр. план | U23: кол-во чеков, скорр. план | V23: Коэфф. Дня Недели | W23: Специфика месяца
B24: 1 | C24: 2 | D24: 3 | E24: 4 | F24: 5 | G24: 6 | H24: 7 | I24: 8 | J24: 9 | K24: 10 | L24: 11 | M24: 12 | N24: 13 | P24: 1 | Q24: 2 | R24: 3 | S24: 4 | T24: 5 | U24: 6 | V24: 10 | W24: 11
A25: 1 | B25: 45962 | C25: сб | D25: =6983+10268+6992+12103 -> 36346 | E25: 6 | F25: =IF(AND(E25<>"",E25<>0),D25/E25,"") -> 6057.6667 | G25: 4 | H25: =IF(AND(G25<>"",G25<>0),D25/G25,"") -> 9086.5 | I25: 20 | J25: =IF(AND(G25<>"",G25<>0),E25/G25,"") -> 1.5 | K25: 10268 | L25: 12103 | M25: 6992 | N25: =IF(AND(I25<>"",I25<>0),G25/I25,"") -> 0.2 | O25: =D25/P25 -> 1.0845681 | P25: =$I$8*V25*W25/SUMPRODUCT($W$25:$W$56,$V$25:$V$56) -> 33511.958 | Q25: =$I$9*V25*W25/SUMPRODUCT($W$25:$W$56,$V$25:$V$56) -> 5.1556859 | R25: =IF($I$12="","",Q25/$I$12) -> 3.0327564 | S25: =IF(D25<>"",D25,P25) -> 36346 | T25: =IF(E25<>"",E25,Q25) -> 6 | U25: =IF(G25<>"",G25,R25) -> 4 | V25: 1 | W25: 1
A26: 2 | B26: 45963 | C26: вс | D26: =63254+31287+32389 -> 126930 | E26: 15 | F26: =IF(AND(E26<>"",E26<>0),D26/E26,"") -> 8462 | G26: 8 | H26: =IF(AND(G26<>"",G26<>0),D26/G26,"") -> 15866.25 | I26: 40 | J26: =IF(AND(G26<>"",G26<>0),E26/G26,"") -> 1.875 | K26: 63254 | M26: 31287 | N26: =IF(AND(I26<>"",I26<>0),G26/I26,"") -> 0.2 | O26: =D26/P26 -> 3.7876032 | P26: =$I$8*V26*W26/SUMPRODUCT($W$25:$W$56,$V$25:$V$56) -> 33511.958 | Q26: =$I$9*V26*W26/SUMPRODUCT($W$25:$W$58,$V$25:$V$58) -> 5.1556859 | R26: =IF($I$12="","",Q26/$I$12) -> 3.0327564 | S26: =IF(W26<>"",IF(D26<>"",D26,($I$8-SUM($S$25:S25))*V26*W26/SUMPRODUCT($W26:$W$56,$V26:$V$56)),"") -> 126930 | T26: =IF(W26<>"",IF(E26<>"",E26,($I$9-SUM($T$25:T25))*V26*W26/SUMPRODUCT($W26:$W$58,$V26:$V$58)),"") -> 15 | U26: =IF(W26<>"",IF($I$12<>"",IF(G26<>"",G26,($I$9/$I$12-SUM($U$25:U25))*V26*W26/SUMPRODUCT($W26:$W$58,$V26:$V$58)),""),"") -> 8 | V26: 1 | W26: 1
A27: 3 | B27: 45964 | C27: пн | D27: 8692 | E27: 1 | F27: 8692 | G27: 1 | H27: =IF(AND(G27<>"",G27<>0),D27/G27,"") -> 8692 | I27: 25 | J27: =IF(AND(G27<>"",G27<>0),E27/G27,"") -> 1 | K27: 8692 | N27: =IF(AND(I27<>"",I27<>0),G27/I27,"") -> 0.04 | O27: =D27/P27 -> 0.2593701 | P27: =$I$8*V27*W27/SUMPRODUCT($W$25:$W$56,$V$25:$V$56) -> 33511.958 | Q27: =$I$9*V27*W27/SUMPRODUCT($W$25:$W$58,$V$25:$V$58) -> 5.1556859 | R27: =IF($I$12="","",Q27/$I$12) -> 3.0327564 | S27: =IF(W27<>"",IF(D27<>"",D27,($I$8-SUM($S$25:S26))*V27*W27/SUMPRODUCT($W27:$W$58,$V27:$V$58)),"") -> 8692 | T27: =IF(W27<>"",IF(E27<>"",E27,($I$9-SUM($T$25:T26))*V27*W27/SUMPRODUCT($W27:$W$58,$V27:$V$58)),"") -> 1 | U27: =IF(W27<>"",IF($I$12<>"",IF(G27<>"",G27,($I$9/$I$12-SUM($U$25:U26))*V27*W27/SUMPRODUCT($W27:$W$58,$V27:$V$58)),""),"") -> 1 | V27: 1 | W27: 1
A28: 4 | B28: 45965 | C28: вт | D28: =8539+16490 -> 25029 | E28: 3 | F28: =IF(AND(E28<>"",E28<>0),D28/E28,"") -> 8343 | G28: 3 | H28: =IF(AND(G28<>"",G28<>0),D28/G28,"") -> 8343 | I28: 30 | J28: =IF(AND(G28<>"",G28<>0),E28/G28,"") -> 1 | K28: 16490 | N28: =IF(AND(I28<>"",I28<>0),G28/I28,"") -> 0.1 | O28: =D28/P28 -> 0.74686772 | P28: =$I$8*V28*W28/SUMPRODUCT($W$25:$W$56,$V$25:$V$56) -> 33511.958 | Q28: =$I$9*V28*W28/SUMPRODUCT($W$25:$W$58,$V$25:$V$58) -> 5.1556859 | R28: =IF($I$12="","",Q28/$I$12) -> 3.0327564 | S28: =IF(W28<>"",IF(D28<>"",D28,($I$8-SUM($S$25:S27))*V28*W28/SUMPRODUCT($W28:$W$58,$V28:$V$58)),"") -> 25029 | T28: =IF(W28<>"",IF(E28<>"",E28,($I$9-SUM($T$25:T27))*V28*W28/SUMPRODUCT($W28:$W$58,$V28:$V$58)),"") -> 3 | U28: =IF(W28<>"",IF($I$12<>"",IF(G28<>"",G28,($I$9/$I$12-SUM($U$25:U27))*V28*W28/SUMPRODUCT($W28:$W$58,$V28:$V$58)),""),"") -> 3 | V28: 1 | W28: 1
A29: 5 | B29: 45966 | C29: ср | D29: 28069 | E29: 6 | F29: =IF(AND(E29<>"",E29<>0),D29/E29,"") -> 4678.1667 | G29: 2 | H29: =IF(AND(G29<>"",G29<>0),D29/G29,"") -> 14034.5 | I29: 35 | J29: =IF(AND(G29<>"",G29<>0),E29/G29,"") -> 3 | N29: =IF(AND(I29<>"",I29<>0),G29/I29,"") -> 0.057142857 | O29: =D29/P29 -> 0.83758161 | P29: =$I$8*V29*W29/SUMPRODUCT($W$25:$W$56,$V$25:$V$56) -> 33511.958 | Q29: =$I$9*V29*W29/SUMPRODUCT($W$25:$W$58,$V$25:$V$58) -> 5.1556859 | R29: =IF($I$12="","",Q29/$I$12) -> 3.0327564 | S29: =IF(W29<>"",IF(D29<>"",D29,($I$8-SUM($S$25:S28))*V29*W29/SUMPRODUCT($W29:$W$58,$V29:$V$58)),"") -> 28069 | T29: =IF(W29<>"",IF(E29<>"",E29,($I$9-SUM($T$25:T28))*V29*W29/SUMPRODUCT($W29:$W$58,$V29:$V$58)),"") -> 6 | U29: =IF(W29<>"",IF($I$12<>"",IF(G29<>"",G29,($I$9/$I$12-SUM($U$25:U28))*V29*W29/SUMPRODUCT($W29:$W$58,$V29:$V$58)),""),"") -> 2 | V29: 1 | W29: 1
A30: 6 | B30: 45967 | C30: чт | D30: 14400 | E30: 4 | F30: =IF(AND(E30<>"",E30<>0),D30/E30,"") -> 3600 | G30: 2 | H30: =IF(AND(G30<>"",G30<>0),D30/G30,"") -> 7200 | I30: 30 | J30: =IF(AND(G30<>"",G30<>0),E30/G30,"") -> 2 | N30: =IF(AND(I30<>"",I30<>0),G30/I30,"") -> 0.066666667 | O30: =D30/P30 -> 0.42969736 | P30: =$I$8*V30*W30/SUMPRODUCT($W$25:$W$56,$V$25:$V$56) -> 33511.958 | Q30: =$I$9*V30*W30/SUMPRODUCT($W$25:$W$58,$V$25:$V$58) -> 5.1556859 | R30: =IF($I$12="","",Q30/$I$12) -> 3.0327564 | S30: =IF(W30<>"",IF(D30<>"",D30,($I$8-SUM($S$25:S29))*V30*W30/SUMPRODUCT($W30:$W$58,$V30:$V$58)),"") -> 14400 | T30: =IF(W30<>"",IF(E30<>"",E30,($I$9-SUM($T$25:T29))*V30*W30/SUMPRODUCT($W30:$W$58,$V30:$V$58)),"") -> 4 | U30: =IF(W30<>"",IF($I$12<>"",IF(G30<>"",G30,($I$9/$I$12-SUM($U$25:U29))*V30*W30/SUMPRODUCT($W30:$W$58,$V30:$V$58)),""),"") -> 2 | V30: 1 | W30: 1
A31: 7 | B31: 45968 | C31: пт | D31: 25849 | E31: 6 | F31: =IF(AND(E31<>"",E31<>0),D31/E31,"") -> 4308.1667 | G31: 3 | H31: =IF(AND(G31<>"",G31<>0),D31/G31,"") -> 8616.3333 | I31: 20 | J31: =IF(AND(G31<>"",G31<>0),E31/G31,"") -> 2 | N31: =IF(AND(I31<>"",I31<>0),G31/I31,"") -> 0.15 | O31: =D31/P31 -> 0.7713366 | P31: =$I$8*V31*W31/SUMPRODUCT($W$25:$W$56,$V$25:$V$56) -> 33511.958 | Q31: =$I$9*V31*W31/SUMPRODUCT($W$25:$W$58,$V$25:$V$58) -> 5.1556859 | R31: =IF($I$12="","",Q31/$I$12) -> 3.0327564 | S31: =IF(W31<>"",IF(D31<>"",D31,($I$8-SUM($S$25:S30))*V31*W31/SUMPRODUCT($W31:$W$58,$V31:$V$58)),"") -> 25849 | T31: =IF(W31<>"",IF(E31<>"",E31,($I$9-SUM($T$25:T30))*V31*W31/SUMPRODUCT($W31:$W$58,$V31:$V$58)),"") -> 6 | U31: =IF(W31<>"",IF($I$12<>"",IF(G31<>"",G31,($I$9/$I$12-SUM($U$25:U30))*V31*W31/SUMPRODUCT($W31:$W$58,$V31:$V$58)),""),"") -> 3 | V31: 1 | W31: 1
A32: 8 | B32: 45969 | C32: сб | D32: =20809+5892 -> 26701 | E32: 3 | F32: =IF(AND(E32<>"",E32<>0),D32/E32,"") -> 8900.3333 | G32: 3 | H32: =IF(AND(G32<>"",G32<>0),D32/G32,"") -> 8900.3333 | I32: 20 | J32: =IF(AND(G32<>"",G32<>0),E32/G32,"") -> 1 | K32: 20809 | N32: =IF(AND(I32<>"",I32<>0),G32/I32,"") -> 0.15 | O32: =D32/P32 -> 0.79676036 | P32: =$I$8*V32*W32/SUMPRODUCT($W$25:$W$56,$V$25:$V$56) -> 33511.958 | Q32: =$I$9*V32*W32/SUMPRODUCT($W$25:$W$58,$V$25:$V$58) -> 5.1556859 | R32: =IF($I$12="","",Q32/$I$12) -> 3.0327564 | S32: =IF(W32<>"",IF(D32<>"",D32,($I$8-SUM($S$25:S31))*V32*W32/SUMPRODUCT($W32:$W$58,$V32:$V$58)),"") -> 26701 | T32: =IF(W32<>"",IF(E32<>"",E32,($I$9-SUM($T$25:T31))*V32*W32/SUMPRODUCT($W32:$W$58,$V32:$V$58)),"") -> 3 | U32: =IF(W32<>"",IF($I$12<>"",IF(G32<>"",G32,($I$9/$I$12-SUM($U$25:U31))*V32*W32/SUMPRODUCT($W32:$W$58,$V32:$V$58)),""),"") -> 3 | V32: 1 | W32: 1
A33: 9 | B33: 45970 | C33: вс | D33: 6992 | E33: 1 | F33: =IF(AND(E33<>"",E33<>0),D33/E33,"") -> 6992 | G33: 1 | H33: =IF(AND(G33<>"",G33<>0),D33/G33,"") -> 6992 | I33: 35 | J33: =IF(AND(G33<>"",G33<>0),E33/G33,"") -> 1 | M33: 6992 | N33: =IF(AND(I33<>"",I33<>0),G33/I33,"") -> 0.028571429 | O33: =D33/P33 -> 0.20864194 | P33: =$I$8*V33*W33/SUMPRODUCT($W$25:$W$56,$V$25:$V$56) -> 33511.958 | Q33: =$I$9*V33*W33/SUMPRODUCT($W$25:$W$58,$V$25:$V$58) -> 5.1556859 | R33: =IF($I$12="","",Q33/$I$12) -> 3.0327564 | S33: =IF(W33<>"",IF(D33<>"",D33,($I$8-SUM($S$25:S32))*V33*W33/SUMPRODUCT($W33:$W$58,$V33:$V$58)),"") -> 6992 | T33: =IF(W33<>"",IF(E33<>"",E33,($I$9-SUM($T$25:T32))*V33*W33/SUMPRODUCT($W33:$W$58,$V33:$V$58)),"") -> 1 | U33: =IF(W33<>"",IF($I$12<>"",IF(G33<>"",G33,($I$9/$I$12-SUM($U$25:U32))*V33*W33/SUMPRODUCT($W33:$W$58,$V33:$V$58)),""),"") -> 1 | V33: 1 | W33: 1
A34: 10 | B34: 45971 | C34: пн | D34: 30575 | E34: 3 | F34: =IF(AND(E34<>"",E34<>0),D34/E34,"") -> 10191.667 | G34: 2 | H34: =IF(AND(G34<>"",G34<>0),D34/G34,"") -> 15287.5 | I34: 20 | J34: =IF(AND(G34<>"",G34<>0),E34/G34,"") -> 1.5 | K34: 15292 | N34: =IF(AND(I34<>"",I34<>0),G34/I34,"") -> 0.1 | O34: =D34/P34 -> 0.91236089 | P34: =$I$8*V34*W34/SUMPRODUCT($W$25:$W$56,$V$25:$V$56) -> 33511.958 | Q34: =$I$9*V34*W34/SUMPRODUCT($W$25:$W$58,$V$25:$V$58) -> 5.1556859 | R34: =IF($I$12="","",Q34/$I$12) -> 3.0327564 | S34: =IF(W34<>"",IF(D34<>"",D34,($I$8-SUM($S$25:S33))*V34*W34/SUMPRODUCT($W34:$W$58,$V34:$V$58)),"") -> 30575 | T34: =IF(W34<>"",IF(E34<>"",E34,($I$9-SUM($T$25:T33))*V34*W34/SUMPRODUCT($W34:$W$58,$V34:$V$58)),"") -> 3 | U34: =IF(W34<>"",IF($I$12<>"",IF(G34<>"",G34,($I$9/$I$12-SUM($U$25:U33))*V34*W34/SUMPRODUCT($W34:$W$58,$V34:$V$58)),""),"") -> 2 | V34: 1 | W34: 1
A35: 11 | B35: 45972 | C35: вт | D35: 71465 | E35: 4 | F35: =IF(AND(E35<>"",E35<>0),D35/E35,"") -> 17866.25 | G35: 2 | H35: =IF(AND(G35<>"",G35<>0),D35/G35,"") -> 35732.5 | I35: 20 | J35: =IF(AND(G35<>"",G35<>0),E35/G35,"") -> 2 | K35: 68170 | N35: =IF(AND(I35<>"",I35<>0),G35/I35,"") -> 0.1 | O35: =D35/P35 -> 2.1325223 | P35: =$I$8*V35*W35/SUMPRODUCT($W$25:$W$56,$V$25:$V$56) -> 33511.958 | Q35: =$I$9*V35*W35/SUMPRODUCT($W$25:$W$58,$V$25:$V$58) -> 5.1556859 | R35: =IF($I$12="","",Q35/$I$12) -> 3.0327564 | S35: =IF(W35<>"",IF(D35<>"",D35,($I$8-SUM($S$25:S34))*V35*W35/SUMPRODUCT($W35:$W$58,$V35:$V$58)),"") -> 71465 | T35: =IF(W35<>"",IF(E34<>"",E34,($I$9-SUM($T$25:T34))*V35*W35/SUMPRODUCT($W35:$W$58,$V35:$V$58)),"") -> 3 | U35: =IF(W35<>"",IF($I$12<>"",IF(G35<>"",G35,($I$9/$I$12-SUM($U$25:U34))*V35*W35/SUMPRODUCT($W35:$W$58,$V35:$V$58)),""),"") -> 2 | V35: 1 | W35: 1
A36: 11 | B36: 45973 | C36: ср | D36: 39579 | E36: 4 | F36: =IF(AND(E36<>"",E36<>0),D36/E36,"") -> 9894.75 | G36: 2 | H36: =IF(AND(G36<>"",G36<>0),D36/G36,"") -> 19789.5 | I36: 15 | J36: =IF(AND(G36<>"",G36<>0),E36/G36,"") -> 2 | K36: 36977 | N36: =IF(AND(I36<>"",I36<>0),G36/I36,"") -> 0.13333333 | O36: =D36/P36 -> 1.1810411 | P36: =$I$8*V36*W36/SUMPRODUCT($W$25:$W$56,$V$25:$V$56) -> 33511.958 | Q36: =$I$9*V36*W36/SUMPRODUCT($W$25:$W$58,$V$25:$V$58) -> 5.1556859 | R36: =IF($I$12="","",Q36/$I$12) -> 3.0327564 | S36: =IF(W36<>"",IF(D36<>"",D36,($I$8-SUM($S$25:S35))*V36*W36/SUMPRODUCT($W36:$W$58,$V36:$V$58)),"") -> 39579 | T36: =IF(W36<>"",IF(E35<>"",E35,($I$9-SUM($T$25:T35))*V36*W36/SUMPRODUCT($W36:$W$58,$V36:$V$58)),"") -> 4 | U36: =IF(W36<>"",IF($I$12<>"",IF(G36<>"",G36,($I$9/$I$12-SUM($U$25:U35))*V36*W36/SUMPRODUCT($W36:$W$58,$V36:$V$58)),""),"") -> 2 | V36: 1 | W36: 1
A37: 13 | B37: 45974 | C37: чт | F37: =IF(AND(E37<>"",E37<>0),D37/E37,"") | H37: =IF(AND(G37<>"",G37<>0),D37/G37,"") | I37: 15 | J37: =IF(AND(G37<>"",G37<>0),E37/G37,"") | N37: =IF(AND(I37<>"",I37<>0),G37/I37,"") -> 0 | O37: =D37/P37 -> 0 | P37: =$I$8*V37*W37/SUMPRODUCT($W$25:$W$56,$V$25:$V$56) -> 33511.958 | Q37: =$I$9*V37*W37/SUMPRODUCT($W$25:$W$58,$V$25:$V$58) -> 5.1556859 | R37: =IF($I$12="","",Q37/$I$12) -> 3.0327564 | S37: =IF(W37<>"",IF(D37<>"",D37,($I$8-SUM($S$25:S36))*V37*W37/SUMPRODUCT($W37:$W$58,$V37:$V$58)),"") -> 30551.689 | T37: =IF(W37<>"",IF(E37<>"",E37,($I$9-SUM($T$25:T36))*V37*W37/SUMPRODUCT($W37:$W$58,$V37:$V$58)),"") -> 5.6840113 | U37: =IF(W37<>"",IF($I$12<>"",IF(G37<>"",G37,($I$9/$I$12-SUM($U$25:U36))*V37*W37/SUMPRODUCT($W37:$W$58,$V37:$V$58)),""),"") -> 3.2937623 | V37: 1 | W37: 1
A38: 14 | B38: 45975 | C38: пт | D38: 24575 | E38: 3 | F38: =IF(AND(E38<>"",E38<>0),D38/E38,"") -> 8191.6667 | G38: 2 | H38: =IF(AND(G38<>"",G38<>0),D38/G38,"") -> 12287.5 | I38: 20 | J38: =IF(AND(G38<>"",G38<>0),E38/G38,"") -> 1.5 | M38: 19883 | N38: =IF(AND(I38<>"",I38<>0),G38/I38,"") -> 0.1 | O38: =D38/P38 -> 0.73332032 | P38: =$I$8*V38*W38/SUMPRODUCT($W$25:$W$56,$V$25:$V$56) -> 33511.958 | Q38: =$I$9*V38*W38/SUMPRODUCT($W$25:$W$58,$V$25:$V$58) -> 5.1556859 | R38: =IF($I$12="","",Q38/$I$12) -> 3.0327564 | S38: =IF(W38<>"",IF(D38<>"",D38,($I$8-SUM($S$25:S37))*V38*W38/SUMPRODUCT($W38:$W$58,$V38:$V$58)),"") -> 24575 | T38: =IF(W38<>"",IF(E38<>"",E38,($I$9-SUM($T$25:T37))*V38*W38/SUMPRODUCT($W38:$W$58,$V38:$V$58)),"") -> 3 | U38: =IF(W38<>"",IF($I$12<>"",IF(G38<>"",G38,($I$9/$I$12-SUM($U$25:U37))*V38*W38/SUMPRODUCT($W38:$W$58,$V38:$V$58)),""),"") -> 2 | V38: 1 | W38: 1
A39: 15 | B39: 45976 | C39: сб | D39: 24262 | E39: 3 | F39: =IF(AND(E39<>"",E39<>0),D39/E39,"") -> 8087.3333 | G39: 1 | H39: =IF(AND(G39<>"",G39<>0),D39/G39,"") -> 24262 | I39: 15 | J39: =IF(AND(G39<>"",G39<>0),E39/G39,"") -> 3 | K39: 11155 | N39: =IF(AND(I39<>"",I39<>0),G39/I39,"") -> 0.066666667 | O39: =D39/P39 -> 0.72398037 | P39: =$I$8*V39*W39/SUMPRODUCT($W$25:$W$56,$V$25:$V$56) -> 33511.958 | Q39: =$I$9*V39*W39/SUMPRODUCT($W$25:$W$58,$V$25:$V$58) -> 5.1556859 | R39: =IF($I$12="","",Q39/$I$12) -> 3.0327564 | S39: =IF(W39<>"",IF(D39<>"",D39,($I$8-SUM($S$25:S38))*V39*W39/SUMPRODUCT($W39:$W$58,$V39:$V$58)),"") -> 24262 | T39: =IF(W39<>"",IF(E39<>"",E39,($I$9-SUM($T$25:T38))*V39*W39/SUMPRODUCT($W39:$W$58,$V39:$V$58)),"") -> 3 | U39: =IF(W39<>"",IF($I$12<>"",IF(G39<>"",G39,($I$9/$I$12-SUM($U$25:U38))*V39*W39/SUMPRODUCT($W39:$W$58,$V39:$V$58)),""),"") -> 1 | V39: 1 | W39: 1
A40: 16 | B40: 45979 | C40: вт | D40: 25769 | E40: 4 | F40: =IF(AND(E40<>"",E40<>0),D40/E40,"") -> 6442.25 | G40: 3 | H40: =IF(AND(G40<>"",G40<>0),D40/G40,"") -> 8589.6667 | I40: 11 | J40: =IF(AND(G40<>"",G40<>0),E40/G40,"") -> 1.3333333 | K40: 6890 | N40: =IF(AND(I40<>"",I40<>0),G40/I40,"") -> 0.27272727 | O40: =D40/P40 -> 0.76894939 | P40: =$I$8*V40*W40/SUMPRODUCT($W$25:$W$56,$V$25:$V$56) -> 33511.958 | Q40: =$I$9*V40*W40/SUMPRODUCT($W$25:$W$58,$V$25:$V$58) -> 5.1556859 | R40: =IF($I$12="","",Q40/$I$12) -> 3.0327564 | S40: =IF(W40<>"",IF(D40<>"",D40,($I$8-SUM($S$25:S39))*V40*W40/SUMPRODUCT($W40:$W$58,$V40:$V$58)),"") -> 25769 | T40: =IF(W40<>"",IF(E40<>"",E40,($I$9-SUM($T$25:T39))*V40*W40/SUMPRODUCT($W40:$W$58,$V40:$V$58)),"") -> 4 | U40: =IF(W40<>"",IF($I$12<>"",IF(G40<>"",G40,($I$9/$I$12-SUM($U$25:U39))*V40*W40/SUMPRODUCT($W40:$W$58,$V40:$V$58)),""),"") -> 3 | V40: 1 | W40: 1
A41: 17 | B41: 45980 | C41: ср | D41: =6993+6393 -> 13386 | E41: 2 | F41: =IF(AND(E41<>"",E41<>0),D41/E41,"") -> 6693 | G41: 2 | H41: =IF(AND(G41<>"",G41<>0),D41/G41,"") -> 6693 | I41: 10 | J41: =IF(AND(G41<>"",G41<>0),E41/G41,"") -> 1 | K41: 6993 | N41: =IF(AND(I41<>"",I41<>0),G41/I41,"") -> 0.2 | O41: =D41/P41 -> 0.3994395 | P41: =$I$8*V41*W41/SUMPRODUCT($W$25:$W$56,$V$25:$V$56) -> 33511.958 | Q41: =$I$9*V41*W41/SUMPRODUCT($W$25:$W$58,$V$25:$V$58) -> 5.1556859 | R41: =IF($I$12="","",Q41/$I$12) -> 3.0327564 | S41: =IF(W41<>"",IF(D41<>"",D41,($I$8-SUM($S$25:S40))*V41*W41/SUMPRODUCT($W41:$W$58,$V41:$V$58)),"") -> 13386 | T41: =IF(W41<>"",IF(E41<>"",E41,($I$9-SUM($T$25:T40))*V41*W41/SUMPRODUCT($W41:$W$58,$V41:$V$58)),"") -> 2 | U41: =IF(W41<>"",IF($I$12<>"",IF(G41<>"",G41,($I$9/$I$12-SUM($U$25:U40))*V41*W41/SUMPRODUCT($W41:$W$58,$V41:$V$58)),""),"") -> 2 | V41: 1 | W41: 1
A42: 18 | B42: 45981 | C42: чт | F42: =IF(AND(E42<>"",E42<>0),D42/E42,"") | H42: =IF(AND(G42<>"",G42<>0),D42/G42,"") | I42: 10 | J42: =IF(AND(G42<>"",G42<>0),E42/G42,"") | N42: =IF(AND(I42<>"",I42<>0),G42/I42,"") -> 0 | O42: =D42/P42 -> 0 | P42: =$I$8*V42*W42/SUMPRODUCT($W$25:$W$56,$V$25:$V$56) -> 33511.958 | Q42: =$I$9*V42*W42/SUMPRODUCT($W$25:$W$58,$V$25:$V$58) -> 5.1556859 | R42: =IF($I$12="","",Q42/$I$12) -> 3.0327564 | S42: =IF(W42<>"",IF(D42<>"",D42,($I$8-SUM($S$25:S41))*V42*W42/SUMPRODUCT($W42:$W$58,$V42:$V$58)),"") -> 34828.534 | T42: =IF(W42<>"",IF(E42<>"",E42,($I$9-SUM($T$25:T41))*V42*W42/SUMPRODUCT($W42:$W$58,$V42:$V$58)),"") -> 7.026017 | U42: =IF(W42<>"",IF($I$12<>"",IF(G42<>"",G42,($I$9/$I$12-SUM($U$25:U41))*V42*W42/SUMPRODUCT($W42:$W$58,$V42:$V$58)),""),"") -> 3.9406435 | V42: 1 | W42: 1
A43: 19 | B43: 45982 | C43: пт | F43: =IF(AND(E43<>"",E43<>0),D43/E43,"") | H43: =IF(AND(G43<>"",G43<>0),D43/G43,"") | I43: 14 | J43: =IF(AND(G43<>"",G43<>0),E43/G43,"") | N43: =IF(AND(I43<>"",I43<>0),G43/I43,"") -> 0 | O43: =D43/P43 -> 0 | P43: =$I$8*V43*W43/SUMPRODUCT($W$25:$W$56,$V$25:$V$56) -> 33511.958 | Q43: =$I$9*V43*W43/SUMPRODUCT($W$25:$W$58,$V$25:$V$58) -> 5.1556859 | R43: =IF($I$12="","",Q43/$I$12) -> 3.0327564 | S43: =IF(W43<>"",IF(D43<>"",D43,($I$8-SUM($S$25:S42))*V43*W43/SUMPRODUCT($W43:$W$58,$V43:$V$58)),"") -> 34828.534 | T43: =IF(W43<>"",IF(E43<>"",E43,($I$9-SUM($T$25:T42))*V43*W43/SUMPRODUCT($W43:$W$58,$V43:$V$58)),"") -> 7.026017 | U43: =IF(W43<>"",IF($I$12<>"",IF(G43<>"",G43,($I$9/$I$12-SUM($U$25:U42))*V43*W43/SUMPRODUCT($W43:$W$58,$V43:$V$58)),""),"") -> 3.9406435 | V43: 1 | W43: 1
A44: 20 | B44: 45983 | C44: сб | D44: 58441 | E44: 7 | F44: =IF(AND(E44<>"",E44<>0),D44/E44,"") -> 8348.7143 | G44: 4 | H44: =IF(AND(G44<>"",G44<>0),D44/G44,"") -> 14610.25 | I44: 30 | J44: =IF(AND(G44<>"",G44<>0),E44/G44,"") -> 1.75 | K44: 21086 | N44: =IF(AND(I44<>"",I44<>0),G44/I44,"") -> 0.13333333 | O44: =D44/P44 -> 1.743885 | P44: =$I$8*V44*W44/SUMPRODUCT($W$25:$W$56,$V$25:$V$56) -> 33511.958 | Q44: =$I$9*V44*W44/SUMPRODUCT($W$25:$W$58,$V$25:$V$58) -> 5.1556859 | R44: =IF($I$12="","",Q44/$I$12) -> 3.0327564 | S44: =IF(W44<>"",IF(D44<>"",D44,($I$8-SUM($S$25:S43))*V44*W44/SUMPRODUCT($W44:$W$58,$V44:$V$58)),"") -> 58441 | T44: =IF(W44<>"",IF(E44<>"",E44,($I$9-SUM($T$25:T43))*V44*W44/SUMPRODUCT($W44:$W$58,$V44:$V$58)),"") -> 7 | U44: =IF(W44<>"",IF($I$12<>"",IF(G44<>"",G44,($I$9/$I$12-SUM($U$25:U43))*V44*W44/SUMPRODUCT($W44:$W$58,$V44:$V$58)),""),"") -> 4 | V44: 1 | W44: 1
A45: 21 | B45: 45984 | C45: вс | D45: 27367 | E45: 3 | F45: =IF(AND(E45<>"",E45<>0),D45/E45,"") -> 9122.3333 | G45: 3 | H45: =IF(AND(G45<>"",G45<>0),D45/G45,"") -> 9122.3333 | I45: 25 | J45: =IF(AND(G45<>"",G45<>0),E45/G45,"") -> 1 | K45: 9081 | N45: =IF(AND(I45<>"",I45<>0),G45/I45,"") -> 0.12 | O45: =D45/P45 -> 0.81663386 | P45: =$I$8*V45*W45/SUMPRODUCT($W$25:$W$56,$V$25:$V$56) -> 33511.958 | Q45: =$I$9*V45*W45/SUMPRODUCT($W$25:$W$58,$V$25:$V$58) -> 5.1556859 | R45: =IF($I$12="","",Q45/$I$12) -> 3.0327564 | S45: =IF(W45<>"",IF(D45<>"",D45,($I$8-SUM($S$25:S44))*V45*W45/SUMPRODUCT($W45:$W$58,$V45:$V$58)),"") -> 27367 | T45: =IF(W45<>"",IF(E45<>"",E45,($I$9-SUM($T$25:T44))*V45*W45/SUMPRODUCT($W45:$W$58,$V45:$V$58)),"") -> 3 | U45: =IF(W45<>"",IF($I$12<>"",IF(G45<>"",G45,($I$9/$I$12-SUM($U$25:U44))*V45*W45/SUMPRODUCT($W45:$W$58,$V45:$V$58)),""),"") -> 3 | V45: 1 | W45: 1
A46: 22 | B46: 45986 | C46: вт | F46: =IF(AND(E46<>"",E46<>0),D46/E46,"") | H46: =IF(AND(G46<>"",G46<>0),D46/G46,"") | I46: 7 | J46: =IF(AND(G46<>"",G46<>0),E46/G46,"") | N46: =IF(AND(I46<>"",I46<>0),G46/I46,"") -> 0 | O46: =D46/P46 -> 0 | P46: =$I$8*V46*W46/SUMPRODUCT($W$25:$W$56,$V$25:$V$56) -> 33511.958 | Q46: =$I$9*V46*W46/SUMPRODUCT($W$25:$W$58,$V$25:$V$58) -> 5.1556859 | R46: =IF($I$12="","",Q46/$I$12) -> 3.0327564 | S46: =IF(W46<>"",IF(D46<>"",D46,($I$8-SUM($S$25:S45))*V46*W46/SUMPRODUCT($W46:$W$58,$V46:$V$58)),"") -> 30790.8 | T46: =IF(W46<>"",IF(E46<>"",E46,($I$9-SUM($T$25:T45))*V46*W46/SUMPRODUCT($W46:$W$58,$V46:$V$58)),"") -> 8.0390255 | U46: =IF(W46<>"",IF($I$12<>"",IF(G46<>"",G46,($I$9/$I$12-SUM($U$25:U45))*V46*W46/SUMPRODUCT($W46:$W$58,$V46:$V$58)),""),"") -> 4.1609652 | V46: 1 | W46: 1
A47: 23 | B47: 46352 | C47: ср | F47: =IF(AND(E47<>"",E47<>0),D47/E47,"") | H47: =IF(AND(G47<>"",G47<>0),D47/G47,"") | I47: 13 | J47: =IF(AND(G47<>"",G47<>0),E47/G47,"") | N47: =IF(AND(I47<>"",I47<>0),G47/I47,"") -> 0 | O47: =D47/P47 -> 0 | P47: =$I$8*V47*W47/SUMPRODUCT($W$25:$W$56,$V$25:$V$56) -> 33511.958 | Q47: =$I$9*V47*W47/SUMPRODUCT($W$25:$W$58,$V$25:$V$58) -> 5.1556859 | R47: =IF($I$12="","",Q47/$I$12) -> 3.0327564 | S47: =IF(W47<>"",IF(D47<>"",D47,($I$8-SUM($S$25:S46))*V47*W47/SUMPRODUCT($W47:$W$58,$V47:$V$58)),"") -> 30790.8 | T47: =IF(W47<>"",IF(E47<>"",E47,($I$9-SUM($T$25:T46))*V47*W47/SUMPRODUCT($W47:$W$58,$V47:$V$58)),"") -> 8.0390255 | U47: =IF(W47<>"",IF($I$12<>"",IF(G47<>"",G47,($I$9/$I$12-SUM($U$25:U46))*V47*W47/SUMPRODUCT($W47:$W$58,$V47:$V$58)),""),"") -> 4.1609652 | V47: 1 | W47: 1
A48: 24 | B48: 45988 | C48: чт | F48: =IF(AND(E48<>"",E48<>0),D48/E48,"") | H48: =IF(AND(G48<>"",G48<>0),D48/G48,"") | I48: 12 | J48: =IF(AND(G48<>"",G48<>0),E48/G48,"") | N48: =IF(AND(I48<>"",I48<>0),G48/I48,"") -> 0 | O48: =D48/P48 -> 0 | P48: =$I$8*V48*W48/SUMPRODUCT($W$25:$W$56,$V$25:$V$56) -> 33511.958 | Q48: =$I$9*V48*W48/SUMPRODUCT($W$25:$W$58,$V$25:$V$58) -> 5.1556859 | R48: =IF($I$12="","",Q48/$I$12) -> 3.0327564 | S48: =IF(W48<>"",IF(D48<>"",D48,($I$8-SUM($S$25:S47))*V48*W48/SUMPRODUCT($W48:$W$58,$V48:$V$58)),"") -> 30790.8 | T48: =IF(W48<>"",IF(E48<>"",E48,($I$9-SUM($T$25:T47))*V48*W48/SUMPRODUCT($W48:$W$58,$V48:$V$58)),"") -> 8.0390255 | U48: =IF(W48<>"",IF($I$12<>"",IF(G48<>"",G48,($I$9/$I$12-SUM($U$25:U47))*V48*W48/SUMPRODUCT($W48:$W$58,$V48:$V$58)),""),"") -> 4.1609652 | V48: 1 | W48: 1
A49: 25 | B49: 45989 | C49: пт | D49: =7693+19795 -> 27488 | E49: 3 | F49: =IF(AND(E49<>"",E49<>0),D49/E49,"") -> 9162.6667 | G49: 2 | H49: =IF(AND(G49<>"",G49<>0),D49/G49,"") -> 13744 | I49: 15 | J49: =IF(AND(G49<>"",G49<>0),E49/G49,"") -> 1.5 | M49: 7693 | N49: =IF(AND(I49<>"",I49<>0),G49/I49,"") -> 0.13333333 | O49: =D49/P49 -> 0.82024451 | P49: =$I$8*V49*W49/SUMPRODUCT($W$25:$W$56,$V$25:$V$56) -> 33511.958 | Q49: =$I$9*V49*W49/SUMPRODUCT($W$25:$W$58,$V$25:$V$58) -> 5.1556859 | R49: =IF($I$12="","",Q49/$I$12) -> 3.0327564 | S49: =IF(W49<>"",IF(D49<>"",D49,($I$8-SUM($S$25:S48))*V49*W49/SUMPRODUCT($W49:$W$58,$V49:$V$58)),"") -> 27488 | T49: =IF(W49<>"",IF(E49<>"",E49,($I$9-SUM($T$25:T48))*V49*W49/SUMPRODUCT($W49:$W$58,$V49:$V$58)),"") -> 3 | U49: =IF(W49<>"",IF($I$12<>"",IF(G49<>"",G49,($I$9/$I$12-SUM($U$25:U48))*V49*W49/SUMPRODUCT($W49:$W$58,$V49:$V$58)),""),"") -> 2 | V49: 1 | W49: 1
A50: 26 | F50: =IF(AND(E50<>"",E50<>0),D50/E50,"") | H50: =IF(AND(G50<>"",G50<>0),D50/G50,"") | J50: =IF(AND(G50<>"",G50<>0),E50/G50,"") | N50: =IF(AND(I50<>"",I50<>0),G50/I50,"") | O50: =D50/P50 -> #DIV/0! | P50: =$I$8*V50*W50/SUMPRODUCT($W$25:$W$56,$V$25:$V$56) -> 0 | Q50: =$I$9*V50*W50/SUMPRODUCT($W$25:$W$58,$V$25:$V$58) -> 0 | R50: =IF($I$12="","",Q50/$I$12) -> 0 | S50: =IF(W50<>"",IF(D50<>"",D50,($I$8-SUM($S$25:S49))*V50*W50/SUMPRODUCT($W50:$W$58,$V50:$V$58)),"") | T50: =IF(W50<>"",IF(E50<>"",E50,($I$9-SUM($T$25:T49))*V50*W50/SUMPRODUCT($W50:$W$58,$V50:$V$58)),"") | U50: =IF(W50<>"",IF($I$12<>"",IF(G50<>"",G50,($I$9/$I$12-SUM($U$25:U49))*V50*W50/SUMPRODUCT($W50:$W$58,$V50:$V$58)),""),"")
A51: 27 | F51: =IF(AND(E51<>"",E51<>0),D51/E51,"") | H51: =IF(AND(G51<>"",G51<>0),D51/G51,"") | J51: =IF(AND(G51<>"",G51<>0),E51/G51,"") | N51: =IF(AND(I51<>"",I51<>0),G51/I51,"") | O51: =D51/P51 -> #DIV/0! | P51: =$I$8*V51*W51/SUMPRODUCT($W$25:$W$56,$V$25:$V$56) -> 0 | Q51: =$I$9*V51*W51/SUMPRODUCT($W$25:$W$58,$V$25:$V$58) -> 0 | R51: =IF($I$12="","",Q51/$I$12) -> 0 | S51: =IF(W51<>"",IF(D51<>"",D51,($I$8-SUM($S$25:S50))*V51*W51/SUMPRODUCT($W51:$W$58,$V51:$V$58)),"") | T51: =IF(W51<>"",IF(E51<>"",E51,($I$9-SUM($T$25:T50))*V51*W51/SUMPRODUCT($W51:$W$58,$V51:$V$58)),"") | U51: =IF(W51<>"",IF($I$12<>"",IF(G51<>"",G51,($I$9/$I$12-SUM($U$25:U50))*V51*W51/SUMPRODUCT($W51:$W$58,$V51:$V$58)),""),"")
A52: 28 | F52: =IF(AND(E52<>"",E52<>0),D52/E52,"") | H52: =IF(AND(G52<>"",G52<>0),D52/G52,"") | J52: =IF(AND(G52<>"",G52<>0),E52/G52,"") | N52: =IF(AND(I52<>"",I52<>0),G52/I52,"") | O52: =D52/P52 -> #DIV/0! | P52: =$I$8*V52*W52/SUMPRODUCT($W$25:$W$56,$V$25:$V$56) -> 0 | Q52: =$I$9*V52*W52/SUMPRODUCT($W$25:$W$58,$V$25:$V$58) -> 0 | R52: =IF($I$12="","",Q52/$I$12) -> 0 | S52: =IF(W52<>"",IF(D52<>"",D52,($I$8-SUM($S$25:S51))*V52*W52/SUMPRODUCT($W52:$W$58,$V52:$V$58)),"") | T52: =IF(W52<>"",IF(E52<>"",E52,($I$9-SUM($T$25:T51))*V52*W52/SUMPRODUCT($W52:$W$58,$V52:$V$58)),"") | U52: =IF(W52<>"",IF($I$12<>"",IF(G52<>"",G52,($I$9/$I$12-SUM($U$25:U51))*V52*W52/SUMPRODUCT($W52:$W$58,$V52:$V$58)),""),"")
A53: 29 | F53: =IF(AND(E53<>"",E53<>0),D53/E53,"") | H53: =IF(AND(G53<>"",G53<>0),D53/G53,"") | J53: =IF(AND(G53<>"",G53<>0),E53/G53,"") | N53: =IF(AND(I53<>"",I53<>0),G53/I53,"") | O53: =D53/P53 -> #DIV/0! | P53: =$I$8*V53*W53/SUMPRODUCT($W$25:$W$56,$V$25:$V$56) -> 0 | Q53: =$I$9*V53*W53/SUMPRODUCT($W$25:$W$58,$V$25:$V$58) -> 0 | R53: =IF($I$12="","",Q53/$I$12) -> 0 | S53: =IF(W53<>"",IF(D53<>"",D53,($I$8-SUM($S$25:S52))*V53*W53/SUMPRODUCT($W53:$W$58,$V53:$V$58)),"") | T53: =IF(W53<>"",IF(E53<>"",E53,($I$9-SUM($T$25:T52))*V53*W53/SUMPRODUCT($W53:$W$58,$V53:$V$58)),"") | U53: =IF(W53<>"",IF($I$12<>"",IF(G53<>"",G53,($I$9/$I$12-SUM($U$25:U52))*V53*W53/SUMPRODUCT($W53:$W$58,$V53:$V$58)),""),"")
F54: =IF(AND(E54<>"",E54<>0),D54/E54,"") | H54: =IF(AND(G54<>"",G54<>0),D54/G54,"") | J54: =IF(AND(G54<>"",G54<>0),E54/G54,"") | N54: =IF(AND(I54<>"",I54<>0),G54/I54,"") | O54: =D54/P54 -> #DIV/0! | P54: =$I$8*V54*W54/SUMPRODUCT($W$25:$W$56,$V$25:$V$56) -> 0 | Q54: =$I$9*V54*W54/SUMPRODUCT($W$25:$W$58,$V$25:$V$58) -> 0 | R54: =IF($I$12="","",Q54/$I$12) -> 0 | S54: =IF(W54<>"",IF(D54<>"",D54,($I$8-SUM($S$25:S50))*V54*W54/SUMPRODUCT($W54:$W$58,$V54:$V$58)),"") | T54: =IF(W54<>"",IF(E54<>"",E54,($I$9-SUM($T$25:T50))*V54*W54/SUMPRODUCT($W54:$W$58,$V54:$V$58)),"") | U54: =IF(W54<>"",IF($I$12<>"",IF(G54<>"",G54,($I$9/$I$12-SUM($U$25:U50))*V54*W54/SUMPRODUCT($W54:$W$58,$V54:$V$58)),""),"")
F55: =IF(AND(E55<>"",E55<>0),D55/E55,"") | H55: =IF(AND(G55<>"",G55<>0),D55/G55,"") | J55: =IF(AND(G55<>"",G55<>0),E55/G55,"") | N55: =IF(AND(I55<>"",I55<>0),G55/I55,"") | O55: =D55/P55 -> #DIV/0! | P55: =$I$8*V55*W55/SUMPRODUCT($W$25:$W$56,$V$25:$V$56) -> 0 | Q55: =$I$9*V55*W55/SUMPRODUCT($W$25:$W$58,$V$25:$V$58) -> 0 | R55: =IF($I$12="","",Q55/$I$12) -> 0 | S55: =IF(W55<>"",IF(D55<>"",D55,($I$8-SUM($S$25:S54))*V55*W55/SUMPRODUCT($W55:$W$58,$V55:$V$58)),"") | T55: =IF(W55<>"",IF(E55<>"",E55,($I$9-SUM($T$25:T54))*V55*W55/SUMPRODUCT($W55:$W$58,$V55:$V$58)),"") | U55: =IF(W55<>"",IF($I$12<>"",IF(G55<>"",G55,($I$9/$I$12-SUM($U$25:U54))*V55*W55/SUMPRODUCT($W55:$W$58,$V55:$V$58)),""),"")
F56: =IF(AND(E56<>"",E56<>0),D56/E56,"") | H56: =IF(AND(G56<>"",G56<>0),D56/G56,"") | J56: =IF(AND(G56<>"",G56<>0),E56/G56,"") | N56: =IF(AND(I56<>"",I56<>0),G56/I56,"") | O56: =D56/P56 -> #DIV/0! | P56: =$I$8*V56*W56/SUMPRODUCT($W$25:$W$56,$V$25:$V$56) -> 0 | Q56: =$I$9*V56*W56/SUMPRODUCT($W$25:$W$58,$V$25:$V$58) -> 0 | R56: =IF($I$12="","",Q56/$I$12) -> 0 | S56: =IF(W56<>"",IF(D56<>"",D56,($I$8-SUM($S$25:S55))*V56*W56/SUMPRODUCT($W56:$W$58,$V56:$V$58)),"") | T56: =IF(W56<>"",IF(E56<>"",E56,($I$9-SUM($T$25:T55))*V56*W56/SUMPRODUCT($W56:$W$58,$V56:$V$58)),"") | U56: =IF(W56<>"",IF($I$12<>"",IF(G56<>"",G56,($I$9/$I$12-SUM($U$25:U55))*V56*W56/SUMPRODUCT($W56:$W$58,$V56:$V$58)),""),"")
D57: =SUM(D25:D56) -> 641915 | E57: =SUM(E25:E56) -> 81 | F57: =IF(AND(E57<>"",E57<>0),D57/E57,"") -> 7924.8765 | G57: =SUM(G25:G56) -> 50 | H57: =IF(AND(G57<>"",G57<>0),D57/G57,"") -> 12838.3 | I57: =SUM(I25:I56) -> 507 | J57: =IF(AND(G57<>"",G57<>0),E57/G57,"") -> 1.62 | K57: =SUM(K25:K56) -> 295157 | L57: =SUM(L25:L56) -> 12103 | M57: =SUM(M25:M56) -> 72847 | N57: =IF(AND(I57<>"",I57<>0),G57/I57,"") -> 0.098619329 | O57: =D57/P57 -> 0.76619217 | P57: =SUM(P25:P56) -> 837798.96 | Q57: =SUM(Q25:Q55) -> 128.89215 | R57: =SUM(R25:R55) -> 75.81891 | S57: =SUM(S25:S56) -> 834496.16 | T57: =SUM(T25:T55) -> 123.85312 | U57: =SUM(U25:U55) -> 73.657945
D58: =SUMIF(D25:D54,"",P25:P54)+D57 -> 842986.75

Sheet Уразгильдеева Е. Р. 
B1: =TODAY()-1 -> 46000
B2: (отчетная дата) | J2: ЕЖЕДНЕВНЫЙ ОТЧЕТ О ПРОДАЖАХ
B3: Осталось до выполнения плана!!! | J3: =График!B28 -> Уразгильдеева Екатерина
C4: =I8-D50 -> 470227.08 | E4: =IF(I8<>0, C4/I8, 0) -> 1
F6: Целевые показатели
F7: Показатель | I7: План | J7: Факт | K7: % выполнения | L7: Прогноз выполнения | M7: % выполнения по прогнозу | N7: Отклонение | O7: Факт аналогичного месяца прошлого года | P7: Отклонение LFL
F8: Выручка | I8: ='Ялта, Ленина, 18'!I8/График!AJ31*График!AJ28 -> 470227.08 | J8: =D57 -> 263849 | K8: =IF(AND(I8<>"",I8<>0,J8<>""),J8/I8,"") -> 0.56110975 | L8: =IF(SUMIF($D$25:$D$56,">=0",$P$25:$P$56)<>0,I8*D57/SUMIF($D$25:$D$56,">=0",$P$25:$P$56),0) -> 343003.7 | M8: =IF(AND(I8<>"",I8<>0,L8<>"",L8<>0),L8/I8,"") -> 0.72944267 | N8: =IF(AND(J8<>0,J8<>"",I8<>0,I8<>""),L8-I8,"") -> -127223.38 | P8: =IF(AND(O8<>"", O8<>0, L8<>"", L8<>0), -O8+L8, "") | Q8: =IF(AND(P8<>"", P8<>0, O8<>0, O8<>""), P8/O8, "")
F9: Кол-во изделий | I9: =I8/I11 -> 72.342628 | J9: =E57 -> 37 | K9: =IF(AND(I9<>"", I9<>0, J9<>""), J9/I9, "") -> 0.51145502 | L9: =IF(SUMIF($E$25:$E$54,">=0",$Q$25:$Q$54)<>0,I9*E57/SUMIF($E$25:$E$54,">=0",$Q$25:$Q$54),0) -> 48.1 | M9: =IF(AND(I9<>"",I9<>0,L9<>"",L9<>0),L9/I9,"") -> 0.66489152 | N9: =IF(AND(J9<>0,J9<>"",I9<>0,I9<>""),L9-I9,"") -> -24.242628 | O9: =O8/O11 -> #DIV/0! | P9: =IF(AND(O9<>"", O9<>0, L9<>"", L9<>0), -O9+L9, "") -> #DIV/0! | Q9: =IF(AND(P9<>"", P9<>0, O9<>0, O9<>""), P9/O9, "") -> #DIV/0!
F10: Средний чек | I10: =I11*I12 -> 11050 | J10: =H57 -> 11993.136 | K10: =IF(AND(I10<>"", I10<>0, J10<>""), J10/I10, "") -> 1.0853517 | L10: =J10 -> 11993.136 | M10: =IF(AND(I10<>"",I10<>0,L10<>"",L10<>0),L10/I10,"") -> 1.0853517 | N10: =IF(AND(J10<>0,J10<>"",I10<>0,I10<>""),L10-I10,"") -> 943.13636 | O10: =O11*O12 -> 0 | P10: =IF(AND(O10<>"", O10<>0, L10<>"", L10<>0), -O10+L10, "") | Q10: =IF(AND(P10<>"", P10<>0, O10<>0, O10<>""), P10/O10, "") | S10: IS | V10: =M23 -> Agafi
F11: Средняя стоимость изделия | I11: ='Ялта, Ленина, 18'!I11 -> 6500 | J11: =F57 -> 7131.0541 | K11: =IF(AND(I11<>"", I11<>0, J11<>""), J11/I11, "") -> 1.0970852 | L11: =IF(L9>0,L8/L9,"") -> 7131.0541 | M11: =IF(AND(I11<>"",I11<>0,L11<>"",L11<>0),L11/I11,"") -> 1.0970852 | N11: =IF(AND(J11<>0,J11<>"",I11<>0,I11<>""),L11-I11,"") -> 631.05405 | P11: =IF(AND(O11<>"", O11<>0, L11<>"", L11<>0), -O11+L11, "") | Q11: =IF(AND(P11<>"", P11<>0, O11<>0, O11<>""), P11/O11, "")
F12: Длина чека | I12: ='Ялта, Ленина, 18'!I12 -> 1.7 | J12: =J57 -> 1.6818182 | K12: =IF(AND(I12<>"", I12<>0, J12<>""), J12/I12, "") -> 0.98930481 | L12: =J12 -> 1.6818182 | M12: =IF(AND(I12<>"",I12<>0,L12<>"",L12<>0),L12/I12,"") -> 0.98930481 | N12: =IF(AND(J12<>0,J12<>"",I12<>0,I12<>""),L12-I12,"") -> -0.018181818 | P12: =IF(AND(O12<>"", O12<>0, L12<>"", L12<>0), -O12+L12, "") | Q12: =IF(AND(P12<>"", P12<>0, O12<>0, O12<>""), P12/O12, "") | S12: ='Ялта, Ленина, 18'!S12*График!AJ28/График!AJ31 -> 116057.69 | T12: =L57 -> 0 | U12: =S12-T12 -> 116057.69 | V12: ='Ялта, Ленина, 18'!V12/График!AJ31*График!AJ28 -> 109230.77 | W12: =M57 -> 0 | X12: =V12-W12 -> 109230.77
F13: Кол-во чеков | I13: =IF(I12<>0, I9/I12, "") -> 42.554487 | J13: =G57 -> 22 | K13: =IF(AND(I13<>"", I13<>0, J13<>""), J13/I13, "") -> 0.51698426 | L13: =IF(SUMIF($G$25:$G$54,">=0",$R$25:$R$54)<>0,I13*G57/SUMIF($G$25:$G$54,">=0",$R$25:$R$54),"") -> 28.6 | M13: =IF(AND(I13<>"",I13<>0,L13<>"",L13<>0),L13/I13,"") -> 0.67207954 | N13: =IF(AND(J13<>0,J13<>"",I13<>0,I13<>""),L13-I13,"") -> -13.954487 | P13: =IF(AND(O13<>"", O13<>0, L13<>"", L13<>0), -O13+L13, "") | Q13: =IF(AND(P13<>"", P13<>0, O13<>0, O13<>""), P13/O13, "") | S13: =T12/S12 -> 0 | T13: =S13/J14*I14 -> 0 | V13: =W12/V12 -> 0 | W13: =V13/J14*I14 -> 0
F14: Кол-во смен план/отработано | I14: =График!AI28 -> 13 | J14: 13 | K14: =IF(AND(I14<>"", I14<>0, J14<>""), J14/I14, "") -> 1 | L14: =I14 -> 13 | M14: =IF(AND(I14<>"",I14<>0,L14<>"",L14<>0),L14/I14,"") -> 1 | N14: =IF(AND(J14<>0,J14<>"",I14<>0,I14<>""),L14-I14,"") -> 0 | P14: =IF(AND(O14<>"", O14<>0, L14<>"", L14<>0), -O14+L14, "") | Q14: =IF(AND(P14<>"", P14<>0, O14<>0, O14<>""), P14/O14, "")
F15: Средние продажи в смену | I15: ='Ялта, Ленина, 18'!I15 -> 68878.333 | J15: =J8/J14 -> 20296.077 | K15: =IF(AND(I15<>"", I15<>0, J15<>""), J15/I15, "") -> 0.29466562 | L15: =J15 -> 20296.077 | M15: =IF(AND(I15<>"",I15<>0,L15<>"",L15<>0),L15/I15,"") -> 0.29466562 | N15: =IF(AND(J15<>0,J15<>"",I15<>0,I15<>""),L15-I15,"") -> -48582.256 | P15: =IF(AND(O15<>"", O15<>0, L15<>"", L15<>0), -O15+L15, "") | Q15: =IF(AND(P15<>"", P15<>0, O15<>0, O15<>""), P15/O15, "")
F16: Отставание/Перевыполнение | J16: =J8-I15*J14 -> -631569.33 | K16: =IF(AND(I16<>"", I16<>0, J16<>""), J16/I16, "") | L16: =J16 -> -631569.33 | M16: =IF(AND(I16<>"",I16<>0,L16<>"",L16<>0),L16/I16,"") | N16: =IF(AND(J16<>0,J16<>"",I16<>0,I16<>""),L16-I16,"") | P16: =IF(AND(O16<>"", O16<>0, L16<>"", L16<>0), -O16+L16, "") | Q16: =IF(AND(P16<>"", P16<>0, O16<>0, O16<>""), P16/O16, "") | S16: UNOde50
F17: Трафик | I17: ='Ялта, Ленина, 18'!I17/График!AJ31*График!AJ28 -> 386.85897 | J17: =I57 -> 237 | K17: =IF(AND(I17<>"", I17<>0, J17<>""), J17/I17, "") -> 0.61262635 | L17: =J17/J14*I14 -> 237 | M17: =IF(AND(I17<>"",I17<>0,L17<>"",L17<>0),L17/I17,"") -> 0.61262635 | N17: =IF(AND(J17<>0,J17<>"",I17<>0,I17<>""),L17-I17,"") -> -149.85897 | P17: =IF(AND(O17<>"", O17<>0, L17<>"", L17<>0), -O17+L17, "") | Q17: =IF(AND(P17<>"", P17<>0, O17<>0, O17<>""), P17/O17, "")
K18: =IF(AND(I18<>"", I18<>0, J18<>""), J18/I18, "") | L18: =J18 -> 0 | M18: =IF(AND(I18<>"",I18<>0,L18<>"",L18<>0),L18/I18,"") | N18: =IF(AND(J18<>0,J18<>"",I18<>0,I18<>""),L18-I18,"") | O18: 0 | P18: =IF(AND(O18<>"", O18<>0, L18<>"", L18<>0), -O18+L18, "") | Q18: =IF(AND(P18<>"", P18<>0, O18<>0, O18<>""), P18/O18, "") | S18: ='Ялта, Ленина, 18'!S18*График!AJ28/График!AJ31 -> 232115.38 | T18: =K57 -> 91284
K19: =IF(AND(I19<>"", I19<>0, J19<>""), J19/I19, "") | L19: =J19 -> 0 | M19: =IF(AND(I19<>"",I19<>0,L19<>"",L19<>0),L19/I19,"") | N19: =IF(AND(J19<>0,J19<>"",I19<>0,I19<>""),L19-I19,"") | O19: 0 | P19: =IF(AND(O19<>"", O19<>0, L19<>"", L19<>0), -O19+L19, "") | Q19: =IF(AND(P19<>"", P19<>0, O19<>0, O19<>""), P19/O19, "") | S19: =T18/S18 -> 0.39326993 | T19: =S19/J14*I14 -> 0.39326993
F20: Конверсия план/факт | I20: ='Ялта, Ленина, 18'!I20 -> 0.11 | J20: =N57 -> 0.092827004 | K20: =J20/I20 -> 0.84388186 | L20: =IF(AND(K8<>0,I14<>0,I57<>0),(I57*N57+(I57/K8-I57)*I20)/(I57/K8),0) -> 0.10036406 | M20: =IF(AND(I20<>"",I20<>0,L20<>"",L20<>0),L20/I20,"") -> 0.91240059 | N20: =IF(AND(J20<>0,J20<>"",I20<>0,I20<>""),L20-I20,"") -> -0.0096359353 | P20: =IF(AND(O20<>"", O20<>0, L20<>"", L20<>0), -O20+L20, "") | Q20: =IF(AND(P20<>"", P20<>0, O20<>0, O20<>""), P20/O20, "")
B22: Факт продаж за месяц | O22: % выполнения дневного плана | P22: Раcпределение плана по дням
B23: Дата | C23: День недели | D23: Выручка (руб) | E23: Кол-во единиц (шт.) | F23: Средняя стоимость изделия (руб.) | G23: Количество чеков (шт.) | H23: Средняя сумма чека (руб.) | I23: Трафик | J23: Длина чека (шт.) | K23: UNOde50 | L23: IS | M23: Agafi | N23: Конверсия (%) | P23: выручка, план | Q23: кол-во ед, план | R23: Кол-во чеков, план | S23: выручка, скорректир.план | T23: кол-во ед, скорр. план | U23: кол-во чеков, скорр. план | V23: Коэфф. Дня Недели | W23: Специфика месяца
B24: 1 | C24: 2 | D24: 3 | E24: в | F24: 5 | G24: 6 | H24: 7 | I24: 8 | J24: 9 | K24: 10 | L24: 11 | M24: 12 | N24: 13 | P24: 1 | Q24: 2 | R24: 3 | S24: 4 | T24: 5 | U24: 6 | V24: 10 | W24: 11
A25: 1 | B25: 45962 | C25: сб | D25: 12384 | E25: 2 | F25: =IF(AND(E25<>"",E25<>0),D25/E25,"") -> 6192 | G25: 2 | H25: =IF(AND(G25<>"",G25<>0),D25/G25,"") -> 6192 | I25: 20 | J25: =IF(AND(G25<>"",G25<>0),E25/G25,"") -> 1 | N25: =IF(AND(I25<>"",I25<>0),G25/I25,"") -> 0.1 | O25: =D25/P25 -> 0.34237075 | P25: =$I$8*V25*W25/SUMPRODUCT($W$25:$W$56,$V$25:$V$56) -> 36171.314 | Q25: =$I$9*V25*W25/SUMPRODUCT($W$25:$W$56,$V$25:$V$56) -> 5.5648176 | R25: =IF($I$12="","",Q25/$I$12) -> 3.2734221 | S25: =IF(D25<>"",D25,P25) -> 12384 | T25: =IF(E25<>"",E25,Q25) -> 2 | U25: =IF(G25<>"",G25,R25) -> 2 | V25: 1 | W25: 1
A26: 2 | B26: 45963 | C26: вс | D26: 20566 | E26: 4 | F26: =IF(AND(E26<>"",E26<>0),D26/E26,"") -> 5141.5 | G26: 3 | H26: =IF(AND(G26<>"",G26<>0),D26/G26,"") -> 6855.3333 | I26: 50 | J26: =IF(AND(G26<>"",G26<>0),E26/G26,"") -> 1.3333333 | N26: =IF(AND(I26<>"",I26<>0),G26/I26,"") -> 0.06 | O26: =D26/P26 -> 0.5685721 | P26: =$I$8*V26*W26/SUMPRODUCT($W$25:$W$56,$V$25:$V$56) -> 36171.314 | Q26: =$I$9*V26*W26/SUMPRODUCT($W$25:$W$58,$V$25:$V$58) -> 5.5648176 | R26: =IF($I$12="","",Q26/$I$12) -> 3.2734221 | S26: =IF(W26<>"",IF(D26<>"",D26,($I$8-SUM($S$25:S25))*V26*W26/SUMPRODUCT($W26:$W$56,$V26:$V$56)),"") -> 20566 | T26: =IF(W26<>"",IF(E26<>"",E26,($I$9-SUM($T$25:T25))*V26*W26/SUMPRODUCT($W26:$W$55,$V26:$V$55)),"") -> 4 | U26: =IF(W26<>"",IF($I$12<>"",IF(G26<>"",G26,($I$9/$I$12-SUM($U$25:U25))*V26*W26/SUMPRODUCT($W26:$W$55,$V26:$V$55)),""),"") -> 3 | V26: 1 | W26: 1
A27: 3 | B27: 45976 | C27: сб | D27: 7992 | E27: 1 | F27: =IF(AND(E27<>"",E27<>0),D27/E27,"") -> 7992 | G27: 1 | H27: =IF(AND(G27<>"",G27<>0),D27/G27,"") -> 7992 | I27: 15 | J27: =IF(AND(G27<>"",G27<>0),E27/G27,"") -> 1 | K27: 7992 | N27: =IF(AND(I27<>"",I27<>0),G27/I27,"") -> 0.066666667 | O27: =D27/P27 -> 0.22094857 | P27: =$I$8*V27*W27/SUMPRODUCT($W$25:$W$56,$V$25:$V$56) -> 36171.314 | Q27: =$I$9*V27*W27/SUMPRODUCT($W$25:$W$58,$V$25:$V$58) -> 5.5648176 | R27: =IF($I$12="","",Q27/$I$12) -> 3.2734221 | S27: =IF(W27<>"",IF(D27<>"",D27,($I$8-SUM($S$25:S26))*V27*W27/SUMPRODUCT($W27:$W$58,$V27:$V$58)),"") -> 7992 | T27: =IF(W27<>"",IF(E27<>"",E27,($I$9-SUM($T$25:T26))*V27*W27/SUMPRODUCT($W27:$W$55,$V27:$V$55)),"") -> 1 | U27: =IF(W27<>"",IF($I$12<>"",IF(G27<>"",G27,($I$9/$I$12-SUM($U$25:U26))*V27*W27/SUMPRODUCT($W27:$W$55,$V27:$V$55)),""),"") -> 1 | V27: 1 | W27: 1
A28: 4 | B28: 45977 | C28: вс | D28: 10883 | E28: 2 | F28: =IF(AND(E28<>"",E28<>0),D28/E28,"") -> 5441.5 | G28: 2 | H28: =IF(AND(G28<>"",G28<>0),D28/G28,"") -> 5441.5 | I28: 13 | J28: =IF(AND(G28<>"",G28<>0),E28/G28,"") -> 1 | N28: =IF(AND(I28<>"",I28<>0),G28/I28,"") -> 0.15384615 | O28: =D28/P28 -> 0.30087378 | P28: =$I$8*V28*W28/SUMPRODUCT($W$25:$W$56,$V$25:$V$56) -> 36171.314 | Q28: =$I$9*V28*W28/SUMPRODUCT($W$25:$W$58,$V$25:$V$58) -> 5.5648176 | R28: =IF($I$12="","",Q28/$I$12) -> 3.2734221 | S28: =IF(W28<>"",IF(D28<>"",D28,($I$8-SUM($S$25:S27))*V28*W28/SUMPRODUCT($W28:$W$58,$V28:$V$58)),"") -> 10883 | T28: =IF(W28<>"",IF(E28<>"",E28,($I$9-SUM($T$25:T27))*V28*W28/SUMPRODUCT($W28:$W$58,$V28:$V$58)),"") -> 2 | U28: =IF(W28<>"",IF($I$12<>"",IF(G28<>"",G28,($I$9/$I$12-SUM($U$25:U27))*V28*W28/SUMPRODUCT($W28:$W$58,$V28:$V$58)),""),"") -> 2 | V28: 1 | W28: 1
A29: 5 | B29: 45978 | C29: пн | D29: 76121 | E29: 8 | F29: =IF(AND(E29<>"",E29<>0),D29/E29,"") -> 9515.125 | G29: 2 | H29: =IF(AND(G29<>"",G29<>0),D29/G29,"") -> 38060.5 | I29: 12 | J29: =IF(AND(G29<>"",G29<>0),E29/G29,"") -> 4 | K29: 45170 | N29: =IF(AND(I29<>"",I29<>0),G29/I29,"") -> 0.16666667 | O29: =D29/P29 -> 2.1044577 | P29: =$I$8*V29*W29/SUMPRODUCT($W$25:$W$56,$V$25:$V$56) -> 36171.314 | Q29: =$I$9*V29*W29/SUMPRODUCT($W$25:$W$58,$V$25:$V$58) -> 5.5648176 | R29: =IF($I$12="","",Q29/$I$12) -> 3.2734221 | S29: =IF(W29<>"",IF(D29<>"",D29,($I$8-SUM($S$25:S28))*V29*W29/SUMPRODUCT($W29:$W$58,$V29:$V$58)),"") -> 76121 | T29: =IF(W29<>"",IF(E29<>"",E29,($I$9-SUM($T$25:T28))*V29*W29/SUMPRODUCT($W29:$W$58,$V29:$V$58)),"") -> 8 | U29: =IF(W29<>"",IF($I$12<>"",IF(G29<>"",G29,($I$9/$I$12-SUM($U$25:U28))*V29*W29/SUMPRODUCT($W29:$W$58,$V29:$V$58)),""),"") -> 2 | V29: 1 | W29: 1
A30: 6 | B30: 45980 | C30: ср | D30: 10383 | E30: 2 | F30: =IF(AND(E30<>"",E30<>0),D30/E30,"") -> 5191.5 | G30: 1 | H30: =IF(AND(G30<>"",G30<>0),D30/G30,"") -> 10383 | I30: 10 | J30: =IF(AND(G30<>"",G30<>0),E30/G30,"") -> 2 | N30: =IF(AND(I30<>"",I30<>0),G30/I30,"") -> 0.1 | O30: =D30/P30 -> 0.28705067 | P30: =$I$8*V30*W30/SUMPRODUCT($W$25:$W$56,$V$25:$V$56) -> 36171.314 | Q30: =$I$9*V30*W30/SUMPRODUCT($W$25:$W$58,$V$25:$V$58) -> 5.5648176 | R30: =IF($I$12="","",Q30/$I$12) -> 3.2734221 | S30: =IF(W30<>"",IF(D30<>"",D30,($I$8-SUM($S$25:S29))*V30*W30/SUMPRODUCT($W30:$W$58,$V30:$V$58)),"") -> 10383 | T30: =IF(W30<>"",IF(E30<>"",E30,($I$9-SUM($T$25:T29))*V30*W30/SUMPRODUCT($W30:$W$58,$V30:$V$58)),"") -> 2 | U30: =IF(W30<>"",IF($I$12<>"",IF(G30<>"",G30,($I$9/$I$12-SUM($U$25:U29))*V30*W30/SUMPRODUCT($W30:$W$58,$V30:$V$58)),""),"") -> 1 | V30: 1 | W30: 1
A31: 7 | B31: 45981 | C31: чт | F31: =IF(AND(E31<>"",E31<>0),D31/E31,"") | H31: =IF(AND(G31<>"",G31<>0),D31/G31,"") | I31: 10 | J31: =IF(AND(G31<>"",G31<>0),E31/G31,"") | N31: =IF(AND(I31<>"",I31<>0),G31/I31,"") -> 0 | O31: =D31/P31 -> 0 | P31: =$I$8*V31*W31/SUMPRODUCT($W$25:$W$56,$V$25:$V$56) -> 36171.314 | Q31: =$I$9*V31*W31/SUMPRODUCT($W$25:$W$58,$V$25:$V$58) -> 5.5648176 | R31: =IF($I$12="","",Q31/$I$12) -> 3.2734221 | S31: =IF(W31<>"",IF(D31<>"",D31,($I$8-SUM($S$25:S30))*V31*W31/SUMPRODUCT($W31:$W$58,$V31:$V$58)),"") -> 47414.012 | T31: =IF(W31<>"",IF(E31<>"",E31,($I$9-SUM($T$25:T30))*V31*W31/SUMPRODUCT($W31:$W$58,$V31:$V$58)),"") -> 7.6203755 | U31: =IF(W31<>"",IF($I$12<>"",IF(G31<>"",G31,($I$9/$I$12-SUM($U$25:U30))*V31*W31/SUMPRODUCT($W31:$W$58,$V31:$V$58)),""),"") -> 4.5077839 | V31: 1 | W31: 1
A32: 8 | B32: 45984 | C32: вс | D32: =38122+5493+3534 -> 47149 | E32: 5 | F32: =IF(AND(E32<>"",E32<>0),D32/E32,"") -> 9429.8 | G32: 4 | H32: =IF(AND(G32<>"",G32<>0),D32/G32,"") -> 11787.25 | I32: 25 | J32: =IF(AND(G32<>"",G32<>0),E32/G32,"") -> 1.25 | K32: 38122 | N32: =IF(AND(I32<>"",I32<>0),G32/I32,"") -> 0.16 | O32: =D32/P32 -> 1.3034915 | P32: =$I$8*V32*W32/SUMPRODUCT($W$25:$W$56,$V$25:$V$56) -> 36171.314 | Q32: =$I$9*V32*W32/SUMPRODUCT($W$25:$W$58,$V$25:$V$58) -> 5.5648176 | R32: =IF($I$12="","",Q32/$I$12) -> 3.2734221 | S32: =IF(W32<>"",IF(D32<>"",D32,($I$8-SUM($S$25:S31))*V32*W32/SUMPRODUCT($W32:$W$58,$V32:$V$58)),"") -> 47149 | T32: =IF(W32<>"",IF(E32<>"",E32,($I$9-SUM($T$25:T31))*V32*W32/SUMPRODUCT($W32:$W$58,$V32:$V$58)),"") -> 5 | U32: =IF(W32<>"",IF($I$12<>"",IF(G32<>"",G32,($I$9/$I$12-SUM($U$25:U31))*V32*W32/SUMPRODUCT($W32:$W$58,$V32:$V$58)),""),"") -> 4 | V32: 1 | W32: 1
A33: 9 | B33: 45985 | C33: пн | D33: 29111 | E33: 4 | F33: =IF(AND(E33<>"",E33<>0),D33/E33,"") -> 7277.75 | G33: 2 | H33: =IF(AND(G33<>"",G33<>0),D33/G33,"") -> 14555.5 | I33: 10 | J33: =IF(AND(G33<>"",G33<>0),E33/G33,"") -> 2 | N33: =IF(AND(I33<>"",I33<>0),G33/I33,"") -> 0.2 | O33: =D33/P33 -> 0.80480902 | P33: =$I$8*V33*W33/SUMPRODUCT($W$25:$W$56,$V$25:$V$56) -> 36171.314 | Q33: =$I$9*V33*W33/SUMPRODUCT($W$25:$W$58,$V$25:$V$58) -> 5.5648176 | R33: =IF($I$12="","",Q33/$I$12) -> 3.2734221 | S33: =IF(W33<>"",IF(D33<>"",D33,($I$8-SUM($S$25:S32))*V33*W33/SUMPRODUCT($W33:$W$58,$V33:$V$58)),"") -> 29111 | T33: =IF(W33<>"",IF(E33<>"",E33,($I$9-SUM($T$25:T32))*V33*W33/SUMPRODUCT($W33:$W$58,$V33:$V$58)),"") -> 4 | U33: =IF(W33<>"",IF($I$12<>"",IF(G33<>"",G33,($I$9/$I$12-SUM($U$25:U32))*V33*W33/SUMPRODUCT($W33:$W$58,$V33:$V$58)),""),"") -> 2 | V33: 1 | W33: 1
A34: 10 | B34: 45987 | C34: ср | F34: =IF(AND(E34<>"",E34<>0),D34/E34,"") | H34: =IF(AND(G34<>"",G34<>0),D34/G34,"") | I34: 13 | J34: =IF(AND(G34<>"",G34<>0),E34/G34,"") | N34: =IF(AND(I34<>"",I34<>0),G34/I34,"") -> 0 | O34: =D34/P34 -> 0 | P34: =$I$8*V34*W34/SUMPRODUCT($W$25:$W$56,$V$25:$V$56) -> 36171.314 | Q34: =$I$9*V34*W34/SUMPRODUCT($W$25:$W$58,$V$25:$V$58) -> 5.5648176 | R34: =IF($I$12="","",Q34/$I$12) -> 3.2734221 | S34: =IF(W34<>"",IF(D34<>"",D34,($I$8-SUM($S$25:S33))*V34*W34/SUMPRODUCT($W34:$W$58,$V34:$V$58)),"") -> 52056.018 | T34: =IF(W34<>"",IF(E34<>"",E34,($I$9-SUM($T$25:T33))*V34*W34/SUMPRODUCT($W34:$W$58,$V34:$V$58)),"") -> 9.1805632 | U34: =IF(W34<>"",IF($I$12<>"",IF(G34<>"",G34,($I$9/$I$12-SUM($U$25:U33))*V34*W34/SUMPRODUCT($W34:$W$58,$V34:$V$58)),""),"") -> 5.2616758 | V34: 1 | W34: 1
A35: 11 | B35: 45988 | C35: чт | D35: 17908 | E35: 3 | F35: =IF(AND(E35<>"",E35<>0),D35/E35,"") -> 5969.3333 | G35: 2 | H35: =IF(AND(G35<>"",G35<>0),D35/G35,"") -> 8954 | I35: 12 | J35: =IF(AND(G35<>"",G35<>0),E35/G35,"") -> 1.5 | N35: =IF(AND(I35<>"",I35<>0),G35/I35,"") -> 0.16666667 | O35: =D35/P35 -> 0.49508845 | P35: =$I$8*V35*W35/SUMPRODUCT($W$25:$W$56,$V$25:$V$56) -> 36171.314 | Q35: =$I$9*V35*W35/SUMPRODUCT($W$25:$W$58,$V$25:$V$58) -> 5.5648176 | R35: =IF($I$12="","",Q35/$I$12) -> 3.2734221 | S35: =IF(W35<>"",IF(D35<>"",D35,($I$8-SUM($S$25:S34))*V35*W35/SUMPRODUCT($W35:$W$58,$V35:$V$58)),"") -> 17908 | T35: =IF(W35<>"",IF(E34<>"",E34,($I$9-SUM($T$25:T34))*V35*W35/SUMPRODUCT($W35:$W$58,$V35:$V$58)),"") -> 9.1805632 | U35: =IF(W35<>"",IF($I$12<>"",IF(G35<>"",G35,($I$9/$I$12-SUM($U$25:U34))*V35*W35/SUMPRODUCT($W35:$W$58,$V35:$V$58)),""),"") -> 2 | V35: 1 | W35: 1
A36: 11 | B36: 45990 | C36: сб | D36: 31352 | E36: 6 | F36: =IF(AND(E36<>"",E36<>0),D36/E36,"") -> 5225.3333 | G36: 3 | H36: =IF(AND(G36<>"",G36<>0),D36/G36,"") -> 10450.667 | I36: 32 | J36: =IF(AND(G36<>"",G36<>0),E36/G36,"") -> 2 | N36: =IF(AND(I36<>"",I36<>0),G36/I36,"") -> 0.09375 | O36: =D36/P36 -> 0.8667642 | P36: =$I$8*V36*W36/SUMPRODUCT($W$25:$W$56,$V$25:$V$56) -> 36171.314 | Q36: =$I$9*V36*W36/SUMPRODUCT($W$25:$W$58,$V$25:$V$58) -> 5.5648176 | R36: =IF($I$12="","",Q36/$I$12) -> 3.2734221 | S36: =IF(W36<>"",IF(D36<>"",D36,($I$8-SUM($S$25:S35))*V36*W36/SUMPRODUCT($W36:$W$58,$V36:$V$58)),"") -> 31352 | T36: =IF(W36<>"",IF(E35<>"",E35,($I$9-SUM($T$25:T35))*V36*W36/SUMPRODUCT($W36:$W$58,$V36:$V$58)),"") -> 3 | U36: =IF(W36<>"",IF($I$12<>"",IF(G36<>"",G36,($I$9/$I$12-SUM($U$25:U35))*V36*W36/SUMPRODUCT($W36:$W$58,$V36:$V$58)),""),"") -> 3 | V36: 1 | W36: 1
A37: 13 | B37: 45991 | C37: вс | F37: =IF(AND(E37<>"",E37<>0),D37/E37,"") | H37: =IF(AND(G37<>"",G37<>0),D37/G37,"") | I37: 15 | J37: =IF(AND(G37<>"",G37<>0),E37/G37,"") | N37: =IF(AND(I37<>"",I37<>0),G37/I37,"") -> 0 | O37: =D37/P37 -> 0 | P37: =$I$8*V37*W37/SUMPRODUCT($W$25:$W$56,$V$25:$V$56) -> 36171.314 | Q37: =$I$9*V37*W37/SUMPRODUCT($W$25:$W$58,$V$25:$V$58) -> 5.5648176 | R37: =IF($I$12="","",Q37/$I$12) -> 3.2734221 | S37: =IF(W37<>"",IF(D37<>"",D37,($I$8-SUM($S$25:S36))*V37*W37/SUMPRODUCT($W37:$W$58,$V37:$V$58)),"") -> 106908.05 | T37: =IF(W37<>"",IF(E37<>"",E37,($I$9-SUM($T$25:T36))*V37*W37/SUMPRODUCT($W37:$W$58,$V37:$V$58)),"") -> 15.361126 | U37: =IF(W37<>"",IF($I$12<>"",IF(G37<>"",G37,($I$9/$I$12-SUM($U$25:U36))*V37*W37/SUMPRODUCT($W37:$W$58,$V37:$V$58)),""),"") -> 10.785027 | V37: 1 | W37: 1
A38: 14 | F38: =IF(AND(E38<>"",E38<>0),D38/E38,"") | H38: =IF(AND(G38<>"",G38<>0),D38/G38,"") | J38: =IF(AND(G38<>"",G38<>0),E38/G38,"") | N38: =IF(AND(I38<>"",I38<>0),G38/I38,"") | O38: =D38/P38 -> #DIV/0! | P38: =$I$8*V38*W38/SUMPRODUCT($W$25:$W$56,$V$25:$V$56) -> 0 | Q38: =$I$9*V38*W38/SUMPRODUCT($W$25:$W$58,$V$25:$V$58) -> 0 | R38: =IF($I$12="","",Q38/$I$12) -> 0 | S38: =IF(W38<>"",IF(D38<>"",D38,($I$8-SUM($S$25:S37))*V38*W38/SUMPRODUCT($W38:$W$58,$V38:$V$58)),"") | T38: =IF(W38<>"",IF(E38<>"",E38,($I$9-SUM($T$25:T37))*V38*W38/SUMPRODUCT($W38:$W$58,$V38:$V$58)),"") | U38: =IF(W38<>"",IF($I$12<>"",IF(G38<>"",G38,($I$9/$I$12-SUM($U$25:U37))*V38*W38/SUMPRODUCT($W38:$W$58,$V38:$V$58)),""),"")
A39: 15 | F39: =IF(AND(E39<>"",E39<>0),D39/E39,"") | H39: =IF(AND(G39<>"",G39<>0),D39/G39,"") | J39: =IF(AND(G39<>"",G39<>0),E39/G39,"") | N39: =IF(AND(I39<>"",I39<>0),G39/I39,"") | O39: =D39/P39 -> #DIV/0! | P39: =$I$8*V39*W39/SUMPRODUCT($W$25:$W$56,$V$25:$V$56) -> 0 | Q39: =$I$9*V39*W39/SUMPRODUCT($W$25:$W$58,$V$25:$V$58) -> 0 | R39: =IF($I$12="","",Q39/$I$12) -> 0 | S39: =IF(W39<>"",IF(D39<>"",D39,($I$8-SUM($S$25:S38))*V39*W39/SUMPRODUCT($W39:$W$58,$V39:$V$58)),"") | T39: =IF(W39<>"",IF(E39<>"",E39,($I$9-SUM($T$25:T38))*V39*W39/SUMPRODUCT($W39:$W$58,$V39:$V$58)),"") | U39: =IF(W39<>"",IF($I$12<>"",IF(G39<>"",G39,($I$9/$I$12-SUM($U$25:U38))*V39*W39/SUMPRODUCT($W39:$W$58,$V39:$V$58)),""),"")
A40: 16 | F40: =IF(AND(E40<>"",E40<>0),D40/E40,"") | H40: =IF(AND(G40<>"",G40<>0),D40/G40,"") | J40: =IF(AND(G40<>"",G40<>0),E40/G40,"") | N40: =IF(AND(I40<>"",I40<>0),G40/I40,"") | O40: =D40/P40 -> #DIV/0! | P40: =$I$8*V40*W40/SUMPRODUCT($W$25:$W$56,$V$25:$V$56) -> 0 | Q40: =$I$9*V40*W40/SUMPRODUCT($W$25:$W$58,$V$25:$V$58) -> 0 | R40: =IF($I$12="","",Q40/$I$12) -> 0 | S40: =IF(W40<>"",IF(D40<>"",D40,($I$8-SUM($S$25:S39))*V40*W40/SUMPRODUCT($W40:$W$58,$V40:$V$58)),"") | T40: =IF(W40<>"",IF(E40<>"",E40,($I$9-SUM($T$25:T39))*V40*W40/SUMPRODUCT($W40:$W$58,$V40:$V$58)),"") | U40: =IF(W40<>"",IF($I$12<>"",IF(G40<>"",G40,($I$9/$I$12-SUM($U$25:U39))*V40*W40/SUMPRODUCT($W40:$W$58,$V40:$V$58)),""),"")
A41: 17 | F41: =IF(AND(E41<>"",E41<>0),D41/E41,"") | H41: =IF(AND(G41<>"",G41<>0),D41/G41,"") | J41: =IF(AND(G41<>"",G41<>0),E41/G41,"") | N41: =IF(AND(I41<>"",I41<>0),G41/I41,"") | O41: =D41/P41 -> #DIV/0! | P41: =$I$8*V41*W41/SUMPRODUCT($W$25:$W$56,$V$25:$V$56) -> 0 | Q41: =$I$9*V41*W41/SUMPRODUCT($W$25:$W$58,$V$25:$V$58) -> 0 | R41: =IF($I$12="","",Q41/$I$12) -> 0 | S41: =IF(W41<>"",IF(D41<>"",D41,($I$8-SUM($S$25:S40))*V41*W41/SUMPRODUCT($W41:$W$58,$V41:$V$58)),"") | T41: =IF(W41<>"",IF(E41<>"",E41,($I$9-SUM($T$25:T40))*V41*W41/SUMPRODUCT($W41:$W$58,$V41:$V$58)),"") | U41: =IF(W41<>"",IF($I$12<>"",IF(G41<>"",G41,($I$9/$I$12-SUM($U$25:U40))*V41*W41/SUMPRODUCT($W41:$W$58,$V41:$V$58)),""),"")
A42: 18 | F42: =IF(AND(E42<>"",E42<>0),D42/E42,"") | H42: =IF(AND(G42<>"",G42<>0),D42/G42,"") | J42: =IF(AND(G42<>"",G42<>0),E42/G42,"") | N42: =IF(AND(I42<>"",I42<>0),G42/I42,"") | O42: =D42/P42 -> #DIV/0! | P42: =$I$8*V42*W42/SUMPRODUCT($W$25:$W$56,$V$25:$V$56) -> 0 | Q42: =$I$9*V42*W42/SUMPRODUCT($W$25:$W$58,$V$25:$V$58) -> 0 | R42: =IF($I$12="","",Q42/$I$12) -> 0 | S42: =IF(W42<>"",IF(D42<>"",D42,($I$8-SUM($S$25:S41))*V42*W42/SUMPRODUCT($W42:$W$58,$V42:$V$58)),"") | T42: =IF(W42<>"",IF(E42<>"",E42,($I$9-SUM($T$25:T41))*V42*W42/SUMPRODUCT($W42:$W$58,$V42:$V$58)),"") | U42: =IF(W42<>"",IF($I$12<>"",IF(G42<>"",G42,($I$9/$I$12-SUM($U$25:U41))*V42*W42/SUMPRODUCT($W42:$W$58,$V42:$V$58)),""),"")
A43: 19 | F43: =IF(AND(E43<>"",E43<>0),D43/E43,"") | H43: =IF(AND(G43<>"",G43<>0),D43/G43,"") | J43: =IF(AND(G43<>"",G43<>0),E43/G43,"") | N43: =IF(AND(I43<>"",I43<>0),G43/I43,"") | O43: =D43/P43 -> #DIV/0! | P43: =$I$8*V43*W43/SUMPRODUCT($W$25:$W$56,$V$25:$V$56) -> 0 | Q43: =$I$9*V43*W43/SUMPRODUCT($W$25:$W$58,$V$25:$V$58) -> 0 | R43: =IF($I$12="","",Q43/$I$12) -> 0 | S43: =IF(W43<>"",IF(D43<>"",D43,($I$8-SUM($S$25:S42))*V43*W43/SUMPRODUCT($W43:$W$58,$V43:$V$58)),"") | T43: =IF(W43<>"",IF(E43<>"",E43,($I$9-SUM($T$25:T42))*V43*W43/SUMPRODUCT($W43:$W$58,$V43:$V$58)),"") | U43: =IF(W43<>"",IF($I$12<>"",IF(G43<>"",G43,($I$9/$I$12-SUM($U$25:U42))*V43*W43/SUMPRODUCT($W43:$W$58,$V43:$V$58)),""),"")
A44: 20 | F44: =IF(AND(E44<>"",E44<>0),D44/E44,"") | H44: =IF(AND(G44<>"",G44<>0),D44/G44,"") | J44: =IF(AND(G44<>"",G44<>0),E44/G44,"") | N44: =IF(AND(I44<>"",I44<>0),G44/I44,"") | O44: =D44/P44 -> #DIV/0! | P44: =$I$8*V44*W44/SUMPRODUCT($W$25:$W$56,$V$25:$V$56) -> 0 | Q44: =$I$9*V44*W44/SUMPRODUCT($W$25:$W$58,$V$25:$V$58) -> 0 | R44: =IF($I$12="","",Q44/$I$12) -> 0 | S44: =IF(W44<>"",IF(D44<>"",D44,($I$8-SUM($S$25:S43))*V44*W44/SUMPRODUCT($W44:$W$58,$V44:$V$58)),"") | T44: =IF(W44<>"",IF(E44<>"",E44,($I$9-SUM($T$25:T43))*V44*W44/SUMPRODUCT($W44:$W$58,$V44:$V$58)),"") | U44: =IF(W44<>"",IF($I$12<>"",IF(G44<>"",G44,($I$9/$I$12-SUM($U$25:U43))*V44*W44/SUMPRODUCT($W44:$W$58,$V44:$V$58)),""),"")
A45: 21 | F45: =IF(AND(E45<>"",E45<>0),D45/E45,"") | H45: =IF(AND(G45<>"",G45<>0),D45/G45,"") | J45: =IF(AND(G45<>"",G45<>0),E45/G45,"") | N45: =IF(AND(I45<>"",I45<>0),G45/I45,"") | O45: =D45/P45 -> #DIV/0! | P45: =$I$8*V45*W45/SUMPRODUCT($W$25:$W$56,$V$25:$V$56) -> 0 | Q45: =$I$9*V45*W45/SUMPRODUCT($W$25:$W$58,$V$25:$V$58) -> 0 | R45: =IF($I$12="","",Q45/$I$12) -> 0 | S45: =IF(W45<>"",IF(D45<>"",D45,($I$8-SUM($S$25:S44))*V45*W45/SUMPRODUCT($W45:$W$58,$V45:$V$58)),"") | T45: =IF(W45<>"",IF(E45<>"",E45,($I$9-SUM($T$25:T44))*V45*W45/SUMPRODUCT($W45:$W$58,$V45:$V$58)),"") | U45: =IF(W45<>"",IF($I$12<>"",IF(G45<>"",G45,($I$9/$I$12-SUM($U$25:U44))*V45*W45/SUMPRODUCT($W45:$W$58,$V45:$V$58)),""),"")
A46: 22 | F46: =IF(AND(E46<>"",E46<>0),D46/E46,"") | H46: =IF(AND(G46<>"",G46<>0),D46/G46,"") | J46: =IF(AND(G46<>"",G46<>0),E46/G46,"") | N46: =IF(AND(I46<>"",I46<>0),G46/I46,"") | O46: =D46/P46 -> #DIV/0! | P46: =$I$8*V46*W46/SUMPRODUCT($W$25:$W$56,$V$25:$V$56) -> 0 | Q46: =$I$9*V46*W46/SUMPRODUCT($W$25:$W$58,$V$25:$V$58) -> 0 | R46: =IF($I$12="","",Q46/$I$12) -> 0 | S46: =IF(W46<>"",IF(D46<>"",D46,($I$8-SUM($S$25:S45))*V46*W46/SUMPRODUCT($W46:$W$58,$V46:$V$58)),"") | T46: =IF(W46<>"",IF(E46<>"",E46,($I$9-SUM($T$25:T45))*V46*W46/SUMPRODUCT($W46:$W$58,$V46:$V$58)),"") | U46: =IF(W46<>"",IF($I$12<>"",IF(G46<>"",G46,($I$9/$I$12-SUM($U$25:U45))*V46*W46/SUMPRODUCT($W46:$W$58,$V46:$V$58)),""),"")
A47: 23 | F47: =IF(AND(E47<>"",E47<>0),D47/E47,"") | H47: =IF(AND(G47<>"",G47<>0),D47/G47,"") | J47: =IF(AND(G47<>"",G47<>0),E47/G47,"") | N47: =IF(AND(I47<>"",I47<>0),G47/I47,"") | O47: =D47/P47 -> #DIV/0! | P47: =$I$8*V47*W47/SUMPRODUCT($W$25:$W$56,$V$25:$V$56) -> 0 | Q47: =$I$9*V47*W47/SUMPRODUCT($W$25:$W$58,$V$25:$V$58) -> 0 | R47: =IF($I$12="","",Q47/$I$12) -> 0 | S47: =IF(W47<>"",IF(D47<>"",D47,($I$8-SUM($S$25:S46))*V47*W47/SUMPRODUCT($W47:$W$58,$V47:$V$58)),"") | T47: =IF(W47<>"",IF(E47<>"",E47,($I$9-SUM($T$25:T46))*V47*W47/SUMPRODUCT($W47:$W$58,$V47:$V$58)),"") | U47: =IF(W47<>"",IF($I$12<>"",IF(G47<>"",G47,($I$9/$I$12-SUM($U$25:U46))*V47*W47/SUMPRODUCT($W47:$W$58,$V47:$V$58)),""),"")
A48: 24 | F48: =IF(AND(E48<>"",E48<>0),D48/E48,"") | H48: =IF(AND(G48<>"",G48<>0),D48/G48,"") | J48: =IF(AND(G48<>"",G48<>0),E48/G48,"") | N48: =IF(AND(I48<>"",I48<>0),G48/I48,"") | O48: =D48/P48 -> #DIV/0! | P48: =$I$8*V48*W48/SUMPRODUCT($W$25:$W$56,$V$25:$V$56) -> 0 | Q48: =$I$9*V48*W48/SUMPRODUCT($W$25:$W$58,$V$25:$V$58) -> 0 | R48: =IF($I$12="","",Q48/$I$12) -> 0 | S48: =IF(W48<>"",IF(D48<>"",D48,($I$8-SUM($S$25:S47))*V48*W48/SUMPRODUCT($W48:$W$58,$V48:$V$58)),"") | T48: =IF(W48<>"",IF(E48<>"",E48,($I$9-SUM($T$25:T47))*V48*W48/SUMPRODUCT($W48:$W$58,$V48:$V$58)),"") | U48: =IF(W48<>"",IF($I$12<>"",IF(G48<>"",G48,($I$9/$I$12-SUM($U$25:U47))*V48*W48/SUMPRODUCT($W48:$W$58,$V48:$V$58)),""),"")
A49: 25 | F49: =IF(AND(E49<>"",E49<>0),D49/E49,"") | H49: =IF(AND(G49<>"",G49<>0),D49/G49,"") | J49: =IF(AND(G49<>"",G49<>0),E49/G49,"") | N49: =IF(AND(I49<>"",I49<>0),G49/I49,"") | O49: =D49/P49 -> #DIV/0! | P49: =$I$8*V49*W49/SUMPRODUCT($W$25:$W$56,$V$25:$V$56) -> 0 | Q49: =$I$9*V49*W49/SUMPRODUCT($W$25:$W$58,$V$25:$V$58) -> 0 | R49: =IF($I$12="","",Q49/$I$12) -> 0 | S49: =IF(W49<>"",IF(D49<>"",D49,($I$8-SUM($S$25:S48))*V49*W49/SUMPRODUCT($W49:$W$58,$V49:$V$58)),"") | T49: =IF(W49<>"",IF(E49<>"",E49,($I$9-SUM($T$25:T48))*V49*W49/SUMPRODUCT($W49:$W$58,$V49:$V$58)),"") | U49: =IF(W49<>"",IF($I$12<>"",IF(G49<>"",G49,($I$9/$I$12-SUM($U$25:U48))*V49*W49/SUMPRODUCT($W49:$W$58,$V49:$V$58)),""),"")
... A53: 29 | F53: =IF(AND(E53<>"",E53<>0),D53/E53,"") | H53: =IF(AND(G53<>"",G53<>0),D53/G53,"") | J53: =IF(AND(G53<>"",G53<>0),E53/G53,"") | N53: =IF(AND(I53<>"",I53<>0),G53/I53,"") | O53: =D53/P53 -> #DIV/0! | P53: =$I$8*V53*W53/SUMPRODUCT($W$25:$W$56,$V$25:$V$56) -> 0 | Q53: =$I$9*V53*W53/SUMPRODUCT($W$25:$W$58,$V$25:$V$58) -> 0 | R53: =IF($I$12="","",Q53/$I$12) -> 0 | S53: =IF(W53<>"",IF(D53<>"",D53,($I$8-SUM($S$25:S52))*V53*W53/SUMPRODUCT($W53:$W$58,$V53:$V$58)),"") | T53: =IF(W53<>"",IF(E53<>"",E53,($I$9-SUM($T$25:T52))*V53*W53/SUMPRODUCT($W53:$W$58,$V53:$V$58)),"") | U53: =IF(W53<>"",IF($I$12<>"",IF(G53<>"",G53,($I$9/$I$12-SUM($U$25:U52))*V53*W53/SUMPRODUCT($W53:$W$58,$V53:$V$58)),""),"")
F54: =IF(AND(E54<>"",E54<>0),D54/E54,"") | H54: =IF(AND(G54<>"",G54<>0),D54/G54,"") | J54: =IF(AND(G54<>"",G54<>0),E54/G54,"") | N54: =IF(AND(I54<>"",I54<>0),G54/I54,"") | O54: =D54/P54 -> #DIV/0! | P54: =$I$8*V54*W54/SUMPRODUCT($W$25:$W$56,$V$25:$V$56) -> 0 | Q54: =$I$9*V54*W54/SUMPRODUCT($W$25:$W$58,$V$25:$V$58) -> 0 | R54: =IF($I$12="","",Q54/$I$12) -> 0 | S54: =IF(W54<>"",IF(D54<>"",D54,($I$8-SUM($S$25:S50))*V54*W54/SUMPRODUCT($W54:$W$58,$V54:$V$58)),"") | T54: =IF(W54<>"",IF(E54<>"",E54,($I$9-SUM($T$25:T50))*V54*W54/SUMPRODUCT($W54:$W$58,$V54:$V$58)),"") | U54: =IF(W54<>"",IF($I$12<>"",IF(G54<>"",G54,($I$9/$I$12-SUM($U$25:U50))*V54*W54/SUMPRODUCT($W54:$W$58,$V54:$V$58)),""),"")
F55: =IF(AND(E55<>"",E55<>0),D55/E55,"") | H55: =IF(AND(G55<>"",G55<>0),D55/G55,"") | J55: =IF(AND(G55<>"",G55<>0),E55/G55,"") | N55: =IF(AND(I55<>"",I55<>0),G55/I55,"") | O55: =D55/P55 -> #DIV/0! | P55: =$I$8*V55*W55/SUMPRODUCT($W$25:$W$56,$V$25:$V$56) -> 0 | Q55: =$I$9*V55*W55/SUMPRODUCT($W$25:$W$58,$V$25:$V$58) -> 0 | R55: =IF($I$12="","",Q55/$I$12) -> 0 | S55: =IF(W55<>"",IF(D55<>"",D55,($I$8-SUM($S$25:S54))*V55*W55/SUMPRODUCT($W55:$W$58,$V55:$V$58)),"") | T55: =IF(W55<>"",IF(E55<>"",E55,($I$9-SUM($T$25:T54))*V55*W55/SUMPRODUCT($W55:$W$58,$V55:$V$58)),"") | U55: =IF(W55<>"",IF($I$12<>"",IF(G55<>"",G55,($I$9/$I$12-SUM($U$25:U54))*V55*W55/SUMPRODUCT($W55:$W$58,$V55:$V$58)),""),"")
F56: =IF(AND(E56<>"",E56<>0),D56/E56,"") | H56: =IF(AND(G56<>"",G56<>0),D56/G56,"") | J56: =IF(AND(G56<>"",G56<>0),E56/G56,"") | N56: =IF(AND(I56<>"",I56<>0),G56/I56,"") | O56: =D56/P56 -> #DIV/0! | P56: =$I$8*V56*W56/SUMPRODUCT($W$25:$W$56,$V$25:$V$56) -> 0 | Q56: =$I$9*V56*W56/SUMPRODUCT($W$25:$W$58,$V$25:$V$58) -> 0 | R56: =IF($I$12="","",Q56/$I$12) -> 0 | S56: =IF(W56<>"",IF(D56<>"",D56,($I$8-SUM($S$25:S55))*V56*W56/SUMPRODUCT($W56:$W$58,$V56:$V$58)),"") | T56: =IF(W56<>"",IF(E56<>"",E56,($I$9-SUM($T$25:T55))*V56*W56/SUMPRODUCT($W56:$W$58,$V56:$V$58)),"") | U56: =IF(W56<>"",IF($I$12<>"",IF(G56<>"",G56,($I$9/$I$12-SUM($U$25:U55))*V56*W56/SUMPRODUCT($W56:$W$58,$V56:$V$58)),""),"")
D57: =SUM(D25:D56) -> 263849 | E57: =SUM(E25:E56) -> 37 | F57: =IF(AND(E57<>"",E57<>0),D57/E57,"") -> 7131.0541 | G57: =SUM(G25:G56) -> 22 | H57: =IF(AND(G57<>"",G57<>0),D57/G57,"") -> 11993.136 | I57: =SUM(I25:I56) -> 237 | J57: =IF(AND(G57<>"",G57<>0),E57/G57,"") -> 1.6818182 | K57: =SUM(K25:K56) -> 91284 | L57: =SUM(L25:L56) -> 0 | M57: =SUM(M25:M56) -> 0 | N57: =IF(AND(I57<>"",I57<>0),G57/I57,"") -> 0.092827004 | O57: =D57/P57 -> 0.56110975 | P57: =SUM(P25:P56) -> 470227.08 | Q57: =SUM(Q25:Q55) -> 72.342628 | R57: =SUM(R25:R55) -> 42.554487 | S57: =SUM(S25:S56) -> 470227.08 | T57: =SUM(T25:T55) -> 72.342628 | U57: =SUM(U25:U55) -> 42.554487

Sheet Арапова А. В.
B1: =TODAY()-1 -> 46000
B2: (отчетная дата) | J2: ЕЖЕДНЕВНЫЙ ОТЧЕТ О ПРОДАЖАХ
B3: Осталось до выполнения плана!!! | J3: Арапова Анна -Мария
C4: =I8-D50 -> 470227.08 | E4: =IF(I8<>0,C4/I8,0) -> 1
F6: Целевые показатели
F7: Показатель | I7: План | J7: Факт | K7: % выполнения | L7: Прогноз выполнения | M7: % выполнения по прогнозу | N7: Отклонение | O7: Факт аналогичного месяца прошлого года | P7: Отклонение LFL
F8: Выручка | I8: ='Ялта, Ленина, 18'!I8/График!AJ31*График!AJ28 -> 470227.08 | J8: =D57 -> 194103 | K8: =IF(AND(I8<>"",I8<>0,J8<>""),J8/I8,"") -> 0.41278567 | L8: =IF(SUMIF($D$25:$D$56,">=0",$P$25:$P$56)<>0,I8*D57/SUMIF($D$25:$D$56,">=0",$P$25:$P$56),0) -> 307329.75 | M8: =IF(AND(I8<>"",I8<>0,L8<>"",L8<>0),L8/I8,"") -> 0.65357731 | N8: =IF(AND(J8<>0,J8<>"",I8<>0,I8<>""),L8-I8,"") -> -162897.33 | P8: =IF(AND(O8<>"",O8<>0,L8<>"",L8<>0),-O8+L8,"") | Q8: =IF(AND(P8<>"",P8<>0,O8<>0,O8<>""),P8/O8,"")
F9: Кол-во изделий | I9: =I8/I11 -> 72.342628 | J9: =E57 -> 31 | K9: =IF(AND(I9<>"",I9<>0,J9<>""),J9/I9,"") -> 0.42851636 | L9: =IF(SUMIF($E$25:$E$54,">=0",$Q$25:$Q$54)<>0,I9*E57/SUMIF($E$25:$E$54,">=0",$Q$25:$Q$54),0) -> 49.083333 | M9: =IF(AND(I9<>"",I9<>0,L9<>"",L9<>0),L9/I9,"") -> 0.67848424 | N9: =IF(AND(J9<>0,J9<>"",I9<>0,I9<>""),L9-I9,"") -> -23.259295 | O9: =O8/O11 -> #DIV/0! | P9: =IF(AND(O9<>"",O9<>0,L9<>"",L9<>0),-O9+L9,"") -> #DIV/0! | Q9: =IF(AND(P9<>"",P9<>0,O9<>0,O9<>""),P9/O9,"") -> #DIV/0!
F10: Средний чек | I10: =I11*I12 -> 11050 | J10: =H57 -> 8439.2609 | K10: =IF(AND(I10<>"",I10<>0,J10<>""),J10/I10,"") -> 0.76373402 | L10: =J10 -> 8439.2609 | M10: =IF(AND(I10<>"",I10<>0,L10<>"",L10<>0),L10/I10,"") -> 0.76373402 | N10: =IF(AND(J10<>0,J10<>"",I10<>0,I10<>""),L10-I10,"") -> -2610.7391 | O10: =O11*O12 -> 0 | P10: =IF(AND(O10<>"",O10<>0,L10<>"",L10<>0),-O10+L10,"") | Q10: =IF(AND(P10<>"",P10<>0,O10<>0,O10<>""),P10/O10,"") | S10: IS | V10: =M23 -> Agafi
F11: Средняя стоимость изделия | I11: ='Ялта, Ленина, 18'!I11 -> 6500 | J11: =F57 -> 6261.3871 | K11: =IF(AND(I11<>"",I11<>0,J11<>""),J11/I11,"") -> 0.96329032 | L11: =IF(L9>0,L8/L9,"") -> 6261.3871 | M11: =IF(AND(I11<>"",I11<>0,L11<>"",L11<>0),L11/I11,"") -> 0.96329032 | N11: =IF(AND(J11<>0,J11<>"",I11<>0,I11<>""),L11-I11,"") -> -238.6129 | P11: =IF(AND(O11<>"",O11<>0,L11<>"",L11<>0),-O11+L11,"") | Q11: =IF(AND(P11<>"",P11<>0,O11<>0,O11<>""),P11/O11,"")
F12: Длина чека | I12: ='Ялта, Ленина, 18'!I12 -> 1.7 | J12: =J57 -> 1.3478261 | K12: =IF(AND(I12<>"",I12<>0,J12<>""),J12/I12,"") -> 0.79283887 | L12: =J12 -> 1.3478261 | M12: =IF(AND(I12<>"",I12<>0,L12<>"",L12<>0),L12/I12,"") -> 0.79283887 | N12: =IF(AND(J12<>0,J12<>"",I12<>0,I12<>""),L12-I12,"") -> -0.35217391 | P12: =IF(AND(O12<>"",O12<>0,L12<>"",L12<>0),-O12+L12,"") | Q12: =IF(AND(P12<>"",P12<>0,O12<>0,O12<>""),P12/O12,"") | S12: ='Ялта, Ленина, 18'!S12*График!AJ28/График!AJ31 -> 116057.69 | T12: =L57 -> 34346 | U12: =S12-T12 -> 81711.692 | V12: ='Ялта, Ленина, 18'!V12/График!AJ31*График!AJ28 -> 109230.77 | W12: =M57 -> 0 | X12: =V12-W12 -> 109230.77
F13: Кол-во чеков | I13: =IF(I12<>0,I9/I12,"") -> 42.554487 | J13: =G57 -> 23 | K13: =IF(AND(I13<>"",I13<>0,J13<>""),J13/I13,"") -> 0.54048354 | L13: =IF(SUMIF($G$25:$G$54,">=0",$R$25:$R$54)<>0,I13*G57/SUMIF($G$25:$G$54,">=0",$R$25:$R$54),"") -> 36.416667 | M13: =IF(AND(I13<>"",I13<>0,L13<>"",L13<>0),L13/I13,"") -> 0.85576561 | N13: =IF(AND(J13<>0,J13<>"",I13<>0,I13<>""),L13-I13,"") -> -6.1378205 | P13: =IF(AND(O13<>"",O13<>0,L13<>"",L13<>0),-O13+L13,"") | Q13: =IF(AND(P13<>"",P13<>0,O13<>0,O13<>""),P13/O13,"") | S13: =T12/S12 -> 0.29593902 | T13: =S13/J14*I14 -> 0.29593902 | V13: =W12/V12 -> 0 | W13: =V13/J14*I14 -> 0
F14: Кол-во смен план/отработано | I14: =График!AI27 -> 19 | J14: 19 | K14: =IF(AND(I14<>"",I14<>0,J14<>""),J14/I14,"") -> 1 | L14: =I14 -> 19 | M14: =IF(AND(I14<>"",I14<>0,L14<>"",L14<>0),L14/I14,"") -> 1 | N14: =IF(AND(J14<>0,J14<>"",I14<>0,I14<>""),L14-I14,"") -> 0 | P14: =IF(AND(O14<>"",O14<>0,L14<>"",L14<>0),-O14+L14,"") | Q14: =IF(AND(P14<>"",P14<>0,O14<>0,O14<>""),P14/O14,"")
F15: Средние продажи в смену | I15: ='Ялта, Ленина, 18'!I15 -> 68878.333 | J15: =J8/J14 -> 10215.947 | K15: =IF(AND(I15<>"",I15<>0,J15<>""),J15/I15,"") -> 0.14831874 | L15: =J15 -> 10215.947 | M15: =IF(AND(I15<>"",I15<>0,L15<>"",L15<>0),L15/I15,"") -> 0.14831874 | N15: =IF(AND(J15<>0,J15<>"",I15<>0,I15<>""),L15-I15,"") -> -58662.386 | P15: =IF(AND(O15<>"",O15<>0,L15<>"",L15<>0),-O15+L15,"") | Q15: =IF(AND(P15<>"",P15<>0,O15<>0,O15<>""),P15/O15,"")
F16: Отставание/Перевыполнение | J16: =J8-I15*J14 -> -1114585.3 | K16: =IF(AND(I16<>"",I16<>0,J16<>""),J16/I16,"") | L16: =J16 -> -1114585.3 | M16: =IF(AND(I16<>"",I16<>0,L16<>"",L16<>0),L16/I16,"") | N16: =IF(AND(J16<>0,J16<>"",I16<>0,I16<>""),L16-I16,"") | P16: =IF(AND(O16<>"",O16<>0,L16<>"",L16<>0),-O16+L16,"") | Q16: =IF(AND(P16<>"",P16<>0,O16<>0,O16<>""),P16/O16,"") | S16: UNOde50
F17: Трафик | I17: ='Ялта, Ленина, 18'!I17/График!AJ31*График!AJ28 -> 386.85897 | J17: =I57 -> 318 | K17: =IF(AND(I17<>"",I17<>0,J17<>""),J17/I17,"") -> 0.82200497 | L17: =J17/J14*I14 -> 318 | M17: =IF(AND(I17<>"",I17<>0,L17<>"",L17<>0),L17/I17,"") -> 0.82200497 | N17: =IF(AND(J17<>0,J17<>"",I17<>0,I17<>""),L17-I17,"") -> -68.858974 | P17: =IF(AND(O17<>"",O17<>0,L17<>"",L17<>0),-O17+L17,"") | Q17: =IF(AND(P17<>"",P17<>0,O17<>0,O17<>""),P17/O17,"")
K18: =IF(AND(I18<>"",I18<>0,J18<>""),J18/I18,"") | L18: =J18 -> 0 | M18: =IF(AND(I18<>"",I18<>0,L18<>"",L18<>0),L18/I18,"") | N18: =IF(AND(J18<>0,J18<>"",I18<>0,I18<>""),L18-I18,"") | O18: 0 | P18: =IF(AND(O18<>"",O18<>0,L18<>"",L18<>0),-O18+L18,"") | Q18: =IF(AND(P18<>"",P18<>0,O18<>0,O18<>""),P18/O18,"") | S18: ='Ялта, Ленина, 18'!S18*График!AJ28/График!AJ31 -> 232115.38 | T18: =K57 -> 29977
K19: =IF(AND(I19<>"",I19<>0,J19<>""),J19/I19,"") | L19: =J19 -> 0 | M19: =IF(AND(I19<>"",I19<>0,L19<>"",L19<>0),L19/I19,"") | N19: =IF(AND(J19<>0,J19<>"",I19<>0,I19<>""),L19-I19,"") | O19: 0 | P19: =IF(AND(O19<>"",O19<>0,L19<>"",L19<>0),-O19+L19,"") | Q19: =IF(AND(P19<>"",P19<>0,O19<>0,O19<>""),P19/O19,"") | S19: =T18/S18 -> 0.12914698 | T19: =S19/J14*I14 -> 0.12914698
F20: Конверсия план/факт | I20: ='Ялта, Ленина, 18'!I20 -> 0.11 | J20: =N57 -> 0.072327044 | K20: =J20/I20 -> 0.65751858 | L20: =IF(AND(K8<>0,I14<>0,I57<>0),(I57*N57+(I57/K8-I57)*I20)/(I57/K8),0) -> 0.094449144 | M20: =IF(AND(I20<>"",I20<>0,L20<>"",L20<>0),L20/I20,"") -> 0.85862858 | N20: =IF(AND(J20<>0,J20<>"",I20<>0,I20<>""),L20-I20,"") -> -0.015550856 | P20: =IF(AND(O20<>"",O20<>0,L20<>"",L20<>0),-O20+L20,"") | Q20: =IF(AND(P20<>"",P20<>0,O20<>0,O20<>""),P20/O20,"")
B22: Факт продаж за месяц | O22: % выполнения дневного плана | P22: Раcпределение плана по дням
B23: Дата | C23: День недели | D23: Выручка (руб) | E23: Кол-во единиц (шт.) | F23: Средняя стоимость изделия (руб.) | G23: Количество чеков (шт.) | H23: Средняя сумма чека (руб.) | I23: Трафик | J23: Длина чека (шт.) | K23: UNOde50 | L23: IS | M23: Agafi | N23: Конверсия (%) | P23: выручка, план | Q23: кол-во ед, план | R23: Кол-во чеков, план | S23: выручка, скорректир.план | T23: кол-во ед, скорр. план | U23: кол-во чеков, скорр. план | V23: Коэфф. Дня Недели | W23: Специфика месяца
B24: 1 | C24: 2 | D24: 3 | E24: в | F24: 5 | G24: 6 | H24: 7 | I24: 8 | J24: 9 | K24: 10 | L24: 11 | M24: 12 | N24: 13 | P24: 1 | Q24: 2 | R24: 3 | S24: 4 | T24: 5 | U24: 6 | V24: 10 | W24: 11
A25: 1 | B25: 45962 | C25: сб | D25: =10584+8403 -> 18987 | E25: 4 | F25: =IF(AND(E25<>"",E25<>0),D25/E25,"") -> 4746.75 | G25: 3 | H25: =IF(AND(G25<>"",G25<>0),D25/G25,"") -> 6329 | I25: 20 | J25: =IF(AND(G25<>"",G25<>0),E25/G25,"") -> 1.3333333 | L25: 8403 | N25: =IF(AND(I25<>"",I25<>0),G25/I25,"") -> 0.15 | O25: =D25/P25 -> 0.7671889 | P25: =$I$8*V25*W25/SUMPRODUCT($W$25:$W$56,$V$25:$V$56) -> 24748.794 | Q25: =$I$9*V25*W25/SUMPRODUCT($W$25:$W$56,$V$25:$V$56) -> 3.8075067 | R25: =IF($I$12="","",Q25/$I$12) -> 2.2397099 | S25: =IF(D25<>"",D25,P25) -> 18987 | T25: =IF(E25<>"",E25,Q25) -> 4 | U25: =IF(G25<>"",G25,R25) -> 3 | V25: 1 | W25: 1
A26: 2 | B26: 45964 | C26: пн | F26: =IF(AND(E26<>"",E26<>0),D26/E26,"") | H26: =IF(AND(G26<>"",G26<>0),D26/G26,"") | I26: 25 | J26: =IF(AND(G26<>"",G26<>0),E26/G26,"") | N26: =IF(AND(I26<>"",I26<>0),G26/I26,"") -> 0 | O26: =D26/P26 -> 0 | P26: =$I$8*V26*W26/SUMPRODUCT($W$25:$W$56,$V$25:$V$56) -> 24748.794 | Q26: =$I$9*V26*W26/SUMPRODUCT($W$25:$W$58,$V$25:$V$58) -> 3.8075067 | R26: =IF($I$12="","",Q26/$I$12) -> 2.2397099 | S26: =IF(W26<>"",IF(D26<>"",D26,($I$8-SUM($S$25:S25))*V26*W26/SUMPRODUCT($W26:$W$56,$V26:$V$56)),"") -> 25068.894 | T26: =IF(W26<>"",IF(E26<>"",E26,($I$9-SUM($T$25:T25))*V26*W26/SUMPRODUCT($W26:$W$55,$V26:$V$55)),"") -> 3.7968127 | U26: =IF(W26<>"",IF($I$12<>"",IF(G26<>"",G26,($I$9/$I$12-SUM($U$25:U25))*V26*W26/SUMPRODUCT($W26:$W$55,$V26:$V$55)),""),"") -> 2.1974715 | V26: 1 | W26: 1
A27: 3 | B27: 45965 | C27: вт | D27: 5393 | E27: 1 | F27: =IF(AND(E27<>"",E27<>0),D27/E27,"") -> 5393 | G27: 1 | H27: =IF(AND(G27<>"",G27<>0),D27/G27,"") -> 5393 | I27: 30 | J27: =IF(AND(G27<>"",G27<>0),E27/G27,"") -> 1 | N27: =IF(AND(I27<>"",I27<>0),G27/I27,"") -> 0.033333333 | O27: =D27/P27 -> 0.21790961 | P27: =$I$8*V27*W27/SUMPRODUCT($W$25:$W$56,$V$25:$V$56) -> 24748.794 | Q27: =$I$9*V27*W27/SUMPRODUCT($W$25:$W$58,$V$25:$V$58) -> 3.8075067 | R27: =IF($I$12="","",Q27/$I$12) -> 2.2397099 | S27: =IF(W27<>"",IF(D27<>"",D27,($I$8-SUM($S$25:S26))*V27*W27/SUMPRODUCT($W27:$W$58,$V27:$V$58)),"") -> 5393 | T27: =IF(W27<>"",IF(E27<>"",E27,($I$9-SUM($T$25:T26))*V27*W27/SUMPRODUCT($W27:$W$55,$V27:$V$55)),"") -> 1 | U27: =IF(W27<>"",IF($I$12<>"",IF(G27<>"",G27,($I$9/$I$12-SUM($U$25:U26))*V27*W27/SUMPRODUCT($W27:$W$55,$V27:$V$55)),""),"") -> 1 | V27: 1 | W27: 1
A28: 4 | B28: 45967 | C28: чт | F28: =IF(AND(E28<>"",E28<>0),D28/E28,"") | H28: =IF(AND(G28<>"",G28<>0),D28/G28,"") | J28: =IF(AND(G28<>"",G28<>0),E28/G28,"") | N28: =IF(AND(I28<>"",I28<>0),G28/I28,"") | O28: =D28/P28 -> 0 | P28: =$I$8*V28*W28/SUMPRODUCT($W$25:$W$56,$V$25:$V$56) -> 24748.794 | Q28: =$I$9*V28*W28/SUMPRODUCT($W$25:$W$58,$V$25:$V$58) -> 3.8075067 | R28: =IF($I$12="","",Q28/$I$12) -> 2.2397099 | S28: =IF(W28<>"",IF(D28<>"",D28,($I$8-SUM($S$25:S27))*V28*W28/SUMPRODUCT($W28:$W$58,$V28:$V$58)),"") -> 26298.637 | T28: =IF(W28<>"",IF(E28<>"",E28,($I$9-SUM($T$25:T27))*V28*W28/SUMPRODUCT($W28:$W$58,$V28:$V$58)),"") -> 3.9716135 | U28: =IF(W28<>"",IF($I$12<>"",IF(G28<>"",G28,($I$9/$I$12-SUM($U$25:U27))*V28*W28/SUMPRODUCT($W28:$W$58,$V28:$V$58)),""),"") -> 2.2723135 | V28: 1 | W28: 1
A29: 5 | B29: 45968 | C29: пт | D29: 14776 | E29: 3 | F29: =IF(AND(E29<>"",E29<>0),D29/E29,"") -> 4925.3333 | G29: 3 | H29: =IF(AND(G29<>"",G29<>0),D29/G29,"") -> 4925.3333 | I29: 20 | J29: =IF(AND(G29<>"",G29<>0),E29/G29,"") -> 1 | N29: =IF(AND(I29<>"",I29<>0),G29/I29,"") -> 0.15 | O29: =D29/P29 -> 0.5970392 | P29: =$I$8*V29*W29/SUMPRODUCT($W$25:$W$56,$V$25:$V$56) -> 24748.794 | Q29: =$I$9*V29*W29/SUMPRODUCT($W$25:$W$58,$V$25:$V$58) -> 3.8075067 | R29: =IF($I$12="","",Q29/$I$12) -> 2.2397099 | S29: =IF(W29<>"",IF(D29<>"",D29,($I$8-SUM($S$25:S28))*V29*W29/SUMPRODUCT($W29:$W$58,$V29:$V$58)),"") -> 14776 | T29: =IF(W29<>"",IF(E29<>"",E29,($I$9-SUM($T$25:T28))*V29*W29/SUMPRODUCT($W29:$W$58,$V29:$V$58)),"") -> 3 | U29: =IF(W29<>"",IF($I$12<>"",IF(G29<>"",G29,($I$9/$I$12-SUM($U$25:U28))*V29*W29/SUMPRODUCT($W29:$W$58,$V29:$V$58)),""),"") -> 3 | V29: 1 | W29: 1
A30: 6 | B30: 45969 | C30: сб | D30: 15565 | E30: 4 | F30: =IF(AND(E30<>"",E30<>0),D30/E30,"") -> 3891.25 | G30: 2 | H30: =IF(AND(G30<>"",G30<>0),D30/G30,"") -> 7782.5 | I30: 20 | J30: =IF(AND(G30<>"",G30<>0),E30/G30,"") -> 2 | N30: =IF(AND(I30<>"",I30<>0),G30/I30,"") -> 0.1 | O30: =D30/P30 -> 0.62891954 | P30: =$I$8*V30*W30/SUMPRODUCT($W$25:$W$56,$V$25:$V$56) -> 24748.794 | Q30: =$I$9*V30*W30/SUMPRODUCT($W$25:$W$58,$V$25:$V$58) -> 3.8075067 | R30: =IF($I$12="","",Q30/$I$12) -> 2.2397099 | S30: =IF(W30<>"",IF(D30<>"",D30,($I$8-SUM($S$25:S29))*V30*W30/SUMPRODUCT($W30:$W$58,$V30:$V$58)),"") -> 15565 | T30: =IF(W30<>"",IF(E30<>"",E30,($I$9-SUM($T$25:T29))*V30*W30/SUMPRODUCT($W30:$W$58,$V30:$V$58)),"") -> 4 | U30: =IF(W30<>"",IF($I$12<>"",IF(G30<>"",G30,($I$9/$I$12-SUM($U$25:U29))*V30*W30/SUMPRODUCT($W30:$W$58,$V30:$V$58)),""),"") -> 2 | V30: 1 | W30: 1
A31: 7 | B31: 45972 | C31: вт | F31: =IF(AND(E31<>"",E31<>0),D31/E31,"") | H31: =IF(AND(G31<>"",G31<>0),D31/G31,"") | I31: 20 | J31: =IF(AND(G31<>"",G31<>0),E31/G31,"") | N31: =IF(AND(I31<>"",I31<>0),G31/I31,"") -> 0 | O31: =D31/P31 -> 0 | P31: =$I$8*V31*W31/SUMPRODUCT($W$25:$W$56,$V$25:$V$56) -> 24748.794 | Q31: =$I$9*V31*W31/SUMPRODUCT($W$25:$W$58,$V$25:$V$58) -> 3.8075067 | R31: =IF($I$12="","",Q31/$I$12) -> 2.2397099 | S31: =IF(W31<>"",IF(D31<>"",D31,($I$8-SUM($S$25:S30))*V31*W31/SUMPRODUCT($W31:$W$58,$V31:$V$58)),"") -> 28010.658 | T31: =IF(W31<>"",IF(E31<>"",E31,($I$9-SUM($T$25:T30))*V31*W31/SUMPRODUCT($W31:$W$58,$V31:$V$58)),"") -> 4.0441694 | U31: =IF(W31<>"",IF($I$12<>"",IF(G31<>"",G31,($I$9/$I$12-SUM($U$25:U30))*V31*W31/SUMPRODUCT($W31:$W$58,$V31:$V$58)),""),"") -> 2.2372848 | V31: 1 | W31: 1
A32: 8 | B32: 45973 | C32: ср | D32: 16902 | E32: 1 | F32: =IF(AND(E32<>"",E32<>0),D32/E32,"") -> 16902 | G32: 1 | H32: =IF(AND(G32<>"",G32<>0),D32/G32,"") -> 16902 | I32: 15 | J32: =IF(AND(G32<>"",G32<>0),E32/G32,"") -> 1 | L32: 16902 | N32: =IF(AND(I32<>"",I32<>0),G32/I32,"") -> 0.066666667 | O32: =D32/P32 -> 0.68294237 | P32: =$I$8*V32*W32/SUMPRODUCT($W$25:$W$56,$V$25:$V$56) -> 24748.794 | Q32: =$I$9*V32*W32/SUMPRODUCT($W$25:$W$58,$V$25:$V$58) -> 3.8075067 | R32: =IF($I$12="","",Q32/$I$12) -> 2.2397099 | S32: =IF(W32<>"",IF(D32<>"",D32,($I$8-SUM($S$25:S31))*V32*W32/SUMPRODUCT($W32:$W$58,$V32:$V$58)),"") -> 16902 | T32: =IF(W32<>"",IF(E32<>"",E32,($I$9-SUM($T$25:T31))*V32*W32/SUMPRODUCT($W32:$W$58,$V32:$V$58)),"") -> 1 | U32: =IF(W32<>"",IF($I$12<>"",IF(G32<>"",G32,($I$9/$I$12-SUM($U$25:U31))*V32*W32/SUMPRODUCT($W32:$W$58,$V32:$V$58)),""),"") -> 1 | V32: 1 | W32: 1
A33: 9 | B33: 45975 | C33: пт | D33: 31566 | E33: 4 | F33: =IF(AND(E33<>"",E33<>0),D33/E33,"") -> 7891.5 | G33: 2 | H33: =IF(AND(G33<>"",G33<>0),D33/G33,"") -> 15783 | I33: 20 | J33: =IF(AND(G33<>"",G33<>0),E33/G33,"") -> 2 | N33: =IF(AND(I33<>"",I33<>0),G33/I33,"") -> 0.1 | O33: =D33/P33 -> 1.2754561 | P33: =$I$8*V33*W33/SUMPRODUCT($W$25:$W$56,$V$25:$V$56) -> 24748.794 | Q33: =$I$9*V33*W33/SUMPRODUCT($W$25:$W$58,$V$25:$V$58) -> 3.8075067 | R33: =IF($I$12="","",Q33/$I$12) -> 2.2397099 | S33: =IF(W33<>"",IF(D33<>"",D33,($I$8-SUM($S$25:S32))*V33*W33/SUMPRODUCT($W33:$W$58,$V33:$V$58)),"") -> 31566 | T33: =IF(W33<>"",IF(E33<>"",E33,($I$9-SUM($T$25:T32))*V33*W33/SUMPRODUCT($W33:$W$58,$V33:$V$58)),"") -> 4 | U33: =IF(W33<>"",IF($I$12<>"",IF(G33<>"",G33,($I$9/$I$12-SUM($U$25:U32))*V33*W33/SUMPRODUCT($W33:$W$58,$V33:$V$58)),""),"") -> 2 | V33: 1 | W33: 1
A34: 10 | B34: 45977 | C34: вс | D34: 14352 | E34: 3 | F34: =IF(AND(E34<>"",E34<>0),D34/E34,"") -> 4784 | G34: 2 | H34: =IF(AND(G34<>"",G34<>0),D34/G34,"") -> 7176 | I34: 12 | J34: =IF(AND(G34<>"",G34<>0),E34/G34,"") -> 1.5 | N34: =IF(AND(I34<>"",I34<>0),G34/I34,"") -> 0.16666667 | O34: =D34/P34 -> 0.57990705 | P34: =$I$8*V34*W34/SUMPRODUCT($W$25:$W$56,$V$25:$V$56) -> 24748.794 | Q34: =$I$9*V34*W34/SUMPRODUCT($W$25:$W$58,$V$25:$V$58) -> 3.8075067 | R34: =IF($I$12="","",Q34/$I$12) -> 2.2397099 | S34: =IF(W34<>"",IF(D34<>"",D34,($I$8-SUM($S$25:S33))*V34*W34/SUMPRODUCT($W34:$W$58,$V34:$V$58)),"") -> 14352 | T34: =IF(W34<>"",IF(E34<>"",E34,($I$9-SUM($T$25:T33))*V34*W34/SUMPRODUCT($W34:$W$58,$V34:$V$58)),"") -> 3 | U34: =IF(W34<>"",IF($I$12<>"",IF(G34<>"",G34,($I$9/$I$12-SUM($U$25:U33))*V34*W34/SUMPRODUCT($W34:$W$58,$V34:$V$58)),""),"") -> 2 | V34: 1 | W34: 1
A35: 11 | B35: 45978 | C35: пн | F35: =IF(AND(E35<>"",E35<>0),D35/E35,"") | H35: =IF(AND(G35<>"",G35<>0),D35/G35,"") | I35: 13 | J35: =IF(AND(G35<>"",G35<>0),E35/G35,"") | N35: =IF(AND(I35<>"",I35<>0),G35/I35,"") -> 0 | O35: =D35/P35 -> 0 | P35: =$I$8*V35*W35/SUMPRODUCT($W$25:$W$56,$V$25:$V$56) -> 24748.794 | Q35: =$I$9*V35*W35/SUMPRODUCT($W$25:$W$58,$V$25:$V$58) -> 3.8075067 | R35: =IF($I$12="","",Q35/$I$12) -> 2.2397099 | S35: =IF(W35<>"",IF(D35<>"",D35,($I$8-SUM($S$25:S34))*V35*W35/SUMPRODUCT($W35:$W$58,$V35:$V$58)),"") -> 30367.544 | T35: =IF(W35<>"",IF(E34<>"",E34,($I$9-SUM($T$25:T34))*V35*W35/SUMPRODUCT($W35:$W$58,$V35:$V$58)),"") -> 3 | U35: =IF(W35<>"",IF($I$12<>"",IF(G35<>"",G35,($I$9/$I$12-SUM($U$25:U34))*V35*W35/SUMPRODUCT($W35:$W$58,$V35:$V$58)),""),"") -> 2.4274908 | V35: 1 | W35: 1
A36: 11 | B36: 45979 | C36: вт | F36: =IF(AND(E36<>"",E36<>0),D36/E36,"") | H36: =IF(AND(G36<>"",G36<>0),D36/G36,"") | J36: =IF(AND(G36<>"",G36<>0),E36/G36,"") | N36: =IF(AND(I36<>"",I36<>0),G36/I36,"") | O36: =D36/P36 -> 0 | P36: =$I$8*V36*W36/SUMPRODUCT($W$25:$W$56,$V$25:$V$56) -> 24748.794 | Q36: =$I$9*V36*W36/SUMPRODUCT($W$25:$W$58,$V$25:$V$58) -> 3.8075067 | R36: =IF($I$12="","",Q36/$I$12) -> 2.2397099 | S36: =IF(W36<>"",IF(D36<>"",D36,($I$8-SUM($S$25:S35))*V36*W36/SUMPRODUCT($W36:$W$58,$V36:$V$58)),"") -> 30367.544 | T36: =IF(W36<>"",IF(E35<>"",E35,($I$9-SUM($T$25:T35))*V36*W36/SUMPRODUCT($W36:$W$58,$V36:$V$58)),"") -> 4.6912541 | U36: =IF(W36<>"",IF($I$12<>"",IF(G36<>"",G36,($I$9/$I$12-SUM($U$25:U35))*V36*W36/SUMPRODUCT($W36:$W$58,$V36:$V$58)),""),"") -> 2.4274908 | V36: 1 | W36: 1
A37: 13 | B37: 45982 | C37: пт | D37: 8212 | E37: 1 | F37: =IF(AND(E37<>"",E37<>0),D37/E37,"") -> 8212 | G37: 2 | H37: =IF(AND(G37<>"",G37<>0),D37/G37,"") -> 4106 | I37: 14 | J37: =IF(AND(G37<>"",G37<>0),E37/G37,"") -> 0.5 | L37: 220 | N37: =IF(AND(I37<>"",I37<>0),G37/I37,"") -> 0.14285714 | O37: =D37/P37 -> 0.33181415 | P37: =$I$8*V37*W37/SUMPRODUCT($W$25:$W$56,$V$25:$V$56) -> 24748.794 | Q37: =$I$9*V37*W37/SUMPRODUCT($W$25:$W$58,$V$25:$V$58) -> 3.8075067 | R37: =IF($I$12="","",Q37/$I$12) -> 2.2397099 | S37: =IF(W37<>"",IF(D37<>"",D37,($I$8-SUM($S$25:S36))*V37*W37/SUMPRODUCT($W37:$W$58,$V37:$V$58)),"") -> 8212 | T37: =IF(W37<>"",IF(E37<>"",E37,($I$9-SUM($T$25:T36))*V37*W37/SUMPRODUCT($W37:$W$58,$V37:$V$58)),"") -> 1 | U37: =IF(W37<>"",IF($I$12<>"",IF(G37<>"",G37,($I$9/$I$12-SUM($U$25:U36))*V37*W37/SUMPRODUCT($W37:$W$58,$V37:$V$58)),""),"") -> 2 | V37: 1 | W37: 1
A38: 14 | B38: 45983 | C38: сб | D38: 31166 | E38: 4 | F38: =IF(AND(E38<>"",E38<>0),D38/E38,"") -> 7791.5 | G38: 2 | H38: =IF(AND(G38<>"",G38<>0),D38/G38,"") -> 15583 | I38: 30 | J38: =IF(AND(G38<>"",G38<>0),E38/G38,"") -> 2 | K38: 11491 | N38: =IF(AND(I38<>"",I38<>0),G38/I38,"") -> 0.066666667 | O38: =D38/P38 -> 1.2592937 | P38: =$I$8*V38*W38/SUMPRODUCT($W$25:$W$56,$V$25:$V$56) -> 24748.794 | Q38: =$I$9*V38*W38/SUMPRODUCT($W$25:$W$58,$V$25:$V$58) -> 3.8075067 | R38: =IF($I$12="","",Q38/$I$12) -> 2.2397099 | S38: =IF(W38<>"",IF(D38<>"",D38,($I$8-SUM($S$25:S37))*V38*W38/SUMPRODUCT($W38:$W$58,$V38:$V$58)),"") -> 31166 | T38: =IF(W38<>"",IF(E38<>"",E38,($I$9-SUM($T$25:T37))*V38*W38/SUMPRODUCT($W38:$W$58,$V38:$V$58)),"") -> 4 | U38: =IF(W38<>"",IF($I$12<>"",IF(G38<>"",G38,($I$9/$I$12-SUM($U$25:U37))*V38*W38/SUMPRODUCT($W38:$W$58,$V38:$V$58)),""),"") -> 2 | V38: 1 | W38: 1
A39: 15 | B39: 45985 | C39: пн | F39: =IF(AND(E39<>"",E39<>0),D39/E39,"") | H39: =IF(AND(G39<>"",G39<>0),D39/G39,"") | I39: 10 | J39: =IF(AND(G39<>"",G39<>0),E39/G39,"") | N39: =IF(AND(I39<>"",I39<>0),G39/I39,"") -> 0 | O39: =D39/P39 -> 0 | P39: =$I$8*V39*W39/SUMPRODUCT($W$25:$W$56,$V$25:$V$56) -> 24748.794 | Q39: =$I$9*V39*W39/SUMPRODUCT($W$25:$W$58,$V$25:$V$58) -> 3.8075067 | R39: =IF($I$12="","",Q39/$I$12) -> 2.2397099 | S39: =IF(W39<>"",IF(D39<>"",D39,($I$8-SUM($S$25:S38))*V39*W39/SUMPRODUCT($W39:$W$58,$V39:$V$58)),"") -> 34638.961 | T39: =IF(W39<>"",IF(E39<>"",E39,($I$9-SUM($T$25:T38))*V39*W39/SUMPRODUCT($W39:$W$58,$V39:$V$58)),"") -> 5.5677557 | U39: =IF(W39<>"",IF($I$12<>"",IF(G39<>"",G39,($I$9/$I$12-SUM($U$25:U38))*V39*W39/SUMPRODUCT($W39:$W$58,$V39:$V$58)),""),"") -> 2.5984872 | V39: 1 | W39: 1
A40: 16 | B40: 45986 | C40: вт | D40: 12714 | E40: 2 | F40: =IF(AND(E40<>"",E40<>0),D40/E40,"") -> 6357 | G40: 2 | H40: =IF(AND(G40<>"",G40<>0),D40/G40,"") -> 6357 | I40: 7 | J40: =IF(AND(G40<>"",G40<>0),E40/G40,"") -> 1 | L40: 8821 | N40: =IF(AND(I40<>"",I40<>0),G40/I40,"") -> 0.28571429 | O40: =D40/P40 -> 0.513722 | P40: =$I$8*V40*W40/SUMPRODUCT($W$25:$W$56,$V$25:$V$56) -> 24748.794 | Q40: =$I$9*V40*W40/SUMPRODUCT($W$25:$W$58,$V$25:$V$58) -> 3.8075067 | R40: =IF($I$12="","",Q40/$I$12) -> 2.2397099 | S40: =IF(W40<>"",IF(D40<>"",D40,($I$8-SUM($S$25:S39))*V40*W40/SUMPRODUCT($W40:$W$58,$V40:$V$58)),"") -> 12714 | T40: =IF(W40<>"",IF(E40<>"",E40,($I$9-SUM($T$25:T39))*V40*W40/SUMPRODUCT($W40:$W$58,$V40:$V$58)),"") -> 2 | U40: =IF(W40<>"",IF($I$12<>"",IF(G40<>"",G40,($I$9/$I$12-SUM($U$25:U39))*V40*W40/SUMPRODUCT($W40:$W$58,$V40:$V$58)),""),"") -> 2 | V40: 1 | W40: 1
A41: 17 | B41: 45989 | C41: пт | D41: 6993 | E41: 1 | F41: =IF(AND(E41<>"",E41<>0),D41/E41,"") -> 6993 | G41: 1 | H41: =IF(AND(G41<>"",G41<>0),D41/G41,"") -> 6993 | I41: 15 | J41: =IF(AND(G41<>"",G41<>0),E41/G41,"") -> 1 | K41: 6993 | N41: =IF(AND(I41<>"",I41<>0),G41/I41,"") -> 0.066666667 | O41: =D41/P41 -> 0.28255922 | P41: =$I$8*V41*W41/SUMPRODUCT($W$25:$W$56,$V$25:$V$56) -> 24748.794 | Q41: =$I$9*V41*W41/SUMPRODUCT($W$25:$W$58,$V$25:$V$58) -> 3.8075067 | R41: =IF($I$12="","",Q41/$I$12) -> 2.2397099 | S41: =IF(W41<>"",IF(D41<>"",D41,($I$8-SUM($S$25:S40))*V41*W41/SUMPRODUCT($W41:$W$58,$V41:$V$58)),"") -> 6993 | T41: =IF(W41<>"",IF(E41<>"",E41,($I$9-SUM($T$25:T40))*V41*W41/SUMPRODUCT($W41:$W$58,$V41:$V$58)),"") -> 1 | U41: =IF(W41<>"",IF($I$12<>"",IF(G41<>"",G41,($I$9/$I$12-SUM($U$25:U40))*V41*W41/SUMPRODUCT($W41:$W$58,$V41:$V$58)),""),"") -> 1 | V41: 1 | W41: 1
A42: 18 | B42: 45990 | C42: сб | D42: 5984 | E42: 2 | F42: =IF(AND(E42<>"",E42<>0),D42/E42,"") -> 2992 | G42: 1 | H42: =IF(AND(G42<>"",G42<>0),D42/G42,"") -> 5984 | I42: 32 | J42: =IF(AND(G42<>"",G42<>0),E42/G42,"") -> 2 | N42: =IF(AND(I42<>"",I42<>0),G42/I42,"") -> 0.03125 | O42: =D42/P42 -> 0.24178956 | P42: =$I$8*V42*W42/SUMPRODUCT($W$25:$W$56,$V$25:$V$56) -> 24748.794 | Q42: =$I$9*V42*W42/SUMPRODUCT($W$25:$W$58,$V$25:$V$58) -> 3.8075067 | R42: =IF($I$12="","",Q42/$I$12) -> 2.2397099 | S42: =IF(W42<>"",IF(D42<>"",D42,($I$8-SUM($S$25:S41))*V42*W42/SUMPRODUCT($W42:$W$58,$V42:$V$58)),"") -> 5984 | T42: =IF(W42<>"",IF(E42<>"",E42,($I$9-SUM($T$25:T41))*V42*W42/SUMPRODUCT($W42:$W$58,$V42:$V$58)),"") -> 2 | U42: =IF(W42<>"",IF($I$12<>"",IF(G42<>"",G42,($I$9/$I$12-SUM($U$25:U41))*V42*W42/SUMPRODUCT($W42:$W$58,$V42:$V$58)),""),"") -> 1 | V42: 1 | W42: 1
A43: 19 | B43: 45991 | C43: вс | F43: =IF(AND(E43<>"",E43<>0),D43/E43,"") | H43: =IF(AND(G43<>"",G43<>0),D43/G43,"") | I43: 15 | J43: =IF(AND(G43<>"",G43<>0),E43/G43,"") | N43: =IF(AND(I43<>"",I43<>0),G43/I43,"") -> 0 | O43: =D43/P43 -> 0 | P43: =$I$8*V43*W43/SUMPRODUCT($W$25:$W$56,$V$25:$V$56) -> 24748.794 | Q43: =$I$9*V43*W43/SUMPRODUCT($W$25:$W$58,$V$25:$V$58) -> 3.8075067 | R43: =IF($I$12="","",Q43/$I$12) -> 2.2397099 | S43: =IF(W43<>"",IF(D43<>"",D43,($I$8-SUM($S$25:S42))*V43*W43/SUMPRODUCT($W43:$W$58,$V43:$V$58)),"") -> 112864.85 | T43: =IF(W43<>"",IF(E43<>"",E43,($I$9-SUM($T$25:T42))*V43*W43/SUMPRODUCT($W43:$W$58,$V43:$V$58)),"") -> 17.271023 | U43: =IF(W43<>"",IF($I$12<>"",IF(G43<>"",G43,($I$9/$I$12-SUM($U$25:U42))*V43*W43/SUMPRODUCT($W43:$W$58,$V43:$V$58)),""),"") -> 6.3939486 | V43: 1 | W43: 1
A44: 20 | F44: =IF(AND(E44<>"",E44<>0),D44/E44,"") | H44: =IF(AND(G44<>"",G44<>0),D44/G44,"") | J44: =IF(AND(G44<>"",G44<>0),E44/G44,"") | N44: =IF(AND(I44<>"",I44<>0),G44/I44,"") | O44: =D44/P44 -> #DIV/0! | P44: =$I$8*V44*W44/SUMPRODUCT($W$25:$W$56,$V$25:$V$56) -> 0 | Q44: =$I$9*V44*W44/SUMPRODUCT($W$25:$W$58,$V$25:$V$58) -> 0 | R44: =IF($I$12="","",Q44/$I$12) -> 0 | S44: =IF(W44<>"",IF(D44<>"",D44,($I$8-SUM($S$25:S43))*V44*W44/SUMPRODUCT($W44:$W$58,$V44:$V$58)),"") | T44: =IF(W44<>"",IF(E44<>"",E44,($I$9-SUM($T$25:T43))*V44*W44/SUMPRODUCT($W44:$W$58,$V44:$V$58)),"") | U44: =IF(W44<>"",IF($I$12<>"",IF(G44<>"",G44,($I$9/$I$12-SUM($U$25:U43))*V44*W44/SUMPRODUCT($W44:$W$58,$V44:$V$58)),""),"")
A45: 21 | B45: 45984 | C45: вс | D45: 11493 | E45: 1 | F45: =IF(AND(E45<>"",E45<>0),D45/E45,"") -> 11493 | G45: 1 | H45: =IF(AND(G45<>"",G45<>0),D45/G45,"") -> 11493 | J45: =IF(AND(G45<>"",G45<>0),E45/G45,"") -> 1 | K45: 11493 | N45: =IF(AND(I45<>"",I45<>0),G45/I45,"") | O45: =D45/P45 -> #DIV/0! | P45: =$I$8*V45*W45/SUMPRODUCT($W$25:$W$56,$V$25:$V$56) -> 0 | Q45: =$I$9*V45*W45/SUMPRODUCT($W$25:$W$58,$V$25:$V$58) -> 0 | R45: =IF($I$12="","",Q45/$I$12) -> 0 | S45: =IF(W45<>"",IF(D45<>"",D45,($I$8-SUM($S$25:S44))*V45*W45/SUMPRODUCT($W45:$W$58,$V45:$V$58)),"") | T45: =IF(W45<>"",IF(E45<>"",E45,($I$9-SUM($T$25:T44))*V45*W45/SUMPRODUCT($W45:$W$58,$V45:$V$58)),"") | U45: =IF(W45<>"",IF($I$12<>"",IF(G45<>"",G45,($I$9/$I$12-SUM($U$25:U44))*V45*W45/SUMPRODUCT($W45:$W$58,$V45:$V$58)),""),"")
A46: 22 | F46: =IF(AND(E46<>"",E46<>0),D46/E46,"") | H46: =IF(AND(G46<>"",G46<>0),D46/G46,"") | J46: =IF(AND(G46<>"",G46<>0),E46/G46,"") | N46: =IF(AND(I46<>"",I46<>0),G46/I46,"") | O46: =D46/P46 -> #DIV/0! | P46: =$I$8*V46*W46/SUMPRODUCT($W$25:$W$56,$V$25:$V$56) -> 0 | Q46: =$I$9*V46*W46/SUMPRODUCT($W$25:$W$58,$V$25:$V$58) -> 0 | R46: =IF($I$12="","",Q46/$I$12) -> 0 | S46: =IF(W46<>"",IF(D46<>"",D46,($I$8-SUM($S$25:S45))*V46*W46/SUMPRODUCT($W46:$W$58,$V46:$V$58)),"") | T46: =IF(W46<>"",IF(E46<>"",E46,($I$9-SUM($T$25:T45))*V46*W46/SUMPRODUCT($W46:$W$58,$V46:$V$58)),"") | U46: =IF(W46<>"",IF($I$12<>"",IF(G46<>"",G46,($I$9/$I$12-SUM($U$25:U45))*V46*W46/SUMPRODUCT($W46:$W$58,$V46:$V$58)),""),"")
A47: 23 | F47: =IF(AND(E47<>"",E47<>0),D47/E47,"") | H47: =IF(AND(G47<>"",G47<>0),D47/G47,"") | J47: =IF(AND(G47<>"",G47<>0),E47/G47,"") | N47: =IF(AND(I47<>"",I47<>0),G47/I47,"") | O47: =D47/P47 -> #DIV/0! | P47: =$I$8*V47*W47/SUMPRODUCT($W$25:$W$56,$V$25:$V$56) -> 0 | Q47: =$I$9*V47*W47/SUMPRODUCT($W$25:$W$58,$V$25:$V$58) -> 0 | R47: =IF($I$12="","",Q47/$I$12) -> 0 | S47: =IF(W47<>"",IF(D47<>"",D47,($I$8-SUM($S$25:S46))*V47*W47/SUMPRODUCT($W47:$W$58,$V47:$V$58)),"") | T47: =IF(W47<>"",IF(E47<>"",E47,($I$9-SUM($T$25:T46))*V47*W47/SUMPRODUCT($W47:$W$58,$V47:$V$58)),"") | U47: =IF(W47<>"",IF($I$12<>"",IF(G47<>"",G47,($I$9/$I$12-SUM($U$25:U46))*V47*W47/SUMPRODUCT($W47:$W$58,$V47:$V$58)),""),"")
A48: 24 | F48: =IF(AND(E48<>"",E48<>0),D48/E48,"") | H48: =IF(AND(G48<>"",G48<>0),D48/G48,"") | J48: =IF(AND(G48<>"",G48<>0),E48/G48,"") | N48: =IF(AND(I48<>"",I48<>0),G48/I48,"") | O48: =D48/P48 -> #DIV/0! | P48: =$I$8*V48*W48/SUMPRODUCT($W$25:$W$56,$V$25:$V$56) -> 0 | Q48: =$I$9*V48*W48/SUMPRODUCT($W$25:$W$58,$V$25:$V$58) -> 0 | R48: =IF($I$12="","",Q48/$I$12) -> 0 | S48: =IF(W48<>"",IF(D48<>"",D48,($I$8-SUM($S$25:S47))*V48*W48/SUMPRODUCT($W48:$W$58,$V48:$V$58)),"") | T48: =IF(W48<>"",IF(E48<>"",E48,($I$9-SUM($T$25:T47))*V48*W48/SUMPRODUCT($W48:$W$58,$V48:$V$58)),"") | U48: =IF(W48<>"",IF($I$12<>"",IF(G48<>"",G48,($I$9/$I$12-SUM($U$25:U47))*V48*W48/SUMPRODUCT($W48:$W$58,$V48:$V$58)),""),"")
A49: 25 | F49: =IF(AND(E49<>"",E49<>0),D49/E49,"") | H49: =IF(AND(G49<>"",G49<>0),D49/G49,"") | J49: =IF(AND(G49<>"",G49<>0),E49/G49,"") | N49: =IF(AND(I49<>"",I49<>0),G49/I49,"") | O49: =D49/P49 -> #DIV/0! | P49: =$I$8*V49*W49/SUMPRODUCT($W$25:$W$56,$V$25:$V$56) -> 0 | Q49: =$I$9*V49*W49/SUMPRODUCT($W$25:$W$58,$V$25:$V$58) -> 0 | R49: =IF($I$12="","",Q49/$I$12) -> 0 | S49: =IF(W49<>"",IF(D49<>"",D49,($I$8-SUM($S$25:S48))*V49*W49/SUMPRODUCT($W49:$W$58,$V49:$V$58)),"") | T49: =IF(W49<>"",IF(E49<>"",E49,($I$9-SUM($T$25:T48))*V49*W49/SUMPRODUCT($W49:$W$58,$V49:$V$58)),"") | U49: =IF(W49<>"",IF($I$12<>"",IF(G49<>"",G49,($I$9/$I$12-SUM($U$25:U48))*V49*W49/SUMPRODUCT($W49:$W$58,$V49:$V$58)),""),"")
A50: 26 | F50: =IF(AND(E50<>"",E50<>0),D50/E50,"") | H50: =IF(AND(G50<>"",G50<>0),D50/G50,"") | J50: =IF(AND(G50<>"",G50<>0),E50/G50,"") | N50: =IF(AND(I50<>"",I50<>0),G50/I50,"") | O50: =D50/P50 -> #DIV/0! | P50: =$I$8*V50*W50/SUMPRODUCT($W$25:$W$56,$V$25:$V$56) -> 0 | Q50: =$I$9*V50*W50/SUMPRODUCT($W$25:$W$58,$V$25:$V$58) -> 0 | R50: =IF($I$12="","",Q50/$I$12) -> 0 | S50: =IF(W50<>"",IF(D50<>"",D50,($I$8-SUM($S$25:S49))*V50*W50/SUMPRODUCT($W50:$W$58,$V50:$V$58)),"") | T50: =IF(W50<>"",IF(E50<>"",E50,($I$9-SUM($T$25:T49))*V50*W50/SUMPRODUCT($W50:$W$58,$V50:$V$58)),"") | U50: =IF(W50<>"",IF($I$12<>"",IF(G50<>"",G50,($I$9/$I$12-SUM($U$25:U49))*V50*W50/SUMPRODUCT($W50:$W$58,$V50:$V$58)),""),"")
A51: 27 | F51: =IF(AND(E51<>"",E51<>0),D51/E51,"") | H51: =IF(AND(G51<>"",G51<>0),D51/G51,"") | J51: =IF(AND(G51<>"",G51<>0),E51/G51,"") | N51: =IF(AND(I51<>"",I51<>0),G51/I51,"") | O51: =D51/P51 -> #DIV/0! | P51: =$I$8*V51*W51/SUMPRODUCT($W$25:$W$56,$V$25:$V$56) -> 0 | Q51: =$I$9*V51*W51/SUMPRODUCT($W$25:$W$58,$V$25:$V$58) -> 0 | R51: =IF($I$12="","",Q51/$I$12) -> 0 | S51: =IF(W51<>"",IF(D51<>"",D51,($I$8-SUM($S$25:S50))*V51*W51/SUMPRODUCT($W51:$W$58,$V51:$V$58)),"") | T51: =IF(W51<>"",IF(E51<>"",E51,($I$9-SUM($T$25:T50))*V51*W51/SUMPRODUCT($W51:$W$58,$V51:$V$58)),"") | U51: =IF(W51<>"",IF($I$12<>"",IF(G51<>"",G51,($I$9/$I$12-SUM($U$25:U50))*V51*W51/SUMPRODUCT($W51:$W$58,$V51:$V$58)),""),"")
A52: 28 | F52: =IF(AND(E52<>"",E52<>0),D52/E52,"") | H52: =IF(AND(G52<>"",G52<>0),D52/G52,"") | J52: =IF(AND(G52<>"",G52<>0),E52/G52,"") | N52: =IF(AND(I52<>"",I52<>0),G52/I52,"") | O52: =D52/P52 -> #DIV/0! | P52: =$I$8*V52*W52/SUMPRODUCT($W$25:$W$56,$V$25:$V$56) -> 0 | Q52: =$I$9*V52*W52/SUMPRODUCT($W$25:$W$58,$V$25:$V$58) -> 0 | R52: =IF($I$12="","",Q52/$I$12) -> 0 | S52: =IF(W52<>"",IF(D52<>"",D52,($I$8-SUM($S$25:S51))*V52*W52/SUMPRODUCT($W52:$W$58,$V52:$V$58)),"") | T52: =IF(W52<>"",IF(E52<>"",E52,($I$9-SUM($T$25:T51))*V52*W52/SUMPRODUCT($W52:$W$58,$V52:$V$58)),"") | U52: =IF(W52<>"",IF($I$12<>"",IF(G52<>"",G52,($I$9/$I$12-SUM($U$25:U51))*V52*W52/SUMPRODUCT($W52:$W$58,$V52:$V$58)),""),"")
A53: 29 | F53: =IF(AND(E53<>"",E53<>0),D53/E53,"") | H53: =IF(AND(G53<>"",G53<>0),D53/G53,"") | J53: =IF(AND(G53<>"",G53<>0),E53/G53,"") | N53: =IF(AND(I53<>"",I53<>0),G53/I53,"") | O53: =D53/P53 -> #DIV/0! | P53: =$I$8*V53*W53/SUMPRODUCT($W$25:$W$56,$V$25:$V$56) -> 0 | Q53: =$I$9*V53*W53/SUMPRODUCT($W$25:$W$58,$V$25:$V$58) -> 0 | R53: =IF($I$12="","",Q53/$I$12) -> 0 | S53: =IF(W53<>"",IF(D53<>"",D53,($I$8-SUM($S$25:S52))*V53*W53/SUMPRODUCT($W53:$W$58,$V53:$V$58)),"") | T53: =IF(W53<>"",IF(E53<>"",E53,($I$9-SUM($T$25:T52))*V53*W53/SUMPRODUCT($W53:$W$58,$V53:$V$58)),"") | U53: =IF(W53<>"",IF($I$12<>"",IF(G53<>"",G53,($I$9/$I$12-SUM($U$25:U52))*V53*W53/SUMPRODUCT($W53:$W$58,$V53:$V$58)),""),"")
F54: =IF(AND(E54<>"",E54<>0),D54/E54,"") | H54: =IF(AND(G54<>"",G54<>0),D54/G54,"") | J54: =IF(AND(G54<>"",G54<>0),E54/G54,"") | N54: =IF(AND(I54<>"",I54<>0),G54/I54,"") | O54: =D54/P54 -> #DIV/0! | P54: =$I$8*V54*W54/SUMPRODUCT($W$25:$W$56,$V$25:$V$56) -> 0 | Q54: =$I$9*V54*W54/SUMPRODUCT($W$25:$W$58,$V$25:$V$58) -> 0 | R54: =IF($I$12="","",Q54/$I$12) -> 0 | S54: =IF(W54<>"",IF(D54<>"",D54,($I$8-SUM($S$25:S50))*V54*W54/SUMPRODUCT($W54:$W$58,$V54:$V$58)),"") | T54: =IF(W54<>"",IF(E54<>"",E54,($I$9-SUM($T$25:T50))*V54*W54/SUMPRODUCT($W54:$W$58,$V54:$V$58)),"") | U54: =IF(W54<>"",IF($I$12<>"",IF(G54<>"",G54,($I$9/$I$12-SUM($U$25:U50))*V54*W54/SUMPRODUCT($W54:$W$58,$V54:$V$58)),""),"")
F55: =IF(AND(E55<>"",E55<>0),D55/E55,"") | H55: =IF(AND(G55<>"",G55<>0),D55/G55,"") | J55: =IF(AND(G55<>"",G55<>0),E55/G55,"") | N55: =IF(AND(I55<>"",I55<>0),G55/I55,"") | O55: =D55/P55 -> #DIV/0! | P55: =$I$8*V55*W55/SUMPRODUCT($W$25:$W$56,$V$25:$V$56) -> 0 | Q55: =$I$9*V55*W55/SUMPRODUCT($W$25:$W$58,$V$25:$V$58) -> 0 | R55: =IF($I$12="","",Q55/$I$12) -> 0 | S55: =IF(W55<>"",IF(D55<>"",D55,($I$8-SUM($S$25:S54))*V55*W55/SUMPRODUCT($W55:$W$58,$V55:$V$58)),"") | T55: =IF(W55<>"",IF(E55<>"",E55,($I$9-SUM($T$25:T54))*V55*W55/SUMPRODUCT($W55:$W$58,$V55:$V$58)),"") | U55: =IF(W55<>"",IF($I$12<>"",IF(G55<>"",G55,($I$9/$I$12-SUM($U$25:U54))*V55*W55/SUMPRODUCT($W55:$W$58,$V55:$V$58)),""),"")
F56: =IF(AND(E56<>"",E56<>0),D56/E56,"") | H56: =IF(AND(G56<>"",G56<>0),D56/G56,"") | J56: =IF(AND(G56<>"",G56<>0),E56/G56,"") | N56: =IF(AND(I56<>"",I56<>0),G56/I56,"") | O56: =D56/P56 -> #DIV/0! | P56: =$I$8*V56*W56/SUMPRODUCT($W$25:$W$56,$V$25:$V$56) -> 0 | Q56: =$I$9*V56*W56/SUMPRODUCT($W$25:$W$58,$V$25:$V$58) -> 0 | R56: =IF($I$12="","",Q56/$I$12) -> 0 | S56: =IF(W56<>"",IF(D56<>"",D56,($I$8-SUM($S$25:S55))*V56*W56/SUMPRODUCT($W56:$W$58,$V56:$V$58)),"") | T56: =IF(W56<>"",IF(E56<>"",E56,($I$9-SUM($T$25:T55))*V56*W56/SUMPRODUCT($W56:$W$58,$V56:$V$58)),"") | U56: =IF(W56<>"",IF($I$12<>"",IF(G56<>"",G56,($I$9/$I$12-SUM($U$25:U55))*V56*W56/SUMPRODUCT($W56:$W$58,$V56:$V$58)),""),"")
D57: =SUM(D25:D56) -> 194103 | E57: =SUM(E25:E56) -> 31 | F57: =IF(AND(E57<>"",E57<>0),D57/E57,"") -> 6261.3871 | G57: =SUM(G25:G56) -> 23 | H57: =IF(AND(G57<>"",G57<>0),D57/G57,"") -> 8439.2609 | I57: =SUM(I25:I56) -> 318 | J57: =IF(AND(G57<>"",G57<>0),E57/G57,"") -> 1.3478261 | K57: =SUM(K25:K56) -> 29977 | L57: =SUM(L25:L56) -> 34346 | M57: =SUM(M25:M56) -> 0 | N57: =IF(AND(I57<>"",I57<>0),G57/I57,"") -> 0.072327044 | O57: =D57/P57 -> 0.41278567 | P57: =SUM(P25:P56) -> 470227.08 | Q57: =SUM(Q25:Q55) -> 72.342628 | R57: =SUM(R25:R55) -> 42.554487 | S57: =SUM(S25:S56) -> 470227.08 | T57: =SUM(T25:T55) -> 72.342628 | U57: =SUM(U25:U55) -> 42.554487

Sheet Доп сотрудник
B1: =TODAY()-1 -> 46000
B2: (отчетная дата) | J2: ЕЖЕДНЕВНЫЙ ОТЧЕТ О ПРОДАЖАХ
B3: Осталось до выполнения плана!!! | J3: Доп сотрудник
C4: =I8-D50 -> 470227.08 | E4: =IF(I8<>0,C4/I8,0) -> 1
F6: Целевые показатели
F7: Показатель | I7: План | J7: Факт | K7: % выполнения | L7: Прогноз выполнения | M7: % выполнения по прогнозу | N7: Отклонение | O7: Факт аналогичного месяца прошлого года | P7: Отклонение LFL
F8: Выручка | I8: ='Ялта, Ленина, 18'!I8/График!AJ31*График!AJ28 -> 470227.08 | J8: =D57 -> 19779 | K8: =IF(AND(I8<>"",I8<>0,J8<>""),J8/I8,"") -> 0.042062656 | L8: =IF(SUMIF($D$25:$D$56,">=0",$P$25:$P$56)<>0,I8*D57/SUMIF($D$25:$D$56,">=0",$P$25:$P$56),0) -> 164825 | M8: =IF(AND(I8<>"",I8<>0,L8<>"",L8<>0),L8/I8,"") -> 0.35052213 | N8: =IF(AND(J8<>0,J8<>"",I8<>0,I8<>""),L8-I8,"") -> -305402.08 | P8: =IF(AND(O8<>"",O8<>0,L8<>"",L8<>0),-O8+L8,"") | Q8: =IF(AND(P8<>"",P8<>0,O8<>0,O8<>""),P8/O8,"")
F9: Кол-во изделий | I9: =I8/I11 -> 72.342628 | J9: =E57 -> 3 | K9: =IF(AND(I9<>"",I9<>0,J9<>""),J9/I9,"") -> 0.041469326 | L9: =IF(SUMIF($E$25:$E$54,">=0",$Q$25:$Q$54)<>0,I9*E57/SUMIF($E$25:$E$54,">=0",$Q$25:$Q$54),0) -> 25 | M9: =IF(AND(I9<>"",I9<>0,L9<>"",L9<>0),L9/I9,"") -> 0.34557771 | N9: =IF(AND(J9<>0,J9<>"",I9<>0,I9<>""),L9-I9,"") -> -47.342628 | O9: =O8/O11 -> #DIV/0! | P9: =IF(AND(O9<>"",O9<>0,L9<>"",L9<>0),-O9+L9,"") -> #DIV/0! | Q9: =IF(AND(P9<>"",P9<>0,O9<>0,O9<>""),P9/O9,"") -> #DIV/0!
F10: Средний чек | I10: =I11*I12 -> 11050 | J10: =H57 -> 6593 | K10: =IF(AND(I10<>"",I10<>0,J10<>""),J10/I10,"") -> 0.59665158 | L10: =J10 -> 6593 | M10: =IF(AND(I10<>"",I10<>0,L10<>"",L10<>0),L10/I10,"") -> 0.59665158 | N10: =IF(AND(J10<>0,J10<>"",I10<>0,I10<>""),L10-I10,"") -> -4457 | O10: =O11*O12 -> 0 | P10: =IF(AND(O10<>"",O10<>0,L10<>"",L10<>0),-O10+L10,"") | Q10: =IF(AND(P10<>"",P10<>0,O10<>0,O10<>""),P10/O10,"") | S10: IS | V10: =M23 -> Agafi
F11: Средняя стоимость изделия | I11: ='Ялта, Ленина, 18'!I11 -> 6500 | J11: =F57 -> 6593 | K11: =IF(AND(I11<>"",I11<>0,J11<>""),J11/I11,"") -> 1.0143077 | L11: =IF(L9>0,L8/L9,"") -> 6593 | M11: =IF(AND(I11<>"",I11<>0,L11<>"",L11<>0),L11/I11,"") -> 1.0143077 | N11: =IF(AND(J11<>0,J11<>"",I11<>0,I11<>""),L11-I11,"") -> 93 | P11: =IF(AND(O11<>"",O11<>0,L11<>"",L11<>0),-O11+L11,"") | Q11: =IF(AND(P11<>"",P11<>0,O11<>0,O11<>""),P11/O11,"")
F12: Длина чека | I12: ='Ялта, Ленина, 18'!I12 -> 1.7 | J12: =J57 -> 1 | K12: =IF(AND(I12<>"",I12<>0,J12<>""),J12/I12,"") -> 0.58823529 | L12: =J12 -> 1 | M12: =IF(AND(I12<>"",I12<>0,L12<>"",L12<>0),L12/I12,"") -> 0.58823529 | N12: =IF(AND(J12<>0,J12<>"",I12<>0,I12<>""),L12-I12,"") -> -0.7 | P12: =IF(AND(O12<>"",O12<>0,L12<>"",L12<>0),-O12+L12,"") | Q12: =IF(AND(P12<>"",P12<>0,O12<>0,O12<>""),P12/O12,"") | S12: ='Ялта, Ленина, 18'!S12*График!AJ28/График!AJ31 -> 116057.69 | T12: =L57 -> 0 | U12: =S12-T12 -> 116057.69 | V12: ='Ялта, Ленина, 18'!V12/График!AJ31*График!AJ28 -> 109230.77 | W12: =M57 -> 0 | X12: =V12-W12 -> 109230.77
F13: Кол-во чеков | I13: =IF(I12<>0,I9/I12,"") -> 42.554487 | J13: =G57 -> 3 | K13: =IF(AND(I13<>"",I13<>0,J13<>""),J13/I13,"") -> 0.070497853 | L13: =IF(SUMIF($G$25:$G$54,">=0",$R$25:$R$54)<>0,I13*G57/SUMIF($G$25:$G$54,">=0",$R$25:$R$54),"") -> 25 | M13: =IF(AND(I13<>"",I13<>0,L13<>"",L13<>0),L13/I13,"") -> 0.58748211 | N13: =IF(AND(J13<>0,J13<>"",I13<>0,I13<>""),L13-I13,"") -> -17.554487 | P13: =IF(AND(O13<>"",O13<>0,L13<>"",L13<>0),-O13+L13,"") | Q13: =IF(AND(P13<>"",P13<>0,O13<>0,O13<>""),P13/O13,"") | S13: =T12/S12 -> 0 | T13: =S13/J14*I14 -> 0 | V13: =W12/V12 -> 0 | W13: =V13/J14*I14 -> 0
F14: Кол-во смен план/отработано | I14: =График!AI28 -> 13 | J14: 2 | K14: =IF(AND(I14<>"",I14<>0,J14<>""),J14/I14,"") -> 0.15384615 | L14: =I14 -> 13 | M14: =IF(AND(I14<>"",I14<>0,L14<>"",L14<>0),L14/I14,"") -> 1 | N14: =IF(AND(J14<>0,J14<>"",I14<>0,I14<>""),L14-I14,"") -> 0 | P14: =IF(AND(O14<>"",O14<>0,L14<>"",L14<>0),-O14+L14,"") | Q14: =IF(AND(P14<>"",P14<>0,O14<>0,O14<>""),P14/O14,"")
F15: Средние продажи в смену | I15: ='Ялта, Ленина, 18'!I15 -> 68878.333 | J15: =J8/J14 -> 9889.5 | K15: =IF(AND(I15<>"",I15<>0,J15<>""),J15/I15,"") -> 0.14357926 | L15: =J15 -> 9889.5 | M15: =IF(AND(I15<>"",I15<>0,L15<>"",L15<>0),L15/I15,"") -> 0.14357926 | N15: =IF(AND(J15<>0,J15<>"",I15<>0,I15<>""),L15-I15,"") -> -58988.833 | P15: =IF(AND(O15<>"",O15<>0,L15<>"",L15<>0),-O15+L15,"") | Q15: =IF(AND(P15<>"",P15<>0,O15<>0,O15<>""),P15/O15,"")
F16: Отставание/Перевыполнение | J16: =J8-I15*J14 -> -117977.67 | K16: =IF(AND(I16<>"",I16<>0,J16<>""),J16/I16,"") | L16: =J16 -> -117977.67 | M16: =IF(AND(I16<>"",I16<>0,L16<>"",L16<>0),L16/I16,"") | N16: =IF(AND(J16<>0,J16<>"",I16<>0,I16<>""),L16-I16,"") | P16: =IF(AND(O16<>"",O16<>0,L16<>"",L16<>0),-O16+L16,"") | Q16: =IF(AND(P16<>"",P16<>0,O16<>0,O16<>""),P16/O16,"") | S16: UNOde50
F17: Трафик | I17: ='Ялта, Ленина, 18'!I17/График!AJ31*График!AJ28 -> 386.85897 | J17: =I57 -> 33 | K17: =IF(AND(I17<>"",I17<>0,J17<>""),J17/I17,"") -> 0.085302403 | L17: =J17/J14*I14 -> 214.5 | M17: =IF(AND(I17<>"",I17<>0,L17<>"",L17<>0),L17/I17,"") -> 0.55446562 | N17: =IF(AND(J17<>0,J17<>"",I17<>0,I17<>""),L17-I17,"") -> -172.35897 | P17: =IF(AND(O17<>"",O17<>0,L17<>"",L17<>0),-O17+L17,"") | Q17: =IF(AND(P17<>"",P17<>0,O17<>0,O17<>""),P17/O17,"")
K18: =IF(AND(I18<>"",I18<>0,J18<>""),J18/I18,"") | L18: =J18 -> 0 | M18: =IF(AND(I18<>"",I18<>0,L18<>"",L18<>0),L18/I18,"") | N18: =IF(AND(J18<>0,J18<>"",I18<>0,I18<>""),L18-I18,"") | O18: 0 | P18: =IF(AND(O18<>"",O18<>0,L18<>"",L18<>0),-O18+L18,"") | Q18: =IF(AND(P18<>"",P18<>0,O18<>0,O18<>""),P18/O18,"") | S18: ='Ялта, Ленина, 18'!S18*График!AJ28/График!AJ31 -> 232115.38 | T18: =K57 -> 0
K19: =IF(AND(I19<>"",I19<>0,J19<>""),J19/I19,"") | L19: =J19 -> 0 | M19: =IF(AND(I19<>"",I19<>0,L19<>"",L19<>0),L19/I19,"") | N19: =IF(AND(J19<>0,J19<>"",I19<>0,I19<>""),L19-I19,"") | O19: 0 | P19: =IF(AND(O19<>"",O19<>0,L19<>"",L19<>0),-O19+L19,"") | Q19: =IF(AND(P19<>"",P19<>0,O19<>0,O19<>""),P19/O19,"") | S19: =T18/S18 -> 0 | T19: =S19/J14*I14 -> 0
F20: Конверсия план/факт | I20: ='Ялта, Ленина, 18'!I20 -> 0.11 | J20: =N57 -> 0.090909091 | K20: =J20/I20 -> 0.82644628 | L20: =IF(AND(K8<>0,I14<>0,I57<>0),(I57*N57+(I57/K8-I57)*I20)/(I57/K8),0) -> 0.10919699 | M20: =IF(AND(I20<>"",I20<>0,L20<>"",L20<>0),L20/I20,"") -> 0.99269987 | N20: =IF(AND(J20<>0,J20<>"",I20<>0,I20<>""),L20-I20,"") -> -0.00080301434 | P20: =IF(AND(O20<>"",O20<>0,L20<>"",L20<>0),-O20+L20,"") | Q20: =IF(AND(P20<>"",P20<>0,O20<>0,O20<>""),P20/O20,"")
B22: Факт продаж за месяц | O22: % выполнения дневного плана | P22: Раcпределение плана по дням
B23: Дата | C23: День недели | D23: Выручка (руб) | E23: Кол-во единиц (шт.) | F23: Средняя стоимость изделия (руб.) | G23: Количество чеков (шт.) | H23: Средняя сумма чека (руб.) | I23: Трафик | J23: Длина чека (шт.) | K23: UNOde50 | L23: IS | M23: Agafi | N23: Конверсия (%) | P23: выручка, план | Q23: кол-во ед, план | R23: Кол-во чеков, план | S23: выручка, скорректир.план | T23: кол-во ед, скорр. план | U23: кол-во чеков, скорр. план | V23: Коэфф. Дня Недели | W23: Специфика месяца
B24: 1 | C24: 2 | D24: 3 | E24: в | F24: 5 | G24: 6 | H24: 7 | I24: 8 | J24: 9 | K24: 10 | L24: 11 | M24: 12 | N24: 13 | P24: 1 | Q24: 2 | R24: 3 | S24: 4 | T24: 5 | U24: 6 | V24: 10 | W24: 11
A25: 1 | B25: 08.11.2025НАСТЯ | C25: сб | D25: 4692 | E25: 1 | F25: =IF(AND(E25<>"",E25<>0),D25/E25,"") -> 4692 | G25: 1 | H25: =IF(AND(G25<>"",G25<>0),D25/G25,"") -> 4692 | I25: 20 | J25: =IF(AND(G25<>"",G25<>0),E25/G25,"") -> 1 | N25: =IF(AND(I25<>"",I25<>0),G25/I25,"") -> 0.05 | O25: =D25/P25 -> 0.24945394 | P25: =$I$8*V25*W25/SUMPRODUCT($W$25:$W$56,$V$25:$V$56) -> 18809.083 | Q25: =$I$9*V25*W25/SUMPRODUCT($W$25:$W$56,$V$25:$V$56) -> 2.8937051 | R25: =IF($I$12="","",Q25/$I$12) -> 1.7021795 | S25: =IF(D25<>"",D25,P25) -> 4692 | T25: =IF(E25<>"",E25,Q25) -> 1 | U25: =IF(G25<>"",G25,R25) -> 1 | V25: 1 | W25: 1
A26: 2 | B26: 19.11.2025Лера | C26: ср | D26: 10793 | E26: 1 | F26: =IF(AND(E26<>"",E26<>0),D26/E26,"") -> 10793 | G26: 1 | H26: =IF(AND(G26<>"",G26<>0),D26/G26,"") -> 10793 | I26: 5 | J26: =IF(AND(G26<>"",G26<>0),E26/G26,"") -> 1 | N26: =IF(AND(I26<>"",I26<>0),G26/I26,"") -> 0.2 | O26: =D26/P26 -> 0.5738185 | P26: =$I$8*V26*W26/SUMPRODUCT($W$25:$W$56,$V$25:$V$56) -> 18809.083 | Q26: =$I$9*V26*W26/SUMPRODUCT($W$25:$W$58,$V$25:$V$58) -> 2.8937051 | R26: =IF($I$12="","",Q26/$I$12) -> 1.7021795 | S26: =IF(W26<>"",IF(D26<>"",D26,($I$8-SUM($S$25:S25))*V26*W26/SUMPRODUCT($W26:$W$56,$V26:$V$56)),"") -> 10793 | T26: =IF(W26<>"",IF(E26<>"",E26,($I$9-SUM($T$25:T25))*V26*W26/SUMPRODUCT($W26:$W$55,$V26:$V$55)),"") -> 1 | U26: =IF(W26<>"",IF($I$12<>"",IF(G26<>"",G26,($I$9/$I$12-SUM($U$25:U25))*V26*W26/SUMPRODUCT($W26:$W$55,$V26:$V$55)),""),"") -> 1 | V26: 1 | W26: 1
A27: 3 | B27: 21.11.2025 Настя | C27: пт | D27: 4294 | E27: 1 | F27: =IF(AND(E27<>"",E27<>0),D27/E27,"") -> 4294 | G27: 1 | H27: =IF(AND(G27<>"",G27<>0),D27/G27,"") -> 4294 | I27: 8 | J27: =IF(AND(G27<>"",G27<>0),E27/G27,"") -> 1 | N27: =IF(AND(I27<>"",I27<>0),G27/I27,"") -> 0.125 | O27: =D27/P27 -> 0.22829395 | P27: =$I$8*V27*W27/SUMPRODUCT($W$25:$W$56,$V$25:$V$56) -> 18809.083 | Q27: =$I$9*V27*W27/SUMPRODUCT($W$25:$W$58,$V$25:$V$58) -> 2.8937051 | R27: =IF($I$12="","",Q27/$I$12) -> 1.7021795 | S27: =IF(W27<>"",IF(D27<>"",D27,($I$8-SUM($S$25:S26))*V27*W27/SUMPRODUCT($W27:$W$58,$V27:$V$58)),"") -> 4294 | T27: =IF(W27<>"",IF(E27<>"",E27,($I$9-SUM($T$25:T26))*V27*W27/SUMPRODUCT($W27:$W$55,$V27:$V$55)),"") -> 1 | U27: =IF(W27<>"",IF($I$12<>"",IF(G27<>"",G27,($I$9/$I$12-SUM($U$25:U26))*V27*W27/SUMPRODUCT($W27:$W$55,$V27:$V$55)),""),"") -> 1 | V27: 1 | W27: 1
A28: 4 | F28: =IF(AND(E28<>"",E28<>0),D28/E28,"") | H28: =IF(AND(G28<>"",G28<>0),D28/G28,"") | J28: =IF(AND(G28<>"",G28<>0),E28/G28,"") | N28: =IF(AND(I28<>"",I28<>0),G28/I28,"") | O28: =D28/P28 -> 0 | P28: =$I$8*V28*W28/SUMPRODUCT($W$25:$W$56,$V$25:$V$56) -> 18809.083 | Q28: =$I$9*V28*W28/SUMPRODUCT($W$25:$W$58,$V$25:$V$58) -> 2.8937051 | R28: =IF($I$12="","",Q28/$I$12) -> 1.7021795 | S28: =IF(W28<>"",IF(D28<>"",D28,($I$8-SUM($S$25:S27))*V28*W28/SUMPRODUCT($W28:$W$58,$V28:$V$58)),"") -> 20474.913 | T28: =IF(W28<>"",IF(E28<>"",E28,($I$9-SUM($T$25:T27))*V28*W28/SUMPRODUCT($W28:$W$58,$V28:$V$58)),"") -> 3.1519376 | U28: =IF(W28<>"",IF($I$12<>"",IF(G28<>"",G28,($I$9/$I$12-SUM($U$25:U27))*V28*W28/SUMPRODUCT($W28:$W$58,$V28:$V$58)),""),"") -> 1.7979312 | V28: 1 | W28: 1
A29: 5 | F29: =IF(AND(E29<>"",E29<>0),D29/E29,"") | H29: =IF(AND(G29<>"",G29<>0),D29/G29,"") | J29: =IF(AND(G29<>"",G29<>0),E29/G29,"") | N29: =IF(AND(I29<>"",I29<>0),G29/I29,"") | O29: =D29/P29 -> 0 | P29: =$I$8*V29*W29/SUMPRODUCT($W$25:$W$56,$V$25:$V$56) -> 18809.083 | Q29: =$I$9*V29*W29/SUMPRODUCT($W$25:$W$58,$V$25:$V$58) -> 2.8937051 | R29: =IF($I$12="","",Q29/$I$12) -> 1.7021795 | S29: =IF(W29<>"",IF(D29<>"",D29,($I$8-SUM($S$25:S28))*V29*W29/SUMPRODUCT($W29:$W$58,$V29:$V$58)),"") -> 20474.913 | T29: =IF(W29<>"",IF(E29<>"",E29,($I$9-SUM($T$25:T28))*V29*W29/SUMPRODUCT($W29:$W$58,$V29:$V$58)),"") -> 3.1519376 | U29: =IF(W29<>"",IF($I$12<>"",IF(G29<>"",G29,($I$9/$I$12-SUM($U$25:U28))*V29*W29/SUMPRODUCT($W29:$W$58,$V29:$V$58)),""),"") -> 1.7979312 | V29: 1 | W29: 1
A30: 6 | F30: =IF(AND(E30<>"",E30<>0),D30/E30,"") | H30: =IF(AND(G30<>"",G30<>0),D30/G30,"") | J30: =IF(AND(G30<>"",G30<>0),E30/G30,"") | N30: =IF(AND(I30<>"",I30<>0),G30/I30,"") | O30: =D30/P30 -> 0 | P30: =$I$8*V30*W30/SUMPRODUCT($W$25:$W$56,$V$25:$V$56) -> 18809.083 | Q30: =$I$9*V30*W30/SUMPRODUCT($W$25:$W$58,$V$25:$V$58) -> 2.8937051 | R30: =IF($I$12="","",Q30/$I$12) -> 1.7021795 | S30: =IF(W30<>"",IF(D30<>"",D30,($I$8-SUM($S$25:S29))*V30*W30/SUMPRODUCT($W30:$W$58,$V30:$V$58)),"") -> 20474.913 | T30: =IF(W30<>"",IF(E30<>"",E30,($I$9-SUM($T$25:T29))*V30*W30/SUMPRODUCT($W30:$W$58,$V30:$V$58)),"") -> 3.1519376 | U30: =IF(W30<>"",IF($I$12<>"",IF(G30<>"",G30,($I$9/$I$12-SUM($U$25:U29))*V30*W30/SUMPRODUCT($W30:$W$58,$V30:$V$58)),""),"") -> 1.7979312 | V30: 1 | W30: 1
A31: 7 | F31: =IF(AND(E31<>"",E31<>0),D31/E31,"") | H31: =IF(AND(G31<>"",G31<>0),D31/G31,"") | J31: =IF(AND(G31<>"",G31<>0),E31/G31,"") | N31: =IF(AND(I31<>"",I31<>0),G31/I31,"") | O31: =D31/P31 -> 0 | P31: =$I$8*V31*W31/SUMPRODUCT($W$25:$W$56,$V$25:$V$56) -> 18809.083 | Q31: =$I$9*V31*W31/SUMPRODUCT($W$25:$W$58,$V$25:$V$58) -> 2.8937051 | R31: =IF($I$12="","",Q31/$I$12) -> 1.7021795 | S31: =IF(W31<>"",IF(D31<>"",D31,($I$8-SUM($S$25:S30))*V31*W31/SUMPRODUCT($W31:$W$58,$V31:$V$58)),"") -> 20474.913 | T31: =IF(W31<>"",IF(E31<>"",E31,($I$9-SUM($T$25:T30))*V31*W31/SUMPRODUCT($W31:$W$58,$V31:$V$58)),"") -> 3.1519376 | U31: =IF(W31<>"",IF($I$12<>"",IF(G31<>"",G31,($I$9/$I$12-SUM($U$25:U30))*V31*W31/SUMPRODUCT($W31:$W$58,$V31:$V$58)),""),"") -> 1.7979312 | V31: 1 | W31: 1
A32: 8 | F32: =IF(AND(E32<>"",E32<>0),D32/E32,"") | H32: =IF(AND(G32<>"",G32<>0),D32/G32,"") | J32: =IF(AND(G32<>"",G32<>0),E32/G32,"") | N32: =IF(AND(I32<>"",I32<>0),G32/I32,"") | O32: =D32/P32 -> 0 | P32: =$I$8*V32*W32/SUMPRODUCT($W$25:$W$56,$V$25:$V$56) -> 18809.083 | Q32: =$I$9*V32*W32/SUMPRODUCT($W$25:$W$58,$V$25:$V$58) -> 2.8937051 | R32: =IF($I$12="","",Q32/$I$12) -> 1.7021795 | S32: =IF(W32<>"",IF(D32<>"",D32,($I$8-SUM($S$25:S31))*V32*W32/SUMPRODUCT($W32:$W$58,$V32:$V$58)),"") -> 20474.913 | T32: =IF(W32<>"",IF(E32<>"",E32,($I$9-SUM($T$25:T31))*V32*W32/SUMPRODUCT($W32:$W$58,$V32:$V$58)),"") -> 3.1519376 | U32: =IF(W32<>"",IF($I$12<>"",IF(G32<>"",G32,($I$9/$I$12-SUM($U$25:U31))*V32*W32/SUMPRODUCT($W32:$W$58,$V32:$V$58)),""),"") -> 1.7979312 | V32: 1 | W32: 1
A33: 9 | F33: =IF(AND(E33<>"",E33<>0),D33/E33,"") | H33: =IF(AND(G33<>"",G33<>0),D33/G33,"") | J33: =IF(AND(G33<>"",G33<>0),E33/G33,"") | N33: =IF(AND(I33<>"",I33<>0),G33/I33,"") | O33: =D33/P33 -> 0 | P33: =$I$8*V33*W33/SUMPRODUCT($W$25:$W$56,$V$25:$V$56) -> 18809.083 | Q33: =$I$9*V33*W33/SUMPRODUCT($W$25:$W$58,$V$25:$V$58) -> 2.8937051 | R33: =IF($I$12="","",Q33/$I$12) -> 1.7021795 | S33: =IF(W33<>"",IF(D33<>"",D33,($I$8-SUM($S$25:S32))*V33*W33/SUMPRODUCT($W33:$W$58,$V33:$V$58)),"") -> 20474.913 | T33: =IF(W33<>"",IF(E33<>"",E33,($I$9-SUM($T$25:T32))*V33*W33/SUMPRODUCT($W33:$W$58,$V33:$V$58)),"") -> 3.1519376 | U33: =IF(W33<>"",IF($I$12<>"",IF(G33<>"",G33,($I$9/$I$12-SUM($U$25:U32))*V33*W33/SUMPRODUCT($W33:$W$58,$V33:$V$58)),""),"") -> 1.7979312 | V33: 1 | W33: 1
A34: 10 | F34: =IF(AND(E34<>"",E34<>0),D34/E34,"") | H34: =IF(AND(G34<>"",G34<>0),D34/G34,"") | J34: =IF(AND(G34<>"",G34<>0),E34/G34,"") | N34: =IF(AND(I34<>"",I34<>0),G34/I34,"") | O34: =D34/P34 -> 0 | P34: =$I$8*V34*W34/SUMPRODUCT($W$25:$W$56,$V$25:$V$56) -> 18809.083 | Q34: =$I$9*V34*W34/SUMPRODUCT($W$25:$W$58,$V$25:$V$58) -> 2.8937051 | R34: =IF($I$12="","",Q34/$I$12) -> 1.7021795 | S34: =IF(W34<>"",IF(D34<>"",D34,($I$8-SUM($S$25:S33))*V34*W34/SUMPRODUCT($W34:$W$58,$V34:$V$58)),"") -> 20474.913 | T34: =IF(W34<>"",IF(E34<>"",E34,($I$9-SUM($T$25:T33))*V34*W34/SUMPRODUCT($W34:$W$58,$V34:$V$58)),"") -> 3.1519376 | U34: =IF(W34<>"",IF($I$12<>"",IF(G34<>"",G34,($I$9/$I$12-SUM($U$25:U33))*V34*W34/SUMPRODUCT($W34:$W$58,$V34:$V$58)),""),"") -> 1.7979312 | V34: 1 | W34: 1
A35: 11 | F35: =IF(AND(E35<>"",E35<>0),D35/E35,"") | H35: =IF(AND(G35<>"",G35<>0),D35/G35,"") | J35: =IF(AND(G35<>"",G35<>0),E35/G35,"") | N35: =IF(AND(I35<>"",I35<>0),G35/I35,"") | O35: =D35/P35 -> 0 | P35: =$I$8*V35*W35/SUMPRODUCT($W$25:$W$56,$V$25:$V$56) -> 18809.083 | Q35: =$I$9*V35*W35/SUMPRODUCT($W$25:$W$58,$V$25:$V$58) -> 2.8937051 | R35: =IF($I$12="","",Q35/$I$12) -> 1.7021795 | S35: =IF(W35<>"",IF(D35<>"",D35,($I$8-SUM($S$25:S34))*V35*W35/SUMPRODUCT($W35:$W$58,$V35:$V$58)),"") -> 20474.913 | T35: =IF(W35<>"",IF(E34<>"",E34,($I$9-SUM($T$25:T34))*V35*W35/SUMPRODUCT($W35:$W$58,$V35:$V$58)),"") -> 3.1519376 | U35: =IF(W35<>"",IF($I$12<>"",IF(G35<>"",G35,($I$9/$I$12-SUM($U$25:U34))*V35*W35/SUMPRODUCT($W35:$W$58,$V35:$V$58)),""),"") -> 1.7979312 | V35: 1 | W35: 1
A36: 11 | F36: =IF(AND(E36<>"",E36<>0),D36/E36,"") | H36: =IF(AND(G36<>"",G36<>0),D36/G36,"") | J36: =IF(AND(G36<>"",G36<>0),E36/G36,"") | N36: =IF(AND(I36<>"",I36<>0),G36/I36,"") | O36: =D36/P36 -> 0 | P36: =$I$8*V36*W36/SUMPRODUCT($W$25:$W$56,$V$25:$V$56) -> 18809.083 | Q36: =$I$9*V36*W36/SUMPRODUCT($W$25:$W$58,$V$25:$V$58) -> 2.8937051 | R36: =IF($I$12="","",Q36/$I$12) -> 1.7021795 | S36: =IF(W36<>"",IF(D36<>"",D36,($I$8-SUM($S$25:S35))*V36*W36/SUMPRODUCT($W36:$W$58,$V36:$V$58)),"") -> 20474.913 | T36: =IF(W36<>"",IF(E35<>"",E35,($I$9-SUM($T$25:T35))*V36*W36/SUMPRODUCT($W36:$W$58,$V36:$V$58)),"") -> 3.1519376 | U36: =IF(W36<>"",IF($I$12<>"",IF(G36<>"",G36,($I$9/$I$12-SUM($U$25:U35))*V36*W36/SUMPRODUCT($W36:$W$58,$V36:$V$58)),""),"") -> 1.7979312 | V36: 1 | W36: 1
A37: 13 | F37: =IF(AND(E37<>"",E37<>0),D37/E37,"") | H37: =IF(AND(G37<>"",G37<>0),D37/G37,"") | J37: =IF(AND(G37<>"",G37<>0),E37/G37,"") | N37: =IF(AND(I37<>"",I37<>0),G37/I37,"") | O37: =D37/P37 -> 0 | P37: =$I$8*V37*W37/SUMPRODUCT($W$25:$W$56,$V$25:$V$56) -> 18809.083 | Q37: =$I$9*V37*W37/SUMPRODUCT($W$25:$W$58,$V$25:$V$58) -> 2.8937051 | R37: =IF($I$12="","",Q37/$I$12) -> 1.7021795 | S37: =IF(W37<>"",IF(D37<>"",D37,($I$8-SUM($S$25:S36))*V37*W37/SUMPRODUCT($W37:$W$58,$V37:$V$58)),"") -> 20474.913 | T37: =IF(W37<>"",IF(E37<>"",E37,($I$9-SUM($T$25:T36))*V37*W37/SUMPRODUCT($W37:$W$58,$V37:$V$58)),"") -> 3.1519376 | U37: =IF(W37<>"",IF($I$12<>"",IF(G37<>"",G37,($I$9/$I$12-SUM($U$25:U36))*V37*W37/SUMPRODUCT($W37:$W$58,$V37:$V$58)),""),"") -> 1.7979312 | V37: 1 | W37: 1
A38: 14 | F38: =IF(AND(E38<>"",E38<>0),D38/E38,"") | H38: =IF(AND(G38<>"",G38<>0),D38/G38,"") | J38: =IF(AND(G38<>"",G38<>0),E38/G38,"") | N38: =IF(AND(I38<>"",I38<>0),G38/I38,"") | O38: =D38/P38 -> 0 | P38: =$I$8*V38*W38/SUMPRODUCT($W$25:$W$56,$V$25:$V$56) -> 18809.083 | Q38: =$I$9*V38*W38/SUMPRODUCT($W$25:$W$58,$V$25:$V$58) -> 2.8937051 | R38: =IF($I$12="","",Q38/$I$12) -> 1.7021795 | S38: =IF(W38<>"",IF(D38<>"",D38,($I$8-SUM($S$25:S37))*V38*W38/SUMPRODUCT($W38:$W$58,$V38:$V$58)),"") -> 20474.913 | T38: =IF(W38<>"",IF(E38<>"",E38,($I$9-SUM($T$25:T37))*V38*W38/SUMPRODUCT($W38:$W$58,$V38:$V$58)),"") -> 3.1519376 | U38: =IF(W38<>"",IF($I$12<>"",IF(G38<>"",G38,($I$9/$I$12-SUM($U$25:U37))*V38*W38/SUMPRODUCT($W38:$W$58,$V38:$V$58)),""),"") -> 1.7979312 | V38: 1 | W38: 1
A39: 15 | F39: =IF(AND(E39<>"",E39<>0),D39/E39,"") | H39: =IF(AND(G39<>"",G39<>0),D39/G39,"") | J39: =IF(AND(G39<>"",G39<>0),E39/G39,"") | N39: =IF(AND(I39<>"",I39<>0),G39/I39,"") | O39: =D39/P39 -> 0 | P39: =$I$8*V39*W39/SUMPRODUCT($W$25:$W$56,$V$25:$V$56) -> 18809.083 | Q39: =$I$9*V39*W39/SUMPRODUCT($W$25:$W$58,$V$25:$V$58) -> 2.8937051 | R39: =IF($I$12="","",Q39/$I$12) -> 1.7021795 | S39: =IF(W39<>"",IF(D39<>"",D39,($I$8-SUM($S$25:S38))*V39*W39/SUMPRODUCT($W39:$W$58,$V39:$V$58)),"") -> 20474.913 | T39: =IF(W39<>"",IF(E39<>"",E39,($I$9-SUM($T$25:T38))*V39*W39/SUMPRODUCT($W39:$W$58,$V39:$V$58)),"") -> 3.1519376 | U39: =IF(W39<>"",IF($I$12<>"",IF(G39<>"",G39,($I$9/$I$12-SUM($U$25:U38))*V39*W39/SUMPRODUCT($W39:$W$58,$V39:$V$58)),""),"") -> 1.7979312 | V39: 1 | W39: 1
A40: 16 | F40: =IF(AND(E40<>"",E40<>0),D40/E40,"") | H40: =IF(AND(G40<>"",G40<>0),D40/G40,"") | J40: =IF(AND(G40<>"",G40<>0),E40/G40,"") | N40: =IF(AND(I40<>"",I40<>0),G40/I40,"") | O40: =D40/P40 -> 0 | P40: =$I$8*V40*W40/SUMPRODUCT($W$25:$W$56,$V$25:$V$56) -> 18809.083 | Q40: =$I$9*V40*W40/SUMPRODUCT($W$25:$W$58,$V$25:$V$58) -> 2.8937051 | R40: =IF($I$12="","",Q40/$I$12) -> 1.7021795 | S40: =IF(W40<>"",IF(D40<>"",D40,($I$8-SUM($S$25:S39))*V40*W40/SUMPRODUCT($W40:$W$58,$V40:$V$58)),"") -> 20474.913 | T40: =IF(W40<>"",IF(E40<>"",E40,($I$9-SUM($T$25:T39))*V40*W40/SUMPRODUCT($W40:$W$58,$V40:$V$58)),"") -> 3.1519376 | U40: =IF(W40<>"",IF($I$12<>"",IF(G40<>"",G40,($I$9/$I$12-SUM($U$25:U39))*V40*W40/SUMPRODUCT($W40:$W$58,$V40:$V$58)),""),"") -> 1.7979312 | V40: 1 | W40: 1
A41: 17 | F41: =IF(AND(E41<>"",E41<>0),D41/E41,"") | H41: =IF(AND(G41<>"",G41<>0),D41/G41,"") | J41: =IF(AND(G41<>"",G41<>0),E41/G41,"") | N41: =IF(AND(I41<>"",I41<>0),G41/I41,"") | O41: =D41/P41 -> 0 | P41: =$I$8*V41*W41/SUMPRODUCT($W$25:$W$56,$V$25:$V$56) -> 18809.083 | Q41: =$I$9*V41*W41/SUMPRODUCT($W$25:$W$58,$V$25:$V$58) -> 2.8937051 | R41: =IF($I$12="","",Q41/$I$12) -> 1.7021795 | S41: =IF(W41<>"",IF(D41<>"",D41,($I$8-SUM($S$25:S40))*V41*W41/SUMPRODUCT($W41:$W$58,$V41:$V$58)),"") -> 20474.913 | T41: =IF(W41<>"",IF(E41<>"",E41,($I$9-SUM($T$25:T40))*V41*W41/SUMPRODUCT($W41:$W$58,$V41:$V$58)),"") -> 3.1519376 | U41: =IF(W41<>"",IF($I$12<>"",IF(G41<>"",G41,($I$9/$I$12-SUM($U$25:U40))*V41*W41/SUMPRODUCT($W41:$W$58,$V41:$V$58)),""),"") -> 1.7979312 | V41: 1 | W41: 1
A42: 18 | F42: =IF(AND(E42<>"",E42<>0),D42/E42,"") | H42: =IF(AND(G42<>"",G42<>0),D42/G42,"") | J42: =IF(AND(G42<>"",G42<>0),E42/G42,"") | N42: =IF(AND(I42<>"",I42<>0),G42/I42,"") | O42: =D42/P42 -> 0 | P42: =$I$8*V42*W42/SUMPRODUCT($W$25:$W$56,$V$25:$V$56) -> 18809.083 | Q42: =$I$9*V42*W42/SUMPRODUCT($W$25:$W$58,$V$25:$V$58) -> 2.8937051 | R42: =IF($I$12="","",Q42/$I$12) -> 1.7021795 | S42: =IF(W42<>"",IF(D42<>"",D42,($I$8-SUM($S$25:S41))*V42*W42/SUMPRODUCT($W42:$W$58,$V42:$V$58)),"") -> 20474.913 | T42: =IF(W42<>"",IF(E42<>"",E42,($I$9-SUM($T$25:T41))*V42*W42/SUMPRODUCT($W42:$W$58,$V42:$V$58)),"") -> 3.1519376 | U42: =IF(W42<>"",IF($I$12<>"",IF(G42<>"",G42,($I$9/$I$12-SUM($U$25:U41))*V42*W42/SUMPRODUCT($W42:$W$58,$V42:$V$58)),""),"") -> 1.7979312 | V42: 1 | W42: 1
A43: 19 | F43: =IF(AND(E43<>"",E43<>0),D43/E43,"") | H43: =IF(AND(G43<>"",G43<>0),D43/G43,"") | J43: =IF(AND(G43<>"",G43<>0),E43/G43,"") | N43: =IF(AND(I43<>"",I43<>0),G43/I43,"") | O43: =D43/P43 -> 0 | P43: =$I$8*V43*W43/SUMPRODUCT($W$25:$W$56,$V$25:$V$56) -> 18809.083 | Q43: =$I$9*V43*W43/SUMPRODUCT($W$25:$W$58,$V$25:$V$58) -> 2.8937051 | R43: =IF($I$12="","",Q43/$I$12) -> 1.7021795 | S43: =IF(W43<>"",IF(D43<>"",D43,($I$8-SUM($S$25:S42))*V43*W43/SUMPRODUCT($W43:$W$58,$V43:$V$58)),"") -> 20474.913 | T43: =IF(W43<>"",IF(E43<>"",E43,($I$9-SUM($T$25:T42))*V43*W43/SUMPRODUCT($W43:$W$58,$V43:$V$58)),"") -> 3.1519376 | U43: =IF(W43<>"",IF($I$12<>"",IF(G43<>"",G43,($I$9/$I$12-SUM($U$25:U42))*V43*W43/SUMPRODUCT($W43:$W$58,$V43:$V$58)),""),"") -> 1.7979312 | V43: 1 | W43: 1
A44: 20 | F44: =IF(AND(E44<>"",E44<>0),D44/E44,"") | H44: =IF(AND(G44<>"",G44<>0),D44/G44,"") | J44: =IF(AND(G44<>"",G44<>0),E44/G44,"") | N44: =IF(AND(I44<>"",I44<>0),G44/I44,"") | O44: =D44/P44 -> 0 | P44: =$I$8*V44*W44/SUMPRODUCT($W$25:$W$56,$V$25:$V$56) -> 18809.083 | Q44: =$I$9*V44*W44/SUMPRODUCT($W$25:$W$58,$V$25:$V$58) -> 2.8937051 | R44: =IF($I$12="","",Q44/$I$12) -> 1.7021795 | S44: =IF(W44<>"",IF(D44<>"",D44,($I$8-SUM($S$25:S43))*V44*W44/SUMPRODUCT($W44:$W$58,$V44:$V$58)),"") -> 20474.913 | T44: =IF(W44<>"",IF(E44<>"",E44,($I$9-SUM($T$25:T43))*V44*W44/SUMPRODUCT($W44:$W$58,$V44:$V$58)),"") -> 3.1519376 | U44: =IF(W44<>"",IF($I$12<>"",IF(G44<>"",G44,($I$9/$I$12-SUM($U$25:U43))*V44*W44/SUMPRODUCT($W44:$W$58,$V44:$V$58)),""),"") -> 1.7979312 | V44: 1 | W44: 1
A45: 21 | F45: =IF(AND(E45<>"",E45<>0),D45/E45,"") | H45: =IF(AND(G45<>"",G45<>0),D45/G45,"") | J45: =IF(AND(G45<>"",G45<>0),E45/G45,"") | N45: =IF(AND(I45<>"",I45<>0),G45/I45,"") | O45: =D45/P45 -> 0 | P45: =$I$8*V45*W45/SUMPRODUCT($W$25:$W$56,$V$25:$V$56) -> 18809.083 | Q45: =$I$9*V45*W45/SUMPRODUCT($W$25:$W$58,$V$25:$V$58) -> 2.8937051 | R45: =IF($I$12="","",Q45/$I$12) -> 1.7021795 | S45: =IF(W45<>"",IF(D45<>"",D45,($I$8-SUM($S$25:S44))*V45*W45/SUMPRODUCT($W45:$W$58,$V45:$V$58)),"") -> 20474.913 | T45: =IF(W45<>"",IF(E45<>"",E45,($I$9-SUM($T$25:T44))*V45*W45/SUMPRODUCT($W45:$W$58,$V45:$V$58)),"") -> 3.1519376 | U45: =IF(W45<>"",IF($I$12<>"",IF(G45<>"",G45,($I$9/$I$12-SUM($U$25:U44))*V45*W45/SUMPRODUCT($W45:$W$58,$V45:$V$58)),""),"") -> 1.7979312 | V45: 1 | W45: 1
A46: 22 | F46: =IF(AND(E46<>"",E46<>0),D46/E46,"") | H46: =IF(AND(G46<>"",G46<>0),D46/G46,"") | J46: =IF(AND(G46<>"",G46<>0),E46/G46,"") | N46: =IF(AND(I46<>"",I46<>0),G46/I46,"") | O46: =D46/P46 -> 0 | P46: =$I$8*V46*W46/SUMPRODUCT($W$25:$W$56,$V$25:$V$56) -> 18809.083 | Q46: =$I$9*V46*W46/SUMPRODUCT($W$25:$W$58,$V$25:$V$58) -> 2.8937051 | R46: =IF($I$12="","",Q46/$I$12) -> 1.7021795 | S46: =IF(W46<>"",IF(D46<>"",D46,($I$8-SUM($S$25:S45))*V46*W46/SUMPRODUCT($W46:$W$58,$V46:$V$58)),"") -> 20474.913 | T46: =IF(W46<>"",IF(E46<>"",E46,($I$9-SUM($T$25:T45))*V46*W46/SUMPRODUCT($W46:$W$58,$V46:$V$58)),"") -> 3.1519376 | U46: =IF(W46<>"",IF($I$12<>"",IF(G46<>"",G46,($I$9/$I$12-SUM($U$25:U45))*V46*W46/SUMPRODUCT($W46:$W$58,$V46:$V$58)),""),"") -> 1.7979312 | V46: 1 | W46: 1
A47: 23 | F47: =IF(AND(E47<>"",E47<>0),D47/E47,"") | H47: =IF(AND(G47<>"",G47<>0),D47/G47,"") | J47: =IF(AND(G47<>"",G47<>0),E47/G47,"") | N47: =IF(AND(I47<>"",I47<>0),G47/I47,"") | O47: =D47/P47 -> 0 | P47: =$I$8*V47*W47/SUMPRODUCT($W$25:$W$56,$V$25:$V$56) -> 18809.083 | Q47: =$I$9*V47*W47/SUMPRODUCT($W$25:$W$58,$V$25:$V$58) -> 2.8937051 | R47: =IF($I$12="","",Q47/$I$12) -> 1.7021795 | S47: =IF(W47<>"",IF(D47<>"",D47,($I$8-SUM($S$25:S46))*V47*W47/SUMPRODUCT($W47:$W$58,$V47:$V$58)),"") -> 20474.913 | T47: =IF(W47<>"",IF(E47<>"",E47,($I$9-SUM($T$25:T46))*V47*W47/SUMPRODUCT($W47:$W$58,$V47:$V$58)),"") -> 3.1519376 | U47: =IF(W47<>"",IF($I$12<>"",IF(G47<>"",G47,($I$9/$I$12-SUM($U$25:U46))*V47*W47/SUMPRODUCT($W47:$W$58,$V47:$V$58)),""),"") -> 1.7979312 | V47: 1 | W47: 1
A48: 24 | F48: =IF(AND(E48<>"",E48<>0),D48/E48,"") | H48: =IF(AND(G48<>"",G48<>0),D48/G48,"") | J48: =IF(AND(G48<>"",G48<>0),E48/G48,"") | N48: =IF(AND(I48<>"",I48<>0),G48/I48,"") | O48: =D48/P48 -> 0 | P48: =$I$8*V48*W48/SUMPRODUCT($W$25:$W$56,$V$25:$V$56) -> 18809.083 | Q48: =$I$9*V48*W48/SUMPRODUCT($W$25:$W$58,$V$25:$V$58) -> 2.8937051 | R48: =IF($I$12="","",Q48/$I$12) -> 1.7021795 | S48: =IF(W48<>"",IF(D48<>"",D48,($I$8-SUM($S$25:S47))*V48*W48/SUMPRODUCT($W48:$W$58,$V48:$V$58)),"") -> 20474.913 | T48: =IF(W48<>"",IF(E48<>"",E48,($I$9-SUM($T$25:T47))*V48*W48/SUMPRODUCT($W48:$W$58,$V48:$V$58)),"") -> 3.1519376 | U48: =IF(W48<>"",IF($I$12<>"",IF(G48<>"",G48,($I$9/$I$12-SUM($U$25:U47))*V48*W48/SUMPRODUCT($W48:$W$58,$V48:$V$58)),""),"") -> 1.7979312 | V48: 1 | W48: 1
A49: 25 | F49: =IF(AND(E49<>"",E49<>0),D49/E49,"") | H49: =IF(AND(G49<>"",G49<>0),D49/G49,"") | J49: =IF(AND(G49<>"",G49<>0),E49/G49,"") | N49: =IF(AND(I49<>"",I49<>0),G49/I49,"") | O49: =D49/P49 -> 0 | P49: =$I$8*V49*W49/SUMPRODUCT($W$25:$W$56,$V$25:$V$56) -> 18809.083 | Q49: =$I$9*V49*W49/SUMPRODUCT($W$25:$W$58,$V$25:$V$58) -> 2.8937051 | R49: =IF($I$12="","",Q49/$I$12) -> 1.7021795 | S49: =IF(W49<>"",IF(D49<>"",D49,($I$8-SUM($S$25:S48))*V49*W49/SUMPRODUCT($W49:$W$58,$V49:$V$58)),"") -> 20474.913 | T49: =IF(W49<>"",IF(E49<>"",E49,($I$9-SUM($T$25:T48))*V49*W49/SUMPRODUCT($W49:$W$58,$V49:$V$58)),"") -> 3.1519376 | U49: =IF(W49<>"",IF($I$12<>"",IF(G49<>"",G49,($I$9/$I$12-SUM($U$25:U48))*V49*W49/SUMPRODUCT($W49:$W$58,$V49:$V$58)),""),"") -> 1.7979312 | V49: 1 | W49: 1
A50: 26 | F50: =IF(AND(E50<>"",E50<>0),D50/E50,"") | H50: =IF(AND(G50<>"",G50<>0),D50/G50,"") | J50: =IF(AND(G50<>"",G50<>0),E50/G50,"") | N50: =IF(AND(I50<>"",I50<>0),G50/I50,"") | O50: =D50/P50 -> #DIV/0! | P50: =$I$8*V50*W50/SUMPRODUCT($W$25:$W$56,$V$25:$V$56) -> 0 | Q50: =$I$9*V50*W50/SUMPRODUCT($W$25:$W$58,$V$25:$V$58) -> 0 | R50: =IF($I$12="","",Q50/$I$12) -> 0 | S50: =IF(W50<>"",IF(D50<>"",D50,($I$8-SUM($S$25:S49))*V50*W50/SUMPRODUCT($W50:$W$58,$V50:$V$58)),"") | T50: =IF(W50<>"",IF(E50<>"",E50,($I$9-SUM($T$25:T49))*V50*W50/SUMPRODUCT($W50:$W$58,$V50:$V$58)),"") | U50: =IF(W50<>"",IF($I$12<>"",IF(G50<>"",G50,($I$9/$I$12-SUM($U$25:U49))*V50*W50/SUMPRODUCT($W50:$W$58,$V50:$V$58)),""),"")
A51: 27 | F51: =IF(AND(E51<>"",E51<>0),D51/E51,"") | H51: =IF(AND(G51<>"",G51<>0),D51/G51,"") | J51: =IF(AND(G51<>"",G51<>0),E51/G51,"") | N51: =IF(AND(I51<>"",I51<>0),G51/I51,"") | O51: =D51/P51 -> #DIV/0! | P51: =$I$8*V51*W51/SUMPRODUCT($W$25:$W$56,$V$25:$V$56) -> 0 | Q51: =$I$9*V51*W51/SUMPRODUCT($W$25:$W$58,$V$25:$V$58) -> 0 | R51: =IF($I$12="","",Q51/$I$12) -> 0 | S51: =IF(W51<>"",IF(D51<>"",D51,($I$8-SUM($S$25:S50))*V51*W51/SUMPRODUCT($W51:$W$58,$V51:$V$58)),"") | T51: =IF(W51<>"",IF(E51<>"",E51,($I$9-SUM($T$25:T50))*V51*W51/SUMPRODUCT($W51:$W$58,$V51:$V$58)),"") | U51: =IF(W51<>"",IF($I$12<>"",IF(G51<>"",G51,($I$9/$I$12-SUM($U$25:U50))*V51*W51/SUMPRODUCT($W51:$W$58,$V51:$V$58)),""),"")
A52: 28 | F52: =IF(AND(E52<>"",E52<>0),D52/E52,"") | H52: =IF(AND(G52<>"",G52<>0),D52/G52,"") | J52: =IF(AND(G52<>"",G52<>0),E52/G52,"") | N52: =IF(AND(I52<>"",I52<>0),G52/I52,"") | O52: =D52/P52 -> #DIV/0! | P52: =$I$8*V52*W52/SUMPRODUCT($W$25:$W$56,$V$25:$V$56) -> 0 | Q52: =$I$9*V52*W52/SUMPRODUCT($W$25:$W$58,$V$25:$V$58) -> 0 | R52: =IF($I$12="","",Q52/$I$12) -> 0 | S52: =IF(W52<>"",IF(D52<>"",D52,($I$8-SUM($S$25:S51))*V52*W52/SUMPRODUCT($W52:$W$58,$V52:$V$58)),"") | T52: =IF(W52<>"",IF(E52<>"",E52,($I$9-SUM($T$25:T51))*V52*W52/SUMPRODUCT($W52:$W$58,$V52:$V$58)),"") | U52: =IF(W52<>"",IF($I$12<>"",IF(G52<>"",G52,($I$9/$I$12-SUM($U$25:U51))*V52*W52/SUMPRODUCT($W52:$W$58,$V52:$V$58)),""),"")
A53: 29 | F53: =IF(AND(E53<>"",E53<>0),D53/E53,"") | H53: =IF(AND(G53<>"",G53<>0),D53/G53,"") | J53: =IF(AND(G53<>"",G53<>0),E53/G53,"") | N53: =IF(AND(I53<>"",I53<>0),G53/I53,"") | O53: =D53/P53 -> #DIV/0! | P53: =$I$8*V53*W53/SUMPRODUCT($W$25:$W$56,$V$25:$V$56) -> 0 | Q53: =$I$9*V53*W53/SUMPRODUCT($W$25:$W$58,$V$25:$V$58) -> 0 | R53: =IF($I$12="","",Q53/$I$12) -> 0 | S53: =IF(W53<>"",IF(D53<>"",D53,($I$8-SUM($S$25:S52))*V53*W53/SUMPRODUCT($W53:$W$58,$V53:$V$58)),"") | T53: =IF(W53<>"",IF(E53<>"",E53,($I$9-SUM($T$25:T52))*V53*W53/SUMPRODUCT($W53:$W$58,$V53:$V$58)),"") | U53: =IF(W53<>"",IF($I$12<>"",IF(G53<>"",G53,($I$9/$I$12-SUM($U$25:U52))*V53*W53/SUMPRODUCT($W53:$W$58,$V53:$V$58)),""),"")
F54: =IF(AND(E54<>"",E54<>0),D54/E54,"") | H54: =IF(AND(G54<>"",G54<>0),D54/G54,"") | J54: =IF(AND(G54<>"",G54<>0),E54/G54,"") | N54: =IF(AND(I54<>"",I54<>0),G54/I54,"") | O54: =D54/P54 -> #DIV/0! | P54: =$I$8*V54*W54/SUMPRODUCT($W$25:$W$56,$V$25:$V$56) -> 0 | Q54: =$I$9*V54*W54/SUMPRODUCT($W$25:$W$58,$V$25:$V$58) -> 0 | R54: =IF($I$12="","",Q54/$I$12) -> 0 | S54: =IF(W54<>"",IF(D54<>"",D54,($I$8-SUM($S$25:S50))*V54*W54/SUMPRODUCT($W54:$W$58,$V54:$V$58)),"") | T54: =IF(W54<>"",IF(E54<>"",E54,($I$9-SUM($T$25:T50))*V54*W54/SUMPRODUCT($W54:$W$58,$V54:$V$58)),"") | U54: =IF(W54<>"",IF($I$12<>"",IF(G54<>"",G54,($I$9/$I$12-SUM($U$25:U50))*V54*W54/SUMPRODUCT($W54:$W$58,$V54:$V$58)),""),"")
F55: =IF(AND(E55<>"",E55<>0),D55/E55,"") | H55: =IF(AND(G55<>"",G55<>0),D55/G55,"") | J55: =IF(AND(G55<>"",G55<>0),E55/G55,"") | N55: =IF(AND(I55<>"",I55<>0),G55/I55,"") | O55: =D55/P55 -> #DIV/0! | P55: =$I$8*V55*W55/SUMPRODUCT($W$25:$W$56,$V$25:$V$56) -> 0 | Q55: =$I$9*V55*W55/SUMPRODUCT($W$25:$W$58,$V$25:$V$58) -> 0 | R55: =IF($I$12="","",Q55/$I$12) -> 0 | S55: =IF(W55<>"",IF(D55<>"",D55,($I$8-SUM($S$25:S54))*V55*W55/SUMPRODUCT($W55:$W$58,$V55:$V$58)),"") | T55: =IF(W55<>"",IF(E55<>"",E55,($I$9-SUM($T$25:T54))*V55*W55/SUMPRODUCT($W55:$W$58,$V55:$V$58)),"") | U55: =IF(W55<>"",IF($I$12<>"",IF(G55<>"",G55,($I$9/$I$12-SUM($U$25:U54))*V55*W55/SUMPRODUCT($W55:$W$58,$V55:$V$58)),""),"")
F56: =IF(AND(E56<>"",E56<>0),D56/E56,"") | H56: =IF(AND(G56<>"",G56<>0),D56/G56,"") | J56: =IF(AND(G56<>"",G56<>0),E56/G56,"") | N56: =IF(AND(I56<>"",I56<>0),G56/I56,"") | O56: =D56/P56 -> #DIV/0! | P56: =$I$8*V56*W56/SUMPRODUCT($W$25:$W$56,$V$25:$V$56) -> 0 | Q56: =$I$9*V56*W56/SUMPRODUCT($W$25:$W$58,$V$25:$V$58) -> 0 | R56: =IF($I$12="","",Q56/$I$12) -> 0 | S56: =IF(W56<>"",IF(D56<>"",D56,($I$8-SUM($S$25:S55))*V56*W56/SUMPRODUCT($W56:$W$58,$V56:$V$58)),"") | T56: =IF(W56<>"",IF(E56<>"",E56,($I$9-SUM($T$25:T55))*V56*W56/SUMPRODUCT($W56:$W$58,$V56:$V$58)),"") | U56: =IF(W56<>"",IF($I$12<>"",IF(G56<>"",G56,($I$9/$I$12-SUM($U$25:U55))*V56*W56/SUMPRODUCT($W56:$W$58,$V56:$V$58)),""),"")
D57: =SUM(D25:D56) -> 19779 | E57: =SUM(E25:E56) -> 3 | F57: =IF(AND(E57<>"",E57<>0),D57/E57,"") -> 6593 | G57: =SUM(G25:G56) -> 3 | H57: =IF(AND(G57<>"",G57<>0),D57/G57,"") -> 6593 | I57: =SUM(I25:I56) -> 33 | J57: =IF(AND(G57<>"",G57<>0),E57/G57,"") -> 1 | K57: =SUM(K25:K56) -> 0 | L57: =SUM(L25:L56) -> 0 | M57: =SUM(M25:M56) -> 0 | N57: =IF(AND(I57<>"",I57<>0),G57/I57,"") -> 0.090909091 | O57: =D57/P57 -> 0.042062656 | P57: =SUM(P25:P56) -> 470227.08 | Q57: =SUM(Q25:Q55) -> 72.342628 | R57: =SUM(R25:R55) -> 42.554487 | S57: =SUM(S25:S56) -> 470227.08 | T57: =SUM(T25:T55) -> 72.342628 | U57: =SUM(U25:U55) -> 42.554487
C59: Корж | D59: =D25+D27 -> 8986
C60: Козлова | D60: =D26 -> 10793

Sheet Вед-ть Рогалевич
A1: =График!B1 -> Ноябрь, 2025
A2: =График!B3 -> ул. Набережная Ленина, 18 | D2: =График!B4 -> GL-0005
A3: Сотрудник | D3: Выплачено на карту | E3: Выплачено наличными по платежной ведомости | F3: Дополнительные начисления, доплаты | G3: Оклад | H3: Бонусная часть от личных продаж | I3: Бонусная часть от общих продаж | J3: Базовый бонус за выполнение плана | K3: Итого: | L3: Вычеты | M3: Итого к выдаче с учетом авансов и вычетов | N3: Подпись
A4: =График!B29 -> Рогалевич Ирина | D4: =44000-C8 -> 38280 | F4: =H8+H9+G16+G24+L24 -> 11196.46 | G4: =D11 -> 25300 | H4: =D18 -> 25676.6 | I4: =L18 -> 9079.1807 | J4: =L11 -> 0 | K4: =H4+J4+G4+F4+I4 -> 71252.241 | L4: =C8+C9 -> 5720 | M4: =K4-L4-D4-E4 -> 27252.241
B6: Вычеты | G6: Доп начисления
B7: Дата | C7: Сумма | D7: Описание | G7: Дата | H7: Сумма | J7: Описание
B8: 45991 | C8: 5720 | D8: НДФЛ ноябрь 2025 | G8: 45991 | H8: ='Ялта, Ленина, 18'!J8*0.01 -> 11196.46 | J8: Административный %
A11: Оклад: | D11: =G15 -> 25300 | I11: Базовый бонус за выполнение плана | L11: =L15+L16 -> 0
B13: Оклад: | J13: Базовый бонус за выполнение плана
B14: Дней | C14: Магазин | D14: Должность | E14: Зачислено часов | F14: Ставка за час, руб | G14: Начислено за день, руб | J14: Магазин | K14: КВП | L14: Начисленный ББ
B15: =График!AI29 -> 25 | C15: =A2 -> ул. Набережная Ленина, 18 | D15: ПК | E15: =График!AJ29 -> 253 | F15: 100 | G15: =E15*F15 -> 25300 | J15: =График!B3 -> ул. Набережная Ленина, 18 | K15: ='Ялта, Ленина, 18'!K8 -> 0.54184722
D16: ПК | G16: =E16*F16 -> 0
A18: БонуснаяЧасть | D18: =G23 -> 25676.6 | I18: Бонусная часть от общих продаж | L18: =N23 -> 9079.1807
B21: Бонус от личных продаж по категории товара | I21: Бонус от общих продаж
B22: Сотрудник | C22: Магазин | E22: Процент от продажи | F22: Продано на сумму, руб | G22: Начисленный бонус от продаж, руб | I22: Сотрудник | J22: Магазин | K22: Кол-во отработанных личных часов | L22: Кол-во отработанных общих часов | M22: Процент от продажи | N22: Начисленный бонус от продаж, руб
B23: =A4 -> Рогалевич Ирина | C23: =A2 -> ул. Набережная Ленина, 18 | E23: 0.04 | F23: ='Рогалевич И. Е. '!J8 -> 641915 | G23: =F23*E23 -> 25676.6 | I23: =B23 -> Рогалевич Ирина | J23: =C23 -> ул. Набережная Ленина, 18 | K23: =E15 -> 253 | L23: =График!AJ31 -> 624 | M23: 0.02 | N23: ='Ялта, Ленина, 18'!J8*M23*K23/L23 -> 9079.1807
B24: =B23 -> Рогалевич Ирина | C24: =C16 -> 0 | G24: =F24*E24 -> 0 | N24: =1477363.14*M24*K24/L24 -> #DIV/0!

Sheet Вед-ть Арапова
A1: =График!B1 -> Ноябрь, 2025
A2: =График!B3 -> ул. Набережная Ленина, 18 | D2: =График!B4 -> GL-0005
A3: Сотрудник | D3: Выплачено на карту | E3: Выплачено наличными по платежной ведомости | F3: Дополнительные начисления, доплаты | G3: Оклад | H3: Бонусная часть от личных продаж | I3: Бонусная часть от общих продаж | J3: Базовый бонус за выполнение плана | K3: Итого: | L3: Вычеты | M3: Итого к выдаче с учетом авансов и вычетов | N3: Подпись
A4: =График!B27 -> Арапова Анна-Мария | D4: =40000-C8 -> 34800 | F4: =H8+H9 -> 0 | G4: =D12 -> 19300 | H4: =D19 -> 7764.12 | I4: =L19 -> 6926.0153 | J4: =L12 -> 0 | K4: =H4+J4+G4+F4+I4 -> 33990.135 | L4: =C8+C9+C10 -> 5200 | M4: =K4-L4-D4-E4 -> -6009.8647
B6: Вычеты | G6: Доп начисления
B7: Дата | C7: Сумма | D7: Описание | G7: Дата | H7: Сумма | J7: Описание
B8: 45991 | C8: 5200 | D8: НДФЛ ноябрь 2025
A12: Оклад: | D12: =G16 -> 19300 | I12: Базовый бонус за выполнение плана | L12: =L16+L17 -> 0
B14: Оклад: | J14: Базовый бонус за выполнение плана
B15: Дней | C15: Магазин | D15: Должность | E15: Зачислено часов | F15: Ставка за час, руб | G15: Начислено за день, руб | J15: Магазин | K15: КВП | L15: Начисленный ББ
B16: =График!AI27 -> 19 | C16: =A2 -> ул. Набережная Ленина, 18 | D16: ПК | E16: =График!AJ27 -> 193 | F16: 100 | G16: =E16*F16 -> 19300 | J16: =График!B3 -> ул. Набережная Ленина, 18 | K16: ='Ялта, Ленина, 18'!K8 -> 0.54184722 | L16: 0
A19: БонуснаяЧасть | D19: =G24 -> 7764.12 | I19: Бонусная часть от общих продаж | L19: =N24 -> 6926.0153
B22: Бонус от личных продаж по категории товара | I22: Бонус от общих продаж
B23: Сотрудник | C23: Магазин | E23: Процент от продажи | F23: Продано на сумму, руб | G23: Начисленный бонус от продаж, руб | I23: Сотрудник | J23: Магазин | K23: Кол-во отработанных личных часов | L23: Кол-во отработанных общих часов | M23: Процент от продажи | N23: Начисленный бонус от продаж, руб
B24: =A4 -> Арапова Анна-Мария | C24: =A2 -> ул. Набережная Ленина, 18 | E24: 0.04 | F24: ='Арапова А. В.'!D57 -> 194103 | G24: =F24*E24 -> 7764.12 | I24: =B24 -> Арапова Анна-Мария | J24: =C24 -> ул. Набережная Ленина, 18 | K24: =E16 -> 193 | L24: =График!AJ31 -> 624 | M24: 0.02 | N24: ='Ялта, Ленина, 18'!D56*M24*K24/L24 -> 6926.0153
B25: =B24 -> Арапова Анна-Мария

Sheet Вед-ть Уразгильдеева
A1: =График!B1 -> Ноябрь, 2025
A2: =График!B3 -> ул. Набережная Ленина, 18 | D2: =График!B4 -> GL-0005
A3: Сотрудник | D3: Выплачено на карту | E3: Выплачено наличными по платежной ведомости | F3: Дополнительные начисления, доплаты | G3: Оклад | H3: Бонусная часть от личных продаж | I3: Бонусная часть от общих продаж | J3: Базовый бонус за выполнение плана | K3: Итого: | L3: Вычеты | M3: Итого к выдаче с учетом авансов и вычетов | N3: Подпись
A4: =График!B28 -> Уразгильдеева Екатерина | D4: =1934+18212.89+13928.92 -> 34075.81 | F4: =H8+H9 -> 16009.92 | G4: =D12 -> 14200 | H4: =D19 -> 10553.96 | I4: =L19 -> 5095.8247 | J4: =L12 -> 0 | K4: =H4+J4+G4+F4+I4 -> 45859.705 | L4: =C8+C9+C10 -> 5092 | M4: =K4-L4-D4-E4 -> 6691.8947 | S4: пб
B6: Вычеты | G6: Доп начисления
B7: Дата | C7: Сумма | D7: Описание | G7: Дата | H7: Сумма | J7: Описание
B8: 45991 | C8: =2081+289+2722 -> 5092 | D8: НДФЛ ноябрь 2025 | G8: 45991 | H8: 16009.92 | J8: Отпускные 03-15.11
A12: Оклад: | D12: =G16 -> 14200 | I12: Базовый бонус за выполнение плана | L12: =L16+L17 -> 0
B14: Оклад: | J14: Базовый бонус за выполнение плана
B15: Дней | C15: Магазин | D15: Должность | E15: Зачислено часов | F15: Ставка за час, руб | G15: Начислено за день, руб | J15: Магазин | K15: КВП | L15: Начисленный ББ
B16: =График!AI28 -> 13 | C16: =A2 -> ул. Набережная Ленина, 18 | D16: ПК | E16: =График!AJ28 -> 142 | F16: 100 | G16: =E16*F16 -> 14200 | J16: =График!B3 -> ул. Набережная Ленина, 18 | K16: ='Ялта, Ленина, 18'!K8 -> 0.54184722 | L16: 0
A19: БонуснаяЧасть | D19: =G24 -> 10553.96 | I19: Бонусная часть от общих продаж | L19: =N24 -> 5095.8247
B22: Бонус от личных продаж по категории товара | I22: Бонус от общих продаж
B23: Сотрудник | C23: Магазин | E23: Процент от продажи | F23: Продано на сумму, руб | G23: Начисленный бонус от продаж, руб | I23: Сотрудник | J23: Магазин | K23: Кол-во отработанных личных часов | L23: Кол-во отработанных общих часов | M23: Процент от продажи | N23: Начисленный бонус от продаж, руб
B24: =A4 -> Уразгильдеева Екатерина | C24: =A2 -> ул. Набережная Ленина, 18 | E24: 0.04 | F24: ='Уразгильдеева Е. Р. '!J8 -> 263849 | G24: =F24*E24 -> 10553.96 | I24: =B24 -> Уразгильдеева Екатерина | J24: =C24 -> ул. Набережная Ленина, 18 | K24: =E16 -> 142 | L24: =График!AJ31 -> 624 | M24: 0.02 | N24: ='Ялта, Ленина, 18'!J8*M24*K24/L24 -> 5095.8247
B25: =B24 -> Уразгильдеева Екатерина | N25: =1477363.14*M25*K25/L25 -> #DIV/0!

Sheet График
B1: Ноябрь, 2025 | T1: в
B2: г. Ялта
B3: ул. Набережная Ленина, 18
B4: GL-0005
B5: 10.00-22.00
B6: ФОТ | C6: Кол-во дней в месяц | AK6: 30
B7: =BT31*100/BH31 -> #DIV/0!
D8: сб | E8: вс | F8: пн | G8: вт | H8: ср | I8: чт | J8: пт | K8: сб | L8: вс | M8: пн | N8: вт | O8: ср | P8: чт | Q8: пт | R8: сб | S8: вс | T8: пн | U8: вт | V8: ср | W8: чт | X8: пт | Y8: сб | Z8: вс | AA8: пн | AB8: вт | AC8: ср | AD8: чт | AE8: пт | AF8: сб | AG8: вс | AJ8: Часы | AK8: Выходные | AL8: Отпуск | AM8: Больничный (официальный) | AN8: Дни стажировки
A10: № | B10: ФИО | C10: Должность | D10: 1 | E10: 2 | F10: 3 | G10: 4 | H10: 5 | I10: 6 | J10: 7 | K10: 8 | L10: 9 | M10: 10 | N10: 11 | O10: 12 | P10: 13 | Q10: 14 | R10: 15 | S10: 16 | T10: 17 | U10: 18 | V10: 19 | W10: 20 | X10: 21 | Y10: 22 | Z10: 23 | AA10: 24 | AB10: 25 | AC10: 26 | AD10: 27 | AE10: 28 | AF10: 29 | AG10: 30 | AI10: Дни
A11: 20 | AI11: 0 | AJ11: 0 | AK11: 0 | AL11: 0 | AM11: 0 | AN11: 0
A12: 19 | AI12: 0 | AJ12: 0 | AK12: 0 | AL12: 0 | AM12: 0 | AN12: 0
A13: 18 | AI13: 0 | AJ13: 0 | AK13: 0 | AL13: 0 | AM13: 0 | AN13: 0
A14: 17 | AI14: 0 | AJ14: 0 | AK14: 0 | AL14: 0 | AM14: 0 | AN14: 0
A15: 16 | AI15: 0 | AJ15: 0 | AK15: 0 | AL15: 0 | AM15: 0 | AN15: 0
A16: 15 | AI16: 0 | AJ16: 0 | AK16: 0 | AL16: 0 | AM16: 0 | AN16: 0
A17: 14 | AI17: 0 | AJ17: 0 | AK17: 0 | AL17: 0 | AM17: 0 | AN17: 0
A18: 13 | AI18: 0 | AJ18: 0 | AK18: 0 | AL18: 0 | AM18: 0 | AN18: 0
A19: 12 | AI19: 0 | AJ19: 0 | AK19: 0 | AL19: 0 | AM19: 0 | AN19: 0
A20: 11 | AI20: 0 | AJ20: 0 | AK20: 0 | AL20: 0 | AM20: 0 | AN20: 0
A21: 10 | AI21: 0 | AJ21: 0 | AK21: 0 | AL21: 0 | AM21: 0 | AN21: 0
A22: 9 | AI22: =COUNTIF(D22:AH22, ">0") -> 0 | AJ22: 0 | AK22: 0 | AL22: 0 | AM22: 0 | AN22: 0
A23: 8 | AI23: =COUNTIF(D23:AH23, ">0") -> 0 | AJ23: 0 | AK23: 0 | AL23: 0 | AM23: 0 | AN23: 0
A24: 7 | AI24: =COUNTIF(D24:AH24, ">0") -> 0 | AJ24: 0 | AK24: 0 | AL24: 0 | AM24: 0 | AN24: 0
A25: 6 | B25: Козлова Валерия | L25: 8 | V25: 8 | AI25: =COUNTIF(D25:AH25,">0") -> 2 | AJ25: =SUMIF(D25:AH25,">0") -> 16 | AK25: =COUNTIF(D25:AH25,"В") -> 0 | AL25: =COUNTIF(E25:AI25,"о") -> 0 | AM25: =COUNTIF(F25:AJ25,"б") -> 0 | AN25: 0
A26: 5 | B26: Корж Анастасия | K26: 11 | X26: 9 | AI26: =COUNTIF(D26:AH26, ">0") -> 2 | AJ26: =SUMIF(D26:AH26,">0") -> 20 | AK26: =COUNTIF(D26:AH26, "В") -> 0 | AL26: 0 | AM26: 0 | AN26: 0
A27: 4 | B27: Арапова Анна-Мария | C27: ПК | D27: 12 | E27: в | F27: 11 | G27: 11 | H27: в | I27: 9 | J27: 9 | K27: 10 | L27: в | M27: в | N27: 11 | O27: 9 | P27: в | Q27: 10 | R27: в | S27: 11 | T27: 11 | U27: 3 | V27: в | W27: в | X27: 10 | Y27: 12 | Z27: в | AA27: 9 | AB27: 11 | AC27: в | AD27: в | AE27: 12 | AF27: 11 | AG27: 11 | AI27: =COUNTIF(D27:AH27,">0") -> 19 | AJ27: =SUMIF(D27:AH27,">0") -> 193 | AK27: =COUNTIF(D27:AH27,"В") -> 11 | AL27: =COUNTIF(E27:AI27,"о") -> 0 | AM27: =COUNTIF(F27:AJ27,"б") -> 0 | AN27: 0
A28: 3 | B28: Уразгильдеева Екатерина | C28: ПК | D28: 9 | E28: 11 | F28: о | G28: о | H28: о | I28: о | J28: о | K28: о | L28: о | M28: о | N28: о | O28: о | P28: о | Q28: о | R28: 12 | S28: 11 | T28: 11 | U28: в | V28: 11 | W28: 11 | X28: в | Y28: в | Z28: 11 | AA28: 11 | AB28: в | AC28: 11 | AD28: 11 | AE28: в | AF28: 12 | AG28: 10 | AI28: =COUNTIF(D28:AH28,">0") -> 13 | AJ28: =SUMIF(D28:AH28,">0") -> 142 | AK28: =COUNTIF(D28:AH28,"В") -> 5 | AL28: =COUNTIF(E28:AI28,"о") -> 12 | AM28: =COUNTIF(F28:AJ28,"б") -> 0 | AN28: 0
A29: 2 | B29: Рогалевич Ирина | C29: УМ | D29: 8 | E29: 8 | F29: 11 | G29: 11 | H29: 11 | I29: 11 | J29: 12 | K29: 12 | L29: 11 | M29: 11 | N29: 11 | O29: 11 | P29: 11 | Q29: 12 | R29: 9 | S29: в | T29: в | U29: 11 | V29: 8 | W29: 8 | X29: 12 | Y29: 10 | Z29: 8 | AA29: в | AB29: 9 | AC29: 8 | AD29: 8 | AE29: 11 | AF29: в | AG29: в | AI29: =COUNTIF(D29:AH29,">0") -> 25 | AJ29: =SUMIF(D29:AH29,">0") -> 253 | AK29: =COUNTIF(D29:AH29,"В") -> 5 | AL29: =COUNTIF(E29:AI29,"о") -> 0 | AM29: =COUNTIF(F29:AJ29,"б") -> 0 | AN29: 0
A30: 1 | AI30: =COUNTIF(D30:AH30, ">0") -> 0 | AJ30: =SUMIF(D30:AH30,">0") -> 0 | AK30: =COUNTIF(D30:AH30, "В") -> 0 | AL30: =COUNTIF(E30:AI30, "о") -> 0 | AM30: =COUNTIF(F30:AJ30, "б") -> 0 | AN30: 0
B31: Итого магазин | D31: =COUNTIF(D11:D30, ">0") -> 3 | E31: =COUNTIF(E11:E30, ">0") -> 2 | F31: =COUNTIF(F11:F30, ">0") -> 2 | G31: =COUNTIF(G11:G30, ">0") -> 2 | H31: =COUNTIF(H11:H30, ">0") -> 1 | I31: =COUNTIF(I11:I30, ">0") -> 2 | J31: =COUNTIF(J11:J30, ">0") -> 2 | K31: =COUNTIF(K11:K29, ">0") -> 3 | L31: =COUNTIF(L11:L30, ">0") -> 2 | M31: =COUNTIF(M11:M30, ">0") -> 1 | N31: =COUNTIF(N11:N30, ">0") -> 2 | O31: =COUNTIF(O11:O30, ">0") -> 2 | P31: =COUNTIF(P11:P30, ">0") -> 1 | Q31: =COUNTIF(Q11:Q30, ">0") -> 2 | R31: =COUNTIF(R11:R30, ">0") -> 2 | S31: =COUNTIF(S11:S30, ">0") -> 2 | ... AH31: =COUNTIF(AH11:AH30, ">0") -> 0 | AI31: =SUM(AI11:AI30) -> 61 | AJ31: =SUM(AJ11:AJ30) -> 624 | AK31: =SUM(AK11:AK30) -> 21 | AL31: =SUM(AL11:AL30) -> 12 | AM31: =SUM(AM11:AM30) -> 0 | AN31: =SUM(AN11:AN30) -> 0
K32: я | L32: я | V32: я | X32: я
B33: Выделять рабочие дни цветом, выходные не выделять.
B34: Указывать темной или светлой заливкой вечернюю или утреннюю смену.
