Workbook
Name маг: NA()

Sheet Ялта, Ленина, 18
B1: =TODAY()-1 -> 45909
B2: (отчетная дата)
C3: Осталось до выполнения плана!!! | I3: =График!B3 -> ул. Набережная Ленина, 18
C4: =I8-D56 -> 818706 | E4: =IF(I8<>0, C4/I8, 0) -> 0.17418684
D5: =C4/(I14-J14) -> #DIV/0!
F6: Целевые показатели
F7: Показатель | I7: План | J7: Факт | K7: % выполнения | L7: Прогноз выполнения | M7: % выполнения по прогнозу | N7: Отклонение | O7: Факт аналогичного месяца прошлого года | P7: Отклонение LFL
F8: Выручка | I8: =I11*I12*I13 -> 4700160 | J8: =D56 -> 3881454 | K8: =IF(AND(I8<>"",I8<>0,J8<>""),J8/I8,"") -> 0.82581316 | L8: =IF(SUMIF($D$25:$D$55,">=0",$P$25:$P$55)<>0,I8*D56/SUMIF($D$25:$D$55,">=0",$P$25:$P$55),0) -> 3881454 | M8: =IF(AND(I8<>"", I8<>0, L8<>"", L8<>0), L8/I8, "") -> 0.82581316 | N8: =IF(AND(J8<>0, J8<>"", I8<>0, I8<>""), L8-I8, "") -> -818706 | P8: =IF(AND(O8<>"", O8<>0, L8<>"", L8<>0), -O8+L8, "") | Q8: =IF(AND(P8<>"", P8<>0, O8<>0, O8<>""), P8/O8, "")
F9: Кол-во изделий | I9: =I8/I11 -> 783.36 | J9: =E56 -> 672 | K9: =IF(AND(I9<>"", I9<>0, J9<>""), J9/I9, "") -> 0.85784314 | L9: =IF(SUMIF($E$25:$E$55, ">=0", $Q$25:$Q$55)<>0, I9*E56/SUMIF($E$25:$E$55, ">=0", $Q$25:$Q$55), 0) -> 672 | M9: =IF(AND(I9<>"", I9<>0, L9<>"", L9<>0), L9/I9, "") -> 0.85784314 | N9: =IF(AND(J9<>0, J9<>"", I9<>0, I9<>""), L9-I9, "") -> -111.36 | O9: =O8/O11 -> #DIV/0! | P9: =IF(AND(O9<>"", O9<>0, L9<>"", L9<>0), -O9+L9, "") -> #DIV/0! | Q9: =IF(AND(P9<>"", P9<>0, O9<>0, O9<>""), P9/O9, "") -> #DIV/0!
F10: Средний чек | I10: =I11*I12 -> 10200 | J10: =H56 -> 10323.016 | K10: =IF(AND(I10<>"", I10<>0, J10<>""), J10/I10, "") -> 1.0120604 | L10: =J10 -> 10323.016 | M10: =IF(AND(I10<>"", I10<>0, L10<>"", L10<>0), L10/I10, "") -> 1.0120604 | N10: =IF(AND(J10<>0, J10<>"", I10<>0, I10<>""), L10-I10, "") -> 123.01596 | O10: =O11*O12 -> 0 | P10: =IF(AND(O10<>"", O10<>0, L10<>"", L10<>0), -O10+L10, "") | Q10: =IF(AND(P10<>"", P10<>0, O10<>0, O10<>""), P10/O10, "") | S10: =L23 -> IS | V10: =M23 -> Agafi
F11: Средняя стоимость изделия | I11: 6000 | J11: =F56 -> 5775.9732 | K11: =IF(AND(I11<>"", I11<>0, J11<>""), J11/I11, "") -> 0.9626622 | L11: =IF(L9>0, L8/L9, "") -> 5775.9732 | M11: =IF(AND(I11<>"", I11<>0, L11<>"", L11<>0), L11/I11, "") -> 0.9626622 | N11: =IF(AND(J11<>0, J11<>"", I11<>0, I11<>""), L11-I11, "") -> -224.02679 | P11: =IF(AND(O11<>"", O11<>0, L11<>"", L11<>0), -O11+L11, "") | Q11: =IF(AND(P11<>"", P11<>0, O11<>0, O11<>""), P11/O11, "")
F12: Длина чека | I12: 1.7 | J12: =J56 -> 1.787234 | K12: =IF(AND(I12<>"", I12<>0, J12<>""), J12/I12, "") -> 1.0513141 | L12: =J12 -> 1.787234 | M12: =IF(AND(I12<>"", I12<>0, L12<>"", L12<>0), L12/I12, "") -> 1.0513141 | N12: =IF(AND(J12<>0, J12<>"", I12<>0, I12<>""), L12-I12, "") -> 0.087234043 | P12: =IF(AND(O12<>"", O12<>0, L12<>"", L12<>0), -O12+L12, "") | Q12: =IF(AND(P12<>"", P12<>0, O12<>0, O12<>""), P12/O12, "") | S12: 760000 | T12: =L56 -> 420152 | V12: 460000 | W12: =M56 -> 296296.31
F13: Кол-во чеков | I13: =I17*I20 -> 460.8 | J13: =G56 -> 376 | K13: =IF(AND(I13<>"", I13<>0, J13<>""), J13/I13, "") -> 0.81597222 | L13: =IF(SUMIF($G$25:$G$55, ">=0", $R$25:$R$55)<>0, I13*G56/SUMIF($G$25:$G$55, ">=0", $R$25:$R$55), "") -> 376 | M13: =IF(AND(I13<>"", I13<>0, L13<>"", L13<>0), L13/I13, "") -> 0.81597222 | N13: =IF(AND(J13<>0, J13<>"", I13<>0, I13<>""), L13-I13, "") -> -84.8 | P13: =IF(AND(O13<>"", O13<>0, L13<>"", L13<>0), -O13+L13, "") | Q13: =IF(AND(P13<>"", P13<>0, O13<>0, O13<>""), P13/O13, "") | S13: =T12/S12 -> 0.55283158 | T13: =S13/J14*I14 -> 0.55283158 | V13: =W12/V12 -> 0.64412241 | W13: =V13/J14*I14 -> 0.64412241
F14: Кол-во смен | I14: 31 | J14: 31 | K14: =IF(AND(I14<>"", I14<>0, J14<>""), J14/I14, "") -> 1 | L14: =I14 -> 31 | M14: =IF(AND(I14<>"", I14<>0, L14<>"", L14<>0), L14/I14, "") -> 1 | N14: =IF(AND(J14<>0, J14<>"", I14<>0, I14<>""), L14-I14, "") -> 0 | P14: =IF(AND(O14<>"", O14<>0, L14<>"", L14<>0), -O14+L14, "") | Q14: =IF(AND(P14<>"", P14<>0, O14<>0, O14<>""), P14/O14, "")
F15: Средние продажи в смену | I15: =I8/I14 -> 151618.06 | J15: =J8/J14 -> 125208.19 | K15: =IF(AND(I15<>"", I15<>0, J15<>""), J15/I15, "") -> 0.82581316 | L15: =J15 -> 125208.19 | M15: =IF(AND(I15<>"", I15<>0, L15<>"", L15<>0), L15/I15, "") -> 0.82581316 | N15: =IF(AND(J15<>0, J15<>"", I15<>0, I15<>""), L15-I15, "") -> -26409.871 | P15: =IF(AND(O15<>"", O15<>0, L15<>"", L15<>0), -O15+L15, "") | Q15: =IF(AND(P15<>"", P15<>0, O15<>0, O15<>""), P15/O15, "")
F16: Отставание/Перевыполнение | J16: =J8-I15*J14 -> -818706 | K16: =IF(AND(I16<>"", I16<>0, J16<>""), J16/I16, "") | L16: =J16 -> -818706 | M16: =IF(AND(I16<>"", I16<>0, L16<>"", L16<>0), L16/I16, "") | N16: =IF(AND(J16<>0, J16<>"", I16<>0, I16<>""), L16-I16, "") | P16: =IF(AND(O16<>"", O16<>0, L16<>"", L16<>0), -O16+L16, "") | Q16: =IF(AND(P16<>"", P16<>0, O16<>0, O16<>""), P16/O16, "") | S16: =K23 -> UNOde50
F17: Трафик | I17: 2560 | J17: =I56 -> 2645 | K17: =IF(AND(I17<>"", I17<>0, J17<>""), J17/I17, "") -> 1.0332031 | L17: =J17/J14*I14 -> 2645 | M17: =IF(AND(I17<>"", I17<>0, L17<>"", L17<>0), L17/I17, "") -> 1.0332031 | N17: =IF(AND(J17<>0, J17<>"", I17<>0, I17<>""), L17-I17, "") -> 85 | P17: =IF(AND(O17<>"", O17<>0, L17<>"", L17<>0), -O17+L17, "") | Q17: =IF(AND(P17<>"", P17<>0, O17<>0, O17<>""), P17/O17, "")
K18: =IF(AND(I18<>"", I18<>0, J18<>""), J18/I18, "") | L18: =J18 -> 0 | M18: =IF(AND(I18<>"", I18<>0, L18<>"", L18<>0), L18/I18, "") | N18: =IF(AND(J18<>0, J18<>"", I18<>0, I18<>""), L18-I18, "") | O18: 0 | P18: =IF(AND(O18<>"", O18<>0, L18<>"", L18<>0), -O18+L18, "") | Q18: =IF(AND(P18<>"", P18<>0, O18<>0, O18<>""), P18/O18, "") | S18: 880000 | T18: =K56 -> 639010.35
K19: =IF(AND(I19<>"", I19<>0, J19<>""), J19/I19, "") | L19: =J19 -> 0 | M19: =IF(AND(I19<>"", I19<>0, L19<>"", L19<>0), L19/I19, "") | N19: =IF(AND(J19<>0, J19<>"", I19<>0, I19<>""), L19-I19, "") | O19: 0 | P19: =IF(AND(O19<>"", O19<>0, L19<>"", L19<>0), -O19+L19, "") | Q19: =IF(AND(P19<>"", P19<>0, O19<>0, O19<>""), P19/O19, "") | S19: =T18/S18 -> 0.72614812 | T19: =S19/J14*I14 -> 0.72614812
F20: Конверсия план/факт | I20: 0.18 | J20: =N56 -> 0.14215501 | K20: =J20/I20 -> 0.78975005 | L20: =IF(AND(K8<>0, I14<>0, I56<>0), (I56*N56+(I56/K8-I56)*I20)/(I56/K8), 0) -> 0.14874711 | M20: =IF(AND(I20<>"", I20<>0, L20<>"", L20<>0), L20/I20, "") -> 0.82637283 | N20: =IF(AND(J20<>0, J20<>"", I20<>0, I20<>""), L20-I20, "") -> -0.031252891 | P20: =IF(AND(O20<>"", O20<>0, L20<>"", L20<>0), -O20+L20, "") | Q20: =IF(AND(P20<>"", P20<>0, O20<>0, O20<>""), P20/O20, "")
A22: Факт продаж за месяц | O22: % выполнения дневного плана | P22: Раcпределение плана по дням
A23: Сотрудник | B23: Дата | C23: День недели | D23: Выручка (руб) | E23: Кол-во единиц (шт.) | F23: Средняя стоимость изделия (руб.) | G23: Количество чеков (шт.) | H23: Средняя сумма чека (руб.) | I23: Трафик | J23: Длина чека (шт.) | K23: UNOde50 | L23: IS | M23: Agafi | N23: Конверсия (%) | P23: выручка, план | Q23: кол-во ед, план | R23: Кол-во чеков, план | S23: выручка, скорректир.план | T23: кол-во ед, скорр. план | U23: кол-во чеков, скорр. план | V23: Коэфф. Дня Недели | W23: Специфика месяца
B24: 1 | C24: 2 | D24: 3 | E24: 4 | F24: 5 | G24: 6 | H24: 7 | I24: 8 | J24: 9 | K24: 10 | L24: 11 | M24: 12 | N24: 13 | P24: 1 | Q24: 2 | R24: 3 | S24: 4 | T24: 5 | U24: 6 | V24: 10 | W24: 11
A25: Уразгильдеева,Яковенко | B25: 45870 | C25: пт | D25: =14392+15952+3413.7+35091 -> 68848.7 | E25: 15 | F25: =IF(AND(E25<>"",E25<>0),D25/E25,"") -> 4589.9133 | G25: 9 | H25: =IF(AND(G25<>"",G25<>0),D25/G25,"") -> 7649.8556 | I25: 40 | J25: =IF(AND(G25<>"",G25<>0),E25/G25,"") -> 1.6666667 | K25: 14392 | M25: 4772.06 | N25: =IF(AND(I25<>"",I25<>0),G25/I25,"") -> 0.225 | O25: =D25/P25 -> 0.45057013 | P25: =$I$8*V25*W25/SUMPRODUCT($W$25:$W$55,$V$25:$V$55) -> 152803.52 | Q25: =$I$9*V25*W25/SUMPRODUCT($W$25:$W$55,$V$25:$V$55) -> 25.467253 | R25: =IF($I$12="","",Q25/$I$12) -> 14.980737 | S25: =IF(D25<>"",D25,P25) -> 68848.7 | T25: =IF(E25<>"",E25,Q25) -> 15 | U25: =IF(G25<>"",G25,R25) -> 9 | V25: 0.9414554 | W25: 0.9414554
A26: Рогалевич,Уразгильдеева | B26: 45871 | C26: сб | D26: =16900+48674+11383 -> 76957 | E26: 13 | F26: =IF(AND(E26<>"",E26<>0),D26/E26,"") -> 5919.7692 | G26: 9 | H26: =IF(AND(G26<>"",G26<>0),D26/G26,"") -> 8550.7778 | I26: 60 | J26: =IF(AND(G26<>"",G26<>0),E26/G26,"") -> 1.4444444 | K26: 11383 | L26: 16900 | M26: 0 | N26: =IF(AND(I26<>"",I26<>0),G26/I26,"") -> 0.15 | O26: =D26/P26 -> 0.61335516 | P26: =$I$8*V26*W26/SUMPRODUCT($W$25:$W$55,$V$25:$V$55) -> 125468.91 | Q26: =$I$9*V26*W26/SUMPRODUCT($W$25:$W$55,$V$25:$V$55) -> 20.911484 | R26: =IF($I$12="","",Q26/$I$12) -> 12.300873 | S26: =IF(W26<>"",IF(D26<>"",D26,($I$8-SUM($S$25:S25))*V26*W26/SUMPRODUCT($W26:$W$55,$V26:$V$55)),"") -> 76957 | T26: =IF(W26<>"",IF(E26<>"",E26,($I$9-SUM($T$25:T25))*V26*W26/SUMPRODUCT($W26:$W$55,$V26:$V$55)),"") -> 13 | U26: =IF(W26<>"",IF($I$12<>"",IF(G26<>"",G26,($I$9/$I$12-SUM($U$25:U25))*V26*W26/SUMPRODUCT($W26:$W$55,$V26:$V$55)),""),"") -> 9 | V26: 0.85310234 | W26: 0.85310234
A27: Рогалевич,Яковенко | B27: 45872 | C27: вс | D27: =222210.6+4623 -> 226833.6 | E27: 46 | F27: =IF(AND(E27<>"",E27<>0),D27/E27,"") -> 4931.1652 | G27: 20 | H27: =IF(AND(G27<>"",G27<>0),D27/G27,"") -> 11341.68 | I27: 110 | J27: =IF(AND(G27<>"",G27<>0),E27/G27,"") -> 2.3 | L27: 4623 | M27: 44443.25 | N27: =IF(AND(I27<>"",I27<>0),G27/I27,"") -> 0.18181818 | O27: =D27/P27 -> 1.807887 | P27: =$I$8*V27*W27/SUMPRODUCT($W$25:$W$55,$V$25:$V$55) -> 125468.91 | Q27: =$I$9*V27*W27/SUMPRODUCT($W$25:$W$55,$V$25:$V$55) -> 20.911484 | R27: =IF($I$12="","",Q27/$I$12) -> 12.300873 | S27: =IF(W27<>"",IF(D27<>"",D27,($I$8-SUM($S$25:S26))*V27*W27/SUMPRODUCT($W27:$W$55,$V27:$V$55)),"") -> 226833.6 | T27: =IF(W27<>"",IF(E27<>"",E27,($I$9-SUM($T$25:T26))*V27*W27/SUMPRODUCT($W27:$W$55,$V27:$V$55)),"") -> 46 | U27: =IF(W27<>"",IF($I$12<>"",IF(G27<>"",G27,($I$9/$I$12-SUM($U$25:U26))*V27*W27/SUMPRODUCT($W27:$W$55,$V27:$V$55)),""),"") -> 20 | V27: 0.85310234 | W27: 0.85310234
A28: Рогалевич,Яковенко | B28: 45873 | C28: пн | D28: 45513 | E28: 11 | F28: =IF(AND(E28<>"",E28<>0),D28/E28,"") -> 4137.5455 | G28: 9 | H28: =IF(AND(G28<>"",G28<>0),D28/G28,"") -> 5057 | I28: 60 | J28: =IF(AND(G28<>"",G28<>0),E28/G28,"") -> 1.2222222 | N28: =IF(AND(I28<>"",I28<>0),G28/I28,"") -> 0.15 | O28: =D28/P28 -> 0.36274326 | P28: =$I$8*V28*W28/SUMPRODUCT($W$25:$W$55,$V$25:$V$55) -> 125468.91 | Q28: =$I$9*V28*W28/SUMPRODUCT($W$25:$W$55,$V$25:$V$55) -> 20.911484 | R28: =IF($I$12="","",Q28/$I$12) -> 12.300873 | S28: =IF(W28<>"",IF(D28<>"",D28,($I$8-SUM($S$25:S27))*V28*W28/SUMPRODUCT($W28:$W$55,$V28:$V$55)),"") -> 45513 | T28: =IF(W28<>"",IF(E28<>"",E28,($I$9-SUM($T$25:T27))*V28*W28/SUMPRODUCT($W28:$W$55,$V28:$V$55)),"") -> 11 | U28: =IF(W28<>"",IF($I$12<>"",IF(G28<>"",G28,($I$9/$I$12-SUM($U$25:U27))*V28*W28/SUMPRODUCT($W28:$W$55,$V28:$V$55)),""),"") -> 9 | V28: 0.85310234 | W28: 0.85310234
A29: Яковенко,Уразгильдеева | B29: 45874 | C29: вт | D29: 82687.7 | E29: 18 | F29: =IF(AND(E29<>"",E29<>0),D29/E29,"") -> 4593.7611 | G29: 11 | H29: =IF(AND(G29<>"",G29<>0),D29/G29,"") -> 7517.0636 | I29: 50 | J29: =IF(AND(G29<>"",G29<>0),E29/G29,"") -> 1.6363636 | L29: 16203 | N29: =IF(AND(I29<>"",I29<>0),G29/I29,"") -> 0.22 | O29: =D29/P29 -> 0.66384886 | P29: =$I$8*V29*W29/SUMPRODUCT($W$25:$W$55,$V$25:$V$55) -> 124558.02 | Q29: =$I$9*V29*W29/SUMPRODUCT($W$25:$W$55,$V$25:$V$55) -> 20.75967 | R29: =IF($I$12="","",Q29/$I$12) -> 12.211571 | S29: =IF(W29<>"",IF(D29<>"",D29,($I$8-SUM($S$25:S28))*V29*W29/SUMPRODUCT($W29:$W$55,$V29:$V$55)),"") -> 82687.7 | T29: =IF(W29<>"",IF(E29<>"",E29,($I$9-SUM($T$25:T28))*V29*W29/SUMPRODUCT($W29:$W$55,$V29:$V$55)),"") -> 18 | U29: =IF(W29<>"",IF($I$12<>"",IF(G29<>"",G29,($I$9/$I$12-SUM($U$25:U28))*V29*W29/SUMPRODUCT($W29:$W$55,$V29:$V$55)),""),"") -> 11 | V29: 0.85 | W29: 0.85
A30: Рогалевич,Уразгильдеева | B30: 45875 | C30: ср | D30: =24903+46510+57982 -> 129395 | E30: 13 | F30: =IF(AND(E30<>"",E30<>0),D30/E30,"") -> 9953.4615 | G30: 11 | H30: =IF(AND(G30<>"",G30<>0),D30/G30,"") -> 11763.182 | I30: 50 | J30: =IF(AND(G30<>"",G30<>0),E30/G30,"") -> 1.1818182 | K30: 57982 | L30: 24903 | N30: =IF(AND(I30<>"",I30<>0),G30/I30,"") -> 0.22 | O30: =D30/P30 -> 0.75055695 | P30: =$I$8*V30*W30/SUMPRODUCT($W$25:$W$55,$V$25:$V$55) -> 172398.64 | Q30: =$I$9*V30*W30/SUMPRODUCT($W$25:$W$55,$V$25:$V$55) -> 28.733107 | R30: =IF($I$12="","",Q30/$I$12) -> 16.901828 | S30: =IF(W30<>"",IF(D30<>"",D30,($I$8-SUM($S$25:S29))*V30*W30/SUMPRODUCT($W30:$W$55,$V30:$V$55)),"") -> 129395 | T30: =IF(W30<>"",IF(E30<>"",E30,($I$9-SUM($T$25:T29))*V30*W30/SUMPRODUCT($W30:$W$55,$V30:$V$55)),"") -> 13 | U30: =IF(W30<>"",IF($I$12<>"",IF(G30<>"",G30,($I$9/$I$12-SUM($U$25:U29))*V30*W30/SUMPRODUCT($W30:$W$55,$V30:$V$55)),""),"") -> 11 | V30: 1 | W30: 1
A31: Рогалевич,Яковенко | B31: 45876 | C31: чт | D31: =16403+77557+50326+38820 -> 183106 | E31: 27 | F31: =IF(AND(E31<>"",E31<>0),D31/E31,"") -> 6781.7037 | G31: 19 | H31: =IF(AND(G31<>"",G31<>0),D31/G31,"") -> 9637.1579 | I31: 110 | J31: =IF(AND(G31<>"",G31<>0),E31/G31,"") -> 1.4210526 | K31: 77557 | L31: 16403 | M31: 12890 | N31: =IF(AND(I31<>"",I31<>0),G31/I31,"") -> 0.17272727 | O31: =D31/P31 -> 1.4593735 | P31: =$I$8*V31*W31/SUMPRODUCT($W$25:$W$55,$V$25:$V$55) -> 125468.91 | Q31: =$I$9*V31*W31/SUMPRODUCT($W$25:$W$55,$V$25:$V$55) -> 20.911484 | R31: =IF($I$12="","",Q31/$I$12) -> 12.300873 | S31: =IF(W31<>"",IF(D31<>"",D31,($I$8-SUM($S$25:S30))*V31*W31/SUMPRODUCT($W31:$W$55,$V31:$V$55)),"") -> 183106 | T31: =IF(W31<>"",IF(E31<>"",E31,($I$9-SUM($T$25:T30))*V31*W31/SUMPRODUCT($W31:$W$55,$V31:$V$55)),"") -> 27 | U31: =IF(W31<>"",IF($I$12<>"",IF(G31<>"",G31,($I$9/$I$12-SUM($U$25:U30))*V31*W31/SUMPRODUCT($W31:$W$55,$V31:$V$55)),""),"") -> 19 | V31: 0.85310234 | W31: 0.85310234
A32: Рогалевич,Яковенко | B32: 45877 | C32: пт | D32: =110637+25206+7492 -> 143335 | E32: 22 | F32: =IF(AND(E32<>"",E32<>0),D32/E32,"") -> 6515.2273 | G32: 11 | H32: =IF(AND(G32<>"",G32<>0),D32/G32,"") -> 13030.455 | I32: 80 | J32: =IF(AND(G32<>"",G32<>0),E32/G32,"") -> 2 | K32: 7492 | L32: 25206 | M32: 34570 | N32: =IF(AND(I32<>"",I32<>0),G32/I32,"") -> 0.1375 | O32: =D32/P32 -> 1.1423946 | P32: =$I$8*V32*W32/SUMPRODUCT($W$25:$W$55,$V$25:$V$55) -> 125468.91 | Q32: =$I$9*V32*W32/SUMPRODUCT($W$25:$W$55,$V$25:$V$55) -> 20.911484 | R32: =IF($I$12="","",Q32/$I$12) -> 12.300873 | S32: =IF(W32<>"",IF(D32<>"",D32,($I$8-SUM($S$25:S31))*V32*W32/SUMPRODUCT($W32:$W$55,$V32:$V$55)),"") -> 143335 | T32: =IF(W32<>"",IF(E32<>"",E32,($I$9-SUM($T$25:T31))*V32*W32/SUMPRODUCT($W32:$W$55,$V32:$V$55)),"") -> 22 | U32: =IF(W32<>"",IF($I$12<>"",IF(G32<>"",G32,($I$9/$I$12-SUM($U$25:U31))*V32*W32/SUMPRODUCT($W32:$W$55,$V32:$V$55)),""),"") -> 11 | V32: 0.85310234 | W32: 0.85310234
A33: Рогалевич,Яковенко,Уразгильдеева | B33: 45878 | C33: сб | D33: =46707+128331 -> 175038 | E33: 22 | F33: =IF(AND(E33<>"",E33<>0),D33/E33,"") -> 7956.2727 | G33: 16 | H33: =IF(AND(G33<>"",G33<>0),D33/G33,"") -> 10939.875 | I33: 110 | J33: =IF(AND(G33<>"",G33<>0),E33/G33,"") -> 1.375 | L33: 46707 | M33: 49280 | N33: =IF(AND(I33<>"",I33<>0),G33/I33,"") -> 0.14545455 | O33: =D33/P33 -> 1.3950708 | P33: =$I$8*V33*W33/SUMPRODUCT($W$25:$W$55,$V$25:$V$55) -> 125468.91 | Q33: =$I$9*V33*W33/SUMPRODUCT($W$25:$W$55,$V$25:$V$55) -> 20.911484 | R33: =IF($I$12="","",Q33/$I$12) -> 12.300873 | S33: =IF(W33<>"",IF(D33<>"",D33,($I$8-SUM($S$25:S32))*V33*W33/SUMPRODUCT($W33:$W$55,$V33:$V$55)),"") -> 175038 | T33: =IF(W33<>"",IF(E33<>"",E33,($I$9-SUM($T$25:T32))*V33*W33/SUMPRODUCT($W33:$W$55,$V33:$V$55)),"") -> 22 | U33: =IF(W33<>"",IF($I$12<>"",IF(G33<>"",G33,($I$9/$I$12-SUM($U$25:U32))*V33*W33/SUMPRODUCT($W33:$W$55,$V33:$V$55)),""),"") -> 16 | V33: 0.85310234 | W33: 0.85310234
A34: Рогалевич,Уразгильдеева | B34: 45879 | C34: вс | D34: =6991+50928+33665+20158 -> 111742 | E34: 17 | F34: =IF(AND(E34<>"",E34<>0),D34/E34,"") -> 6573.0588 | G34: 10 | H34: =IF(AND(G34<>"",G34<>0),D34/G34,"") -> 11174.2 | I34: 60 | J34: =IF(AND(G34<>"",G34<>0),E34/G34,"") -> 1.7 | K34: 6991 | L34: 50928 | N34: =IF(AND(I34<>"",I34<>0),G34/I34,"") -> 0.16666667 | O34: =D34/P34 -> 0.89059516 | P34: =$I$8*V34*W34/SUMPRODUCT($W$25:$W$55,$V$25:$V$55) -> 125468.91 | Q34: =$I$9*V34*W34/SUMPRODUCT($W$25:$W$55,$V$25:$V$55) -> 20.911484 | R34: =IF($I$12="","",Q34/$I$12) -> 12.300873 | S34: =IF(W34<>"",IF(D34<>"",D34,($I$8-SUM($S$25:S33))*V34*W34/SUMPRODUCT($W34:$W$55,$V34:$V$55)),"") -> 111742 | T34: =IF(W34<>"",IF(E34<>"",E34,($I$9-SUM($T$25:T33))*V34*W34/SUMPRODUCT($W34:$W$55,$V34:$V$55)),"") -> 17 | U34: =IF(W34<>"",IF($I$12<>"",IF(G34<>"",G34,($I$9/$I$12-SUM($U$25:U33))*V34*W34/SUMPRODUCT($W34:$W$55,$V34:$V$55)),""),"") -> 10 | V34: 0.85310234 | W34: 0.85310234
A35: Рогалевич,Яковенко | B35: 45880 | C35: пн | D35: =6992+35332+6000+38721 -> 87045 | E35: 20 | F35: =IF(AND(E35<>"",E35<>0),D35/E35,"") -> 4352.25 | G35: 10 | H35: =IF(AND(G35<>"",G35<>0),D35/G35,"") -> 8704.5 | I35: 60 | J35: =IF(AND(G35<>"",G35<>0),E35/G35,"") -> 2 | K35: 6992 | N35: =IF(AND(I35<>"",I35<>0),G35/I35,"") -> 0.16666667 | O35: =D35/P35 -> 0.50490536 | P35: =$I$8*V35*W35/SUMPRODUCT($W$25:$W$55,$V$25:$V$55) -> 172398.64 | Q35: =$I$9*V35*W35/SUMPRODUCT($W$25:$W$55,$V$25:$V$55) -> 28.733107 | R35: =IF($I$12="","",Q35/$I$12) -> 16.901828 | S35: =IF(W35<>"",IF(D35<>"",D35,($I$8-SUM($S$25:S34))*V35*W35/SUMPRODUCT($W35:$W$55,$V35:$V$55)),"") -> 87045 | T35: =IF(W35<>"",IF(E35<>"",E35,($I$9-SUM($T$25:T34))*V35*W35/SUMPRODUCT($W35:$W$55,$V35:$V$55)),"") -> 20 | U35: =IF(W35<>"",IF($I$12<>"",IF(G35<>"",G35,($I$9/$I$12-SUM($U$25:U34))*V35*W35/SUMPRODUCT($W35:$W$55,$V35:$V$55)),""),"") -> 10 | V35: 1 | W35: 1
A36: Рогалевич,Яковенко | B36: 45881 | C36: вт | D36: =20806+14280+66878+79259 -> 181223 | E36: 38 | F36: =IF(AND(E36<>"",E36<>0),D36/E36,"") -> 4769.0263 | G36: 23 | H36: =IF(AND(G36<>"",G36<>0),D36/G36,"") -> 7879.2609 | I36: 110 | J36: =IF(AND(G36<>"",G36<>0),E36/G36,"") -> 1.6521739 | L36: 20806 | M36: 14280 | N36: =IF(AND(I36<>"",I36<>0),G36/I36,"") -> 0.20909091 | O36: =D36/P36 -> 1.0511858 | P36: =$I$8*V36*W36/SUMPRODUCT($W$25:$W$55,$V$25:$V$55) -> 172398.64 | Q36: =$I$9*V36*W36/SUMPRODUCT($W$25:$W$55,$V$25:$V$55) -> 28.733107 | R36: =IF($I$12="","",Q36/$I$12) -> 16.901828 | S36: =IF(W36<>"",IF(D36<>"",D36,($I$8-SUM($S$25:S35))*V36*W36/SUMPRODUCT($W36:$W$55,$V36:$V$55)),"") -> 181223 | T36: =IF(W36<>"",IF(E36<>"",E36,($I$9-SUM($T$25:T35))*V36*W36/SUMPRODUCT($W36:$W$55,$V36:$V$55)),"") -> 38 | U36: =IF(W36<>"",IF($I$12<>"",IF(G36<>"",G36,($I$9/$I$12-SUM($U$25:U35))*V36*W36/SUMPRODUCT($W36:$W$55,$V36:$V$55)),""),"") -> 23 | V36: 1 | W36: 1
A37: Рогалевич,Уразгильдеева,Яковенко | B37: 45882 | C37: ср | D37: 268700 | E37: 40 | F37: =IF(AND(E37<>"",E37<>0),D37/E37,"") -> 6717.5 | G37: 18 | H37: =IF(AND(G37<>"",G37<>0),D37/G37,"") -> 14927.778 | I37: 110 | J37: =IF(AND(G37<>"",G37<>0),E37/G37,"") -> 2.2222222 | K37: 109143 | L37: 16106 | M37: 7390 | N37: =IF(AND(I37<>"",I37<>0),G37/I37,"") -> 0.16363636 | O37: =D37/P37 -> 1.5585969 | P37: =$I$8*V37*W37/SUMPRODUCT($W$25:$W$55,$V$25:$V$55) -> 172398.64 | Q37: =$I$9*V37*W37/SUMPRODUCT($W$25:$W$55,$V$25:$V$55) -> 28.733107 | R37: =IF($I$12="","",Q37/$I$12) -> 16.901828 | S37: =IF(W37<>"",IF(D37<>"",D37,($I$8-SUM($S$25:S36))*V37*W37/SUMPRODUCT($W37:$W$55,$V37:$V$55)),"") -> 268700 | T37: =IF(W37<>"",IF(E37<>"",E37,($I$9-SUM($T$25:T36))*V37*W37/SUMPRODUCT($W37:$W$55,$V37:$V$55)),"") -> 40 | U37: =IF(W37<>"",IF($I$12<>"",IF(G37<>"",G37,($I$9/$I$12-SUM($U$25:U36))*V37*W37/SUMPRODUCT($W37:$W$55,$V37:$V$55)),""),"") -> 18 | V37: 1 | W37: 1
A38: Уразгильдеева,Яковенко | B38: 45883 | C38: чт | D38: 127931 | E38: 21 | F38: =IF(AND(E38<>"",E38<>0),D38/E38,"") -> 6091.9524 | G38: 9 | H38: =IF(AND(G38<>"",G38<>0),D38/G38,"") -> 14214.556 | I38: 100 | J38: =IF(AND(G38<>"",G38<>0),E38/G38,"") -> 2.3333333 | K38: 36570.35 | L38: 0 | M38: 19970 | N38: =IF(AND(I38<>"",I38<>0),G38/I38,"") -> 0.09 | O38: =D38/P38 -> 0.742065 | P38: =$I$8*V38*W38/SUMPRODUCT($W$25:$W$55,$V$25:$V$55) -> 172398.64 | Q38: =$I$9*V38*W38/SUMPRODUCT($W$25:$W$55,$V$25:$V$55) -> 28.733107 | R38: =IF($I$12="","",Q38/$I$12) -> 16.901828 | S38: =IF(W38<>"",IF(D38<>"",D38,($I$8-SUM($S$25:S37))*V38*W38/SUMPRODUCT($W38:$W$55,$V38:$V$55)),"") -> 127931 | T38: =IF(W38<>"",IF(E38<>"",E38,($I$9-SUM($T$25:T37))*V38*W38/SUMPRODUCT($W38:$W$55,$V38:$V$55)),"") -> 21 | U38: =IF(W38<>"",IF($I$12<>"",IF(G38<>"",G38,($I$9/$I$12-SUM($U$25:U37))*V38*W38/SUMPRODUCT($W38:$W$55,$V38:$V$55)),""),"") -> 9 | V38: 1 | W38: 1
A39: Рогалевич,Яковенко | B39: 45853 | C39: пт | D39: =19598+47387+39885 -> 106870 | E39: 20 | F39: =IF(AND(E39<>"",E39<>0),D39/E39,"") -> 5343.5 | G39: 12 | H39: =IF(AND(G39<>"",G39<>0),D39/G39,"") -> 8905.8333 | I39: 100 | J39: =IF(AND(G39<>"",G39<>0),E39/G39,"") -> 1.6666667 | K39: 19598 | N39: =IF(AND(I39<>"",I39<>0),G39/I39,"") -> 0.12 | O39: =D39/P39 -> 0.61990047 | P39: =$I$8*V39*W39/SUMPRODUCT($W$25:$W$55,$V$25:$V$55) -> 172398.64 | Q39: =$I$9*V39*W39/SUMPRODUCT($W$25:$W$55,$V$25:$V$55) -> 28.733107 | R39: =IF($I$12="","",Q39/$I$12) -> 16.901828 | S39: =IF(W39<>"",IF(D39<>"",D39,($I$8-SUM($S$25:S38))*V39*W39/SUMPRODUCT($W39:$W$55,$V39:$V$55)),"") -> 106870 | T39: =IF(W39<>"",IF(E39<>"",E39,($I$9-SUM($T$25:T38))*V39*W39/SUMPRODUCT($W39:$W$55,$V39:$V$55)),"") -> 20 | U39: =IF(W39<>"",IF($I$12<>"",IF(G39<>"",G39,($I$9/$I$12-SUM($U$25:U38))*V39*W39/SUMPRODUCT($W39:$W$55,$V39:$V$55)),""),"") -> 12 | V39: 1 | W39: 1
A40: Рогалевич,Яковенко,Уразгильдеева | B40: 45854 | C40: сб | D40: =5501+49605+66972+74558+9283 -> 205919 | E40: 42 | F40: =IF(AND(E40<>"",E40<>0),D40/E40,"") -> 4902.8333 | G40: 23 | H40: =IF(AND(G40<>"",G40<>0),D40/G40,"") -> 8953 | I40: 100 | J40: =IF(AND(G40<>"",G40<>0),E40/G40,"") -> 1.826087 | L40: 5501 | N40: =IF(AND(I40<>"",I40<>0),G40/I40,"") -> 0.23 | O40: =D40/P40 -> 1.1944351 | P40: =$I$8*V40*W40/SUMPRODUCT($W$25:$W$55,$V$25:$V$55) -> 172398.64 | Q40: =$I$9*V40*W40/SUMPRODUCT($W$25:$W$55,$V$25:$V$55) -> 28.733107 | R40: =IF($I$12="","",Q40/$I$12) -> 16.901828 | S40: =IF(W40<>"",IF(D40<>"",D40,($I$8-SUM($S$25:S39))*V40*W40/SUMPRODUCT($W40:$W$55,$V40:$V$55)),"") -> 205919 | T40: =IF(W40<>"",IF(E40<>"",E40,($I$9-SUM($T$25:T39))*V40*W40/SUMPRODUCT($W40:$W$55,$V40:$V$55)),"") -> 42 | U40: =IF(W40<>"",IF($I$12<>"",IF(G40<>"",G40,($I$9/$I$12-SUM($U$25:U39))*V40*W40/SUMPRODUCT($W40:$W$55,$V40:$V$55)),""),"") -> 23 | V40: 1 | W40: 1
A41: Рогалевич,Уразгильдеева | B41: 45855 | C41: вс | D41: 67955 | E41: 16 | F41: =IF(AND(E41<>"",E41<>0),D41/E41,"") -> 4247.1875 | G41: 9 | H41: =IF(AND(G41<>"",G41<>0),D41/G41,"") -> 7550.5556 | I41: 70 | J41: =IF(AND(G41<>"",G41<>0),E41/G41,"") -> 1.7777778 | N41: =IF(AND(I41<>"",I41<>0),G41/I41,"") -> 0.12857143 | O41: =D41/P41 -> 0.39417363 | P41: =$I$8*V41*W41/SUMPRODUCT($W$25:$W$55,$V$25:$V$55) -> 172398.64 | Q41: =$I$9*V41*W41/SUMPRODUCT($W$25:$W$55,$V$25:$V$55) -> 28.733107 | R41: =IF($I$12="","",Q41/$I$12) -> 16.901828 | S41: =IF(W41<>"",IF(D41<>"",D41,($I$8-SUM($S$25:S40))*V41*W41/SUMPRODUCT($W41:$W$55,$V41:$V$55)),"") -> 67955 | T41: =IF(W41<>"",IF(E41<>"",E41,($I$9-SUM($T$25:T40))*V41*W41/SUMPRODUCT($W41:$W$55,$V41:$V$55)),"") -> 16 | U41: =IF(W41<>"",IF($I$12<>"",IF(G41<>"",G41,($I$9/$I$12-SUM($U$25:U40))*V41*W41/SUMPRODUCT($W41:$W$55,$V41:$V$55)),""),"") -> 9 | V41: 1 | W41: 1
A42: Рогалевич,Яковенко | B42: 45856 | C42: пн | D42: =21304+23583+65259+39632 -> 149778 | E42: 27 | F42: =IF(AND(E42<>"",E42<>0),D42/E42,"") -> 5547.3333 | G42: 13 | H42: =IF(AND(G42<>"",G42<>0),D42/G42,"") -> 11521.385 | I42: 90 | J42: =IF(AND(G42<>"",G42<>0),E42/G42,"") -> 2.0769231 | L42: 21304 | M42: 23583 | N42: =IF(AND(I42<>"",I42<>0),G42/I42,"") -> 0.14444444 | O42: =D42/P42 -> 0.86878873 | P42: =$I$8*V42*W42/SUMPRODUCT($W$25:$W$55,$V$25:$V$55) -> 172398.64 | Q42: =$I$9*V42*W42/SUMPRODUCT($W$25:$W$55,$V$25:$V$55) -> 28.733107 | R42: =IF($I$12="","",Q42/$I$12) -> 16.901828 | S42: =IF(W42<>"",IF(D42<>"",D42,($I$8-SUM($S$25:S41))*V42*W42/SUMPRODUCT($W42:$W$55,$V42:$V$55)),"") -> 149778 | T42: =IF(W42<>"",IF(E42<>"",E42,($I$9-SUM($T$25:T41))*V42*W42/SUMPRODUCT($W42:$W$55,$V42:$V$55)),"") -> 27 | U42: =IF(W42<>"",IF($I$12<>"",IF(G42<>"",G42,($I$9/$I$12-SUM($U$25:U41))*V42*W42/SUMPRODUCT($W42:$W$55,$V42:$V$55)),""),"") -> 13 | V42: 1 | W42: 1
A43: Рогалевич,Яковенко | B43: 45857 | C43: вт | D43: =59466+2203+13180+72366+69525 -> 216740 | E43: 37 | F43: 5859 | G43: 19 | H43: =IF(AND(G43<>"",G43<>0),D43/G43,"") -> 11407.368 | I43: 150 | J43: =IF(AND(G43<>"",G43<>0),E43/G43,"") -> 1.9473684 | K43: 59466 | L43: 2203 | M43: 13180 | N43: =IF(AND(I43<>"",I43<>0),G43/I43,"") -> 0.12666667 | O43: =D43/P43 -> 1.2572025 | P43: =$I$8*V43*W43/SUMPRODUCT($W$25:$W$55,$V$25:$V$55) -> 172398.64 | Q43: =$I$9*V43*W43/SUMPRODUCT($W$25:$W$55,$V$25:$V$55) -> 28.733107 | R43: =IF($I$12="","",Q43/$I$12) -> 16.901828 | S43: =IF(W43<>"",IF(D43<>"",D43,($I$8-SUM($S$25:S42))*V43*W43/SUMPRODUCT($W43:$W$55,$V43:$V$55)),"") -> 216740 | T43: =IF(W43<>"",IF(E43<>"",E43,($I$9-SUM($T$25:T42))*V43*W43/SUMPRODUCT($W43:$W$55,$V43:$V$55)),"") -> 37 | U43: =IF(W43<>"",IF($I$12<>"",IF(G43<>"",G43,($I$9/$I$12-SUM($U$25:U42))*V43*W43/SUMPRODUCT($W43:$W$55,$V43:$V$55)),""),"") -> 19 | V43: 1 | W43: 1
A44: Рогалевич, Уразгильдеева | B44: 45858 | C44: ср | D44: =126520+36309+14265+26550 -> 203644 | E44: 22 | F44: =IF(AND(E44<>"",E44<>0),D44/E44,"") -> 9256.5455 | G44: 11 | H44: =IF(AND(G44<>"",G44<>0),D44/G44,"") -> 18513.091 | I44: 99 | J44: =IF(AND(G44<>"",G44<>0),E44/G44,"") -> 2 | K44: 126520 | L44: 36309 | N44: =IF(AND(I44<>"",I44<>0),G44/I44,"") -> 0.11111111 | O44: =D44/P44 -> 1.181239 | P44: =$I$8*V44*W44/SUMPRODUCT($W$25:$W$55,$V$25:$V$55) -> 172398.64 | Q44: =$I$9*V44*W44/SUMPRODUCT($W$25:$W$55,$V$25:$V$55) -> 28.733107 | R44: =IF($I$12="","",Q44/$I$12) -> 16.901828 | S44: =IF(W44<>"",IF(D44<>"",D44,($I$8-SUM($S$25:S43))*V44*W44/SUMPRODUCT($W44:$W$55,$V44:$V$55)),"") -> 203644 | T44: =IF(W44<>"",IF(E44<>"",E44,($I$9-SUM($T$25:T43))*V44*W44/SUMPRODUCT($W44:$W$55,$V44:$V$55)),"") -> 22 | U44: =IF(W44<>"",IF($I$12<>"",IF(G44<>"",G44,($I$9/$I$12-SUM($U$25:U43))*V44*W44/SUMPRODUCT($W44:$W$55,$V44:$V$55)),""),"") -> 11 | V44: 1 | W44: 1
A45: Уразгильдеева,Яковенко | B45: 45859 | C45: чт | D45: =28480+18503+6392+95543+45615+18974 -> 213507 | E45: 40 | F45: =IF(AND(E45<>"",E45<>0),D45/E45,"") -> 5337.675 | G45: 20 | H45: =IF(AND(G45<>"",G45<>0),D45/G45,"") -> 10675.35 | I45: 145 | J45: =IF(AND(G45<>"",G45<>0),E45/G45,"") -> 2 | K45: 28480 | L45: 18503 | M45: 6392 | N45: =IF(AND(I45<>"",I45<>0),G45/I45,"") -> 0.13793103 | O45: =D45/P45 -> 1.2384494 | P45: =$I$8*V45*W45/SUMPRODUCT($W$25:$W$55,$V$25:$V$55) -> 172398.64 | Q45: =$I$9*V45*W45/SUMPRODUCT($W$25:$W$55,$V$25:$V$55) -> 28.733107 | R45: =IF($I$12="","",Q45/$I$12) -> 16.901828 | S45: =IF(W45<>"",IF(D45<>"",D45,($I$8-SUM($S$25:S44))*V45*W45/SUMPRODUCT($W45:$W$55,$V45:$V$55)),"") -> 213507 | T45: =IF(W45<>"",IF(E45<>"",E45,($I$9-SUM($T$25:T44))*V45*W45/SUMPRODUCT($W45:$W$55,$V45:$V$55)),"") -> 40 | U45: =IF(W45<>"",IF($I$12<>"",IF(G45<>"",G45,($I$9/$I$12-SUM($U$25:U44))*V45*W45/SUMPRODUCT($W45:$W$55,$V45:$V$55)),""),"") -> 20 | V45: 1 | W45: 1
A46: Рогалевич,Яковенко | B46: 45860 | C46: пт | D46: =14990+87860+23648 -> 126498 | E46: 23 | F46: =IF(AND(E46<>"",E46<>0),D46/E46,"") -> 5499.913 | G46: 6 | H46: =IF(AND(G46<>"",G46<>0),D46/G46,"") -> 21083 | I46: 72 | J46: =IF(AND(G46<>"",G46<>0),E46/G46,"") -> 3.8333333 | K46: 14990 | N46: =IF(AND(I46<>"",I46<>0),G46/I46,"") -> 0.083333333 | O46: =D46/P46 -> 0.73375287 | P46: =$I$8*V46*W46/SUMPRODUCT($W$25:$W$55,$V$25:$V$55) -> 172398.64 | Q46: =$I$9*V46*W46/SUMPRODUCT($W$25:$W$55,$V$25:$V$55) -> 28.733107 | R46: =IF($I$12="","",Q46/$I$12) -> 16.901828 | S46: =IF(W46<>"",IF(D46<>"",D46,($I$8-SUM($S$25:S45))*V46*W46/SUMPRODUCT($W46:$W$55,$V46:$V$55)),"") -> 126498 | T46: =IF(W46<>"",IF(E46<>"",E46,($I$9-SUM($T$25:T45))*V46*W46/SUMPRODUCT($W46:$W$55,$V46:$V$55)),"") -> 23 | U46: =IF(W46<>"",IF($I$12<>"",IF(G46<>"",G46,($I$9/$I$12-SUM($U$25:U45))*V46*W46/SUMPRODUCT($W46:$W$55,$V46:$V$55)),""),"") -> 6 | V46: 1 | W46: 1
A47: Рогалевич,Уразгильдеева | B47: 45861 | C47: сб | D47: =13992+9903+40123+37729 -> 101747 | E47: 17 | F47: =IF(AND(E47<>"",E47<>0),D47/E47,"") -> 5985.1176 | G47: 11 | H47: =IF(AND(G47<>"",G47<>0),D47/G47,"") -> 9249.7273 | I47: 108 | J47: =IF(AND(G47<>"",G47<>0),E47/G47,"") -> 1.5454545 | K47: 13992 | L47: 9903 | N47: =IF(AND(I47<>"",I47<>0),G47/I47,"") -> 0.10185185 | O47: =D47/P47 -> 0.59018446 | P47: =$I$8*V47*W47/SUMPRODUCT($W$25:$W$55,$V$25:$V$55) -> 172398.64 | Q47: =$I$9*V47*W47/SUMPRODUCT($W$25:$W$55,$V$25:$V$55) -> 28.733107 | R47: =IF($I$12="","",Q47/$I$12) -> 16.901828 | S47: =IF(W47<>"",IF(D47<>"",D47,($I$8-SUM($S$25:S46))*V47*W47/SUMPRODUCT($W47:$W$55,$V47:$V$55)),"") -> 101747 | T47: =IF(W47<>"",IF(E47<>"",E47,($I$9-SUM($T$25:T46))*V47*W47/SUMPRODUCT($W47:$W$55,$V47:$V$55)),"") -> 17 | U47: =IF(W47<>"",IF($I$12<>"",IF(G47<>"",G47,($I$9/$I$12-SUM($U$25:U46))*V47*W47/SUMPRODUCT($W47:$W$55,$V47:$V$55)),""),"") -> 11 | V47: 1 | W47: 1
A48: Рогалевич,Уразгильдеева | B48: 45862 | C48: вс | D48: =7903+36349 -> 44252 | E48: 7 | F48: =IF(AND(E48<>"",E48<>0),D48/E48,"") -> 6321.7143 | G48: 4 | H48: =IF(AND(G48<>"",G48<>0),D48/G48,"") -> 11063 | I48: 89 | J48: =IF(AND(G48<>"",G48<>0),E48/G48,"") -> 1.75 | K48: 22980 | L48: 7903 | N48: =IF(AND(I48<>"",I48<>0),G48/I48,"") -> 0.04494382 | O48: =D48/P48 -> 0.25668415 | P48: =$I$8*V48*W48/SUMPRODUCT($W$25:$W$55,$V$25:$V$55) -> 172398.64 | Q48: =$I$9*V48*W48/SUMPRODUCT($W$25:$W$55,$V$25:$V$55) -> 28.733107 | R48: =IF($I$12="","",Q48/$I$12) -> 16.901828 | S48: =IF(W48<>"",IF(D48<>"",D48,($I$8-SUM($S$25:S47))*V48*W48/SUMPRODUCT($W48:$W$55,$V48:$V$55)),"") -> 44252 | T48: =IF(W48<>"",IF(E48<>"",E48,($I$9-SUM($T$25:T47))*V48*W48/SUMPRODUCT($W48:$W$55,$V48:$V$55)),"") -> 7 | U48: =IF(W48<>"",IF($I$12<>"",IF(G48<>"",G48,($I$9/$I$12-SUM($U$25:U47))*V48*W48/SUMPRODUCT($W48:$W$55,$V48:$V$55)),""),"") -> 4 | V48: 1 | W48: 1
A49: Рогалевич,Яковенко | B49: 45863 | C49: пн | D49: =16992+28726+33172+18966+24262 -> 122118 | E49: 16 | F49: =IF(AND(E49<>"",E49<>0),D49/E49,"") -> 7632.375 | G49: 12 | H49: =IF(AND(G49<>"",G49<>0),D49/G49,"") -> 10176.5 | I49: 78 | J49: =IF(AND(G49<>"",G49<>0),E49/G49,"") -> 1.3333333 | K49: 16992 | L49: 28726 | M49: 33172 | N49: =IF(AND(I49<>"",I49<>0),G49/I49,"") -> 0.15384615 | O49: =D49/P49 -> 0.70834664 | P49: =$I$8*V49*W49/SUMPRODUCT($W$25:$W$55,$V$25:$V$55) -> 172398.64 | Q49: =$I$9*V49*W49/SUMPRODUCT($W$25:$W$55,$V$25:$V$55) -> 28.733107 | R49: =IF($I$12="","",Q49/$I$12) -> 16.901828 | S49: =IF(W49<>"",IF(D49<>"",D49,($I$8-SUM($S$25:S48))*V49*W49/SUMPRODUCT($W49:$W$55,$V49:$V$55)),"") -> 122118 | T49: =IF(W49<>"",IF(E49<>"",E49,($I$9-SUM($T$25:T48))*V49*W49/SUMPRODUCT($W49:$W$55,$V49:$V$55)),"") -> 16 | U49: =IF(W49<>"",IF($I$12<>"",IF(G49<>"",G49,($I$9/$I$12-SUM($U$25:U48))*V49*W49/SUMPRODUCT($W49:$W$55,$V49:$V$55)),""),"") -> 12 | V49: 1 | W49: 1
A50: Рогалевич,Яковенко | B50: 45864 | C50: вт | D50: =8692+54126+32441+15374-6203 -> 104430 | E50: 22 | F50: =IF(AND(E50<>"",E50<>0),D50/E50,"") -> 4746.8182 | G50: 10 | H50: =IF(AND(G50<>"",G50<>0),D50/G50,"") -> 10443 | I50: 98 | J50: =IF(AND(G50<>"",G50<>0),E50/G50,"") -> 2.2 | L50: -6203 | M50: 8692 | N50: =IF(AND(I50<>"",I50<>0),G50/I50,"") -> 0.10204082 | O50: =D50/P50 -> 0.60574722 | P50: =$I$8*V50*W50/SUMPRODUCT($W$25:$W$55,$V$25:$V$55) -> 172398.64 | Q50: =$I$9*V50*W50/SUMPRODUCT($W$25:$W$55,$V$25:$V$55) -> 28.733107 | R50: =IF($I$12="","",Q50/$I$12) -> 16.901828 | S50: =IF(W50<>"",IF(D50<>"",D50,($I$8-SUM($S$25:S49))*V50*W50/SUMPRODUCT($W50:$W$55,$V50:$V$55)),"") -> 104430 | T50: =IF(W50<>"",IF(E50<>"",E50,($I$9-SUM($T$25:T49))*V50*W50/SUMPRODUCT($W50:$W$55,$V50:$V$55)),"") -> 22 | U50: =IF(W50<>"",IF($I$12<>"",IF(G50<>"",G50,($I$9/$I$12-SUM($U$25:U49))*V50*W50/SUMPRODUCT($W50:$W$55,$V50:$V$55)),""),"") -> 10 | V50: 1 | W50: 1
A51: Яковенко ,Уразгильдеева | B51: 45865 | C51: ср | D51: 61467 | E51: 14 | F51: =IF(AND(E51<>"",E51<>0),D51/E51,"") -> 4390.5 | G51: 10 | H51: =IF(AND(G51<>"",G51<>0),D51/G51,"") -> 6146.7 | I51: 88 | J51: =IF(AND(G51<>"",G51<>0),E51/G51,"") -> 1.4 | N51: =IF(AND(I51<>"",I51<>0),G51/I51,"") -> 0.11363636 | O51: =D51/P51 -> 0.35653993 | P51: =$I$8*V51*W51/SUMPRODUCT($W$25:$W$55,$V$25:$V$55) -> 172398.64 | Q51: =$I$9*V51*W51/SUMPRODUCT($W$25:$W$55,$V$25:$V$55) -> 28.733107 | R51: =IF($I$12="","",Q51/$I$12) -> 16.901828 | S51: =IF(W51<>"",IF(D51<>"",D51,($I$8-SUM($S$25:S50))*V51*W51/SUMPRODUCT($W51:$W$55,$V51:$V$55)),"") -> 61467 | T51: =IF(W51<>"",IF(E51<>"",E51,($I$9-SUM($T$25:T50))*V51*W51/SUMPRODUCT($W51:$W$55,$V51:$V$55)),"") -> 14 | U51: =IF(W51<>"",IF($I$12<>"",IF(G51<>"",G51,($I$9/$I$12-SUM($U$25:U50))*V51*W51/SUMPRODUCT($W51:$W$55,$V51:$V$55)),""),"") -> 10 | V51: 1 | W51: 1
A52: Рогалевич,Уразгильдеева | B52: 45866 | C52: чт | D52: =48843+2203 -> 51046 | E52: 8 | F52: =IF(AND(E52<>"",E52<>0),D52/E52,"") -> 6380.75 | G52: 7 | H52: =IF(AND(G52<>"",G52<>0),D52/G52,"") -> 7292.2857 | I52: 71 | J52: =IF(AND(G52<>"",G52<>0),E52/G52,"") -> 1.1428571 | K52: 7490 | L52: 2203 | M52: 8892 | N52: =IF(AND(I52<>"",I52<>0),G52/I52,"") -> 0.098591549 | O52: =D52/P52 -> 0.46264502 | P52: =$I$8*V52*W52/SUMPRODUCT($W$25:$W$55,$V$25:$V$55) -> 110335.13 | Q52: =$I$9*V52*W52/SUMPRODUCT($W$25:$W$55,$V$25:$V$55) -> 18.389189 | R52: =IF($I$12="","",Q52/$I$12) -> 10.81717 | S52: =IF(W52<>"",IF(D52<>"",D52,($I$8-SUM($S$25:S51))*V52*W52/SUMPRODUCT($W52:$W$55,$V52:$V$55)),"") -> 51046 | T52: =IF(W52<>"",IF(E52<>"",E52,($I$9-SUM($T$25:T51))*V52*W52/SUMPRODUCT($W52:$W$55,$V52:$V$55)),"") -> 8 | U52: =IF(W52<>"",IF($I$12<>"",IF(G52<>"",G52,($I$9/$I$12-SUM($U$25:U51))*V52*W52/SUMPRODUCT($W52:$W$55,$V52:$V$55)),""),"") -> 7 | V52: 0.8 | W52: 0.8
A53: Рогалевич,Яковенко | B53: 45867 | C53: пт | D53: =55394+L53 -> 65297 | E53: 12 | F53: =IF(AND(E53<>"",E53<>0),D53/E53,"") -> 5441.4167 | G53: 6 | H53: =IF(AND(G53<>"",G53<>0),D53/G53,"") -> 10882.833 | I53: 56 | J53: =IF(AND(G53<>"",G53<>0),E53/G53,"") -> 2 | L53: 9903 | N53: =IF(AND(I53<>"",I53<>0),G53/I53,"") -> 0.10714286 | O53: =D53/P53 -> 0.59180606 | P53: =$I$8*V53*W53/SUMPRODUCT($W$25:$W$55,$V$25:$V$55) -> 110335.13 | Q53: =$I$9*V53*W53/SUMPRODUCT($W$25:$W$55,$V$25:$V$55) -> 18.389189 | R53: =IF($I$12="","",Q53/$I$12) -> 10.81717 | S53: =IF(W53<>"",IF(D53<>"",D53,($I$8-SUM($S$25:S52))*V53*W53/SUMPRODUCT($W53:$W$55,$V53:$V$55)),"") -> 65297 | T53: =IF(W53<>"",IF(E53<>"",E53,($I$9-SUM($T$25:T52))*V53*W53/SUMPRODUCT($W53:$W$55,$V53:$V$55)),"") -> 12 | U53: =IF(W53<>"",IF($I$12<>"",IF(G53<>"",G53,($I$9/$I$12-SUM($U$25:U52))*V53*W53/SUMPRODUCT($W53:$W$55,$V53:$V$55)),""),"") -> 6 | V53: 0.8 | W53: 0.8
A54: Рогалевич,Уразгильдеева | B54: 45868 | C54: сб | D54: =23402+L54 -> 46608 | E54: 10 | F54: =IF(AND(E54<>"",E54<>0),D54/E54,"") -> 4660.8 | G54: 7 | H54: =IF(AND(G54<>"",G54<>0),D54/G54,"") -> 6658.2857 | I54: 50 | J54: =IF(AND(G54<>"",G54<>0),E54/G54,"") -> 1.4285714 | L54: 23206 | N54: =IF(AND(I54<>"",I54<>0),G54/I54,"") -> 0.14 | O54: =D54/P54 -> 0.42242212 | P54: =$I$8*V54*W54/SUMPRODUCT($W$25:$W$55,$V$25:$V$55) -> 110335.13 | Q54: =$I$9*V54*W54/SUMPRODUCT($W$25:$W$55,$V$25:$V$55) -> 18.389189 | R54: =IF($I$12="","",Q54/$I$12) -> 10.81717 | S54: =IF(W54<>"",IF(D54<>"",D54,($I$8-SUM($S$25:S53))*V54*W54/SUMPRODUCT($W54:$W$55,$V54:$V$55)),"") -> 46608 | T54: =IF(W54<>"",IF(E54<>"",E54,($I$9-SUM($T$25:T53))*V54*W54/SUMPRODUCT($W54:$W$55,$V54:$V$55)),"") -> 10 | U54: =IF(W54<>"",IF($I$12<>"",IF(G54<>"",G54,($I$9/$I$12-SUM($U$25:U53))*V54*W54/SUMPRODUCT($W54:$W$55,$V54:$V$55)),""),"") -> 7 | V54: 0.8 | W54: 0.8
A55: Рогалевич,Уразгильдеева | B55: 45869 | C55: вс | D55: =63317+L55 -> 85223 | E55: 16 | F55: =IF(AND(E55<>"",E55<>0),D55/E55,"") -> 5326.4375 | G55: 11 | H55: =IF(AND(G55<>"",G55<>0),D55/G55,"") -> 7747.5455 | I55: 71 | J55: =IF(AND(G55<>"",G55<>0),E55/G55,"") -> 1.4545455 | L55: 21906 | M55: 14790 | N55: =IF(AND(I55<>"",I55<>0),G55/I55,"") -> 0.15492958 | O55: =D55/P55 -> 0.7724013 | P55: =$I$8*V55*W55/SUMPRODUCT($W$25:$W$55,$V$25:$V$55) -> 110335.13 | Q55: =$I$9*V55*W55/SUMPRODUCT($W$25:$W$55,$V$25:$V$55) -> 18.389189 | R55: =IF($I$12="","",Q55/$I$12) -> 10.81717 | S55: =IF(W55<>"",IF(D55<>"",D55,($I$8-SUM($S$25:S54))*V55*W55/SUMPRODUCT($W55:$W$55,$V55:$V$55)),"") -> 85223 | T55: =IF(W55<>"",IF(E55<>"",E55,($I$9-SUM($T$25:T54))*V55*W55/SUMPRODUCT($W55:$W$55,$V55:$V$55)),"") -> 16 | U55: =IF(W55<>"",IF($I$12<>"",IF(G55<>"",G55,($I$9/$I$12-SUM($U$25:U54))*V55*W55/SUMPRODUCT($W55:$W$55,$V55:$V$55)),""),"") -> 11 | V55: 0.8 | W55: 0.8
B56: итого | D56: =SUM(D25:D55) -> 3881454 | E56: =SUM(E25:E55) -> 672 | F56: =IF(AND(E56<>"", E56<>0), D56/E56, "") -> 5775.9732 | G56: =SUM(G25:G55) -> 376 | H56: =IF(AND(G56<>"", G56<>0), D56/G56, "") -> 10323.016 | I56: =SUM(I25:I55) -> 2645 | J56: =E56/G56 -> 1.787234 | K56: =SUM(K25:K55) -> 639010.35 | L56: =SUM(L25:L55) -> 420152 | M56: =SUM(M25:M55) -> 296296.31 | N56: =IF(AND(I56<>"", I56<>0), G56/I56, "") -> 0.14215501 | O56: =D56/P56 -> 0.82581316 | P56: =SUM(P25:P55) -> 4700160 | Q56: =SUM(Q25:Q55) -> 783.36 | R56: =SUM(R25:R55) -> 460.8 | S56: =SUM(S25:S55) -> 3881454 | T56: =SUM(T25:T55) -> 672 | U56: =SUM(U25:U55) -> 376
D57: =SUMIF(D25:D55,"",P25:P55)+D56 -> 3881454 | I57: =I56/J14 -> 85.322581
D58: ='Рогалевич И. Е. '!J8+'Уразгильдеева Е. Р. '!J8+'Доп сотрудник'!J8+'Яковенко А. К. '!J8 -> 3881454 | E58: ='Рогалевич И. Е. '!E54+'Уразгильдеева Е. Р. '!E50+'Яковенко А. К. '!E49 -> 672 | G58: ='Рогалевич И. Е. '!G54+'Уразгильдеева Е. Р. '!G50+'Яковенко А. К. '!G49 -> 377 | I58: ='Рогалевич И. Е. '!I54+'Уразгильдеева Е. Р. '!I50+'Яковенко А. К. '!I49 -> 2645 | K58: ='Рогалевич И. Е. '!K54+'Уразгильдеева Е. Р. '!K50+'Яковенко А. К. '!K49 -> 639010.35 | L58: ='Рогалевич И. Е. '!L54+'Уразгильдеева Е. Р. '!L50+'Яковенко А. К. '!L49 -> 420152 | M58: ='Рогалевич И. Е. '!M54+'Уразгильдеева Е. Р. '!M50+'Яковенко А. К. '!M49 -> 296296.31
D60: 3881457

Sheet Конкурс
A1: Сотрудник | B1: Длина чека | C1: КВП
D2: 11 | E2: 12 | F2: 13 | G2: 14 | H2: 15 | I2: 16 | J2: 17 | K2: 18 | L2: 19 | M2: 20 | N2: 21 | O2: 22 | P2: 23 | Q2: 24 | R2: 25 | S2: 26 | T2: 27 | U2: 28 | V2: 29 | W2: 30 | X2: 31 | Y2: Итого
A3: =График!B29 -> Рогалевич Ирина | B3: ='Рогалевич И. Е. '!J12 -> 1.8355263 | C3: ='Рогалевич И. Е. '!K8 -> 0.93589757 | D3: 2 | E3: 1 | F3: 1 | G3: 0 | H3: 1 | I3: 1 | J3: 0 | K3: 0 | L3: 2 | M3: 0 | N3: 0 | O3: 1 | P3: 1 | Q3: 0 | R3: 1 | S3: 0 | T3: 1 | U3: 0 | V3: 0 | W3: 1 | X3: 2 | Y3: =SUM(D3:X3) -> 15
A4: =График!B28 -> Уразгильдеева Екатерина | B4: ='Уразгильдеева Е. Р. '!J12 -> 1.5824176 | C4: ='Уразгильдеева Е. Р. '!K8 -> 0.65490658 | D4: 0 | E4: 0 | F4: 1 | G4: 0 | H4: 0 | I4: 1 | J4: 2 | K4: 0 | L4: 0 | M4: 0 | N4: 1 | O4: 0 | P4: 0 | Q4: 0 | R4: 0 | S4: 0 | T4: 0 | U4: 0 | V4: 0 | W4: 0 | X4: 0 | Y4: =SUM(D4:X4) -> 5
A5: =График!B27 -> Яковенко Алина | B5: ='Яковенко А. К. '!J12 -> 1.858209 | C5: ='Яковенко А. К. '!K8 -> 0.8645136 | D5: 1 | E5: 1 | F5: 0 | G5: 1 | H5: 0 | I5: 0 | J5: 0 | K5: 0 | L5: 0 | M5: 0 | N5: 1 | O5: 1 | P5: 0 | Q5: 0 | R5: 0 | S5: 0 | T5: 1 | U5: 0 | V5: 0 | W5: 0 | X5: 0 | Y5: =SUM(D5:X5) -> 6

Sheet Св. по пок.
A1: 1-20.08
A2: Показатель | D2: ='Ялта, Ленина, 18'!I3 -> ул. Набережная Ленина, 18 | G2: =График!B29 -> Рогалевич Ирина | J2: =График!B28 -> Уразгильдеева Екатерина | M2: =График!B27 -> Яковенко Алина
D3: Факт | F3: Прогноз | G3: Факт | I3: Прогноз | J3: Факт | L3: Прогноз | M3: Факт | O3: Прогноз
A4: Выручка | D4: ='Ялта, Ленина, 18'!K8 -> 0.82581316 | E4: ='Ялта, Ленина, 18'!J8 -> 3881454 | F4: ='Ялта, Ленина, 18'!M8 -> 0.82581316 | G4: ='Рогалевич И. Е. '!K8 -> 0.93589757 | H4: ='Рогалевич И. Е. '!J8 -> 1621279.7 | I4: ='Рогалевич И. Е. '!M8 -> 0.93589757 | J4: ='Уразгильдеева Е. Р. '!K8 -> 0.65490658 | K4: ='Уразгильдеева Е. Р. '!J8 -> 954702.3 | L4: ='Уразгильдеева Е. Р. '!M8 -> 0.65490658 | M4: ='Яковенко А. К. '!K8 -> 0.8645136 | N4: ='Яковенко А. К. '!J8 -> 1305472 | O4: ='Яковенко А. К. '!M8 -> 0.8645136
A5: Кол-во изделий | D5: ='Ялта, Ленина, 18'!K9 -> 0.85784314 | E5: ='Ялта, Ленина, 18'!J9 -> 672 | F5: ='Ялта, Ленина, 18'!M9 -> 0.85784314 | G5: ='Рогалевич И. Е. '!K9 -> 0.96633081 | H5: ='Рогалевич И. Е. '!J9 -> 279 | I5: ='Рогалевич И. Е. '!M9 -> 0.96633081 | J5: ='Уразгильдеева Е. Р. '!K9 -> 0.59268663 | K5: ='Уразгильдеева Е. Р. '!J9 -> 144 | L5: ='Уразгильдеева Е. Р. '!M9 -> 0.59268663 | M5: ='Яковенко А. К. '!K9 -> 0.98936118 | N5: ='Яковенко А. К. '!J9 -> 249 | O5: ='Яковенко А. К. '!M9 -> 0.98936118
A6: Средний чек | D6: ='Ялта, Ленина, 18'!K10 -> 1.0120604 | E6: ='Ялта, Ленина, 18'!J10 -> 10323.016 | F6: ='Ялта, Ленина, 18'!M10 -> 1.0120604 | G6: ='Рогалевич И. Е. '!K10 -> 1.045717 | H6: ='Рогалевич И. Е. '!J10 -> 10666.314 | I6: ='Рогалевич И. Е. '!M10 -> 1.045717 | J6: ='Уразгильдеева Е. Р. '!K10 -> 1.0285524 | K6: ='Уразгильдеева Е. Р. '!J10 -> 10491.234 | L6: ='Уразгильдеева Е. Р. '!M10 -> 1.0285524 | M6: ='Яковенко А. К. '!K10 -> 0.95513023 | N6: ='Яковенко А. К. '!J10 -> 9742.3284 | O6: ='Яковенко А. К. '!M10 -> 0.95513023
A7: Средняя стоимость изделия | D7: ='Ялта, Ленина, 18'!K11 -> 0.9626622 | E7: ='Ялта, Ленина, 18'!J11 -> 5775.9732 | F7: ='Ялта, Ленина, 18'!M11 -> 0.9626622 | G7: ='Рогалевич И. Е. '!K11 -> 0.96850639 | H7: ='Рогалевич И. Е. '!J11 -> 5811.0384 | I7: ='Рогалевич И. Е. '!M11 -> 0.96850639 | J7: ='Уразгильдеева Е. Р. '!K11 -> 1.1049795 | K7: ='Уразгильдеева Е. Р. '!J11 -> 6629.8771 | L7: ='Уразгильдеева Е. Р. '!M11 -> 1.1049795 | M7: ='Яковенко А. К. '!K11 -> 0.87380991 | N7: ='Яковенко А. К. '!J11 -> 5242.8594 | O7: ='Яковенко А. К. '!M11 -> 0.87380991
A8: Длина чека | D8: ='Ялта, Ленина, 18'!K12 -> 1.0513141 | E8: ='Ялта, Ленина, 18'!J12 -> 1.787234 | F8: ='Ялта, Ленина, 18'!M12 -> 1.0513141 | G8: ='Рогалевич И. Е. '!K12 -> 1.0797214 | H8: ='Рогалевич И. Е. '!J12 -> 1.8355263 | I8: ='Рогалевич И. Е. '!M12 -> 1.0797214 | J8: ='Уразгильдеева Е. Р. '!K12 -> 0.93083387 | K8: ='Уразгильдеева Е. Р. '!J12 -> 1.5824176 | L8: ='Уразгильдеева Е. Р. '!M12 -> 0.93083387 | M8: ='Яковенко А. К. '!K12 -> 1.0930641 | N8: ='Яковенко А. К. '!J12 -> 1.858209 | O8: ='Яковенко А. К. '!M12 -> 1.0930641
A9: Кол-во чеков | D9: ='Ялта, Ленина, 18'!K13 -> 0.81597222 | E9: ='Ялта, Ленина, 18'!J13 -> 376 | F9: ='Ялта, Ленина, 18'!M13 -> 0.81597222 | G9: ='Рогалевич И. Е. '!K13 -> 0.89498166 | H9: ='Рогалевич И. Е. '!J13 -> 152 | I9: ='Рогалевич И. Е. '!M13 -> 0.89498166 | J9: ='Уразгильдеева Е. Р. '!K13 -> 0.63672654 | K9: ='Уразгильдеева Е. Р. '!J13 -> 91 | L9: ='Уразгильдеева Е. Р. '!M13 -> 0.63672654 | M9: ='Яковенко А. К. '!K13 -> 0.90512641 | N9: ='Яковенко А. К. '!J13 -> 134 | O9: ='Яковенко А. К. '!M13 -> 0.90512641
A10: Кол-во смен план/отработано | D10: ='Ялта, Ленина, 18'!K14 -> 1 | E10: ='Ялта, Ленина, 18'!J14 -> 31 | G10: ='Рогалевич И. Е. '!K14 -> 1 | H10: ='Рогалевич И. Е. '!J14 -> 26 | J10: ='Уразгильдеева Е. Р. '!K14 -> 1 | K10: ='Уразгильдеева Е. Р. '!J14 -> 18 | M10: ='Яковенко А. К. '!K14 -> 1 | N10: ='Яковенко А. К. '!J14 -> 21
A11: Средние продажи в смену | D11: ='Ялта, Ленина, 18'!K15 -> 0.82581316 | E11: ='Ялта, Ленина, 18'!J15 -> 125208.19 | F11: ='Ялта, Ленина, 18'!M15 -> 0.82581316 | G11: ='Рогалевич И. Е. '!K15 -> 0.41127627 | H11: ='Рогалевич И. Е. '!J15 -> 62356.912 | I11: ='Рогалевич И. Е. '!M15 -> 0.41127627 | J11: ='Уразгильдеева Е. Р. '!K15 -> 0.3498199 | K11: ='Уразгильдеева Е. Р. '!J15 -> 53039.017 | L11: ='Уразгильдеева Е. Р. '!M15 -> 0.3498199 | M11: ='Яковенко А. К. '!K15 -> 0.41001271 | N11: ='Яковенко А. К. '!J15 -> 62165.333 | O11: ='Яковенко А. К. '!M15 -> 0.41001271
A12: Трафик | D12: ='Ялта, Ленина, 18'!K17 -> 1.0332031 | E12: ='Ялта, Ленина, 18'!J17 -> 2645 | F12: ='Ялта, Ленина, 18'!M17 -> 1.0332031 | G12: ='Рогалевич И. Е. '!K17 -> 1.0736247 | H12: ='Рогалевич И. Е. '!J17 -> 1013 | I12: ='Рогалевич И. Е. '!M17 -> 1.0736247 | J12: ='Уразгильдеева Е. Р. '!K17 -> 0.92444297 | K12: ='Уразгильдеева Е. Р. '!J17 -> 734 | L12: ='Уразгильдеева Е. Р. '!M17 -> 0.92444297 | M12: ='Яковенко А. К. '!K17 -> 1.0918256 | N12: ='Яковенко А. К. '!J17 -> 898 | O12: ='Яковенко А. К. '!M17 -> 1.0918256
A13: UNOde50 | D13: ='Ялта, Ленина, 18'!S19 -> 0.72614812 | E13: ='Ялта, Ленина, 18'!T18 -> 639010.35 | F13: ='Ялта, Ленина, 18'!T19 -> 0.72614812 | G13: ='Рогалевич И. Е. '!S19 -> 0.98418521 | H13: ='Рогалевич И. Е. '!T18 -> 319210 | I13: ='Рогалевич И. Е. '!T19 -> 0.98418521 | J13: ='Уразгильдеева Е. Р. '!S19 -> 0.82748513 | K13: ='Уразгильдеева Е. Р. '!T18 -> 225849.35 | L13: ='Уразгильдеева Е. Р. '!T19 -> 0.82748513 | M13: ='Яковенко А. К. '!S19 -> 0.33230406 | N13: ='Яковенко А. К. '!T18 -> 93951 | O13: ='Яковенко А. К. '!T19 -> 0.33230406
A14: IS | D14: ='Ялта, Ленина, 18'!S13 -> 0.55283158 | E14: ='Ялта, Ленина, 18'!T12 -> 420152 | F14: ='Ялта, Ленина, 18'!T13 -> 0.55283158 | G14: ='Рогалевич И. Е. '!S13 -> 0.54286642 | H14: ='Рогалевич И. Е. '!T12 -> 152063 | I14: ='Рогалевич И. Е. '!T13 -> 0.54286642 | J14: ='Уразгильдеева Е. Р. '!S13 -> 0.65226299 | K14: ='Уразгильдеева Е. Р. '!T12 -> 153749 | L14: ='Уразгильдеева Е. Р. '!T13 -> 0.65226299 | M14: ='Яковенко А. К. '!S13 -> 0.46827558 | N14: ='Яковенко А. К. '!T12 -> 114340 | O14: ='Яковенко А. К. '!T13 -> 0.46827558
A15: ='Ялта, Ленина, 18'!M23 -> Agafi | D15: ='Ялта, Ленина, 18'!V13 -> 0.64412241 | E15: ='Ялта, Ленина, 18'!W12 -> 296296.31 | F15: ='Ялта, Ленина, 18'!W13 -> 0.64412241 | G15: ='Рогалевич И. Е. '!V13 -> 0.50266299 | H15: ='Рогалевич И. Е. '!W12 -> 85222 | I15: ='Рогалевич И. Е. '!W13 -> 0.50266299 | J15: ='Уразгильдеева Е. Р. '!V13 -> 0.38439655 | K15: ='Уразгильдеева Е. Р. '!W12 -> 54842 | L15: ='Уразгильдеева Е. Р. '!W13 -> 0.38439655 | M15: ='Яковенко А. К. '!V13 -> 1.0571337 | N15: ='Яковенко А. К. '!W12 -> 156232.31 | O15: ='Яковенко А. К. '!W13 -> 1.0571337
A16: Отклонение от плана | D16: ='Ялта, Ленина, 18'!J16 -> -818706 | G16: ='Рогалевич И. Е. '!N8 -> -111046.31 | J16: ='Уразгильдеева Е. Р. '!N8 -> -503066.38 | M16: ='Яковенко А. К. '!N8 -> -204593.31

Sheet План на день
A1: Выручка | D1: 172399
A2: Кол-во изделий | D2: =D1/D4 -> 28.733167
A3: Средний чек | D3: =D4*D5 -> 10200
A4: Средняя стоимость изделия | D4: ='Ялта, Ленина, 18'!I11 -> 6000
A5: Длина чека | D5: ='Ялта, Ленина, 18'!I12 -> 1.7
A6: Кол-во чеков | D6: =IF(D5<>0,D2/D5,"") -> 16.901863
A7: Конверсия | D7: ='Ялта, Ленина, 18'!I20 -> 0.18
A8: IS | D8: =('Ялта, Ленина, 18'!S12-'Ялта, Ленина, 18'!T12)/('Ялта, Ленина, 18'!I14-'Ялта, Ленина, 18'!J14) -> #DIV/0!
A9: UNOde50 | D9: =('Ялта, Ленина, 18'!S18-'Ялта, Ленина, 18'!T18)/('Ялта, Ленина, 18'!I14-'Ялта, Ленина, 18'!J14) -> #DIV/0!
A10: ='Ялта, Ленина, 18'!M23 -> Agafi | D10: =('Ялта, Ленина, 18'!V12-'Ялта, Ленина, 18'!W12)/('Ялта, Ленина, 18'!I14-'Ялта, Ленина, 18'!J14) -> #DIV/0!

Sheet Рогалевич И. Е. 
B1: =TODAY()-1 -> 45909
B2: (отчетная дата) | J2: ЕЖЕДНЕВНЫЙ ОТЧЕТ О ПРОДАЖАХ
B3: Осталось до выполнения плана!!! | J3: =График!B29 -> Рогалевич Ирина
C4: =I8-D54 -> 111046.31 | E4: =IF(I8<>0,C4/I8,0) -> 0.064102431
F6: Целевые показатели
F7: Показатель | I7: План | J7: Факт | K7: % выполнения | L7: Прогноз выполнения | M7: % выполнения по прогнозу | N7: Отклонение | O7: Факт аналогичного месяца прошлого года | P7: Отклонение LFL
F8: Выручка | I8: ='Ялта, Ленина, 18'!I8/График!AJ31*График!AJ29 -> 1732326 | J8: =D54 -> 1621279.7 | K8: =IF(AND(I8<>"",I8<>0,J8<>""),J8/I8,"") -> 0.93589757 | L8: =IF(SUMIF($D$25:$D$53,">=0",$P$25:$P$53)<>0,I8*D54/SUMIF($D$25:$D$53,">=0",$P$25:$P$53),0) -> 1621279.7 | M8: =IF(AND(I8<>"",I8<>0,L8<>"",L8<>0),L8/I8,"") -> 0.93589757 | N8: =IF(AND(J8<>0,J8<>"",I8<>0,I8<>""),L8-I8,"") -> -111046.31 | P8: =IF(AND(O8<>"",O8<>0,L8<>"",L8<>0),-O8+L8,"") | Q8: =IF(AND(P8<>"",P8<>0,O8<>0,O8<>""),P8/O8,"")
F9: Кол-во изделий | I9: =I8/I11 -> 288.721 | J9: =E54 -> 279 | K9: =IF(AND(I9<>"",I9<>0,J9<>""),J9/I9,"") -> 0.96633081 | L9: =IF(SUMIF($E$25:$E$51,">=0",$Q$25:$Q$51)<>0,I9*E54/SUMIF($E$25:$E$51,">=0",$Q$25:$Q$51),0) -> 279 | M9: =IF(AND(I9<>"",I9<>0,L9<>"",L9<>0),L9/I9,"") -> 0.96633081 | N9: =IF(AND(J9<>0,J9<>"",I9<>0,I9<>""),L9-I9,"") -> -9.7210014 | O9: =O8/O11 -> #DIV/0! | P9: =IF(AND(O9<>"",O9<>0,L9<>"",L9<>0),-O9+L9,"") -> #DIV/0! | Q9: =IF(AND(P9<>"",P9<>0,O9<>0,O9<>""),P9/O9,"") -> #DIV/0!
F10: Средний чек | I10: =I11*I12 -> 10200 | J10: =H54 -> 10666.314 | K10: =IF(AND(I10<>"",I10<>0,J10<>""),J10/I10,"") -> 1.045717 | L10: =J10 -> 10666.314 | M10: =IF(AND(I10<>"",I10<>0,L10<>"",L10<>0),L10/I10,"") -> 1.045717 | N10: =IF(AND(J10<>0,J10<>"",I10<>0,I10<>""),L10-I10,"") -> 466.31382 | O10: =O11*O12 -> 0 | P10: =IF(AND(O10<>"",O10<>0,L10<>"",L10<>0),-O10+L10,"") | Q10: =IF(AND(P10<>"",P10<>0,O10<>0,O10<>""),P10/O10,"") | S10: IS | V10: =M23 -> Agafi
F11: Средняя стоимость изделия | I11: ='Ялта, Ленина, 18'!I11 -> 6000 | J11: =F54 -> 5811.0384 | K11: =IF(AND(I11<>"",I11<>0,J11<>""),J11/I11,"") -> 0.96850639 | L11: =IF(L9>0,L8/L9,"") -> 5811.0384 | M11: =IF(AND(I11<>"",I11<>0,L11<>"",L11<>0),L11/I11,"") -> 0.96850639 | N11: =IF(AND(J11<>0,J11<>"",I11<>0,I11<>""),L11-I11,"") -> -188.96165 | P11: =IF(AND(O11<>"",O11<>0,L11<>"",L11<>0),-O11+L11,"") | Q11: =IF(AND(P11<>"",P11<>0,O11<>0,O11<>""),P11/O11,"")
F12: Длина чека | I12: ='Ялта, Ленина, 18'!I12 -> 1.7 | J12: =J54 -> 1.8355263 | K12: =IF(AND(I12<>"",I12<>0,J12<>""),J12/I12,"") -> 1.0797214 | L12: =J12 -> 1.8355263 | M12: =IF(AND(I12<>"",I12<>0,L12<>"",L12<>0),L12/I12,"") -> 1.0797214 | N12: =IF(AND(J12<>0,J12<>"",I12<>0,I12<>""),L12-I12,"") -> 0.13552632 | P12: =IF(AND(O12<>"",O12<>0,L12<>"",L12<>0),-O12+L12,"") | Q12: =IF(AND(P12<>"",P12<>0,O12<>0,O12<>""),P12/O12,"") | S12: ='Ялта, Ленина, 18'!S12*График!AJ29/График!AJ31 -> 280111.27 | T12: =L54 -> 152063 | V12: ='Ялта, Ленина, 18'!V12/График!AJ31*График!AJ29 -> 169541.03 | W12: =M54 -> 85222
F13: Кол-во чеков | I13: =IF(I12<>0,I9/I12,"") -> 169.83588 | J13: =G54 -> 152 | K13: =IF(AND(I13<>"",I13<>0,J13<>""),J13/I13,"") -> 0.89498166 | L13: =IF(SUMIF($G$25:$G$51,">=0",$R$25:$R$51)<>0,I13*G54/SUMIF($G$25:$G$51,">=0",$R$25:$R$51),"") -> 152 | M13: =IF(AND(I13<>"",I13<>0,L13<>"",L13<>0),L13/I13,"") -> 0.89498166 | N13: =IF(AND(J13<>0,J13<>"",I13<>0,I13<>""),L13-I13,"") -> -17.835883 | P13: =IF(AND(O13<>"",O13<>0,L13<>"",L13<>0),-O13+L13,"") | Q13: =IF(AND(P13<>"",P13<>0,O13<>0,O13<>""),P13/O13,"") | S13: =T12/S12 -> 0.54286642 | T13: =S13/J14*I14 -> 0.54286642 | V13: =W12/V12 -> 0.50266299 | W13: =V13/J14*I14 -> 0.50266299
F14: Кол-во смен план/отработано | I14: =График!AI29 -> 26 | J14: 26 | K14: =IF(AND(I14<>"",I14<>0,J14<>""),J14/I14,"") -> 1 | L14: =I14 -> 26 | M14: =IF(AND(I14<>"",I14<>0,L14<>"",L14<>0),L14/I14,"") -> 1 | N14: =IF(AND(J14<>0,J14<>"",I14<>0,I14<>""),L14-I14,"") -> 0 | P14: =IF(AND(O14<>"",O14<>0,L14<>"",L14<>0),-O14+L14,"") | Q14: =IF(AND(P14<>"",P14<>0,O14<>0,O14<>""),P14/O14,"")
F15: Средние продажи в смену | I15: ='Ялта, Ленина, 18'!I15 -> 151618.06 | J15: =J8/J14 -> 62356.912 | K15: =IF(AND(I15<>"",I15<>0,J15<>""),J15/I15,"") -> 0.41127627 | L15: =J15 -> 62356.912 | M15: =IF(AND(I15<>"",I15<>0,L15<>"",L15<>0),L15/I15,"") -> 0.41127627 | N15: =IF(AND(J15<>0,J15<>"",I15<>0,I15<>""),L15-I15,"") -> -89261.153 | P15: =IF(AND(O15<>"",O15<>0,L15<>"",L15<>0),-O15+L15,"") | Q15: =IF(AND(P15<>"",P15<>0,O15<>0,O15<>""),P15/O15,"")
F16: Отставание/Перевыполнение | J16: =J8-I15*J14 -> -2320790 | K16: =IF(AND(I16<>"",I16<>0,J16<>""),J16/I16,"") | L16: =J16 -> -2320790 | M16: =IF(AND(I16<>"",I16<>0,L16<>"",L16<>0),L16/I16,"") | N16: =IF(AND(J16<>0,J16<>"",I16<>0,I16<>""),L16-I16,"") | P16: =IF(AND(O16<>"",O16<>0,L16<>"",L16<>0),-O16+L16,"") | Q16: =IF(AND(P16<>"",P16<>0,O16<>0,O16<>""),P16/O16,"") | S16: UNOde50
F17: Трафик | I17: ='Ялта, Ленина, 18'!I17/График!AJ31*График!AJ29 -> 943.53268 | J17: =I54 -> 1013 | K17: =IF(AND(I17<>"",I17<>0,J17<>""),J17/I17,"") -> 1.0736247 | L17: =J17/J14*I14 -> 1013 | M17: =IF(AND(I17<>"",I17<>0,L17<>"",L17<>0),L17/I17,"") -> 1.0736247 | N17: =IF(AND(J17<>0,J17<>"",I17<>0,I17<>""),L17-I17,"") -> 69.467316 | P17: =IF(AND(O17<>"",O17<>0,L17<>"",L17<>0),-O17+L17,"") | Q17: =IF(AND(P17<>"",P17<>0,O17<>0,O17<>""),P17/O17,"")
K18: =IF(AND(I18<>"",I18<>0,J18<>""),J18/I18,"") | L18: =J18 -> 0 | M18: =IF(AND(I18<>"",I18<>0,L18<>"",L18<>0),L18/I18,"") | N18: =IF(AND(J18<>0,J18<>"",I18<>0,I18<>""),L18-I18,"") | O18: 0 | P18: =IF(AND(O18<>"",O18<>0,L18<>"",L18<>0),-O18+L18,"") | Q18: =IF(AND(P18<>"",P18<>0,O18<>0,O18<>""),P18/O18,"") | S18: ='Ялта, Ленина, 18'!S18*График!AJ29/График!AJ31 -> 324339.36 | T18: =K54 -> 319210
J19: =M54 -> 85222 | K19: =IF(AND(I19<>"",I19<>0,J19<>""),J19/I19,"") | L19: =J19 -> 85222 | M19: =IF(AND(I19<>"",I19<>0,L19<>"",L19<>0),L19/I19,"") | N19: =IF(AND(J19<>0,J19<>"",I19<>0,I19<>""),L19-I19,"") | O19: 0 | P19: =IF(AND(O19<>"",O19<>0,L19<>"",L19<>0),-O19+L19,"") | Q19: =IF(AND(P19<>"",P19<>0,O19<>0,O19<>""),P19/O19,"") | S19: =T18/S18 -> 0.98418521 | T19: =S19/J14*I14 -> 0.98418521
F20: Конверсия план/факт | I20: ='Ялта, Ленина, 18'!I20 -> 0.18 | J20: =N54 -> 0.15004936 | K20: =J20/I20 -> 0.83360755 | L20: =IF(AND(K8<>0,I14<>0,I54<>0),(I54*N54+(I54/K8-I54)*I20)/(I54/K8),0) -> 0.15196927 | M20: =IF(AND(I20<>"",I20<>0,L20<>"",L20<>0),L20/I20,"") -> 0.84427371 | N20: =IF(AND(J20<>0,J20<>"",I20<>0,I20<>""),L20-I20,"") -> -0.028030733 | P20: =IF(AND(O20<>"",O20<>0,L20<>"",L20<>0),-O20+L20,"") | Q20: =IF(AND(P20<>"",P20<>0,O20<>0,O20<>""),P20/O20,"")
B22: Факт продаж за месяц | O22: % выполнения дневного плана | P22: Раcпределение плана по дням
B23: Дата | C23: День недели | D23: Выручка (руб) | E23: Кол-во единиц (шт.) | F23: Средняя стоимость изделия (руб.) | G23: Количество чеков (шт.) | H23: Средняя сумма чека (руб.) | I23: Трафик | J23: Длина чека (шт.) | K23: UNOde50 | L23: IS | M23: Agafi | N23: Конверсия (%) | P23: выручка, план | Q23: кол-во ед, план | R23: Кол-во чеков, план | S23: выручка, скорректир.план | T23: кол-во ед, скорр. план | U23: кол-во чеков, скорр. план | V23: Коэфф. Дня Недели | W23: Специфика месяца
B24: 1 | C24: 2 | D24: 3 | E24: 4 | F24: 5 | G24: 6 | H24: 7 | I24: 8 | J24: 9 | K24: 10 | L24: 11 | M24: 12 | N24: 13 | P24: 1 | Q24: 2 | R24: 3 | S24: 4 | T24: 5 | U24: 6 | V24: 10 | W24: 11
A25: 1 | B25: 45871 | C25: сб | D25: 32095 | E25: 8 | F25: =IF(AND(E25<>"",E25<>0),D25/E25,"") -> 4011.875 | G25: 4 | H25: =IF(AND(G25<>"",G25<>0),D25/G25,"") -> 8023.75 | I25: 30 | J25: =IF(AND(G25<>"",G25<>0),E25/G25,"") -> 2 | N25: =IF(AND(I25<>"",I25<>0),G25/I25,"") -> 0.13333333 | O25: =D25/P25 -> 0.48170494 | P25: =$I$8*V25*W25/SUMPRODUCT($W$25:$W$53,$V$25:$V$53) -> 66627.923 | Q25: =$I$9*V25*W25/SUMPRODUCT($W$25:$W$53,$V$25:$V$53) -> 11.104654 | R25: =IF($I$12="","",Q25/$I$12) -> 6.5321494 | S25: =IF(D25<>"",D25,P25) -> 32095 | T25: =IF(E25<>"",E25,Q25) -> 8 | U25: =IF(G25<>"",G25,R25) -> 4 | V25: 1 | W25: 1
A26: 2 | B26: 45872 | C26: вс | D26: =122924+4623 -> 127547 | E26: 25 | F26: =IF(AND(E26<>"",E26<>0),D26/E26,"") -> 5101.88 | G26: 10 | H26: =IF(AND(G26<>"",G26<>0),D26/G26,"") -> 12754.7 | I26: 55 | J26: =IF(AND(G26<>"",G26<>0),E26/G26,"") -> 2.5 | L26: 4623 | M26: 27270 | N26: =IF(AND(I26<>"",I26<>0),G26/I26,"") -> 0.18181818 | O26: =D26/P26 -> 1.9143175 | P26: =$I$8*V26*W26/SUMPRODUCT($W$25:$W$53,$V$25:$V$53) -> 66627.923 | Q26: =$I$9*V26*W26/SUMPRODUCT($W$25:$W$53,$V$25:$V$53) -> 11.104654 | R26: =IF($I$12="","",Q26/$I$12) -> 6.5321494 | S26: =IF(W26<>"",IF(D26<>"",D26,($I$8-SUM($S$25:S25))*V26*W26/SUMPRODUCT($W26:$W$55,$V26:$V$55)),"") -> 127547 | T26: =IF(W26<>"",IF(E26<>"",E26,($I$9-SUM($T$25:T25))*V26*W26/SUMPRODUCT($W26:$W$55,$V26:$V$55)),"") -> 25 | U26: =IF(W26<>"",IF($I$12<>"",IF(G26<>"",G26,($I$9/$I$12-SUM($U$25:U25))*V26*W26/SUMPRODUCT($W26:$W$55,$V26:$V$55)),""),"") -> 10 | V26: 1 | W26: 1
A27: 3 | B27: 45873 | C27: пн | D27: 22961 | E27: 5 | F27: =IF(AND(E27<>"",E27<>0),D27/E27,"") -> 4592.2 | G27: 4 | H27: =IF(AND(G27<>"",G27<>0),D27/G27,"") -> 5740.25 | I27: 30 | J27: =IF(AND(G27<>"",G27<>0),E27/G27,"") -> 1.25 | N27: =IF(AND(I27<>"",I27<>0),G27/I27,"") -> 0.13333333 | O27: =D27/P27 -> 0.34461527 | P27: =$I$8*V27*W27/SUMPRODUCT($W$25:$W$53,$V$25:$V$53) -> 66627.923 | Q27: =$I$9*V27*W27/SUMPRODUCT($W$25:$W$53,$V$25:$V$53) -> 11.104654 | R27: =IF($I$12="","",Q27/$I$12) -> 6.5321494 | S27: =IF(W27<>"",IF(D27<>"",D27,($I$8-SUM($S$25:S26))*V27*W27/SUMPRODUCT($W27:$W$55,$V27:$V$55)),"") -> 22961 | T27: =IF(W27<>"",IF(E27<>"",E27,($I$9-SUM($T$25:T26))*V27*W27/SUMPRODUCT($W27:$W$55,$V27:$V$55)),"") -> 5 | U27: =IF(W27<>"",IF($I$12<>"",IF(G27<>"",G27,($I$9/$I$12-SUM($U$25:U26))*V27*W27/SUMPRODUCT($W27:$W$55,$V27:$V$55)),""),"") -> 4 | V27: 1 | W27: 1
A28: 4 | B28: 45875 | C28: ср | D28: =57982+27939 -> 85921 | E28: 8 | F28: =IF(AND(E28<>"",E28<>0),D28/E28,"") -> 10740.125 | G28: 6 | H28: =IF(AND(G28<>"",G28<>0),D28/G28,"") -> 14320.167 | I28: 25 | J28: =IF(AND(G28<>"",G28<>0),E28/G28,"") -> 1.3333333 | K28: 57982 | N28: =IF(AND(I28<>"",I28<>0),G28/I28,"") -> 0.24 | O28: =D28/P28 -> 1.2895644 | P28: =$I$8*V28*W28/SUMPRODUCT($W$25:$W$53,$V$25:$V$53) -> 66627.923 | Q28: =$I$9*V28*W28/SUMPRODUCT($W$25:$W$53,$V$25:$V$53) -> 11.104654 | R28: =IF($I$12="","",Q28/$I$12) -> 6.5321494 | S28: =IF(W28<>"",IF(D28<>"",D28,($I$8-SUM($S$25:S27))*V28*W28/SUMPRODUCT($W28:$W$55,$V28:$V$55)),"") -> 85921 | T28: =IF(W28<>"",IF(E28<>"",E28,($I$9-SUM($T$25:T27))*V28*W28/SUMPRODUCT($W28:$W$55,$V28:$V$55)),"") -> 8 | U28: =IF(W28<>"",IF($I$12<>"",IF(G28<>"",G28,($I$9/$I$12-SUM($U$25:U27))*V28*W28/SUMPRODUCT($W28:$W$55,$V28:$V$55)),""),"") -> 6 | V28: 1 | W28: 1
A29: 5 | B29: 45876 | C29: чт | D29: =77557+16403+38820 -> 132780 | E29: 17 | F29: =IF(AND(E29<>"",E29<>0),D29/E29,"") -> 7810.5882 | G29: 13 | H29: =IF(AND(G29<>"",G29<>0),D29/G29,"") -> 10213.846 | I29: 55 | J29: =IF(AND(G29<>"",G29<>0),E29/G29,"") -> 1.3076923 | K29: 77557 | L29: 16403 | N29: =IF(AND(I29<>"",I29<>0),G29/I29,"") -> 0.23636364 | O29: =D29/P29 -> 1.9928581 | P29: =$I$8*V29*W29/SUMPRODUCT($W$25:$W$53,$V$25:$V$53) -> 66627.923 | Q29: =$I$9*V29*W29/SUMPRODUCT($W$25:$W$53,$V$25:$V$53) -> 11.104654 | R29: =IF($I$12="","",Q29/$I$12) -> 6.5321494 | S29: =IF(W29<>"",IF(D29<>"",D29,($I$8-SUM($S$25:S28))*V29*W29/SUMPRODUCT($W29:$W$55,$V29:$V$55)),"") -> 132780 | T29: =IF(W29<>"",IF(E29<>"",E29,($I$9-SUM($T$25:T28))*V29*W29/SUMPRODUCT($W29:$W$55,$V29:$V$55)),"") -> 17 | U29: =IF(W29<>"",IF($I$12<>"",IF(G29<>"",G29,($I$9/$I$12-SUM($U$25:U28))*V29*W29/SUMPRODUCT($W29:$W$55,$V29:$V$55)),""),"") -> 13 | V29: 1 | W29: 1
A30: 6 | B30: 45877 | C30: пт | D30: =7492+38149 -> 45641 | E30: 7 | F30: =IF(AND(E30<>"",E30<>0),D30/E30,"") -> 6520.1429 | G30: 4 | H30: =IF(AND(G30<>"",G30<>0),D30/G30,"") -> 11410.25 | I30: 40 | J30: =IF(AND(G30<>"",G30<>0),E30/G30,"") -> 1.75 | K30: 7492 | M30: 13290 | N30: =IF(AND(I30<>"",I30<>0),G30/I30,"") -> 0.1 | O30: =D30/P30 -> 0.68501309 | P30: =$I$8*V30*W30/SUMPRODUCT($W$25:$W$53,$V$25:$V$53) -> 66627.923 | Q30: =$I$9*V30*W30/SUMPRODUCT($W$25:$W$53,$V$25:$V$53) -> 11.104654 | R30: =IF($I$12="","",Q30/$I$12) -> 6.5321494 | S30: =IF(W30<>"",IF(D30<>"",D30,($I$8-SUM($S$25:S29))*V30*W30/SUMPRODUCT($W30:$W$55,$V30:$V$55)),"") -> 45641 | T30: =IF(W30<>"",IF(E30<>"",E30,($I$9-SUM($T$25:T29))*V30*W30/SUMPRODUCT($W30:$W$55,$V30:$V$55)),"") -> 7 | U30: =IF(W30<>"",IF($I$12<>"",IF(G30<>"",G30,($I$9/$I$12-SUM($U$25:U29))*V30*W30/SUMPRODUCT($W30:$W$55,$V30:$V$55)),""),"") -> 4 | V30: 1 | W30: 1
A31: 7 | B31: 45878 | C31: сб | D31: 28859 | E31: 6 | F31: =IF(AND(E31<>"",E31<>0),D31/E31,"") -> 4809.8333 | G31: 4 | H31: =IF(AND(G31<>"",G31<>0),D31/G31,"") -> 7214.75 | I31: 30 | J31: =IF(AND(G31<>"",G31<>0),E31/G31,"") -> 1.5 | N31: =IF(AND(I31<>"",I31<>0),G31/I31,"") -> 0.13333333 | O31: =D31/P31 -> 0.43313672 | P31: =$I$8*V31*W31/SUMPRODUCT($W$25:$W$53,$V$25:$V$53) -> 66627.923 | Q31: =$I$9*V31*W31/SUMPRODUCT($W$25:$W$53,$V$25:$V$53) -> 11.104654 | R31: =IF($I$12="","",Q31/$I$12) -> 6.5321494 | S31: =IF(W31<>"",IF(D31<>"",D31,($I$8-SUM($S$25:S30))*V31*W31/SUMPRODUCT($W31:$W$55,$V31:$V$55)),"") -> 28859 | T31: =IF(W31<>"",IF(E31<>"",E31,($I$9-SUM($T$25:T30))*V31*W31/SUMPRODUCT($W31:$W$55,$V31:$V$55)),"") -> 6 | U31: =IF(W31<>"",IF($I$12<>"",IF(G31<>"",G31,($I$9/$I$12-SUM($U$25:U30))*V31*W31/SUMPRODUCT($W31:$W$55,$V31:$V$55)),""),"") -> 4 | V31: 1 | W31: 1
A32: 8 | B32: 45879 | C32: вс | D32: 33665 | E32: 8 | F32: =IF(AND(E32<>"",E32<>0),D32/E32,"") -> 4208.125 | G32: 4 | H32: =IF(AND(G32<>"",G32<>0),D32/G32,"") -> 8416.25 | I32: 30 | J32: =IF(AND(G32<>"",G32<>0),E32/G32,"") -> 2 | N32: =IF(AND(I32<>"",I32<>0),G32/I32,"") -> 0.13333333 | O32: =D32/P32 -> 0.50526864 | P32: =$I$8*V32*W32/SUMPRODUCT($W$25:$W$53,$V$25:$V$53) -> 66627.923 | Q32: =$I$9*V32*W32/SUMPRODUCT($W$25:$W$53,$V$25:$V$53) -> 11.104654 | R32: =IF($I$12="","",Q32/$I$12) -> 6.5321494 | S32: =IF(W32<>"",IF(D32<>"",D32,($I$8-SUM($S$25:S31))*V32*W32/SUMPRODUCT($W32:$W$55,$V32:$V$55)),"") -> 33665 | T32: =IF(W32<>"",IF(E32<>"",E32,($I$9-SUM($T$25:T31))*V32*W32/SUMPRODUCT($W32:$W$55,$V32:$V$55)),"") -> 8 | U32: =IF(W32<>"",IF($I$12<>"",IF(G32<>"",G32,($I$9/$I$12-SUM($U$25:U31))*V32*W32/SUMPRODUCT($W32:$W$55,$V32:$V$55)),""),"") -> 4 | V32: 1 | W32: 1
A33: 9 | B33: 45880 | C33: пн | D33: =38721+6992 -> 45713 | E33: 11 | F33: =IF(AND(E33<>"",E33<>0),D33/E33,"") -> 4155.7273 | G33: 5 | H33: =IF(AND(G33<>"",G33<>0),D33/G33,"") -> 9142.6 | I33: 30 | J33: =IF(AND(G33<>"",G33<>0),E33/G33,"") -> 2.2 | K33: 6992 | N33: =IF(AND(I33<>"",I33<>0),G33/I33,"") -> 0.16666667 | O33: =D33/P33 -> 0.68609372 | P33: =$I$8*V33*W33/SUMPRODUCT($W$25:$W$53,$V$25:$V$53) -> 66627.923 | Q33: =$I$9*V33*W33/SUMPRODUCT($W$25:$W$53,$V$25:$V$53) -> 11.104654 | R33: =IF($I$12="","",Q33/$I$12) -> 6.5321494 | S33: =IF(W33<>"",IF(D33<>"",D33,($I$8-SUM($S$25:S32))*V33*W33/SUMPRODUCT($W33:$W$55,$V33:$V$55)),"") -> 45713 | T33: =IF(W33<>"",IF(E33<>"",E33,($I$9-SUM($T$25:T32))*V33*W33/SUMPRODUCT($W33:$W$55,$V33:$V$55)),"") -> 11 | U33: =IF(W33<>"",IF($I$12<>"",IF(G33<>"",G33,($I$9/$I$12-SUM($U$25:U32))*V33*W33/SUMPRODUCT($W33:$W$55,$V33:$V$55)),""),"") -> 5 | V33: 1 | W33: 1
A34: 10 | B34: 45881 | C34: вт | D34: =79259+14803 -> 94062 | E34: 19 | F34: =IF(AND(E34<>"",E34<>0),D34/E34,"") -> 4950.6316 | G34: 11 | H34: =IF(AND(G34<>"",G34<>0),D34/G34,"") -> 8551.0909 | I34: 55 | J34: =IF(AND(G34<>"",G34<>0),E34/G34,"") -> 1.7272727 | L34: 14803 | N34: =IF(AND(I34<>"",I34<>0),G34/I34,"") -> 0.2 | O34: =D34/P34 -> 1.4117504 | P34: =$I$8*V34*W34/SUMPRODUCT($W$25:$W$53,$V$25:$V$53) -> 66627.923 | Q34: =$I$9*V34*W34/SUMPRODUCT($W$25:$W$53,$V$25:$V$53) -> 11.104654 | R34: =IF($I$12="","",Q34/$I$12) -> 6.5321494 | S34: =IF(W34<>"",IF(D34<>"",D34,($I$8-SUM($S$25:S33))*V34*W34/SUMPRODUCT($W34:$W$55,$V34:$V$55)),"") -> 94062 | T34: =IF(W34<>"",IF(E34<>"",E34,($I$9-SUM($T$25:T33))*V34*W34/SUMPRODUCT($W34:$W$55,$V34:$V$55)),"") -> 19 | U34: =IF(W34<>"",IF($I$12<>"",IF(G34<>"",G34,($I$9/$I$12-SUM($U$25:U33))*V34*W34/SUMPRODUCT($W34:$W$55,$V34:$V$55)),""),"") -> 11 | V34: 1 | W34: 1
A35: 11 | B35: 45882 | C35: ср | D35: 99166 | E35: 18 | F35: =IF(AND(E35<>"",E35<>0),D35/E35,"") -> 5509.2222 | G35: 7 | H35: =IF(AND(G35<>"",G35<>0),D35/G35,"") -> 14166.571 | I35: 40 | J35: =IF(AND(G35<>"",G35<>0),E35/G35,"") -> 2.5714286 | K35: 21180 | L35: 9903 | N35: =IF(AND(I35<>"",I35<>0),G35/I35,"") -> 0.175 | O35: =D35/P35 -> 1.488355 | P35: =$I$8*V35*W35/SUMPRODUCT($W$25:$W$53,$V$25:$V$53) -> 66627.923 | Q35: =$I$9*V35*W35/SUMPRODUCT($W$25:$W$53,$V$25:$V$53) -> 11.104654 | R35: =IF($I$12="","",Q35/$I$12) -> 6.5321494 | S35: =IF(W35<>"",IF(D35<>"",D35,($I$8-SUM($S$25:S34))*V35*W35/SUMPRODUCT($W35:$W$55,$V35:$V$55)),"") -> 99166 | T35: =IF(W35<>"",IF(E34<>"",E34,($I$9-SUM($T$25:T34))*V35*W35/SUMPRODUCT($W35:$W$55,$V35:$V$55)),"") -> 19 | U35: =IF(W35<>"",IF($I$12<>"",IF(G35<>"",G35,($I$9/$I$12-SUM($U$25:U34))*V35*W35/SUMPRODUCT($W35:$W$55,$V35:$V$55)),""),"") -> 7 | V35: 1 | W35: 1
A36: 12 | B36: 45884 | C36: пт | D36: =39885+19598 -> 59483 | E36: 8 | F36: 7435 | G36: 5 | H36: =IF(AND(G36<>"",G36<>0),D36/G36,"") -> 11896.6 | I36: 50 | J36: =IF(AND(G36<>"",G36<>0),E36/G36,"") -> 1.6 | K36: 19598 | N36: =IF(AND(I36<>"",I36<>0),G36/I36,"") -> 0.1 | O36: =D36/P36 -> 0.89276383 | P36: =$I$8*V36*W36/SUMPRODUCT($W$25:$W$53,$V$25:$V$53) -> 66627.923 | Q36: =$I$9*V36*W36/SUMPRODUCT($W$25:$W$53,$V$25:$V$53) -> 11.104654 | R36: =IF($I$12="","",Q36/$I$12) -> 6.5321494 | S36: =IF(W36<>"",IF(D36<>"",D36,($I$8-SUM($S$25:S35))*V36*W36/SUMPRODUCT($W36:$W$55,$V36:$V$55)),"") -> 59483 | T36: =IF(W36<>"",IF(E36<>"",E36,($I$9-SUM($T$25:T35))*V36*W36/SUMPRODUCT($W36:$W$55,$V36:$V$55)),"") -> 8 | U36: =IF(W36<>"",IF($I$12<>"",IF(G36<>"",G36,($I$9/$I$12-SUM($U$25:U35))*V36*W36/SUMPRODUCT($W36:$W$55,$V36:$V$55)),""),"") -> 5 | V36: 1 | W36: 1
A37: 13 | B37: 45885 | C37: сб | D37: 74558 | E37: 15 | F37: =IF(AND(E37<>"",E37<>0),D37/E37,"") -> 4970.5333 | G37: 6 | H37: =IF(AND(G37<>"",G37<>0),D37/G37,"") -> 12426.333 | I37: 30 | J37: =IF(AND(G37<>"",G37<>0),E37/G37,"") -> 2.5 | N37: =IF(AND(I37<>"",I37<>0),G37/I37,"") -> 0.2 | O37: =D37/P37 -> 1.1190203 | P37: =$I$8*V37*W37/SUMPRODUCT($W$25:$W$53,$V$25:$V$53) -> 66627.923 | Q37: =$I$9*V37*W37/SUMPRODUCT($W$25:$W$53,$V$25:$V$53) -> 11.104654 | R37: =IF($I$12="","",Q37/$I$12) -> 6.5321494 | S37: =IF(W37<>"",IF(D37<>"",D37,($I$8-SUM($S$25:S36))*V37*W37/SUMPRODUCT($W37:$W$55,$V37:$V$55)),"") -> 74558 | T37: =IF(W37<>"",IF(E37<>"",E37,($I$9-SUM($T$25:T36))*V37*W37/SUMPRODUCT($W37:$W$55,$V37:$V$55)),"") -> 15 | U37: =IF(W37<>"",IF($I$12<>"",IF(G37<>"",G37,($I$9/$I$12-SUM($U$25:U36))*V37*W37/SUMPRODUCT($W37:$W$55,$V37:$V$55)),""),"") -> 6 | V37: 1 | W37: 1
A38: 14 | B38: 45886 | C38: вс | D38: 21063 | E38: 5 | F38: =IF(AND(E38<>"",E38<>0),D38/E38,"") -> 4212.6 | G38: 4 | H38: =IF(AND(G38<>"",G38<>0),D38/G38,"") -> 5265.75 | I38: 35 | J38: =IF(AND(G38<>"",G38<>0),E38/G38,"") -> 1.25 | N38: =IF(AND(I38<>"",I38<>0),G38/I38,"") -> 0.11428571 | O38: =D38/P38 -> 0.31612872 | P38: =$I$8*V38*W38/SUMPRODUCT($W$25:$W$53,$V$25:$V$53) -> 66627.923 | Q38: =$I$9*V38*W38/SUMPRODUCT($W$25:$W$53,$V$25:$V$53) -> 11.104654 | R38: =IF($I$12="","",Q38/$I$12) -> 6.5321494 | S38: =IF(W38<>"",IF(D38<>"",D38,($I$8-SUM($S$25:S37))*V38*W38/SUMPRODUCT($W38:$W$55,$V38:$V$55)),"") -> 21063 | T38: =IF(W38<>"",IF(E38<>"",E38,($I$9-SUM($T$25:T37))*V38*W38/SUMPRODUCT($W38:$W$55,$V38:$V$55)),"") -> 5 | U38: =IF(W38<>"",IF($I$12<>"",IF(G38<>"",G38,($I$9/$I$12-SUM($U$25:U37))*V38*W38/SUMPRODUCT($W38:$W$55,$V38:$V$55)),""),"") -> 4 | V38: 1 | W38: 1
A39: 15 | B39: 45887 | C39: пн | D39: =21304+39632 -> 60936 | E39: 10 | F39: =IF(AND(E39<>"",E39<>0),D39/E39,"") -> 6093.6 | G39: 6 | H39: =IF(AND(G39<>"",G39<>0),D39/G39,"") -> 10156 | I39: 40 | J39: =IF(AND(G39<>"",G39<>0),E39/G39,"") -> 1.6666667 | L39: 21304 | N39: =IF(AND(I39<>"",I39<>0),G39/I39,"") -> 0.15 | O39: =D39/P39 -> 0.9145715 | P39: =$I$8*V39*W39/SUMPRODUCT($W$25:$W$53,$V$25:$V$53) -> 66627.923 | Q39: =$I$9*V39*W39/SUMPRODUCT($W$25:$W$53,$V$25:$V$53) -> 11.104654 | R39: =IF($I$12="","",Q39/$I$12) -> 6.5321494 | S39: =IF(W39<>"",IF(D39<>"",D39,($I$8-SUM($S$25:S38))*V39*W39/SUMPRODUCT($W39:$W$55,$V39:$V$55)),"") -> 60936 | T39: =IF(W39<>"",IF(E39<>"",E39,($I$9-SUM($T$25:T38))*V39*W39/SUMPRODUCT($W39:$W$55,$V39:$V$55)),"") -> 10 | U39: =IF(W39<>"",IF($I$12<>"",IF(G39<>"",G39,($I$9/$I$12-SUM($U$25:U38))*V39*W39/SUMPRODUCT($W39:$W$55,$V39:$V$55)),""),"") -> 6 | V39: 1 | W39: 1
A40: 16 | B40: 45888 | C40: вт | D40: =41975+2203+69525 -> 113703 | E40: 18 | F40: =IF(AND(E40<>"",E40<>0),D40/E40,"") -> 6316.8333 | G40: 11 | H40: =IF(AND(G40<>"",G40<>0),D40/G40,"") -> 10336.636 | I40: 75 | J40: =IF(AND(G40<>"",G40<>0),E40/G40,"") -> 1.6363636 | K40: 41975 | L40: 2203 | N40: =IF(AND(I40<>"",I40<>0),G40/I40,"") -> 0.14666667 | O40: =D40/P40 -> 1.7065368 | P40: =$I$8*V40*W40/SUMPRODUCT($W$25:$W$53,$V$25:$V$53) -> 66627.923 | Q40: =$I$9*V40*W40/SUMPRODUCT($W$25:$W$53,$V$25:$V$53) -> 11.104654 | R40: =IF($I$12="","",Q40/$I$12) -> 6.5321494 | S40: =IF(W40<>"",IF(D40<>"",D40,($I$8-SUM($S$25:S39))*V40*W40/SUMPRODUCT($W40:$W$55,$V40:$V$55)),"") -> 113703 | T40: =IF(W40<>"",IF(E40<>"",E40,($I$9-SUM($T$25:T39))*V40*W40/SUMPRODUCT($W40:$W$55,$V40:$V$55)),"") -> 18 | U40: =IF(W40<>"",IF($I$12<>"",IF(G40<>"",G40,($I$9/$I$12-SUM($U$25:U39))*V40*W40/SUMPRODUCT($W40:$W$55,$V40:$V$55)),""),"") -> 11 | V40: 1 | W40: 1
A41: 17 | B41: 45889 | C41: ср | D41: =9990+15103+26550 -> 51643 | E41: 9 | F41: =IF(AND(E41<>"",E41<>0),D41/E41,"") -> 5738.1111 | G41: 6 | H41: =IF(AND(G41<>"",G41<>0),D41/G41,"") -> 8607.1667 | I41: 49 | J41: =IF(AND(G41<>"",G41<>0),E41/G41,"") -> 1.5 | K41: 9990 | L41: 15103 | N41: =IF(AND(I41<>"",I41<>0),G41/I41,"") -> 0.12244898 | O41: =D41/P41 -> 0.77509545 | P41: =$I$8*V41*W41/SUMPRODUCT($W$25:$W$53,$V$25:$V$53) -> 66627.923 | Q41: =$I$9*V41*W41/SUMPRODUCT($W$25:$W$53,$V$25:$V$53) -> 11.104654 | R41: =IF($I$12="","",Q41/$I$12) -> 6.5321494 | S41: =IF(W41<>"",IF(D41<>"",D41,($I$8-SUM($S$25:S40))*V41*W41/SUMPRODUCT($W41:$W$55,$V41:$V$55)),"") -> 51643 | T41: =IF(W41<>"",IF(E41<>"",E41,($I$9-SUM($T$25:T40))*V41*W41/SUMPRODUCT($W41:$W$55,$V41:$V$55)),"") -> 9 | U41: =IF(W41<>"",IF($I$12<>"",IF(G41<>"",G41,($I$9/$I$12-SUM($U$25:U40))*V41*W41/SUMPRODUCT($W41:$W$55,$V41:$V$55)),""),"") -> 6 | V41: 1 | W41: 1
A42: 18 | B42: 45891 | C42: пт | D42: =14990+87860 -> 102850 | E42: 17 | F42: =IF(AND(E42<>"",E42<>0),D42/E42,"") -> 6050 | G42: 3 | H42: =IF(AND(G42<>"",G42<>0),D42/G42,"") -> 34283.333 | I42: 32 | J42: =IF(AND(G42<>"",G42<>0),E42/G42,"") -> 5.6666667 | K42: 14990 | N42: =IF(AND(I42<>"",I42<>0),G42/I42,"") -> 0.09375 | O42: =D42/P42 -> 1.5436471 | P42: =$I$8*V42*W42/SUMPRODUCT($W$25:$W$53,$V$25:$V$53) -> 66627.923 | Q42: =$I$9*V42*W42/SUMPRODUCT($W$25:$W$53,$V$25:$V$53) -> 11.104654 | R42: =IF($I$12="","",Q42/$I$12) -> 6.5321494 | S42: =IF(W42<>"",IF(D42<>"",D42,($I$8-SUM($S$25:S41))*V42*W42/SUMPRODUCT($W42:$W$55,$V42:$V$55)),"") -> 102850 | T42: =IF(W42<>"",IF(E42<>"",E42,($I$9-SUM($T$25:T41))*V42*W42/SUMPRODUCT($W42:$W$55,$V42:$V$55)),"") -> 17 | U42: =IF(W42<>"",IF($I$12<>"",IF(G42<>"",G42,($I$9/$I$12-SUM($U$25:U41))*V42*W42/SUMPRODUCT($W42:$W$55,$V42:$V$55)),""),"") -> 3 | V42: 1 | W42: 1
A43: 19 | B43: 45892 | C43: сб | D43: =13992+37729 -> 51721 | E43: 8 | F43: =IF(AND(E43<>"",E43<>0),D43/E43,"") -> 6465.125 | G43: 5 | H43: =IF(AND(G43<>"",G43<>0),D43/G43,"") -> 10344.2 | I43: 51 | J43: =IF(AND(G43<>"",G43<>0),E43/G43,"") -> 1.6 | K43: 13992 | N43: =IF(AND(I43<>"",I43<>0),G43/I43,"") -> 0.098039216 | O43: =D43/P43 -> 0.77626613 | P43: =$I$8*V43*W43/SUMPRODUCT($W$25:$W$53,$V$25:$V$53) -> 66627.923 | Q43: =$I$9*V43*W43/SUMPRODUCT($W$25:$W$53,$V$25:$V$53) -> 11.104654 | R43: =IF($I$12="","",Q43/$I$12) -> 6.5321494 | S43: =IF(W43<>"",IF(D43<>"",D43,($I$8-SUM($S$25:S42))*V43*W43/SUMPRODUCT($W43:$W$55,$V43:$V$55)),"") -> 51721 | T43: =IF(W43<>"",IF(E43<>"",E43,($I$9-SUM($T$25:T42))*V43*W43/SUMPRODUCT($W43:$W$55,$V43:$V$55)),"") -> 8 | U43: =IF(W43<>"",IF($I$12<>"",IF(G43<>"",G43,($I$9/$I$12-SUM($U$25:U42))*V43*W43/SUMPRODUCT($W43:$W$55,$V43:$V$55)),""),"") -> 5 | V43: 1 | W43: 1
A44: 20 | B44: 45893 | C44: вс | D44: =7903+22980+2794 -> 33677 | E44: 4 | F44: =IF(AND(E44<>"",E44<>0),D44/E44,"") -> 8419.25 | G44: 2 | H44: =IF(AND(G44<>"",G44<>0),D44/G44,"") -> 16838.5 | I44: 35 | J44: =IF(AND(G44<>"",G44<>0),E44/G44,"") -> 2 | K44: 22980 | L44: 7903 | N44: =IF(AND(I44<>"",I44<>0),G44/I44,"") -> 0.057142857 | O44: =D44/P44 -> 0.50544874 | P44: =$I$8*V44*W44/SUMPRODUCT($W$25:$W$53,$V$25:$V$53) -> 66627.923 | Q44: =$I$9*V44*W44/SUMPRODUCT($W$25:$W$53,$V$25:$V$53) -> 11.104654 | R44: =IF($I$12="","",Q44/$I$12) -> 6.5321494 | S44: =IF(W44<>"",IF(D44<>"",D44,($I$8-SUM($S$25:S43))*V44*W44/SUMPRODUCT($W44:$W$55,$V44:$V$55)),"") -> 33677 | T44: =IF(W44<>"",IF(E44<>"",E44,($I$9-SUM($T$25:T43))*V44*W44/SUMPRODUCT($W44:$W$55,$V44:$V$55)),"") -> 4 | U44: =IF(W44<>"",IF($I$12<>"",IF(G44<>"",G44,($I$9/$I$12-SUM($U$25:U43))*V44*W44/SUMPRODUCT($W44:$W$55,$V44:$V$55)),""),"") -> 2 | V44: 1 | W44: 1
A45: 21 | B45: 45894 | C45: пн | D45: =16992+6003+20980+24262 -> 68237 | E45: 10 | F45: =IF(AND(E45<>"",E45<>0),D45/E45,"") -> 6823.7 | G45: 7 | H45: =IF(AND(G45<>"",G45<>0),D45/G45,"") -> 9748.1429 | I45: 39 | J45: =IF(AND(G45<>"",G45<>0),E45/G45,"") -> 1.4285714 | K45: 16992 | L45: 6003 | M45: 20980 | N45: =IF(AND(I45<>"",I45<>0),G45/I45,"") -> 0.17948718 | O45: =D45/P45 -> 1.0241502 | P45: =$I$8*V45*W45/SUMPRODUCT($W$25:$W$53,$V$25:$V$53) -> 66627.923 | Q45: =$I$9*V45*W45/SUMPRODUCT($W$25:$W$53,$V$25:$V$53) -> 11.104654 | R45: =IF($I$12="","",Q45/$I$12) -> 6.5321494 | S45: =IF(W45<>"",IF(D45<>"",D45,($I$8-SUM($S$25:S44))*V45*W45/SUMPRODUCT($W45:$W$55,$V45:$V$55)),"") -> 68237 | T45: =IF(W45<>"",IF(E45<>"",E45,($I$9-SUM($T$25:T44))*V45*W45/SUMPRODUCT($W45:$W$55,$V45:$V$55)),"") -> 10 | U45: =IF(W45<>"",IF($I$12<>"",IF(G45<>"",G45,($I$9/$I$12-SUM($U$25:U44))*V45*W45/SUMPRODUCT($W45:$W$55,$V45:$V$55)),""),"") -> 7 | V45: 1 | W45: 1
A46: 22 | B46: 45895 | C46: вт | D46: 32441 | E46: 7 | F46: =IF(AND(E46<>"",E46<>0),D46/E46,"") -> 4634.4286 | G46: 4 | H46: =IF(AND(G46<>"",G46<>0),D46/G46,"") -> 8110.25 | I46: 40 | J46: =IF(AND(G46<>"",G46<>0),E46/G46,"") -> 1.75 | N46: =IF(AND(I46<>"",I46<>0),G46/I46,"") -> 0.1 | O46: =D46/P46 -> 0.48689796 | P46: =$I$8*V46*W46/SUMPRODUCT($W$25:$W$53,$V$25:$V$53) -> 66627.923 | Q46: =$I$9*V46*W46/SUMPRODUCT($W$25:$W$53,$V$25:$V$53) -> 11.104654 | R46: =IF($I$12="","",Q46/$I$12) -> 6.5321494 | S46: =IF(W46<>"",IF(D46<>"",D46,($I$8-SUM($S$25:S45))*V46*W46/SUMPRODUCT($W46:$W$55,$V46:$V$55)),"") -> 32441 | T46: =IF(W46<>"",IF(E46<>"",E46,($I$9-SUM($T$25:T45))*V46*W46/SUMPRODUCT($W46:$W$55,$V46:$V$55)),"") -> 7 | U46: =IF(W46<>"",IF($I$12<>"",IF(G46<>"",G46,($I$9/$I$12-SUM($U$25:U45))*V46*W46/SUMPRODUCT($W46:$W$55,$V46:$V$55)),""),"") -> 4 | V46: 1 | W46: 1
A47: 23 | B47: 45897 | C47: чт | D47: =33050+L47 -> 35253 | E47: 7 | F47: =IF(AND(E47<>"",E47<>0),D47/E47,"") -> 5036.1429 | G47: 5 | H47: =IF(AND(G47<>"",G47<>0),D47/G47,"") -> 7050.6 | I47: 29 | J47: =IF(AND(G47<>"",G47<>0),E47/G47,"") -> 1.4 | K47: 7490 | L47: 2203 | M47: 8892 | N47: =IF(AND(I47<>"",I47<>0),G47/I47,"") -> 0.17241379 | O47: =D47/P47 -> 0.52910249 | P47: =$I$8*V47*W47/SUMPRODUCT($W$25:$W$53,$V$25:$V$53) -> 66627.923 | Q47: =$I$9*V47*W47/SUMPRODUCT($W$25:$W$53,$V$25:$V$53) -> 11.104654 | R47: =IF($I$12="","",Q47/$I$12) -> 6.5321494 | S47: =IF(W47<>"",IF(D47<>"",D47,($I$8-SUM($S$25:S46))*V47*W47/SUMPRODUCT($W47:$W$55,$V47:$V$55)),"") -> 35253 | T47: =IF(W47<>"",IF(E47<>"",E47,($I$9-SUM($T$25:T46))*V47*W47/SUMPRODUCT($W47:$W$55,$V47:$V$55)),"") -> 7 | U47: =IF(W47<>"",IF($I$12<>"",IF(G47<>"",G47,($I$9/$I$12-SUM($U$25:U46))*V47*W47/SUMPRODUCT($W47:$W$55,$V47:$V$55)),""),"") -> 5 | V47: 1 | W47: 1
A48: 24 | B48: 45898 | C48: пт | D48: =9903+39919 -> 49822 | E48: 9 | F48: =IF(AND(E48<>"",E48<>0),D48/E48,"") -> 5535.7778 | G48: 4 | H48: =IF(AND(G48<>"",G48<>0),D48/G48,"") -> 12455.5 | I48: 28 | J48: =IF(AND(G48<>"",G48<>0),E48/G48,"") -> 2.25 | L48: 9903 | N48: =IF(AND(I48<>"",I48<>0),G48/I48,"") -> 0.14285714 | O48: =D48/P48 -> 0.74776456 | P48: =$I$8*V48*W48/SUMPRODUCT($W$25:$W$53,$V$25:$V$53) -> 66627.923 | Q48: =$I$9*V48*W48/SUMPRODUCT($W$25:$W$53,$V$25:$V$53) -> 11.104654 | R48: =IF($I$12="","",Q48/$I$12) -> 6.5321494 | S48: =IF(W48<>"",IF(D48<>"",D48,($I$8-SUM($S$25:S47))*V48*W48/SUMPRODUCT($W48:$W$55,$V48:$V$55)),"") -> 49822 | T48: =IF(W48<>"",IF(E48<>"",E48,($I$9-SUM($T$25:T47))*V48*W48/SUMPRODUCT($W48:$W$55,$V48:$V$55)),"") -> 9 | U48: =IF(W48<>"",IF($I$12<>"",IF(G48<>"",G48,($I$9/$I$12-SUM($U$25:U47))*V48*W48/SUMPRODUCT($W48:$W$55,$V48:$V$55)),""),"") -> 4 | V48: 1 | W48: 1
A49: 25 | B49: 45899 | C49: сб | D49: =23206+15317 -> 38523 | E49: 7 | F49: =IF(AND(E49<>"",E49<>0),D49/E49,"") -> 5503.2857 | G49: 4 | H49: =IF(AND(G49<>"",G49<>0),D49/G49,"") -> 9630.75 | I49: 22 | J49: =IF(AND(G49<>"",G49<>0),E49/G49,"") -> 1.75 | L49: 23206 | N49: =IF(AND(I49<>"",I49<>0),G49/I49,"") -> 0.18181818 | O49: =D49/P49 -> 0.57818101 | P49: =$I$8*V49*W49/SUMPRODUCT($W$25:$W$53,$V$25:$V$53) -> 66627.923 | Q49: =$I$9*V49*W49/SUMPRODUCT($W$25:$W$53,$V$25:$V$53) -> 11.104654 | R49: =IF($I$12="","",Q49/$I$12) -> 6.5321494 | S49: =IF(W49<>"",IF(D49<>"",D49,($I$8-SUM($S$25:S48))*V49*W49/SUMPRODUCT($W49:$W$55,$V49:$V$55)),"") -> 38523 | T49: =IF(W49<>"",IF(E49<>"",E49,($I$9-SUM($T$25:T48))*V49*W49/SUMPRODUCT($W49:$W$55,$V49:$V$55)),"") -> 7 | U49: =IF(W49<>"",IF($I$12<>"",IF(G49<>"",G49,($I$9/$I$12-SUM($U$25:U48))*V49*W49/SUMPRODUCT($W49:$W$55,$V49:$V$55)),""),"") -> 4 | V49: 1 | W49: 1
A50: 26 | B50: 45900 | C50: вс | D50: =14790+15796 -> 30586 | E50: 6 | F50: =IF(AND(E50<>"",E50<>0),D50/E50,"") -> 5097.6667 | G50: 4 | H50: =IF(AND(G50<>"",G50<>0),D50/G50,"") -> 7646.5 | I50: 38 | J50: =IF(AND(G50<>"",G50<>0),E50/G50,"") -> 1.5 | M50: 14790 | N50: =IF(AND(I50<>"",I50<>0),G50/I50,"") -> 0.10526316 | O50: =D50/P50 -> 0.45905678 | P50: =$I$8*V50*W50/SUMPRODUCT($W$25:$W$53,$V$25:$V$53) -> 66627.923 | Q50: =$I$9*V50*W50/SUMPRODUCT($W$25:$W$53,$V$25:$V$53) -> 11.104654 | R50: =IF($I$12="","",Q50/$I$12) -> 6.5321494 | S50: =IF(W50<>"",IF(D50<>"",D50,($I$8-SUM($S$25:S49))*V50*W50/SUMPRODUCT($W50:$W$55,$V50:$V$55)),"") -> 30586 | T50: =IF(W50<>"",IF(E50<>"",E50,($I$9-SUM($T$25:T49))*V50*W50/SUMPRODUCT($W50:$W$55,$V50:$V$55)),"") -> 6 | U50: =IF(W50<>"",IF($I$12<>"",IF(G50<>"",G50,($I$9/$I$12-SUM($U$25:U49))*V50*W50/SUMPRODUCT($W50:$W$55,$V50:$V$55)),""),"") -> 4 | V50: 1 | W50: 1
B51: 45870 | C51: пт | D51: 3413.7 | E51: 1 | F51: =IF(AND(E51<>"",E51<>0),D51/E51,"") -> 3413.7 | G51: 1 | H51: =IF(AND(G51<>"",G51<>0),D51/G51,"") -> 3413.7 | J51: =IF(AND(G51<>"",G51<>0),E51/G51,"") -> 1 | N51: =IF(AND(I51<>"",I51<>0),G51/I51,"") | O51: =D51/P51 -> #DIV/0! | P51: =$I$8*V51*W51/SUMPRODUCT($W$25:$W$53,$V$25:$V$53) -> 0 | Q51: =$I$9*V51*W51/SUMPRODUCT($W$25:$W$53,$V$25:$V$53) -> 0 | R51: =IF($I$12="","",Q51/$I$12) -> 0 | S51: =IF(W51<>"",IF(D51<>"",D51,($I$8-SUM($S$25:S50))*V51*W51/SUMPRODUCT($W51:$W$55,$V51:$V$55)),"") | T51: =IF(W51<>"",IF(E51<>"",E51,($I$9-SUM($T$25:T50))*V51*W51/SUMPRODUCT($W51:$W$55,$V51:$V$55)),"") | U51: =IF(W51<>"",IF($I$12<>"",IF(G51<>"",G51,($I$9/$I$12-SUM($U$25:U50))*V51*W51/SUMPRODUCT($W51:$W$55,$V51:$V$55)),""),"")
B52: 45890 | C52: чт | D52: =18974+18503 -> 37477 | E52: 4 | F52: =IF(AND(E52<>"",E52<>0),D52/E52,"") -> 9369.25 | G52: 2 | H52: =IF(AND(G52<>"",G52<>0),D52/G52,"") -> 18738.5 | J52: =IF(AND(G52<>"",G52<>0),E52/G52,"") -> 2 | L52: 18503 | N52: =IF(AND(I52<>"",I52<>0),G52/I52,"") | O52: =D52/P52 -> #DIV/0! | P52: =$I$8*V52*W52/SUMPRODUCT($W$25:$W$53,$V$25:$V$53) -> 0 | Q52: =$I$9*V52*W52/SUMPRODUCT($W$25:$W$53,$V$25:$V$53) -> 0 | R52: =IF($I$12="","",Q52/$I$12) -> 0 | S52: =IF(W52<>"",IF(D52<>"",D52,($I$8-SUM($S$25:S51))*V52*W52/SUMPRODUCT($W52:$W$55,$V52:$V$55)),"") | T52: =IF(W52<>"",IF(E52<>"",E52,($I$9-SUM($T$25:T51))*V52*W52/SUMPRODUCT($W52:$W$55,$V52:$V$55)),"") | U52: =IF(W52<>"",IF($I$12<>"",IF(G52<>"",G52,($I$9/$I$12-SUM($U$25:U51))*V52*W52/SUMPRODUCT($W52:$W$55,$V52:$V$55)),""),"")
B53: 45896 | C53: ср | D53: 7483 | E53: 2 | F53: =IF(AND(E53<>"",E53<>0),D53/E53,"") -> 3741.5 | G53: 1 | H53: =IF(AND(G53<>"",G53<>0),D53/G53,"") -> 7483 | J53: =IF(AND(G53<>"",G53<>0),E53/G53,"") -> 2 | N53: =IF(AND(I53<>"",I53<>0),G53/I53,"") | O53: =D53/P53 -> #DIV/0! | P53: =$I$8*V53*W53/SUMPRODUCT($W$25:$W$53,$V$25:$V$53) -> 0 | Q53: =$I$9*V53*W53/SUMPRODUCT($W$25:$W$53,$V$25:$V$53) -> 0 | R53: =IF($I$12="","",Q53/$I$12) -> 0 | S53: =IF(W53<>"",IF(D53<>"",D53,($I$8-SUM($S$25:S52))*V53*W53/SUMPRODUCT($W53:$W$55,$V53:$V$55)),"") | T53: =IF(W53<>"",IF(E53<>"",E53,($I$9-SUM($T$25:T52))*V53*W53/SUMPRODUCT($W53:$W$55,$V53:$V$55)),"") | U53: =IF(W53<>"",IF($I$12<>"",IF(G53<>"",G53,($I$9/$I$12-SUM($U$25:U52))*V53*W53/SUMPRODUCT($W53:$W$55,$V53:$V$55)),""),"")
B54: итого | D54: =SUM(D25:D53) -> 1621279.7 | E54: =SUM(E25:E53) -> 279 | F54: =IF(AND(E54<>"",E54<>0),D54/E54,"") -> 5811.0384 | G54: =SUM(G25:G53) -> 152 | H54: =IF(AND(G54<>"",G54<>0),D54/G54,"") -> 10666.314 | I54: =SUM(I25:I53) -> 1013 | J54: =IF(AND(G54<>"",G54<>0),E54/G54,"") -> 1.8355263 | K54: =SUM(K25:K53) -> 319210 | L54: =SUM(L25:L53) -> 152063 | M54: =SUM(M25:M53) -> 85222 | N54: =IF(AND(I54<>"",I54<>0),G54/I54,"") -> 0.15004936 | O54: =D54/P54 -> 0.93589757 | P54: =SUM(P25:P53) -> 1732326 | Q54: =SUM(Q25:Q52) -> 288.721 | R54: =SUM(R25:R52) -> 169.83588 | S54: =SUM(S25:S53) -> 1572906 | T54: =SUM(T25:T52) -> 273 | U54: =SUM(U25:U52) -> 148
D55: =SUMIF(D25:D51,"",P25:P51)+D54 -> 1621279.7

Sheet Уразгильдеева Е. Р. 
B1: =TODAY()-1 -> 45909
B2: (отчетная дата) | J2: ЕЖЕДНЕВНЫЙ ОТЧЕТ О ПРОДАЖАХ
B3: Осталось до выполнения плана!!! | J3: =График!B28 -> Уразгильдеева Екатерина
C4: =I8-D50 -> 503066.38 | E4: =IF(I8<>0, C4/I8, 0) -> 0.34509342
F6: Целевые показатели
F7: Показатель | I7: План | J7: Факт | K7: % выполнения | L7: Прогноз выполнения | M7: % выполнения по прогнозу | N7: Отклонение | O7: Факт аналогичного месяца прошлого года | P7: Отклонение LFL
F8: Выручка | I8: ='Ялта, Ленина, 18'!I8/График!AJ31*График!AJ28 -> 1457768.7 | J8: =D50 -> 954702.3 | K8: =IF(AND(I8<>"",I8<>0,J8<>""),J8/I8,"") -> 0.65490658 | L8: =IF(SUMIF($D$25:$D$49,">=0",$P$25:$P$49)<>0,I8*D50/SUMIF($D$25:$D$49,">=0",$P$25:$P$49),0) -> 954702.3 | M8: =IF(AND(I8<>"",I8<>0,L8<>"",L8<>0),L8/I8,"") -> 0.65490658 | N8: =IF(AND(J8<>0, J8<>"", I8<>0, I8<>""), L8-I8, "") -> -503066.38 | P8: =IF(AND(O8<>"", O8<>0, L8<>"", L8<>0), -O8+L8, "") | Q8: =IF(AND(P8<>"", P8<>0, O8<>0, O8<>""), P8/O8, "")
F9: Кол-во изделий | I9: =I8/I11 -> 242.96145 | J9: =E50 -> 144 | K9: =IF(AND(I9<>"", I9<>0, J9<>""), J9/I9, "") -> 0.59268663 | L9: =J9 -> 144 | M9: =IF(AND(I9<>"",I9<>0,L9<>"",L9<>0),L9/I9,"") -> 0.59268663 | N9: =IF(AND(J9<>0, J9<>"", I9<>0, I9<>""), L9-I9, "") -> -98.961446 | O9: =O8/O11 -> #DIV/0! | P9: =IF(AND(O9<>"", O9<>0, L9<>"", L9<>0), -O9+L9, "") -> #DIV/0! | Q9: =IF(AND(P9<>"", P9<>0, O9<>0, O9<>""), P9/O9, "") -> #DIV/0!
F10: Средний чек | I10: =I11*I12 -> 10200 | J10: =H50 -> 10491.234 | K10: =IF(AND(I10<>"", I10<>0, J10<>""), J10/I10, "") -> 1.0285524 | L10: =J10 -> 10491.234 | M10: =IF(AND(I10<>"",I10<>0,L10<>"",L10<>0),L10/I10,"") -> 1.0285524 | N10: =IF(AND(J10<>0, J10<>"", I10<>0, I10<>""), L10-I10, "") -> 291.23407 | O10: =O11*O12 -> 0 | P10: =IF(AND(O10<>"", O10<>0, L10<>"", L10<>0), -O10+L10, "") | Q10: =IF(AND(P10<>"", P10<>0, O10<>0, O10<>""), P10/O10, "") | S10: IS | V10: =M23 -> Agafi
F11: Средняя стоимость изделия | I11: ='Ялта, Ленина, 18'!I11 -> 6000 | J11: =F50 -> 6629.8771 | K11: =IF(AND(I11<>"", I11<>0, J11<>""), J11/I11, "") -> 1.1049795 | L11: =J11 -> 6629.8771 | M11: =IF(AND(I11<>"",I11<>0,L11<>"",L11<>0),L11/I11,"") -> 1.1049795 | N11: =IF(AND(J11<>0, J11<>"", I11<>0, I11<>""), L11-I11, "") -> 629.87708 | P11: =IF(AND(O11<>"", O11<>0, L11<>"", L11<>0), -O11+L11, "") | Q11: =IF(AND(P11<>"", P11<>0, O11<>0, O11<>""), P11/O11, "")
F12: Длина чека | I12: ='Ялта, Ленина, 18'!I12 -> 1.7 | J12: =J50 -> 1.5824176 | K12: =IF(AND(I12<>"", I12<>0, J12<>""), J12/I12, "") -> 0.93083387 | L12: =J12 -> 1.5824176 | M12: =IF(AND(I12<>"",I12<>0,L12<>"",L12<>0),L12/I12,"") -> 0.93083387 | N12: =IF(AND(J12<>0, J12<>"", I12<>0, I12<>""), L12-I12, "") -> -0.11758242 | P12: =IF(AND(O12<>"", O12<>0, L12<>"", L12<>0), -O12+L12, "") | Q12: =IF(AND(P12<>"", P12<>0, O12<>0, O12<>""), P12/O12, "") | S12: ='Ялта, Ленина, 18'!S12*График!AJ28/График!AJ31 -> 235716.27 | T12: =L50 -> 153749 | U12: =S12-T12 -> 81967.273 | V12: ='Ялта, Ленина, 18'!V12/График!AJ31*График!AJ28 -> 142670.38 | W12: =M50 -> 54842 | X12: =V12-W12 -> 87828.376
F13: Кол-во чеков | I13: =IF(I12<>0, I9/I12, "") -> 142.9185 | J13: =G50 -> 91 | K13: =IF(AND(I13<>"", I13<>0, J13<>""), J13/I13, "") -> 0.63672654 | L13: =J13 -> 91 | M13: =IF(AND(I13<>"",I13<>0,L13<>"",L13<>0),L13/I13,"") -> 0.63672654 | N13: =IF(AND(J13<>0, J13<>"", I13<>0, I13<>""), L13-I13, "") -> -51.918498 | P13: =IF(AND(O13<>"", O13<>0, L13<>"", L13<>0), -O13+L13, "") | Q13: =IF(AND(P13<>"", P13<>0, O13<>0, O13<>""), P13/O13, "") | S13: =T12/S12 -> 0.65226299 | T13: =S13/J14*I14 -> 0.65226299 | V13: =W12/V12 -> 0.38439655 | W13: =V13/J14*I14 -> 0.38439655
F14: Кол-во смен план/отработано | I14: =График!AI28 -> 18 | J14: 18 | K14: =IF(AND(I14<>"", I14<>0, J14<>""), J14/I14, "") -> 1 | L14: =I14 -> 18 | M14: =IF(AND(I14<>"",I14<>0,L14<>"",L14<>0),L14/I14,"") -> 1 | N14: =IF(AND(J14<>0, J14<>"", I14<>0, I14<>""), L14-I14, "") -> 0 | P14: =IF(AND(O14<>"", O14<>0, L14<>"", L14<>0), -O14+L14, "") | Q14: =IF(AND(P14<>"", P14<>0, O14<>0, O14<>""), P14/O14, "")
F15: Средние продажи в смену | I15: ='Ялта, Ленина, 18'!I15 -> 151618.06 | J15: =J8/J14 -> 53039.017 | K15: =IF(AND(I15<>"", I15<>0, J15<>""), J15/I15, "") -> 0.3498199 | L15: =J15 -> 53039.017 | M15: =IF(AND(I15<>"",I15<>0,L15<>"",L15<>0),L15/I15,"") -> 0.3498199 | N15: =IF(AND(J15<>0, J15<>"", I15<>0, I15<>""), L15-I15, "") -> -98579.048 | P15: =IF(AND(O15<>"", O15<>0, L15<>"", L15<>0), -O15+L15, "") | Q15: =IF(AND(P15<>"", P15<>0, O15<>0, O15<>""), P15/O15, "")
F16: Отставание/Перевыполнение | J16: =J8-I15*J14 -> -1774422.9 | K16: =IF(AND(I16<>"", I16<>0, J16<>""), J16/I16, "") | L16: =J16 -> -1774422.9 | M16: =IF(AND(I16<>"",I16<>0,L16<>"",L16<>0),L16/I16,"") | N16: =IF(AND(J16<>0, J16<>"", I16<>0, I16<>""), L16-I16, "") | P16: =IF(AND(O16<>"", O16<>0, L16<>"", L16<>0), -O16+L16, "") | Q16: =IF(AND(P16<>"", P16<>0, O16<>0, O16<>""), P16/O16, "") | S16: UNOde50
F17: Трафик | I17: ='Ялта, Ленина, 18'!I17/График!AJ31*График!AJ28 -> 793.99166 | J17: =I50 -> 734 | K17: =IF(AND(I17<>"", I17<>0, J17<>""), J17/I17, "") -> 0.92444297 | L17: =J17/J14*I14 -> 734 | M17: =IF(AND(I17<>"",I17<>0,L17<>"",L17<>0),L17/I17,"") -> 0.92444297 | N17: =IF(AND(J17<>0, J17<>"", I17<>0, I17<>""), L17-I17, "") -> -59.991655 | P17: =IF(AND(O17<>"", O17<>0, L17<>"", L17<>0), -O17+L17, "") | Q17: =IF(AND(P17<>"", P17<>0, O17<>0, O17<>""), P17/O17, "")
K18: =IF(AND(I18<>"", I18<>0, J18<>""), J18/I18, "") | L18: =J18 -> 0 | M18: =IF(AND(I18<>"",I18<>0,L18<>"",L18<>0),L18/I18,"") | N18: =IF(AND(J18<>0, J18<>"", I18<>0, I18<>""), L18-I18, "") | O18: 0 | P18: =IF(AND(O18<>"", O18<>0, L18<>"", L18<>0), -O18+L18, "") | Q18: =IF(AND(P18<>"", P18<>0, O18<>0, O18<>""), P18/O18, "") | S18: ='Ялта, Ленина, 18'!S18*График!AJ28/График!AJ31 -> 272934.63 | T18: =K50 -> 225849.35
K19: =IF(AND(I19<>"", I19<>0, J19<>""), J19/I19, "") | L19: =J19 -> 0 | M19: =IF(AND(I19<>"",I19<>0,L19<>"",L19<>0),L19/I19,"") | N19: =IF(AND(J19<>0, J19<>"", I19<>0, I19<>""), L19-I19, "") | O19: 0 | P19: =IF(AND(O19<>"", O19<>0, L19<>"", L19<>0), -O19+L19, "") | Q19: =IF(AND(P19<>"", P19<>0, O19<>0, O19<>""), P19/O19, "") | S19: =T18/S18 -> 0.82748513 | T19: =S19/J14*I14 -> 0.82748513
F20: Конверсия план/факт | I20: ='Ялта, Ленина, 18'!I20 -> 0.18 | J20: =N50 -> 0.1239782 | K20: =J20/I20 -> 0.68876779 | L20: =IF(AND(K8<>0,I14<>0,I50<>0),(I50*N50+(I50/K8-I50)*I20)/(I50/K8),0) -> 0.14331096 | M20: =IF(AND(I20<>"",I20<>0,L20<>"",L20<>0),L20/I20,"") -> 0.79617198 | N20: =IF(AND(J20<>0, J20<>"", I20<>0, I20<>""), L20-I20, "") -> -0.036689044 | P20: =IF(AND(O20<>"", O20<>0, L20<>"", L20<>0), -O20+L20, "") | Q20: =IF(AND(P20<>"", P20<>0, O20<>0, O20<>""), P20/O20, "")
B22: Факт продаж за месяц | O22: % выполнения дневного плана | P22: Раcпределение плана по дням
B23: Дата | C23: День недели | D23: Выручка (руб) | E23: Кол-во единиц (шт.) | F23: Средняя стоимость изделия (руб.) | G23: Количество чеков (шт.) | H23: Средняя сумма чека (руб.) | I23: Трафик | J23: Длина чека (шт.) | K23: UNOde50 | L23: IS | M23: Agafi | N23: Конверсия (%) | P23: выручка, план | Q23: кол-во ед, план | R23: Кол-во чеков, план | S23: выручка, скорректир.план | T23: кол-во ед, скорр. план | U23: кол-во чеков, скорр. план | V23: Коэфф. Дня Недели | W23: Специфика месяца
B24: 1 | C24: 2 | D24: 3 | E24: в | F24: 5 | G24: 6 | H24: 7 | I24: 8 | J24: 9 | K24: 10 | L24: 11 | M24: 12 | N24: 13 | P24: 1 | Q24: 2 | R24: 3 | S24: 4 | T24: 5 | U24: 6 | V24: 10 | W24: 11
A25: 1 | B25: 45870 | C25: пт | D25: =14392+35091 -> 49483 | E25: 10 | F25: =IF(AND(E25<>"",E25<>0),D25/E25,"") -> 4948.3 | G25: 5 | H25: =IF(AND(G25<>"",G25<>0),D25/G25,"") -> 9896.6 | I25: 20 | J25: =IF(AND(G25<>"",G25<>0),E25/G25,"") -> 2 | K25: 14392 | N25: =IF(AND(I25<>"",I25<>0),G25/I25,"") -> 0.25 | O25: =D25/P25 -> 0.7692878 | P25: =$I$8*V25*W25/SUMPRODUCT($W$25:$W$49,$V$25:$V$49) -> 64323.131 | Q25: =$I$9*V25*W25/SUMPRODUCT($W$25:$W$49,$V$25:$V$49) -> 10.720522 | R25: =IF($I$12="","",Q25/$I$12) -> 6.3061893 | S25: =IF(D25<>"",D25,P25) -> 49483 | T25: =IF(E25<>"",E25,Q25) -> 10 | U25: =IF(G25<>"",G25,R25) -> 5 | V25: 0.9004852 | W25: 0.9004852
A26: 2 | B26: 45871 | C26: сб | D26: =11383+16579 -> 27962 | E26: 4 | F26: =IF(AND(E26<>"",E26<>0),D26/E26,"") -> 6990.5 | G26: 4 | H26: =IF(AND(G26<>"",G26<>0),D26/G26,"") -> 6990.5 | I26: 30 | J26: =IF(AND(G26<>"",G26<>0),E26/G26,"") -> 1 | K26: 11383 | N26: =IF(AND(I26<>"",I26<>0),G26/I26,"") -> 0.13333333 | O26: =D26/P26 -> 0.31301666 | P26: =$I$8*V26*W26/SUMPRODUCT($W$25:$W$49,$V$25:$V$49) -> 89330.708 | Q26: =$I$9*V26*W26/SUMPRODUCT($W$25:$W$49,$V$25:$V$49) -> 14.888451 | R26: =IF($I$12="","",Q26/$I$12) -> 8.7579125 | S26: =IF(W26<>"",IF(D26<>"",D26,($I$8-SUM($S$25:S25))*V26*W26/SUMPRODUCT($W26:$W$55,$V26:$V$55)),"") -> 27962 | T26: =IF(W26<>"",IF(E26<>"",E26,($I$9-SUM($T$25:T25))*V26*W26/SUMPRODUCT($W26:$W$55,$V26:$V$55)),"") -> 4 | U26: =IF(W26<>"",IF($I$12<>"",IF(G26<>"",G26,($I$9/$I$12-SUM($U$25:U25))*V26*W26/SUMPRODUCT($W26:$W$55,$V26:$V$55)),""),"") -> 4 | V26: 1.0611906 | W26: 1.0611906
A27: 3 | B27: 45874 | C27: вт | D27: 30745 | E27: 7 | F27: =IF(AND(E27<>"",E27<>0),D27/E27,"") -> 4392.1429 | G27: 4 | H27: =IF(AND(G27<>"",G27<>0),D27/G27,"") -> 7686.25 | I27: 25 | J27: =IF(AND(G27<>"",G27<>0),E27/G27,"") -> 1.75 | N27: =IF(AND(I27<>"",I27<>0),G27/I27,"") -> 0.16 | O27: =D27/P27 -> 0.26915223 | P27: =$I$8*V27*W27/SUMPRODUCT($W$25:$W$49,$V$25:$V$49) -> 114229.04 | Q27: =$I$9*V27*W27/SUMPRODUCT($W$25:$W$49,$V$25:$V$49) -> 19.038173 | R27: =IF($I$12="","",Q27/$I$12) -> 11.198925 | S27: =IF(W27<>"",IF(D27<>"",D27,($I$8-SUM($S$25:S26))*V27*W27/SUMPRODUCT($W27:$W$55,$V27:$V$55)),"") -> 30745 | T27: =IF(W27<>"",IF(E27<>"",E27,($I$9-SUM($T$25:T26))*V27*W27/SUMPRODUCT($W27:$W$55,$V27:$V$55)),"") -> 7 | U27: =IF(W27<>"",IF($I$12<>"",IF(G27<>"",G27,($I$9/$I$12-SUM($U$25:U26))*V27*W27/SUMPRODUCT($W27:$W$55,$V27:$V$55)),""),"") -> 4 | V27: 1.2 | W27: 1.2
A28: 4 | B28: 45875 | C28: ср | D28: =24903+18571 -> 43474 | E28: 5 | F28: =IF(AND(E28<>"",E28<>0),D28/E28,"") -> 8694.8 | G28: 5 | H28: =IF(AND(G28<>"",G28<>0),D28/G28,"") -> 8694.8 | I28: 25 | J28: =IF(AND(G28<>"",G28<>0),E28/G28,"") -> 1 | L28: 24903 | N28: =IF(AND(I28<>"",I28<>0),G28/I28,"") -> 0.2 | O28: =D28/P28 -> 0.54804419 | P28: =$I$8*V28*W28/SUMPRODUCT($W$25:$W$49,$V$25:$V$49) -> 79325.72 | Q28: =$I$9*V28*W28/SUMPRODUCT($W$25:$W$49,$V$25:$V$49) -> 13.220953 | R28: =IF($I$12="","",Q28/$I$12) -> 7.7770314 | S28: =IF(W28<>"",IF(D28<>"",D28,($I$8-SUM($S$25:S27))*V28*W28/SUMPRODUCT($W28:$W$60,$V28:$V$60)),"") -> 43474 | T28: =IF(W28<>"",IF(E28<>"",E28,($I$9-SUM($T$25:T27))*V28*W28/SUMPRODUCT($W28:$W$60,$V28:$V$60)),"") -> 5 | U28: =IF(W28<>"",IF($I$12<>"",IF(G28<>"",G28,($I$9/$I$12-SUM($U$25:U27))*V28*W28/SUMPRODUCT($W28:$W$60,$V28:$V$60)),""),"") -> 5 | V28: 1 | W28: 1
A29: 5 | B29: 45878 | C29: сб | D29: =24903+53110 -> 78013 | E29: 7 | F29: =IF(AND(E29<>"",E29<>0),D29/E29,"") -> 11144.714 | G29: 5 | H29: =IF(AND(G29<>"",G29<>0),D29/G29,"") -> 15602.6 | I29: 40 | J29: =IF(AND(G29<>"",G29<>0),E29/G29,"") -> 1.4 | L29: 24903 | M29: 28380 | N29: =IF(AND(I29<>"",I29<>0),G29/I29,"") -> 0.125 | O29: =D29/P29 -> 0.98345152 | P29: =$I$8*V29*W29/SUMPRODUCT($W$25:$W$49,$V$25:$V$49) -> 79325.72 | Q29: =$I$9*V29*W29/SUMPRODUCT($W$25:$W$49,$V$25:$V$49) -> 13.220953 | R29: =IF($I$12="","",Q29/$I$12) -> 7.7770314 | S29: =IF(W29<>"",IF(D29<>"",D29,($I$8-SUM($S$25:S28))*V29*W29/SUMPRODUCT($W29:$W$55,$V29:$V$55)),"") -> 78013 | T29: =IF(W29<>"",IF(E29<>"",E29,($I$9-SUM($T$25:T28))*V29*W29/SUMPRODUCT($W29:$W$55,$V29:$V$55)),"") -> 7 | U29: =IF(W29<>"",IF($I$12<>"",IF(G29<>"",G29,($I$9/$I$12-SUM($U$25:U28))*V29*W29/SUMPRODUCT($W29:$W$55,$V29:$V$55)),""),"") -> 5 | V29: 1 | W29: 1
A30: 6 | B30: 45879 | C30: вс | D30: =6991+50928+20158 -> 78077 | E30: 9 | F30: =IF(AND(E30<>"",E30<>0),D30/E30,"") -> 8675.2222 | G30: 6 | H30: =IF(AND(G30<>"",G30<>0),D30/G30,"") -> 13012.833 | I30: 40 | J30: =IF(AND(G30<>"",G30<>0),E30/G30,"") -> 1.5 | K30: 6991 | L30: 50928 | N30: =IF(AND(I30<>"",I30<>0),G30/I30,"") -> 0.15 | O30: =D30/P30 -> 0.98425832 | P30: =$I$8*V30*W30/SUMPRODUCT($W$25:$W$49,$V$25:$V$49) -> 79325.72 | Q30: =$I$9*V30*W30/SUMPRODUCT($W$25:$W$49,$V$25:$V$49) -> 13.220953 | R30: =IF($I$12="","",Q30/$I$12) -> 7.7770314 | S30: =IF(W30<>"",IF(D30<>"",D30,($I$8-SUM($S$25:S29))*V30*W30/SUMPRODUCT($W30:$W$55,$V30:$V$55)),"") -> 78077 | T30: =IF(W30<>"",IF(E30<>"",E30,($I$9-SUM($T$25:T29))*V30*W30/SUMPRODUCT($W30:$W$55,$V30:$V$55)),"") -> 9 | U30: =IF(W30<>"",IF($I$12<>"",IF(G30<>"",G30,($I$9/$I$12-SUM($U$25:U29))*V30*W30/SUMPRODUCT($W30:$W$55,$V30:$V$55)),""),"") -> 6 | V30: 1 | W30: 1
A31: 7 | B31: 45882 | C31: ср | D31: 86307 | E31: 12 | F31: =IF(AND(E31<>"",E31<>0),D31/E31,"") -> 7192.25 | G31: 8 | H31: =IF(AND(G31<>"",G31<>0),D31/G31,"") -> 10788.375 | I31: 50 | J31: =IF(AND(G31<>"",G31<>0),E31/G31,"") -> 1.5 | K31: 39983 | M31: 7390 | N31: =IF(AND(I31<>"",I31<>0),G31/I31,"") -> 0.16 | O31: =D31/P31 -> 1.0880078 | P31: =$I$8*V31*W31/SUMPRODUCT($W$25:$W$49,$V$25:$V$49) -> 79325.72 | Q31: =$I$9*V31*W31/SUMPRODUCT($W$25:$W$49,$V$25:$V$49) -> 13.220953 | R31: =IF($I$12="","",Q31/$I$12) -> 7.7770314 | S31: =IF(W31<>"",IF(D31<>"",D31,($I$8-SUM($S$25:S30))*V31*W31/SUMPRODUCT($W31:$W$55,$V31:$V$55)),"") -> 86307 | T31: =IF(W31<>"",IF(E31<>"",E31,($I$9-SUM($T$25:T30))*V31*W31/SUMPRODUCT($W31:$W$55,$V31:$V$55)),"") -> 12 | U31: =IF(W31<>"",IF($I$12<>"",IF(G31<>"",G31,($I$9/$I$12-SUM($U$25:U30))*V31*W31/SUMPRODUCT($W31:$W$55,$V31:$V$55)),""),"") -> 8 | V31: 1 | W31: 1
A32: 8 | B32: 45883 | C32: чт | D32: 76717 | E32: 10 | F32: =IF(AND(E32<>"",E32<>0),D32/E32,"") -> 7671.7 | G32: 5 | H32: =IF(AND(G32<>"",G32<>0),D32/G32,"") -> 15343.4 | I32: 50 | J32: =IF(AND(G32<>"",G32<>0),E32/G32,"") -> 2 | K32: 36570.35 | M32: 12680 | N32: =IF(AND(I32<>"",I32<>0),G32/I32,"") -> 0.1 | O32: =D32/P32 -> 0.96711382 | P32: =$I$8*V32*W32/SUMPRODUCT($W$25:$W$49,$V$25:$V$49) -> 79325.72 | Q32: =$I$9*V32*W32/SUMPRODUCT($W$25:$W$49,$V$25:$V$49) -> 13.220953 | R32: =IF($I$12="","",Q32/$I$12) -> 7.7770314 | S32: =IF(W32<>"",IF(D32<>"",D32,($I$8-SUM($S$25:S31))*V32*W32/SUMPRODUCT($W32:$W$55,$V32:$V$55)),"") -> 76717 | T32: =IF(W32<>"",IF(E31<>"",E31,($I$9-SUM($T$25:T31))*V32*W32/SUMPRODUCT($W32:$W$55,$V32:$V$55)),"") -> 12 | U32: =IF(W32<>"",IF($I$12<>"",IF(G32<>"",G32,($I$9/$I$12-SUM($U$25:U31))*V32*W32/SUMPRODUCT($W32:$W$55,$V32:$V$55)),""),"") -> 5 | V32: 1 | W32: 1
A33: 9 | B33: 45885 | C33: сб | D33: 49605 | E33: 10 | F33: =IF(AND(E33<>"",E33<>0),D33/E33,"") -> 4960.5 | G33: 6 | H33: =IF(AND(G33<>"",G33<>0),D33/G33,"") -> 8267.5 | I33: 35 | J33: =IF(AND(G33<>"",G33<>0),E33/G33,"") -> 1.6666667 | N33: =IF(AND(I33<>"",I33<>0),G33/I33,"") -> 0.17142857 | O33: =D33/P33 -> 0.62533312 | P33: =$I$8*V33*W33/SUMPRODUCT($W$25:$W$49,$V$25:$V$49) -> 79325.72 | Q33: =$I$9*V33*W33/SUMPRODUCT($W$25:$W$49,$V$25:$V$49) -> 13.220953 | R33: =IF($I$12="","",Q33/$I$12) -> 7.7770314 | S33: =IF(W33<>"",IF(D33<>"",D33,($I$8-SUM($S$25:S32))*V33*W33/SUMPRODUCT($W33:$W$55,$V33:$V$55)),"") -> 49605 | T33: =IF(W33<>"",IF(E33<>"",E33,($I$9-SUM($T$25:T32))*V33*W33/SUMPRODUCT($W33:$W$55,$V33:$V$55)),"") -> 10 | U33: =IF(W33<>"",IF($I$12<>"",IF(G33<>"",G33,($I$9/$I$12-SUM($U$25:U32))*V33*W33/SUMPRODUCT($W33:$W$55,$V33:$V$55)),""),"") -> 6 | V33: 1 | W33: 1
A34: 10 | B34: 45886 | C34: вс | D34: 46892 | E34: 11 | F34: =IF(AND(E34<>"",E34<>0),D34/E34,"") -> 4262.9091 | G34: 5 | H34: =IF(AND(G34<>"",G34<>0),D34/G34,"") -> 9378.4 | I34: 35 | J34: =IF(AND(G34<>"",G34<>0),E34/G34,"") -> 2.2 | N34: =IF(AND(I34<>"",I34<>0),G34/I34,"") -> 0.14285714 | O34: =D34/P34 -> 0.59113236 | P34: =$I$8*V34*W34/SUMPRODUCT($W$25:$W$49,$V$25:$V$49) -> 79325.72 | Q34: =$I$9*V34*W34/SUMPRODUCT($W$25:$W$49,$V$25:$V$49) -> 13.220953 | R34: =IF($I$12="","",Q34/$I$12) -> 7.7770314 | S34: =IF(W34<>"",IF(D34<>"",D34,($I$8-SUM($S$25:S33))*V34*W34/SUMPRODUCT($W34:$W$60,$V34:$V$60)),"") -> 46892 | T34: =IF(W34<>"",IF(E34<>"",E34,($I$9-SUM($T$25:T33))*V34*W34/SUMPRODUCT($W34:$W$60,$V34:$V$60)),"") -> 11 | U34: =IF(W34<>"",IF($I$12<>"",IF(G34<>"",G34,($I$9/$I$12-SUM($U$25:U33))*V34*W34/SUMPRODUCT($W34:$W$60,$V34:$V$60)),""),"") -> 5 | V34: 1 | W34: 1
A35: 11 | B35: 45889 | C35: ср | D35: =116530+21206+14265 -> 152001 | E35: 13 | F35: =IF(AND(E35<>"",E35<>0),D35/E35,"") -> 11692.385 | G35: 5 | H35: =IF(AND(G35<>"",G35<>0),D35/G35,"") -> 30400.2 | I35: 50 | J35: =IF(AND(G35<>"",G35<>0),E35/G35,"") -> 2.6 | K35: 116530 | L35: 21206 | N35: =IF(AND(I35<>"",I35<>0),G35/I35,"") -> 0.1 | O35: =D35/P35 -> 1.9161629 | P35: =$I$8*V35*W35/SUMPRODUCT($W$25:$W$49,$V$25:$V$49) -> 79325.72 | Q35: =$I$9*V35*W35/SUMPRODUCT($W$25:$W$49,$V$25:$V$49) -> 13.220953 | R35: =IF($I$12="","",Q35/$I$12) -> 7.7770314 | S35: =IF(W35<>"",IF(D35<>"",D35,($I$8-SUM($S$25:S34))*V35*W35/SUMPRODUCT($W35:$W$55,$V35:$V$55)),"") -> 152001 | T35: =IF(W35<>"",IF(E35<>"",E35,($I$9-SUM($T$25:T34))*V35*W35/SUMPRODUCT($W35:$W$55,$V35:$V$55)),"") -> 13 | U35: =IF(W35<>"",IF($I$12<>"",IF(G35<>"",G35,($I$9/$I$12-SUM($U$25:U34))*V35*W35/SUMPRODUCT($W35:$W$55,$V35:$V$55)),""),"") -> 5 | V35: 1 | W35: 1
A36: 12 | B36: 45890 | C36: чт | D36: =6392+45615 -> 52007 | E36: 11 | F36: =IF(AND(E36<>"",E36<>0),D36/E36,"") -> 4727.9091 | G36: 6 | H36: =IF(AND(G36<>"",G36<>0),D36/G36,"") -> 8667.8333 | I36: 75 | J36: =IF(AND(G36<>"",G36<>0),E36/G36,"") -> 1.8333333 | M36: 6392 | N36: =IF(AND(I36<>"",I36<>0),G36/I36,"") -> 0.08 | O36: =D36/P36 -> 0.65561334 | P36: =$I$8*V36*W36/SUMPRODUCT($W$25:$W$49,$V$25:$V$49) -> 79325.72 | Q36: =$I$9*V36*W36/SUMPRODUCT($W$25:$W$49,$V$25:$V$49) -> 13.220953 | R36: =IF($I$12="","",Q36/$I$12) -> 7.7770314 | S36: =IF(W36<>"",IF(D36<>"",D36,($I$8-SUM($S$25:S35))*V36*W36/SUMPRODUCT($W36:$W$55,$V36:$V$55)),"") -> 52007 | T36: =IF(W36<>"",IF(E36<>"",E36,($I$9-SUM($T$25:T35))*V36*W36/SUMPRODUCT($W36:$W$55,$V36:$V$55)),"") -> 11 | U36: =IF(W36<>"",IF($I$12<>"",IF(G36<>"",G36,($I$9/$I$12-SUM($U$25:U35))*V36*W36/SUMPRODUCT($W36:$W$55,$V36:$V$55)),""),"") -> 6 | V36: 1 | W36: 1
A37: 13 | B37: 45892 | C37: сб | D37: =9903+40123 -> 50026 | E37: 9 | F37: =IF(AND(E37<>"",E37<>0),D37/E37,"") -> 5558.4444 | G37: 6 | H37: =IF(AND(G37<>"",G37<>0),D37/G37,"") -> 8337.6667 | I37: 57 | J37: =IF(AND(G37<>"",G37<>0),E37/G37,"") -> 1.5 | L37: 9903 | N37: =IF(AND(I37<>"",I37<>0),G37/I37,"") -> 0.10526316 | O37: =D37/P37 -> 0.63064035 | P37: =$I$8*V37*W37/SUMPRODUCT($W$25:$W$49,$V$25:$V$49) -> 79325.72 | Q37: =$I$9*V37*W37/SUMPRODUCT($W$25:$W$49,$V$25:$V$49) -> 13.220953 | R37: =IF($I$12="","",Q37/$I$12) -> 7.7770314 | S37: =IF(W37<>"",IF(D37<>"",D37,($I$8-SUM($S$25:S36))*V37*W37/SUMPRODUCT($W37:$W$55,$V37:$V$55)),"") -> 50026 | T37: =IF(W37<>"",IF(E37<>"",E37,($I$9-SUM($T$25:T36))*V37*W37/SUMPRODUCT($W37:$W$55,$V37:$V$55)),"") -> 9 | U37: =IF(W37<>"",IF($I$12<>"",IF(G37<>"",G37,($I$9/$I$12-SUM($U$25:U36))*V37*W37/SUMPRODUCT($W37:$W$55,$V37:$V$55)),""),"") -> 6 | V37: 1 | W37: 1
A38: 14 | B38: 45893 | C38: вс | D38: 10575 | E38: 3 | F38: =IF(AND(E38<>"",E38<>0),D38/E38,"") -> 3525 | G38: 2 | H38: =IF(AND(G38<>"",G38<>0),D38/G38,"") -> 5287.5 | I38: 54 | J38: =IF(AND(G38<>"",G38<>0),E38/G38,"") -> 1.5 | N38: =IF(AND(I38<>"",I38<>0),G38/I38,"") -> 0.037037037 | O38: =D38/P38 -> 0.13331111 | P38: =$I$8*V38*W38/SUMPRODUCT($W$25:$W$49,$V$25:$V$49) -> 79325.72 | Q38: =$I$9*V38*W38/SUMPRODUCT($W$25:$W$49,$V$25:$V$49) -> 13.220953 | R38: =IF($I$12="","",Q38/$I$12) -> 7.7770314 | S38: =IF(W38<>"",IF(D38<>"",D38,($I$8-SUM($S$25:S37))*V38*W38/SUMPRODUCT($W38:$W$55,$V38:$V$55)),"") -> 10575 | T38: =IF(W38<>"",IF(E38<>"",E38,($I$9-SUM($T$25:T37))*V38*W38/SUMPRODUCT($W38:$W$55,$V38:$V$55)),"") -> 3 | U38: =IF(W38<>"",IF($I$12<>"",IF(G38<>"",G38,($I$9/$I$12-SUM($U$25:U37))*V38*W38/SUMPRODUCT($W38:$W$55,$V38:$V$55)),""),"") -> 2 | V38: 1 | W38: 1
A39: 15 | B39: 45896 | C39: ср | D39: 18768 | E39: 4 | F39: =IF(AND(E39<>"",E39<>0),D39/E39,"") -> 4692 | G39: 4 | H39: =IF(AND(G39<>"",G39<>0),D39/G39,"") -> 4692 | I39: 45 | J39: =IF(AND(G39<>"",G39<>0),E39/G39,"") -> 1 | N39: =IF(AND(I39<>"",I39<>0),G39/I39,"") -> 0.088888889 | O39: =D39/P39 -> 0.23659413 | P39: =$I$8*V39*W39/SUMPRODUCT($W$25:$W$49,$V$25:$V$49) -> 79325.72 | Q39: =$I$9*V39*W39/SUMPRODUCT($W$25:$W$49,$V$25:$V$49) -> 13.220953 | R39: =IF($I$12="","",Q39/$I$12) -> 7.7770314 | S39: =IF(W39<>"",IF(D39<>"",D39,($I$8-SUM($S$25:S38))*V39*W39/SUMPRODUCT($W39:$W$60,$V39:$V$60)),"") -> 18768 | T39: =IF(W39<>"",IF(E39<>"",E39,($I$9-SUM($T$25:T38))*V39*W39/SUMPRODUCT($W39:$W$60,$V39:$V$60)),"") -> 4 | U39: =IF(W39<>"",IF($I$12<>"",IF(G39<>"",G39,($I$9/$I$12-SUM($U$25:U38))*V39*W39/SUMPRODUCT($W39:$W$60,$V39:$V$60)),""),"") -> 4 | V39: 1 | W39: 1
A40: 16 | B40: 45897 | C40: чт | D40: 15793 | E40: 1 | F40: =IF(AND(E40<>"",E40<>0),D40/E40,"") -> 15793 | G40: 2 | H40: =IF(AND(G40<>"",G40<>0),D40/G40,"") -> 7896.5 | I40: 42 | J40: =IF(AND(G40<>"",G40<>0),E40/G40,"") -> 0.5 | N40: =IF(AND(I40<>"",I40<>0),G40/I40,"") -> 0.047619048 | O40: =D40/P40 -> 0.19909053 | P40: =$I$8*V40*W40/SUMPRODUCT($W$25:$W$49,$V$25:$V$49) -> 79325.72 | Q40: =$I$9*V40*W40/SUMPRODUCT($W$25:$W$49,$V$25:$V$49) -> 13.220953 | R40: =IF($I$12="","",Q40/$I$12) -> 7.7770314 | S40: =IF(W40<>"",IF(D40<>"",D40,($I$8-SUM($S$25:S39))*V40*W40/SUMPRODUCT($W40:$W$60,$V40:$V$60)),"") -> 15793 | T40: =IF(W40<>"",IF(E40<>"",E40,($I$9-SUM($T$25:T39))*V40*W40/SUMPRODUCT($W40:$W$60,$V40:$V$60)),"") -> 1 | U40: =IF(W40<>"",IF($I$12<>"",IF(G40<>"",G40,($I$9/$I$12-SUM($U$25:U39))*V40*W40/SUMPRODUCT($W40:$W$60,$V40:$V$60)),""),"") -> 2 | V40: 1 | W40: 1
A41: 17 | B41: 45899 | C41: сб | D41: 8085 | E41: 3 | F41: =IF(AND(E41<>"",E41<>0),D41/E41,"") -> 2695 | G41: 3 | H41: =IF(AND(G41<>"",G41<>0),D41/G41,"") -> 2695 | I41: 28 | J41: =IF(AND(G41<>"",G41<>0),E41/G41,"") -> 1 | N41: =IF(AND(I41<>"",I41<>0),G41/I41,"") -> 0.10714286 | O41: =D41/P41 -> 0.10192155 | P41: =$I$8*V41*W41/SUMPRODUCT($W$25:$W$49,$V$25:$V$49) -> 79325.72 | Q41: =$I$9*V41*W41/SUMPRODUCT($W$25:$W$49,$V$25:$V$49) -> 13.220953 | R41: =IF($I$12="","",Q41/$I$12) -> 7.7770314 | S41: =IF(W41<>"",IF(D41<>"",D41,($I$8-SUM($S$25:S40))*V41*W41/SUMPRODUCT($W41:$W$60,$V41:$V$60)),"") -> 8085 | T41: =IF(W41<>"",IF(E41<>"",E41,($I$9-SUM($T$25:T40))*V41*W41/SUMPRODUCT($W41:$W$60,$V41:$V$60)),"") -> 3 | U41: =IF(W41<>"",IF($I$12<>"",IF(G41<>"",G41,($I$9/$I$12-SUM($U$25:U40))*V41*W41/SUMPRODUCT($W41:$W$60,$V41:$V$60)),""),"") -> 3 | V41: 1 | W41: 1
A42: 18 | B42: 45900 | C42: вс | D42: =21906+32731 -> 54637 | E42: 10 | F42: =IF(AND(E42<>"",E42<>0),D42/E42,"") -> 5463.7 | G42: 7 | H42: =IF(AND(G42<>"",G42<>0),D42/G42,"") -> 7805.2857 | I42: 33 | J42: =IF(AND(G42<>"",G42<>0),E42/G42,"") -> 1.4285714 | L42: 21906 | N42: =IF(AND(I42<>"",I42<>0),G42/I42,"") -> 0.21212121 | O42: =D42/P42 -> 0.68876778 | P42: =$I$8*V42*W42/SUMPRODUCT($W$25:$W$49,$V$25:$V$49) -> 79325.72 | Q42: =$I$9*V42*W42/SUMPRODUCT($W$25:$W$49,$V$25:$V$49) -> 13.220953 | R42: =IF($I$12="","",Q42/$I$12) -> 7.7770314 | S42: =IF(W42<>"",IF(D42<>"",D42,($I$8-SUM($S$25:S41))*V42*W42/SUMPRODUCT($W42:$W$60,$V42:$V$60)),"") -> 54637 | T42: =IF(W42<>"",IF(E42<>"",E42,($I$9-SUM($T$25:T41))*V42*W42/SUMPRODUCT($W42:$W$60,$V42:$V$60)),"") -> 10 | U42: =IF(W42<>"",IF($I$12<>"",IF(G42<>"",G42,($I$9/$I$12-SUM($U$25:U41))*V42*W42/SUMPRODUCT($W42:$W$60,$V42:$V$60)),""),"") -> 7 | V42: 1 | W42: 1
A43: 19 | F43: =IF(AND(E43<>"",E43<>0),D43/E43,"") | H43: =IF(AND(G43<>"",G43<>0),D43/G43,"") | J43: =IF(AND(G43<>"",G43<>0),E43/G43,"") | N43: =IF(AND(I43<>"",I43<>0),G43/I43,"") | O43: =D43/P43 -> #DIV/0! | P43: =$I$8*V43*W43/SUMPRODUCT($W$25:$W$49,$V$25:$V$49) -> 0 | Q43: =$I$9*V43*W43/SUMPRODUCT($W$25:$W$49,$V$25:$V$49) -> 0 | R43: =IF($I$12="","",Q43/$I$12) -> 0 | S43: =IF(W43<>"",IF(D43<>"",D43,($I$8-SUM($S$25:S42))*V43*W43/SUMPRODUCT($W43:$W$60,$V43:$V$60)),"") | T43: =IF(W43<>"",IF(E43<>"",E43,($I$9-SUM($T$25:T42))*V43*W43/SUMPRODUCT($W43:$W$60,$V43:$V$60)),"") | U43: =IF(W43<>"",IF($I$12<>"",IF(G43<>"",G43,($I$9/$I$12-SUM($U$25:U42))*V43*W43/SUMPRODUCT($W43:$W$60,$V43:$V$60)),""),"")
A44: 20 | F44: =IF(AND(E44<>"",E44<>0),D44/E44,"") | H44: =IF(AND(G44<>"",G44<>0),D44/G44,"") | J44: =IF(AND(G44<>"",G44<>0),E44/G44,"") | N44: =IF(AND(I44<>"",I44<>0),G44/I44,"") | O44: =D44/P44 -> #DIV/0! | P44: =$I$8*V44*W44/SUMPRODUCT($W$25:$W$49,$V$25:$V$49) -> 0 | Q44: =$I$9*V44*W44/SUMPRODUCT($W$25:$W$49,$V$25:$V$49) -> 0 | R44: =IF($I$12="","",Q44/$I$12) -> 0 | S44: =IF(W44<>"",IF(D44<>"",D44,($I$8-SUM($S$25:S43))*V44*W44/SUMPRODUCT($W44:$W$60,$V44:$V$60)),"") | T44: =IF(W44<>"",IF(E44<>"",E44,($I$9-SUM($T$25:T43))*V44*W44/SUMPRODUCT($W44:$W$60,$V44:$V$60)),"") | U44: =IF(W44<>"",IF($I$12<>"",IF(G44<>"",G44,($I$9/$I$12-SUM($U$25:U43))*V44*W44/SUMPRODUCT($W44:$W$60,$V44:$V$60)),""),"")
A45: 21 | B45: 45872 | C45: вс | D45: 4161.3 | E45: 1 | F45: =IF(AND(E45<>"",E45<>0),D45/E45,"") -> 4161.3 | G45: 1 | H45: =IF(AND(G45<>"",G45<>0),D45/G45,"") -> 4161.3 | J45: =IF(AND(G45<>"",G45<>0),E45/G45,"") -> 1 | N45: =IF(AND(I45<>"",I45<>0),G45/I45,"") | O45: =D45/P45 -> #DIV/0! | P45: =$I$8*V45*W45/SUMPRODUCT($W$25:$W$49,$V$25:$V$49) -> 0 | Q45: =$I$9*V45*W45/SUMPRODUCT($W$25:$W$49,$V$25:$V$49) -> 0 | R45: =IF($I$12="","",Q45/$I$12) -> 0 | S45: =IF(W45<>"",IF(D45<>"",D45,($I$8-SUM($S$25:S44))*V45*W45/SUMPRODUCT($W45:$W$60,$V45:$V$60)),"") | T45: =IF(W45<>"",IF(E45<>"",E45,($I$9-SUM($T$25:T44))*V45*W45/SUMPRODUCT($W45:$W$60,$V45:$V$60)),"") | U45: =IF(W45<>"",IF($I$12<>"",IF(G45<>"",G45,($I$9/$I$12-SUM($U$25:U44))*V45*W45/SUMPRODUCT($W45:$W$60,$V45:$V$60)),""),"")
A46: 22 | B46: 45880 | C46: пн | D46: 6000 | E46: 1 | F46: =IF(AND(E46<>"",E46<>0),D46/E46,"") -> 6000 | G46: 1 | H46: =IF(AND(G46<>"",G46<>0),D46/G46,"") -> 6000 | J46: =IF(AND(G46<>"",G46<>0),E46/G46,"") -> 1 | N46: =IF(AND(I46<>"",I46<>0),G46/I46,"") | O46: =D46/P46 -> #DIV/0! | P46: =$I$8*V46*W46/SUMPRODUCT($W$25:$W$49,$V$25:$V$49) -> 0 | Q46: =$I$9*V46*W46/SUMPRODUCT($W$25:$W$49,$V$25:$V$49) -> 0 | R46: =IF($I$12="","",Q46/$I$12) -> 0 | S46: =IF(W46<>"",IF(D46<>"",D46,($I$8-SUM($S$25:S45))*V46*W46/SUMPRODUCT($W46:$W$60,$V46:$V$60)),"") | T46: =IF(W46<>"",IF(E46<>"",E46,($I$9-SUM($T$25:T45))*V46*W46/SUMPRODUCT($W46:$W$60,$V46:$V$60)),"") | U46: =IF(W46<>"",IF($I$12<>"",IF(G46<>"",G46,($I$9/$I$12-SUM($U$25:U45))*V46*W46/SUMPRODUCT($W46:$W$60,$V46:$V$60)),""),"")
A47: 23 | B47: 45895 | C47: вт | D47: 15374 | E47: 3 | F47: =IF(AND(E47<>"",E47<>0),D47/E47,"") -> 5124.6667 | G47: 1 | H47: =IF(AND(G47<>"",G47<>0),D47/G47,"") -> 15374 | J47: =IF(AND(G47<>"",G47<>0),E47/G47,"") -> 3 | N47: =IF(AND(I47<>"",I47<>0),G47/I47,"") | O47: =D47/P47 -> #DIV/0! | P47: =$I$8*V47*W47/SUMPRODUCT($W$25:$W$49,$V$25:$V$49) -> 0 | Q47: =$I$9*V47*W47/SUMPRODUCT($W$25:$W$49,$V$25:$V$49) -> 0 | R47: =IF($I$12="","",Q47/$I$12) -> 0 | S47: =IF(W47<>"",IF(D47<>"",D47,($I$8-SUM($S$25:S46))*V47*W47/SUMPRODUCT($W47:$W$60,$V47:$V$60)),"") | T47: =IF(W47<>"",IF(E47<>"",E47,($I$9-SUM($T$25:T46))*V47*W47/SUMPRODUCT($W47:$W$60,$V47:$V$60)),"") | U47: =IF(W47<>"",IF($I$12<>"",IF(G47<>"",G47,($I$9/$I$12-SUM($U$25:U46))*V47*W47/SUMPRODUCT($W47:$W$60,$V47:$V$60)),""),"")
A48: 24 | F48: =IF(AND(E48<>"",E48<>0),D48/E48,"") | H48: =IF(AND(G48<>"",G48<>0),D48/G48,"") | J48: =IF(AND(G48<>"",G48<>0),E48/G48,"") | N48: =IF(AND(I48<>"",I48<>0),G48/I48,"") | O48: =D48/P48 -> #DIV/0! | P48: =$I$8*V48*W48/SUMPRODUCT($W$25:$W$49,$V$25:$V$49) -> 0 | Q48: =$I$9*V48*W48/SUMPRODUCT($W$25:$W$49,$V$25:$V$49) -> 0 | R48: =IF($I$12="","",Q48/$I$12) -> 0 | S48: =IF(W48<>"",IF(D48<>"",D48,($I$8-SUM($S$25:S47))*V48*W48/SUMPRODUCT($W48:$W$60,$V48:$V$60)),"") | T48: =IF(W48<>"",IF(E48<>"",E48,($I$9-SUM($T$25:T47))*V48*W48/SUMPRODUCT($W48:$W$60,$V48:$V$60)),"") | U48: =IF(W48<>"",IF($I$12<>"",IF(G48<>"",G48,($I$9/$I$12-SUM($U$25:U47))*V48*W48/SUMPRODUCT($W48:$W$60,$V48:$V$60)),""),"")
A49: 25 | F49: =IF(AND(E49<>"",E49<>0),D49/E49,"") | H49: =IF(AND(G49<>"",G49<>0),D49/G49,"") | J49: =IF(AND(G49<>"",G49<>0),E49/G49,"") | N49: =IF(AND(I49<>"",I49<>0),G49/I49,"") | O49: =D49/P49 -> #DIV/0! | P49: =$I$8*V49*W49/SUMPRODUCT($W$25:$W$49,$V$25:$V$49) -> 0 | Q49: =$I$9*V49*W49/SUMPRODUCT($W$25:$W$49,$V$25:$V$49) -> 0 | R49: =IF($I$12="","",Q49/$I$12) -> 0 | S49: =IF(W49<>"",IF(D49<>"",D49,($I$8-SUM($S$25:S48))*V49*W49/SUMPRODUCT($W49:$W$60,$V49:$V$60)),"") | T49: =IF(W49<>"",IF(E49<>"",E49,($I$9-SUM($T$25:T48))*V49*W49/SUMPRODUCT($W49:$W$60,$V49:$V$60)),"") | U49: =IF(W49<>"",IF($I$12<>"",IF(G49<>"",G49,($I$9/$I$12-SUM($U$25:U48))*V49*W49/SUMPRODUCT($W49:$W$60,$V49:$V$60)),""),"")
B50: итого | D50: =SUM(D25:D49) -> 954702.3 | E50: =SUM(E25:E49) -> 144 | F50: =IF(AND(E50<>"",E50<>0),D50/E50,"") -> 6629.8771 | G50: =SUM(G25:G49) -> 91 | H50: =IF(AND(G50<>"",G50<>0),D50/G50,"") -> 10491.234 | I50: =SUM(I25:I49) -> 734 | J50: =IF(AND(G50<>"",G50<>0),E50/G50,"") -> 1.5824176 | K50: =SUM(K25:K49) -> 225849.35 | L50: =SUM(L25:L49) -> 153749 | M50: =SUM(M25:M49) -> 54842 | N50: =IF(AND(I50<>"",I50<>0),G50/I50,"") -> 0.1239782 | O50: =D50/P50 -> 0.65490658 | P50: =SUM(P25:P49) -> 1457768.7 | Q50: =SUM(Q25:Q49) -> 242.96145 | R50: =SUM(R25:R49) -> 142.9185 | S50: =SUM(S25:S49) -> 929167 | T50: =SUM(T25:T49) -> 141 | U50: =SUM(U25:U49) -> 88
D51: =SUMIF(D25:D49,"",P25:P49)+D50 -> 954702.3

Sheet Яковенко А. К. 
B1: =TODAY()-1 -> 45909
B2: (отчетная дата) | J2: ЕЖЕДНЕВНЫЙ ОТЧЕТ О ПРОДАЖАХ
B3: Осталось до выполнения плана!!! | J3: =График!B27 -> Яковенко Алина
C4: =I8-D49 -> 204593.31 | E4: =IF(I8<>0,C4/I8,0) -> 0.1354864
F6: Целевые показатели
F7: Показатель | I7: План | J7: Факт | K7: % выполнения | L7: Прогноз выполнения | M7: % выполнения по прогнозу | N7: Отклонение | O7: Факт аналогичного месяца прошлого года | P7: Отклонение LFL
F8: Выручка | I8: ='Ялта, Ленина, 18'!I8/График!AJ31*График!AJ27 -> 1510065.3 | J8: =D49 -> 1305472 | K8: =IF(AND(I8<>"",I8<>0,J8<>""),J8/I8,"") -> 0.8645136 | L8: =IF(SUMIF($D$25:$D$48,">=0",$P$25:$P$48)<>0,I8*D49/SUMIF($D$25:$D$48,">=0",$P$25:$P$48),0) -> 1305472 | M8: =IF(AND(I8<>"",I8<>0,L8<>"",L8<>0),L8/I8,"") -> 0.8645136 | N8: =IF(AND(J8<>0,J8<>"",I8<>0,I8<>""),L8-I8,"") -> -204593.31 | P8: =IF(AND(O8<>"",O8<>0,L8<>"",L8<>0),-O8+L8,"") | Q8: =IF(AND(P8<>"",P8<>0,O8<>0,O8<>""),P8/O8,"")
F9: Кол-во изделий | I9: =I8/I11 -> 251.67755 | J9: =E49 -> 249 | K9: =IF(AND(I9<>"",I9<>0,J9<>""),J9/I9,"") -> 0.98936118 | L9: =IF(SUMIF($E$25:$E$48,">=0",$Q$25:$Q$48)<>0,I9*E49/SUMIF($E$25:$E$48,">=0",$Q$25:$Q$48),0) -> 249 | M9: =IF(AND(I9<>"",I9<>0,L9<>"",L9<>0),L9/I9,"") -> 0.98936118 | N9: =IF(AND(J9<>0,J9<>"",I9<>0,I9<>""),L9-I9,"") -> -2.6775522 | O9: =O8/O11 -> #DIV/0! | P9: =IF(AND(O9<>"",O9<>0,L9<>"",L9<>0),-O9+L9,"") -> #DIV/0! | Q9: =IF(AND(P9<>"",P9<>0,O9<>0,O9<>""),P9/O9,"") -> #DIV/0!
F10: Средний чек | I10: =I11*I12 -> 10200 | J10: =H49 -> 9742.3284 | K10: =IF(AND(I10<>"",I10<>0,J10<>""),J10/I10,"") -> 0.95513023 | L10: =J10 -> 9742.3284 | M10: =IF(AND(I10<>"",I10<>0,L10<>"",L10<>0),L10/I10,"") -> 0.95513023 | N10: =IF(AND(J10<>0,J10<>"",I10<>0,I10<>""),L10-I10,"") -> -457.67164 | O10: =O11*O12 -> 0 | P10: =IF(AND(O10<>"",O10<>0,L10<>"",L10<>0),-O10+L10,"") | Q10: =IF(AND(P10<>"",P10<>0,O10<>0,O10<>""),P10/O10,"") | S10: IS | V10: =M23 -> Agafi
F11: Средняя стоимость изделия | I11: ='Ялта, Ленина, 18'!I11 -> 6000 | J11: =F49 -> 5242.8594 | K11: =IF(AND(I11<>"",I11<>0,J11<>""),J11/I11,"") -> 0.87380991 | L11: =IF(L9>0,L8/L9,"") -> 5242.8594 | M11: =IF(AND(I11<>"",I11<>0,L11<>"",L11<>0),L11/I11,"") -> 0.87380991 | N11: =IF(AND(J11<>0,J11<>"",I11<>0,I11<>""),L11-I11,"") -> -757.14056 | P11: =IF(AND(O11<>"",O11<>0,L11<>"",L11<>0),-O11+L11,"") | Q11: =IF(AND(P11<>"",P11<>0,O11<>0,O11<>""),P11/O11,"")
F12: Длина чека | I12: ='Ялта, Ленина, 18'!I12 -> 1.7 | J12: =J49 -> 1.858209 | K12: =IF(AND(I12<>"",I12<>0,J12<>""),J12/I12,"") -> 1.0930641 | L12: =J12 -> 1.858209 | M12: =IF(AND(I12<>"",I12<>0,L12<>"",L12<>0),L12/I12,"") -> 1.0930641 | N12: =IF(AND(J12<>0,J12<>"",I12<>0,I12<>""),L12-I12,"") -> 0.15820896 | P12: =IF(AND(O12<>"",O12<>0,L12<>"",L12<>0),-O12+L12,"") | Q12: =IF(AND(P12<>"",P12<>0,O12<>0,O12<>""),P12/O12,"") | S12: ='Ялта, Ленина, 18'!S12*График!AJ27/График!AJ31 -> 244172.46 | T12: =L49 -> 114340 | U12: =S12-T12 -> 129832.46 | V12: ='Ялта, Ленина, 18'!V12/График!AJ31*График!AJ27 -> 147788.6 | W12: =M49 -> 156232.31
F13: Кол-во чеков | I13: =IF(I12<>0,I9/I12,"") -> 148.04562 | J13: =G49 -> 134 | K13: =IF(AND(I13<>"",I13<>0,J13<>""),J13/I13,"") -> 0.90512641 | L13: =IF(SUMIF($G$25:$G$48,">=0",$R$25:$R$48)<>0,I13*G49/SUMIF($G$25:$G$48,">=0",$R$25:$R$48),"") -> 134 | M13: =IF(AND(I13<>"",I13<>0,L13<>"",L13<>0),L13/I13,"") -> 0.90512641 | N13: =IF(AND(J13<>0,J13<>"",I13<>0,I13<>""),L13-I13,"") -> -14.045619 | P13: =IF(AND(O13<>"",O13<>0,L13<>"",L13<>0),-O13+L13,"") | Q13: =IF(AND(P13<>"",P13<>0,O13<>0,O13<>""),P13/O13,"") | S13: =T12/S12 -> 0.46827558 | T13: =S13/J14*I14 -> 0.46827558 | V13: =W12/V12 -> 1.0571337 | W13: =V13/J14*I14 -> 1.0571337
F14: Кол-во смен план/отработано | I14: =График!AI27 -> 21 | J14: 21 | K14: =IF(AND(I14<>"",I14<>0,J14<>""),J14/I14,"") -> 1 | L14: =I14 -> 21 | M14: =IF(AND(I14<>"",I14<>0,L14<>"",L14<>0),L14/I14,"") -> 1 | N14: =IF(AND(J14<>0,J14<>"",I14<>0,I14<>""),L14-I14,"") -> 0 | P14: =IF(AND(O14<>"",O14<>0,L14<>"",L14<>0),-O14+L14,"") | Q14: =IF(AND(P14<>"",P14<>0,O14<>0,O14<>""),P14/O14,"")
F15: Средние продажи в смену | I15: ='Ялта, Ленина, 18'!I15 -> 151618.06 | J15: =J8/J14 -> 62165.333 | K15: =IF(AND(I15<>"",I15<>0,J15<>""),J15/I15,"") -> 0.41001271 | L15: =J15 -> 62165.333 | M15: =IF(AND(I15<>"",I15<>0,L15<>"",L15<>0),L15/I15,"") -> 0.41001271 | N15: =IF(AND(J15<>0,J15<>"",I15<>0,I15<>""),L15-I15,"") -> -89452.731 | P15: =IF(AND(O15<>"",O15<>0,L15<>"",L15<>0),-O15+L15,"") | Q15: =IF(AND(P15<>"",P15<>0,O15<>0,O15<>""),P15/O15,"")
F16: Отставание/Перевыполнение | J16: =J8-I15*J14 -> -1878507.4 | K16: =IF(AND(I16<>"",I16<>0,J16<>""),J16/I16,"") | L16: =J16 -> -1878507.4 | M16: =IF(AND(I16<>"",I16<>0,L16<>"",L16<>0),L16/I16,"") | N16: =IF(AND(J16<>0,J16<>"",I16<>0,I16<>""),L16-I16,"") | P16: =IF(AND(O16<>"",O16<>0,L16<>"",L16<>0),-O16+L16,"") | Q16: =IF(AND(P16<>"",P16<>0,O16<>0,O16<>""),P16/O16,"") | S16: UNOde50
F17: Трафик | I17: ='Ялта, Ленина, 18'!I17/График!AJ31*График!AJ27 -> 822.47566 | J17: =I49 -> 898 | K17: =IF(AND(I17<>"",I17<>0,J17<>""),J17/I17,"") -> 1.0918256 | L17: =J17/J14*I14 -> 898 | M17: =IF(AND(I17<>"",I17<>0,L17<>"",L17<>0),L17/I17,"") -> 1.0918256 | N17: =IF(AND(J17<>0,J17<>"",I17<>0,I17<>""),L17-I17,"") -> 75.524339 | P17: =IF(AND(O17<>"",O17<>0,L17<>"",L17<>0),-O17+L17,"") | Q17: =IF(AND(P17<>"",P17<>0,O17<>0,O17<>""),P17/O17,"")
K18: =IF(AND(I18<>"",I18<>0,J18<>""),J18/I18,"") | L18: =J18 -> 0 | M18: =IF(AND(I18<>"",I18<>0,L18<>"",L18<>0),L18/I18,"") | N18: =IF(AND(J18<>0,J18<>"",I18<>0,I18<>""),L18-I18,"") | O18: 0 | P18: =IF(AND(O18<>"",O18<>0,L18<>"",L18<>0),-O18+L18,"") | Q18: =IF(AND(P18<>"",P18<>0,O18<>0,O18<>""),P18/O18,"") | S18: ='Ялта, Ленина, 18'!S18*График!AJ27/График!AJ31 -> 282726.01 | T18: =K49 -> 93951 | U18: =S18-T18 -> 188775.01
K19: =IF(AND(I19<>"",I19<>0,J19<>""),J19/I19,"") | L19: =J19 -> 0 | M19: =IF(AND(I19<>"",I19<>0,L19<>"",L19<>0),L19/I19,"") | N19: =IF(AND(J19<>0,J19<>"",I19<>0,I19<>""),L19-I19,"") | O19: 0 | P19: =IF(AND(O19<>"",O19<>0,L19<>"",L19<>0),-O19+L19,"") | Q19: =IF(AND(P19<>"",P19<>0,O19<>0,O19<>""),P19/O19,"") | S19: =T18/S18 -> 0.33230406 | T19: =S19/J14*I14 -> 0.33230406
F20: Конверсия план/факт | I20: ='Ялта, Ленина, 18'!I20 -> 0.18 | J20: =N49 -> 0.14922049 | K20: =J20/I20 -> 0.82900272 | L20: =IF(AND(K8<>0,I14<>0,I49<>0),(I49*N49+(I49/K8-I49)*I20)/(I49/K8),0) -> 0.15339069 | M20: =IF(AND(I20<>"",I20<>0,L20<>"",L20<>0),L20/I20,"") -> 0.85217053 | N20: =IF(AND(J20<>0,J20<>"",I20<>0,I20<>""),L20-I20,"") -> -0.026609305 | P20: =IF(AND(O20<>"",O20<>0,L20<>"",L20<>0),-O20+L20,"") | Q20: =IF(AND(P20<>"",P20<>0,O20<>0,O20<>""),P20/O20,"")
B22: Факт продаж за месяц | O22: % выполнения дневного плана | P22: Раcпределение плана по дням
B23: Дата | C23: День недели | D23: Выручка (руб) | E23: Кол-во единиц (шт.) | F23: Средняя стоимость изделия (руб.) | G23: Количество чеков (шт.) | H23: Средняя сумма чека (руб.) | I23: Трафик | J23: Длина чека (шт.) | K23: UNOde50 | L23: IS | M23: Agafi | N23: Конверсия (%) | P23: выручка, план | Q23: кол-во ед, план | R23: Кол-во чеков, план | S23: выручка, скорректир.план | T23: кол-во ед, скорр. план | U23: кол-во чеков, скорр. план | V23: Коэфф. Дня Недели | W23: Специфика месяца
B24: 1 | C24: 2 | D24: 3 | E24: 4 | F24: 5 | G24: 6 | H24: 7 | I24: 8 | J24: 9 | K24: 10 | L24: 11 | M24: 12 | N24: 13 | P24: 1 | Q24: 2 | R24: 3 | S24: 4 | T24: 5 | U24: 6 | V24: 10 | W24: 11
A25: 1 | B25: 45870 | C25: пт | D25: 15952 | E25: 4 | F25: =IF(AND(E25<>"",E25<>0),D25/E25,"") -> 3988 | G25: 3 | H25: =IF(AND(G25<>"",G25<>0),D25/G25,"") -> 5317.3333 | I25: 20 | J25: =IF(AND(G25<>"",G25<>0),E25/G25,"") -> 1.3333333 | M25: 4772.06 | N25: =IF(AND(I25<>"",I25<>0),G25/I25,"") -> 0.15 | O25: =D25/P25 -> 0.15728297 | P25: =$I$8*V25*W25/SUMPRODUCT($W$25:$W$48,$V$25:$V$48) -> 101422.3 | Q25: =$I$9*V25*W25/SUMPRODUCT($W$25:$W$48,$V$25:$V$48) -> 16.903716 | R25: =IF($I$12="","",Q25/$I$12) -> 9.9433625 | S25: =IF(W25<>"",IF(D25<>"",D25,($I$8-SUM($S25:S$25))*V25*W25/SUMPRODUCT($W25:$W$48,$V25:$V$48)),"") -> 15952 | T25: =IF(W25<>"",IF(E25<>"",E25,($I$9-SUM($T25:T$25))*V25*W25/SUMPRODUCT($W25:$W$48,$V25:$V$48)),"") -> 4 | U25: =IF(W25<>"",IF($I$12<>"",IF(G25<>"",G25,($I$9/$I$12-SUM($U25:U$25))*V25*W25/SUMPRODUCT($W25:$W$48,$V25:$V$48)),""),"") -> 3 | V25: 1.2 | W25: 1.2
A26: 2 | B26: 45872 | C26: вс | D26: 95125.3 | E26: 20 | F26: =IF(AND(E26<>"",E26<>0),D26/E26,"") -> 4756.265 | G26: 10 | H26: =IF(AND(G26<>"",G26<>0),D26/G26,"") -> 9512.53 | I26: 55 | J26: =IF(AND(G26<>"",G26<>0),E26/G26,"") -> 2 | M26: 17173.25 | N26: =IF(AND(I26<>"",I26<>0),G26/I26,"") -> 0.18181818 | O26: =D26/P26 -> 1.3505948 | P26: =$I$8*V26*W26/SUMPRODUCT($W$25:$W$48,$V$25:$V$48) -> 70432.151 | Q26: =$I$9*V26*W26/SUMPRODUCT($W$25:$W$48,$V$25:$V$48) -> 11.738692 | R26: =IF($I$12="","",Q26/$I$12) -> 6.9051128 | S26: =IF(W26<>"",IF(D26<>"",D26,($I$8-SUM($S$25:S26))*V26*W26/SUMPRODUCT($W26:$W$48,$V26:$V$48)),"") -> 95125.3 | T26: =IF(W26<>"",IF(E26<>"",E26,($I$9-SUM($T25:T$25))*V26*W26/SUMPRODUCT($W26:$W$56,$V26:$V$56)),"") -> 20 | U26: =IF(W26<>"",IF($I$12<>"",IF(G26<>"",G26,($I$9/$I$12-SUM($U25:U$25))*V26*W26/SUMPRODUCT($W26:$W$56,$V26:$V$56)),""),"") -> 10 | V26: 1 | W26: 1
A27: 3 | B27: 45873 | C27: пн | D27: 22552 | E27: 6 | F27: 3759 | G27: 5 | H27: =IF(AND(G27<>"",G27<>0),D27/G27,"") -> 4510.4 | I27: 30 | J27: =IF(AND(G27<>"",G27<>0),E27/G27,"") -> 1.2 | N27: =IF(AND(I27<>"",I27<>0),G27/I27,"") -> 0.16666667 | O27: =D27/P27 -> 0.32019468 | P27: =$I$8*V27*W27/SUMPRODUCT($W$25:$W$48,$V$25:$V$48) -> 70432.151 | Q27: =$I$9*V27*W27/SUMPRODUCT($W$25:$W$48,$V$25:$V$48) -> 11.738692 | R27: =IF($I$12="","",Q27/$I$12) -> 6.9051128 | S27: =IF(W27<>"",IF(D27<>"",D27,($I$8-SUM($S$25:S27))*V27*W27/SUMPRODUCT($W27:$W$48,$V27:$V$48)),"") -> 22552 | T27: =IF(W27<>"",IF(E27<>"",E27,($I$9-SUM($T$25:T26))*V27*W27/SUMPRODUCT($W27:$W$56,$V27:$V$56)),"") -> 6 | U27: =IF(W27<>"",IF($I$12<>"",IF(G27<>"",G27,($I$9/$I$12-SUM($U$25:U26))*V27*W27/SUMPRODUCT($W27:$W$56,$V27:$V$56)),""),"") -> 5 | V27: 1 | W27: 1
A28: 4 | B28: 45874 | C28: вт | D28: =16203+35739.7 -> 51942.7 | E28: 11 | F28: 4725 | G28: 7 | H28: =IF(AND(G28<>"",G28<>0),D28/G28,"") -> 7420.3857 | I28: 25 | J28: =IF(AND(G28<>"",G28<>0),E28/G28,"") -> 1.5714286 | L28: 16203 | N28: =IF(AND(I28<>"",I28<>0),G28/I28,"") -> 0.28 | O28: =D28/P28 -> 0.73748564 | P28: =$I$8*V28*W28/SUMPRODUCT($W$25:$W$48,$V$25:$V$48) -> 70432.151 | Q28: =$I$9*V28*W28/SUMPRODUCT($W$25:$W$48,$V$25:$V$48) -> 11.738692 | R28: =IF($I$12="","",Q28/$I$12) -> 6.9051128 | S28: =IF(W28<>"",IF(D28<>"",D28,($I$8-SUM($S$25:S28))*V28*W28/SUMPRODUCT($W28:$W$48,$V28:$V$48)),"") -> 51942.7 | T28: =IF(W28<>"",IF(E28<>"",E28,($I$9-SUM($T$25:T27))*V28*W28/SUMPRODUCT($W28:$W$56,$V28:$V$56)),"") -> 11 | U28: =IF(W28<>"",IF($I$12<>"",IF(G28<>"",G28,($I$9/$I$12-SUM($U$25:U27))*V28*W28/SUMPRODUCT($W28:$W$56,$V28:$V$56)),""),"") -> 7 | V28: 1 | W28: 1
A29: 5 | B29: 45876 | C29: чт | D29: 50326 | E29: 10 | F29: 5032 | G29: 6 | H29: =IF(AND(G29<>"",G29<>0),D29/G29,"") -> 8387.6667 | I29: 55 | J29: =IF(AND(G29<>"",G29<>0),E29/G29,"") -> 1.6666667 | M29: 12890 | N29: =IF(AND(I29<>"",I29<>0),G29/I29,"") -> 0.10909091 | O29: =D29/P29 -> 0.71453164 | P29: =$I$8*V29*W29/SUMPRODUCT($W$25:$W$48,$V$25:$V$48) -> 70432.151 | Q29: =$I$9*V29*W29/SUMPRODUCT($W$25:$W$48,$V$25:$V$48) -> 11.738692 | R29: =IF($I$12="","",Q29/$I$12) -> 6.9051128 | S29: =IF(W29<>"",IF(D29<>"",D29,($I$8-SUM($S$25:S29))*V29*W29/SUMPRODUCT($W29:$W$48,$V29:$V$48)),"") -> 50326 | T29: =IF(W29<>"",IF(E29<>"",E29,($I$9-SUM($T$25:T28))*V29*W29/SUMPRODUCT($W29:$W$56,$V29:$V$56)),"") -> 10 | U29: =IF(W29<>"",IF($I$12<>"",IF(G29<>"",G29,($I$9/$I$12-SUM($U$25:U28))*V29*W29/SUMPRODUCT($W29:$W$56,$V29:$V$56)),""),"") -> 6 | V29: 1 | W29: 1
A30: 6 | B30: 45877 | C30: пт | D30: =25206+72488 -> 97694 | E30: 15 | F30: =IF(AND(E30<>"",E30<>0),D30/E30,"") -> 6512.9333 | G30: 7 | H30: =IF(AND(G30<>"",G30<>0),D30/G30,"") -> 13956.286 | I30: 40 | J30: =IF(AND(G30<>"",G30<>0),E30/G30,"") -> 2.1428571 | L30: 25206 | M30: 21280 | N30: =IF(AND(I30<>"",I30<>0),G30/I30,"") -> 0.175 | O30: =D30/P30 -> 1.3870654 | P30: =$I$8*V30*W30/SUMPRODUCT($W$25:$W$48,$V$25:$V$48) -> 70432.151 | Q30: =$I$9*V30*W30/SUMPRODUCT($W$25:$W$48,$V$25:$V$48) -> 11.738692 | R30: =IF($I$12="","",Q30/$I$12) -> 6.9051128 | S30: =IF(W30<>"",IF(D30<>"",D30,($I$8-SUM($S$25:S30))*V30*W30/SUMPRODUCT($W30:$W$48,$V30:$V$48)),"") -> 97694 | T30: =IF(W30<>"",IF(E29<>"",E29,($I$9-SUM($T$25:T29))*V30*W30/SUMPRODUCT($W30:$W$56,$V30:$V$56)),"") -> 10 | U30: =IF(W30<>"",IF($I$12<>"",IF(G30<>"",G30,($I$9/$I$12-SUM($U$25:U29))*V30*W30/SUMPRODUCT($W30:$W$56,$V30:$V$56)),""),"") -> 7 | V30: 1 | W30: 1
A31: 7 | B31: 45878 | C31: сб | D31: =21804+46362 -> 68166 | E31: 9 | F31: =IF(AND(E31<>"",E31<>0),D31/E31,"") -> 7574 | G31: 7 | H31: =IF(AND(G31<>"",G31<>0),D31/G31,"") -> 9738 | I31: 40 | J31: =IF(AND(G31<>"",G31<>0),E31/G31,"") -> 1.2857143 | L31: 21804 | M31: 20900 | N31: =IF(AND(I31<>"",I31<>0),G31/I31,"") -> 0.175 | O31: =D31/P31 -> 0.96782505 | P31: =$I$8*V31*W31/SUMPRODUCT($W$25:$W$48,$V$25:$V$48) -> 70432.151 | Q31: =$I$9*V31*W31/SUMPRODUCT($W$25:$W$48,$V$25:$V$48) -> 11.738692 | R31: =IF($I$12="","",Q31/$I$12) -> 6.9051128 | S31: =IF(W31<>"",IF(D31<>"",D31,($I$8-SUM($S$25:S31))*V31*W31/SUMPRODUCT($W31:$W$48,$V31:$V$48)),"") -> 68166 | T31: =IF(W31<>"",IF(E31<>"",E31,($I$9-SUM($T$25:T30))*V31*W31/SUMPRODUCT($W31:$W$56,$V31:$V$56)),"") -> 9 | U31: =IF(W31<>"",IF($I$12<>"",IF(G31<>"",G31,($I$9/$I$12-SUM($U$25:U30))*V31*W31/SUMPRODUCT($W31:$W$56,$V31:$V$56)),""),"") -> 7 | V31: 1 | W31: 1
A32: 8 | B32: 45880 | C32: пн | D32: 35332 | E32: 8 | F32: =IF(AND(E32<>"",E32<>0),D32/E32,"") -> 4416.5 | G32: 4 | H32: =IF(AND(G32<>"",G32<>0),D32/G32,"") -> 8833 | I32: 30 | J32: =IF(AND(G32<>"",G32<>0),E32/G32,"") -> 2 | N32: =IF(AND(I32<>"",I32<>0),G32/I32,"") -> 0.13333333 | O32: =D32/P32 -> 0.5016459 | P32: =$I$8*V32*W32/SUMPRODUCT($W$25:$W$48,$V$25:$V$48) -> 70432.151 | Q32: =$I$9*V32*W32/SUMPRODUCT($W$25:$W$48,$V$25:$V$48) -> 11.738692 | R32: =IF($I$12="","",Q32/$I$12) -> 6.9051128 | S32: =IF(W32<>"",IF(D32<>"",D32,($I$8-SUM($S$25:S32))*V32*W32/SUMPRODUCT($W32:$W$48,$V32:$V$48)),"") -> 35332 | T32: =IF(W32<>"",IF(E32<>"",E32,($I$9-SUM($T$25:T31))*V32*W32/SUMPRODUCT($W32:$W$56,$V32:$V$56)),"") -> 8 | U32: =IF(W32<>"",IF($I$12<>"",IF(G32<>"",G32,($I$9/$I$12-SUM($U$25:U31))*V32*W32/SUMPRODUCT($W32:$W$56,$V32:$V$56)),""),"") -> 4 | V32: 1 | W32: 1
A33: 9 | B33: 45881 | C33: вт | D33: =6003+14280+66878 -> 87161 | E33: 19 | F33: =IF(AND(E33<>"",E33<>0),D33/E33,"") -> 4587.4211 | G33: 12 | H33: =IF(AND(G33<>"",G33<>0),D33/G33,"") -> 7263.4167 | I33: 55 | J33: =IF(AND(G33<>"",G33<>0),E33/G33,"") -> 1.5833333 | L33: 6003 | M33: 14280 | N33: =IF(AND(I33<>"",I33<>0),G33/I33,"") -> 0.21818182 | O33: =D33/P33 -> 1.2375172 | P33: =$I$8*V33*W33/SUMPRODUCT($W$25:$W$48,$V$25:$V$48) -> 70432.151 | Q33: =$I$9*V33*W33/SUMPRODUCT($W$25:$W$48,$V$25:$V$48) -> 11.738692 | R33: =IF($I$12="","",Q33/$I$12) -> 6.9051128 | S33: =IF(W33<>"",IF(D33<>"",D33,($I$8-SUM($S$25:S33))*V33*W33/SUMPRODUCT($W33:$W$48,$V33:$V$48)),"") -> 87161 | T33: =IF(W33<>"",IF(E33<>"",E33,($I$9-SUM($T$25:T32))*V33*W33/SUMPRODUCT($W33:$W$56,$V33:$V$56)),"") -> 19 | U33: =IF(W33<>"",IF($I$12<>"",IF(G33<>"",G33,($I$9/$I$12-SUM($U$25:U32))*V33*W33/SUMPRODUCT($W33:$W$56,$V33:$V$56)),""),"") -> 12 | V33: 1 | W33: 1
A34: 10 | B34: 45882 | C34: ср | D34: 83227 | E34: 10 | F34: =IF(AND(E34<>"",E34<>0),D34/E34,"") -> 8322.7 | G34: 3 | H34: =IF(AND(G34<>"",G34<>0),D34/G34,"") -> 27742.333 | I34: 20 | J34: =IF(AND(G34<>"",G34<>0),E34/G34,"") -> 3.3333333 | K34: 47980 | L34: 6203 | N34: =IF(AND(I34<>"",I34<>0),G34/I34,"") -> 0.15 | O34: =D34/P34 -> 1.1816621 | P34: =$I$8*V34*W34/SUMPRODUCT($W$25:$W$48,$V$25:$V$48) -> 70432.151 | Q34: =$I$9*V34*W34/SUMPRODUCT($W$25:$W$48,$V$25:$V$48) -> 11.738692 | R34: =IF($I$12="","",Q34/$I$12) -> 6.9051128 | S34: =IF(W34<>"",IF(D34<>"",D34,($I$8-SUM($S$25:S34))*V34*W34/SUMPRODUCT($W34:$W$48,$V34:$V$48)),"") -> 83227 | T34: =IF(W34<>"",IF(E34<>"",E34,($I$9-SUM($T$25:T33))*V34*W34/SUMPRODUCT($W34:$W$56,$V34:$V$56)),"") -> 10 | U34: =IF(W34<>"",IF($I$12<>"",IF(G34<>"",G34,($I$9/$I$12-SUM($U$25:U33))*V34*W34/SUMPRODUCT($W34:$W$56,$V34:$V$56)),""),"") -> 3 | V34: 1 | W34: 1
A35: 11 | B35: 45883 | C35: чт | D35: 51214 | E35: 11 | F35: =IF(AND(E35<>"",E35<>0),D35/E35,"") -> 4655.8182 | G35: 4 | H35: =IF(AND(G35<>"",G35<>0),D35/G35,"") -> 12803.5 | I35: 50 | J35: =IF(AND(G35<>"",G35<>0),E35/G35,"") -> 2.75 | M35: 7290 | N35: =IF(AND(I35<>"",I35<>0),G35/I35,"") -> 0.08 | O35: =D35/P35 -> 0.72713952 | P35: =$I$8*V35*W35/SUMPRODUCT($W$25:$W$48,$V$25:$V$48) -> 70432.151 | Q35: =$I$9*V35*W35/SUMPRODUCT($W$25:$W$48,$V$25:$V$48) -> 11.738692 | R35: =IF($I$12="","",Q35/$I$12) -> 6.9051128 | S35: =IF(W35<>"",IF(D35<>"",D35,($I$8-SUM($S$25:S35))*V35*W35/SUMPRODUCT($W35:$W$48,$V35:$V$48)),"") -> 51214 | T35: =IF(W35<>"",IF(E35<>"",E35,($I$9-SUM($T$25:T34))*V35*W35/SUMPRODUCT($W35:$W$56,$V35:$V$56)),"") -> 11 | U35: =IF(W35<>"",IF($I$12<>"",IF(G35<>"",G35,($I$9/$I$12-SUM($U$25:U34))*V35*W35/SUMPRODUCT($W35:$W$56,$V35:$V$56)),""),"") -> 4 | V35: 1 | W35: 1
A36: 12 | B36: 45884 | C36: пт | D36: 47387 | E36: 12 | F36: =IF(AND(E36<>"",E36<>0),D36/E36,"") -> 3948.9167 | G36: 7 | H36: =IF(AND(G36<>"",G36<>0),D36/G36,"") -> 6769.5714 | I36: 50 | J36: =IF(AND(G36<>"",G36<>0),E36/G36,"") -> 1.7142857 | N36: =IF(AND(I36<>"",I36<>0),G36/I36,"") -> 0.14 | O36: =D36/P36 -> 0.67280353 | P36: =$I$8*V36*W36/SUMPRODUCT($W$25:$W$48,$V$25:$V$48) -> 70432.151 | Q36: =$I$9*V36*W36/SUMPRODUCT($W$25:$W$48,$V$25:$V$48) -> 11.738692 | R36: =IF($I$12="","",Q36/$I$12) -> 6.9051128 | S36: =IF(W36<>"",IF(D36<>"",D36,($I$8-SUM($S$25:S36))*V36*W36/SUMPRODUCT($W36:$W$48,$V36:$V$48)),"") -> 47387 | T36: =IF(W36<>"",IF(E36<>"",E36,($I$9-SUM($T$25:T35))*V36*W36/SUMPRODUCT($W36:$W$56,$V36:$V$56)),"") -> 12 | U36: =IF(W36<>"",IF($I$12<>"",IF(G36<>"",G36,($I$9/$I$12-SUM($U$25:U35))*V36*W36/SUMPRODUCT($W36:$W$56,$V36:$V$56)),""),"") -> 7 | V36: 1 | W36: 1
A37: 13 | B37: 45885 | C37: сб | D37: =5501+76255 -> 81756 | E37: 17 | F37: =IF(AND(E37<>"",E37<>0),D37/E37,"") -> 4809.1765 | G37: 11 | H37: =IF(AND(G37<>"",G37<>0),D37/G37,"") -> 7432.3636 | I37: 35 | J37: =IF(AND(G37<>"",G37<>0),E37/G37,"") -> 1.5454545 | L37: 5501 | N37: =IF(AND(I37<>"",I37<>0),G37/I37,"") -> 0.31428571 | O37: =D37/P37 -> 1.1607767 | P37: =$I$8*V37*W37/SUMPRODUCT($W$25:$W$48,$V$25:$V$48) -> 70432.151 | Q37: =$I$9*V37*W37/SUMPRODUCT($W$25:$W$48,$V$25:$V$48) -> 11.738692 | R37: =IF($I$12="","",Q37/$I$12) -> 6.9051128 | S37: =IF(W37<>"",IF(D37<>"",D37,($I$8-SUM($S$25:S37))*V37*W37/SUMPRODUCT($W37:$W$48,$V37:$V$48)),"") -> 81756 | T37: =IF(W37<>"",IF(E37<>"",E37,($I$9-SUM($T$25:T36))*V37*W37/SUMPRODUCT($W37:$W$56,$V37:$V$56)),"") -> 17 | U37: =IF(W37<>"",IF($I$12<>"",IF(G37<>"",G37,($I$9/$I$12-SUM($U$25:U36))*V37*W37/SUMPRODUCT($W37:$W$56,$V37:$V$56)),""),"") -> 11 | V37: 1 | W37: 1
A38: 14 | B38: 45887 | C38: пн | D38: =23583+65259 -> 88842 | E38: 17 | F38: =IF(AND(E38<>"",E38<>0),D38/E38,"") -> 5226 | G38: 7 | H38: =IF(AND(G38<>"",G38<>0),D38/G38,"") -> 12691.714 | I38: 40 | J38: =IF(AND(G38<>"",G38<>0),E38/G38,"") -> 2.4285714 | M38: 23583 | N38: =IF(AND(I38<>"",I38<>0),G38/I38,"") -> 0.175 | O38: =D38/P38 -> 1.2613842 | P38: =$I$8*V38*W38/SUMPRODUCT($W$25:$W$48,$V$25:$V$48) -> 70432.151 | Q38: =$I$9*V38*W38/SUMPRODUCT($W$25:$W$48,$V$25:$V$48) -> 11.738692 | R38: =IF($I$12="","",Q38/$I$12) -> 6.9051128 | S38: =IF(W38<>"",IF(D38<>"",D38,($I$8-SUM($S$25:S38))*V38*W38/SUMPRODUCT($W38:$W$48,$V38:$V$48)),"") -> 88842 | T38: =IF(W38<>"",IF(E38<>"",E38,($I$9-SUM($T$25:T37))*V38*W38/SUMPRODUCT($W38:$W$56,$V38:$V$56)),"") -> 17 | U38: =IF(W38<>"",IF($I$12<>"",IF(G38<>"",G38,($I$9/$I$12-SUM($U$25:U37))*V38*W38/SUMPRODUCT($W38:$W$56,$V38:$V$56)),""),"") -> 7 | V38: 1 | W38: 1
A39: 15 | B39: 45888 | C39: вт | D39: =17491+13180+72366 -> 103037 | E39: 19 | F39: =IF(AND(E39<>"",E39<>0),D39/E39,"") -> 5423 | G39: 8 | H39: =IF(AND(G39<>"",G39<>0),D39/G39,"") -> 12879.625 | I39: 75 | J39: =IF(AND(G39<>"",G39<>0),E39/G39,"") -> 2.375 | K39: 17491 | M39: 13180 | N39: =IF(AND(I39<>"",I39<>0),G39/I39,"") -> 0.10666667 | O39: =D39/P39 -> 1.4629257 | P39: =$I$8*V39*W39/SUMPRODUCT($W$25:$W$48,$V$25:$V$48) -> 70432.151 | Q39: =$I$9*V39*W39/SUMPRODUCT($W$25:$W$48,$V$25:$V$48) -> 11.738692 | R39: =IF($I$12="","",Q39/$I$12) -> 6.9051128 | S39: =IF(W39<>"",IF(D39<>"",D39,($I$8-SUM($S$25:S39))*V39*W39/SUMPRODUCT($W39:$W$48,$V39:$V$48)),"") -> 103037 | T39: =IF(W39<>"",IF(E39<>"",E39,($I$9-SUM($T$25:T38))*V39*W39/SUMPRODUCT($W39:$W$56,$V39:$V$56)),"") -> 19 | U39: =IF(W39<>"",IF($I$12<>"",IF(G39<>"",G39,($I$9/$I$12-SUM($U$25:U38))*V39*W39/SUMPRODUCT($W39:$W$56,$V39:$V$56)),""),"") -> 8 | V39: 1 | W39: 1
A40: 16 | B40: 45890 | C40: чт | D40: =28480+95543 -> 124023 | E40: 25 | F40: =IF(AND(E40<>"",E40<>0),D40/E40,"") -> 4960.92 | G40: 12 | H40: =IF(AND(G40<>"",G40<>0),D40/G40,"") -> 10335.25 | I40: 70 | J40: =IF(AND(G40<>"",G40<>0),E40/G40,"") -> 2.0833333 | K40: 28480 | N40: =IF(AND(I40<>"",I40<>0),G40/I40,"") -> 0.17142857 | O40: =D40/P40 -> 1.7608862 | P40: =$I$8*V40*W40/SUMPRODUCT($W$25:$W$48,$V$25:$V$48) -> 70432.151 | Q40: =$I$9*V40*W40/SUMPRODUCT($W$25:$W$48,$V$25:$V$48) -> 11.738692 | R40: =IF($I$12="","",Q40/$I$12) -> 6.9051128 | S40: =IF(W40<>"",IF(D40<>"",D40,($I$8-SUM($S$25:S40))*V40*W40/SUMPRODUCT($W40:$W$48,$V40:$V$48)),"") -> 124023 | T40: =IF(W40<>"",IF(E40<>"",E40,($I$9-SUM($T$25:T39))*V40*W40/SUMPRODUCT($W40:$W$56,$V40:$V$56)),"") -> 25 | U40: =IF(W40<>"",IF($I$12<>"",IF(G40<>"",G40,($I$9/$I$12-SUM($U$25:U39))*V40*W40/SUMPRODUCT($W40:$W$56,$V40:$V$56)),""),"") -> 12 | V40: 1 | W40: 1
A41: 17 | B41: 45891 | C41: пт | D41: 23648 | E41: 6 | F41: =IF(AND(E41<>"",E41<>0),D41/E41,"") -> 3941.3333 | G41: 3 | H41: =IF(AND(G41<>"",G41<>0),D41/G41,"") -> 7882.6667 | I41: 40 | J41: =IF(AND(G41<>"",G41<>0),E41/G41,"") -> 2 | N41: =IF(AND(I41<>"",I41<>0),G41/I41,"") -> 0.075 | O41: =D41/P41 -> 0.33575576 | P41: =$I$8*V41*W41/SUMPRODUCT($W$25:$W$48,$V$25:$V$48) -> 70432.151 | Q41: =$I$9*V41*W41/SUMPRODUCT($W$25:$W$48,$V$25:$V$48) -> 11.738692 | R41: =IF($I$12="","",Q41/$I$12) -> 6.9051128 | S41: =IF(W41<>"",IF(D41<>"",D41,($I$8-SUM($S$25:S41))*V41*W41/SUMPRODUCT($W41:$W$48,$V41:$V$48)),"") -> 23648 | T41: =IF(W41<>"",IF(E41<>"",E41,($I$9-SUM($T$25:T40))*V41*W41/SUMPRODUCT($W41:$W$56,$V41:$V$56)),"") -> 6 | U41: =IF(W41<>"",IF($I$12<>"",IF(G41<>"",G41,($I$9/$I$12-SUM($U$25:U40))*V41*W41/SUMPRODUCT($W41:$W$56,$V41:$V$56)),""),"") -> 3 | V41: 1 | W41: 1
A42: 18 | B42: 45894 | C42: пн | D42: =22723+12192+18966 -> 53881 | E42: 6 | F42: =IF(AND(E42<>"",E42<>0),D42/E42,"") -> 8980.1667 | G42: 5 | H42: =IF(AND(G42<>"",G42<>0),D42/G42,"") -> 10776.2 | I42: 39 | J42: =IF(AND(G42<>"",G42<>0),E42/G42,"") -> 1.2 | L42: 22723 | M42: 12192 | N42: =IF(AND(I42<>"",I42<>0),G42/I42,"") -> 0.12820513 | O42: =D42/P42 -> 0.76500575 | P42: =$I$8*V42*W42/SUMPRODUCT($W$25:$W$48,$V$25:$V$48) -> 70432.151 | Q42: =$I$9*V42*W42/SUMPRODUCT($W$25:$W$48,$V$25:$V$48) -> 11.738692 | R42: =IF($I$12="","",Q42/$I$12) -> 6.9051128 | S42: =IF(W42<>"",IF(D42<>"",D42,($I$8-SUM($S$25:S42))*V42*W42/SUMPRODUCT($W42:$W$48,$V42:$V$48)),"") -> 53881 | T42: =IF(W42<>"",IF(E42<>"",E42,($I$9-SUM($T$25:T41))*V42*W42/SUMPRODUCT($W42:$W$56,$V42:$V$56)),"") -> 6 | U42: =IF(W42<>"",IF($I$12<>"",IF(G42<>"",G42,($I$9/$I$12-SUM($U$25:U41))*V42*W42/SUMPRODUCT($W42:$W$56,$V42:$V$56)),""),"") -> 5 | V42: 1 | W42: 1
A43: 19 | B43: 45895 | C43: вт | D43: =54126+8692-6203 -> 56615 | E43: 12 | F43: =IF(AND(E43<>"",E43<>0),D43/E43,"") -> 4717.9167 | G43: 5 | H43: =IF(AND(G43<>"",G43<>0),D43/G43,"") -> 11323 | I43: 58 | J43: =IF(AND(G43<>"",G43<>0),E43/G43,"") -> 2.4 | L43: -6203 | M43: 8692 | N43: =IF(AND(I43<>"",I43<>0),G43/I43,"") -> 0.086206897 | O43: =D43/P43 -> 0.80382324 | P43: =$I$8*V43*W43/SUMPRODUCT($W$25:$W$48,$V$25:$V$48) -> 70432.151 | Q43: =$I$9*V43*W43/SUMPRODUCT($W$25:$W$48,$V$25:$V$48) -> 11.738692 | R43: =IF($I$12="","",Q43/$I$12) -> 6.9051128 | S43: =IF(W43<>"",IF(D43<>"",D43,($I$8-SUM($S$25:S43))*V43*W43/SUMPRODUCT($W43:$W$48,$V43:$V$48)),"") -> 56615 | T43: =IF(W43<>"",IF(E43<>"",E43,($I$9-SUM($T$25:T42))*V43*W43/SUMPRODUCT($W43:$W$56,$V43:$V$56)),"") -> 12 | U43: =IF(W43<>"",IF($I$12<>"",IF(G43<>"",G43,($I$9/$I$12-SUM($U$25:U42))*V43*W43/SUMPRODUCT($W43:$W$56,$V43:$V$56)),""),"") -> 5 | V43: 1 | W43: 1
A44: 20 | B44: 45896 | C44: ср | D44: 35216 | E44: 8 | F44: =IF(AND(E44<>"",E44<>0),D44/E44,"") -> 4402 | G44: 5 | H44: =IF(AND(G44<>"",G44<>0),D44/G44,"") -> 7043.2 | I44: 43 | J44: =IF(AND(G44<>"",G44<>0),E44/G44,"") -> 1.6 | N44: =IF(AND(I44<>"",I44<>0),G44/I44,"") -> 0.11627907 | O44: =D44/P44 -> 0.49999893 | P44: =$I$8*V44*W44/SUMPRODUCT($W$25:$W$48,$V$25:$V$48) -> 70432.151 | Q44: =$I$9*V44*W44/SUMPRODUCT($W$25:$W$48,$V$25:$V$48) -> 11.738692 | R44: =IF($I$12="","",Q44/$I$12) -> 6.9051128 | S44: =IF(W44<>"",IF(D44<>"",D44,($I$8-SUM($S$25:S44))*V44*W44/SUMPRODUCT($W44:$W$48,$V44:$V$48)),"") -> 35216 | T44: =IF(W44<>"",IF(E44<>"",E44,($I$9-SUM($T$25:T43))*V44*W44/SUMPRODUCT($W44:$W$56,$V44:$V$56)),0) -> 8 | U44: =IF(W44<>"",IF($I$12<>"",IF(G44<>"",G44,($I$9/$I$12-SUM($U$25:U43))*V44*W44/SUMPRODUCT($W44:$W$56,$V44:$V$56)),""),"") -> 5 | V44: 1 | W44: 1
A45: 21 | B45: 45898 | C45: пт | D45: 15475 | E45: 3 | F45: =IF(AND(E45<>"",E45<>0),D45/E45,"") -> 5158.3333 | G45: 2 | H45: =IF(AND(G45<>"",G45<>0),D45/G45,"") -> 7737.5 | I45: 28 | J45: =IF(AND(G45<>"",G45<>0),E45/G45,"") -> 1.5 | N45: =IF(AND(I45<>"",I45<>0),G45/I45,"") -> 0.071428571 | O45: =D45/P45 -> 0.219715 | P45: =$I$8*V45*W45/SUMPRODUCT($W$25:$W$48,$V$25:$V$48) -> 70432.151 | Q45: =$I$9*V45*W45/SUMPRODUCT($W$25:$W$48,$V$25:$V$48) -> 11.738692 | R45: =IF($I$12="","",Q45/$I$12) -> 6.9051128 | S45: =IF(W45<>"",IF(D45<>"",D45,($I$8-SUM($S$25:S45))*V45*W45/SUMPRODUCT($W45:$W$48,$V45:$V$48)),"") -> 15475 | T45: =IF(W45<>"",IF(E45<>"",E45,($I$9-SUM($T$25:T44))*V45*W45/SUMPRODUCT($W45:$W$56,$V45:$V$56)),0) -> 3 | U45: =IF(W45<>"",IF($I$12<>"",IF(G45<>"",G45,($I$9/$I$12-SUM($U$25:U44))*V45*W45/SUMPRODUCT($W45:$W$56,$V45:$V$56)),""),"") -> 2 | V45: 1 | W45: 1
F46: =IF(AND(E46<>"",E46<>0),D46/E46,"") | H46: =IF(AND(G46<>"",G46<>0),D46/G46,"") | J46: =IF(AND(G46<>"",G46<>0),E46/G46,"") | N46: =IF(AND(I46<>"",I46<>0),G46/I46,"") | O46: =D46/P46 -> #DIV/0! | P46: =$I$8*V46*W46/SUMPRODUCT($W$25:$W$48,$V$25:$V$48) -> 0 | Q46: =$I$9*V46*W46/SUMPRODUCT($W$25:$W$48,$V$25:$V$48) -> 0 | R46: =IF($I$12="","",Q46/$I$12) -> 0 | S46: =IF(W46<>"",IF(D46<>"",D46,($I$8-SUM($S$25:S46))*V46*W46/SUMPRODUCT($W46:$W$48,$V46:$V$48)),"") | T46: =IF(W46<>"",IF(E46<>"",E46,($I$9-SUM($T$25:T44))*V46*W46/SUMPRODUCT($W$44:$W46,$V$44:$V46)),"") | U46: =IF(W46<>"",IF($I$12<>"",IF(G46<>"",G46,($I$9/$I$12-SUM($U$25:U44))*V46*W46/SUMPRODUCT($W$44:$W46,$V$44:$V46)),""),"")
F47: =IF(AND(E47<>"",E47<>0),D47/E47,"") | H47: =IF(AND(G47<>"",G47<>0),D47/G47,"") | J47: =IF(AND(G47<>"",G47<>0),E47/G47,"") | N47: =IF(AND(I47<>"",I47<>0),G47/I47,"") | O47: =D47/P47 -> #DIV/0! | P47: =$I$8*V47*W47/SUMPRODUCT($W$25:$W$48,$V$25:$V$48) -> 0 | Q47: =$I$9*V47*W47/SUMPRODUCT($W$25:$W$48,$V$25:$V$48) -> 0 | R47: =IF($I$12="","",Q47/$I$12) -> 0 | S47: =IF(W47<>"",IF(D47<>"",D47,($I$8-SUM($S$25:S47))*V47*W47/SUMPRODUCT($W47:$W$48,$V47:$V$48)),"") | T47: =IF(W47<>"",IF(E47<>"",E47,($I$9-SUM($T$25:T46))*V47*W47/SUMPRODUCT($W$44:$W47,$V$44:$V47)),"") | U47: =IF(W47<>"",IF($I$12<>"",IF(G47<>"",G47,($I$9/$I$12-SUM($U$25:U46))*V47*W47/SUMPRODUCT($W$44:$W47,$V$44:$V47)),""),"")
B48: 45871 | C48: сб | D48: 16900 | E48: 1 | F48: =IF(AND(E48<>"",E48<>0),D48/E48,"") -> 16900 | G48: 1 | H48: =IF(AND(G48<>"",G48<>0),D48/G48,"") -> 16900 | J48: =IF(AND(G48<>"",G48<>0),E48/G48,"") -> 1 | L48: 16900 | N48: =IF(AND(I48<>"",I48<>0),G48/I48,"") | O48: =D48/P48 -> #DIV/0! | P48: =$I$8*V48*W48/SUMPRODUCT($W$25:$W$48,$V$25:$V$48) -> 0 | Q48: =$I$9*V48*W48/SUMPRODUCT($W$25:$W$48,$V$25:$V$48) -> 0 | R48: =IF($I$12="","",Q48/$I$12) -> 0 | S48: =IF(W48<>"",IF(D48<>"",D48,($I$8-SUM($S$25:S48))*V48*W48/SUMPRODUCT($W48:$W$48,$V48:$V$48)),"") | T48: =IF(W48<>"",IF(E48<>"",E48,($I$9-SUM($T$25:T46))*V48*W48/SUMPRODUCT($W$44:$W48,$V$44:$V48)),"") | U48: =IF(W48<>"",IF($I$12<>"",IF(G48<>"",G48,($I$9/$I$12-SUM($U$25:U46))*V48*W48/SUMPRODUCT($W$44:$W48,$V$44:$V48)),""),"")
B49: итого | D49: =SUM(D25:D48) -> 1305472 | E49: =SUM(E25:E48) -> 249 | F49: =IF(AND(E49<>"",E49<>0),D49/E49,"") -> 5242.8594 | G49: =SUM(G25:G48) -> 134 | H49: =IF(AND(G49<>"",G49<>0),D49/G49,"") -> 9742.3284 | I49: =SUM(I25:I48) -> 898 | J49: =IF(AND(G49<>"",G49<>0),E49/G49,"") -> 1.858209 | K49: =SUM(K25:K48) -> 93951 | L49: =SUM(L25:L48) -> 114340 | M49: =SUM(M25:M48) -> 156232.31 | N49: =IF(AND(I49<>"",I49<>0),G49/I49,"") -> 0.14922049 | O49: =D49/P49 -> 0.8645136 | P49: =SUM(P25:P48) -> 1510065.3 | Q49: =SUM(Q25:Q48) -> 251.67755 | R49: =SUM(R25:R48) -> 148.04562 | S49: =SUM(S25:S48) -> 1288572 | T49: =SUM(T25:T48) -> 243 | U49: =SUM(U25:U48) -> 133
D50: =SUMIF(D25:D48,"",P25:P48)+D49 -> 1305472

Sheet ПК 3
B1: =TODAY()-1 -> 45909
B2: (отчетная дата) | J2: ЕЖЕДНЕВНЫЙ ОТЧЕТ О ПРОДАЖАХ
B3: Осталось до выполнения плана!!! | J3: =График!B26 -> 0
C4: =I8-D48 -> 0 | E4: =IF(I8<>0,C4/I8,0) -> 0
F6: Целевые показатели
F7: Показатель | I7: План | J7: Факт | K7: % выполнения | L7: Прогноз выполнения | M7: % выполнения по прогнозу | N7: Отклонение | O7: Факт аналогичного месяца прошлого года | P7: Отклонение LFL
F8: Выручка | I8: ='Ялта, Ленина, 18'!I8/График!AJ31*График!AJ26 -> 0 | J8: =D48 -> 0 | K8: =IF(AND(I8<>"",I8<>0,J8<>""),J8/I8,"") | L8: =IF(SUMIF($D$25:$D$47,">=0",$P$25:$P$47)<>0,I8*D48/SUMIF($D$25:$D$47,">=0",$P$25:$P$47),0) -> 0 | M8: =IF(AND(I8<>"",I8<>0,L8<>"",L8<>0),L8/I8,"") | N8: =IF(AND(J8<>0,J8<>"",I8<>0,I8<>""),L8-I8,"") | P8: =IF(AND(O8<>"",O8<>0,L8<>"",L8<>0),-O8+L8,"") | Q8: =IF(AND(P8<>"",P8<>0,O8<>0,O8<>""),P8/O8,"")
F9: Кол-во изделий | I9: =I8/I11 -> 0 | J9: =E48 -> 0 | K9: =IF(AND(I9<>"",I9<>0,J9<>""),J9/I9,"") | L9: =IF(SUMIF($E$25:$E$47,">=0",$Q$25:$Q$47)<>0,I9*E48/SUMIF($E$25:$E$47,">=0",$Q$25:$Q$47),0) -> 0 | M9: =IF(AND(I9<>"",I9<>0,L9<>"",L9<>0),L9/I9,"") | N9: =IF(AND(J9<>0,J9<>"",I9<>0,I9<>""),L9-I9,"") | O9: =O8/O11 -> #DIV/0! | P9: =IF(AND(O9<>"",O9<>0,L9<>"",L9<>0),-O9+L9,"") -> #DIV/0! | Q9: =IF(AND(P9<>"",P9<>0,O9<>0,O9<>""),P9/O9,"") -> #DIV/0!
F10: Средний чек | I10: =I11*I12 -> 10200 | J10: =H48 | K10: =IF(AND(I10<>"",I10<>0,J10<>""),J10/I10,"") | L10: =J10 | M10: =IF(AND(I10<>"",I10<>0,L10<>"",L10<>0),L10/I10,"") | N10: =IF(AND(J10<>0,J10<>"",I10<>0,I10<>""),L10-I10,"") | O10: =O11*O12 -> 0 | P10: =IF(AND(O10<>"",O10<>0,L10<>"",L10<>0),-O10+L10,"") | Q10: =IF(AND(P10<>"",P10<>0,O10<>0,O10<>""),P10/O10,"") | S10: IS
F11: Средняя стоимость изделия | I11: ='Ялта, Ленина, 18'!I11 -> 6000 | J11: =F48 | K11: =IF(AND(I11<>"",I11<>0,J11<>""),J11/I11,"") | L11: =IF(L9>0,L8/L9,"") | M11: =IF(AND(I11<>"",I11<>0,L11<>"",L11<>0),L11/I11,"") | N11: =IF(AND(J11<>0,J11<>"",I11<>0,I11<>""),L11-I11,"") | P11: =IF(AND(O11<>"",O11<>0,L11<>"",L11<>0),-O11+L11,"") | Q11: =IF(AND(P11<>"",P11<>0,O11<>0,O11<>""),P11/O11,"")
F12: Длина чека | I12: ='Ялта, Ленина, 18'!I12 -> 1.7 | J12: =J48 | K12: =IF(AND(I12<>"",I12<>0,J12<>""),J12/I12,"") | L12: =J12 | M12: =IF(AND(I12<>"",I12<>0,L12<>"",L12<>0),L12/I12,"") | N12: =IF(AND(J12<>0,J12<>"",I12<>0,I12<>""),L12-I12,"") | P12: =IF(AND(O12<>"",O12<>0,L12<>"",L12<>0),-O12+L12,"") | Q12: =IF(AND(P12<>"",P12<>0,O12<>0,O12<>""),P12/O12,"") | S12: ='Ялта, Ленина, 18'!S12*График!AJ26/График!AJ31 -> 0 | T12: =L54 -> 0
F13: Кол-во чеков | I13: =IF(I12<>0,I9/I12,"") -> 0 | J13: =G48 -> 0 | K13: =IF(AND(I13<>"",I13<>0,J13<>""),J13/I13,"") | L13: =IF(SUMIF($G$25:$G$47,">=0",$R$25:$R$47)<>0,I13*G48/SUMIF($G$25:$G$47,">=0",$R$25:$R$47),"") -> #DIV/0! | M13: =IF(AND(I13<>"",I13<>0,L13<>"",L13<>0),L13/I13,"") -> #DIV/0! | N13: =IF(AND(J13<>0,J13<>"",I13<>0,I13<>""),L13-I13,"") | P13: =IF(AND(O13<>"",O13<>0,L13<>"",L13<>0),-O13+L13,"") -> #DIV/0! | Q13: =IF(AND(P13<>"",P13<>0,O13<>0,O13<>""),P13/O13,"") -> #DIV/0! | S13: =T12/S12 -> #DIV/0! | T13: =S13/J14*I14 -> #DIV/0!
F14: Кол-во смен план/отработано | I14: =График!AI27 -> 21 | K14: =IF(AND(I14<>"",I14<>0,J14<>""),J14/I14,"") | L14: =I14 -> 21 | M14: =IF(AND(I14<>"",I14<>0,L14<>"",L14<>0),L14/I14,"") -> 1 | N14: =IF(AND(J14<>0,J14<>"",I14<>0,I14<>""),L14-I14,"") | P14: =IF(AND(O14<>"",O14<>0,L14<>"",L14<>0),-O14+L14,"") | Q14: =IF(AND(P14<>"",P14<>0,O14<>0,O14<>""),P14/O14,"")
F15: Средние продажи в смену | I15: ='Ялта, Ленина, 18'!I15 -> 151618.06 | J15: =J8/J14 -> #DIV/0! | K15: =IF(AND(I15<>"",I15<>0,J15<>""),J15/I15,"") -> #DIV/0! | L15: =J15 -> #DIV/0! | M15: =IF(AND(I15<>"",I15<>0,L15<>"",L15<>0),L15/I15,"") -> #DIV/0! | N15: =IF(AND(J15<>0,J15<>"",I15<>0,I15<>""),L15-I15,"") -> #DIV/0! | P15: =IF(AND(O15<>"",O15<>0,L15<>"",L15<>0),-O15+L15,"") -> #DIV/0! | Q15: =IF(AND(P15<>"",P15<>0,O15<>0,O15<>""),P15/O15,"") -> #DIV/0!
F16: Отставание/Перевыполнение | J16: =J8-I15*J14 -> 0 | K16: =IF(AND(I16<>"",I16<>0,J16<>""),J16/I16,"") | L16: =J16 -> 0 | M16: =IF(AND(I16<>"",I16<>0,L16<>"",L16<>0),L16/I16,"") | N16: =IF(AND(J16<>0,J16<>"",I16<>0,I16<>""),L16-I16,"") | P16: =IF(AND(O16<>"",O16<>0,L16<>"",L16<>0),-O16+L16,"") | Q16: =IF(AND(P16<>"",P16<>0,O16<>0,O16<>""),P16/O16,"") | S16: UNOde50
F17: Трафик | I17: ='Ялта, Ленина, 18'!I17/График!AJ31*График!AJ26 -> 0 | J17: =I48 -> 0 | K17: =IF(AND(I17<>"",I17<>0,J17<>""),J17/I17,"") | L17: =J17/J14*I14 -> #DIV/0! | M17: =IF(AND(I17<>"",I17<>0,L17<>"",L17<>0),L17/I17,"") -> #DIV/0! | N17: =IF(AND(J17<>0,J17<>"",I17<>0,I17<>""),L17-I17,"") | P17: =IF(AND(O17<>"",O17<>0,L17<>"",L17<>0),-O17+L17,"") -> #DIV/0! | Q17: =IF(AND(P17<>"",P17<>0,O17<>0,O17<>""),P17/O17,"") -> #DIV/0!
K18: =IF(AND(I18<>"",I18<>0,J18<>""),J18/I18,"") | L18: =J18 -> 0 | M18: =IF(AND(I18<>"",I18<>0,L18<>"",L18<>0),L18/I18,"") | N18: =IF(AND(J18<>0,J18<>"",I18<>0,I18<>""),L18-I18,"") | O18: 0 | P18: =IF(AND(O18<>"",O18<>0,L18<>"",L18<>0),-O18+L18,"") | Q18: =IF(AND(P18<>"",P18<>0,O18<>0,O18<>""),P18/O18,"") | S18: ='Ялта, Ленина, 18'!S18*График!AJ26/График!AJ31 -> 0 | T18: =K54 -> 0
J19: =M48 -> 0 | K19: =IF(AND(I19<>"",I19<>0,J19<>""),J19/I19,"") | L19: =J19 -> 0 | M19: =IF(AND(I19<>"",I19<>0,L19<>"",L19<>0),L19/I19,"") | N19: =IF(AND(J19<>0,J19<>"",I19<>0,I19<>""),L19-I19,"") | O19: 0 | P19: =IF(AND(O19<>"",O19<>0,L19<>"",L19<>0),-O19+L19,"") | Q19: =IF(AND(P19<>"",P19<>0,O19<>0,O19<>""),P19/O19,"") | S19: =T18/S18 -> #DIV/0! | T19: =S19/J14*I14 -> #DIV/0!
F20: Конверсия план/факт | I20: ='Ялта, Ленина, 18'!I20 -> 0.18 | J20: =N48 | K20: =J20/I20 -> #VALUE! | L20: =IF(AND(K8<>0,I14<>0,I48<>0),(I48*N48+(I48/K8-I48)*I20)/(I48/K8),0) -> 0 | M20: =IF(AND(I20<>"",I20<>0,L20<>"",L20<>0),L20/I20,"") | N20: =IF(AND(J20<>0,J20<>"",I20<>0,I20<>""),L20-I20,"") | P20: =IF(AND(O20<>"",O20<>0,L20<>"",L20<>0),-O20+L20,"") | Q20: =IF(AND(P20<>"",P20<>0,O20<>0,O20<>""),P20/O20,"")
B22: Факт продаж за месяц | O22: % выполнения дневного плана | P22: Раcпределение плана по дням
B23: Дата | C23: День недели | D23: Выручка (руб) | E23: Кол-во единиц (шт.) | F23: Средняя стоимость изделия (руб.) | G23: Количество чеков (шт.) | H23: Средняя сумма чека (руб.) | I23: Трафик | J23: Длина чека (шт.) | K23: UNOde50 | L23: IS | M23: Запасной | N23: Конверсия (%) | P23: выручка, план | Q23: кол-во ед, план | R23: Кол-во чеков, план | S23: выручка, скорректир.план | T23: кол-во ед, скорр. план | U23: кол-во чеков, скорр. план | V23: Коэфф. Дня Недели | W23: Специфика месяца
B24: 1 | C24: 2 | D24: 3 | E24: 4 | F24: 5 | G24: 6 | H24: 7 | I24: 8 | J24: 9 | K24: 10 | L24: 11 | M24: 12 | N24: 13 | P24: 1 | Q24: 2 | R24: 3 | S24: 4 | T24: 5 | U24: 6 | V24: 10 | W24: 11
A25: 1 | F25: =IF(AND(E25<>"",E25<>0),D25/E25,"") | H25: =IF(AND(G25<>"",G25<>0),D25/G25,"") | J25: =IF(AND(G25<>"",G25<>0),E25/G25,"") | N25: =IF(AND(I25<>"",I25<>0),G25/I25,"") | O25: =D25/P25 -> #DIV/0! | P25: =$I$8*V25*W25/SUMPRODUCT($W$25:$W$47,$V$25:$V$47) -> #DIV/0! | Q25: =$I$9*V25*W25/SUMPRODUCT($W$25:$W$55,$V$25:$V$55) -> #DIV/0! | R25: =IF($I$12="","",Q25/$I$12) -> #DIV/0! | S25: =IF(D25<>"",D25,P25) -> #DIV/0! | T25: =IF(E25<>"",E25,Q25) -> #DIV/0! | U25: =IF(G25<>"",G25,R25) -> #DIV/0!
A26: 2 | F26: =IF(AND(E26<>"",E26<>0),D26/E26,"") | G26: 0 | H26: =IF(AND(G26<>"",G26<>0),D26/G26,"") | J26: =IF(AND(G26<>"",G26<>0),E26/G26,"") | N26: =IF(AND(I26<>"",I26<>0),G26/I26,"") | O26: =D26/P26 -> #DIV/0! | P26: =$I$8*V26*W26/SUMPRODUCT($W$25:$W$47,$V$25:$V$47) -> #DIV/0! | Q26: =$I$9*V26*W26/SUMPRODUCT($W$25:$W$55,$V$25:$V$55) -> #DIV/0! | R26: =IF($I$12="","",Q26/$I$12) -> #DIV/0! | S26: =IF(W26<>"",IF(D26<>"",D26,($I$8-SUM($S$25:S25))*V26*W26/SUMPRODUCT($W26:$W$55,$V26:$V$55)),"") | T26: =IF(W26<>"",IF(E26<>"",E26,($I$9-SUM($T$25:T25))*V26*W26/SUMPRODUCT($W26:$W$55,$V26:$V$55)),"") | U26: =IF(W26<>"",IF($I$12<>"",IF(G26<>"",G26,($I$9/$I$12-SUM($U$25:U25))*V26*W26/SUMPRODUCT($W26:$W$55,$V26:$V$55)),""),"")
A27: 3 | F27: =IF(AND(E27<>"",E27<>0),D27/E27,"") | H27: =IF(AND(G27<>"",G27<>0),D27/G27,"") | J27: =IF(AND(G27<>"",G27<>0),E27/G27,"") | N27: =IF(AND(I27<>"",I27<>0),G27/I27,"") | O27: =D27/P27 -> #DIV/0! | P27: =$I$8*V27*W27/SUMPRODUCT($W$25:$W$47,$V$25:$V$47) -> #DIV/0! | Q27: =$I$9*V27*W27/SUMPRODUCT($W$25:$W$55,$V$25:$V$55) -> #DIV/0! | R27: =IF($I$12="","",Q27/$I$12) -> #DIV/0! | S27: =IF(W27<>"",IF(D27<>"",D27,($I$8-SUM($S$25:S26))*V27*W27/SUMPRODUCT($W27:$W$55,$V27:$V$55)),"") | T27: =IF(W27<>"",IF(E27<>"",E27,($I$9-SUM($T$25:T26))*V27*W27/SUMPRODUCT($W27:$W$55,$V27:$V$55)),"") | U27: =IF(W27<>"",IF($I$12<>"",IF(G27<>"",G27,($I$9/$I$12-SUM($U$25:U26))*V27*W27/SUMPRODUCT($W27:$W$55,$V27:$V$55)),""),"")
A28: 4 | F28: =IF(AND(E28<>"",E28<>0),D28/E28,"") | H28: =IF(AND(G28<>"",G28<>0),D28/G28,"") | J28: =IF(AND(G28<>"",G28<>0),E28/G28,"") | N28: =IF(AND(I28<>"",I28<>0),G28/I28,"") | O28: =D28/P28 -> #DIV/0! | P28: =$I$8*V28*W28/SUMPRODUCT($W$25:$W$47,$V$25:$V$47) -> #DIV/0! | Q28: =$I$9*V28*W28/SUMPRODUCT($W$25:$W$55,$V$25:$V$55) -> #DIV/0! | R28: =IF($I$12="","",Q28/$I$12) -> #DIV/0! | S28: =IF(W28<>"",IF(D28<>"",D28,($I$8-SUM($S$25:S27))*V28*W28/SUMPRODUCT($W28:$W$55,$V28:$V$55)),"") | T28: =IF(W28<>"",IF(E28<>"",E28,($I$9-SUM($T$25:T27))*V28*W28/SUMPRODUCT($W28:$W$55,$V28:$V$55)),"") | U28: =IF(W28<>"",IF($I$12<>"",IF(G28<>"",G28,($I$9/$I$12-SUM($U$25:U27))*V28*W28/SUMPRODUCT($W28:$W$55,$V28:$V$55)),""),"")
A29: 5 | F29: =IF(AND(E29<>"",E29<>0),D29/E29,"") | H29: =IF(AND(G29<>"",G29<>0),D29/G29,"") | J29: =IF(AND(G29<>"",G29<>0),E29/G29,"") | N29: =IF(AND(I29<>"",I29<>0),G29/I29,"") | O29: =D29/P29 -> #DIV/0! | P29: =$I$8*V29*W29/SUMPRODUCT($W$25:$W$47,$V$25:$V$47) -> #DIV/0! | Q29: =$I$9*V29*W29/SUMPRODUCT($W$25:$W$55,$V$25:$V$55) -> #DIV/0! | R29: =IF($I$12="","",Q29/$I$12) -> #DIV/0! | S29: =IF(W29<>"",IF(D29<>"",D29,($I$8-SUM($S$25:S28))*V29*W29/SUMPRODUCT($W29:$W$55,$V29:$V$55)),"") | T29: =IF(W29<>"",IF(E29<>"",E29,($I$9-SUM($T$25:T28))*V29*W29/SUMPRODUCT($W29:$W$55,$V29:$V$55)),"") | U29: =IF(W29<>"",IF($I$12<>"",IF(G29<>"",G29,($I$9/$I$12-SUM($U$25:U28))*V29*W29/SUMPRODUCT($W29:$W$55,$V29:$V$55)),""),"")
A30: 6 | F30: =IF(AND(E30<>"",E30<>0),D30/E30,"") | H30: =IF(AND(G30<>"",G30<>0),D30/G30,"") | J30: =IF(AND(G30<>"",G30<>0),E30/G30,"") | N30: =IF(AND(I30<>"",I30<>0),G30/I30,"") | O30: =D30/P30 -> #DIV/0! | P30: =$I$8*V30*W30/SUMPRODUCT($W$25:$W$47,$V$25:$V$47) -> #DIV/0! | Q30: =$I$9*V30*W30/SUMPRODUCT($W$25:$W$55,$V$25:$V$55) -> #DIV/0! | R30: =IF($I$12="","",Q30/$I$12) -> #DIV/0! | S30: =IF(W30<>"",IF(D30<>"",D30,($I$8-SUM($S$25:S29))*V30*W30/SUMPRODUCT($W30:$W$55,$V30:$V$55)),"") | T30: =IF(W30<>"",IF(E29<>"",E29,($I$9-SUM($T$25:T29))*V30*W30/SUMPRODUCT($W30:$W$55,$V30:$V$55)),"") | U30: =IF(W30<>"",IF($I$12<>"",IF(G30<>"",G30,($I$9/$I$12-SUM($U$25:U29))*V30*W30/SUMPRODUCT($W30:$W$55,$V30:$V$55)),""),"")
A31: 7 | F31: =IF(AND(E31<>"",E31<>0),D31/E31,"") | H31: =IF(AND(G31<>"",G31<>0),D31/G31,"") | J31: =IF(AND(G31<>"",G31<>0),E31/G31,"") | N31: =IF(AND(I31<>"",I31<>0),G31/I31,"") | O31: =D31/P31 -> #DIV/0! | P31: =$I$8*V31*W31/SUMPRODUCT($W$25:$W$47,$V$25:$V$47) -> #DIV/0! | Q31: =$I$9*V31*W31/SUMPRODUCT($W$25:$W$55,$V$25:$V$55) -> #DIV/0! | R31: =IF($I$12="","",Q31/$I$12) -> #DIV/0! | S31: =IF(W31<>"",IF(D31<>"",D31,($I$8-SUM($S$25:S30))*V31*W31/SUMPRODUCT($W31:$W$55,$V31:$V$55)),"") | T31: =IF(W31<>"",IF(E31<>"",E31,($I$9-SUM($T$25:T30))*V31*W31/SUMPRODUCT($W31:$W$55,$V31:$V$55)),"") | U31: =IF(W31<>"",IF($I$12<>"",IF(G31<>"",G31,($I$9/$I$12-SUM($U$25:U30))*V31*W31/SUMPRODUCT($W31:$W$55,$V31:$V$55)),""),"")
A32: 8 | F32: =IF(AND(E32<>"",E32<>0),D32/E32,"") | H32: =IF(AND(G32<>"",G32<>0),D32/G32,"") | J32: =IF(AND(G32<>"",G32<>0),E32/G32,"") | N32: =IF(AND(I32<>"",I32<>0),G32/I32,"") | O32: =D32/P32 -> #DIV/0! | P32: =$I$8*V32*W32/SUMPRODUCT($W$25:$W$47,$V$25:$V$47) -> #DIV/0! | Q32: =$I$9*V32*W32/SUMPRODUCT($W$25:$W$55,$V$25:$V$55) -> #DIV/0! | R32: =IF($I$12="","",Q32/$I$12) -> #DIV/0! | S32: =IF(W32<>"",IF(D32<>"",D32,($I$8-SUM($S$25:S31))*V32*W32/SUMPRODUCT($W32:$W$55,$V32:$V$55)),"") | T32: =IF(W32<>"",IF(E32<>"",E32,($I$9-SUM($T$25:T31))*V32*W32/SUMPRODUCT($W32:$W$55,$V32:$V$55)),"") | U32: =IF(W32<>"",IF($I$12<>"",IF(G32<>"",G32,($I$9/$I$12-SUM($U$25:U31))*V32*W32/SUMPRODUCT($W32:$W$55,$V32:$V$55)),""),"")
A33: 9 | F33: =IF(AND(E33<>"",E33<>0),D33/E33,"") | H33: =IF(AND(G33<>"",G33<>0),D33/G33,"") | J33: =IF(AND(G33<>"",G33<>0),E33/G33,"") | N33: =IF(AND(I33<>"",I33<>0),G33/I33,"") | O33: =D33/P33 -> #DIV/0! | P33: =$I$8*V33*W33/SUMPRODUCT($W$25:$W$47,$V$25:$V$47) -> #DIV/0! | Q33: =$I$9*V33*W33/SUMPRODUCT($W$25:$W$55,$V$25:$V$55) -> #DIV/0! | R33: =IF($I$12="","",Q33/$I$12) -> #DIV/0! | S33: =IF(W33<>"",IF(D33<>"",D33,($I$8-SUM($S$25:S32))*V33*W33/SUMPRODUCT($W33:$W$55,$V33:$V$55)),"") | T33: =IF(W33<>"",IF(E33<>"",E33,($I$9-SUM($T$25:T32))*V33*W33/SUMPRODUCT($W33:$W$55,$V33:$V$55)),"") | U33: =IF(W33<>"",IF($I$12<>"",IF(G33<>"",G33,($I$9/$I$12-SUM($U$25:U32))*V33*W33/SUMPRODUCT($W33:$W$55,$V33:$V$55)),""),"")
A34: 10 | F34: =IF(AND(E34<>"",E34<>0),D34/E34,"") | H34: =IF(AND(G34<>"",G34<>0),D34/G34,"") | J34: =IF(AND(G34<>"",G34<>0),E34/G34,"") | N34: =IF(AND(I34<>"",I34<>0),G34/I34,"") | O34: =D34/P34 -> #DIV/0! | P34: =$I$8*V34*W34/SUMPRODUCT($W$25:$W$47,$V$25:$V$47) -> #DIV/0! | Q34: =$I$9*V34*W34/SUMPRODUCT($W$25:$W$55,$V$25:$V$55) -> #DIV/0! | R34: =IF($I$12="","",Q34/$I$12) -> #DIV/0! | S34: =IF(W34<>"",IF(D34<>"",D34,($I$8-SUM($S$25:S33))*V34*W34/SUMPRODUCT($W34:$W$55,$V34:$V$55)),"") | T34: =IF(W34<>"",IF(E34<>"",E34,($I$9-SUM($T$25:T33))*V34*W34/SUMPRODUCT($W34:$W$55,$V34:$V$55)),"") | U34: =IF(W34<>"",IF($I$12<>"",IF(G34<>"",G34,($I$9/$I$12-SUM($U$25:U33))*V34*W34/SUMPRODUCT($W34:$W$55,$V34:$V$55)),""),"")
A35: 11 | F35: =IF(AND(E35<>"",E35<>0),D35/E35,"") | H35: =IF(AND(G35<>"",G35<>0),D35/G35,"") | J35: =IF(AND(G35<>"",G35<>0),E35/G35,"") | N35: =IF(AND(I35<>"",I35<>0),G35/I35,"") | O35: =D35/P35 -> #DIV/0! | P35: =$I$8*V35*W35/SUMPRODUCT($W$25:$W$47,$V$25:$V$47) -> #DIV/0! | Q35: =$I$9*V35*W35/SUMPRODUCT($W$25:$W$55,$V$25:$V$55) -> #DIV/0! | R35: =IF($I$12="","",Q35/$I$12) -> #DIV/0! | S35: =IF(W35<>"",IF(D35<>"",D35,($I$8-SUM($S$25:S34))*V35*W35/SUMPRODUCT($W35:$W$55,$V35:$V$55)),"") | T35: =IF(W35<>"",IF(E35<>"",E35,($I$9-SUM($T$25:T34))*V35*W35/SUMPRODUCT($W35:$W$55,$V35:$V$55)),"") | U35: =IF(W35<>"",IF($I$12<>"",IF(G35<>"",G35,($I$9/$I$12-SUM($U$25:U34))*V35*W35/SUMPRODUCT($W35:$W$55,$V35:$V$55)),""),"")
A36: 12 | F36: =IF(AND(E36<>"",E36<>0),D36/E36,"") | H36: =IF(AND(G36<>"",G36<>0),D36/G36,"") | J36: =IF(AND(G36<>"",G36<>0),E36/G36,"") | N36: =IF(AND(I36<>"",I36<>0),G36/I36,"") | O36: =D36/P36 -> #DIV/0! | P36: =$I$8*V36*W36/SUMPRODUCT($W$25:$W$47,$V$25:$V$47) -> #DIV/0! | Q36: =$I$9*V36*W36/SUMPRODUCT($W$25:$W$55,$V$25:$V$55) -> #DIV/0! | R36: =IF($I$12="","",Q36/$I$12) -> #DIV/0! | S36: =IF(W36<>"",IF(D36<>"",D36,($I$8-SUM($S$25:S35))*V36*W36/SUMPRODUCT($W36:$W$55,$V36:$V$55)),"") | T36: =IF(W36<>"",IF(E36<>"",E36,($I$9-SUM($T$25:T35))*V36*W36/SUMPRODUCT($W36:$W$55,$V36:$V$55)),"") | U36: =IF(W36<>"",IF($I$12<>"",IF(G36<>"",G36,($I$9/$I$12-SUM($U$25:U35))*V36*W36/SUMPRODUCT($W36:$W$55,$V36:$V$55)),""),"")
A37: 13 | F37: =IF(AND(E37<>"",E37<>0),D37/E37,"") | H37: =IF(AND(G37<>"",G37<>0),D37/G37,"") | J37: =IF(AND(G37<>"",G37<>0),E37/G37,"") | N37: =IF(AND(I37<>"",I37<>0),G37/I37,"") | O37: =D37/P37 -> #DIV/0! | P37: =$I$8*V37*W37/SUMPRODUCT($W$25:$W$47,$V$25:$V$47) -> #DIV/0! | Q37: =$I$9*V37*W37/SUMPRODUCT($W$25:$W$55,$V$25:$V$55) -> #DIV/0! | R37: =IF($I$12="","",Q37/$I$12) -> #DIV/0! | S37: =IF(W37<>"",IF(D37<>"",D37,($I$8-SUM($S$25:S36))*V37*W37/SUMPRODUCT($W37:$W$55,$V37:$V$55)),"") | T37: =IF(W37<>"",IF(E37<>"",E37,($I$9-SUM($T$25:T36))*V37*W37/SUMPRODUCT($W37:$W$55,$V37:$V$55)),"") | U37: =IF(W37<>"",IF($I$12<>"",IF(G37<>"",G37,($I$9/$I$12-SUM($U$25:U36))*V37*W37/SUMPRODUCT($W37:$W$55,$V37:$V$55)),""),"")
A38: 14 | F38: =IF(AND(E38<>"",E38<>0),D38/E38,"") | H38: =IF(AND(G38<>"",G38<>0),D38/G38,"") | J38: =IF(AND(G38<>"",G38<>0),E38/G38,"") | N38: =IF(AND(I38<>"",I38<>0),G38/I38,"") | O38: =D38/P38 -> #DIV/0! | P38: =$I$8*V38*W38/SUMPRODUCT($W$25:$W$47,$V$25:$V$47) -> #DIV/0! | Q38: =$I$9*V38*W38/SUMPRODUCT($W$25:$W$55,$V$25:$V$55) -> #DIV/0! | R38: =IF($I$12="","",Q38/$I$12) -> #DIV/0! | S38: =IF(W38<>"",IF(D38<>"",D38,($I$8-SUM($S$25:S37))*V38*W38/SUMPRODUCT($W38:$W$55,$V38:$V$55)),"") | T38: =IF(W38<>"",IF(E38<>"",E38,($I$9-SUM($T$25:T37))*V38*W38/SUMPRODUCT($W38:$W$55,$V38:$V$55)),"") | U38: =IF(W38<>"",IF($I$12<>"",IF(G38<>"",G38,($I$9/$I$12-SUM($U$25:U37))*V38*W38/SUMPRODUCT($W38:$W$55,$V38:$V$55)),""),"")
A39: 15 | F39: =IF(AND(E39<>"",E39<>0),D39/E39,"") | H39: =IF(AND(G39<>"",G39<>0),D39/G39,"") | J39: =IF(AND(G39<>"",G39<>0),E39/G39,"") | N39: =IF(AND(I39<>"",I39<>0),G39/I39,"") | O39: =D39/P39 -> #DIV/0! | P39: =$I$8*V39*W39/SUMPRODUCT($W$25:$W$47,$V$25:$V$47) -> #DIV/0! | Q39: =$I$9*V39*W39/SUMPRODUCT($W$25:$W$55,$V$25:$V$55) -> #DIV/0! | R39: =IF($I$12="","",Q39/$I$12) -> #DIV/0! | S39: =IF(W39<>"",IF(D39<>"",D39,($I$8-SUM($S$25:S38))*V39*W39/SUMPRODUCT($W39:$W$55,$V39:$V$55)),"") | T39: =IF(W39<>"",IF(E39<>"",E39,($I$9-SUM($T$25:T38))*V39*W39/SUMPRODUCT($W39:$W$55,$V39:$V$55)),"") | U39: =IF(W39<>"",IF($I$12<>"",IF(G39<>"",G39,($I$9/$I$12-SUM($U$25:U38))*V39*W39/SUMPRODUCT($W39:$W$55,$V39:$V$55)),""),"")
A40: 16 | F40: =IF(AND(E40<>"",E40<>0),D40/E40,"") | H40: =IF(AND(G40<>"",G40<>0),D40/G40,"") | J40: =IF(AND(G40<>"",G40<>0),E40/G40,"") | N40: =IF(AND(I40<>"",I40<>0),G40/I40,"") | O40: =D40/P40 -> #DIV/0! | P40: =$I$8*V40*W40/SUMPRODUCT($W$25:$W$47,$V$25:$V$47) -> #DIV/0! | Q40: =$I$9*V40*W40/SUMPRODUCT($W$25:$W$55,$V$25:$V$55) -> #DIV/0! | R40: =IF($I$12="","",Q40/$I$12) -> #DIV/0! | S40: =IF(W40<>"",IF(D40<>"",D40,($I$8-SUM($S$25:S39))*V40*W40/SUMPRODUCT($W40:$W$55,$V40:$V$55)),"") | T40: =IF(W40<>"",IF(E40<>"",E40,($I$9-SUM($T$25:T39))*V40*W40/SUMPRODUCT($W40:$W$55,$V40:$V$55)),"") | U40: =IF(W40<>"",IF($I$12<>"",IF(G40<>"",G40,($I$9/$I$12-SUM($U$25:U39))*V40*W40/SUMPRODUCT($W40:$W$55,$V40:$V$55)),""),"")
A41: 17 | F41: =IF(AND(E41<>"",E41<>0),D41/E41,"") | H41: =IF(AND(G41<>"",G41<>0),D41/G41,"") | J41: =IF(AND(G41<>"",G41<>0),E41/G41,"") | N41: =IF(AND(I41<>"",I41<>0),G41/I41,"") | O41: =D41/P41 -> #DIV/0! | P41: =$I$8*V41*W41/SUMPRODUCT($W$25:$W$47,$V$25:$V$47) -> #DIV/0! | Q41: =$I$9*V41*W41/SUMPRODUCT($W$25:$W$55,$V$25:$V$55) -> #DIV/0! | R41: =IF($I$12="","",Q41/$I$12) -> #DIV/0! | S41: =IF(W41<>"",IF(D41<>"",D41,($I$8-SUM($S$25:S40))*V41*W41/SUMPRODUCT($W41:$W$55,$V41:$V$55)),"") | T41: =IF(W41<>"",IF(E41<>"",E41,($I$9-SUM($T$25:T40))*V41*W41/SUMPRODUCT($W41:$W$55,$V41:$V$55)),"") | U41: =IF(W41<>"",IF($I$12<>"",IF(G41<>"",G41,($I$9/$I$12-SUM($U$25:U40))*V41*W41/SUMPRODUCT($W41:$W$55,$V41:$V$55)),""),"")
A42: 18 | F42: =IF(AND(E42<>"",E42<>0),D42/E42,"") | H42: =IF(AND(G42<>"",G42<>0),D42/G42,"") | J42: =IF(AND(G42<>"",G42<>0),E42/G42,"") | N42: =IF(AND(I42<>"",I42<>0),G42/I42,"") | O42: =D42/P42 -> #DIV/0! | P42: =$I$8*V42*W42/SUMPRODUCT($W$25:$W$47,$V$25:$V$47) -> #DIV/0! | Q42: =$I$9*V42*W42/SUMPRODUCT($W$25:$W$55,$V$25:$V$55) -> #DIV/0! | R42: =IF($I$12="","",Q42/$I$12) -> #DIV/0! | S42: =IF(W42<>"",IF(D42<>"",D42,($I$8-SUM($S$25:S41))*V42*W42/SUMPRODUCT($W42:$W$55,$V42:$V$55)),"") | T42: =IF(W42<>"",IF(E42<>"",E42,($I$9-SUM($T$25:T41))*V42*W42/SUMPRODUCT($W42:$W$55,$V42:$V$55)),"") | U42: =IF(W42<>"",IF($I$12<>"",IF(G42<>"",G42,($I$9/$I$12-SUM($U$25:U41))*V42*W42/SUMPRODUCT($W42:$W$55,$V42:$V$55)),""),"")
F43: =IF(AND(E43<>"",E43<>0),D43/E43,"") | H43: =IF(AND(G43<>"",G43<>0),D43/G43,"") | J43: =IF(AND(G43<>"",G43<>0),E43/G43,"") | N43: =IF(AND(I43<>"",I43<>0),G43/I43,"") | O43: =D43/P43 -> #DIV/0! | P43: =$I$8*V43*W43/SUMPRODUCT($W$25:$W$47,$V$25:$V$47) -> #DIV/0! | Q43: =$I$9*V43*W43/SUMPRODUCT($W$25:$W$55,$V$25:$V$55) -> #DIV/0! | R43: =IF($I$12="","",Q43/$I$12) -> #DIV/0! | S43: =IF(W43<>"",IF(D43<>"",D43,($I$8-SUM($S$25:S42))*V43*W43/SUMPRODUCT($W43:$W$55,$V43:$V$55)),"") | T43: =IF(W43<>"",IF(E43<>"",E43,($I$9-SUM($T$25:T42))*V43*W43/SUMPRODUCT($W43:$W$55,$V43:$V$55)),"") | U43: =IF(W43<>"",IF($I$12<>"",IF(G43<>"",G43,($I$9/$I$12-SUM($U$25:U42))*V43*W43/SUMPRODUCT($W43:$W$55,$V43:$V$55)),""),"")
F44: =IF(AND(E44<>"",E44<>0),D44/E44,"") | H44: =IF(AND(G44<>"",G44<>0),D44/G44,"") | J44: =IF(AND(G44<>"",G44<>0),E44/G44,"") | N44: =IF(AND(I44<>"",I44<>0),G44/I44,"") | O44: =D44/P44 -> #DIV/0! | P44: =$I$8*V44*W44/SUMPRODUCT($W$25:$W$47,$V$25:$V$47) -> #DIV/0! | Q44: =$I$9*V44*W44/SUMPRODUCT($W$25:$W$55,$V$25:$V$55) -> #DIV/0! | R44: =IF($I$12="","",Q44/$I$12) -> #DIV/0! | S44: =IF(W44<>"",IF(D44<>"",D44,($I$8-SUM($S$25:S43))*V44*W44/SUMPRODUCT($W44:$W$55,$V44:$V$55)),"") | T44: =IF(W44<>"",IF(E44<>"",E44,($I$9-SUM($T$25:T43))*V44*W44/SUMPRODUCT($W44:$W$55,$V44:$V$55)),0) -> 0 | U44: =IF(W44<>"",IF($I$12<>"",IF(G44<>"",G44,($I$9/$I$12-SUM($U$25:U43))*V44*W44/SUMPRODUCT($W44:$W$55,$V44:$V$55)),""),"")
F45: =IF(AND(E45<>"",E45<>0),D45/E45,"") | H45: =IF(AND(G45<>"",G45<>0),D45/G45,"") | J45: =IF(AND(G45<>"",G45<>0),E45/G45,"") | N45: =IF(AND(I45<>"",I45<>0),G45/I45,"") | O45: =D45/P45 -> #DIV/0! | P45: =$I$8*V45*W45/SUMPRODUCT($W$25:$W$47,$V$25:$V$47) -> #DIV/0! | Q45: =$I$9*V45*W45/SUMPRODUCT($W$25:$W$44,$V$25:$V$44) -> #DIV/0! | R45: =IF($I$12="","",Q45/$I$12) -> #DIV/0! | S45: =IF(W45<>"",IF(D45<>"",D45,($I$8-SUM($S$25:S44))*V45*W45/SUMPRODUCT($W$44:$W45,$V$44:$V45)),"") | T45: =IF(W45<>"",IF(E45<>"",E45,($I$9-SUM($T$25:T44))*V45*W45/SUMPRODUCT($W$44:$W45,$V$44:$V45)),"") | U45: =IF(W45<>"",IF($I$12<>"",IF(G45<>"",G45,($I$9/$I$12-SUM($U$25:U44))*V45*W45/SUMPRODUCT($W$44:$W45,$V$44:$V45)),""),"")
F46: =IF(AND(E46<>"",E46<>0),D46/E46,"") | H46: =IF(AND(G46<>"",G46<>0),D46/G46,"") | J46: =IF(AND(G46<>"",G46<>0),E46/G46,"") | N46: =IF(AND(I46<>"",I46<>0),G46/I46,"") | O46: =D46/P46 -> #DIV/0! | P46: =$I$8*V46*W46/SUMPRODUCT($W$25:$W$47,$V$25:$V$47) -> #DIV/0! | Q46: =$I$9*V46*W46/SUMPRODUCT($W$25:$W$44,$V$25:$V$44) -> #DIV/0! | R46: =IF($I$12="","",Q46/$I$12) -> #DIV/0! | S46: =IF(W46<>"",IF(D46<>"",D46,($I$8-SUM($S$25:S45))*V46*W46/SUMPRODUCT($W$44:$W46,$V$44:$V46)),"") | T46: =IF(W46<>"",IF(E46<>"",E46,($I$9-SUM($T$25:T45))*V46*W46/SUMPRODUCT($W$44:$W46,$V$44:$V46)),"") | U46: =IF(W46<>"",IF($I$12<>"",IF(G46<>"",G46,($I$9/$I$12-SUM($U$25:U45))*V46*W46/SUMPRODUCT($W$44:$W46,$V$44:$V46)),""),"")
F47: =IF(AND(E47<>"",E47<>0),D47/E47,"") | H47: =IF(AND(G47<>"",G47<>0),D47/G47,"") | J47: =IF(AND(G47<>"",G47<>0),E47/G47,"") | N47: =IF(AND(I47<>"",I47<>0),G47/I47,"") | O47: =D47/P47 -> #DIV/0! | P47: =$I$8*V47*W47/SUMPRODUCT($W$25:$W$47,$V$25:$V$47) -> #DIV/0! | Q47: =$I$9*V47*W47/SUMPRODUCT($W$25:$W$47,$V$25:$V$47) -> #DIV/0! | R47: =IF($I$12="","",Q47/$I$12) -> #DIV/0! | S47: =IF(W47<>"",IF(D47<>"",D47,($I$8-SUM($S$25:S46))*V47*W47/SUMPRODUCT($W47:$W$47,$V47:$V$47)),"") | T47: =IF(W47<>"",IF(E47<>"",E47,($I$9-SUM($T$25:T46))*V47*W47/SUMPRODUCT($W47:$W$47,$V47:$V$47)),"") | U47: =IF(W47<>"",IF($I$12<>"",IF(G47<>"",G47,($I$9/$I$12-SUM($U$25:U46))*V47*W47/SUMPRODUCT($W47:$W$47,$V47:$V$47)),""),"")
B48: итого | D48: =SUM(D25:D47) -> 0 | E48: =SUM(E25:E47) -> 0 | F48: =IF(AND(E48<>"",E48<>0),D48/E48,"") | G48: =SUM(G25:G47) -> 0 | H48: =IF(AND(G48<>"",G48<>0),D48/G48,"") | I48: =SUM(I25:I47) -> 0 | J48: =IF(AND(G48<>"",G48<>0),E48/G48,"") | K48: =SUM(K25:K47) -> 0 | L48: =SUM(L25:L47) -> 0 | M48: =SUM(M25:M47) -> 0 | N48: =IF(AND(I48<>"",I48<>0),G48/I48,"") | O48: =D48/P48 -> #DIV/0! | P48: =SUM(P25:P47) -> #DIV/0! | Q48: =SUM(Q25:Q47) -> #DIV/0! | R48: =SUM(R25:R47) -> #DIV/0! | S48: =SUM(S25:S47) -> #DIV/0! | T48: =SUM(T25:T47) -> #DIV/0! | U48: =SUM(U25:U47) -> #DIV/0!
D49: =SUMIF(D25:D47,"",P25:P47)+D48 -> #DIV/0!

Sheet Доп сотрудник
B1: =TODAY()-1 -> 45909
B2: (отчетная дата) | J2: ЕЖЕДНЕВНЫЙ ОТЧЕТ О ПРОДАЖАХ
B3: Осталось до выполнения плана!!! | J3: =График!B25 -> 0
C4: =I8-D48 -> 0 | E4: =IF(I8<>0,C4/I8,0) -> 0
F6: Целевые показатели
F7: Показатель | I7: План | J7: Факт | K7: % выполнения | L7: Прогноз выполнения | M7: % выполнения по прогнозу | N7: Отклонение | O7: Факт аналогичного месяца прошлого года | P7: Отклонение LFL
F8: Выручка | I8: ='Ялта, Ленина, 18'!I8/График!AI31*График!AI25 -> 0 | J8: =D48 -> 0 | K8: =IF(AND(I8<>"", I8<>0, J8<>""), J8/I8, "") | L8: =IF(SUMIF($D$25:$D$47,">=0",$P$25:$P$47)<>0,I8*D48/SUMIF($D$25:$D$47,">=0",$P$25:$P$47),0) -> 0 | M8: =IF(AND(I8<>"", I8<>0, L8<>"", L8<>0), L8/I8, "") | N8: =IF(AND(J8<>0, J8<>"", I8<>0, I8<>""), L8-I8, "") | P8: =IF(AND(O8<>"", O8<>0, L8<>"", L8<>0), -O8+L8, "") | Q8: =IF(AND(P8<>"", P8<>0, O8<>0, O8<>""), P8/O8, "")
F9: Кол-во изделий | I9: =I8/I11 -> 0 | J9: =E48 -> 0 | K9: =IF(AND(I9<>"", I9<>0, J9<>""), J9/I9, "") | L9: =IF(SUMIF($E$25:$E$47,">=0",$Q$25:$Q$47)<>0,I9*E48/SUMIF($E$25:$E$47,">=0",$Q$25:$Q$47),0) -> 0 | M9: =IF(AND(I9<>"", I9<>0, L9<>"", L9<>0), L9/I9, "") | N9: =IF(AND(J9<>0, J9<>"", I9<>0, I9<>""), L9-I9, "") | O9: =O8/O11 -> #DIV/0! | P9: =IF(AND(O9<>"", O9<>0, L9<>"", L9<>0), -O9+L9, "") -> #DIV/0! | Q9: =IF(AND(P9<>"", P9<>0, O9<>0, O9<>""), P9/O9, "") -> #DIV/0!
F10: Средний чек | I10: =I11*I12 -> 10200 | J10: =H48 | K10: =IF(AND(I10<>"", I10<>0, J10<>""), J10/I10, "") | L10: =J10 | M10: =IF(AND(I10<>"", I10<>0, L10<>"", L10<>0), L10/I10, "") | N10: =IF(AND(J10<>0, J10<>"", I10<>0, I10<>""), L10-I10, "") | O10: =O11*O12 -> 0 | P10: =IF(AND(O10<>"", O10<>0, L10<>"", L10<>0), -O10+L10, "") | Q10: =IF(AND(P10<>"", P10<>0, O10<>0, O10<>""), P10/O10, "") | S10: IS
F11: Средняя стоимость изделия | I11: ='Ялта, Ленина, 18'!I11 -> 6000 | J11: =F48 | K11: =IF(AND(I11<>"", I11<>0, J11<>""), J11/I11, "") | L11: =IF(L9>0, L8/L9, "") | M11: =IF(AND(I11<>"", I11<>0, L11<>"", L11<>0), L11/I11, "") | N11: =IF(AND(J11<>0, J11<>"", I11<>0, I11<>""), L11-I11, "") | P11: =IF(AND(O11<>"", O11<>0, L11<>"", L11<>0), -O11+L11, "") | Q11: =IF(AND(P11<>"", P11<>0, O11<>0, O11<>""), P11/O11, "")
F12: Длина чека | I12: ='Ялта, Ленина, 18'!I12 -> 1.7 | J12: =J48 | K12: =IF(AND(I12<>"", I12<>0, J12<>""), J12/I12, "") | L12: =J12 | M12: =IF(AND(I12<>"", I12<>0, L12<>"", L12<>0), L12/I12, "") | N12: =IF(AND(J12<>0, J12<>"", I12<>0, I12<>""), L12-I12, "") | P12: =IF(AND(O12<>"", O12<>0, L12<>"", L12<>0), -O12+L12, "") | Q12: =IF(AND(P12<>"", P12<>0, O12<>0, O12<>""), P12/O12, "") | S12: ='Ялта, Ленина, 18'!S12*График!AJ25/График!AJ31 -> 0 | T12: =L48 -> 0
F13: Кол-во чеков | I13: =IF(I12<>0, I9/I12, "") -> 0 | J13: =G48 -> 0 | K13: =IF(AND(I13<>"", I13<>0, J13<>""), J13/I13, "") | L13: =IF(SUMIF($G$25:$G$47,">=0",$R$25:$R$47)<>0,I13*G48/SUMIF($G$25:$G$47,">=0",$R$25:$R$47),"") | M13: =IF(AND(I13<>"", I13<>0, L13<>"", L13<>0), L13/I13, "") | N13: =IF(AND(J13<>0, J13<>"", I13<>0, I13<>""), L13-I13, "") | P13: =IF(AND(O13<>"", O13<>0, L13<>"", L13<>0), -O13+L13, "") | Q13: =IF(AND(P13<>"", P13<>0, O13<>0, O13<>""), P13/O13, "") | S13: =T12/S12 -> #DIV/0! | T13: =S13/J14*I14 -> #DIV/0!
F14: Кол-во смен план/отработано | I14: =График!AI25 -> 0 | K14: =IF(AND(I14<>"", I14<>0, J14<>""), J14/I14, "") | M14: =IF(AND(I14<>"", I14<>0, L14<>"", L14<>0), L14/I14, "") | N14: =IF(AND(J14<>0, J14<>"", I14<>0, I14<>""), L14-I14, "") | P14: =IF(AND(O14<>"", O14<>0, L14<>"", L14<>0), -O14+L14, "") | Q14: =IF(AND(P14<>"", P14<>0, O14<>0, O14<>""), P14/O14, "")
F15: Средние продажи в смену | I15: ='Ялта, Ленина, 18'!I15 -> 151618.06 | J15: =J8/J14 -> #DIV/0! | K15: =IF(AND(I15<>"", I15<>0, J15<>""), J15/I15, "") -> #DIV/0! | L15: =J15 -> #DIV/0! | M15: =IF(AND(I15<>"", I15<>0, L15<>"", L15<>0), L15/I15, "") -> #DIV/0! | N15: =IF(AND(J15<>0, J15<>"", I15<>0, I15<>""), L15-I15, "") -> #DIV/0! | P15: =IF(AND(O15<>"", O15<>0, L15<>"", L15<>0), -O15+L15, "") -> #DIV/0! | Q15: =IF(AND(P15<>"", P15<>0, O15<>0, O15<>""), P15/O15, "") -> #DIV/0!
F16: Отставание/Перевыполнение | J16: =J8-I15*J14 -> 0 | K16: =IF(AND(I16<>"", I16<>0, J16<>""), J16/I16, "") | L16: =J16 -> 0 | M16: =IF(AND(I16<>"", I16<>0, L16<>"", L16<>0), L16/I16, "") | N16: =IF(AND(J16<>0, J16<>"", I16<>0, I16<>""), L16-I16, "") | P16: =IF(AND(O16<>"", O16<>0, L16<>"", L16<>0), -O16+L16, "") | Q16: =IF(AND(P16<>"", P16<>0, O16<>0, O16<>""), P16/O16, "") | S16: UNOde50
F17: Трафик | I17: ='Ялта, Ленина, 18'!I17/График!AJ31*График!AJ25 -> 0 | J17: =I48 -> 0 | K17: =IF(AND(I17<>"", I17<>0, J17<>""), J17/I17, "") | L17: =J17/J14*I14 -> #DIV/0! | M17: =IF(AND(I17<>"", I17<>0, L17<>"", L17<>0), L17/I17, "") -> #DIV/0! | N17: =IF(AND(J17<>0, J17<>"", I17<>0, I17<>""), L17-I17, "") | P17: =IF(AND(O17<>"", O17<>0, L17<>"", L17<>0), -O17+L17, "") -> #DIV/0! | Q17: =IF(AND(P17<>"", P17<>0, O17<>0, O17<>""), P17/O17, "") -> #DIV/0!
K18: =IF(AND(I18<>"", I18<>0, J18<>""), J18/I18, "") | L18: =J18 -> 0 | M18: =IF(AND(I18<>"", I18<>0, L18<>"", L18<>0), L18/I18, "") | N18: =IF(AND(J18<>0, J18<>"", I18<>0, I18<>""), L18-I18, "") | O18: 0 | P18: =IF(AND(O18<>"", O18<>0, L18<>"", L18<>0), -O18+L18, "") | Q18: =IF(AND(P18<>"", P18<>0, O18<>0, O18<>""), P18/O18, "") | S18: ='Ялта, Ленина, 18'!S18*График!AJ25/График!AJ31 -> 0 | T18: =K48 -> 0
K19: =IF(AND(I19<>"", I19<>0, J19<>""), J19/I19, "") | L19: =J19 -> 0 | M19: =IF(AND(I19<>"", I19<>0, L19<>"", L19<>0), L19/I19, "") | N19: =IF(AND(J19<>0, J19<>"", I19<>0, I19<>""), L19-I19, "") | O19: 0 | P19: =IF(AND(O19<>"", O19<>0, L19<>"", L19<>0), -O19+L19, "") | Q19: =IF(AND(P19<>"", P19<>0, O19<>0, O19<>""), P19/O19, "") | S19: =T18/S18 -> #DIV/0! | T19: =S19/J14*I14 -> #DIV/0!
F20: Конверсия план/факт | I20: ='Ялта, Ленина, 18'!I20 -> 0.18 | J20: =N48 | K20: =J20/I20 -> #VALUE! | L20: =IF(AND(K8<>0,I14<>0,I48<>0),(I48*N48+(I48/K8-I48)*I20)/(I48/K8),0) -> 0 | M20: =IF(AND(I20<>"", I20<>0, L20<>"", L20<>0), L20/I20, "") | N20: =IF(AND(J20<>0, J20<>"", I20<>0, I20<>""), L20-I20, "") | P20: =IF(AND(O20<>"", O20<>0, L20<>"", L20<>0), -O20+L20, "") | Q20: =IF(AND(P20<>"", P20<>0, O20<>0, O20<>""), P20/O20, "")
B22: Факт продаж за месяц | O22: % выполнения дневного плана | P22: Раcпределение плана по дням
B23: Дата | C23: День недели | D23: Выручка (руб) | E23: Кол-во единиц (шт.) | F23: Средняя стоимость изделия (руб.) | G23: Количество чеков (шт.) | H23: Средняя сумма чека (руб.) | I23: Трафик | J23: Длина чека (шт.) | K23: UNOde50 | L23: IS | M23: Запасной | N23: Конверсия (%) | P23: выручка, план | Q23: кол-во ед, план | R23: Кол-во чеков, план | S23: выручка, скорректир.план | T23: кол-во ед, скорр. план | U23: кол-во чеков, скорр. план | V23: Коэфф. Дня Недели | W23: Специфика месяца
B24: 1 | C24: 2 | D24: 3 | E24: в | F24: 5 | G24: 6 | H24: 7 | I24: 8 | J24: 9 | K24: 10 | L24: 11 | M24: 12 | N24: 13 | P24: 1 | Q24: 2 | R24: 3 | S24: 4 | T24: 5 | U24: 6 | V24: 10 | W24: 11
F25: =IF(AND(E25<>"",E25<>0),D25/E25,"") | H25: =IF(AND(G25<>"",G25<>0),D25/G25,"") | J25: =IF(AND(G25<>"",G25<>0),E25/G25,"") | N25: =IF(AND(I25<>"",I25<>0),G25/I25,"") | O25: =D25/P25 -> #DIV/0! | P25: =$I$8*V25*W25/SUMPRODUCT($W$25:$W$55,$V$25:$V$55) -> 0 | Q25: =$I$9*V25*W25/SUMPRODUCT($W$25:$W$55,$V$25:$V$55) -> 0 | R25: =IF($I$12="","",Q25/$I$12) -> 0 | S25: =IF(W25<>"",IF(D25<>"",D25,($I$8-SUM($S24:S$25))*V25*W25/SUMPRODUCT($W25:$W$55,$V25:$V$55)),"") -> #REF! | T25: =IF(W25<>"",IF(E25<>"",E25,($I$9-SUM($T24:T$25))*V25*W25/SUMPRODUCT($W25:$W$55,$V25:$V$55)),"") -> #REF! | U25: =IF(W25<>"",IF($I$12<>"",IF(G25<>"",G25,($I$9/$I$12-SUM($U24:U$25))*V25*W25/SUMPRODUCT($W25:$W$55,$V25:$V$55)),""),"") -> #REF! | V25: 1.1982013 | W25: 1.1982013
F26: =IF(AND(E26<>"",E26<>0),D26/E26,"") | H26: =IF(AND(G26<>"",G26<>0),D26/G26,"") | J26: =IF(AND(G26<>"",G26<>0),E26/G26,"") | N26: =IF(AND(I26<>"",I26<>0),G26/I26,"") | O26: =D26/P26 -> #DIV/0! | P26: =$I$8*V26*W26/SUMPRODUCT($W$25:$W$55,$V$25:$V$55) -> 0 | Q26: =$I$9*V26*W26/SUMPRODUCT($W$25:$W$55,$V$25:$V$55) -> 0 | R26: =IF($I$12="","",Q26/$I$12) -> 0 | S26: =IF(W26<>"",IF(D26<>"",D26,($I$8-SUM($S$25:S25))*V26*W26/SUMPRODUCT($W26:$W$55,$V26:$V$55)),"") | T26: =IF(W26<>"",IF(E25<>"",E25,($I$9-SUM($T$25:T25))*V26*W26/SUMPRODUCT($W26:$W$55,$V26:$V$55)),"") | U26: =IF(W26<>"",IF($I$12<>"",IF(G26<>"",G26,($I$9/$I$12-SUM($U$25:U25))*V26*W26/SUMPRODUCT($W26:$W$55,$V26:$V$55)),""),"")
F27: =IF(AND(E27<>"",E27<>0),D27/E27,"") | H27: =IF(AND(G27<>"",G27<>0),D27/G27,"") | J27: =IF(AND(G27<>"",G27<>0),E27/G27,"") | N27: =IF(AND(I27<>"",I27<>0),G27/I27,"") | O27: =D27/P27 -> #DIV/0! | P27: =$I$8*V27*W27/SUMPRODUCT($W$25:$W$55,$V$25:$V$55) -> 0 | Q27: =$I$9*V27*W27/SUMPRODUCT($W$25:$W$55,$V$25:$V$55) -> 0 | R27: =IF($I$12="","",Q27/$I$12) -> 0 | S27: =IF(W27<>"",IF(D27<>"",D27,($I$8-SUM($S$25:S26))*V27*W27/SUMPRODUCT($W27:$W$55,$V27:$V$55)),"") | T27: =IF(W27<>"",IF(E27<>"",E27,($I$9-SUM($T$25:T26))*V27*W27/SUMPRODUCT($W27:$W$55,$V27:$V$55)),"") | U27: =IF(W27<>"",IF($I$12<>"",IF(G27<>"",G27,($I$9/$I$12-SUM($U$25:U26))*V27*W27/SUMPRODUCT($W27:$W$55,$V27:$V$55)),""),"")
F28: =IF(AND(E28<>"",E28<>0),D28/E28,"") | H28: =IF(AND(G28<>"",G28<>0),D28/G28,"") | J28: =IF(AND(G28<>"",G28<>0),E28/G28,"") | N28: =IF(AND(I28<>"",I28<>0),G28/I28,"") | O28: =D28/P28 -> #DIV/0! | P28: =$I$8*V28*W28/SUMPRODUCT($W$25:$W$55,$V$25:$V$55) -> 0 | Q28: =$I$9*V28*W28/SUMPRODUCT($W$25:$W$55,$V$25:$V$55) -> 0 | R28: =IF($I$12="","",Q28/$I$12) -> 0 | S28: =IF(W28<>"",IF(D28<>"",D28,($I$8-SUM($S$25:S27))*V28*W28/SUMPRODUCT($W28:$W$55,$V28:$V$55)),"") | T28: =IF(W28<>"",IF(E28<>"",E28,($I$9-SUM($T$25:T27))*V28*W28/SUMPRODUCT($W28:$W$55,$V28:$V$55)),"") | U28: =IF(W28<>"",IF($I$12<>"",IF(G28<>"",G28,($I$9/$I$12-SUM($U$25:U27))*V28*W28/SUMPRODUCT($W28:$W$55,$V28:$V$55)),""),"")
F29: =IF(AND(E29<>"",E29<>0),D29/E29,"") | H29: =IF(AND(G29<>"",G29<>0),D29/G29,"") | J29: =IF(AND(G29<>"",G29<>0),E29/G29,"") | N29: =IF(AND(I29<>"",I29<>0),G29/I29,"") | O29: =D29/P29 -> #DIV/0! | P29: =$I$8*V29*W29/SUMPRODUCT($W$25:$W$55,$V$25:$V$55) -> 0 | Q29: =$I$9*V29*W29/SUMPRODUCT($W$25:$W$55,$V$25:$V$55) -> 0 | R29: =IF($I$12="","",Q29/$I$12) -> 0 | S29: =IF(W29<>"",IF(D29<>"",D29,($I$8-SUM($S$25:S28))*V29*W29/SUMPRODUCT($W29:$W$55,$V29:$V$55)),"") | T29: =IF(W29<>"",IF(E29<>"",E29,($I$9-SUM($T$25:T28))*V29*W29/SUMPRODUCT($W29:$W$55,$V29:$V$55)),"") | U29: =IF(W29<>"",IF($I$12<>"",IF(G29<>"",G29,($I$9/$I$12-SUM($U$25:U28))*V29*W29/SUMPRODUCT($W29:$W$55,$V29:$V$55)),""),"")
F30: =IF(AND(E30<>"",E30<>0),D30/E30,"") | H30: =IF(AND(G30<>"",G30<>0),D30/G30,"") | J30: =IF(AND(G30<>"",G30<>0),E30/G30,"") | N30: =IF(AND(I30<>"",I30<>0),G30/I30,"") | O30: =D30/P30 -> #DIV/0! | P30: =$I$8*V30*W30/SUMPRODUCT($W$25:$W$55,$V$25:$V$55) -> 0 | Q30: =$I$9*V30*W30/SUMPRODUCT($W$25:$W$55,$V$25:$V$55) -> 0 | R30: =IF($I$12="","",Q30/$I$12) -> 0 | S30: =IF(W30<>"",IF(D30<>"",D30,($I$8-SUM($S$25:S29))*V30*W30/SUMPRODUCT($W30:$W$55,$V30:$V$55)),"") | T30: =IF(W30<>"",IF(E30<>"",E30,($I$9-SUM($T$25:T29))*V30*W30/SUMPRODUCT($W30:$W$55,$V30:$V$55)),"") | U30: =IF(W30<>"",IF($I$12<>"",IF(G30<>"",G30,($I$9/$I$12-SUM($U$25:U29))*V30*W30/SUMPRODUCT($W30:$W$55,$V30:$V$55)),""),"")
F31: =IF(AND(E31<>"",E31<>0),D31/E31,"") | H31: =IF(AND(G31<>"",G31<>0),D31/G31,"") | J31: =IF(AND(G31<>"",G31<>0),E31/G31,"") | N31: =IF(AND(I31<>"",I31<>0),G31/I31,"") | O31: =D31/P31 -> #DIV/0! | P31: =$I$8*V31*W31/SUMPRODUCT($W$25:$W$55,$V$25:$V$55) -> 0 | Q31: =$I$9*V31*W31/SUMPRODUCT($W$25:$W$55,$V$25:$V$55) -> 0 | R31: =IF($I$12="","",Q31/$I$12) -> 0 | S31: =IF(W31<>"",IF(D31<>"",D31,($I$8-SUM($S$25:S30))*V31*W31/SUMPRODUCT($W31:$W$55,$V31:$V$55)),"") | T31: =IF(W31<>"",IF(E31<>"",E31,($I$9-SUM($T$25:T30))*V31*W31/SUMPRODUCT($W31:$W$55,$V31:$V$55)),"") | U31: =IF(W31<>"",IF($I$12<>"",IF(G31<>"",G31,($I$9/$I$12-SUM($U$25:U30))*V31*W31/SUMPRODUCT($W31:$W$55,$V31:$V$55)),""),"")
F32: =IF(AND(E32<>"",E32<>0),D32/E32,"") | H32: =IF(AND(G32<>"",G32<>0),D32/G32,"") | J32: =IF(AND(G32<>"",G32<>0),E32/G32,"") | N32: =IF(AND(I32<>"",I32<>0),G32/I32,"") | O32: =D32/P32 -> #DIV/0! | P32: =$I$8*V32*W32/SUMPRODUCT($W$25:$W$55,$V$25:$V$55) -> 0 | Q32: =$I$9*V32*W32/SUMPRODUCT($W$25:$W$55,$V$25:$V$55) -> 0 | R32: =IF($I$12="","",Q32/$I$12) -> 0 | S32: =IF(W32<>"",IF(D32<>"",D32,($I$8-SUM($S$25:S31))*V32*W32/SUMPRODUCT($W32:$W$55,$V32:$V$55)),"") | T32: =IF(W32<>"",IF(E32<>"",E32,($I$9-SUM($T$25:T31))*V32*W32/SUMPRODUCT($W32:$W$55,$V32:$V$55)),"") | U32: =IF(W32<>"",IF($I$12<>"",IF(G32<>"",G32,($I$9/$I$12-SUM($U$25:U31))*V32*W32/SUMPRODUCT($W32:$W$55,$V32:$V$55)),""),"")
F33: =IF(AND(E33<>"",E33<>0),D33/E33,"") | H33: =IF(AND(G33<>"",G33<>0),D33/G33,"") | J33: =IF(AND(G33<>"",G33<>0),E33/G33,"") | N33: =IF(AND(I33<>"",I33<>0),G33/I33,"") | O33: =D33/P33 -> #DIV/0! | P33: =$I$8*V33*W33/SUMPRODUCT($W$25:$W$55,$V$25:$V$55) -> 0 | Q33: =$I$9*V33*W33/SUMPRODUCT($W$25:$W$55,$V$25:$V$55) -> 0 | R33: =IF($I$12="","",Q33/$I$12) -> 0 | S33: =IF(W33<>"",IF(D33<>"",D33,($I$8-SUM($S$25:S32))*V33*W33/SUMPRODUCT($W33:$W$55,$V33:$V$55)),"") | T33: =IF(W33<>"",IF(E33<>"",E33,($I$9-SUM($T$25:T32))*V33*W33/SUMPRODUCT($W33:$W$55,$V33:$V$55)),"") | U33: =IF(W33<>"",IF($I$12<>"",IF(G33<>"",G33,($I$9/$I$12-SUM($U$25:U32))*V33*W33/SUMPRODUCT($W33:$W$55,$V33:$V$55)),""),"")
F34: =IF(AND(E34<>"",E34<>0),D34/E34,"") | H34: =IF(AND(G34<>"",G34<>0),D34/G34,"") | J34: =IF(AND(G34<>"",G34<>0),E34/G34,"") | N34: =IF(AND(I34<>"",I34<>0),G34/I34,"") | O34: =D34/P34 -> #DIV/0! | P34: =$I$8*V34*W34/SUMPRODUCT($W$25:$W$55,$V$25:$V$55) -> 0 | Q34: =$I$9*V34*W34/SUMPRODUCT($W$25:$W$55,$V$25:$V$55) -> 0 | R34: =IF($I$12="","",Q34/$I$12) -> 0 | S34: =IF(W34<>"",IF(D34<>"",D34,($I$8-SUM($S$25:S33))*V34*W34/SUMPRODUCT($W34:$W$55,$V34:$V$55)),"") | T34: =IF(W34<>"",IF(E34<>"",E34,($I$9-SUM($T$25:T33))*V34*W34/SUMPRODUCT($W34:$W$55,$V34:$V$55)),"") | U34: =IF(W34<>"",IF($I$12<>"",IF(G34<>"",G34,($I$9/$I$12-SUM($U$25:U33))*V34*W34/SUMPRODUCT($W34:$W$55,$V34:$V$55)),""),"")
F35: =IF(AND(E35<>"",E35<>0),D35/E35,"") | H35: =IF(AND(G35<>"",G35<>0),D35/G35,"") | J35: =IF(AND(G35<>"",G35<>0),E35/G35,"") | N35: =IF(AND(I35<>"",I35<>0),G35/I35,"") | O35: =D35/P35 -> #DIV/0! | P35: =$I$8*V35*W35/SUMPRODUCT($W$25:$W$55,$V$25:$V$55) -> 0 | Q35: =$I$9*V35*W35/SUMPRODUCT($W$25:$W$55,$V$25:$V$55) -> 0 | R35: =IF($I$12="","",Q35/$I$12) -> 0 | S35: =IF(W35<>"",IF(D35<>"",D35,($I$8-SUM($S$25:S34))*V35*W35/SUMPRODUCT($W35:$W$55,$V35:$V$55)),"") | T35: =IF(W35<>"",IF(E35<>"",E35,($I$9-SUM($T$25:T34))*V35*W35/SUMPRODUCT($W35:$W$55,$V35:$V$55)),"") | U35: =IF(W35<>"",IF($I$12<>"",IF(G35<>"",G35,($I$9/$I$12-SUM($U$25:U34))*V35*W35/SUMPRODUCT($W35:$W$55,$V35:$V$55)),""),"")
F36: =IF(AND(E36<>"",E36<>0),D36/E36,"") | H36: =IF(AND(G36<>"",G36<>0),D36/G36,"") | J36: =IF(AND(G36<>"",G36<>0),E36/G36,"") | N36: =IF(AND(I36<>"",I36<>0),G36/I36,"") | O36: =D36/P36 -> #DIV/0! | P36: =$I$8*V36*W36/SUMPRODUCT($W$25:$W$55,$V$25:$V$55) -> 0 | Q36: =$I$9*V36*W36/SUMPRODUCT($W$25:$W$55,$V$25:$V$55) -> 0 | R36: =IF($I$12="","",Q36/$I$12) -> 0 | S36: =IF(W36<>"",IF(D36<>"",D36,($I$8-SUM($S$25:S35))*V36*W36/SUMPRODUCT($W36:$W$55,$V36:$V$55)),"") | T36: =IF(W36<>"",IF(E36<>"",E36,($I$9-SUM($T$25:T35))*V36*W36/SUMPRODUCT($W36:$W$55,$V36:$V$55)),"") | U36: =IF(W36<>"",IF($I$12<>"",IF(G36<>"",G36,($I$9/$I$12-SUM($U$25:U35))*V36*W36/SUMPRODUCT($W36:$W$55,$V36:$V$55)),""),"")
F37: =IF(AND(E37<>"",E37<>0),D37/E37,"") | H37: =IF(AND(G37<>"",G37<>0),D37/G37,"") | J37: =IF(AND(G37<>"",G37<>0),E37/G37,"") | N37: =IF(AND(I37<>"",I37<>0),G37/I37,"") | O37: =D37/P37 -> #DIV/0! | P37: =$I$8*V37*W37/SUMPRODUCT($W$25:$W$55,$V$25:$V$55) -> 0 | Q37: =$I$9*V37*W37/SUMPRODUCT($W$25:$W$55,$V$25:$V$55) -> 0 | R37: =IF($I$12="","",Q37/$I$12) -> 0 | S37: =IF(W37<>"",IF(D37<>"",D37,($I$8-SUM($S$25:S36))*V37*W37/SUMPRODUCT($W37:$W$55,$V37:$V$55)),"") | T37: =IF(W37<>"",IF(E37<>"",E37,($I$9-SUM($T$25:T36))*V37*W37/SUMPRODUCT($W37:$W$55,$V37:$V$55)),"") | U37: =IF(W37<>"",IF($I$12<>"",IF(G37<>"",G37,($I$9/$I$12-SUM($U$25:U36))*V37*W37/SUMPRODUCT($W37:$W$55,$V37:$V$55)),""),"")
F38: =IF(AND(E38<>"",E38<>0),D38/E38,"") | H38: =IF(AND(G38<>"",G38<>0),D38/G38,"") | J38: =IF(AND(G38<>"",G38<>0),E38/G38,"") | N38: =IF(AND(I38<>"",I38<>0),G38/I38,"") | O38: =D38/P38 -> #DIV/0! | P38: =$I$8*V38*W38/SUMPRODUCT($W$25:$W$44,$V$25:$V$44) -> 0 | Q38: =$I$9*V38*W38/SUMPRODUCT($W$25:$W$44,$V$25:$V$44) -> 0 | R38: =IF($I$12="","",Q38/$I$12) -> 0 | S38: =IF(W38<>"",IF(D38<>"",D38,($I$8-SUM($S$25:S37))*V38*W38/SUMPRODUCT($W38:$W$55,$V38:$V$55)),"") | T38: =IF(W38<>"",IF(E38<>"",E38,($I$9-SUM($T$25:T37))*V38*W38/SUMPRODUCT($W38:$W$55,$V38:$V$55)),"") | U38: =IF(W38<>"",IF($I$12<>"",IF(G38<>"",G38,($I$9/$I$12-SUM($U$25:U37))*V38*W38/SUMPRODUCT($W38:$W$55,$V38:$V$55)),""),"")
F39: =IF(AND(E39<>"",E39<>0),D39/E39,"") | H39: =IF(AND(G39<>"",G39<>0),D39/G39,"") | J39: =IF(AND(G39<>"",G39<>0),E39/G39,"") | N39: =IF(AND(I39<>"",I39<>0),G39/I39,"") | O39: =D39/P39 -> #DIV/0! | P39: =$I$8*V39*W39/SUMPRODUCT($W$25:$W$44,$V$25:$V$44) -> 0 | Q39: =$I$9*V39*W39/SUMPRODUCT($W$25:$W$44,$V$25:$V$44) -> 0 | R39: =IF($I$12="","",Q39/$I$12) -> 0 | S39: =IF(W39<>"",IF(D39<>"",D39,($I$8-SUM($S$25:S38))*V39*W39/SUMPRODUCT($W39:$W$55,$V39:$V$55)),"") | T39: =IF(W39<>"",IF(E39<>"",E39,($I$9-SUM($T$25:T38))*V39*W39/SUMPRODUCT($W39:$W$55,$V39:$V$55)),"") | U39: =IF(W39<>"",IF($I$12<>"",IF(G39<>"",G39,($I$9/$I$12-SUM($U$25:U38))*V39*W39/SUMPRODUCT($W39:$W$55,$V39:$V$55)),""),"")
F40: =IF(AND(E40<>"",E40<>0),D40/E40,"") | H40: =IF(AND(G40<>"",G40<>0),D40/G40,"") | J40: =IF(AND(G40<>"",G40<>0),E40/G40,"") | N40: =IF(AND(I40<>"",I40<>0),G40/I40,"") | O40: =D40/P40 -> #DIV/0! | P40: =$I$8*V40*W40/SUMPRODUCT($W$25:$W$47,$V$25:$V$47) -> 0 | Q40: =$I$9*V40*W40/SUMPRODUCT($W$25:$W$47,$V$25:$V$47) -> 0 | R40: =IF($I$12="", "", Q40/$I$12) -> 0 | S40: =IF(W40<>"",IF(D40<>"",D40,($I$8-SUM($S$25:S39))*V40*W40/SUMPRODUCT($W40:$W$55,$V40:$V$55)),"") | T40: =IF(W40<>"",IF(E40<>"",E40,($I$9-SUM($T$25:T39))*V40*W40/SUMPRODUCT($W40:$W$55,$V40:$V$55)),"") | U40: =IF(W40<>"",IF($I$12<>"",IF(G40<>"",G40,($I$9/$I$12-SUM($U$25:U39))*V40*W40/SUMPRODUCT($W40:$W$55,$V40:$V$55)),""),"")
F41: =IF(AND(E41<>"",E41<>0),D41/E41,"") | H41: =IF(AND(G41<>"",G41<>0),D41/G41,"") | J41: =IF(AND(G41<>"",G41<>0),E41/G41,"") | N41: =IF(AND(I41<>"",I41<>0),G41/I41,"") | O41: =D41/P41 -> #DIV/0! | P41: =$I$8*V41*W41/SUMPRODUCT($W$25:$W$47,$V$25:$V$47) -> 0 | Q41: =$I$9*V41*W41/SUMPRODUCT($W$25:$W$47,$V$25:$V$47) -> 0 | R41: =IF($I$12="", "", Q41/$I$12) -> 0 | S41: =IF(W41<>"",IF(D41<>"",D41,($I$8-SUM($S$25:S40))*V41*W41/SUMPRODUCT($W41:$W$55,$V41:$V$55)),"") | T41: =IF(W41<>"",IF(E41<>"",E41,($I$9-SUM($T$25:T40))*V41*W41/SUMPRODUCT($W41:$W$55,$V41:$V$55)),"") | U41: =IF(W41<>"",IF($I$12<>"",IF(G41<>"",G41,($I$9/$I$12-SUM($U$25:U40))*V41*W41/SUMPRODUCT($W41:$W$55,$V41:$V$55)),""),"")
F42: =IF(AND(E42<>"",E42<>0),D42/E42,"") | H42: =IF(AND(G42<>"",G42<>0),D42/G42,"") | J42: =IF(AND(G42<>"",G42<>0),E42/G42,"") | N42: =IF(AND(I42<>"",I42<>0),G42/I42,"") | O42: =D42/P42 -> #DIV/0! | P42: =$I$8*V42*W42/SUMPRODUCT($W$25:$W$47,$V$25:$V$47) -> 0 | Q42: =$I$9*V42*W42/SUMPRODUCT($W$25:$W$47,$V$25:$V$47) -> 0 | R42: =IF($I$12="", "", Q42/$I$12) -> 0 | S42: =IF(W42<>"",IF(D42<>"",D42,($I$8-SUM($S$25:S41))*V42*W42/SUMPRODUCT($W42:$W$55,$V42:$V$55)),"") | T42: =IF(W42<>"",IF(E42<>"",E42,($I$9-SUM($T$25:T41))*V42*W42/SUMPRODUCT($W42:$W$55,$V42:$V$55)),"") | U42: =IF(W42<>"",IF($I$12<>"",IF(G42<>"",G42,($I$9/$I$12-SUM($U$25:U41))*V42*W42/SUMPRODUCT($W42:$W$55,$V42:$V$55)),""),"")
F43: =IF(AND(E43<>"",E43<>0),D43/E43,"") | H43: =IF(AND(G43<>"",G43<>0),D43/G43,"") | J43: =IF(AND(G43<>"",G43<>0),E43/G43,"") | N43: =IF(AND(I43<>"",I43<>0),G43/I43,"") | O43: =D43/P43 -> #DIV/0! | P43: =$I$8*V43*W43/SUMPRODUCT($W$25:$W$44, $V$25:$V$44) -> 0 | Q43: =$I$9*V43*W43/SUMPRODUCT($W$25:$W$44, $V$25:$V$44) -> 0 | R43: =IF($I$12="", "", Q43/$I$12) -> 0 | S43: =IF(W43<>"",IF(D43<>"",D43,($I$8-SUM($S$25:S42))*V43*W43/SUMPRODUCT($W43:$W$55,$V43:$V$55)),"") | T43: =IF(W43<>"",IF(E43<>"",E43,($I$9-SUM($T$25:T42))*V43*W43/SUMPRODUCT($W43:$W$55,$V43:$V$55)),"") | U43: =IF(W43<>"",IF($I$12<>"",IF(G43<>"",G43,($I$9/$I$12-SUM($U$25:U42))*V43*W43/SUMPRODUCT($W43:$W$55,$V43:$V$55)),""),"")
F44: =IF(AND(E44<>"",E44<>0),D44/E44,"") | H44: =IF(AND(G44<>"",G44<>0),D44/G44,"") | J44: =IF(AND(G44<>"",G44<>0),E44/G44,"") | N44: =IF(AND(I44<>"",I44<>0),G44/I44,"") | O44: =D44/P44 -> #DIV/0! | P44: =$I$8*V44*W44/SUMPRODUCT($W$25:$W$44, $V$25:$V$44) -> 0 | Q44: =$I$9*V44*W44/SUMPRODUCT($W$25:$W$44, $V$25:$V$44) -> 0 | R44: =IF($I$12="", "", Q44/$I$12) -> 0 | S44: =IF(W44<>"",IF(D44<>"",D44,($I$8-SUM($S$25:S43))*V44*W44/SUMPRODUCT($W44:$W$55,$V44:$V$55)),"") | T44: =IF(W44<>"",IF(E44<>"",E44,($I$9-SUM($T$25:T43))*V44*W44/SUMPRODUCT($W44:$W$55,$V44:$V$55)),"") | U44: =IF(W44<>"",IF($I$12<>"",IF(G44<>"",G44,($I$9/$I$12-SUM($U$25:U43))*V44*W44/SUMPRODUCT($W44:$W$55,$V44:$V$55)),""),"")
F45: =IF(AND(E45<>"",E45<>0),D45/E45,"") | H45: =IF(AND(G45<>"",G45<>0),D45/G45,"") | J45: =IF(AND(G45<>"",G45<>0),E45/G45,"") | N45: =IF(AND(I45<>"",I45<>0),G45/I45,"") | O45: =D45/P45 -> #DIV/0! | P45: =$I$8*V45*W45/SUMPRODUCT($W$25:$W$44, $V$25:$V$44) -> 0 | Q45: =$I$9*V45*W45/SUMPRODUCT($W$25:$W$44, $V$25:$V$44) -> 0 | R45: =IF($I$12="", "", Q45/$I$12) -> 0 | S45: =IF(W45<>"",IF(D45<>"",D45,($I$8-SUM($S$25:S44))*V45*W45/SUMPRODUCT($W45:$W$55,$V45:$V$55)),"") | T45: =IF(W45<>"",IF(E45<>"",E45,($I$9-SUM($T$25:T44))*V45*W45/SUMPRODUCT($W45:$W$55,$V45:$V$55)),"") | U45: =IF(W45<>"",IF($I$12<>"",IF(G45<>"",G45,($I$9/$I$12-SUM($U$25:U44))*V45*W45/SUMPRODUCT($W45:$W$55,$V45:$V$55)),""),"")
F46: =IF(AND(E46<>"",E46<>0),D46/E46,"") | H46: =IF(AND(G46<>"",G46<>0),D46/G46,"") | J46: =IF(AND(G46<>"",G46<>0),E46/G46,"") | N46: =IF(AND(I46<>"",I46<>0),G46/I46,"") | O46: =D46/P46 -> #DIV/0! | P46: =$I$8*V46*W46/SUMPRODUCT($W$25:$W$44, $V$25:$V$44) -> 0 | Q46: =$I$9*V46*W46/SUMPRODUCT($W$25:$W$44, $V$25:$V$44) -> 0 | R46: =IF($I$12="", "", Q46/$I$12) -> 0 | S46: =IF(W46<>"",IF(D46<>"",D46,($I$8-SUM($S$25:S45))*V46*W46/SUMPRODUCT($W46:$W$55,$V46:$V$55)),"") | T46: =IF(W46<>"",IF(E46<>"",E46,($I$9-SUM($T$25:T45))*V46*W46/SUMPRODUCT($W46:$W$55,$V46:$V$55)),"") | U46: =IF(W46<>"",IF($I$12<>"",IF(G46<>"",G46,($I$9/$I$12-SUM($U$25:U45))*V46*W46/SUMPRODUCT($W46:$W$55,$V46:$V$55)),""),"")
F47: =IF(AND(E47<>"",E47<>0),D47/E47,"") | H47: =IF(AND(G47<>"",G47<>0),D47/G47,"") | J47: =IF(AND(G47<>"",G47<>0),E47/G47,"") | N47: =IF(AND(I47<>"",I47<>0),G47/I47,"") | O47: =D47/P47 -> #DIV/0! | P47: =$I$8*V47*W47/SUMPRODUCT($W$25:$W$55,$V$25:$V$55) -> 0 | Q47: =$I$9*V47*W47/SUMPRODUCT($W$25:$W$55,$V$25:$V$55) -> 0 | R47: =IF($I$12="","",Q47/$I$12) -> 0 | S47: =IF(W47<>"",IF(D47<>"",D47,($I$8-SUM($S$25:S46))*V47*W47/SUMPRODUCT($W47:$W$55,$V47:$V$55)),"") | T47: =IF(W47<>"",IF(E47<>"",E47,($I$9-SUM($T$25:T46))*V47*W47/SUMPRODUCT($W47:$W$55,$V47:$V$55)),"") | U47: =IF(W47<>"",IF($I$12<>"",IF(G47<>"",G47,($I$9/$I$12-SUM($U$25:U46))*V47*W47/SUMPRODUCT($W47:$W$55,$V47:$V$55)),""),"")
B48: итого | D48: =SUM(D25:D47) -> 0 | E48: =SUM(E25:E47) -> 0 | F48: =IF(AND(E48<>"",E48<>0),D48/E48,"") | G48: =SUM(G25:G47) -> 0 | H48: =IF(AND(G48<>"",G48<>0),D48/G48,"") | I48: =SUM(I25:I47) -> 0 | J48: =IF(AND(G48<>"",G48<>0),E48/G48,"") | K48: =SUM(K25:K47) -> 0 | L48: =SUM(L25:L47) -> 0 | M48: =SUM(M25:M47) -> 0 | N48: =IF(AND(I48<>"",I48<>0),G48/I48,"") | O48: =D48/P48 -> #DIV/0! | P48: =SUM(P25:P47) -> 0 | Q48: =SUM(Q25:Q47) -> 0 | R48: =SUM(R25:R47) -> 0 | S48: =SUM(S25:S47) -> #REF! | T48: =SUM(T25:T47) -> #REF! | U48: =SUM(U25:U47) -> #REF!
D49: =SUMIF(D25:D47,"",P25:P47)+D48 -> 0

Sheet Вед-ть Рогалевич
A1: =График!B1 -> Август, 2025
A2: =График!B3 -> ул. Набережная Ленина, 18 | D2: =График!B4 -> GL-0005
A3: Сотрудник | D3: Выплачено на карту | E3: Выплачено наличными по платежной ведомости | F3: Дополнительные начисления, доплаты | G3: Оклад | H3: Бонусная часть от личных продаж | I3: Бонусная часть от общих продаж | J3: Базовый бонус за выполнение плана | K3: Итого: | L3: Вычеты | M3: Итого к выдаче с учетом авансов и вычетов | N3: Подпись
A4: =График!B29 -> Рогалевич Ирина | D4: =19140*2 -> 38280 | F4: =H8+H9 -> 42814.54 | G4: =D11 -> 26500 | H4: =D18 -> 97276.782 | I4: =L18 -> 28611.552 | J4: =L11 -> 0 | K4: =H4+J4+G4+F4+I4 -> 195202.87 | L4: =C8+C9 -> 7994 | M4: =K4-L4-D4-E4 -> 148928.87
B6: Вычеты | G6: Доп начисления
B7: Дата | C7: Сумма | D7: Описание | G7: Дата | H7: Сумма | J7: Описание
B8: 45900 | C8: =2860*2 -> 5720 | D8: НДФЛ август 2025 | G8: 45900 | H8: ='Ялта, Ленина, 18'!J8*0.01 -> 38814.54 | J8: Административный %
B9: 45900 | C9: 2274 | D9: Вычет согласно инвентаризационной ведомости | G9: 45900 | H9: 4000 | J9: Конкурс август 2025 (Акционные позиции)
A11: Оклад: | D11: =G15+G16 -> 26500 | I11: Базовый бонус за выполнение плана | L11: =L15+L16 -> 0
B13: Оклад: | J13: Базовый бонус за выполнение плана
B14: Дней | C14: Магазин | D14: Должность | E14: Зачислено часов | F14: Ставка за час, руб | G14: Начислено за день, руб | J14: Магазин | K14: КВП | L14: Начисленный ББ
B15: =График!AI29 -> 26 | C15: =A2 -> ул. Набережная Ленина, 18 | D15: ПК | E15: =График!AJ29 -> 265 | F15: 100 | G15: =E15*F15 -> 26500 | J15: =График!B3 -> ул. Набережная Ленина, 18 | K15: ='Ялта, Ленина, 18'!K8 -> 0.82581316
D16: ПК | G16: =E16*F16 -> 0
A18: БонуснаяЧасть | D18: =G23+G24 -> 97276.782 | I18: Бонусная часть от общих продаж | L18: =N23 -> 28611.552
B21: Бонус от личных продаж по категории товара | I21: Бонус от общих продаж
B22: Сотрудник | C22: Магазин | E22: Процент от продажи | F22: Продано на сумму, руб | G22: Начисленный бонус от продаж, руб | I22: Сотрудник | J22: Магазин | K22: Кол-во отработанных личных часов | L22: Кол-во отработанных общих часов | M22: Процент от продажи | N22: Начисленный бонус от продаж, руб
B23: =A4 -> Рогалевич Ирина | C23: =A2 -> ул. Набережная Ленина, 18 | E23: 0.06 | F23: ='Рогалевич И. Е. '!J8 -> 1621279.7 | G23: =F23*E23 -> 97276.782 | I23: =B23 -> Рогалевич Ирина | J23: =C23 -> ул. Набережная Ленина, 18 | K23: =E15 -> 265 | L23: =График!AJ31 -> 719 | M23: 0.02 | N23: ='Ялта, Ленина, 18'!J8*M23*K23/L23 -> 28611.552
B24: =B23 -> Рогалевич Ирина | C24: =C16 -> 0 | G24: =F24*E24 -> 0 | N24: =1477363.14*M24*K24/L24 -> #DIV/0!

Sheet Вед-ть Яковенко
A1: =График!B1 -> Август, 2025
A2: =График!B3 -> ул. Набережная Ленина, 18 | D2: =График!B4 -> GL-0005
A3: Сотрудник | D3: Выплачено на карту | E3: Выплачено наличными по платежной ведомости | F3: Дополнительные начисления, доплаты | G3: Оклад | H3: Бонусная часть от личных продаж | I3: Бонусная часть от общих продаж | J3: Базовый бонус за выполнение плана | K3: Итого: | L3: Вычеты | M3: Итого к выдаче с учетом авансов и вычетов | N3: Подпись
A4: =График!B27 -> Яковенко Алина | D4: =17400+23326.85 -> 40726.85 | F4: =H8+H9 -> 9811.85 | G4: =D13 -> 23100 | H4: =D20 -> 78328.32 | I4: =L20 -> 24940.636 | J4: =L13 -> 0 | K4: =F4+G4+H4+I4+J4 -> 136180.81 | L4: =C8+C9+C11+C10 -> 15454 | M4: =K4-L4-D4-E4 -> 79999.956
B6: Вычеты | G6: Доп начисления
B7: Дата | C7: Сумма | D7: Описание | G7: Дата | H7: Сумма | J7: Описание
B8: 45898 | C8: =2600+2600+885 -> 6085 | D8: НДФЛ август 2025 | G8: 45898 | H8: 6811.85 | J8: Компенсация отпуска при увольнении
B9: 45898 | C9: 2085 | D9: Форма лето 2025 | G9: 45902 | H9: 3000 | J9: Конкурс август 2025 (Длина чека)
B10: 45898 | C10: 5100 | D10: Вычет стажировочные часы (51 час)
B11: 45898 | C11: 2184 | D11: Вычет согласно инвентаризационной ведомости
A13: Оклад: | D13: =G17 -> 23100 | I13: Базовый бонус за выполнение плана | L13: =L17+L18 -> 0
B15: Оклад: | J15: Базовый бонус за выполнение плана
B16: Дней | C16: Магазин | D16: Должность | E16: Зачислено часов | F16: Ставка за час, руб | G16: Начислено за день, руб | J16: Магазин | K16: КВП | L16: Начисленный ББ
B17: =График!AI27 -> 21 | C17: =A2 -> ул. Набережная Ленина, 18 | D17: ПК | E17: =График!AJ27 -> 231 | F17: 100 | G17: =E17*F17 -> 23100 | J17: =График!B3 -> ул. Набережная Ленина, 18 | K17: ='Ялта, Ленина, 18'!K8 -> 0.82581316 | L17: 0
A20: БонуснаяЧасть | D20: =G25 -> 78328.32 | I20: Бонусная часть от общих продаж | L20: =N25 -> 24940.636
B23: Бонус от личных продаж по категории товара | I23: Бонус от общих продаж
B24: Сотрудник | C24: Магазин | E24: Процент от продажи | F24: Продано на сумму, руб | G24: Начисленный бонус от продаж, руб | I24: Сотрудник | J24: Магазин | K24: Кол-во отработанных личных часов | L24: Кол-во отработанных общих часов | M24: Процент от продажи | N24: Начисленный бонус от продаж, руб
B25: =A4 -> Яковенко Алина | C25: =A2 -> ул. Набережная Ленина, 18 | E25: 0.06 | F25: ='Яковенко А. К. '!J8 -> 1305472 | G25: =F25*E25 -> 78328.32 | I25: =B25 -> Яковенко Алина | J25: =C25 -> ул. Набережная Ленина, 18 | K25: =E17 -> 231 | L25: =График!AJ31 -> 719 | M25: 0.02 | N25: ='Ялта, Ленина, 18'!J8*M25*K25/L25 -> 24940.636
B26: =B25 -> Яковенко Алина

Sheet Вед-ть Уразгильдеева
A1: =График!B1 -> Август, 2025
A2: =График!B3 -> ул. Набережная Ленина, 18 | D2: =График!B4 -> GL-0005
A3: Сотрудник | D3: Выплачено на карту | E3: Выплачено наличными по платежной ведомости | F3: Дополнительные начисления, доплаты | G3: Оклад | H3: Бонусная часть от личных продаж | I3: Бонусная часть от общих продаж | J3: Базовый бонус за выполнение плана | K3: Итого: | L3: Вычеты | M3: Итого к выдаче с учетом авансов и вычетов | N3: Подпись
A4: =График!B28 -> Уразгильдеева Екатерина | D4: =17400*2 -> 34800 | F4: =H8+H9 -> 0 | G4: =D12 -> 22300 | H4: =D19 -> 57282.138 | I4: =L19 -> 24076.891 | J4: =L12 -> 0 | K4: =H4+J4+G4+F4+I4 -> 103659.03 | L4: =C8+C9+C10 -> 7744 | M4: =K4-L4-D4-E4 -> 61115.029 | S4: пб
B6: Вычеты | G6: Доп начисления
B7: Дата | C7: Сумма | D7: Описание | G7: Дата | H7: Сумма | J7: Описание
B8: 45900 | C8: =2600*2 -> 5200 | D8: НДфЛ август 2025
B9: 45900 | C9: 2544 | D9: Вычет согласно инвентаризационной ведомости
A12: Оклад: | D12: =G16 -> 22300 | I12: Базовый бонус за выполнение плана | L12: =L16+L17 -> 0
B14: Оклад: | J14: Базовый бонус за выполнение плана
B15: Дней | C15: Магазин | D15: Должность | E15: Зачислено часов | F15: Ставка за час, руб | G15: Начислено за день, руб | J15: Магазин | K15: КВП | L15: Начисленный ББ
B16: =График!AI28 -> 18 | C16: =A2 -> ул. Набережная Ленина, 18 | D16: ПК | E16: =График!AJ28 -> 223 | F16: 100 | G16: =E16*F16 -> 22300 | J16: =График!B3 -> ул. Набережная Ленина, 18 | K16: ='Ялта, Ленина, 18'!K8 -> 0.82581316 | L16: 0
A19: БонуснаяЧасть | D19: =G24 -> 57282.138 | I19: Бонусная часть от общих продаж | L19: =N24 -> 24076.891
B22: Бонус от личных продаж по категории товара | I22: Бонус от общих продаж
B23: Сотрудник | C23: Магазин | E23: Процент от продажи | F23: Продано на сумму, руб | G23: Начисленный бонус от продаж, руб | I23: Сотрудник | J23: Магазин | K23: Кол-во отработанных личных часов | L23: Кол-во отработанных общих часов | M23: Процент от продажи | N23: Начисленный бонус от продаж, руб
B24: =A4 -> Уразгильдеева Екатерина | C24: =A2 -> ул. Набережная Ленина, 18 | E24: 0.06 | F24: ='Уразгильдеева Е. Р. '!J8 -> 954702.3 | G24: =F24*E24 -> 57282.138 | I24: =B24 -> Уразгильдеева Екатерина | J24: =C24 -> ул. Набережная Ленина, 18 | K24: =E16 -> 223 | L24: =График!AJ31 -> 719 | M24: 0.02 | N24: ='Ялта, Ленина, 18'!J8*M24*K24/L24 -> 24076.891
B25: =B24 -> Уразгильдеева Екатерина | N25: =1477363.14*M25*K25/L25 -> #DIV/0!

Sheet График
B1: Август, 2025 | T1: в
B2: г. Ялта
B3: ул. Набережная Ленина, 18
B4: GL-0005
B5: 10.00-23.00
B6: ФОТ | C6: Кол-во дней в месяц | AK6: 31
B7: =BT31*100/BH31 -> #DIV/0!
D8: пт | E8: сб | F8: вс | G8: пн | H8: вт | I8: ср | J8: чт | K8: пт | L8: сб | M8: вс | N8: пн | O8: вт | P8: ср | Q8: чт | R8: пт | S8: сб | T8: вс | U8: пн | V8: вт | W8: ср | X8: чт | Y8: пт | Z8: сб | AA8: вс | AB8: пн | AC8: вт | AD8: ср | AE8: чт | AF8: пт | AG8: сб | AH8: вс | AJ8: Часы | AK8: Выходные | AL8: Отпуск | AM8: Больничный (официальный) | AN8: Дни стажировки
A10: № | B10: ФИО | C10: Должность | D10: 1 | E10: 2 | F10: 3 | G10: 4 | H10: 5 | I10: 6 | J10: 7 | K10: 8 | L10: 9 | M10: 10 | N10: 11 | O10: 12 | P10: 13 | Q10: 14 | R10: 15 | S10: 16 | T10: 17 | U10: 18 | V10: 19 | W10: 20 | X10: 21 | Y10: 22 | Z10: 23 | AA10: 24 | AB10: 25 | AC10: 26 | AD10: 27 | AE10: 28 | AF10: 29 | AG10: 30 | AH10: 31 | AI10: Дни
A11: 20 | AI11: 0 | AJ11: 0 | AK11: 0 | AL11: 0 | AM11: 0 | AN11: 0
A12: 19 | AI12: 0 | AJ12: 0 | AK12: 0 | AL12: 0 | AM12: 0 | AN12: 0
A13: 18 | AI13: 0 | AJ13: 0 | AK13: 0 | AL13: 0 | AM13: 0 | AN13: 0
A14: 17 | AI14: 0 | AJ14: 0 | AK14: 0 | AL14: 0 | AM14: 0 | AN14: 0
A15: 16 | AI15: 0 | AJ15: 0 | AK15: 0 | AL15: 0 | AM15: 0 | AN15: 0
A16: 15 | AI16: 0 | AJ16: 0 | AK16: 0 | AL16: 0 | AM16: 0 | AN16: 0
A17: 14 | AI17: 0 | AJ17: 0 | AK17: 0 | AL17: 0 | AM17: 0 | AN17: 0
A18: 13 | AI18: 0 | AJ18: 0 | AK18: 0 | AL18: 0 | AM18: 0 | AN18: 0
A19: 12 | AI19: 0 | AJ19: 0 | AK19: 0 | AL19: 0 | AM19: 0 | AN19: 0
A20: 11 | AI20: 0 | AJ20: 0 | AK20: 0 | AL20: 0 | AM20: 0 | AN20: 0
A21: 10 | AI21: 0 | AJ21: 0 | AK21: 0 | AL21: 0 | AM21: 0 | AN21: 0
A22: 9 | AI22: =COUNTIF(D22:AH22, ">0") -> 0 | AJ22: 0 | AK22: 0 | AL22: 0 | AM22: 0 | AN22: 0
A23: 8 | AI23: =COUNTIF(D23:AH23, ">0") -> 0 | AJ23: 0 | AK23: 0 | AL23: 0 | AM23: 0 | AN23: 0
A24: 7 | AI24: =COUNTIF(D24:AH24, ">0") -> 0 | AJ24: 0 | AK24: 0 | AL24: 0 | AM24: 0 | AN24: 0
A25: 6 | AI25: =COUNTIF(D25:AH25,">0") -> 0 | AJ25: =SUMIF(D25:AH25,">0") -> 0 | AK25: =COUNTIF(D25:AH25,"В") -> 0 | AL25: =COUNTIF(E25:AI25,"о") -> 0 | AM25: =COUNTIF(F25:AJ25,"б") -> 0 | AN25: 0
A26: 5 | AI26: =COUNTIF(D26:AH26, ">0") -> 0 | AJ26: =SUMIF(D26:AH26,">0") -> 0 | AK26: =COUNTIF(D26:AH26, "В") -> 0 | AL26: 0 | AM26: 0 | AN26: 0
A27: 4 | B27: Яковенко Алина | C27: ПК | D27: 11 | E27: в | F27: 9 | G27: 13 | H27: 10 | I27: в | J27: 10 | K27: 13 | L27: 11 | M27: в | N27: 9 | O27: 13 | P27: 2 | Q27: 13 | R27: 13 | S27: 10 | T27: в | U27: 13 | V27: 13 | W27: в | X27: 11 | Y27: 13 | Z27: в | AA27: в | AB27: 10 | AC27: 13 | AD27: 10 | AE27: в | AF27: 11 | AG27: у | AH27: у | AI27: =COUNTIF(D27:AH27,">0") -> 21 | AJ27: =SUMIF(D27:AH27,">0") -> 231 | AK27: =COUNTIF(D27:AH27,"В") -> 8 | AL27: =COUNTIF(E27:AI27,"о") -> 0 | AM27: =COUNTIF(F27:AJ27,"б") -> 0 | AN27: 0
A28: 3 | B28: Уразгильдеева Екатерина | C28: ПК | D28: 13 | E28: 13 | F28: в | G28: в | H28: 13 | I28: 13 | J28: в | K28: в | L28: 12 | M28: 13 | N28: в | O28: в | P28: 10 | Q28: 10 | R28: в | S28: 12 | T28: 13 | U28: в | V28: в | W28: 13 | X28: 13 | Y28: в | Z28: 13 | AA28: 13 | AB28: в | AC28: в | AD28: 13 | AE28: 13 | AF28: в | AG28: 13 | AH28: 10 | AI28: =COUNTIF(D28:AH28,">0") -> 18 | AJ28: =SUMIF(D28:AH28,">0") -> 223 | AK28: =COUNTIF(D28:AH28,"В") -> 13 | AL28: =COUNTIF(E28:AI28,"о") -> 0 | AM28: =COUNTIF(F28:AJ28,"б") -> 0 | AN28: 0
A29: 2 | B29: Рогалевич Ирина | C29: УМ | D29: в | E29: 9 | F29: 13 | G29: 9 | H29: в | I29: 9 | J29: 13 | K29: 9 | L29: 8 | M29: 9 | N29: 13 | O29: 9 | P29: 11 | Q29: в | R29: 9 | S29: 9 | T29: 9 | U29: 9 | V29: 10 | W29: 9 | X29: в | Y29: 11 | Z29: 10 | AA29: 9 | AB29: 13 | AC29: 10 | AD29: в | AE29: 10 | AF29: 13 | AG29: 9 | AH29: 13 | AI29: =COUNTIF(D29:AH29,">0") -> 26 | AJ29: =SUMIF(D29:AH29,">0") -> 265 | AK29: =COUNTIF(D29:AH29,"В") -> 5 | AL29: =COUNTIF(E29:AI29,"о") -> 0 | AM29: =COUNTIF(F29:AJ29,"б") -> 0 | AN29: 0
A30: 1 | AI30: =COUNTIF(D30:AH30, ">0") -> 0 | AJ30: =SUMIF(D30:AH30,">0") -> 0 | AK30: =COUNTIF(D30:AH30, "В") -> 0 | AL30: =COUNTIF(E30:AI30, "о") -> 0 | AM30: =COUNTIF(F30:AJ30, "б") -> 0 | AN30: 0
B31: Итого магазин | D31: =COUNTIF(D11:D30, ">0") -> 2 | E31: =COUNTIF(E11:E30, ">0") -> 2 | F31: =COUNTIF(F11:F30, ">0") -> 2 | G31: =COUNTIF(G11:G30, ">0") -> 2 | H31: =COUNTIF(H11:H30, ">0") -> 2 | I31: =COUNTIF(I11:I30, ">0") -> 2 | J31: =COUNTIF(J11:J30, ">0") -> 2 | K31: =COUNTIF(K11:K29, ">0") -> 2 | L31: =COUNTIF(L11:L30, ">0") -> 3 | M31: =COUNTIF(M11:M30, ">0") -> 2 | N31: =COUNTIF(N11:N30, ">0") -> 2 | O31: =COUNTIF(O11:O30, ">0") -> 2 | P31: =COUNTIF(P11:P30, ">0") -> 3 | Q31: =COUNTIF(Q11:Q30, ">0") -> 2 | R31: =COUNTIF(R11:R30, ">0") -> 2 | S31: =COUNTIF(S11:S30, ">0") -> 3 | ... AH31: =COUNTIF(AH11:AH30, ">0") -> 2 | AI31: =SUM(AI11:AI30) -> 65 | AJ31: =SUM(AJ11:AJ30) -> 719 | AK31: =SUM(AK11:AK30) -> 26 | AL31: =SUM(AL11:AL30) -> 0 | AM31: =SUM(AM11:AM30) -> 0 | AN31: =SUM(AN11:AN30) -> 0
B33: График рандомный для приблизительного прогноза по продажам.
