Workbook
Name маг: NA()

Sheet Ялта, Ленина, 18
B1: =TODAY()-1 -> 46080
B2: (отчетная дата)
C3: Осталось до выполнения плана!!! | I3: =График!B3 -> ул. Набережная Ленина, 18
C4: =I8-D56 -> 287680.6 | E4: =IF(I8<>0, C4/I8, 0) -> 0.26224551
F6: Целевые показатели
F7: Показатель | I7: План | J7: Факт | K7: % выполнения | L7: Прогноз выполнения | M7: % выполнения по прогнозу | N7: Отклонение | O7: Факт аналогичного месяца прошлого года | P7: Отклонение LFL
F8: Выручка | I8: =I10*I13 -> 1096989.6 | J8: =D56 -> 809309 | K8: =IF(AND(I8<>"", I8<>0, J8<>""), J8/I8, "") -> 0.73775449 | L8: =IF(SUMIF($D$25:$D$55,">=0",$P$25:$P$55)<>0,I8*D56/SUMIF($D$25:$D$55,">=0",$P$25:$P$55),0) -> 888582.94 | M8: =IF(AND(I8<>"", I8<>0, L8<>"", L8<>0), L8/I8, "") -> 0.81001948 | N8: =IF(AND(J8<>0, J8<>"", I8<>0, I8<>""), L8-I8, "") -> -208406.66 | P8: =IF(AND(O8<>"", O8<>0, L8<>"", L8<>0), -O8+L8, "") | Q8: =IF(AND(P8<>"", P8<>0, O8<>0, O8<>""), P8/O8, "")
F9: Кол-во изделий | I9: =I8/I11 -> 285.6 | J9: =E56 -> 192 | K9: =IF(AND(I9<>"", I9<>0, J9<>""), J9/I9, "") -> 0.67226891 | L9: =IF(SUMIF($E$25:$E$55, ">=0", $Q$25:$Q$55)<>0, I9*E56/SUMIF($E$25:$E$55, ">=0", $Q$25:$Q$55), 0) -> 192 | M9: =IF(AND(I9<>"", I9<>0, L9<>"", L9<>0), L9/I9, "") -> 0.67226891 | N9: =IF(AND(J9<>0, J9<>"", I9<>0, I9<>""), L9-I9, "") -> -93.6 | O9: =O8/O11 -> #DIV/0! | P9: =IF(AND(O9<>"", O9<>0, L9<>"", L9<>0), -O9+L9, "") -> #DIV/0! | Q9: =IF(AND(P9<>"", P9<>0, O9<>0, O9<>""), P9/O9, "") -> #DIV/0!
F10: Средний чек | I10: =I11*I12 -> 7682 | J10: =H56 -> 7781.8173 | K10: =IF(AND(I10<>"", I10<>0, J10<>""), J10/I10, "") -> 1.0129937 | L10: =J10 -> 7781.8173 | M10: =IF(AND(I10<>"", I10<>0, L10<>"", L10<>0), L10/I10, "") -> 1.0129937 | N10: =IF(AND(J10<>0, J10<>"", I10<>0, I10<>""), L10-I10, "") -> 99.817308 | O10: =O11*O12 -> 0 | P10: =IF(AND(O10<>"", O10<>0, L10<>"", L10<>0), -O10+L10, "") | Q10: =IF(AND(P10<>"", P10<>0, O10<>0, O10<>""), P10/O10, "")
F11: Средняя стоимость изделия | I11: 3841 | J11: =F56 -> 4215.151 | K11: =IF(AND(I11<>"", I11<>0, J11<>""), J11/I11, "") -> 1.0974098 | L11: =IF(L9>0, L8/L9, "") -> 4628.0362 | M11: =IF(AND(I11<>"", I11<>0, L11<>"", L11<>0), L11/I11, "") -> 1.204904 | N11: =IF(AND(J11<>0, J11<>"", I11<>0, I11<>""), L11-I11, "") -> 787.03617 | P11: =IF(AND(O11<>"", O11<>0, L11<>"", L11<>0), -O11+L11, "") | Q11: =IF(AND(P11<>"", P11<>0, O11<>0, O11<>""), P11/O11, "")
F12: Длина чека | I12: 2 | J12: =J56 -> 1.8461538 | K12: =IF(AND(I12<>"", I12<>0, J12<>""), J12/I12, "") -> 0.92307692 | L12: =J12 -> 1.8461538 | M12: =IF(AND(I12<>"", I12<>0, L12<>"", L12<>0), L12/I12, "") -> 0.92307692 | N12: =IF(AND(J12<>0, J12<>"", I12<>0, I12<>""), L12-I12, "") -> -0.15384615 | P12: =IF(AND(O12<>"", O12<>0, L12<>"", L12<>0), -O12+L12, "") | Q12: =IF(AND(P12<>"", P12<>0, O12<>0, O12<>""), P12/O12, "")
F13: Кол-во чеков | I13: =I17*I20 -> 142.8 | J13: =G56 -> 104 | K13: =IF(AND(I13<>"", I13<>0, J13<>""), J13/I13, "") -> 0.72829132 | L13: =IF(SUMIF($G$25:$G$55, ">=0", $R$25:$R$55)<>0, I13*G56/SUMIF($G$25:$G$55, ">=0", $R$25:$R$55), "") -> 104 | M13: =IF(AND(I13<>"", I13<>0, L13<>"", L13<>0), L13/I13, "") -> 0.72829132 | N13: =IF(AND(J13<>0, J13<>"", I13<>0, I13<>""), L13-I13, "") -> -38.8 | P13: =IF(AND(O13<>"", O13<>0, L13<>"", L13<>0), -O13+L13, "") | Q13: =IF(AND(P13<>"", P13<>0, O13<>0, O13<>""), P13/O13, "")
F14: Кол-во смен | I14: 28 | J14: 28 | K14: =IF(AND(I14<>"", I14<>0, J14<>""), J14/I14, "") -> 1 | L14: =IF(SUMIF($D$25:$D$55,">=0",$P$25:$P$55),I56*I8/SUMIF($D$25:$D$55,">=0",$P$25:$P$55),"") -> 374.40185 | M14: =IF(AND(I14<>"", I14<>0, L14<>"", L14<>0), L14/I14, "") -> 13.371495 | N14: =IF(AND(J14<>0, J14<>"", I14<>0, I14<>""), L14-I14, "") -> 346.40185 | P14: =IF(AND(O14<>"", O14<>0, L14<>"", L14<>0), -O14+L14, "") | Q14: =IF(AND(P14<>"", P14<>0, O14<>0, O14<>""), P14/O14, "")
F15: Средние продажи в смену | I15: =I8/I14 -> 39178.2 | J15: =J8/J14 -> 28903.893 | K15: =IF(AND(I15<>"", I15<>0, J15<>""), J15/I15, "") -> 0.73775449 | L15: =J15 -> 28903.893 | M15: =IF(AND(I15<>"", I15<>0, L15<>"", L15<>0), L15/I15, "") -> 0.73775449 | N15: =IF(AND(J15<>0, J15<>"", I15<>0, I15<>""), L15-I15, "") -> -10274.307 | P15: =IF(AND(O15<>"", O15<>0, L15<>"", L15<>0), -O15+L15, "") | Q15: =IF(AND(P15<>"", P15<>0, O15<>0, O15<>""), P15/O15, "")
F16: Отставание/Перевыполнение | J16: =J8-I15*J14 -> -287680.6 | K16: =IF(AND(I16<>"", I16<>0, J16<>""), J16/I16, "") | L16: =J16 -> -287680.6 | M16: =IF(AND(I16<>"", I16<>0, L16<>"", L16<>0), L16/I16, "") | N16: =IF(AND(J16<>0, J16<>"", I16<>0, I16<>""), L16-I16, "") | P16: =IF(AND(O16<>"", O16<>0, L16<>"", L16<>0), -O16+L16, "") | Q16: =IF(AND(P16<>"", P16<>0, O16<>0, O16<>""), P16/O16, "") | S16: Подарочные сертификаты
F17: Трафик | I17: =17*28 -> 476 | J17: =I56 -> 341 | K17: =IF(AND(I17<>"", I17<>0, J17<>""), J17/I17, "") -> 0.71638655 | L17: =J17/J14*I14 -> 341 | M17: =IF(AND(I17<>"", I17<>0, L17<>"", L17<>0), L17/I17, "") -> 0.71638655 | N17: =IF(AND(J17<>0, J17<>"", I17<>0, I17<>""), L17-I17, "") -> -135 | P17: =IF(AND(O17<>"", O17<>0, L17<>"", L17<>0), -O17+L17, "") | Q17: =IF(AND(P17<>"", P17<>0, O17<>0, O17<>""), P17/O17, "")
K18: =IF(AND(I18<>"", I18<>0, J18<>""), J18/I18, "") | L18: =J18 -> 0 | M18: =IF(AND(I18<>"", I18<>0, L18<>"", L18<>0), L18/I18, "") | N18: =IF(AND(J18<>0, J18<>"", I18<>0, I18<>""), L18-I18, "") | O18: 0 | P18: =IF(AND(O18<>"", O18<>0, L18<>"", L18<>0), -O18+L18, "") | Q18: =IF(AND(P18<>"", P18<>0, O18<>0, O18<>""), P18/O18, "")
J19: =M56 -> 0 | K19: =IF(AND(I19<>"", I19<>0, J19<>""), J19/I19, "") | L19: =J19 -> 0 | M19: =IF(AND(I19<>"", I19<>0, L19<>"", L19<>0), L19/I19, "") | N19: =IF(AND(J19<>0, J19<>"", I19<>0, I19<>""), L19-I19, "") | O19: 0 | P19: =IF(AND(O19<>"", O19<>0, L19<>"", L19<>0), -O19+L19, "") | Q19: =IF(AND(P19<>"", P19<>0, O19<>0, O19<>""), P19/O19, "") | S19: =S18/I16 -> #DIV/0!
F20: Конверсия план/факт | I20: 0.3 | J20: =N56 -> 0.30498534 | K20: =J20/I20 -> 1.0166178 | L20: =IF(AND(K8<>0, I14<>0, I56<>0), (I56*N56+(I56/K8-I56)*I20)/(I56/K8), 0) -> 0.30367795 | M20: =IF(AND(I20<>"", I20<>0, L20<>"", L20<>0), L20/I20, "") -> 1.0122598 | N20: =IF(AND(J20<>0, J20<>"", I20<>0, I20<>""), L20-I20, "") -> 0.0036779549 | P20: =IF(AND(O20<>"", O20<>0, L20<>"", L20<>0), -O20+L20, "") | Q20: =IF(AND(P20<>"", P20<>0, O20<>0, O20<>""), P20/O20, "")
A22: Факт продаж за месяц | O22: % выполнения дневного плана | P22: Раcпределение плана по дням
A23: Сотрудник | B23: Дата | C23: День недели | D23: Выручка (руб) | E23: Кол-во единиц (шт.) | F23: Средняя стоимость изделия (руб.) | G23: Количество чеков (шт.) | H23: Средняя сумма чека (руб.) | I23: Трафик | J23: Длина чека (шт.) | K23: Запасной | L23: Запасной | M23: Запасной | N23: Конверсия (%) | P23: выручка, план | Q23: кол-во ед, план | R23: Кол-во чеков, план | S23: выручка, скорректир.план | T23: кол-во ед, скорр. план | U23: кол-во чеков, скорр. план | V23: Коэфф. Дня Недели | W23: Специфика месяца
B24: 1 | C24: 2 | D24: 3 | E24: 4 | F24: 5 | G24: 6 | H24: 7 | I24: 8 | J24: 9 | K24: 10 | L24: 11 | M24: 12 | N24: 13 | P24: 1 | Q24: 2 | R24: 3 | S24: 4 | T24: 5 | U24: 6 | V24: 10 | W24: 11
A25: Стекольщикова | B25: 45689 | C25: сб | D25: 18650 | E25: 6 | F25: =IF(AND(E25<>"",E25<>0),D25/E25,"") -> 3108.3333 | G25: 4 | H25: =IF(AND(G25<>"",G25<>0),D25/G25,"") -> 4662.5 | I25: 20 | J25: =IF(AND(G25<>"",G25<>0),E25/G25,"") -> 1.5 | N25: =IF(AND(I25<>"",I25<>0),G25/I25,"") -> 0.2 | O25: =D25/P25 -> 0.46497934 | P25: =$I$8*V25*W25/SUMPRODUCT($W$25:$W$55,$V$25:$V$55) -> 40109.309 | Q25: =$I$9*V25*W25/SUMPRODUCT($W$25:$W$55,$V$25:$V$55) -> 10.442413 | R25: =IF($I$12="","",Q25/$I$12) -> 5.2212066 | S25: =IF(D25<>"",D25,P25) -> 18650 | T25: =IF(E25<>"",E25,Q25) -> 6 | U25: =IF(G25<>"",G25,R25) -> 4 | V25: 1 | W25: 1
A26: Стекольщикова | B26: 45690 | C26: вс | D26: 52680 | E26: 15 | F26: =IF(AND(E26<>"",E26<>0),D26/E26,"") -> 3512 | G26: 6 | H26: =IF(AND(G26<>"",G26<>0),D26/G26,"") -> 8780 | I26: 20 | J26: =IF(AND(G26<>"",G26<>0),E26/G26,"") -> 2.5 | N26: =IF(AND(I26<>"",I26<>0),G26/I26,"") -> 0.3 | O26: =D26/P26 -> 1.0854635 | P26: =$I$8*V26*W26/SUMPRODUCT($W$25:$W$55,$V$25:$V$55) -> 48532.264 | Q26: =$I$9*V26*W26/SUMPRODUCT($W$25:$W$55,$V$25:$V$55) -> 12.63532 | R26: =IF($I$12="","",Q26/$I$12) -> 6.31766 | S26: =IF(W26<>"",IF(D26<>"",D26,($I$8-SUM($S$25:S25))*V26*W26/SUMPRODUCT($W26:$W$55,$V26:$V$55)),"") -> 52680 | T26: =IF(W26<>"",IF(E26<>"",E26,($I$9-SUM($T$25:T25))*V26*W26/SUMPRODUCT($W26:$W$55,$V26:$V$55)),"") -> 15 | U26: =IF(W26<>"",IF($I$12<>"",IF(G26<>"",G26,($I$9/$I$12-SUM($U$25:U25))*V26*W26/SUMPRODUCT($W26:$W$55,$V26:$V$55)),""),"") -> 6 | V26: 1.1 | W26: 1.1
A27: Рогалевич | B27: 45691 | C27: пн | D27: 13237 | E27: 4 | F27: =IF(AND(E27<>"",E27<>0),D27/E27,"") -> 3309.25 | G27: 3 | H27: =IF(AND(G27<>"",G27<>0),D27/G27,"") -> 4412.3333 | I27: 8 | J27: =IF(AND(G27<>"",G27<>0),E27/G27,"") -> 1.3333333 | N27: =IF(AND(I27<>"",I27<>0),G27/I27,"") -> 0.375 | O27: =D27/P27 -> 0.51566115 | P27: =$I$8*V27*W27/SUMPRODUCT($W$25:$W$55,$V$25:$V$55) -> 25669.958 | Q27: =$I$9*V27*W27/SUMPRODUCT($W$25:$W$55,$V$25:$V$55) -> 6.6831444 | R27: =IF($I$12="","",Q27/$I$12) -> 3.3415722 | S27: =IF(W27<>"",IF(D27<>"",D27,($I$8-SUM($S$25:S26))*V27*W27/SUMPRODUCT($W27:$W$55,$V27:$V$55)),"") -> 13237 | T27: =IF(W27<>"",IF(E27<>"",E27,($I$9-SUM($T$25:T26))*V27*W27/SUMPRODUCT($W27:$W$55,$V27:$V$55)),"") -> 4 | U27: =IF(W27<>"",IF($I$12<>"",IF(G27<>"",G27,($I$9/$I$12-SUM($U$25:U26))*V27*W27/SUMPRODUCT($W27:$W$55,$V27:$V$55)),""),"") -> 3 | V27: 0.8 | W27: 0.8
A28: Рогалевич | B28: 45692 | C28: вт | D28: =7683+41907 -> 49590 | E28: 11 | F28: =IF(AND(E28<>"",E28<>0),D28/E28,"") -> 4508.1818 | G28: 5 | H28: =IF(AND(G28<>"",G28<>0),D28/G28,"") -> 9918 | I28: 16 | J28: =IF(AND(G28<>"",G28<>0),E28/G28,"") -> 2.2 | N28: =IF(AND(I28<>"",I28<>0),G28/I28,"") -> 0.3125 | O28: =D28/P28 -> 1.9318302 | P28: =$I$8*V28*W28/SUMPRODUCT($W$25:$W$55,$V$25:$V$55) -> 25669.958 | Q28: =$I$9*V28*W28/SUMPRODUCT($W$25:$W$55,$V$25:$V$55) -> 6.6831444 | R28: =IF($I$12="","",Q28/$I$12) -> 3.3415722 | S28: =IF(W28<>"",IF(D28<>"",D28,($I$8-SUM($S$25:S27))*V28*W28/SUMPRODUCT($W28:$W$55,$V28:$V$55)),"") -> 49590 | T28: =IF(W28<>"",IF(E28<>"",E28,($I$9-SUM($T$25:T27))*V28*W28/SUMPRODUCT($W28:$W$55,$V28:$V$55)),"") -> 11 | U28: =IF(W28<>"",IF($I$12<>"",IF(G28<>"",G28,($I$9/$I$12-SUM($U$25:U27))*V28*W28/SUMPRODUCT($W28:$W$55,$V28:$V$55)),""),"") -> 5 | V28: 0.8 | W28: 0.8
A29: Рогалевич | B29: 45693 | C29: ср | D29: 15563 | E29: 3 | F29: =IF(AND(E29<>"",E29<>0),D29/E29,"") -> 5187.6667 | G29: 2 | H29: =IF(AND(G29<>"",G29<>0),D29/G29,"") -> 7781.5 | I29: 9 | J29: =IF(AND(G29<>"",G29<>0),E29/G29,"") -> 1.5 | N29: =IF(AND(I29<>"",I29<>0),G29/I29,"") -> 0.22222222 | O29: =D29/P29 -> 0.47903045 | P29: =$I$8*V29*W29/SUMPRODUCT($W$25:$W$55,$V$25:$V$55) -> 32488.54 | Q29: =$I$9*V29*W29/SUMPRODUCT($W$25:$W$55,$V$25:$V$55) -> 8.4583547 | R29: =IF($I$12="","",Q29/$I$12) -> 4.2291773 | S29: =IF(W29<>"",IF(D29<>"",D29,($I$8-SUM($S$25:S28))*V29*W29/SUMPRODUCT($W29:$W$55,$V29:$V$55)),"") -> 15563 | T29: =IF(W29<>"",IF(E29<>"",E29,($I$9-SUM($T$25:T28))*V29*W29/SUMPRODUCT($W29:$W$55,$V29:$V$55)),"") -> 3 | U29: =IF(W29<>"",IF($I$12<>"",IF(G29<>"",G29,($I$9/$I$12-SUM($U$25:U28))*V29*W29/SUMPRODUCT($W29:$W$55,$V29:$V$55)),""),"") -> 2 | V29: 0.9 | W29: 0.9
A30: Рогалевич | B30: 45694 | C30: чт | E30: 0 | F30: =IF(AND(E30<>"",E30<>0),D30/E30,"") | G30: 0 | H30: =IF(AND(G30<>"",G30<>0),D30/G30,"") | I30: 4 | J30: =IF(AND(G30<>"",G30<>0),E30/G30,"") | N30: =IF(AND(I30<>"",I30<>0),G30/I30,"") -> 0 | O30: =D30/P30 -> 0 | P30: =$I$8*V30*W30/SUMPRODUCT($W$25:$W$55,$V$25:$V$55) -> 57757.405 | Q30: =$I$9*V30*W30/SUMPRODUCT($W$25:$W$55,$V$25:$V$55) -> 15.037075 | R30: =IF($I$12="","",Q30/$I$12) -> 7.5185375 | S30: =IF(W30<>"",IF(D30<>"",D30,($I$8-SUM($S$25:S29))*V30*W30/SUMPRODUCT($W30:$W$55,$V30:$V$55)),"") -> 59178.665 | T30: =IF(W30<>"",IF(E30<>"",E30,($I$9-SUM($T$25:T29))*V30*W30/SUMPRODUCT($W30:$W$55,$V30:$V$55)),"") -> 0 | U30: =IF(W30<>"",IF($I$12<>"",IF(G30<>"",G30,($I$9/$I$12-SUM($U$25:U29))*V30*W30/SUMPRODUCT($W30:$W$55,$V30:$V$55)),""),"") -> 0 | V30: 1.2 | W30: 1.2
A31: Рогалевич | B31: 45695 | C31: пт | D31: 5984 | E31: 2 | F31: =IF(AND(E31<>"",E31<>0),D31/E31,"") -> 2992 | G31: 2 | H31: =IF(AND(G31<>"",G31<>0),D31/G31,"") -> 2992 | I31: 9 | J31: =IF(AND(G31<>"",G31<>0),E31/G31,"") -> 1 | N31: =IF(AND(I31<>"",I31<>0),G31/I31,"") -> 0.22222222 | O31: =D31/P31 -> 0.088279467 | P31: =$I$8*V31*W31/SUMPRODUCT($W$25:$W$55,$V$25:$V$55) -> 67784.732 | Q31: =$I$9*V31*W31/SUMPRODUCT($W$25:$W$55,$V$25:$V$55) -> 17.647678 | R31: =IF($I$12="","",Q31/$I$12) -> 8.8238391 | S31: =IF(W31<>"",IF(D31<>"",D31,($I$8-SUM($S$25:S30))*V31*W31/SUMPRODUCT($W31:$W$55,$V31:$V$55)),"") -> 5984 | T31: =IF(W31<>"",IF(E31<>"",E31,($I$9-SUM($T$25:T30))*V31*W31/SUMPRODUCT($W31:$W$55,$V31:$V$55)),"") -> 2 | U31: =IF(W31<>"",IF($I$12<>"",IF(G31<>"",G31,($I$9/$I$12-SUM($U$25:U30))*V31*W31/SUMPRODUCT($W31:$W$55,$V31:$V$55)),""),"") -> 2 | V31: 1.3 | W31: 1.3
A32: Рогалевич | B32: 45696 | C32: сб | D32: 13876 | E32: 3 | F32: =IF(AND(E32<>"",E32<>0),D32/E32,"") -> 4625.3333 | G32: 3 | H32: =IF(AND(G32<>"",G32<>0),D32/G32,"") -> 4625.3333 | I32: 4 | J32: =IF(AND(G32<>"",G32<>0),E32/G32,"") -> 1 | N32: =IF(AND(I32<>"",I32<>0),G32/I32,"") -> 0.75 | O32: =D32/P32 -> 0.1537576 | P32: =$I$8*V32*W32/SUMPRODUCT($W$25:$W$55,$V$25:$V$55) -> 90245.945 | Q32: =$I$9*V32*W32/SUMPRODUCT($W$25:$W$55,$V$25:$V$55) -> 23.49543 | R32: =IF($I$12="","",Q32/$I$12) -> 11.747715 | S32: =IF(W32<>"",IF(D32<>"",D32,($I$8-SUM($S$25:S31))*V32*W32/SUMPRODUCT($W32:$W$55,$V32:$V$55)),"") -> 13876 | T32: =IF(W32<>"",IF(E32<>"",E32,($I$9-SUM($T$25:T31))*V32*W32/SUMPRODUCT($W32:$W$55,$V32:$V$55)),"") -> 3 | U32: =IF(W32<>"",IF($I$12<>"",IF(G32<>"",G32,($I$9/$I$12-SUM($U$25:U31))*V32*W32/SUMPRODUCT($W32:$W$55,$V32:$V$55)),""),"") -> 3 | V32: 1.5 | W32: 1.5
A33: Рогалевич | B33: 45697 | C33: вс | E33: 0 | F33: =IF(AND(E33<>"",E33<>0),D33/E33,"") | G33: 0 | H33: =IF(AND(G33<>"",G33<>0),D33/G33,"") | I33: 4 | J33: =IF(AND(G33<>"",G33<>0),E33/G33,"") | N33: =IF(AND(I33<>"",I33<>0),G33/I33,"") -> 0 | O33: =D33/P33 -> 0 | P33: =$I$8*V33*W33/SUMPRODUCT($W$25:$W$55,$V$25:$V$55) -> 40109.309 | Q33: =$I$9*V33*W33/SUMPRODUCT($W$25:$W$55,$V$25:$V$55) -> 10.442413 | R33: =IF($I$12="","",Q33/$I$12) -> 5.2212066 | S33: =IF(W33<>"",IF(D33<>"",D33,($I$8-SUM($S$25:S32))*V33*W33/SUMPRODUCT($W33:$W$55,$V33:$V$55)),"") -> 49135.876 | T33: =IF(W33<>"",IF(E33<>"",E33,($I$9-SUM($T$25:T32))*V33*W33/SUMPRODUCT($W33:$W$55,$V33:$V$55)),"") -> 0 | U33: =IF(W33<>"",IF($I$12<>"",IF(G33<>"",G33,($I$9/$I$12-SUM($U$25:U32))*V33*W33/SUMPRODUCT($W33:$W$55,$V33:$V$55)),""),"") -> 0 | V33: 1 | W33: 1
A34: Рогалевич | B34: 45698 | C34: пн | D34: 17966 | E34: 4 | F34: =IF(AND(E34<>"",E34<>0),D34/E34,"") -> 4491.5 | G34: 2 | H34: =IF(AND(G34<>"",G34<>0),D34/G34,"") -> 8983 | I34: 12 | J34: =IF(AND(G34<>"",G34<>0),E34/G34,"") -> 2 | N34: =IF(AND(I34<>"",I34<>0),G34/I34,"") -> 0.16666667 | O34: =D34/P34 -> 0.55299499 | P34: =$I$8*V34*W34/SUMPRODUCT($W$25:$W$55,$V$25:$V$55) -> 32488.54 | Q34: =$I$9*V34*W34/SUMPRODUCT($W$25:$W$55,$V$25:$V$55) -> 8.4583547 | R34: =IF($I$12="","",Q34/$I$12) -> 4.2291773 | S34: =IF(W34<>"",IF(D34<>"",D34,($I$8-SUM($S$25:S33))*V34*W34/SUMPRODUCT($W34:$W$55,$V34:$V$55)),"") -> 17966 | T34: =IF(W34<>"",IF(E34<>"",E34,($I$9-SUM($T$25:T33))*V34*W34/SUMPRODUCT($W34:$W$55,$V34:$V$55)),"") -> 4 | U34: =IF(W34<>"",IF($I$12<>"",IF(G34<>"",G34,($I$9/$I$12-SUM($U$25:U33))*V34*W34/SUMPRODUCT($W34:$W$55,$V34:$V$55)),""),"") -> 2 | V34: 0.9 | W34: 0.9
A35: Рогалевич | B35: 45699 | C35: вт | D35: 12675 | E35: 3 | F35: =IF(AND(E35<>"",E35<>0),D35/E35,"") -> 4225 | G35: 2 | H35: =IF(AND(G35<>"",G35<>0),D35/G35,"") -> 6337.5 | I35: 10 | J35: =IF(AND(G35<>"",G35<>0),E35/G35,"") -> 1.5 | N35: =IF(AND(I35<>"",I35<>0),G35/I35,"") -> 0.2 | O35: =D35/P35 -> 0.39013757 | P35: =$I$8*V35*W35/SUMPRODUCT($W$25:$W$55,$V$25:$V$55) -> 32488.54 | Q35: =$I$9*V35*W35/SUMPRODUCT($W$25:$W$55,$V$25:$V$55) -> 8.4583547 | R35: =IF($I$12="","",Q35/$I$12) -> 4.2291773 | S35: =IF(W35<>"",IF(D35<>"",D35,($I$8-SUM($S$25:S34))*V35*W35/SUMPRODUCT($W35:$W$55,$V35:$V$55)),"") -> 12675 | T35: =IF(W35<>"",IF(E35<>"",E35,($I$9-SUM($T$25:T34))*V35*W35/SUMPRODUCT($W35:$W$55,$V35:$V$55)),"") -> 3 | U35: =IF(W35<>"",IF($I$12<>"",IF(G35<>"",G35,($I$9/$I$12-SUM($U$25:U34))*V35*W35/SUMPRODUCT($W35:$W$55,$V35:$V$55)),""),"") -> 2 | V35: 0.9 | W35: 0.9
A36: Рогалевич | B36: 45700 | C36: ср | D36: 21858 | E36: 5 | F36: =IF(AND(E36<>"",E36<>0),D36/E36,"") -> 4371.6 | G36: 3 | H36: =IF(AND(G36<>"",G36<>0),D36/G36,"") -> 7286 | I36: 8 | J36: =IF(AND(G36<>"",G36<>0),E36/G36,"") -> 1.6666667 | N36: =IF(AND(I36<>"",I36<>0),G36/I36,"") -> 0.375 | O36: =D36/P36 -> 0.67279108 | P36: =$I$8*V36*W36/SUMPRODUCT($W$25:$W$55,$V$25:$V$55) -> 32488.54 | Q36: =$I$9*V36*W36/SUMPRODUCT($W$25:$W$55,$V$25:$V$55) -> 8.4583547 | R36: =IF($I$12="","",Q36/$I$12) -> 4.2291773 | S36: =IF(W36<>"",IF(D36<>"",D36,($I$8-SUM($S$25:S35))*V36*W36/SUMPRODUCT($W36:$W$55,$V36:$V$55)),"") -> 21858 | T36: =IF(W36<>"",IF(E35<>"",E35,($I$9-SUM($T$25:T35))*V36*W36/SUMPRODUCT($W36:$W$55,$V36:$V$55)),"") -> 3 | U36: =IF(W36<>"",IF($I$12<>"",IF(G36<>"",G36,($I$9/$I$12-SUM($U$25:U35))*V36*W36/SUMPRODUCT($W36:$W$55,$V36:$V$55)),""),"") -> 3 | V36: 0.9 | W36: 0.9
A37: Рогалевич | B37: 45701 | C37: чт | D37: 71996 | E37: 16 | F37: =IF(AND(E37<>"",E37<>0),D37/E37,"") -> 4499.75 | G37: 7 | H37: =IF(AND(G37<>"",G37<>0),D37/G37,"") -> 10285.143 | I37: 18 | J37: =IF(AND(G37<>"",G37<>0),E37/G37,"") -> 2.2857143 | N37: =IF(AND(I37<>"",I37<>0),G37/I37,"") -> 0.38888889 | O37: =D37/P37 -> 1.7949948 | P37: =$I$8*V37*W37/SUMPRODUCT($W$25:$W$55,$V$25:$V$55) -> 40109.309 | Q37: =$I$9*V37*W37/SUMPRODUCT($W$25:$W$55,$V$25:$V$55) -> 10.442413 | R37: =IF($I$12="","",Q37/$I$12) -> 5.2212066 | S37: =IF(W37<>"",IF(D37<>"",D37,($I$8-SUM($S$25:S36))*V37*W37/SUMPRODUCT($W37:$W$55,$V37:$V$55)),"") -> 71996 | T37: =IF(W37<>"",IF(E37<>"",E37,($I$9-SUM($T$25:T36))*V37*W37/SUMPRODUCT($W37:$W$55,$V37:$V$55)),"") -> 16 | U37: =IF(W37<>"",IF($I$12<>"",IF(G37<>"",G37,($I$9/$I$12-SUM($U$25:U36))*V37*W37/SUMPRODUCT($W37:$W$55,$V37:$V$55)),""),"") -> 7 | V37: 1 | W37: 1
A38: Рогалевич | B38: 45702 | C38: пт | D38: 56474 | E38: 15 | F38: =IF(AND(E38<>"",E38<>0),D38/E38,"") -> 3764.9333 | G38: 7 | H38: =IF(AND(G38<>"",G38<>0),D38/G38,"") -> 8067.7143 | I38: 20 | J38: =IF(AND(G38<>"",G38<>0),E38/G38,"") -> 2.1428571 | N38: =IF(AND(I38<>"",I38<>0),G38/I38,"") -> 0.35 | O38: =D38/P38 -> 1.4080023 | P38: =$I$8*V38*W38/SUMPRODUCT($W$25:$W$55,$V$25:$V$55) -> 40109.309 | Q38: =$I$9*V38*W38/SUMPRODUCT($W$25:$W$55,$V$25:$V$55) -> 10.442413 | R38: =IF($I$12="","",Q38/$I$12) -> 5.2212066 | S38: =IF(W38<>"",IF(D38<>"",D38,($I$8-SUM($S$25:S37))*V38*W38/SUMPRODUCT($W38:$W$55,$V38:$V$55)),"") -> 56474 | T38: =IF(W38<>"",IF(E38<>"",E38,($I$9-SUM($T$25:T37))*V38*W38/SUMPRODUCT($W38:$W$55,$V38:$V$55)),"") -> 15 | U38: =IF(W38<>"",IF($I$12<>"",IF(G38<>"",G38,($I$9/$I$12-SUM($U$25:U37))*V38*W38/SUMPRODUCT($W38:$W$55,$V38:$V$55)),""),"") -> 7 | V38: 1 | W38: 1
A39: Рогалевич | B39: 45703 | C39: сб | D39: 63280 | E39: 14 | F39: =IF(AND(E39<>"",E39<>0),D39/E39,"") -> 4520 | G39: 6 | H39: =IF(AND(G39<>"",G39<>0),D39/G39,"") -> 10546.667 | I39: 25 | J39: =IF(AND(G39<>"",G39<>0),E39/G39,"") -> 2.3333333 | N39: =IF(AND(I39<>"",I39<>0),G39/I39,"") -> 0.24 | O39: =D39/P39 -> 1.3038749 | P39: =$I$8*V39*W39/SUMPRODUCT($W$25:$W$55,$V$25:$V$55) -> 48532.264 | Q39: =$I$9*V39*W39/SUMPRODUCT($W$25:$W$55,$V$25:$V$55) -> 12.63532 | R39: =IF($I$12="","",Q39/$I$12) -> 6.31766 | S39: =IF(W39<>"",IF(D39<>"",D39,($I$8-SUM($S$25:S38))*V39*W39/SUMPRODUCT($W39:$W$55,$V39:$V$55)),"") -> 63280 | T39: =IF(W39<>"",IF(E39<>"",E39,($I$9-SUM($T$25:T38))*V39*W39/SUMPRODUCT($W39:$W$55,$V39:$V$55)),"") -> 14 | U39: =IF(W39<>"",IF($I$12<>"",IF(G39<>"",G39,($I$9/$I$12-SUM($U$25:U38))*V39*W39/SUMPRODUCT($W39:$W$55,$V39:$V$55)),""),"") -> 6 | V39: 1.1 | W39: 1.1
A40: Рогалевич | B40: 45704 | C40: вс | D40: 21059 | E40: 5 | F40: =IF(AND(E40<>"",E40<>0),D40/E40,"") -> 4211.8 | G40: 2 | H40: =IF(AND(G40<>"",G40<>0),D40/G40,"") -> 10529.5 | I40: 4 | J40: =IF(AND(G40<>"",G40<>0),E40/G40,"") -> 2.5 | N40: =IF(AND(I40<>"",I40<>0),G40/I40,"") -> 0.5 | O40: =D40/P40 -> 0.43391753 | P40: =$I$8*V40*W40/SUMPRODUCT($W$25:$W$55,$V$25:$V$55) -> 48532.264 | Q40: =$I$9*V40*W40/SUMPRODUCT($W$25:$W$55,$V$25:$V$55) -> 12.63532 | R40: =IF($I$12="","",Q40/$I$12) -> 6.31766 | S40: =IF(W40<>"",IF(D40<>"",D40,($I$8-SUM($S$25:S39))*V40*W40/SUMPRODUCT($W40:$W$55,$V40:$V$55)),"") -> 21059 | T40: =IF(W40<>"",IF(E40<>"",E40,($I$9-SUM($T$25:T39))*V40*W40/SUMPRODUCT($W40:$W$55,$V40:$V$55)),"") -> 5 | U40: =IF(W40<>"",IF($I$12<>"",IF(G40<>"",G40,($I$9/$I$12-SUM($U$25:U39))*V40*W40/SUMPRODUCT($W40:$W$55,$V40:$V$55)),""),"") -> 2 | V40: 1.1 | W40: 1.1
A41: Рогалевич | B41: 45705 | C41: пн | D41: 29039 | E41: 7 | F41: =IF(AND(E41<>"",E41<>0),D41/E41,"") -> 4148.4286 | G41: 4 | H41: =IF(AND(G41<>"",G41<>0),D41/G41,"") -> 7259.75 | I41: 16 | J41: =IF(AND(G41<>"",G41<>0),E41/G41,"") -> 1.75 | N41: =IF(AND(I41<>"",I41<>0),G41/I41,"") -> 0.25 | O41: =D41/P41 -> 1.1312446 | P41: =$I$8*V41*W41/SUMPRODUCT($W$25:$W$55,$V$25:$V$55) -> 25669.958 | Q41: =$I$9*V41*W41/SUMPRODUCT($W$25:$W$55,$V$25:$V$55) -> 6.6831444 | R41: =IF($I$12="","",Q41/$I$12) -> 3.3415722 | S41: =IF(W41<>"",IF(D41<>"",D41,($I$8-SUM($S$25:S40))*V41*W41/SUMPRODUCT($W41:$W$55,$V41:$V$55)),"") -> 29039 | T41: =IF(W41<>"",IF(E41<>"",E41,($I$9-SUM($T$25:T40))*V41*W41/SUMPRODUCT($W41:$W$55,$V41:$V$55)),"") -> 7 | U41: =IF(W41<>"",IF($I$12<>"",IF(G41<>"",G41,($I$9/$I$12-SUM($U$25:U40))*V41*W41/SUMPRODUCT($W41:$W$55,$V41:$V$55)),""),"") -> 4 | V41: 0.8 | W41: 0.8
A42: Рогалевич | B42: 45706 | C42: вт | D42: 37624 | E42: 9 | F42: =IF(AND(E42<>"",E42<>0),D42/E42,"") -> 4180.4444 | G42: 5 | H42: =IF(AND(G42<>"",G42<>0),D42/G42,"") -> 7524.8 | I42: 11 | J42: =IF(AND(G42<>"",G42<>0),E42/G42,"") -> 1.8 | N42: =IF(AND(I42<>"",I42<>0),G42/I42,"") -> 0.45454545 | O42: =D42/P42 -> 1.4656822 | P42: =$I$8*V42*W42/SUMPRODUCT($W$25:$W$55,$V$25:$V$55) -> 25669.958 | Q42: =$I$9*V42*W42/SUMPRODUCT($W$25:$W$55,$V$25:$V$55) -> 6.6831444 | R42: =IF($I$12="","",Q42/$I$12) -> 3.3415722 | S42: =IF(W42<>"",IF(D42<>"",D42,($I$8-SUM($S$25:S41))*V42*W42/SUMPRODUCT($W42:$W$55,$V42:$V$55)),"") -> 37624 | T42: =IF(W42<>"",IF(E42<>"",E42,($I$9-SUM($T$25:T41))*V42*W42/SUMPRODUCT($W42:$W$55,$V42:$V$55)),"") -> 9 | U42: =IF(W42<>"",IF($I$12<>"",IF(G42<>"",G42,($I$9/$I$12-SUM($U$25:U41))*V42*W42/SUMPRODUCT($W42:$W$55,$V42:$V$55)),""),"") -> 5 | V42: 0.8 | W42: 0.8
A43: Рогалевич | B43: 45707 | C43: ср | D43: 42905 | E43: 9 | F43: =IF(AND(E43<>"",E43<>0),D43/E43,"") -> 4767.2222 | G43: 5 | H43: =IF(AND(G43<>"",G43<>0),D43/G43,"") -> 8581 | I43: 17 | J43: =IF(AND(G43<>"",G43<>0),E43/G43,"") -> 1.8 | N43: =IF(AND(I43<>"",I43<>0),G43/I43,"") -> 0.29411765 | O43: =D43/P43 -> 1.6714091 | P43: =$I$8*V43*W43/SUMPRODUCT($W$25:$W$55,$V$25:$V$55) -> 25669.958 | Q43: =$I$9*V43*W43/SUMPRODUCT($W$25:$W$55,$V$25:$V$55) -> 6.6831444 | R43: =IF($I$12="","",Q43/$I$12) -> 3.3415722 | S43: =IF(W43<>"",IF(D43<>"",D43,($I$8-SUM($S$25:S42))*V43*W43/SUMPRODUCT($W43:$W$55,$V43:$V$55)),"") -> 42905 | T43: =IF(W43<>"",IF(E43<>"",E43,($I$9-SUM($T$25:T42))*V43*W43/SUMPRODUCT($W43:$W$55,$V43:$V$55)),"") -> 9 | U43: =IF(W43<>"",IF($I$12<>"",IF(G43<>"",G43,($I$9/$I$12-SUM($U$25:U42))*V43*W43/SUMPRODUCT($W43:$W$55,$V43:$V$55)),""),"") -> 5 | V43: 0.8 | W43: 0.8
A44: Рогалевич | B44: 45708 | C44: чт | D44: 66400 | E44: 16 | F44: =IF(AND(E44<>"",E44<>0),D44/E44,"") -> 4150 | G44: 9 | H44: =IF(AND(G44<>"",G44<>0),D44/G44,"") -> 7377.7778 | I44: 20 | J44: =IF(AND(G44<>"",G44<>0),E44/G44,"") -> 1.7777778 | N44: =IF(AND(I44<>"",I44<>0),G44/I44,"") -> 0.45 | O44: =D44/P44 -> 2.0437976 | P44: =$I$8*V44*W44/SUMPRODUCT($W$25:$W$55,$V$25:$V$55) -> 32488.54 | Q44: =$I$9*V44*W44/SUMPRODUCT($W$25:$W$55,$V$25:$V$55) -> 8.4583547 | R44: =IF($I$12="","",Q44/$I$12) -> 4.2291773 | S44: =IF(W44<>"",IF(D44<>"",D44,($I$8-SUM($S$25:S43))*V44*W44/SUMPRODUCT($W44:$W$55,$V44:$V$55)),"") -> 66400 | T44: =IF(W44<>"",IF(E44<>"",E44,($I$9-SUM($T$25:T43))*V44*W44/SUMPRODUCT($W44:$W$55,$V44:$V$55)),"") -> 16 | U44: =IF(W44<>"",IF($I$12<>"",IF(G44<>"",G44,($I$9/$I$12-SUM($U$25:U43))*V44*W44/SUMPRODUCT($W44:$W$55,$V44:$V$55)),""),"") -> 9 | V44: 0.9 | W44: 0.9
A45: Рогалевич | B45: 45709 | C45: пт | D45: 28558 | E45: 5 | F45: =IF(AND(E45<>"",E45<>0),D45/E45,"") -> 5711.6 | G45: 2 | H45: =IF(AND(G45<>"",G45<>0),D45/G45,"") -> 14279 | I45: 7 | J45: =IF(AND(G45<>"",G45<>0),E45/G45,"") -> 2.5 | N45: =IF(AND(I45<>"",I45<>0),G45/I45,"") -> 0.28571429 | O45: =D45/P45 -> 0.87901764 | P45: =$I$8*V45*W45/SUMPRODUCT($W$25:$W$55,$V$25:$V$55) -> 32488.54 | Q45: =$I$9*V45*W45/SUMPRODUCT($W$25:$W$55,$V$25:$V$55) -> 8.4583547 | R45: =IF($I$12="","",Q45/$I$12) -> 4.2291773 | S45: =IF(W45<>"",IF(D45<>"",D45,($I$8-SUM($S$25:S44))*V45*W45/SUMPRODUCT($W45:$W$55,$V45:$V$55)),"") -> 28558 | T45: =IF(W45<>"",IF(E45<>"",E45,($I$9-SUM($T$25:T44))*V45*W45/SUMPRODUCT($W45:$W$55,$V45:$V$55)),"") -> 5 | U45: =IF(W45<>"",IF($I$12<>"",IF(G45<>"",G45,($I$9/$I$12-SUM($U$25:U44))*V45*W45/SUMPRODUCT($W45:$W$55,$V45:$V$55)),""),"") -> 2 | V45: 0.9 | W45: 0.9
A46: Рогалевич | B46: 45710 | C46: сб | D46: 22350 | E46: 6 | F46: =IF(AND(E46<>"",E46<>0),D46/E46,"") -> 3725 | G46: 4 | H46: =IF(AND(G46<>"",G46<>0),D46/G46,"") -> 5587.5 | I46: 15 | J46: =IF(AND(G46<>"",G46<>0),E46/G46,"") -> 1.5 | N46: =IF(AND(I46<>"",I46<>0),G46/I46,"") -> 0.26666667 | O46: =D46/P46 -> 0.55722725 | P46: =$I$8*V46*W46/SUMPRODUCT($W$25:$W$55,$V$25:$V$55) -> 40109.309 | Q46: =$I$9*V46*W46/SUMPRODUCT($W$25:$W$55,$V$25:$V$55) -> 10.442413 | R46: =IF($I$12="","",Q46/$I$12) -> 5.2212066 | S46: =IF(W46<>"",IF(D46<>"",D46,($I$8-SUM($S$25:S45))*V46*W46/SUMPRODUCT($W46:$W$55,$V46:$V$55)),"") -> 22350 | T46: =IF(W46<>"",IF(E46<>"",E46,($I$9-SUM($T$25:T45))*V46*W46/SUMPRODUCT($W46:$W$55,$V46:$V$55)),"") -> 6 | U46: =IF(W46<>"",IF($I$12<>"",IF(G46<>"",G46,($I$9/$I$12-SUM($U$25:U45))*V46*W46/SUMPRODUCT($W46:$W$55,$V46:$V$55)),""),"") -> 4 | V46: 1 | W46: 1
A47: Рогалевич | B47: 45711 | C47: вс | D47: 56582 | E47: 13 | F47: =IF(AND(E47<>"",E47<>0),D47/E47,"") -> 4352.4615 | G47: 9 | H47: =IF(AND(G47<>"",G47<>0),D47/G47,"") -> 6286.8889 | I47: 24 | J47: =IF(AND(G47<>"",G47<>0),E47/G47,"") -> 1.4444444 | N47: =IF(AND(I47<>"",I47<>0),G47/I47,"") -> 0.375 | O47: =D47/P47 -> 1.410695 | P47: =$I$8*V47*W47/SUMPRODUCT($W$25:$W$55,$V$25:$V$55) -> 40109.309 | Q47: =$I$9*V47*W47/SUMPRODUCT($W$25:$W$55,$V$25:$V$55) -> 10.442413 | R47: =IF($I$12="","",Q47/$I$12) -> 5.2212066 | S47: =IF(W47<>"",IF(D47<>"",D47,($I$8-SUM($S$25:S46))*V47*W47/SUMPRODUCT($W47:$W$55,$V47:$V$55)),"") -> 56582 | T47: =IF(W47<>"",IF(E47<>"",E47,($I$9-SUM($T$25:T46))*V47*W47/SUMPRODUCT($W47:$W$55,$V47:$V$55)),"") -> 13 | U47: =IF(W47<>"",IF($I$12<>"",IF(G47<>"",G47,($I$9/$I$12-SUM($U$25:U46))*V47*W47/SUMPRODUCT($W47:$W$55,$V47:$V$55)),""),"") -> 9 | V47: 1 | W47: 1
A48: Рогалевич | B48: 45712 | C48: пн | D48: 3892 | E48: 1 | F48: =IF(AND(E48<>"",E48<>0),D48/E48,"") -> 3892 | G48: 1 | H48: =IF(AND(G48<>"",G48<>0),D48/G48,"") -> 3892 | I48: 5 | J48: =IF(AND(G48<>"",G48<>0),E48/G48,"") -> 1 | N48: =IF(AND(I48<>"",I48<>0),G48/I48,"") -> 0.2 | O48: =D48/P48 -> 0.15161692 | P48: =$I$8*V48*W48/SUMPRODUCT($W$25:$W$55,$V$25:$V$55) -> 25669.958 | Q48: =$I$9*V48*W48/SUMPRODUCT($W$25:$W$55,$V$25:$V$55) -> 6.6831444 | R48: =IF($I$12="","",Q48/$I$12) -> 3.3415722 | S48: =IF(W48<>"",IF(D48<>"",D48,($I$8-SUM($S$25:S47))*V48*W48/SUMPRODUCT($W48:$W$55,$V48:$V$55)),"") -> 3892 | T48: =IF(W48<>"",IF(E48<>"",E48,($I$9-SUM($T$25:T47))*V48*W48/SUMPRODUCT($W48:$W$55,$V48:$V$55)),"") -> 1 | U48: =IF(W48<>"",IF($I$12<>"",IF(G48<>"",G48,($I$9/$I$12-SUM($U$25:U47))*V48*W48/SUMPRODUCT($W48:$W$55,$V48:$V$55)),""),"") -> 1 | V48: 0.8 | W48: 0.8
... A52: Рогалевич | B52: 45716 | C52: пт | D52: 20159 | E52: 5 | F52: =IF(AND(E52<>"",E52<>0),D52/E52,"") -> 4031.8 | G52: 5 | H52: =IF(AND(G52<>"",G52<>0),D52/G52,"") -> 4031.8 | I52: 10 | J52: =IF(AND(G52<>"",G52<>0),E52/G52,"") -> 1 | N52: =IF(AND(I52<>"",I52<>0),G52/I52,"") -> 0.5 | O52: =D52/P52 -> 0.50260153 | P52: =$I$8*V52*W52/SUMPRODUCT($W$25:$W$55,$V$25:$V$55) -> 40109.309 | Q52: =$I$9*V52*W52/SUMPRODUCT($W$25:$W$55,$V$25:$V$55) -> 10.442413 | R52: =IF($I$12="","",Q52/$I$12) -> 5.2212066 | S52: =IF(W52<>"",IF(D52<>"",D52,($I$8-SUM($S$25:S51))*V52*W52/SUMPRODUCT($W52:$W$55,$V52:$V$55)),"") -> 20159 | T52: =IF(W52<>"",IF(E52<>"",E52,($I$9-SUM($T$25:T51))*V52*W52/SUMPRODUCT($W52:$W$55,$V52:$V$55)),"") -> 5 | U52: =IF(W52<>"",IF($I$12<>"",IF(G52<>"",G52,($I$9/$I$12-SUM($U$25:U51))*V52*W52/SUMPRODUCT($W52:$W$55,$V52:$V$55)),""),"") -> 5 | V52: 1 | W52: 1
F53: =IF(AND(E53<>"",E53<>0),D53/E53,"") | H53: =IF(AND(G53<>"",G53<>0),D53/G53,"") | J53: =IF(AND(G53<>"",G53<>0),E53/G53,"") | N53: =IF(AND(I53<>"",I53<>0),G53/I53,"") | O53: =D53/P53 -> #DIV/0! | P53: =$I$8*V53*W53/SUMPRODUCT($W$25:$W$55,$V$25:$V$55) -> 0 | Q53: =$I$9*V53*W53/SUMPRODUCT($W$25:$W$55,$V$25:$V$55) -> 0 | R53: =IF($I$12="","",Q53/$I$12) -> 0 | S53: =IF(W53<>"",IF(D53<>"",D53,($I$8-SUM($S$25:S52))*V53*W53/SUMPRODUCT($W53:$W$55,$V53:$V$55)),"") | T53: =IF(W53<>"",IF(E53<>"",E53,($I$9-SUM($T$25:T52))*V53*W53/SUMPRODUCT($W53:$W$55,$V53:$V$55)),"") | U53: =IF(W53<>"",IF($I$12<>"",IF(G53<>"",G53,($I$9/$I$12-SUM($U$25:U52))*V53*W53/SUMPRODUCT($W53:$W$55,$V53:$V$55)),""),"")
F54: =IF(AND(E54<>"",E54<>0),D54/E54,"") | H54: =IF(AND(G54<>"",G54<>0),D54/G54,"") | J54: =IF(AND(G54<>"",G54<>0),E54/G54,"") | N54: =IF(AND(I54<>"",I54<>0),G54/I54,"") | O54: =D54/P54 -> #DIV/0! | P54: =$I$8*V54*W54/SUMPRODUCT($W$25:$W$55,$V$25:$V$55) -> 0 | Q54: =$I$9*V54*W54/SUMPRODUCT($W$25:$W$55,$V$25:$V$55) -> 0 | R54: =IF($I$12="","",Q54/$I$12) -> 0 | S54: =IF(W54<>"",IF(D54<>"",D54,($I$8-SUM($S$25:S53))*V54*W54/SUMPRODUCT($W54:$W$55,$V54:$V$55)),"") | T54: =IF(W54<>"",IF(E54<>"",E54,($I$9-SUM($T$25:T53))*V54*W54/SUMPRODUCT($W54:$W$55,$V54:$V$55)),"") | U54: =IF(W54<>"",IF($I$12<>"",IF(G54<>"",G54,($I$9/$I$12-SUM($U$25:U53))*V54*W54/SUMPRODUCT($W54:$W$55,$V54:$V$55)),""),"")
F55: =IF(AND(E55<>"",E55<>0),D55/E55,"") | H55: =IF(AND(G55<>"",G55<>0),D55/G55,"") | J55: =IF(AND(G55<>"",G55<>0),E55/G55,"") | N55: =IF(AND(I55<>"",I55<>0),G55/I55,"") | O55: =D55/P55 -> #DIV/0! | P55: =$I$8*V55*W55/SUMPRODUCT($W$25:$W$55,$V$25:$V$55) -> 0 | Q55: =$I$9*V55*W55/SUMPRODUCT($W$25:$W$55,$V$25:$V$55) -> 0 | R55: =IF($I$12="","",Q55/$I$12) -> 0 | S55: =IF(W55<>"",IF(D55<>"",D55,($I$8-SUM($S$25:S54))*V55*W55/SUMPRODUCT($W55:$W$55,$V55:$V$55)),"") | T55: =IF(W55<>"",IF(E55<>"",E55,($I$9-SUM($T$25:T54))*V55*W55/SUMPRODUCT($W55:$W$55,$V55:$V$55)),0) -> 0 | U55: =IF(W55<>"",IF($I$12<>"",IF(G55<>"",G55,($I$9/$I$12-SUM($U$25:U54))*V55*W55/SUMPRODUCT($W55:$W$55,$V55:$V$55)),""),"")
B56: итого | D56: =SUM(D25:D55) -> 809309 | E56: =SUM(E25:E55) -> 192 | F56: =IF(AND(E56<>"", E56<>0), D56/E56, "") -> 4215.151 | G56: =SUM(G25:G55) -> 104 | H56: =IF(AND(G56<>"", G56<>0), D56/G56, "") -> 7781.8173 | I56: =SUM(I25:I55) -> 341 | J56: =E56/G56 -> 1.8461538 | K56: =SUM(K25:K55) -> 0 | L56: =SUM(L25:L55) -> 0 | M56: =SUM(M25:M55) -> 0 | N56: =IF(AND(I56<>"", I56<>0), G56/I56, "") -> 0.30498534 | O56: =D56/P56 -> 0.73775449 | P56: =SUM(P25:P55) -> 1096989.6 | Q56: =SUM(Q25:Q55) -> 285.6 | R56: =SUM(R25:R55) -> 142.8 | S56: =SUM(S25:S55) -> 917623.54 | T56: =SUM(T25:T55) -> 190 | U56: =SUM(U25:U55) -> 104
D57: =SUMIF(D25:D55,"",P25:P55)+D56 -> 907175.71 | I57: =I56/J14 -> 12.178571
D58: ='Рогалевич И. Е.'!J8+ПК1!J8+'ПК 2'!J8+'Доп сотрудник'!J8 -> 809309

Sheet Св. по пок.
A1: Сводная по показателям
A2: Показатель | D2: ='Ялта, Ленина, 18'!I3 -> ул. Набережная Ленина, 18 | G2: =График!B29 -> Рогалевич Ирина | J2: =График!B30 -> 0
D3: Факт | F3: Прогноз | G3: Факт | I3: Прогноз | J3: Факт | L3: Прогноз
A4: Выручка | D4: ='Ялта, Ленина, 18'!K8 -> 0.73775449 | E4: ='Ялта, Ленина, 18'!J8 -> 809309 | F4: ='Ялта, Ленина, 18'!M8 -> 0.81001948 | G4: ='Рогалевич И. Е.'!K8 -> 0.72389889 | H4: ='Рогалевич И. Е.'!J8 -> 723113 | I4: ='Рогалевич И. Е.'!M8 -> 0.80171004 | J4: =ПК1!K8 -> #DIV/0! | K4: =ПК1!J8 -> 0 | L4: =ПК1!M8
A5: Кол-во изделий | D5: ='Ялта, Ленина, 18'!K9 -> 0.67226891 | E5: ='Ялта, Ленина, 18'!J9 -> 192 | F5: ='Ялта, Ленина, 18'!M9 -> 0.67226891 | G5: ='Рогалевич И. Е.'!K9 -> 0.64214413 | H5: ='Рогалевич И. Е.'!J9 -> 167 | I5: ='Рогалевич И. Е.'!M9 -> 0.69764492 | J5: =ПК1!K9 | K5: =ПК1!J9 -> 0 | L5: =ПК1!M9
A6: Средний чек | D6: ='Ялта, Ленина, 18'!K10 -> 1.0129937 | E6: ='Ялта, Ленина, 18'!J10 -> 7781.8173 | F6: ='Ялта, Ленина, 18'!M10 -> 1.0129937 | G6: ='Рогалевич И. Е.'!K10 -> 1.0231611 | H6: ='Рогалевич И. Е.'!J10 -> 7859.9239 | I6: ='Рогалевич И. Е.'!M10 -> 1.0231611 | J6: =ПК1!K10 | K6: =ПК1!J10 | L6: =ПК1!M10
A7: Средняя стоимость изделия | D7: ='Ялта, Ленина, 18'!K11 -> 1.0974098 | E7: ='Ялта, Ленина, 18'!J11 -> 4215.151 | F7: ='Ялта, Ленина, 18'!M11 -> 1.204904 | G7: ='Рогалевич И. Е.'!K11 -> 1.1273153 | H7: ='Рогалевич И. Е.'!J11 -> 4330.018 | I7: ='Рогалевич И. Е.'!M11 -> 1.1491663 | J7: =ПК1!K11 | K7: =ПК1!J11 | L7: =ПК1!M11
A8: Длина чека | D8: ='Ялта, Ленина, 18'!K12 -> 0.92307692 | E8: ='Ялта, Ленина, 18'!J12 -> 1.8461538 | F8: ='Ялта, Ленина, 18'!M12 -> 0.92307692 | G8: ='Рогалевич И. Е.'!K12 -> 0.9076087 | H8: ='Рогалевич И. Е.'!J12 -> 1.8152174 | I8: ='Рогалевич И. Е.'!M12 -> 0.9076087 | J8: =ПК1!K12 | K8: =ПК1!J12 | L8: =ПК1!M12
A9: Кол-во чеков | D9: ='Ялта, Ленина, 18'!K13 -> 0.72829132 | E9: ='Ялта, Ленина, 18'!J13 -> 104 | F9: ='Ялта, Ленина, 18'!M13 -> 0.72829132 | G9: ='Рогалевич И. Е.'!K13 -> 0.7075121 | H9: ='Рогалевич И. Е.'!J13 -> 92 | I9: ='Рогалевич И. Е.'!M13 -> 0.76866267 | J9: =ПК1!K13 | K9: =ПК1!J13 -> 0 | L9: =ПК1!M13
A10: Кол-во смен план/отработано | D10: ='Ялта, Ленина, 18'!K14 -> 1 | E10: ='Ялта, Ленина, 18'!J14 -> 28 | F10: ='Ялта, Ленина, 18'!M14 -> 13.371495 | G10: ='Рогалевич И. Е.'!K14 -> 1 | H10: ='Рогалевич И. Е.'!J14 -> 26 | I10: ='Рогалевич И. Е.'!M14 -> 13.966667 | J10: =ПК1!K14 | K10: =ПК1!J14 -> 0 | L10: =ПК1!M14
A11: Средние продажи в смену | D11: ='Ялта, Ленина, 18'!K15 -> 0.73775449 | E11: ='Ялта, Ленина, 18'!J15 -> 28903.893 | F11: ='Ялта, Ленина, 18'!M15 -> 0.73775449 | G11: ='Рогалевич И. Е.'!K15 -> 0.70988556 | H11: ='Рогалевич И. Е.'!J15 -> 27812.038 | I11: ='Рогалевич И. Е.'!M15 -> 0.70988556 | J11: =ПК1!K15 -> #DIV/0! | K11: =ПК1!J15 -> #DIV/0! | L11: =ПК1!M15 -> #DIV/0!
A12: Отставание/Перевыполнение | D12: ='Ялта, Ленина, 18'!J16 -> -287680.6 | G12: ='Рогалевич И. Е.'!J16 -> -295520.2 | J12: =ПК1!J16 -> 0

Sheet План на день
A1: Выручка | D1: 81988
A2: Кол-во изделий | D2: =D1/D4 -> 21.345483
A3: Средний чек | D3: =D4*D5 -> 7682
A4: Средняя стоимость изделия | D4: ='Ялта, Ленина, 18'!I11 -> 3841
A5: Длина чека | D5: ='Ялта, Ленина, 18'!I12 -> 2
A6: Кол-во чеков | D6: =IF(D5<>0,D2/D5,"") -> 10.672741
A7: Конверсия | D7: ='Ялта, Ленина, 18'!I20 -> 0.3

Sheet Рогалевич И. Е.
B1: =TODAY()-1 -> 46080
B2: (отчетная дата) | J2: ЕЖЕДНЕВНЫЙ ОТЧЕТ О ПРОДАЖАХ
B3: Осталось до выполнения плана!!! | J3: =График!B29 -> Рогалевич Ирина
C4: =I8-D51 -> 275801.37 | E4: =IF(I8<>0,C4/I8,0) -> 0.27610111
F6: Целевые показатели
F7: Показатель | I7: План | J7: Факт | K7: % выполнения | L7: Прогноз выполнения | M7: % выполнения по прогнозу | N7: Отклонение | O7: Факт аналогичного месяца прошлого года | P7: Отклонение LFL
F8: Выручка | I8: ='Ялта, Ленина, 18'!I8/График!AJ31*График!AJ29 -> 998914.37 | J8: =D51 -> 723113 | K8: =IF(AND(I8<>"",I8<>0,J8<>""),J8/I8,"") -> 0.72389889 | L8: =IF(SUMIF($D$25:$D$50,">=0",$P$25:$P$50)<>0,I8*D51/SUMIF($D$25:$D$50,">=0",$P$25:$P$50),0) -> 800839.68 | M8: =IF(AND(I8<>"",I8<>0,L8<>"",L8<>0),L8/I8,"") -> 0.80171004 | N8: =IF(AND(J8<>0,J8<>"",I8<>0,I8<>""),L8-I8,"") -> -198074.69 | P8: =IF(AND(O8<>"",O8<>0,L8<>"",L8<>0),-O8+L8,"") | Q8: =IF(AND(P8<>"",P8<>0,O8<>0,O8<>""),P8/O8,"")
F9: Кол-во изделий | I9: =I8/I11 -> 260.06623 | J9: =E51 -> 167 | K9: =IF(AND(I9<>"",I9<>0,J9<>""),J9/I9,"") -> 0.64214413 | L9: =IF(SUMIF($E$25:$E$48,">=0",$Q$25:$Q$48)<>0,I9*E51/SUMIF($E$25:$E$48,">=0",$Q$25:$Q$48),0) -> 181.43388 | M9: =IF(AND(I9<>"",I9<>0,L9<>"",L9<>0),L9/I9,"") -> 0.69764492 | N9: =IF(AND(J9<>0,J9<>"",I9<>0,I9<>""),L9-I9,"") -> -78.632344 | O9: =O8/O11 -> #DIV/0! | P9: =IF(AND(O9<>"",O9<>0,L9<>"",L9<>0),-O9+L9,"") -> #DIV/0! | Q9: =IF(AND(P9<>"",P9<>0,O9<>0,O9<>""),P9/O9,"") -> #DIV/0!
F10: Средний чек | I10: =I11*I12 -> 7682 | J10: =H51 -> 7859.9239 | K10: =IF(AND(I10<>"",I10<>0,J10<>""),J10/I10,"") -> 1.0231611 | L10: =J10 -> 7859.9239 | M10: =IF(AND(I10<>"",I10<>0,L10<>"",L10<>0),L10/I10,"") -> 1.0231611 | N10: =IF(AND(J10<>0,J10<>"",I10<>0,I10<>""),L10-I10,"") -> 177.92391 | O10: =O11*O12 -> 0 | P10: =IF(AND(O10<>"",O10<>0,L10<>"",L10<>0),-O10+L10,"") | Q10: =IF(AND(P10<>"",P10<>0,O10<>0,O10<>""),P10/O10,"")
F11: Средняя стоимость изделия | I11: ='Ялта, Ленина, 18'!I11 -> 3841 | J11: =F51 -> 4330.018 | K11: =IF(AND(I11<>"",I11<>0,J11<>""),J11/I11,"") -> 1.1273153 | L11: =IF(L9>0,L8/L9,"") -> 4413.9478 | M11: =IF(AND(I11<>"",I11<>0,L11<>"",L11<>0),L11/I11,"") -> 1.1491663 | N11: =IF(AND(J11<>0,J11<>"",I11<>0,I11<>""),L11-I11,"") -> 572.94783 | P11: =IF(AND(O11<>"",O11<>0,L11<>"",L11<>0),-O11+L11,"") | Q11: =IF(AND(P11<>"",P11<>0,O11<>0,O11<>""),P11/O11,"")
F12: Длина чека | I12: ='Ялта, Ленина, 18'!I12 -> 2 | J12: =J51 -> 1.8152174 | K12: =IF(AND(I12<>"",I12<>0,J12<>""),J12/I12,"") -> 0.9076087 | L12: =J12 -> 1.8152174 | M12: =IF(AND(I12<>"",I12<>0,L12<>"",L12<>0),L12/I12,"") -> 0.9076087 | N12: =IF(AND(J12<>0,J12<>"",I12<>0,I12<>""),L12-I12,"") -> -0.18478261 | P12: =IF(AND(O12<>"",O12<>0,L12<>"",L12<>0),-O12+L12,"") | Q12: =IF(AND(P12<>"",P12<>0,O12<>0,O12<>""),P12/O12,"")
F13: Кол-во чеков | I13: =IF(I12<>0,I9/I12,"") -> 130.03311 | J13: =G51 -> 92 | K13: =IF(AND(I13<>"",I13<>0,J13<>""),J13/I13,"") -> 0.7075121 | L13: =IF(SUMIF($G$25:$G$48,">=0",$R$25:$R$48)<>0,I13*G51/SUMIF($G$25:$G$48,">=0",$R$25:$R$48),"") -> 99.951599 | M13: =IF(AND(I13<>"",I13<>0,L13<>"",L13<>0),L13/I13,"") -> 0.76866267 | N13: =IF(AND(J13<>0,J13<>"",I13<>0,I13<>""),L13-I13,"") -> -30.081514 | P13: =IF(AND(O13<>"",O13<>0,L13<>"",L13<>0),-O13+L13,"") | Q13: =IF(AND(P13<>"",P13<>0,O13<>0,O13<>""),P13/O13,"")
F14: Кол-во смен план/отработано | I14: =График!AI29 -> 26 | J14: 26 | K14: =IF(AND(I14<>"",I14<>0,J14<>""),J14/I14,"") -> 1 | L14: =IF(SUMIF($D$25:$D$48,">=0",$P$25:$P$48),I51*I8/SUMIF($D$25:$D$48,">=0",$P$25:$P$48),"") -> 363.13333 | M14: =IF(AND(I14<>"",I14<>0,L14<>"",L14<>0),L14/I14,"") -> 13.966667 | N14: =IF(AND(J14<>0,J14<>"",I14<>0,I14<>""),L14-I14,"") -> 337.13333 | P14: =IF(AND(O14<>"",O14<>0,L14<>"",L14<>0),-O14+L14,"") | Q14: =IF(AND(P14<>"",P14<>0,O14<>0,O14<>""),P14/O14,"")
F15: Средние продажи в смену | I15: ='Ялта, Ленина, 18'!I15 -> 39178.2 | J15: =J8/J14 -> 27812.038 | K15: =IF(AND(I15<>"",I15<>0,J15<>""),J15/I15,"") -> 0.70988556 | L15: =J15 -> 27812.038 | M15: =IF(AND(I15<>"",I15<>0,L15<>"",L15<>0),L15/I15,"") -> 0.70988556 | N15: =IF(AND(J15<>0,J15<>"",I15<>0,I15<>""),L15-I15,"") -> -11366.162 | P15: =IF(AND(O15<>"",O15<>0,L15<>"",L15<>0),-O15+L15,"") | Q15: =IF(AND(P15<>"",P15<>0,O15<>0,O15<>""),P15/O15,"")
F16: Отставание/Перевыполнение | J16: =J8-I15*J14 -> -295520.2 | K16: =IF(AND(I16<>"",I16<>0,J16<>""),J16/I16,"") | L16: =J16 -> -295520.2 | M16: =IF(AND(I16<>"",I16<>0,L16<>"",L16<>0),L16/I16,"") | N16: =IF(AND(J16<>0,J16<>"",I16<>0,I16<>""),L16-I16,"") | P16: =IF(AND(O16<>"",O16<>0,L16<>"",L16<>0),-O16+L16,"") | Q16: =IF(AND(P16<>"",P16<>0,O16<>0,O16<>""),P16/O16,"") | S16: Подарочные сертификаты
F17: Трафик | I17: ='Ялта, Ленина, 18'!I17/График!AJ31*График!AJ29 -> 433.44371 | J17: =I51 -> 299 | K17: =IF(AND(I17<>"",I17<>0,J17<>""),J17/I17,"") -> 0.68982429 | L17: =J17/J14*I14 -> 299 | M17: =IF(AND(I17<>"",I17<>0,L17<>"",L17<>0),L17/I17,"") -> 0.68982429 | N17: =IF(AND(J17<>0,J17<>"",I17<>0,I17<>""),L17-I17,"") -> -134.44371 | P17: =IF(AND(O17<>"",O17<>0,L17<>"",L17<>0),-O17+L17,"") | Q17: =IF(AND(P17<>"",P17<>0,O17<>0,O17<>""),P17/O17,"")
K18: =IF(AND(I18<>"",I18<>0,J18<>""),J18/I18,"") | L18: =J18 -> 0 | M18: =IF(AND(I18<>"",I18<>0,L18<>"",L18<>0),L18/I18,"") | N18: =IF(AND(J18<>0,J18<>"",I18<>0,I18<>""),L18-I18,"") | O18: 0 | P18: =IF(AND(O18<>"",O18<>0,L18<>"",L18<>0),-O18+L18,"") | Q18: =IF(AND(P18<>"",P18<>0,O18<>0,O18<>""),P18/O18,"")
J19: =M51 -> 0 | K19: =IF(AND(I19<>"",I19<>0,J19<>""),J19/I19,"") | L19: =J19 -> 0 | M19: =IF(AND(I19<>"",I19<>0,L19<>"",L19<>0),L19/I19,"") | N19: =IF(AND(J19<>0,J19<>"",I19<>0,I19<>""),L19-I19,"") | O19: 0 | P19: =IF(AND(O19<>"",O19<>0,L19<>"",L19<>0),-O19+L19,"") | Q19: =IF(AND(P19<>"",P19<>0,O19<>0,O19<>""),P19/O19,"") | S19: =S18/I16 -> #DIV/0!
F20: Конверсия план/факт | I20: ='Ялта, Ленина, 18'!I20 -> 0.3 | J20: =N51 -> 0.30769231 | K20: =J20/I20 -> 1.025641 | L20: =IF(AND(K8<>0,I14<>0,I51<>0),(I51*N51+(I51/K8-I51)*I20)/(I51/K8),0) -> 0.30556845 | M20: =IF(AND(I20<>"",I20<>0,L20<>"",L20<>0),L20/I20,"") -> 1.0185615 | N20: =IF(AND(J20<>0,J20<>"",I20<>0,I20<>""),L20-I20,"") -> 0.005568453 | P20: =IF(AND(O20<>"",O20<>0,L20<>"",L20<>0),-O20+L20,"") | Q20: =IF(AND(P20<>"",P20<>0,O20<>0,O20<>""),P20/O20,"")
B22: Факт продаж за месяц | O22: % выполнения дневного плана | P22: Раcпределение плана по дням
B23: Дата | C23: День недели | D23: Выручка (руб) | E23: Кол-во единиц (шт.) | F23: Средняя стоимость изделия (руб.) | G23: Количество чеков (шт.) | H23: Средняя сумма чека (руб.) | I23: Трафик | J23: Длина чека (шт.) | K23: Запасной | L23: Запасной | M23: Запасной | N23: Конверсия (%) | P23: выручка, план | Q23: кол-во ед, план | R23: Кол-во чеков, план | S23: выручка, скорректир.план | T23: кол-во ед, скорр. план | U23: кол-во чеков, скорр. план | V23: Коэфф. Дня Недели | W23: Специфика месяца
B24: 1 | C24: 2 | D24: 3 | E24: 4 | F24: 5 | G24: 6 | H24: 7 | I24: 8 | J24: 9 | K24: 10 | L24: 11 | M24: 12 | N24: 13 | P24: 1 | Q24: 2 | R24: 3 | S24: 4 | T24: 5 | U24: 6 | V24: 10 | W24: 11
A25: 1 | B25: 45691 | C25: пн | D25: 13237 | E25: 4 | F25: =IF(AND(E25<>"",E25<>0),D25/E25,"") -> 3309.25 | G25: 3 | H25: =IF(AND(G25<>"",G25<>0),D25/G25,"") -> 4412.3333 | I25: 8 | J25: =IF(AND(G25<>"",G25<>0),E25/G25,"") -> 1.3333333 | N25: =IF(AND(I25<>"",I25<>0),G25/I25,"") -> 0.375 | O25: =D25/P25 -> 0.52053101 | P25: =$I$8*V25*W25/SUMPRODUCT($W$25:$W$56,$V$25:$V$56) -> 25429.801 | Q25: =$I$9*V25*W25/SUMPRODUCT($W$25:$W$56,$V$25:$V$56) -> 6.6206199 | R25: =IF($I$12="","",Q25/$I$12) -> 3.3103099 | S25: =IF(W25<>"",IF(D25<>"",D25,($I$8-SUM($S24:S$25))*V25*W25/SUMPRODUCT($W25:$W$56,$V25:$V$56)),"") -> 13237 | T25: =IF(W25<>"",IF(E25<>"",E25,($I$9-SUM($T24:T$25))*V25*W25/SUMPRODUCT($W25:$W$56,$V25:$V$56)),"") -> 4 | U25: =IF(W25<>"",IF($I$12<>"",IF(G25<>"",G25,($I$9/$I$12-SUM($U24:U$25))*V25*W25/SUMPRODUCT($W25:$W$56,$V25:$V$56)),""),"") -> 3 | V25: 0.8 | W25: 0.8
A26: 2 | B26: 45692 | C26: вт | D26: 41907 | E26: 9 | F26: =IF(AND(E26<>"",E26<>0),D26/E26,"") -> 4656.3333 | G26: 4 | H26: =IF(AND(G26<>"",G26<>0),D26/G26,"") -> 10476.75 | I26: 16 | J26: =IF(AND(G26<>"",G26<>0),E26/G26,"") -> 2.25 | N26: =IF(AND(I26<>"",I26<>0),G26/I26,"") -> 0.25 | O26: =D26/P26 -> 1.6479484 | P26: =$I$8*V26*W26/SUMPRODUCT($W$25:$W$55,$V$25:$V$55) -> 25429.801 | Q26: =$I$9*V26*W26/SUMPRODUCT($W$25:$W$55,$V$25:$V$55) -> 6.6206199 | R26: =IF($I$12="","",Q26/$I$12) -> 3.3103099 | S26: =IF(W26<>"",IF(D26<>"",D26,($I$8-SUM($S$25:S25))*V26*W26/SUMPRODUCT($W26:$W$55,$V26:$V$55)),"") -> 41907 | T26: =IF(W26<>"",IF(E26<>"",E26,($I$9-SUM($T$25:T25))*V26*W26/SUMPRODUCT($W26:$W$55,$V26:$V$55)),"") -> 9 | U26: =IF(W26<>"",IF($I$12<>"",IF(G26<>"",G26,($I$9/$I$12-SUM($U$25:U25))*V26*W26/SUMPRODUCT($W26:$W$55,$V26:$V$55)),""),"") -> 4 | V26: 0.8 | W26: 0.8
A27: 3 | B27: 45693 | C27: ср | D27: 15563 | E27: 3 | F27: =IF(AND(E27<>"",E27<>0),D27/E27,"") -> 5187.6667 | G27: 2 | H27: =IF(AND(G27<>"",G27<>0),D27/G27,"") -> 7781.5 | I27: 9 | J27: =IF(AND(G27<>"",G27<>0),E27/G27,"") -> 1.5 | N27: =IF(AND(I27<>"",I27<>0),G27/I27,"") -> 0.22222222 | O27: =D27/P27 -> 0.48355437 | P27: =$I$8*V27*W27/SUMPRODUCT($W$25:$W$55,$V$25:$V$55) -> 32184.592 | Q27: =$I$9*V27*W27/SUMPRODUCT($W$25:$W$55,$V$25:$V$55) -> 8.3792221 | R27: =IF($I$12="","",Q27/$I$12) -> 4.189611 | S27: =IF(W27<>"",IF(D27<>"",D27,($I$8-SUM($S$25:S26))*V27*W27/SUMPRODUCT($W27:$W$55,$V27:$V$55)),"") -> 15563 | T27: =IF(W27<>"",IF(E27<>"",E27,($I$9-SUM($T$25:T26))*V27*W27/SUMPRODUCT($W27:$W$55,$V27:$V$55)),"") -> 3 | U27: =IF(W27<>"",IF($I$12<>"",IF(G27<>"",G27,($I$9/$I$12-SUM($U$25:U26))*V27*W27/SUMPRODUCT($W27:$W$55,$V27:$V$55)),""),"") -> 2 | V27: 0.9 | W27: 0.9
A28: 4 | B28: 45694 | C28: чт | E28: 0 | F28: =IF(AND(E28<>"",E28<>0),D28/E28,"") | G28: 0 | H28: =IF(AND(G28<>"",G28<>0),D28/G28,"") | I28: 4 | J28: =IF(AND(G28<>"",G28<>0),E28/G28,"") | N28: =IF(AND(I28<>"",I28<>0),G28/I28,"") -> 0 | O28: =D28/P28 -> 0 | P28: =$I$8*V28*W28/SUMPRODUCT($W$25:$W$55,$V$25:$V$55) -> 57217.052 | Q28: =$I$9*V28*W28/SUMPRODUCT($W$25:$W$55,$V$25:$V$55) -> 14.896395 | R28: =IF($I$12="","",Q28/$I$12) -> 7.4481974 | S28: =IF(W28<>"",IF(D28<>"",D28,($I$8-SUM($S$25:S27))*V28*W28/SUMPRODUCT($W28:$W$55,$V28:$V$55)),"") -> 57987.792 | T28: =IF(W28<>"",IF(E28<>"",E28,($I$9-SUM($T$25:T27))*V28*W28/SUMPRODUCT($W28:$W$55,$V28:$V$55)),"") -> 0 | U28: =IF(W28<>"",IF($I$12<>"",IF(G28<>"",G28,($I$9/$I$12-SUM($U$25:U27))*V28*W28/SUMPRODUCT($W28:$W$55,$V28:$V$55)),""),"") -> 0 | V28: 1.2 | W28: 1.2
A29: 5 | B29: 45695 | C29: пт | D29: 5984 | E29: 2 | F29: =IF(AND(E29<>"",E29<>0),D29/E29,"") -> 2992 | G29: 2 | H29: =IF(AND(G29<>"",G29<>0),D29/G29,"") -> 2992 | I29: 9 | J29: =IF(AND(G29<>"",G29<>0),E29/G29,"") -> 1 | N29: =IF(AND(I29<>"",I29<>0),G29/I29,"") -> 0.22222222 | O29: =D29/P29 -> 0.08911317 | P29: =$I$8*V29*W29/SUMPRODUCT($W$25:$W$55,$V$25:$V$55) -> 67150.568 | Q29: =$I$9*V29*W29/SUMPRODUCT($W$25:$W$55,$V$25:$V$55) -> 17.482574 | R29: =IF($I$12="","",Q29/$I$12) -> 8.7412872 | S29: =IF(W29<>"",IF(D29<>"",D29,($I$8-SUM($S$25:S28))*V29*W29/SUMPRODUCT($W29:$W$55,$V29:$V$55)),"") -> 5984 | T29: =IF(W29<>"",IF(E29<>"",E29,($I$9-SUM($T$25:T28))*V29*W29/SUMPRODUCT($W29:$W$55,$V29:$V$55)),"") -> 2 | U29: =IF(W29<>"",IF($I$12<>"",IF(G29<>"",G29,($I$9/$I$12-SUM($U$25:U28))*V29*W29/SUMPRODUCT($W29:$W$55,$V29:$V$55)),""),"") -> 2 | V29: 1.3 | W29: 1.3
A30: 6 | B30: 45696 | C30: сб | D30: 13876 | E30: 3 | F30: =IF(AND(E30<>"",E30<>0),D30/E30,"") -> 4625.3333 | G30: 3 | H30: =IF(AND(G30<>"",G30<>0),D30/G30,"") -> 4625.3333 | I30: 4 | J30: =IF(AND(G30<>"",G30<>0),E30/G30,"") -> 1 | N30: =IF(AND(I30<>"",I30<>0),G30/I30,"") -> 0.75 | O30: =D30/P30 -> 0.15520967 | P30: =$I$8*V30*W30/SUMPRODUCT($W$25:$W$55,$V$25:$V$55) -> 89401.644 | Q30: =$I$9*V30*W30/SUMPRODUCT($W$25:$W$55,$V$25:$V$55) -> 23.275617 | R30: =IF($I$12="","",Q30/$I$12) -> 11.637808 | S30: =IF(W30<>"",IF(D30<>"",D30,($I$8-SUM($S$25:S29))*V30*W30/SUMPRODUCT($W30:$W$55,$V30:$V$55)),"") -> 13876 | T30: =IF(W30<>"",IF(E30<>"",E30,($I$9-SUM($T$25:T29))*V30*W30/SUMPRODUCT($W30:$W$55,$V30:$V$55)),"") -> 3 | U30: =IF(W30<>"",IF($I$12<>"",IF(G30<>"",G30,($I$9/$I$12-SUM($U$25:U29))*V30*W30/SUMPRODUCT($W30:$W$55,$V30:$V$55)),""),"") -> 3 | V30: 1.5 | W30: 1.5
A31: 7 | B31: 45697 | C31: вс | E31: 0 | F31: =IF(AND(E31<>"",E31<>0),D31/E31,"") | G31: 0 | H31: =IF(AND(G31<>"",G31<>0),D31/G31,"") | I31: 4 | J31: =IF(AND(G31<>"",G31<>0),E31/G31,"") | N31: =IF(AND(I31<>"",I31<>0),G31/I31,"") -> 0 | O31: =D31/P31 -> 0 | P31: =$I$8*V31*W31/SUMPRODUCT($W$25:$W$55,$V$25:$V$55) -> 39734.064 | Q31: =$I$9*V31*W31/SUMPRODUCT($W$25:$W$55,$V$25:$V$55) -> 10.344719 | R31: =IF($I$12="","",Q31/$I$12) -> 5.1723593 | S31: =IF(W31<>"",IF(D31<>"",D31,($I$8-SUM($S$25:S30))*V31*W31/SUMPRODUCT($W31:$W$55,$V31:$V$55)),"") -> 48124.481 | T31: =IF(W31<>"",IF(E31<>"",E31,($I$9-SUM($T$25:T30))*V31*W31/SUMPRODUCT($W31:$W$55,$V31:$V$55)),"") -> 0 | U31: =IF(W31<>"",IF($I$12<>"",IF(G31<>"",G31,($I$9/$I$12-SUM($U$25:U30))*V31*W31/SUMPRODUCT($W31:$W$55,$V31:$V$55)),""),"") -> 0 | V31: 1 | W31: 1
A32: 8 | B32: 45698 | C32: пн | D32: 17966 | E32: 4 | F32: =IF(AND(E32<>"",E32<>0),D32/E32,"") -> 4491.5 | G32: 2 | H32: =IF(AND(G32<>"",G32<>0),D32/G32,"") -> 8983 | I32: 12 | J32: =IF(AND(G32<>"",G32<>0),E32/G32,"") -> 2 | N32: =IF(AND(I32<>"",I32<>0),G32/I32,"") -> 0.16666667 | O32: =D32/P32 -> 0.55821742 | P32: =$I$8*V32*W32/SUMPRODUCT($W$25:$W$55,$V$25:$V$55) -> 32184.592 | Q32: =$I$9*V32*W32/SUMPRODUCT($W$25:$W$55,$V$25:$V$55) -> 8.3792221 | R32: =IF($I$12="","",Q32/$I$12) -> 4.189611 | S32: =IF(W32<>"",IF(D32<>"",D32,($I$8-SUM($S$25:S31))*V32*W32/SUMPRODUCT($W32:$W$55,$V32:$V$55)),"") -> 17966 | T32: =IF(W32<>"",IF(E32<>"",E32,($I$9-SUM($T$25:T31))*V32*W32/SUMPRODUCT($W32:$W$55,$V32:$V$55)),"") -> 4 | U32: =IF(W32<>"",IF($I$12<>"",IF(G32<>"",G32,($I$9/$I$12-SUM($U$25:U31))*V32*W32/SUMPRODUCT($W32:$W$55,$V32:$V$55)),""),"") -> 2 | V32: 0.9 | W32: 0.9
A33: 9 | B33: 45699 | C33: вт | D33: 12675 | E33: 3 | F33: =IF(AND(E33<>"",E33<>0),D33/E33,"") -> 4225 | G33: 2 | H33: =IF(AND(G33<>"",G33<>0),D33/G33,"") -> 6337.5 | I33: 10 | J33: =IF(AND(G33<>"",G33<>0),E33/G33,"") -> 1.5 | N33: =IF(AND(I33<>"",I33<>0),G33/I33,"") -> 0.2 | O33: =D33/P33 -> 0.39382199 | P33: =$I$8*V33*W33/SUMPRODUCT($W$25:$W$55,$V$25:$V$55) -> 32184.592 | Q33: =$I$9*V33*W33/SUMPRODUCT($W$25:$W$55,$V$25:$V$55) -> 8.3792221 | R33: =IF($I$12="","",Q33/$I$12) -> 4.189611 | S33: =IF(W33<>"",IF(D33<>"",D33,($I$8-SUM($S$25:S32))*V33*W33/SUMPRODUCT($W33:$W$55,$V33:$V$55)),"") -> 12675 | T33: =IF(W33<>"",IF(E33<>"",E33,($I$9-SUM($T$25:T32))*V33*W33/SUMPRODUCT($W33:$W$55,$V33:$V$55)),"") -> 3 | U33: =IF(W33<>"",IF($I$12<>"",IF(G33<>"",G33,($I$9/$I$12-SUM($U$25:U32))*V33*W33/SUMPRODUCT($W33:$W$55,$V33:$V$55)),""),"") -> 2 | V33: 0.9 | W33: 0.9
A34: 10 | B34: 45700 | C34: ср | D34: 21858 | E34: 5 | F34: =IF(AND(E34<>"",E34<>0),D34/E34,"") -> 4371.6 | G34: 3 | H34: =IF(AND(G34<>"",G34<>0),D34/G34,"") -> 7286 | I34: 8 | J34: =IF(AND(G34<>"",G34<>0),E34/G34,"") -> 1.6666667 | N34: =IF(AND(I34<>"",I34<>0),G34/I34,"") -> 0.375 | O34: =D34/P34 -> 0.67914485 | P34: =$I$8*V34*W34/SUMPRODUCT($W$25:$W$55,$V$25:$V$55) -> 32184.592 | Q34: =$I$9*V34*W34/SUMPRODUCT($W$25:$W$55,$V$25:$V$55) -> 8.3792221 | R34: =IF($I$12="","",Q34/$I$12) -> 4.189611 | S34: =IF(W34<>"",IF(D34<>"",D34,($I$8-SUM($S$25:S33))*V34*W34/SUMPRODUCT($W34:$W$55,$V34:$V$55)),"") -> 21858 | T34: =IF(W34<>"",IF(E33<>"",E33,($I$9-SUM($T$25:T33))*V34*W34/SUMPRODUCT($W34:$W$55,$V34:$V$55)),"") -> 3 | U34: =IF(W34<>"",IF($I$12<>"",IF(G34<>"",G34,($I$9/$I$12-SUM($U$25:U33))*V34*W34/SUMPRODUCT($W34:$W$55,$V34:$V$55)),""),"") -> 3 | V34: 0.9 | W34: 0.9
A35: 11 | B35: 45701 | C35: чт | D35: 71996 | E35: 16 | F35: =IF(AND(E35<>"",E35<>0),D35/E35,"") -> 4499.75 | G35: 7 | H35: =IF(AND(G35<>"",G35<>0),D35/G35,"") -> 10285.143 | I35: 18 | J35: =IF(AND(G35<>"",G35<>0),E35/G35,"") -> 2.2857143 | N35: =IF(AND(I35<>"",I35<>0),G35/I35,"") -> 0.38888889 | O35: =D35/P35 -> 1.8119465 | P35: =$I$8*V35*W35/SUMPRODUCT($W$25:$W$55,$V$25:$V$55) -> 39734.064 | Q35: =$I$9*V35*W35/SUMPRODUCT($W$25:$W$55,$V$25:$V$55) -> 10.344719 | R35: =IF($I$12="","",Q35/$I$12) -> 5.1723593 | S35: =IF(W35<>"",IF(D35<>"",D35,($I$8-SUM($S$25:S34))*V35*W35/SUMPRODUCT($W35:$W$55,$V35:$V$55)),"") -> 71996 | T35: =IF(W35<>"",IF(E35<>"",E35,($I$9-SUM($T$25:T34))*V35*W35/SUMPRODUCT($W35:$W$55,$V35:$V$55)),"") -> 16 | U35: =IF(W35<>"",IF($I$12<>"",IF(G35<>"",G35,($I$9/$I$12-SUM($U$25:U34))*V35*W35/SUMPRODUCT($W35:$W$55,$V35:$V$55)),""),"") -> 7 | V35: 1 | W35: 1
A36: 12 | B36: 45702 | C36: пт | D36: 56474 | E36: 15 | F36: =IF(AND(E36<>"",E36<>0),D36/E36,"") -> 3764.9333 | G36: 7 | H36: =IF(AND(G36<>"",G36<>0),D36/G36,"") -> 8067.7143 | I36: 20 | J36: =IF(AND(G36<>"",G36<>0),E36/G36,"") -> 2.1428571 | N36: =IF(AND(I36<>"",I36<>0),G36/I36,"") -> 0.35 | O36: =D36/P36 -> 1.4212994 | P36: =$I$8*V36*W36/SUMPRODUCT($W$25:$W$55,$V$25:$V$55) -> 39734.064 | Q36: =$I$9*V36*W36/SUMPRODUCT($W$25:$W$55,$V$25:$V$55) -> 10.344719 | R36: =IF($I$12="","",Q36/$I$12) -> 5.1723593 | S36: =IF(W36<>"",IF(D36<>"",D36,($I$8-SUM($S$25:S35))*V36*W36/SUMPRODUCT($W36:$W$55,$V36:$V$55)),"") -> 56474 | T36: =IF(W36<>"",IF(E36<>"",E36,($I$9-SUM($T$25:T35))*V36*W36/SUMPRODUCT($W36:$W$55,$V36:$V$55)),"") -> 15 | U36: =IF(W36<>"",IF($I$12<>"",IF(G36<>"",G36,($I$9/$I$12-SUM($U$25:U35))*V36*W36/SUMPRODUCT($W36:$W$55,$V36:$V$55)),""),"") -> 7 | V36: 1 | W36: 1
A37: 13 | B37: 45703 | C37: сб | D37: 63280 | E37: 14 | F37: =IF(AND(E37<>"",E37<>0),D37/E37,"") -> 4520 | G37: 6 | H37: =IF(AND(G37<>"",G37<>0),D37/G37,"") -> 10546.667 | I37: 25 | J37: =IF(AND(G37<>"",G37<>0),E37/G37,"") -> 2.3333333 | N37: =IF(AND(I37<>"",I37<>0),G37/I37,"") -> 0.24 | O37: =D37/P37 -> 1.3161886 | P37: =$I$8*V37*W37/SUMPRODUCT($W$25:$W$55,$V$25:$V$55) -> 48078.218 | Q37: =$I$9*V37*W37/SUMPRODUCT($W$25:$W$55,$V$25:$V$55) -> 12.517109 | R37: =IF($I$12="","",Q37/$I$12) -> 6.2585547 | S37: =IF(W37<>"",IF(D37<>"",D37,($I$8-SUM($S$25:S36))*V37*W37/SUMPRODUCT($W37:$W$55,$V37:$V$55)),"") -> 63280 | T37: =IF(W37<>"",IF(E37<>"",E37,($I$9-SUM($T$25:T36))*V37*W37/SUMPRODUCT($W37:$W$55,$V37:$V$55)),"") -> 14 | U37: =IF(W37<>"",IF($I$12<>"",IF(G37<>"",G37,($I$9/$I$12-SUM($U$25:U36))*V37*W37/SUMPRODUCT($W37:$W$55,$V37:$V$55)),""),"") -> 6 | V37: 1.1 | W37: 1.1
A38: 14 | B38: 45704 | C38: вс | D38: 21059 | E38: 5 | F38: =IF(AND(E38<>"",E38<>0),D38/E38,"") -> 4211.8 | G38: 2 | H38: =IF(AND(G38<>"",G38<>0),D38/G38,"") -> 10529.5 | I38: 4 | J38: =IF(AND(G38<>"",G38<>0),E38/G38,"") -> 2.5 | N38: =IF(AND(I38<>"",I38<>0),G38/I38,"") -> 0.5 | O38: =D38/P38 -> 0.43801541 | P38: =$I$8*V38*W38/SUMPRODUCT($W$25:$W$55,$V$25:$V$55) -> 48078.218 | Q38: =$I$9*V38*W38/SUMPRODUCT($W$25:$W$55,$V$25:$V$55) -> 12.517109 | R38: =IF($I$12="","",Q38/$I$12) -> 6.2585547 | S38: =IF(W38<>"",IF(D38<>"",D38,($I$8-SUM($S$25:S37))*V38*W38/SUMPRODUCT($W38:$W$55,$V38:$V$55)),"") -> 21059 | T38: =IF(W38<>"",IF(E38<>"",E38,($I$9-SUM($T$25:T37))*V38*W38/SUMPRODUCT($W38:$W$55,$V38:$V$55)),"") -> 5 | U38: =IF(W38<>"",IF($I$12<>"",IF(G38<>"",G38,($I$9/$I$12-SUM($U$25:U37))*V38*W38/SUMPRODUCT($W38:$W$55,$V38:$V$55)),""),"") -> 2 | V38: 1.1 | W38: 1.1
A39: 15 | B39: 45705 | C39: пн | D39: 29039 | E39: 7 | F39: =IF(AND(E39<>"",E39<>0),D39/E39,"") -> 4148.4286 | G39: 4 | H39: =IF(AND(G39<>"",G39<>0),D39/G39,"") -> 7259.75 | I39: 16 | J39: =IF(AND(G39<>"",G39<>0),E39/G39,"") -> 1.75 | N39: =IF(AND(I39<>"",I39<>0),G39/I39,"") -> 0.25 | O39: =D39/P39 -> 1.1419279 | P39: =$I$8*V39*W39/SUMPRODUCT($W$25:$W$55,$V$25:$V$55) -> 25429.801 | Q39: =$I$9*V39*W39/SUMPRODUCT($W$25:$W$55,$V$25:$V$55) -> 6.6206199 | R39: =IF($I$12="","",Q39/$I$12) -> 3.3103099 | S39: =IF(W39<>"",IF(D39<>"",D39,($I$8-SUM($S$25:S38))*V39*W39/SUMPRODUCT($W39:$W$55,$V39:$V$55)),"") -> 29039 | T39: =IF(W39<>"",IF(E39<>"",E39,($I$9-SUM($T$25:T38))*V39*W39/SUMPRODUCT($W39:$W$55,$V39:$V$55)),"") -> 7 | U39: =IF(W39<>"",IF($I$12<>"",IF(G39<>"",G39,($I$9/$I$12-SUM($U$25:U38))*V39*W39/SUMPRODUCT($W39:$W$55,$V39:$V$55)),""),"") -> 4 | V39: 0.8 | W39: 0.8
A40: 16 | B40: 45706 | C40: вт | D40: 37624 | E40: 9 | F40: =IF(AND(E40<>"",E40<>0),D40/E40,"") -> 4180.4444 | G40: 5 | H40: =IF(AND(G40<>"",G40<>0),D40/G40,"") -> 7524.8 | I40: 11 | J40: =IF(AND(G40<>"",G40<>0),E40/G40,"") -> 1.8 | N40: =IF(AND(I40<>"",I40<>0),G40/I40,"") -> 0.45454545 | O40: =D40/P40 -> 1.479524 | P40: =$I$8*V40*W40/SUMPRODUCT($W$25:$W$55,$V$25:$V$55) -> 25429.801 | Q40: =$I$9*V40*W40/SUMPRODUCT($W$25:$W$55,$V$25:$V$55) -> 6.6206199 | R40: =IF($I$12="","",Q40/$I$12) -> 3.3103099 | S40: =IF(W40<>"",IF(D40<>"",D40,($I$8-SUM($S$25:S39))*V40*W40/SUMPRODUCT($W40:$W$55,$V40:$V$55)),"") -> 37624 | T40: =IF(W40<>"",IF(E40<>"",E40,($I$9-SUM($T$25:T39))*V40*W40/SUMPRODUCT($W40:$W$55,$V40:$V$55)),"") -> 9 | U40: =IF(W40<>"",IF($I$12<>"",IF(G40<>"",G40,($I$9/$I$12-SUM($U$25:U39))*V40*W40/SUMPRODUCT($W40:$W$55,$V40:$V$55)),""),"") -> 5 | V40: 0.8 | W40: 0.8
A41: 17 | B41: 45707 | C41: ср | D41: 42905 | E41: 9 | F41: =IF(AND(E41<>"",E41<>0),D41/E41,"") -> 4767.2222 | G41: 5 | H41: =IF(AND(G41<>"",G41<>0),D41/G41,"") -> 8581 | I41: 17 | J41: =IF(AND(G41<>"",G41<>0),E41/G41,"") -> 1.8 | N41: =IF(AND(I41<>"",I41<>0),G41/I41,"") -> 0.29411765 | O41: =D41/P41 -> 1.6871937 | P41: =$I$8*V41*W41/SUMPRODUCT($W$25:$W$55,$V$25:$V$55) -> 25429.801 | Q41: =$I$9*V41*W41/SUMPRODUCT($W$25:$W$55,$V$25:$V$55) -> 6.6206199 | R41: =IF($I$12="","",Q41/$I$12) -> 3.3103099 | S41: =IF(W41<>"",IF(D41<>"",D41,($I$8-SUM($S$25:S40))*V41*W41/SUMPRODUCT($W41:$W$55,$V41:$V$55)),"") -> 42905 | T41: =IF(W41<>"",IF(E41<>"",E41,($I$9-SUM($T$25:T40))*V41*W41/SUMPRODUCT($W41:$W$55,$V41:$V$55)),"") -> 9 | U41: =IF(W41<>"",IF($I$12<>"",IF(G41<>"",G41,($I$9/$I$12-SUM($U$25:U40))*V41*W41/SUMPRODUCT($W41:$W$55,$V41:$V$55)),""),"") -> 5 | V41: 0.8 | W41: 0.8
A42: 18 | B42: 45708 | C42: чт | D42: 66400 | E42: 16 | F42: =IF(AND(E42<>"",E42<>0),D42/E42,"") -> 4150 | G42: 9 | H42: =IF(AND(G42<>"",G42<>0),D42/G42,"") -> 7377.7778 | I42: 20 | J42: =IF(AND(G42<>"",G42<>0),E42/G42,"") -> 1.7777778 | N42: =IF(AND(I42<>"",I42<>0),G42/I42,"") -> 0.45 | O42: =D42/P42 -> 2.063099 | P42: =$I$8*V42*W42/SUMPRODUCT($W$25:$W$55,$V$25:$V$55) -> 32184.592 | Q42: =$I$9*V42*W42/SUMPRODUCT($W$25:$W$55,$V$25:$V$55) -> 8.3792221 | R42: =IF($I$12="","",Q42/$I$12) -> 4.189611 | S42: =IF(W42<>"",IF(D42<>"",D42,($I$8-SUM($S$25:S41))*V42*W42/SUMPRODUCT($W42:$W$55,$V42:$V$55)),"") -> 66400 | T42: =IF(W42<>"",IF(E42<>"",E42,($I$9-SUM($T$25:T41))*V42*W42/SUMPRODUCT($W42:$W$55,$V42:$V$55)),"") -> 16 | U42: =IF(W42<>"",IF($I$12<>"",IF(G42<>"",G42,($I$9/$I$12-SUM($U$25:U41))*V42*W42/SUMPRODUCT($W42:$W$55,$V42:$V$55)),""),"") -> 9 | V42: 0.9 | W42: 0.9
A43: 19 | B43: 45709 | C43: пт | D43: 28558 | E43: 5 | F43: =IF(AND(E43<>"",E43<>0),D43/E43,"") -> 5711.6 | G43: 2 | H43: =IF(AND(G43<>"",G43<>0),D43/G43,"") -> 14279 | I43: 7 | J43: =IF(AND(G43<>"",G43<>0),E43/G43,"") -> 2.5 | N43: =IF(AND(I43<>"",I43<>0),G43/I43,"") -> 0.28571429 | O43: =D43/P43 -> 0.887319 | P43: =$I$8*V43*W43/SUMPRODUCT($W$25:$W$55,$V$25:$V$55) -> 32184.592 | Q43: =$I$9*V43*W43/SUMPRODUCT($W$25:$W$55,$V$25:$V$55) -> 8.3792221 | R43: =IF($I$12="","",Q43/$I$12) -> 4.189611 | S43: =IF(W43<>"",IF(D43<>"",D43,($I$8-SUM($S$25:S42))*V43*W43/SUMPRODUCT($W43:$W$55,$V43:$V$55)),"") -> 28558 | T43: =IF(W43<>"",IF(E43<>"",E43,($I$9-SUM($T$25:T42))*V43*W43/SUMPRODUCT($W43:$W$55,$V43:$V$55)),"") -> 5 | U43: =IF(W43<>"",IF($I$12<>"",IF(G43<>"",G43,($I$9/$I$12-SUM($U$25:U42))*V43*W43/SUMPRODUCT($W43:$W$55,$V43:$V$55)),""),"") -> 2 | V43: 0.9 | W43: 0.9
A44: 20 | B44: 45710 | C44: сб | D44: 22350 | E44: 6 | F44: =IF(AND(E44<>"",E44<>0),D44/E44,"") -> 3725 | G44: 4 | H44: =IF(AND(G44<>"",G44<>0),D44/G44,"") -> 5587.5 | I44: 15 | J44: =IF(AND(G44<>"",G44<>0),E44/G44,"") -> 1.5 | N44: =IF(AND(I44<>"",I44<>0),G44/I44,"") -> 0.26666667 | O44: =D44/P44 -> 0.56248966 | P44: =$I$8*V44*W44/SUMPRODUCT($W$25:$W$55,$V$25:$V$55) -> 39734.064 | Q44: =$I$9*V44*W44/SUMPRODUCT($W$25:$W$55,$V$25:$V$55) -> 10.344719 | R44: =IF($I$12="","",Q44/$I$12) -> 5.1723593 | S44: =IF(W44<>"",IF(D44<>"",D44,($I$8-SUM($S$25:S43))*V44*W44/SUMPRODUCT($W44:$W$55,$V44:$V$55)),"") -> 22350 | T44: =IF(W44<>"",IF(E44<>"",E44,($I$9-SUM($T$25:T43))*V44*W44/SUMPRODUCT($W44:$W$55,$V44:$V$55)),"") -> 6 | U44: =IF(W44<>"",IF($I$12<>"",IF(G44<>"",G44,($I$9/$I$12-SUM($U$25:U43))*V44*W44/SUMPRODUCT($W44:$W$55,$V44:$V$55)),""),"") -> 4 | V44: 1 | W44: 1
A45: 21 | B45: 45711 | C45: вс | D45: 56582 | E45: 13 | F45: =IF(AND(E45<>"",E45<>0),D45/E45,"") -> 4352.4615 | G45: 9 | H45: =IF(AND(G45<>"",G45<>0),D45/G45,"") -> 6286.8889 | I45: 24 | J45: =IF(AND(G45<>"",G45<>0),E45/G45,"") -> 1.4444444 | N45: =IF(AND(I45<>"",I45<>0),G45/I45,"") -> 0.375 | O45: =D45/P45 -> 1.4240174 | P45: =$I$8*V45*W45/SUMPRODUCT($W$25:$W$55,$V$25:$V$55) -> 39734.064 | Q45: =$I$9*V45*W45/SUMPRODUCT($W$25:$W$55,$V$25:$V$55) -> 10.344719 | R45: =IF($I$12="","",Q45/$I$12) -> 5.1723593 | S45: =IF(W45<>"",IF(D45<>"",D45,($I$8-SUM($S$25:S44))*V45*W45/SUMPRODUCT($W45:$W$55,$V45:$V$55)),"") -> 56582 | T45: =IF(W45<>"",IF(E45<>"",E45,($I$9-SUM($T$25:T44))*V45*W45/SUMPRODUCT($W45:$W$55,$V45:$V$55)),"") -> 13 | U45: =IF(W45<>"",IF($I$12<>"",IF(G45<>"",G45,($I$9/$I$12-SUM($U$25:U44))*V45*W45/SUMPRODUCT($W45:$W$55,$V45:$V$55)),""),"") -> 9 | V45: 1 | W45: 1
A46: 22 | B46: 45712 | C46: пн | D46: 3892 | E46: 1 | F46: =IF(AND(E46<>"",E46<>0),D46/E46,"") -> 3892 | G46: 1 | H46: =IF(AND(G46<>"",G46<>0),D46/G46,"") -> 3892 | I46: 5 | J46: =IF(AND(G46<>"",G46<>0),E46/G46,"") -> 1 | N46: =IF(AND(I46<>"",I46<>0),G46/I46,"") -> 0.2 | O46: =D46/P46 -> 0.15304878 | P46: =$I$8*V46*W46/SUMPRODUCT($W$25:$W$55,$V$25:$V$55) -> 25429.801 | Q46: =$I$9*V46*W46/SUMPRODUCT($W$25:$W$55,$V$25:$V$55) -> 6.6206199 | R46: =IF($I$12="","",Q46/$I$12) -> 3.3103099 | S46: =IF(W46<>"",IF(D46<>"",D46,($I$8-SUM($S$25:S45))*V46*W46/SUMPRODUCT($W46:$W$55,$V46:$V$55)),"") -> 3892 | T46: =IF(W46<>"",IF(E46<>"",E46,($I$9-SUM($T$25:T45))*V46*W46/SUMPRODUCT($W46:$W$55,$V46:$V$55)),"") -> 1 | U46: =IF(W46<>"",IF($I$12<>"",IF(G46<>"",G46,($I$9/$I$12-SUM($U$25:U45))*V46*W46/SUMPRODUCT($W46:$W$55,$V46:$V$55)),""),"") -> 1 | V46: 0.8 | W46: 0.8
... A50: 26 | B50: 45716 | C50: пт | D50: 20159 | E50: 5 | F50: =IF(AND(E50<>"",E50<>0),D50/E50,"") -> 4031.8 | G50: 5 | H50: =IF(AND(G50<>"",G50<>0),D50/G50,"") -> 4031.8 | I50: 10 | J50: =IF(AND(G50<>"",G50<>0),E50/G50,"") -> 1 | N50: =IF(AND(I50<>"",I50<>0),G50/I50,"") -> 0.5 | O50: =D50/P50 -> 0.50734805 | P50: =$I$8*V50*W50/SUMPRODUCT($W$25:$W$55,$V$25:$V$55) -> 39734.064 | Q50: =$I$9*V50*W50/SUMPRODUCT($W$25:$W$55,$V$25:$V$55) -> 10.344719 | R50: =IF($I$12="","",Q50/$I$12) -> 5.1723593 | S50: =IF(W50<>"",IF(D50<>"",D50,($I$8-SUM($S$25:S49))*V50*W50/SUMPRODUCT($W50:$W$55,$V50:$V$55)),"") -> 20159 | T50: =IF(W50<>"",IF(E50<>"",E50,($I$9-SUM($T$25:T49))*V50*W50/SUMPRODUCT($W50:$W$55,$V50:$V$55)),"") -> 5 | U50: =IF(W50<>"",IF($I$12<>"",IF(G50<>"",G50,($I$9/$I$12-SUM($U$25:U49))*V50*W50/SUMPRODUCT($W50:$W$55,$V50:$V$55)),""),"") -> 5 | V50: 1 | W50: 1
B51: итого | D51: =SUM(D25:D50) -> 723113 | E51: =SUM(E25:E50) -> 167 | F51: =IF(AND(E51<>"",E51<>0),D51/E51,"") -> 4330.018 | G51: =SUM(G25:G50) -> 92 | H51: =IF(AND(G51<>"",G51<>0),D51/G51,"") -> 7859.9239 | I51: =SUM(I25:I50) -> 299 | J51: =IF(AND(G51<>"",G51<>0),E51/G51,"") -> 1.8152174 | K51: =SUM(K25:K48) -> 0 | L51: =SUM(L25:L48) -> 0 | M51: =SUM(M25:M48) -> 0 | N51: =IF(AND(I51<>"",I51<>0),G51/I51,"") -> 0.30769231 | O51: =D51/P51 -> 0.75388641 | P51: =SUM(P25:P49) -> 959180.31 | Q51: =SUM(Q25:Q49) -> 249.72151 | R51: =SUM(R25:R49) -> 124.86075 | S51: =SUM(S25:S49) -> 809066.27 | T51: =SUM(T25:T49) -> 160 | U51: =SUM(U25:U49) -> 87
D52: =SUMIF(D25:D48,"",P25:P48)+D51 -> 820064.12

Sheet ПК1
B1: =TODAY()-1 -> 46080
B2: (отчетная дата) | J2: ЕЖЕДНЕВНЫЙ ОТЧЕТ О ПРОДАЖАХ
B3: Осталось до выполнения плана!!! | J3: =График!B30 -> 0
C4: =I8-D50 -> 0 | E4: =IF(I8<>0, C4/I8, 0) -> 0
F6: Целевые показатели
F7: Показатель | I7: План | J7: Факт | K7: % выполнения | L7: Прогноз выполнения | M7: % выполнения по прогнозу | N7: Отклонение | O7: Факт аналогичного месяца прошлого года | P7: Отклонение LFL
F8: Выручка | I8: ='Ялта, Ленина, 18'!I8/График!AJ31*График!AJ30 -> 0 | J8: =D50 -> 0 | K8: =J8/I8 -> #DIV/0! | L8: =IF(SUMIF($D$25:$D$49,">=0",$P$25:$P$49)<>0,I8*D50/SUMIF($D$25:$D$49,">=0",$P$25:$P$49),0) -> 0 | M8: =IF(AND(I8<>"",I8<>0,L8<>"",L8<>0),L8/I8,"") | N8: =IF(AND(J8<>0, J8<>"", I8<>0, I8<>""), L8-I8, "") | P8: =IF(AND(O8<>"", O8<>0, L8<>"", L8<>0), -O8+L8, "") | Q8: =IF(AND(P8<>"", P8<>0, O8<>0, O8<>""), P8/O8, "")
F9: Кол-во изделий | I9: =I8/I11 -> 0 | J9: =E50 -> 0 | K9: =IF(AND(I9<>"", I9<>0, J9<>""), J9/I9, "") | L9: =J9 -> 0 | M9: =IF(AND(I9<>"",I9<>0,L9<>"",L9<>0),L9/I9,"") | N9: =IF(AND(J9<>0, J9<>"", I9<>0, I9<>""), L9-I9, "") | O9: =O8/O11 -> #DIV/0! | P9: =IF(AND(O9<>"", O9<>0, L9<>"", L9<>0), -O9+L9, "") -> #DIV/0! | Q9: =IF(AND(P9<>"", P9<>0, O9<>0, O9<>""), P9/O9, "") -> #DIV/0!
F10: Средний чек | I10: =I11*I12 -> 7682 | J10: =H50 | K10: =IF(AND(I10<>"", I10<>0, J10<>""), J10/I10, "") | L10: =J10 | M10: =IF(AND(I10<>"",I10<>0,L10<>"",L10<>0),L10/I10,"") | N10: =IF(AND(J10<>0, J10<>"", I10<>0, I10<>""), L10-I10, "") | O10: =O11*O12 -> 0 | P10: =IF(AND(O10<>"", O10<>0, L10<>"", L10<>0), -O10+L10, "") | Q10: =IF(AND(P10<>"", P10<>0, O10<>0, O10<>""), P10/O10, "")
F11: Средняя стоимость изделия | I11: ='Ялта, Ленина, 18'!I11 -> 3841 | J11: =F50 | K11: =IF(AND(I11<>"", I11<>0, J11<>""), J11/I11, "") | L11: =J11 | M11: =IF(AND(I11<>"",I11<>0,L11<>"",L11<>0),L11/I11,"") | N11: =IF(AND(J11<>0, J11<>"", I11<>0, I11<>""), L11-I11, "") | P11: =IF(AND(O11<>"", O11<>0, L11<>"", L11<>0), -O11+L11, "") | Q11: =IF(AND(P11<>"", P11<>0, O11<>0, O11<>""), P11/O11, "")
F12: Длина чека | I12: ='Ялта, Ленина, 18'!I12 -> 2 | J12: =J50 | K12: =IF(AND(I12<>"", I12<>0, J12<>""), J12/I12, "") | L12: =J12 | M12: =IF(AND(I12<>"",I12<>0,L12<>"",L12<>0),L12/I12,"") | N12: =IF(AND(J12<>0, J12<>"", I12<>0, I12<>""), L12-I12, "") | P12: =IF(AND(O12<>"", O12<>0, L12<>"", L12<>0), -O12+L12, "") | Q12: =IF(AND(P12<>"", P12<>0, O12<>0, O12<>""), P12/O12, "")
F13: Кол-во чеков | I13: =IF(I12<>0, I9/I12, "") -> 0 | J13: =G50 -> 0 | K13: =IF(AND(I13<>"", I13<>0, J13<>""), J13/I13, "") | L13: =J13 -> 0 | M13: =IF(AND(I13<>"",I13<>0,L13<>"",L13<>0),L13/I13,"") | N13: =IF(AND(J13<>0, J13<>"", I13<>0, I13<>""), L13-I13, "") | P13: =IF(AND(O13<>"", O13<>0, L13<>"", L13<>0), -O13+L13, "") | Q13: =IF(AND(P13<>"", P13<>0, O13<>0, O13<>""), P13/O13, "")
F14: Кол-во смен план/отработано | I14: =График!AI30 -> 0 | K14: =IF(AND(I14<>"", I14<>0, J14<>""), J14/I14, "") | L14: =J14 -> 0 | M14: =IF(AND(I14<>"",I14<>0,L14<>"",L14<>0),L14/I14,"") | N14: =IF(AND(J14<>0, J14<>"", I14<>0, I14<>""), L14-I14, "") | P14: =IF(AND(O14<>"", O14<>0, L14<>"", L14<>0), -O14+L14, "") | Q14: =IF(AND(P14<>"", P14<>0, O14<>0, O14<>""), P14/O14, "")
F15: Средние продажи в смену | I15: ='Ялта, Ленина, 18'!I15 -> 39178.2 | J15: =J8/J14 -> #DIV/0! | K15: =IF(AND(I15<>"", I15<>0, J15<>""), J15/I15, "") -> #DIV/0! | L15: =J15 -> #DIV/0! | M15: =IF(AND(I15<>"",I15<>0,L15<>"",L15<>0),L15/I15,"") -> #DIV/0! | N15: =IF(AND(J15<>0, J15<>"", I15<>0, I15<>""), L15-I15, "") -> #DIV/0! | P15: =IF(AND(O15<>"", O15<>0, L15<>"", L15<>0), -O15+L15, "") -> #DIV/0! | Q15: =IF(AND(P15<>"", P15<>0, O15<>0, O15<>""), P15/O15, "") -> #DIV/0!
F16: Отставание/Перевыполнение | J16: =J8-I15*J14 -> 0 | K16: =IF(AND(I16<>"", I16<>0, J16<>""), J16/I16, "") | L16: =J16 -> 0 | M16: =IF(AND(I16<>"",I16<>0,L16<>"",L16<>0),L16/I16,"") | N16: =IF(AND(J16<>0, J16<>"", I16<>0, I16<>""), L16-I16, "") | P16: =IF(AND(O16<>"", O16<>0, L16<>"", L16<>0), -O16+L16, "") | Q16: =IF(AND(P16<>"", P16<>0, O16<>0, O16<>""), P16/O16, "") | S16: Подарочные сертификаты
F17: Трафик | I17: ='Ялта, Ленина, 18'!I17/График!AJ31*График!AJ30 -> 0 | J17: =I50 -> 0 | K17: =IF(AND(I17<>"", I17<>0, J17<>""), J17/I17, "") | L17: =J17/J14*I14 -> #DIV/0! | M17: =IF(AND(I17<>"",I17<>0,L17<>"",L17<>0),L17/I17,"") -> #DIV/0! | N17: =IF(AND(J17<>0, J17<>"", I17<>0, I17<>""), L17-I17, "") | P17: =IF(AND(O17<>"", O17<>0, L17<>"", L17<>0), -O17+L17, "") -> #DIV/0! | Q17: =IF(AND(P17<>"", P17<>0, O17<>0, O17<>""), P17/O17, "") -> #DIV/0!
K18: =IF(AND(I18<>"", I18<>0, J18<>""), J18/I18, "") | L18: =J18 -> 0 | M18: =IF(AND(I18<>"",I18<>0,L18<>"",L18<>0),L18/I18,"") | N18: =IF(AND(J18<>0, J18<>"", I18<>0, I18<>""), L18-I18, "") | O18: 0 | P18: =IF(AND(O18<>"", O18<>0, L18<>"", L18<>0), -O18+L18, "") | Q18: =IF(AND(P18<>"", P18<>0, O18<>0, O18<>""), P18/O18, "") | S18: 3000
J19: =M50 -> 0 | K19: =IF(AND(I19<>"", I19<>0, J19<>""), J19/I19, "") | L19: =J19 -> 0 | M19: =IF(AND(I19<>"",I19<>0,L19<>"",L19<>0),L19/I19,"") | N19: =IF(AND(J19<>0, J19<>"", I19<>0, I19<>""), L19-I19, "") | O19: 0 | P19: =IF(AND(O19<>"", O19<>0, L19<>"", L19<>0), -O19+L19, "") | Q19: =IF(AND(P19<>"", P19<>0, O19<>0, O19<>""), P19/O19, "") | S19: =S18/I16 -> #DIV/0!
F20: Конверсия план/факт | I20: ='Ялта, Ленина, 18'!I20 -> 0.3 | J20: =N50 | K20: =J20/I20 -> #VALUE! | L20: =IF(AND(K8<>0,I14<>0,I50<>0),(I50*N50+(I50/K8-I50)*I20)/(I50/K8),0) -> #DIV/0! | M20: =IF(AND(I20<>"",I20<>0,L20<>"",L20<>0),L20/I20,"") -> #DIV/0! | N20: =IF(AND(J20<>0, J20<>"", I20<>0, I20<>""), L20-I20, "") | P20: =IF(AND(O20<>"", O20<>0, L20<>"", L20<>0), -O20+L20, "") -> #DIV/0! | Q20: =IF(AND(P20<>"", P20<>0, O20<>0, O20<>""), P20/O20, "") -> #DIV/0!
B22: Факт продаж за месяц | O22: % выполнения дневного плана | P22: Раcпределение плана по дням
B23: Дата | C23: День недели | D23: Выручка (руб) | E23: Кол-во единиц (шт.) | F23: Средняя стоимость изделия (руб.) | G23: Количество чеков (шт.) | H23: Средняя сумма чека (руб.) | I23: Трафик | J23: Длина чека (шт.) | K23: Запасной | L23: Запасной | M23: Запасной | N23: Конверсия (%) | P23: выручка, план | Q23: кол-во ед, план | R23: Кол-во чеков, план | S23: выручка, скорректир.план | T23: кол-во ед, скорр. план | U23: кол-во чеков, скорр. план | V23: Коэфф. Дня Недели | W23: Специфика месяца
B24: 1 | C24: 2 | D24: 3 | E24: в | F24: 5 | G24: 6 | H24: 7 | I24: 8 | J24: 9 | K24: 10 | L24: 11 | M24: 12 | N24: 13 | P24: 1 | Q24: 2 | R24: 3 | S24: 4 | T24: 5 | U24: 6 | V24: 10 | W24: 11
A25: 1 | F25: =IF(AND(E25<>"",E25<>0),D25/E25,"") | H25: =IF(AND(G25<>"",G25<>0),D25/G25,"") | J25: =IF(AND(G25<>"",G25<>0),E25/G25,"") | N25: =IF(AND(I25<>"",I25<>0),G25/I25,"") | O25: =D25/P25 -> #DIV/0! | P25: =$I$8*V25*W25/SUMPRODUCT($W$25:$W$60,$V$25:$V$60) -> 0 | Q25: =$I$9*V25*W25/SUMPRODUCT($W$25:$W$60,$V$25:$V$60) -> 0 | R25: =IF($I$12="","",Q25/$I$12) -> 0 | S25: =IF(W25<>"",IF(D25<>"",D25,($I$8-SUM($S24:S$25))*V25*W25/SUMPRODUCT($W25:$W$60,$V25:$V$60)),"") -> #REF! | T25: =IF(W25<>"",IF(E25<>"",E25,($I$9-SUM($T24:T$25))*V25*W25/SUMPRODUCT($W25:$W$60,$V25:$V$60)),"") -> #REF! | U25: =IF(W25<>"",IF($I$12<>"",IF(G25<>"",G25,($I$9/$I$12-SUM($U24:U$25))*V25*W25/SUMPRODUCT($W25:$W$60,$V25:$V$60)),""),"") -> #REF! | V25: 1 | W25: 1
A26: 2 | F26: =IF(AND(E26<>"",E26<>0),D26/E26,"") | H26: =IF(AND(G26<>"",G26<>0),D26/G26,"") | J26: =IF(AND(G26<>"",G26<>0),E26/G26,"") | N26: =IF(AND(I26<>"",I26<>0),G26/I26,"") | O26: =D26/P26 -> #DIV/0! | P26: =$I$8*V26*W26/SUMPRODUCT($W$25:$W$60,$V$25:$V$60) -> 0 | Q26: =$I$9*V26*W26/SUMPRODUCT($W$25:$W$60,$V$25:$V$60) -> 0 | R26: =IF($I$12="","",Q26/$I$12) -> 0 | S26: =IF(W26<>"",IF(D26<>"",D26,($I$8-SUM($S$25:S25))*V26*W26/SUMPRODUCT($W26:$W$60,$V26:$V$60)),"") -> #REF! | T26: =IF(W26<>"",IF(E26<>"",E26,($I$9-SUM($T$25:T25))*V26*W26/SUMPRODUCT($W26:$W$60,$V26:$V$60)),"") -> #REF! | U26: =IF(W26<>"",IF($I$12<>"",IF(G26<>"",G26,($I$9/$I$12-SUM($U$25:U25))*V26*W26/SUMPRODUCT($W26:$W$60,$V26:$V$60)),""),"") -> #REF! | V26: 1 | W26: 1
A27: 3 | F27: =IF(AND(E27<>"",E27<>0),D27/E27,"") | H27: =IF(AND(G27<>"",G27<>0),D27/G27,"") | J27: =IF(AND(G27<>"",G27<>0),E27/G27,"") | N27: =IF(AND(I27<>"",I27<>0),G27/I27,"") | O27: =D27/P27 -> #DIV/0! | P27: =$I$8*V27*W27/SUMPRODUCT($W$25:$W$60,$V$25:$V$60) -> 0 | Q27: =$I$9*V27*W27/SUMPRODUCT($W$25:$W$60,$V$25:$V$60) -> 0 | R27: =IF($I$12="","",Q27/$I$12) -> 0 | S27: =IF(W27<>"",IF(D27<>"",D27,($I$8-SUM($S$25:S26))*V27*W27/SUMPRODUCT($W27:$W$60,$V27:$V$60)),"") -> #REF! | T27: =IF(W27<>"",IF(E27<>"",E27,($I$9-SUM($T$25:T26))*V27*W27/SUMPRODUCT($W27:$W$60,$V27:$V$60)),"") -> #REF! | U27: =IF(W27<>"",IF($I$12<>"",IF(G27<>"",G27,($I$9/$I$12-SUM($U$25:U26))*V27*W27/SUMPRODUCT($W27:$W$60,$V27:$V$60)),""),"") -> #REF! | V27: 1 | W27: 1
A28: 4 | F28: =IF(AND(E28<>"",E28<>0),D28/E28,"") | H28: =IF(AND(G28<>"",G28<>0),D28/G28,"") | J28: =IF(AND(G28<>"",G28<>0),E28/G28,"") | N28: =IF(AND(I28<>"",I28<>0),G28/I28,"") | O28: =D28/P28 -> #DIV/0! | P28: =$I$8*V28*W28/SUMPRODUCT($W$25:$W$60,$V$25:$V$60) -> 0 | Q28: =$I$9*V28*W28/SUMPRODUCT($W$25:$W$60,$V$25:$V$60) -> 0 | R28: =IF($I$12="","",Q28/$I$12) -> 0 | S28: =IF(W28<>"",IF(D28<>"",D28,($I$8-SUM($S$25:S27))*V28*W28/SUMPRODUCT($W28:$W$60,$V28:$V$60)),"") -> #REF! | T28: =IF(W28<>"",IF(E28<>"",E28,($I$9-SUM($T$25:T27))*V28*W28/SUMPRODUCT($W28:$W$60,$V28:$V$60)),"") -> #REF! | U28: =IF(W28<>"",IF($I$12<>"",IF(G28<>"",G28,($I$9/$I$12-SUM($U$25:U27))*V28*W28/SUMPRODUCT($W28:$W$60,$V28:$V$60)),""),"") -> #REF! | V28: 1 | W28: 1
A29: 4 | F29: =IF(AND(E29<>"",E29<>0),D29/E29,"") | H29: =IF(AND(G29<>"",G29<>0),D29/G29,"") | J29: =IF(AND(G29<>"",G29<>0),E29/G29,"") | N29: =IF(AND(I29<>"",I29<>0),G29/I29,"") | O29: =D29/P29 -> #DIV/0! | P29: =$I$8*V29*W29/SUMPRODUCT($W$25:$W$60,$V$25:$V$60) -> 0 | Q29: =$I$9*V29*W29/SUMPRODUCT($W$25:$W$60,$V$25:$V$60) -> 0 | R29: =IF($I$12="","",Q29/$I$12) -> 0 | S29: =IF(W29<>"",IF(D29<>"",D29,($I$8-SUM($S$25:S28))*V29*W29/SUMPRODUCT($W29:$W$60,$V29:$V$60)),"") -> #REF! | T29: =IF(W29<>"",IF(E29<>"",E29,($I$9-SUM($T$25:T28))*V29*W29/SUMPRODUCT($W29:$W$60,$V29:$V$60)),"") -> #REF! | U29: =IF(W29<>"",IF($I$12<>"",IF(G29<>"",G29,($I$9/$I$12-SUM($U$25:U28))*V29*W29/SUMPRODUCT($W29:$W$60,$V29:$V$60)),""),"") -> #REF! | V29: 1 | W29: 1
A30: 4 | F30: =IF(AND(E30<>"",E30<>0),D30/E30,"") | H30: =IF(AND(G30<>"",G30<>0),D30/G30,"") | J30: =IF(AND(G30<>"",G30<>0),E30/G30,"") | N30: =IF(AND(I30<>"",I30<>0),G30/I30,"") | O30: =D30/P30 -> #DIV/0! | P30: =$I$8*V30*W30/SUMPRODUCT($W$25:$W$60,$V$25:$V$60) -> 0 | Q30: =$I$9*V30*W30/SUMPRODUCT($W$25:$W$60,$V$25:$V$60) -> 0 | R30: =IF($I$12="","",Q30/$I$12) -> 0 | S30: =IF(W30<>"",IF(D30<>"",D30,($I$8-SUM($S$25:S29))*V30*W30/SUMPRODUCT($W30:$W$60,$V30:$V$60)),"") -> #REF! | T30: =IF(W30<>"",IF(E30<>"",E30,($I$9-SUM($T$25:T29))*V30*W30/SUMPRODUCT($W30:$W$60,$V30:$V$60)),"") -> #REF! | U30: =IF(W30<>"",IF($I$12<>"",IF(G30<>"",G30,($I$9/$I$12-SUM($U$25:U29))*V30*W30/SUMPRODUCT($W30:$W$60,$V30:$V$60)),""),"") -> #REF! | V30: 1 | W30: 1
A31: 4 | F31: =IF(AND(E31<>"",E31<>0),D31/E31,"") | H31: =IF(AND(G31<>"",G31<>0),D31/G31,"") | J31: =IF(AND(G31<>"",G31<>0),E31/G31,"") | N31: =IF(AND(I31<>"",I31<>0),G31/I31,"") | O31: =D31/P31 -> #DIV/0! | P31: =$I$8*V31*W31/SUMPRODUCT($W$25:$W$60,$V$25:$V$60) -> 0 | Q31: =$I$9*V31*W31/SUMPRODUCT($W$25:$W$60,$V$25:$V$60) -> 0 | R31: =IF($I$12="","",Q31/$I$12) -> 0 | S31: =IF(W31<>"",IF(D31<>"",D31,($I$8-SUM($S$25:S30))*V31*W31/SUMPRODUCT($W31:$W$60,$V31:$V$60)),"") -> #REF! | T31: =IF(W31<>"",IF(E31<>"",E31,($I$9-SUM($T$25:T30))*V31*W31/SUMPRODUCT($W31:$W$60,$V31:$V$60)),"") -> #REF! | U31: =IF(W31<>"",IF($I$12<>"",IF(G31<>"",G31,($I$9/$I$12-SUM($U$25:U30))*V31*W31/SUMPRODUCT($W31:$W$60,$V31:$V$60)),""),"") -> #REF! | V31: 1 | W31: 1
A32: 8 | F32: =IF(AND(E32<>"",E32<>0),D32/E32,"") | H32: =IF(AND(G32<>"",G32<>0),D32/G32,"") | J32: =IF(AND(G32<>"",G32<>0),E32/G32,"") | N32: =IF(AND(I32<>"",I32<>0),G32/I32,"") | O32: =D32/P32 -> #DIV/0! | P32: =$I$8*V32*W32/SUMPRODUCT($W$25:$W$55,$V$25:$V$55) -> 0 | Q32: =$I$9*V32*W32/SUMPRODUCT($W$25:$W$55,$V$25:$V$55) -> 0 | R32: =IF($I$12="","",Q32/$I$12) -> 0 | S32: =IF(W32<>"",IF(D32<>"",D32,($I$8-SUM($S$25:S31))*V32*W32/SUMPRODUCT($W32:$W$55,$V32:$V$55)),"") -> #REF! | T32: =IF(W32<>"",IF(E31<>"",E31,($I$9-SUM($T$25:T31))*V32*W32/SUMPRODUCT($W32:$W$55,$V32:$V$55)),"") -> #REF! | U32: =IF(W32<>"",IF($I$12<>"",IF(G32<>"",G32,($I$9/$I$12-SUM($U$25:U31))*V32*W32/SUMPRODUCT($W32:$W$55,$V32:$V$55)),""),"") -> #REF! | V32: 1 | W32: 1
A33: 9 | F33: =IF(AND(E33<>"",E33<>0),D33/E33,"") | H33: =IF(AND(G33<>"",G33<>0),D33/G33,"") | J33: =IF(AND(G33<>"",G33<>0),E33/G33,"") | N33: =IF(AND(I33<>"",I33<>0),G33/I33,"") | O33: =D33/P33 -> #DIV/0! | P33: =$I$8*V33*W33/SUMPRODUCT($W$25:$W$55,$V$25:$V$55) -> 0 | Q33: =$I$9*V33*W33/SUMPRODUCT($W$25:$W$55,$V$25:$V$55) -> 0 | R33: =IF($I$12="","",Q33/$I$12) -> 0 | S33: =IF(W33<>"",IF(D33<>"",D33,($I$8-SUM($S$25:S32))*V33*W33/SUMPRODUCT($W33:$W$55,$V33:$V$55)),"") -> #REF! | T33: =IF(W33<>"",IF(E33<>"",E33,($I$9-SUM($T$25:T32))*V33*W33/SUMPRODUCT($W33:$W$55,$V33:$V$55)),"") -> #REF! | U33: =IF(W33<>"",IF($I$12<>"",IF(G33<>"",G33,($I$9/$I$12-SUM($U$25:U32))*V33*W33/SUMPRODUCT($W33:$W$55,$V33:$V$55)),""),"") -> #REF! | V33: 1 | W33: 1
A34: 10 | F34: =IF(AND(E34<>"",E34<>0),D34/E34,"") | H34: =IF(AND(G34<>"",G34<>0),D34/G34,"") | J34: =IF(AND(G34<>"",G34<>0),E34/G34,"") | N34: =IF(AND(I34<>"",I34<>0),G34/I34,"") | O34: =D34/P34 -> #DIV/0! | P34: =$I$8*V34*W34/SUMPRODUCT($W$25:$W$60,$V$25:$V$60) -> 0 | Q34: =$I$9*V34*W34/SUMPRODUCT($W$25:$W$60,$V$25:$V$60) -> 0 | R34: =IF($I$12="","",Q34/$I$12) -> 0 | S34: =IF(W34<>"",IF(D34<>"",D34,($I$8-SUM($S$25:S33))*V34*W34/SUMPRODUCT($W34:$W$60,$V34:$V$60)),"") -> #REF! | T34: =IF(W34<>"",IF(E34<>"",E34,($I$9-SUM($T$25:T33))*V34*W34/SUMPRODUCT($W34:$W$60,$V34:$V$60)),"") -> #REF! | U34: =IF(W34<>"",IF($I$12<>"",IF(G34<>"",G34,($I$9/$I$12-SUM($U$25:U33))*V34*W34/SUMPRODUCT($W34:$W$60,$V34:$V$60)),""),"") -> #REF! | V34: 1 | W34: 1
A35: 11 | F35: =IF(AND(E35<>"",E35<>0),D35/E35,"") | H35: =IF(AND(G35<>"",G35<>0),D35/G35,"") | J35: =IF(AND(G35<>"",G35<>0),E35/G35,"") | N35: =IF(AND(I35<>"",I35<>0),G35/I35,"") | O35: =D35/P35 -> #DIV/0! | P35: =$I$8*V35*W35/SUMPRODUCT($W$25:$W$55,$V$25:$V$55) -> 0 | Q35: =$I$9*V35*W35/SUMPRODUCT($W$25:$W$55,$V$25:$V$55) -> 0 | R35: =IF($I$12="","",Q35/$I$12) -> 0 | S35: =IF(W35<>"",IF(D35<>"",D35,($I$8-SUM($S$25:S34))*V35*W35/SUMPRODUCT($W35:$W$55,$V35:$V$55)),"") -> #REF! | T35: =IF(W35<>"",IF(E35<>"",E35,($I$9-SUM($T$25:T34))*V35*W35/SUMPRODUCT($W35:$W$55,$V35:$V$55)),"") -> #REF! | U35: =IF(W35<>"",IF($I$12<>"",IF(G35<>"",G35,($I$9/$I$12-SUM($U$25:U34))*V35*W35/SUMPRODUCT($W35:$W$55,$V35:$V$55)),""),"") -> #REF! | V35: 1 | W35: 1
A36: 12 | F36: =IF(AND(E36<>"",E36<>0),D36/E36,"") | H36: =IF(AND(G36<>"",G36<>0),D36/G36,"") | J36: =IF(AND(G36<>"",G36<>0),E36/G36,"") | N36: =IF(AND(I36<>"",I36<>0),G36/I36,"") | O36: =D36/P36 -> #DIV/0! | P36: =$I$8*V36*W36/SUMPRODUCT($W$25:$W$55,$V$25:$V$55) -> 0 | Q36: =$I$9*V36*W36/SUMPRODUCT($W$25:$W$55,$V$25:$V$55) -> 0 | R36: =IF($I$12="","",Q36/$I$12) -> 0 | S36: =IF(W36<>"",IF(D36<>"",D36,($I$8-SUM($S$25:S35))*V36*W36/SUMPRODUCT($W36:$W$55,$V36:$V$55)),"") -> #REF! | T36: =IF(W36<>"",IF(E36<>"",E36,($I$9-SUM($T$25:T35))*V36*W36/SUMPRODUCT($W36:$W$55,$V36:$V$55)),"") -> #REF! | U36: =IF(W36<>"",IF($I$12<>"",IF(G36<>"",G36,($I$9/$I$12-SUM($U$25:U35))*V36*W36/SUMPRODUCT($W36:$W$55,$V36:$V$55)),""),"") -> #REF! | V36: 1 | W36: 1
A37: 13 | F37: =IF(AND(E37<>"",E37<>0),D37/E37,"") | H37: =IF(AND(G37<>"",G37<>0),D37/G37,"") | J37: =IF(AND(G37<>"",G37<>0),E37/G37,"") | N37: =IF(AND(I37<>"",I37<>0),G37/I37,"") | O37: =D37/P37 -> #DIV/0! | P37: =$I$8*V37*W37/SUMPRODUCT($W$25:$W$55,$V$25:$V$55) -> 0 | Q37: =$I$9*V37*W37/SUMPRODUCT($W$25:$W$55,$V$25:$V$55) -> 0 | R37: =IF($I$12="","",Q37/$I$12) -> 0 | S37: =IF(W37<>"",IF(D37<>"",D37,($I$8-SUM($S$25:S36))*V37*W37/SUMPRODUCT($W37:$W$55,$V37:$V$55)),"") -> #REF! | T37: =IF(W37<>"",IF(E37<>"",E37,($I$9-SUM($T$25:T36))*V37*W37/SUMPRODUCT($W37:$W$55,$V37:$V$55)),"") -> #REF! | U37: =IF(W37<>"",IF($I$12<>"",IF(G37<>"",G37,($I$9/$I$12-SUM($U$25:U36))*V37*W37/SUMPRODUCT($W37:$W$55,$V37:$V$55)),""),"") -> #REF! | V37: 1 | W37: 1
A38: 14 | F38: =IF(AND(E38<>"",E38<>0),D38/E38,"") | H38: =IF(AND(G38<>"",G38<>0),D38/G38,"") | J38: =IF(AND(G38<>"",G38<>0),E38/G38,"") | N38: =IF(AND(I38<>"",I38<>0),G38/I38,"") | O38: =D38/P38 -> #DIV/0! | P38: =$I$8*V38*W38/SUMPRODUCT($W$25:$W$55,$V$25:$V$55) -> 0 | Q38: =$I$9*V38*W38/SUMPRODUCT($W$25:$W$55,$V$25:$V$55) -> 0 | R38: =IF($I$12="","",Q38/$I$12) -> 0 | S38: =IF(W38<>"",IF(D38<>"",D38,($I$8-SUM($S$25:S37))*V38*W38/SUMPRODUCT($W38:$W$55,$V38:$V$55)),"") -> #REF! | T38: =IF(W38<>"",IF(E38<>"",E38,($I$9-SUM($T$25:T37))*V38*W38/SUMPRODUCT($W38:$W$55,$V38:$V$55)),"") -> #REF! | U38: =IF(W38<>"",IF($I$12<>"",IF(G38<>"",G38,($I$9/$I$12-SUM($U$25:U37))*V38*W38/SUMPRODUCT($W38:$W$55,$V38:$V$55)),""),"") -> #REF! | V38: 1 | W38: 1
A39: 15 | F39: =IF(AND(E39<>"",E39<>0),D39/E39,"") | H39: =IF(AND(G39<>"",G39<>0),D39/G39,"") | J39: =IF(AND(G39<>"",G39<>0),E39/G39,"") | N39: =IF(AND(I39<>"",I39<>0),G39/I39,"") | O39: =D39/P39 -> #DIV/0! | P39: =$I$8*V39*W39/SUMPRODUCT($W$25:$W$60,$V$25:$V$60) -> 0 | Q39: =$I$9*V39*W39/SUMPRODUCT($W$25:$W$60,$V$25:$V$60) -> 0 | R39: =IF($I$12="","",Q39/$I$12) -> 0 | S39: =IF(W39<>"",IF(D39<>"",D39,($I$8-SUM($S$25:S38))*V39*W39/SUMPRODUCT($W39:$W$60,$V39:$V$60)),"") -> #REF! | T39: =IF(W39<>"",IF(E39<>"",E39,($I$9-SUM($T$25:T38))*V39*W39/SUMPRODUCT($W39:$W$60,$V39:$V$60)),"") -> #REF! | U39: =IF(W39<>"",IF($I$12<>"",IF(G39<>"",G39,($I$9/$I$12-SUM($U$25:U38))*V39*W39/SUMPRODUCT($W39:$W$60,$V39:$V$60)),""),"") -> #REF! | V39: 1 | W39: 1
A40: 16 | F40: =IF(AND(E40<>"",E40<>0),D40/E40,"") | H40: =IF(AND(G40<>"",G40<>0),D40/G40,"") | J40: =IF(AND(G40<>"",G40<>0),E40/G40,"") | N40: =IF(AND(I40<>"",I40<>0),G40/I40,"") | O40: =D40/P40 -> #DIV/0! | P40: =$I$8*V40*W40/SUMPRODUCT($W$25:$W$60,$V$25:$V$60) -> 0 | Q40: =$I$9*V40*W40/SUMPRODUCT($W$25:$W$60,$V$25:$V$60) -> 0 | R40: =IF($I$12="","",Q40/$I$12) -> 0 | S40: =IF(W40<>"",IF(D40<>"",D40,($I$8-SUM($S$25:S39))*V40*W40/SUMPRODUCT($W40:$W$60,$V40:$V$60)),"") -> #REF! | T40: =IF(W40<>"",IF(E40<>"",E40,($I$9-SUM($T$25:T39))*V40*W40/SUMPRODUCT($W40:$W$60,$V40:$V$60)),"") -> #REF! | U40: =IF(W40<>"",IF($I$12<>"",IF(G40<>"",G40,($I$9/$I$12-SUM($U$25:U39))*V40*W40/SUMPRODUCT($W40:$W$60,$V40:$V$60)),""),"") -> #REF! | V40: 1 | W40: 1
A41: 17 | F41: =IF(AND(E41<>"",E41<>0),D41/E41,"") | H41: =IF(AND(G41<>"",G41<>0),D41/G41,"") | J41: =IF(AND(G41<>"",G41<>0),E41/G41,"") | N41: =IF(AND(I41<>"",I41<>0),G41/I41,"") | O41: =D41/P41 -> #DIV/0! | P41: =$I$8*V41*W41/SUMPRODUCT($W$25:$W$60,$V$25:$V$60) -> 0 | Q41: =$I$9*V41*W41/SUMPRODUCT($W$25:$W$60,$V$25:$V$60) -> 0 | R41: =IF($I$12="","",Q41/$I$12) -> 0 | S41: =IF(W41<>"",IF(D41<>"",D41,($I$8-SUM($S$25:S40))*V41*W41/SUMPRODUCT($W41:$W$60,$V41:$V$60)),"") -> #REF! | T41: =IF(W41<>"",IF(E41<>"",E41,($I$9-SUM($T$25:T40))*V41*W41/SUMPRODUCT($W41:$W$60,$V41:$V$60)),"") -> #REF! | U41: =IF(W41<>"",IF($I$12<>"",IF(G41<>"",G41,($I$9/$I$12-SUM($U$25:U40))*V41*W41/SUMPRODUCT($W41:$W$60,$V41:$V$60)),""),"") -> #REF! | V41: 1 | W41: 1
A42: 18 | F42: =IF(AND(E42<>"",E42<>0),D42/E42,"") | H42: =IF(AND(G42<>"",G42<>0),D42/G42,"") | J42: =IF(AND(G42<>"",G42<>0),E42/G42,"") | N42: =IF(AND(I42<>"",I42<>0),G42/I42,"") | O42: =D42/P42 -> #DIV/0! | P42: =$I$8*V42*W42/SUMPRODUCT($W$25:$W$60,$V$25:$V$60) -> 0 | Q42: =$I$9*V42*W42/SUMPRODUCT($W$25:$W$60,$V$25:$V$60) -> 0 | R42: =IF($I$12="","",Q42/$I$12) -> 0 | S42: =IF(W42<>"",IF(D42<>"",D42,($I$8-SUM($S$25:S41))*V42*W42/SUMPRODUCT($W42:$W$60,$V42:$V$60)),"") -> #REF! | T42: =IF(W42<>"",IF(E42<>"",E42,($I$9-SUM($T$25:T41))*V42*W42/SUMPRODUCT($W42:$W$60,$V42:$V$60)),"") -> #REF! | U42: =IF(W42<>"",IF($I$12<>"",IF(G42<>"",G42,($I$9/$I$12-SUM($U$25:U41))*V42*W42/SUMPRODUCT($W42:$W$60,$V42:$V$60)),""),"") -> #REF! | V42: 1 | W42: 1
A43: 19 | F43: =IF(AND(E43<>"",E43<>0),D43/E43,"") | H43: =IF(AND(G43<>"",G43<>0),D43/G43,"") | J43: =IF(AND(G43<>"",G43<>0),E43/G43,"") | N43: =IF(AND(I43<>"",I43<>0),G43/I43,"") | O43: =D43/P43 -> #DIV/0! | P43: =$I$8*V43*W43/SUMPRODUCT($W$25:$W$60,$V$25:$V$60) -> 0 | Q43: =$I$9*V43*W43/SUMPRODUCT($W$25:$W$60,$V$25:$V$60) -> 0 | R43: =IF($I$12="","",Q43/$I$12) -> 0 | S43: =IF(W43<>"",IF(D43<>"",D43,($I$8-SUM($S$25:S42))*V43*W43/SUMPRODUCT($W43:$W$60,$V43:$V$60)),"") -> #REF! | T43: =IF(W43<>"",IF(E43<>"",E43,($I$9-SUM($T$25:T42))*V43*W43/SUMPRODUCT($W43:$W$60,$V43:$V$60)),"") -> #REF! | U43: =IF(W43<>"",IF($I$12<>"",IF(G43<>"",G43,($I$9/$I$12-SUM($U$25:U42))*V43*W43/SUMPRODUCT($W43:$W$60,$V43:$V$60)),""),"") -> #REF! | V43: 1 | W43: 1
A44: 20 | F44: =IF(AND(E44<>"",E44<>0),D44/E44,"") | H44: =IF(AND(G44<>"",G44<>0),D44/G44,"") | J44: =IF(AND(G44<>"",G44<>0),E44/G44,"") | N44: =IF(AND(I44<>"",I44<>0),G44/I44,"") | O44: =D44/P44 -> #DIV/0! | P44: =$I$8*V44*W44/SUMPRODUCT($W$25:$W$60,$V$25:$V$60) -> 0 | Q44: =$I$9*V44*W44/SUMPRODUCT($W$25:$W$60,$V$25:$V$60) -> 0 | R44: =IF($I$12="","",Q44/$I$12) -> 0 | S44: =IF(W44<>"",IF(D44<>"",D44,($I$8-SUM($S$25:S43))*V44*W44/SUMPRODUCT($W44:$W$60,$V44:$V$60)),"") -> #REF! | T44: =IF(W44<>"",IF(E44<>"",E44,($I$9-SUM($T$25:T43))*V44*W44/SUMPRODUCT($W44:$W$60,$V44:$V$60)),"") -> #REF! | U44: =IF(W44<>"",IF($I$12<>"",IF(G44<>"",G44,($I$9/$I$12-SUM($U$25:U43))*V44*W44/SUMPRODUCT($W44:$W$60,$V44:$V$60)),""),"") -> #REF! | V44: 1 | W44: 1
A45: 21 | F45: =IF(AND(E45<>"",E45<>0),D45/E45,"") | H45: =IF(AND(G45<>"",G45<>0),D45/G45,"") | J45: =IF(AND(G45<>"",G45<>0),E45/G45,"") | N45: =IF(AND(I45<>"",I45<>0),G45/I45,"") | O45: =D45/P45 -> #DIV/0! | P45: =$I$8*V45*W45/SUMPRODUCT($W$25:$W$60,$V$25:$V$60) -> 0 | Q45: =$I$9*V45*W45/SUMPRODUCT($W$25:$W$60,$V$25:$V$60) -> 0 | R45: =IF($I$12="","",Q45/$I$12) -> 0 | S45: =IF(W45<>"",IF(D45<>"",D45,($I$8-SUM($S$25:S44))*V45*W45/SUMPRODUCT($W45:$W$60,$V45:$V$60)),"") -> #REF! | T45: =IF(W45<>"",IF(E45<>"",E45,($I$9-SUM($T$25:T44))*V45*W45/SUMPRODUCT($W45:$W$60,$V45:$V$60)),"") -> #REF! | U45: =IF(W45<>"",IF($I$12<>"",IF(G45<>"",G45,($I$9/$I$12-SUM($U$25:U44))*V45*W45/SUMPRODUCT($W45:$W$60,$V45:$V$60)),""),"") -> #REF! | V45: 1 | W45: 1
A46: 22 | F46: =IF(AND(E46<>"",E46<>0),D46/E46,"") | H46: =IF(AND(G46<>"",G46<>0),D46/G46,"") | J46: =IF(AND(G46<>"",G46<>0),E46/G46,"") | N46: =IF(AND(I46<>"",I46<>0),G46/I46,"") | O46: =D46/P46 -> #DIV/0! | P46: =$I$8*V46*W46/SUMPRODUCT($W$25:$W$60,$V$25:$V$60) -> 0 | Q46: =$I$9*V46*W46/SUMPRODUCT($W$25:$W$60,$V$25:$V$60) -> 0 | R46: =IF($I$12="","",Q46/$I$12) -> 0 | S46: =IF(W46<>"",IF(D46<>"",D46,($I$8-SUM($S$25:S45))*V46*W46/SUMPRODUCT($W46:$W$60,$V46:$V$60)),"") -> #REF! | T46: =IF(W46<>"",IF(E46<>"",E46,($I$9-SUM($T$25:T45))*V46*W46/SUMPRODUCT($W46:$W$60,$V46:$V$60)),"") -> #REF! | U46: =IF(W46<>"",IF($I$12<>"",IF(G46<>"",G46,($I$9/$I$12-SUM($U$25:U45))*V46*W46/SUMPRODUCT($W46:$W$60,$V46:$V$60)),""),"") -> #REF! | V46: 1 | W46: 1
A47: 23 | F47: =IF(AND(E47<>"",E47<>0),D47/E47,"") | H47: =IF(AND(G47<>"",G47<>0),D47/G47,"") | J47: =IF(AND(G47<>"",G47<>0),E47/G47,"") | N47: =IF(AND(I47<>"",I47<>0),G47/I47,"") | O47: =D47/P47 -> #DIV/0! | P47: =$I$8*V47*W47/SUMPRODUCT($W$25:$W$60,$V$25:$V$60) -> 0 | Q47: =$I$9*V47*W47/SUMPRODUCT($W$25:$W$60,$V$25:$V$60) -> 0 | R47: =IF($I$12="","",Q47/$I$12) -> 0 | S47: =IF(W47<>"",IF(D47<>"",D47,($I$8-SUM($S$25:S46))*V47*W47/SUMPRODUCT($W47:$W$60,$V47:$V$60)),"") -> #REF! | T47: =IF(W47<>"",IF(E47<>"",E47,($I$9-SUM($T$25:T46))*V47*W47/SUMPRODUCT($W47:$W$60,$V47:$V$60)),"") -> #REF! | U47: =IF(W47<>"",IF($I$12<>"",IF(G47<>"",G47,($I$9/$I$12-SUM($U$25:U46))*V47*W47/SUMPRODUCT($W47:$W$60,$V47:$V$60)),""),"") -> #REF! | V47: 1 | W47: 1
A48: 24 | F48: =IF(AND(E48<>"",E48<>0),D48/E48,"") | H48: =IF(AND(G48<>"",G48<>0),D48/G48,"") | J48: =IF(AND(G48<>"",G48<>0),E48/G48,"") | N48: =IF(AND(I48<>"",I48<>0),G48/I48,"") | O48: =D48/P48 -> #DIV/0! | P48: =$I$8*V48*W48/SUMPRODUCT($W$25:$W$60,$V$25:$V$60) -> 0 | Q48: =$I$9*V48*W48/SUMPRODUCT($W$25:$W$60,$V$25:$V$60) -> 0 | R48: =IF($I$12="","",Q48/$I$12) -> 0 | S48: =IF(W48<>"",IF(D48<>"",D48,($I$8-SUM($S$25:S47))*V48*W48/SUMPRODUCT($W48:$W$60,$V48:$V$60)),"") -> #REF! | T48: =IF(W48<>"",IF(E48<>"",E48,($I$9-SUM($T$25:T47))*V48*W48/SUMPRODUCT($W48:$W$60,$V48:$V$60)),"") -> #REF! | U48: =IF(W48<>"",IF($I$12<>"",IF(G48<>"",G48,($I$9/$I$12-SUM($U$25:U47))*V48*W48/SUMPRODUCT($W48:$W$60,$V48:$V$60)),""),"") -> #REF! | V48: 1 | W48: 1
A49: 25 | F49: =IF(AND(E49<>"",E49<>0),D49/E49,"") | H49: =IF(AND(G49<>"",G49<>0),D49/G49,"") | J49: =IF(AND(G49<>"",G49<>0),E49/G49,"") | N49: =IF(AND(I49<>"",I49<>0),G49/I49,"") | O49: =D49/P49 -> #DIV/0! | P49: =$I$8*V49*W49/SUMPRODUCT($W$25:$W$60,$V$25:$V$60) -> 0 | Q49: =$I$9*V49*W49/SUMPRODUCT($W$25:$W$60,$V$25:$V$60) -> 0 | R49: =IF($I$12="","",Q49/$I$12) -> 0 | S49: =IF(W49<>"",IF(D49<>"",D49,($I$8-SUM($S$25:S48))*V49*W49/SUMPRODUCT($W49:$W$60,$V49:$V$60)),"") -> #REF! | T49: =IF(W49<>"",IF(E49<>"",E49,($I$9-SUM($T$25:T48))*V49*W49/SUMPRODUCT($W49:$W$60,$V49:$V$60)),"") -> #REF! | U49: =IF(W49<>"",IF($I$12<>"",IF(G49<>"",G49,($I$9/$I$12-SUM($U$25:U48))*V49*W49/SUMPRODUCT($W49:$W$60,$V49:$V$60)),""),"") -> #REF! | V49: 1 | W49: 1
B50: итого | D50: =SUM(D25:D49) -> 0 | E50: =SUM(E25:E49) -> 0 | F50: =IF(AND(E50<>"",E50<>0),D50/E50,"") | G50: =SUM(G25:G49) -> 0 | H50: =IF(AND(G50<>"",G50<>0),D50/G50,"") | I50: =SUM(I25:I49) -> 0 | J50: =IF(AND(G50<>"",G50<>0),E50/G50,"") | K50: =SUM(K25:K49) -> 0 | L50: =SUM(L25:L49) -> 0 | M50: =SUM(M25:M49) -> 0 | N50: =IF(AND(I50<>"",I50<>0),G50/I50,"") | O50: =D50/P50 -> #DIV/0! | P50: =SUM(P25:P49) -> 0 | Q50: =SUM(Q25:Q49) -> 0 | R50: =SUM(R25:R49) -> 0 | S50: =SUM(S25:S49) -> #REF! | T50: =SUM(T25:T49) -> #REF! | U50: =SUM(U25:U49) -> #REF!
D51: =SUMIF(D25:D49,"",P25:P49)+D50 -> 0

Sheet ПК 2
B1: =TODAY()-1 -> 46080
B2: (отчетная дата) | J2: ЕЖЕДНЕВНЫЙ ОТЧЕТ О ПРОДАЖАХ
B3: Осталось до выполнения плана!!! | J3: =График!B29 -> Рогалевич Ирина
C4: =I8-D48 -> 998914.37 | E4: =IF(I8<>0,C4/I8,0) -> 1
F6: Целевые показатели
F7: Показатель | I7: План | J7: Факт | K7: % выполнения | L7: Прогноз выполнения | M7: % выполнения по прогнозу | N7: Отклонение | O7: Факт аналогичного месяца прошлого года | P7: Отклонение LFL
F8: Выручка | I8: ='Ялта, Ленина, 18'!I8/График!AJ31*График!AJ29 -> 998914.37 | J8: =D48 -> 0 | K8: =IF(AND(I8<>"",I8<>0,J8<>""),J8/I8,"") -> 0 | L8: =IF(SUMIF($D$25:$D$47,">=0",$P$25:$P$47)<>0,I8*D48/SUMIF($D$25:$D$47,">=0",$P$25:$P$47),0) -> 0 | M8: =IF(AND(I8<>"",I8<>0,L8<>"",L8<>0),L8/I8,"") | N8: =IF(AND(J8<>0,J8<>"",I8<>0,I8<>""),L8-I8,"") | P8: =IF(AND(O8<>"",O8<>0,L8<>"",L8<>0),-O8+L8,"") | Q8: =IF(AND(P8<>"",P8<>0,O8<>0,O8<>""),P8/O8,"")
F9: Кол-во изделий | I9: =I8/I11 -> 260.06623 | J9: =E48 -> 0 | K9: =IF(AND(I9<>"",I9<>0,J9<>""),J9/I9,"") -> 0 | L9: =IF(SUMIF($E$25:$E$47,">=0",$Q$25:$Q$47)<>0,I9*E48/SUMIF($E$25:$E$47,">=0",$Q$25:$Q$47),0) -> 0 | M9: =IF(AND(I9<>"",I9<>0,L9<>"",L9<>0),L9/I9,"") | N9: =IF(AND(J9<>0,J9<>"",I9<>0,I9<>""),L9-I9,"") | O9: =O8/O11 -> #DIV/0! | P9: =IF(AND(O9<>"",O9<>0,L9<>"",L9<>0),-O9+L9,"") -> #DIV/0! | Q9: =IF(AND(P9<>"",P9<>0,O9<>0,O9<>""),P9/O9,"") -> #DIV/0!
F10: Средний чек | I10: =I11*I12 -> 7682 | J10: =H48 | K10: =IF(AND(I10<>"",I10<>0,J10<>""),J10/I10,"") | L10: =J10 | M10: =IF(AND(I10<>"",I10<>0,L10<>"",L10<>0),L10/I10,"") | N10: =IF(AND(J10<>0,J10<>"",I10<>0,I10<>""),L10-I10,"") | O10: =O11*O12 -> 0 | P10: =IF(AND(O10<>"",O10<>0,L10<>"",L10<>0),-O10+L10,"") | Q10: =IF(AND(P10<>"",P10<>0,O10<>0,O10<>""),P10/O10,"")
F11: Средняя стоимость изделия | I11: ='Ялта, Ленина, 18'!I11 -> 3841 | J11: =F48 | K11: =IF(AND(I11<>"",I11<>0,J11<>""),J11/I11,"") | L11: =IF(L9>0,L8/L9,"") | M11: =IF(AND(I11<>"",I11<>0,L11<>"",L11<>0),L11/I11,"") | N11: =IF(AND(J11<>0,J11<>"",I11<>0,I11<>""),L11-I11,"") | P11: =IF(AND(O11<>"",O11<>0,L11<>"",L11<>0),-O11+L11,"") | Q11: =IF(AND(P11<>"",P11<>0,O11<>0,O11<>""),P11/O11,"")
F12: Длина чека | I12: ='Ялта, Ленина, 18'!I12 -> 2 | J12: =J48 | K12: =IF(AND(I12<>"",I12<>0,J12<>""),J12/I12,"") | L12: =J12 | M12: =IF(AND(I12<>"",I12<>0,L12<>"",L12<>0),L12/I12,"") | N12: =IF(AND(J12<>0,J12<>"",I12<>0,I12<>""),L12-I12,"") | P12: =IF(AND(O12<>"",O12<>0,L12<>"",L12<>0),-O12+L12,"") | Q12: =IF(AND(P12<>"",P12<>0,O12<>0,O12<>""),P12/O12,"")
F13: Кол-во чеков | I13: =IF(I12<>0,I9/I12,"") -> 130.03311 | J13: =G48 -> 0 | K13: =IF(AND(I13<>"",I13<>0,J13<>""),J13/I13,"") -> 0 | L13: =IF(SUMIF($G$25:$G$47,">=0",$R$25:$R$47)<>0,I13*G48/SUMIF($G$25:$G$47,">=0",$R$25:$R$47),"") -> #DIV/0! | M13: =IF(AND(I13<>"",I13<>0,L13<>"",L13<>0),L13/I13,"") -> #DIV/0! | N13: =IF(AND(J13<>0,J13<>"",I13<>0,I13<>""),L13-I13,"") | P13: =IF(AND(O13<>"",O13<>0,L13<>"",L13<>0),-O13+L13,"") -> #DIV/0! | Q13: =IF(AND(P13<>"",P13<>0,O13<>0,O13<>""),P13/O13,"") -> #DIV/0!
F14: Кол-во смен план/отработано | I14: =График!AI29 -> 26 | K14: =IF(AND(I14<>"",I14<>0,J14<>""),J14/I14,"") | L14: =IF(SUMIF($D$25:$D$47,">=0",$P$25:$P$47),I48*I8/SUMIF($D$25:$D$47,">=0",$P$25:$P$47),"") | M14: =IF(AND(I14<>"",I14<>0,L14<>"",L14<>0),L14/I14,"") | N14: =IF(AND(J14<>0,J14<>"",I14<>0,I14<>""),L14-I14,"") | P14: =IF(AND(O14<>"",O14<>0,L14<>"",L14<>0),-O14+L14,"") | Q14: =IF(AND(P14<>"",P14<>0,O14<>0,O14<>""),P14/O14,"")
F15: Средние продажи в смену | I15: ='Ялта, Ленина, 18'!I15 -> 39178.2 | J15: =J8/J14 -> #DIV/0! | K15: =IF(AND(I15<>"",I15<>0,J15<>""),J15/I15,"") -> #DIV/0! | L15: =J15 -> #DIV/0! | M15: =IF(AND(I15<>"",I15<>0,L15<>"",L15<>0),L15/I15,"") -> #DIV/0! | N15: =IF(AND(J15<>0,J15<>"",I15<>0,I15<>""),L15-I15,"") -> #DIV/0! | P15: =IF(AND(O15<>"",O15<>0,L15<>"",L15<>0),-O15+L15,"") -> #DIV/0! | Q15: =IF(AND(P15<>"",P15<>0,O15<>0,O15<>""),P15/O15,"") -> #DIV/0!
F16: Отставание/Перевыполнение | J16: =J8-I15*J14 -> 0 | K16: =IF(AND(I16<>"",I16<>0,J16<>""),J16/I16,"") | L16: =J16 -> 0 | M16: =IF(AND(I16<>"",I16<>0,L16<>"",L16<>0),L16/I16,"") | N16: =IF(AND(J16<>0,J16<>"",I16<>0,I16<>""),L16-I16,"") | P16: =IF(AND(O16<>"",O16<>0,L16<>"",L16<>0),-O16+L16,"") | Q16: =IF(AND(P16<>"",P16<>0,O16<>0,O16<>""),P16/O16,"") | S16: Подарочные сертификаты
F17: Трафик | I17: ='Ялта, Ленина, 18'!I17/График!AJ31*График!AJ29 -> 433.44371 | J17: =I48 -> 0 | K17: =IF(AND(I17<>"",I17<>0,J17<>""),J17/I17,"") -> 0 | L17: =J17/J14*I14 -> #DIV/0! | M17: =IF(AND(I17<>"",I17<>0,L17<>"",L17<>0),L17/I17,"") -> #DIV/0! | N17: =IF(AND(J17<>0,J17<>"",I17<>0,I17<>""),L17-I17,"") | P17: =IF(AND(O17<>"",O17<>0,L17<>"",L17<>0),-O17+L17,"") -> #DIV/0! | Q17: =IF(AND(P17<>"",P17<>0,O17<>0,O17<>""),P17/O17,"") -> #DIV/0!
K18: =IF(AND(I18<>"",I18<>0,J18<>""),J18/I18,"") | L18: =J18 -> 0 | M18: =IF(AND(I18<>"",I18<>0,L18<>"",L18<>0),L18/I18,"") | N18: =IF(AND(J18<>0,J18<>"",I18<>0,I18<>""),L18-I18,"") | O18: 0 | P18: =IF(AND(O18<>"",O18<>0,L18<>"",L18<>0),-O18+L18,"") | Q18: =IF(AND(P18<>"",P18<>0,O18<>0,O18<>""),P18/O18,"")
J19: =M48 -> 0 | K19: =IF(AND(I19<>"",I19<>0,J19<>""),J19/I19,"") | L19: =J19 -> 0 | M19: =IF(AND(I19<>"",I19<>0,L19<>"",L19<>0),L19/I19,"") | N19: =IF(AND(J19<>0,J19<>"",I19<>0,I19<>""),L19-I19,"") | O19: 0 | P19: =IF(AND(O19<>"",O19<>0,L19<>"",L19<>0),-O19+L19,"") | Q19: =IF(AND(P19<>"",P19<>0,O19<>0,O19<>""),P19/O19,"") | S19: =S18/I16 -> #DIV/0!
F20: Конверсия план/факт | I20: ='Ялта, Ленина, 18'!I20 -> 0.3 | J20: =N48 | K20: =J20/I20 -> #VALUE! | L20: =IF(AND(K8<>0,I14<>0,I48<>0),(I48*N48+(I48/K8-I48)*I20)/(I48/K8),0) -> 0 | M20: =IF(AND(I20<>"",I20<>0,L20<>"",L20<>0),L20/I20,"") | N20: =IF(AND(J20<>0,J20<>"",I20<>0,I20<>""),L20-I20,"") | P20: =IF(AND(O20<>"",O20<>0,L20<>"",L20<>0),-O20+L20,"") | Q20: =IF(AND(P20<>"",P20<>0,O20<>0,O20<>""),P20/O20,"")
B22: Факт продаж за месяц | O22: % выполнения дневного плана | P22: Раcпределение плана по дням
B23: Дата | C23: День недели | D23: Выручка (руб) | E23: Кол-во единиц (шт.) | F23: Средняя стоимость изделия (руб.) | G23: Количество чеков (шт.) | H23: Средняя сумма чека (руб.) | I23: Трафик | J23: Длина чека (шт.) | K23: Запасной | L23: Запасной | M23: Запасной | N23: Конверсия (%) | P23: выручка, план | Q23: кол-во ед, план | R23: Кол-во чеков, план | S23: выручка, скорректир.план | T23: кол-во ед, скорр. план | U23: кол-во чеков, скорр. план | V23: Коэфф. Дня Недели | W23: Специфика месяца
B24: 1 | C24: 2 | D24: 3 | E24: 4 | F24: 5 | G24: 6 | H24: 7 | I24: 8 | J24: 9 | K24: 10 | L24: 11 | M24: 12 | N24: 13 | P24: 1 | Q24: 2 | R24: 3 | S24: 4 | T24: 5 | U24: 6 | V24: 10 | W24: 11
A25: 1 | F25: =IF(AND(E25<>"",E25<>0),D25/E25,"") | H25: =IF(AND(G25<>"",G25<>0),D25/G25,"") | J25: =IF(AND(G25<>"",G25<>0),E25/G25,"") | N25: =IF(AND(I25<>"",I25<>0),G25/I25,"") | O25: =D25/P25 -> #DIV/0! | P25: =$I$8*V25*W25/SUMPRODUCT($W$25:$W$55,$V$25:$V$55) -> #DIV/0! | Q25: =$I$9*V25*W25/SUMPRODUCT($W$25:$W$55,$V$25:$V$55) -> #DIV/0! | R25: =IF($I$12="","",Q25/$I$12) -> #DIV/0! | S25: =IF(D25<>"",D25,P25) -> #DIV/0! | T25: =IF(E25<>"",E25,Q25) -> #DIV/0! | U25: =IF(G25<>"",G25,R25) -> #DIV/0!
A26: 2 | F26: =IF(AND(E26<>"",E26<>0),D26/E26,"") | G26: 0 | H26: =IF(AND(G26<>"",G26<>0),D26/G26,"") | J26: =IF(AND(G26<>"",G26<>0),E26/G26,"") | N26: =IF(AND(I26<>"",I26<>0),G26/I26,"") | O26: =D26/P26 -> #DIV/0! | P26: =$I$8*V26*W26/SUMPRODUCT($W$25:$W$55,$V$25:$V$55) -> #DIV/0! | Q26: =$I$9*V26*W26/SUMPRODUCT($W$25:$W$55,$V$25:$V$55) -> #DIV/0! | R26: =IF($I$12="","",Q26/$I$12) -> #DIV/0! | S26: =IF(W26<>"",IF(D26<>"",D26,($I$8-SUM($S$25:S25))*V26*W26/SUMPRODUCT($W26:$W$55,$V26:$V$55)),"") | T26: =IF(W26<>"",IF(E26<>"",E26,($I$9-SUM($T$25:T25))*V26*W26/SUMPRODUCT($W26:$W$55,$V26:$V$55)),"") | U26: =IF(W26<>"",IF($I$12<>"",IF(G26<>"",G26,($I$9/$I$12-SUM($U$25:U25))*V26*W26/SUMPRODUCT($W26:$W$55,$V26:$V$55)),""),"")
A27: 3 | F27: =IF(AND(E27<>"",E27<>0),D27/E27,"") | H27: =IF(AND(G27<>"",G27<>0),D27/G27,"") | J27: =IF(AND(G27<>"",G27<>0),E27/G27,"") | N27: =IF(AND(I27<>"",I27<>0),G27/I27,"") | O27: =D27/P27 -> #DIV/0! | P27: =$I$8*V27*W27/SUMPRODUCT($W$25:$W$55,$V$25:$V$55) -> #DIV/0! | Q27: =$I$9*V27*W27/SUMPRODUCT($W$25:$W$55,$V$25:$V$55) -> #DIV/0! | R27: =IF($I$12="","",Q27/$I$12) -> #DIV/0! | S27: =IF(W27<>"",IF(D27<>"",D27,($I$8-SUM($S$25:S26))*V27*W27/SUMPRODUCT($W27:$W$55,$V27:$V$55)),"") | T27: =IF(W27<>"",IF(E27<>"",E27,($I$9-SUM($T$25:T26))*V27*W27/SUMPRODUCT($W27:$W$55,$V27:$V$55)),"") | U27: =IF(W27<>"",IF($I$12<>"",IF(G27<>"",G27,($I$9/$I$12-SUM($U$25:U26))*V27*W27/SUMPRODUCT($W27:$W$55,$V27:$V$55)),""),"")
A28: 4 | F28: =IF(AND(E28<>"",E28<>0),D28/E28,"") | H28: =IF(AND(G28<>"",G28<>0),D28/G28,"") | J28: =IF(AND(G28<>"",G28<>0),E28/G28,"") | N28: =IF(AND(I28<>"",I28<>0),G28/I28,"") | O28: =D28/P28 -> #DIV/0! | P28: =$I$8*V28*W28/SUMPRODUCT($W$25:$W$55,$V$25:$V$55) -> #DIV/0! | Q28: =$I$9*V28*W28/SUMPRODUCT($W$25:$W$55,$V$25:$V$55) -> #DIV/0! | R28: =IF($I$12="","",Q28/$I$12) -> #DIV/0! | S28: =IF(W28<>"",IF(D28<>"",D28,($I$8-SUM($S$25:S27))*V28*W28/SUMPRODUCT($W28:$W$55,$V28:$V$55)),"") | T28: =IF(W28<>"",IF(E28<>"",E28,($I$9-SUM($T$25:T27))*V28*W28/SUMPRODUCT($W28:$W$55,$V28:$V$55)),"") | U28: =IF(W28<>"",IF($I$12<>"",IF(G28<>"",G28,($I$9/$I$12-SUM($U$25:U27))*V28*W28/SUMPRODUCT($W28:$W$55,$V28:$V$55)),""),"")
A29: 5 | F29: =IF(AND(E29<>"",E29<>0),D29/E29,"") | H29: =IF(AND(G29<>"",G29<>0),D29/G29,"") | J29: =IF(AND(G29<>"",G29<>0),E29/G29,"") | N29: =IF(AND(I29<>"",I29<>0),G29/I29,"") | O29: =D29/P29 -> #DIV/0! | P29: =$I$8*V29*W29/SUMPRODUCT($W$25:$W$55,$V$25:$V$55) -> #DIV/0! | Q29: =$I$9*V29*W29/SUMPRODUCT($W$25:$W$55,$V$25:$V$55) -> #DIV/0! | R29: =IF($I$12="","",Q29/$I$12) -> #DIV/0! | S29: =IF(W29<>"",IF(D29<>"",D29,($I$8-SUM($S$25:S28))*V29*W29/SUMPRODUCT($W29:$W$55,$V29:$V$55)),"") | T29: =IF(W29<>"",IF(E29<>"",E29,($I$9-SUM($T$25:T28))*V29*W29/SUMPRODUCT($W29:$W$55,$V29:$V$55)),"") | U29: =IF(W29<>"",IF($I$12<>"",IF(G29<>"",G29,($I$9/$I$12-SUM($U$25:U28))*V29*W29/SUMPRODUCT($W29:$W$55,$V29:$V$55)),""),"")
A30: 6 | F30: =IF(AND(E30<>"",E30<>0),D30/E30,"") | H30: =IF(AND(G30<>"",G30<>0),D30/G30,"") | J30: =IF(AND(G30<>"",G30<>0),E30/G30,"") | N30: =IF(AND(I30<>"",I30<>0),G30/I30,"") | O30: =D30/P30 -> #DIV/0! | P30: =$I$8*V30*W30/SUMPRODUCT($W$25:$W$55,$V$25:$V$55) -> #DIV/0! | Q30: =$I$9*V30*W30/SUMPRODUCT($W$25:$W$55,$V$25:$V$55) -> #DIV/0! | R30: =IF($I$12="","",Q30/$I$12) -> #DIV/0! | S30: =IF(W30<>"",IF(D30<>"",D30,($I$8-SUM($S$25:S29))*V30*W30/SUMPRODUCT($W30:$W$55,$V30:$V$55)),"") | T30: =IF(W30<>"",IF(E29<>"",E29,($I$9-SUM($T$25:T29))*V30*W30/SUMPRODUCT($W30:$W$55,$V30:$V$55)),"") | U30: =IF(W30<>"",IF($I$12<>"",IF(G30<>"",G30,($I$9/$I$12-SUM($U$25:U29))*V30*W30/SUMPRODUCT($W30:$W$55,$V30:$V$55)),""),"")
A31: 7 | F31: =IF(AND(E31<>"",E31<>0),D31/E31,"") | H31: =IF(AND(G31<>"",G31<>0),D31/G31,"") | J31: =IF(AND(G31<>"",G31<>0),E31/G31,"") | N31: =IF(AND(I31<>"",I31<>0),G31/I31,"") | O31: =D31/P31 -> #DIV/0! | P31: =$I$8*V31*W31/SUMPRODUCT($W$25:$W$55,$V$25:$V$55) -> #DIV/0! | Q31: =$I$9*V31*W31/SUMPRODUCT($W$25:$W$55,$V$25:$V$55) -> #DIV/0! | R31: =IF($I$12="","",Q31/$I$12) -> #DIV/0! | S31: =IF(W31<>"",IF(D31<>"",D31,($I$8-SUM($S$25:S30))*V31*W31/SUMPRODUCT($W31:$W$55,$V31:$V$55)),"") | T31: =IF(W31<>"",IF(E31<>"",E31,($I$9-SUM($T$25:T30))*V31*W31/SUMPRODUCT($W31:$W$55,$V31:$V$55)),"") | U31: =IF(W31<>"",IF($I$12<>"",IF(G31<>"",G31,($I$9/$I$12-SUM($U$25:U30))*V31*W31/SUMPRODUCT($W31:$W$55,$V31:$V$55)),""),"")
A32: 8 | F32: =IF(AND(E32<>"",E32<>0),D32/E32,"") | H32: =IF(AND(G32<>"",G32<>0),D32/G32,"") | J32: =IF(AND(G32<>"",G32<>0),E32/G32,"") | N32: =IF(AND(I32<>"",I32<>0),G32/I32,"") | O32: =D32/P32 -> #DIV/0! | P32: =$I$8*V32*W32/SUMPRODUCT($W$25:$W$55,$V$25:$V$55) -> #DIV/0! | Q32: =$I$9*V32*W32/SUMPRODUCT($W$25:$W$55,$V$25:$V$55) -> #DIV/0! | R32: =IF($I$12="","",Q32/$I$12) -> #DIV/0! | S32: =IF(W32<>"",IF(D32<>"",D32,($I$8-SUM($S$25:S31))*V32*W32/SUMPRODUCT($W32:$W$55,$V32:$V$55)),"") | T32: =IF(W32<>"",IF(E32<>"",E32,($I$9-SUM($T$25:T31))*V32*W32/SUMPRODUCT($W32:$W$55,$V32:$V$55)),"") | U32: =IF(W32<>"",IF($I$12<>"",IF(G32<>"",G32,($I$9/$I$12-SUM($U$25:U31))*V32*W32/SUMPRODUCT($W32:$W$55,$V32:$V$55)),""),"")
A33: 9 | F33: =IF(AND(E33<>"",E33<>0),D33/E33,"") | H33: =IF(AND(G33<>"",G33<>0),D33/G33,"") | J33: =IF(AND(G33<>"",G33<>0),E33/G33,"") | N33: =IF(AND(I33<>"",I33<>0),G33/I33,"") | O33: =D33/P33 -> #DIV/0! | P33: =$I$8*V33*W33/SUMPRODUCT($W$25:$W$55,$V$25:$V$55) -> #DIV/0! | Q33: =$I$9*V33*W33/SUMPRODUCT($W$25:$W$55,$V$25:$V$55) -> #DIV/0! | R33: =IF($I$12="","",Q33/$I$12) -> #DIV/0! | S33: =IF(W33<>"",IF(D33<>"",D33,($I$8-SUM($S$25:S32))*V33*W33/SUMPRODUCT($W33:$W$55,$V33:$V$55)),"") | T33: =IF(W33<>"",IF(E33<>"",E33,($I$9-SUM($T$25:T32))*V33*W33/SUMPRODUCT($W33:$W$55,$V33:$V$55)),"") | U33: =IF(W33<>"",IF($I$12<>"",IF(G33<>"",G33,($I$9/$I$12-SUM($U$25:U32))*V33*W33/SUMPRODUCT($W33:$W$55,$V33:$V$55)),""),"")
A34: 10 | F34: =IF(AND(E34<>"",E34<>0),D34/E34,"") | H34: =IF(AND(G34<>"",G34<>0),D34/G34,"") | J34: =IF(AND(G34<>"",G34<>0),E34/G34,"") | N34: =IF(AND(I34<>"",I34<>0),G34/I34,"") | O34: =D34/P34 -> #DIV/0! | P34: =$I$8*V34*W34/SUMPRODUCT($W$25:$W$55,$V$25:$V$55) -> #DIV/0! | Q34: =$I$9*V34*W34/SUMPRODUCT($W$25:$W$55,$V$25:$V$55) -> #DIV/0! | R34: =IF($I$12="","",Q34/$I$12) -> #DIV/0! | S34: =IF(W34<>"",IF(D34<>"",D34,($I$8-SUM($S$25:S33))*V34*W34/SUMPRODUCT($W34:$W$55,$V34:$V$55)),"") | T34: =IF(W34<>"",IF(E34<>"",E34,($I$9-SUM($T$25:T33))*V34*W34/SUMPRODUCT($W34:$W$55,$V34:$V$55)),"") | U34: =IF(W34<>"",IF($I$12<>"",IF(G34<>"",G34,($I$9/$I$12-SUM($U$25:U33))*V34*W34/SUMPRODUCT($W34:$W$55,$V34:$V$55)),""),"")
A35: 11 | F35: =IF(AND(E35<>"",E35<>0),D35/E35,"") | H35: =IF(AND(G35<>"",G35<>0),D35/G35,"") | J35: =IF(AND(G35<>"",G35<>0),E35/G35,"") | N35: =IF(AND(I35<>"",I35<>0),G35/I35,"") | O35: =D35/P35 -> #DIV/0! | P35: =$I$8*V35*W35/SUMPRODUCT($W$25:$W$55,$V$25:$V$55) -> #DIV/0! | Q35: =$I$9*V35*W35/SUMPRODUCT($W$25:$W$55,$V$25:$V$55) -> #DIV/0! | R35: =IF($I$12="","",Q35/$I$12) -> #DIV/0! | S35: =IF(W35<>"",IF(D35<>"",D35,($I$8-SUM($S$25:S34))*V35*W35/SUMPRODUCT($W35:$W$55,$V35:$V$55)),"") | T35: =IF(W35<>"",IF(E35<>"",E35,($I$9-SUM($T$25:T34))*V35*W35/SUMPRODUCT($W35:$W$55,$V35:$V$55)),"") | U35: =IF(W35<>"",IF($I$12<>"",IF(G35<>"",G35,($I$9/$I$12-SUM($U$25:U34))*V35*W35/SUMPRODUCT($W35:$W$55,$V35:$V$55)),""),"")
A36: 12 | F36: =IF(AND(E36<>"",E36<>0),D36/E36,"") | H36: =IF(AND(G36<>"",G36<>0),D36/G36,"") | J36: =IF(AND(G36<>"",G36<>0),E36/G36,"") | N36: =IF(AND(I36<>"",I36<>0),G36/I36,"") | O36: =D36/P36 -> #DIV/0! | P36: =$I$8*V36*W36/SUMPRODUCT($W$25:$W$55,$V$25:$V$55) -> #DIV/0! | Q36: =$I$9*V36*W36/SUMPRODUCT($W$25:$W$55,$V$25:$V$55) -> #DIV/0! | R36: =IF($I$12="","",Q36/$I$12) -> #DIV/0! | S36: =IF(W36<>"",IF(D36<>"",D36,($I$8-SUM($S$25:S35))*V36*W36/SUMPRODUCT($W36:$W$55,$V36:$V$55)),"") | T36: =IF(W36<>"",IF(E36<>"",E36,($I$9-SUM($T$25:T35))*V36*W36/SUMPRODUCT($W36:$W$55,$V36:$V$55)),"") | U36: =IF(W36<>"",IF($I$12<>"",IF(G36<>"",G36,($I$9/$I$12-SUM($U$25:U35))*V36*W36/SUMPRODUCT($W36:$W$55,$V36:$V$55)),""),"")
A37: 13 | F37: =IF(AND(E37<>"",E37<>0),D37/E37,"") | H37: =IF(AND(G37<>"",G37<>0),D37/G37,"") | J37: =IF(AND(G37<>"",G37<>0),E37/G37,"") | N37: =IF(AND(I37<>"",I37<>0),G37/I37,"") | O37: =D37/P37 -> #DIV/0! | P37: =$I$8*V37*W37/SUMPRODUCT($W$25:$W$55,$V$25:$V$55) -> #DIV/0! | Q37: =$I$9*V37*W37/SUMPRODUCT($W$25:$W$55,$V$25:$V$55) -> #DIV/0! | R37: =IF($I$12="","",Q37/$I$12) -> #DIV/0! | S37: =IF(W37<>"",IF(D37<>"",D37,($I$8-SUM($S$25:S36))*V37*W37/SUMPRODUCT($W37:$W$55,$V37:$V$55)),"") | T37: =IF(W37<>"",IF(E37<>"",E37,($I$9-SUM($T$25:T36))*V37*W37/SUMPRODUCT($W37:$W$55,$V37:$V$55)),"") | U37: =IF(W37<>"",IF($I$12<>"",IF(G37<>"",G37,($I$9/$I$12-SUM($U$25:U36))*V37*W37/SUMPRODUCT($W37:$W$55,$V37:$V$55)),""),"")
A38: 14 | F38: =IF(AND(E38<>"",E38<>0),D38/E38,"") | H38: =IF(AND(G38<>"",G38<>0),D38/G38,"") | J38: =IF(AND(G38<>"",G38<>0),E38/G38,"") | N38: =IF(AND(I38<>"",I38<>0),G38/I38,"") | O38: =D38/P38 -> #DIV/0! | P38: =$I$8*V38*W38/SUMPRODUCT($W$25:$W$55,$V$25:$V$55) -> #DIV/0! | Q38: =$I$9*V38*W38/SUMPRODUCT($W$25:$W$55,$V$25:$V$55) -> #DIV/0! | R38: =IF($I$12="","",Q38/$I$12) -> #DIV/0! | S38: =IF(W38<>"",IF(D38<>"",D38,($I$8-SUM($S$25:S37))*V38*W38/SUMPRODUCT($W38:$W$55,$V38:$V$55)),"") | T38: =IF(W38<>"",IF(E38<>"",E38,($I$9-SUM($T$25:T37))*V38*W38/SUMPRODUCT($W38:$W$55,$V38:$V$55)),"") | U38: =IF(W38<>"",IF($I$12<>"",IF(G38<>"",G38,($I$9/$I$12-SUM($U$25:U37))*V38*W38/SUMPRODUCT($W38:$W$55,$V38:$V$55)),""),"")
A39: 15 | F39: =IF(AND(E39<>"",E39<>0),D39/E39,"") | H39: =IF(AND(G39<>"",G39<>0),D39/G39,"") | J39: =IF(AND(G39<>"",G39<>0),E39/G39,"") | N39: =IF(AND(I39<>"",I39<>0),G39/I39,"") | O39: =D39/P39 -> #DIV/0! | P39: =$I$8*V39*W39/SUMPRODUCT($W$25:$W$55,$V$25:$V$55) -> #DIV/0! | Q39: =$I$9*V39*W39/SUMPRODUCT($W$25:$W$55,$V$25:$V$55) -> #DIV/0! | R39: =IF($I$12="","",Q39/$I$12) -> #DIV/0! | S39: =IF(W39<>"",IF(D39<>"",D39,($I$8-SUM($S$25:S38))*V39*W39/SUMPRODUCT($W39:$W$55,$V39:$V$55)),"") | T39: =IF(W39<>"",IF(E39<>"",E39,($I$9-SUM($T$25:T38))*V39*W39/SUMPRODUCT($W39:$W$55,$V39:$V$55)),"") | U39: =IF(W39<>"",IF($I$12<>"",IF(G39<>"",G39,($I$9/$I$12-SUM($U$25:U38))*V39*W39/SUMPRODUCT($W39:$W$55,$V39:$V$55)),""),"")
A40: 16 | F40: =IF(AND(E40<>"",E40<>0),D40/E40,"") | H40: =IF(AND(G40<>"",G40<>0),D40/G40,"") | J40: =IF(AND(G40<>"",G40<>0),E40/G40,"") | N40: =IF(AND(I40<>"",I40<>0),G40/I40,"") | O40: =D40/P40 -> #DIV/0! | P40: =$I$8*V40*W40/SUMPRODUCT($W$25:$W$55,$V$25:$V$55) -> #DIV/0! | Q40: =$I$9*V40*W40/SUMPRODUCT($W$25:$W$55,$V$25:$V$55) -> #DIV/0! | R40: =IF($I$12="","",Q40/$I$12) -> #DIV/0! | S40: =IF(W40<>"",IF(D40<>"",D40,($I$8-SUM($S$25:S39))*V40*W40/SUMPRODUCT($W40:$W$55,$V40:$V$55)),"") | T40: =IF(W40<>"",IF(E40<>"",E40,($I$9-SUM($T$25:T39))*V40*W40/SUMPRODUCT($W40:$W$55,$V40:$V$55)),"") | U40: =IF(W40<>"",IF($I$12<>"",IF(G40<>"",G40,($I$9/$I$12-SUM($U$25:U39))*V40*W40/SUMPRODUCT($W40:$W$55,$V40:$V$55)),""),"")
A41: 17 | F41: =IF(AND(E41<>"",E41<>0),D41/E41,"") | H41: =IF(AND(G41<>"",G41<>0),D41/G41,"") | J41: =IF(AND(G41<>"",G41<>0),E41/G41,"") | N41: =IF(AND(I41<>"",I41<>0),G41/I41,"") | O41: =D41/P41 -> #DIV/0! | P41: =$I$8*V41*W41/SUMPRODUCT($W$25:$W$55,$V$25:$V$55) -> #DIV/0! | Q41: =$I$9*V41*W41/SUMPRODUCT($W$25:$W$55,$V$25:$V$55) -> #DIV/0! | R41: =IF($I$12="","",Q41/$I$12) -> #DIV/0! | S41: =IF(W41<>"",IF(D41<>"",D41,($I$8-SUM($S$25:S40))*V41*W41/SUMPRODUCT($W41:$W$55,$V41:$V$55)),"") | T41: =IF(W41<>"",IF(E41<>"",E41,($I$9-SUM($T$25:T40))*V41*W41/SUMPRODUCT($W41:$W$55,$V41:$V$55)),"") | U41: =IF(W41<>"",IF($I$12<>"",IF(G41<>"",G41,($I$9/$I$12-SUM($U$25:U40))*V41*W41/SUMPRODUCT($W41:$W$55,$V41:$V$55)),""),"")
A42: 18 | F42: =IF(AND(E42<>"",E42<>0),D42/E42,"") | H42: =IF(AND(G42<>"",G42<>0),D42/G42,"") | J42: =IF(AND(G42<>"",G42<>0),E42/G42,"") | N42: =IF(AND(I42<>"",I42<>0),G42/I42,"") | O42: =D42/P42 -> #DIV/0! | P42: =$I$8*V42*W42/SUMPRODUCT($W$25:$W$55,$V$25:$V$55) -> #DIV/0! | Q42: =$I$9*V42*W42/SUMPRODUCT($W$25:$W$55,$V$25:$V$55) -> #DIV/0! | R42: =IF($I$12="","",Q42/$I$12) -> #DIV/0! | S42: =IF(W42<>"",IF(D42<>"",D42,($I$8-SUM($S$25:S41))*V42*W42/SUMPRODUCT($W42:$W$55,$V42:$V$55)),"") | T42: =IF(W42<>"",IF(E42<>"",E42,($I$9-SUM($T$25:T41))*V42*W42/SUMPRODUCT($W42:$W$55,$V42:$V$55)),"") | U42: =IF(W42<>"",IF($I$12<>"",IF(G42<>"",G42,($I$9/$I$12-SUM($U$25:U41))*V42*W42/SUMPRODUCT($W42:$W$55,$V42:$V$55)),""),"")
F43: =IF(AND(E43<>"",E43<>0),D43/E43,"") | H43: =IF(AND(G43<>"",G43<>0),D43/G43,"") | J43: =IF(AND(G43<>"",G43<>0),E43/G43,"") | N43: =IF(AND(I43<>"",I43<>0),G43/I43,"") | O43: =D43/P43 -> #DIV/0! | P43: =$I$8*V43*W43/SUMPRODUCT($W$25:$W$55,$V$25:$V$55) -> #DIV/0! | Q43: =$I$9*V43*W43/SUMPRODUCT($W$25:$W$55,$V$25:$V$55) -> #DIV/0! | R43: =IF($I$12="","",Q43/$I$12) -> #DIV/0! | S43: =IF(W43<>"",IF(D43<>"",D43,($I$8-SUM($S$25:S42))*V43*W43/SUMPRODUCT($W43:$W$55,$V43:$V$55)),"") | T43: =IF(W43<>"",IF(E43<>"",E43,($I$9-SUM($T$25:T42))*V43*W43/SUMPRODUCT($W43:$W$55,$V43:$V$55)),"") | U43: =IF(W43<>"",IF($I$12<>"",IF(G43<>"",G43,($I$9/$I$12-SUM($U$25:U42))*V43*W43/SUMPRODUCT($W43:$W$55,$V43:$V$55)),""),"")
F44: =IF(AND(E44<>"",E44<>0),D44/E44,"") | H44: =IF(AND(G44<>"",G44<>0),D44/G44,"") | J44: =IF(AND(G44<>"",G44<>0),E44/G44,"") | N44: =IF(AND(I44<>"",I44<>0),G44/I44,"") | O44: =D44/P44 -> #DIV/0! | P44: =$I$8*V44*W44/SUMPRODUCT($W$25:$W$55,$V$25:$V$55) -> #DIV/0! | Q44: =$I$9*V44*W44/SUMPRODUCT($W$25:$W$55,$V$25:$V$55) -> #DIV/0! | R44: =IF($I$12="","",Q44/$I$12) -> #DIV/0! | S44: =IF(W44<>"",IF(D44<>"",D44,($I$8-SUM($S$25:S43))*V44*W44/SUMPRODUCT($W44:$W$55,$V44:$V$55)),"") | T44: =IF(W44<>"",IF(E44<>"",E44,($I$9-SUM($T$25:T43))*V44*W44/SUMPRODUCT($W44:$W$55,$V44:$V$55)),0) -> 0 | U44: =IF(W44<>"",IF($I$12<>"",IF(G44<>"",G44,($I$9/$I$12-SUM($U$25:U43))*V44*W44/SUMPRODUCT($W44:$W$55,$V44:$V$55)),""),"")
F45: =IF(AND(E45<>"",E45<>0),D45/E45,"") | H45: =IF(AND(G45<>"",G45<>0),D45/G45,"") | J45: =IF(AND(G45<>"",G45<>0),E45/G45,"") | N45: =IF(AND(I45<>"",I45<>0),G45/I45,"") | O45: =D45/P45 -> #DIV/0! | P45: =$I$8*V45*W45/SUMPRODUCT($W$25:$W$44,$V$25:$V$44) -> #DIV/0! | Q45: =$I$9*V45*W45/SUMPRODUCT($W$25:$W$44,$V$25:$V$44) -> #DIV/0! | R45: =IF($I$12="","",Q45/$I$12) -> #DIV/0! | S45: =IF(W45<>"",IF(D45<>"",D45,($I$8-SUM($S$25:S44))*V45*W45/SUMPRODUCT($W$44:$W45,$V$44:$V45)),"") | T45: =IF(W45<>"",IF(E45<>"",E45,($I$9-SUM($T$25:T44))*V45*W45/SUMPRODUCT($W$44:$W45,$V$44:$V45)),"") | U45: =IF(W45<>"",IF($I$12<>"",IF(G45<>"",G45,($I$9/$I$12-SUM($U$25:U44))*V45*W45/SUMPRODUCT($W$44:$W45,$V$44:$V45)),""),"")
F46: =IF(AND(E46<>"",E46<>0),D46/E46,"") | H46: =IF(AND(G46<>"",G46<>0),D46/G46,"") | J46: =IF(AND(G46<>"",G46<>0),E46/G46,"") | N46: =IF(AND(I46<>"",I46<>0),G46/I46,"") | O46: =D46/P46 -> #DIV/0! | P46: =$I$8*V46*W46/SUMPRODUCT($W$25:$W$44,$V$25:$V$44) -> #DIV/0! | Q46: =$I$9*V46*W46/SUMPRODUCT($W$25:$W$44,$V$25:$V$44) -> #DIV/0! | R46: =IF($I$12="","",Q46/$I$12) -> #DIV/0! | S46: =IF(W46<>"",IF(D46<>"",D46,($I$8-SUM($S$25:S45))*V46*W46/SUMPRODUCT($W$44:$W46,$V$44:$V46)),"") | T46: =IF(W46<>"",IF(E46<>"",E46,($I$9-SUM($T$25:T45))*V46*W46/SUMPRODUCT($W$44:$W46,$V$44:$V46)),"") | U46: =IF(W46<>"",IF($I$12<>"",IF(G46<>"",G46,($I$9/$I$12-SUM($U$25:U45))*V46*W46/SUMPRODUCT($W$44:$W46,$V$44:$V46)),""),"")
F47: =IF(AND(E47<>"",E47<>0),D47/E47,"") | H47: =IF(AND(G47<>"",G47<>0),D47/G47,"") | J47: =IF(AND(G47<>"",G47<>0),E47/G47,"") | N47: =IF(AND(I47<>"",I47<>0),G47/I47,"") | O47: =D47/P47 -> #DIV/0! | P47: =$I$8*V47*W47/SUMPRODUCT($W$25:$W$47,$V$25:$V$47) -> #DIV/0! | Q47: =$I$9*V47*W47/SUMPRODUCT($W$25:$W$47,$V$25:$V$47) -> #DIV/0! | R47: =IF($I$12="","",Q47/$I$12) -> #DIV/0! | S47: =IF(W47<>"",IF(D47<>"",D47,($I$8-SUM($S$25:S46))*V47*W47/SUMPRODUCT($W47:$W$47,$V47:$V$47)),"") | T47: =IF(W47<>"",IF(E47<>"",E47,($I$9-SUM($T$25:T46))*V47*W47/SUMPRODUCT($W47:$W$47,$V47:$V$47)),"") | U47: =IF(W47<>"",IF($I$12<>"",IF(G47<>"",G47,($I$9/$I$12-SUM($U$25:U46))*V47*W47/SUMPRODUCT($W47:$W$47,$V47:$V$47)),""),"")
B48: итого | D48: =SUM(D25:D47) -> 0 | E48: =SUM(E25:E47) -> 0 | F48: =IF(AND(E48<>"",E48<>0),D48/E48,"") | G48: =SUM(G25:G47) -> 0 | H48: =IF(AND(G48<>"",G48<>0),D48/G48,"") | I48: =SUM(I25:I47) -> 0 | J48: =IF(AND(G48<>"",G48<>0),E48/G48,"") | K48: =SUM(K25:K47) -> 0 | L48: =SUM(L25:L47) -> 0 | M48: =SUM(M25:M47) -> 0 | N48: =IF(AND(I48<>"",I48<>0),G48/I48,"") | O48: =D48/P48 -> #DIV/0! | P48: =SUM(P25:P47) -> #DIV/0! | Q48: =SUM(Q25:Q47) -> #DIV/0! | R48: =SUM(R25:R47) -> #DIV/0! | S48: =SUM(S25:S47) -> #DIV/0! | T48: =SUM(T25:T47) -> #DIV/0! | U48: =SUM(U25:U47) -> #DIV/0!
D49: =SUMIF(D25:D47,"",P25:P47)+D48 -> #DIV/0!

Sheet Доп сотрудник
B1: =TODAY()-1 -> 46080
B2: (отчетная дата) | J2: ЕЖЕДНЕВНЫЙ ОТЧЕТ О ПРОДАЖАХ
B3: Осталось до выполнения плана!!! | J3: =График!B27 -> Орешникова Елена
C4: =I8-D48 -> -6282.8503 | E4: =IF(I8<>0,C4/I8,0) -> -0.078620982
F6: Целевые показатели
F7: Показатель | I7: План | J7: Факт | K7: % выполнения | L7: Прогноз выполнения | M7: % выполнения по прогнозу | N7: Отклонение | O7: Факт аналогичного месяца прошлого года | P7: Отклонение LFL
F8: Выручка | I8: ='Ялта, Ленина, 18'!I8/График!AJ31*График!AJ28 -> 79913.15 | J8: =D48 -> 86196 | K8: =IF(AND(I8<>"", I8<>0, J8<>""), J8/I8, "") -> 1.078621 | L8: =IF(SUMIF($D$25:$D$47,">=0",$P$25:$P$47)<>0,I8*D48/SUMIF($D$25:$D$47,">=0",$P$25:$P$47),0) -> 86196 | M8: =IF(AND(I8<>"", I8<>0, L8<>"", L8<>0), L8/I8, "") -> 1.078621 | N8: =IF(AND(J8<>0, J8<>"", I8<>0, I8<>""), L8-I8, "") -> 6282.8503 | P8: =IF(AND(O8<>"", O8<>0, L8<>"", L8<>0), -O8+L8, "") | Q8: =IF(AND(P8<>"", P8<>0, O8<>0, O8<>""), P8/O8, "")
F9: Кол-во изделий | I9: =I8/I11 -> 20.805298 | J9: =E48 -> 25 | K9: =IF(AND(I9<>"", I9<>0, J9<>""), J9/I9, "") -> 1.201617 | L9: =IF(SUMIF($E$25:$E$47,">=0",$Q$25:$Q$47)<>0,I9*E48/SUMIF($E$25:$E$47,">=0",$Q$25:$Q$47),0) -> 25 | M9: =IF(AND(I9<>"", I9<>0, L9<>"", L9<>0), L9/I9, "") -> 1.201617 | N9: =IF(AND(J9<>0, J9<>"", I9<>0, I9<>""), L9-I9, "") -> 4.194702 | O9: =O8/O11 -> #DIV/0! | P9: =IF(AND(O9<>"", O9<>0, L9<>"", L9<>0), -O9+L9, "") -> #DIV/0! | Q9: =IF(AND(P9<>"", P9<>0, O9<>0, O9<>""), P9/O9, "") -> #DIV/0!
F10: Средний чек | I10: =I11*I12 -> 7682 | J10: =H48 -> 7183 | K10: =IF(AND(I10<>"", I10<>0, J10<>""), J10/I10, "") -> 0.93504296 | L10: =J10 -> 7183 | M10: =IF(AND(I10<>"", I10<>0, L10<>"", L10<>0), L10/I10, "") -> 0.93504296 | N10: =IF(AND(J10<>0, J10<>"", I10<>0, I10<>""), L10-I10, "") -> -499 | O10: =O11*O12 -> 0 | P10: =IF(AND(O10<>"", O10<>0, L10<>"", L10<>0), -O10+L10, "") | Q10: =IF(AND(P10<>"", P10<>0, O10<>0, O10<>""), P10/O10, "")
F11: Средняя стоимость изделия | I11: ='Ялта, Ленина, 18'!I11 -> 3841 | J11: =F48 -> 3447.84 | K11: =IF(AND(I11<>"", I11<>0, J11<>""), J11/I11, "") -> 0.89764124 | L11: =IF(L9>0, L8/L9, "") -> 3447.84 | M11: =IF(AND(I11<>"", I11<>0, L11<>"", L11<>0), L11/I11, "") -> 0.89764124 | N11: =IF(AND(J11<>0, J11<>"", I11<>0, I11<>""), L11-I11, "") -> -393.16 | P11: =IF(AND(O11<>"", O11<>0, L11<>"", L11<>0), -O11+L11, "") | Q11: =IF(AND(P11<>"", P11<>0, O11<>0, O11<>""), P11/O11, "")
F12: Длина чека | I12: ='Ялта, Ленина, 18'!I12 -> 2 | J12: =J48 -> 2.0833333 | K12: =IF(AND(I12<>"", I12<>0, J12<>""), J12/I12, "") -> 1.0416667 | L12: =J12 -> 2.0833333 | M12: =IF(AND(I12<>"", I12<>0, L12<>"", L12<>0), L12/I12, "") -> 1.0416667 | N12: =IF(AND(J12<>0, J12<>"", I12<>0, I12<>""), L12-I12, "") -> 0.083333333 | P12: =IF(AND(O12<>"", O12<>0, L12<>"", L12<>0), -O12+L12, "") | Q12: =IF(AND(P12<>"", P12<>0, O12<>0, O12<>""), P12/O12, "")
F13: Кол-во чеков | I13: =IF(I12<>0, I9/I12, "") -> 10.402649 | J13: =G48 -> 12 | K13: =IF(AND(I13<>"", I13<>0, J13<>""), J13/I13, "") -> 1.1535523 | L13: =IF(SUMIF($G$25:$G$47,">=0",$R$25:$R$47)<>0,I13*G48/SUMIF($G$25:$G$47,">=0",$R$25:$R$47),"") -> 12 | M13: =IF(AND(I13<>"", I13<>0, L13<>"", L13<>0), L13/I13, "") -> 1.1535523 | N13: =IF(AND(J13<>0, J13<>"", I13<>0, I13<>""), L13-I13, "") -> 1.597351 | P13: =IF(AND(O13<>"", O13<>0, L13<>"", L13<>0), -O13+L13, "") | Q13: =IF(AND(P13<>"", P13<>0, O13<>0, O13<>""), P13/O13, "")
F14: Кол-во смен план/отработано | I14: =График!AI28 -> 2 | J14: 2 | K14: =IF(AND(I14<>"", I14<>0, J14<>""), J14/I14, "") -> 1 | L14: =IF(SUMIF($D$25:$D$47,">=0",$P$25:$P$47),I48*I8/SUMIF($D$25:$D$47,">=0",$P$25:$P$47),"") -> 42 | M14: =IF(AND(I14<>"", I14<>0, L14<>"", L14<>0), L14/I14, "") -> 21 | N14: =IF(AND(J14<>0, J14<>"", I14<>0, I14<>""), L14-I14, "") -> 40 | P14: =IF(AND(O14<>"", O14<>0, L14<>"", L14<>0), -O14+L14, "") | Q14: =IF(AND(P14<>"", P14<>0, O14<>0, O14<>""), P14/O14, "")
F15: Средние продажи в смену | I15: ='Ялта, Ленина, 18'!I15 -> 39178.2 | J15: =J8/J14 -> 43098 | K15: =IF(AND(I15<>"", I15<>0, J15<>""), J15/I15, "") -> 1.1000505 | L15: =J15 -> 43098 | M15: =IF(AND(I15<>"", I15<>0, L15<>"", L15<>0), L15/I15, "") -> 1.1000505 | N15: =IF(AND(J15<>0, J15<>"", I15<>0, I15<>""), L15-I15, "") -> 3919.8 | P15: =IF(AND(O15<>"", O15<>0, L15<>"", L15<>0), -O15+L15, "") | Q15: =IF(AND(P15<>"", P15<>0, O15<>0, O15<>""), P15/O15, "")
F16: Отставание/Перевыполнение | J16: =J8-I15*J14 -> 7839.6 | K16: =IF(AND(I16<>"", I16<>0, J16<>""), J16/I16, "") | L16: =J16 -> 7839.6 | M16: =IF(AND(I16<>"", I16<>0, L16<>"", L16<>0), L16/I16, "") | N16: =IF(AND(J16<>0, J16<>"", I16<>0, I16<>""), L16-I16, "") | P16: =IF(AND(O16<>"", O16<>0, L16<>"", L16<>0), -O16+L16, "") | Q16: =IF(AND(P16<>"", P16<>0, O16<>0, O16<>""), P16/O16, "") | S16: Подарочные сертификаты
F17: Трафик | I17: ='Ялта, Ленина, 18'!I17/График!AJ31*График!AJ28 -> 34.675497 | J17: =I48 -> 42 | K17: =IF(AND(I17<>"", I17<>0, J17<>""), J17/I17, "") -> 1.2112299 | L17: =J17/J14*I14 -> 42 | M17: =IF(AND(I17<>"", I17<>0, L17<>"", L17<>0), L17/I17, "") -> 1.2112299 | N17: =IF(AND(J17<>0, J17<>"", I17<>0, I17<>""), L17-I17, "") -> 7.3245033 | P17: =IF(AND(O17<>"", O17<>0, L17<>"", L17<>0), -O17+L17, "") | Q17: =IF(AND(P17<>"", P17<>0, O17<>0, O17<>""), P17/O17, "")
K18: =IF(AND(I18<>"", I18<>0, J18<>""), J18/I18, "") | L18: =J18 -> 0 | M18: =IF(AND(I18<>"", I18<>0, L18<>"", L18<>0), L18/I18, "") | N18: =IF(AND(J18<>0, J18<>"", I18<>0, I18<>""), L18-I18, "") | O18: 0 | P18: =IF(AND(O18<>"", O18<>0, L18<>"", L18<>0), -O18+L18, "") | Q18: =IF(AND(P18<>"", P18<>0, O18<>0, O18<>""), P18/O18, "")
K19: =IF(AND(I19<>"", I19<>0, J19<>""), J19/I19, "") | L19: =J19 -> 0 | M19: =IF(AND(I19<>"", I19<>0, L19<>"", L19<>0), L19/I19, "") | N19: =IF(AND(J19<>0, J19<>"", I19<>0, I19<>""), L19-I19, "") | O19: 0 | P19: =IF(AND(O19<>"", O19<>0, L19<>"", L19<>0), -O19+L19, "") | Q19: =IF(AND(P19<>"", P19<>0, O19<>0, O19<>""), P19/O19, "") | S19: =S18/I16 -> #DIV/0!
F20: Конверсия план/факт | I20: ='Ялта, Ленина, 18'!I20 -> 0.3 | J20: =N48 -> 0.28571429 | K20: =J20/I20 -> 0.95238095 | L20: =IF(AND(K8<>0,I14<>0,I48<>0),(I48*N48+(I48/K8-I48)*I20)/(I48/K8),0) -> 0.28459113 | M20: =IF(AND(I20<>"", I20<>0, L20<>"", L20<>0), L20/I20, "") -> 0.9486371 | N20: =IF(AND(J20<>0, J20<>"", I20<>0, I20<>""), L20-I20, "") -> -0.015408871 | P20: =IF(AND(O20<>"", O20<>0, L20<>"", L20<>0), -O20+L20, "") | Q20: =IF(AND(P20<>"", P20<>0, O20<>0, O20<>""), P20/O20, "")
B22: Факт продаж за месяц | O22: % выполнения дневного плана | P22: Раcпределение плана по дням
B23: Дата | C23: День недели | D23: Выручка (руб) | E23: Кол-во единиц (шт.) | F23: Средняя стоимость изделия (руб.) | G23: Количество чеков (шт.) | H23: Средняя сумма чека (руб.) | I23: Трафик | J23: Длина чека (шт.) | K23: Запасной | L23: Запасной | M23: Запасной | N23: Конверсия (%) | P23: выручка, план | Q23: кол-во ед, план | R23: Кол-во чеков, план | S23: выручка, скорректир.план | T23: кол-во ед, скорр. план | U23: кол-во чеков, скорр. план | V23: Коэфф. Дня Недели | W23: Специфика месяца
B24: 1 | C24: 2 | D24: 3 | E24: в | F24: 5 | G24: 6 | H24: 7 | I24: 8 | J24: 9 | K24: 10 | L24: 11 | M24: 12 | N24: 13 | P24: 1 | Q24: 2 | R24: 3 | S24: 4 | T24: 5 | U24: 6 | V24: 10 | W24: 11
A25: Стекольщикова | B25: 45689 | C25: сб | D25: 18650 | E25: 6 | F25: =IF(AND(E25<>"",E25<>0),D25/E25,"") -> 3108.3333 | G25: 4 | H25: =IF(AND(G25<>"",G25<>0),D25/G25,"") -> 4662.5 | I25: 20 | J25: =IF(AND(G25<>"",G25<>0),E25/G25,"") -> 1.5 | N25: =IF(AND(I25<>"",I25<>0),G25/I25,"") -> 0.2 | O25: =D25/P25 -> 0.74914454 | P25: =$I$8*V25*W25/SUMPRODUCT($W$25:$W$55,$V$25:$V$55) -> 24895.062 | Q25: =$I$9*V25*W25/SUMPRODUCT($W$25:$W$55,$V$25:$V$55) -> 6.4814013 | R25: =IF($I$12="","",Q25/$I$12) -> 3.2407006 | S25: =IF(D25<>"",D25,P25) -> 18650 | T25: =IF(E25<>"",E25,Q25) -> 6 | U25: =IF(G25<>"",G25,R25) -> 4 | V25: 1 | W25: 1
A26: Стекольщикова | B26: 45690 | C26: вс | D26: 52680 | E26: 15 | F26: =IF(AND(E26<>"",E26<>0),D26/E26,"") -> 3512 | G26: 6 | H26: =IF(AND(G26<>"",G26<>0),D26/G26,"") -> 8780 | I26: 20 | J26: =IF(AND(G26<>"",G26<>0),E26/G26,"") -> 2.5 | N26: =IF(AND(I26<>"",I26<>0),G26/I26,"") -> 0.3 | O26: =D26/P26 -> 1.7488283 | P26: =$I$8*V26*W26/SUMPRODUCT($W$25:$W$55,$V$25:$V$55) -> 30123.025 | Q26: =$I$9*V26*W26/SUMPRODUCT($W$25:$W$55,$V$25:$V$55) -> 7.8424955 | R26: =IF($I$12="","",Q26/$I$12) -> 3.9212478 | S26: =IF(W26<>"",IF(D26<>"",D26,($I$8-SUM($S$25:S25))*V26*W26/SUMPRODUCT($W26:$W$55,$V26:$V$55)),"") -> 52680 | T26: =IF(W26<>"",IF(E26<>"",E26,($I$9-SUM($T$25:T25))*V26*W26/SUMPRODUCT($W26:$W$55,$V26:$V$55)),"") -> 15 | U26: =IF(W26<>"",IF($I$12<>"",IF(G26<>"",G26,($I$9/$I$12-SUM($U$25:U25))*V26*W26/SUMPRODUCT($W26:$W$55,$V26:$V$55)),""),"") -> 6 | V26: 1.1 | W26: 1.1
A27: Орешникова | B27: 45692 | D27: 7683 | E27: 2 | F27: =IF(AND(E27<>"",E27<>0),D27/E27,"") -> 3841.5 | G27: 1 | H27: =IF(AND(G27<>"",G27<>0),D27/G27,"") -> 7683 | J27: =IF(AND(G27<>"",G27<>0),E27/G27,"") -> 2 | N27: =IF(AND(I27<>"",I27<>0),G27/I27,"") | O27: =D27/P27 -> #DIV/0! | P27: =$I$8*V27*W27/SUMPRODUCT($W$25:$W$55,$V$25:$V$55) -> 0 | Q27: =$I$9*V27*W27/SUMPRODUCT($W$25:$W$55,$V$25:$V$55) -> 0 | R27: =IF($I$12="","",Q27/$I$12) -> 0 | S27: =IF(W27<>"",IF(D27<>"",D27,($I$8-SUM($S$25:S26))*V27*W27/SUMPRODUCT($W27:$W$55,$V27:$V$55)),"") | T27: =IF(W27<>"",IF(E27<>"",E27,($I$9-SUM($T$25:T26))*V27*W27/SUMPRODUCT($W27:$W$55,$V27:$V$55)),"") | U27: =IF(W27<>"",IF($I$12<>"",IF(G27<>"",G27,($I$9/$I$12-SUM($U$25:U26))*V27*W27/SUMPRODUCT($W27:$W$55,$V27:$V$55)),""),"")
A28: Орешникова | B28: 45714 | C28: ср | D28: 7183 | E28: 2 | F28: =IF(AND(E28<>"",E28<>0),D28/E28,"") -> 3591.5 | G28: 1 | H28: =IF(AND(G28<>"",G28<>0),D28/G28,"") -> 7183 | I28: 2 | J28: =IF(AND(G28<>"",G28<>0),E28/G28,"") -> 2 | N28: =IF(AND(I28<>"",I28<>0),G28/I28,"") -> 0.5 | O28: =D28/P28 -> 0.28853111 | P28: =$I$8*V28*W28/SUMPRODUCT($W$25:$W$55,$V$25:$V$55) -> 24895.062 | Q28: =$I$9*V28*W28/SUMPRODUCT($W$25:$W$55,$V$25:$V$55) -> 6.4814013 | R28: =IF($I$12="","",Q28/$I$12) -> 3.2407006 | S28: =IF(W28<>"",IF(D28<>"",D28,($I$8-SUM($S$25:S27))*V28*W28/SUMPRODUCT($W28:$W$55,$V28:$V$55)),"") -> 7183 | T28: =IF(W28<>"",IF(E28<>"",E28,($I$9-SUM($T$25:T27))*V28*W28/SUMPRODUCT($W28:$W$55,$V28:$V$55)),"") -> 2 | U28: =IF(W28<>"",IF($I$12<>"",IF(G28<>"",G28,($I$9/$I$12-SUM($U$25:U27))*V28*W28/SUMPRODUCT($W28:$W$55,$V28:$V$55)),""),"") -> 1 | V28: 1 | W28: 1
F29: =IF(AND(E29<>"",E29<>0),D29/E29,"") | H29: =IF(AND(G29<>"",G29<>0),D29/G29,"") | J29: =IF(AND(G29<>"",G29<>0),E29/G29,"") | N29: =IF(AND(I29<>"",I29<>0),G29/I29,"") | O29: =D29/P29 -> #DIV/0! | P29: =$I$8*V29*W29/SUMPRODUCT($W$25:$W$55,$V$25:$V$55) -> 0 | Q29: =$I$9*V29*W29/SUMPRODUCT($W$25:$W$55,$V$25:$V$55) -> 0 | R29: =IF($I$12="","",Q29/$I$12) -> 0 | S29: =IF(W29<>"",IF(D29<>"",D29,($I$8-SUM($S$25:S28))*V29*W29/SUMPRODUCT($W29:$W$55,$V29:$V$55)),"") | T29: =IF(W29<>"",IF(E29<>"",E29,($I$9-SUM($T$25:T28))*V29*W29/SUMPRODUCT($W29:$W$55,$V29:$V$55)),"") | U29: =IF(W29<>"",IF($I$12<>"",IF(G29<>"",G29,($I$9/$I$12-SUM($U$25:U28))*V29*W29/SUMPRODUCT($W29:$W$55,$V29:$V$55)),""),"")
F30: =IF(AND(E30<>"",E30<>0),D30/E30,"") | H30: =IF(AND(G30<>"",G30<>0),D30/G30,"") | J30: =IF(AND(G30<>"",G30<>0),E30/G30,"") | N30: =IF(AND(I30<>"",I30<>0),G30/I30,"") | O30: =D30/P30 -> #DIV/0! | P30: =$I$8*V30*W30/SUMPRODUCT($W$25:$W$55,$V$25:$V$55) -> 0 | Q30: =$I$9*V30*W30/SUMPRODUCT($W$25:$W$55,$V$25:$V$55) -> 0 | R30: =IF($I$12="","",Q30/$I$12) -> 0 | S30: =IF(W30<>"",IF(D30<>"",D30,($I$8-SUM($S$25:S29))*V30*W30/SUMPRODUCT($W30:$W$55,$V30:$V$55)),"") | T30: =IF(W30<>"",IF(E30<>"",E30,($I$9-SUM($T$25:T29))*V30*W30/SUMPRODUCT($W30:$W$55,$V30:$V$55)),"") | U30: =IF(W30<>"",IF($I$12<>"",IF(G30<>"",G30,($I$9/$I$12-SUM($U$25:U29))*V30*W30/SUMPRODUCT($W30:$W$55,$V30:$V$55)),""),"")
F31: =IF(AND(E31<>"",E31<>0),D31/E31,"") | H31: =IF(AND(G31<>"",G31<>0),D31/G31,"") | J31: =IF(AND(G31<>"",G31<>0),E31/G31,"") | N31: =IF(AND(I31<>"",I31<>0),G31/I31,"") | O31: =D31/P31 -> #DIV/0! | P31: =$I$8*V31*W31/SUMPRODUCT($W$25:$W$55,$V$25:$V$55) -> 0 | Q31: =$I$9*V31*W31/SUMPRODUCT($W$25:$W$55,$V$25:$V$55) -> 0 | R31: =IF($I$12="","",Q31/$I$12) -> 0 | S31: =IF(W31<>"",IF(D31<>"",D31,($I$8-SUM($S$25:S30))*V31*W31/SUMPRODUCT($W31:$W$55,$V31:$V$55)),"") | T31: =IF(W31<>"",IF(E31<>"",E31,($I$9-SUM($T$25:T30))*V31*W31/SUMPRODUCT($W31:$W$55,$V31:$V$55)),"") | U31: =IF(W31<>"",IF($I$12<>"",IF(G31<>"",G31,($I$9/$I$12-SUM($U$25:U30))*V31*W31/SUMPRODUCT($W31:$W$55,$V31:$V$55)),""),"")
F32: =IF(AND(E32<>"",E32<>0),D32/E32,"") | H32: =IF(AND(G32<>"",G32<>0),D32/G32,"") | J32: =IF(AND(G32<>"",G32<>0),E32/G32,"") | N32: =IF(AND(I32<>"",I32<>0),G32/I32,"") | O32: =D32/P32 -> #DIV/0! | P32: =$I$8*V32*W32/SUMPRODUCT($W$25:$W$55,$V$25:$V$55) -> 0 | Q32: =$I$9*V32*W32/SUMPRODUCT($W$25:$W$55,$V$25:$V$55) -> 0 | R32: =IF($I$12="","",Q32/$I$12) -> 0 | S32: =IF(W32<>"",IF(D32<>"",D32,($I$8-SUM($S$25:S31))*V32*W32/SUMPRODUCT($W32:$W$55,$V32:$V$55)),"") | T32: =IF(W32<>"",IF(E32<>"",E32,($I$9-SUM($T$25:T31))*V32*W32/SUMPRODUCT($W32:$W$55,$V32:$V$55)),"") | U32: =IF(W32<>"",IF($I$12<>"",IF(G32<>"",G32,($I$9/$I$12-SUM($U$25:U31))*V32*W32/SUMPRODUCT($W32:$W$55,$V32:$V$55)),""),"")
F33: =IF(AND(E33<>"",E33<>0),D33/E33,"") | H33: =IF(AND(G33<>"",G33<>0),D33/G33,"") | J33: =IF(AND(G33<>"",G33<>0),E33/G33,"") | N33: =IF(AND(I33<>"",I33<>0),G33/I33,"") | O33: =D33/P33 -> #DIV/0! | P33: =$I$8*V33*W33/SUMPRODUCT($W$25:$W$55,$V$25:$V$55) -> 0 | Q33: =$I$9*V33*W33/SUMPRODUCT($W$25:$W$55,$V$25:$V$55) -> 0 | R33: =IF($I$12="","",Q33/$I$12) -> 0 | S33: =IF(W33<>"",IF(D33<>"",D33,($I$8-SUM($S$25:S32))*V33*W33/SUMPRODUCT($W33:$W$55,$V33:$V$55)),"") | T33: =IF(W33<>"",IF(E33<>"",E33,($I$9-SUM($T$25:T32))*V33*W33/SUMPRODUCT($W33:$W$55,$V33:$V$55)),"") | U33: =IF(W33<>"",IF($I$12<>"",IF(G33<>"",G33,($I$9/$I$12-SUM($U$25:U32))*V33*W33/SUMPRODUCT($W33:$W$55,$V33:$V$55)),""),"")
F34: =IF(AND(E34<>"",E34<>0),D34/E34,"") | H34: =IF(AND(G34<>"",G34<>0),D34/G34,"") | J34: =IF(AND(G34<>"",G34<>0),E34/G34,"") | N34: =IF(AND(I34<>"",I34<>0),G34/I34,"") | O34: =D34/P34 -> #DIV/0! | P34: =$I$8*V34*W34/SUMPRODUCT($W$25:$W$55,$V$25:$V$55) -> 0 | Q34: =$I$9*V34*W34/SUMPRODUCT($W$25:$W$55,$V$25:$V$55) -> 0 | R34: =IF($I$12="","",Q34/$I$12) -> 0 | S34: =IF(W34<>"",IF(D34<>"",D34,($I$8-SUM($S$25:S33))*V34*W34/SUMPRODUCT($W34:$W$55,$V34:$V$55)),"") | T34: =IF(W34<>"",IF(E34<>"",E34,($I$9-SUM($T$25:T33))*V34*W34/SUMPRODUCT($W34:$W$55,$V34:$V$55)),"") | U34: =IF(W34<>"",IF($I$12<>"",IF(G34<>"",G34,($I$9/$I$12-SUM($U$25:U33))*V34*W34/SUMPRODUCT($W34:$W$55,$V34:$V$55)),""),"")
F35: =IF(AND(E35<>"",E35<>0),D35/E35,"") | H35: =IF(AND(G35<>"",G35<>0),D35/G35,"") | J35: =IF(AND(G35<>"",G35<>0),E35/G35,"") | N35: =IF(AND(I35<>"",I35<>0),G35/I35,"") | O35: =D35/P35 -> #DIV/0! | P35: =$I$8*V35*W35/SUMPRODUCT($W$25:$W$55,$V$25:$V$55) -> 0 | Q35: =$I$9*V35*W35/SUMPRODUCT($W$25:$W$55,$V$25:$V$55) -> 0 | R35: =IF($I$12="","",Q35/$I$12) -> 0 | S35: =IF(W35<>"",IF(D35<>"",D35,($I$8-SUM($S$25:S34))*V35*W35/SUMPRODUCT($W35:$W$55,$V35:$V$55)),"") | T35: =IF(W35<>"",IF(E35<>"",E35,($I$9-SUM($T$25:T34))*V35*W35/SUMPRODUCT($W35:$W$55,$V35:$V$55)),"") | U35: =IF(W35<>"",IF($I$12<>"",IF(G35<>"",G35,($I$9/$I$12-SUM($U$25:U34))*V35*W35/SUMPRODUCT($W35:$W$55,$V35:$V$55)),""),"")
F36: =IF(AND(E36<>"",E36<>0),D36/E36,"") | H36: =IF(AND(G36<>"",G36<>0),D36/G36,"") | J36: =IF(AND(G36<>"",G36<>0),E36/G36,"") | N36: =IF(AND(I36<>"",I36<>0),G36/I36,"") | O36: =D36/P36 -> #DIV/0! | P36: =$I$8*V36*W36/SUMPRODUCT($W$25:$W$55,$V$25:$V$55) -> 0 | Q36: =$I$9*V36*W36/SUMPRODUCT($W$25:$W$55,$V$25:$V$55) -> 0 | R36: =IF($I$12="","",Q36/$I$12) -> 0 | S36: =IF(W36<>"",IF(D36<>"",D36,($I$8-SUM($S$25:S35))*V36*W36/SUMPRODUCT($W36:$W$55,$V36:$V$55)),"") | T36: =IF(W36<>"",IF(E36<>"",E36,($I$9-SUM($T$25:T35))*V36*W36/SUMPRODUCT($W36:$W$55,$V36:$V$55)),"") | U36: =IF(W36<>"",IF($I$12<>"",IF(G36<>"",G36,($I$9/$I$12-SUM($U$25:U35))*V36*W36/SUMPRODUCT($W36:$W$55,$V36:$V$55)),""),"")
F37: =IF(AND(E37<>"",E37<>0),D37/E37,"") | H37: =IF(AND(G37<>"",G37<>0),D37/G37,"") | J37: =IF(AND(G37<>"",G37<>0),E37/G37,"") | N37: =IF(AND(I37<>"",I37<>0),G37/I37,"") | O37: =D37/P37 -> #DIV/0! | P37: =$I$8*V37*W37/SUMPRODUCT($W$25:$W$55,$V$25:$V$55) -> 0 | Q37: =$I$9*V37*W37/SUMPRODUCT($W$25:$W$55,$V$25:$V$55) -> 0 | R37: =IF($I$12="","",Q37/$I$12) -> 0 | S37: =IF(W37<>"",IF(D37<>"",D37,($I$8-SUM($S$25:S36))*V37*W37/SUMPRODUCT($W37:$W$55,$V37:$V$55)),"") | T37: =IF(W37<>"",IF(E37<>"",E37,($I$9-SUM($T$25:T36))*V37*W37/SUMPRODUCT($W37:$W$55,$V37:$V$55)),"") | U37: =IF(W37<>"",IF($I$12<>"",IF(G37<>"",G37,($I$9/$I$12-SUM($U$25:U36))*V37*W37/SUMPRODUCT($W37:$W$55,$V37:$V$55)),""),"")
F38: =IF(AND(E38<>"",E38<>0),D38/E38,"") | H38: =IF(AND(G38<>"",G38<>0),D38/G38,"") | J38: =IF(AND(G38<>"",G38<>0),E38/G38,"") | N38: =IF(AND(I38<>"",I38<>0),G38/I38,"") | O38: =D38/P38 -> #DIV/0! | P38: =$I$8*V38*W38/SUMPRODUCT($W$25:$W$44,$V$25:$V$44) -> 0 | Q38: =$I$9*V38*W38/SUMPRODUCT($W$25:$W$44,$V$25:$V$44) -> 0 | R38: =IF($I$12="","",Q38/$I$12) -> 0 | S38: =IF(W38<>"",IF(D38<>"",D38,($I$8-SUM($S$25:S37))*V38*W38/SUMPRODUCT($W38:$W$55,$V38:$V$55)),"") | T38: =IF(W38<>"",IF(E38<>"",E38,($I$9-SUM($T$25:T37))*V38*W38/SUMPRODUCT($W38:$W$55,$V38:$V$55)),"") | U38: =IF(W38<>"",IF($I$12<>"",IF(G38<>"",G38,($I$9/$I$12-SUM($U$25:U37))*V38*W38/SUMPRODUCT($W38:$W$55,$V38:$V$55)),""),"")
F39: =IF(AND(E39<>"",E39<>0),D39/E39,"") | H39: =IF(AND(G39<>"",G39<>0),D39/G39,"") | J39: =IF(AND(G39<>"",G39<>0),E39/G39,"") | N39: =IF(AND(I39<>"",I39<>0),G39/I39,"") | O39: =D39/P39 -> #DIV/0! | P39: =$I$8*V39*W39/SUMPRODUCT($W$25:$W$44,$V$25:$V$44) -> 0 | Q39: =$I$9*V39*W39/SUMPRODUCT($W$25:$W$44,$V$25:$V$44) -> 0 | R39: =IF($I$12="","",Q39/$I$12) -> 0 | S39: =IF(W39<>"",IF(D39<>"",D39,($I$8-SUM($S$25:S38))*V39*W39/SUMPRODUCT($W39:$W$55,$V39:$V$55)),"") | T39: =IF(W39<>"",IF(E39<>"",E39,($I$9-SUM($T$25:T38))*V39*W39/SUMPRODUCT($W39:$W$55,$V39:$V$55)),"") | U39: =IF(W39<>"",IF($I$12<>"",IF(G39<>"",G39,($I$9/$I$12-SUM($U$25:U38))*V39*W39/SUMPRODUCT($W39:$W$55,$V39:$V$55)),""),"")
F40: =IF(AND(E40<>"",E40<>0),D40/E40,"") | H40: =IF(AND(G40<>"",G40<>0),D40/G40,"") | J40: =IF(AND(G40<>"",G40<>0),E40/G40,"") | N40: =IF(AND(I40<>"",I40<>0),G40/I40,"") | O40: =D40/P40 -> #DIV/0! | P40: =$I$8*V40*W40/SUMPRODUCT($W$25:$W$47,$V$25:$V$47) -> 0 | Q40: =$I$9*V40*W40/SUMPRODUCT($W$25:$W$47,$V$25:$V$47) -> 0 | R40: =IF($I$12="", "", Q40/$I$12) -> 0 | S40: =IF(W40<>"",IF(D40<>"",D40,($I$8-SUM($S$25:S39))*V40*W40/SUMPRODUCT($W40:$W$55,$V40:$V$55)),"") | T40: =IF(W40<>"",IF(E40<>"",E40,($I$9-SUM($T$25:T39))*V40*W40/SUMPRODUCT($W40:$W$55,$V40:$V$55)),"") | U40: =IF(W40<>"",IF($I$12<>"",IF(G40<>"",G40,($I$9/$I$12-SUM($U$25:U39))*V40*W40/SUMPRODUCT($W40:$W$55,$V40:$V$55)),""),"")
F41: =IF(AND(E41<>"",E41<>0),D41/E41,"") | H41: =IF(AND(G41<>"",G41<>0),D41/G41,"") | J41: =IF(AND(G41<>"",G41<>0),E41/G41,"") | N41: =IF(AND(I41<>"",I41<>0),G41/I41,"") | O41: =D41/P41 -> #DIV/0! | P41: =$I$8*V41*W41/SUMPRODUCT($W$25:$W$47,$V$25:$V$47) -> 0 | Q41: =$I$9*V41*W41/SUMPRODUCT($W$25:$W$47,$V$25:$V$47) -> 0 | R41: =IF($I$12="", "", Q41/$I$12) -> 0 | S41: =IF(W41<>"",IF(D41<>"",D41,($I$8-SUM($S$25:S40))*V41*W41/SUMPRODUCT($W41:$W$55,$V41:$V$55)),"") | T41: =IF(W41<>"",IF(E41<>"",E41,($I$9-SUM($T$25:T40))*V41*W41/SUMPRODUCT($W41:$W$55,$V41:$V$55)),"") | U41: =IF(W41<>"",IF($I$12<>"",IF(G41<>"",G41,($I$9/$I$12-SUM($U$25:U40))*V41*W41/SUMPRODUCT($W41:$W$55,$V41:$V$55)),""),"")
F42: =IF(AND(E42<>"",E42<>0),D42/E42,"") | H42: =IF(AND(G42<>"",G42<>0),D42/G42,"") | J42: =IF(AND(G42<>"",G42<>0),E42/G42,"") | N42: =IF(AND(I42<>"",I42<>0),G42/I42,"") | O42: =D42/P42 -> #DIV/0! | P42: =$I$8*V42*W42/SUMPRODUCT($W$25:$W$47,$V$25:$V$47) -> 0 | Q42: =$I$9*V42*W42/SUMPRODUCT($W$25:$W$47,$V$25:$V$47) -> 0 | R42: =IF($I$12="", "", Q42/$I$12) -> 0 | S42: =IF(W42<>"",IF(D42<>"",D42,($I$8-SUM($S$25:S41))*V42*W42/SUMPRODUCT($W42:$W$55,$V42:$V$55)),"") | T42: =IF(W42<>"",IF(E42<>"",E42,($I$9-SUM($T$25:T41))*V42*W42/SUMPRODUCT($W42:$W$55,$V42:$V$55)),"") | U42: =IF(W42<>"",IF($I$12<>"",IF(G42<>"",G42,($I$9/$I$12-SUM($U$25:U41))*V42*W42/SUMPRODUCT($W42:$W$55,$V42:$V$55)),""),"")
F43: =IF(AND(E43<>"",E43<>0),D43/E43,"") | H43: =IF(AND(G43<>"",G43<>0),D43/G43,"") | J43: =IF(AND(G43<>"",G43<>0),E43/G43,"") | N43: =IF(AND(I43<>"",I43<>0),G43/I43,"") | O43: =D43/P43 -> #DIV/0! | P43: =$I$8*V43*W43/SUMPRODUCT($W$25:$W$44, $V$25:$V$44) -> 0 | Q43: =$I$9*V43*W43/SUMPRODUCT($W$25:$W$44, $V$25:$V$44) -> 0 | R43: =IF($I$12="", "", Q43/$I$12) -> 0 | S43: =IF(W43<>"",IF(D43<>"",D43,($I$8-SUM($S$25:S42))*V43*W43/SUMPRODUCT($W43:$W$55,$V43:$V$55)),"") | T43: =IF(W43<>"",IF(E43<>"",E43,($I$9-SUM($T$25:T42))*V43*W43/SUMPRODUCT($W43:$W$55,$V43:$V$55)),"") | U43: =IF(W43<>"",IF($I$12<>"",IF(G43<>"",G43,($I$9/$I$12-SUM($U$25:U42))*V43*W43/SUMPRODUCT($W43:$W$55,$V43:$V$55)),""),"")
F44: =IF(AND(E44<>"",E44<>0),D44/E44,"") | H44: =IF(AND(G44<>"",G44<>0),D44/G44,"") | J44: =IF(AND(G44<>"",G44<>0),E44/G44,"") | N44: =IF(AND(I44<>"",I44<>0),G44/I44,"") | O44: =D44/P44 -> #DIV/0! | P44: =$I$8*V44*W44/SUMPRODUCT($W$25:$W$44, $V$25:$V$44) -> 0 | Q44: =$I$9*V44*W44/SUMPRODUCT($W$25:$W$44, $V$25:$V$44) -> 0 | R44: =IF($I$12="", "", Q44/$I$12) -> 0 | S44: =IF(W44<>"",IF(D44<>"",D44,($I$8-SUM($S$25:S43))*V44*W44/SUMPRODUCT($W44:$W$55,$V44:$V$55)),"") | T44: =IF(W44<>"",IF(E44<>"",E44,($I$9-SUM($T$25:T43))*V44*W44/SUMPRODUCT($W44:$W$55,$V44:$V$55)),"") | U44: =IF(W44<>"",IF($I$12<>"",IF(G44<>"",G44,($I$9/$I$12-SUM($U$25:U43))*V44*W44/SUMPRODUCT($W44:$W$55,$V44:$V$55)),""),"")
F45: =IF(AND(E45<>"",E45<>0),D45/E45,"") | H45: =IF(AND(G45<>"",G45<>0),D45/G45,"") | J45: =IF(AND(G45<>"",G45<>0),E45/G45,"") | N45: =IF(AND(I45<>"",I45<>0),G45/I45,"") | O45: =D45/P45 -> #DIV/0! | P45: =$I$8*V45*W45/SUMPRODUCT($W$25:$W$44, $V$25:$V$44) -> 0 | Q45: =$I$9*V45*W45/SUMPRODUCT($W$25:$W$44, $V$25:$V$44) -> 0 | R45: =IF($I$12="", "", Q45/$I$12) -> 0 | S45: =IF(W45<>"",IF(D45<>"",D45,($I$8-SUM($S$25:S44))*V45*W45/SUMPRODUCT($W45:$W$55,$V45:$V$55)),"") | T45: =IF(W45<>"",IF(E45<>"",E45,($I$9-SUM($T$25:T44))*V45*W45/SUMPRODUCT($W45:$W$55,$V45:$V$55)),"") | U45: =IF(W45<>"",IF($I$12<>"",IF(G45<>"",G45,($I$9/$I$12-SUM($U$25:U44))*V45*W45/SUMPRODUCT($W45:$W$55,$V45:$V$55)),""),"")
F46: =IF(AND(E46<>"",E46<>0),D46/E46,"") | H46: =IF(AND(G46<>"",G46<>0),D46/G46,"") | J46: =IF(AND(G46<>"",G46<>0),E46/G46,"") | N46: =IF(AND(I46<>"",I46<>0),G46/I46,"") | O46: =D46/P46 -> #DIV/0! | P46: =$I$8*V46*W46/SUMPRODUCT($W$25:$W$44, $V$25:$V$44) -> 0 | Q46: =$I$9*V46*W46/SUMPRODUCT($W$25:$W$44, $V$25:$V$44) -> 0 | R46: =IF($I$12="", "", Q46/$I$12) -> 0 | S46: =IF(W46<>"",IF(D46<>"",D46,($I$8-SUM($S$25:S45))*V46*W46/SUMPRODUCT($W46:$W$55,$V46:$V$55)),"") | T46: =IF(W46<>"",IF(E46<>"",E46,($I$9-SUM($T$25:T45))*V46*W46/SUMPRODUCT($W46:$W$55,$V46:$V$55)),"") | U46: =IF(W46<>"",IF($I$12<>"",IF(G46<>"",G46,($I$9/$I$12-SUM($U$25:U45))*V46*W46/SUMPRODUCT($W46:$W$55,$V46:$V$55)),""),"")
F47: =IF(AND(E47<>"",E47<>0),D47/E47,"") | H47: =IF(AND(G47<>"",G47<>0),D47/G47,"") | J47: =IF(AND(G47<>"",G47<>0),E47/G47,"") | N47: =IF(AND(I47<>"",I47<>0),G47/I47,"") | O47: =D47/P47 -> #DIV/0! | P47: =$I$8*V47*W47/SUMPRODUCT($W$25:$W$55,$V$25:$V$55) -> 0 | Q47: =$I$9*V47*W47/SUMPRODUCT($W$25:$W$55,$V$25:$V$55) -> 0 | R47: =IF($I$12="","",Q47/$I$12) -> 0 | S47: =IF(W47<>"",IF(D47<>"",D47,($I$8-SUM($S$25:S46))*V47*W47/SUMPRODUCT($W47:$W$55,$V47:$V$55)),"") | T47: =IF(W47<>"",IF(E47<>"",E47,($I$9-SUM($T$25:T46))*V47*W47/SUMPRODUCT($W47:$W$55,$V47:$V$55)),"") | U47: =IF(W47<>"",IF($I$12<>"",IF(G47<>"",G47,($I$9/$I$12-SUM($U$25:U46))*V47*W47/SUMPRODUCT($W47:$W$55,$V47:$V$55)),""),"")
B48: итого | D48: =SUM(D25:D47) -> 86196 | E48: =SUM(E25:E47) -> 25 | F48: =IF(AND(E48<>"",E48<>0),D48/E48,"") -> 3447.84 | G48: =SUM(G25:G47) -> 12 | H48: =IF(AND(G48<>"",G48<>0),D48/G48,"") -> 7183 | I48: =SUM(I25:I47) -> 42 | J48: =IF(AND(G48<>"",G48<>0),E48/G48,"") -> 2.0833333 | K48: =SUM(K25:K47) -> 0 | L48: =SUM(L25:L47) -> 0 | M48: =SUM(M25:M47) -> 0 | N48: =IF(AND(I48<>"",I48<>0),G48/I48,"") -> 0.28571429 | O48: =D48/P48 -> 1.078621 | P48: =SUM(P25:P47) -> 79913.15 | Q48: =SUM(Q25:Q47) -> 20.805298 | R48: =SUM(R25:R47) -> 10.402649 | S48: =SUM(S25:S47) -> 78513 | T48: =SUM(T25:T47) -> 23 | U48: =SUM(U25:U47) -> 11
D49: =SUMIF(D25:D47,"",P25:P47)+D48 -> 86196
D51: =D27+D28 -> 14866

Sheet Вед-ть ПК1
A1: =График!B1 -> Февраль, 2025
A2: =График!B3 -> ул. Набережная Ленина, 18 | D2: =График!B4 -> GL-0005
A3: Сотрудник | D3: Выплачено на карту | E3: Выплачено наличными по платежной ведомости | F3: Дополнительные начисления, доплаты | G3: Оклад | H3: Бонусная часть от личных продаж | I3: Бонусная часть от общих продаж | J3: Базовый бонус за выполнение плана | K3: Итого: | L3: Вычеты | M3: Итого к выдаче с учетом авансов и вычетов | N3: Подпись
A4: =График!B30 -> 0 | D4: 16376.53 | F4: =H8+H9 -> 2576.17 | G4: =D12 -> 0 | H4: =D19 -> 0 | I4: =L19 -> 0 | J4: =L12 -> 0 | K4: =H4+J4+G4+F4+I4 -> 2576.17 | L4: =C8+C9+C10 -> 4246 | M4: =K4-L4-D4-E4 -> -18046.36
B6: Вычеты | G6: Доп начисления
B7: Дата | C7: Сумма | D7: Описание | G7: Дата | H7: Сумма | J7: Описание
B8: 45679 | C8: 2447 | D8: НДФЛ январь 2025 | G8: 45679 | H8: 400 | J8: Оплата 4 часа 31.12.2024
B9: 45679 | C9: 1799 | D9: Форма зима 2024 | G9: 45679 | H9: =217617*0.01 -> 2176.17 | J9: Административный %
A12: Оклад: | D12: =G16 -> 0 | I12: Базовый бонус за выполнение плана | L12: =L16+L17 -> 0
B14: Оклад: | J14: Базовый бонус за выполнение плана
B15: Дней | C15: Магазин | D15: Должность | E15: Зачислено часов | F15: Ставка за час, руб | G15: Начислено за день, руб | J15: Магазин | K15: КВП | L15: Начисленный ББ
B16: =График!AI30 -> 0 | C16: =A2 -> ул. Набережная Ленина, 18 | D16: ПК | E16: =График!AJ30 -> 0 | F16: 100 | G16: =E16*F16 -> 0 | J16: =График!B3 -> ул. Набережная Ленина, 18 | K16: 0.5284 | L16: 0
A19: БонуснаяЧасть | D19: =G24 -> 0 | I19: Бонусная часть от общих продаж | L19: =N24 -> 0
B22: Бонус от личных продаж по категории товара | I22: Бонус от общих продаж
B23: Сотрудник | C23: Магазин | E23: Процент от продажи | F23: Продано на сумму, руб | G23: Начисленный бонус от продаж, руб | I23: Сотрудник | J23: Магазин | K23: Кол-во отработанных личных часов | L23: Кол-во отработанных общих часов | M23: Процент от продажи | N23: Начисленный бонус от продаж, руб
B24: =A4 -> 0 | C24: =A2 -> ул. Набережная Ленина, 18 | E24: 0.04 | F24: =ПК1!J8 -> 0 | G24: =F24*E24 -> 0 | I24: =B24 -> 0 | J24: =C24 -> ул. Набережная Ленина, 18 | K24: =E16 -> 0 | L24: 351 | M24: 0.02 | N24: =1162485*M24*K24/L24 -> 0
B25: =B24 -> 0 | N25: =1477363.14*M25*K25/L25 -> #DIV/0!

Sheet Вед-ть Рогалевич
A1: =График!B1 -> Февраль, 2025
A2: =График!B3 -> ул. Набережная Ленина, 18 | D2: =График!B4 -> GL-0005
A3: Сотрудник | D3: Выплачено на карту | E3: Выплачено наличными по платежной ведомости | F3: Дополнительные начисления, доплаты | G3: Оклад | H3: Бонусная часть от личных продаж | I3: Бонусная часть от общих продаж | J3: Базовый бонус за выполнение плана | K3: Итого: | L3: Вычеты | M3: Итого к выдаче с учетом авансов и вычетов | N3: Подпись
A4: =График!B29 -> Рогалевич Ирина | D4: =15000-C8 -> 13050 | F4: =H8+H9+G16+G24+L24 -> 0 | G4: =D11 -> 41250 | H4: =D18 -> 28924.52 | I4: =L18 -> 14739.071 | J4: =L11 -> 11550 | K4: =H4+J4+G4+F4+I4 -> 96463.591 | L4: =C8+C9 -> 1950 | M4: =K4-L4-D4-E4 -> 81463.591
B6: Вычеты | G6: Доп начисления
B7: Дата | C7: Сумма | D7: Описание | G7: Дата | H7: Сумма | J7: Описание
B8: 45716 | C8: 1950 | D8: НДФЛ февраль 2025
A11: Оклад: | D11: =G15 -> 41250 | I11: Базовый бонус за выполнение плана | L11: =L15+L16 -> 11550
B13: Оклад: | J13: Базовый бонус за выполнение плана
B14: Дней | C14: Магазин | D14: Должность | E14: Зачислено часов | F14: Ставка за час, руб | G14: Начислено за день, руб | J14: Магазин | K14: КВП | L14: Начисленный ББ
B15: =График!AI29 -> 26 | C15: =A2 -> ул. Набережная Ленина, 18 | D15: ПК | E15: =График!AJ29 -> 275 | F15: 150 | G15: =E15*F15 -> 41250 | J15: =График!B3 -> ул. Набережная Ленина, 18 | K15: 1 | L15: 11550
D16: ПК | G16: =E16*F16 -> 0
A18: БонуснаяЧасть | D18: =G23 -> 28924.52 | I18: Бонусная часть от общих продаж | L18: =N23 -> 14739.071
B21: Бонус от личных продаж по категории товара | I21: Бонус от общих продаж
B22: Сотрудник | C22: Магазин | E22: Процент от продажи | F22: Продано на сумму, руб | G22: Начисленный бонус от продаж, руб | I22: Сотрудник | J22: Магазин | K22: Кол-во отработанных личных часов | L22: Кол-во отработанных общих часов | M22: Процент от продажи | N22: Начисленный бонус от продаж, руб
B23: =A4 -> Рогалевич Ирина | C23: =A2 -> ул. Набережная Ленина, 18 | E23: 0.04 | F23: ='Рогалевич И. Е.'!J8 -> 723113 | G23: =F23*E23 -> 28924.52 | I23: =B23 -> Рогалевич Ирина | J23: =C23 -> ул. Набережная Ленина, 18 | K23: =E15 -> 275 | L23: =График!AJ31 -> 302 | M23: 0.02 | N23: ='Ялта, Ленина, 18'!J8*M23*K23/L23 -> 14739.071
B24: =B23 -> Рогалевич Ирина | C24: =C16 -> 0 | G24: =F24*E24 -> 0 | N24: =1477363.14*M24*K24/L24 -> #DIV/0!

Sheet График
B1: Февраль, 2025 | T1: в
B2: г. Ялта
B3: ул. Набережная Ленина, 18
B4: GL-0005
B5: 10.00-21.00
B6: ФОТ | C6: Кол-во дней в месяц | AK6: 30
B7: =BT31*100/BH31 -> #DIV/0!
D8: сб | E8: вс | F8: пн | G8: вт | H8: ср | I8: чт | J8: пт | K8: сб | L8: вс | M8: пн | N8: вт | O8: ср | P8: чт | Q8: пт | R8: сб | S8: вс | T8: пн | U8: вт | V8: ср | W8: чт | X8: пт | Y8: сб | Z8: вс | AA8: пн | AB8: вт | AC8: ср | AD8: чт | AE8: пт | AJ8: Часы | AK8: Выходные | AL8: Отпуск | AM8: Больничный (официальный) | AN8: Дни стажировки
A10: № | B10: ФИО | C10: Должность | D10: 1 | E10: 2 | F10: 3 | G10: 4 | H10: 5 | I10: 6 | J10: 7 | K10: 8 | L10: 9 | M10: 10 | N10: 11 | O10: 12 | P10: 13 | Q10: 14 | R10: 15 | S10: 16 | T10: 17 | U10: 18 | V10: 19 | W10: 20 | X10: 21 | Y10: 22 | Z10: 23 | AA10: 24 | AB10: 25 | AC10: 26 | AD10: 27 | AE10: 28 | AF10: 29 | AG10: 30 | AH10: 31 | AI10: Дни
A11: 20 | AI11: 0 | AJ11: 0 | AK11: 0 | AL11: 0 | AM11: 0 | AN11: 0
A12: 19 | AI12: 0 | AJ12: 0 | AK12: 0 | AL12: 0 | AM12: 0 | AN12: 0
A13: 18 | AI13: 0 | AJ13: 0 | AK13: 0 | AL13: 0 | AM13: 0 | AN13: 0
A14: 17 | AI14: 0 | AJ14: 0 | AK14: 0 | AL14: 0 | AM14: 0 | AN14: 0
A15: 16 | AI15: 0 | AJ15: 0 | AK15: 0 | AL15: 0 | AM15: 0 | AN15: 0
A16: 15 | AI16: 0 | AJ16: 0 | AK16: 0 | AL16: 0 | AM16: 0 | AN16: 0
A17: 14 | AI17: 0 | AJ17: 0 | AK17: 0 | AL17: 0 | AM17: 0 | AN17: 0
A18: 13 | AI18: 0 | AJ18: 0 | AK18: 0 | AL18: 0 | AM18: 0 | AN18: 0
A19: 12 | AI19: 0 | AJ19: 0 | AK19: 0 | AL19: 0 | AM19: 0 | AN19: 0
A20: 11 | AI20: 0 | AJ20: 0 | AK20: 0 | AL20: 0 | AM20: 0 | AN20: 0
A21: 10 | AI21: 0 | AJ21: 0 | AK21: 0 | AL21: 0 | AM21: 0 | AN21: 0
A22: 9 | AI22: =COUNTIF(D22:AH22, ">0") -> 0 | AJ22: 0 | AK22: 0 | AL22: 0 | AM22: 0 | AN22: 0
A23: 8 | AI23: =COUNTIF(D23:AH23, ">0") -> 0 | AJ23: 0 | AK23: 0 | AL23: 0 | AM23: 0 | AN23: 0
A24: 7 | AI24: =COUNTIF(D24:AH24, ">0") -> 0 | AJ24: 0 | AK24: 0 | AL24: 0 | AM24: 0 | AN24: 0
A25: 6 | AI25: =COUNTIF(D25:AH25,">0") -> 0 | AJ25: =SUMIF(D25:AH25,">0") -> 0 | AK25: =COUNTIF(D25:AH25,"В") -> 0 | AL25: =COUNTIF(E25:AI25,"о") -> 0 | AM25: =COUNTIF(F25:AJ25,"б") -> 0 | AN25: 0
A26: 5 | AI26: =COUNTIF(D26:AH26, ">0") -> 0 | AJ26: =SUMIF(D26:AH26, ">0") -> 0 | AK26: =COUNTIF(D26:AH26, "В") -> 0 | AL26: 0 | AM26: 0 | AN26: 0
A27: 4 | B27: Орешникова Елена | AC27: 5 | AI27: =COUNTIF(D27:AH27,">0") -> 1 | AJ27: =SUMIF(D27:AH27,">0") -> 5 | AK27: =COUNTIF(D27:AH27,"В") -> 0 | AL27: =COUNTIF(E27:AI27,"о") -> 0 | AM27: =COUNTIF(F27:AJ27,"б") -> 0 | AN27: 0
A28: 3 | B28: Стекольщикова Алла | C28: ДМ | D28: 11 | E28: 11 | AI28: =COUNTIF(D28:AH28,">0") -> 2 | AJ28: =SUMIF(D28:AH28,">0") -> 22 | AK28: =COUNTIF(D28:AH28,"В") -> 0 | AL28: =COUNTIF(E28:AI28,"о") -> 0 | AM28: =COUNTIF(F28:AJ28,"б") -> 0 | AN28: 0
A29: 2 | B29: Рогалевич Ирина | C29: ПК | D29: в | E29: в | F29: 11 | G29: 11 | H29: 11 | I29: 11 | J29: 11 | K29: 9 | L29: 9 | M29: 11 | N29: 11 | O29: 11 | P29: 11 | Q29: 11 | R29: 11 | S29: 9.5 | T29: 11 | U29: 11 | V29: 11 | W29: 11 | X29: 11 | Y29: 11 | Z29: 10.5 | AA29: 11 | AB29: 11 | AC29: 6 | AD29: 11 | AE29: 11 | AI29: =COUNTIF(D29:AH29,">0") -> 26 | AJ29: =SUMIF(D29:AH29,">0") -> 275 | AK29: =COUNTIF(D29:AH29,"В") -> 2 | AL29: =COUNTIF(E29:AI29,"о") -> 0 | AM29: =COUNTIF(F29:AJ29,"б") -> 0 | AN29: 0
A30: 1 | AI30: =COUNTIF(D30:AH30, ">0") -> 0 | AJ30: =SUMIF(D30:AH30, ">0") -> 0 | AK30: =COUNTIF(D30:AH30, "В") -> 0 | AL30: =COUNTIF(E30:AI30, "о") -> 0 | AM30: =COUNTIF(F30:AJ30, "б") -> 0 | AN30: 0
B31: Итого магазин | D31: =COUNTIF(D11:D30, ">0") -> 1 | E31: =COUNTIF(E11:E30, ">0") -> 1 | F31: =COUNTIF(F11:F30, ">0") -> 1 | G31: =COUNTIF(G11:G30, ">0") -> 1 | H31: =COUNTIF(H11:H30, ">0") -> 1 | I31: =COUNTIF(I11:I30, ">0") -> 1 | J31: =COUNTIF(J11:J30, ">0") -> 1 | K31: =COUNTIF(K11:K29, ">0") -> 1 | L31: =COUNTIF(L11:L30, ">0") -> 1 | M31: =COUNTIF(M11:M30, ">0") -> 1 | N31: =COUNTIF(N11:N30, ">0") -> 1 | O31: =COUNTIF(O11:O30, ">0") -> 1 | P31: =COUNTIF(P11:P30, ">0") -> 1 | Q31: =COUNTIF(Q11:Q30, ">0") -> 1 | R31: =COUNTIF(R11:R30, ">0") -> 1 | S31: =COUNTIF(S11:S30, ">0") -> 1 | ... AH31: =COUNTIF(AH11:AH30, ">0") -> 0 | AI31: =SUM(AI11:AI30) -> 29 | AJ31: =SUM(AJ11:AJ30) -> 302 | AK31: =SUM(AK11:AK30) -> 2 | AL31: =SUM(AL11:AL30) -> 0 | AM31: =SUM(AM11:AM30) -> 0 | AN31: =SUM(AN11:AN30) -> 0
