Workbook
Name маг: NA()

Sheet Ялта, Ленина, 18
B1: =TODAY()-1 -> 46060
B2: (отчетная дата)
C3: Осталось до выполнения плана!!! | I3: =График!B3 -> ул. Набережная Ленина, 18
C4: =I8-D56 -> 1352577.8 | E4: =IF(I8<>0, C4/I8, 0) -> 0.51905954
D5: =C4/(I14-J14) -> #DIV/0!
F6: Целевые показатели
F7: Показатель | I7: План | J7: Факт | K7: % выполнения | L7: Прогноз выполнения | M7: % выполнения по прогнозу | N7: Отклонение | O7: Факт аналогичного месяца прошлого года | P7: Отклонение LFL
F8: Выручка | I8: =I11*I12*I13 -> 2605824 | J8: =D56 -> 1253246.2 | K8: =IF(AND(I8<>"",I8<>0,J8<>""),J8/I8,"") -> 0.48094046 | L8: =IF(SUMIF($D$25:$D$55,">=0",$R$25:$R$55)<>0,I8*D56/SUMIF($D$25:$D$55,">=0",$R$25:$R$55),0) -> 1493405.3 | M8: =IF(AND(I8<>"", I8<>0, L8<>"", L8<>0), L8/I8, "") -> 0.57310289 | N8: =IF(AND(J8<>0, J8<>"", I8<>0, I8<>""), L8-I8, "") -> -1112418.7 | P8: =IF(AND(O8<>"", O8<>0, L8<>"", L8<>0), -O8+L8, "") | Q8: =IF(AND(P8<>"", P8<>0, O8<>0, O8<>""), P8/O8, "")
F9: Кол-во изделий | I9: =I8/I11 -> 334.08 | J9: =E56 -> 143 | K9: =IF(AND(I9<>"", I9<>0, J9<>""), J9/I9, "") -> 0.42804119 | L9: =IF(SUMIF($E$25:$E$55, ">=0", $S$25:$S$55)<>0, I9*E56/SUMIF($E$25:$E$55, ">=0", $S$25:$S$55), 0) -> 170.40303 | M9: =IF(AND(I9<>"", I9<>0, L9<>"", L9<>0), L9/I9, "") -> 0.51006655 | N9: =IF(AND(J9<>0, J9<>"", I9<>0, I9<>""), L9-I9, "") -> -163.67697 | O9: =O8/O11 -> #DIV/0! | P9: =IF(AND(O9<>"", O9<>0, L9<>"", L9<>0), -O9+L9, "") -> #DIV/0! | Q9: =IF(AND(P9<>"", P9<>0, O9<>0, O9<>""), P9/O9, "") -> #DIV/0!
F10: Средний чек | I10: =I11*I12 -> 13572 | J10: =H56 -> 15863.876 | K10: =IF(AND(I10<>"", I10<>0, J10<>""), J10/I10, "") -> 1.168868 | L10: =J10 -> 15863.876 | M10: =IF(AND(I10<>"", I10<>0, L10<>"", L10<>0), L10/I10, "") -> 1.168868 | N10: =IF(AND(J10<>0, J10<>"", I10<>0, I10<>""), L10-I10, "") -> 2291.8759 | O10: =O11*O12 -> 0 | P10: =IF(AND(O10<>"", O10<>0, L10<>"", L10<>0), -O10+L10, "") | Q10: =IF(AND(P10<>"", P10<>0, O10<>0, O10<>""), P10/O10, "") | U10: =L23 -> IS | X10: =M23 -> Agafi
F11: Средняя стоимость изделия | I11: 7800 | J11: =F56 -> 8763.9594 | K11: =IF(AND(I11<>"", I11<>0, J11<>""), J11/I11, "") -> 1.1235845 | L11: =IF(L9>0, L8/L9, "") -> 8763.9594 | M11: =IF(AND(I11<>"", I11<>0, L11<>"", L11<>0), L11/I11, "") -> 1.1235845 | N11: =IF(AND(J11<>0, J11<>"", I11<>0, I11<>""), L11-I11, "") -> 963.95944 | P11: =IF(AND(O11<>"", O11<>0, L11<>"", L11<>0), -O11+L11, "") | Q11: =IF(AND(P11<>"", P11<>0, O11<>0, O11<>""), P11/O11, "")
F12: Длина чека | I12: 1.74 | J12: =J56 -> 1.8101266 | K12: =IF(AND(I12<>"", I12<>0, J12<>""), J12/I12, "") -> 1.0403026 | L12: =J12 -> 1.8101266 | M12: =IF(AND(I12<>"", I12<>0, L12<>"", L12<>0), L12/I12, "") -> 1.0403026 | N12: =IF(AND(J12<>0, J12<>"", I12<>0, I12<>""), L12-I12, "") -> 0.070126582 | P12: =IF(AND(O12<>"", O12<>0, L12<>"", L12<>0), -O12+L12, "") | Q12: =IF(AND(P12<>"", P12<>0, O12<>0, O12<>""), P12/O12, "") | U12: 510000 | V12: =L56 -> 26123 | X12: 480000 | Y12: =M56 -> 50973
F13: Кол-во чеков | I13: =I17*I20 -> 192 | J13: =G56 -> 79 | K13: =IF(AND(I13<>"", I13<>0, J13<>""), J13/I13, "") -> 0.41145833 | L13: =IF(SUMIF($G$25:$G$55, ">=0", $T$25:$T$55)<>0, I13*G56/SUMIF($G$25:$G$55, ">=0", $T$25:$T$55), "") -> 94.138738 | M13: =IF(AND(I13<>"", I13<>0, L13<>"", L13<>0), L13/I13, "") -> 0.49030593 | N13: =IF(AND(J13<>0, J13<>"", I13<>0, I13<>""), L13-I13, "") -> -97.861262 | P13: =IF(AND(O13<>"", O13<>0, L13<>"", L13<>0), -O13+L13, "") | Q13: =IF(AND(P13<>"", P13<>0, O13<>0, O13<>""), P13/O13, "") | U13: =V12/U12 -> 0.051221569 | V13: =U13/J14*I14 -> 0.051221569 | X13: =Y12/X12 -> 0.10619375 | Y13: =X13/J14*I14 -> 0.10619375
F14: Кол-во смен | I14: 31 | J14: 31 | K14: =IF(AND(I14<>"", I14<>0, J14<>""), J14/I14, "") -> 1 | L14: =I14 -> 31 | M14: =IF(AND(I14<>"", I14<>0, L14<>"", L14<>0), L14/I14, "") -> 1 | N14: =IF(AND(J14<>0, J14<>"", I14<>0, I14<>""), L14-I14, "") -> 0 | P14: =IF(AND(O14<>"", O14<>0, L14<>"", L14<>0), -O14+L14, "") | Q14: =IF(AND(P14<>"", P14<>0, O14<>0, O14<>""), P14/O14, "")
F15: Средние продажи в смену | I15: =I8/I14 -> 84058.839 | J15: =J8/J14 -> 40427.297 | K15: =IF(AND(I15<>"", I15<>0, J15<>""), J15/I15, "") -> 0.48094046 | L15: =J15 -> 40427.297 | M15: =IF(AND(I15<>"", I15<>0, L15<>"", L15<>0), L15/I15, "") -> 0.48094046 | N15: =IF(AND(J15<>0, J15<>"", I15<>0, I15<>""), L15-I15, "") -> -43631.542 | P15: =IF(AND(O15<>"", O15<>0, L15<>"", L15<>0), -O15+L15, "") | Q15: =IF(AND(P15<>"", P15<>0, O15<>0, O15<>""), P15/O15, "")
F16: Отставание/Перевыполнение | J16: =J8-I15*J14 -> -1352577.8 | K16: =IF(AND(I16<>"", I16<>0, J16<>""), J16/I16, "") | L16: =J16 -> -1352577.8 | M16: =IF(AND(I16<>"", I16<>0, L16<>"", L16<>0), L16/I16, "") | N16: =IF(AND(J16<>0, J16<>"", I16<>0, I16<>""), L16-I16, "") | P16: =IF(AND(O16<>"", O16<>0, L16<>"", L16<>0), -O16+L16, "") | Q16: =IF(AND(P16<>"", P16<>0, O16<>0, O16<>""), P16/O16, "") | U16: =K23 -> UNOde50
F17: Трафик | I17: 1600 | J17: =I56 -> 912 | K17: =IF(AND(I17<>"", I17<>0, J17<>""), J17/I17, "") -> 0.57 | L17: =J17/J14*I14 -> 912 | M17: =IF(AND(I17<>"", I17<>0, L17<>"", L17<>0), L17/I17, "") -> 0.57 | N17: =IF(AND(J17<>0, J17<>"", I17<>0, I17<>""), L17-I17, "") -> -688 | P17: =IF(AND(O17<>"", O17<>0, L17<>"", L17<>0), -O17+L17, "") | Q17: =IF(AND(P17<>"", P17<>0, O17<>0, O17<>""), P17/O17, "")
K18: =IF(AND(I18<>"", I18<>0, J18<>""), J18/I18, "") | L18: =J18 -> 0 | M18: =IF(AND(I18<>"", I18<>0, L18<>"", L18<>0), L18/I18, "") | N18: =IF(AND(J18<>0, J18<>"", I18<>0, I18<>""), L18-I18, "") | O18: 0 | P18: =IF(AND(O18<>"", O18<>0, L18<>"", L18<>0), -O18+L18, "") | Q18: =IF(AND(P18<>"", P18<>0, O18<>0, O18<>""), P18/O18, "") | U18: 1020000 | V18: =K56 -> 326792
K19: =IF(AND(I19<>"", I19<>0, J19<>""), J19/I19, "") | L19: =J19 -> 0 | M19: =IF(AND(I19<>"", I19<>0, L19<>"", L19<>0), L19/I19, "") | N19: =IF(AND(J19<>0, J19<>"", I19<>0, I19<>""), L19-I19, "") | O19: 0 | P19: =IF(AND(O19<>"", O19<>0, L19<>"", L19<>0), -O19+L19, "") | Q19: =IF(AND(P19<>"", P19<>0, O19<>0, O19<>""), P19/O19, "") | U19: =V18/U18 -> 0.32038431 | V19: =U19/J14*I14 -> 0.32038431
F20: Конверсия план/факт | I20: 0.12 | J20: =P56 -> 0.086622807 | K20: =J20/I20 -> 0.72185673 | L20: =IF(AND(K8<>0, I14<>0, I56<>0), (I56*P56+(I56/K8-I56)*I20)/(I56/K8), 0) -> 0.10394756 | M20: =IF(AND(I20<>"", I20<>0, L20<>"", L20<>0), L20/I20, "") -> 0.86622964 | N20: =IF(AND(J20<>0, J20<>"", I20<>0, I20<>""), L20-I20, "") -> -0.016052443 | P20: =IF(AND(O20<>"", O20<>0, L20<>"", L20<>0), -O20+L20, "") | Q20: =IF(AND(P20<>"", P20<>0, O20<>0, O20<>""), P20/O20, "")
A22: Факт продаж за месяц | Q22: % выполнения дневного плана | R22: Раcпределение плана по дням
A23: Сотрудник | B23: Дата | C23: День недели | D23: Выручка (руб) | E23: Кол-во единиц (шт.) | F23: Средняя стоимость изделия (руб.) | G23: Количество чеков (шт.) | H23: Средняя сумма чека (руб.) | I23: Трафик | J23: Длина чека (шт.) | K23: UNOde50 | L23: IS | M23: Agafi | N23: Kalliope | O23: Raganella | P23: Конверсия (%) | R23: выручка, план | S23: кол-во ед, план | T23: Кол-во чеков, план | U23: выручка, скорректир.план | V23: кол-во ед, скорр. план | W23: кол-во чеков, скорр. план | X23: Коэфф. Дня Недели | Y23: Специфика месяца
B24: 1 | C24: 2 | D24: 3 | E24: 4 | F24: 5 | G24: 6 | H24: 7 | I24: 8 | J24: 9 | K24: 10 | L24: 11 | M24: 12 | N24: 13 | O24: 14 | P24: 15 | R24: 1 | S24: 2 | T24: 3 | U24: 4 | V24: 5 | W24: 6 | X24: 10 | Y24: 11
A25: Уразгильдеева | B25: 45992 | C25: пн | D25: 3293 | E25: 1 | F25: =IF(AND(E25<>"",E25<>0),D25/E25,"") -> 3293 | G25: 1 | H25: =IF(AND(G25<>"",G25<>0),D25/G25,"") -> 3293 | I25: 27 | J25: =IF(AND(G25<>"",G25<>0),E25/G25,"") -> 1 | P25: =IF(AND(I25<>"",I25<>0),G25/I25,"") -> 0.037037037 | Q25: =D25/R25 -> 0.040231815 | R25: =$I$8*X25*Y25/SUMPRODUCT($Y$25:$Y$55,$X$25:$X$55) -> 81850.645 | S25: =$I$9*X25*Y25/SUMPRODUCT($Y$25:$Y$55,$X$25:$X$55) -> 10.493672 | T25: =IF($I$12="","",S25/$I$12) -> 6.0308462 | U25: =IF(D25<>"",D25,R25) -> 3293 | V25: =IF(E25<>"",E25,S25) -> 1 | W25: =IF(G25<>"",G25,T25) -> 1 | X25: 0.9414554 | Y25: 0.9414554
A26: Уразгильдеева,Арапова | B26: 45993 | C26: вт | D26: 3555 | E26: 1 | F26: =IF(AND(E26<>"",E26<>0),D26/E26,"") -> 3555 | G26: 1 | H26: =IF(AND(G26<>"",G26<>0),D26/G26,"") -> 3555 | I26: 35 | J26: =IF(AND(G26<>"",G26<>0),E26/G26,"") -> 1 | P26: =IF(AND(I26<>"",I26<>0),G26/I26,"") -> 0.028571429 | Q26: =D26/R26 -> 0.052895014 | R26: =$I$8*X26*Y26/SUMPRODUCT($Y$25:$Y$55,$X$25:$X$55) -> 67208.603 | S26: =$I$9*X26*Y26/SUMPRODUCT($Y$25:$Y$55,$X$25:$X$55) -> 8.6164875 | T26: =IF($I$12="","",S26/$I$12) -> 4.9520043 | U26: =IF(Y26<>"",IF(D26<>"",D26,($I$8-SUM($U$25:U25))*X26*Y26/SUMPRODUCT($Y26:$Y$55,$X26:$X$55)),"") -> 3555 | V26: =IF(Y26<>"",IF(E26<>"",E26,($I$9-SUM($V$25:V25))*X26*Y26/SUMPRODUCT($Y26:$Y$55,$X26:$X$55)),"") -> 1 | W26: =IF(Y26<>"",IF(E26<>"",E26,($I$9-SUM($V$25:V25))*X26*Y26/SUMPRODUCT($Y26:$Y$55,$X26:$X$55)),"") -> 1 | X26: 0.85310234 | Y26: 0.85310234
A27: Уразгильдеева | B27: 45994 | C27: ср | D27: 47669 | E27: 3 | F27: =IF(AND(E27<>"",E27<>0),D27/E27,"") -> 15889.667 | G27: 2 | H27: =IF(AND(G27<>"",G27<>0),D27/G27,"") -> 23834.5 | I27: 30 | J27: =IF(AND(G27<>"",G27<>0),E27/G27,"") -> 1.5 | K27: 42669 | P27: =IF(AND(I27<>"",I27<>0),G27/I27,"") -> 0.066666667 | Q27: =D27/R27 -> 0.70926932 | R27: =$I$8*X27*Y27/SUMPRODUCT($Y$25:$Y$55,$X$25:$X$55) -> 67208.603 | S27: =$I$9*X27*Y27/SUMPRODUCT($Y$25:$Y$55,$X$25:$X$55) -> 8.6164875 | T27: =IF($I$12="","",S27/$I$12) -> 4.9520043 | U27: =IF(Y27<>"",IF(D27<>"",D27,($I$8-SUM($U$25:U26))*X27*Y27/SUMPRODUCT($Y27:$Y$55,$X27:$X$55)),"") -> 47669 | V27: =IF(Y27<>"",IF(E27<>"",E27,($I$9-SUM($V$25:V26))*X27*Y27/SUMPRODUCT($Y27:$Y$55,$X27:$X$55)),"") -> 3 | W27: =IF(Y27<>"",IF(E27<>"",E27,($I$9-SUM($V$25:V26))*X27*Y27/SUMPRODUCT($Y27:$Y$55,$X27:$X$55)),"") -> 3 | X27: 0.85310234 | Y27: 0.85310234
A28: Уразгильдеева | B28: 45995 | C28: чт | D28: 49966 | E28: 6 | F28: =IF(AND(E28<>"",E28<>0),D28/E28,"") -> 8327.6667 | G28: 3 | H28: =IF(AND(G28<>"",G28<>0),D28/G28,"") -> 16655.333 | I28: 45 | J28: =IF(AND(G28<>"",G28<>0),E28/G28,"") -> 2 | P28: =IF(AND(I28<>"",I28<>0),G28/I28,"") -> 0.066666667 | Q28: =D28/R28 -> 0.7434465 | R28: =$I$8*X28*Y28/SUMPRODUCT($Y$25:$Y$55,$X$25:$X$55) -> 67208.603 | S28: =$I$9*X28*Y28/SUMPRODUCT($Y$25:$Y$55,$X$25:$X$55) -> 8.6164875 | T28: =IF($I$12="","",S28/$I$12) -> 4.9520043 | U28: =IF(Y28<>"",IF(D28<>"",D28,($I$8-SUM($U$25:U27))*X28*Y28/SUMPRODUCT($Y28:$Y$55,$X28:$X$55)),"") -> 49966 | V28: =IF(Y28<>"",IF(E28<>"",E28,($I$9-SUM($V$25:V27))*X28*Y28/SUMPRODUCT($Y28:$Y$55,$X28:$X$55)),"") -> 6 | W28: =IF(Y28<>"",IF(E28<>"",E28,($I$9-SUM($V$25:V27))*X28*Y28/SUMPRODUCT($Y28:$Y$55,$X28:$X$55)),"") -> 6 | X28: 0.85310234 | Y28: 0.85310234
A29: Уразгильдеева,Арапова | B29: 45996 | C29: пт | D29: =40368+26123 -> 66491 | E29: 5 | F29: =IF(AND(E29<>"",E29<>0),D29/E29,"") -> 13298.2 | G29: 4 | H29: =IF(AND(G29<>"",G29<>0),D29/G29,"") -> 16622.75 | I29: 40 | J29: =IF(AND(G29<>"",G29<>0),E29/G29,"") -> 1.25 | K29: 28984 | L29: 26123 | P29: =IF(AND(I29<>"",I29<>0),G29/I29,"") -> 0.1 | Q29: =D29/R29 -> 0.99655761 | R29: =$I$8*X29*Y29/SUMPRODUCT($Y$25:$Y$55,$X$25:$X$55) -> 66720.678 | S29: =$I$9*X29*Y29/SUMPRODUCT($Y$25:$Y$55,$X$25:$X$55) -> 8.5539331 | T29: =IF($I$12="","",S29/$I$12) -> 4.9160535 | U29: =IF(Y29<>"",IF(D29<>"",D29,($I$8-SUM($U$25:U28))*X29*Y29/SUMPRODUCT($Y29:$Y$55,$X29:$X$55)),"") -> 66491 | V29: =IF(Y29<>"",IF(E29<>"",E29,($I$9-SUM($V$25:V28))*X29*Y29/SUMPRODUCT($Y29:$Y$55,$X29:$X$55)),"") -> 5 | W29: =IF(Y29<>"",IF(E29<>"",E29,($I$9-SUM($V$25:V28))*X29*Y29/SUMPRODUCT($Y29:$Y$55,$X29:$X$55)),"") -> 5 | X29: 0.85 | Y29: 0.85
A30: Уразгильдеева,Арапова | B30: 45997 | C30: сб | D30: 5893 | E30: 1 | F30: =IF(AND(E30<>"",E30<>0),D30/E30,"") -> 5893 | G30: 1 | H30: =IF(AND(G30<>"",G30<>0),D30/G30,"") -> 5893 | I30: 62 | J30: =IF(AND(G30<>"",G30<>0),E30/G30,"") -> 1 | P30: =IF(AND(I30<>"",I30<>0),G30/I30,"") -> 0.016129032 | Q30: =D30/R30 -> 0.063813687 | R30: =$I$8*X30*Y30/SUMPRODUCT($Y$25:$Y$55,$X$25:$X$55) -> 92346.96 | S30: =$I$9*X30*Y30/SUMPRODUCT($Y$25:$Y$55,$X$25:$X$55) -> 11.839354 | T30: =IF($I$12="","",S30/$I$12) -> 6.8042263 | U30: =IF(Y30<>"",IF(D30<>"",D30,($I$8-SUM($U$25:U29))*X30*Y30/SUMPRODUCT($Y30:$Y$55,$X30:$X$55)),"") -> 5893 | V30: =IF(Y30<>"",IF(E30<>"",E30,($I$9-SUM($V$25:V29))*X30*Y30/SUMPRODUCT($Y30:$Y$55,$X30:$X$55)),"") -> 1 | W30: =IF(Y30<>"",IF(E30<>"",E30,($I$9-SUM($V$25:V29))*X30*Y30/SUMPRODUCT($Y30:$Y$55,$X30:$X$55)),"") -> 1 | X30: 1 | Y30: 1
A31: Уразгильдеева,Арапова | B31: 45998 | C31: вс | D31: 18884 | E31: 2 | F31: =IF(AND(E31<>"",E31<>0),D31/E31,"") -> 9442 | G31: 1 | H31: =IF(AND(G31<>"",G31<>0),D31/G31,"") -> 18884 | I31: 31 | J31: =IF(AND(G31<>"",G31<>0),E31/G31,"") -> 2 | P31: =IF(AND(I31<>"",I31<>0),G31/I31,"") -> 0.032258065 | Q31: =D31/R31 -> 0.20448968 | R31: =$I$8*X31*Y31/SUMPRODUCT($Y$25:$Y$55,$X$25:$X$55) -> 92346.96 | S31: =$I$9*X31*Y31/SUMPRODUCT($Y$25:$Y$55,$X$25:$X$55) -> 11.839354 | T31: =IF($I$12="","",S31/$I$12) -> 6.8042263 | U31: =IF(Y31<>"",IF(D31<>"",D31,($I$8-SUM($U$25:U30))*X31*Y31/SUMPRODUCT($Y31:$Y$55,$X31:$X$55)),"") -> 18884 | V31: =IF(Y31<>"",IF(E31<>"",E31,($I$9-SUM($V$25:V30))*X31*Y31/SUMPRODUCT($Y31:$Y$55,$X31:$X$55)),"") -> 2 | W31: =IF(Y31<>"",IF(E31<>"",E31,($I$9-SUM($V$25:V30))*X31*Y31/SUMPRODUCT($Y31:$Y$55,$X31:$X$55)),"") -> 2 | X31: 1 | Y31: 1
A32: Уразгильдеева | B32: 45999 | C32: пн | D32: 12484 | E32: 2 | F32: =IF(AND(E32<>"",E32<>0),D32/E32,"") -> 6242 | G32: 1 | H32: =IF(AND(G32<>"",G32<>0),D32/G32,"") -> 12484 | I32: 39 | J32: =IF(AND(G32<>"",G32<>0),E32/G32,"") -> 2 | K32: 8490 | P32: =IF(AND(I32<>"",I32<>0),G32/I32,"") -> 0.025641026 | Q32: =D32/R32 -> 0.18575003 | R32: =$I$8*X32*Y32/SUMPRODUCT($Y$25:$Y$55,$X$25:$X$55) -> 67208.603 | S32: =$I$9*X32*Y32/SUMPRODUCT($Y$25:$Y$55,$X$25:$X$55) -> 8.6164875 | T32: =IF($I$12="","",S32/$I$12) -> 4.9520043 | U32: =IF(Y32<>"",IF(D32<>"",D32,($I$8-SUM($U$25:U31))*X32*Y32/SUMPRODUCT($Y32:$Y$55,$X32:$X$55)),"") -> 12484 | V32: =IF(Y32<>"",IF(E32<>"",E32,($I$9-SUM($V$25:V31))*X32*Y32/SUMPRODUCT($Y32:$Y$55,$X32:$X$55)),"") -> 2 | W32: =IF(Y32<>"",IF(E32<>"",E32,($I$9-SUM($V$25:V31))*X32*Y32/SUMPRODUCT($Y32:$Y$55,$X32:$X$55)),"") -> 2 | X32: 0.85310234 | Y32: 0.85310234
A33: Рогалевич,Арапова | B33: 46000 | C33: вт | F33: =IF(AND(E33<>"",E33<>0),D33/E33,"") | H33: =IF(AND(G33<>"",G33<>0),D33/G33,"") | I33: 13 | J33: =IF(AND(G33<>"",G33<>0),E33/G33,"") | P33: =IF(AND(I33<>"",I33<>0),G33/I33,"") -> 0 | Q33: =D33/R33 -> 0 | R33: =$I$8*X33*Y33/SUMPRODUCT($Y$25:$Y$55,$X$25:$X$55) -> 67208.603 | S33: =$I$9*X33*Y33/SUMPRODUCT($Y$25:$Y$55,$X$25:$X$55) -> 8.6164875 | T33: =IF($I$12="","",S33/$I$12) -> 4.9520043 | U33: =IF(Y33<>"",IF(D33<>"",D33,($I$8-SUM($U$25:U32))*X33*Y33/SUMPRODUCT($Y33:$Y$55,$X33:$X$55)),"") -> 80419.548 | V33: =IF(Y33<>"",IF(E33<>"",E33,($I$9-SUM($V$25:V32))*X33*Y33/SUMPRODUCT($Y33:$Y$55,$X33:$X$55)),"") -> 10.501279 | W33: =IF(Y33<>"",IF(E33<>"",E33,($I$9-SUM($V$25:V32))*X33*Y33/SUMPRODUCT($Y33:$Y$55,$X33:$X$55)),"") -> 10.501279 | X33: 0.85310234 | Y33: 0.85310234
A34: Рогалевич,Арапова | B34: 46001 | C34: ср | D34: 89424 | E34: 9 | F34: =IF(AND(E34<>"",E34<>0),D34/E34,"") -> 9936 | G34: 2 | H34: =IF(AND(G34<>"",G34<>0),D34/G34,"") -> 44712 | I34: 22 | J34: =IF(AND(G34<>"",G34<>0),E34/G34,"") -> 4.5 | K34: 52470 | P34: =IF(AND(I34<>"",I34<>0),G34/I34,"") -> 0.090909091 | Q34: =D34/R34 -> 2.4829438 | R34: =$I$8*X34*Y34/SUMPRODUCT($Y$25:$Y$55,$X$25:$X$55) -> 36015.314 | S34: =$I$9*X34*Y34/SUMPRODUCT($Y$25:$Y$55,$X$25:$X$55) -> 4.617348 | T34: =IF($I$12="","",S34/$I$12) -> 2.6536483 | U34: =IF(Y34<>"",IF(D34<>"",D34,($I$8-SUM($U$25:U33))*X34*Y34/SUMPRODUCT($Y34:$Y$55,$X34:$X$55)),"") -> 89424 | V34: =IF(Y34<>"",IF(E34<>"",E34,($I$9-SUM($V$25:V33))*X34*Y34/SUMPRODUCT($Y34:$Y$55,$X34:$X$55)),"") -> 9 | W34: =IF(Y34<>"",IF(E34<>"",E34,($I$9-SUM($V$25:V33))*X34*Y34/SUMPRODUCT($Y34:$Y$55,$X34:$X$55)),"") -> 9 | X34: 0.65 | Y34: 0.6
A35: Рогалевич,Уразгильдеева | B35: 46002 | C35: чт | D35: 7984 | E35: 2 | F35: =IF(AND(E35<>"",E35<>0),D35/E35,"") -> 3992 | G35: 1 | H35: =IF(AND(G35<>"",G35<>0),D35/G35,"") -> 7984 | I35: 30 | J35: =IF(AND(G35<>"",G35<>0),E35/G35,"") -> 2 | P35: =IF(AND(I35<>"",I35<>0),G35/I35,"") -> 0.033333333 | Q35: =D35/R35 -> 0.16467915 | R35: =$I$8*X35*Y35/SUMPRODUCT($Y$25:$Y$55,$X$25:$X$55) -> 48482.154 | S35: =$I$9*X35*Y35/SUMPRODUCT($Y$25:$Y$55,$X$25:$X$55) -> 6.2156607 | T35: =IF($I$12="","",S35/$I$12) -> 3.5722188 | U35: =IF(Y35<>"",IF(D35<>"",D35,($I$8-SUM($U$25:U34))*X35*Y35/SUMPRODUCT($Y35:$Y$55,$X35:$X$55)),"") -> 7984 | V35: =IF(Y35<>"",IF(E35<>"",E35,($I$9-SUM($V$25:V34))*X35*Y35/SUMPRODUCT($Y35:$Y$55,$X35:$X$55)),"") -> 2 | W35: =IF(Y35<>"",IF(E35<>"",E35,($I$9-SUM($V$25:V34))*X35*Y35/SUMPRODUCT($Y35:$Y$55,$X35:$X$55)),"") -> 2 | X35: 0.75 | Y35: 0.7
A36: Рогалевич,Уразгильдеева | B36: 46003 | C36: пт | D36: 58874 | E36: 7 | F36: =IF(AND(E36<>"",E36<>0),D36/E36,"") -> 8410.5714 | G36: 5 | H36: =IF(AND(G36<>"",G36<>0),D36/G36,"") -> 11774.8 | I36: 39 | J36: =IF(AND(G36<>"",G36<>0),E36/G36,"") -> 1.4 | N36: 22384 | O36: 23381 | P36: =IF(AND(I36<>"",I36<>0),G36/I36,"") -> 0.12820513 | Q36: =D36/R36 -> 0.8823951 | R36: =$I$8*X36*Y36/SUMPRODUCT($Y$25:$Y$55,$X$25:$X$55) -> 66720.678 | S36: =$I$9*X36*Y36/SUMPRODUCT($Y$25:$Y$55,$X$25:$X$55) -> 8.5539331 | T36: =IF($I$12="","",S36/$I$12) -> 4.9160535 | U36: =IF(Y36<>"",IF(D36<>"",D36,($I$8-SUM($U$25:U35))*X36*Y36/SUMPRODUCT($Y36:$Y$55,$X36:$X$55)),"") -> 58874 | V36: =IF(Y36<>"",IF(E36<>"",E36,($I$9-SUM($V$25:V35))*X36*Y36/SUMPRODUCT($Y36:$Y$55,$X36:$X$55)),"") -> 7 | W36: =IF(Y36<>"",IF(E36<>"",E36,($I$9-SUM($V$25:V35))*X36*Y36/SUMPRODUCT($Y36:$Y$55,$X36:$X$55)),"") -> 7 | X36: 0.85 | Y36: 0.85
A37: Рогалевич,Арапова | B37: 46004 | C37: сб | D37: 12384 | E37: 2 | F37: =IF(AND(E37<>"",E37<>0),D37/E37,"") -> 6192 | G37: 1 | H37: =IF(AND(G37<>"",G37<>0),D37/G37,"") -> 12384 | I37: 40 | J37: =IF(AND(G37<>"",G37<>0),E37/G37,"") -> 2 | P37: =IF(AND(I37<>"",I37<>0),G37/I37,"") -> 0.025 | Q37: =D37/R37 -> 0.14859053 | R37: =$I$8*X37*Y37/SUMPRODUCT($Y$25:$Y$55,$X$25:$X$55) -> 83343.131 | S37: =$I$9*X37*Y37/SUMPRODUCT($Y$25:$Y$55,$X$25:$X$55) -> 10.685017 | T37: =IF($I$12="","",S37/$I$12) -> 6.1408143 | U37: =IF(Y37<>"",IF(D37<>"",D37,($I$8-SUM($U$25:U36))*X37*Y37/SUMPRODUCT($Y37:$Y$55,$X37:$X$55)),"") -> 12384 | V37: =IF(Y37<>"",IF(E37<>"",E37,($I$9-SUM($V$25:V36))*X37*Y37/SUMPRODUCT($Y37:$Y$55,$X37:$X$55)),"") -> 2 | W37: =IF(Y37<>"",IF(E37<>"",E37,($I$9-SUM($V$25:V36))*X37*Y37/SUMPRODUCT($Y37:$Y$55,$X37:$X$55)),"") -> 2 | X37: 0.95 | Y37: 0.95
A38: Рогалевич,Арапова | B38: 46005 | C38: вс | D38: 58143 | E38: 7 | F38: =IF(AND(E38<>"",E38<>0),D38/E38,"") -> 8306.1429 | G38: 3 | H38: =IF(AND(G38<>"",G38<>0),D38/G38,"") -> 19381 | I38: 49 | J38: =IF(AND(G38<>"",G38<>0),E38/G38,"") -> 2.3333333 | O38: 34170 | P38: =IF(AND(I38<>"",I38<>0),G38/I38,"") -> 0.06122449 | Q38: =D38/R38 -> 0.69763398 | R38: =$I$8*X38*Y38/SUMPRODUCT($Y$25:$Y$55,$X$25:$X$55) -> 83343.131 | S38: =$I$9*X38*Y38/SUMPRODUCT($Y$25:$Y$55,$X$25:$X$55) -> 10.685017 | T38: =IF($I$12="","",S38/$I$12) -> 6.1408143 | U38: =IF(Y38<>"",IF(D38<>"",D38,($I$8-SUM($U$25:U37))*X38*Y38/SUMPRODUCT($Y38:$Y$55,$X38:$X$55)),"") -> 58143 | V38: =IF(Y38<>"",IF(E38<>"",E38,($I$9-SUM($V$25:V37))*X38*Y38/SUMPRODUCT($Y38:$Y$55,$X38:$X$55)),"") -> 7 | W38: =IF(Y38<>"",IF(E38<>"",E38,($I$9-SUM($V$25:V37))*X38*Y38/SUMPRODUCT($Y38:$Y$55,$X38:$X$55)),"") -> 7 | X38: 0.95 | Y38: 0.95
A39: Уразгильдеева,Арапова | B39: 46006 | C39: пн | D39: 16868 | E39: 3 | F39: =IF(AND(E39<>"",E39<>0),D39/E39,"") -> 5622.6667 | G39: 3 | H39: =IF(AND(G39<>"",G39<>0),D39/G39,"") -> 5622.6667 | I39: 35 | J39: =IF(AND(G39<>"",G39<>0),E39/G39,"") -> 1 | P39: =IF(AND(I39<>"",I39<>0),G39/I39,"") -> 0.085714286 | Q39: =D39/R39 -> 0.43232891 | R39: =$I$8*X39*Y39/SUMPRODUCT($Y$25:$Y$55,$X$25:$X$55) -> 39016.59 | S39: =$I$9*X39*Y39/SUMPRODUCT($Y$25:$Y$55,$X$25:$X$55) -> 5.002127 | T39: =IF($I$12="","",S39/$I$12) -> 2.8747856 | U39: =IF(Y39<>"",IF(D39<>"",D39,($I$8-SUM($U$25:U38))*X39*Y39/SUMPRODUCT($Y39:$Y$55,$X39:$X$55)),"") -> 16868 | V39: =IF(Y39<>"",IF(E39<>"",E39,($I$9-SUM($V$25:V38))*X39*Y39/SUMPRODUCT($Y39:$Y$55,$X39:$X$55)),"") -> 3 | W39: =IF(Y39<>"",IF(E39<>"",E39,($I$9-SUM($V$25:V38))*X39*Y39/SUMPRODUCT($Y39:$Y$55,$X39:$X$55)),"") -> 3 | X39: 0.65 | Y39: 0.65
A40: Рогалевич,Уразгильдеева | B40: 46007 | C40: вт | D40: 4493 | E40: 1 | F40: =IF(AND(E40<>"",E40<>0),D40/E40,"") -> 4493 | G40: 1 | H40: =IF(AND(G40<>"",G40<>0),D40/G40,"") -> 4493 | I40: 30 | J40: =IF(AND(G40<>"",G40<>0),E40/G40,"") -> 1 | P40: =IF(AND(I40<>"",I40<>0),G40/I40,"") -> 0.033333333 | Q40: =D40/R40 -> 0.086495057 | R40: =$I$8*X40*Y40/SUMPRODUCT($Y$25:$Y$55,$X$25:$X$55) -> 51945.165 | S40: =$I$9*X40*Y40/SUMPRODUCT($Y$25:$Y$55,$X$25:$X$55) -> 6.6596365 | T40: =IF($I$12="","",S40/$I$12) -> 3.8273773 | U40: =IF(Y40<>"",IF(D40<>"",D40,($I$8-SUM($U$25:U39))*X40*Y40/SUMPRODUCT($Y40:$Y$55,$X40:$X$55)),"") -> 4493 | V40: =IF(Y40<>"",IF(E40<>"",E40,($I$9-SUM($V$25:V39))*X40*Y40/SUMPRODUCT($Y40:$Y$55,$X40:$X$55)),"") -> 1 | W40: =IF(Y40<>"",IF(E40<>"",E40,($I$9-SUM($V$25:V39))*X40*Y40/SUMPRODUCT($Y40:$Y$55,$X40:$X$55)),"") -> 1 | X40: 0.75 | Y40: 0.75
A41: Рогалевич | B41: 46008 | C41: ср | D41: 42550 | E41: 6 | F41: =IF(AND(E41<>"",E41<>0),D41/E41,"") -> 7091.6667 | G41: 2 | H41: =IF(AND(G41<>"",G41<>0),D41/G41,"") -> 21275 | I41: 33 | J41: =IF(AND(G41<>"",G41<>0),E41/G41,"") -> 3 | O41: 14193 | P41: =IF(AND(I41<>"",I41<>0),G41/I41,"") -> 0.060606061 | Q41: =D41/R41 -> 0.63773332 | R41: =$I$8*X41*Y41/SUMPRODUCT($Y$25:$Y$55,$X$25:$X$55) -> 66720.678 | S41: =$I$9*X41*Y41/SUMPRODUCT($Y$25:$Y$55,$X$25:$X$55) -> 8.5539331 | T41: =IF($I$12="","",S41/$I$12) -> 4.9160535 | U41: =IF(Y41<>"",IF(D41<>"",D41,($I$8-SUM($U$25:U40))*X41*Y41/SUMPRODUCT($Y41:$Y$55,$X41:$X$55)),"") -> 42550 | V41: =IF(Y41<>"",IF(E41<>"",E41,($I$9-SUM($V$25:V40))*X41*Y41/SUMPRODUCT($Y41:$Y$55,$X41:$X$55)),"") -> 6 | W41: =IF(Y41<>"",IF(E41<>"",E41,($I$9-SUM($V$25:V40))*X41*Y41/SUMPRODUCT($Y41:$Y$55,$X41:$X$55)),"") -> 6 | X41: 0.85 | Y41: 0.85
A42: Рогалевич,Арапова | B42: 46009 | C42: чт | F42: =IF(AND(E42<>"",E42<>0),D42/E42,"") | H42: =IF(AND(G42<>"",G42<>0),D42/G42,"") | I42: 51 | J42: =IF(AND(G42<>"",G42<>0),E42/G42,"") | P42: =IF(AND(I42<>"",I42<>0),G42/I42,"") -> 0 | Q42: =D42/R42 -> 0 | R42: =$I$8*X42*Y42/SUMPRODUCT($Y$25:$Y$55,$X$25:$X$55) -> 74801.037 | S42: =$I$9*X42*Y42/SUMPRODUCT($Y$25:$Y$55,$X$25:$X$55) -> 9.5898766 | T42: =IF($I$12="","",S42/$I$12) -> 5.5114233 | U42: =IF(Y42<>"",IF(D42<>"",D42,($I$8-SUM($U$25:U41))*X42*Y42/SUMPRODUCT($Y42:$Y$55,$X42:$X$55)),"") -> 103756.26 | V42: =IF(Y42<>"",IF(E42<>"",E42,($I$9-SUM($V$25:V41))*X42*Y42/SUMPRODUCT($Y42:$Y$55,$X42:$X$55)),"") -> 13.597899 | W42: =IF(Y42<>"",IF(E42<>"",E42,($I$9-SUM($V$25:V41))*X42*Y42/SUMPRODUCT($Y42:$Y$55,$X42:$X$55)),"") -> 13.597899 | X42: 0.9 | Y42: 0.9
A43: Уразгильдеева,Арапова | B43: 46010 | C43: пт | D43: 35548 | E43: 5 | F43: =IF(AND(E43<>"",E43<>0),D43/E43,"") -> 7109.6 | G43: 1 | H43: =IF(AND(G43<>"",G43<>0),D43/G43,"") -> 35548 | I43: 45 | J43: =IF(AND(G43<>"",G43<>0),E43/G43,"") -> 5 | K43: 9390 | P43: =IF(AND(I43<>"",I43<>0),G43/I43,"") -> 0.022222222 | Q43: =D43/R43 -> 0.47523405 | R43: =$I$8*X43*Y43/SUMPRODUCT($Y$25:$Y$55,$X$25:$X$55) -> 74801.037 | S43: =$I$9*X43*Y43/SUMPRODUCT($Y$25:$Y$55,$X$25:$X$55) -> 9.5898766 | T43: =IF($I$12="","",S43/$I$12) -> 5.5114233 | U43: =IF(Y43<>"",IF(D43<>"",D43,($I$8-SUM($U$25:U42))*X43*Y43/SUMPRODUCT($Y43:$Y$55,$X43:$X$55)),"") -> 35548 | V43: =IF(Y43<>"",IF(E43<>"",E43,($I$9-SUM($V$25:V42))*X43*Y43/SUMPRODUCT($Y43:$Y$55,$X43:$X$55)),"") -> 5 | W43: =IF(Y43<>"",IF(E43<>"",E43,($I$9-SUM($V$25:V42))*X43*Y43/SUMPRODUCT($Y43:$Y$55,$X43:$X$55)),"") -> 5 | X43: 0.9 | Y43: 0.9
A44: Уразгильдеева,Арапова | B44: 46011 | C44: сб | D44: 67609.7 | E44: 7 | F44: =IF(AND(E44<>"",E44<>0),D44/E44,"") -> 9658.5286 | G44: 5 | H44: =IF(AND(G44<>"",G44<>0),D44/G44,"") -> 13521.94 | I44: 41 | J44: =IF(AND(G44<>"",G44<>0),E44/G44,"") -> 1.4 | K44: 14484 | N44: 7293 | O44: 30936 | P44: =IF(AND(I44<>"",I44<>0),G44/I44,"") -> 0.12195122 | Q44: =D44/R44 -> 0.73212697 | R44: =$I$8*X44*Y44/SUMPRODUCT($Y$25:$Y$55,$X$25:$X$55) -> 92346.96 | S44: =$I$9*X44*Y44/SUMPRODUCT($Y$25:$Y$55,$X$25:$X$55) -> 11.839354 | T44: =IF($I$12="","",S44/$I$12) -> 6.8042263 | U44: =IF(Y44<>"",IF(D44<>"",D44,($I$8-SUM($U$25:U43))*X44*Y44/SUMPRODUCT($Y44:$Y$55,$X44:$X$55)),"") -> 67609.7 | V44: =IF(Y44<>"",IF(E44<>"",E44,($I$9-SUM($V$25:V43))*X44*Y44/SUMPRODUCT($Y44:$Y$55,$X44:$X$55)),"") -> 7 | W44: =IF(Y44<>"",IF(E44<>"",E44,($I$9-SUM($V$25:V43))*X44*Y44/SUMPRODUCT($Y44:$Y$55,$X44:$X$55)),"") -> 7 | X44: 1 | Y44: 1
A45: Уразгильдеева,Арапова | B45: 46012 | C45: вс | D45: 66915 | E45: 7 | F45: =IF(AND(E45<>"",E45<>0),D45/E45,"") -> 9559.2857 | G45: 4 | H45: =IF(AND(G45<>"",G45<>0),D45/G45,"") -> 16728.75 | I45: 61 | J45: =IF(AND(G45<>"",G45<>0),E45/G45,"") -> 1.75 | P45: =IF(AND(I45<>"",I45<>0),G45/I45,"") -> 0.06557377 | Q45: =D45/R45 -> 0.72460426 | R45: =$I$8*X45*Y45/SUMPRODUCT($Y$25:$Y$55,$X$25:$X$55) -> 92346.96 | S45: =$I$9*X45*Y45/SUMPRODUCT($Y$25:$Y$55,$X$25:$X$55) -> 11.839354 | T45: =IF($I$12="","",S45/$I$12) -> 6.8042263 | U45: =IF(Y45<>"",IF(D45<>"",D45,($I$8-SUM($U$25:U44))*X45*Y45/SUMPRODUCT($Y45:$Y$55,$X45:$X$55)),"") -> 66915 | V45: =IF(Y45<>"",IF(E45<>"",E45,($I$9-SUM($V$25:V44))*X45*Y45/SUMPRODUCT($Y45:$Y$55,$X45:$X$55)),"") -> 7 | W45: =IF(Y45<>"",IF(E45<>"",E45,($I$9-SUM($V$25:V44))*X45*Y45/SUMPRODUCT($Y45:$Y$55,$X45:$X$55)),"") -> 7 | X45: 1 | Y45: 1
A46: Уразгильдеева | B46: 46013 | C46: пн | D46: 16375 | E46: 3 | F46: =IF(AND(E46<>"",E46<>0),D46/E46,"") -> 5458.3333 | G46: 1 | H46: =IF(AND(G46<>"",G46<>0),D46/G46,"") -> 16375 | I46: 30 | J46: =IF(AND(G46<>"",G46<>0),E46/G46,"") -> 3 | P46: =IF(AND(I46<>"",I46<>0),G46/I46,"") -> 0.033333333 | Q46: =D46/R46 -> 0.1773204 | R46: =$I$8*X46*Y46/SUMPRODUCT($Y$25:$Y$55,$X$25:$X$55) -> 92346.96 | S46: =$I$9*X46*Y46/SUMPRODUCT($Y$25:$Y$55,$X$25:$X$55) -> 11.839354 | T46: =IF($I$12="","",S46/$I$12) -> 6.8042263 | U46: =IF(Y46<>"",IF(D46<>"",D46,($I$8-SUM($U$25:U45))*X46*Y46/SUMPRODUCT($Y46:$Y$55,$X46:$X$55)),"") -> 16375 | V46: =IF(Y46<>"",IF(E46<>"",E46,($I$9-SUM($V$25:V45))*X46*Y46/SUMPRODUCT($Y46:$Y$55,$X46:$X$55)),"") -> 3 | W46: =IF(Y46<>"",IF(E46<>"",E46,($I$9-SUM($V$25:V45))*X46*Y46/SUMPRODUCT($Y46:$Y$55,$X46:$X$55)),"") -> 3 | X46: 1 | Y46: 1
A47: Уразгильдеева,Арапова | B47: 46014 | C47: вт | F47: =IF(AND(E47<>"",E47<>0),D47/E47,"") | H47: =IF(AND(G47<>"",G47<>0),D47/G47,"") | I47: 25 | J47: =IF(AND(G47<>"",G47<>0),E47/G47,"") | P47: =IF(AND(I47<>"",I47<>0),G47/I47,"") -> 0 | Q47: =D47/R47 -> 0 | R47: =$I$8*X47*Y47/SUMPRODUCT($Y$25:$Y$55,$X$25:$X$55) -> 92346.96 | S47: =$I$9*X47*Y47/SUMPRODUCT($Y$25:$Y$55,$X$25:$X$55) -> 11.839354 | T47: =IF($I$12="","",S47/$I$12) -> 6.8042263 | U47: =IF(Y47<>"",IF(D47<>"",D47,($I$8-SUM($U$25:U46))*X47*Y47/SUMPRODUCT($Y47:$Y$55,$X47:$X$55)),"") -> 155021.92 | V47: =IF(Y47<>"",IF(E47<>"",E47,($I$9-SUM($V$25:V46))*X47*Y47/SUMPRODUCT($Y47:$Y$55,$X47:$X$55)),"") -> 20.534002 | W47: =IF(Y47<>"",IF(E47<>"",E47,($I$9-SUM($V$25:V46))*X47*Y47/SUMPRODUCT($Y47:$Y$55,$X47:$X$55)),"") -> 20.534002 | X47: 1 | Y47: 1
A48: Арапова | B48: 46015 | C48: ср | F48: =IF(AND(E48<>"",E48<>0),D48/E48,"") | H48: =IF(AND(G48<>"",G48<>0),D48/G48,"") | I48: 19 | J48: =IF(AND(G48<>"",G48<>0),E48/G48,"") | P48: =IF(AND(I48<>"",I48<>0),G48/I48,"") -> 0 | Q48: =D48/R48 -> 0 | R48: =$I$8*X48*Y48/SUMPRODUCT($Y$25:$Y$55,$X$25:$X$55) -> 92346.96 | S48: =$I$9*X48*Y48/SUMPRODUCT($Y$25:$Y$55,$X$25:$X$55) -> 11.839354 | T48: =IF($I$12="","",S48/$I$12) -> 6.8042263 | U48: =IF(Y48<>"",IF(D48<>"",D48,($I$8-SUM($U$25:U47))*X48*Y48/SUMPRODUCT($Y48:$Y$55,$X48:$X$55)),"") -> 155021.92 | V48: =IF(Y48<>"",IF(E48<>"",E48,($I$9-SUM($V$25:V47))*X48*Y48/SUMPRODUCT($Y48:$Y$55,$X48:$X$55)),"") -> 20.534002 | W48: =IF(Y48<>"",IF(E48<>"",E48,($I$9-SUM($V$25:V47))*X48*Y48/SUMPRODUCT($Y48:$Y$55,$X48:$X$55)),"") -> 20.534002 | X48: 1 | Y48: 1
A49: Уразгильдеева | B49: 46016 | C49: чт | F49: =IF(AND(E49<>"",E49<>0),D49/E49,"") | H49: =IF(AND(G49<>"",G49<>0),D49/G49,"") | I49: 23 | J49: =IF(AND(G49<>"",G49<>0),E49/G49,"") | P49: =IF(AND(I49<>"",I49<>0),G49/I49,"") -> 0 | Q49: =D49/R49 -> 0 | R49: =$I$8*X49*Y49/SUMPRODUCT($Y$25:$Y$55,$X$25:$X$55) -> 92346.96 | S49: =$I$9*X49*Y49/SUMPRODUCT($Y$25:$Y$55,$X$25:$X$55) -> 11.839354 | T49: =IF($I$12="","",S49/$I$12) -> 6.8042263 | U49: =IF(Y49<>"",IF(D49<>"",D49,($I$8-SUM($U$25:U48))*X49*Y49/SUMPRODUCT($Y49:$Y$55,$X49:$X$55)),"") -> 155021.92 | V49: =IF(Y49<>"",IF(E49<>"",E49,($I$9-SUM($V$25:V48))*X49*Y49/SUMPRODUCT($Y49:$Y$55,$X49:$X$55)),"") -> 20.534002 | W49: =IF(Y49<>"",IF(E49<>"",E49,($I$9-SUM($V$25:V48))*X49*Y49/SUMPRODUCT($Y49:$Y$55,$X49:$X$55)),"") -> 20.534002 | X49: 1 | Y49: 1
A50: Уразгильдеева,Арапова | B50: 46017 | C50: пт | D50: 30584 | E50: 3 | F50: =IF(AND(E50<>"",E50<>0),D50/E50,"") -> 10194.667 | G50: 2 | H50: =IF(AND(G50<>"",G50<>0),D50/G50,"") -> 15292 | I50: 21 | J50: =IF(AND(G50<>"",G50<>0),E50/G50,"") -> 1.5 | M50: 15100 | P50: =IF(AND(I50<>"",I50<>0),G50/I50,"") -> 0.095238095 | Q50: =D50/R50 -> 0.22999013 | R50: =$I$8*X50*Y50/SUMPRODUCT($Y$25:$Y$55,$X$25:$X$55) -> 132979.62 | S50: =$I$9*X50*Y50/SUMPRODUCT($Y$25:$Y$55,$X$25:$X$55) -> 17.048669 | T50: =IF($I$12="","",S50/$I$12) -> 9.7980859 | U50: =IF(Y50<>"",IF(D50<>"",D50,($I$8-SUM($U$25:U49))*X50*Y50/SUMPRODUCT($Y50:$Y$55,$X50:$X$55)),"") -> 30584 | V50: =IF(Y50<>"",IF(E50<>"",E50,($I$9-SUM($V$25:V49))*X50*Y50/SUMPRODUCT($Y50:$Y$55,$X50:$X$55)),"") -> 3 | W50: =IF(Y50<>"",IF(E50<>"",E50,($I$9-SUM($V$25:V49))*X50*Y50/SUMPRODUCT($Y50:$Y$55,$X50:$X$55)),"") -> 3 | X50: 1.2 | Y50: 1.2
A51: Уразгильдеева,Арапова | B51: 46018 | C51: сб | D51: 126047 | E51: 14 | F51: =IF(AND(E51<>"",E51<>0),D51/E51,"") -> 9003.3571 | G51: 6 | H51: =IF(AND(G51<>"",G51<>0),D51/G51,"") -> 21007.833 | I51: 36 | J51: =IF(AND(G51<>"",G51<>0),E51/G51,"") -> 2.3333333 | K51: 36980 | M51: 8390 | P51: =IF(AND(I51<>"",I51<>0),G51/I51,"") -> 0.16666667 | Q51: =D51/R51 -> 0.94786704 | R51: =$I$8*X51*Y51/SUMPRODUCT($Y$25:$Y$55,$X$25:$X$55) -> 132979.62 | S51: =$I$9*X51*Y51/SUMPRODUCT($Y$25:$Y$55,$X$25:$X$55) -> 17.048669 | T51: =IF($I$12="","",S51/$I$12) -> 9.7980859 | U51: =IF(Y51<>"",IF(D51<>"",D51,($I$8-SUM($U$25:U50))*X51*Y51/SUMPRODUCT($Y51:$Y$55,$X51:$X$55)),"") -> 126047 | V51: =IF(Y51<>"",IF(E51<>"",E51,($I$9-SUM($V$25:V50))*X51*Y51/SUMPRODUCT($Y51:$Y$55,$X51:$X$55)),"") -> 14 | W51: =IF(Y51<>"",IF(E51<>"",E51,($I$9-SUM($V$25:V50))*X51*Y51/SUMPRODUCT($Y51:$Y$55,$X51:$X$55)),"") -> 14 | X51: 1.2 | Y51: 1.2
A52: Уразгильдеева,Арапова | B52: 46019 | C52: вс | D52: 43254 | E52: 3 | F52: =IF(AND(E52<>"",E52<>0),D52/E52,"") -> 14418 | G52: 2 | H52: =IF(AND(G52<>"",G52<>0),D52/G52,"") -> 21627 | I52: 38 | J52: =IF(AND(G52<>"",G52<>0),E52/G52,"") -> 1.5 | K52: 28272 | M52: 13690 | P52: =IF(AND(I52<>"",I52<>0),G52/I52,"") -> 0.052631579 | Q52: =D52/R52 -> 0.32526788 | R52: =$I$8*X52*Y52/SUMPRODUCT($Y$25:$Y$55,$X$25:$X$55) -> 132979.62 | S52: =$I$9*X52*Y52/SUMPRODUCT($Y$25:$Y$55,$X$25:$X$55) -> 17.048669 | T52: =IF($I$12="","",S52/$I$12) -> 9.7980859 | U52: =IF(Y52<>"",IF(D52<>"",D52,($I$8-SUM($U$25:U51))*X52*Y52/SUMPRODUCT($Y52:$Y$55,$X52:$X$55)),"") -> 43254 | V52: =IF(Y52<>"",IF(E52<>"",E52,($I$9-SUM($V$25:V51))*X52*Y52/SUMPRODUCT($Y52:$Y$55,$X52:$X$55)),"") -> 3 | W52: =IF(Y52<>"",IF(E52<>"",E52,($I$9-SUM($V$25:V51))*X52*Y52/SUMPRODUCT($Y52:$Y$55,$X52:$X$55)),"") -> 3 | X52: 1.2 | Y52: 1.2
A53: Рогалевич,Арапова | B53: 46020 | C53: пн | D53: 40391 | E53: 5 | F53: =IF(AND(E53<>"",E53<>0),D53/E53,"") -> 8078.2 | G53: 3 | H53: =IF(AND(G53<>"",G53<>0),D53/G53,"") -> 13463.667 | I53: 10 | J53: =IF(AND(G53<>"",G53<>0),E53/G53,"") -> 1.6666667 | M53: 13793 | N53: 15985 | O53: 6690 | P53: =IF(AND(I53<>"",I53<>0),G53/I53,"") -> 0.3 | Q53: =D53/R53 -> 0.30373827 | R53: =$I$8*X53*Y53/SUMPRODUCT($Y$25:$Y$55,$X$25:$X$55) -> 132979.62 | S53: =$I$9*X53*Y53/SUMPRODUCT($Y$25:$Y$55,$X$25:$X$55) -> 17.048669 | T53: =IF($I$12="","",S53/$I$12) -> 9.7980859 | U53: =IF(Y53<>"",IF(D53<>"",D53,($I$8-SUM($U$25:U52))*X53*Y53/SUMPRODUCT($Y53:$Y$55,$X53:$X$55)),"") -> 40391 | V53: =IF(Y53<>"",IF(E53<>"",E53,($I$9-SUM($V$25:V52))*X53*Y53/SUMPRODUCT($Y53:$Y$55,$X53:$X$55)),"") -> 5 | W53: =IF(Y53<>"",IF(E53<>"",E53,($I$9-SUM($V$25:V52))*X53*Y53/SUMPRODUCT($Y53:$Y$55,$X53:$X$55)),"") -> 5 | X53: 1.2 | Y53: 1.2
A54: Рогалевич,Уразгильдеева,Арапова | B54: 46021 | C54: вт | D54: 188697.5 | E54: 22 | F54: =IF(AND(E54<>"",E54<>0),D54/E54,"") -> 8577.1591 | G54: 14 | H54: =IF(AND(G54<>"",G54<>0),D54/G54,"") -> 13478.393 | I54: 80 | J54: =IF(AND(G54<>"",G54<>0),E54/G54,"") -> 1.5714286 | K54: 50083 | N54: 7993 | P54: =IF(AND(I54<>"",I54<>0),G54/I54,"") -> 0.175 | Q54: =D54/R54 -> 1.4189956 | R54: =$I$8*X54*Y54/SUMPRODUCT($Y$25:$Y$55,$X$25:$X$55) -> 132979.62 | S54: =$I$9*X54*Y54/SUMPRODUCT($Y$25:$Y$55,$X$25:$X$55) -> 17.048669 | T54: =IF($I$12="","",S54/$I$12) -> 9.7980859 | U54: =IF(Y54<>"",IF(D54<>"",D54,($I$8-SUM($U$25:U53))*X54*Y54/SUMPRODUCT($Y54:$Y$55,$X54:$X$55)),"") -> 188697.5 | V54: =IF(Y54<>"",IF(E54<>"",E54,($I$9-SUM($V$25:V53))*X54*Y54/SUMPRODUCT($Y54:$Y$55,$X54:$X$55)),"") -> 22 | W54: =IF(Y54<>"",IF(E54<>"",E54,($I$9-SUM($V$25:V53))*X54*Y54/SUMPRODUCT($Y54:$Y$55,$X54:$X$55)),"") -> 22 | X54: 1.2 | Y54: 1.2
A55: Рогалевич,Арапова.Уразгильдеева | B55: 46022 | C55: ср | D55: =115985+22885 -> 138870 | E55: 16 | F55: =IF(AND(E55<>"",E55<>0),D55/E55,"") -> 8679.375 | G55: 9 | H55: =IF(AND(G55<>"",G55<>0),D55/G55,"") -> 15430 | I55: 60 | J55: =IF(AND(G55<>"",G55<>0),E55/G55,"") -> 1.7777778 | K55: 54970 | P55: =IF(AND(I55<>"",I55<>0),G55/I55,"") -> 0.15 | Q55: =D55/R55 -> 1.5037853 | R55: =$I$8*X55*Y55/SUMPRODUCT($Y$25:$Y$55,$X$25:$X$55) -> 92346.96 | S55: =$I$9*X55*Y55/SUMPRODUCT($Y$25:$Y$55,$X$25:$X$55) -> 11.839354 | T55: =IF($I$12="","",S55/$I$12) -> 6.8042263 | U55: =IF(Y55<>"",IF(D55<>"",D55,($I$8-SUM($U$25:U54))*X55*Y55/SUMPRODUCT($Y55:$Y$55,$X55:$X$55)),"") -> 138870 | V55: =IF(Y55<>"",IF(E55<>"",E55,($I$9-SUM($V$25:V54))*X55*Y55/SUMPRODUCT($Y55:$Y$55,$X55:$X$55)),"") -> 16 | W55: =IF(Y55<>"",IF(E55<>"",E55,($I$9-SUM($V$25:V54))*X55*Y55/SUMPRODUCT($Y55:$Y$55,$X55:$X$55)),"") -> 16 | X55: 1 | Y55: 1
B56: итого | D56: =SUM(D25:D55) -> 1253246.2 | E56: =SUM(E25:E55) -> 143 | F56: =IF(AND(E56<>"", E56<>0), D56/E56, "") -> 8763.9594 | G56: =SUM(G25:G55) -> 79 | H56: =IF(AND(G56<>"",G56<>0),D56/G56,"") -> 15863.876 | I56: =SUM(I25:I55)*0.8 -> 912 | J56: =E56/G56 -> 1.8101266 | K56: =SUM(K25:K55) -> 326792 | L56: =SUM(L25:L55) -> 26123 | M56: =SUM(M25:M55) -> 50973 | N56: =SUM(N25:N55) -> 53655 | O56: =SUM(O25:O55) -> 109370 | P56: =IF(AND(I56<>"", I56<>0), G56/I56, "") -> 0.086622807 | Q56: =D56/R56 -> 0.48094046 | R56: =SUM(R25:R55) -> 2605824 | S56: =SUM(S25:S55) -> 334.08 | T56: =SUM(T25:T55) -> 192 | U56: =SUM(U25:U55) -> 1902487.8 | V56: =SUM(V25:V55) -> 228.70118 | W56: =SUM(W25:W55) -> 228.70118
D57: =SUMIF(D25:D55,"",R25:R55)+D56 -> 1672296.7 | I57: =I56/J14 -> 29.419355
D58: ='Рогалевич И. Е. '!J8+'Уразгильдеева Е. Р. '!J8+'Арапова А. В.'!J8+'Доп сотрудник'!D57 -> 1253246.2 | E58: ='Рогалевич И. Е. '!E57+'Уразгильдеева Е. Р. '!E57+'Арапова А. В.'!E57+'Доп сотрудник'!E57 -> 143 | G58: ='Рогалевич И. Е. '!G57+'Уразгильдеева Е. Р. '!G57+'Арапова А. В.'!G57+'Доп сотрудник'!G57 -> 79 | I58: ='Рогалевич И. Е. '!I57+'Уразгильдеева Е. Р. '!I57 -> 482 | K58: ='Рогалевич И. Е. '!K57+'Уразгильдеева Е. Р. '!K57+'Арапова А. В.'!K57 -> 326792 | L58: ='Рогалевич И. Е. '!L57+'Уразгильдеева Е. Р. '!L57+'Арапова А. В.'!L57 -> 26123 | M58: ='Рогалевич И. Е. '!M57+'Уразгильдеева Е. Р. '!M57+'Арапова А. В.'!M57 -> 50973

Sheet Конкурс
A2: Личный ежедневный КВП, %
A4: Сотруник | B4: 45282 | C4: 45283 | D4: 45284 | E4: 45285 | F4: 45286 | G4: 45287 | H4: 45288 | I4: 45289 | J4: 45290 | K4: 45291 | L4: Итого:
A5: Рогалевич Ирина | E5: 0.57 | F5: 0.73 | G5: 0.88 | H5: 0.98 | I5: 0.69 | J5: 1.82 | K5: 2.89
A6: Арапова Анна | C6: 0 | D6: 0 | E6: 0 | F6: 0 | G6: 0.83 | H6: 0 | I6: 0.28 | J6: 0.46 | K6: 0.89
A7: Уразгильдеева Екатерина | B7: 0.39 | C7: 0 | E7: 0 | F7: 0.49 | G7: 1.19 | H7: 0.69 | J7: 1.63 | K7: 0.81
A9: Личный КВП, баллы
A11: Сотруник | B11: 45282 | C11: 45283 | D11: 45284 | E11: 45285 | F11: 45286 | G11: 45287 | H11: 45288 | I11: 45289 | J11: 45290 | K11: 45291 | L11: Итого:
A12: Рогалевич Ирина | E12: 1 | F12: 1 | G12: 1 | H12: 1 | I12: 1 | J12: 2 | K12: 3 | L12: =SUM(B12:K12) -> 10
A13: Арапова Анна | L13: =SUM(B13:K13) -> 0
A14: Уразгильдеева Екатерина | B14: 1 | F14: 1 | G14: 2 | H14: 1 | J14: 1 | L14: =SUM(B14:K14) -> 6

Sheet Св. по пок.
A1: 1-20.08
A2: Показатель | D2: ='Ялта, Ленина, 18'!I3 -> ул. Набережная Ленина, 18 | G2: =График!B29 -> Рогалевич Ирина | J2: =График!B28 -> Уразгильдеева Екатерина | M2: =График!B27 -> Арапова Анна-Мария
D3: Факт | F3: Прогноз | G3: Факт | I3: Прогноз | J3: Факт | L3: Прогноз | M3: Факт | O3: Прогноз
A4: Выручка | D4: ='Ялта, Ленина, 18'!K8 -> 0.48094046 | E4: ='Ялта, Ленина, 18'!J8 -> 1253246.2 | F4: ='Ялта, Ленина, 18'!M8 -> 0.57310289 | G4: ='Рогалевич И. Е. '!K8 -> 0.74053666 | H4: ='Рогалевич И. Е. '!J8 -> 352381.5 | I4: ='Рогалевич И. Е. '!M8 -> 1.2188958 | J4: ='Уразгильдеева Е. Р. '!K8 -> 0.55855872 | K4: ='Уразгильдеева Е. Р. '!J8 -> 620172 | L4: ='Уразгильдеева Е. Р. '!M8 -> 0.64369128 | M4: ='[1]Яковенко А. К'!K8 -> #REF! | N4: ='[1]Яковенко А. К'!J8 -> #REF! | O4: ='[1]Яковенко А. К'!M8 -> #REF!
A5: Кол-во изделий | D5: ='Ялта, Ленина, 18'!K9 -> 0.42804119 | E5: ='Ялта, Ленина, 18'!J9 -> 143 | F5: ='Ялта, Ленина, 18'!M9 -> 0.51006655 | G5: ='Рогалевич И. Е. '!K9 -> 0.63928229 | H5: ='Рогалевич И. Е. '!J9 -> 39 | I5: ='Рогалевич И. Е. '!M9 -> 1.1408068 | J5: ='Уразгильдеева Е. Р. '!K9 -> 0.49175561 | K5: ='Уразгильдеева Е. Р. '!J9 -> 70 | L5: ='Уразгильдеева Е. Р. '!M9 -> 0.5667064 | M5: ='[1]Яковенко А. К'!K9 -> #REF! | N5: ='[1]Яковенко А. К'!J9 -> #REF! | O5: ='[1]Яковенко А. К'!M9 -> #REF!
A6: Средний чек | D6: ='Ялта, Ленина, 18'!K10 -> 1.168868 | E6: ='Ялта, Ленина, 18'!J10 -> 15863.876 | F6: ='Ялта, Ленина, 18'!M10 -> 1.168868 | G6: ='Рогалевич И. Е. '!K10 -> 1.3665189 | H6: ='Рогалевич И. Е. '!J10 -> 18546.395 | I6: ='Рогалевич И. Е. '!M10 -> 1.3665189 | J6: ='Уразгильдеева Е. Р. '!K10 -> 1.1145112 | K6: ='Уразгильдеева Е. Р. '!J10 -> 15126.146 | L6: ='Уразгильдеева Е. Р. '!M10 -> 1.1145112 | M6: ='[1]Яковенко А. К'!K10 -> #REF! | N6: ='[1]Яковенко А. К'!J10 -> #REF! | O6: ='[1]Яковенко А. К'!M10 -> #REF!
A7: Средняя стоимость изделия | D7: ='Ялта, Ленина, 18'!K11 -> 1.1235845 | E7: ='Ялта, Ленина, 18'!J11 -> 8763.9594 | F7: ='Ялта, Ленина, 18'!M11 -> 1.1235845 | G7: ='Рогалевич И. Е. '!K11 -> 1.1583876 | H7: ='Рогалевич И. Е. '!J11 -> 9035.4231 | I7: ='Рогалевич И. Е. '!M11 -> 1.0684507 | J7: ='Уразгильдеева Е. Р. '!K11 -> 1.1358462 | K7: ='Уразгильдеева Е. Р. '!J11 -> 8859.6 | L7: ='Уразгильдеева Е. Р. '!M11 -> 1.1358462 | M7: ='[1]Яковенко А. К'!K11 -> #REF! | N7: ='[1]Яковенко А. К'!J11 -> #REF! | O7: ='[1]Яковенко А. К'!M11 -> #REF!
A8: Длина чека | D8: ='Ялта, Ленина, 18'!K12 -> 1.0403026 | E8: ='Ялта, Ленина, 18'!J12 -> 1.8101266 | F8: ='Ялта, Ленина, 18'!M12 -> 1.0403026 | G8: ='Рогалевич И. Е. '!K12 -> 1.1796733 | H8: ='Рогалевич И. Е. '!J12 -> 2.0526316 | I8: ='Рогалевич И. Е. '!M12 -> 1.1796733 | J8: ='Уразгильдеева Е. Р. '!K12 -> 0.98121671 | K8: ='Уразгильдеева Е. Р. '!J12 -> 1.7073171 | L8: ='Уразгильдеева Е. Р. '!M12 -> 0.98121671 | M8: ='[1]Яковенко А. К'!K12 -> #REF! | N8: ='[1]Яковенко А. К'!J12 -> #REF! | O8: ='[1]Яковенко А. К'!M12 -> #REF!
A9: Кол-во чеков | D9: ='Ялта, Ленина, 18'!K13 -> 0.41145833 | E9: ='Ялта, Ленина, 18'!J13 -> 79 | F9: ='Ялта, Ленина, 18'!M13 -> 0.49030593 | G9: ='Рогалевич И. Е. '!K13 -> 0.54191468 | H9: ='Рогалевич И. Е. '!J13 -> 19 | I9: ='Рогалевич И. Е. '!M13 -> 0.96705314 | J9: ='Уразгильдеева Е. Р. '!K13 -> 0.50116922 | K9: ='Уразгильдеева Е. Р. '!J13 -> 41 | L9: ='Уразгильдеева Е. Р. '!M13 -> 0.57755478 | M9: ='[1]Яковенко А. К'!K13 -> #REF! | N9: ='[1]Яковенко А. К'!J13 -> #REF! | O9: ='[1]Яковенко А. К'!M13 -> #REF!
A10: Кол-во смен план/отработано | D10: ='Ялта, Ленина, 18'!K14 -> 1 | E10: ='Ялта, Ленина, 18'!J14 -> 31 | G10: ='Рогалевич И. Е. '!K14 -> 1 | H10: ='Рогалевич И. Е. '!J14 -> 12 | J10: ='Уразгильдеева Е. Р. '!K14 -> 1 | K10: ='Уразгильдеева Е. Р. '!J14 -> 23 | M10: ='[1]Яковенко А. К'!K14 -> #REF! | N10: ='[1]Яковенко А. К'!J14 -> #REF!
A11: Средние продажи в смену | D11: ='Ялта, Ленина, 18'!K15 -> 0.48094046 | E11: ='Ялта, Ленина, 18'!J15 -> 40427.297 | F11: ='Ялта, Ленина, 18'!M15 -> 0.48094046 | G11: ='Рогалевич И. Е. '!K15 -> 0.34934012 | H11: ='Рогалевич И. Е. '!J15 -> 29365.125 | I11: ='Рогалевич И. Е. '!M15 -> 0.34934012 | J11: ='Уразгильдеева Е. Р. '!K15 -> 0.32077531 | K11: ='Уразгильдеева Е. Р. '!J15 -> 26964 | L11: ='Уразгильдеева Е. Р. '!M15 -> 0.32077531 | M11: ='[1]Яковенко А. К'!K15 -> #REF! | N11: ='[1]Яковенко А. К'!J15 -> #REF! | O11: ='[1]Яковенко А. К'!M15 -> #REF!
A12: Трафик | D12: ='Ялта, Ленина, 18'!K17 -> 0.57 | E12: ='Ялта, Ленина, 18'!J17 -> 912 | F12: ='Ялта, Ленина, 18'!M17 -> 0.57 | G12: ='Рогалевич И. Е. '!K17 -> 0.54077381 | H12: ='Рогалевич И. Е. '!J17 -> 158 | I12: ='Рогалевич И. Е. '!M17 -> 0.54077381 | J12: ='Уразгильдеева Е. Р. '!K17 -> 0.4752551 | K12: ='Уразгильдеева Е. Р. '!J17 -> 324 | L12: ='Уразгильдеева Е. Р. '!M17 -> 0.4752551 | M12: ='[1]Яковенко А. К'!K17 -> #REF! | N12: ='[1]Яковенко А. К'!J17 -> #REF! | O12: ='[1]Яковенко А. К'!M17 -> #REF!
A13: UNOde50 | D13: ='Ялта, Ленина, 18'!U19 -> 0.32038431 | E13: ='Ялта, Ленина, 18'!V18 -> 326792 | F13: ='Ялта, Ленина, 18'!V19 -> 0.32038431 | G13: ='Рогалевич И. Е. '!S19 -> 0.41586835 | H13: ='Рогалевич И. Е. '!T18 -> 77460 | I13: ='Рогалевич И. Е. '!T19 -> 0.41586835 | J13: ='Уразгильдеева Е. Р. '!S19 -> 0.46331793 | K13: ='Уразгильдеева Е. Р. '!T18 -> 201362 | L13: ='Уразгильдеева Е. Р. '!T19 -> 0.46331793 | M13: ='[1]Яковенко А. К'!S19 -> #REF! | N13: ='[1]Яковенко А. К'!T18 -> #REF! | O13: ='[1]Яковенко А. К'!T19 -> #REF!
A14: IS | D14: ='Ялта, Ленина, 18'!U13 -> 0.051221569 | E14: ='Ялта, Ленина, 18'!V12 -> 26123 | F14: ='Ялта, Ленина, 18'!V13 -> 0.051221569 | G14: ='Рогалевич И. Е. '!S13 -> 0.27813679 | H14: ='Рогалевич И. Е. '!T12 -> 25903 | I14: ='Рогалевич И. Е. '!T13 -> 0.27813679 | J14: ='Уразгильдеева Е. Р. '!S13 -> 0.001012405 | K14: ='Уразгильдеева Е. Р. '!T12 -> 220 | L14: ='Уразгильдеева Е. Р. '!T13 -> 0.001012405 | M14: ='[1]Яковенко А. К'!S13 -> #REF! | N14: ='[1]Яковенко А. К'!T12 -> #REF! | O14: ='[1]Яковенко А. К'!T13 -> #REF!
A15: ='Ялта, Ленина, 18'!M23 -> Agafi | D15: ='Ялта, Ленина, 18'!X13 -> 0.10619375 | E15: ='Ялта, Ленина, 18'!Y12 -> 50973 | F15: ='Ялта, Ленина, 18'!Y13 -> 0.10619375 | G15: ='Рогалевич И. Е. '!V13 -> 0 | H15: ='Рогалевич И. Е. '!W12 -> 0 | I15: ='Рогалевич И. Е. '!W13 -> 0 | J15: ='Уразгильдеева Е. Р. '!V13 -> 0.18178997 | K15: ='Уразгильдеева Е. Р. '!W12 -> 37180 | L15: ='Уразгильдеева Е. Р. '!W13 -> 0.18178997 | M15: ='[1]Яковенко А. К'!V13 -> #REF! | N15: ='[1]Яковенко А. К'!W12 -> #REF! | O15: ='[1]Яковенко А. К'!W13 -> #REF!
A16: Отклонение от плана | D16: ='Ялта, Ленина, 18'!J16 -> -1352577.8 | G16: ='Рогалевич И. Е. '!N8 -> 104160.7 | J16: ='Уразгильдеева Е. Р. '!N8 -> -395612.28 | M16: ='[1]Яковенко А. К'!N8 -> #REF!

Sheet План на день
A1: Выручка | D1: 152000
A2: Кол-во изделий | D2: =D1/D4 -> 19.487179
A3: Средний чек | D3: =D4*D5 -> 13572
A4: Средняя стоимость изделия | D4: ='Ялта, Ленина, 18'!I11 -> 7800
A5: Длина чека | D5: ='Ялта, Ленина, 18'!I12 -> 1.74
A6: Кол-во чеков | D6: =IF(D5<>0,D2/D5,"") -> 11.199528
A7: Конверсия | D7: ='Ялта, Ленина, 18'!I20 -> 0.12
A8: IS | D8: =('Ялта, Ленина, 18'!U12-'Ялта, Ленина, 18'!V12)/('Ялта, Ленина, 18'!I14-'Ялта, Ленина, 18'!J14) -> #DIV/0!
A9: UNOde50 | D9: =('Ялта, Ленина, 18'!U18-'Ялта, Ленина, 18'!V18)/('Ялта, Ленина, 18'!I14-'Ялта, Ленина, 18'!J14) -> #DIV/0!
A10: ='Ялта, Ленина, 18'!M23 -> Agafi | D10: =('Ялта, Ленина, 18'!X12-'Ялта, Ленина, 18'!Y12)/('Ялта, Ленина, 18'!I14-'Ялта, Ленина, 18'!J14) -> #DIV/0!

Sheet Рогалевич И. Е. 
B1: =TODAY()-1 -> 46060
B2: (отчетная дата) | J2: ЕЖЕДНЕВНЫЙ ОТЧЕТ О ПРОДАЖАХ
B3: Осталось до выполнения плана!!! | J3: =График!B29 -> Рогалевич Ирина
C4: =I8-D57 -> 123464.62 | E4: =IF(I8<>0,C4/I8,0) -> 0.25946334
F6: Целевые показатели
F7: Показатель | I7: План | J7: Факт | K7: % выполнения | L7: Прогноз выполнения | M7: % выполнения по прогнозу | N7: Отклонение | O7: Факт аналогичного месяца прошлого года | P7: Отклонение LFL
F8: Выручка | I8: ='Ялта, Ленина, 18'!I8/График!AJ31*График!AJ29 -> 475846.12 | J8: =D57 -> 352381.5 | K8: =IF(AND(I8<>"",I8<>0,J8<>""),J8/I8,"") -> 0.74053666 | L8: =IF(SUMIF($D$25:$D$56,">=0",$P$25:$P$56)<>0,I8*D57/SUMIF($D$25:$D$56,">=0",$P$25:$P$56),0) -> 580006.82 | M8: =IF(AND(I8<>"",I8<>0,L8<>"",L8<>0),L8/I8,"") -> 1.2188958 | N8: =IF(AND(J8<>0,J8<>"",I8<>0,I8<>""),L8-I8,"") -> 104160.7 | P8: =IF(AND(O8<>"",O8<>0,L8<>"",L8<>0),-O8+L8,"") | Q8: =IF(AND(P8<>"",P8<>0,O8<>0,O8<>""),P8/O8,"")
F9: Кол-во изделий | I9: =I8/I11 -> 61.005913 | J9: =E57 -> 39 | K9: =IF(AND(I9<>"",I9<>0,J9<>""),J9/I9,"") -> 0.63928229 | L9: =IF(SUMIF($E$25:$E$54,">=0",$Q$25:$Q$54)<>0,I9*E57/SUMIF($E$25:$E$54,">=0",$Q$25:$Q$54),0) -> 69.59596 | M9: =IF(AND(I9<>"",I9<>0,L9<>"",L9<>0),L9/I9,"") -> 1.1408068 | N9: =IF(AND(J9<>0,J9<>"",I9<>0,I9<>""),L9-I9,"") -> 8.5900466 | O9: =O8/O11 -> #DIV/0! | P9: =IF(AND(O9<>"",O9<>0,L9<>"",L9<>0),-O9+L9,"") -> #DIV/0! | Q9: =IF(AND(P9<>"",P9<>0,O9<>0,O9<>""),P9/O9,"") -> #DIV/0!
F10: Средний чек | I10: =I11*I12 -> 13572 | J10: =H57 -> 18546.395 | K10: =IF(AND(I10<>"",I10<>0,J10<>""),J10/I10,"") -> 1.3665189 | L10: =J10 -> 18546.395 | M10: =IF(AND(I10<>"",I10<>0,L10<>"",L10<>0),L10/I10,"") -> 1.3665189 | N10: =IF(AND(J10<>0,J10<>"",I10<>0,I10<>""),L10-I10,"") -> 4974.3947 | O10: =O11*O12 -> 0 | P10: =IF(AND(O10<>"",O10<>0,L10<>"",L10<>0),-O10+L10,"") | Q10: =IF(AND(P10<>"",P10<>0,O10<>0,O10<>""),P10/O10,"") | S10: IS | V10: =M23 -> Agafi
F11: Средняя стоимость изделия | I11: ='Ялта, Ленина, 18'!I11 -> 7800 | J11: =F57 -> 9035.4231 | K11: =IF(AND(I11<>"",I11<>0,J11<>""),J11/I11,"") -> 1.1583876 | L11: =IF(L9>0,L8/L9,"") -> 8333.9151 | M11: =IF(AND(I11<>"",I11<>0,L11<>"",L11<>0),L11/I11,"") -> 1.0684507 | N11: =IF(AND(J11<>0,J11<>"",I11<>0,I11<>""),L11-I11,"") -> 533.91507 | P11: =IF(AND(O11<>"",O11<>0,L11<>"",L11<>0),-O11+L11,"") | Q11: =IF(AND(P11<>"",P11<>0,O11<>0,O11<>""),P11/O11,"")
F12: Длина чека | I12: ='Ялта, Ленина, 18'!I12 -> 1.74 | J12: =J57 -> 2.0526316 | K12: =IF(AND(I12<>"",I12<>0,J12<>""),J12/I12,"") -> 1.1796733 | L12: =J12 -> 2.0526316 | M12: =IF(AND(I12<>"",I12<>0,L12<>"",L12<>0),L12/I12,"") -> 1.1796733 | N12: =IF(AND(J12<>0,J12<>"",I12<>0,I12<>""),L12-I12,"") -> 0.31263158 | P12: =IF(AND(O12<>"",O12<>0,L12<>"",L12<>0),-O12+L12,"") | Q12: =IF(AND(P12<>"",P12<>0,O12<>0,O12<>""),P12/O12,"") | S12: ='Ялта, Ленина, 18'!U12*График!AJ29/График!AJ31 -> 93130.435 | T12: =L57 -> 25903 | V12: ='Ялта, Ленина, 18'!X12/График!AJ31*График!AJ29 -> 87652.174 | W12: =M57 -> 0
F13: Кол-во чеков | I13: =IF(I12<>0,I9/I12,"") -> 35.06087 | J13: =G57 -> 19 | K13: =IF(AND(I13<>"",I13<>0,J13<>""),J13/I13,"") -> 0.54191468 | L13: =IF(SUMIF($G$25:$G$54,">=0",$R$25:$R$54)<>0,I13*G57/SUMIF($G$25:$G$54,">=0",$R$25:$R$54),"") -> 33.905724 | M13: =IF(AND(I13<>"",I13<>0,L13<>"",L13<>0),L13/I13,"") -> 0.96705314 | N13: =IF(AND(J13<>0,J13<>"",I13<>0,I13<>""),L13-I13,"") -> -1.1551457 | P13: =IF(AND(O13<>"",O13<>0,L13<>"",L13<>0),-O13+L13,"") | Q13: =IF(AND(P13<>"",P13<>0,O13<>0,O13<>""),P13/O13,"") | S13: =T12/S12 -> 0.27813679 | T13: =S13/J14*I14 -> 0.27813679 | V13: =W12/V12 -> 0 | W13: =V13/J14*I14 -> 0
F14: Кол-во смен план/отработано | I14: =График!AI29 -> 12 | J14: 12 | K14: =IF(AND(I14<>"",I14<>0,J14<>""),J14/I14,"") -> 1 | L14: =I14 -> 12 | M14: =IF(AND(I14<>"",I14<>0,L14<>"",L14<>0),L14/I14,"") -> 1 | N14: =IF(AND(J14<>0,J14<>"",I14<>0,I14<>""),L14-I14,"") -> 0 | P14: =IF(AND(O14<>"",O14<>0,L14<>"",L14<>0),-O14+L14,"") | Q14: =IF(AND(P14<>"",P14<>0,O14<>0,O14<>""),P14/O14,"")
F15: Средние продажи в смену | I15: ='Ялта, Ленина, 18'!I15 -> 84058.839 | J15: =J8/J14 -> 29365.125 | K15: =IF(AND(I15<>"",I15<>0,J15<>""),J15/I15,"") -> 0.34934012 | L15: =J15 -> 29365.125 | M15: =IF(AND(I15<>"",I15<>0,L15<>"",L15<>0),L15/I15,"") -> 0.34934012 | N15: =IF(AND(J15<>0,J15<>"",I15<>0,I15<>""),L15-I15,"") -> -54693.714 | P15: =IF(AND(O15<>"",O15<>0,L15<>"",L15<>0),-O15+L15,"") | Q15: =IF(AND(P15<>"",P15<>0,O15<>0,O15<>""),P15/O15,"")
F16: Отставание/Перевыполнение | J16: =J8-I15*J14 -> -656324.56 | K16: =IF(AND(I16<>"",I16<>0,J16<>""),J16/I16,"") | L16: =J16 -> -656324.56 | M16: =IF(AND(I16<>"",I16<>0,L16<>"",L16<>0),L16/I16,"") | N16: =IF(AND(J16<>0,J16<>"",I16<>0,I16<>""),L16-I16,"") | P16: =IF(AND(O16<>"",O16<>0,L16<>"",L16<>0),-O16+L16,"") | Q16: =IF(AND(P16<>"",P16<>0,O16<>0,O16<>""),P16/O16,"") | S16: UNOde50
F17: Трафик | I17: ='Ялта, Ленина, 18'!I17/График!AJ31*График!AJ29 -> 292.17391 | J17: =I57 -> 158 | K17: =IF(AND(I17<>"",I17<>0,J17<>""),J17/I17,"") -> 0.54077381 | L17: =J17/J14*I14 -> 158 | M17: =IF(AND(I17<>"",I17<>0,L17<>"",L17<>0),L17/I17,"") -> 0.54077381 | N17: =IF(AND(J17<>0,J17<>"",I17<>0,I17<>""),L17-I17,"") -> -134.17391 | P17: =IF(AND(O17<>"",O17<>0,L17<>"",L17<>0),-O17+L17,"") | Q17: =IF(AND(P17<>"",P17<>0,O17<>0,O17<>""),P17/O17,"")
K18: =IF(AND(I18<>"",I18<>0,J18<>""),J18/I18,"") | L18: =J18 -> 0 | M18: =IF(AND(I18<>"",I18<>0,L18<>"",L18<>0),L18/I18,"") | N18: =IF(AND(J18<>0,J18<>"",I18<>0,I18<>""),L18-I18,"") | O18: 0 | P18: =IF(AND(O18<>"",O18<>0,L18<>"",L18<>0),-O18+L18,"") | Q18: =IF(AND(P18<>"",P18<>0,O18<>0,O18<>""),P18/O18,"") | S18: ='Ялта, Ленина, 18'!U18*График!AJ29/График!AJ31 -> 186260.87 | T18: =K57 -> 77460
K19: =IF(AND(I19<>"",I19<>0,J19<>""),J19/I19,"") | L19: =J19 -> 0 | M19: =IF(AND(I19<>"",I19<>0,L19<>"",L19<>0),L19/I19,"") | N19: =IF(AND(J19<>0,J19<>"",I19<>0,I19<>""),L19-I19,"") | O19: 0 | P19: =IF(AND(O19<>"",O19<>0,L19<>"",L19<>0),-O19+L19,"") | Q19: =IF(AND(P19<>"",P19<>0,O19<>0,O19<>""),P19/O19,"") | S19: =T18/S18 -> 0.41586835 | T19: =S19/J14*I14 -> 0.41586835
F20: Конверсия план/факт | I20: ='Ялта, Ленина, 18'!I20 -> 0.12 | J20: =N57 -> 0.12025316 | K20: =J20/I20 -> 1.0021097 | L20: =IF(AND(K8<>0,I14<>0,I57<>0),(I57*N57+(I57/K8-I57)*I20)/(I57/K8),0) -> 0.12018748 | M20: =IF(AND(I20<>"",I20<>0,L20<>"",L20<>0),L20/I20,"") -> 1.0015623 | N20: =IF(AND(J20<>0,J20<>"",I20<>0,I20<>""),L20-I20,"") -> 0.00018747764 | P20: =IF(AND(O20<>"",O20<>0,L20<>"",L20<>0),-O20+L20,"") | Q20: =IF(AND(P20<>"",P20<>0,O20<>0,O20<>""),P20/O20,"")
B22: Факт продаж за месяц | O22: % выполнения дневного плана | P22: Раcпределение плана по дням
B23: Дата | C23: День недели | D23: Выручка (руб) | E23: Кол-во единиц (шт.) | F23: Средняя стоимость изделия (руб.) | G23: Количество чеков (шт.) | H23: Средняя сумма чека (руб.) | I23: Трафик | J23: Длина чека (шт.) | K23: UNOde50 | L23: IS | M23: Agafi | N23: Конверсия (%) | P23: выручка, план | Q23: кол-во ед, план | R23: Кол-во чеков, план | S23: выручка, скорректир.план | T23: кол-во ед, скорр. план | U23: кол-во чеков, скорр. план | V23: Коэфф. Дня Недели | W23: Специфика месяца
B24: 1 | C24: 2 | D24: 3 | E24: 4 | F24: 5 | G24: 6 | H24: 7 | I24: 8 | J24: 9 | K24: 10 | L24: 11 | M24: 12 | N24: 13 | P24: 1 | Q24: 2 | R24: 3 | S24: 4 | T24: 5 | U24: 6 | V24: 10 | W24: 11
A25: 1 | B25: 46000 | C25: вт | F25: =IF(AND(E25<>"",E25<>0),D25/E25,"") | H25: =IF(AND(G25<>"",G25<>0),D25/G25,"") | J25: =IF(AND(G25<>"",G25<>0),E25/G25,"") | N25: =IF(AND(I25<>"",I25<>0),G25/I25,"") | O25: =D25/P25 -> 0 | P25: =$I$8*V25*W25/SUMPRODUCT($W$25:$W$56,$V$25:$V$56) -> 22445.572 | Q25: =$I$9*V25*W25/SUMPRODUCT($W$25:$W$56,$V$25:$V$56) -> 2.8776374 | R25: =IF($I$12="","",Q25/$I$12) -> 1.6538146 | S25: =IF(D25<>"",D25,P25) -> 22445.572 | T25: =IF(E25<>"",E25,Q25) -> 2.8776374 | U25: =IF(G25<>"",G25,R25) -> 1.6538146 | V25: 1 | W25: 1
A26: 2 | B26: 46001 | C26: ср | D26: 69549 | E26: 6 | F26: =IF(AND(E26<>"",E26<>0),D26/E26,"") -> 11591.5 | G26: 1 | H26: =IF(AND(G26<>"",G26<>0),D26/G26,"") -> 69549 | I26: 4 | J26: =IF(AND(G26<>"",G26<>0),E26/G26,"") -> 6 | K26: 39980 | N26: =IF(AND(I26<>"",I26<>0),G26/I26,"") -> 0.25 | O26: =D26/P26 -> 3.0985622 | P26: =$I$8*V26*W26/SUMPRODUCT($W$25:$W$56,$V$25:$V$56) -> 22445.572 | Q26: =$I$9*V26*W26/SUMPRODUCT($W$25:$W$58,$V$25:$V$58) -> 2.8776374 | R26: =IF($I$12="","",Q26/$I$12) -> 1.6538146 | S26: =IF(W26<>"",IF(D26<>"",D26,($I$8-SUM($S$25:S25))*V26*W26/SUMPRODUCT($W26:$W$56,$V26:$V$56)),"") -> 69549 | T26: =IF(W26<>"",IF(E26<>"",E26,($I$9-SUM($T$25:T25))*V26*W26/SUMPRODUCT($W26:$W$58,$V26:$V$58)),"") -> 6 | U26: =IF(W26<>"",IF($I$12<>"",IF(G26<>"",G26,($I$9/$I$12-SUM($U$25:U25))*V26*W26/SUMPRODUCT($W26:$W$58,$V26:$V$58)),""),"") -> 1 | V26: 1 | W26: 1
A27: 3 | B27: 46002 | C27: чт | D27: 7984 | E27: 2 | F27: 3992 | G27: 1 | H27: =IF(AND(G27<>"",G27<>0),D27/G27,"") -> 7984 | I27: 6 | J27: =IF(AND(G27<>"",G27<>0),E27/G27,"") -> 2 | N27: =IF(AND(I27<>"",I27<>0),G27/I27,"") -> 0.16666667 | O27: =D27/P27 -> 0.35570491 | P27: =$I$8*V27*W27/SUMPRODUCT($W$25:$W$56,$V$25:$V$56) -> 22445.572 | Q27: =$I$9*V27*W27/SUMPRODUCT($W$25:$W$58,$V$25:$V$58) -> 2.8776374 | R27: =IF($I$12="","",Q27/$I$12) -> 1.6538146 | S27: =IF(W27<>"",IF(D27<>"",D27,($I$8-SUM($S$25:S26))*V27*W27/SUMPRODUCT($W27:$W$58,$V27:$V$58)),"") -> 7984 | T27: =IF(W27<>"",IF(E27<>"",E27,($I$9-SUM($T$25:T26))*V27*W27/SUMPRODUCT($W27:$W$58,$V27:$V$58)),"") -> 2 | U27: =IF(W27<>"",IF($I$12<>"",IF(G27<>"",G27,($I$9/$I$12-SUM($U$25:U26))*V27*W27/SUMPRODUCT($W27:$W$58,$V27:$V$58)),""),"") -> 1 | V27: 1 | W27: 1
A28: 4 | B28: 46003 | C28: пт | D28: 4494 | E28: 1 | F28: =IF(AND(E28<>"",E28<>0),D28/E28,"") -> 4494 | G28: 1 | H28: =IF(AND(G28<>"",G28<>0),D28/G28,"") -> 4494 | I28: 13 | J28: =IF(AND(G28<>"",G28<>0),E28/G28,"") -> 1 | N28: =IF(AND(I28<>"",I28<>0),G28/I28,"") -> 0.076923077 | O28: =D28/P28 -> 0.20021767 | P28: =$I$8*V28*W28/SUMPRODUCT($W$25:$W$56,$V$25:$V$56) -> 22445.572 | Q28: =$I$9*V28*W28/SUMPRODUCT($W$25:$W$58,$V$25:$V$58) -> 2.8776374 | R28: =IF($I$12="","",Q28/$I$12) -> 1.6538146 | S28: =IF(W28<>"",IF(D28<>"",D28,($I$8-SUM($S$25:S27))*V28*W28/SUMPRODUCT($W28:$W$58,$V28:$V$58)),"") -> 4494 | T28: =IF(W28<>"",IF(E28<>"",E28,($I$9-SUM($T$25:T27))*V28*W28/SUMPRODUCT($W28:$W$58,$V28:$V$58)),"") -> 1 | U28: =IF(W28<>"",IF($I$12<>"",IF(G28<>"",G28,($I$9/$I$12-SUM($U$25:U27))*V28*W28/SUMPRODUCT($W28:$W$58,$V28:$V$58)),""),"") -> 1 | V28: 1 | W28: 1
A29: 5 | B29: 46004 | C29: сб | D29: 12384 | E29: 2 | F29: =IF(AND(E29<>"",E29<>0),D29/E29,"") -> 6192 | G29: 1 | H29: =IF(AND(G29<>"",G29<>0),D29/G29,"") -> 12384 | I29: 10 | J29: =IF(AND(G29<>"",G29<>0),E29/G29,"") -> 2 | N29: =IF(AND(I29<>"",I29<>0),G29/I29,"") -> 0.1 | O29: =D29/P29 -> 0.55173466 | P29: =$I$8*V29*W29/SUMPRODUCT($W$25:$W$56,$V$25:$V$56) -> 22445.572 | Q29: =$I$9*V29*W29/SUMPRODUCT($W$25:$W$58,$V$25:$V$58) -> 2.8776374 | R29: =IF($I$12="","",Q29/$I$12) -> 1.6538146 | S29: =IF(W29<>"",IF(D29<>"",D29,($I$8-SUM($S$25:S28))*V29*W29/SUMPRODUCT($W29:$W$58,$V29:$V$58)),"") -> 12384 | T29: =IF(W29<>"",IF(E29<>"",E29,($I$9-SUM($T$25:T28))*V29*W29/SUMPRODUCT($W29:$W$58,$V29:$V$58)),"") -> 2 | U29: =IF(W29<>"",IF($I$12<>"",IF(G29<>"",G29,($I$9/$I$12-SUM($U$25:U28))*V29*W29/SUMPRODUCT($W29:$W$58,$V29:$V$58)),""),"") -> 1 | V29: 1 | W29: 1
A30: 6 | B30: 46005 | C30: вс | D30: 37966 | E30: 4 | F30: =IF(AND(E30<>"",E30<>0),D30/E30,"") -> 9491.5 | G30: 1 | H30: =IF(AND(G30<>"",G30<>0),D30/G30,"") -> 37966 | I30: 18 | J30: =IF(AND(G30<>"",G30<>0),E30/G30,"") -> 4 | N30: =IF(AND(I30<>"",I30<>0),G30/I30,"") -> 0.055555556 | O30: =D30/P30 -> 1.6914695 | P30: =$I$8*V30*W30/SUMPRODUCT($W$25:$W$56,$V$25:$V$56) -> 22445.572 | Q30: =$I$9*V30*W30/SUMPRODUCT($W$25:$W$58,$V$25:$V$58) -> 2.8776374 | R30: =IF($I$12="","",Q30/$I$12) -> 1.6538146 | S30: =IF(W30<>"",IF(D30<>"",D30,($I$8-SUM($S$25:S29))*V30*W30/SUMPRODUCT($W30:$W$58,$V30:$V$58)),"") -> 37966 | T30: =IF(W30<>"",IF(E30<>"",E30,($I$9-SUM($T$25:T29))*V30*W30/SUMPRODUCT($W30:$W$58,$V30:$V$58)),"") -> 4 | U30: =IF(W30<>"",IF($I$12<>"",IF(G30<>"",G30,($I$9/$I$12-SUM($U$25:U29))*V30*W30/SUMPRODUCT($W30:$W$58,$V30:$V$58)),""),"") -> 1 | V30: 1 | W30: 1
A31: 7 | B31: 46007 | C31: вт | D31: 4493 | E31: 1 | F31: =IF(AND(E31<>"",E31<>0),D31/E31,"") -> 4493 | G31: 1 | H31: =IF(AND(G31<>"",G31<>0),D31/G31,"") -> 4493 | I31: 6 | J31: =IF(AND(G31<>"",G31<>0),E31/G31,"") -> 1 | N31: =IF(AND(I31<>"",I31<>0),G31/I31,"") -> 0.16666667 | O31: =D31/P31 -> 0.20017311 | P31: =$I$8*V31*W31/SUMPRODUCT($W$25:$W$56,$V$25:$V$56) -> 22445.572 | Q31: =$I$9*V31*W31/SUMPRODUCT($W$25:$W$58,$V$25:$V$58) -> 2.8776374 | R31: =IF($I$12="","",Q31/$I$12) -> 1.6538146 | S31: =IF(W31<>"",IF(D31<>"",D31,($I$8-SUM($S$25:S30))*V31*W31/SUMPRODUCT($W31:$W$58,$V31:$V$58)),"") -> 4493 | T31: =IF(W31<>"",IF(E31<>"",E31,($I$9-SUM($T$25:T30))*V31*W31/SUMPRODUCT($W31:$W$58,$V31:$V$58)),"") -> 1 | U31: =IF(W31<>"",IF($I$12<>"",IF(G31<>"",G31,($I$9/$I$12-SUM($U$25:U30))*V31*W31/SUMPRODUCT($W31:$W$58,$V31:$V$58)),""),"") -> 1 | V31: 1 | W31: 1
A32: 8 | B32: 46008 | C32: ср | D32: 42550 | E32: 6 | F32: =IF(AND(E32<>"",E32<>0),D32/E32,"") -> 7091.6667 | G32: 2 | H32: =IF(AND(G32<>"",G32<>0),D32/G32,"") -> 21275 | I32: 22 | J32: =IF(AND(G32<>"",G32<>0),E32/G32,"") -> 3 | N32: =IF(AND(I32<>"",I32<>0),G32/I32,"") -> 0.090909091 | O32: =D32/P32 -> 1.8956969 | P32: =$I$8*V32*W32/SUMPRODUCT($W$25:$W$56,$V$25:$V$56) -> 22445.572 | Q32: =$I$9*V32*W32/SUMPRODUCT($W$25:$W$58,$V$25:$V$58) -> 2.8776374 | R32: =IF($I$12="","",Q32/$I$12) -> 1.6538146 | S32: =IF(W32<>"",IF(D32<>"",D32,($I$8-SUM($S$25:S31))*V32*W32/SUMPRODUCT($W32:$W$58,$V32:$V$58)),"") -> 42550 | T32: =IF(W32<>"",IF(E32<>"",E32,($I$9-SUM($T$25:T31))*V32*W32/SUMPRODUCT($W32:$W$58,$V32:$V$58)),"") -> 6 | U32: =IF(W32<>"",IF($I$12<>"",IF(G32<>"",G32,($I$9/$I$12-SUM($U$25:U31))*V32*W32/SUMPRODUCT($W32:$W$58,$V32:$V$58)),""),"") -> 2 | V32: 1 | W32: 1
A33: 9 | B33: 46009 | C33: чт | D33: 0 | E33: 0 | F33: =IF(AND(E33<>"",E33<>0),D33/E33,"") | G33: 0 | H33: =IF(AND(G33<>"",G33<>0),D33/G33,"") | I33: 26 | J33: =IF(AND(G33<>"",G33<>0),E33/G33,"") | N33: =IF(AND(I33<>"",I33<>0),G33/I33,"") -> 0 | O33: =D33/P33 -> 0 | P33: =$I$8*V33*W33/SUMPRODUCT($W$25:$W$56,$V$25:$V$56) -> 22445.572 | Q33: =$I$9*V33*W33/SUMPRODUCT($W$25:$W$58,$V$25:$V$58) -> 2.8776374 | R33: =IF($I$12="","",Q33/$I$12) -> 1.6538146 | S33: =IF(W33<>"",IF(D33<>"",D33,($I$8-SUM($S$25:S32))*V33*W33/SUMPRODUCT($W33:$W$58,$V33:$V$58)),"") -> 0 | T33: =IF(W33<>"",IF(E33<>"",E33,($I$9-SUM($T$25:T32))*V33*W33/SUMPRODUCT($W33:$W$58,$V33:$V$58)),"") -> 0 | U33: =IF(W33<>"",IF($I$12<>"",IF(G33<>"",G33,($I$9/$I$12-SUM($U$25:U32))*V33*W33/SUMPRODUCT($W33:$W$58,$V33:$V$58)),""),"") -> 0 | V33: 1 | W33: 1
A34: 10 | B34: 46010 | C34: пт | F34: =IF(AND(E34<>"",E34<>0),D34/E34,"") | H34: =IF(AND(G34<>"",G34<>0),D34/G34,"") | J34: =IF(AND(G34<>"",G34<>0),E34/G34,"") | N34: =IF(AND(I34<>"",I34<>0),G34/I34,"") | O34: =D34/P34 -> #DIV/0! | P34: =$I$8*V34*W34/SUMPRODUCT($W$25:$W$56,$V$25:$V$56) -> 0 | Q34: =$I$9*V34*W34/SUMPRODUCT($W$25:$W$58,$V$25:$V$58) -> 0 | R34: =IF($I$12="","",Q34/$I$12) -> 0 | S34: =IF(W34<>"",IF(D34<>"",D34,($I$8-SUM($S$25:S33))*V34*W34/SUMPRODUCT($W34:$W$58,$V34:$V$58)),"") | T34: =IF(W34<>"",IF(E34<>"",E34,($I$9-SUM($T$25:T33))*V34*W34/SUMPRODUCT($W34:$W$58,$V34:$V$58)),"") | U34: =IF(W34<>"",IF($I$12<>"",IF(G34<>"",G34,($I$9/$I$12-SUM($U$25:U33))*V34*W34/SUMPRODUCT($W34:$W$58,$V34:$V$58)),""),"")
A35: 11 | B35: 46011 | C35: сб | F35: =IF(AND(E35<>"",E35<>0),D35/E35,"") | H35: =IF(AND(G35<>"",G35<>0),D35/G35,"") | J35: =IF(AND(G35<>"",G35<>0),E35/G35,"") | N35: =IF(AND(I35<>"",I35<>0),G35/I35,"") | O35: =D35/P35 -> #DIV/0! | P35: =$I$8*V35*W35/SUMPRODUCT($W$25:$W$56,$V$25:$V$56) -> 0 | Q35: =$I$9*V35*W35/SUMPRODUCT($W$25:$W$58,$V$25:$V$58) -> 0 | R35: =IF($I$12="","",Q35/$I$12) -> 0 | S35: =IF(W35<>"",IF(D35<>"",D35,($I$8-SUM($S$25:S34))*V35*W35/SUMPRODUCT($W35:$W$58,$V35:$V$58)),"") | T35: =IF(W35<>"",IF(E34<>"",E34,($I$9-SUM($T$25:T34))*V35*W35/SUMPRODUCT($W35:$W$58,$V35:$V$58)),"") | U35: =IF(W35<>"",IF($I$12<>"",IF(G35<>"",G35,($I$9/$I$12-SUM($U$25:U34))*V35*W35/SUMPRODUCT($W35:$W$58,$V35:$V$58)),""),"")
A36: 12 | B36: 46012 | C36: вс | F36: =IF(AND(E36<>"",E36<>0),D36/E36,"") | H36: =IF(AND(G36<>"",G36<>0),D36/G36,"") | J36: =IF(AND(G36<>"",G36<>0),E36/G36,"") | N36: =IF(AND(I36<>"",I36<>0),G36/I36,"") | O36: =D36/P36 -> #DIV/0! | P36: =$I$8*V36*W36/SUMPRODUCT($W$25:$W$56,$V$25:$V$56) -> 0 | Q36: =$I$9*V36*W36/SUMPRODUCT($W$25:$W$58,$V$25:$V$58) -> 0 | R36: =IF($I$12="","",Q36/$I$12) -> 0 | S36: =IF(W36<>"",IF(D36<>"",D36,($I$8-SUM($S$25:S35))*V36*W36/SUMPRODUCT($W36:$W$58,$V36:$V$58)),"") | T36: =IF(W36<>"",IF(E35<>"",E35,($I$9-SUM($T$25:T35))*V36*W36/SUMPRODUCT($W36:$W$58,$V36:$V$58)),"") | U36: =IF(W36<>"",IF($I$12<>"",IF(G36<>"",G36,($I$9/$I$12-SUM($U$25:U35))*V36*W36/SUMPRODUCT($W36:$W$58,$V36:$V$58)),""),"")
A37: 13 | B37: 46013 | C37: пн | F37: =IF(AND(E37<>"",E37<>0),D37/E37,"") | H37: =IF(AND(G37<>"",G37<>0),D37/G37,"") | J37: =IF(AND(G37<>"",G37<>0),E37/G37,"") | N37: =IF(AND(I37<>"",I37<>0),G37/I37,"") | O37: =D37/P37 -> #DIV/0! | P37: =$I$8*V37*W37/SUMPRODUCT($W$25:$W$56,$V$25:$V$56) -> 0 | Q37: =$I$9*V37*W37/SUMPRODUCT($W$25:$W$58,$V$25:$V$58) -> 0 | R37: =IF($I$12="","",Q37/$I$12) -> 0 | S37: =IF(W37<>"",IF(D37<>"",D37,($I$8-SUM($S$25:S36))*V37*W37/SUMPRODUCT($W37:$W$58,$V37:$V$58)),"") | T37: =IF(W37<>"",IF(E37<>"",E37,($I$9-SUM($T$25:T36))*V37*W37/SUMPRODUCT($W37:$W$58,$V37:$V$58)),"") | U37: =IF(W37<>"",IF($I$12<>"",IF(G37<>"",G37,($I$9/$I$12-SUM($U$25:U36))*V37*W37/SUMPRODUCT($W37:$W$58,$V37:$V$58)),""),"")
A38: 14 | B38: 46014 | C38: вт | F38: =IF(AND(E38<>"",E38<>0),D38/E38,"") | H38: =IF(AND(G38<>"",G38<>0),D38/G38,"") | J38: =IF(AND(G38<>"",G38<>0),E38/G38,"") | N38: =IF(AND(I38<>"",I38<>0),G38/I38,"") | O38: =D38/P38 -> 0 | P38: =$I$8*V38*W38/SUMPRODUCT($W$25:$W$56,$V$25:$V$56) -> 22445.572 | Q38: =$I$9*V38*W38/SUMPRODUCT($W$25:$W$58,$V$25:$V$58) -> 2.8776374 | R38: =IF($I$12="","",Q38/$I$12) -> 1.6538146 | S38: =IF(W38<>"",IF(D38<>"",D38,($I$8-SUM($S$25:S37))*V38*W38/SUMPRODUCT($W38:$W$58,$V38:$V$58)),"") -> 22457.422 | T38: =IF(W38<>"",IF(E38<>"",E38,($I$9-SUM($T$25:T37))*V38*W38/SUMPRODUCT($W38:$W$58,$V38:$V$58)),"") -> 2.9613341 | U38: =IF(W38<>"",IF($I$12<>"",IF(G38<>"",G38,($I$9/$I$12-SUM($U$25:U37))*V38*W38/SUMPRODUCT($W38:$W$58,$V38:$V$58)),""),"") -> 2.0825455 | V38: 1 | W38: 1
A39: 15 | B39: 46015 | C39: ср | F39: =IF(AND(E39<>"",E39<>0),D39/E39,"") | H39: =IF(AND(G39<>"",G39<>0),D39/G39,"") | J39: =IF(AND(G39<>"",G39<>0),E39/G39,"") | N39: =IF(AND(I39<>"",I39<>0),G39/I39,"") | O39: =D39/P39 -> 0 | P39: =$I$8*V39*W39/SUMPRODUCT($W$25:$W$56,$V$25:$V$56) -> 22445.572 | Q39: =$I$9*V39*W39/SUMPRODUCT($W$25:$W$58,$V$25:$V$58) -> 2.8776374 | R39: =IF($I$12="","",Q39/$I$12) -> 1.6538146 | S39: =IF(W39<>"",IF(D39<>"",D39,($I$8-SUM($S$25:S38))*V39*W39/SUMPRODUCT($W39:$W$58,$V39:$V$58)),"") -> 22457.422 | T39: =IF(W39<>"",IF(E39<>"",E39,($I$9-SUM($T$25:T38))*V39*W39/SUMPRODUCT($W39:$W$58,$V39:$V$58)),"") -> 2.9613341 | U39: =IF(W39<>"",IF($I$12<>"",IF(G39<>"",G39,($I$9/$I$12-SUM($U$25:U38))*V39*W39/SUMPRODUCT($W39:$W$58,$V39:$V$58)),""),"") -> 2.0825455 | V39: 1 | W39: 1
A40: 16 | B40: 46016 | C40: чт | F40: =IF(AND(E40<>"",E40<>0),D40/E40,"") | H40: =IF(AND(G40<>"",G40<>0),D40/G40,"") | J40: =IF(AND(G40<>"",G40<>0),E40/G40,"") | N40: =IF(AND(I40<>"",I40<>0),G40/I40,"") | O40: =D40/P40 -> 0 | P40: =$I$8*V40*W40/SUMPRODUCT($W$25:$W$56,$V$25:$V$56) -> 22445.572 | Q40: =$I$9*V40*W40/SUMPRODUCT($W$25:$W$58,$V$25:$V$58) -> 2.8776374 | R40: =IF($I$12="","",Q40/$I$12) -> 1.6538146 | S40: =IF(W40<>"",IF(D40<>"",D40,($I$8-SUM($S$25:S39))*V40*W40/SUMPRODUCT($W40:$W$58,$V40:$V$58)),"") -> 22457.422 | T40: =IF(W40<>"",IF(E39<>"",E39,($I$9-SUM($T$25:T39))*V40*W40/SUMPRODUCT($W40:$W$58,$V40:$V$58)),"") -> 2.9613341 | U40: =IF(W40<>"",IF($I$12<>"",IF(G40<>"",G40,($I$9/$I$12-SUM($U$25:U39))*V40*W40/SUMPRODUCT($W40:$W$58,$V40:$V$58)),""),"") -> 2.0825455 | V40: 1 | W40: 1
A41: 17 | B41: 46017 | C41: пт | F41: =IF(AND(E41<>"",E41<>0),D41/E41,"") | H41: =IF(AND(G41<>"",G41<>0),D41/G41,"") | J41: =IF(AND(G41<>"",G41<>0),E41/G41,"") | N41: =IF(AND(I41<>"",I41<>0),G41/I41,"") | O41: =D41/P41 -> 0 | P41: =$I$8*V41*W41/SUMPRODUCT($W$25:$W$56,$V$25:$V$56) -> 32321.623 | Q41: =$I$9*V41*W41/SUMPRODUCT($W$25:$W$58,$V$25:$V$58) -> 4.1437979 | R41: =IF($I$12="","",Q41/$I$12) -> 2.381493 | S41: =IF(W41<>"",IF(D41<>"",D41,($I$8-SUM($S$25:S40))*V41*W41/SUMPRODUCT($W41:$W$58,$V41:$V$58)),"") -> 32338.688 | T41: =IF(W41<>"",IF(E40<>"",E40,($I$9-SUM($T$25:T40))*V41*W41/SUMPRODUCT($W41:$W$58,$V41:$V$58)),"") -> 4.2643211 | U41: =IF(W41<>"",IF($I$12<>"",IF(G41<>"",G41,($I$9/$I$12-SUM($U$25:U40))*V41*W41/SUMPRODUCT($W41:$W$58,$V41:$V$58)),""),"") -> 2.9988655 | V41: 1.2 | W41: 1.2
A42: 18 | B42: 46018 | C42: сб | F42: =IF(AND(E42<>"",E42<>0),D42/E42,"") | H42: =IF(AND(G42<>"",G42<>0),D42/G42,"") | J42: =IF(AND(G42<>"",G42<>0),E42/G42,"") | N42: =IF(AND(I42<>"",I42<>0),G42/I42,"") | O42: =D42/P42 -> 0 | P42: =$I$8*V42*W42/SUMPRODUCT($W$25:$W$56,$V$25:$V$56) -> 32321.623 | Q42: =$I$9*V42*W42/SUMPRODUCT($W$25:$W$58,$V$25:$V$58) -> 4.1437979 | R42: =IF($I$12="","",Q42/$I$12) -> 2.381493 | S42: =IF(W42<>"",IF(D42<>"",D42,($I$8-SUM($S$25:S41))*V42*W42/SUMPRODUCT($W42:$W$58,$V42:$V$58)),"") -> 32338.688 | T42: =IF(W42<>"",IF(E42<>"",E42,($I$9-SUM($T$25:T41))*V42*W42/SUMPRODUCT($W42:$W$58,$V42:$V$58)),"") -> 4.2643211 | U42: =IF(W42<>"",IF($I$12<>"",IF(G42<>"",G42,($I$9/$I$12-SUM($U$25:U41))*V42*W42/SUMPRODUCT($W42:$W$58,$V42:$V$58)),""),"") -> 2.9988655 | V42: 1.2 | W42: 1.2
A43: 19 | B43: 46019 | C43: вс | F43: =IF(AND(E43<>"",E43<>0),D43/E43,"") | H43: =IF(AND(G43<>"",G43<>0),D43/G43,"") | J43: =IF(AND(G43<>"",G43<>0),E43/G43,"") | N43: =IF(AND(I43<>"",I43<>0),G43/I43,"") | O43: =D43/P43 -> 0 | P43: =$I$8*V43*W43/SUMPRODUCT($W$25:$W$56,$V$25:$V$56) -> 32321.623 | Q43: =$I$9*V43*W43/SUMPRODUCT($W$25:$W$58,$V$25:$V$58) -> 4.1437979 | R43: =IF($I$12="","",Q43/$I$12) -> 2.381493 | S43: =IF(W43<>"",IF(D43<>"",D43,($I$8-SUM($S$25:S42))*V43*W43/SUMPRODUCT($W43:$W$58,$V43:$V$58)),"") -> 32338.688 | T43: =IF(W43<>"",IF(E43<>"",E43,($I$9-SUM($T$25:T42))*V43*W43/SUMPRODUCT($W43:$W$58,$V43:$V$58)),"") -> 4.2643211 | U43: =IF(W43<>"",IF($I$12<>"",IF(G43<>"",G43,($I$9/$I$12-SUM($U$25:U42))*V43*W43/SUMPRODUCT($W43:$W$58,$V43:$V$58)),""),"") -> 2.9988655 | V43: 1.2 | W43: 1.2
A44: 20 | B44: 46020 | C44: пн | D44: 22675 | E44: 3 | F44: =IF(AND(E44<>"",E44<>0),D44/E44,"") -> 7558.3333 | G44: 1 | H44: =IF(AND(G44<>"",G44<>0),D44/G44,"") -> 22675 | I44: 5 | J44: =IF(AND(G44<>"",G44<>0),E44/G44,"") -> 3 | N44: =IF(AND(I44<>"",I44<>0),G44/I44,"") -> 0.2 | O44: =D44/P44 -> 0.70154273 | P44: =$I$8*V44*W44/SUMPRODUCT($W$25:$W$56,$V$25:$V$56) -> 32321.623 | Q44: =$I$9*V44*W44/SUMPRODUCT($W$25:$W$58,$V$25:$V$58) -> 4.1437979 | R44: =IF($I$12="","",Q44/$I$12) -> 2.381493 | S44: =IF(W44<>"",IF(D44<>"",D44,($I$8-SUM($S$25:S43))*V44*W44/SUMPRODUCT($W44:$W$58,$V44:$V$58)),"") -> 22675 | T44: =IF(W44<>"",IF(E44<>"",E44,($I$9-SUM($T$25:T43))*V44*W44/SUMPRODUCT($W44:$W$58,$V44:$V$58)),"") -> 3 | U44: =IF(W44<>"",IF($I$12<>"",IF(G44<>"",G44,($I$9/$I$12-SUM($U$25:U43))*V44*W44/SUMPRODUCT($W44:$W$58,$V44:$V$58)),""),"") -> 1 | V44: 1.2 | W44: 1.2
A45: 21 | B45: 46021 | C45: вт | D45: 59531.5 | E45: 8 | F45: =IF(AND(E45<>"",E45<>0),D45/E45,"") -> 7441.4375 | G45: 5 | H45: =IF(AND(G45<>"",G45<>0),D45/G45,"") -> 11906.3 | I45: 28 | J45: =IF(AND(G45<>"",G45<>0),E45/G45,"") -> 1.6 | N45: =IF(AND(I45<>"",I45<>0),G45/I45,"") -> 0.17857143 | O45: =D45/P45 -> 1.8418475 | P45: =$I$8*V45*W45/SUMPRODUCT($W$25:$W$56,$V$25:$V$56) -> 32321.623 | Q45: =$I$9*V45*W45/SUMPRODUCT($W$25:$W$58,$V$25:$V$58) -> 4.1437979 | R45: =IF($I$12="","",Q45/$I$12) -> 2.381493 | S45: =IF(W45<>"",IF(D45<>"",D45,($I$8-SUM($S$25:S44))*V45*W45/SUMPRODUCT($W45:$W$58,$V45:$V$58)),"") -> 59531.5 | T45: =IF(W45<>"",IF(E45<>"",E45,($I$9-SUM($T$25:T44))*V45*W45/SUMPRODUCT($W45:$W$58,$V45:$V$58)),"") -> 8 | U45: =IF(W45<>"",IF($I$12<>"",IF(G45<>"",G45,($I$9/$I$12-SUM($U$25:U44))*V45*W45/SUMPRODUCT($W45:$W$58,$V45:$V$58)),""),"") -> 5 | V45: 1.2 | W45: 1.2
A46: 22 | B46: 46022 | C46: ср | D46: =27372+25490+11990 -> 64852 | E46: 5 | F46: =IF(AND(E46<>"",E46<>0),D46/E46,"") -> 12970.4 | G46: 4 | H46: =IF(AND(G46<>"",G46<>0),D46/G46,"") -> 16213 | I46: 20 | J46: =IF(AND(G46<>"",G46<>0),E46/G46,"") -> 1.25 | K46: =11990+25490 -> 37480 | N46: =IF(AND(I46<>"",I46<>0),G46/I46,"") -> 0.2 | O46: =D46/P46 -> 2.8893004 | P46: =$I$8*V46*W46/SUMPRODUCT($W$25:$W$56,$V$25:$V$56) -> 22445.572 | Q46: =$I$9*V46*W46/SUMPRODUCT($W$25:$W$58,$V$25:$V$58) -> 2.8776374 | R46: =IF($I$12="","",Q46/$I$12) -> 1.6538146 | S46: =IF(W46<>"",IF(D46<>"",D46,($I$8-SUM($S$25:S45))*V46*W46/SUMPRODUCT($W46:$W$58,$V46:$V$58)),"") -> 64852 | T46: =IF(W46<>"",IF(E46<>"",E46,($I$9-SUM($T$25:T45))*V46*W46/SUMPRODUCT($W46:$W$58,$V46:$V$58)),"") -> 5 | U46: =IF(W46<>"",IF($I$12<>"",IF(G46<>"",G46,($I$9/$I$12-SUM($U$25:U45))*V46*W46/SUMPRODUCT($W46:$W$58,$V46:$V$58)),""),"") -> 4 | V46: 1 | W46: 1
A47: 23 | F47: =IF(AND(E47<>"",E47<>0),D47/E47,"") | H47: =IF(AND(G47<>"",G47<>0),D47/G47,"") | J47: =IF(AND(G47<>"",G47<>0),E47/G47,"") | N47: =IF(AND(I47<>"",I47<>0),G47/I47,"") | O47: =D47/P47 -> #DIV/0! | P47: =$I$8*V47*W47/SUMPRODUCT($W$25:$W$56,$V$25:$V$56) -> 0 | Q47: =$I$9*V47*W47/SUMPRODUCT($W$25:$W$58,$V$25:$V$58) -> 0 | R47: =IF($I$12="","",Q47/$I$12) -> 0 | S47: =IF(W47<>"",IF(D47<>"",D47,($I$8-SUM($S$25:S46))*V47*W47/SUMPRODUCT($W47:$W$58,$V47:$V$58)),"") | T47: =IF(W47<>"",IF(E47<>"",E47,($I$9-SUM($T$25:T46))*V47*W47/SUMPRODUCT($W47:$W$58,$V47:$V$58)),"") | U47: =IF(W47<>"",IF($I$12<>"",IF(G47<>"",G47,($I$9/$I$12-SUM($U$25:U46))*V47*W47/SUMPRODUCT($W47:$W$58,$V47:$V$58)),""),"")
A48: 24 | F48: =IF(AND(E48<>"",E48<>0),D48/E48,"") | H48: =IF(AND(G48<>"",G48<>0),D48/G48,"") | J48: =IF(AND(G48<>"",G48<>0),E48/G48,"") | N48: =IF(AND(I48<>"",I48<>0),G48/I48,"") | O48: =D48/P48 -> #DIV/0! | P48: =$I$8*V48*W48/SUMPRODUCT($W$25:$W$56,$V$25:$V$56) -> 0 | Q48: =$I$9*V48*W48/SUMPRODUCT($W$25:$W$58,$V$25:$V$58) -> 0 | R48: =IF($I$12="","",Q48/$I$12) -> 0 | S48: =IF(W48<>"",IF(D48<>"",D48,($I$8-SUM($S$25:S47))*V48*W48/SUMPRODUCT($W48:$W$58,$V48:$V$58)),"") | T48: =IF(W48<>"",IF(E48<>"",E48,($I$9-SUM($T$25:T47))*V48*W48/SUMPRODUCT($W48:$W$58,$V48:$V$58)),"") | U48: =IF(W48<>"",IF($I$12<>"",IF(G48<>"",G48,($I$9/$I$12-SUM($U$25:U47))*V48*W48/SUMPRODUCT($W48:$W$58,$V48:$V$58)),""),"")
A49: 25 | F49: =IF(AND(E49<>"",E49<>0),D49/E49,"") | H49: =IF(AND(G49<>"",G49<>0),D49/G49,"") | J49: =IF(AND(G49<>"",G49<>0),E49/G49,"") | N49: =IF(AND(I49<>"",I49<>0),G49/I49,"") | O49: =D49/P49 -> #DIV/0! | P49: =$I$8*V49*W49/SUMPRODUCT($W$25:$W$56,$V$25:$V$56) -> 0 | Q49: =$I$9*V49*W49/SUMPRODUCT($W$25:$W$58,$V$25:$V$58) -> 0 | R49: =IF($I$12="","",Q49/$I$12) -> 0 | S49: =IF(W49<>"",IF(D49<>"",D49,($I$8-SUM($S$25:S48))*V49*W49/SUMPRODUCT($W49:$W$58,$V49:$V$58)),"") | T49: =IF(W49<>"",IF(E49<>"",E49,($I$9-SUM($T$25:T48))*V49*W49/SUMPRODUCT($W49:$W$58,$V49:$V$58)),"") | U49: =IF(W49<>"",IF($I$12<>"",IF(G49<>"",G49,($I$9/$I$12-SUM($U$25:U48))*V49*W49/SUMPRODUCT($W49:$W$58,$V49:$V$58)),""),"")
A50: 26 | F50: =IF(AND(E50<>"",E50<>0),D50/E50,"") | H50: =IF(AND(G50<>"",G50<>0),D50/G50,"") | J50: =IF(AND(G50<>"",G50<>0),E50/G50,"") | N50: =IF(AND(I50<>"",I50<>0),G50/I50,"") | O50: =D50/P50 -> #DIV/0! | P50: =$I$8*V50*W50/SUMPRODUCT($W$25:$W$56,$V$25:$V$56) -> 0 | Q50: =$I$9*V50*W50/SUMPRODUCT($W$25:$W$58,$V$25:$V$58) -> 0 | R50: =IF($I$12="","",Q50/$I$12) -> 0 | S50: =IF(W50<>"",IF(D50<>"",D50,($I$8-SUM($S$25:S49))*V50*W50/SUMPRODUCT($W50:$W$58,$V50:$V$58)),"") | T50: =IF(W50<>"",IF(E50<>"",E50,($I$9-SUM($T$25:T49))*V50*W50/SUMPRODUCT($W50:$W$58,$V50:$V$58)),"") | U50: =IF(W50<>"",IF($I$12<>"",IF(G50<>"",G50,($I$9/$I$12-SUM($U$25:U49))*V50*W50/SUMPRODUCT($W50:$W$58,$V50:$V$58)),""),"")
A51: 27 | F51: =IF(AND(E51<>"",E51<>0),D51/E51,"") | H51: =IF(AND(G51<>"",G51<>0),D51/G51,"") | J51: =IF(AND(G51<>"",G51<>0),E51/G51,"") | N51: =IF(AND(I51<>"",I51<>0),G51/I51,"") | O51: =D51/P51 -> #DIV/0! | P51: =$I$8*V51*W51/SUMPRODUCT($W$25:$W$56,$V$25:$V$56) -> 0 | Q51: =$I$9*V51*W51/SUMPRODUCT($W$25:$W$58,$V$25:$V$58) -> 0 | R51: =IF($I$12="","",Q51/$I$12) -> 0 | S51: =IF(W51<>"",IF(D51<>"",D51,($I$8-SUM($S$25:S50))*V51*W51/SUMPRODUCT($W51:$W$58,$V51:$V$58)),"") | T51: =IF(W51<>"",IF(E51<>"",E51,($I$9-SUM($T$25:T50))*V51*W51/SUMPRODUCT($W51:$W$58,$V51:$V$58)),"") | U51: =IF(W51<>"",IF($I$12<>"",IF(G51<>"",G51,($I$9/$I$12-SUM($U$25:U50))*V51*W51/SUMPRODUCT($W51:$W$58,$V51:$V$58)),""),"")
A52: 28 | F52: =IF(AND(E52<>"",E52<>0),D52/E52,"") | H52: =IF(AND(G52<>"",G52<>0),D52/G52,"") | J52: =IF(AND(G52<>"",G52<>0),E52/G52,"") | N52: =IF(AND(I52<>"",I52<>0),G52/I52,"") | O52: =D52/P52 -> #DIV/0! | P52: =$I$8*V52*W52/SUMPRODUCT($W$25:$W$56,$V$25:$V$56) -> 0 | Q52: =$I$9*V52*W52/SUMPRODUCT($W$25:$W$58,$V$25:$V$58) -> 0 | R52: =IF($I$12="","",Q52/$I$12) -> 0 | S52: =IF(W52<>"",IF(D52<>"",D52,($I$8-SUM($S$25:S51))*V52*W52/SUMPRODUCT($W52:$W$58,$V52:$V$58)),"") | T52: =IF(W52<>"",IF(E52<>"",E52,($I$9-SUM($T$25:T51))*V52*W52/SUMPRODUCT($W52:$W$58,$V52:$V$58)),"") | U52: =IF(W52<>"",IF($I$12<>"",IF(G52<>"",G52,($I$9/$I$12-SUM($U$25:U51))*V52*W52/SUMPRODUCT($W52:$W$58,$V52:$V$58)),""),"")
A53: 29 | F53: =IF(AND(E53<>"",E53<>0),D53/E53,"") | H53: =IF(AND(G53<>"",G53<>0),D53/G53,"") | J53: =IF(AND(G53<>"",G53<>0),E53/G53,"") | N53: =IF(AND(I53<>"",I53<>0),G53/I53,"") | O53: =D53/P53 -> #DIV/0! | P53: =$I$8*V53*W53/SUMPRODUCT($W$25:$W$56,$V$25:$V$56) -> 0 | Q53: =$I$9*V53*W53/SUMPRODUCT($W$25:$W$58,$V$25:$V$58) -> 0 | R53: =IF($I$12="","",Q53/$I$12) -> 0 | S53: =IF(W53<>"",IF(D53<>"",D53,($I$8-SUM($S$25:S52))*V53*W53/SUMPRODUCT($W53:$W$58,$V53:$V$58)),"") | T53: =IF(W53<>"",IF(E53<>"",E53,($I$9-SUM($T$25:T52))*V53*W53/SUMPRODUCT($W53:$W$58,$V53:$V$58)),"") | U53: =IF(W53<>"",IF($I$12<>"",IF(G53<>"",G53,($I$9/$I$12-SUM($U$25:U52))*V53*W53/SUMPRODUCT($W53:$W$58,$V53:$V$58)),""),"")
F54: =IF(AND(E54<>"",E54<>0),D54/E54,"") | H54: =IF(AND(G54<>"",G54<>0),D54/G54,"") | J54: =IF(AND(G54<>"",G54<>0),E54/G54,"") | N54: =IF(AND(I54<>"",I54<>0),G54/I54,"") | O54: =D54/P54 -> #DIV/0! | P54: =$I$8*V54*W54/SUMPRODUCT($W$25:$W$56,$V$25:$V$56) -> 0 | Q54: =$I$9*V54*W54/SUMPRODUCT($W$25:$W$58,$V$25:$V$58) -> 0 | R54: =IF($I$12="","",Q54/$I$12) -> 0 | S54: =IF(W54<>"",IF(D54<>"",D54,($I$8-SUM($S$25:S50))*V54*W54/SUMPRODUCT($W54:$W$58,$V54:$V$58)),"") | T54: =IF(W54<>"",IF(E54<>"",E54,($I$9-SUM($T$25:T50))*V54*W54/SUMPRODUCT($W54:$W$58,$V54:$V$58)),"") | U54: =IF(W54<>"",IF($I$12<>"",IF(G54<>"",G54,($I$9/$I$12-SUM($U$25:U50))*V54*W54/SUMPRODUCT($W54:$W$58,$V54:$V$58)),""),"")
F55: =IF(AND(E55<>"",E55<>0),D55/E55,"") | H55: =IF(AND(G55<>"",G55<>0),D55/G55,"") | J55: =IF(AND(G55<>"",G55<>0),E55/G55,"") | N55: =IF(AND(I55<>"",I55<>0),G55/I55,"") | O55: =D55/P55 -> #DIV/0! | P55: =$I$8*V55*W55/SUMPRODUCT($W$25:$W$56,$V$25:$V$56) -> 0 | Q55: =$I$9*V55*W55/SUMPRODUCT($W$25:$W$58,$V$25:$V$58) -> 0 | R55: =IF($I$12="","",Q55/$I$12) -> 0 | S55: =IF(W55<>"",IF(D55<>"",D55,($I$8-SUM($S$25:S54))*V55*W55/SUMPRODUCT($W55:$W$58,$V55:$V$58)),"") | T55: =IF(W55<>"",IF(E55<>"",E55,($I$9-SUM($T$25:T54))*V55*W55/SUMPRODUCT($W55:$W$58,$V55:$V$58)),"") | U55: =IF(W55<>"",IF($I$12<>"",IF(G55<>"",G55,($I$9/$I$12-SUM($U$25:U54))*V55*W55/SUMPRODUCT($W55:$W$58,$V55:$V$58)),""),"")
B56: 45996 | C56: пт | D56: 25903 | E56: 1 | F56: =IF(AND(E56<>"",E56<>0),D56/E56,"") -> 25903 | G56: 1 | H56: =IF(AND(G56<>"",G56<>0),D56/G56,"") -> 25903 | J56: =IF(AND(G56<>"",G56<>0),E56/G56,"") -> 1 | L56: 25903 | N56: =IF(AND(I56<>"",I56<>0),G56/I56,"") | O56: =D56/P56 -> 1.1540361 | P56: =$I$8*V56*W56/SUMPRODUCT($W$25:$W$56,$V$25:$V$56) -> 22445.572 | Q56: =$I$9*V56*W56/SUMPRODUCT($W$25:$W$58,$V$25:$V$58) -> 2.8776374 | R56: =IF($I$12="","",Q56/$I$12) -> 1.6538146 | S56: =IF(W56<>"",IF(D56<>"",D56,($I$8-SUM($S$25:S55))*V56*W56/SUMPRODUCT($W56:$W$58,$V56:$V$58)),"") -> 25903 | T56: =IF(W56<>"",IF(E56<>"",E56,($I$9-SUM($T$25:T55))*V56*W56/SUMPRODUCT($W56:$W$58,$V56:$V$58)),"") -> 1 | U56: =IF(W56<>"",IF($I$12<>"",IF(G56<>"",G56,($I$9/$I$12-SUM($U$25:U55))*V56*W56/SUMPRODUCT($W56:$W$58,$V56:$V$58)),""),"") -> 1 | V56: 1 | W56: 1
D57: =SUM(D25:D56) -> 352381.5 | E57: =SUM(E25:E56) -> 39 | F57: =IF(AND(E57<>"",E57<>0),D57/E57,"") -> 9035.4231 | G57: =SUM(G25:G56) -> 19 | H57: =IF(AND(G57<>"",G57<>0),D57/G57,"") -> 18546.395 | I57: =SUM(I25:I56) -> 158 | J57: =IF(AND(G57<>"",G57<>0),E57/G57,"") -> 2.0526316 | K57: =SUM(K25:K56) -> 77460 | L57: =SUM(L25:L56) -> 25903 | M57: =SUM(M25:M56) -> 0 | N57: =IF(AND(I57<>"",I57<>0),G57/I57,"") -> 0.12025316 | O57: =D57/P57 -> 0.74053666 | P57: =SUM(P25:P56) -> 475846.12 | Q57: =SUM(Q25:Q55) -> 58.128276 | R57: =SUM(R25:R55) -> 33.407055 | S57: =SUM(S25:S56) -> 539215.4 | T57: =SUM(T25:T55) -> 62.554603 | U57: =SUM(U25:U55) -> 34.898048
D58: =SUMIF(D25:D54,"",P25:P54)+D57 -> 539128.66

Sheet Уразгильдеева Е. Р. 
B1: =TODAY()-1 -> 46060
B2: (отчетная дата) | J2: ЕЖЕДНЕВНЫЙ ОТЧЕТ О ПРОДАЖАХ
B3: Осталось до выполнения плана!!! | J3: =График!B28 -> Уразгильдеева Екатерина
C4: =I8-D50 -> 1110307.6 | E4: =IF(I8<>0, C4/I8, 0) -> 1
F6: Целевые показатели
F7: Показатель | I7: План | J7: Факт | K7: % выполнения | L7: Прогноз выполнения | M7: % выполнения по прогнозу | N7: Отклонение | O7: Факт аналогичного месяца прошлого года | P7: Отклонение LFL
F8: Выручка | I8: ='Ялта, Ленина, 18'!I8/График!AJ31*График!AJ28 -> 1110307.6 | J8: =D57 -> 620172 | K8: =IF(AND(I8<>"",I8<>0,J8<>""),J8/I8,"") -> 0.55855872 | L8: =IF(SUMIF($D$25:$D$56,">=0",$P$25:$P$56)<>0,I8*D57/SUMIF($D$25:$D$56,">=0",$P$25:$P$56),0) -> 714695.34 | M8: =IF(AND(I8<>"",I8<>0,L8<>"",L8<>0),L8/I8,"") -> 0.64369128 | N8: =IF(AND(J8<>0,J8<>"",I8<>0,I8<>""),L8-I8,"") -> -395612.28 | P8: =IF(AND(O8<>"", O8<>0, L8<>"", L8<>0), -O8+L8, "") | Q8: =IF(AND(P8<>"", P8<>0, O8<>0, O8<>""), P8/O8, "")
F9: Кол-во изделий | I9: =I8/I11 -> 142.34713 | J9: =E57 -> 70 | K9: =IF(AND(I9<>"", I9<>0, J9<>""), J9/I9, "") -> 0.49175561 | L9: =IF(SUMIF($E$25:$E$54,">=0",$Q$25:$Q$54)<>0,I9*E57/SUMIF($E$25:$E$54,">=0",$Q$25:$Q$54),0) -> 80.66903 | M9: =IF(AND(I9<>"",I9<>0,L9<>"",L9<>0),L9/I9,"") -> 0.5667064 | N9: =IF(AND(J9<>0,J9<>"",I9<>0,I9<>""),L9-I9,"") -> -61.678101 | O9: =O8/O11 -> #DIV/0! | P9: =IF(AND(O9<>"", O9<>0, L9<>"", L9<>0), -O9+L9, "") -> #DIV/0! | Q9: =IF(AND(P9<>"", P9<>0, O9<>0, O9<>""), P9/O9, "") -> #DIV/0!
F10: Средний чек | I10: =I11*I12 -> 13572 | J10: =H57 -> 15126.146 | K10: =IF(AND(I10<>"", I10<>0, J10<>""), J10/I10, "") -> 1.1145112 | L10: =J10 -> 15126.146 | M10: =IF(AND(I10<>"",I10<>0,L10<>"",L10<>0),L10/I10,"") -> 1.1145112 | N10: =IF(AND(J10<>0,J10<>"",I10<>0,I10<>""),L10-I10,"") -> 1554.1463 | O10: =O11*O12 -> 0 | P10: =IF(AND(O10<>"", O10<>0, L10<>"", L10<>0), -O10+L10, "") | Q10: =IF(AND(P10<>"", P10<>0, O10<>0, O10<>""), P10/O10, "") | S10: IS | V10: =M23 -> Agafi
F11: Средняя стоимость изделия | I11: ='Ялта, Ленина, 18'!I11 -> 7800 | J11: =F57 -> 8859.6 | K11: =IF(AND(I11<>"", I11<>0, J11<>""), J11/I11, "") -> 1.1358462 | L11: =IF(L9>0,L8/L9,"") -> 8859.6 | M11: =IF(AND(I11<>"",I11<>0,L11<>"",L11<>0),L11/I11,"") -> 1.1358462 | N11: =IF(AND(J11<>0,J11<>"",I11<>0,I11<>""),L11-I11,"") -> 1059.6 | P11: =IF(AND(O11<>"", O11<>0, L11<>"", L11<>0), -O11+L11, "") | Q11: =IF(AND(P11<>"", P11<>0, O11<>0, O11<>""), P11/O11, "")
F12: Длина чека | I12: ='Ялта, Ленина, 18'!I12 -> 1.74 | J12: =J57 -> 1.7073171 | K12: =IF(AND(I12<>"", I12<>0, J12<>""), J12/I12, "") -> 0.98121671 | L12: =J12 -> 1.7073171 | M12: =IF(AND(I12<>"",I12<>0,L12<>"",L12<>0),L12/I12,"") -> 0.98121671 | N12: =IF(AND(J12<>0,J12<>"",I12<>0,I12<>""),L12-I12,"") -> -0.032682927 | P12: =IF(AND(O12<>"", O12<>0, L12<>"", L12<>0), -O12+L12, "") | Q12: =IF(AND(P12<>"", P12<>0, O12<>0, O12<>""), P12/O12, "") | S12: ='Ялта, Ленина, 18'!U12*График!AJ28/График!AJ31 -> 217304.35 | T12: =L57 -> 220 | U12: =S12-T12 -> 217084.35 | V12: ='Ялта, Ленина, 18'!X12/График!AJ31*График!AJ28 -> 204521.74 | W12: =M57 -> 37180 | X12: =V12-W12 -> 167341.74
F13: Кол-во чеков | I13: =IF(I12<>0, I9/I12, "") -> 81.808696 | J13: =G57 -> 41 | K13: =IF(AND(I13<>"", I13<>0, J13<>""), J13/I13, "") -> 0.50116922 | L13: =IF(SUMIF($G$25:$G$54,">=0",$R$25:$R$54)<>0,I13*G57/SUMIF($G$25:$G$54,">=0",$R$25:$R$54),"") -> 47.249003 | M13: =IF(AND(I13<>"",I13<>0,L13<>"",L13<>0),L13/I13,"") -> 0.57755478 | N13: =IF(AND(J13<>0,J13<>"",I13<>0,I13<>""),L13-I13,"") -> -34.559693 | P13: =IF(AND(O13<>"", O13<>0, L13<>"", L13<>0), -O13+L13, "") | Q13: =IF(AND(P13<>"", P13<>0, O13<>0, O13<>""), P13/O13, "") | S13: =T12/S12 -> 0.001012405 | T13: =S13/J14*I14 -> 0.001012405 | V13: =W12/V12 -> 0.18178997 | W13: =V13/J14*I14 -> 0.18178997
F14: Кол-во смен план/отработано | I14: =График!AI28 -> 23 | J14: 23 | K14: =IF(AND(I14<>"", I14<>0, J14<>""), J14/I14, "") -> 1 | L14: =I14 -> 23 | M14: =IF(AND(I14<>"",I14<>0,L14<>"",L14<>0),L14/I14,"") -> 1 | N14: =IF(AND(J14<>0,J14<>"",I14<>0,I14<>""),L14-I14,"") -> 0 | P14: =IF(AND(O14<>"", O14<>0, L14<>"", L14<>0), -O14+L14, "") | Q14: =IF(AND(P14<>"", P14<>0, O14<>0, O14<>""), P14/O14, "")
F15: Средние продажи в смену | I15: ='Ялта, Ленина, 18'!I15 -> 84058.839 | J15: =J8/J14 -> 26964 | K15: =IF(AND(I15<>"", I15<>0, J15<>""), J15/I15, "") -> 0.32077531 | L15: =J15 -> 26964 | M15: =IF(AND(I15<>"",I15<>0,L15<>"",L15<>0),L15/I15,"") -> 0.32077531 | N15: =IF(AND(J15<>0,J15<>"",I15<>0,I15<>""),L15-I15,"") -> -57094.839 | P15: =IF(AND(O15<>"", O15<>0, L15<>"", L15<>0), -O15+L15, "") | Q15: =IF(AND(P15<>"", P15<>0, O15<>0, O15<>""), P15/O15, "")
F16: Отставание/Перевыполнение | J16: =J8-I15*J14 -> -1313181.3 | K16: =IF(AND(I16<>"", I16<>0, J16<>""), J16/I16, "") | L16: =J16 -> -1313181.3 | M16: =IF(AND(I16<>"",I16<>0,L16<>"",L16<>0),L16/I16,"") | N16: =IF(AND(J16<>0,J16<>"",I16<>0,I16<>""),L16-I16,"") | P16: =IF(AND(O16<>"", O16<>0, L16<>"", L16<>0), -O16+L16, "") | Q16: =IF(AND(P16<>"", P16<>0, O16<>0, O16<>""), P16/O16, "") | S16: UNOde50
F17: Трафик | I17: ='Ялта, Ленина, 18'!I17/График!AJ31*График!AJ28 -> 681.73913 | J17: =I57 -> 324 | K17: =IF(AND(I17<>"", I17<>0, J17<>""), J17/I17, "") -> 0.4752551 | L17: =J17/J14*I14 -> 324 | M17: =IF(AND(I17<>"",I17<>0,L17<>"",L17<>0),L17/I17,"") -> 0.4752551 | N17: =IF(AND(J17<>0,J17<>"",I17<>0,I17<>""),L17-I17,"") -> -357.73913 | P17: =IF(AND(O17<>"", O17<>0, L17<>"", L17<>0), -O17+L17, "") | Q17: =IF(AND(P17<>"", P17<>0, O17<>0, O17<>""), P17/O17, "")
K18: =IF(AND(I18<>"", I18<>0, J18<>""), J18/I18, "") | L18: =J18 -> 0 | M18: =IF(AND(I18<>"",I18<>0,L18<>"",L18<>0),L18/I18,"") | N18: =IF(AND(J18<>0,J18<>"",I18<>0,I18<>""),L18-I18,"") | O18: 0 | P18: =IF(AND(O18<>"", O18<>0, L18<>"", L18<>0), -O18+L18, "") | Q18: =IF(AND(P18<>"", P18<>0, O18<>0, O18<>""), P18/O18, "") | S18: ='Ялта, Ленина, 18'!U18*График!AJ28/График!AJ31 -> 434608.7 | T18: =K57 -> 201362
K19: =IF(AND(I19<>"", I19<>0, J19<>""), J19/I19, "") | L19: =J19 -> 0 | M19: =IF(AND(I19<>"",I19<>0,L19<>"",L19<>0),L19/I19,"") | N19: =IF(AND(J19<>0,J19<>"",I19<>0,I19<>""),L19-I19,"") | O19: 0 | P19: =IF(AND(O19<>"", O19<>0, L19<>"", L19<>0), -O19+L19, "") | Q19: =IF(AND(P19<>"", P19<>0, O19<>0, O19<>""), P19/O19, "") | S19: =T18/S18 -> 0.46331793 | T19: =S19/J14*I14 -> 0.46331793
F20: Конверсия план/факт | I20: ='Ялта, Ленина, 18'!I20 -> 0.12 | J20: =N57 -> 0.12654321 | K20: =J20/I20 -> 1.0545267 | L20: =IF(AND(K8<>0,I14<>0,I57<>0),(I57*N57+(I57/K8-I57)*I20)/(I57/K8),0) -> 0.12365477 | M20: =IF(AND(I20<>"",I20<>0,L20<>"",L20<>0),L20/I20,"") -> 1.0304564 | N20: =IF(AND(J20<>0,J20<>"",I20<>0,I20<>""),L20-I20,"") -> 0.0036547669 | P20: =IF(AND(O20<>"", O20<>0, L20<>"", L20<>0), -O20+L20, "") | Q20: =IF(AND(P20<>"", P20<>0, O20<>0, O20<>""), P20/O20, "")
B22: Факт продаж за месяц | O22: % выполнения дневного плана | P22: Раcпределение плана по дням
B23: Дата | C23: День недели | D23: Выручка (руб) | E23: Кол-во единиц (шт.) | F23: Средняя стоимость изделия (руб.) | G23: Количество чеков (шт.) | H23: Средняя сумма чека (руб.) | I23: Трафик | J23: Длина чека (шт.) | K23: UNOde50 | L23: IS | M23: Agafi | N23: Конверсия (%) | P23: выручка, план | Q23: кол-во ед, план | R23: Кол-во чеков, план | S23: выручка, скорректир.план | T23: кол-во ед, скорр. план | U23: кол-во чеков, скорр. план | V23: Коэфф. Дня Недели | W23: Специфика месяца
B24: 1 | C24: 2 | D24: 3 | E24: в | F24: 5 | G24: 6 | H24: 7 | I24: 8 | J24: 9 | K24: 10 | L24: 11 | M24: 12 | N24: 13 | P24: 1 | Q24: 2 | R24: 3 | S24: 4 | T24: 5 | U24: 6 | V24: 10 | W24: 11
A25: 1 | B25: 45992 | C25: пн | D25: 3293 | E25: 1 | F25: 3293 | G25: 1 | H25: =IF(AND(G25<>"",G25<>0),D25/G25,"") -> 3293 | I25: 25 | J25: =IF(AND(G25<>"",G25<>0),E25/G25,"") -> 1 | N25: =IF(AND(I25<>"",I25<>0),G25/I25,"") -> 0.04 | O25: =D25/P25 -> 0.077141622 | P25: =$I$8*V25*W25/SUMPRODUCT($W$25:$W$56,$V$25:$V$56) -> 42687.721 | Q25: =$I$9*V25*W25/SUMPRODUCT($W$25:$W$56,$V$25:$V$56) -> 5.4727847 | R25: =IF($I$12="","",Q25/$I$12) -> 3.1452786 | S25: =IF(D25<>"",D25,P25) -> 3293 | T25: =IF(E25<>"",E25,Q25) -> 1 | U25: =IF(G25<>"",G25,R25) -> 1 | V25: 1 | W25: 1
A26: 2 | B26: 45993 | C26: вт | D26: 3555 | E26: 1 | F26: =IF(AND(E26<>"",E26<>0),D26/E26,"") -> 3555 | G26: 1 | H26: =IF(AND(G26<>"",G26<>0),D26/G26,"") -> 3555 | I26: 10 | J26: =IF(AND(G26<>"",G26<>0),E26/G26,"") -> 1 | N26: =IF(AND(I26<>"",I26<>0),G26/I26,"") -> 0.1 | O26: =D26/P26 -> 0.083279218 | P26: =$I$8*V26*W26/SUMPRODUCT($W$25:$W$56,$V$25:$V$56) -> 42687.721 | Q26: =$I$9*V26*W26/SUMPRODUCT($W$25:$W$58,$V$25:$V$58) -> 5.4727847 | R26: =IF($I$12="","",Q26/$I$12) -> 3.1452786 | S26: =IF(W26<>"",IF(D26<>"",D26,($I$8-SUM($S$25:S25))*V26*W26/SUMPRODUCT($W26:$W$56,$V26:$V$56)),"") -> 3555 | T26: =IF(W26<>"",IF(E26<>"",E26,($I$9-SUM($T$25:T25))*V26*W26/SUMPRODUCT($W26:$W$55,$V26:$V$55)),"") -> 1 | U26: =IF(W26<>"",IF($I$12<>"",IF(G26<>"",G26,($I$9/$I$12-SUM($U$25:U25))*V26*W26/SUMPRODUCT($W26:$W$55,$V26:$V$55)),""),"") -> 1 | V26: 1 | W26: 1
A27: 3 | B27: 45994 | C27: ср | D27: 47669 | E27: 3 | F27: =IF(AND(E27<>"",E27<>0),D27/E27,"") -> 15889.667 | G27: 2 | H27: =IF(AND(G27<>"",G27<>0),D27/G27,"") -> 23834.5 | I27: 28 | J27: =IF(AND(G27<>"",G27<>0),E27/G27,"") -> 1.5 | K27: 42669 | N27: =IF(AND(I27<>"",I27<>0),G27/I27,"") -> 0.071428571 | O27: =D27/P27 -> 1.1166911 | P27: =$I$8*V27*W27/SUMPRODUCT($W$25:$W$56,$V$25:$V$56) -> 42687.721 | Q27: =$I$9*V27*W27/SUMPRODUCT($W$25:$W$58,$V$25:$V$58) -> 5.4727847 | R27: =IF($I$12="","",Q27/$I$12) -> 3.1452786 | S27: =IF(W27<>"",IF(D27<>"",D27,($I$8-SUM($S$25:S26))*V27*W27/SUMPRODUCT($W27:$W$58,$V27:$V$58)),"") -> 47669 | T27: =IF(W27<>"",IF(E27<>"",E27,($I$9-SUM($T$25:T26))*V27*W27/SUMPRODUCT($W27:$W$55,$V27:$V$55)),"") -> 3 | U27: =IF(W27<>"",IF($I$12<>"",IF(G27<>"",G27,($I$9/$I$12-SUM($U$25:U26))*V27*W27/SUMPRODUCT($W27:$W$55,$V27:$V$55)),""),"") -> 2 | V27: 1 | W27: 1
A28: 4 | B28: 45995 | C28: чт | D28: 49966 | E28: 6 | F28: =IF(AND(E28<>"",E28<>0),D28/E28,"") -> 8327.6667 | G28: 3 | H28: =IF(AND(G28<>"",G28<>0),D28/G28,"") -> 16655.333 | I28: 20 | J28: =IF(AND(G28<>"",G28<>0),E28/G28,"") -> 2 | N28: =IF(AND(I28<>"",I28<>0),G28/I28,"") -> 0.15 | O28: =D28/P28 -> 1.1705005 | P28: =$I$8*V28*W28/SUMPRODUCT($W$25:$W$56,$V$25:$V$56) -> 42687.721 | Q28: =$I$9*V28*W28/SUMPRODUCT($W$25:$W$58,$V$25:$V$58) -> 5.4727847 | R28: =IF($I$12="","",Q28/$I$12) -> 3.1452786 | S28: =IF(W28<>"",IF(D28<>"",D28,($I$8-SUM($S$25:S27))*V28*W28/SUMPRODUCT($W28:$W$58,$V28:$V$58)),"") -> 49966 | T28: =IF(W28<>"",IF(E28<>"",E28,($I$9-SUM($T$25:T27))*V28*W28/SUMPRODUCT($W28:$W$58,$V28:$V$58)),"") -> 6 | U28: =IF(W28<>"",IF($I$12<>"",IF(G28<>"",G28,($I$9/$I$12-SUM($U$25:U27))*V28*W28/SUMPRODUCT($W28:$W$58,$V28:$V$58)),""),"") -> 3 | V28: 1 | W28: 1
A29: 5 | B29: 45996 | C29: пт | D29: =28984+220 -> 29204 | E29: 2 | F29: =IF(AND(E29<>"",E29<>0),D29/E29,"") -> 14602 | G29: 2 | H29: =IF(AND(G29<>"",G29<>0),D29/G29,"") -> 14602 | I29: 13 | J29: =IF(AND(G29<>"",G29<>0),E29/G29,"") -> 1 | K29: 28984 | L29: 220 | N29: =IF(AND(I29<>"",I29<>0),G29/I29,"") -> 0.15384615 | O29: =D29/P29 -> 0.68413116 | P29: =$I$8*V29*W29/SUMPRODUCT($W$25:$W$56,$V$25:$V$56) -> 42687.721 | Q29: =$I$9*V29*W29/SUMPRODUCT($W$25:$W$58,$V$25:$V$58) -> 5.4727847 | R29: =IF($I$12="","",Q29/$I$12) -> 3.1452786 | S29: =IF(W29<>"",IF(D29<>"",D29,($I$8-SUM($S$25:S28))*V29*W29/SUMPRODUCT($W29:$W$58,$V29:$V$58)),"") -> 29204 | T29: =IF(W29<>"",IF(E29<>"",E29,($I$9-SUM($T$25:T28))*V29*W29/SUMPRODUCT($W29:$W$58,$V29:$V$58)),"") -> 2 | U29: =IF(W29<>"",IF($I$12<>"",IF(G29<>"",G29,($I$9/$I$12-SUM($U$25:U28))*V29*W29/SUMPRODUCT($W29:$W$58,$V29:$V$58)),""),"") -> 2 | V29: 1 | W29: 1
A30: 6 | B30: 45997 | C30: сб | D30: 0 | E30: 0 | F30: =IF(AND(E30<>"",E30<>0),D30/E30,"") | G30: 0 | H30: =IF(AND(G30<>"",G30<>0),D30/G30,"") | I30: 10 | J30: =IF(AND(G30<>"",G30<>0),E30/G30,"") | N30: =IF(AND(I30<>"",I30<>0),G30/I30,"") -> 0 | O30: =D30/P30 -> 0 | P30: =$I$8*V30*W30/SUMPRODUCT($W$25:$W$56,$V$25:$V$56) -> 42687.721 | Q30: =$I$9*V30*W30/SUMPRODUCT($W$25:$W$58,$V$25:$V$58) -> 5.4727847 | R30: =IF($I$12="","",Q30/$I$12) -> 3.1452786 | S30: =IF(W30<>"",IF(D30<>"",D30,($I$8-SUM($S$25:S29))*V30*W30/SUMPRODUCT($W30:$W$58,$V30:$V$58)),"") -> 0 | T30: =IF(W30<>"",IF(E30<>"",E30,($I$9-SUM($T$25:T29))*V30*W30/SUMPRODUCT($W30:$W$58,$V30:$V$58)),"") -> 0 | U30: =IF(W30<>"",IF($I$12<>"",IF(G30<>"",G30,($I$9/$I$12-SUM($U$25:U29))*V30*W30/SUMPRODUCT($W30:$W$58,$V30:$V$58)),""),"") -> 0 | V30: 1 | W30: 1
A31: 7 | B31: 45998 | C31: вс | D31: 18884 | E31: 2 | F31: =IF(AND(E31<>"",E31<>0),D31/E31,"") -> 9442 | G31: 1 | H31: =IF(AND(G31<>"",G31<>0),D31/G31,"") -> 18884 | I31: 12 | J31: =IF(AND(G31<>"",G31<>0),E31/G31,"") -> 2 | N31: =IF(AND(I31<>"",I31<>0),G31/I31,"") -> 0.083333333 | O31: =D31/P31 -> 0.44237546 | P31: =$I$8*V31*W31/SUMPRODUCT($W$25:$W$56,$V$25:$V$56) -> 42687.721 | Q31: =$I$9*V31*W31/SUMPRODUCT($W$25:$W$58,$V$25:$V$58) -> 5.4727847 | R31: =IF($I$12="","",Q31/$I$12) -> 3.1452786 | S31: =IF(W31<>"",IF(D31<>"",D31,($I$8-SUM($S$25:S30))*V31*W31/SUMPRODUCT($W31:$W$58,$V31:$V$58)),"") -> 18884 | T31: =IF(W31<>"",IF(E31<>"",E31,($I$9-SUM($T$25:T30))*V31*W31/SUMPRODUCT($W31:$W$58,$V31:$V$58)),"") -> 2 | U31: =IF(W31<>"",IF($I$12<>"",IF(G31<>"",G31,($I$9/$I$12-SUM($U$25:U30))*V31*W31/SUMPRODUCT($W31:$W$58,$V31:$V$58)),""),"") -> 1 | V31: 1 | W31: 1
A32: 8 | B32: 45999 | C32: пн | D32: 12484 | E32: 2 | F32: =IF(AND(E32<>"",E32<>0),D32/E32,"") -> 6242 | G32: 1 | H32: =IF(AND(G32<>"",G32<>0),D32/G32,"") -> 12484 | I32: 20 | J32: =IF(AND(G32<>"",G32<>0),E32/G32,"") -> 2 | K32: 8490 | N32: =IF(AND(I32<>"",I32<>0),G32/I32,"") -> 0.05 | O32: =D32/P32 -> 0.29244944 | P32: =$I$8*V32*W32/SUMPRODUCT($W$25:$W$56,$V$25:$V$56) -> 42687.721 | Q32: =$I$9*V32*W32/SUMPRODUCT($W$25:$W$58,$V$25:$V$58) -> 5.4727847 | R32: =IF($I$12="","",Q32/$I$12) -> 3.1452786 | S32: =IF(W32<>"",IF(D32<>"",D32,($I$8-SUM($S$25:S31))*V32*W32/SUMPRODUCT($W32:$W$58,$V32:$V$58)),"") -> 12484 | T32: =IF(W32<>"",IF(E32<>"",E32,($I$9-SUM($T$25:T31))*V32*W32/SUMPRODUCT($W32:$W$58,$V32:$V$58)),"") -> 2 | U32: =IF(W32<>"",IF($I$12<>"",IF(G32<>"",G32,($I$9/$I$12-SUM($U$25:U31))*V32*W32/SUMPRODUCT($W32:$W$58,$V32:$V$58)),""),"") -> 1 | V32: 1 | W32: 1
A33: 9 | B33: 46002 | C33: чт | D33: 0 | E33: 0 | F33: =IF(AND(E33<>"",E33<>0),D33/E33,"") | G33: 0 | H33: =IF(AND(G33<>"",G33<>0),D33/G33,"") | I33: 6 | J33: =IF(AND(G33<>"",G33<>0),E33/G33,"") | N33: =IF(AND(I33<>"",I33<>0),G33/I33,"") -> 0 | O33: =D33/P33 -> 0 | P33: =$I$8*V33*W33/SUMPRODUCT($W$25:$W$56,$V$25:$V$56) -> 42687.721 | Q33: =$I$9*V33*W33/SUMPRODUCT($W$25:$W$58,$V$25:$V$58) -> 5.4727847 | R33: =IF($I$12="","",Q33/$I$12) -> 3.1452786 | S33: =IF(W33<>"",IF(D33<>"",D33,($I$8-SUM($S$25:S32))*V33*W33/SUMPRODUCT($W33:$W$58,$V33:$V$58)),"") -> 0 | T33: =IF(W33<>"",IF(E33<>"",E33,($I$9-SUM($T$25:T32))*V33*W33/SUMPRODUCT($W33:$W$58,$V33:$V$58)),"") -> 0 | U33: =IF(W33<>"",IF($I$12<>"",IF(G33<>"",G33,($I$9/$I$12-SUM($U$25:U32))*V33*W33/SUMPRODUCT($W33:$W$58,$V33:$V$58)),""),"") -> 0 | V33: 1 | W33: 1
A34: 10 | B34: 46003 | C34: пт | D34: 54380 | E34: 6 | F34: =IF(AND(E34<>"",E34<>0),D34/E34,"") -> 9063.3333 | G34: 4 | H34: =IF(AND(G34<>"",G34<>0),D34/G34,"") -> 13595 | I34: 13 | J34: =IF(AND(G34<>"",G34<>0),E34/G34,"") -> 1.5 | N34: =IF(AND(I34<>"",I34<>0),G34/I34,"") -> 0.30769231 | O34: =D34/P34 -> 1.2739026 | P34: =$I$8*V34*W34/SUMPRODUCT($W$25:$W$56,$V$25:$V$56) -> 42687.721 | Q34: =$I$9*V34*W34/SUMPRODUCT($W$25:$W$58,$V$25:$V$58) -> 5.4727847 | R34: =IF($I$12="","",Q34/$I$12) -> 3.1452786 | S34: =IF(W34<>"",IF(D34<>"",D34,($I$8-SUM($S$25:S33))*V34*W34/SUMPRODUCT($W34:$W$58,$V34:$V$58)),"") -> 54380 | T34: =IF(W34<>"",IF(E34<>"",E34,($I$9-SUM($T$25:T33))*V34*W34/SUMPRODUCT($W34:$W$58,$V34:$V$58)),"") -> 6 | U34: =IF(W34<>"",IF($I$12<>"",IF(G34<>"",G34,($I$9/$I$12-SUM($U$25:U33))*V34*W34/SUMPRODUCT($W34:$W$58,$V34:$V$58)),""),"") -> 4 | V34: 1 | W34: 1
A35: 11 | B35: 46006 | C35: пн | D35: 16868 | E35: 3 | F35: =IF(AND(E35<>"",E35<>0),D35/E35,"") -> 5622.6667 | G35: 3 | H35: =IF(AND(G35<>"",G35<>0),D35/G35,"") -> 5622.6667 | I35: 5 | J35: =IF(AND(G35<>"",G35<>0),E35/G35,"") -> 1 | N35: =IF(AND(I35<>"",I35<>0),G35/I35,"") -> 0.6 | O35: =D35/P35 -> 0.39514876 | P35: =$I$8*V35*W35/SUMPRODUCT($W$25:$W$56,$V$25:$V$56) -> 42687.721 | Q35: =$I$9*V35*W35/SUMPRODUCT($W$25:$W$58,$V$25:$V$58) -> 5.4727847 | R35: =IF($I$12="","",Q35/$I$12) -> 3.1452786 | S35: =IF(W35<>"",IF(D35<>"",D35,($I$8-SUM($S$25:S34))*V35*W35/SUMPRODUCT($W35:$W$58,$V35:$V$58)),"") -> 16868 | T35: =IF(W35<>"",IF(E34<>"",E34,($I$9-SUM($T$25:T34))*V35*W35/SUMPRODUCT($W35:$W$58,$V35:$V$58)),"") -> 6 | U35: =IF(W35<>"",IF($I$12<>"",IF(G35<>"",G35,($I$9/$I$12-SUM($U$25:U34))*V35*W35/SUMPRODUCT($W35:$W$58,$V35:$V$58)),""),"") -> 3 | V35: 1 | W35: 1
A36: 11 | B36: 46007 | C36: вт | D36: 0 | E36: 0 | F36: =IF(AND(E36<>"",E36<>0),D36/E36,"") | G36: 0 | H36: =IF(AND(G36<>"",G36<>0),D36/G36,"") | I36: 6 | J36: =IF(AND(G36<>"",G36<>0),E36/G36,"") | N36: =IF(AND(I36<>"",I36<>0),G36/I36,"") -> 0 | O36: =D36/P36 -> 0 | P36: =$I$8*V36*W36/SUMPRODUCT($W$25:$W$56,$V$25:$V$56) -> 42687.721 | Q36: =$I$9*V36*W36/SUMPRODUCT($W$25:$W$58,$V$25:$V$58) -> 5.4727847 | R36: =IF($I$12="","",Q36/$I$12) -> 3.1452786 | S36: =IF(W36<>"",IF(D36<>"",D36,($I$8-SUM($S$25:S35))*V36*W36/SUMPRODUCT($W36:$W$58,$V36:$V$58)),"") -> 0 | T36: =IF(W36<>"",IF(E35<>"",E35,($I$9-SUM($T$25:T35))*V36*W36/SUMPRODUCT($W36:$W$58,$V36:$V$58)),"") -> 3 | U36: =IF(W36<>"",IF($I$12<>"",IF(G36<>"",G36,($I$9/$I$12-SUM($U$25:U35))*V36*W36/SUMPRODUCT($W36:$W$58,$V36:$V$58)),""),"") -> 0 | V36: 1 | W36: 1
A37: 13 | B37: 46010 | C37: пт | D37: 35548 | E37: 5 | F37: =IF(AND(E37<>"",E37<>0),D37/E37,"") -> 7109.6 | G37: 1 | H37: =IF(AND(G37<>"",G37<>0),D37/G37,"") -> 35548 | I37: 13 | J37: =IF(AND(G37<>"",G37<>0),E37/G37,"") -> 5 | K37: 9390 | N37: =IF(AND(I37<>"",I37<>0),G37/I37,"") -> 0.076923077 | O37: =D37/P37 -> 1.0280807 | P37: =$I$8*V37*W37/SUMPRODUCT($W$25:$W$56,$V$25:$V$56) -> 34577.054 | Q37: =$I$9*V37*W37/SUMPRODUCT($W$25:$W$58,$V$25:$V$58) -> 4.4329556 | R37: =IF($I$12="","",Q37/$I$12) -> 2.5476756 | S37: =IF(W37<>"",IF(D37<>"",D37,($I$8-SUM($S$25:S36))*V37*W37/SUMPRODUCT($W37:$W$58,$V37:$V$58)),"") -> 35548 | T37: =IF(W37<>"",IF(E37<>"",E37,($I$9-SUM($T$25:T36))*V37*W37/SUMPRODUCT($W37:$W$58,$V37:$V$58)),"") -> 5 | U37: =IF(W37<>"",IF($I$12<>"",IF(G37<>"",G37,($I$9/$I$12-SUM($U$25:U36))*V37*W37/SUMPRODUCT($W37:$W$58,$V37:$V$58)),""),"") -> 1 | V37: 0.9 | W37: 0.9
A38: 14 | B38: 46011 | C38: сб | D38: 21777 | E38: 3 | F38: =IF(AND(E38<>"",E38<>0),D38/E38,"") -> 7259 | G38: 2 | H38: =IF(AND(G38<>"",G38<>0),D38/G38,"") -> 10888.5 | I38: 18 | J38: =IF(AND(G38<>"",G38<>0),E38/G38,"") -> 1.5 | K38: 14484 | N38: =IF(AND(I38<>"",I38<>0),G38/I38,"") -> 0.11111111 | O38: =D38/P38 -> 0.5101467 | P38: =$I$8*V38*W38/SUMPRODUCT($W$25:$W$56,$V$25:$V$56) -> 42687.721 | Q38: =$I$9*V38*W38/SUMPRODUCT($W$25:$W$58,$V$25:$V$58) -> 5.4727847 | R38: =IF($I$12="","",Q38/$I$12) -> 3.1452786 | S38: =IF(W38<>"",IF(D38<>"",D38,($I$8-SUM($S$25:S37))*V38*W38/SUMPRODUCT($W38:$W$58,$V38:$V$58)),"") -> 21777 | T38: =IF(W38<>"",IF(E38<>"",E38,($I$9-SUM($T$25:T37))*V38*W38/SUMPRODUCT($W38:$W$58,$V38:$V$58)),"") -> 3 | U38: =IF(W38<>"",IF($I$12<>"",IF(G38<>"",G38,($I$9/$I$12-SUM($U$25:U37))*V38*W38/SUMPRODUCT($W38:$W$58,$V38:$V$58)),""),"") -> 2 | V38: 1 | W38: 1
A39: 15 | B39: 46012 | C39: вс | D39: 28148 | E39: 3 | F39: =IF(AND(E39<>"",E39<>0),D39/E39,"") -> 9382.6667 | G39: 2 | H39: =IF(AND(G39<>"",G39<>0),D39/G39,"") -> 14074 | I39: 15 | J39: =IF(AND(G39<>"",G39<>0),E39/G39,"") -> 1.5 | N39: =IF(AND(I39<>"",I39<>0),G39/I39,"") -> 0.13333333 | O39: =D39/P39 -> 0.65939337 | P39: =$I$8*V39*W39/SUMPRODUCT($W$25:$W$56,$V$25:$V$56) -> 42687.721 | Q39: =$I$9*V39*W39/SUMPRODUCT($W$25:$W$58,$V$25:$V$58) -> 5.4727847 | R39: =IF($I$12="","",Q39/$I$12) -> 3.1452786 | S39: =IF(W39<>"",IF(D39<>"",D39,($I$8-SUM($S$25:S38))*V39*W39/SUMPRODUCT($W39:$W$58,$V39:$V$58)),"") -> 28148 | T39: =IF(W39<>"",IF(E39<>"",E39,($I$9-SUM($T$25:T38))*V39*W39/SUMPRODUCT($W39:$W$58,$V39:$V$58)),"") -> 3 | U39: =IF(W39<>"",IF($I$12<>"",IF(G39<>"",G39,($I$9/$I$12-SUM($U$25:U38))*V39*W39/SUMPRODUCT($W39:$W$58,$V39:$V$58)),""),"") -> 2 | V39: 1 | W39: 1
A40: 16 | B40: 46013 | C40: пн | D40: 16375 | E40: 3 | F40: =IF(AND(E40<>"",E40<>0),D40/E40,"") -> 5458.3333 | G40: 1 | H40: =IF(AND(G40<>"",G40<>0),D40/G40,"") -> 16375 | I40: 20 | J40: =IF(AND(G40<>"",G40<>0),E40/G40,"") -> 3 | N40: =IF(AND(I40<>"",I40<>0),G40/I40,"") -> 0.05 | O40: =D40/P40 -> 0.38359977 | P40: =$I$8*V40*W40/SUMPRODUCT($W$25:$W$56,$V$25:$V$56) -> 42687.721 | Q40: =$I$9*V40*W40/SUMPRODUCT($W$25:$W$58,$V$25:$V$58) -> 5.4727847 | R40: =IF($I$12="","",Q40/$I$12) -> 3.1452786 | S40: =IF(W40<>"",IF(D40<>"",D40,($I$8-SUM($S$25:S39))*V40*W40/SUMPRODUCT($W40:$W$58,$V40:$V$58)),"") -> 16375 | T40: =IF(W40<>"",IF(E40<>"",E40,($I$9-SUM($T$25:T39))*V40*W40/SUMPRODUCT($W40:$W$58,$V40:$V$58)),"") -> 3 | U40: =IF(W40<>"",IF($I$12<>"",IF(G40<>"",G40,($I$9/$I$12-SUM($U$25:U39))*V40*W40/SUMPRODUCT($W40:$W$58,$V40:$V$58)),""),"") -> 1 | V40: 1 | W40: 1
A41: 17 | B41: 46014 | C41: вт | F41: =IF(AND(E41<>"",E41<>0),D41/E41,"") | H41: =IF(AND(G41<>"",G41<>0),D41/G41,"") | I41: 10 | J41: =IF(AND(G41<>"",G41<>0),E41/G41,"") | N41: =IF(AND(I41<>"",I41<>0),G41/I41,"") -> 0 | O41: =D41/P41 -> 0 | P41: =$I$8*V41*W41/SUMPRODUCT($W$25:$W$56,$V$25:$V$56) -> 42687.721 | Q41: =$I$9*V41*W41/SUMPRODUCT($W$25:$W$58,$V$25:$V$58) -> 5.4727847 | R41: =IF($I$12="","",Q41/$I$12) -> 3.1452786 | S41: =IF(W41<>"",IF(D41<>"",D41,($I$8-SUM($S$25:S40))*V41*W41/SUMPRODUCT($W41:$W$58,$V41:$V$58)),"") -> 75701.629 | T41: =IF(W41<>"",IF(E41<>"",E41,($I$9-SUM($T$25:T40))*V41*W41/SUMPRODUCT($W41:$W$58,$V41:$V$58)),"") -> 9.4457971 | U41: =IF(W41<>"",IF($I$12<>"",IF(G41<>"",G41,($I$9/$I$12-SUM($U$25:U40))*V41*W41/SUMPRODUCT($W41:$W$58,$V41:$V$58)),""),"") -> 5.6675192 | V41: 1 | W41: 1
A42: 18 | B42: 46015 | C42: ср | F42: =IF(AND(E42<>"",E42<>0),D42/E42,"") | H42: =IF(AND(G42<>"",G42<>0),D42/G42,"") | J42: =IF(AND(G42<>"",G42<>0),E42/G42,"") | N42: =IF(AND(I42<>"",I42<>0),G42/I42,"") | O42: =D42/P42 -> #DIV/0! | P42: =$I$8*V42*W42/SUMPRODUCT($W$25:$W$56,$V$25:$V$56) -> 0 | Q42: =$I$9*V42*W42/SUMPRODUCT($W$25:$W$58,$V$25:$V$58) -> 0 | R42: =IF($I$12="","",Q42/$I$12) -> 0 | S42: =IF(W42<>"",IF(D42<>"",D42,($I$8-SUM($S$25:S41))*V42*W42/SUMPRODUCT($W42:$W$58,$V42:$V$58)),"") | T42: =IF(W42<>"",IF(E42<>"",E42,($I$9-SUM($T$25:T41))*V42*W42/SUMPRODUCT($W42:$W$58,$V42:$V$58)),"") | U42: =IF(W42<>"",IF($I$12<>"",IF(G42<>"",G42,($I$9/$I$12-SUM($U$25:U41))*V42*W42/SUMPRODUCT($W42:$W$58,$V42:$V$58)),""),"")
A43: 18 | B43: 46016 | C43: чт | F43: =IF(AND(E43<>"",E43<>0),D43/E43,"") | H43: =IF(AND(G43<>"",G43<>0),D43/G43,"") | I43: 4 | J43: =IF(AND(G43<>"",G43<>0),E43/G43,"") | N43: =IF(AND(I43<>"",I43<>0),G43/I43,"") -> 0 | O43: =D43/P43 -> 0 | P43: =$I$8*V43*W43/SUMPRODUCT($W$25:$W$56,$V$25:$V$56) -> 42687.721 | Q43: =$I$9*V43*W43/SUMPRODUCT($W$25:$W$58,$V$25:$V$58) -> 5.4727847 | R43: =IF($I$12="","",Q43/$I$12) -> 3.1452786 | S43: =IF(W43<>"",IF(D43<>"",D43,($I$8-SUM($S$25:S42))*V43*W43/SUMPRODUCT($W43:$W$58,$V43:$V$58)),"") -> 75701.629 | T43: =IF(W43<>"",IF(E43<>"",E43,($I$9-SUM($T$25:T42))*V43*W43/SUMPRODUCT($W43:$W$58,$V43:$V$58)),"") -> 9.4457971 | U43: =IF(W43<>"",IF($I$12<>"",IF(G43<>"",G43,($I$9/$I$12-SUM($U$25:U42))*V43*W43/SUMPRODUCT($W43:$W$58,$V43:$V$58)),""),"") -> 5.6675192 | V43: 1 | W43: 1
A44: 19 | B44: 46017 | C44: пт | D44: 30584 | E44: 3 | F44: =IF(AND(E44<>"",E44<>0),D44/E44,"") -> 10194.667 | G44: 2 | H44: =IF(AND(G44<>"",G44<>0),D44/G44,"") -> 15292 | I44: 5 | J44: =IF(AND(G44<>"",G44<>0),E44/G44,"") -> 1.5 | M44: 15100 | N44: =IF(AND(I44<>"",I44<>0),G44/I44,"") -> 0.4 | O44: =D44/P44 -> 0.49754094 | P44: =$I$8*V44*W44/SUMPRODUCT($W$25:$W$56,$V$25:$V$56) -> 61470.318 | Q44: =$I$9*V44*W44/SUMPRODUCT($W$25:$W$58,$V$25:$V$58) -> 7.88081 | R44: =IF($I$12="","",Q44/$I$12) -> 4.5292011 | S44: =IF(W44<>"",IF(D44<>"",D44,($I$8-SUM($S$25:S43))*V44*W44/SUMPRODUCT($W44:$W$58,$V44:$V$58)),"") -> 30584 | T44: =IF(W44<>"",IF(E44<>"",E44,($I$9-SUM($T$25:T43))*V44*W44/SUMPRODUCT($W44:$W$58,$V44:$V$58)),"") -> 3 | U44: =IF(W44<>"",IF($I$12<>"",IF(G44<>"",G44,($I$9/$I$12-SUM($U$25:U43))*V44*W44/SUMPRODUCT($W44:$W$58,$V44:$V$58)),""),"") -> 2 | V44: 1.2 | W44: 1.2
A45: 20 | B45: 46018 | C45: сб | D45: =18990+8390+46546 -> 73926 | E45: 9 | F45: =IF(AND(E45<>"",E45<>0),D45/E45,"") -> 8214 | G45: 4 | H45: =IF(AND(G45<>"",G45<>0),D45/G45,"") -> 18481.5 | I45: 12 | J45: =IF(AND(G45<>"",G45<>0),E45/G45,"") -> 2.25 | K45: 18990 | M45: 8390 | N45: =IF(AND(I45<>"",I45<>0),G45/I45,"") -> 0.33333333 | O45: =D45/P45 -> 1.2026292 | P45: =$I$8*V45*W45/SUMPRODUCT($W$25:$W$56,$V$25:$V$56) -> 61470.318 | Q45: =$I$9*V45*W45/SUMPRODUCT($W$25:$W$58,$V$25:$V$58) -> 7.88081 | R45: =IF($I$12="","",Q45/$I$12) -> 4.5292011 | S45: =IF(W45<>"",IF(D45<>"",D45,($I$8-SUM($S$25:S44))*V45*W45/SUMPRODUCT($W45:$W$58,$V45:$V$58)),"") -> 73926 | T45: =IF(W45<>"",IF(E45<>"",E45,($I$9-SUM($T$25:T44))*V45*W45/SUMPRODUCT($W45:$W$58,$V45:$V$58)),"") -> 9 | U45: =IF(W45<>"",IF($I$12<>"",IF(G45<>"",G45,($I$9/$I$12-SUM($U$25:U44))*V45*W45/SUMPRODUCT($W45:$W$58,$V45:$V$58)),""),"") -> 4 | V45: 1.2 | W45: 1.2
A46: 21 | B46: 46019 | C46: вс | D46: 43254 | E46: 3 | F46: =IF(AND(E46<>"",E46<>0),D46/E46,"") -> 14418 | G46: 2 | H46: =IF(AND(G46<>"",G46<>0),D46/G46,"") -> 21627 | I46: 11 | J46: =IF(AND(G46<>"",G46<>0),E46/G46,"") -> 1.5 | K46: 28272 | M46: 13690 | N46: =IF(AND(I46<>"",I46<>0),G46/I46,"") -> 0.18181818 | O46: =D46/P46 -> 0.70365668 | P46: =$I$8*V46*W46/SUMPRODUCT($W$25:$W$56,$V$25:$V$56) -> 61470.318 | Q46: =$I$9*V46*W46/SUMPRODUCT($W$25:$W$58,$V$25:$V$58) -> 7.88081 | R46: =IF($I$12="","",Q46/$I$12) -> 4.5292011 | S46: =IF(W46<>"",IF(D46<>"",D46,($I$8-SUM($S$25:S45))*V46*W46/SUMPRODUCT($W46:$W$58,$V46:$V$58)),"") -> 43254 | T46: =IF(W46<>"",IF(E46<>"",E46,($I$9-SUM($T$25:T45))*V46*W46/SUMPRODUCT($W46:$W$58,$V46:$V$58)),"") -> 3 | U46: =IF(W46<>"",IF($I$12<>"",IF(G46<>"",G46,($I$9/$I$12-SUM($U$25:U45))*V46*W46/SUMPRODUCT($W46:$W$58,$V46:$V$58)),""),"") -> 2 | V46: 1.2 | W46: 1.2
A47: 22 | B47: 46020 | C47: пн | F47: =IF(AND(E47<>"",E47<>0),D47/E47,"") | H47: =IF(AND(G47<>"",G47<>0),D47/G47,"") | J47: =IF(AND(G47<>"",G47<>0),E47/G47,"") | N47: =IF(AND(I47<>"",I47<>0),G47/I47,"") | O47: =D47/P47 -> 0 | P47: =$I$8*V47*W47/SUMPRODUCT($W$25:$W$56,$V$25:$V$56) -> 61470.318 | Q47: =$I$9*V47*W47/SUMPRODUCT($W$25:$W$58,$V$25:$V$58) -> 7.88081 | R47: =IF($I$12="","",Q47/$I$12) -> 4.5292011 | S47: =IF(W47<>"",IF(D47<>"",D47,($I$8-SUM($S$25:S46))*V47*W47/SUMPRODUCT($W47:$W$58,$V47:$V$58)),"") -> 175542.44 | T47: =IF(W47<>"",IF(E47<>"",E47,($I$9-SUM($T$25:T46))*V47*W47/SUMPRODUCT($W47:$W$58,$V47:$V$58)),"") -> 23.179374 | U47: =IF(W47<>"",IF($I$12<>"",IF(G47<>"",G47,($I$9/$I$12-SUM($U$25:U46))*V47*W47/SUMPRODUCT($W47:$W$58,$V47:$V$58)),""),"") -> 14.278883 | V47: 1.2 | W47: 1.2
A48: 23 | B48: 46021 | C48: вт | D48: =49522+50083 -> 99605 | E48: 9 | F48: =IF(AND(E48<>"",E48<>0),D48/E48,"") -> 11067.222 | G48: 6 | H48: =IF(AND(G48<>"",G48<>0),D48/G48,"") -> 16600.833 | I48: 28 | J48: =IF(AND(G48<>"",G48<>0),E48/G48,"") -> 1.5 | K48: 50083 | N48: =IF(AND(I48<>"",I48<>0),G48/I48,"") -> 0.21428571 | O48: =D48/P48 -> 1.6203755 | P48: =$I$8*V48*W48/SUMPRODUCT($W$25:$W$56,$V$25:$V$56) -> 61470.318 | Q48: =$I$9*V48*W48/SUMPRODUCT($W$25:$W$58,$V$25:$V$58) -> 7.88081 | R48: =IF($I$12="","",Q48/$I$12) -> 4.5292011 | S48: =IF(W48<>"",IF(D48<>"",D48,($I$8-SUM($S$25:S47))*V48*W48/SUMPRODUCT($W48:$W$58,$V48:$V$58)),"") -> 99605 | T48: =IF(W48<>"",IF(E48<>"",E48,($I$9-SUM($T$25:T47))*V48*W48/SUMPRODUCT($W48:$W$58,$V48:$V$58)),"") -> 9 | U48: =IF(W48<>"",IF($I$12<>"",IF(G48<>"",G48,($I$9/$I$12-SUM($U$25:U47))*V48*W48/SUMPRODUCT($W48:$W$58,$V48:$V$58)),""),"") -> 6 | V48: 1.2 | W48: 1.2
A49: 24 | B49: 46022 | C49: ср | D49: 34652 | E49: 6 | F49: =IF(AND(E49<>"",E49<>0),D49/E49,"") -> 5775.3333 | G49: 3 | H49: =IF(AND(G49<>"",G49<>0),D49/G49,"") -> 11550.667 | I49: 20 | J49: =IF(AND(G49<>"",G49<>0),E49/G49,"") -> 2 | N49: =IF(AND(I49<>"",I49<>0),G49/I49,"") -> 0.15 | O49: =D49/P49 -> 0.81175568 | P49: =$I$8*V49*W49/SUMPRODUCT($W$25:$W$56,$V$25:$V$56) -> 42687.721 | Q49: =$I$9*V49*W49/SUMPRODUCT($W$25:$W$58,$V$25:$V$58) -> 5.4727847 | R49: =IF($I$12="","",Q49/$I$12) -> 3.1452786 | S49: =IF(W49<>"",IF(D49<>"",D49,($I$8-SUM($S$25:S48))*V49*W49/SUMPRODUCT($W49:$W$58,$V49:$V$58)),"") -> 34652 | T49: =IF(W49<>"",IF(E49<>"",E49,($I$9-SUM($T$25:T48))*V49*W49/SUMPRODUCT($W49:$W$58,$V49:$V$58)),"") -> 6 | U49: =IF(W49<>"",IF($I$12<>"",IF(G49<>"",G49,($I$9/$I$12-SUM($U$25:U48))*V49*W49/SUMPRODUCT($W49:$W$58,$V49:$V$58)),""),"") -> 3 | V49: 1 | W49: 1
F50: =IF(AND(E50<>"",E50<>0),D50/E50,"") | H50: =IF(AND(G50<>"",G50<>0),D50/G50,"") | J50: =IF(AND(G50<>"",G50<>0),E50/G50,"") | N50: =IF(AND(I50<>"",I50<>0),G50/I50,"") | O50: =D50/P50 -> #DIV/0! | P50: =$I$8*V50*W50/SUMPRODUCT($W$25:$W$56,$V$25:$V$56) -> 0 | Q50: =$I$9*V50*W50/SUMPRODUCT($W$25:$W$58,$V$25:$V$58) -> 0 | R50: =IF($I$12="","",Q50/$I$12) -> 0 | S50: =IF(W50<>"",IF(D50<>"",D50,($I$8-SUM($S$25:S49))*V50*W50/SUMPRODUCT($W50:$W$58,$V50:$V$58)),"") | T50: =IF(W50<>"",IF(E50<>"",E50,($I$9-SUM($T$25:T49))*V50*W50/SUMPRODUCT($W50:$W$58,$V50:$V$58)),"") | U50: =IF(W50<>"",IF($I$12<>"",IF(G50<>"",G50,($I$9/$I$12-SUM($U$25:U49))*V50*W50/SUMPRODUCT($W50:$W$58,$V50:$V$58)),""),"")
F51: =IF(AND(E51<>"",E51<>0),D51/E51,"") | H51: =IF(AND(G51<>"",G51<>0),D51/G51,"") | J51: =IF(AND(G51<>"",G51<>0),E51/G51,"") | N51: =IF(AND(I51<>"",I51<>0),G51/I51,"") | O51: =D51/P51 -> #DIV/0! | P51: =$I$8*V51*W51/SUMPRODUCT($W$25:$W$56,$V$25:$V$56) -> 0 | Q51: =$I$9*V51*W51/SUMPRODUCT($W$25:$W$58,$V$25:$V$58) -> 0 | R51: =IF($I$12="","",Q51/$I$12) -> 0 | S51: =IF(W51<>"",IF(D51<>"",D51,($I$8-SUM($S$25:S50))*V51*W51/SUMPRODUCT($W51:$W$58,$V51:$V$58)),"") | T51: =IF(W51<>"",IF(E51<>"",E51,($I$9-SUM($T$25:T50))*V51*W51/SUMPRODUCT($W51:$W$58,$V51:$V$58)),"") | U51: =IF(W51<>"",IF($I$12<>"",IF(G51<>"",G51,($I$9/$I$12-SUM($U$25:U50))*V51*W51/SUMPRODUCT($W51:$W$58,$V51:$V$58)),""),"")
F52: =IF(AND(E52<>"",E52<>0),D52/E52,"") | H52: =IF(AND(G52<>"",G52<>0),D52/G52,"") | J52: =IF(AND(G52<>"",G52<>0),E52/G52,"") | N52: =IF(AND(I52<>"",I52<>0),G52/I52,"") | O52: =D52/P52 -> #DIV/0! | P52: =$I$8*V52*W52/SUMPRODUCT($W$25:$W$56,$V$25:$V$56) -> 0 | Q52: =$I$9*V52*W52/SUMPRODUCT($W$25:$W$58,$V$25:$V$58) -> 0 | R52: =IF($I$12="","",Q52/$I$12) -> 0 | S52: =IF(W52<>"",IF(D52<>"",D52,($I$8-SUM($S$25:S51))*V52*W52/SUMPRODUCT($W52:$W$58,$V52:$V$58)),"") | T52: =IF(W52<>"",IF(E52<>"",E52,($I$9-SUM($T$25:T51))*V52*W52/SUMPRODUCT($W52:$W$58,$V52:$V$58)),"") | U52: =IF(W52<>"",IF($I$12<>"",IF(G52<>"",G52,($I$9/$I$12-SUM($U$25:U51))*V52*W52/SUMPRODUCT($W52:$W$58,$V52:$V$58)),""),"")
F53: =IF(AND(E53<>"",E53<>0),D53/E53,"") | H53: =IF(AND(G53<>"",G53<>0),D53/G53,"") | J53: =IF(AND(G53<>"",G53<>0),E53/G53,"") | N53: =IF(AND(I53<>"",I53<>0),G53/I53,"") | O53: =D53/P53 -> #DIV/0! | P53: =$I$8*V53*W53/SUMPRODUCT($W$25:$W$56,$V$25:$V$56) -> 0 | Q53: =$I$9*V53*W53/SUMPRODUCT($W$25:$W$58,$V$25:$V$58) -> 0 | R53: =IF($I$12="","",Q53/$I$12) -> 0 | S53: =IF(W53<>"",IF(D53<>"",D53,($I$8-SUM($S$25:S52))*V53*W53/SUMPRODUCT($W53:$W$58,$V53:$V$58)),"") | T53: =IF(W53<>"",IF(E53<>"",E53,($I$9-SUM($T$25:T52))*V53*W53/SUMPRODUCT($W53:$W$58,$V53:$V$58)),"") | U53: =IF(W53<>"",IF($I$12<>"",IF(G53<>"",G53,($I$9/$I$12-SUM($U$25:U52))*V53*W53/SUMPRODUCT($W53:$W$58,$V53:$V$58)),""),"")
F54: =IF(AND(E54<>"",E54<>0),D54/E54,"") | H54: =IF(AND(G54<>"",G54<>0),D54/G54,"") | J54: =IF(AND(G54<>"",G54<>0),E54/G54,"") | N54: =IF(AND(I54<>"",I54<>0),G54/I54,"") | O54: =D54/P54 -> #DIV/0! | P54: =$I$8*V54*W54/SUMPRODUCT($W$25:$W$56,$V$25:$V$56) -> 0 | Q54: =$I$9*V54*W54/SUMPRODUCT($W$25:$W$58,$V$25:$V$58) -> 0 | R54: =IF($I$12="","",Q54/$I$12) -> 0 | S54: =IF(W54<>"",IF(D54<>"",D54,($I$8-SUM($S$25:S50))*V54*W54/SUMPRODUCT($W54:$W$58,$V54:$V$58)),"") | T54: =IF(W54<>"",IF(E54<>"",E54,($I$9-SUM($T$25:T50))*V54*W54/SUMPRODUCT($W54:$W$58,$V54:$V$58)),"") | U54: =IF(W54<>"",IF($I$12<>"",IF(G54<>"",G54,($I$9/$I$12-SUM($U$25:U50))*V54*W54/SUMPRODUCT($W54:$W$58,$V54:$V$58)),""),"")
F55: =IF(AND(E55<>"",E55<>0),D55/E55,"") | H55: =IF(AND(G55<>"",G55<>0),D55/G55,"") | J55: =IF(AND(G55<>"",G55<>0),E55/G55,"") | N55: =IF(AND(I55<>"",I55<>0),G55/I55,"") | O55: =D55/P55 -> #DIV/0! | P55: =$I$8*V55*W55/SUMPRODUCT($W$25:$W$56,$V$25:$V$56) -> 0 | Q55: =$I$9*V55*W55/SUMPRODUCT($W$25:$W$58,$V$25:$V$58) -> 0 | R55: =IF($I$12="","",Q55/$I$12) -> 0 | S55: =IF(W55<>"",IF(D55<>"",D55,($I$8-SUM($S$25:S54))*V55*W55/SUMPRODUCT($W55:$W$58,$V55:$V$58)),"") | T55: =IF(W55<>"",IF(E55<>"",E55,($I$9-SUM($T$25:T54))*V55*W55/SUMPRODUCT($W55:$W$58,$V55:$V$58)),"") | U55: =IF(W55<>"",IF($I$12<>"",IF(G55<>"",G55,($I$9/$I$12-SUM($U$25:U54))*V55*W55/SUMPRODUCT($W55:$W$58,$V55:$V$58)),""),"")
F56: =IF(AND(E56<>"",E56<>0),D56/E56,"") | H56: =IF(AND(G56<>"",G56<>0),D56/G56,"") | J56: =IF(AND(G56<>"",G56<>0),E56/G56,"") | N56: =IF(AND(I56<>"",I56<>0),G56/I56,"") | O56: =D56/P56 -> #DIV/0! | P56: =$I$8*V56*W56/SUMPRODUCT($W$25:$W$56,$V$25:$V$56) -> 0 | Q56: =$I$9*V56*W56/SUMPRODUCT($W$25:$W$58,$V$25:$V$58) -> 0 | R56: =IF($I$12="","",Q56/$I$12) -> 0 | S56: =IF(W56<>"",IF(D56<>"",D56,($I$8-SUM($S$25:S55))*V56*W56/SUMPRODUCT($W56:$W$58,$V56:$V$58)),"") | T56: =IF(W56<>"",IF(E56<>"",E56,($I$9-SUM($T$25:T55))*V56*W56/SUMPRODUCT($W56:$W$58,$V56:$V$58)),"") | U56: =IF(W56<>"",IF($I$12<>"",IF(G56<>"",G56,($I$9/$I$12-SUM($U$25:U55))*V56*W56/SUMPRODUCT($W56:$W$58,$V56:$V$58)),""),"")
D57: =SUM(D25:D56) -> 620172 | E57: =SUM(E25:E56) -> 70 | F57: =IF(AND(E57<>"",E57<>0),D57/E57,"") -> 8859.6 | G57: =SUM(G25:G56) -> 41 | H57: =IF(AND(G57<>"",G57<>0),D57/G57,"") -> 15126.146 | I57: =SUM(I25:I56) -> 324 | J57: =IF(AND(G57<>"",G57<>0),E57/G57,"") -> 1.7073171 | K57: =SUM(K25:K56) -> 201362 | L57: =SUM(L25:L56) -> 220 | M57: =SUM(M25:M56) -> 37180 | N57: =IF(AND(I57<>"",I57<>0),G57/I57,"") -> 0.12654321 | O57: =D57/P57 -> 0.55855872 | P57: =SUM(P25:P56) -> 1110307.6 | Q57: =SUM(Q25:Q55) -> 142.34713 | R57: =SUM(R25:R55) -> 81.808696 | S57: =SUM(S25:S56) -> 947117.7 | T57: =SUM(T25:T55) -> 118.07097 | U57: =SUM(U25:U55) -> 66.613921

Sheet Арапова А. В.
B1: =TODAY()-1 -> 46060
B2: (отчетная дата) | J2: ЕЖЕДНЕВНЫЙ ОТЧЕТ О ПРОДАЖАХ
B3: Осталось до выполнения плана!!! | J3: Арапова Анна -Мария
C4: =I8-D50 -> 1019670.3 | E4: =IF(I8<>0,C4/I8,0) -> 1
F6: Целевые показатели
F7: Показатель | I7: План | J7: Факт | K7: % выполнения | L7: Прогноз выполнения | M7: % выполнения по прогнозу | N7: Отклонение | O7: Факт аналогичного месяца прошлого года | P7: Отклонение LFL
F8: Выручка | I8: ='Ялта, Ленина, 18'!I8/График!AJ31*График!AJ27 -> 1019670.3 | J8: =D57 -> 280692.7 | K8: =IF(AND(I8<>"",I8<>0,J8<>""),J8/I8,"") -> 0.27527791 | L8: =IF(SUMIF($D$25:$D$56,">=0",$P$25:$P$56)<>0,I8*D57/SUMIF($D$25:$D$56,">=0",$P$25:$P$56),0) -> 484890.32 | M8: =IF(AND(I8<>"",I8<>0,L8<>"",L8<>0),L8/I8,"") -> 0.47553639 | N8: =IF(AND(J8<>0,J8<>"",I8<>0,I8<>""),L8-I8,"") -> -534779.94 | P8: =IF(AND(O8<>"",O8<>0,L8<>"",L8<>0),-O8+L8,"") | Q8: =IF(AND(P8<>"",P8<>0,O8<>0,O8<>""),P8/O8,"")
F9: Кол-во изделий | I9: =I8/I11 -> 130.72696 | J9: =E57 -> 34 | K9: =IF(AND(I9<>"",I9<>0,J9<>""),J9/I9,"") -> 0.26008408 | L9: =IF(SUMIF($E$25:$E$54,">=0",$Q$25:$Q$54)<>0,I9*E57/SUMIF($E$25:$E$54,">=0",$Q$25:$Q$54),0) -> 58.734234 | M9: =IF(AND(I9<>"",I9<>0,L9<>"",L9<>0),L9/I9,"") -> 0.44928939 | N9: =IF(AND(J9<>0,J9<>"",I9<>0,I9<>""),L9-I9,"") -> -71.992722 | O9: =O8/O11 -> #DIV/0! | P9: =IF(AND(O9<>"",O9<>0,L9<>"",L9<>0),-O9+L9,"") -> #DIV/0! | Q9: =IF(AND(P9<>"",P9<>0,O9<>0,O9<>""),P9/O9,"") -> #DIV/0!
F10: Средний чек | I10: =I11*I12 -> 13572 | J10: =H57 -> 14773.3 | K10: =IF(AND(I10<>"",I10<>0,J10<>""),J10/I10,"") -> 1.0885131 | L10: =J10 -> 14773.3 | M10: =IF(AND(I10<>"",I10<>0,L10<>"",L10<>0),L10/I10,"") -> 1.0885131 | N10: =IF(AND(J10<>0,J10<>"",I10<>0,I10<>""),L10-I10,"") -> 1201.3 | O10: =O11*O12 -> 0 | P10: =IF(AND(O10<>"",O10<>0,L10<>"",L10<>0),-O10+L10,"") | Q10: =IF(AND(P10<>"",P10<>0,O10<>0,O10<>""),P10/O10,"") | S10: IS | V10: =M23 -> Agafi
F11: Средняя стоимость изделия | I11: ='Ялта, Ленина, 18'!I11 -> 7800 | J11: =F57 -> 8255.6676 | K11: =IF(AND(I11<>"",I11<>0,J11<>""),J11/I11,"") -> 1.0584189 | L11: =IF(L9>0,L8/L9,"") -> 8255.6676 | M11: =IF(AND(I11<>"",I11<>0,L11<>"",L11<>0),L11/I11,"") -> 1.0584189 | N11: =IF(AND(J11<>0,J11<>"",I11<>0,I11<>""),L11-I11,"") -> 455.66765 | P11: =IF(AND(O11<>"",O11<>0,L11<>"",L11<>0),-O11+L11,"") | Q11: =IF(AND(P11<>"",P11<>0,O11<>0,O11<>""),P11/O11,"")
F12: Длина чека | I12: ='Ялта, Ленина, 18'!I12 -> 1.74 | J12: =J57 -> 1.7894737 | K12: =IF(AND(I12<>"",I12<>0,J12<>""),J12/I12,"") -> 1.0284332 | L12: =J12 -> 1.7894737 | M12: =IF(AND(I12<>"",I12<>0,L12<>"",L12<>0),L12/I12,"") -> 1.0284332 | N12: =IF(AND(J12<>0,J12<>"",I12<>0,I12<>""),L12-I12,"") -> 0.049473684 | P12: =IF(AND(O12<>"",O12<>0,L12<>"",L12<>0),-O12+L12,"") | Q12: =IF(AND(P12<>"",P12<>0,O12<>0,O12<>""),P12/O12,"") | S12: ='Ялта, Ленина, 18'!U12*График!AJ28/График!AJ31 -> 217304.35 | T12: =L57 -> 0 | U12: =S12-T12 -> 217304.35 | V12: ='Ялта, Ленина, 18'!X12/График!AJ31*График!AJ28 -> 204521.74 | W12: =M57 -> 13793 | X12: =V12-W12 -> 190728.74
F13: Кол-во чеков | I13: =IF(I12<>0,I9/I12,"") -> 75.130435 | J13: =G57 -> 19 | K13: =IF(AND(I13<>"",I13<>0,J13<>""),J13/I13,"") -> 0.25289352 | L13: =IF(SUMIF($G$25:$G$54,">=0",$R$25:$R$54)<>0,I13*G57/SUMIF($G$25:$G$54,">=0",$R$25:$R$54),"") -> 32.822072 | M13: =IF(AND(I13<>"",I13<>0,L13<>"",L13<>0),L13/I13,"") -> 0.43686786 | N13: =IF(AND(J13<>0,J13<>"",I13<>0,I13<>""),L13-I13,"") -> -42.308363 | P13: =IF(AND(O13<>"",O13<>0,L13<>"",L13<>0),-O13+L13,"") | Q13: =IF(AND(P13<>"",P13<>0,O13<>0,O13<>""),P13/O13,"") | S13: =T12/S12 -> 0 | T13: =S13/J14*I14 -> 0 | V13: =W12/V12 -> 0.067440264 | W13: =V13/J14*I14 -> 0.067440264
F14: Кол-во смен план/отработано | I14: =График!AI27 -> 21 | J14: 21 | K14: =IF(AND(I14<>"",I14<>0,J14<>""),J14/I14,"") -> 1 | L14: =I14 -> 21 | M14: =IF(AND(I14<>"",I14<>0,L14<>"",L14<>0),L14/I14,"") -> 1 | N14: =IF(AND(J14<>0,J14<>"",I14<>0,I14<>""),L14-I14,"") -> 0 | P14: =IF(AND(O14<>"",O14<>0,L14<>"",L14<>0),-O14+L14,"") | Q14: =IF(AND(P14<>"",P14<>0,O14<>0,O14<>""),P14/O14,"")
F15: Средние продажи в смену | I15: ='Ялта, Ленина, 18'!I15 -> 84058.839 | J15: =J8/J14 -> 13366.319 | K15: =IF(AND(I15<>"",I15<>0,J15<>""),J15/I15,"") -> 0.15901146 | L15: =J15 -> 13366.319 | M15: =IF(AND(I15<>"",I15<>0,L15<>"",L15<>0),L15/I15,"") -> 0.15901146 | N15: =IF(AND(J15<>0,J15<>"",I15<>0,I15<>""),L15-I15,"") -> -70692.52 | P15: =IF(AND(O15<>"",O15<>0,L15<>"",L15<>0),-O15+L15,"") | Q15: =IF(AND(P15<>"",P15<>0,O15<>0,O15<>""),P15/O15,"")
F16: Отставание/Перевыполнение | J16: =J8-I15*J14 -> -1484542.9 | K16: =IF(AND(I16<>"",I16<>0,J16<>""),J16/I16,"") | L16: =J16 -> -1484542.9 | M16: =IF(AND(I16<>"",I16<>0,L16<>"",L16<>0),L16/I16,"") | N16: =IF(AND(J16<>0,J16<>"",I16<>0,I16<>""),L16-I16,"") | P16: =IF(AND(O16<>"",O16<>0,L16<>"",L16<>0),-O16+L16,"") | Q16: =IF(AND(P16<>"",P16<>0,O16<>0,O16<>""),P16/O16,"") | S16: UNOde50
F17: Трафик | I17: ='Ялта, Ленина, 18'!I17/График!AJ31*График!AJ28 -> 681.73913 | J17: =I57 -> 257 | K17: =IF(AND(I17<>"",I17<>0,J17<>""),J17/I17,"") -> 0.37697704 | L17: =J17/J14*I14 -> 257 | M17: =IF(AND(I17<>"",I17<>0,L17<>"",L17<>0),L17/I17,"") -> 0.37697704 | N17: =IF(AND(J17<>0,J17<>"",I17<>0,I17<>""),L17-I17,"") -> -424.73913 | P17: =IF(AND(O17<>"",O17<>0,L17<>"",L17<>0),-O17+L17,"") | Q17: =IF(AND(P17<>"",P17<>0,O17<>0,O17<>""),P17/O17,"")
K18: =IF(AND(I18<>"",I18<>0,J18<>""),J18/I18,"") | L18: =J18 -> 0 | M18: =IF(AND(I18<>"",I18<>0,L18<>"",L18<>0),L18/I18,"") | N18: =IF(AND(J18<>0,J18<>"",I18<>0,I18<>""),L18-I18,"") | O18: 0 | P18: =IF(AND(O18<>"",O18<>0,L18<>"",L18<>0),-O18+L18,"") | Q18: =IF(AND(P18<>"",P18<>0,O18<>0,O18<>""),P18/O18,"") | S18: ='Ялта, Ленина, 18'!U18*График!AJ28/График!AJ31 -> 434608.7 | T18: =K57 -> 47970
K19: =IF(AND(I19<>"",I19<>0,J19<>""),J19/I19,"") | L19: =J19 -> 0 | M19: =IF(AND(I19<>"",I19<>0,L19<>"",L19<>0),L19/I19,"") | N19: =IF(AND(J19<>0,J19<>"",I19<>0,I19<>""),L19-I19,"") | O19: 0 | P19: =IF(AND(O19<>"",O19<>0,L19<>"",L19<>0),-O19+L19,"") | Q19: =IF(AND(P19<>"",P19<>0,O19<>0,O19<>""),P19/O19,"") | S19: =T18/S18 -> 0.11037515 | T19: =S19/J14*I14 -> 0.11037515
F20: Конверсия план/факт | I20: ='Ялта, Ленина, 18'!I20 -> 0.12 | J20: =N57 -> 0.073929961 | K20: =J20/I20 -> 0.61608301 | L20: =IF(AND(K8<>0,I14<>0,I57<>0),(I57*N57+(I57/K8-I57)*I20)/(I57/K8),0) -> 0.10731794 | M20: =IF(AND(I20<>"",I20<>0,L20<>"",L20<>0),L20/I20,"") -> 0.89431613 | N20: =IF(AND(J20<>0,J20<>"",I20<>0,I20<>""),L20-I20,"") -> -0.012682064 | P20: =IF(AND(O20<>"",O20<>0,L20<>"",L20<>0),-O20+L20,"") | Q20: =IF(AND(P20<>"",P20<>0,O20<>0,O20<>""),P20/O20,"")
B22: Факт продаж за месяц | O22: % выполнения дневного плана | P22: Раcпределение плана по дням
B23: Дата | C23: День недели | D23: Выручка (руб) | E23: Кол-во единиц (шт.) | F23: Средняя стоимость изделия (руб.) | G23: Количество чеков (шт.) | H23: Средняя сумма чека (руб.) | I23: Трафик | J23: Длина чека (шт.) | K23: UNOde50 | L23: IS | M23: Agafi | N23: Конверсия (%) | P23: выручка, план | Q23: кол-во ед, план | R23: Кол-во чеков, план | S23: выручка, скорректир.план | T23: кол-во ед, скорр. план | U23: кол-во чеков, скорр. план | V23: Коэфф. Дня Недели | W23: Специфика месяца
B24: 1 | C24: 2 | D24: 3 | E24: в | F24: 5 | G24: 6 | H24: 7 | I24: 8 | J24: 9 | K24: 10 | L24: 11 | M24: 12 | N24: 13 | P24: 1 | Q24: 2 | R24: 3 | S24: 4 | T24: 5 | U24: 6 | V24: 10 | W24: 11
A25: 1 | B25: 45993 | C25: вт | F25: =IF(AND(E25<>"",E25<>0),D25/E25,"") | H25: =IF(AND(G25<>"",G25<>0),D25/G25,"") | I25: 10 | J25: =IF(AND(G25<>"",G25<>0),E25/G25,"") | N25: =IF(AND(I25<>"",I25<>0),G25/I25,"") -> 0 | O25: =D25/P25 -> 0 | P25: =$I$8*V25*W25/SUMPRODUCT($W$25:$W$56,$V$25:$V$56) -> 44314.223 | Q25: =$I$9*V25*W25/SUMPRODUCT($W$25:$W$56,$V$25:$V$56) -> 5.6813106 | R25: =IF($I$12="","",Q25/$I$12) -> 3.265121 | S25: =IF(D25<>"",D25,P25) -> 44314.223 | T25: =IF(E25<>"",E25,Q25) -> 5.6813106 | U25: =IF(G25<>"",G25,R25) -> 3.265121 | V25: 1 | W25: 1
A26: 2 | B26: 45996 | C26: пт | D26: 11384 | E26: 2 | F26: =IF(AND(E26<>"",E26<>0),D26/E26,"") -> 5692 | G26: 1 | H26: =IF(AND(G26<>"",G26<>0),D26/G26,"") -> 11384 | I26: 13 | J26: =IF(AND(G26<>"",G26<>0),E26/G26,"") -> 2 | N26: =IF(AND(I26<>"",I26<>0),G26/I26,"") -> 0.076923077 | O26: =D26/P26 -> 0.25689269 | P26: =$I$8*V26*W26/SUMPRODUCT($W$25:$W$56,$V$25:$V$56) -> 44314.223 | Q26: =$I$9*V26*W26/SUMPRODUCT($W$25:$W$58,$V$25:$V$58) -> 5.6813106 | R26: =IF($I$12="","",Q26/$I$12) -> 3.265121 | S26: =IF(W26<>"",IF(D26<>"",D26,($I$8-SUM($S$25:S25))*V26*W26/SUMPRODUCT($W26:$W$56,$V26:$V$56)),"") -> 11384 | T26: =IF(W26<>"",IF(E26<>"",E26,($I$9-SUM($T$25:T25))*V26*W26/SUMPRODUCT($W26:$W$55,$V26:$V$55)),"") -> 2 | U26: =IF(W26<>"",IF($I$12<>"",IF(G26<>"",G26,($I$9/$I$12-SUM($U$25:U25))*V26*W26/SUMPRODUCT($W26:$W$55,$V26:$V$55)),""),"") -> 1 | V26: 1 | W26: 1
A27: 3 | B27: 45997 | C27: сб | D27: 5893 | E27: 1 | F27: =IF(AND(E27<>"",E27<>0),D27/E27,"") -> 5893 | G27: 1 | H27: =IF(AND(G27<>"",G27<>0),D27/G27,"") -> 5893 | I27: 10 | J27: =IF(AND(G27<>"",G27<>0),E27/G27,"") -> 1 | N27: =IF(AND(I27<>"",I27<>0),G27/I27,"") -> 0.1 | O27: =D27/P27 -> 0.13298214 | P27: =$I$8*V27*W27/SUMPRODUCT($W$25:$W$56,$V$25:$V$56) -> 44314.223 | Q27: =$I$9*V27*W27/SUMPRODUCT($W$25:$W$58,$V$25:$V$58) -> 5.6813106 | R27: =IF($I$12="","",Q27/$I$12) -> 3.265121 | S27: =IF(W27<>"",IF(D27<>"",D27,($I$8-SUM($S$25:S26))*V27*W27/SUMPRODUCT($W27:$W$58,$V27:$V$58)),"") -> 5893 | T27: =IF(W27<>"",IF(E27<>"",E27,($I$9-SUM($T$25:T26))*V27*W27/SUMPRODUCT($W27:$W$55,$V27:$V$55)),"") -> 1 | U27: =IF(W27<>"",IF($I$12<>"",IF(G27<>"",G27,($I$9/$I$12-SUM($U$25:U26))*V27*W27/SUMPRODUCT($W27:$W$55,$V27:$V$55)),""),"") -> 1 | V27: 1 | W27: 1
A28: 4 | B28: 45998 | C28: вс | F28: =IF(AND(E28<>"",E28<>0),D28/E28,"") | H28: =IF(AND(G28<>"",G28<>0),D28/G28,"") | I28: 13 | J28: =IF(AND(G28<>"",G28<>0),E28/G28,"") | N28: =IF(AND(I28<>"",I28<>0),G28/I28,"") -> 0 | O28: =D28/P28 -> 0 | P28: =$I$8*V28*W28/SUMPRODUCT($W$25:$W$56,$V$25:$V$56) -> 44314.223 | Q28: =$I$9*V28*W28/SUMPRODUCT($W$25:$W$58,$V$25:$V$58) -> 5.6813106 | R28: =IF($I$12="","",Q28/$I$12) -> 3.265121 | S28: =IF(W28<>"",IF(D28<>"",D28,($I$8-SUM($S$25:S27))*V28*W28/SUMPRODUCT($W28:$W$58,$V28:$V$58)),"") -> 47880.012 | T28: =IF(W28<>"",IF(E28<>"",E28,($I$9-SUM($T$25:T27))*V28*W28/SUMPRODUCT($W28:$W$58,$V28:$V$58)),"") -> 6.0992327 | U28: =IF(W28<>"",IF($I$12<>"",IF(G28<>"",G28,($I$9/$I$12-SUM($U$25:U27))*V28*W28/SUMPRODUCT($W28:$W$58,$V28:$V$58)),""),"") -> 3.4915199 | V28: 1 | W28: 1
A29: 5 | B29: 46000 | C29: вт | F29: =IF(AND(E29<>"",E29<>0),D29/E29,"") | H29: =IF(AND(G29<>"",G29<>0),D29/G29,"") | I29: 1 | J29: =IF(AND(G29<>"",G29<>0),E29/G29,"") | N29: =IF(AND(I29<>"",I29<>0),G29/I29,"") -> 0 | O29: =D29/P29 -> 0 | P29: =$I$8*V29*W29/SUMPRODUCT($W$25:$W$56,$V$25:$V$56) -> 44314.223 | Q29: =$I$9*V29*W29/SUMPRODUCT($W$25:$W$58,$V$25:$V$58) -> 5.6813106 | R29: =IF($I$12="","",Q29/$I$12) -> 3.265121 | S29: =IF(W29<>"",IF(D29<>"",D29,($I$8-SUM($S$25:S28))*V29*W29/SUMPRODUCT($W29:$W$58,$V29:$V$58)),"") -> 47880.012 | T29: =IF(W29<>"",IF(E29<>"",E29,($I$9-SUM($T$25:T28))*V29*W29/SUMPRODUCT($W29:$W$58,$V29:$V$58)),"") -> 6.0992327 | U29: =IF(W29<>"",IF($I$12<>"",IF(G29<>"",G29,($I$9/$I$12-SUM($U$25:U28))*V29*W29/SUMPRODUCT($W29:$W$58,$V29:$V$58)),""),"") -> 3.4915199 | V29: 1 | W29: 1
A30: 6 | B30: 46001 | C30: ср | D30: 19875 | E30: 3 | F30: =IF(AND(E30<>"",E30<>0),D30/E30,"") -> 6625 | G30: 1 | H30: =IF(AND(G30<>"",G30<>0),D30/G30,"") -> 19875 | I30: 4 | J30: =IF(AND(G30<>"",G30<>0),E30/G30,"") -> 3 | K30: 12490 | N30: =IF(AND(I30<>"",I30<>0),G30/I30,"") -> 0.25 | O30: =D30/P30 -> 0.44850161 | P30: =$I$8*V30*W30/SUMPRODUCT($W$25:$W$56,$V$25:$V$56) -> 44314.223 | Q30: =$I$9*V30*W30/SUMPRODUCT($W$25:$W$58,$V$25:$V$58) -> 5.6813106 | R30: =IF($I$12="","",Q30/$I$12) -> 3.265121 | S30: =IF(W30<>"",IF(D30<>"",D30,($I$8-SUM($S$25:S29))*V30*W30/SUMPRODUCT($W30:$W$58,$V30:$V$58)),"") -> 19875 | T30: =IF(W30<>"",IF(E30<>"",E30,($I$9-SUM($T$25:T29))*V30*W30/SUMPRODUCT($W30:$W$58,$V30:$V$58)),"") -> 3 | U30: =IF(W30<>"",IF($I$12<>"",IF(G30<>"",G30,($I$9/$I$12-SUM($U$25:U29))*V30*W30/SUMPRODUCT($W30:$W$58,$V30:$V$58)),""),"") -> 1 | V30: 1 | W30: 1
A31: 7 | B31: 46004 | C31: сб | F31: =IF(AND(E31<>"",E31<>0),D31/E31,"") | H31: =IF(AND(G31<>"",G31<>0),D31/G31,"") | I31: 10 | J31: =IF(AND(G31<>"",G31<>0),E31/G31,"") | N31: =IF(AND(I31<>"",I31<>0),G31/I31,"") -> 0 | O31: =D31/P31 -> 0 | P31: =$I$8*V31*W31/SUMPRODUCT($W$25:$W$56,$V$25:$V$56) -> 44314.223 | Q31: =$I$9*V31*W31/SUMPRODUCT($W$25:$W$58,$V$25:$V$58) -> 5.6813106 | R31: =IF($I$12="","",Q31/$I$12) -> 3.265121 | S31: =IF(W31<>"",IF(D31<>"",D31,($I$8-SUM($S$25:S30))*V31*W31/SUMPRODUCT($W31:$W$58,$V31:$V$58)),"") -> 49526.397 | T31: =IF(W31<>"",IF(E31<>"",E31,($I$9-SUM($T$25:T30))*V31*W31/SUMPRODUCT($W31:$W$58,$V31:$V$58)),"") -> 6.2814333 | U31: =IF(W31<>"",IF($I$12<>"",IF(G31<>"",G31,($I$9/$I$12-SUM($U$25:U30))*V31*W31/SUMPRODUCT($W31:$W$58,$V31:$V$58)),""),"") -> 3.6379938 | V31: 1 | W31: 1
A32: 8 | B32: 46005 | C32: вс | D32: =6493+13684 -> 20177 | E32: 3 | F32: =IF(AND(E32<>"",E32<>0),D32/E32,"") -> 6725.6667 | G32: 2 | H32: =IF(AND(G32<>"",G32<>0),D32/G32,"") -> 10088.5 | I32: 18 | J32: =IF(AND(G32<>"",G32<>0),E32/G32,"") -> 1.5 | N32: =IF(AND(I32<>"",I32<>0),G32/I32,"") -> 0.11111111 | O32: =D32/P32 -> 0.45531657 | P32: =$I$8*V32*W32/SUMPRODUCT($W$25:$W$56,$V$25:$V$56) -> 44314.223 | Q32: =$I$9*V32*W32/SUMPRODUCT($W$25:$W$58,$V$25:$V$58) -> 5.6813106 | R32: =IF($I$12="","",Q32/$I$12) -> 3.265121 | S32: =IF(W32<>"",IF(D32<>"",D32,($I$8-SUM($S$25:S31))*V32*W32/SUMPRODUCT($W32:$W$58,$V32:$V$58)),"") -> 20177 | T32: =IF(W32<>"",IF(E32<>"",E32,($I$9-SUM($T$25:T31))*V32*W32/SUMPRODUCT($W32:$W$58,$V32:$V$58)),"") -> 3 | U32: =IF(W32<>"",IF($I$12<>"",IF(G32<>"",G32,($I$9/$I$12-SUM($U$25:U31))*V32*W32/SUMPRODUCT($W32:$W$58,$V32:$V$58)),""),"") -> 2 | V32: 1 | W32: 1
A33: 9 | B33: 46006 | C33: пн | D33: 0 | E33: 0 | F33: =IF(AND(E33<>"",E33<>0),D33/E33,"") | G33: 0 | H33: =IF(AND(G33<>"",G33<>0),D33/G33,"") | I33: 5 | J33: =IF(AND(G33<>"",G33<>0),E33/G33,"") | N33: =IF(AND(I33<>"",I33<>0),G33/I33,"") -> 0 | O33: =D33/P33 -> 0 | P33: =$I$8*V33*W33/SUMPRODUCT($W$25:$W$56,$V$25:$V$56) -> 44314.223 | Q33: =$I$9*V33*W33/SUMPRODUCT($W$25:$W$58,$V$25:$V$58) -> 5.6813106 | R33: =IF($I$12="","",Q33/$I$12) -> 3.265121 | S33: =IF(W33<>"",IF(D33<>"",D33,($I$8-SUM($S$25:S32))*V33*W33/SUMPRODUCT($W33:$W$58,$V33:$V$58)),"") -> 0 | T33: =IF(W33<>"",IF(E33<>"",E33,($I$9-SUM($T$25:T32))*V33*W33/SUMPRODUCT($W33:$W$58,$V33:$V$58)),"") -> 0 | U33: =IF(W33<>"",IF($I$12<>"",IF(G33<>"",G33,($I$9/$I$12-SUM($U$25:U32))*V33*W33/SUMPRODUCT($W33:$W$58,$V33:$V$58)),""),"") -> 0 | V33: 1 | W33: 1
A34: 10 | B34: 46009 | C34: чт | D34: 0 | E34: 0 | F34: =IF(AND(E34<>"",E34<>0),D34/E34,"") | G34: 0 | H34: =IF(AND(G34<>"",G34<>0),D34/G34,"") | I34: 26 | J34: =IF(AND(G34<>"",G34<>0),E34/G34,"") | N34: =IF(AND(I34<>"",I34<>0),G34/I34,"") -> 0 | O34: =D34/P34 -> 0 | P34: =$I$8*V34*W34/SUMPRODUCT($W$25:$W$56,$V$25:$V$56) -> 44314.223 | Q34: =$I$9*V34*W34/SUMPRODUCT($W$25:$W$58,$V$25:$V$58) -> 5.6813106 | R34: =IF($I$12="","",Q34/$I$12) -> 3.265121 | S34: =IF(W34<>"",IF(D34<>"",D34,($I$8-SUM($S$25:S33))*V34*W34/SUMPRODUCT($W34:$W$58,$V34:$V$58)),"") -> 0 | T34: =IF(W34<>"",IF(E34<>"",E34,($I$9-SUM($T$25:T33))*V34*W34/SUMPRODUCT($W34:$W$58,$V34:$V$58)),"") -> 0 | U34: =IF(W34<>"",IF($I$12<>"",IF(G34<>"",G34,($I$9/$I$12-SUM($U$25:U33))*V34*W34/SUMPRODUCT($W34:$W$58,$V34:$V$58)),""),"") -> 0 | V34: 1 | W34: 1
A35: 11 | B35: 46010 | C35: пт | F35: =IF(AND(E35<>"",E35<>0),D35/E35,"") | H35: =IF(AND(G35<>"",G35<>0),D35/G35,"") | I35: 12 | J35: =IF(AND(G35<>"",G35<>0),E35/G35,"") | N35: =IF(AND(I35<>"",I35<>0),G35/I35,"") -> 0 | O35: =D35/P35 -> 0 | P35: =$I$8*V35*W35/SUMPRODUCT($W$25:$W$56,$V$25:$V$56) -> 35894.52 | Q35: =$I$9*V35*W35/SUMPRODUCT($W$25:$W$58,$V$25:$V$58) -> 4.6018616 | R35: =IF($I$12="","",Q35/$I$12) -> 2.644748 | S35: =IF(W35<>"",IF(D35<>"",D35,($I$8-SUM($S$25:S34))*V35*W35/SUMPRODUCT($W35:$W$58,$V35:$V$58)),"") -> 48110.676 | T35: =IF(W35<>"",IF(E35<>"",E35,($I$9-SUM($T$25:T34))*V35*W35/SUMPRODUCT($W35:$W$58,$V35:$V$58)),"") -> 6.0744239 | U35: =IF(W35<>"",IF($I$12<>"",IF(G35<>"",G35,($I$9/$I$12-SUM($U$25:U34))*V35*W35/SUMPRODUCT($W35:$W$58,$V35:$V$58)),""),"") -> 3.5017576 | V35: 0.9 | W35: 0.9
A36: 12 | B36: 46011 | C36: сб | D36: 45832.7 | E36: 4 | F36: =IF(AND(E36<>"",E36<>0),D36/E36,"") -> 11458.175 | G36: 3 | H36: =IF(AND(G36<>"",G36<>0),D36/G36,"") -> 15277.567 | I36: 18 | J36: =IF(AND(G36<>"",G36<>0),E36/G36,"") -> 1.3333333 | N36: =IF(AND(I36<>"",I36<>0),G36/I36,"") -> 0.16666667 | O36: =D36/P36 -> 1.0342661 | P36: =$I$8*V36*W36/SUMPRODUCT($W$25:$W$56,$V$25:$V$56) -> 44314.223 | Q36: =$I$9*V36*W36/SUMPRODUCT($W$25:$W$58,$V$25:$V$58) -> 5.6813106 | R36: =IF($I$12="","",Q36/$I$12) -> 3.265121 | S36: =IF(W36<>"",IF(D36<>"",D36,($I$8-SUM($S$25:S35))*V36*W36/SUMPRODUCT($W36:$W$58,$V36:$V$58)),"") -> 45832.7 | T36: =IF(W36<>"",IF(E36<>"",E36,($I$9-SUM($T$25:T35))*V36*W36/SUMPRODUCT($W36:$W$58,$V36:$V$58)),"") -> 4 | U36: =IF(W36<>"",IF($I$12<>"",IF(G36<>"",G36,($I$9/$I$12-SUM($U$25:U35))*V36*W36/SUMPRODUCT($W36:$W$58,$V36:$V$58)),""),"") -> 3 | V36: 1 | W36: 1
A37: 13 | B37: 46012 | C37: вс | D37: 38767 | E37: 4 | F37: 9692 | G37: 2 | H37: =IF(AND(G37<>"",G37<>0),D37/G37,"") -> 19383.5 | I37: 15 | J37: =IF(AND(G37<>"",G37<>0),E37/G37,"") -> 2 | N37: =IF(AND(I37<>"",I37<>0),G37/I37,"") -> 0.13333333 | O37: =D37/P37 -> 0.87482072 | P37: =$I$8*V37*W37/SUMPRODUCT($W$25:$W$56,$V$25:$V$56) -> 44314.223 | Q37: =$I$9*V37*W37/SUMPRODUCT($W$25:$W$58,$V$25:$V$58) -> 5.6813106 | R37: =IF($I$12="","",Q37/$I$12) -> 3.265121 | S37: =IF(W37<>"",IF(D37<>"",D37,($I$8-SUM($S$25:S36))*V37*W37/SUMPRODUCT($W37:$W$58,$V37:$V$58)),"") -> 38767 | T37: =IF(W37<>"",IF(E37<>"",E37,($I$9-SUM($T$25:T36))*V37*W37/SUMPRODUCT($W37:$W$58,$V37:$V$58)),"") -> 4 | U37: =IF(W37<>"",IF($I$12<>"",IF(G37<>"",G37,($I$9/$I$12-SUM($U$25:U36))*V37*W37/SUMPRODUCT($W37:$W$58,$V37:$V$58)),""),"") -> 2 | V37: 1 | W37: 1
A38: 14 | B38: 46013 | C38: пн | F38: =IF(AND(E38<>"",E38<>0),D38/E38,"") | H38: =IF(AND(G38<>"",G38<>0),D38/G38,"") | J38: =IF(AND(G38<>"",G38<>0),E38/G38,"") | N38: =IF(AND(I38<>"",I38<>0),G38/I38,"") | O38: =D38/P38 -> #DIV/0! | P38: =$I$8*V38*W38/SUMPRODUCT($W$25:$W$56,$V$25:$V$56) -> 0 | Q38: =$I$9*V38*W38/SUMPRODUCT($W$25:$W$58,$V$25:$V$58) -> 0 | R38: =IF($I$12="","",Q38/$I$12) -> 0 | S38: =IF(W38<>"",IF(D38<>"",D38,($I$8-SUM($S$25:S37))*V38*W38/SUMPRODUCT($W38:$W$58,$V38:$V$58)),"") | T38: =IF(W38<>"",IF(E38<>"",E38,($I$9-SUM($T$25:T37))*V38*W38/SUMPRODUCT($W38:$W$58,$V38:$V$58)),"") | U38: =IF(W38<>"",IF($I$12<>"",IF(G38<>"",G38,($I$9/$I$12-SUM($U$25:U37))*V38*W38/SUMPRODUCT($W38:$W$58,$V38:$V$58)),""),"")
A39: 15 | B39: 46014 | C39: вт | F39: =IF(AND(E39<>"",E39<>0),D39/E39,"") | H39: =IF(AND(G39<>"",G39<>0),D39/G39,"") | I39: 10 | J39: =IF(AND(G39<>"",G39<>0),E39/G39,"") | N39: =IF(AND(I39<>"",I39<>0),G39/I39,"") -> 0 | O39: =D39/P39 -> 0 | P39: =$I$8*V39*W39/SUMPRODUCT($W$25:$W$56,$V$25:$V$56) -> 44314.223 | Q39: =$I$9*V39*W39/SUMPRODUCT($W$25:$W$58,$V$25:$V$58) -> 5.6813106 | R39: =IF($I$12="","",Q39/$I$12) -> 3.265121 | S39: =IF(W39<>"",IF(D39<>"",D39,($I$8-SUM($S$25:S38))*V39*W39/SUMPRODUCT($W39:$W$58,$V39:$V$58)),"") -> 62748.063 | T39: =IF(W39<>"",IF(E39<>"",E39,($I$9-SUM($T$25:T38))*V39*W39/SUMPRODUCT($W39:$W$58,$V39:$V$58)),"") -> 8.1854239 | U39: =IF(W39<>"",IF($I$12<>"",IF(G39<>"",G39,($I$9/$I$12-SUM($U$25:U38))*V39*W39/SUMPRODUCT($W39:$W$58,$V39:$V$58)),""),"") -> 4.6806395 | V39: 1 | W39: 1
A40: 16 | B40: 46015 | C40: ср | F40: =IF(AND(E40<>"",E40<>0),D40/E40,"") | H40: =IF(AND(G40<>"",G40<>0),D40/G40,"") | I40: 15 | J40: =IF(AND(G40<>"",G40<>0),E40/G40,"") | N40: =IF(AND(I40<>"",I40<>0),G40/I40,"") -> 0 | O40: =D40/P40 -> 0 | P40: =$I$8*V40*W40/SUMPRODUCT($W$25:$W$56,$V$25:$V$56) -> 44314.223 | Q40: =$I$9*V40*W40/SUMPRODUCT($W$25:$W$58,$V$25:$V$58) -> 5.6813106 | R40: =IF($I$12="","",Q40/$I$12) -> 3.265121 | S40: =IF(W40<>"",IF(D40<>"",D40,($I$8-SUM($S$25:S39))*V40*W40/SUMPRODUCT($W40:$W$58,$V40:$V$58)),"") -> 62748.063 | T40: =IF(W40<>"",IF(E40<>"",E40,($I$9-SUM($T$25:T39))*V40*W40/SUMPRODUCT($W40:$W$58,$V40:$V$58)),"") -> 8.1854239 | U40: =IF(W40<>"",IF($I$12<>"",IF(G40<>"",G40,($I$9/$I$12-SUM($U$25:U39))*V40*W40/SUMPRODUCT($W40:$W$58,$V40:$V$58)),""),"") -> 4.6806395 | V40: 1 | W40: 1
A41: 17 | B41: 46016 | C41: чт | F41: =IF(AND(E41<>"",E41<>0),D41/E41,"") | H41: =IF(AND(G41<>"",G41<>0),D41/G41,"") | J41: =IF(AND(G41<>"",G41<>0),E41/G41,"") | N41: =IF(AND(I41<>"",I41<>0),G41/I41,"") | O41: =D41/P41 -> #DIV/0! | P41: =$I$8*V41*W41/SUMPRODUCT($W$25:$W$56,$V$25:$V$56) -> 0 | Q41: =$I$9*V41*W41/SUMPRODUCT($W$25:$W$58,$V$25:$V$58) -> 0 | R41: =IF($I$12="","",Q41/$I$12) -> 0 | S41: =IF(W41<>"",IF(D41<>"",D41,($I$8-SUM($S$25:S40))*V41*W41/SUMPRODUCT($W41:$W$58,$V41:$V$58)),"") | T41: =IF(W41<>"",IF(E41<>"",E41,($I$9-SUM($T$25:T40))*V41*W41/SUMPRODUCT($W41:$W$58,$V41:$V$58)),"") | U41: =IF(W41<>"",IF($I$12<>"",IF(G41<>"",G41,($I$9/$I$12-SUM($U$25:U40))*V41*W41/SUMPRODUCT($W41:$W$58,$V41:$V$58)),""),"")
A42: 18 | B42: 46017 | C42: пт | F42: =IF(AND(E42<>"",E42<>0),D42/E42,"") | H42: =IF(AND(G42<>"",G42<>0),D42/G42,"") | I42: 5 | J42: =IF(AND(G42<>"",G42<>0),E42/G42,"") | N42: =IF(AND(I42<>"",I42<>0),G42/I42,"") -> 0 | O42: =D42/P42 -> 0 | P42: =$I$8*V42*W42/SUMPRODUCT($W$25:$W$56,$V$25:$V$56) -> 63812.48 | Q42: =$I$9*V42*W42/SUMPRODUCT($W$25:$W$58,$V$25:$V$58) -> 8.1810872 | R42: =IF($I$12="","",Q42/$I$12) -> 4.7017743 | S42: =IF(W42<>"",IF(D42<>"",D42,($I$8-SUM($S$25:S41))*V42*W42/SUMPRODUCT($W42:$W$58,$V42:$V$58)),"") -> 90357.21 | T42: =IF(W42<>"",IF(E42<>"",E42,($I$9-SUM($T$25:T41))*V42*W42/SUMPRODUCT($W42:$W$58,$V42:$V$58)),"") -> 11.78701 | U42: =IF(W42<>"",IF($I$12<>"",IF(G42<>"",G42,($I$9/$I$12-SUM($U$25:U41))*V42*W42/SUMPRODUCT($W42:$W$58,$V42:$V$58)),""),"") -> 6.7401208 | V42: 1.2 | W42: 1.2
A43: 19 | B43: 46018 | C43: сб | D43: =17990+34131 -> 52121 | E43: 5 | F43: =IF(AND(E43<>"",E43<>0),D43/E43,"") -> 10424.2 | G43: 2 | H43: =IF(AND(G43<>"",G43<>0),D43/G43,"") -> 26060.5 | I43: 12 | J43: =IF(AND(G43<>"",G43<>0),E43/G43,"") -> 2.5 | K43: 17990 | N43: =IF(AND(I43<>"",I43<>0),G43/I43,"") -> 0.16666667 | O43: =D43/P43 -> 0.8167838 | P43: =$I$8*V43*W43/SUMPRODUCT($W$25:$W$56,$V$25:$V$56) -> 63812.48 | Q43: =$I$9*V43*W43/SUMPRODUCT($W$25:$W$58,$V$25:$V$58) -> 8.1810872 | R43: =IF($I$12="","",Q43/$I$12) -> 4.7017743 | S43: =IF(W43<>"",IF(D43<>"",D43,($I$8-SUM($S$25:S42))*V43*W43/SUMPRODUCT($W43:$W$58,$V43:$V$58)),"") -> 52121 | T43: =IF(W43<>"",IF(E43<>"",E43,($I$9-SUM($T$25:T42))*V43*W43/SUMPRODUCT($W43:$W$58,$V43:$V$58)),"") -> 5 | U43: =IF(W43<>"",IF($I$12<>"",IF(G43<>"",G43,($I$9/$I$12-SUM($U$25:U42))*V43*W43/SUMPRODUCT($W43:$W$58,$V43:$V$58)),""),"") -> 2 | V43: 1.2 | W43: 1.2
A44: 20 | B44: 46019 | C44: вс | F44: =IF(AND(E44<>"",E44<>0),D44/E44,"") | H44: =IF(AND(G44<>"",G44<>0),D44/G44,"") | I44: 11 | J44: =IF(AND(G44<>"",G44<>0),E44/G44,"") | N44: =IF(AND(I44<>"",I44<>0),G44/I44,"") -> 0 | O44: =D44/P44 -> 0 | P44: =$I$8*V44*W44/SUMPRODUCT($W$25:$W$56,$V$25:$V$56) -> 63812.48 | Q44: =$I$9*V44*W44/SUMPRODUCT($W$25:$W$58,$V$25:$V$58) -> 8.1810872 | R44: =IF($I$12="","",Q44/$I$12) -> 4.7017743 | S44: =IF(W44<>"",IF(D44<>"",D44,($I$8-SUM($S$25:S43))*V44*W44/SUMPRODUCT($W44:$W$58,$V44:$V$58)),"") -> 100706.86 | T44: =IF(W44<>"",IF(E44<>"",E44,($I$9-SUM($T$25:T43))*V44*W44/SUMPRODUCT($W44:$W$58,$V44:$V$58)),"") -> 13.624096 | U44: =IF(W44<>"",IF($I$12<>"",IF(G44<>"",G44,($I$9/$I$12-SUM($U$25:U43))*V44*W44/SUMPRODUCT($W44:$W$58,$V44:$V$58)),""),"") -> 8.023161 | V44: 1.2 | W44: 1.2
A45: 21 | B45: 46020 | C45: пн | D45: =13793+3923 -> 17716 | E45: 2 | F45: =IF(AND(E45<>"",E45<>0),D45/E45,"") -> 8858 | G45: 2 | H45: =IF(AND(G45<>"",G45<>0),D45/G45,"") -> 8858 | I45: 5 | J45: =IF(AND(G45<>"",G45<>0),E45/G45,"") -> 1 | M45: 13793 | N45: =IF(AND(I45<>"",I45<>0),G45/I45,"") -> 0.4 | O45: =D45/P45 -> 0.27762594 | P45: =$I$8*V45*W45/SUMPRODUCT($W$25:$W$56,$V$25:$V$56) -> 63812.48 | Q45: =$I$9*V45*W45/SUMPRODUCT($W$25:$W$58,$V$25:$V$58) -> 8.1810872 | R45: =IF($I$12="","",Q45/$I$12) -> 4.7017743 | S45: =IF(W45<>"",IF(D45<>"",D45,($I$8-SUM($S$25:S44))*V45*W45/SUMPRODUCT($W45:$W$58,$V45:$V$58)),"") -> 17716 | T45: =IF(W45<>"",IF(E45<>"",E45,($I$9-SUM($T$25:T44))*V45*W45/SUMPRODUCT($W45:$W$58,$V45:$V$58)),"") -> 2 | U45: =IF(W45<>"",IF($I$12<>"",IF(G45<>"",G45,($I$9/$I$12-SUM($U$25:U44))*V45*W45/SUMPRODUCT($W45:$W$58,$V45:$V$58)),""),"") -> 2 | V45: 1.2 | W45: 1.2
A46: 22 | B46: 46021 | C46: вт | D46: =7993+21568 -> 29561 | E46: 5 | F46: =IF(AND(E46<>"",E46<>0),D46/E46,"") -> 5912.2 | G46: 3 | H46: =IF(AND(G46<>"",G46<>0),D46/G46,"") -> 9853.6667 | I46: 24 | J46: =IF(AND(G46<>"",G46<>0),E46/G46,"") -> 1.6666667 | N46: =IF(AND(I46<>"",I46<>0),G46/I46,"") -> 0.125 | O46: =D46/P46 -> 0.46324794 | P46: =$I$8*V46*W46/SUMPRODUCT($W$25:$W$56,$V$25:$V$56) -> 63812.48 | Q46: =$I$9*V46*W46/SUMPRODUCT($W$25:$W$58,$V$25:$V$58) -> 8.1810872 | R46: =IF($I$12="","",Q46/$I$12) -> 4.7017743 | S46: =IF(W46<>"",IF(D46<>"",D46,($I$8-SUM($S$25:S45))*V46*W46/SUMPRODUCT($W46:$W$58,$V46:$V$58)),"") -> 29561 | T46: =IF(W46<>"",IF(E46<>"",E46,($I$9-SUM($T$25:T45))*V46*W46/SUMPRODUCT($W46:$W$58,$V46:$V$58)),"") -> 5 | U46: =IF(W46<>"",IF($I$12<>"",IF(G46<>"",G46,($I$9/$I$12-SUM($U$25:U45))*V46*W46/SUMPRODUCT($W46:$W$58,$V46:$V$58)),""),"") -> 3 | V46: 1.2 | W46: 1.2
A47: 23 | B47: 46022 | C47: ср | D47: =17490+21876 -> 39366 | E47: 5 | F47: =IF(AND(E47<>"",E47<>0),D47/E47,"") -> 7873.2 | G47: 2 | H47: =IF(AND(G47<>"",G47<>0),D47/G47,"") -> 19683 | I47: 20 | J47: =IF(AND(G47<>"",G47<>0),E47/G47,"") -> 2.5 | K47: 17490 | N47: =IF(AND(I47<>"",I47<>0),G47/I47,"") -> 0.1 | O47: =D47/P47 -> 0.88833782 | P47: =$I$8*V47*W47/SUMPRODUCT($W$25:$W$56,$V$25:$V$56) -> 44314.223 | Q47: =$I$9*V47*W47/SUMPRODUCT($W$25:$W$58,$V$25:$V$58) -> 5.6813106 | R47: =IF($I$12="","",Q47/$I$12) -> 3.265121 | S47: =IF(W47<>"",IF(D47<>"",D47,($I$8-SUM($S$25:S46))*V47*W47/SUMPRODUCT($W47:$W$58,$V47:$V$58)),"") -> 39366 | T47: =IF(W47<>"",IF(E47<>"",E47,($I$9-SUM($T$25:T46))*V47*W47/SUMPRODUCT($W47:$W$58,$V47:$V$58)),"") -> 5 | U47: =IF(W47<>"",IF($I$12<>"",IF(G47<>"",G47,($I$9/$I$12-SUM($U$25:U46))*V47*W47/SUMPRODUCT($W47:$W$58,$V47:$V$58)),""),"") -> 2 | V47: 1 | W47: 1
F48: =IF(AND(E48<>"",E48<>0),D48/E48,"") | H48: =IF(AND(G48<>"",G48<>0),D48/G48,"") | J48: =IF(AND(G48<>"",G48<>0),E48/G48,"") | N48: =IF(AND(I48<>"",I48<>0),G48/I48,"") | O48: =D48/P48 -> #DIV/0! | P48: =$I$8*V48*W48/SUMPRODUCT($W$25:$W$56,$V$25:$V$56) -> 0 | Q48: =$I$9*V48*W48/SUMPRODUCT($W$25:$W$58,$V$25:$V$58) -> 0 | R48: =IF($I$12="","",Q48/$I$12) -> 0 | S48: =IF(W48<>"",IF(D48<>"",D48,($I$8-SUM($S$25:S47))*V48*W48/SUMPRODUCT($W48:$W$58,$V48:$V$58)),"") | T48: =IF(W48<>"",IF(E48<>"",E48,($I$9-SUM($T$25:T47))*V48*W48/SUMPRODUCT($W48:$W$58,$V48:$V$58)),"") | U48: =IF(W48<>"",IF($I$12<>"",IF(G48<>"",G48,($I$9/$I$12-SUM($U$25:U47))*V48*W48/SUMPRODUCT($W48:$W$58,$V48:$V$58)),""),"")
F49: =IF(AND(E49<>"",E49<>0),D49/E49,"") | H49: =IF(AND(G49<>"",G49<>0),D49/G49,"") | J49: =IF(AND(G49<>"",G49<>0),E49/G49,"") | N49: =IF(AND(I49<>"",I49<>0),G49/I49,"") | O49: =D49/P49 -> #DIV/0! | P49: =$I$8*V49*W49/SUMPRODUCT($W$25:$W$56,$V$25:$V$56) -> 0 | Q49: =$I$9*V49*W49/SUMPRODUCT($W$25:$W$58,$V$25:$V$58) -> 0 | R49: =IF($I$12="","",Q49/$I$12) -> 0 | S49: =IF(W49<>"",IF(D49<>"",D49,($I$8-SUM($S$25:S48))*V49*W49/SUMPRODUCT($W49:$W$58,$V49:$V$58)),"") | T49: =IF(W49<>"",IF(E49<>"",E49,($I$9-SUM($T$25:T48))*V49*W49/SUMPRODUCT($W49:$W$58,$V49:$V$58)),"") | U49: =IF(W49<>"",IF($I$12<>"",IF(G49<>"",G49,($I$9/$I$12-SUM($U$25:U48))*V49*W49/SUMPRODUCT($W49:$W$58,$V49:$V$58)),""),"")
F50: =IF(AND(E50<>"",E50<>0),D50/E50,"") | H50: =IF(AND(G50<>"",G50<>0),D50/G50,"") | J50: =IF(AND(G50<>"",G50<>0),E50/G50,"") | N50: =IF(AND(I50<>"",I50<>0),G50/I50,"") | O50: =D50/P50 -> #DIV/0! | P50: =$I$8*V50*W50/SUMPRODUCT($W$25:$W$56,$V$25:$V$56) -> 0 | Q50: =$I$9*V50*W50/SUMPRODUCT($W$25:$W$58,$V$25:$V$58) -> 0 | R50: =IF($I$12="","",Q50/$I$12) -> 0 | S50: =IF(W50<>"",IF(D50<>"",D50,($I$8-SUM($S$25:S49))*V50*W50/SUMPRODUCT($W50:$W$58,$V50:$V$58)),"") | T50: =IF(W50<>"",IF(E50<>"",E50,($I$9-SUM($T$25:T49))*V50*W50/SUMPRODUCT($W50:$W$58,$V50:$V$58)),"") | U50: =IF(W50<>"",IF($I$12<>"",IF(G50<>"",G50,($I$9/$I$12-SUM($U$25:U49))*V50*W50/SUMPRODUCT($W50:$W$58,$V50:$V$58)),""),"")
F51: =IF(AND(E51<>"",E51<>0),D51/E51,"") | H51: =IF(AND(G51<>"",G51<>0),D51/G51,"") | J51: =IF(AND(G51<>"",G51<>0),E51/G51,"") | N51: =IF(AND(I51<>"",I51<>0),G51/I51,"") | O51: =D51/P51 -> #DIV/0! | P51: =$I$8*V51*W51/SUMPRODUCT($W$25:$W$56,$V$25:$V$56) -> 0 | Q51: =$I$9*V51*W51/SUMPRODUCT($W$25:$W$58,$V$25:$V$58) -> 0 | R51: =IF($I$12="","",Q51/$I$12) -> 0 | S51: =IF(W51<>"",IF(D51<>"",D51,($I$8-SUM($S$25:S50))*V51*W51/SUMPRODUCT($W51:$W$58,$V51:$V$58)),"") | T51: =IF(W51<>"",IF(E51<>"",E51,($I$9-SUM($T$25:T50))*V51*W51/SUMPRODUCT($W51:$W$58,$V51:$V$58)),"") | U51: =IF(W51<>"",IF($I$12<>"",IF(G51<>"",G51,($I$9/$I$12-SUM($U$25:U50))*V51*W51/SUMPRODUCT($W51:$W$58,$V51:$V$58)),""),"")
F52: =IF(AND(E52<>"",E52<>0),D52/E52,"") | H52: =IF(AND(G52<>"",G52<>0),D52/G52,"") | J52: =IF(AND(G52<>"",G52<>0),E52/G52,"") | N52: =IF(AND(I52<>"",I52<>0),G52/I52,"") | O52: =D52/P52 -> #DIV/0! | P52: =$I$8*V52*W52/SUMPRODUCT($W$25:$W$56,$V$25:$V$56) -> 0 | Q52: =$I$9*V52*W52/SUMPRODUCT($W$25:$W$58,$V$25:$V$58) -> 0 | R52: =IF($I$12="","",Q52/$I$12) -> 0 | S52: =IF(W52<>"",IF(D52<>"",D52,($I$8-SUM($S$25:S51))*V52*W52/SUMPRODUCT($W52:$W$58,$V52:$V$58)),"") | T52: =IF(W52<>"",IF(E52<>"",E52,($I$9-SUM($T$25:T51))*V52*W52/SUMPRODUCT($W52:$W$58,$V52:$V$58)),"") | U52: =IF(W52<>"",IF($I$12<>"",IF(G52<>"",G52,($I$9/$I$12-SUM($U$25:U51))*V52*W52/SUMPRODUCT($W52:$W$58,$V52:$V$58)),""),"")
F53: =IF(AND(E53<>"",E53<>0),D53/E53,"") | H53: =IF(AND(G53<>"",G53<>0),D53/G53,"") | J53: =IF(AND(G53<>"",G53<>0),E53/G53,"") | N53: =IF(AND(I53<>"",I53<>0),G53/I53,"") | O53: =D53/P53 -> #DIV/0! | P53: =$I$8*V53*W53/SUMPRODUCT($W$25:$W$56,$V$25:$V$56) -> 0 | Q53: =$I$9*V53*W53/SUMPRODUCT($W$25:$W$58,$V$25:$V$58) -> 0 | R53: =IF($I$12="","",Q53/$I$12) -> 0 | S53: =IF(W53<>"",IF(D53<>"",D53,($I$8-SUM($S$25:S52))*V53*W53/SUMPRODUCT($W53:$W$58,$V53:$V$58)),"") | T53: =IF(W53<>"",IF(E53<>"",E53,($I$9-SUM($T$25:T52))*V53*W53/SUMPRODUCT($W53:$W$58,$V53:$V$58)),"") | U53: =IF(W53<>"",IF($I$12<>"",IF(G53<>"",G53,($I$9/$I$12-SUM($U$25:U52))*V53*W53/SUMPRODUCT($W53:$W$58,$V53:$V$58)),""),"")
F54: =IF(AND(E54<>"",E54<>0),D54/E54,"") | H54: =IF(AND(G54<>"",G54<>0),D54/G54,"") | J54: =IF(AND(G54<>"",G54<>0),E54/G54,"") | N54: =IF(AND(I54<>"",I54<>0),G54/I54,"") | O54: =D54/P54 -> #DIV/0! | P54: =$I$8*V54*W54/SUMPRODUCT($W$25:$W$56,$V$25:$V$56) -> 0 | Q54: =$I$9*V54*W54/SUMPRODUCT($W$25:$W$58,$V$25:$V$58) -> 0 | R54: =IF($I$12="","",Q54/$I$12) -> 0 | S54: =IF(W54<>"",IF(D54<>"",D54,($I$8-SUM($S$25:S50))*V54*W54/SUMPRODUCT($W54:$W$58,$V54:$V$58)),"") | T54: =IF(W54<>"",IF(E54<>"",E54,($I$9-SUM($T$25:T50))*V54*W54/SUMPRODUCT($W54:$W$58,$V54:$V$58)),"") | U54: =IF(W54<>"",IF($I$12<>"",IF(G54<>"",G54,($I$9/$I$12-SUM($U$25:U50))*V54*W54/SUMPRODUCT($W54:$W$58,$V54:$V$58)),""),"")
F55: =IF(AND(E55<>"",E55<>0),D55/E55,"") | H55: =IF(AND(G55<>"",G55<>0),D55/G55,"") | J55: =IF(AND(G55<>"",G55<>0),E55/G55,"") | N55: =IF(AND(I55<>"",I55<>0),G55/I55,"") | O55: =D55/P55 -> #DIV/0! | P55: =$I$8*V55*W55/SUMPRODUCT($W$25:$W$56,$V$25:$V$56) -> 0 | Q55: =$I$9*V55*W55/SUMPRODUCT($W$25:$W$58,$V$25:$V$58) -> 0 | R55: =IF($I$12="","",Q55/$I$12) -> 0 | S55: =IF(W55<>"",IF(D55<>"",D55,($I$8-SUM($S$25:S54))*V55*W55/SUMPRODUCT($W55:$W$58,$V55:$V$58)),"") | T55: =IF(W55<>"",IF(E55<>"",E55,($I$9-SUM($T$25:T54))*V55*W55/SUMPRODUCT($W55:$W$58,$V55:$V$58)),"") | U55: =IF(W55<>"",IF($I$12<>"",IF(G55<>"",G55,($I$9/$I$12-SUM($U$25:U54))*V55*W55/SUMPRODUCT($W55:$W$58,$V55:$V$58)),""),"")
F56: =IF(AND(E56<>"",E56<>0),D56/E56,"") | H56: =IF(AND(G56<>"",G56<>0),D56/G56,"") | J56: =IF(AND(G56<>"",G56<>0),E56/G56,"") | N56: =IF(AND(I56<>"",I56<>0),G56/I56,"") | O56: =D56/P56 -> #DIV/0! | P56: =$I$8*V56*W56/SUMPRODUCT($W$25:$W$56,$V$25:$V$56) -> 0 | Q56: =$I$9*V56*W56/SUMPRODUCT($W$25:$W$58,$V$25:$V$58) -> 0 | R56: =IF($I$12="","",Q56/$I$12) -> 0 | S56: =IF(W56<>"",IF(D56<>"",D56,($I$8-SUM($S$25:S55))*V56*W56/SUMPRODUCT($W56:$W$58,$V56:$V$58)),"") | T56: =IF(W56<>"",IF(E56<>"",E56,($I$9-SUM($T$25:T55))*V56*W56/SUMPRODUCT($W56:$W$58,$V56:$V$58)),"") | U56: =IF(W56<>"",IF($I$12<>"",IF(G56<>"",G56,($I$9/$I$12-SUM($U$25:U55))*V56*W56/SUMPRODUCT($W56:$W$58,$V56:$V$58)),""),"")
D57: =SUM(D25:D56) -> 280692.7 | E57: =SUM(E25:E56) -> 34 | F57: =IF(AND(E57<>"",E57<>0),D57/E57,"") -> 8255.6676 | G57: =SUM(G25:G56) -> 19 | H57: =IF(AND(G57<>"",G57<>0),D57/G57,"") -> 14773.3 | I57: =SUM(I25:I56) -> 257 | J57: =IF(AND(G57<>"",G57<>0),E57/G57,"") -> 1.7894737 | K57: =SUM(K25:K56) -> 47970 | L57: =SUM(L25:L56) -> 0 | M57: =SUM(M25:M56) -> 13793 | N57: =IF(AND(I57<>"",I57<>0),G57/I57,"") -> 0.073929961 | O57: =D57/P57 -> 0.27527791 | P57: =SUM(P25:P56) -> 1019670.3 | Q57: =SUM(Q25:Q55) -> 130.72696 | R57: =SUM(R25:R55) -> 75.130435 | S57: =SUM(S25:S56) -> 834964.22 | T57: =SUM(T25:T55) -> 106.01759 | U57: =SUM(U25:U55) -> 60.512473

Sheet Доп сотрудник
B1: =TODAY()-1 -> 46060
B2: (отчетная дата) | J2: ЕЖЕДНЕВНЫЙ ОТЧЕТ О ПРОДАЖАХ
B3: Осталось до выполнения плана!!! | J3: Доп сотрудник
C4: =I8-D50 -> 1110307.6 | E4: =IF(I8<>0,C4/I8,0) -> 1
F6: Целевые показатели
F7: Показатель | I7: План | J7: Факт | K7: % выполнения | L7: Прогноз выполнения | M7: % выполнения по прогнозу | N7: Отклонение | O7: Факт аналогичного месяца прошлого года | P7: Отклонение LFL
F8: Выручка | I8: ='Ялта, Ленина, 18'!I8/График!AJ31*График!AJ28 -> 1110307.6 | J8: =D57 -> 0 | K8: =IF(AND(I8<>"",I8<>0,J8<>""),J8/I8,"") -> 0 | L8: =IF(SUMIF($D$25:$D$56,">=0",$P$25:$P$56)<>0,I8*D57/SUMIF($D$25:$D$56,">=0",$P$25:$P$56),0) -> 0 | M8: =IF(AND(I8<>"",I8<>0,L8<>"",L8<>0),L8/I8,"") | N8: =IF(AND(J8<>0,J8<>"",I8<>0,I8<>""),L8-I8,"") | P8: =IF(AND(O8<>"",O8<>0,L8<>"",L8<>0),-O8+L8,"") | Q8: =IF(AND(P8<>"",P8<>0,O8<>0,O8<>""),P8/O8,"")
F9: Кол-во изделий | I9: =I8/I11 -> 142.34713 | J9: =E57 -> 0 | K9: =IF(AND(I9<>"",I9<>0,J9<>""),J9/I9,"") -> 0 | L9: =IF(SUMIF($E$25:$E$54,">=0",$Q$25:$Q$54)<>0,I9*E57/SUMIF($E$25:$E$54,">=0",$Q$25:$Q$54),0) -> 0 | M9: =IF(AND(I9<>"",I9<>0,L9<>"",L9<>0),L9/I9,"") | N9: =IF(AND(J9<>0,J9<>"",I9<>0,I9<>""),L9-I9,"") | O9: =O8/O11 -> #DIV/0! | P9: =IF(AND(O9<>"",O9<>0,L9<>"",L9<>0),-O9+L9,"") -> #DIV/0! | Q9: =IF(AND(P9<>"",P9<>0,O9<>0,O9<>""),P9/O9,"") -> #DIV/0!
F10: Средний чек | I10: =I11*I12 -> 13572 | J10: =H57 | K10: =IF(AND(I10<>"",I10<>0,J10<>""),J10/I10,"") | L10: =J10 | M10: =IF(AND(I10<>"",I10<>0,L10<>"",L10<>0),L10/I10,"") | N10: =IF(AND(J10<>0,J10<>"",I10<>0,I10<>""),L10-I10,"") | O10: =O11*O12 -> 0 | P10: =IF(AND(O10<>"",O10<>0,L10<>"",L10<>0),-O10+L10,"") | Q10: =IF(AND(P10<>"",P10<>0,O10<>0,O10<>""),P10/O10,"") | S10: IS | V10: =M23 -> Agafi
F11: Средняя стоимость изделия | I11: ='Ялта, Ленина, 18'!I11 -> 7800 | J11: =F57 | K11: =IF(AND(I11<>"",I11<>0,J11<>""),J11/I11,"") | L11: =IF(L9>0,L8/L9,"") | M11: =IF(AND(I11<>"",I11<>0,L11<>"",L11<>0),L11/I11,"") | N11: =IF(AND(J11<>0,J11<>"",I11<>0,I11<>""),L11-I11,"") | P11: =IF(AND(O11<>"",O11<>0,L11<>"",L11<>0),-O11+L11,"") | Q11: =IF(AND(P11<>"",P11<>0,O11<>0,O11<>""),P11/O11,"")
F12: Длина чека | I12: ='Ялта, Ленина, 18'!I12 -> 1.74 | J12: =J57 | K12: =IF(AND(I12<>"",I12<>0,J12<>""),J12/I12,"") | L12: =J12 | M12: =IF(AND(I12<>"",I12<>0,L12<>"",L12<>0),L12/I12,"") | N12: =IF(AND(J12<>0,J12<>"",I12<>0,I12<>""),L12-I12,"") | P12: =IF(AND(O12<>"",O12<>0,L12<>"",L12<>0),-O12+L12,"") | Q12: =IF(AND(P12<>"",P12<>0,O12<>0,O12<>""),P12/O12,"") | S12: ='Ялта, Ленина, 18'!U12*График!AJ28/График!AJ31 -> 217304.35 | T12: =L57 -> 0 | U12: =S12-T12 -> 217304.35 | V12: ='Ялта, Ленина, 18'!X12/График!AJ31*График!AJ28 -> 204521.74 | W12: =M57 -> 0 | X12: =V12-W12 -> 204521.74
F13: Кол-во чеков | I13: =IF(I12<>0,I9/I12,"") -> 81.808696 | J13: =G57 -> 0 | K13: =IF(AND(I13<>"",I13<>0,J13<>""),J13/I13,"") -> 0 | L13: =IF(SUMIF($G$25:$G$54,">=0",$R$25:$R$54)<>0,I13*G57/SUMIF($G$25:$G$54,">=0",$R$25:$R$54),"") | M13: =IF(AND(I13<>"",I13<>0,L13<>"",L13<>0),L13/I13,"") | N13: =IF(AND(J13<>0,J13<>"",I13<>0,I13<>""),L13-I13,"") | P13: =IF(AND(O13<>"",O13<>0,L13<>"",L13<>0),-O13+L13,"") | Q13: =IF(AND(P13<>"",P13<>0,O13<>0,O13<>""),P13/O13,"") | S13: =T12/S12 -> 0 | T13: =S13/J14*I14 -> #DIV/0! | V13: =W12/V12 -> 0 | W13: =V13/J14*I14 -> #DIV/0!
F14: Кол-во смен план/отработано | I14: =График!AI28 -> 23 | K14: =IF(AND(I14<>"",I14<>0,J14<>""),J14/I14,"") | L14: =I14 -> 23 | M14: =IF(AND(I14<>"",I14<>0,L14<>"",L14<>0),L14/I14,"") -> 1 | N14: =IF(AND(J14<>0,J14<>"",I14<>0,I14<>""),L14-I14,"") | P14: =IF(AND(O14<>"",O14<>0,L14<>"",L14<>0),-O14+L14,"") | Q14: =IF(AND(P14<>"",P14<>0,O14<>0,O14<>""),P14/O14,"")
F15: Средние продажи в смену | I15: ='Ялта, Ленина, 18'!I15 -> 84058.839 | J15: =J8/J14 -> #DIV/0! | K15: =IF(AND(I15<>"",I15<>0,J15<>""),J15/I15,"") -> #DIV/0! | L15: =J15 -> #DIV/0! | M15: =IF(AND(I15<>"",I15<>0,L15<>"",L15<>0),L15/I15,"") -> #DIV/0! | N15: =IF(AND(J15<>0,J15<>"",I15<>0,I15<>""),L15-I15,"") -> #DIV/0! | P15: =IF(AND(O15<>"",O15<>0,L15<>"",L15<>0),-O15+L15,"") -> #DIV/0! | Q15: =IF(AND(P15<>"",P15<>0,O15<>0,O15<>""),P15/O15,"") -> #DIV/0!
F16: Отставание/Перевыполнение | J16: =J8-I15*J14 -> 0 | K16: =IF(AND(I16<>"",I16<>0,J16<>""),J16/I16,"") | L16: =J16 -> 0 | M16: =IF(AND(I16<>"",I16<>0,L16<>"",L16<>0),L16/I16,"") | N16: =IF(AND(J16<>0,J16<>"",I16<>0,I16<>""),L16-I16,"") | P16: =IF(AND(O16<>"",O16<>0,L16<>"",L16<>0),-O16+L16,"") | Q16: =IF(AND(P16<>"",P16<>0,O16<>0,O16<>""),P16/O16,"") | S16: UNOde50
F17: Трафик | I17: ='Ялта, Ленина, 18'!I17/График!AJ31*График!AJ28 -> 681.73913 | J17: =I57 -> 0 | K17: =IF(AND(I17<>"",I17<>0,J17<>""),J17/I17,"") -> 0 | L17: =J17/J14*I14 -> #DIV/0! | M17: =IF(AND(I17<>"",I17<>0,L17<>"",L17<>0),L17/I17,"") -> #DIV/0! | N17: =IF(AND(J17<>0,J17<>"",I17<>0,I17<>""),L17-I17,"") | P17: =IF(AND(O17<>"",O17<>0,L17<>"",L17<>0),-O17+L17,"") -> #DIV/0! | Q17: =IF(AND(P17<>"",P17<>0,O17<>0,O17<>""),P17/O17,"") -> #DIV/0!
K18: =IF(AND(I18<>"",I18<>0,J18<>""),J18/I18,"") | L18: =J18 -> 0 | M18: =IF(AND(I18<>"",I18<>0,L18<>"",L18<>0),L18/I18,"") | N18: =IF(AND(J18<>0,J18<>"",I18<>0,I18<>""),L18-I18,"") | O18: 0 | P18: =IF(AND(O18<>"",O18<>0,L18<>"",L18<>0),-O18+L18,"") | Q18: =IF(AND(P18<>"",P18<>0,O18<>0,O18<>""),P18/O18,"") | S18: ='Ялта, Ленина, 18'!U18*График!AJ28/График!AJ31 -> 434608.7 | T18: =K57 -> 0
K19: =IF(AND(I19<>"",I19<>0,J19<>""),J19/I19,"") | L19: =J19 -> 0 | M19: =IF(AND(I19<>"",I19<>0,L19<>"",L19<>0),L19/I19,"") | N19: =IF(AND(J19<>0,J19<>"",I19<>0,I19<>""),L19-I19,"") | O19: 0 | P19: =IF(AND(O19<>"",O19<>0,L19<>"",L19<>0),-O19+L19,"") | Q19: =IF(AND(P19<>"",P19<>0,O19<>0,O19<>""),P19/O19,"") | S19: =T18/S18 -> 0 | T19: =S19/J14*I14 -> #DIV/0!
F20: Конверсия план/факт | I20: ='Ялта, Ленина, 18'!I20 -> 0.12 | J20: =N57 | K20: =J20/I20 -> #VALUE! | L20: =IF(AND(K8<>0,I14<>0,I57<>0),(I57*N57+(I57/K8-I57)*I20)/(I57/K8),0) -> 0 | M20: =IF(AND(I20<>"",I20<>0,L20<>"",L20<>0),L20/I20,"") | N20: =IF(AND(J20<>0,J20<>"",I20<>0,I20<>""),L20-I20,"") | P20: =IF(AND(O20<>"",O20<>0,L20<>"",L20<>0),-O20+L20,"") | Q20: =IF(AND(P20<>"",P20<>0,O20<>0,O20<>""),P20/O20,"")
B22: Факт продаж за месяц | O22: % выполнения дневного плана | P22: Раcпределение плана по дням
B23: Дата | C23: День недели | D23: Выручка (руб) | E23: Кол-во единиц (шт.) | F23: Средняя стоимость изделия (руб.) | G23: Количество чеков (шт.) | H23: Средняя сумма чека (руб.) | I23: Трафик | J23: Длина чека (шт.) | K23: UNOde50 | L23: IS | M23: Agafi | N23: Конверсия (%) | P23: выручка, план | Q23: кол-во ед, план | R23: Кол-во чеков, план | S23: выручка, скорректир.план | T23: кол-во ед, скорр. план | U23: кол-во чеков, скорр. план | V23: Коэфф. Дня Недели | W23: Специфика месяца
B24: 1 | C24: 2 | D24: 3 | E24: в | F24: 5 | G24: 6 | H24: 7 | I24: 8 | J24: 9 | K24: 10 | L24: 11 | M24: 12 | N24: 13 | P24: 1 | Q24: 2 | R24: 3 | S24: 4 | T24: 5 | U24: 6 | V24: 10 | W24: 11
A25: 1 | F25: =IF(AND(E25<>"",E25<>0),D25/E25,"") | H25: =IF(AND(G25<>"",G25<>0),D25/G25,"") | J25: =IF(AND(G25<>"",G25<>0),E25/G25,"") | N25: =IF(AND(I25<>"",I25<>0),G25/I25,"") | O25: =D25/P25 -> 0 | P25: =$I$8*V25*W25/SUMPRODUCT($W$25:$W$56,$V$25:$V$56) -> 44412.305 | Q25: =$I$9*V25*W25/SUMPRODUCT($W$25:$W$56,$V$25:$V$56) -> 5.6938852 | R25: =IF($I$12="","",Q25/$I$12) -> 3.2723478 | S25: =IF(D25<>"",D25,P25) -> 44412.305 | T25: =IF(E25<>"",E25,Q25) -> 5.6938852 | U25: =IF(G25<>"",G25,R25) -> 3.2723478 | V25: 1 | W25: 1
A26: 2 | F26: =IF(AND(E26<>"",E26<>0),D26/E26,"") | H26: =IF(AND(G26<>"",G26<>0),D26/G26,"") | J26: =IF(AND(G26<>"",G26<>0),E26/G26,"") | N26: =IF(AND(I26<>"",I26<>0),G26/I26,"") | O26: =D26/P26 -> 0 | P26: =$I$8*V26*W26/SUMPRODUCT($W$25:$W$56,$V$25:$V$56) -> 44412.305 | Q26: =$I$9*V26*W26/SUMPRODUCT($W$25:$W$58,$V$25:$V$58) -> 5.6938852 | R26: =IF($I$12="","",Q26/$I$12) -> 3.2723478 | S26: =IF(W26<>"",IF(D26<>"",D26,($I$8-SUM($S$25:S25))*V26*W26/SUMPRODUCT($W26:$W$56,$V26:$V$56)),"") -> 44412.305 | T26: =IF(W26<>"",IF(E26<>"",E26,($I$9-SUM($T$25:T25))*V26*W26/SUMPRODUCT($W26:$W$55,$V26:$V$55)),"") -> 5.6938852 | U26: =IF(W26<>"",IF($I$12<>"",IF(G26<>"",G26,($I$9/$I$12-SUM($U$25:U25))*V26*W26/SUMPRODUCT($W26:$W$55,$V26:$V$55)),""),"") -> 3.2723478 | V26: 1 | W26: 1
A27: 3 | F27: =IF(AND(E27<>"",E27<>0),D27/E27,"") | H27: =IF(AND(G27<>"",G27<>0),D27/G27,"") | J27: =IF(AND(G27<>"",G27<>0),E27/G27,"") | N27: =IF(AND(I27<>"",I27<>0),G27/I27,"") | O27: =D27/P27 -> 0 | P27: =$I$8*V27*W27/SUMPRODUCT($W$25:$W$56,$V$25:$V$56) -> 44412.305 | Q27: =$I$9*V27*W27/SUMPRODUCT($W$25:$W$58,$V$25:$V$58) -> 5.6938852 | R27: =IF($I$12="","",Q27/$I$12) -> 3.2723478 | S27: =IF(W27<>"",IF(D27<>"",D27,($I$8-SUM($S$25:S26))*V27*W27/SUMPRODUCT($W27:$W$58,$V27:$V$58)),"") -> 44412.305 | T27: =IF(W27<>"",IF(E27<>"",E27,($I$9-SUM($T$25:T26))*V27*W27/SUMPRODUCT($W27:$W$55,$V27:$V$55)),"") -> 5.6938852 | U27: =IF(W27<>"",IF($I$12<>"",IF(G27<>"",G27,($I$9/$I$12-SUM($U$25:U26))*V27*W27/SUMPRODUCT($W27:$W$55,$V27:$V$55)),""),"") -> 3.2723478 | V27: 1 | W27: 1
A28: 4 | F28: =IF(AND(E28<>"",E28<>0),D28/E28,"") | H28: =IF(AND(G28<>"",G28<>0),D28/G28,"") | J28: =IF(AND(G28<>"",G28<>0),E28/G28,"") | N28: =IF(AND(I28<>"",I28<>0),G28/I28,"") | O28: =D28/P28 -> 0 | P28: =$I$8*V28*W28/SUMPRODUCT($W$25:$W$56,$V$25:$V$56) -> 44412.305 | Q28: =$I$9*V28*W28/SUMPRODUCT($W$25:$W$58,$V$25:$V$58) -> 5.6938852 | R28: =IF($I$12="","",Q28/$I$12) -> 3.2723478 | S28: =IF(W28<>"",IF(D28<>"",D28,($I$8-SUM($S$25:S27))*V28*W28/SUMPRODUCT($W28:$W$58,$V28:$V$58)),"") -> 44412.305 | T28: =IF(W28<>"",IF(E28<>"",E28,($I$9-SUM($T$25:T27))*V28*W28/SUMPRODUCT($W28:$W$58,$V28:$V$58)),"") -> 5.6938852 | U28: =IF(W28<>"",IF($I$12<>"",IF(G28<>"",G28,($I$9/$I$12-SUM($U$25:U27))*V28*W28/SUMPRODUCT($W28:$W$58,$V28:$V$58)),""),"") -> 3.2723478 | V28: 1 | W28: 1
A29: 5 | F29: =IF(AND(E29<>"",E29<>0),D29/E29,"") | H29: =IF(AND(G29<>"",G29<>0),D29/G29,"") | J29: =IF(AND(G29<>"",G29<>0),E29/G29,"") | N29: =IF(AND(I29<>"",I29<>0),G29/I29,"") | O29: =D29/P29 -> 0 | P29: =$I$8*V29*W29/SUMPRODUCT($W$25:$W$56,$V$25:$V$56) -> 44412.305 | Q29: =$I$9*V29*W29/SUMPRODUCT($W$25:$W$58,$V$25:$V$58) -> 5.6938852 | R29: =IF($I$12="","",Q29/$I$12) -> 3.2723478 | S29: =IF(W29<>"",IF(D29<>"",D29,($I$8-SUM($S$25:S28))*V29*W29/SUMPRODUCT($W29:$W$58,$V29:$V$58)),"") -> 44412.305 | T29: =IF(W29<>"",IF(E29<>"",E29,($I$9-SUM($T$25:T28))*V29*W29/SUMPRODUCT($W29:$W$58,$V29:$V$58)),"") -> 5.6938852 | U29: =IF(W29<>"",IF($I$12<>"",IF(G29<>"",G29,($I$9/$I$12-SUM($U$25:U28))*V29*W29/SUMPRODUCT($W29:$W$58,$V29:$V$58)),""),"") -> 3.2723478 | V29: 1 | W29: 1
A30: 6 | F30: =IF(AND(E30<>"",E30<>0),D30/E30,"") | H30: =IF(AND(G30<>"",G30<>0),D30/G30,"") | J30: =IF(AND(G30<>"",G30<>0),E30/G30,"") | N30: =IF(AND(I30<>"",I30<>0),G30/I30,"") | O30: =D30/P30 -> 0 | P30: =$I$8*V30*W30/SUMPRODUCT($W$25:$W$56,$V$25:$V$56) -> 44412.305 | Q30: =$I$9*V30*W30/SUMPRODUCT($W$25:$W$58,$V$25:$V$58) -> 5.6938852 | R30: =IF($I$12="","",Q30/$I$12) -> 3.2723478 | S30: =IF(W30<>"",IF(D30<>"",D30,($I$8-SUM($S$25:S29))*V30*W30/SUMPRODUCT($W30:$W$58,$V30:$V$58)),"") -> 44412.305 | T30: =IF(W30<>"",IF(E30<>"",E30,($I$9-SUM($T$25:T29))*V30*W30/SUMPRODUCT($W30:$W$58,$V30:$V$58)),"") -> 5.6938852 | U30: =IF(W30<>"",IF($I$12<>"",IF(G30<>"",G30,($I$9/$I$12-SUM($U$25:U29))*V30*W30/SUMPRODUCT($W30:$W$58,$V30:$V$58)),""),"") -> 3.2723478 | V30: 1 | W30: 1
A31: 7 | F31: =IF(AND(E31<>"",E31<>0),D31/E31,"") | H31: =IF(AND(G31<>"",G31<>0),D31/G31,"") | J31: =IF(AND(G31<>"",G31<>0),E31/G31,"") | N31: =IF(AND(I31<>"",I31<>0),G31/I31,"") | O31: =D31/P31 -> 0 | P31: =$I$8*V31*W31/SUMPRODUCT($W$25:$W$56,$V$25:$V$56) -> 44412.305 | Q31: =$I$9*V31*W31/SUMPRODUCT($W$25:$W$58,$V$25:$V$58) -> 5.6938852 | R31: =IF($I$12="","",Q31/$I$12) -> 3.2723478 | S31: =IF(W31<>"",IF(D31<>"",D31,($I$8-SUM($S$25:S30))*V31*W31/SUMPRODUCT($W31:$W$58,$V31:$V$58)),"") -> 44412.305 | T31: =IF(W31<>"",IF(E31<>"",E31,($I$9-SUM($T$25:T30))*V31*W31/SUMPRODUCT($W31:$W$58,$V31:$V$58)),"") -> 5.6938852 | U31: =IF(W31<>"",IF($I$12<>"",IF(G31<>"",G31,($I$9/$I$12-SUM($U$25:U30))*V31*W31/SUMPRODUCT($W31:$W$58,$V31:$V$58)),""),"") -> 3.2723478 | V31: 1 | W31: 1
A32: 8 | F32: =IF(AND(E32<>"",E32<>0),D32/E32,"") | H32: =IF(AND(G32<>"",G32<>0),D32/G32,"") | J32: =IF(AND(G32<>"",G32<>0),E32/G32,"") | N32: =IF(AND(I32<>"",I32<>0),G32/I32,"") | O32: =D32/P32 -> 0 | P32: =$I$8*V32*W32/SUMPRODUCT($W$25:$W$56,$V$25:$V$56) -> 44412.305 | Q32: =$I$9*V32*W32/SUMPRODUCT($W$25:$W$58,$V$25:$V$58) -> 5.6938852 | R32: =IF($I$12="","",Q32/$I$12) -> 3.2723478 | S32: =IF(W32<>"",IF(D32<>"",D32,($I$8-SUM($S$25:S31))*V32*W32/SUMPRODUCT($W32:$W$58,$V32:$V$58)),"") -> 44412.305 | T32: =IF(W32<>"",IF(E32<>"",E32,($I$9-SUM($T$25:T31))*V32*W32/SUMPRODUCT($W32:$W$58,$V32:$V$58)),"") -> 5.6938852 | U32: =IF(W32<>"",IF($I$12<>"",IF(G32<>"",G32,($I$9/$I$12-SUM($U$25:U31))*V32*W32/SUMPRODUCT($W32:$W$58,$V32:$V$58)),""),"") -> 3.2723478 | V32: 1 | W32: 1
A33: 9 | F33: =IF(AND(E33<>"",E33<>0),D33/E33,"") | H33: =IF(AND(G33<>"",G33<>0),D33/G33,"") | J33: =IF(AND(G33<>"",G33<>0),E33/G33,"") | N33: =IF(AND(I33<>"",I33<>0),G33/I33,"") | O33: =D33/P33 -> 0 | P33: =$I$8*V33*W33/SUMPRODUCT($W$25:$W$56,$V$25:$V$56) -> 44412.305 | Q33: =$I$9*V33*W33/SUMPRODUCT($W$25:$W$58,$V$25:$V$58) -> 5.6938852 | R33: =IF($I$12="","",Q33/$I$12) -> 3.2723478 | S33: =IF(W33<>"",IF(D33<>"",D33,($I$8-SUM($S$25:S32))*V33*W33/SUMPRODUCT($W33:$W$58,$V33:$V$58)),"") -> 44412.305 | T33: =IF(W33<>"",IF(E33<>"",E33,($I$9-SUM($T$25:T32))*V33*W33/SUMPRODUCT($W33:$W$58,$V33:$V$58)),"") -> 5.6938852 | U33: =IF(W33<>"",IF($I$12<>"",IF(G33<>"",G33,($I$9/$I$12-SUM($U$25:U32))*V33*W33/SUMPRODUCT($W33:$W$58,$V33:$V$58)),""),"") -> 3.2723478 | V33: 1 | W33: 1
A34: 10 | F34: =IF(AND(E34<>"",E34<>0),D34/E34,"") | H34: =IF(AND(G34<>"",G34<>0),D34/G34,"") | J34: =IF(AND(G34<>"",G34<>0),E34/G34,"") | N34: =IF(AND(I34<>"",I34<>0),G34/I34,"") | O34: =D34/P34 -> 0 | P34: =$I$8*V34*W34/SUMPRODUCT($W$25:$W$56,$V$25:$V$56) -> 44412.305 | Q34: =$I$9*V34*W34/SUMPRODUCT($W$25:$W$58,$V$25:$V$58) -> 5.6938852 | R34: =IF($I$12="","",Q34/$I$12) -> 3.2723478 | S34: =IF(W34<>"",IF(D34<>"",D34,($I$8-SUM($S$25:S33))*V34*W34/SUMPRODUCT($W34:$W$58,$V34:$V$58)),"") -> 44412.305 | T34: =IF(W34<>"",IF(E34<>"",E34,($I$9-SUM($T$25:T33))*V34*W34/SUMPRODUCT($W34:$W$58,$V34:$V$58)),"") -> 5.6938852 | U34: =IF(W34<>"",IF($I$12<>"",IF(G34<>"",G34,($I$9/$I$12-SUM($U$25:U33))*V34*W34/SUMPRODUCT($W34:$W$58,$V34:$V$58)),""),"") -> 3.2723478 | V34: 1 | W34: 1
A35: 11 | F35: =IF(AND(E35<>"",E35<>0),D35/E35,"") | H35: =IF(AND(G35<>"",G35<>0),D35/G35,"") | J35: =IF(AND(G35<>"",G35<>0),E35/G35,"") | N35: =IF(AND(I35<>"",I35<>0),G35/I35,"") | O35: =D35/P35 -> 0 | P35: =$I$8*V35*W35/SUMPRODUCT($W$25:$W$56,$V$25:$V$56) -> 44412.305 | Q35: =$I$9*V35*W35/SUMPRODUCT($W$25:$W$58,$V$25:$V$58) -> 5.6938852 | R35: =IF($I$12="","",Q35/$I$12) -> 3.2723478 | S35: =IF(W35<>"",IF(D35<>"",D35,($I$8-SUM($S$25:S34))*V35*W35/SUMPRODUCT($W35:$W$58,$V35:$V$58)),"") -> 44412.305 | T35: =IF(W35<>"",IF(E34<>"",E34,($I$9-SUM($T$25:T34))*V35*W35/SUMPRODUCT($W35:$W$58,$V35:$V$58)),"") -> 5.6938852 | U35: =IF(W35<>"",IF($I$12<>"",IF(G35<>"",G35,($I$9/$I$12-SUM($U$25:U34))*V35*W35/SUMPRODUCT($W35:$W$58,$V35:$V$58)),""),"") -> 3.2723478 | V35: 1 | W35: 1
A36: 11 | F36: =IF(AND(E36<>"",E36<>0),D36/E36,"") | H36: =IF(AND(G36<>"",G36<>0),D36/G36,"") | J36: =IF(AND(G36<>"",G36<>0),E36/G36,"") | N36: =IF(AND(I36<>"",I36<>0),G36/I36,"") | O36: =D36/P36 -> 0 | P36: =$I$8*V36*W36/SUMPRODUCT($W$25:$W$56,$V$25:$V$56) -> 44412.305 | Q36: =$I$9*V36*W36/SUMPRODUCT($W$25:$W$58,$V$25:$V$58) -> 5.6938852 | R36: =IF($I$12="","",Q36/$I$12) -> 3.2723478 | S36: =IF(W36<>"",IF(D36<>"",D36,($I$8-SUM($S$25:S35))*V36*W36/SUMPRODUCT($W36:$W$58,$V36:$V$58)),"") -> 44412.305 | T36: =IF(W36<>"",IF(E35<>"",E35,($I$9-SUM($T$25:T35))*V36*W36/SUMPRODUCT($W36:$W$58,$V36:$V$58)),"") -> 5.6938852 | U36: =IF(W36<>"",IF($I$12<>"",IF(G36<>"",G36,($I$9/$I$12-SUM($U$25:U35))*V36*W36/SUMPRODUCT($W36:$W$58,$V36:$V$58)),""),"") -> 3.2723478 | V36: 1 | W36: 1
A37: 13 | F37: =IF(AND(E37<>"",E37<>0),D37/E37,"") | H37: =IF(AND(G37<>"",G37<>0),D37/G37,"") | J37: =IF(AND(G37<>"",G37<>0),E37/G37,"") | N37: =IF(AND(I37<>"",I37<>0),G37/I37,"") | O37: =D37/P37 -> 0 | P37: =$I$8*V37*W37/SUMPRODUCT($W$25:$W$56,$V$25:$V$56) -> 44412.305 | Q37: =$I$9*V37*W37/SUMPRODUCT($W$25:$W$58,$V$25:$V$58) -> 5.6938852 | R37: =IF($I$12="","",Q37/$I$12) -> 3.2723478 | S37: =IF(W37<>"",IF(D37<>"",D37,($I$8-SUM($S$25:S36))*V37*W37/SUMPRODUCT($W37:$W$58,$V37:$V$58)),"") -> 44412.305 | T37: =IF(W37<>"",IF(E37<>"",E37,($I$9-SUM($T$25:T36))*V37*W37/SUMPRODUCT($W37:$W$58,$V37:$V$58)),"") -> 5.6938852 | U37: =IF(W37<>"",IF($I$12<>"",IF(G37<>"",G37,($I$9/$I$12-SUM($U$25:U36))*V37*W37/SUMPRODUCT($W37:$W$58,$V37:$V$58)),""),"") -> 3.2723478 | V37: 1 | W37: 1
A38: 14 | F38: =IF(AND(E38<>"",E38<>0),D38/E38,"") | H38: =IF(AND(G38<>"",G38<>0),D38/G38,"") | J38: =IF(AND(G38<>"",G38<>0),E38/G38,"") | N38: =IF(AND(I38<>"",I38<>0),G38/I38,"") | O38: =D38/P38 -> 0 | P38: =$I$8*V38*W38/SUMPRODUCT($W$25:$W$56,$V$25:$V$56) -> 44412.305 | Q38: =$I$9*V38*W38/SUMPRODUCT($W$25:$W$58,$V$25:$V$58) -> 5.6938852 | R38: =IF($I$12="","",Q38/$I$12) -> 3.2723478 | S38: =IF(W38<>"",IF(D38<>"",D38,($I$8-SUM($S$25:S37))*V38*W38/SUMPRODUCT($W38:$W$58,$V38:$V$58)),"") -> 44412.305 | T38: =IF(W38<>"",IF(E38<>"",E38,($I$9-SUM($T$25:T37))*V38*W38/SUMPRODUCT($W38:$W$58,$V38:$V$58)),"") -> 5.6938852 | U38: =IF(W38<>"",IF($I$12<>"",IF(G38<>"",G38,($I$9/$I$12-SUM($U$25:U37))*V38*W38/SUMPRODUCT($W38:$W$58,$V38:$V$58)),""),"") -> 3.2723478 | V38: 1 | W38: 1
A39: 15 | F39: =IF(AND(E39<>"",E39<>0),D39/E39,"") | H39: =IF(AND(G39<>"",G39<>0),D39/G39,"") | J39: =IF(AND(G39<>"",G39<>0),E39/G39,"") | N39: =IF(AND(I39<>"",I39<>0),G39/I39,"") | O39: =D39/P39 -> 0 | P39: =$I$8*V39*W39/SUMPRODUCT($W$25:$W$56,$V$25:$V$56) -> 44412.305 | Q39: =$I$9*V39*W39/SUMPRODUCT($W$25:$W$58,$V$25:$V$58) -> 5.6938852 | R39: =IF($I$12="","",Q39/$I$12) -> 3.2723478 | S39: =IF(W39<>"",IF(D39<>"",D39,($I$8-SUM($S$25:S38))*V39*W39/SUMPRODUCT($W39:$W$58,$V39:$V$58)),"") -> 44412.305 | T39: =IF(W39<>"",IF(E39<>"",E39,($I$9-SUM($T$25:T38))*V39*W39/SUMPRODUCT($W39:$W$58,$V39:$V$58)),"") -> 5.6938852 | U39: =IF(W39<>"",IF($I$12<>"",IF(G39<>"",G39,($I$9/$I$12-SUM($U$25:U38))*V39*W39/SUMPRODUCT($W39:$W$58,$V39:$V$58)),""),"") -> 3.2723478 | V39: 1 | W39: 1
A40: 16 | F40: =IF(AND(E40<>"",E40<>0),D40/E40,"") | H40: =IF(AND(G40<>"",G40<>0),D40/G40,"") | J40: =IF(AND(G40<>"",G40<>0),E40/G40,"") | N40: =IF(AND(I40<>"",I40<>0),G40/I40,"") | O40: =D40/P40 -> 0 | P40: =$I$8*V40*W40/SUMPRODUCT($W$25:$W$56,$V$25:$V$56) -> 44412.305 | Q40: =$I$9*V40*W40/SUMPRODUCT($W$25:$W$58,$V$25:$V$58) -> 5.6938852 | R40: =IF($I$12="","",Q40/$I$12) -> 3.2723478 | S40: =IF(W40<>"",IF(D40<>"",D40,($I$8-SUM($S$25:S39))*V40*W40/SUMPRODUCT($W40:$W$58,$V40:$V$58)),"") -> 44412.305 | T40: =IF(W40<>"",IF(E40<>"",E40,($I$9-SUM($T$25:T39))*V40*W40/SUMPRODUCT($W40:$W$58,$V40:$V$58)),"") -> 5.6938852 | U40: =IF(W40<>"",IF($I$12<>"",IF(G40<>"",G40,($I$9/$I$12-SUM($U$25:U39))*V40*W40/SUMPRODUCT($W40:$W$58,$V40:$V$58)),""),"") -> 3.2723478 | V40: 1 | W40: 1
A41: 17 | F41: =IF(AND(E41<>"",E41<>0),D41/E41,"") | H41: =IF(AND(G41<>"",G41<>0),D41/G41,"") | J41: =IF(AND(G41<>"",G41<>0),E41/G41,"") | N41: =IF(AND(I41<>"",I41<>0),G41/I41,"") | O41: =D41/P41 -> 0 | P41: =$I$8*V41*W41/SUMPRODUCT($W$25:$W$56,$V$25:$V$56) -> 44412.305 | Q41: =$I$9*V41*W41/SUMPRODUCT($W$25:$W$58,$V$25:$V$58) -> 5.6938852 | R41: =IF($I$12="","",Q41/$I$12) -> 3.2723478 | S41: =IF(W41<>"",IF(D41<>"",D41,($I$8-SUM($S$25:S40))*V41*W41/SUMPRODUCT($W41:$W$58,$V41:$V$58)),"") -> 44412.305 | T41: =IF(W41<>"",IF(E41<>"",E41,($I$9-SUM($T$25:T40))*V41*W41/SUMPRODUCT($W41:$W$58,$V41:$V$58)),"") -> 5.6938852 | U41: =IF(W41<>"",IF($I$12<>"",IF(G41<>"",G41,($I$9/$I$12-SUM($U$25:U40))*V41*W41/SUMPRODUCT($W41:$W$58,$V41:$V$58)),""),"") -> 3.2723478 | V41: 1 | W41: 1
A42: 18 | F42: =IF(AND(E42<>"",E42<>0),D42/E42,"") | H42: =IF(AND(G42<>"",G42<>0),D42/G42,"") | J42: =IF(AND(G42<>"",G42<>0),E42/G42,"") | N42: =IF(AND(I42<>"",I42<>0),G42/I42,"") | O42: =D42/P42 -> 0 | P42: =$I$8*V42*W42/SUMPRODUCT($W$25:$W$56,$V$25:$V$56) -> 44412.305 | Q42: =$I$9*V42*W42/SUMPRODUCT($W$25:$W$58,$V$25:$V$58) -> 5.6938852 | R42: =IF($I$12="","",Q42/$I$12) -> 3.2723478 | S42: =IF(W42<>"",IF(D42<>"",D42,($I$8-SUM($S$25:S41))*V42*W42/SUMPRODUCT($W42:$W$58,$V42:$V$58)),"") -> 44412.305 | T42: =IF(W42<>"",IF(E42<>"",E42,($I$9-SUM($T$25:T41))*V42*W42/SUMPRODUCT($W42:$W$58,$V42:$V$58)),"") -> 5.6938852 | U42: =IF(W42<>"",IF($I$12<>"",IF(G42<>"",G42,($I$9/$I$12-SUM($U$25:U41))*V42*W42/SUMPRODUCT($W42:$W$58,$V42:$V$58)),""),"") -> 3.2723478 | V42: 1 | W42: 1
A43: 19 | F43: =IF(AND(E43<>"",E43<>0),D43/E43,"") | H43: =IF(AND(G43<>"",G43<>0),D43/G43,"") | J43: =IF(AND(G43<>"",G43<>0),E43/G43,"") | N43: =IF(AND(I43<>"",I43<>0),G43/I43,"") | O43: =D43/P43 -> 0 | P43: =$I$8*V43*W43/SUMPRODUCT($W$25:$W$56,$V$25:$V$56) -> 44412.305 | Q43: =$I$9*V43*W43/SUMPRODUCT($W$25:$W$58,$V$25:$V$58) -> 5.6938852 | R43: =IF($I$12="","",Q43/$I$12) -> 3.2723478 | S43: =IF(W43<>"",IF(D43<>"",D43,($I$8-SUM($S$25:S42))*V43*W43/SUMPRODUCT($W43:$W$58,$V43:$V$58)),"") -> 44412.305 | T43: =IF(W43<>"",IF(E43<>"",E43,($I$9-SUM($T$25:T42))*V43*W43/SUMPRODUCT($W43:$W$58,$V43:$V$58)),"") -> 5.6938852 | U43: =IF(W43<>"",IF($I$12<>"",IF(G43<>"",G43,($I$9/$I$12-SUM($U$25:U42))*V43*W43/SUMPRODUCT($W43:$W$58,$V43:$V$58)),""),"") -> 3.2723478 | V43: 1 | W43: 1
A44: 20 | F44: =IF(AND(E44<>"",E44<>0),D44/E44,"") | H44: =IF(AND(G44<>"",G44<>0),D44/G44,"") | J44: =IF(AND(G44<>"",G44<>0),E44/G44,"") | N44: =IF(AND(I44<>"",I44<>0),G44/I44,"") | O44: =D44/P44 -> 0 | P44: =$I$8*V44*W44/SUMPRODUCT($W$25:$W$56,$V$25:$V$56) -> 44412.305 | Q44: =$I$9*V44*W44/SUMPRODUCT($W$25:$W$58,$V$25:$V$58) -> 5.6938852 | R44: =IF($I$12="","",Q44/$I$12) -> 3.2723478 | S44: =IF(W44<>"",IF(D44<>"",D44,($I$8-SUM($S$25:S43))*V44*W44/SUMPRODUCT($W44:$W$58,$V44:$V$58)),"") -> 44412.305 | T44: =IF(W44<>"",IF(E44<>"",E44,($I$9-SUM($T$25:T43))*V44*W44/SUMPRODUCT($W44:$W$58,$V44:$V$58)),"") -> 5.6938852 | U44: =IF(W44<>"",IF($I$12<>"",IF(G44<>"",G44,($I$9/$I$12-SUM($U$25:U43))*V44*W44/SUMPRODUCT($W44:$W$58,$V44:$V$58)),""),"") -> 3.2723478 | V44: 1 | W44: 1
A45: 21 | F45: =IF(AND(E45<>"",E45<>0),D45/E45,"") | H45: =IF(AND(G45<>"",G45<>0),D45/G45,"") | J45: =IF(AND(G45<>"",G45<>0),E45/G45,"") | N45: =IF(AND(I45<>"",I45<>0),G45/I45,"") | O45: =D45/P45 -> 0 | P45: =$I$8*V45*W45/SUMPRODUCT($W$25:$W$56,$V$25:$V$56) -> 44412.305 | Q45: =$I$9*V45*W45/SUMPRODUCT($W$25:$W$58,$V$25:$V$58) -> 5.6938852 | R45: =IF($I$12="","",Q45/$I$12) -> 3.2723478 | S45: =IF(W45<>"",IF(D45<>"",D45,($I$8-SUM($S$25:S44))*V45*W45/SUMPRODUCT($W45:$W$58,$V45:$V$58)),"") -> 44412.305 | T45: =IF(W45<>"",IF(E45<>"",E45,($I$9-SUM($T$25:T44))*V45*W45/SUMPRODUCT($W45:$W$58,$V45:$V$58)),"") -> 5.6938852 | U45: =IF(W45<>"",IF($I$12<>"",IF(G45<>"",G45,($I$9/$I$12-SUM($U$25:U44))*V45*W45/SUMPRODUCT($W45:$W$58,$V45:$V$58)),""),"") -> 3.2723478 | V45: 1 | W45: 1
A46: 22 | F46: =IF(AND(E46<>"",E46<>0),D46/E46,"") | H46: =IF(AND(G46<>"",G46<>0),D46/G46,"") | J46: =IF(AND(G46<>"",G46<>0),E46/G46,"") | N46: =IF(AND(I46<>"",I46<>0),G46/I46,"") | O46: =D46/P46 -> 0 | P46: =$I$8*V46*W46/SUMPRODUCT($W$25:$W$56,$V$25:$V$56) -> 44412.305 | Q46: =$I$9*V46*W46/SUMPRODUCT($W$25:$W$58,$V$25:$V$58) -> 5.6938852 | R46: =IF($I$12="","",Q46/$I$12) -> 3.2723478 | S46: =IF(W46<>"",IF(D46<>"",D46,($I$8-SUM($S$25:S45))*V46*W46/SUMPRODUCT($W46:$W$58,$V46:$V$58)),"") -> 44412.305 | T46: =IF(W46<>"",IF(E46<>"",E46,($I$9-SUM($T$25:T45))*V46*W46/SUMPRODUCT($W46:$W$58,$V46:$V$58)),"") -> 5.6938852 | U46: =IF(W46<>"",IF($I$12<>"",IF(G46<>"",G46,($I$9/$I$12-SUM($U$25:U45))*V46*W46/SUMPRODUCT($W46:$W$58,$V46:$V$58)),""),"") -> 3.2723478 | V46: 1 | W46: 1
A47: 23 | F47: =IF(AND(E47<>"",E47<>0),D47/E47,"") | H47: =IF(AND(G47<>"",G47<>0),D47/G47,"") | J47: =IF(AND(G47<>"",G47<>0),E47/G47,"") | N47: =IF(AND(I47<>"",I47<>0),G47/I47,"") | O47: =D47/P47 -> 0 | P47: =$I$8*V47*W47/SUMPRODUCT($W$25:$W$56,$V$25:$V$56) -> 44412.305 | Q47: =$I$9*V47*W47/SUMPRODUCT($W$25:$W$58,$V$25:$V$58) -> 5.6938852 | R47: =IF($I$12="","",Q47/$I$12) -> 3.2723478 | S47: =IF(W47<>"",IF(D47<>"",D47,($I$8-SUM($S$25:S46))*V47*W47/SUMPRODUCT($W47:$W$58,$V47:$V$58)),"") -> 44412.305 | T47: =IF(W47<>"",IF(E47<>"",E47,($I$9-SUM($T$25:T46))*V47*W47/SUMPRODUCT($W47:$W$58,$V47:$V$58)),"") -> 5.6938852 | U47: =IF(W47<>"",IF($I$12<>"",IF(G47<>"",G47,($I$9/$I$12-SUM($U$25:U46))*V47*W47/SUMPRODUCT($W47:$W$58,$V47:$V$58)),""),"") -> 3.2723478 | V47: 1 | W47: 1
A48: 24 | F48: =IF(AND(E48<>"",E48<>0),D48/E48,"") | H48: =IF(AND(G48<>"",G48<>0),D48/G48,"") | J48: =IF(AND(G48<>"",G48<>0),E48/G48,"") | N48: =IF(AND(I48<>"",I48<>0),G48/I48,"") | O48: =D48/P48 -> 0 | P48: =$I$8*V48*W48/SUMPRODUCT($W$25:$W$56,$V$25:$V$56) -> 44412.305 | Q48: =$I$9*V48*W48/SUMPRODUCT($W$25:$W$58,$V$25:$V$58) -> 5.6938852 | R48: =IF($I$12="","",Q48/$I$12) -> 3.2723478 | S48: =IF(W48<>"",IF(D48<>"",D48,($I$8-SUM($S$25:S47))*V48*W48/SUMPRODUCT($W48:$W$58,$V48:$V$58)),"") -> 44412.305 | T48: =IF(W48<>"",IF(E48<>"",E48,($I$9-SUM($T$25:T47))*V48*W48/SUMPRODUCT($W48:$W$58,$V48:$V$58)),"") -> 5.6938852 | U48: =IF(W48<>"",IF($I$12<>"",IF(G48<>"",G48,($I$9/$I$12-SUM($U$25:U47))*V48*W48/SUMPRODUCT($W48:$W$58,$V48:$V$58)),""),"") -> 3.2723478 | V48: 1 | W48: 1
A49: 25 | F49: =IF(AND(E49<>"",E49<>0),D49/E49,"") | H49: =IF(AND(G49<>"",G49<>0),D49/G49,"") | J49: =IF(AND(G49<>"",G49<>0),E49/G49,"") | N49: =IF(AND(I49<>"",I49<>0),G49/I49,"") | O49: =D49/P49 -> 0 | P49: =$I$8*V49*W49/SUMPRODUCT($W$25:$W$56,$V$25:$V$56) -> 44412.305 | Q49: =$I$9*V49*W49/SUMPRODUCT($W$25:$W$58,$V$25:$V$58) -> 5.6938852 | R49: =IF($I$12="","",Q49/$I$12) -> 3.2723478 | S49: =IF(W49<>"",IF(D49<>"",D49,($I$8-SUM($S$25:S48))*V49*W49/SUMPRODUCT($W49:$W$58,$V49:$V$58)),"") -> 44412.305 | T49: =IF(W49<>"",IF(E49<>"",E49,($I$9-SUM($T$25:T48))*V49*W49/SUMPRODUCT($W49:$W$58,$V49:$V$58)),"") -> 5.6938852 | U49: =IF(W49<>"",IF($I$12<>"",IF(G49<>"",G49,($I$9/$I$12-SUM($U$25:U48))*V49*W49/SUMPRODUCT($W49:$W$58,$V49:$V$58)),""),"") -> 3.2723478 | V49: 1 | W49: 1
A50: 26 | F50: =IF(AND(E50<>"",E50<>0),D50/E50,"") | H50: =IF(AND(G50<>"",G50<>0),D50/G50,"") | J50: =IF(AND(G50<>"",G50<>0),E50/G50,"") | N50: =IF(AND(I50<>"",I50<>0),G50/I50,"") | O50: =D50/P50 -> #DIV/0! | P50: =$I$8*V50*W50/SUMPRODUCT($W$25:$W$56,$V$25:$V$56) -> 0 | Q50: =$I$9*V50*W50/SUMPRODUCT($W$25:$W$58,$V$25:$V$58) -> 0 | R50: =IF($I$12="","",Q50/$I$12) -> 0 | S50: =IF(W50<>"",IF(D50<>"",D50,($I$8-SUM($S$25:S49))*V50*W50/SUMPRODUCT($W50:$W$58,$V50:$V$58)),"") | T50: =IF(W50<>"",IF(E50<>"",E50,($I$9-SUM($T$25:T49))*V50*W50/SUMPRODUCT($W50:$W$58,$V50:$V$58)),"") | U50: =IF(W50<>"",IF($I$12<>"",IF(G50<>"",G50,($I$9/$I$12-SUM($U$25:U49))*V50*W50/SUMPRODUCT($W50:$W$58,$V50:$V$58)),""),"")
A51: 27 | F51: =IF(AND(E51<>"",E51<>0),D51/E51,"") | H51: =IF(AND(G51<>"",G51<>0),D51/G51,"") | J51: =IF(AND(G51<>"",G51<>0),E51/G51,"") | N51: =IF(AND(I51<>"",I51<>0),G51/I51,"") | O51: =D51/P51 -> #DIV/0! | P51: =$I$8*V51*W51/SUMPRODUCT($W$25:$W$56,$V$25:$V$56) -> 0 | Q51: =$I$9*V51*W51/SUMPRODUCT($W$25:$W$58,$V$25:$V$58) -> 0 | R51: =IF($I$12="","",Q51/$I$12) -> 0 | S51: =IF(W51<>"",IF(D51<>"",D51,($I$8-SUM($S$25:S50))*V51*W51/SUMPRODUCT($W51:$W$58,$V51:$V$58)),"") | T51: =IF(W51<>"",IF(E51<>"",E51,($I$9-SUM($T$25:T50))*V51*W51/SUMPRODUCT($W51:$W$58,$V51:$V$58)),"") | U51: =IF(W51<>"",IF($I$12<>"",IF(G51<>"",G51,($I$9/$I$12-SUM($U$25:U50))*V51*W51/SUMPRODUCT($W51:$W$58,$V51:$V$58)),""),"")
A52: 28 | F52: =IF(AND(E52<>"",E52<>0),D52/E52,"") | H52: =IF(AND(G52<>"",G52<>0),D52/G52,"") | J52: =IF(AND(G52<>"",G52<>0),E52/G52,"") | N52: =IF(AND(I52<>"",I52<>0),G52/I52,"") | O52: =D52/P52 -> #DIV/0! | P52: =$I$8*V52*W52/SUMPRODUCT($W$25:$W$56,$V$25:$V$56) -> 0 | Q52: =$I$9*V52*W52/SUMPRODUCT($W$25:$W$58,$V$25:$V$58) -> 0 | R52: =IF($I$12="","",Q52/$I$12) -> 0 | S52: =IF(W52<>"",IF(D52<>"",D52,($I$8-SUM($S$25:S51))*V52*W52/SUMPRODUCT($W52:$W$58,$V52:$V$58)),"") | T52: =IF(W52<>"",IF(E52<>"",E52,($I$9-SUM($T$25:T51))*V52*W52/SUMPRODUCT($W52:$W$58,$V52:$V$58)),"") | U52: =IF(W52<>"",IF($I$12<>"",IF(G52<>"",G52,($I$9/$I$12-SUM($U$25:U51))*V52*W52/SUMPRODUCT($W52:$W$58,$V52:$V$58)),""),"")
A53: 29 | F53: =IF(AND(E53<>"",E53<>0),D53/E53,"") | H53: =IF(AND(G53<>"",G53<>0),D53/G53,"") | J53: =IF(AND(G53<>"",G53<>0),E53/G53,"") | N53: =IF(AND(I53<>"",I53<>0),G53/I53,"") | O53: =D53/P53 -> #DIV/0! | P53: =$I$8*V53*W53/SUMPRODUCT($W$25:$W$56,$V$25:$V$56) -> 0 | Q53: =$I$9*V53*W53/SUMPRODUCT($W$25:$W$58,$V$25:$V$58) -> 0 | R53: =IF($I$12="","",Q53/$I$12) -> 0 | S53: =IF(W53<>"",IF(D53<>"",D53,($I$8-SUM($S$25:S52))*V53*W53/SUMPRODUCT($W53:$W$58,$V53:$V$58)),"") | T53: =IF(W53<>"",IF(E53<>"",E53,($I$9-SUM($T$25:T52))*V53*W53/SUMPRODUCT($W53:$W$58,$V53:$V$58)),"") | U53: =IF(W53<>"",IF($I$12<>"",IF(G53<>"",G53,($I$9/$I$12-SUM($U$25:U52))*V53*W53/SUMPRODUCT($W53:$W$58,$V53:$V$58)),""),"")
F54: =IF(AND(E54<>"",E54<>0),D54/E54,"") | H54: =IF(AND(G54<>"",G54<>0),D54/G54,"") | J54: =IF(AND(G54<>"",G54<>0),E54/G54,"") | N54: =IF(AND(I54<>"",I54<>0),G54/I54,"") | O54: =D54/P54 -> #DIV/0! | P54: =$I$8*V54*W54/SUMPRODUCT($W$25:$W$56,$V$25:$V$56) -> 0 | Q54: =$I$9*V54*W54/SUMPRODUCT($W$25:$W$58,$V$25:$V$58) -> 0 | R54: =IF($I$12="","",Q54/$I$12) -> 0 | S54: =IF(W54<>"",IF(D54<>"",D54,($I$8-SUM($S$25:S50))*V54*W54/SUMPRODUCT($W54:$W$58,$V54:$V$58)),"") | T54: =IF(W54<>"",IF(E54<>"",E54,($I$9-SUM($T$25:T50))*V54*W54/SUMPRODUCT($W54:$W$58,$V54:$V$58)),"") | U54: =IF(W54<>"",IF($I$12<>"",IF(G54<>"",G54,($I$9/$I$12-SUM($U$25:U50))*V54*W54/SUMPRODUCT($W54:$W$58,$V54:$V$58)),""),"")
F55: =IF(AND(E55<>"",E55<>0),D55/E55,"") | H55: =IF(AND(G55<>"",G55<>0),D55/G55,"") | J55: =IF(AND(G55<>"",G55<>0),E55/G55,"") | N55: =IF(AND(I55<>"",I55<>0),G55/I55,"") | O55: =D55/P55 -> #DIV/0! | P55: =$I$8*V55*W55/SUMPRODUCT($W$25:$W$56,$V$25:$V$56) -> 0 | Q55: =$I$9*V55*W55/SUMPRODUCT($W$25:$W$58,$V$25:$V$58) -> 0 | R55: =IF($I$12="","",Q55/$I$12) -> 0 | S55: =IF(W55<>"",IF(D55<>"",D55,($I$8-SUM($S$25:S54))*V55*W55/SUMPRODUCT($W55:$W$58,$V55:$V$58)),"") | T55: =IF(W55<>"",IF(E55<>"",E55,($I$9-SUM($T$25:T54))*V55*W55/SUMPRODUCT($W55:$W$58,$V55:$V$58)),"") | U55: =IF(W55<>"",IF($I$12<>"",IF(G55<>"",G55,($I$9/$I$12-SUM($U$25:U54))*V55*W55/SUMPRODUCT($W55:$W$58,$V55:$V$58)),""),"")
F56: =IF(AND(E56<>"",E56<>0),D56/E56,"") | H56: =IF(AND(G56<>"",G56<>0),D56/G56,"") | J56: =IF(AND(G56<>"",G56<>0),E56/G56,"") | N56: =IF(AND(I56<>"",I56<>0),G56/I56,"") | O56: =D56/P56 -> #DIV/0! | P56: =$I$8*V56*W56/SUMPRODUCT($W$25:$W$56,$V$25:$V$56) -> 0 | Q56: =$I$9*V56*W56/SUMPRODUCT($W$25:$W$58,$V$25:$V$58) -> 0 | R56: =IF($I$12="","",Q56/$I$12) -> 0 | S56: =IF(W56<>"",IF(D56<>"",D56,($I$8-SUM($S$25:S55))*V56*W56/SUMPRODUCT($W56:$W$58,$V56:$V$58)),"") | T56: =IF(W56<>"",IF(E56<>"",E56,($I$9-SUM($T$25:T55))*V56*W56/SUMPRODUCT($W56:$W$58,$V56:$V$58)),"") | U56: =IF(W56<>"",IF($I$12<>"",IF(G56<>"",G56,($I$9/$I$12-SUM($U$25:U55))*V56*W56/SUMPRODUCT($W56:$W$58,$V56:$V$58)),""),"")
D57: =SUM(D25:D56) -> 0 | E57: =SUM(E25:E56) -> 0 | F57: =IF(AND(E57<>"",E57<>0),D57/E57,"") | G57: =SUM(G25:G56) -> 0 | H57: =IF(AND(G57<>"",G57<>0),D57/G57,"") | I57: =SUM(I25:I56) -> 0 | J57: =IF(AND(G57<>"",G57<>0),E57/G57,"") | K57: =SUM(K25:K56) -> 0 | L57: =SUM(L25:L56) -> 0 | M57: =SUM(M25:M56) -> 0 | N57: =IF(AND(I57<>"",I57<>0),G57/I57,"") | O57: =D57/P57 -> 0 | P57: =SUM(P25:P56) -> 1110307.6 | Q57: =SUM(Q25:Q55) -> 142.34713 | R57: =SUM(R25:R55) -> 81.808696 | S57: =SUM(S25:S56) -> 1110307.6 | T57: =SUM(T25:T55) -> 142.34713 | U57: =SUM(U25:U55) -> 81.808696

Sheet Вед-ть Рогалевич
A1: =График!B1 -> Декабрь, 2025
A2: =График!B3 -> ул. Набережная Ленина, 18 | D2: =График!B4 -> GL-0005
A3: Сотрудник | D3: Выплачено на карту | E3: Выплачено наличными по платежной ведомости | F3: Дополнительные начисления, доплаты | G3: Оклад | H3: Бонусная часть от личных продаж | I3: Бонусная часть от общих продаж | J3: Базовый бонус за выполнение плана | K3: Итого: | L3: Вычеты | M3: Итого к выдаче с учетом авансов и вычетов | N3: Подпись
A4: =График!B29 -> Рогалевич Ирина | D4: =19140*2 -> 38280 | F4: =H8+H9 -> 22532.462 | G4: =D11 -> 10500 | H4: =D18 -> 14095.26 | I4: =L18 -> 4577.0731 | J4: =L11 -> 0 | K4: =H4+J4+G4+F4+I4 -> 51704.795 | L4: =C8+C9 -> 7230.67 | M4: =K4-L4-D4-E4 -> 6194.1251
B6: Вычеты | G6: Доп начисления
B7: Дата | C7: Сумма | D7: Описание | G7: Дата | H7: Сумма | J7: Описание
B8: 46022 | C8: =44000-D4 -> 5720 | D8: НДФЛ декабрь 2025 | G8: 46022 | H8: ='Ялта, Ленина, 18'!J8*0.01 -> 12532.462 | J8: Административный %
B9: 46031 | C9: 1510.67 | D9: Вычет согласно инвентаризационной ведомости от 09.01 | G9: 46387 | H9: 10000 | J9: Премия "Сотрудник года"
A11: Оклад: | D11: =G15+G16 -> 10500 | I11: Базовый бонус за выполнение плана | L11: =L15+L16 -> 0
B13: Оклад: | J13: Базовый бонус за выполнение плана
B14: Дней | C14: Магазин | D14: Должность | E14: Зачислено часов | F14: Ставка за час, руб | G14: Начислено за день, руб | J14: Магазин | K14: КВП | L14: Начисленный ББ
B15: =График!AI29 -> 12 | C15: =A2 -> ул. Набережная Ленина, 18 | D15: ПК | E15: =График!AJ29 -> 105 | F15: 100 | G15: =E15*F15 -> 10500 | J15: =График!B3 -> ул. Набережная Ленина, 18 | K15: ='Ялта, Ленина, 18'!K8 -> 0.48094046
D16: ПК | G16: =E16*F16 -> 0
A18: БонуснаяЧасть | D18: =G23+G24 -> 14095.26 | I18: Бонусная часть от общих продаж | L18: =N23+N24 -> 4577.0731
B21: Бонус от личных продаж по категории товара | I21: Бонус от общих продаж
B22: Сотрудник | C22: Магазин | E22: Процент от продажи | F22: Продано на сумму, руб | G22: Начисленный бонус от продаж, руб | I22: Сотрудник | J22: Магазин | K22: Кол-во отработанных личных часов | L22: Кол-во отработанных общих часов | M22: Процент от продажи | N22: Начисленный бонус от продаж, руб
B23: =A4 -> Рогалевич Ирина | C23: =A2 -> ул. Набережная Ленина, 18 | E23: 0.04 | F23: ='Рогалевич И. Е. '!J8 -> 352381.5 | G23: =F23*E23 -> 14095.26 | I23: =B23 -> Рогалевич Ирина | J23: =C23 -> ул. Набережная Ленина, 18 | K23: =E15 -> 105 | L23: =График!AJ31 -> 575 | M23: 0.02 | N23: ='Ялта, Ленина, 18'!J8*M23*K23/L23 -> 4577.0731
B24: =B23 -> Рогалевич Ирина | C24: =C16 -> 0 | G24: =F24*E24 -> 0

Sheet Вед-ть Арапова
A1: =График!B1 -> Декабрь, 2025
A2: =График!B3 -> ул. Набережная Ленина, 18 | D2: =График!B4 -> GL-0005
A3: Сотрудник | D3: Выплачено на карту | E3: Выплачено наличными по платежной ведомости | F3: Дополнительные начисления, доплаты | G3: Оклад | H3: Бонусная часть от личных продаж | I3: Бонусная часть от общих продаж | J3: Базовый бонус за выполнение плана | K3: Итого: | L3: Вычеты | M3: Итого к выдаче с учетом авансов и вычетов | N3: Подпись
A4: =График!B27 -> Арапова Анна-Мария | D4: =17400*2 -> 34800 | F4: =H8+H9 -> 0 | G4: =D12 -> 22500 | H4: =D19 -> 11227.708 | I4: =L19 -> 9808.0137 | J4: =L12 -> 0 | K4: =H4+J4+G4+F4+I4 -> 43535.722 | L4: =C8+C9+C10 -> 6710.67 | M4: =K4-L4-D4-E4 -> 2025.0517
B6: Вычеты | G6: Доп начисления
B7: Дата | C7: Сумма | D7: Описание | G7: Дата | H7: Сумма | J7: Описание
B8: 46022 | C8: =40000-D4 -> 5200 | D8: НДФЛ декабрь 2025
B9: 46031 | C9: 1510.67 | D9: Вычет согласно инвентаризационной ведомости от 09.01
A12: Оклад: | D12: =G16 -> 22500 | I12: Базовый бонус за выполнение плана | L12: =L16+L17 -> 0
B14: Оклад: | J14: Базовый бонус за выполнение плана
B15: Дней | C15: Магазин | D15: Должность | E15: Зачислено часов | F15: Ставка за час, руб | G15: Начислено за день, руб | J15: Магазин | K15: КВП | L15: Начисленный ББ
B16: =График!AI27 -> 21 | C16: =A2 -> ул. Набережная Ленина, 18 | D16: ПК | E16: =График!AJ27 -> 225 | F16: 100 | G16: =E16*F16 -> 22500 | J16: =График!B3 -> ул. Набережная Ленина, 18 | K16: ='Ялта, Ленина, 18'!K8 -> 0.48094046 | L16: 0
A19: БонуснаяЧасть | D19: =G24 -> 11227.708 | I19: Бонусная часть от общих продаж | L19: =N24 -> 9808.0137
B22: Бонус от личных продаж по категории товара | I22: Бонус от общих продаж
B23: Сотрудник | C23: Магазин | E23: Процент от продажи | F23: Продано на сумму, руб | G23: Начисленный бонус от продаж, руб | I23: Сотрудник | J23: Магазин | K23: Кол-во отработанных личных часов | L23: Кол-во отработанных общих часов | M23: Процент от продажи | N23: Начисленный бонус от продаж, руб
B24: =A4 -> Арапова Анна-Мария | C24: =A2 -> ул. Набережная Ленина, 18 | E24: 0.04 | F24: ='Арапова А. В.'!D57 -> 280692.7 | G24: =F24*E24 -> 11227.708 | I24: =B24 -> Арапова Анна-Мария | J24: =C24 -> ул. Набережная Ленина, 18 | K24: =E16 -> 225 | L24: =График!AJ31 -> 575 | M24: 0.02 | N24: ='Ялта, Ленина, 18'!D56*M24*K24/L24 -> 9808.0137
B25: =B24 -> Арапова Анна-Мария

Sheet Вед-ть Уразгильдеева
A1: =График!B1 -> Декабрь, 2025
A2: =График!B3 -> ул. Набережная Ленина, 18 | D2: =График!B4 -> GL-0005
A3: Сотрудник | D3: Выплачено на карту | E3: Выплачено наличными по платежной ведомости | F3: Дополнительные начисления, доплаты | G3: Оклад | H3: Бонусная часть от личных продаж | I3: Бонусная часть от общих продаж | J3: Базовый бонус за выполнение плана | K3: Итого: | L3: Вычеты | M3: Итого к выдаче с учетом авансов и вычетов | N3: Подпись
A4: =График!B28 -> Уразгильдеева Екатерина | D4: =17400*2 -> 34800 | E4: 7000 | F4: =H8+H9 -> 0 | G4: =D12 -> 24500 | H4: =D19 -> 24806.88 | I4: =L19 -> 10679.837 | J4: =L12 -> 0 | K4: =H4+J4+G4+F4+I4 -> 59986.717 | L4: =C8+C9+C10 -> 6710.67 | M4: =K4-L4-D4-E4 -> 11476.047 | S4: пб
B6: Вычеты | G6: Доп начисления
B7: Дата | C7: Сумма | D7: Описание | G7: Дата | H7: Сумма | J7: Описание
B8: 46022 | C8: =40000-D4 -> 5200 | D8: НДФЛ декабрь 2025
B9: 46031 | C9: 1510.67 | D9: Вычет согласно инвентаризационной ведомости от 09.01
A12: Оклад: | D12: =G16 -> 24500 | I12: Базовый бонус за выполнение плана | L12: =L16+L17 -> 0
B14: Оклад: | J14: Базовый бонус за выполнение плана
B15: Дней | C15: Магазин | D15: Должность | E15: Зачислено часов | F15: Ставка за час, руб | G15: Начислено за день, руб | J15: Магазин | K15: КВП | L15: Начисленный ББ
B16: =График!AI28 -> 23 | C16: =A2 -> ул. Набережная Ленина, 18 | D16: ПК | E16: =График!AJ28 -> 245 | F16: 100 | G16: =E16*F16 -> 24500 | J16: =График!B3 -> ул. Набережная Ленина, 18 | K16: ='Ялта, Ленина, 18'!K8 -> 0.48094046 | L16: 0
A19: БонуснаяЧасть | D19: =G24 -> 24806.88 | I19: Бонусная часть от общих продаж | L19: =N24 -> 10679.837
B22: Бонус от личных продаж по категории товара | I22: Бонус от общих продаж
B23: Сотрудник | C23: Магазин | E23: Процент от продажи | F23: Продано на сумму, руб | G23: Начисленный бонус от продаж, руб | I23: Сотрудник | J23: Магазин | K23: Кол-во отработанных личных часов | L23: Кол-во отработанных общих часов | M23: Процент от продажи | N23: Начисленный бонус от продаж, руб
B24: =A4 -> Уразгильдеева Екатерина | C24: =A2 -> ул. Набережная Ленина, 18 | E24: 0.04 | F24: ='Уразгильдеева Е. Р. '!J8 -> 620172 | G24: =F24*E24 -> 24806.88 | I24: =B24 -> Уразгильдеева Екатерина | J24: =C24 -> ул. Набережная Ленина, 18 | K24: =E16 -> 245 | L24: =График!AJ31 -> 575 | M24: 0.02 | N24: ='Ялта, Ленина, 18'!J8*M24*K24/L24 -> 10679.837
B25: =B24 -> Уразгильдеева Екатерина | N25: =1477363.14*M25*K25/L25 -> #DIV/0!

Sheet График
B1: Декабрь, 2025 | T1: в
B2: г. Ялта | C2: Симферополь
B3: ул. Набережная Ленина, 18
B4: GL-0005
B5: 10.00-22.00
B6: ФОТ | C6: Кол-во дней в месяц | AK6: 30
B7: =BT31*100/BH31 -> #DIV/0!
D8: пн | E8: вт | F8: ср | G8: чт | H8: пт | I8: сб | J8: вс | K8: пн | L8: вт | M8: ср | N8: чт | O8: пт | P8: сб | Q8: вс | R8: пн | S8: вт | T8: ср | U8: чт | V8: пт | W8: сб | X8: вс | Y8: пн | Z8: вт | AA8: ср | AB8: чт | AC8: пт | AD8: сб | AE8: вс | AF8: пн | AG8: вт | AH8: ср | AJ8: Часы | AK8: Выходные | AL8: Отпуск | AM8: Больничный (официальный) | AN8: Дни стажировки
A10: № | B10: ФИО | C10: Должность | D10: 1 | E10: 2 | F10: 3 | G10: 4 | H10: 5 | I10: 6 | J10: 7 | K10: 8 | L10: 9 | M10: 10 | N10: 11 | O10: 12 | P10: 13 | Q10: 14 | R10: 15 | S10: 16 | T10: 17 | U10: 18 | V10: 19 | W10: 20 | X10: 21 | Y10: 22 | Z10: 23 | AA10: 24 | AB10: 25 | AC10: 26 | AD10: 27 | AE10: 28 | AF10: 29 | AG10: 30 | AH10: 31 | AI10: Дни
A11: 20 | AI11: 0 | AJ11: 0 | AK11: 0 | AL11: 0 | AM11: 0 | AN11: 0
A12: 19 | AI12: 0 | AJ12: 0 | AK12: 0 | AL12: 0 | AM12: 0 | AN12: 0
A13: 18 | AI13: 0 | AJ13: 0 | AK13: 0 | AL13: 0 | AM13: 0 | AN13: 0
A14: 17 | AI14: 0 | AJ14: 0 | AK14: 0 | AL14: 0 | AM14: 0 | AN14: 0
A15: 16 | AI15: 0 | AJ15: 0 | AK15: 0 | AL15: 0 | AM15: 0 | AN15: 0
A16: 15 | AI16: 0 | AJ16: 0 | AK16: 0 | AL16: 0 | AM16: 0 | AN16: 0
A17: 14 | AI17: 0 | AJ17: 0 | AK17: 0 | AL17: 0 | AM17: 0 | AN17: 0
A18: 13 | AI18: 0 | AJ18: 0 | AK18: 0 | AL18: 0 | AM18: 0 | AN18: 0
A19: 12 | AI19: 0 | AJ19: 0 | AK19: 0 | AL19: 0 | AM19: 0 | AN19: 0
A20: 11 | AI20: 0 | AJ20: 0 | AK20: 0 | AL20: 0 | AM20: 0 | AN20: 0
A21: 10 | AI21: 0 | AJ21: 0 | AK21: 0 | AL21: 0 | AM21: 0 | AN21: 0
A22: 9 | AI22: =COUNTIF(D22:AH22, ">0") -> 0 | AJ22: 0 | AK22: 0 | AL22: 0 | AM22: 0 | AN22: 0
A23: 8 | AI23: =COUNTIF(D23:AH23, ">0") -> 0 | AJ23: 0 | AK23: 0 | AL23: 0 | AM23: 0 | AN23: 0
A24: 7 | AI24: =COUNTIF(D24:AH24, ">0") -> 0 | AJ24: 0 | AK24: 0 | AL24: 0 | AM24: 0 | AN24: 0
A25: 6 | AI25: =COUNTIF(D25:AH25,">0") -> 0 | AJ25: =SUMIF(D25:AH25,">0") -> 0 | AK25: =COUNTIF(D25:AH25,"В") -> 0 | AL25: =COUNTIF(E25:AI25,"о") -> 0 | AM25: =COUNTIF(F25:AJ25,"б") -> 0 | AN25: 0
A26: 5 | AI26: =COUNTIF(D26:AH26, ">0") -> 0 | AJ26: =SUMIF(D26:AH26,">0") -> 0 | AK26: =COUNTIF(D26:AH26, "В") -> 0 | AL26: 0 | AM26: 0 | AN26: 0
A27: 4 | B27: Арапова Анна-Мария | C27: ПК | D27: в | E27: 9 | F27: в | G27: в | H27: 12 | I27: 10 | J27: 11 | K27: в | L27: 11 | M27: 11 | N27: в | O27: в | P27: 12 | Q27: 11 | R27: 9 | S27: в | T27: в | U27: 11 | V27: 11 | W27: 12 | X27: 9 | Y27: в | Z27: 11 | AA27: 11 | AB27: в | AC27: 11 | AD27: 12 | AE27: 10 | AF27: 12 | AG27: 10 | AH27: 9 | AI27: =COUNTIF(D27:AH27,">0") -> 21 | AJ27: =SUMIF(D27:AH27,">0") -> 225 | AK27: =COUNTIF(D27:AH27,"В") -> 10 | AL27: =COUNTIF(E27:AI27,"о") -> 0 | AM27: =COUNTIF(F27:AJ27,"б") -> 0 | AN27: 0
A28: 3 | B28: Уразгильдеева Екатерина | C28: ПК | D28: 11 | E28: 9 | F28: 11 | G28: 11 | H28: 10 | I28: 12 | J28: 9 | K28: 11 | L28: в | M28: в | N28: 11 | O28: 12 | P28: в | Q28: в | R28: 11 | S28: 11 | T28: в | U28: в | V28: 11 | W28: 10 | X28: 11 | Y28: 11 | Z28: 9 | AA28: в | AB28: 11 | AC28: 11 | AD28: 9 | AE28: 12 | AF28: в | AG28: 12 | AH28: 9 | AI28: =COUNTIF(D28:AH28,">0") -> 23 | AJ28: =SUMIF(D28:AH28,">0") -> 245 | AK28: =COUNTIF(D28:AH28,"В") -> 8 | AL28: =COUNTIF(E28:AI28,"о") -> 0 | AM28: =COUNTIF(F28:AJ28,"б") -> 0 | AN28: 0
A29: 2 | B29: Рогалевич Ирина | C29: УМ | D29: с | E29: с | F29: с | G29: с | H29: с | I29: с | J29: с | K29: в | L29: 2 | M29: 9 | N29: 9 | O29: 9 | P29: 10 | Q29: 10 | R29: в | S29: 9 | T29: 11 | U29: 9 | V29: c | W29: c | X29: c | Y29: c | Z29: в | AA29: с | AB29: с | AC29: с | AD29: с | AE29: с | AF29: 9 | AG29: 10 | AH29: 8 | AI29: =COUNTIF(D29:AH29,">0") -> 12 | AJ29: =SUMIF(D29:AH29,">0") -> 105 | AK29: =COUNTIF(D29:AH29,"В") -> 3 | AL29: =COUNTIF(E29:AI29,"о") -> 0 | AM29: =COUNTIF(F29:AJ29,"б") -> 0 | AN29: 0
A30: 1 | AI30: =COUNTIF(D30:AH30, ">0") -> 0 | AJ30: =SUMIF(D30:AH30,">0") -> 0 | AK30: =COUNTIF(D30:AH30, "В") -> 0 | AL30: =COUNTIF(E30:AI30, "о") -> 0 | AM30: =COUNTIF(F30:AJ30, "б") -> 0 | AN30: 0
B31: Итого магазин | D31: =COUNTIF(D11:D30, ">0") -> 1 | E31: =COUNTIF(E11:E30, ">0") -> 2 | F31: =COUNTIF(F11:F30, ">0") -> 1 | G31: =COUNTIF(G11:G30, ">0") -> 1 | H31: =COUNTIF(H11:H30, ">0") -> 2 | I31: =COUNTIF(I11:I30, ">0") -> 2 | J31: =COUNTIF(J11:J30, ">0") -> 2 | K31: =COUNTIF(K11:K29, ">0") -> 1 | L31: =COUNTIF(L11:L30, ">0") -> 2 | M31: =COUNTIF(M11:M30, ">0") -> 2 | N31: =COUNTIF(N11:N30, ">0") -> 2 | O31: =COUNTIF(O11:O30, ">0") -> 2 | P31: =COUNTIF(P11:P30, ">0") -> 2 | Q31: =COUNTIF(Q11:Q30, ">0") -> 2 | R31: =COUNTIF(R11:R30, ">0") -> 2 | S31: =COUNTIF(S11:S30, ">0") -> 2 | ... AH31: =COUNTIF(AH11:AH30, ">0") -> 3 | AJ31: =SUM(AJ11:AJ30) -> 575 | AK31: =SUM(AK11:AK30) -> 21 | AL31: =SUM(AL11:AL30) -> 0 | AM31: =SUM(AM11:AM30) -> 0 | AN31: =SUM(AN11:AN30) -> 0
B33: Выделять рабочие дни цветом, выходные не выделять.
B34: Указывать темной или светлой заливкой вечернюю или утреннюю смену.
