Workbook
Name маг: NA()

Sheet Ялта, Ленина, 18
A1: Рогалевич, | B1: =TODAY()-1 -> 46171
B2: (отчетная дата)
C3: Осталось до выполнения плана!!! | I3: =График!B3 -> ул. Набережная Ленина, 18
C4: =I8-D56 -> 798212 | E4: =IF(I8<>0, C4/I8, 0) -> 0.39574062
D5: =C4/(I14-J14) -> #DIV/0!
F6: Целевые показатели
F7: Показатель | I7: План | J7: Факт | K7: % выполнения | L7: Прогноз выполнения | M7: % выполнения по прогнозу | N7: Отклонение | O7: Факт аналогичного месяца прошлого года | P7: Отклонение LFL
F8: Выручка | I8: =I11*I12*I13 -> 2017008 | J8: =D56 -> 1218796 | K8: =IF(AND(I8<>"",I8<>0,J8<>""),J8/I8,"") -> 0.60425938 | L8: =IF(SUMIF($D$25:$D$55,">=0",$U$25:$U$55)<>0,I8*D56/SUMIF($D$25:$D$55,">=0",$U$25:$U$55),0) -> 1218796 | M8: =IF(AND(I8<>"", I8<>0, L8<>"", L8<>0), L8/I8, "") -> 0.60425938 | N8: =IF(AND(J8<>0, J8<>"", I8<>0, I8<>""), L8-I8, "") -> -798212 | O8: 1482639 | P8: =IF(AND(O8<>"", O8<>0, L8<>"", L8<>0), -O8+L8, "") -> -263843 | Q8: =IF(AND(P8<>"",P8<>0,O8<>0,O8<>""),P8/O8,"") -> -0.17795498
F9: Кол-во изделий | I9: =I8/I11 -> 292.32 | J9: =E56 -> 178 | K9: =IF(AND(I9<>"", I9<>0, J9<>""), J9/I9, "") -> 0.60892173 | L9: =IF(SUMIF($E$25:$E$55,">=0",$V$25:$V$55)<>0,I9*E56/SUMIF($E$25:$E$55,">=0",$V$25:$V$55),0) -> 178 | M9: =IF(AND(I9<>"", I9<>0, L9<>"", L9<>0), L9/I9, "") -> 0.60892173 | N9: =IF(AND(J9<>0, J9<>"", I9<>0, I9<>""), L9-I9, "") -> -114.32 | O9: =O8/O11 -> 315.92563 | P9: =IF(AND(O9<>"", O9<>0, L9<>"", L9<>0), -O9+L9, "") -> -137.92563 | Q9: =IF(AND(P9<>"",P9<>0,O9<>0,O9<>""),P9/O9,"") -> -0.43657627
F10: Средний чек | I10: =I11*I12 -> 12006 | J10: =H56 -> 11285.148 | K10: =IF(AND(I10<>"", I10<>0, J10<>""), J10/I10, "") -> 0.93995903 | L10: =J10 -> 11285.148 | M10: =IF(AND(I10<>"", I10<>0, L10<>"", L10<>0), L10/I10, "") -> 0.93995903 | N10: =IF(AND(J10<>0, J10<>"", I10<>0, I10<>""), L10-I10, "") -> -720.85185 | O10: =O11*O12 -> 8306.61 | P10: =IF(AND(O10<>"", O10<>0, L10<>"", L10<>0), -O10+L10, "") -> 2978.5381 | Q10: =IF(AND(P10<>"",P10<>0,O10<>0,O10<>""),P10/O10,"") -> 0.35857445
F11: Средняя стоимость изделия | I11: 6900 | J11: =F56 -> 6847.1685 | K11: =IF(AND(I11<>"", I11<>0, J11<>""), J11/I11, "") -> 0.99234327 | L11: =IF(L9>0, L8/L9, "") -> 6847.1685 | M11: =IF(AND(I11<>"", I11<>0, L11<>"", L11<>0), L11/I11, "") -> 0.99234327 | N11: =IF(AND(J11<>0, J11<>"", I11<>0, I11<>""), L11-I11, "") -> -52.831461 | O11: 4693 | P11: =IF(AND(O11<>"", O11<>0, L11<>"", L11<>0), -O11+L11, "") -> 2154.1685 | Q11: =IF(AND(P11<>"",P11<>0,O11<>0,O11<>""),P11/O11,"") -> 0.45901737
F12: Длина чека | I12: 1.74 | J12: =J56 -> 1.6481481 | K12: =IF(AND(I12<>"", I12<>0, J12<>""), J12/I12, "") -> 0.94721158 | L12: =J12 -> 1.6481481 | M12: =IF(AND(I12<>"", I12<>0, L12<>"", L12<>0), L12/I12, "") -> 0.94721158 | N12: =IF(AND(J12<>0, J12<>"", I12<>0, I12<>""), L12-I12, "") -> -0.091851852 | O12: 1.77 | P12: =IF(AND(O12<>"", O12<>0, L12<>"", L12<>0), -O12+L12, "") -> -0.12185185 | Q12: =IF(AND(P12<>"",P12<>0,O12<>0,O12<>""),P12/O12,"") -> -0.068842854
F13: Кол-во чеков | I13: =I17*I20 -> 168 | J13: =G56 -> 108 | K13: =IF(AND(I13<>"", I13<>0, J13<>""), J13/I13, "") -> 0.64285714 | L13: =IF(SUMIF($G$25:$G$55,">=0",$W$25:$W$55)<>0,I13*G56/SUMIF($G$25:$G$55,">=0",$W$25:$W$55),"") -> 108 | M13: =IF(AND(I13<>"", I13<>0, L13<>"", L13<>0), L13/I13, "") -> 0.64285714 | N13: =IF(AND(J13<>0, J13<>"", I13<>0, I13<>""), L13-I13, "") -> -60 | O13: 181 | P13: =IF(AND(O13<>"", O13<>0, L13<>"", L13<>0), -O13+L13, "") -> -73 | Q13: =IF(AND(P13<>"",P13<>0,O13<>0,O13<>""),P13/O13,"") -> -0.40331492
F14: Кол-во смен | I14: =График!AK6 -> 31 | J14: 31 | K14: =IF(AND(I14<>"", I14<>0, J14<>""), J14/I14, "") -> 1 | L14: =I14 -> 31 | M14: =IF(AND(I14<>"", I14<>0, L14<>"", L14<>0), L14/I14, "") -> 1 | N14: =IF(AND(J14<>0, J14<>"", I14<>0, I14<>""), L14-I14, "") -> 0 | O14: 31 | P14: =IF(AND(O14<>"", O14<>0, L14<>"", L14<>0), -O14+L14, "") -> 0 | Q14: =IF(AND(P14<>"",P14<>0,O14<>0,O14<>""),P14/O14,"")
F15: Средние продажи в смену | I15: =I8/I14 -> 65064.774 | J15: =J8/J14 -> 39316 | K15: =IF(AND(I15<>"", I15<>0, J15<>""), J15/I15, "") -> 0.60425938 | L15: =J15 -> 39316 | M15: =IF(AND(I15<>"", I15<>0, L15<>"", L15<>0), L15/I15, "") -> 0.60425938 | N15: =IF(AND(J15<>0, J15<>"", I15<>0, I15<>""), L15-I15, "") -> -25748.774 | O15: =O8/O14 -> 47827.065 | P15: =IF(AND(O15<>"", O15<>0, L15<>"", L15<>0), -O15+L15, "") -> -8511.0645 | Q15: =IF(AND(P15<>"",P15<>0,O15<>0,O15<>""),P15/O15,"") -> -0.17795498
F16: Отставание/Перевыполнение | J16: =J8-I15*J14 -> -798212 | K16: =IF(AND(I16<>"", I16<>0, J16<>""), J16/I16, "") | L16: =J16 -> -798212 | M16: =IF(AND(I16<>"", I16<>0, L16<>"", L16<>0), L16/I16, "") | N16: =IF(AND(J16<>0, J16<>"", I16<>0, I16<>""), L16-I16, "") | O16: -173502 | P16: =IF(AND(O16<>"", O16<>0, L16<>"", L16<>0), -O16+L16, "") -> -624710 | Q16: =IF(AND(P16<>"",P16<>0,O16<>0,O16<>""),P16/O16,"") -> 3.6005925
F17: Трафик | I17: 1400 | J17: =I56 -> 1312.8 | K17: =IF(AND(I17<>"", I17<>0, J17<>""), J17/I17, "") -> 0.93771429 | L17: =J17/J14*I14 -> 1312.8 | M17: =IF(AND(I17<>"", I17<>0, L17<>"", L17<>0), L17/I17, "") -> 0.93771429 | N17: =IF(AND(J17<>0, J17<>"", I17<>0, I17<>""), L17-I17, "") -> -87.2 | O17: 780 | P17: =IF(AND(O17<>"", O17<>0, L17<>"", L17<>0), -O17+L17, "") -> 532.8 | Q17: =IF(AND(P17<>"",P17<>0,O17<>0,O17<>""),P17/O17,"") -> 0.68307692
F18: Выручка на вошедшего | I18: =I8/I17 -> 1440.72 | J18: =J8/J17 -> 928.39427 | K18: =IF(AND(I18<>"", I18<>0, J18<>""), J18/I18, "") -> 0.64439605 | L18: =J18 -> 928.39427 | M18: =IF(AND(I18<>"", I18<>0, L18<>"", L18<>0), L18/I18, "") -> 0.64439605 | N18: =IF(AND(J18<>0, J18<>"", I18<>0, I18<>""), L18-I18, "") -> -512.32573 | O18: =O8/O17 -> 1900.8192 | P18: =IF(AND(O18<>"", O18<>0, L18<>"", L18<>0), -O18+L18, "") -> -972.42496 | Q18: =IF(AND(P18<>"",P18<>0,O18<>0,O18<>""),P18/O18,"") -> -0.51158203
K19: =IF(AND(I19<>"", I19<>0, J19<>""), J19/I19, "") | L19: =J19 -> 0 | M19: =IF(AND(I19<>"", I19<>0, L19<>"", L19<>0), L19/I19, "") | N19: =IF(AND(J19<>0, J19<>"", I19<>0, I19<>""), L19-I19, "") | O19: 0 | P19: =IF(AND(O19<>"", O19<>0, L19<>"", L19<>0), -O19+L19, "") | Q19: =IF(AND(P19<>"",P19<>0,O19<>0,O19<>""),P19/O19,"")
F20: Конверсия план/факт | I20: 0.12 | J20: =S56 -> 0.08226691 | K20: =J20/I20 -> 0.68555759 | L20: =IF(AND(K8<>0,I14<>0,I56<>0),(I56*S56+(I56/K8-I56)*I20)/(I56/K8),0) -> 0.097199427 | M20: =IF(AND(I20<>"", I20<>0, L20<>"", L20<>0), L20/I20, "") -> 0.80999522 | N20: =IF(AND(J20<>0, J20<>"", I20<>0, I20<>""), L20-I20, "") -> -0.022800573 | O20: =O13/O17 -> 0.23205128 | P20: =IF(AND(O20<>"", O20<>0, L20<>"", L20<>0), -O20+L20, "") -> -0.13485186 | Q20: =IF(AND(P20<>"",P20<>0,O20<>0,O20<>""),P20/O20,"") -> -0.58112954
A22: Факт продаж за месяц | R22: Раcпределение плана по дням
A23: Сотрудник | B23: Дата | C23: День недели | D23: Выручка (руб) | E23: Кол-во единиц (шт.) | F23: Средняя стоимость изделия (руб.) | G23: Количество чеков (шт.) | H23: Средняя сумма чека (руб.) | I23: Трафик | J23: Длина чека (шт.) | K23: UNOde50 | L23: IS | M23: Agafi | N23: Kalliope | O23: Raganella | P23: CC/MP | Q23: Antyra | R23: SALE | S23: Конверсия | T23: % выполнения дневного плана | U23: выручка, план | V23: кол-во ед, план | W23: Кол-во чеков, план | X23: выручка, скорректир.план | Y23: кол-во ед, скорр. план | Z23: кол-во чеков, скорр. план | AA23: Коэфф. Дня Недели | AB23: Специфика месяца
B24: 1 | C24: 2 | D24: 3 | E24: 4 | F24: 5 | G24: 6 | H24: 7 | I24: 8 | J24: 9 | K24: 10 | L24: 11 | M24: 12 | N24: 13 | O24: 14 | P24: 15 | Q24: 16 | R24: 17 | S24: 17 | U24: 1 | V24: 2 | W24: 3 | X24: 4 | Y24: 5 | Z24: 6 | AA24: 10 | AB24: 11
A25: Рогалевич,Уразгильдеева | B25: 46082 | C25: вс | D25: 89496 | E25: 12 | F25: =IF(AND(E25<>"",E25<>0),D25/E25,"") -> 7458 | G25: 8 | H25: =IF(AND(G25<>"",G25<>0),D25/G25,"") -> 11187 | I25: 57 | J25: =IF(AND(G25<>"",G25<>0),E25/G25,"") -> 1.5 | Q25: 32552 | R25: 7690 | S25: =IF(AND(I25<>"",I25<>0),G25/I25,"") -> 0.14035088 | T25: =D25/U25 -> 1.8191975 | U25: =$I$8*AA25*AB25/SUMPRODUCT($AB$25:$AB$55,$AA$25:$AA$55) -> 49195.317 | V25: =$I$9*AA25*AB25/SUMPRODUCT($AB$25:$AB$55,$AA$25:$AA$55) -> 7.1297561 | W25: =IF($I$12="","",V25/$I$12) -> 4.097561 | X25: =IF(D25<>"",D25,U25) -> 89496 | Y25: =IF(E25<>"",E25,V25) -> 12 | Z25: =IF(G25<>"",G25,W25) -> 8 | AA25: 1 | AB25: 1
A26: Рогалевич | B26: 46083 | C26: пн | D26: 12184 | E26: 2 | F26: =IF(AND(E26<>"",E26<>0),D26/E26,"") -> 6092 | G26: 1 | H26: =IF(AND(G26<>"",G26<>0),D26/G26,"") -> 12184 | I26: 43 | J26: =IF(AND(G26<>"",G26<>0),E26/G26,"") -> 2 | S26: =IF(AND(I26<>"",I26<>0),G26/I26,"") -> 0.023255814 | T26: =D26/U26 -> 0.24766585 | U26: =$I$8*AA26*AB26/SUMPRODUCT($AB$25:$AB$55,$AA$25:$AA$55) -> 49195.317 | V26: =$I$9*AA26*AB26/SUMPRODUCT($AB$25:$AB$55,$AA$25:$AA$55) -> 7.1297561 | W26: =IF($I$12="","",V26/$I$12) -> 4.097561 | X26: =IF(AB26<>"",IF(D26<>"",D26,($I$8-SUM($X$25:X25))*AA26*AB26/SUMPRODUCT($AB26:$AB$55,$AA26:$AA$55)),"") -> 12184 | Y26: =IF(AB26<>"",IF(E26<>"",E26,($I$9-SUM($Y$25:Y25))*AA26*AB26/SUMPRODUCT($AB26:$AB$55,$AA26:$AA$55)),"") -> 2 | Z26: =IF(AB26<>"",IF(E26<>"",E26,($I$9-SUM($Y$25:Y25))*AA26*AB26/SUMPRODUCT($AB26:$AB$55,$AA26:$AA$55)),"") -> 2 | AA26: 1 | AB26: 1
A27: Рогалевич | B27: 46084 | C27: вт | D27: 6593 | E27: 1 | F27: =IF(AND(E27<>"",E27<>0),D27/E27,"") -> 6593 | G27: 1 | H27: =IF(AND(G27<>"",G27<>0),D27/G27,"") -> 6593 | I27: 22 | J27: =IF(AND(G27<>"",G27<>0),E27/G27,"") -> 1 | S27: =IF(AND(I27<>"",I27<>0),G27/I27,"") -> 0.045454545 | T27: =D27/U27 -> 0.13401682 | U27: =$I$8*AA27*AB27/SUMPRODUCT($AB$25:$AB$55,$AA$25:$AA$55) -> 49195.317 | V27: =$I$9*AA27*AB27/SUMPRODUCT($AB$25:$AB$55,$AA$25:$AA$55) -> 7.1297561 | W27: =IF($I$12="","",V27/$I$12) -> 4.097561 | X27: =IF(AB27<>"",IF(D27<>"",D27,($I$8-SUM($X$25:X26))*AA27*AB27/SUMPRODUCT($AB27:$AB$55,$AA27:$AA$55)),"") -> 6593 | Y27: =IF(AB27<>"",IF(E27<>"",E27,($I$9-SUM($Y$25:Y26))*AA27*AB27/SUMPRODUCT($AB27:$AB$55,$AA27:$AA$55)),"") -> 1 | Z27: =IF(AB27<>"",IF(E27<>"",E27,($I$9-SUM($Y$25:Y26))*AA27*AB27/SUMPRODUCT($AB27:$AB$55,$AA27:$AA$55)),"") -> 1 | AA27: 1 | AB27: 1
A28: Рогалевич.Уразгильдеева | B28: 46085 | C28: ср | D28: 0 | E28: 0 | F28: 0 | G28: 0 | H28: 0 | I28: 50 | J28: =IF(AND(G28<>"",G28<>0),E28/G28,"") | S28: =IF(AND(I28<>"",I28<>0),G28/I28,"") -> 0 | T28: =D28/U28 -> 0 | U28: =$I$8*AA28*AB28/SUMPRODUCT($AB$25:$AB$55,$AA$25:$AA$55) -> 49195.317 | V28: =$I$9*AA28*AB28/SUMPRODUCT($AB$25:$AB$55,$AA$25:$AA$55) -> 7.1297561 | W28: =IF($I$12="","",V28/$I$12) -> 4.097561 | X28: =IF(AB28<>"",IF(D28<>"",D28,($I$8-SUM($X$25:X27))*AA28*AB28/SUMPRODUCT($AB28:$AB$55,$AA28:$AA$55)),"") -> 0 | Y28: =IF(AB28<>"",IF(E28<>"",E28,($I$9-SUM($Y$25:Y27))*AA28*AB28/SUMPRODUCT($AB28:$AB$55,$AA28:$AA$55)),"") -> 0 | Z28: =IF(AB28<>"",IF(E28<>"",E28,($I$9-SUM($Y$25:Y27))*AA28*AB28/SUMPRODUCT($AB28:$AB$55,$AA28:$AA$55)),"") -> 0 | AA28: 1 | AB28: 1
A29: Рогалевич,Уразгильдеева | B29: 46086 | C29: чт | D29: 55266 | E29: 10 | F29: =IF(AND(E29<>"",E29<>0),D29/E29,"") -> 5526.6 | G29: 4 | H29: =IF(AND(G29<>"",G29<>0),D29/G29,"") -> 13816.5 | I29: 55 | J29: =IF(AND(G29<>"",G29<>0),E29/G29,"") -> 2.5 | Q29: 8790 | R29: 4753 | S29: =IF(AND(I29<>"",I29<>0),G29/I29,"") -> 0.072727273 | T29: =D29/U29 -> 1.1233996 | U29: =$I$8*AA29*AB29/SUMPRODUCT($AB$25:$AB$55,$AA$25:$AA$55) -> 49195.317 | V29: =$I$9*AA29*AB29/SUMPRODUCT($AB$25:$AB$55,$AA$25:$AA$55) -> 7.1297561 | W29: =IF($I$12="","",V29/$I$12) -> 4.097561 | X29: =IF(AB29<>"",IF(D29<>"",D29,($I$8-SUM($X$25:X28))*AA29*AB29/SUMPRODUCT($AB29:$AB$55,$AA29:$AA$55)),"") -> 55266 | Y29: =IF(AB29<>"",IF(E29<>"",E29,($I$9-SUM($Y$25:Y28))*AA29*AB29/SUMPRODUCT($AB29:$AB$55,$AA29:$AA$55)),"") -> 10 | Z29: =IF(AB29<>"",IF(E29<>"",E29,($I$9-SUM($Y$25:Y28))*AA29*AB29/SUMPRODUCT($AB29:$AB$55,$AA29:$AA$55)),"") -> 10 | AA29: 1 | AB29: 1
A30: Рогалевич,Уразгильдеева | B30: 46087 | C30: пт | D30: 34354 | E30: 6 | F30: =IF(AND(E30<>"",E30<>0),D30/E30,"") -> 5725.6667 | G30: 3 | H30: =IF(AND(G30<>"",G30<>0),D30/G30,"") -> 11451.333 | I30: 50 | J30: =IF(AND(G30<>"",G30<>0),E30/G30,"") -> 2 | S30: =IF(AND(I30<>"",I30<>0),G30/I30,"") -> 0.06 | T30: =D30/U30 -> 0.6983185 | U30: =$I$8*AA30*AB30/SUMPRODUCT($AB$25:$AB$55,$AA$25:$AA$55) -> 49195.317 | V30: =$I$9*AA30*AB30/SUMPRODUCT($AB$25:$AB$55,$AA$25:$AA$55) -> 7.1297561 | W30: =IF($I$12="","",V30/$I$12) -> 4.097561 | X30: =IF(AB30<>"",IF(D30<>"",D30,($I$8-SUM($X$25:X29))*AA30*AB30/SUMPRODUCT($AB30:$AB$55,$AA30:$AA$55)),"") -> 34354 | Y30: =IF(AB30<>"",IF(E30<>"",E30,($I$9-SUM($Y$25:Y29))*AA30*AB30/SUMPRODUCT($AB30:$AB$55,$AA30:$AA$55)),"") -> 6 | Z30: =IF(AB30<>"",IF(E30<>"",E30,($I$9-SUM($Y$25:Y29))*AA30*AB30/SUMPRODUCT($AB30:$AB$55,$AA30:$AA$55)),"") -> 6 | AA30: 1 | AB30: 1
A31: Рогалевич,Уразгильдеева | B31: 46088 | C31: сб | D31: 81583 | E31: 15 | F31: =IF(AND(E31<>"",E31<>0),D31/E31,"") -> 5438.8667 | G31: 10 | H31: =IF(AND(G31<>"",G31<>0),D31/G31,"") -> 8158.3 | I31: 82 | J31: =IF(AND(G31<>"",G31<>0),E31/G31,"") -> 1.5 | R31: 2793 | S31: =IF(AND(I31<>"",I31<>0),G31/I31,"") -> 0.12195122 | T31: =D31/U31 -> 1.6583489 | U31: =$I$8*AA31*AB31/SUMPRODUCT($AB$25:$AB$55,$AA$25:$AA$55) -> 49195.317 | V31: =$I$9*AA31*AB31/SUMPRODUCT($AB$25:$AB$55,$AA$25:$AA$55) -> 7.1297561 | W31: =IF($I$12="","",V31/$I$12) -> 4.097561 | X31: =IF(AB31<>"",IF(D31<>"",D31,($I$8-SUM($X$25:X30))*AA31*AB31/SUMPRODUCT($AB31:$AB$55,$AA31:$AA$55)),"") -> 81583 | Y31: =IF(AB31<>"",IF(E31<>"",E31,($I$9-SUM($Y$25:Y30))*AA31*AB31/SUMPRODUCT($AB31:$AB$55,$AA31:$AA$55)),"") -> 15 | Z31: =IF(AB31<>"",IF(E31<>"",E31,($I$9-SUM($Y$25:Y30))*AA31*AB31/SUMPRODUCT($AB31:$AB$55,$AA31:$AA$55)),"") -> 15 | AA31: 1 | AB31: 1
A32: Рогалевич,Уразгильдеева | B32: 46089 | C32: вс | D32: 185650 | E32: 17 | F32: =IF(AND(E32<>"",E32<>0),D32/E32,"") -> 10920.588 | G32: 11 | H32: =IF(AND(G32<>"",G32<>0),D32/G32,"") -> 16877.273 | I32: 148 | J32: =IF(AND(G32<>"",G32<>0),E32/G32,"") -> 1.5454545 | K32: 124299 | N32: 6191 | S32: =IF(AND(I32<>"",I32<>0),G32/I32,"") -> 0.074324324 | T32: =D32/U32 -> 3.7737332 | U32: =$I$8*AA32*AB32/SUMPRODUCT($AB$25:$AB$55,$AA$25:$AA$55) -> 49195.317 | V32: =$I$9*AA32*AB32/SUMPRODUCT($AB$25:$AB$55,$AA$25:$AA$55) -> 7.1297561 | W32: =IF($I$12="","",V32/$I$12) -> 4.097561 | X32: =IF(AB32<>"",IF(D32<>"",D32,($I$8-SUM($X$25:X31))*AA32*AB32/SUMPRODUCT($AB32:$AB$55,$AA32:$AA$55)),"") -> 185650 | Y32: =IF(AB32<>"",IF(E32<>"",E32,($I$9-SUM($Y$25:Y31))*AA32*AB32/SUMPRODUCT($AB32:$AB$55,$AA32:$AA$55)),"") -> 17 | Z32: =IF(AB32<>"",IF(E32<>"",E32,($I$9-SUM($Y$25:Y31))*AA32*AB32/SUMPRODUCT($AB32:$AB$55,$AA32:$AA$55)),"") -> 17 | AA32: 1 | AB32: 1
A33: Рогалевич | B33: 46090 | C33: пн | D33: 20092 | E33: 3 | F33: =IF(AND(E33<>"",E33<>0),D33/E33,"") -> 6697.3333 | G33: 2 | H33: =IF(AND(G33<>"",G33<>0),D33/G33,"") -> 10046 | I33: 66 | J33: =IF(AND(G33<>"",G33<>0),E33/G33,"") -> 1.5 | S33: =IF(AND(I33<>"",I33<>0),G33/I33,"") -> 0.03030303 | T33: =D33/U33 -> 0.40841286 | U33: =$I$8*AA33*AB33/SUMPRODUCT($AB$25:$AB$55,$AA$25:$AA$55) -> 49195.317 | V33: =$I$9*AA33*AB33/SUMPRODUCT($AB$25:$AB$55,$AA$25:$AA$55) -> 7.1297561 | W33: =IF($I$12="","",V33/$I$12) -> 4.097561 | X33: =IF(AB33<>"",IF(D33<>"",D33,($I$8-SUM($X$25:X32))*AA33*AB33/SUMPRODUCT($AB33:$AB$55,$AA33:$AA$55)),"") -> 20092 | Y33: =IF(AB33<>"",IF(E33<>"",E33,($I$9-SUM($Y$25:Y32))*AA33*AB33/SUMPRODUCT($AB33:$AB$55,$AA33:$AA$55)),"") -> 3 | Z33: =IF(AB33<>"",IF(E33<>"",E33,($I$9-SUM($Y$25:Y32))*AA33*AB33/SUMPRODUCT($AB33:$AB$55,$AA33:$AA$55)),"") -> 3 | AA33: 1 | AB33: 1
A34: Рогалевич | B34: 46091 | C34: вт | D34: 38929 | E34: 7 | F34: =IF(AND(E34<>"",E34<>0),D34/E34,"") -> 5561.2857 | G34: 6 | H34: =IF(AND(G34<>"",G34<>0),D34/G34,"") -> 6488.1667 | I34: 75 | J34: =IF(AND(G34<>"",G34<>0),E34/G34,"") -> 1.1666667 | K34: 9493 | S34: =IF(AND(I34<>"",I34<>0),G34/I34,"") -> 0.08 | T34: =D34/U34 -> 0.79131516 | U34: =$I$8*AA34*AB34/SUMPRODUCT($AB$25:$AB$55,$AA$25:$AA$55) -> 49195.317 | V34: =$I$9*AA34*AB34/SUMPRODUCT($AB$25:$AB$55,$AA$25:$AA$55) -> 7.1297561 | W34: =IF($I$12="","",V34/$I$12) -> 4.097561 | X34: =IF(AB34<>"",IF(D34<>"",D34,($I$8-SUM($X$25:X33))*AA34*AB34/SUMPRODUCT($AB34:$AB$55,$AA34:$AA$55)),"") -> 38929 | Y34: =IF(AB34<>"",IF(E34<>"",E34,($I$9-SUM($Y$25:Y33))*AA34*AB34/SUMPRODUCT($AB34:$AB$55,$AA34:$AA$55)),"") -> 7 | Z34: =IF(AB34<>"",IF(E34<>"",E34,($I$9-SUM($Y$25:Y33))*AA34*AB34/SUMPRODUCT($AB34:$AB$55,$AA34:$AA$55)),"") -> 7 | AA34: 1 | AB34: 1
A35: Уразгильдеева | B35: 46092 | C35: ср | D35: 21079 | E35: 3 | F35: =IF(AND(E35<>"",E35<>0),D35/E35,"") -> 7026.3333 | G35: 3 | H35: =IF(AND(G35<>"",G35<>0),D35/G35,"") -> 7026.3333 | I35: 52 | J35: =IF(AND(G35<>"",G35<>0),E35/G35,"") -> 1 | K35: 9993 | S35: =IF(AND(I35<>"",I35<>0),G35/I35,"") -> 0.057692308 | T35: =D35/U35 -> 0.42847574 | U35: =$I$8*AA35*AB35/SUMPRODUCT($AB$25:$AB$55,$AA$25:$AA$55) -> 49195.317 | V35: =$I$9*AA35*AB35/SUMPRODUCT($AB$25:$AB$55,$AA$25:$AA$55) -> 7.1297561 | W35: =IF($I$12="","",V35/$I$12) -> 4.097561 | X35: =IF(AB35<>"",IF(D35<>"",D35,($I$8-SUM($X$25:X34))*AA35*AB35/SUMPRODUCT($AB35:$AB$55,$AA35:$AA$55)),"") -> 21079 | Y35: =IF(AB35<>"",IF(E35<>"",E35,($I$9-SUM($Y$25:Y34))*AA35*AB35/SUMPRODUCT($AB35:$AB$55,$AA35:$AA$55)),"") -> 3 | Z35: =IF(AB35<>"",IF(E35<>"",E35,($I$9-SUM($Y$25:Y34))*AA35*AB35/SUMPRODUCT($AB35:$AB$55,$AA35:$AA$55)),"") -> 3 | AA35: 1 | AB35: 1
A36: Рогалевич,Уразгильдеева | B36: 46093 | C36: чт | D36: 50652 | E36: 6 | F36: =IF(AND(E36<>"",E36<>0),D36/E36,"") -> 8442 | G36: 3 | H36: =IF(AND(G36<>"",G36<>0),D36/G36,"") -> 16884 | I36: 45 | J36: =IF(AND(G36<>"",G36<>0),E36/G36,"") -> 2 | P36: 7093 | Q36: 16890 | R36: 6490 | S36: =IF(AND(I36<>"",I36<>0),G36/I36,"") -> 0.066666667 | T36: =D36/U36 -> 1.0296102 | U36: =$I$8*AA36*AB36/SUMPRODUCT($AB$25:$AB$55,$AA$25:$AA$55) -> 49195.317 | V36: =$I$9*AA36*AB36/SUMPRODUCT($AB$25:$AB$55,$AA$25:$AA$55) -> 7.1297561 | W36: =IF($I$12="","",V36/$I$12) -> 4.097561 | X36: =IF(AB36<>"",IF(D36<>"",D36,($I$8-SUM($X$25:X35))*AA36*AB36/SUMPRODUCT($AB36:$AB$55,$AA36:$AA$55)),"") -> 50652 | Y36: =IF(AB36<>"",IF(E36<>"",E36,($I$9-SUM($Y$25:Y35))*AA36*AB36/SUMPRODUCT($AB36:$AB$55,$AA36:$AA$55)),"") -> 6 | Z36: =IF(AB36<>"",IF(E36<>"",E36,($I$9-SUM($Y$25:Y35))*AA36*AB36/SUMPRODUCT($AB36:$AB$55,$AA36:$AA$55)),"") -> 6 | AA36: 1 | AB36: 1
A37: Рогалевич,Самошкина | B37: 46094 | C37: пт | D37: 18979 | E37: 3 | F37: =IF(AND(E37<>"",E37<>0),D37/E37,"") -> 6326.3333 | G37: 3 | H37: =IF(AND(G37<>"",G37<>0),D37/G37,"") -> 6326.3333 | I37: 39 | J37: =IF(AND(G37<>"",G37<>0),E37/G37,"") -> 1 | S37: =IF(AND(I37<>"",I37<>0),G37/I37,"") -> 0.076923077 | T37: =D37/U37 -> 0.38578875 | U37: =$I$8*AA37*AB37/SUMPRODUCT($AB$25:$AB$55,$AA$25:$AA$55) -> 49195.317 | V37: =$I$9*AA37*AB37/SUMPRODUCT($AB$25:$AB$55,$AA$25:$AA$55) -> 7.1297561 | W37: =IF($I$12="","",V37/$I$12) -> 4.097561 | X37: =IF(AB37<>"",IF(D37<>"",D37,($I$8-SUM($X$25:X36))*AA37*AB37/SUMPRODUCT($AB37:$AB$55,$AA37:$AA$55)),"") -> 18979 | Y37: =IF(AB37<>"",IF(E37<>"",E37,($I$9-SUM($Y$25:Y36))*AA37*AB37/SUMPRODUCT($AB37:$AB$55,$AA37:$AA$55)),"") -> 3 | Z37: =IF(AB37<>"",IF(E37<>"",E37,($I$9-SUM($Y$25:Y36))*AA37*AB37/SUMPRODUCT($AB37:$AB$55,$AA37:$AA$55)),"") -> 3 | AA37: 1 | AB37: 1
A38: Рогалевич,Самошкина | B38: 46095 | C38: сб | D38: 54282 | E38: 6 | F38: =IF(AND(E38<>"",E38<>0),D38/E38,"") -> 9047 | G38: 3 | H38: =IF(AND(G38<>"",G38<>0),D38/G38,"") -> 18094 | I38: 40 | J38: =IF(AND(G38<>"",G38<>0),E38/G38,"") -> 2 | P38: 41805 | S38: =IF(AND(I38<>"",I38<>0),G38/I38,"") -> 0.075 | T38: =D38/U38 -> 1.1033977 | U38: =$I$8*AA38*AB38/SUMPRODUCT($AB$25:$AB$55,$AA$25:$AA$55) -> 49195.317 | V38: =$I$9*AA38*AB38/SUMPRODUCT($AB$25:$AB$55,$AA$25:$AA$55) -> 7.1297561 | W38: =IF($I$12="","",V38/$I$12) -> 4.097561 | X38: =IF(AB38<>"",IF(D38<>"",D38,($I$8-SUM($X$25:X37))*AA38*AB38/SUMPRODUCT($AB38:$AB$55,$AA38:$AA$55)),"") -> 54282 | Y38: =IF(AB38<>"",IF(E38<>"",E38,($I$9-SUM($Y$25:Y37))*AA38*AB38/SUMPRODUCT($AB38:$AB$55,$AA38:$AA$55)),"") -> 6 | Z38: =IF(AB38<>"",IF(E38<>"",E38,($I$9-SUM($Y$25:Y37))*AA38*AB38/SUMPRODUCT($AB38:$AB$55,$AA38:$AA$55)),"") -> 6 | AA38: 1 | AB38: 1
A39: Рогалевич,Самошкина | B39: 46096 | C39: вс | D39: 19385 | E39: 2 | F39: =IF(AND(E39<>"",E39<>0),D39/E39,"") -> 9692.5 | G39: 1 | H39: =IF(AND(G39<>"",G39<>0),D39/G39,"") -> 19385 | I39: 44 | J39: =IF(AND(G39<>"",G39<>0),E39/G39,"") -> 2 | O39: 15390 | S39: =IF(AND(I39<>"",I39<>0),G39/I39,"") -> 0.022727273 | T39: =D39/U39 -> 0.39404157 | U39: =$I$8*AA39*AB39/SUMPRODUCT($AB$25:$AB$55,$AA$25:$AA$55) -> 49195.317 | V39: =$I$9*AA39*AB39/SUMPRODUCT($AB$25:$AB$55,$AA$25:$AA$55) -> 7.1297561 | W39: =IF($I$12="","",V39/$I$12) -> 4.097561 | X39: =IF(AB39<>"",IF(D39<>"",D39,($I$8-SUM($X$25:X38))*AA39*AB39/SUMPRODUCT($AB39:$AB$55,$AA39:$AA$55)),"") -> 19385 | Y39: =IF(AB39<>"",IF(E39<>"",E39,($I$9-SUM($Y$25:Y38))*AA39*AB39/SUMPRODUCT($AB39:$AB$55,$AA39:$AA$55)),"") -> 2 | Z39: =IF(AB39<>"",IF(E39<>"",E39,($I$9-SUM($Y$25:Y38))*AA39*AB39/SUMPRODUCT($AB39:$AB$55,$AA39:$AA$55)),"") -> 2 | AA39: 1 | AB39: 1
A40: Уразгильдеева | B40: 46097 | C40: пн | D40: 92945 | E40: 15 | F40: =IF(AND(E40<>"",E40<>0),D40/E40,"") -> 6196.3333 | G40: 8 | H40: =IF(AND(G40<>"",G40<>0),D40/G40,"") -> 11618.125 | I40: 50 | J40: =IF(AND(G40<>"",G40<>0),E40/G40,"") -> 1.875 | K40: 17593 | P40: 7259 | Q40: 8240 | S40: =IF(AND(I40<>"",I40<>0),G40/I40,"") -> 0.16 | T40: =D40/U40 -> 1.8893058 | U40: =$I$8*AA40*AB40/SUMPRODUCT($AB$25:$AB$55,$AA$25:$AA$55) -> 49195.317 | V40: =$I$9*AA40*AB40/SUMPRODUCT($AB$25:$AB$55,$AA$25:$AA$55) -> 7.1297561 | W40: =IF($I$12="","",V40/$I$12) -> 4.097561 | X40: =IF(AB40<>"",IF(D40<>"",D40,($I$8-SUM($X$25:X39))*AA40*AB40/SUMPRODUCT($AB40:$AB$55,$AA40:$AA$55)),"") -> 92945 | Y40: =IF(AB40<>"",IF(E40<>"",E40,($I$9-SUM($Y$25:Y39))*AA40*AB40/SUMPRODUCT($AB40:$AB$55,$AA40:$AA$55)),"") -> 15 | Z40: =IF(AB40<>"",IF(E40<>"",E40,($I$9-SUM($Y$25:Y39))*AA40*AB40/SUMPRODUCT($AB40:$AB$55,$AA40:$AA$55)),"") -> 15 | AA40: 1 | AB40: 1
A41: Уразгильдеева | B41: 46098 | C41: вт | D41: 11392 | E41: 3 | F41: =IF(AND(E41<>"",E41<>0),D41/E41,"") -> 3797.3333 | G41: 2 | H41: =IF(AND(G41<>"",G41<>0),D41/G41,"") -> 5696 | I41: 30 | J41: =IF(AND(G41<>"",G41<>0),E41/G41,"") -> 1.5 | R41: 4190 | S41: =IF(AND(I41<>"",I41<>0),G41/I41,"") -> 0.066666667 | T41: =D41/U41 -> 0.23156676 | U41: =$I$8*AA41*AB41/SUMPRODUCT($AB$25:$AB$55,$AA$25:$AA$55) -> 49195.317 | V41: =$I$9*AA41*AB41/SUMPRODUCT($AB$25:$AB$55,$AA$25:$AA$55) -> 7.1297561 | W41: =IF($I$12="","",V41/$I$12) -> 4.097561 | X41: =IF(AB41<>"",IF(D41<>"",D41,($I$8-SUM($X$25:X40))*AA41*AB41/SUMPRODUCT($AB41:$AB$55,$AA41:$AA$55)),"") -> 11392 | Y41: =IF(AB41<>"",IF(E41<>"",E41,($I$9-SUM($Y$25:Y40))*AA41*AB41/SUMPRODUCT($AB41:$AB$55,$AA41:$AA$55)),"") -> 3 | Z41: =IF(AB41<>"",IF(E41<>"",E41,($I$9-SUM($Y$25:Y40))*AA41*AB41/SUMPRODUCT($AB41:$AB$55,$AA41:$AA$55)),"") -> 3 | AA41: 1 | AB41: 1
A42: Самошкина | B42: 46099 | C42: ср | D42: 0 | E42: 0 | F42: 0 | G42: 0 | H42: 0 | I42: 16 | J42: =IF(AND(G42<>"",G42<>0),E42/G42,"") | S42: =IF(AND(I42<>"",I42<>0),G42/I42,"") -> 0 | T42: =D42/U42 -> 0 | U42: =$I$8*AA42*AB42/SUMPRODUCT($AB$25:$AB$55,$AA$25:$AA$55) -> 49195.317 | V42: =$I$9*AA42*AB42/SUMPRODUCT($AB$25:$AB$55,$AA$25:$AA$55) -> 7.1297561 | W42: =IF($I$12="","",V42/$I$12) -> 4.097561 | X42: =IF(AB42<>"",IF(D42<>"",D42,($I$8-SUM($X$25:X41))*AA42*AB42/SUMPRODUCT($AB42:$AB$55,$AA42:$AA$55)),"") -> 0 | Y42: =IF(AB42<>"",IF(E42<>"",E42,($I$9-SUM($Y$25:Y41))*AA42*AB42/SUMPRODUCT($AB42:$AB$55,$AA42:$AA$55)),"") -> 0 | Z42: =IF(AB42<>"",IF(E42<>"",E42,($I$9-SUM($Y$25:Y41))*AA42*AB42/SUMPRODUCT($AB42:$AB$55,$AA42:$AA$55)),"") -> 0 | AA42: 1 | AB42: 1
A43: Самошкина | B43: 46100 | C43: чт | D43: 7885 | E43: 2 | F43: 3942 | G43: 2 | H43: =IF(AND(G43<>"",G43<>0),D43/G43,"") -> 3942.5 | I43: 51 | J43: =IF(AND(G43<>"",G43<>0),E43/G43,"") -> 1 | S43: =IF(AND(I43<>"",I43<>0),G43/I43,"") -> 0.039215686 | T43: =D43/U43 -> 0.014570862 | U43: =$I$8*AA43*AB43/SUMPRODUCT($AB$25:$AB$55,$AA$25:$AA$55) -> 541148.49 | V43: =$I$9*AA43*AB43/SUMPRODUCT($AB$25:$AB$55,$AA$25:$AA$55) -> 78.427317 | W43: =IF($I$12="","",V43/$I$12) -> 45.073171 | X43: =IF(AB43<>"",IF(D43<>"",D43,($I$8-SUM($X$25:X42))*AA43*AB43/SUMPRODUCT($AB43:$AB$55,$AA43:$AA$55)),"") -> 7885 | Y43: =IF(AB43<>"",IF(E43<>"",E43,($I$9-SUM($Y$25:Y42))*AA43*AB43/SUMPRODUCT($AB43:$AB$55,$AA43:$AA$55)),"") -> 2 | Z43: =IF(AB43<>"",IF(E43<>"",E43,($I$9-SUM($Y$25:Y42))*AA43*AB43/SUMPRODUCT($AB43:$AB$55,$AA43:$AA$55)),"") -> 2 | AA43: 1 | AB43: 11
A44: Самошкина | B44: 46101 | C44: пт | D44: 0 | E44: 0 | F44: 0 | G44: 0 | H44: 0 | I44: 51 | J44: =IF(AND(G44<>"",G44<>0),E44/G44,"") | S44: =IF(AND(I44<>"",I44<>0),G44/I44,"") -> 0 | T44: =D44/U44 -> 0 | U44: =$I$8*AA44*AB44/SUMPRODUCT($AB$25:$AB$55,$AA$25:$AA$55) -> 49195.317 | V44: =$I$9*AA44*AB44/SUMPRODUCT($AB$25:$AB$55,$AA$25:$AA$55) -> 7.1297561 | W44: =IF($I$12="","",V44/$I$12) -> 4.097561 | X44: =IF(AB44<>"",IF(D44<>"",D44,($I$8-SUM($X$25:X43))*AA44*AB44/SUMPRODUCT($AB44:$AB$55,$AA44:$AA$55)),"") -> 0 | Y44: =IF(AB44<>"",IF(E44<>"",E44,($I$9-SUM($Y$25:Y43))*AA44*AB44/SUMPRODUCT($AB44:$AB$55,$AA44:$AA$55)),"") -> 0 | Z44: =IF(AB44<>"",IF(E44<>"",E44,($I$9-SUM($Y$25:Y43))*AA44*AB44/SUMPRODUCT($AB44:$AB$55,$AA44:$AA$55)),"") -> 0 | AA44: 1 | AB44: 1
A45: Уразгильдеева | B45: 46102 | C45: сб | D45: 37167 | E45: 8 | F45: =IF(AND(E45<>"",E45<>0),D45/E45,"") -> 4645.875 | G45: 6 | H45: =IF(AND(G45<>"",G45<>0),D45/G45,"") -> 6194.5 | I45: 42 | J45: =IF(AND(G45<>"",G45<>0),E45/G45,"") -> 1.3333333 | R45: 13269 | S45: =IF(AND(I45<>"",I45<>0),G45/I45,"") -> 0.14285714 | T45: =D45/U45 -> 0.75549874 | U45: =$I$8*AA45*AB45/SUMPRODUCT($AB$25:$AB$55,$AA$25:$AA$55) -> 49195.317 | V45: =$I$9*AA45*AB45/SUMPRODUCT($AB$25:$AB$55,$AA$25:$AA$55) -> 7.1297561 | W45: =IF($I$12="","",V45/$I$12) -> 4.097561 | X45: =IF(AB45<>"",IF(D45<>"",D45,($I$8-SUM($X$25:X44))*AA45*AB45/SUMPRODUCT($AB45:$AB$55,$AA45:$AA$55)),"") -> 37167 | Y45: =IF(AB45<>"",IF(E45<>"",E45,($I$9-SUM($Y$25:Y44))*AA45*AB45/SUMPRODUCT($AB45:$AB$55,$AA45:$AA$55)),"") -> 8 | Z45: =IF(AB45<>"",IF(E45<>"",E45,($I$9-SUM($Y$25:Y44))*AA45*AB45/SUMPRODUCT($AB45:$AB$55,$AA45:$AA$55)),"") -> 8 | AA45: 1 | AB45: 1
A46: Уразгильдеева,Самошкина | B46: 46103 | C46: вс | D46: 4693 | E46: 1 | F46: =IF(AND(E46<>"",E46<>0),D46/E46,"") -> 4693 | G46: 1 | H46: =IF(AND(G46<>"",G46<>0),D46/G46,"") -> 4693 | I46: 54 | J46: =IF(AND(G46<>"",G46<>0),E46/G46,"") -> 1 | S46: =IF(AND(I46<>"",I46<>0),G46/I46,"") -> 0.018518519 | T46: =D46/U46 -> 0.095395259 | U46: =$I$8*AA46*AB46/SUMPRODUCT($AB$25:$AB$55,$AA$25:$AA$55) -> 49195.317 | V46: =$I$9*AA46*AB46/SUMPRODUCT($AB$25:$AB$55,$AA$25:$AA$55) -> 7.1297561 | W46: =IF($I$12="","",V46/$I$12) -> 4.097561 | X46: =IF(AB46<>"",IF(D46<>"",D46,($I$8-SUM($X$25:X45))*AA46*AB46/SUMPRODUCT($AB46:$AB$55,$AA46:$AA$55)),"") -> 4693 | Y46: =IF(AB46<>"",IF(E46<>"",E46,($I$9-SUM($Y$25:Y45))*AA46*AB46/SUMPRODUCT($AB46:$AB$55,$AA46:$AA$55)),"") -> 1 | Z46: =IF(AB46<>"",IF(E46<>"",E46,($I$9-SUM($Y$25:Y45))*AA46*AB46/SUMPRODUCT($AB46:$AB$55,$AA46:$AA$55)),"") -> 1 | AA46: 1 | AB46: 1
A47: Уразгильдеева | B47: 46104 | C47: пн | D47: 83292 | E47: 13 | F47: =IF(AND(E47<>"",E47<>0),D47/E47,"") -> 6407.0769 | G47: 5 | H47: =IF(AND(G47<>"",G47<>0),D47/G47,"") -> 16658.4 | I47: 49 | J47: =IF(AND(G47<>"",G47<>0),E47/G47,"") -> 2.6 | Q47: 17583 | S47: =IF(AND(I47<>"",I47<>0),G47/I47,"") -> 0.10204082 | T47: =D47/U47 -> 1.693088 | U47: =$I$8*AA47*AB47/SUMPRODUCT($AB$25:$AB$55,$AA$25:$AA$55) -> 49195.317 | V47: =$I$9*AA47*AB47/SUMPRODUCT($AB$25:$AB$55,$AA$25:$AA$55) -> 7.1297561 | W47: =IF($I$12="","",V47/$I$12) -> 4.097561 | X47: =IF(AB47<>"",IF(D47<>"",D47,($I$8-SUM($X$25:X46))*AA47*AB47/SUMPRODUCT($AB47:$AB$55,$AA47:$AA$55)),"") -> 83292 | Y47: =IF(AB47<>"",IF(E47<>"",E47,($I$9-SUM($Y$25:Y46))*AA47*AB47/SUMPRODUCT($AB47:$AB$55,$AA47:$AA$55)),"") -> 13 | Z47: =IF(AB47<>"",IF(E47<>"",E47,($I$9-SUM($Y$25:Y46))*AA47*AB47/SUMPRODUCT($AB47:$AB$55,$AA47:$AA$55)),"") -> 13 | AA47: 1 | AB47: 1
A48: Уразгильдеева | B48: 46105 | C48: вт | D48: 24862 | E48: 5 | F48: =IF(AND(E48<>"",E48<>0),D48/E48,"") -> 4972.4 | G48: 3 | H48: =IF(AND(G48<>"",G48<>0),D48/G48,"") -> 8287.3333 | I48: 47 | J48: =IF(AND(G48<>"",G48<>0),E48/G48,"") -> 1.6666667 | R48: 2790 | S48: =IF(AND(I48<>"",I48<>0),G48/I48,"") -> 0.063829787 | T48: =D48/U48 -> 0.50537331 | U48: =$I$8*AA48*AB48/SUMPRODUCT($AB$25:$AB$55,$AA$25:$AA$55) -> 49195.317 | V48: =$I$9*AA48*AB48/SUMPRODUCT($AB$25:$AB$55,$AA$25:$AA$55) -> 7.1297561 | W48: =IF($I$12="","",V48/$I$12) -> 4.097561 | X48: =IF(AB48<>"",IF(D48<>"",D48,($I$8-SUM($X$25:X47))*AA48*AB48/SUMPRODUCT($AB48:$AB$55,$AA48:$AA$55)),"") -> 24862 | Y48: =IF(AB48<>"",IF(E48<>"",E48,($I$9-SUM($Y$25:Y47))*AA48*AB48/SUMPRODUCT($AB48:$AB$55,$AA48:$AA$55)),"") -> 5 | Z48: =IF(AB48<>"",IF(E48<>"",E48,($I$9-SUM($Y$25:Y47))*AA48*AB48/SUMPRODUCT($AB48:$AB$55,$AA48:$AA$55)),"") -> 5 | AA48: 1 | AB48: 1
A49: Самошкина | B49: 46106 | C49: ср | D49: 17183 | E49: 2 | F49: 8592 | G49: 1 | H49: =IF(AND(G49<>"",G49<>0),D49/G49,"") -> 17183 | I49: 66 | J49: =IF(AND(G49<>"",G49<>0),E49/G49,"") -> 2 | S49: =IF(AND(I49<>"",I49<>0),G49/I49,"") -> 0.015151515 | T49: =D49/U49 -> 0.34928121 | U49: =$I$8*AA49*AB49/SUMPRODUCT($AB$25:$AB$55,$AA$25:$AA$55) -> 49195.317 | V49: =$I$9*AA49*AB49/SUMPRODUCT($AB$25:$AB$55,$AA$25:$AA$55) -> 7.1297561 | W49: =IF($I$12="","",V49/$I$12) -> 4.097561 | X49: =IF(AB49<>"",IF(D49<>"",D49,($I$8-SUM($X$25:X48))*AA49*AB49/SUMPRODUCT($AB49:$AB$55,$AA49:$AA$55)),"") -> 17183 | Y49: =IF(AB49<>"",IF(E49<>"",E49,($I$9-SUM($Y$25:Y48))*AA49*AB49/SUMPRODUCT($AB49:$AB$55,$AA49:$AA$55)),"") -> 2 | Z49: =IF(AB49<>"",IF(E49<>"",E49,($I$9-SUM($Y$25:Y48))*AA49*AB49/SUMPRODUCT($AB49:$AB$55,$AA49:$AA$55)),"") -> 2 | AA49: 1 | AB49: 1
A50: Самошкина | B50: 46107 | C50: чт | D50: 67031 | E50: 7 | F50: =IF(AND(E50<>"",E50<>0),D50/E50,"") -> 9575.8571 | G50: 4 | H50: =IF(AND(G50<>"",G50<>0),D50/G50,"") -> 16757.75 | I50: 68 | J50: =IF(AND(G50<>"",G50<>0),E50/G50,"") -> 1.75 | K50: 10990 | P50: 12290 | S50: =IF(AND(I50<>"",I50<>0),G50/I50,"") -> 0.058823529 | T50: =D50/U50 -> 1.3625484 | U50: =$I$8*AA50*AB50/SUMPRODUCT($AB$25:$AB$55,$AA$25:$AA$55) -> 49195.317 | V50: =$I$9*AA50*AB50/SUMPRODUCT($AB$25:$AB$55,$AA$25:$AA$55) -> 7.1297561 | W50: =IF($I$12="","",V50/$I$12) -> 4.097561 | X50: =IF(AB50<>"",IF(D50<>"",D50,($I$8-SUM($X$25:X49))*AA50*AB50/SUMPRODUCT($AB50:$AB$55,$AA50:$AA$55)),"") -> 67031 | Y50: =IF(AB50<>"",IF(E50<>"",E50,($I$9-SUM($Y$25:Y49))*AA50*AB50/SUMPRODUCT($AB50:$AB$55,$AA50:$AA$55)),"") -> 7 | Z50: =IF(AB50<>"",IF(E50<>"",E50,($I$9-SUM($Y$25:Y49))*AA50*AB50/SUMPRODUCT($AB50:$AB$55,$AA50:$AA$55)),"") -> 7 | AA50: 1 | AB50: 1
A51: Уразгильдеева | B51: 46108 | C51: пт | D51: 39568 | E51: 4 | F51: =IF(AND(E51<>"",E51<>0),D51/E51,"") -> 9892 | G51: 2 | H51: =IF(AND(G51<>"",G51<>0),D51/G51,"") -> 19784 | I51: 52 | J51: =IF(AND(G51<>"",G51<>0),E51/G51,"") -> 2 | O51: 21180 | P51: 13792 | S51: =IF(AND(I51<>"",I51<>0),G51/I51,"") -> 0.038461538 | T51: =D51/U51 -> 0.8043042 | U51: =$I$8*AA51*AB51/SUMPRODUCT($AB$25:$AB$55,$AA$25:$AA$55) -> 49195.317 | V51: =$I$9*AA51*AB51/SUMPRODUCT($AB$25:$AB$55,$AA$25:$AA$55) -> 7.1297561 | W51: =IF($I$12="","",V51/$I$12) -> 4.097561 | X51: =IF(AB51<>"",IF(D51<>"",D51,($I$8-SUM($X$25:X50))*AA51*AB51/SUMPRODUCT($AB51:$AB$55,$AA51:$AA$55)),"") -> 39568 | Y51: =IF(AB51<>"",IF(E51<>"",E51,($I$9-SUM($Y$25:Y50))*AA51*AB51/SUMPRODUCT($AB51:$AB$55,$AA51:$AA$55)),"") -> 4 | Z51: =IF(AB51<>"",IF(E51<>"",E51,($I$9-SUM($Y$25:Y50))*AA51*AB51/SUMPRODUCT($AB51:$AB$55,$AA51:$AA$55)),"") -> 4 | AA51: 1 | AB51: 1
A52: Уразгильдеева | B52: 46109 | C52: сб | D52: 60520 | E52: 10 | F52: =IF(AND(E52<>"",E52<>0),D52/E52,"") -> 6052 | G52: 5 | H52: =IF(AND(G52<>"",G52<>0),D52/G52,"") -> 12104 | I52: 43 | J52: =IF(AND(G52<>"",G52<>0),E52/G52,"") -> 2 | S52: =IF(AND(I52<>"",I52<>0),G52/I52,"") -> 0.11627907 | T52: =D52/U52 -> 1.2301984 | U52: =$I$8*AA52*AB52/SUMPRODUCT($AB$25:$AB$55,$AA$25:$AA$55) -> 49195.317 | V52: =$I$9*AA52*AB52/SUMPRODUCT($AB$25:$AB$55,$AA$25:$AA$55) -> 7.1297561 | W52: =IF($I$12="","",V52/$I$12) -> 4.097561 | X52: =IF(AB52<>"",IF(D52<>"",D52,($I$8-SUM($X$25:X51))*AA52*AB52/SUMPRODUCT($AB52:$AB$55,$AA52:$AA$55)),"") -> 60520 | Y52: =IF(AB52<>"",IF(E52<>"",E52,($I$9-SUM($Y$25:Y51))*AA52*AB52/SUMPRODUCT($AB52:$AB$55,$AA52:$AA$55)),"") -> 10 | Z52: =IF(AB52<>"",IF(E52<>"",E52,($I$9-SUM($Y$25:Y51))*AA52*AB52/SUMPRODUCT($AB52:$AB$55,$AA52:$AA$55)),"") -> 10 | AA52: 1 | AB52: 1
A53: Уразгильдеева | B53: 46110 | C53: вс | D53: 48038 | E53: 8 | F53: =IF(AND(E53<>"",E53<>0),D53/E53,"") -> 6004.75 | G53: 4 | H53: =IF(AND(G53<>"",G53<>0),D53/G53,"") -> 12009.5 | I53: 75 | J53: =IF(AND(G53<>"",G53<>0),E53/G53,"") -> 2 | R53: 3192 | S53: =IF(AND(I53<>"",I53<>0),G53/I53,"") -> 0.053333333 | T53: =D53/U53 -> 0.97647506 | U53: =$I$8*AA53*AB53/SUMPRODUCT($AB$25:$AB$55,$AA$25:$AA$55) -> 49195.317 | V53: =$I$9*AA53*AB53/SUMPRODUCT($AB$25:$AB$55,$AA$25:$AA$55) -> 7.1297561 | W53: =IF($I$12="","",V53/$I$12) -> 4.097561 | X53: =IF(AB53<>"",IF(D53<>"",D53,($I$8-SUM($X$25:X52))*AA53*AB53/SUMPRODUCT($AB53:$AB$55,$AA53:$AA$55)),"") -> 48038 | Y53: =IF(AB53<>"",IF(E53<>"",E53,($I$9-SUM($Y$25:Y52))*AA53*AB53/SUMPRODUCT($AB53:$AB$55,$AA53:$AA$55)),"") -> 8 | Z53: =IF(AB53<>"",IF(E53<>"",E53,($I$9-SUM($Y$25:Y52))*AA53*AB53/SUMPRODUCT($AB53:$AB$55,$AA53:$AA$55)),"") -> 8 | AA53: 1 | AB53: 1
A54: Самошкина | B54: 46111 | C54: пн | D54: 13977 | E54: 3 | F54: =IF(AND(E54<>"",E54<>0),D54/E54,"") -> 4659 | G54: 2 | H54: =IF(AND(G54<>"",G54<>0),D54/G54,"") -> 6988.5 | I54: 33 | J54: =IF(AND(G54<>"",G54<>0),E54/G54,"") -> 1.5 | S54: =IF(AND(I54<>"",I54<>0),G54/I54,"") -> 0.060606061 | T54: =D54/U54 -> 0.28411241 | U54: =$I$8*AA54*AB54/SUMPRODUCT($AB$25:$AB$55,$AA$25:$AA$55) -> 49195.317 | V54: =$I$9*AA54*AB54/SUMPRODUCT($AB$25:$AB$55,$AA$25:$AA$55) -> 7.1297561 | W54: =IF($I$12="","",V54/$I$12) -> 4.097561 | X54: =IF(AB54<>"",IF(D54<>"",D54,($I$8-SUM($X$25:X53))*AA54*AB54/SUMPRODUCT($AB54:$AB$55,$AA54:$AA$55)),"") -> 13977 | Y54: =IF(AB54<>"",IF(E54<>"",E54,($I$9-SUM($Y$25:Y53))*AA54*AB54/SUMPRODUCT($AB54:$AB$55,$AA54:$AA$55)),"") -> 3 | Z54: =IF(AB54<>"",IF(E54<>"",E54,($I$9-SUM($Y$25:Y53))*AA54*AB54/SUMPRODUCT($AB54:$AB$55,$AA54:$AA$55)),"") -> 3 | AA54: 1 | AB54: 1
A55: Самошкина | B55: 46112 | C55: вт | D55: 21719 | E55: 4 | F55: =IF(AND(E55<>"",E55<>0),D55/E55,"") -> 5429.75 | G55: 4 | H55: =IF(AND(G55<>"",G55<>0),D55/G55,"") -> 5429.75 | I55: 46 | J55: =IF(AND(G55<>"",G55<>0),E55/G55,"") -> 1 | R55: 2555 | S55: =IF(AND(I55<>"",I55<>0),G55/I55,"") -> 0.086956522 | T55: =D55/U55 -> 0.44148511 | U55: =$I$8*AA55*AB55/SUMPRODUCT($AB$25:$AB$55,$AA$25:$AA$55) -> 49195.317 | V55: =$I$9*AA55*AB55/SUMPRODUCT($AB$25:$AB$55,$AA$25:$AA$55) -> 7.1297561 | W55: =IF($I$12="","",V55/$I$12) -> 4.097561 | X55: =IF(AB55<>"",IF(D55<>"",D55,($I$8-SUM($X$25:X54))*AA55*AB55/SUMPRODUCT($AB55:$AB$55,$AA55:$AA$55)),"") -> 21719 | Y55: =IF(AB55<>"",IF(E55<>"",E55,($I$9-SUM($Y$25:Y54))*AA55*AB55/SUMPRODUCT($AB55:$AB$55,$AA55:$AA$55)),"") -> 4 | Z55: =IF(AB55<>"",IF(E55<>"",E55,($I$9-SUM($Y$25:Y54))*AA55*AB55/SUMPRODUCT($AB55:$AB$55,$AA55:$AA$55)),"") -> 4 | AA55: 1 | AB55: 1
B56: итого | D56: =SUM(D25:D55) -> 1218796 | E56: =SUM(E25:E55) -> 178 | F56: =IF(AND(E56<>"", E56<>0), D56/E56, "") -> 6847.1685 | G56: =SUM(G25:G55) -> 108 | H56: =IF(AND(G56<>"",G56<>0),D56/G56,"") -> 11285.148 | I56: =SUM(I25:I55)*0.8 -> 1312.8 | J56: =E56/G56 -> 1.6481481 | K56: =SUM(K25:K55) -> 172368 | L56: =SUM(L25:L55) -> 0 | M56: =SUM(M25:M55) -> 0 | N56: =SUM(N25:N55) -> 6191 | O56: =SUM(O25:O55) -> 36570 | P56: =SUM(P25:P55) -> 82239 | Q56: =SUM(Q25:Q55) -> 84055 | R56: =SUM(R25:R55) -> 47722 | S56: =IF(AND(I56<>"", I56<>0), G56/I56, "") -> 0.08226691 | T56: =D56/U56 -> 0.60425938 | U56: =SUM(U25:U55) -> 2017008 | V56: =SUM(V25:V55) -> 292.32 | W56: =SUM(W25:W55) -> 168 | X56: =SUM(X25:X55) -> 1218796 | Y56: =SUM(Y25:Y55) -> 178 | Z56: =SUM(Z25:Z55) -> 174
D57: =SUMIF(D25:D55,"",U25:U55)+D56 -> 1218796 | I57: =I56/J14 -> 42.348387
D58: =Рогалевич!D57+Самошкина!D57+Уразгильдеева!D57 -> 1218796 | E58: =Рогалевич!E57+Уразгильдеева!E57+Самошкина!E57 -> 182 | G58: =Рогалевич!G57+Уразгильдеева!G57+Самошкина!G57 -> 110 | I58: =Рогалевич!I57+Уразгильдеева!I57+Самошкина!I57 -> 1277 | K58: =Рогалевич!K57+Уразгильдеева!K57+Самошкина!K57 -> 172368 | L58: =Рогалевич!L57+Уразгильдеева!L57 -> 0 | M58: =Рогалевич!M57+Уразгильдеева!M57 -> 0 | N58: =Рогалевич!N57+Уразгильдеева!N57 -> 6191 | O58: =Уразгильдеева!O57+Рогалевич!O57 -> 36570 | P58: =Рогалевич!P57+Уразгильдеева!P57+Самошкина!P57 -> 82239 | Q58: =Уразгильдеева!Q57+Рогалевич!Q57 -> 84055 | R58: =Рогалевич!R57+Уразгильдеева!R57+Самошкина!R57 -> 47722

Sheet Конкурс
A2: Личный ежедневный КВП, %
A4: Сотруник | B4: 45282 | C4: 45283 | D4: 45284 | E4: 45285 | F4: 45286 | G4: 45287 | H4: 45288 | I4: 45289 | J4: 45290 | K4: 45291 | L4: Итого:
A5: Рогалевич Ирина | E5: 0.57 | F5: 0.73 | G5: 0.88 | H5: 0.98 | I5: 0.69 | J5: 1.82 | K5: 2.89
A6: Арапова Анна | C6: 0 | D6: 0 | E6: 0 | F6: 0 | G6: 0.83 | H6: 0 | I6: 0.28 | J6: 0.46 | K6: 0.89
A7: Уразгильдеева Екатерина | B7: 0.39 | C7: 0 | E7: 0 | F7: 0.49 | G7: 1.19 | H7: 0.69 | J7: 1.63 | K7: 0.81
A9: Личный КВП, баллы
A11: Сотруник | B11: 45282 | C11: 45283 | D11: 45284 | E11: 45285 | F11: 45286 | G11: 45287 | H11: 45288 | I11: 45289 | J11: 45290 | K11: 45291 | L11: Итого:
A12: Рогалевич Ирина | E12: 1 | F12: 1 | G12: 1 | H12: 1 | I12: 1 | J12: 2 | K12: 3 | L12: =SUM(B12:K12) -> 10
A13: Арапова Анна | L13: =SUM(B13:K13) -> 0
A14: Уразгильдеева Екатерина | B14: 1 | F14: 1 | G14: 2 | H14: 1 | J14: 1 | L14: =SUM(B14:K14) -> 6

Sheet Св. по пок.
A1: 1-20.08
A2: Показатель | D2: ='Ялта, Ленина, 18'!I3 -> ул. Набережная Ленина, 18 | G2: =График!B29 -> Рогалевич Ирина | J2: =График!B28 -> Уразгильдеева Екатерина | M2: =График!B27 -> Самошкина Алина
D3: Факт | F3: Прогноз | G3: Факт | I3: Прогноз | J3: Факт | L3: Прогноз | M3: Факт | O3: Прогноз
A4: Выручка | D4: ='Ялта, Ленина, 18'!K8 -> 0.60425938 | E4: ='Ялта, Ленина, 18'!J8 -> 1218796 | F4: ='Ялта, Ленина, 18'!M8 -> 0.60425938 | G4: =Рогалевич!N8 -> 0.75636055 | H4: =Рогалевич!M8 -> 474399 | I4: =Рогалевич!P8 -> 0.75636055 | J4: =Уразгильдеева!N8 -> 0.68291551 | K4: =Уразгильдеева!M8 -> 576247 | L4: =Уразгильдеева!P8 -> 0.68291551 | M4: ='[2]Яковенко А. К'!K8 -> #REF! | N4: ='[2]Яковенко А. К'!J8 -> #REF! | O4: ='[2]Яковенко А. К'!M8 -> #REF!
A5: Кол-во изделий | D5: ='Ялта, Ленина, 18'!K9 -> 0.60892173 | E5: ='Ялта, Ленина, 18'!J9 -> 178 | F5: ='Ялта, Ленина, 18'!M9 -> 0.60892173 | G5: =Рогалевич!N9 -> 0.69306624 | H5: =Рогалевич!M9 -> 63 | I5: =Рогалевич!P9 -> 0.69306624 | J5: =Уразгильдеева!N9 -> 0.77683895 | K5: =Уразгильдеева!M9 -> 95 | L5: =Уразгильдеева!P9 -> 0.77683895 | M5: ='[2]Яковенко А. К'!K9 -> #REF! | N5: ='[2]Яковенко А. К'!J9 -> #REF! | O5: ='[2]Яковенко А. К'!M9 -> #REF!
A6: Средний чек | D6: ='Ялта, Ленина, 18'!K10 -> 0.93995903 | E6: ='Ялта, Ленина, 18'!J10 -> 11285.148 | F6: ='Ялта, Ленина, 18'!M10 -> 0.93995903 | G6: =Рогалевич!N10 -> 0.94079746 | H6: =Рогалевич!M10 -> 11295.214 | I6: =Рогалевич!P10 -> 0.94079746 | J6: =Уразгильдеева!N10 -> 0.9599317 | K6: =Уразгильдеева!M10 -> 11524.94 | L6: =Уразгильдеева!P10 -> 0.9599317 | M6: ='[2]Яковенко А. К'!K10 -> #REF! | N6: ='[2]Яковенко А. К'!J10 -> #REF! | O6: ='[2]Яковенко А. К'!M10 -> #REF!
A7: Средняя стоимость изделия | D7: ='Ялта, Ленина, 18'!K11 -> 0.99234327 | E7: ='Ялта, Ленина, 18'!J11 -> 6847.1685 | F7: ='Ялта, Ленина, 18'!M11 -> 0.99234327 | G7: =Рогалевич!N11 -> 1.0913251 | H7: =Рогалевич!M11 -> 7530.1429 | I7: =Рогалевич!P11 -> 1.0913251 | J7: =Уразгильдеева!N11 -> 0.87909535 | K7: =Уразгильдеева!M11 -> 6065.7579 | L7: =Уразгильдеева!P11 -> 0.87909535 | M7: ='[2]Яковенко А. К'!K11 -> #REF! | N7: ='[2]Яковенко А. К'!J11 -> #REF! | O7: ='[2]Яковенко А. К'!M11 -> #REF!
A8: Длина чека | D8: ='Ялта, Ленина, 18'!K12 -> 0.94721158 | E8: ='Ялта, Ленина, 18'!J12 -> 1.6481481 | F8: ='Ялта, Ленина, 18'!M12 -> 0.94721158 | G8: =Рогалевич!N12 -> 0.86206897 | H8: =Рогалевич!M12 -> 1.5 | I8: =Рогалевич!P12 -> 0.86206897 | J8: =Уразгильдеева!N12 -> 1.091954 | K8: =Уразгильдеева!M12 -> 1.9 | L8: =Уразгильдеева!P12 -> 1.091954 | M8: ='[2]Яковенко А. К'!K12 -> #REF! | N8: ='[2]Яковенко А. К'!J12 -> #REF! | O8: ='[2]Яковенко А. К'!M12 -> #REF!
A9: Кол-во чеков | D9: ='Ялта, Ленина, 18'!K13 -> 0.64285714 | E9: ='Ялта, Ленина, 18'!J13 -> 108 | F9: ='Ялта, Ленина, 18'!M13 -> 0.64285714 | G9: =Рогалевич!N13 -> 0.80395683 | H9: =Рогалевич!M13 -> 42 | I9: =Рогалевич!P13 -> 0.80395683 | J9: =Уразгильдеева!N13 -> 0.71142093 | K9: =Уразгильдеева!M13 -> 50 | L9: =Уразгильдеева!P13 -> 0.71142093 | M9: ='[2]Яковенко А. К'!K13 -> #REF! | N9: ='[2]Яковенко А. К'!J13 -> #REF! | O9: ='[2]Яковенко А. К'!M13 -> #REF!
A10: Кол-во смен план/отработано | D10: ='Ялта, Ленина, 18'!K14 -> 1 | E10: ='Ялта, Ленина, 18'!J14 -> 31 | G10: =Рогалевич!N14 -> 1 | H10: =Рогалевич!M14 -> 14 | J10: =Уразгильдеева!N14 -> 1 | K10: =Уразгильдеева!M14 -> 17 | M10: ='[2]Яковенко А. К'!K14 -> #REF! | N10: ='[2]Яковенко А. К'!J14 -> #REF!
A11: Средние продажи в смену | D11: ='Ялта, Ленина, 18'!K15 -> 0.60425938 | E11: ='Ялта, Ленина, 18'!J15 -> 39316 | F11: ='Ялта, Ленина, 18'!M15 -> 0.60425938 | G11: =Рогалевич!N15 -> 0.52079859 | H11: =Рогалевич!M15 -> 33885.643 | I11: =Рогалевич!P15 -> 0.52079859 | J11: =Уразгильдеева!N15 -> 0.52097134 | K11: =Уразгильдеева!M15 -> 33896.882 | L11: =Уразгильдеева!P15 -> 0.52097134 | M11: ='[2]Яковенко А. К'!K15 -> #REF! | N11: ='[2]Яковенко А. К'!J15 -> #REF! | O11: ='[2]Яковенко А. К'!M15 -> #REF!
A12: Трафик | D12: ='Ялта, Ленина, 18'!K17 -> 0.93771429 | E12: ='Ялта, Ленина, 18'!J17 -> 1312.8 | F12: ='Ялта, Ленина, 18'!M17 -> 0.93771429 | G12: =Рогалевич!N17 -> 0.68451182 | H12: =Рогалевич!M17 -> 298 | I12: =Рогалевич!P17 -> 0.68451182 | J12: =Уразгильдеева!N17 -> 1.0500573 | K12: =Уразгильдеева!M17 -> 615 | L12: =Уразгильдеева!P17 -> 1.0500573 | M12: ='[2]Яковенко А. К'!K17 -> #REF! | N12: ='[2]Яковенко А. К'!J17 -> #REF! | O12: ='[2]Яковенко А. К'!M17 -> #REF!
A13: UNOde50 | D13: ='Ялта, Ленина, 18'!R19 -> 0 | E13: ='Ялта, Ленина, 18'!S18 -> 0 | F13: ='Ялта, Ленина, 18'!S19 -> 0 | G13: =Рогалевич!X19 -> 0 | H13: =Рогалевич!Y18 -> 0 | I13: =Рогалевич!Y19 -> 0 | J13: =Уразгильдеева!U19 -> 0 | K13: =Уразгильдеева!V18 -> 0 | L13: =Уразгильдеева!V19 -> 0 | M13: ='[2]Яковенко А. К'!S19 -> #REF! | N13: ='[2]Яковенко А. К'!T18 -> #REF! | O13: ='[2]Яковенко А. К'!T19 -> #REF!
A14: IS | D14: ='Ялта, Ленина, 18'!R13 -> 0 | E14: ='Ялта, Ленина, 18'!S12 -> 0 | F14: ='Ялта, Ленина, 18'!S13 -> 0 | G14: =Рогалевич!Y13 -> 0 | H14: =Рогалевич!Y12 -> 0 | I14: =Рогалевич!Z13 -> 0 | J14: =Уразгильдеева!U13 -> 0 | K14: =Уразгильдеева!V12 -> 0 | L14: =Уразгильдеева!V13 -> 0 | M14: ='[2]Яковенко А. К'!S13 -> #REF! | N14: ='[2]Яковенко А. К'!T12 -> #REF! | O14: ='[2]Яковенко А. К'!T13 -> #REF!
A15: ='Ялта, Ленина, 18'!M23 -> Agafi | D15: ='Ялта, Ленина, 18'!U13 -> 0 | E15: ='Ялта, Ленина, 18'!V12 -> 0 | F15: ='Ялта, Ленина, 18'!V13 -> 0 | G15: =Рогалевич!AB13 -> 0 | H15: =Рогалевич!AB12 -> 0 | I15: =Рогалевич!AC13 -> 0 | J15: =Уразгильдеева!X13 -> 0 | K15: =Уразгильдеева!Y12 -> 0 | L15: =Уразгильдеева!Y13 -> 0 | M15: ='[2]Яковенко А. К'!V13 -> #REF! | N15: ='[2]Яковенко А. К'!W12 -> #REF! | O15: ='[2]Яковенко А. К'!W13 -> #REF!
A16: Отклонение от плана | D16: ='Ялта, Ленина, 18'!J16 -> -798212 | G16: =Рогалевич!Q8 -> -152813.78 | J16: =Уразгильдеева!Q8 -> -267557.24 | M16: ='[2]Яковенко А. К'!N8 -> #REF!

Sheet План на день
A1: Выручка | B1: 73000
A2: Кол-во изделий | B2: =B1/B4 -> 10.57971
A3: Средний чек | B3: =B4*B5 -> 12006
A4: Средняя стоимость изделия | B4: ='Ялта, Ленина, 18'!I11 -> 6900
A5: Длина чека | B5: ='Ялта, Ленина, 18'!I12 -> 1.74
A6: Кол-во чеков | B6: =IF(B5<>0,B2/B5,"") -> 6.0802932
A7: Конверсия | B7: ='Ялта, Ленина, 18'!I20 -> 0.12
A8: IS | B8: =('Ялта, Ленина, 18'!R12-'Ялта, Ленина, 18'!S12)/('Ялта, Ленина, 18'!I14-'Ялта, Ленина, 18'!J14) -> #DIV/0!
A9: UNOde50 | B9: =('Ялта, Ленина, 18'!R18-'Ялта, Ленина, 18'!S18)/('Ялта, Ленина, 18'!I14-'Ялта, Ленина, 18'!J14) -> #DIV/0!
A10: ='Ялта, Ленина, 18'!M23 -> Agafi | B10: =('Ялта, Ленина, 18'!U12-'Ялта, Ленина, 18'!V12)/('Ялта, Ленина, 18'!I14-'Ялта, Ленина, 18'!J14) -> #DIV/0!

Sheet Рогалевич
B1: Специфика месяца
B2: (отчетная дата) | J2: ЕЖЕДНЕВНЫЙ ОТЧЕТ О ПРОДАЖАХ
B3: Осталось до выполнения плана!!! | J3: =График!B29 -> Рогалевич Ирина
C4: =L8-D57 -> 152813.78 | E4: =IF(L8<>0,C4/L8,0) -> 0.24363945
I6: Целевые показатели
I7: Показатель | L7: План | M7: Факт | N7: % выполнения | O7: Прогноз выполнения | P7: % выполнения по прогнозу | Q7: Отклонение | R7: Факт аналогичного месяца прошлого года | S7: Отклонение LFL
I8: Выручка | L8: ='Ялта, Ленина, 18'!I8/График!AJ30*График!AJ29 -> 627212.78 | M8: =D57 -> 474399 | N8: =IF(AND(L8<>"",L8<>0,M8<>""),M8/L8,"") -> 0.75636055 | O8: =IF(SUMIF($D$25:$D$56,">=0",$U$25:$U$56)<>0,L8*D57/SUMIF($D$25:$D$56,">=0",$U$25:$U$56),0) -> 474399 | P8: =IF(AND(L8<>"",L8<>0,O8<>"",O8<>0),O8/L8,"") -> 0.75636055 | Q8: =IF(AND(M8<>0,M8<>"",L8<>0,L8<>""),O8-L8,"") -> -152813.78 | S8: =IF(AND(R8<>"",R8<>0,O8<>"",O8<>0),-R8+O8,"") | T8: =IF(AND(S8<>"",S8<>0,R8<>0,R8<>""),S8/R8,"")
I9: Кол-во изделий | L9: =L8/L11 -> 90.900403 | M9: =E57 -> 63 | N9: =IF(AND(L9<>"",L9<>0,M9<>""),M9/L9,"") -> 0.69306624 | O9: =IF(SUMIF($E$25:$E$54,">=0",$V$25:$V$54)<>0,L9*E57/SUMIF($E$25:$E$54,">=0",$V$25:$V$54),0) -> 63 | P9: =IF(AND(L9<>"",L9<>0,O9<>"",O9<>0),O9/L9,"") -> 0.69306624 | Q9: =IF(AND(M9<>0,M9<>"",L9<>0,L9<>""),O9-L9,"") -> -27.900403 | R9: =R8/R11 -> #DIV/0! | S9: =IF(AND(R9<>"",R9<>0,O9<>"",O9<>0),-R9+O9,"") -> #DIV/0! | T9: =IF(AND(S9<>"",S9<>0,R9<>0,R9<>""),S9/R9,"") -> #DIV/0!
I10: Средний чек | L10: =L11*L12 -> 12006 | M10: =H57 -> 11295.214 | N10: =IF(AND(L10<>"",L10<>0,M10<>""),M10/L10,"") -> 0.94079746 | O10: =M10 -> 11295.214 | P10: =IF(AND(L10<>"",L10<>0,O10<>"",O10<>0),O10/L10,"") -> 0.94079746 | Q10: =IF(AND(M10<>0,M10<>"",L10<>0,L10<>""),O10-L10,"") -> -710.78571 | R10: =R11*R12 -> 0 | S10: =IF(AND(R10<>"",R10<>0,O10<>"",O10<>0),-R10+O10,"") | T10: =IF(AND(S10<>"",S10<>0,R10<>0,R10<>""),S10/R10,"")
I11: Средняя стоимость изделия | L11: ='Ялта, Ленина, 18'!I11 -> 6900 | M11: =F57 -> 7530.1429 | N11: =IF(AND(L11<>"",L11<>0,M11<>""),M11/L11,"") -> 1.0913251 | O11: =IF(O9>0,O8/O9,"") -> 7530.1429 | P11: =IF(AND(L11<>"",L11<>0,O11<>"",O11<>0),O11/L11,"") -> 1.0913251 | Q11: =IF(AND(M11<>0,M11<>"",L11<>0,L11<>""),O11-L11,"") -> 630.14286 | S11: =IF(AND(R11<>"",R11<>0,O11<>"",O11<>0),-R11+O11,"") | T11: =IF(AND(S11<>"",S11<>0,R11<>0,R11<>""),S11/R11,"")
I12: Длина чека | L12: ='Ялта, Ленина, 18'!I12 -> 1.74 | M12: =J57 -> 1.5 | N12: =IF(AND(L12<>"",L12<>0,M12<>""),M12/L12,"") -> 0.86206897 | O12: =M12 -> 1.5 | P12: =IF(AND(L12<>"",L12<>0,O12<>"",O12<>0),O12/L12,"") -> 0.86206897 | Q12: =IF(AND(M12<>0,M12<>"",L12<>0,L12<>""),O12-L12,"") -> -0.24 | S12: =IF(AND(R12<>"",R12<>0,O12<>"",O12<>0),-R12+O12,"") | T12: =IF(AND(S12<>"",S12<>0,R12<>0,R12<>""),S12/R12,"")
I13: Кол-во чеков | L13: =IF(L12<>0,L9/L12,"") -> 52.241611 | M13: =G57 -> 42 | N13: =IF(AND(L13<>"",L13<>0,M13<>""),M13/L13,"") -> 0.80395683 | O13: =IF(SUMIF($G$25:$G$54,">=0",$W$25:$W$54)<>0,L13*G57/SUMIF($G$25:$G$54,">=0",$W$25:$W$54),"") -> 42 | P13: =IF(AND(L13<>"",L13<>0,O13<>"",O13<>0),O13/L13,"") -> 0.80395683 | Q13: =IF(AND(M13<>0,M13<>"",L13<>0,L13<>""),O13-L13,"") -> -10.241611 | S13: =IF(AND(R13<>"",R13<>0,O13<>"",O13<>0),-R13+O13,"")
I14: Кол-во смен план/отработано | L14: =График!AI29 -> 14 | M14: 14 | N14: =IF(AND(L14<>"",L14<>0,M14<>""),M14/L14,"") -> 1 | O14: =L14 -> 14 | P14: =IF(AND(L14<>"",L14<>0,O14<>"",O14<>0),O14/L14,"") -> 1 | Q14: =IF(AND(M14<>0,M14<>"",L14<>0,L14<>""),O14-L14,"") -> 0 | S14: =IF(AND(R14<>"",R14<>0,O14<>"",O14<>0),-R14+O14,"") | T14: =IF(AND(S14<>"",S14<>0,R14<>0,R14<>""),S14/R14,"")
I15: Средние продажи в смену | L15: ='Ялта, Ленина, 18'!I15 -> 65064.774 | M15: =M8/M14 -> 33885.643 | N15: =IF(AND(L15<>"",L15<>0,M15<>""),M15/L15,"") -> 0.52079859 | O15: =M15 -> 33885.643 | P15: =IF(AND(L15<>"",L15<>0,O15<>"",O15<>0),O15/L15,"") -> 0.52079859 | Q15: =IF(AND(M15<>0,M15<>"",L15<>0,L15<>""),O15-L15,"") -> -31179.131 | S15: =IF(AND(R15<>"",R15<>0,O15<>"",O15<>0),-R15+O15,"") | T15: =IF(AND(S15<>"",S15<>0,R15<>0,R15<>""),S15/R15,"")
I16: Отставание/Перевыполнение | M16: =M8-L15*M14 -> -436507.84 | N16: =IF(AND(L16<>"",L16<>0,M16<>""),M16/L16,"") | O16: =M16 -> -436507.84 | P16: =IF(AND(L16<>"",L16<>0,O16<>"",O16<>0),O16/L16,"") | Q16: =IF(AND(M16<>0,M16<>"",L16<>0,L16<>""),O16-L16,"") | S16: =IF(AND(R16<>"",R16<>0,O16<>"",O16<>0),-R16+O16,"") | T16: =IF(AND(S16<>"",S16<>0,R16<>0,R16<>""),S16/R16,"")
I17: Трафик | L17: ='Ялта, Ленина, 18'!I17/График!AJ30*График!AJ29 -> 435.34676 | M17: =I57 -> 298 | N17: =IF(AND(L17<>"",L17<>0,M17<>""),M17/L17,"") -> 0.68451182 | O17: =M17/M14*L14 -> 298 | P17: =IF(AND(L17<>"",L17<>0,O17<>"",O17<>0),O17/L17,"") -> 0.68451182 | Q17: =IF(AND(M17<>0,M17<>"",L17<>0,L17<>""),O17-L17,"") -> -137.34676 | S17: =IF(AND(R17<>"",R17<>0,O17<>"",O17<>0),-R17+O17,"") | T17: =IF(AND(S17<>"",S17<>0,R17<>0,R17<>""),S17/R17,"")
N18: =IF(AND(L18<>"",L18<>0,M18<>""),M18/L18,"") | O18: =M18 -> 0 | P18: =IF(AND(L18<>"",L18<>0,O18<>"",O18<>0),O18/L18,"") | Q18: =IF(AND(M18<>0,M18<>"",L18<>0,L18<>""),O18-L18,"") | R18: 0 | S18: =IF(AND(R18<>"",R18<>0,O18<>"",O18<>0),-R18+O18,"") | T18: =IF(AND(S18<>"",S18<>0,R18<>0,R18<>""),S18/R18,"")
N19: =IF(AND(L19<>"",L19<>0,M19<>""),M19/L19,"") | O19: =M19 -> 0 | P19: =IF(AND(L19<>"",L19<>0,O19<>"",O19<>0),O19/L19,"") | Q19: =IF(AND(M19<>0,M19<>"",L19<>0,L19<>""),O19-L19,"") | R19: 0 | S19: =IF(AND(R19<>"",R19<>0,O19<>"",O19<>0),-R19+O19,"") | T19: =IF(AND(S19<>"",S19<>0,R19<>0,R19<>""),S19/R19,"")
I20: Конверсия план/факт | L20: ='Ялта, Ленина, 18'!I20 -> 0.12 | M20: =S57 -> 0.1409396 | N20: =M20/L20 -> 1.1744966 | O20: =IF(AND(N8<>0,L14<>0,I57<>0),(I57*S57+(I57/N8-I57)*L20)/(I57/N8),0) -> 0.13583789 | P20: =IF(AND(L20<>"",L20<>0,O20<>"",O20<>0),O20/L20,"") -> 1.1319824 | Q20: =IF(AND(M20<>0,M20<>"",L20<>0,L20<>""),O20-L20,"") -> 0.015837885 | S20: =IF(AND(R20<>"",R20<>0,O20<>"",O20<>0),-R20+O20,"") | T20: =IF(AND(S20<>"",S20<>0,R20<>0,R20<>""),S20/R20,"")
B22: Факт продаж за месяц | T22: % выполнения дневного плана | U22: Раcпределение плана по дням
B23: Дата | C23: День недели | D23: Выручка (руб) | E23: Кол-во единиц (шт.) | F23: Средняя стоимость изделия (руб.) | G23: Количество чеков (шт.) | H23: Средняя сумма чека (руб.) | I23: Трафик | J23: Длина чека (шт.) | K23: UNOde50 | L23: IS | M23: Agafi | N23: Kalliope | O23: Raganella | P23: CC\MP | Q23: Antura | R23: SALE | S23: Конверсия (%) | U23: выручка, план | V23: кол-во ед, план | W23: Кол-во чеков, план | X23: выручка, скорректир.план | Y23: кол-во ед, скорр. план | Z23: кол-во чеков, скорр. план | AA23: Коэфф. Дня Недели | AB23: Специфика месяца
B24: 1 | C24: 2 | D24: 3 | E24: 4 | F24: 5 | G24: 6 | H24: 7 | I24: 8 | J24: 9 | K24: 10 | L24: 11 | M24: 12 | N24: 13 | O24: 14 | Q24: 15 | R24: 16 | S24: 17 | U24: 1 | V24: 2 | W24: 3 | X24: 4 | Y24: 5 | Z24: 6 | AA24: 10 | AB24: 11
A25: 1 | B25: 46082 | C25: вс | D25: 70021 | E25: 9 | F25: =IF(AND(E25<>"",E25<>0),D25/E25,"") -> 7780.1111 | G25: 7 | H25: =IF(AND(G25<>"",G25<>0),D25/G25,"") -> 10003 | I25: 20 | J25: =IF(AND(G25<>"",G25<>0),E25/G25,"") -> 1.2857143 | Q25: 32552 | S25: =IF(AND(I25<>"",I25<>0),G25/I25,"") -> 0.35 | T25: =D25/U25 -> 1.5629369 | U25: =$L$8*AA25*AB25/SUMPRODUCT($AB$25:$AB$56,$AA$25:$AA$56) -> 44800.913 | V25: =$L$9*AA25*AB25/SUMPRODUCT($AB$25:$AB$56,$AA$25:$AA$56) -> 6.4928859 | W25: =IF($L$12="","",V25/$L$12) -> 3.7315436 | X25: =IF(D25<>"",D25,U25) -> 70021 | Y25: =IF(E25<>"",E25,V25) -> 9 | Z25: =IF(G25<>"",G25,W25) -> 7 | AA25: 1 | AB25: 1
A26: 2 | B26: 46083 | C26: пн | D26: 12184 | E26: 2 | F26: =IF(AND(E26<>"",E26<>0),D26/E26,"") -> 6092 | G26: 1 | H26: =IF(AND(G26<>"",G26<>0),D26/G26,"") -> 12184 | I26: 13 | J26: =IF(AND(G26<>"",G26<>0),E26/G26,"") -> 2 | S26: =IF(AND(I26<>"",I26<>0),G26/I26,"") -> 0.076923077 | T26: =D26/U26 -> 0.27195874 | U26: =$L$8*AA26*AB26/SUMPRODUCT($AB$25:$AB$56,$AA$25:$AA$56) -> 44800.913 | V26: =$L$9*AA26*AB26/SUMPRODUCT($AB$25:$AB$58,$AA$25:$AA$58) -> 6.4928859 | W26: =IF($L$12="","",V26/$L$12) -> 3.7315436 | X26: =IF(AB26<>"",IF(D26<>"",D26,($L$8-SUM($X$25:X25))*AA26*AB26/SUMPRODUCT($AB26:$AB$56,$AA26:$AA$56)),"") -> 12184 | Y26: =IF(AB26<>"",IF(E26<>"",E26,($L$9-SUM($Y$25:Y25))*AA26*AB26/SUMPRODUCT($AB26:$AB$58,$AA26:$AA$58)),"") -> 2 | Z26: =IF(AB26<>"",IF($L$12<>"",IF(G26<>"",G26,($L$9/$L$12-SUM($Z$25:Z25))*AA26*AB26/SUMPRODUCT($AB26:$AB$58,$AA26:$AA$58)),""),"") -> 1 | AA26: 1 | AB26: 1
A27: 3 | B27: 46084 | C27: вт | D27: 6593 | E27: 1 | F27: 6593 | G27: 1 | H27: =IF(AND(G27<>"",G27<>0),D27/G27,"") -> 6593 | I27: 10 | J27: =IF(AND(G27<>"",G27<>0),E27/G27,"") -> 1 | S27: =IF(AND(I27<>"",I27<>0),G27/I27,"") -> 0.1 | T27: =D27/U27 -> 0.14716218 | U27: =$L$8*AA27*AB27/SUMPRODUCT($AB$25:$AB$56,$AA$25:$AA$56) -> 44800.913 | V27: =$L$9*AA27*AB27/SUMPRODUCT($AB$25:$AB$58,$AA$25:$AA$58) -> 6.4928859 | W27: =IF($L$12="","",V27/$L$12) -> 3.7315436 | X27: =IF(AB27<>"",IF(D27<>"",D27,($L$8-SUM($X$25:X26))*AA27*AB27/SUMPRODUCT($AB27:$AB$58,$AA27:$AA$58)),"") -> 6593 | Y27: =IF(AB27<>"",IF(E27<>"",E27,($L$9-SUM($Y$25:Y26))*AA27*AB27/SUMPRODUCT($AB27:$AB$58,$AA27:$AA$58)),"") -> 1 | Z27: =IF(AB27<>"",IF($L$12<>"",IF(G27<>"",G27,($L$9/$L$12-SUM($Z$25:Z26))*AA27*AB27/SUMPRODUCT($AB27:$AB$58,$AA27:$AA$58)),""),"") -> 1 | AA27: 1 | AB27: 1
A28: 4 | B28: 46085 | C28: ср | D28: 0 | E28: 0 | F28: 0 | G28: 0 | H28: 0 | I28: 10 | J28: =IF(AND(G28<>"",G28<>0),E28/G28,"") | S28: =IF(AND(I28<>"",I28<>0),G28/I28,"") -> 0 | T28: =D28/U28 -> 0 | U28: =$L$8*AA28*AB28/SUMPRODUCT($AB$25:$AB$56,$AA$25:$AA$56) -> 44800.913 | V28: =$L$9*AA28*AB28/SUMPRODUCT($AB$25:$AB$58,$AA$25:$AA$58) -> 6.4928859 | W28: =IF($L$12="","",V28/$L$12) -> 3.7315436 | X28: =IF(AB28<>"",IF(D28<>"",D28,($L$8-SUM($X$25:X27))*AA28*AB28/SUMPRODUCT($AB28:$AB$58,$AA28:$AA$58)),"") -> 0 | Y28: =IF(AB28<>"",IF(E28<>"",E28,($L$9-SUM($Y$25:Y27))*AA28*AB28/SUMPRODUCT($AB28:$AB$58,$AA28:$AA$58)),"") -> 0 | Z28: =IF(AB28<>"",IF($L$12<>"",IF(G28<>"",G28,($L$9/$L$12-SUM($Z$25:Z27))*AA28*AB28/SUMPRODUCT($AB28:$AB$58,$AA28:$AA$58)),""),"") -> 0 | AA28: 1 | AB28: 1
A29: 5 | B29: 46086 | C29: чт | D29: 20466 | E29: 4 | F29: =IF(AND(E29<>"",E29<>0),D29/E29,"") -> 5116.5 | G29: 1 | H29: =IF(AND(G29<>"",G29<>0),D29/G29,"") -> 20466 | I29: 15 | J29: =IF(AND(G29<>"",G29<>0),E29/G29,"") -> 4 | Q29: 8790 | S29: =IF(AND(I29<>"",I29<>0),G29/I29,"") -> 0.066666667 | T29: =D29/U29 -> 0.45682105 | U29: =$L$8*AA29*AB29/SUMPRODUCT($AB$25:$AB$56,$AA$25:$AA$56) -> 44800.913 | V29: =$L$9*AA29*AB29/SUMPRODUCT($AB$25:$AB$58,$AA$25:$AA$58) -> 6.4928859 | W29: =IF($L$12="","",V29/$L$12) -> 3.7315436 | X29: =IF(AB29<>"",IF(D29<>"",D29,($L$8-SUM($X$25:X28))*AA29*AB29/SUMPRODUCT($AB29:$AB$58,$AA29:$AA$58)),"") -> 20466 | Y29: =IF(AB29<>"",IF(E29<>"",E29,($L$9-SUM($Y$25:Y28))*AA29*AB29/SUMPRODUCT($AB29:$AB$58,$AA29:$AA$58)),"") -> 4 | Z29: =IF(AB29<>"",IF($L$12<>"",IF(G29<>"",G29,($L$9/$L$12-SUM($Z$25:Z28))*AA29*AB29/SUMPRODUCT($AB29:$AB$58,$AA29:$AA$58)),""),"") -> 1 | AA29: 1 | AB29: 1
A30: 6 | B30: 46087 | C30: пт | D30: 21978 | E30: 3 | F30: =IF(AND(E30<>"",E30<>0),D30/E30,"") -> 7326 | G30: 2 | H30: =IF(AND(G30<>"",G30<>0),D30/G30,"") -> 10989 | I30: 10 | J30: =IF(AND(G30<>"",G30<>0),E30/G30,"") -> 1.5 | S30: =IF(AND(I30<>"",I30<>0),G30/I30,"") -> 0.2 | T30: =D30/U30 -> 0.49057036 | U30: =$L$8*AA30*AB30/SUMPRODUCT($AB$25:$AB$56,$AA$25:$AA$56) -> 44800.913 | V30: =$L$9*AA30*AB30/SUMPRODUCT($AB$25:$AB$58,$AA$25:$AA$58) -> 6.4928859 | W30: =IF($L$12="","",V30/$L$12) -> 3.7315436 | X30: =IF(AB30<>"",IF(D30<>"",D30,($L$8-SUM($X$25:X29))*AA30*AB30/SUMPRODUCT($AB30:$AB$58,$AA30:$AA$58)),"") -> 21978 | Y30: =IF(AB30<>"",IF(E30<>"",E30,($L$9-SUM($Y$25:Y29))*AA30*AB30/SUMPRODUCT($AB30:$AB$58,$AA30:$AA$58)),"") -> 3 | Z30: =IF(AB30<>"",IF($L$12<>"",IF(G30<>"",G30,($L$9/$L$12-SUM($Z$25:Z29))*AA30*AB30/SUMPRODUCT($AB30:$AB$58,$AA30:$AA$58)),""),"") -> 2 | AA30: 1 | AB30: 1
A31: 7 | B31: 46088 | C31: сб | D31: 34746 | E31: 7 | F31: =IF(AND(E31<>"",E31<>0),D31/E31,"") -> 4963.7143 | G31: 6 | H31: =IF(AND(G31<>"",G31<>0),D31/G31,"") -> 5791 | I31: 25 | J31: =IF(AND(G31<>"",G31<>0),E31/G31,"") -> 1.1666667 | R31: 2793 | S31: =IF(AND(I31<>"",I31<>0),G31/I31,"") -> 0.24 | T31: =D31/U31 -> 0.77556456 | U31: =$L$8*AA31*AB31/SUMPRODUCT($AB$25:$AB$56,$AA$25:$AA$56) -> 44800.913 | V31: =$L$9*AA31*AB31/SUMPRODUCT($AB$25:$AB$58,$AA$25:$AA$58) -> 6.4928859 | W31: =IF($L$12="","",V31/$L$12) -> 3.7315436 | X31: =IF(AB31<>"",IF(D31<>"",D31,($L$8-SUM($X$25:X30))*AA31*AB31/SUMPRODUCT($AB31:$AB$58,$AA31:$AA$58)),"") -> 34746 | Y31: =IF(AB31<>"",IF(E31<>"",E31,($L$9-SUM($Y$25:Y30))*AA31*AB31/SUMPRODUCT($AB31:$AB$58,$AA31:$AA$58)),"") -> 7 | Z31: =IF(AB31<>"",IF($L$12<>"",IF(G31<>"",G31,($L$9/$L$12-SUM($Z$25:Z30))*AA31*AB31/SUMPRODUCT($AB31:$AB$58,$AA31:$AA$58)),""),"") -> 6 | AA31: 1 | AB31: 1
A32: 8 | B32: 46089 | C32: вс | D32: =28093+100576+6191 -> 134860 | E32: 12 | F32: =IF(AND(E32<>"",E32<>0),D32/E32,"") -> 11238.333 | G32: 8 | H32: =IF(AND(G32<>"",G32<>0),D32/G32,"") -> 16857.5 | I32: 40 | J32: =IF(AND(G32<>"",G32<>0),E32/G32,"") -> 1.5 | K32: 100576 | N32: 6191 | S32: =IF(AND(I32<>"",I32<>0),G32/I32,"") -> 0.2 | T32: =D32/U32 -> 3.0102065 | U32: =$L$8*AA32*AB32/SUMPRODUCT($AB$25:$AB$56,$AA$25:$AA$56) -> 44800.913 | V32: =$L$9*AA32*AB32/SUMPRODUCT($AB$25:$AB$58,$AA$25:$AA$58) -> 6.4928859 | W32: =IF($L$12="","",V32/$L$12) -> 3.7315436 | X32: =IF(AB32<>"",IF(D32<>"",D32,($L$8-SUM($X$25:X31))*AA32*AB32/SUMPRODUCT($AB32:$AB$58,$AA32:$AA$58)),"") -> 134860 | Y32: =IF(AB32<>"",IF(E32<>"",E32,($L$9-SUM($Y$25:Y31))*AA32*AB32/SUMPRODUCT($AB32:$AB$58,$AA32:$AA$58)),"") -> 12 | Z32: =IF(AB32<>"",IF($L$12<>"",IF(G32<>"",G32,($L$9/$L$12-SUM($Z$25:Z31))*AA32*AB32/SUMPRODUCT($AB32:$AB$58,$AA32:$AA$58)),""),"") -> 8 | AA32: 1 | AB32: 1
A33: 9 | B33: 46090 | C33: пн | D33: 20092 | E33: 3 | F33: =IF(AND(E33<>"",E33<>0),D33/E33,"") -> 6697.3333 | G33: 2 | H33: =IF(AND(G33<>"",G33<>0),D33/G33,"") -> 10046 | I33: 40 | J33: =IF(AND(G33<>"",G33<>0),E33/G33,"") -> 1.5 | S33: =IF(AND(I33<>"",I33<>0),G33/I33,"") -> 0.05 | T33: =D33/U33 -> 0.44847301 | U33: =$L$8*AA33*AB33/SUMPRODUCT($AB$25:$AB$56,$AA$25:$AA$56) -> 44800.913 | V33: =$L$9*AA33*AB33/SUMPRODUCT($AB$25:$AB$58,$AA$25:$AA$58) -> 6.4928859 | W33: =IF($L$12="","",V33/$L$12) -> 3.7315436 | X33: =IF(AB33<>"",IF(D33<>"",D33,($L$8-SUM($X$25:X32))*AA33*AB33/SUMPRODUCT($AB33:$AB$58,$AA33:$AA$58)),"") -> 20092 | Y33: =IF(AB33<>"",IF(E33<>"",E33,($L$9-SUM($Y$25:Y32))*AA33*AB33/SUMPRODUCT($AB33:$AB$58,$AA33:$AA$58)),"") -> 3 | Z33: =IF(AB33<>"",IF($L$12<>"",IF(G33<>"",G33,($L$9/$L$12-SUM($Z$25:Z32))*AA33*AB33/SUMPRODUCT($AB33:$AB$58,$AA33:$AA$58)),""),"") -> 2 | AA33: 1 | AB33: 1
A34: 10 | B34: 46091 | C34: вт | D34: 38929 | E34: 7 | F34: =IF(AND(E34<>"",E34<>0),D34/E34,"") -> 5561.2857 | G34: 6 | H34: =IF(AND(G34<>"",G34<>0),D34/G34,"") -> 6488.1667 | I34: 40 | J34: =IF(AND(G34<>"",G34<>0),E34/G34,"") -> 1.1666667 | K34: 9493 | S34: =IF(AND(I34<>"",I34<>0),G34/I34,"") -> 0.15 | T34: =D34/U34 -> 0.86893319 | U34: =$L$8*AA34*AB34/SUMPRODUCT($AB$25:$AB$56,$AA$25:$AA$56) -> 44800.913 | V34: =$L$9*AA34*AB34/SUMPRODUCT($AB$25:$AB$58,$AA$25:$AA$58) -> 6.4928859 | W34: =IF($L$12="","",V34/$L$12) -> 3.7315436 | X34: =IF(AB34<>"",IF(D34<>"",D34,($L$8-SUM($X$25:X33))*AA34*AB34/SUMPRODUCT($AB34:$AB$58,$AA34:$AA$58)),"") -> 38929 | Y34: =IF(AB34<>"",IF(E34<>"",E34,($L$9-SUM($Y$25:Y33))*AA34*AB34/SUMPRODUCT($AB34:$AB$58,$AA34:$AA$58)),"") -> 7 | Z34: =IF(AB34<>"",IF($L$12<>"",IF(G34<>"",G34,($L$9/$L$12-SUM($Z$25:Z33))*AA34*AB34/SUMPRODUCT($AB34:$AB$58,$AA34:$AA$58)),""),"") -> 6 | AA34: 1 | AB34: 1
A35: 11 | B35: 46093 | C35: чт | D35: 32075 | E35: 3 | F35: =IF(AND(E35<>"",E35<>0),D35/E35,"") -> 10691.667 | G35: 1 | H35: =IF(AND(G35<>"",G35<>0),D35/G35,"") -> 32075 | I35: 18 | J35: =IF(AND(G35<>"",G35<>0),E35/G35,"") -> 3 | Q35: 16890 | S35: =IF(AND(I35<>"",I35<>0),G35/I35,"") -> 0.055555556 | T35: =D35/U35 -> 0.71594523 | U35: =$L$8*AA35*AB35/SUMPRODUCT($AB$25:$AB$56,$AA$25:$AA$56) -> 44800.913 | V35: =$L$9*AA35*AB35/SUMPRODUCT($AB$25:$AB$58,$AA$25:$AA$58) -> 6.4928859 | W35: =IF($L$12="","",V35/$L$12) -> 3.7315436 | X35: =IF(AB35<>"",IF(D35<>"",D35,($L$8-SUM($X$25:X34))*AA35*AB35/SUMPRODUCT($AB35:$AB$58,$AA35:$AA$58)),"") -> 32075 | Y35: =IF(AB35<>"",IF(E34<>"",E34,($L$9-SUM($Y$25:Y34))*AA35*AB35/SUMPRODUCT($AB35:$AB$58,$AA35:$AA$58)),"") -> 7 | Z35: =IF(AB35<>"",IF($L$12<>"",IF(G35<>"",G35,($L$9/$L$12-SUM($Z$25:Z34))*AA35*AB35/SUMPRODUCT($AB35:$AB$58,$AA35:$AA$58)),""),"") -> 1 | AA35: 1 | AB35: 1
A36: 12 | B36: 46094 | C36: пт | D36: 4693 | E36: 1 | F36: =IF(AND(E36<>"",E36<>0),D36/E36,"") -> 4693 | G36: 1 | H36: =IF(AND(G36<>"",G36<>0),D36/G36,"") -> 4693 | I36: 20 | J36: =IF(AND(G36<>"",G36<>0),E36/G36,"") -> 1 | S36: =IF(AND(I36<>"",I36<>0),G36/I36,"") -> 0.05 | T36: =D36/U36 -> 0.10475233 | U36: =$L$8*AA36*AB36/SUMPRODUCT($AB$25:$AB$56,$AA$25:$AA$56) -> 44800.913 | V36: =$L$9*AA36*AB36/SUMPRODUCT($AB$25:$AB$58,$AA$25:$AA$58) -> 6.4928859 | W36: =IF($L$12="","",V36/$L$12) -> 3.7315436 | X36: =IF(AB36<>"",IF(D36<>"",D36,($L$8-SUM($X$25:X35))*AA36*AB36/SUMPRODUCT($AB36:$AB$58,$AA36:$AA$58)),"") -> 4693 | Y36: =IF(AB36<>"",IF(E35<>"",E35,($L$9-SUM($Y$25:Y35))*AA36*AB36/SUMPRODUCT($AB36:$AB$58,$AA36:$AA$58)),"") -> 3 | Z36: =IF(AB36<>"",IF($L$12<>"",IF(G36<>"",G36,($L$9/$L$12-SUM($Z$25:Z35))*AA36*AB36/SUMPRODUCT($AB36:$AB$58,$AA36:$AA$58)),""),"") -> 1 | AA36: 1 | AB36: 1
A37: 13 | B37: 46095 | C37: сб | D37: =41805+4893 -> 46698 | E37: 4 | F37: =IF(AND(E37<>"",E37<>0),D37/E37,"") -> 11674.5 | G37: 2 | H37: =IF(AND(G37<>"",G37<>0),D37/G37,"") -> 23349 | I37: 15 | J37: =IF(AND(G37<>"",G37<>0),E37/G37,"") -> 2 | P37: 41805 | S37: =IF(AND(I37<>"",I37<>0),G37/I37,"") -> 0.13333333 | T37: =D37/U37 -> 1.0423448 | U37: =$L$8*AA37*AB37/SUMPRODUCT($AB$25:$AB$56,$AA$25:$AA$56) -> 44800.913 | V37: =$L$9*AA37*AB37/SUMPRODUCT($AB$25:$AB$58,$AA$25:$AA$58) -> 6.4928859 | W37: =IF($L$12="","",V37/$L$12) -> 3.7315436 | X37: =IF(AB37<>"",IF(D37<>"",D37,($L$8-SUM($X$25:X36))*AA37*AB37/SUMPRODUCT($AB37:$AB$58,$AA37:$AA$58)),"") -> 46698 | Y37: =IF(AB37<>"",IF(E37<>"",E37,($L$9-SUM($Y$25:Y36))*AA37*AB37/SUMPRODUCT($AB37:$AB$58,$AA37:$AA$58)),"") -> 4 | Z37: =IF(AB37<>"",IF($L$12<>"",IF(G37<>"",G37,($L$9/$L$12-SUM($Z$25:Z36))*AA37*AB37/SUMPRODUCT($AB37:$AB$58,$AA37:$AA$58)),""),"") -> 2 | AA37: 1 | AB37: 1
A38: .22 | B38: 46096 | C38: вс | D38: 19385 | E38: 2 | F38: =IF(AND(E38<>"",E38<>0),D38/E38,"") -> 9692.5 | G38: 1 | H38: =IF(AND(G38<>"",G38<>0),D38/G38,"") -> 19385 | I38: 22 | J38: =IF(AND(G38<>"",G38<>0),E38/G38,"") -> 2 | O38: 15390 | S38: =IF(AND(I38<>"",I38<>0),G38/I38,"") -> 0.045454545 | T38: =D38/U38 -> 0.43269208 | U38: =$L$8*AA38*AB38/SUMPRODUCT($AB$25:$AB$56,$AA$25:$AA$56) -> 44800.913 | V38: =$L$9*AA38*AB38/SUMPRODUCT($AB$25:$AB$58,$AA$25:$AA$58) -> 6.4928859 | W38: =IF($L$12="","",V38/$L$12) -> 3.7315436 | X38: =IF(AB38<>"",IF(D38<>"",D38,($L$8-SUM($X$25:X37))*AA38*AB38/SUMPRODUCT($AB38:$AB$58,$AA38:$AA$58)),"") -> 19385 | Y38: =IF(AB38<>"",IF(E38<>"",E38,($L$9-SUM($Y$25:Y37))*AA38*AB38/SUMPRODUCT($AB38:$AB$58,$AA38:$AA$58)),"") -> 2 | Z38: =IF(AB38<>"",IF($L$12<>"",IF(G38<>"",G38,($L$9/$L$12-SUM($Z$25:Z37))*AA38*AB38/SUMPRODUCT($AB38:$AB$58,$AA38:$AA$58)),""),"") -> 1 | AA38: 1 | AB38: 1
A39: 15 | F39: =IF(AND(E39<>"",E39<>0),D39/E39,"") | H39: =IF(AND(G39<>"",G39<>0),D39/G39,"") | J39: =IF(AND(G39<>"",G39<>0),E39/G39,"") | S39: =IF(AND(I39<>"",I39<>0),G39/I39,"") | T39: =D39/U39 -> #DIV/0! | U39: =$L$8*AA39*AB39/SUMPRODUCT($AB$25:$AB$56,$AA$25:$AA$56) -> 0 | V39: =$L$9*AA39*AB39/SUMPRODUCT($AB$25:$AB$58,$AA$25:$AA$58) -> 0 | W39: =IF($L$12="","",V39/$L$12) -> 0 | X39: =IF(AB39<>"",IF(D39<>"",D39,($L$8-SUM($X$25:X38))*AA39*AB39/SUMPRODUCT($AB39:$AB$58,$AA39:$AA$58)),"") | Y39: =IF(AB39<>"",IF(E39<>"",E39,($L$9-SUM($Y$25:Y38))*AA39*AB39/SUMPRODUCT($AB39:$AB$58,$AA39:$AA$58)),"") | Z39: =IF(AB39<>"",IF($L$12<>"",IF(G39<>"",G39,($L$9/$L$12-SUM($Z$25:Z38))*AA39*AB39/SUMPRODUCT($AB39:$AB$58,$AA39:$AA$58)),""),"")
A40: 16 | F40: =IF(AND(E40<>"",E40<>0),D40/E40,"") | H40: =IF(AND(G40<>"",G40<>0),D40/G40,"") | J40: =IF(AND(G40<>"",G40<>0),E40/G40,"") | S40: =IF(AND(I40<>"",I40<>0),G40/I40,"") | T40: =D40/U40 -> #DIV/0! | U40: =$L$8*AA40*AB40/SUMPRODUCT($AB$25:$AB$56,$AA$25:$AA$56) -> 0 | V40: =$L$9*AA40*AB40/SUMPRODUCT($AB$25:$AB$58,$AA$25:$AA$58) -> 0 | W40: =IF($L$12="","",V40/$L$12) -> 0 | X40: =IF(AB40<>"",IF(D40<>"",D40,($L$8-SUM($X$25:X39))*AA40*AB40/SUMPRODUCT($AB40:$AB$58,$AA40:$AA$58)),"") | Y40: =IF(AB40<>"",IF(E39<>"",E39,($L$9-SUM($Y$25:Y39))*AA40*AB40/SUMPRODUCT($AB40:$AB$58,$AA40:$AA$58)),"") | Z40: =IF(AB40<>"",IF($L$12<>"",IF(G40<>"",G40,($L$9/$L$12-SUM($Z$25:Z39))*AA40*AB40/SUMPRODUCT($AB40:$AB$58,$AA40:$AA$58)),""),"")
A41: 17 | F41: =IF(AND(E41<>"",E41<>0),D41/E41,"") | H41: =IF(AND(G41<>"",G41<>0),D41/G41,"") | J41: =IF(AND(G41<>"",G41<>0),E41/G41,"") | S41: =IF(AND(I41<>"",I41<>0),G41/I41,"") | T41: =D41/U41 -> #DIV/0! | U41: =$L$8*AA41*AB41/SUMPRODUCT($AB$25:$AB$56,$AA$25:$AA$56) -> 0 | V41: =$L$9*AA41*AB41/SUMPRODUCT($AB$25:$AB$58,$AA$25:$AA$58) -> 0 | W41: =IF($L$12="","",V41/$L$12) -> 0 | X41: =IF(AB41<>"",IF(D41<>"",D41,($L$8-SUM($X$25:X40))*AA41*AB41/SUMPRODUCT($AB41:$AB$58,$AA41:$AA$58)),"") | Y41: =IF(AB41<>"",IF(E40<>"",E40,($L$9-SUM($Y$25:Y40))*AA41*AB41/SUMPRODUCT($AB41:$AB$58,$AA41:$AA$58)),"") | Z41: =IF(AB41<>"",IF($L$12<>"",IF(G41<>"",G41,($L$9/$L$12-SUM($Z$25:Z40))*AA41*AB41/SUMPRODUCT($AB41:$AB$58,$AA41:$AA$58)),""),"")
A42: 18 | F42: =IF(AND(E42<>"",E42<>0),D42/E42,"") | H42: =IF(AND(G42<>"",G42<>0),D42/G42,"") | J42: =IF(AND(G42<>"",G42<>0),E42/G42,"") | S42: =IF(AND(I42<>"",I42<>0),G42/I42,"") | T42: =D42/U42 -> #DIV/0! | U42: =$L$8*AA42*AB42/SUMPRODUCT($AB$25:$AB$56,$AA$25:$AA$56) -> 0 | V42: =$L$9*AA42*AB42/SUMPRODUCT($AB$25:$AB$58,$AA$25:$AA$58) -> 0 | W42: =IF($L$12="","",V42/$L$12) -> 0 | X42: =IF(AB42<>"",IF(D42<>"",D42,($L$8-SUM($X$25:X41))*AA42*AB42/SUMPRODUCT($AB42:$AB$58,$AA42:$AA$58)),"") | Y42: =IF(AB42<>"",IF(E42<>"",E42,($L$9-SUM($Y$25:Y41))*AA42*AB42/SUMPRODUCT($AB42:$AB$58,$AA42:$AA$58)),"") | Z42: =IF(AB42<>"",IF($L$12<>"",IF(G42<>"",G42,($L$9/$L$12-SUM($Z$25:Z41))*AA42*AB42/SUMPRODUCT($AB42:$AB$58,$AA42:$AA$58)),""),"")
A43: 19 | J43: =IF(AND(G43<>"",G43<>0),E43/G43,"") | S43: =IF(AND(I43<>"",I43<>0),G43/I43,"") | T43: =D43/U43 -> #DIV/0! | U43: =$L$8*AA43*AB43/SUMPRODUCT($AB$25:$AB$56,$AA$25:$AA$56) -> 0 | V43: =$L$9*AA43*AB43/SUMPRODUCT($AB$25:$AB$58,$AA$25:$AA$58) -> 0 | W43: =IF($L$12="","",V43/$L$12) -> 0 | X43: =IF(AB43<>"",IF(D43<>"",D43,($L$8-SUM($X$25:X42))*AA43*AB43/SUMPRODUCT($AB43:$AB$58,$AA43:$AA$58)),"") | Y43: =IF(AB43<>"",IF(E43<>"",E43,($L$9-SUM($Y$25:Y42))*AA43*AB43/SUMPRODUCT($AB43:$AB$58,$AA43:$AA$58)),"") | Z43: =IF(AB43<>"",IF($L$12<>"",IF(G43<>"",G43,($L$9/$L$12-SUM($Z$25:Z42))*AA43*AB43/SUMPRODUCT($AB43:$AB$58,$AA43:$AA$58)),""),"")
A44: 20 | J44: =IF(AND(G44<>"",G44<>0),E44/G44,"") | S44: =IF(AND(I44<>"",I44<>0),G44/I44,"") | T44: =D44/U44 -> #DIV/0! | U44: =$L$8*AA44*AB44/SUMPRODUCT($AB$25:$AB$56,$AA$25:$AA$56) -> 0 | V44: =$L$9*AA44*AB44/SUMPRODUCT($AB$25:$AB$58,$AA$25:$AA$58) -> 0 | W44: =IF($L$12="","",V44/$L$12) -> 0 | X44: =IF(AB44<>"",IF(D44<>"",D44,($L$8-SUM($X$25:X43))*AA44*AB44/SUMPRODUCT($AB44:$AB$58,$AA44:$AA$58)),"") | Y44: =IF(AB44<>"",IF(E44<>"",E44,($L$9-SUM($Y$25:Y43))*AA44*AB44/SUMPRODUCT($AB44:$AB$58,$AA44:$AA$58)),"") | Z44: =IF(AB44<>"",IF($L$12<>"",IF(G44<>"",G44,($L$9/$L$12-SUM($Z$25:Z43))*AA44*AB44/SUMPRODUCT($AB44:$AB$58,$AA44:$AA$58)),""),"")
A45: 21 | J45: =IF(AND(G45<>"",G45<>0),E45/G45,"") | S45: =IF(AND(I45<>"",I45<>0),G45/I45,"") | T45: =D45/U45 -> #DIV/0! | U45: =$L$8*AA45*AB45/SUMPRODUCT($AB$25:$AB$56,$AA$25:$AA$56) -> 0 | V45: =$L$9*AA45*AB45/SUMPRODUCT($AB$25:$AB$58,$AA$25:$AA$58) -> 0 | W45: =IF($L$12="","",V45/$L$12) -> 0 | X45: =IF(AB45<>"",IF(D45<>"",D45,($L$8-SUM($X$25:X44))*AA45*AB45/SUMPRODUCT($AB45:$AB$58,$AA45:$AA$58)),"") | Y45: =IF(AB45<>"",IF(E45<>"",E45,($L$9-SUM($Y$25:Y44))*AA45*AB45/SUMPRODUCT($AB45:$AB$58,$AA45:$AA$58)),"") | Z45: =IF(AB45<>"",IF($L$12<>"",IF(G45<>"",G45,($L$9/$L$12-SUM($Z$25:Z44))*AA45*AB45/SUMPRODUCT($AB45:$AB$58,$AA45:$AA$58)),""),"")
A46: 22 | F46: =IF(AND(E46<>"",E46<>0),D46/E46,"") | H46: =IF(AND(G46<>"",G46<>0),D46/G46,"") | J46: =IF(AND(G46<>"",G46<>0),E46/G46,"") | S46: =IF(AND(I46<>"",I46<>0),G46/I46,"") | T46: =D46/U46 -> #DIV/0! | U46: =$L$8*AA46*AB46/SUMPRODUCT($AB$25:$AB$56,$AA$25:$AA$56) -> 0 | V46: =$L$9*AA46*AB46/SUMPRODUCT($AB$25:$AB$58,$AA$25:$AA$58) -> 0 | W46: =IF($L$12="","",V46/$L$12) -> 0 | X46: =IF(AB46<>"",IF(D46<>"",D46,($L$8-SUM($X$25:X45))*AA46*AB46/SUMPRODUCT($AB46:$AB$58,$AA46:$AA$58)),"") | Y46: =IF(AB46<>"",IF(E46<>"",E46,($L$9-SUM($Y$25:Y45))*AA46*AB46/SUMPRODUCT($AB46:$AB$58,$AA46:$AA$58)),"") | Z46: =IF(AB46<>"",IF($L$12<>"",IF(G46<>"",G46,($L$9/$L$12-SUM($Z$25:Z45))*AA46*AB46/SUMPRODUCT($AB46:$AB$58,$AA46:$AA$58)),""),"")
A47: 23 | F47: =IF(AND(E47<>"",E47<>0),D47/E47,"") | H47: =IF(AND(G47<>"",G47<>0),D47/G47,"") | J47: =IF(AND(G47<>"",G47<>0),E47/G47,"") | S47: =IF(AND(I47<>"",I47<>0),G47/I47,"") | T47: =D47/U47 -> #DIV/0! | U47: =$L$8*AA47*AB47/SUMPRODUCT($AB$25:$AB$56,$AA$25:$AA$56) -> 0 | V47: =$L$9*AA47*AB47/SUMPRODUCT($AB$25:$AB$58,$AA$25:$AA$58) -> 0 | W47: =IF($L$12="","",V47/$L$12) -> 0 | X47: =IF(AB47<>"",IF(D47<>"",D47,($L$8-SUM($X$25:X46))*AA47*AB47/SUMPRODUCT($AB47:$AB$58,$AA47:$AA$58)),"") | Y47: =IF(AB47<>"",IF(E47<>"",E47,($L$9-SUM($Y$25:Y46))*AA47*AB47/SUMPRODUCT($AB47:$AB$58,$AA47:$AA$58)),"") | Z47: =IF(AB47<>"",IF($L$12<>"",IF(G47<>"",G47,($L$9/$L$12-SUM($Z$25:Z46))*AA47*AB47/SUMPRODUCT($AB47:$AB$58,$AA47:$AA$58)),""),"")
A48: 24 | F48: =IF(AND(E48<>"",E48<>0),D48/E48,"") | H48: =IF(AND(G48<>"",G48<>0),D48/G48,"") | J48: =IF(AND(G48<>"",G48<>0),E48/G48,"") | S48: =IF(AND(I48<>"",I48<>0),G48/I48,"") | T48: =D48/U48 -> #DIV/0! | U48: =$L$8*AA48*AB48/SUMPRODUCT($AB$25:$AB$56,$AA$25:$AA$56) -> 0 | V48: =$L$9*AA48*AB48/SUMPRODUCT($AB$25:$AB$58,$AA$25:$AA$58) -> 0 | W48: =IF($L$12="","",V48/$L$12) -> 0 | X48: =IF(AB48<>"",IF(D48<>"",D48,($L$8-SUM($X$25:X47))*AA48*AB48/SUMPRODUCT($AB48:$AB$58,$AA48:$AA$58)),"") | Y48: =IF(AB48<>"",IF(E48<>"",E48,($L$9-SUM($Y$25:Y47))*AA48*AB48/SUMPRODUCT($AB48:$AB$58,$AA48:$AA$58)),"") | Z48: =IF(AB48<>"",IF($L$12<>"",IF(G48<>"",G48,($L$9/$L$12-SUM($Z$25:Z47))*AA48*AB48/SUMPRODUCT($AB48:$AB$58,$AA48:$AA$58)),""),"")
A49: 25 | B49: 46092 | C49: ср | D49: 9993 | E49: 1 | F49: =IF(AND(E49<>"",E49<>0),D49/E49,"") -> 9993 | G49: 1 | H49: =IF(AND(G49<>"",G49<>0),D49/G49,"") -> 9993 | J49: =IF(AND(G49<>"",G49<>0),E49/G49,"") -> 1 | K49: 9993 | S49: =IF(AND(I49<>"",I49<>0),G49/I49,"") | T49: =D49/U49 -> #DIV/0! | U49: =$L$8*AA49*AB49/SUMPRODUCT($AB$25:$AB$56,$AA$25:$AA$56) -> 0 | V49: =$L$9*AA49*AB49/SUMPRODUCT($AB$25:$AB$58,$AA$25:$AA$58) -> 0 | W49: =IF($L$12="","",V49/$L$12) -> 0 | X49: =IF(AB49<>"",IF(D49<>"",D49,($L$8-SUM($X$25:X48))*AA49*AB49/SUMPRODUCT($AB49:$AB$58,$AA49:$AA$58)),"") | Y49: =IF(AB49<>"",IF(E49<>"",E49,($L$9-SUM($Y$25:Y48))*AA49*AB49/SUMPRODUCT($AB49:$AB$58,$AA49:$AA$58)),"") | Z49: =IF(AB49<>"",IF($L$12<>"",IF(G49<>"",G49,($L$9/$L$12-SUM($Z$25:Z48))*AA49*AB49/SUMPRODUCT($AB49:$AB$58,$AA49:$AA$58)),""),"")
A50: 26 | B50: 46097 | C50: пн | D50: 9270 | E50: 2 | F50: =IF(AND(E50<>"",E50<>0),D50/E50,"") -> 4635 | G50: 1 | H50: =IF(AND(G50<>"",G50<>0),D50/G50,"") -> 9270 | J50: =IF(AND(G50<>"",G50<>0),E50/G50,"") -> 2 | S50: =IF(AND(I50<>"",I50<>0),G50/I50,"") | T50: =D50/U50 -> #DIV/0! | U50: =$L$8*AA50*AB50/SUMPRODUCT($AB$25:$AB$56,$AA$25:$AA$56) -> 0 | V50: =$L$9*AA50*AB50/SUMPRODUCT($AB$25:$AB$58,$AA$25:$AA$58) -> 0 | W50: =IF($L$12="","",V50/$L$12) -> 0 | X50: =IF(AB50<>"",IF(D50<>"",D50,($L$8-SUM($X$25:X49))*AA50*AB50/SUMPRODUCT($AB50:$AB$58,$AA50:$AA$58)),"") | Y50: =IF(AB50<>"",IF(E50<>"",E50,($L$9-SUM($Y$25:Y49))*AA50*AB50/SUMPRODUCT($AB50:$AB$58,$AA50:$AA$58)),"") | Z50: =IF(AB50<>"",IF($L$12<>"",IF(G50<>"",G50,($L$9/$L$12-SUM($Z$25:Z49))*AA50*AB50/SUMPRODUCT($AB50:$AB$58,$AA50:$AA$58)),""),"")
A51: 27 | B51: 46102 | C51: сб | D51: -7584 | E51: 2 | F51: =IF(AND(E51<>"",E51<>0),D51/E51,"") -> -3792 | G51: 1 | H51: =IF(AND(G51<>"",G51<>0),D51/G51,"") -> -7584 | J51: =IF(AND(G51<>"",G51<>0),E51/G51,"") -> 2 | S51: =IF(AND(I51<>"",I51<>0),G51/I51,"") | T51: =D51/U51 -> #DIV/0! | U51: =$L$8*AA51*AB51/SUMPRODUCT($AB$25:$AB$56,$AA$25:$AA$56) -> 0 | V51: =$L$9*AA51*AB51/SUMPRODUCT($AB$25:$AB$58,$AA$25:$AA$58) -> 0 | W51: =IF($L$12="","",V51/$L$12) -> 0 | X51: =IF(AB51<>"",IF(D51<>"",D51,($L$8-SUM($X$25:X50))*AA51*AB51/SUMPRODUCT($AB51:$AB$58,$AA51:$AA$58)),"") | Y51: =IF(AB51<>"",IF(E51<>"",E51,($L$9-SUM($Y$25:Y50))*AA51*AB51/SUMPRODUCT($AB51:$AB$58,$AA51:$AA$58)),"") | Z51: =IF(AB51<>"",IF($L$12<>"",IF(G51<>"",G51,($L$9/$L$12-SUM($Z$25:Z50))*AA51*AB51/SUMPRODUCT($AB51:$AB$58,$AA51:$AA$58)),""),"")
A52: 28 | F52: =IF(AND(E52<>"",E52<>0),D52/E52,"") | H52: =IF(AND(G52<>"",G52<>0),D52/G52,"") | J52: =IF(AND(G52<>"",G52<>0),E52/G52,"") | S52: =IF(AND(I52<>"",I52<>0),G52/I52,"") | T52: =D52/U52 -> #DIV/0! | U52: =$L$8*AA52*AB52/SUMPRODUCT($AB$25:$AB$56,$AA$25:$AA$56) -> 0 | V52: =$L$9*AA52*AB52/SUMPRODUCT($AB$25:$AB$58,$AA$25:$AA$58) -> 0 | W52: =IF($L$12="","",V52/$L$12) -> 0 | X52: =IF(AB52<>"",IF(D52<>"",D52,($L$8-SUM($X$25:X51))*AA52*AB52/SUMPRODUCT($AB52:$AB$58,$AA52:$AA$58)),"") | Y52: =IF(AB52<>"",IF(E52<>"",E52,($L$9-SUM($Y$25:Y51))*AA52*AB52/SUMPRODUCT($AB52:$AB$58,$AA52:$AA$58)),"") | Z52: =IF(AB52<>"",IF($L$12<>"",IF(G52<>"",G52,($L$9/$L$12-SUM($Z$25:Z51))*AA52*AB52/SUMPRODUCT($AB52:$AB$58,$AA52:$AA$58)),""),"")
A53: 29 | F53: =IF(AND(E53<>"",E53<>0),D53/E53,"") | H53: =IF(AND(G53<>"",G53<>0),D53/G53,"") | J53: =IF(AND(G53<>"",G53<>0),E53/G53,"") | S53: =IF(AND(I53<>"",I53<>0),G53/I53,"") | T53: =D53/U53 -> #DIV/0! | U53: =$L$8*AA53*AB53/SUMPRODUCT($AB$25:$AB$56,$AA$25:$AA$56) -> 0 | V53: =$L$9*AA53*AB53/SUMPRODUCT($AB$25:$AB$58,$AA$25:$AA$58) -> 0 | W53: =IF($L$12="","",V53/$L$12) -> 0 | X53: =IF(AB53<>"",IF(D53<>"",D53,($L$8-SUM($X$25:X52))*AA53*AB53/SUMPRODUCT($AB53:$AB$58,$AA53:$AA$58)),"") | Y53: =IF(AB53<>"",IF(E53<>"",E53,($L$9-SUM($Y$25:Y52))*AA53*AB53/SUMPRODUCT($AB53:$AB$58,$AA53:$AA$58)),"") | Z53: =IF(AB53<>"",IF($L$12<>"",IF(G53<>"",G53,($L$9/$L$12-SUM($Z$25:Z52))*AA53*AB53/SUMPRODUCT($AB53:$AB$58,$AA53:$AA$58)),""),"")
F54: =IF(AND(E54<>"",E54<>0),D54/E54,"") | H54: =IF(AND(G54<>"",G54<>0),D54/G54,"") | J54: =IF(AND(G54<>"",G54<>0),E54/G54,"") | S54: =IF(AND(I54<>"",I54<>0),G54/I54,"") | T54: =D54/U54 -> #DIV/0! | U54: =$L$8*AA54*AB54/SUMPRODUCT($AB$25:$AB$56,$AA$25:$AA$56) -> 0 | V54: =$L$9*AA54*AB54/SUMPRODUCT($AB$25:$AB$58,$AA$25:$AA$58) -> 0 | W54: =IF($L$12="","",V54/$L$12) -> 0 | X54: =IF(AB54<>"",IF(D54<>"",D54,($L$8-SUM($X$25:X50))*AA54*AB54/SUMPRODUCT($AB54:$AB$58,$AA54:$AA$58)),"") | Y54: =IF(AB54<>"",IF(E54<>"",E54,($L$9-SUM($Y$25:Y50))*AA54*AB54/SUMPRODUCT($AB54:$AB$58,$AA54:$AA$58)),"") | Z54: =IF(AB54<>"",IF($L$12<>"",IF(G54<>"",G54,($L$9/$L$12-SUM($Z$25:Z50))*AA54*AB54/SUMPRODUCT($AB54:$AB$58,$AA54:$AA$58)),""),"")
F55: =IF(AND(E55<>"",E55<>0),D55/E55,"") | H55: =IF(AND(G55<>"",G55<>0),D55/G55,"") | J55: =IF(AND(G55<>"",G55<>0),E55/G55,"") | S55: =IF(AND(I55<>"",I55<>0),G55/I55,"") | T55: =D55/U55 -> #DIV/0! | U55: =$L$8*AA55*AB55/SUMPRODUCT($AB$25:$AB$56,$AA$25:$AA$56) -> 0 | V55: =$L$9*AA55*AB55/SUMPRODUCT($AB$25:$AB$58,$AA$25:$AA$58) -> 0 | W55: =IF($L$12="","",V55/$L$12) -> 0 | X55: =IF(AB55<>"",IF(D55<>"",D55,($L$8-SUM($X$25:X54))*AA55*AB55/SUMPRODUCT($AB55:$AB$58,$AA55:$AA$58)),"") | Y55: =IF(AB55<>"",IF(E55<>"",E55,($L$9-SUM($Y$25:Y54))*AA55*AB55/SUMPRODUCT($AB55:$AB$58,$AA55:$AA$58)),"") | Z55: =IF(AB55<>"",IF($L$12<>"",IF(G55<>"",G55,($L$9/$L$12-SUM($Z$25:Z54))*AA55*AB55/SUMPRODUCT($AB55:$AB$58,$AA55:$AA$58)),""),"")
F56: =IF(AND(E56<>"",E56<>0),D56/E56,"") | H56: =IF(AND(G56<>"",G56<>0),D56/G56,"") | J56: =IF(AND(G56<>"",G56<>0),E56/G56,"") | S56: =IF(AND(I56<>"",I56<>0),G56/I56,"") | T56: =D56/U56 -> #DIV/0! | U56: =$L$8*AA56*AB56/SUMPRODUCT($AB$25:$AB$56,$AA$25:$AA$56) -> 0 | V56: =$L$9*AA56*AB56/SUMPRODUCT($AB$25:$AB$58,$AA$25:$AA$58) -> 0 | W56: =IF($L$12="","",V56/$L$12) -> 0 | X56: =IF(AB56<>"",IF(D56<>"",D56,($L$8-SUM($X$25:X55))*AA56*AB56/SUMPRODUCT($AB56:$AB$58,$AA56:$AA$58)),"") | Y56: =IF(AB56<>"",IF(E56<>"",E56,($L$9-SUM($Y$25:Y55))*AA56*AB56/SUMPRODUCT($AB56:$AB$58,$AA56:$AA$58)),"") | Z56: =IF(AB56<>"",IF($L$12<>"",IF(G56<>"",G56,($L$9/$L$12-SUM($Z$25:Z55))*AA56*AB56/SUMPRODUCT($AB56:$AB$58,$AA56:$AA$58)),""),"")
D57: =SUM(D25:D56) -> 474399 | E57: =SUM(E25:E56) -> 63 | F57: =IF(AND(E57<>"",E57<>0),D57/E57,"") -> 7530.1429 | G57: =SUM(G25:G56) -> 42 | H57: =IF(AND(G57<>"",G57<>0),D57/G57,"") -> 11295.214 | I57: =SUM(I25:I56) -> 298 | J57: =IF(AND(G57<>"",G57<>0),E57/G57,"") -> 1.5 | K57: =SUM(K25:K56) -> 120062 | L57: =SUM(L25:L56) -> 0 | M57: =SUM(M25:M56) -> 0 | N57: =SUM(N25:N56) -> 6191 | O57: =SUM(O25:O56) -> 15390 | P57: =SUM(P25:P56) -> 41805 | Q57: =SUM(Q25:Q56) -> 58232 | R57: =SUM(R25:R56) -> 2793 | S57: =IF(AND(I57<>"",I57<>0),G57/I57,"") -> 0.1409396 | T57: =D57/U57 -> 0.75636055 | U57: =SUM(U25:U56) -> 627212.78 | V57: =SUM(V25:V55) -> 90.900403 | W57: =SUM(W25:W55) -> 52.241611 | X57: =SUM(X25:X56) -> 462720 | Y57: =SUM(Y25:Y55) -> 64 | Z57: =SUM(Z25:Z55) -> 39
D58: =SUMIF(D25:D54,"",U25:U54)+D57 -> 474399

Sheet Уразгильдеева
B1: =TODAY()-1 -> 46171
B2: (отчетная дата) | J2: ЕЖЕДНЕВНЫЙ ОТЧЕТ О ПРОДАЖАХ
B3: Осталось до выполнения плана!!! | J3: =График!B28 -> Уразгильдеева Екатерина
C4: =L8-D50 -> 843804.24 | E4: =IF(L8<>0,C4/L8,0) -> 1
I6: Целевые показатели
I7: Показатель | L7: План | M7: Факт | N7: % выполнения | O7: Прогноз выполнения | P7: % выполнения по прогнозу | Q7: Отклонение | R7: Факт аналогичного месяца прошлого года | S7: Отклонение LFL
I8: Выручка | L8: ='Ялта, Ленина, 18'!I8/График!AJ30*График!AJ28 -> 843804.24 | M8: =D57 -> 576247 | N8: =IF(AND(L8<>"",L8<>0,M8<>""),M8/L8,"") -> 0.68291551 | O8: =IF(SUMIF($D$25:$D$56,">=0",$U$25:$U$56)<>0,L8*D57/SUMIF($D$25:$D$56,">=0",$U$25:$U$56),0) -> 576247 | P8: =IF(AND(L8<>"",L8<>0,O8<>"",O8<>0),O8/L8,"") -> 0.68291551 | Q8: =IF(AND(M8<>0,M8<>"",L8<>0,L8<>""),O8-L8,"") -> -267557.24 | S8: =IF(AND(R8<>"",R8<>0,O8<>"",O8<>0),-R8+O8,"") | T8: =IF(AND(S8<>"",S8<>0,R8<>0,R8<>""),S8/R8,"")
I9: Кол-во изделий | L9: =L8/L11 -> 122.29047 | M9: =E57 -> 95 | N9: =IF(AND(L9<>"",L9<>0,M9<>""),M9/L9,"") -> 0.77683895 | O9: =IF(SUMIF($E$25:$E$54,">=0",$V$25:$V$54)<>0,L9*E57/SUMIF($E$25:$E$54,">=0",$V$25:$V$54),0) -> 95 | P9: =IF(AND(L9<>"",L9<>0,O9<>"",O9<>0),O9/L9,"") -> 0.77683895 | Q9: =IF(AND(M9<>0,M9<>"",L9<>0,L9<>""),O9-L9,"") -> -27.29047 | R9: =R8/R11 -> #DIV/0! | S9: =IF(AND(R9<>"",R9<>0,O9<>"",O9<>0),-R9+O9,"") -> #DIV/0! | T9: =IF(AND(S9<>"",S9<>0,R9<>0,R9<>""),S9/R9,"") -> #DIV/0!
I10: Средний чек | L10: =L11*L12 -> 12006 | M10: =H57 -> 11524.94 | N10: =IF(AND(L10<>"",L10<>0,M10<>""),M10/L10,"") -> 0.9599317 | O10: =M10 -> 11524.94 | P10: =IF(AND(L10<>"",L10<>0,O10<>"",O10<>0),O10/L10,"") -> 0.9599317 | Q10: =IF(AND(M10<>0,M10<>"",L10<>0,L10<>""),O10-L10,"") -> -481.06 | R10: =R11*R12 -> 0 | S10: =IF(AND(R10<>"",R10<>0,O10<>"",O10<>0),-R10+O10,"") | T10: =IF(AND(S10<>"",S10<>0,R10<>0,R10<>""),S10/R10,"")
I11: Средняя стоимость изделия | L11: ='Ялта, Ленина, 18'!I11 -> 6900 | M11: =F57 -> 6065.7579 | N11: =IF(AND(L11<>"",L11<>0,M11<>""),M11/L11,"") -> 0.87909535 | O11: =IF(O9>0,O8/O9,"") -> 6065.7579 | P11: =IF(AND(L11<>"",L11<>0,O11<>"",O11<>0),O11/L11,"") -> 0.87909535 | Q11: =IF(AND(M11<>0,M11<>"",L11<>0,L11<>""),O11-L11,"") -> -834.24211 | S11: =IF(AND(R11<>"",R11<>0,O11<>"",O11<>0),-R11+O11,"") | T11: =IF(AND(S11<>"",S11<>0,R11<>0,R11<>""),S11/R11,"")
I12: Длина чека | L12: ='Ялта, Ленина, 18'!I12 -> 1.74 | M12: =J57 -> 1.9 | N12: =IF(AND(L12<>"",L12<>0,M12<>""),M12/L12,"") -> 1.091954 | O12: =M12 -> 1.9 | P12: =IF(AND(L12<>"",L12<>0,O12<>"",O12<>0),O12/L12,"") -> 1.091954 | Q12: =IF(AND(M12<>0,M12<>"",L12<>0,L12<>""),O12-L12,"") -> 0.16 | S12: =IF(AND(R12<>"",R12<>0,O12<>"",O12<>0),-R12+O12,"") | T12: =IF(AND(S12<>"",S12<>0,R12<>0,R12<>""),S12/R12,"")
I13: Кол-во чеков | L13: =IF(L12<>0,L9/L12,"") -> 70.281879 | M13: =G57 -> 50 | N13: =IF(AND(L13<>"",L13<>0,M13<>""),M13/L13,"") -> 0.71142093 | O13: =IF(SUMIF($G$25:$G$54,">=0",$W$25:$W$54)<>0,L13*G57/SUMIF($G$25:$G$54,">=0",$W$25:$W$54),"") -> 50 | P13: =IF(AND(L13<>"",L13<>0,O13<>"",O13<>0),O13/L13,"") -> 0.71142093 | Q13: =IF(AND(M13<>0,M13<>"",L13<>0,L13<>""),O13-L13,"") -> -20.281879 | S13: =IF(AND(R13<>"",R13<>0,O13<>"",O13<>0),-R13+O13,"") | T13: =IF(AND(S13<>"",S13<>0,R13<>0,R13<>""),S13/R13,"")
I14: Кол-во смен план/отработано | L14: =График!AI28 -> 17 | M14: 17 | N14: =IF(AND(L14<>"",L14<>0,M14<>""),M14/L14,"") -> 1 | O14: =L14 -> 17 | P14: =IF(AND(L14<>"",L14<>0,O14<>"",O14<>0),O14/L14,"") -> 1 | Q14: =IF(AND(M14<>0,M14<>"",L14<>0,L14<>""),O14-L14,"") -> 0 | S14: =IF(AND(R14<>"",R14<>0,O14<>"",O14<>0),-R14+O14,"") | T14: =IF(AND(S14<>"",S14<>0,R14<>0,R14<>""),S14/R14,"")
I15: Средние продажи в смену | L15: ='Ялта, Ленина, 18'!I15 -> 65064.774 | M15: =M8/M14 -> 33896.882 | N15: =IF(AND(L15<>"",L15<>0,M15<>""),M15/L15,"") -> 0.52097134 | O15: =M15 -> 33896.882 | P15: =IF(AND(L15<>"",L15<>0,O15<>"",O15<>0),O15/L15,"") -> 0.52097134 | Q15: =IF(AND(M15<>0,M15<>"",L15<>0,L15<>""),O15-L15,"") -> -31167.892 | S15: =IF(AND(R15<>"",R15<>0,O15<>"",O15<>0),-R15+O15,"") | T15: =IF(AND(S15<>"",S15<>0,R15<>0,R15<>""),S15/R15,"")
I16: Отставание/Перевыполнение | M16: =M8-L15*M14 -> -529854.16 | N16: =IF(AND(L16<>"",L16<>0,M16<>""),M16/L16,"") | O16: =M16 -> -529854.16 | P16: =IF(AND(L16<>"",L16<>0,O16<>"",O16<>0),O16/L16,"") | Q16: =IF(AND(M16<>0,M16<>"",L16<>0,L16<>""),O16-L16,"") | S16: =IF(AND(R16<>"",R16<>0,O16<>"",O16<>0),-R16+O16,"") | T16: =IF(AND(S16<>"",S16<>0,R16<>0,R16<>""),S16/R16,"")
I17: Трафик | L17: ='Ялта, Ленина, 18'!I17/График!AJ30*График!AJ28 -> 585.68233 | M17: =I57 -> 615 | N17: =IF(AND(L17<>"",L17<>0,M17<>""),M17/L17,"") -> 1.0500573 | O17: =M17/M14*L14 -> 615 | P17: =IF(AND(L17<>"",L17<>0,O17<>"",O17<>0),O17/L17,"") -> 1.0500573 | Q17: =IF(AND(M17<>0,M17<>"",L17<>0,L17<>""),O17-L17,"") -> 29.317673 | S17: =IF(AND(R17<>"",R17<>0,O17<>"",O17<>0),-R17+O17,"") | T17: =IF(AND(S17<>"",S17<>0,R17<>0,R17<>""),S17/R17,"")
N18: =IF(AND(L18<>"",L18<>0,M18<>""),M18/L18,"") | O18: =M18 -> 0 | P18: =IF(AND(L18<>"",L18<>0,O18<>"",O18<>0),O18/L18,"") | Q18: =IF(AND(M18<>0,M18<>"",L18<>0,L18<>""),O18-L18,"") | R18: 0 | S18: =IF(AND(R18<>"",R18<>0,O18<>"",O18<>0),-R18+O18,"") | T18: =IF(AND(S18<>"",S18<>0,R18<>0,R18<>""),S18/R18,"")
N19: =IF(AND(L19<>"",L19<>0,M19<>""),M19/L19,"") | O19: =M19 -> 0 | P19: =IF(AND(L19<>"",L19<>0,O19<>"",O19<>0),O19/L19,"") | Q19: =IF(AND(M19<>0,M19<>"",L19<>0,L19<>""),O19-L19,"") | R19: 0 | S19: =IF(AND(R19<>"",R19<>0,O19<>"",O19<>0),-R19+O19,"") | T19: =IF(AND(S19<>"",S19<>0,R19<>0,R19<>""),S19/R19,"")
I20: Конверсия план/факт | L20: ='Ялта, Ленина, 18'!I20 -> 0.12 | M20: =S57 -> 0.081300813 | N20: =M20/L20 -> 0.67750678 | O20: =IF(AND(N8<>0,L14<>0,I57<>0),(I57*S57+(I57/N8-I57)*L20)/(I57/N8),0) -> 0.093571725 | P20: =IF(AND(L20<>"",L20<>0,O20<>"",O20<>0),O20/L20,"") -> 0.77976438 | Q20: =IF(AND(M20<>0,M20<>"",L20<>0,L20<>""),O20-L20,"") -> -0.026428275 | S20: =IF(AND(R20<>"",R20<>0,O20<>"",O20<>0),-R20+O20,"") | T20: =IF(AND(S20<>"",S20<>0,R20<>0,R20<>""),S20/R20,"")
B22: Факт продаж за месяц | T22: % выполнения дневного плана | U22: Раcпределение плана по дням
B23: Дата | C23: День недели | D23: Выручка (руб) | E23: Кол-во единиц (шт.) | F23: Средняя стоимость изделия (руб.) | G23: Количество чеков (шт.) | H23: Средняя сумма чека (руб.) | I23: Трафик | J23: Длина чека (шт.) | K23: UNOde50 | L23: IS | M23: Agafi | N23: Kalliope | O23: Raganella | P23: CC/MP | Q23: Antura | R23: SALE | S23: Конверсия (%) | U23: выручка, план | V23: кол-во ед, план | W23: Кол-во чеков, план | X23: выручка, скорректир.план | Y23: кол-во ед, скорр. план | Z23: кол-во чеков, скорр. план | AA23: Коэфф. Дня Недели | AB23: Специфика месяца
B24: 1 | C24: 2 | D24: 3 | E24: в | F24: 5 | G24: 6 | H24: 7 | I24: 8 | J24: 9 | K24: 10 | L24: 11 | M24: 12 | N24: 13 | P24: 14 | Q24: 15 | R24: 16 | S24: 17 | U24: 1 | V24: 2 | W24: 3 | X24: 4 | Y24: 5 | Z24: 6 | AA24: 10 | AB24: 11
A25: 1 | B25: 46082 | C25: вс | D25: 19475 | E25: 3 | F25: 6492 | G25: 1 | H25: =IF(AND(G25<>"",G25<>0),D25/G25,"") -> 19475 | I25: 20 | J25: =IF(AND(G25<>"",G25<>0),E25/G25,"") -> 3 | R25: 7690 | S25: =IF(AND(I25<>"",I25<>0),G25/I25,"") -> 0.05 | T25: =D25/U25 -> 0.32311997 | U25: =$L$8*AA25*AB25/SUMPRODUCT($AB$25:$AB$56,$AA$25:$AA$56) -> 60271.732 | V25: =$L$9*AA25*AB25/SUMPRODUCT($AB$25:$AB$56,$AA$25:$AA$56) -> 8.7350336 | W25: =IF($L$12="","",V25/$L$12) -> 5.0201342 | X25: =IF(D25<>"",D25,U25) -> 19475 | Y25: =IF(E25<>"",E25,V25) -> 3 | Z25: =IF(G25<>"",G25,W25) -> 1 | AA25: 1 | AB25: 1
A26: 2 | B26: 46085 | C26: ср | D26: 0 | E26: 0 | F26: 0 | G26: 0 | H26: 0 | I26: 10 | J26: =IF(AND(G26<>"",G26<>0),E26/G26,"") | S26: =IF(AND(I26<>"",I26<>0),G26/I26,"") -> 0 | T26: =D26/U26 -> 0 | U26: =$L$8*AA26*AB26/SUMPRODUCT($AB$25:$AB$56,$AA$25:$AA$56) -> 60271.732 | V26: =$L$9*AA26*AB26/SUMPRODUCT($AB$25:$AB$58,$AA$25:$AA$58) -> 8.7350336 | W26: =IF($L$12="","",V26/$L$12) -> 5.0201342 | X26: =IF(AB26<>"",IF(D26<>"",D26,($L$8-SUM($X$25:X25))*AA26*AB26/SUMPRODUCT($AB26:$AB$56,$AA26:$AA$56)),"") -> 0 | Y26: =IF(AB26<>"",IF(E26<>"",E26,($L$9-SUM($Y$25:Y25))*AA26*AB26/SUMPRODUCT($AB26:$AB$55,$AA26:$AA$55)),"") -> 0 | Z26: =IF(AB26<>"",IF($L$12<>"",IF(G26<>"",G26,($L$9/$L$12-SUM($Z$25:Z25))*AA26*AB26/SUMPRODUCT($AB26:$AB$55,$AA26:$AA$55)),""),"") -> 0 | AA26: 1 | AB26: 1
A27: 3 | B27: 46086 | C27: чт | D27: 34800 | E27: 6 | F27: =IF(AND(E27<>"",E27<>0),D27/E27,"") -> 5800 | G27: 3 | H27: =IF(AND(G27<>"",G27<>0),D27/G27,"") -> 11600 | I27: 15 | J27: =IF(AND(G27<>"",G27<>0),E27/G27,"") -> 2 | R27: 4753 | S27: =IF(AND(I27<>"",I27<>0),G27/I27,"") -> 0.2 | T27: =D27/U27 -> 0.5773851 | U27: =$L$8*AA27*AB27/SUMPRODUCT($AB$25:$AB$56,$AA$25:$AA$56) -> 60271.732 | V27: =$L$9*AA27*AB27/SUMPRODUCT($AB$25:$AB$58,$AA$25:$AA$58) -> 8.7350336 | W27: =IF($L$12="","",V27/$L$12) -> 5.0201342 | X27: =IF(AB27<>"",IF(D27<>"",D27,($L$8-SUM($X$25:X26))*AA27*AB27/SUMPRODUCT($AB27:$AB$58,$AA27:$AA$58)),"") -> 34800 | Y27: =IF(AB27<>"",IF(E27<>"",E27,($L$9-SUM($Y$25:Y26))*AA27*AB27/SUMPRODUCT($AB27:$AB$55,$AA27:$AA$55)),"") -> 6 | Z27: =IF(AB27<>"",IF($L$12<>"",IF(G27<>"",G27,($L$9/$L$12-SUM($Z$25:Z26))*AA27*AB27/SUMPRODUCT($AB27:$AB$55,$AA27:$AA$55)),""),"") -> 3 | AA27: 1 | AB27: 1
A28: 4 | B28: 46087 | C28: пт | D28: 12376 | E28: 3 | F28: =IF(AND(E28<>"",E28<>0),D28/E28,"") -> 4125.3333 | G28: 1 | H28: =IF(AND(G28<>"",G28<>0),D28/G28,"") -> 12376 | I28: 10 | J28: =IF(AND(G28<>"",G28<>0),E28/G28,"") -> 3 | S28: =IF(AND(I28<>"",I28<>0),G28/I28,"") -> 0.1 | T28: =D28/U28 -> 0.20533673 | U28: =$L$8*AA28*AB28/SUMPRODUCT($AB$25:$AB$56,$AA$25:$AA$56) -> 60271.732 | V28: =$L$9*AA28*AB28/SUMPRODUCT($AB$25:$AB$58,$AA$25:$AA$58) -> 8.7350336 | W28: =IF($L$12="","",V28/$L$12) -> 5.0201342 | X28: =IF(AB28<>"",IF(D28<>"",D28,($L$8-SUM($X$25:X27))*AA28*AB28/SUMPRODUCT($AB28:$AB$58,$AA28:$AA$58)),"") -> 12376 | Y28: =IF(AB28<>"",IF(E28<>"",E28,($L$9-SUM($Y$25:Y27))*AA28*AB28/SUMPRODUCT($AB28:$AB$58,$AA28:$AA$58)),"") -> 3 | Z28: =IF(AB28<>"",IF($L$12<>"",IF(G28<>"",G28,($L$9/$L$12-SUM($Z$25:Z27))*AA28*AB28/SUMPRODUCT($AB28:$AB$58,$AA28:$AA$58)),""),"") -> 1 | AA28: 1 | AB28: 1
A29: 5 | B29: 46088 | C29: сб | D29: 46837 | E29: 8 | F29: =IF(AND(E29<>"",E29<>0),D29/E29,"") -> 5854.625 | G29: 4 | H29: =IF(AND(G29<>"",G29<>0),D29/G29,"") -> 11709.25 | I29: 25 | J29: =IF(AND(G29<>"",G29<>0),E29/G29,"") -> 2 | S29: =IF(AND(I29<>"",I29<>0),G29/I29,"") -> 0.16 | T29: =D29/U29 -> 0.7770973 | U29: =$L$8*AA29*AB29/SUMPRODUCT($AB$25:$AB$56,$AA$25:$AA$56) -> 60271.732 | V29: =$L$9*AA29*AB29/SUMPRODUCT($AB$25:$AB$58,$AA$25:$AA$58) -> 8.7350336 | W29: =IF($L$12="","",V29/$L$12) -> 5.0201342 | X29: =IF(AB29<>"",IF(D29<>"",D29,($L$8-SUM($X$25:X28))*AA29*AB29/SUMPRODUCT($AB29:$AB$58,$AA29:$AA$58)),"") -> 46837 | Y29: =IF(AB29<>"",IF(E29<>"",E29,($L$9-SUM($Y$25:Y28))*AA29*AB29/SUMPRODUCT($AB29:$AB$58,$AA29:$AA$58)),"") -> 8 | Z29: =IF(AB29<>"",IF($L$12<>"",IF(G29<>"",G29,($L$9/$L$12-SUM($Z$25:Z28))*AA29*AB29/SUMPRODUCT($AB29:$AB$58,$AA29:$AA$58)),""),"") -> 4 | AA29: 1 | AB29: 1
A30: 6 | B30: 46089 | C30: вс | D30: 50790 | E30: 5 | F30: =IF(AND(E30<>"",E30<>0),D30/E30,"") -> 10158 | G30: 3 | H30: =IF(AND(G30<>"",G30<>0),D30/G30,"") -> 16930 | I30: 40 | J30: =IF(AND(G30<>"",G30<>0),E30/G30,"") -> 1.6666667 | K30: 23723 | S30: =IF(AND(I30<>"",I30<>0),G30/I30,"") -> 0.075 | T30: =D30/U30 -> 0.8426836 | U30: =$L$8*AA30*AB30/SUMPRODUCT($AB$25:$AB$56,$AA$25:$AA$56) -> 60271.732 | V30: =$L$9*AA30*AB30/SUMPRODUCT($AB$25:$AB$58,$AA$25:$AA$58) -> 8.7350336 | W30: =IF($L$12="","",V30/$L$12) -> 5.0201342 | X30: =IF(AB30<>"",IF(D30<>"",D30,($L$8-SUM($X$25:X29))*AA30*AB30/SUMPRODUCT($AB30:$AB$58,$AA30:$AA$58)),"") -> 50790 | Y30: =IF(AB30<>"",IF(E30<>"",E30,($L$9-SUM($Y$25:Y29))*AA30*AB30/SUMPRODUCT($AB30:$AB$58,$AA30:$AA$58)),"") -> 5 | Z30: =IF(AB30<>"",IF($L$12<>"",IF(G30<>"",G30,($L$9/$L$12-SUM($Z$25:Z29))*AA30*AB30/SUMPRODUCT($AB30:$AB$58,$AA30:$AA$58)),""),"") -> 3 | AA30: 1 | AB30: 1
A31: 7 | B31: 46092 | C31: ср | D31: 11086 | E31: 2 | F31: 5543 | G31: 2 | H31: =IF(AND(G31<>"",G31<>0),D31/G31,"") -> 5543 | I31: 40 | J31: =IF(AND(G31<>"",G31<>0),E31/G31,"") -> 1 | S31: =IF(AND(I31<>"",I31<>0),G31/I31,"") -> 0.05 | T31: =D31/U31 -> 0.18393366 | U31: =$L$8*AA31*AB31/SUMPRODUCT($AB$25:$AB$56,$AA$25:$AA$56) -> 60271.732 | V31: =$L$9*AA31*AB31/SUMPRODUCT($AB$25:$AB$58,$AA$25:$AA$58) -> 8.7350336 | W31: =IF($L$12="","",V31/$L$12) -> 5.0201342 | X31: =IF(AB31<>"",IF(D31<>"",D31,($L$8-SUM($X$25:X30))*AA31*AB31/SUMPRODUCT($AB31:$AB$58,$AA31:$AA$58)),"") -> 11086 | Y31: =IF(AB31<>"",IF(E31<>"",E31,($L$9-SUM($Y$25:Y30))*AA31*AB31/SUMPRODUCT($AB31:$AB$58,$AA31:$AA$58)),"") -> 2 | Z31: =IF(AB31<>"",IF($L$12<>"",IF(G31<>"",G31,($L$9/$L$12-SUM($Z$25:Z30))*AA31*AB31/SUMPRODUCT($AB31:$AB$58,$AA31:$AA$58)),""),"") -> 2 | AA31: 1 | AB31: 1
A32: 8 | B32: 46093 | C32: чт | D32: =7093+11484 -> 18577 | E32: 3 | F32: =IF(AND(E32<>"",E32<>0),D32/E32,"") -> 6192.3333 | G32: 2 | H32: =IF(AND(G32<>"",G32<>0),D32/G32,"") -> 9288.5 | I32: 18 | J32: =IF(AND(G32<>"",G32<>0),E32/G32,"") -> 1.5 | P32: 7093 | R32: 6490 | S32: =IF(AND(I32<>"",I32<>0),G32/I32,"") -> 0.11111111 | T32: =D32/U32 -> 0.30822078 | U32: =$L$8*AA32*AB32/SUMPRODUCT($AB$25:$AB$56,$AA$25:$AA$56) -> 60271.732 | V32: =$L$9*AA32*AB32/SUMPRODUCT($AB$25:$AB$58,$AA$25:$AA$58) -> 8.7350336 | W32: =IF($L$12="","",V32/$L$12) -> 5.0201342 | X32: =IF(AB32<>"",IF(D32<>"",D32,($L$8-SUM($X$25:X31))*AA32*AB32/SUMPRODUCT($AB32:$AB$58,$AA32:$AA$58)),"") -> 18577 | Y32: =IF(AB32<>"",IF(E32<>"",E32,($L$9-SUM($Y$25:Y31))*AA32*AB32/SUMPRODUCT($AB32:$AB$58,$AA32:$AA$58)),"") -> 3 | Z32: =IF(AB32<>"",IF($L$12<>"",IF(G32<>"",G32,($L$9/$L$12-SUM($Z$25:Z31))*AA32*AB32/SUMPRODUCT($AB32:$AB$58,$AA32:$AA$58)),""),"") -> 2 | AA32: 1 | AB32: 1
A33: 9 | B33: 46097 | C33: пн | D33: 83675 | E33: 13 | F33: =IF(AND(E33<>"",E33<>0),D33/E33,"") -> 6436.5385 | G33: 7 | H33: =IF(AND(G33<>"",G33<>0),D33/G33,"") -> 11953.571 | I33: 50 | J33: =IF(AND(G33<>"",G33<>0),E33/G33,"") -> 1.8571429 | K33: 17593 | P33: 7259 | Q33: 8240 | S33: =IF(AND(I33<>"",I33<>0),G33/I33,"") -> 0.14 | T33: =D33/U33 -> 1.3882959 | U33: =$L$8*AA33*AB33/SUMPRODUCT($AB$25:$AB$56,$AA$25:$AA$56) -> 60271.732 | V33: =$L$9*AA33*AB33/SUMPRODUCT($AB$25:$AB$58,$AA$25:$AA$58) -> 8.7350336 | W33: =IF($L$12="","",V33/$L$12) -> 5.0201342 | X33: =IF(AB33<>"",IF(D33<>"",D33,($L$8-SUM($X$25:X32))*AA33*AB33/SUMPRODUCT($AB33:$AB$58,$AA33:$AA$58)),"") -> 83675 | Y33: =IF(AB33<>"",IF(E33<>"",E33,($L$9-SUM($Y$25:Y32))*AA33*AB33/SUMPRODUCT($AB33:$AB$58,$AA33:$AA$58)),"") -> 13 | Z33: =IF(AB33<>"",IF($L$12<>"",IF(G33<>"",G33,($L$9/$L$12-SUM($Z$25:Z32))*AA33*AB33/SUMPRODUCT($AB33:$AB$58,$AA33:$AA$58)),""),"") -> 7 | AA33: 1 | AB33: 1
A34: 10 | B34: 46098 | C34: вт | D34: 11392 | E34: 3 | F34: =IF(AND(E34<>"",E34<>0),D34/E34,"") -> 3797.3333 | G34: 2 | H34: =IF(AND(G34<>"",G34<>0),D34/G34,"") -> 5696 | I34: 30 | J34: =IF(AND(G34<>"",G34<>0),E34/G34,"") -> 1.5 | R34: 4190 | S34: =IF(AND(I34<>"",I34<>0),G34/I34,"") -> 0.066666667 | T34: =D34/U34 -> 0.18901066 | U34: =$L$8*AA34*AB34/SUMPRODUCT($AB$25:$AB$56,$AA$25:$AA$56) -> 60271.732 | V34: =$L$9*AA34*AB34/SUMPRODUCT($AB$25:$AB$58,$AA$25:$AA$58) -> 8.7350336 | W34: =IF($L$12="","",V34/$L$12) -> 5.0201342 | X34: =IF(AB34<>"",IF(D34<>"",D34,($L$8-SUM($X$25:X33))*AA34*AB34/SUMPRODUCT($AB34:$AB$58,$AA34:$AA$58)),"") -> 11392 | Y34: =IF(AB34<>"",IF(E34<>"",E34,($L$9-SUM($Y$25:Y33))*AA34*AB34/SUMPRODUCT($AB34:$AB$58,$AA34:$AA$58)),"") -> 3 | Z34: =IF(AB34<>"",IF($L$12<>"",IF(G34<>"",G34,($L$9/$L$12-SUM($Z$25:Z33))*AA34*AB34/SUMPRODUCT($AB34:$AB$58,$AA34:$AA$58)),""),"") -> 2 | AA34: 1 | AB34: 1
A35: 11 | B35: 46102 | C35: сб | D35: 44751 | E35: 10 | F35: =IF(AND(E35<>"",E35<>0),D35/E35,"") -> 4475.1 | G35: 7 | H35: =IF(AND(G35<>"",G35<>0),D35/G35,"") -> 6393 | I35: 35 | J35: =IF(AND(G35<>"",G35<>0),E35/G35,"") -> 1.4285714 | R35: 13269 | S35: =IF(AND(I35<>"",I35<>0),G35/I35,"") -> 0.2 | T35: =D35/U35 -> 0.74248738 | U35: =$L$8*AA35*AB35/SUMPRODUCT($AB$25:$AB$56,$AA$25:$AA$56) -> 60271.732 | V35: =$L$9*AA35*AB35/SUMPRODUCT($AB$25:$AB$58,$AA$25:$AA$58) -> 8.7350336 | W35: =IF($L$12="","",V35/$L$12) -> 5.0201342 | X35: =IF(AB35<>"",IF(D35<>"",D35,($L$8-SUM($X$25:X34))*AA35*AB35/SUMPRODUCT($AB35:$AB$58,$AA35:$AA$58)),"") -> 44751 | Y35: =IF(AB35<>"",IF(E34<>"",E34,($L$9-SUM($Y$25:Y34))*AA35*AB35/SUMPRODUCT($AB35:$AB$58,$AA35:$AA$58)),"") -> 3 | Z35: =IF(AB35<>"",IF($L$12<>"",IF(G35<>"",G35,($L$9/$L$12-SUM($Z$25:Z34))*AA35*AB35/SUMPRODUCT($AB35:$AB$58,$AA35:$AA$58)),""),"") -> 7 | AA35: 1 | AB35: 1
A36: 11 | B36: 46103 | C36: вс | D36: 0 | E36: 0 | F36: 0 | G36: 0 | H36: 0 | I36: 27 | J36: =IF(AND(G36<>"",G36<>0),E36/G36,"") | S36: =IF(AND(I36<>"",I36<>0),G36/I36,"") -> 0 | T36: =D36/U36 -> 0 | U36: =$L$8*AA36*AB36/SUMPRODUCT($AB$25:$AB$56,$AA$25:$AA$56) -> 60271.732 | V36: =$L$9*AA36*AB36/SUMPRODUCT($AB$25:$AB$58,$AA$25:$AA$58) -> 8.7350336 | W36: =IF($L$12="","",V36/$L$12) -> 5.0201342 | X36: =IF(AB36<>"",IF(D36<>"",D36,($L$8-SUM($X$25:X35))*AA36*AB36/SUMPRODUCT($AB36:$AB$58,$AA36:$AA$58)),"") -> 0 | Y36: =IF(AB36<>"",IF(E35<>"",E35,($L$9-SUM($Y$25:Y35))*AA36*AB36/SUMPRODUCT($AB36:$AB$58,$AA36:$AA$58)),"") -> 10 | Z36: =IF(AB36<>"",IF($L$12<>"",IF(G36<>"",G36,($L$9/$L$12-SUM($Z$25:Z35))*AA36*AB36/SUMPRODUCT($AB36:$AB$58,$AA36:$AA$58)),""),"") -> 0 | AA36: 1 | AB36: 1
A37: 13 | B37: 46104 | C37: пн | D37: 83292 | E37: 13 | F37: =IF(AND(E37<>"",E37<>0),D37/E37,"") -> 6407.0769 | G37: 5 | H37: =IF(AND(G37<>"",G37<>0),D37/G37,"") -> 16658.4 | I37: 50 | J37: =IF(AND(G37<>"",G37<>0),E37/G37,"") -> 2.6 | Q37: 17583 | S37: =IF(AND(I37<>"",I37<>0),G37/I37,"") -> 0.1 | T37: =D37/U37 -> 1.3819414 | U37: =$L$8*AA37*AB37/SUMPRODUCT($AB$25:$AB$56,$AA$25:$AA$56) -> 60271.732 | V37: =$L$9*AA37*AB37/SUMPRODUCT($AB$25:$AB$58,$AA$25:$AA$58) -> 8.7350336 | W37: =IF($L$12="","",V37/$L$12) -> 5.0201342 | X37: =IF(AB37<>"",IF(D37<>"",D37,($L$8-SUM($X$25:X36))*AA37*AB37/SUMPRODUCT($AB37:$AB$58,$AA37:$AA$58)),"") -> 83292 | Y37: =IF(AB37<>"",IF(E37<>"",E37,($L$9-SUM($Y$25:Y36))*AA37*AB37/SUMPRODUCT($AB37:$AB$58,$AA37:$AA$58)),"") -> 13 | Z37: =IF(AB37<>"",IF($L$12<>"",IF(G37<>"",G37,($L$9/$L$12-SUM($Z$25:Z36))*AA37*AB37/SUMPRODUCT($AB37:$AB$58,$AA37:$AA$58)),""),"") -> 5 | AA37: 1 | AB37: 1
A38: 14 | B38: 46105 | C38: вт | D38: 24862 | E38: 5 | F38: =IF(AND(E38<>"",E38<>0),D38/E38,"") -> 4972.4 | G38: 3 | H38: =IF(AND(G38<>"",G38<>0),D38/G38,"") -> 8287.3333 | I38: 45 | J38: =IF(AND(G38<>"",G38<>0),E38/G38,"") -> 1.6666667 | R38: 2790 | S38: =IF(AND(I38<>"",I38<>0),G38/I38,"") -> 0.066666667 | T38: =D38/U38 -> 0.41249852 | U38: =$L$8*AA38*AB38/SUMPRODUCT($AB$25:$AB$56,$AA$25:$AA$56) -> 60271.732 | V38: =$L$9*AA38*AB38/SUMPRODUCT($AB$25:$AB$58,$AA$25:$AA$58) -> 8.7350336 | W38: =IF($L$12="","",V38/$L$12) -> 5.0201342 | X38: =IF(AB38<>"",IF(D38<>"",D38,($L$8-SUM($X$25:X37))*AA38*AB38/SUMPRODUCT($AB38:$AB$58,$AA38:$AA$58)),"") -> 24862 | Y38: =IF(AB38<>"",IF(E38<>"",E38,($L$9-SUM($Y$25:Y37))*AA38*AB38/SUMPRODUCT($AB38:$AB$58,$AA38:$AA$58)),"") -> 5 | Z38: =IF(AB38<>"",IF($L$12<>"",IF(G38<>"",G38,($L$9/$L$12-SUM($Z$25:Z37))*AA38*AB38/SUMPRODUCT($AB38:$AB$58,$AA38:$AA$58)),""),"") -> 3 | AA38: 1 | AB38: 1
A39: 15 | B39: 46108 | C39: пт | D39: 25776 | E39: 3 | F39: =IF(AND(E39<>"",E39<>0),D39/E39,"") -> 8592 | G39: 1 | H39: =IF(AND(G39<>"",G39<>0),D39/G39,"") -> 25776 | I39: 60 | J39: =IF(AND(G39<>"",G39<>0),E39/G39,"") -> 3 | O39: 21180 | S39: =IF(AND(I39<>"",I39<>0),G39/I39,"") -> 0.016666667 | T39: =D39/U39 -> #DIV/0! | U39: =$L$8*AA39*AB39/SUMPRODUCT($AB$25:$AB$56,$AA$25:$AA$56) -> 0 | V39: =$L$9*AA39*AB39/SUMPRODUCT($AB$25:$AB$58,$AA$25:$AA$58) -> 0 | W39: =IF($L$12="","",V39/$L$12) -> 0 | X39: =IF(AB39<>"",IF(D39<>"",D39,($L$8-SUM($X$25:X38))*AA39*AB39/SUMPRODUCT($AB39:$AB$58,$AA39:$AA$58)),"") | Y39: =IF(AB39<>"",IF(E39<>"",E39,($L$9-SUM($Y$25:Y38))*AA39*AB39/SUMPRODUCT($AB39:$AB$58,$AA39:$AA$58)),"") | Z39: =IF(AB39<>"",IF($L$12<>"",IF(G39<>"",G39,($L$9/$L$12-SUM($Z$25:Z38))*AA39*AB39/SUMPRODUCT($AB39:$AB$58,$AA39:$AA$58)),""),"")
A40: 16 | B40: 46109 | C40: сб | D40: 60520 | E40: 10 | F40: =IF(AND(E40<>"",E40<>0),D40/E40,"") -> 6052 | G40: 5 | H40: =IF(AND(G40<>"",G40<>0),D40/G40,"") -> 12104 | I40: 65 | J40: =IF(AND(G40<>"",G40<>0),E40/G40,"") -> 2 | S40: =IF(AND(I40<>"",I40<>0),G40/I40,"") -> 0.076923077 | T40: =D40/U40 -> #DIV/0! | U40: =$L$8*AA40*AB40/SUMPRODUCT($AB$25:$AB$56,$AA$25:$AA$56) -> 0 | V40: =$L$9*AA40*AB40/SUMPRODUCT($AB$25:$AB$58,$AA$25:$AA$58) -> 0 | W40: =IF($L$12="","",V40/$L$12) -> 0 | X40: =IF(AB40<>"",IF(D40<>"",D40,($L$8-SUM($X$25:X39))*AA40*AB40/SUMPRODUCT($AB40:$AB$58,$AA40:$AA$58)),"") | Y40: =IF(AB40<>"",IF(E40<>"",E40,($L$9-SUM($Y$25:Y39))*AA40*AB40/SUMPRODUCT($AB40:$AB$58,$AA40:$AA$58)),"") | Z40: =IF(AB40<>"",IF($L$12<>"",IF(G40<>"",G40,($L$9/$L$12-SUM($Z$25:Z39))*AA40*AB40/SUMPRODUCT($AB40:$AB$58,$AA40:$AA$58)),""),"")
A41: 17 | B41: 46110 | C41: вс | D41: 48038 | E41: 8 | F41: =IF(AND(E41<>"",E41<>0),D41/E41,"") -> 6004.75 | G41: 4 | H41: =IF(AND(G41<>"",G41<>0),D41/G41,"") -> 12009.5 | I41: 75 | J41: =IF(AND(G41<>"",G41<>0),E41/G41,"") -> 2 | R41: 3192 | S41: =IF(AND(I41<>"",I41<>0),G41/I41,"") -> 0.053333333 | T41: =D41/U41 -> #DIV/0! | U41: =$L$8*AA41*AB41/SUMPRODUCT($AB$25:$AB$56,$AA$25:$AA$56) -> 0 | V41: =$L$9*AA41*AB41/SUMPRODUCT($AB$25:$AB$58,$AA$25:$AA$58) -> 0 | W41: =IF($L$12="","",V41/$L$12) -> 0 | X41: =IF(AB41<>"",IF(D41<>"",D41,($L$8-SUM($X$25:X40))*AA41*AB41/SUMPRODUCT($AB41:$AB$58,$AA41:$AA$58)),"") | Y41: =IF(AB41<>"",IF(E41<>"",E41,($L$9-SUM($Y$25:Y40))*AA41*AB41/SUMPRODUCT($AB41:$AB$58,$AA41:$AA$58)),"") | Z41: =IF(AB41<>"",IF($L$12<>"",IF(G41<>"",G41,($L$9/$L$12-SUM($Z$25:Z40))*AA41*AB41/SUMPRODUCT($AB41:$AB$58,$AA41:$AA$58)),""),"")
A42: 18 | F42: =IF(AND(E42<>"",E42<>0),D42/E42,"") | H42: =IF(AND(G42<>"",G42<>0),D42/G42,"") | J42: =IF(AND(G42<>"",G42<>0),E42/G42,"") | S42: =IF(AND(I42<>"",I42<>0),G42/I42,"") | T42: =D42/U42 -> #DIV/0! | U42: =$L$8*AA42*AB42/SUMPRODUCT($AB$25:$AB$56,$AA$25:$AA$56) -> 0 | V42: =$L$9*AA42*AB42/SUMPRODUCT($AB$25:$AB$58,$AA$25:$AA$58) -> 0 | W42: =IF($L$12="","",V42/$L$12) -> 0 | X42: =IF(AB42<>"",IF(D42<>"",D42,($L$8-SUM($X$25:X41))*AA42*AB42/SUMPRODUCT($AB42:$AB$58,$AA42:$AA$58)),"") | Y42: =IF(AB42<>"",IF(E42<>"",E42,($L$9-SUM($Y$25:Y41))*AA42*AB42/SUMPRODUCT($AB42:$AB$58,$AA42:$AA$58)),"") | Z42: =IF(AB42<>"",IF($L$12<>"",IF(G42<>"",G42,($L$9/$L$12-SUM($Z$25:Z41))*AA42*AB42/SUMPRODUCT($AB42:$AB$58,$AA42:$AA$58)),""),"")
A43: 18 | F43: =IF(AND(E43<>"",E43<>0),D43/E43,"") | H43: =IF(AND(G43<>"",G43<>0),D43/G43,"") | J43: =IF(AND(G43<>"",G43<>0),E43/G43,"") | S43: =IF(AND(I43<>"",I43<>0),G43/I43,"") | T43: =D43/U43 -> #DIV/0! | U43: =$L$8*AA43*AB43/SUMPRODUCT($AB$25:$AB$56,$AA$25:$AA$56) -> 0 | V43: =$L$9*AA43*AB43/SUMPRODUCT($AB$25:$AB$58,$AA$25:$AA$58) -> 0 | W43: =IF($L$12="","",V43/$L$12) -> 0 | X43: =IF(AB43<>"",IF(D43<>"",D43,($L$8-SUM($X$25:X42))*AA43*AB43/SUMPRODUCT($AB43:$AB$58,$AA43:$AA$58)),"") | Y43: =IF(AB43<>"",IF(E43<>"",E43,($L$9-SUM($Y$25:Y42))*AA43*AB43/SUMPRODUCT($AB43:$AB$58,$AA43:$AA$58)),"") | Z43: =IF(AB43<>"",IF($L$12<>"",IF(G43<>"",G43,($L$9/$L$12-SUM($Z$25:Z42))*AA43*AB43/SUMPRODUCT($AB43:$AB$58,$AA43:$AA$58)),""),"")
A44: 19 | F44: =IF(AND(E44<>"",E44<>0),D44/E44,"") | H44: =IF(AND(G44<>"",G44<>0),D44/G44,"") | J44: =IF(AND(G44<>"",G44<>0),E44/G44,"") | S44: =IF(AND(I44<>"",I44<>0),G44/I44,"") | T44: =D44/U44 -> #DIV/0! | U44: =$L$8*AA44*AB44/SUMPRODUCT($AB$25:$AB$56,$AA$25:$AA$56) -> 0 | V44: =$L$9*AA44*AB44/SUMPRODUCT($AB$25:$AB$58,$AA$25:$AA$58) -> 0 | W44: =IF($L$12="","",V44/$L$12) -> 0 | X44: =IF(AB44<>"",IF(D44<>"",D44,($L$8-SUM($X$25:X43))*AA44*AB44/SUMPRODUCT($AB44:$AB$58,$AA44:$AA$58)),"") | Y44: =IF(AB44<>"",IF(E44<>"",E44,($L$9-SUM($Y$25:Y43))*AA44*AB44/SUMPRODUCT($AB44:$AB$58,$AA44:$AA$58)),"") | Z44: =IF(AB44<>"",IF($L$12<>"",IF(G44<>"",G44,($L$9/$L$12-SUM($Z$25:Z43))*AA44*AB44/SUMPRODUCT($AB44:$AB$58,$AA44:$AA$58)),""),"")
A45: 20 | F45: =IF(AND(E45<>"",E45<>0),D45/E45,"") | H45: =IF(AND(G45<>"",G45<>0),D45/G45,"") | J45: =IF(AND(G45<>"",G45<>0),E45/G45,"") | S45: =IF(AND(I45<>"",I45<>0),G45/I45,"") | T45: =D45/U45 -> #DIV/0! | U45: =$L$8*AA45*AB45/SUMPRODUCT($AB$25:$AB$56,$AA$25:$AA$56) -> 0 | V45: =$L$9*AA45*AB45/SUMPRODUCT($AB$25:$AB$58,$AA$25:$AA$58) -> 0 | W45: =IF($L$12="","",V45/$L$12) -> 0 | X45: =IF(AB45<>"",IF(D45<>"",D45,($L$8-SUM($X$25:X44))*AA45*AB45/SUMPRODUCT($AB45:$AB$58,$AA45:$AA$58)),"") | Y45: =IF(AB45<>"",IF(E45<>"",E45,($L$9-SUM($Y$25:Y44))*AA45*AB45/SUMPRODUCT($AB45:$AB$58,$AA45:$AA$58)),"") | Z45: =IF(AB45<>"",IF($L$12<>"",IF(G45<>"",G45,($L$9/$L$12-SUM($Z$25:Z44))*AA45*AB45/SUMPRODUCT($AB45:$AB$58,$AA45:$AA$58)),""),"")
A46: 21 | F46: =IF(AND(E46<>"",E46<>0),D46/E46,"") | H46: =IF(AND(G46<>"",G46<>0),D46/G46,"") | J46: =IF(AND(G46<>"",G46<>0),E46/G46,"") | S46: =IF(AND(I46<>"",I46<>0),G46/I46,"") | T46: =D46/U46 -> #DIV/0! | U46: =$L$8*AA46*AB46/SUMPRODUCT($AB$25:$AB$56,$AA$25:$AA$56) -> 0 | V46: =$L$9*AA46*AB46/SUMPRODUCT($AB$25:$AB$58,$AA$25:$AA$58) -> 0 | W46: =IF($L$12="","",V46/$L$12) -> 0 | X46: =IF(AB46<>"",IF(D46<>"",D46,($L$8-SUM($X$25:X45))*AA46*AB46/SUMPRODUCT($AB46:$AB$58,$AA46:$AA$58)),"") | Y46: =IF(AB46<>"",IF(E46<>"",E46,($L$9-SUM($Y$25:Y45))*AA46*AB46/SUMPRODUCT($AB46:$AB$58,$AA46:$AA$58)),"") | Z46: =IF(AB46<>"",IF($L$12<>"",IF(G46<>"",G46,($L$9/$L$12-SUM($Z$25:Z45))*AA46*AB46/SUMPRODUCT($AB46:$AB$58,$AA46:$AA$58)),""),"")
A47: 22 | F47: =IF(AND(E47<>"",E47<>0),D47/E47,"") | H47: =IF(AND(G47<>"",G47<>0),D47/G47,"") | J47: =IF(AND(G47<>"",G47<>0),E47/G47,"") | S47: =IF(AND(I47<>"",I47<>0),G47/I47,"") | T47: =D47/U47 -> #DIV/0! | U47: =$L$8*AA47*AB47/SUMPRODUCT($AB$25:$AB$56,$AA$25:$AA$56) -> 0 | V47: =$L$9*AA47*AB47/SUMPRODUCT($AB$25:$AB$58,$AA$25:$AA$58) -> 0 | W47: =IF($L$12="","",V47/$L$12) -> 0 | X47: =IF(AB47<>"",IF(D47<>"",D47,($L$8-SUM($X$25:X46))*AA47*AB47/SUMPRODUCT($AB47:$AB$58,$AA47:$AA$58)),"") | Y47: =IF(AB47<>"",IF(E47<>"",E47,($L$9-SUM($Y$25:Y46))*AA47*AB47/SUMPRODUCT($AB47:$AB$58,$AA47:$AA$58)),"") | Z47: =IF(AB47<>"",IF($L$12<>"",IF(G47<>"",G47,($L$9/$L$12-SUM($Z$25:Z46))*AA47*AB47/SUMPRODUCT($AB47:$AB$58,$AA47:$AA$58)),""),"")
A48: 23 | F48: =IF(AND(E48<>"",E48<>0),D48/E48,"") | H48: =IF(AND(G48<>"",G48<>0),D48/G48,"") | J48: =IF(AND(G48<>"",G48<>0),E48/G48,"") | S48: =IF(AND(I48<>"",I48<>0),G48/I48,"") | T48: =D48/U48 -> #DIV/0! | U48: =$L$8*AA48*AB48/SUMPRODUCT($AB$25:$AB$56,$AA$25:$AA$56) -> 0 | V48: =$L$9*AA48*AB48/SUMPRODUCT($AB$25:$AB$58,$AA$25:$AA$58) -> 0 | W48: =IF($L$12="","",V48/$L$12) -> 0 | X48: =IF(AB48<>"",IF(D48<>"",D48,($L$8-SUM($X$25:X47))*AA48*AB48/SUMPRODUCT($AB48:$AB$58,$AA48:$AA$58)),"") | Y48: =IF(AB48<>"",IF(E48<>"",E48,($L$9-SUM($Y$25:Y47))*AA48*AB48/SUMPRODUCT($AB48:$AB$58,$AA48:$AA$58)),"") | Z48: =IF(AB48<>"",IF($L$12<>"",IF(G48<>"",G48,($L$9/$L$12-SUM($Z$25:Z47))*AA48*AB48/SUMPRODUCT($AB48:$AB$58,$AA48:$AA$58)),""),"")
A49: 24 | H49: =IF(AND(G49<>"",G49<>0),D49/G49,"") | J49: =IF(AND(G49<>"",G49<>0),E49/G49,"") | S49: =IF(AND(I49<>"",I49<>0),G49/I49,"") | T49: =D49/U49 -> #DIV/0! | U49: =$L$8*AA49*AB49/SUMPRODUCT($AB$25:$AB$56,$AA$25:$AA$56) -> 0 | V49: =$L$9*AA49*AB49/SUMPRODUCT($AB$25:$AB$58,$AA$25:$AA$58) -> 0 | W49: =IF($L$12="","",V49/$L$12) -> 0 | X49: =IF(AB49<>"",IF(D49<>"",D49,($L$8-SUM($X$25:X48))*AA49*AB49/SUMPRODUCT($AB49:$AB$58,$AA49:$AA$58)),"") | Y49: =IF(AB49<>"",IF(E49<>"",E49,($L$9-SUM($Y$25:Y48))*AA49*AB49/SUMPRODUCT($AB49:$AB$58,$AA49:$AA$58)),"") | Z49: =IF(AB49<>"",IF($L$12<>"",IF(G49<>"",G49,($L$9/$L$12-SUM($Z$25:Z48))*AA49*AB49/SUMPRODUCT($AB49:$AB$58,$AA49:$AA$58)),""),"")
F50: =IF(AND(E50<>"",E50<>0),D50/E50,"") | H50: =IF(AND(G50<>"",G50<>0),D50/G50,"") | J50: =IF(AND(G50<>"",G50<>0),E50/G50,"") | S50: =IF(AND(I50<>"",I50<>0),G50/I50,"") | T50: =D50/U50 -> #DIV/0! | U50: =$L$8*AA50*AB50/SUMPRODUCT($AB$25:$AB$56,$AA$25:$AA$56) -> 0 | V50: =$L$9*AA50*AB50/SUMPRODUCT($AB$25:$AB$58,$AA$25:$AA$58) -> 0 | W50: =IF($L$12="","",V50/$L$12) -> 0 | X50: =IF(AB50<>"",IF(D50<>"",D50,($L$8-SUM($X$25:X49))*AA50*AB50/SUMPRODUCT($AB50:$AB$58,$AA50:$AA$58)),"") | Y50: =IF(AB50<>"",IF(E50<>"",E50,($L$9-SUM($Y$25:Y49))*AA50*AB50/SUMPRODUCT($AB50:$AB$58,$AA50:$AA$58)),"") | Z50: =IF(AB50<>"",IF($L$12<>"",IF(G50<>"",G50,($L$9/$L$12-SUM($Z$25:Z49))*AA50*AB50/SUMPRODUCT($AB50:$AB$58,$AA50:$AA$58)),""),"")
F51: =IF(AND(E51<>"",E51<>0),D51/E51,"") | H51: =IF(AND(G51<>"",G51<>0),D51/G51,"") | J51: =IF(AND(G51<>"",G51<>0),E51/G51,"") | S51: =IF(AND(I51<>"",I51<>0),G51/I51,"") | T51: =D51/U51 -> #DIV/0! | U51: =$L$8*AA51*AB51/SUMPRODUCT($AB$25:$AB$56,$AA$25:$AA$56) -> 0 | V51: =$L$9*AA51*AB51/SUMPRODUCT($AB$25:$AB$58,$AA$25:$AA$58) -> 0 | W51: =IF($L$12="","",V51/$L$12) -> 0 | X51: =IF(AB51<>"",IF(D51<>"",D51,($L$8-SUM($X$25:X50))*AA51*AB51/SUMPRODUCT($AB51:$AB$58,$AA51:$AA$58)),"") | Y51: =IF(AB51<>"",IF(E51<>"",E51,($L$9-SUM($Y$25:Y50))*AA51*AB51/SUMPRODUCT($AB51:$AB$58,$AA51:$AA$58)),"") | Z51: =IF(AB51<>"",IF($L$12<>"",IF(G51<>"",G51,($L$9/$L$12-SUM($Z$25:Z50))*AA51*AB51/SUMPRODUCT($AB51:$AB$58,$AA51:$AA$58)),""),"")
F52: =IF(AND(E52<>"",E52<>0),D52/E52,"") | H52: =IF(AND(G52<>"",G52<>0),D52/G52,"") | J52: =IF(AND(G52<>"",G52<>0),E52/G52,"") | S52: =IF(AND(I52<>"",I52<>0),G52/I52,"") | T52: =D52/U52 -> #DIV/0! | U52: =$L$8*AA52*AB52/SUMPRODUCT($AB$25:$AB$56,$AA$25:$AA$56) -> 0 | V52: =$L$9*AA52*AB52/SUMPRODUCT($AB$25:$AB$58,$AA$25:$AA$58) -> 0 | W52: =IF($L$12="","",V52/$L$12) -> 0 | X52: =IF(AB52<>"",IF(D52<>"",D52,($L$8-SUM($X$25:X51))*AA52*AB52/SUMPRODUCT($AB52:$AB$58,$AA52:$AA$58)),"") | Y52: =IF(AB52<>"",IF(E52<>"",E52,($L$9-SUM($Y$25:Y51))*AA52*AB52/SUMPRODUCT($AB52:$AB$58,$AA52:$AA$58)),"") | Z52: =IF(AB52<>"",IF($L$12<>"",IF(G52<>"",G52,($L$9/$L$12-SUM($Z$25:Z51))*AA52*AB52/SUMPRODUCT($AB52:$AB$58,$AA52:$AA$58)),""),"")
F53: =IF(AND(E53<>"",E53<>0),D53/E53,"") | H53: =IF(AND(G53<>"",G53<>0),D53/G53,"") | J53: =IF(AND(G53<>"",G53<>0),E53/G53,"") | S53: =IF(AND(I53<>"",I53<>0),G53/I53,"") | T53: =D53/U53 -> #DIV/0! | U53: =$L$8*AA53*AB53/SUMPRODUCT($AB$25:$AB$56,$AA$25:$AA$56) -> 0 | V53: =$L$9*AA53*AB53/SUMPRODUCT($AB$25:$AB$58,$AA$25:$AA$58) -> 0 | W53: =IF($L$12="","",V53/$L$12) -> 0 | X53: =IF(AB53<>"",IF(D53<>"",D53,($L$8-SUM($X$25:X52))*AA53*AB53/SUMPRODUCT($AB53:$AB$58,$AA53:$AA$58)),"") | Y53: =IF(AB53<>"",IF(E53<>"",E53,($L$9-SUM($Y$25:Y52))*AA53*AB53/SUMPRODUCT($AB53:$AB$58,$AA53:$AA$58)),"") | Z53: =IF(AB53<>"",IF($L$12<>"",IF(G53<>"",G53,($L$9/$L$12-SUM($Z$25:Z52))*AA53*AB53/SUMPRODUCT($AB53:$AB$58,$AA53:$AA$58)),""),"")
F54: =IF(AND(E54<>"",E54<>0),D54/E54,"") | H54: =IF(AND(G54<>"",G54<>0),D54/G54,"") | J54: =IF(AND(G54<>"",G54<>0),E54/G54,"") | S54: =IF(AND(I54<>"",I54<>0),G54/I54,"") | T54: =D54/U54 -> #DIV/0! | U54: =$L$8*AA54*AB54/SUMPRODUCT($AB$25:$AB$56,$AA$25:$AA$56) -> 0 | V54: =$L$9*AA54*AB54/SUMPRODUCT($AB$25:$AB$58,$AA$25:$AA$58) -> 0 | W54: =IF($L$12="","",V54/$L$12) -> 0 | X54: =IF(AB54<>"",IF(D54<>"",D54,($L$8-SUM($X$25:X50))*AA54*AB54/SUMPRODUCT($AB54:$AB$58,$AA54:$AA$58)),"") | Y54: =IF(AB54<>"",IF(E54<>"",E54,($L$9-SUM($Y$25:Y50))*AA54*AB54/SUMPRODUCT($AB54:$AB$58,$AA54:$AA$58)),"") | Z54: =IF(AB54<>"",IF($L$12<>"",IF(G54<>"",G54,($L$9/$L$12-SUM($Z$25:Z50))*AA54*AB54/SUMPRODUCT($AB54:$AB$58,$AA54:$AA$58)),""),"")
F55: =IF(AND(E55<>"",E55<>0),D55/E55,"") | H55: =IF(AND(G55<>"",G55<>0),D55/G55,"") | J55: =IF(AND(G55<>"",G55<>0),E55/G55,"") | S55: =IF(AND(I55<>"",I55<>0),G55/I55,"") | T55: =D55/U55 -> #DIV/0! | U55: =$L$8*AA55*AB55/SUMPRODUCT($AB$25:$AB$56,$AA$25:$AA$56) -> 0 | V55: =$L$9*AA55*AB55/SUMPRODUCT($AB$25:$AB$58,$AA$25:$AA$58) -> 0 | W55: =IF($L$12="","",V55/$L$12) -> 0 | X55: =IF(AB55<>"",IF(D55<>"",D55,($L$8-SUM($X$25:X54))*AA55*AB55/SUMPRODUCT($AB55:$AB$58,$AA55:$AA$58)),"") | Y55: =IF(AB55<>"",IF(E55<>"",E55,($L$9-SUM($Y$25:Y54))*AA55*AB55/SUMPRODUCT($AB55:$AB$58,$AA55:$AA$58)),"") | Z55: =IF(AB55<>"",IF($L$12<>"",IF(G55<>"",G55,($L$9/$L$12-SUM($Z$25:Z54))*AA55*AB55/SUMPRODUCT($AB55:$AB$58,$AA55:$AA$58)),""),"")
F56: =IF(AND(E56<>"",E56<>0),D56/E56,"") | H56: =IF(AND(G56<>"",G56<>0),D56/G56,"") | J56: =IF(AND(G56<>"",G56<>0),E56/G56,"") | S56: =IF(AND(I56<>"",I56<>0),G56/I56,"") | T56: =D56/U56 -> #DIV/0! | U56: =$L$8*AA56*AB56/SUMPRODUCT($AB$25:$AB$56,$AA$25:$AA$56) -> 0 | V56: =$L$9*AA56*AB56/SUMPRODUCT($AB$25:$AB$58,$AA$25:$AA$58) -> 0 | W56: =IF($L$12="","",V56/$L$12) -> 0 | X56: =IF(AB56<>"",IF(D56<>"",D56,($L$8-SUM($X$25:X55))*AA56*AB56/SUMPRODUCT($AB56:$AB$58,$AA56:$AA$58)),"") | Y56: =IF(AB56<>"",IF(E56<>"",E56,($L$9-SUM($Y$25:Y55))*AA56*AB56/SUMPRODUCT($AB56:$AB$58,$AA56:$AA$58)),"") | Z56: =IF(AB56<>"",IF($L$12<>"",IF(G56<>"",G56,($L$9/$L$12-SUM($Z$25:Z55))*AA56*AB56/SUMPRODUCT($AB56:$AB$58,$AA56:$AA$58)),""),"")
D57: =SUM(D25:D56) -> 576247 | E57: =SUM(E25:E56) -> 95 | F57: =IF(AND(E57<>"",E57<>0),D57/E57,"") -> 6065.7579 | G57: =SUM(G25:G56) -> 50 | H57: =IF(AND(G57<>"",G57<>0),D57/G57,"") -> 11524.94 | I57: =SUM(I25:I56) -> 615 | J57: =IF(AND(G57<>"",G57<>0),E57/G57,"") -> 1.9 | K57: =SUM(K25:K56) -> 41316 | L57: =SUM(L25:L56) -> 0 | M57: =SUM(M25:M56) -> 0 | N57: =SUM(N25:N56) -> 0 | O57: =SUM(O25:O56) -> 21180 | P57: =SUM(P25:P56) -> 14352 | Q57: =SUM(Q25:Q56) -> 25823 | R57: =SUM(R25:R56) -> 42374 | S57: =IF(AND(I57<>"",I57<>0),G57/I57,"") -> 0.081300813 | T57: =D57/U57 -> 0.68291551 | U57: =SUM(U25:U56) -> 843804.24 | V57: =SUM(V25:V55) -> 122.29047 | W57: =SUM(W25:W55) -> 70.281879 | X57: =SUM(X25:X56) -> 441913 | Y57: =SUM(Y25:Y55) -> 77 | Z57: =SUM(Z25:Z55) -> 40

Sheet Самошкина
B1: =TODAY()-1 -> 46171
B2: (отчетная дата) | J2: ЕЖЕДНЕВНЫЙ ОТЧЕТ О ПРОДАЖАХ
B3: Осталось до выполнения плана!!! | J3: =График!B27 -> Самошкина Алина
C4: =L8-D50 -> 545990.98 | E4: =IF(L8<>0,C4/L8,0) -> 1
I6: Целевые показатели
I7: Показатель | L7: План | M7: Факт | N7: % выполнения | O7: Прогноз выполнения | P7: % выполнения по прогнозу | Q7: Отклонение | R7: Факт аналогичного месяца прошлого года | S7: Отклонение LFL
I8: Выручка | L8: ='Ялта, Ленина, 18'!I8/График!AJ30*График!AJ27 -> 545990.98 | M8: =D57 -> 168150 | N8: =IF(AND(L8<>"",L8<>0,M8<>""),M8/L8,"") -> 0.30797212 | O8: =IF(SUMIF($D$25:$D$56,">=0",$U$25:$U$56)<>0,L8*D57/SUMIF($D$25:$D$56,">=0",$U$25:$U$56),0) -> 168150 | P8: =IF(AND(L8<>"",L8<>0,O8<>"",O8<>0),O8/L8,"") -> 0.30797212 | Q8: =IF(AND(M8<>0,M8<>"",L8<>0,L8<>""),O8-L8,"") -> -377840.98 | S8: =IF(AND(R8<>"",R8<>0,O8<>"",O8<>0),-R8+O8,"") | T8: =IF(AND(S8<>"",S8<>0,R8<>0,R8<>""),S8/R8,"")
I9: Кол-во изделий | L9: =L8/L11 -> 79.129128 | M9: =E57 -> 24 | N9: =IF(AND(L9<>"",L9<>0,M9<>""),M9/L9,"") -> 0.30330171 | O9: =IF(SUMIF($E$25:$E$54,">=0",$V$25:$V$54)<>0,L9*E57/SUMIF($E$25:$E$54,">=0",$V$25:$V$54),0) -> 24 | P9: =IF(AND(L9<>"",L9<>0,O9<>"",O9<>0),O9/L9,"") -> 0.30330171 | Q9: =IF(AND(M9<>0,M9<>"",L9<>0,L9<>""),O9-L9,"") -> -55.129128 | R9: =R8/R11 -> #DIV/0! | S9: =IF(AND(R9<>"",R9<>0,O9<>"",O9<>0),-R9+O9,"") -> #DIV/0! | T9: =IF(AND(S9<>"",S9<>0,R9<>0,R9<>""),S9/R9,"") -> #DIV/0!
I10: Средний чек | L10: =L11*L12 -> 12006 | M10: =H57 -> 9341.6667 | N10: =IF(AND(L10<>"",L10<>0,M10<>""),M10/L10,"") -> 0.77808318 | O10: =M10 -> 9341.6667 | P10: =IF(AND(L10<>"",L10<>0,O10<>"",O10<>0),O10/L10,"") -> 0.77808318 | Q10: =IF(AND(M10<>0,M10<>"",L10<>0,L10<>""),O10-L10,"") -> -2664.3333 | R10: =R11*R12 -> 0 | S10: =IF(AND(R10<>"",R10<>0,O10<>"",O10<>0),-R10+O10,"") | T10: =IF(AND(S10<>"",S10<>0,R10<>0,R10<>""),S10/R10,"")
I11: Средняя стоимость изделия | L11: ='Ялта, Ленина, 18'!I11 -> 6900 | M11: =F57 -> 7006.25 | N11: =IF(AND(L11<>"",L11<>0,M11<>""),M11/L11,"") -> 1.0153986 | O11: =IF(O9>0,O8/O9,"") -> 7006.25 | P11: =IF(AND(L11<>"",L11<>0,O11<>"",O11<>0),O11/L11,"") -> 1.0153986 | Q11: =IF(AND(M11<>0,M11<>"",L11<>0,L11<>""),O11-L11,"") -> 106.25 | S11: =IF(AND(R11<>"",R11<>0,O11<>"",O11<>0),-R11+O11,"") | T11: =IF(AND(S11<>"",S11<>0,R11<>0,R11<>""),S11/R11,"")
I12: Длина чека | L12: ='Ялта, Ленина, 18'!I12 -> 1.74 | M12: =J57 -> 1.3333333 | N12: =IF(AND(L12<>"",L12<>0,M12<>""),M12/L12,"") -> 0.76628352 | O12: =M12 -> 1.3333333 | P12: =IF(AND(L12<>"",L12<>0,O12<>"",O12<>0),O12/L12,"") -> 0.76628352 | Q12: =IF(AND(M12<>0,M12<>"",L12<>0,L12<>""),O12-L12,"") -> -0.40666667 | S12: =IF(AND(R12<>"",R12<>0,O12<>"",O12<>0),-R12+O12,"") | T12: =IF(AND(S12<>"",S12<>0,R12<>0,R12<>""),S12/R12,"") | W12: =U12-V12 -> 0
I13: Кол-во чеков | L13: =IF(L12<>0,L9/L12,"") -> 45.47651 | M13: =G57 -> 18 | N13: =IF(AND(L13<>"",L13<>0,M13<>""),M13/L13,"") -> 0.39580874 | O13: =IF(SUMIF($G$25:$G$54,">=0",$W$25:$W$54)<>0,L13*G57/SUMIF($G$25:$G$54,">=0",$W$25:$W$54),"") -> 18 | P13: =IF(AND(L13<>"",L13<>0,O13<>"",O13<>0),O13/L13,"") -> 0.39580874 | Q13: =IF(AND(M13<>0,M13<>"",L13<>0,L13<>""),O13-L13,"") -> -27.47651 | S13: =IF(AND(R13<>"",R13<>0,O13<>"",O13<>0),-R13+O13,"") | T13: =IF(AND(S13<>"",S13<>0,R13<>0,R13<>""),S13/R13,"")
I14: Кол-во смен план/отработано | L14: =График!AI27 -> 11 | M14: 11 | N14: =IF(AND(L14<>"",L14<>0,M14<>""),M14/L14,"") -> 1 | O14: =L14 -> 11 | P14: =IF(AND(L14<>"",L14<>0,O14<>"",O14<>0),O14/L14,"") -> 1 | Q14: =IF(AND(M14<>0,M14<>"",L14<>0,L14<>""),O14-L14,"") -> 0 | S14: =IF(AND(R14<>"",R14<>0,O14<>"",O14<>0),-R14+O14,"") | T14: =IF(AND(S14<>"",S14<>0,R14<>0,R14<>""),S14/R14,"")
I15: Средние продажи в смену | L15: ='Ялта, Ленина, 18'!I15 -> 65064.774 | M15: =M8/M14 -> 15286.364 | N15: =IF(AND(L15<>"",L15<>0,M15<>""),M15/L15,"") -> 0.2349407 | O15: =M15 -> 15286.364 | P15: =IF(AND(L15<>"",L15<>0,O15<>"",O15<>0),O15/L15,"") -> 0.2349407 | Q15: =IF(AND(M15<>0,M15<>"",L15<>0,L15<>""),O15-L15,"") -> -49778.411 | S15: =IF(AND(R15<>"",R15<>0,O15<>"",O15<>0),-R15+O15,"") | T15: =IF(AND(S15<>"",S15<>0,R15<>0,R15<>""),S15/R15,"")
I16: Отставание/Перевыполнение | M16: =M8-L15*M14 -> -547562.52 | N16: =IF(AND(L16<>"",L16<>0,M16<>""),M16/L16,"") | O16: =M16 -> -547562.52 | P16: =IF(AND(L16<>"",L16<>0,O16<>"",O16<>0),O16/L16,"") | Q16: =IF(AND(M16<>0,M16<>"",L16<>0,L16<>""),O16-L16,"") | S16: =IF(AND(R16<>"",R16<>0,O16<>"",O16<>0),-R16+O16,"") | T16: =IF(AND(S16<>"",S16<>0,R16<>0,R16<>""),S16/R16,"")
I17: Трафик | L17: ='Ялта, Ленина, 18'!I17/График!AJ30*График!AJ27 -> 378.97092 | M17: =I57 -> 364 | N17: =IF(AND(L17<>"",L17<>0,M17<>""),M17/L17,"") -> 0.96049587 | O17: =M17/M14*L14 -> 364 | P17: =IF(AND(L17<>"",L17<>0,O17<>"",O17<>0),O17/L17,"") -> 0.96049587 | Q17: =IF(AND(M17<>0,M17<>"",L17<>0,L17<>""),O17-L17,"") -> -14.970917 | S17: =IF(AND(R17<>"",R17<>0,O17<>"",O17<>0),-R17+O17,"") | T17: =IF(AND(S17<>"",S17<>0,R17<>0,R17<>""),S17/R17,"")
N18: =IF(AND(L18<>"",L18<>0,M18<>""),M18/L18,"") | O18: =M18 -> 0 | P18: =IF(AND(L18<>"",L18<>0,O18<>"",O18<>0),O18/L18,"") | Q18: =IF(AND(M18<>0,M18<>"",L18<>0,L18<>""),O18-L18,"") | R18: 0 | S18: =IF(AND(R18<>"",R18<>0,O18<>"",O18<>0),-R18+O18,"") | T18: =IF(AND(S18<>"",S18<>0,R18<>0,R18<>""),S18/R18,"")
N19: =IF(AND(L19<>"",L19<>0,M19<>""),M19/L19,"") | O19: =M19 -> 0 | P19: =IF(AND(L19<>"",L19<>0,O19<>"",O19<>0),O19/L19,"") | Q19: =IF(AND(M19<>0,M19<>"",L19<>0,L19<>""),O19-L19,"") | R19: 0 | S19: =IF(AND(R19<>"",R19<>0,O19<>"",O19<>0),-R19+O19,"") | T19: =IF(AND(S19<>"",S19<>0,R19<>0,R19<>""),S19/R19,"")
I20: Конверсия план/факт | L20: ='Ялта, Ленина, 18'!I20 -> 0.12 | M20: =S57 -> 0.049450549 | N20: =M20/L20 -> 0.41208791 | O20: =IF(AND(N8<>0,L14<>0,I57<>0),(I57*S57+(I57/N8-I57)*L20)/(I57/N8),0) -> 0.098272736 | P20: =IF(AND(L20<>"",L20<>0,O20<>"",O20<>0),O20/L20,"") -> 0.81893947 | Q20: =IF(AND(M20<>0,M20<>"",L20<>0,L20<>""),O20-L20,"") -> -0.021727264 | S20: =IF(AND(R20<>"",R20<>0,O20<>"",O20<>0),-R20+O20,"") | T20: =IF(AND(S20<>"",S20<>0,R20<>0,R20<>""),S20/R20,"")
B22: Факт продаж за месяц | T22: % выполнения дневного плана | U22: Раcпределение плана по дням
B23: Дата | C23: День недели | D23: Выручка (руб) | E23: Кол-во единиц (шт.) | F23: Средняя стоимость изделия (руб.) | G23: Количество чеков (шт.) | H23: Средняя сумма чека (руб.) | I23: Трафик | J23: Длина чека (шт.) | K23: UNOde50 | L23: IS | M23: Agafi | N23: Kalliope | O23: Raganella | P23: CC/MP | Q23: Antura | R23: SALE | S23: Конверсия (%) | U23: выручка, план | V23: кол-во ед, план | W23: Кол-во чеков, план | X23: выручка, скорректир.план | Y23: кол-во ед, скорр. план | Z23: кол-во чеков, скорр. план | AA23: Коэфф. Дня Недели | AB23: Специфика месяца
B24: 1 | C24: 2 | D24: 3 | E24: в | F24: 5 | G24: 6 | H24: 7 | I24: 8 | J24: 9 | K24: 10 | L24: 11 | M24: 12 | N24: 13 | P24: 14 | Q24: 15 | R24: 16 | S24: 17 | U24: 1 | V24: 2 | W24: 3 | X24: 4 | Y24: 5 | Z24: 6 | AA24: 10 | AB24: 11
A25: 1 | B25: 46094 | C25: пт | D25: =7393+6893 -> 14286 | E25: 2 | F25: =IF(AND(E25<>"",E25<>0),D25/E25,"") -> 7143 | G25: 2 | H25: =IF(AND(G25<>"",G25<>0),D25/G25,"") -> 7143 | I25: 19 | J25: =IF(AND(G25<>"",G25<>0),E25/G25,"") -> 1 | S25: =IF(AND(I25<>"",I25<>0),G25/I25,"") -> 0.10526316 | T25: =D25/U25 -> 0.20932214 | U25: =$L$8*AA25*AB25/SUMPRODUCT($AB$25:$AB$56,$AA$25:$AA$56) -> 68248.872 | V25: =$L$9*AA25*AB25/SUMPRODUCT($AB$25:$AB$56,$AA$25:$AA$56) -> 9.8911409 | W25: =IF($L$12="","",V25/$L$12) -> 5.6845638 | X25: =IF(D25<>"",D25,U25) -> 14286 | Y25: =IF(E25<>"",E25,V25) -> 2 | Z25: =IF(G25<>"",G25,W25) -> 2 | AA25: 1 | AB25: 1
A26: 2 | B26: 46095 | C26: сб | D26: 7584 | E26: 2 | F26: =IF(AND(E26<>"",E26<>0),D26/E26,"") -> 3792 | G26: 1 | H26: =IF(AND(G26<>"",G26<>0),D26/G26,"") -> 7584 | I26: 15 | J26: =IF(AND(G26<>"",G26<>0),E26/G26,"") -> 2 | S26: =IF(AND(I26<>"",I26<>0),G26/I26,"") -> 0.066666667 | T26: =D26/U26 -> 0.11112271 | U26: =$L$8*AA26*AB26/SUMPRODUCT($AB$25:$AB$56,$AA$25:$AA$56) -> 68248.872 | V26: =$L$9*AA26*AB26/SUMPRODUCT($AB$25:$AB$58,$AA$25:$AA$58) -> 9.8911409 | W26: =IF($L$12="","",V26/$L$12) -> 5.6845638 | X26: =IF(AB26<>"",IF(D26<>"",D26,($L$8-SUM($X$25:X25))*AA26*AB26/SUMPRODUCT($AB26:$AB$56,$AA26:$AA$56)),"") -> 7584 | Y26: =IF(AB26<>"",IF(E26<>"",E26,($L$9-SUM($Y$25:Y25))*AA26*AB26/SUMPRODUCT($AB26:$AB$58,$AA26:$AA$58)),"") -> 2 | Z26: =IF(AB26<>"",IF($L$12<>"",IF(G26<>"",G26,($L$9/$L$12-SUM($Z$25:Z25))*AA26*AB26/SUMPRODUCT($AB26:$AB$58,$AA26:$AA$58)),""),"") -> 1 | AA26: 1 | AB26: 1
A27: 3 | B27: 46096 | C27: вс | D27: 0 | E27: 0 | F27: 0 | G27: 0 | H27: 0 | I27: 22 | J27: =IF(AND(G27<>"",G27<>0),E27/G27,"") | S27: =IF(AND(I27<>"",I27<>0),G27/I27,"") -> 0 | T27: =I27/U27 -> 0.00032234965 | U27: =$L$8*AA27*AB27/SUMPRODUCT($AB$25:$AB$56,$AA$25:$AA$56) -> 68248.872 | V27: =$L$9*AA27*AB27/SUMPRODUCT($AB$25:$AB$58,$AA$25:$AA$58) -> 9.8911409 | W27: =IF($L$12="","",V27/$L$12) -> 5.6845638 | X27: =IF(AB27<>"",IF(D27<>"",D27,($L$8-SUM($X$25:X26))*AA27*AB27/SUMPRODUCT($AB27:$AB$58,$AA27:$AA$58)),"") -> 0 | Y27: =IF(AB27<>"",IF(E27<>"",E27,($L$9-SUM($Y$25:Y26))*AA27*AB27/SUMPRODUCT($AB27:$AB$58,$AA27:$AA$58)),"") -> 0 | Z27: =IF(AB27<>"",IF($L$12<>"",IF(G27<>"",G27,($L$9/$L$12-SUM($Z$25:Z26))*AA27*AB27/SUMPRODUCT($AB27:$AB$58,$AA27:$AA$58)),""),"") -> 0 | AA27: 1 | AB27: 1
A28: 4 | B28: 46099 | C28: ср | D28: 0 | E28: 0 | F28: 0 | G28: 0 | H28: 0 | I28: 8 | J28: =IF(AND(G28<>"",G28<>0),E28/G28,"") | S28: =IF(AND(I28<>"",I28<>0),G28/I28,"") -> 0 | T28: =I28/U28 -> 0.00011721805 | U28: =$L$8*AA28*AB28/SUMPRODUCT($AB$25:$AB$56,$AA$25:$AA$56) -> 68248.872 | V28: =$L$9*AA28*AB28/SUMPRODUCT($AB$25:$AB$58,$AA$25:$AA$58) -> 9.8911409 | W28: =IF($L$12="","",V28/$L$12) -> 5.6845638 | X28: =IF(AB28<>"",IF(D28<>"",D28,($L$8-SUM($X$25:X27))*AA28*AB28/SUMPRODUCT($AB28:$AB$58,$AA28:$AA$58)),"") -> 0 | Y28: =IF(AB28<>"",IF(E28<>"",E28,($L$9-SUM($Y$25:Y27))*AA28*AB28/SUMPRODUCT($AB28:$AB$58,$AA28:$AA$58)),"") -> 0 | Z28: =IF(AB28<>"",IF($L$12<>"",IF(G28<>"",G28,($L$9/$L$12-SUM($Z$25:Z27))*AA28*AB28/SUMPRODUCT($AB28:$AB$58,$AA28:$AA$58)),""),"") -> 0 | AA28: 1 | AB28: 1
A29: 5 | B29: 46100 | C29: чт | D29: 7885 | E29: 2 | F29: =IF(AND(E29<>"",E29<>0),D29/E29,"") -> 3942.5 | G29: 2 | H29: =IF(AND(G29<>"",G29<>0),D29/G29,"") -> 3942.5 | I29: 30 | J29: =IF(AND(G29<>"",G29<>0),E29/G29,"") -> 1 | S29: =IF(AND(I29<>"",I29<>0),G29/I29,"") -> 0.066666667 | T29: =I29/U29 -> 0.0004395677 | U29: =$L$8*AA29*AB29/SUMPRODUCT($AB$25:$AB$56,$AA$25:$AA$56) -> 68248.872 | V29: =$L$9*AA29*AB29/SUMPRODUCT($AB$25:$AB$58,$AA$25:$AA$58) -> 9.8911409 | W29: =IF($L$12="","",V29/$L$12) -> 5.6845638 | X29: =IF(AB29<>"",IF(D29<>"",D29,($L$8-SUM($X$25:X28))*AA29*AB29/SUMPRODUCT($AB29:$AB$58,$AA29:$AA$58)),"") -> 7885 | Y29: =IF(AB29<>"",IF(E29<>"",E29,($L$9-SUM($Y$25:Y28))*AA29*AB29/SUMPRODUCT($AB29:$AB$58,$AA29:$AA$58)),"") -> 2 | Z29: =IF(AB29<>"",IF($L$12<>"",IF(G29<>"",G29,($L$9/$L$12-SUM($Z$25:Z28))*AA29*AB29/SUMPRODUCT($AB29:$AB$58,$AA29:$AA$58)),""),"") -> 2 | AA29: 1 | AB29: 1
A30: 6 | B30: 46101 | C30: пт | D30: 0 | E30: 0 | F30: 0 | G30: 0 | H30: 0 | I30: 30 | J30: =IF(AND(G30<>"",G30<>0),E30/G30,"") | S30: =IF(AND(I30<>"",I30<>0),G30/I30,"") -> 0 | T30: =I30/U30 -> 0.0004395677 | U30: =$L$8*AA30*AB30/SUMPRODUCT($AB$25:$AB$56,$AA$25:$AA$56) -> 68248.872 | V30: =$L$9*AA30*AB30/SUMPRODUCT($AB$25:$AB$58,$AA$25:$AA$58) -> 9.8911409 | W30: =IF($L$12="","",V30/$L$12) -> 5.6845638 | X30: =IF(AB30<>"",IF(D30<>"",D30,($L$8-SUM($X$25:X29))*AA30*AB30/SUMPRODUCT($AB30:$AB$58,$AA30:$AA$58)),"") -> 0 | Y30: =IF(AB30<>"",IF(E30<>"",E30,($L$9-SUM($Y$25:Y29))*AA30*AB30/SUMPRODUCT($AB30:$AB$58,$AA30:$AA$58)),"") -> 0 | Z30: =IF(AB30<>"",IF($L$12<>"",IF(G30<>"",G30,($L$9/$L$12-SUM($Z$25:Z29))*AA30*AB30/SUMPRODUCT($AB30:$AB$58,$AA30:$AA$58)),""),"") -> 0 | AA30: 1 | AB30: 1
A31: 7 | B31: 46103 | C31: вс | D31: 4693 | E31: 1 | F31: =IF(AND(E31<>"",E31<>0),D31/E31,"") -> 4693 | G31: 1 | H31: =IF(AND(G31<>"",G31<>0),D31/G31,"") -> 4693 | I31: 27 | J31: =IF(AND(G31<>"",G31<>0),E31/G31,"") -> 1 | S31: =IF(AND(I31<>"",I31<>0),G31/I31,"") -> 0.037037037 | T31: =I31/U31 -> 0.00039561093 | U31: =$L$8*AA31*AB31/SUMPRODUCT($AB$25:$AB$56,$AA$25:$AA$56) -> 68248.872 | V31: =$L$9*AA31*AB31/SUMPRODUCT($AB$25:$AB$58,$AA$25:$AA$58) -> 9.8911409 | W31: =IF($L$12="","",V31/$L$12) -> 5.6845638 | X31: =IF(AB31<>"",IF(D31<>"",D31,($L$8-SUM($X$25:X30))*AA31*AB31/SUMPRODUCT($AB31:$AB$58,$AA31:$AA$58)),"") -> 4693 | Y31: =IF(AB31<>"",IF(E31<>"",E31,($L$9-SUM($Y$25:Y30))*AA31*AB31/SUMPRODUCT($AB31:$AB$58,$AA31:$AA$58)),"") -> 1 | Z31: =IF(AB31<>"",IF($L$12<>"",IF(G31<>"",G31,($L$9/$L$12-SUM($Z$25:Z30))*AA31*AB31/SUMPRODUCT($AB31:$AB$58,$AA31:$AA$58)),""),"") -> 1 | AA31: 1 | AB31: 1
A32: 8 | B32: 46106 | C32: ср | D32: 17183 | E32: 2 | F32: =IF(AND(E32<>"",E32<>0),D32/E32,"") -> 8591.5 | G32: 1 | H32: =IF(AND(G32<>"",G32<>0),D32/G32,"") -> 17183 | I32: 66 | J32: =IF(AND(G32<>"",G32<>0),E32/G32,"") -> 2 | S32: =IF(AND(I32<>"",I32<>0),G32/I32,"") -> 0.015151515 | T32: =I32/U32 -> 0.00096704894 | U32: =$L$8*AA32*AB32/SUMPRODUCT($AB$25:$AB$56,$AA$25:$AA$56) -> 68248.872 | V32: =$L$9*AA32*AB32/SUMPRODUCT($AB$25:$AB$58,$AA$25:$AA$58) -> 9.8911409 | W32: =IF($L$12="","",V32/$L$12) -> 5.6845638 | X32: =IF(AB32<>"",IF(D32<>"",D32,($L$8-SUM($X$25:X31))*AA32*AB32/SUMPRODUCT($AB32:$AB$58,$AA32:$AA$58)),"") -> 17183 | Y32: =IF(AB32<>"",IF(E32<>"",E32,($L$9-SUM($Y$25:Y31))*AA32*AB32/SUMPRODUCT($AB32:$AB$58,$AA32:$AA$58)),"") -> 2 | Z32: =IF(AB32<>"",IF($L$12<>"",IF(G32<>"",G32,($L$9/$L$12-SUM($Z$25:Z31))*AA32*AB32/SUMPRODUCT($AB32:$AB$58,$AA32:$AA$58)),""),"") -> 1 | AA32: 1 | AB32: 1
B33: 46107 | C33: чт | D33: 67031 | E33: 7 | F33: =IF(AND(E33<>"",E33<>0),D33/E33,"") -> 9575.8571 | G33: 4 | H33: =IF(AND(G33<>"",G33<>0),D33/G33,"") -> 16757.75 | I33: 68 | J33: =IF(AND(G33<>"",G33<>0),E33/G33,"") -> 1.75 | K33: 10990 | P33: 12290 | S33: =IF(AND(I33<>"",I33<>0),G33/I33,"") -> 0.058823529 | T33: =I33/U33 -> #DIV/0! | U33: =$L$8*AA33*AB33/SUMPRODUCT($AB$25:$AB$56,$AA$25:$AA$56) -> 0 | V33: =$L$9*AA33*AB33/SUMPRODUCT($AB$25:$AB$58,$AA$25:$AA$58) -> 0 | W33: =IF($L$12="","",V33/$L$12) -> 0 | X33: =IF(AB33<>"",IF(D33<>"",D33,($L$8-SUM($X$25:X32))*AA33*AB33/SUMPRODUCT($AB33:$AB$58,$AA33:$AA$58)),"") | Y33: =IF(AB33<>"",IF(E33<>"",E33,($L$9-SUM($Y$25:Y32))*AA33*AB33/SUMPRODUCT($AB33:$AB$58,$AA33:$AA$58)),"") | Z33: =IF(AB33<>"",IF($L$12<>"",IF(G33<>"",G33,($L$9/$L$12-SUM($Z$25:Z32))*AA33*AB33/SUMPRODUCT($AB33:$AB$58,$AA33:$AA$58)),""),"")
B34: 46111 | C34: пн | D34: 13977 | E34: 3 | F34: =IF(AND(E34<>"",E34<>0),D34/E34,"") -> 4659 | G34: 2 | H34: =IF(AND(G34<>"",G34<>0),D34/G34,"") -> 6988.5 | I34: 33 | J34: =IF(AND(G34<>"",G34<>0),E34/G34,"") -> 1.5 | S34: =IF(AND(I34<>"",I34<>0),G34/I34,"") -> 0.060606061 | T34: =I34/U34 -> #DIV/0! | U34: =$L$8*AA34*AB34/SUMPRODUCT($AB$25:$AB$56,$AA$25:$AA$56) -> 0 | V34: =$L$9*AA34*AB34/SUMPRODUCT($AB$25:$AB$58,$AA$25:$AA$58) -> 0 | W34: =IF($L$12="","",V34/$L$12) -> 0 | X34: =IF(AB34<>"",IF(D34<>"",D34,($L$8-SUM($X$25:X33))*AA34*AB34/SUMPRODUCT($AB34:$AB$58,$AA34:$AA$58)),"") | Y34: =IF(AB34<>"",IF(E34<>"",E34,($L$9-SUM($Y$25:Y33))*AA34*AB34/SUMPRODUCT($AB34:$AB$58,$AA34:$AA$58)),"") | Z34: =IF(AB34<>"",IF($L$12<>"",IF(G34<>"",G34,($L$9/$L$12-SUM($Z$25:Z33))*AA34*AB34/SUMPRODUCT($AB34:$AB$58,$AA34:$AA$58)),""),"")
B35: 46112 | C35: вт | D35: 21719 | E35: 4 | F35: =IF(AND(E35<>"",E35<>0),D35/E35,"") -> 5429.75 | G35: 4 | H35: =IF(AND(G35<>"",G35<>0),D35/G35,"") -> 5429.75 | I35: 46 | J35: =IF(AND(G35<>"",G35<>0),E35/G35,"") -> 1 | R35: 2555 | S35: =IF(AND(I35<>"",I35<>0),G35/I35,"") -> 0.086956522 | T35: =I35/U35 -> #DIV/0! | U35: =$L$8*AA35*AB35/SUMPRODUCT($AB$25:$AB$56,$AA$25:$AA$56) -> 0 | V35: =$L$9*AA35*AB35/SUMPRODUCT($AB$25:$AB$58,$AA$25:$AA$58) -> 0 | W35: =IF($L$12="","",V35/$L$12) -> 0 | X35: =IF(AB35<>"",IF(D35<>"",D35,($L$8-SUM($X$25:X34))*AA35*AB35/SUMPRODUCT($AB35:$AB$58,$AA35:$AA$58)),"") | Y35: =IF(AB35<>"",IF(E35<>"",E35,($L$9-SUM($Y$25:Y34))*AA35*AB35/SUMPRODUCT($AB35:$AB$58,$AA35:$AA$58)),"") | Z35: =IF(AB35<>"",IF($L$12<>"",IF(G35<>"",G35,($L$9/$L$12-SUM($Z$25:Z34))*AA35*AB35/SUMPRODUCT($AB35:$AB$58,$AA35:$AA$58)),""),"")
F36: =IF(AND(E36<>"",E36<>0),D36/E36,"") | H36: =IF(AND(G36<>"",G36<>0),D36/G36,"") | J36: =IF(AND(G36<>"",G36<>0),E36/G36,"") | S36: =IF(AND(I36<>"",I36<>0),G36/I36,"") | T36: =I36/U36 -> #DIV/0! | U36: =$L$8*AA36*AB36/SUMPRODUCT($AB$25:$AB$56,$AA$25:$AA$56) -> 0 | V36: =$L$9*AA36*AB36/SUMPRODUCT($AB$25:$AB$58,$AA$25:$AA$58) -> 0 | W36: =IF($L$12="","",V36/$L$12) -> 0 | X36: =IF(AB36<>"",IF(D36<>"",D36,($L$8-SUM($X$25:X35))*AA36*AB36/SUMPRODUCT($AB36:$AB$58,$AA36:$AA$58)),"") | Y36: =IF(AB36<>"",IF(E36<>"",E36,($L$9-SUM($Y$25:Y35))*AA36*AB36/SUMPRODUCT($AB36:$AB$58,$AA36:$AA$58)),"") | Z36: =IF(AB36<>"",IF($L$12<>"",IF(G36<>"",G36,($L$9/$L$12-SUM($Z$25:Z35))*AA36*AB36/SUMPRODUCT($AB36:$AB$58,$AA36:$AA$58)),""),"")
F37: =IF(AND(E37<>"",E37<>0),D37/E37,"") | H37: =IF(AND(G37<>"",G37<>0),D37/G37,"") | J37: =IF(AND(G37<>"",G37<>0),E37/G37,"") | S37: =IF(AND(I37<>"",I37<>0),G37/I37,"") | T37: =I37/U37 -> #DIV/0! | U37: =$L$8*AA37*AB37/SUMPRODUCT($AB$25:$AB$56,$AA$25:$AA$56) -> 0 | V37: =$L$9*AA37*AB37/SUMPRODUCT($AB$25:$AB$58,$AA$25:$AA$58) -> 0 | W37: =IF($L$12="","",V37/$L$12) -> 0 | X37: =IF(AB37<>"",IF(D37<>"",D37,($L$8-SUM($X$25:X36))*AA37*AB37/SUMPRODUCT($AB37:$AB$58,$AA37:$AA$58)),"") | Y37: =IF(AB37<>"",IF(E37<>"",E37,($L$9-SUM($Y$25:Y36))*AA37*AB37/SUMPRODUCT($AB37:$AB$58,$AA37:$AA$58)),"") | Z37: =IF(AB37<>"",IF($L$12<>"",IF(G37<>"",G37,($L$9/$L$12-SUM($Z$25:Z36))*AA37*AB37/SUMPRODUCT($AB37:$AB$58,$AA37:$AA$58)),""),"")
F38: =IF(AND(E38<>"",E38<>0),D38/E38,"") | H38: =IF(AND(G38<>"",G38<>0),D38/G38,"") | J38: =IF(AND(G38<>"",G38<>0),E38/G38,"") | S38: =IF(AND(I38<>"",I38<>0),G38/I38,"") | T38: =I38/U38 -> #DIV/0! | U38: =$L$8*AA38*AB38/SUMPRODUCT($AB$25:$AB$56,$AA$25:$AA$56) -> 0 | V38: =$L$9*AA38*AB38/SUMPRODUCT($AB$25:$AB$58,$AA$25:$AA$58) -> 0 | W38: =IF($L$12="","",V38/$L$12) -> 0 | X38: =IF(AB38<>"",IF(D38<>"",D38,($L$8-SUM($X$25:X37))*AA38*AB38/SUMPRODUCT($AB38:$AB$58,$AA38:$AA$58)),"") | Y38: =IF(AB38<>"",IF(E38<>"",E38,($L$9-SUM($Y$25:Y37))*AA38*AB38/SUMPRODUCT($AB38:$AB$58,$AA38:$AA$58)),"") | Z38: =IF(AB38<>"",IF($L$12<>"",IF(G38<>"",G38,($L$9/$L$12-SUM($Z$25:Z37))*AA38*AB38/SUMPRODUCT($AB38:$AB$58,$AA38:$AA$58)),""),"")
F39: =IF(AND(E39<>"",E39<>0),D39/E39,"") | H39: =IF(AND(G39<>"",G39<>0),D39/G39,"") | J39: =IF(AND(G39<>"",G39<>0),E39/G39,"") | S39: =IF(AND(I39<>"",I39<>0),G39/I39,"") | T39: =I39/U39 -> #DIV/0! | U39: =$L$8*AA39*AB39/SUMPRODUCT($AB$25:$AB$56,$AA$25:$AA$56) -> 0 | V39: =$L$9*AA39*AB39/SUMPRODUCT($AB$25:$AB$58,$AA$25:$AA$58) -> 0 | W39: =IF($L$12="","",V39/$L$12) -> 0 | X39: =IF(AB39<>"",IF(D39<>"",D39,($L$8-SUM($X$25:X38))*AA39*AB39/SUMPRODUCT($AB39:$AB$58,$AA39:$AA$58)),"") | Y39: =IF(AB39<>"",IF(E39<>"",E39,($L$9-SUM($Y$25:Y38))*AA39*AB39/SUMPRODUCT($AB39:$AB$58,$AA39:$AA$58)),"") | Z39: =IF(AB39<>"",IF($L$12<>"",IF(G39<>"",G39,($L$9/$L$12-SUM($Z$25:Z38))*AA39*AB39/SUMPRODUCT($AB39:$AB$58,$AA39:$AA$58)),""),"")
B40: 46108 | C40: пт | D40: 13792 | E40: 1 | F40: =IF(AND(E40<>"",E40<>0),D40/E40,"") -> 13792 | G40: 1 | H40: =IF(AND(G40<>"",G40<>0),D40/G40,"") -> 13792 | J40: =IF(AND(G40<>"",G40<>0),E40/G40,"") -> 1 | P40: 13792 | S40: =IF(AND(I40<>"",I40<>0),G40/I40,"") | T40: =I40/U40 -> #DIV/0! | U40: =$L$8*AA40*AB40/SUMPRODUCT($AB$25:$AB$56,$AA$25:$AA$56) -> 0 | V40: =$L$9*AA40*AB40/SUMPRODUCT($AB$25:$AB$58,$AA$25:$AA$58) -> 0 | W40: =IF($L$12="","",V40/$L$12) -> 0 | X40: =IF(AB40<>"",IF(D40<>"",D40,($L$8-SUM($X$25:X39))*AA40*AB40/SUMPRODUCT($AB40:$AB$58,$AA40:$AA$58)),"") | Y40: =IF(AB40<>"",IF(E40<>"",E40,($L$9-SUM($Y$25:Y39))*AA40*AB40/SUMPRODUCT($AB40:$AB$58,$AA40:$AA$58)),"") | Z40: =IF(AB40<>"",IF($L$12<>"",IF(G40<>"",G40,($L$9/$L$12-SUM($Z$25:Z39))*AA40*AB40/SUMPRODUCT($AB40:$AB$58,$AA40:$AA$58)),""),"")
F41: =IF(AND(E41<>"",E41<>0),D41/E41,"") | H41: =IF(AND(G41<>"",G41<>0),D41/G41,"") | J41: =IF(AND(G41<>"",G41<>0),E41/G41,"") | S41: =IF(AND(I41<>"",I41<>0),G41/I41,"") | T41: =I41/U41 -> #DIV/0! | U41: =$L$8*AA41*AB41/SUMPRODUCT($AB$25:$AB$56,$AA$25:$AA$56) -> 0 | V41: =$L$9*AA41*AB41/SUMPRODUCT($AB$25:$AB$58,$AA$25:$AA$58) -> 0 | W41: =IF($L$12="","",V41/$L$12) -> 0 | X41: =IF(AB41<>"",IF(D41<>"",D41,($L$8-SUM($X$25:X40))*AA41*AB41/SUMPRODUCT($AB41:$AB$58,$AA41:$AA$58)),"") | Y41: =IF(AB41<>"",IF(E41<>"",E41,($L$9-SUM($Y$25:Y40))*AA41*AB41/SUMPRODUCT($AB41:$AB$58,$AA41:$AA$58)),"") | Z41: =IF(AB41<>"",IF($L$12<>"",IF(G41<>"",G41,($L$9/$L$12-SUM($Z$25:Z40))*AA41*AB41/SUMPRODUCT($AB41:$AB$58,$AA41:$AA$58)),""),"")
F42: =IF(AND(E42<>"",E42<>0),D42/E42,"") | H42: =IF(AND(G42<>"",G42<>0),D42/G42,"") | J42: =IF(AND(G42<>"",G42<>0),E42/G42,"") | S42: =IF(AND(I42<>"",I42<>0),G42/I42,"") | T42: =I42/U42 -> #DIV/0! | U42: =$L$8*AA42*AB42/SUMPRODUCT($AB$25:$AB$56,$AA$25:$AA$56) -> 0 | V42: =$L$9*AA42*AB42/SUMPRODUCT($AB$25:$AB$58,$AA$25:$AA$58) -> 0 | W42: =IF($L$12="","",V42/$L$12) -> 0 | X42: =IF(AB42<>"",IF(D42<>"",D42,($L$8-SUM($X$25:X41))*AA42*AB42/SUMPRODUCT($AB42:$AB$58,$AA42:$AA$58)),"") | Y42: =IF(AB42<>"",IF(E42<>"",E42,($L$9-SUM($Y$25:Y41))*AA42*AB42/SUMPRODUCT($AB42:$AB$58,$AA42:$AA$58)),"") | Z42: =IF(AB42<>"",IF($L$12<>"",IF(G42<>"",G42,($L$9/$L$12-SUM($Z$25:Z41))*AA42*AB42/SUMPRODUCT($AB42:$AB$58,$AA42:$AA$58)),""),"")
F43: =IF(AND(E43<>"",E43<>0),D43/E43,"") | H43: =IF(AND(G43<>"",G43<>0),D43/G43,"") | J43: =IF(AND(G43<>"",G43<>0),E43/G43,"") | S43: =IF(AND(I43<>"",I43<>0),G43/I43,"") | T43: =I43/U43 -> #DIV/0! | U43: =$L$8*AA43*AB43/SUMPRODUCT($AB$25:$AB$56,$AA$25:$AA$56) -> 0 | V43: =$L$9*AA43*AB43/SUMPRODUCT($AB$25:$AB$58,$AA$25:$AA$58) -> 0 | W43: =IF($L$12="","",V43/$L$12) -> 0 | X43: =IF(AB43<>"",IF(D43<>"",D43,($L$8-SUM($X$25:X42))*AA43*AB43/SUMPRODUCT($AB43:$AB$58,$AA43:$AA$58)),"") | Y43: =IF(AB43<>"",IF(E43<>"",E43,($L$9-SUM($Y$25:Y42))*AA43*AB43/SUMPRODUCT($AB43:$AB$58,$AA43:$AA$58)),"") | Z43: =IF(AB43<>"",IF($L$12<>"",IF(G43<>"",G43,($L$9/$L$12-SUM($Z$25:Z42))*AA43*AB43/SUMPRODUCT($AB43:$AB$58,$AA43:$AA$58)),""),"")
F44: =IF(AND(E44<>"",E44<>0),D44/E44,"") | H44: =IF(AND(G44<>"",G44<>0),D44/G44,"") | J44: =IF(AND(G44<>"",G44<>0),E44/G44,"") | S44: =IF(AND(I44<>"",I44<>0),G44/I44,"") | T44: =I44/U44 -> #DIV/0! | U44: =$L$8*AA44*AB44/SUMPRODUCT($AB$25:$AB$56,$AA$25:$AA$56) -> 0 | V44: =$L$9*AA44*AB44/SUMPRODUCT($AB$25:$AB$58,$AA$25:$AA$58) -> 0 | W44: =IF($L$12="","",V44/$L$12) -> 0 | X44: =IF(AB44<>"",IF(D44<>"",D44,($L$8-SUM($X$25:X43))*AA44*AB44/SUMPRODUCT($AB44:$AB$58,$AA44:$AA$58)),"") | Y44: =IF(AB44<>"",IF(E44<>"",E44,($L$9-SUM($Y$25:Y43))*AA44*AB44/SUMPRODUCT($AB44:$AB$58,$AA44:$AA$58)),"") | Z44: =IF(AB44<>"",IF($L$12<>"",IF(G44<>"",G44,($L$9/$L$12-SUM($Z$25:Z43))*AA44*AB44/SUMPRODUCT($AB44:$AB$58,$AA44:$AA$58)),""),"")
F45: =IF(AND(E45<>"",E45<>0),D45/E45,"") | H45: =IF(AND(G45<>"",G45<>0),D45/G45,"") | J45: =IF(AND(G45<>"",G45<>0),E45/G45,"") | S45: =IF(AND(I45<>"",I45<>0),G45/I45,"") | T45: =I45/U45 -> #DIV/0! | U45: =$L$8*AA45*AB45/SUMPRODUCT($AB$25:$AB$56,$AA$25:$AA$56) -> 0 | V45: =$L$9*AA45*AB45/SUMPRODUCT($AB$25:$AB$58,$AA$25:$AA$58) -> 0 | W45: =IF($L$12="","",V45/$L$12) -> 0 | X45: =IF(AB45<>"",IF(D45<>"",D45,($L$8-SUM($X$25:X44))*AA45*AB45/SUMPRODUCT($AB45:$AB$58,$AA45:$AA$58)),"") | Y45: =IF(AB45<>"",IF(E45<>"",E45,($L$9-SUM($Y$25:Y44))*AA45*AB45/SUMPRODUCT($AB45:$AB$58,$AA45:$AA$58)),"") | Z45: =IF(AB45<>"",IF($L$12<>"",IF(G45<>"",G45,($L$9/$L$12-SUM($Z$25:Z44))*AA45*AB45/SUMPRODUCT($AB45:$AB$58,$AA45:$AA$58)),""),"")
F46: =IF(AND(E46<>"",E46<>0),D46/E46,"") | H46: =IF(AND(G46<>"",G46<>0),D46/G46,"") | J46: =IF(AND(G46<>"",G46<>0),E46/G46,"") | S46: =IF(AND(I46<>"",I46<>0),G46/I46,"") | T46: =I46/U46 -> #DIV/0! | U46: =$L$8*AA46*AB46/SUMPRODUCT($AB$25:$AB$56,$AA$25:$AA$56) -> 0 | V46: =$L$9*AA46*AB46/SUMPRODUCT($AB$25:$AB$58,$AA$25:$AA$58) -> 0 | W46: =IF($L$12="","",V46/$L$12) -> 0 | X46: =IF(AB46<>"",IF(D46<>"",D46,($L$8-SUM($X$25:X45))*AA46*AB46/SUMPRODUCT($AB46:$AB$58,$AA46:$AA$58)),"") | Y46: =IF(AB46<>"",IF(E46<>"",E46,($L$9-SUM($Y$25:Y45))*AA46*AB46/SUMPRODUCT($AB46:$AB$58,$AA46:$AA$58)),"") | Z46: =IF(AB46<>"",IF($L$12<>"",IF(G46<>"",G46,($L$9/$L$12-SUM($Z$25:Z45))*AA46*AB46/SUMPRODUCT($AB46:$AB$58,$AA46:$AA$58)),""),"")
F47: =IF(AND(E47<>"",E47<>0),D47/E47,"") | H47: =IF(AND(G47<>"",G47<>0),D47/G47,"") | J47: =IF(AND(G47<>"",G47<>0),E47/G47,"") | S47: =IF(AND(I47<>"",I47<>0),G47/I47,"") | T47: =I47/U47 -> #DIV/0! | U47: =$L$8*AA47*AB47/SUMPRODUCT($AB$25:$AB$56,$AA$25:$AA$56) -> 0 | V47: =$L$9*AA47*AB47/SUMPRODUCT($AB$25:$AB$58,$AA$25:$AA$58) -> 0 | W47: =IF($L$12="","",V47/$L$12) -> 0 | X47: =IF(AB47<>"",IF(D47<>"",D47,($L$8-SUM($X$25:X46))*AA47*AB47/SUMPRODUCT($AB47:$AB$58,$AA47:$AA$58)),"") | Y47: =IF(AB47<>"",IF(E47<>"",E47,($L$9-SUM($Y$25:Y46))*AA47*AB47/SUMPRODUCT($AB47:$AB$58,$AA47:$AA$58)),"") | Z47: =IF(AB47<>"",IF($L$12<>"",IF(G47<>"",G47,($L$9/$L$12-SUM($Z$25:Z46))*AA47*AB47/SUMPRODUCT($AB47:$AB$58,$AA47:$AA$58)),""),"")
F48: =IF(AND(E48<>"",E48<>0),D48/E48,"") | H48: =IF(AND(G48<>"",G48<>0),D48/G48,"") | J48: =IF(AND(G48<>"",G48<>0),E48/G48,"") | S48: =IF(AND(I48<>"",I48<>0),G48/I48,"") | T48: =I48/U48 -> #DIV/0! | U48: =$L$8*AA48*AB48/SUMPRODUCT($AB$25:$AB$56,$AA$25:$AA$56) -> 0 | V48: =$L$9*AA48*AB48/SUMPRODUCT($AB$25:$AB$58,$AA$25:$AA$58) -> 0 | W48: =IF($L$12="","",V48/$L$12) -> 0 | X48: =IF(AB48<>"",IF(D48<>"",D48,($L$8-SUM($X$25:X47))*AA48*AB48/SUMPRODUCT($AB48:$AB$58,$AA48:$AA$58)),"") | Y48: =IF(AB48<>"",IF(E48<>"",E48,($L$9-SUM($Y$25:Y47))*AA48*AB48/SUMPRODUCT($AB48:$AB$58,$AA48:$AA$58)),"") | Z48: =IF(AB48<>"",IF($L$12<>"",IF(G48<>"",G48,($L$9/$L$12-SUM($Z$25:Z47))*AA48*AB48/SUMPRODUCT($AB48:$AB$58,$AA48:$AA$58)),""),"")
H49: =IF(AND(G49<>"",G49<>0),D49/G49,"") | J49: =IF(AND(G49<>"",G49<>0),E49/G49,"") | S49: =IF(AND(I49<>"",I49<>0),G49/I49,"") | T49: =I49/U49 -> #DIV/0! | U49: =$L$8*AA49*AB49/SUMPRODUCT($AB$25:$AB$56,$AA$25:$AA$56) -> 0 | V49: =$L$9*AA49*AB49/SUMPRODUCT($AB$25:$AB$58,$AA$25:$AA$58) -> 0 | W49: =IF($L$12="","",V49/$L$12) -> 0 | X49: =IF(AB49<>"",IF(D49<>"",D49,($L$8-SUM($X$25:X48))*AA49*AB49/SUMPRODUCT($AB49:$AB$58,$AA49:$AA$58)),"") | Y49: =IF(AB49<>"",IF(E49<>"",E49,($L$9-SUM($Y$25:Y48))*AA49*AB49/SUMPRODUCT($AB49:$AB$58,$AA49:$AA$58)),"") | Z49: =IF(AB49<>"",IF($L$12<>"",IF(G49<>"",G49,($L$9/$L$12-SUM($Z$25:Z48))*AA49*AB49/SUMPRODUCT($AB49:$AB$58,$AA49:$AA$58)),""),"")
F50: =IF(AND(E50<>"",E50<>0),D50/E50,"") | H50: =IF(AND(G50<>"",G50<>0),D50/G50,"") | J50: =IF(AND(G50<>"",G50<>0),E50/G50,"") | S50: =IF(AND(I50<>"",I50<>0),G50/I50,"") | T50: =I50/U50 -> #DIV/0! | U50: =$L$8*AA50*AB50/SUMPRODUCT($AB$25:$AB$56,$AA$25:$AA$56) -> 0 | V50: =$L$9*AA50*AB50/SUMPRODUCT($AB$25:$AB$58,$AA$25:$AA$58) -> 0 | W50: =IF($L$12="","",V50/$L$12) -> 0 | X50: =IF(AB50<>"",IF(D50<>"",D50,($L$8-SUM($X$25:X49))*AA50*AB50/SUMPRODUCT($AB50:$AB$58,$AA50:$AA$58)),"") | Y50: =IF(AB50<>"",IF(E50<>"",E50,($L$9-SUM($Y$25:Y49))*AA50*AB50/SUMPRODUCT($AB50:$AB$58,$AA50:$AA$58)),"") | Z50: =IF(AB50<>"",IF($L$12<>"",IF(G50<>"",G50,($L$9/$L$12-SUM($Z$25:Z49))*AA50*AB50/SUMPRODUCT($AB50:$AB$58,$AA50:$AA$58)),""),"")
F51: =IF(AND(E51<>"",E51<>0),D51/E51,"") | H51: =IF(AND(G51<>"",G51<>0),D51/G51,"") | J51: =IF(AND(G51<>"",G51<>0),E51/G51,"") | S51: =IF(AND(I51<>"",I51<>0),G51/I51,"") | T51: =I51/U51 -> #DIV/0! | U51: =$L$8*AA51*AB51/SUMPRODUCT($AB$25:$AB$56,$AA$25:$AA$56) -> 0 | V51: =$L$9*AA51*AB51/SUMPRODUCT($AB$25:$AB$58,$AA$25:$AA$58) -> 0 | W51: =IF($L$12="","",V51/$L$12) -> 0 | X51: =IF(AB51<>"",IF(D51<>"",D51,($L$8-SUM($X$25:X50))*AA51*AB51/SUMPRODUCT($AB51:$AB$58,$AA51:$AA$58)),"") | Y51: =IF(AB51<>"",IF(E51<>"",E51,($L$9-SUM($Y$25:Y50))*AA51*AB51/SUMPRODUCT($AB51:$AB$58,$AA51:$AA$58)),"") | Z51: =IF(AB51<>"",IF($L$12<>"",IF(G51<>"",G51,($L$9/$L$12-SUM($Z$25:Z50))*AA51*AB51/SUMPRODUCT($AB51:$AB$58,$AA51:$AA$58)),""),"")
F52: =IF(AND(E52<>"",E52<>0),D52/E52,"") | H52: =IF(AND(G52<>"",G52<>0),D52/G52,"") | J52: =IF(AND(G52<>"",G52<>0),E52/G52,"") | S52: =IF(AND(I52<>"",I52<>0),G52/I52,"") | T52: =I52/U52 -> #DIV/0! | U52: =$L$8*AA52*AB52/SUMPRODUCT($AB$25:$AB$56,$AA$25:$AA$56) -> 0 | V52: =$L$9*AA52*AB52/SUMPRODUCT($AB$25:$AB$58,$AA$25:$AA$58) -> 0 | W52: =IF($L$12="","",V52/$L$12) -> 0 | X52: =IF(AB52<>"",IF(D52<>"",D52,($L$8-SUM($X$25:X51))*AA52*AB52/SUMPRODUCT($AB52:$AB$58,$AA52:$AA$58)),"") | Y52: =IF(AB52<>"",IF(E52<>"",E52,($L$9-SUM($Y$25:Y51))*AA52*AB52/SUMPRODUCT($AB52:$AB$58,$AA52:$AA$58)),"") | Z52: =IF(AB52<>"",IF($L$12<>"",IF(G52<>"",G52,($L$9/$L$12-SUM($Z$25:Z51))*AA52*AB52/SUMPRODUCT($AB52:$AB$58,$AA52:$AA$58)),""),"")
F53: =IF(AND(E53<>"",E53<>0),D53/E53,"") | H53: =IF(AND(G53<>"",G53<>0),D53/G53,"") | J53: =IF(AND(G53<>"",G53<>0),E53/G53,"") | S53: =IF(AND(I53<>"",I53<>0),G53/I53,"") | T53: =I53/U53 -> #DIV/0! | U53: =$L$8*AA53*AB53/SUMPRODUCT($AB$25:$AB$56,$AA$25:$AA$56) -> 0 | V53: =$L$9*AA53*AB53/SUMPRODUCT($AB$25:$AB$58,$AA$25:$AA$58) -> 0 | W53: =IF($L$12="","",V53/$L$12) -> 0 | X53: =IF(AB53<>"",IF(D53<>"",D53,($L$8-SUM($X$25:X52))*AA53*AB53/SUMPRODUCT($AB53:$AB$58,$AA53:$AA$58)),"") | Y53: =IF(AB53<>"",IF(E53<>"",E53,($L$9-SUM($Y$25:Y52))*AA53*AB53/SUMPRODUCT($AB53:$AB$58,$AA53:$AA$58)),"") | Z53: =IF(AB53<>"",IF($L$12<>"",IF(G53<>"",G53,($L$9/$L$12-SUM($Z$25:Z52))*AA53*AB53/SUMPRODUCT($AB53:$AB$58,$AA53:$AA$58)),""),"")
F54: =IF(AND(E54<>"",E54<>0),D54/E54,"") | H54: =IF(AND(G54<>"",G54<>0),D54/G54,"") | J54: =IF(AND(G54<>"",G54<>0),E54/G54,"") | S54: =IF(AND(I54<>"",I54<>0),G54/I54,"") | T54: =I54/U54 -> #DIV/0! | U54: =$L$8*AA54*AB54/SUMPRODUCT($AB$25:$AB$56,$AA$25:$AA$56) -> 0 | V54: =$L$9*AA54*AB54/SUMPRODUCT($AB$25:$AB$58,$AA$25:$AA$58) -> 0 | W54: =IF($L$12="","",V54/$L$12) -> 0 | X54: =IF(AB54<>"",IF(D54<>"",D54,($L$8-SUM($X$25:X53))*AA54*AB54/SUMPRODUCT($AB54:$AB$58,$AA54:$AA$58)),"") | Y54: =IF(AB54<>"",IF(E54<>"",E54,($L$9-SUM($Y$25:Y53))*AA54*AB54/SUMPRODUCT($AB54:$AB$58,$AA54:$AA$58)),"") | Z54: =IF(AB54<>"",IF($L$12<>"",IF(G54<>"",G54,($L$9/$L$12-SUM($Z$25:Z53))*AA54*AB54/SUMPRODUCT($AB54:$AB$58,$AA54:$AA$58)),""),"")
F55: =IF(AND(E55<>"",E55<>0),D55/E55,"") | H55: =IF(AND(G55<>"",G55<>0),D55/G55,"") | J55: =IF(AND(G55<>"",G55<>0),E55/G55,"") | S55: =IF(AND(I55<>"",I55<>0),G55/I55,"") | T55: =I55/U55 -> #DIV/0! | U55: =$L$8*AA55*AB55/SUMPRODUCT($AB$25:$AB$56,$AA$25:$AA$56) -> 0 | V55: =$L$9*AA55*AB55/SUMPRODUCT($AB$25:$AB$58,$AA$25:$AA$58) -> 0 | W55: =IF($L$12="","",V55/$L$12) -> 0 | X55: =IF(AB55<>"",IF(D55<>"",D55,($L$8-SUM($X$25:X54))*AA55*AB55/SUMPRODUCT($AB55:$AB$58,$AA55:$AA$58)),"") | Y55: =IF(AB55<>"",IF(E55<>"",E55,($L$9-SUM($Y$25:Y54))*AA55*AB55/SUMPRODUCT($AB55:$AB$58,$AA55:$AA$58)),"") | Z55: =IF(AB55<>"",IF($L$12<>"",IF(G55<>"",G55,($L$9/$L$12-SUM($Z$25:Z54))*AA55*AB55/SUMPRODUCT($AB55:$AB$58,$AA55:$AA$58)),""),"")
F56: =IF(AND(E56<>"",E56<>0),D56/E56,"") | H56: =IF(AND(G56<>"",G56<>0),D56/G56,"") | J56: =IF(AND(G56<>"",G56<>0),E56/G56,"") | S56: =IF(AND(I56<>"",I56<>0),G56/I56,"") | T56: =I56/U56 -> #DIV/0! | U56: =$L$8*AA56*AB56/SUMPRODUCT($AB$25:$AB$56,$AA$25:$AA$56) -> 0 | V56: =$L$9*AA56*AB56/SUMPRODUCT($AB$25:$AB$58,$AA$25:$AA$58) -> 0 | W56: =IF($L$12="","",V56/$L$12) -> 0 | X56: =IF(AB56<>"",IF(D56<>"",D56,($L$8-SUM($X$25:X55))*AA56*AB56/SUMPRODUCT($AB56:$AB$58,$AA56:$AA$58)),"") | Y56: =IF(AB56<>"",IF(E56<>"",E56,($L$9-SUM($Y$25:Y55))*AA56*AB56/SUMPRODUCT($AB56:$AB$58,$AA56:$AA$58)),"") | Z56: =IF(AB56<>"",IF($L$12<>"",IF(G56<>"",G56,($L$9/$L$12-SUM($Z$25:Z55))*AA56*AB56/SUMPRODUCT($AB56:$AB$58,$AA56:$AA$58)),""),"")
D57: =SUM(D25:D56) -> 168150 | E57: =SUM(E25:E56) -> 24 | F57: =IF(AND(E57<>"",E57<>0),D57/E57,"") -> 7006.25 | G57: =SUM(G25:G56) -> 18 | H57: =IF(AND(G57<>"",G57<>0),D57/G57,"") -> 9341.6667 | I57: =SUM(I25:I56) -> 364 | J57: =IF(AND(G57<>"",G57<>0),E57/G57,"") -> 1.3333333 | K57: =SUM(K25:K56) -> 10990 | L57: =SUM(L25:L56) -> 0 | M57: =SUM(M25:M56) -> 0 | N57: =SUM(N25:N56) -> 0 | O57: =SUM(O25:O56) -> 0 | P57: =SUM(P25:P56) -> 26082 | Q57: =SUM(Q25:Q56) -> 0 | R57: =SUM(R25:R56) -> 2555 | S57: =IF(AND(I57<>"",I57<>0),G57/I57,"") -> 0.049450549 | T57: =I57/U57 -> 0.00066667768 | U57: =SUM(U25:U56) -> 545990.98 | V57: =SUM(V25:V55) -> 79.129128 | W57: =SUM(W25:W55) -> 45.47651 | X57: =SUM(X25:X56) -> 51631 | Y57: =SUM(Y25:Y55) -> 9 | Z57: =SUM(Z25:Z55) -> 7

Sheet Вед-ть Рогалевич
A1: =[1]График!B1 -> Март, 2026
A2: =График!B3 -> ул. Набережная Ленина, 18 | D2: =[1]График!B4 -> GL-0004
A3: Сотрудник | D3: Выплачено на карту | E3: Выплачено наличными по платежной ведомости | F3: Оклад | G3: Бонус от личных продаж по категории товара | H3: Бонусная часть от общих продаж | I3: Дополнительные начисления, доплаты | J3: Итого: | K3: Вычеты | L3: Итого к выдаче с учетом авансов и вычетов
A4: =График!B29 -> Рогалевич Ирина | D4: =19140+19140 -> 38280 | F4: =G7 -> 13900 | G4: =G14 -> 23859.6 | H4: =G20 -> 7283.1895 | I4: =L14 -> 12187.96 | J4: =G4+F4+I4+H4 -> 57230.75 | K4: =L20 -> 5760 | L4: =J4-K4-D4-E4 -> 13190.75
B7: Оклад: | G7: =G9+G10 -> 13900
B8: Дней | C8: Магазин | D8: Должность | E8: Зачислено часов | F8: Ставка за час, руб | G8: Начислено за день, руб | I8: КВП | J8: % выполнения
B9: =График!AI29 -> 14 | C9: =A2 -> ул. Набережная Ленина, 18 | D9: УМ | E9: =График!AJ29 -> 139 | F9: 100 | G9: =E9*F9 -> 13900 | I9: Магазин | J9: ='Ялта, Ленина, 18'!K8 -> 0.60425938
I10: Личный | J10: =Рогалевич!N8 -> 0.75636055
B14: Бонус от личных продаж по категории товара | G14: =G16+G17 -> 23859.6 | I14: Доп начисления | L14: =J16+J17+J18 -> 12187.96
B15: Категория товара | C15: Магазин | E15: Процент от продажи | F15: Продано на сумму, руб | G15: Начисленный бонус от продаж, руб | I15: Дата | J15: Сумма | K15: Описание
B16: Категория A | C16: =A2 -> ул. Набережная Ленина, 18 | E16: 0.05 | F16: =Рогалевич!M8-'Вед-ть Рогалевич'!F17 -> 471606 | G16: =F16*E16 -> 23580.3 | I16: 46112 | J16: 0 | K16: % наличного оборота ( > < 60%)
B17: Категория N (SALE, IS) | C17: =A2 -> ул. Набережная Ленина, 18 | E17: 0.1 | F17: =Рогалевич!L57+Рогалевич!R57 -> 2793 | G17: =F17*E17 -> 279.3 | I17: 46112 | J17: ='Ялта, Ленина, 18'!J8*0.01 -> 12187.96 | K17: % Управляющий магазином
F18: =F16+F17 -> 474399 | I18: 46112 | J18: 0 | K18: Чек-лист
B20: Бонус от общих продаж | G20: =G22+G23 -> 7283.1895 | I20: Вычеты | L20: =J22+J23+J24 -> 5760
B21: Сотрудник | C21: Магазин | D21: Кол-во отработанных личных часов | E21: Кол-во отработанных общих часов | F21: Процент от продажи | G21: Начисленный бонус от продаж, руб | I21: Дата | J21: Сумма | K21: Описание
B22: =A4 -> Рогалевич Ирина | C22: =C16 -> ул. Набережная Ленина, 18 | D22: =E9 -> 139 | E22: =График!AJ30 -> 447 | F22: 0.02 | G22: =('Ялта, Ленина, 18'!J8-'Ялта, Ленина, 18'!L56-'Ялта, Ленина, 18'!R56)*F22*D22/E22 -> 7283.1895 | I22: 46112 | J22: =2860+2860 -> 5720 | K22: НДФЛ
I23: 46112 | J23: 40 | K23: Вычет согласно инвентаризационной ведомости от 12.03.2026

Sheet Вед-ть Уразгильдеева
A1: =[1]График!B1 -> Март, 2026
A2: =График!B3 -> ул. Набережная Ленина, 18 | D2: =[1]График!B4 -> GL-0004
A3: Сотрудник | D3: Выплачено на карту | E3: Выплачено наличными по платежной ведомости | F3: Оклад | G3: Бонус от личных продаж по категории товара | H3: Бонусная часть от общих продаж | I3: Дополнительные начисления, доплаты | J3: Итого: | K3: Вычеты | L3: Итого к выдаче с учетом авансов и вычетов
A4: =График!B28 -> Уразгильдеева Екатерина | D4: =17400+17400 -> 34800 | F4: =G7 -> 18700 | G4: =G14 -> 30931.05 | H4: =G20 -> 9798.2478 | I4: =L14 -> 0 | J4: =G4+F4+I4+H4 -> 59429.298 | K4: =L20 -> 5240 | L4: =J4-K4-D4-E4 -> 19389.298
B7: Оклад: | G7: =G9+G10 -> 18700
B8: Дней | C8: Магазин | D8: Должность | E8: Зачислено часов | F8: Ставка за час, руб | G8: Начислено за день, руб | I8: КВП | J8: % выполнения
B9: =График!AI28 -> 17 | C9: =A2 -> ул. Набережная Ленина, 18 | D9: ПК | E9: =График!AJ28 -> 187 | F9: 100 | G9: =E9*F9 -> 18700 | I9: Магазин | J9: ='Ялта, Ленина, 18'!K8 -> 0.60425938
I10: Личный | J10: =Уразгильдеева!N8 -> 0.68291551
B14: Бонус от личных продаж по категории товара | G14: =G16+G17 -> 30931.05 | I14: Доп начисления | L14: =J16+J17+J18 -> 0
B15: Категория товара | C15: Магазин | E15: Процент от продажи | F15: Продано на сумму, руб | G15: Начисленный бонус от продаж, руб | I15: Дата | J15: Сумма | K15: Описание
B16: Категория A | C16: =A2 -> ул. Набережная Ленина, 18 | E16: 0.05 | F16: =Уразгильдеева!M8-'Вед-ть Уразгильдеева'!F17 -> 533873 | G16: =F16*E16 -> 26693.65
B17: Категория N (SALE, IS) | C17: =A2 -> ул. Набережная Ленина, 18 | E17: 0.1 | F17: =Уразгильдеева!L57+Уразгильдеева!R57 -> 42374 | G17: =F17*E17 -> 4237.4
F18: =F16+F17 -> 576247
B20: Бонус от общих продаж | G20: =G22+G23 -> 9798.2478 | I20: Вычеты | L20: =J22+J23+J24 -> 5240
B21: Сотрудник | C21: Магазин | D21: Кол-во отработанных личных часов | E21: Кол-во отработанных общих часов | F21: Процент от продажи | G21: Начисленный бонус от продаж, руб | I21: Дата | J21: Сумма | K21: Описание
B22: =A4 -> Уразгильдеева Екатерина | C22: =C16 -> ул. Набережная Ленина, 18 | D22: =E9 -> 187 | E22: =График!AJ30 -> 447 | F22: 0.02 | G22: =('Ялта, Ленина, 18'!J8-'Ялта, Ленина, 18'!L56-'Ялта, Ленина, 18'!R56)*F22*D22/E22 -> 9798.2478 | I22: 46112 | J22: =2600+2600 -> 5200 | K22: НДФЛ
I23: 46112 | J23: 40 | K23: Вычет согласно инвентаризационной ведомости от 12.03.2026

Sheet Вед-ть Самошкина
A1: =[1]График!B1 -> Март, 2026
A2: =График!B3 -> ул. Набережная Ленина, 18 | D2: =[1]График!B4 -> GL-0004
A3: Сотрудник | D3: Выплачено на карту | E3: Выплачено наличными по платежной ведомости | F3: Оклад | G3: Бонус от личных продаж по категории товара | H3: Бонусная часть от общих продаж | I3: Дополнительные начисления, доплаты | J3: Итого: | K3: Вычеты | L3: Итого к выдаче с учетом авансов и вычетов
A4: =График!B27 -> Самошкина Алина | D4: =1934+16294.38 -> 18228.38 | F4: =G7 -> 12100 | G4: =G14 -> 8535.25 | H4: =G20 -> 6340.0427 | I4: =L14 -> 0 | J4: =G4+F4+I4+H4 -> 26975.293 | K4: =L20 -> 2724 | L4: =J4-K4-D4-E4 -> 6022.9127
B7: Оклад: | G7: =G9+G10 -> 12100
B8: Дней | C8: Магазин | D8: Должность | E8: Зачислено часов | F8: Ставка за час, руб | G8: Начислено за день, руб | I8: КВП | J8: % выполнения
B9: =График!AI27 -> 11 | C9: =A2 -> ул. Набережная Ленина, 18 | D9: ПК | E9: =График!AJ27 -> 121 | F9: 100 | G9: =E9*F9 -> 12100 | I9: Магазин | J9: ='Ялта, Ленина, 18'!K8 -> 0.60425938
I10: Личный | J10: =Самошкина!N8 -> 0.30797212
B14: Бонус от личных продаж по категории товара | G14: =G16+G17 -> 8535.25 | I14: Доп начисления | L14: =J16+J17+J18 -> 0
B15: Категория товара | C15: Магазин | E15: Процент от продажи | F15: Продано на сумму, руб | G15: Начисленный бонус от продаж, руб | I15: Дата | J15: Сумма | K15: Описание
B16: Категория A | C16: =A2 -> ул. Набережная Ленина, 18 | E16: 0.05 | F16: =Самошкина!M8-'Вед-ть Самошкина'!F17 -> 165595 | G16: =F16*E16 -> 8279.75
B17: Категория N (SALE, IS) | C17: =A2 -> ул. Набережная Ленина, 18 | E17: 0.1 | F17: =Самошкина!L57+Самошкина!R57 -> 2555 | G17: =F17*E17 -> 255.5
F18: =F16+F17 -> 168150
B20: Бонус от общих продаж | G20: =G22+G23 -> 6340.0427 | I20: Вычеты | L20: =J22+J23+J24 -> 2724
B21: Сотрудник | C21: Магазин | D21: Кол-во отработанных личных часов | E21: Кол-во отработанных общих часов | F21: Процент от продажи | G21: Начисленный бонус от продаж, руб | I21: Дата | J21: Сумма | K21: Описание
B22: =A4 -> Самошкина Алина | C22: =C16 -> ул. Набережная Ленина, 18 | D22: =E9 -> 121 | E22: =График!AJ30 -> 447 | F22: 0.02 | G22: =('Ялта, Ленина, 18'!J8-'Ялта, Ленина, 18'!L56-'Ялта, Ленина, 18'!R56)*F22*D22/E22 -> 6340.0427 | I22: 46112 | J22: =289+2435 -> 2724 | K22: НДФЛ
I23: 46112 | J23: 0 | K23: Вычет согласно инвентаризационной ведомости

Sheet График
B1: Март, 2026 | T1: в
B2: г. Ялта | C2: Симферополь
B3: ул. Набережная Ленина, 18
B4: GL-0005
B5: 10.00-21.00
B6: ФОТ | C6: Кол-во дней в месяц | AK6: 31
B7: =BT30*100/BH30 -> #DIV/0!
D8: вс | E8: пн | F8: вт | G8: ср | H8: чт | I8: пт | J8: сб | K8: вс | L8: пн | M8: вт | N8: ср | O8: чт | P8: пт | Q8: сб | R8: вс | S8: пн | T8: вт | U8: ср | V8: чт | W8: пт | X8: сб | Y8: вс | Z8: пн | AA8: вт | AB8: ср | AC8: чт | AD8: пт | AE8: сб | AF8: вс | AG8: пн | AH8: вт | AJ8: Часы | AK8: Выходные | AL8: Отпуск | AM8: Больничный (официальный) | AN8: Дни стажировки
A10: № | B10: ФИО | C10: Должность | D10: 1 | E10: 2 | F10: 3 | G10: 4 | H10: 5 | I10: 6 | J10: 7 | K10: 8 | L10: 9 | M10: 10 | N10: 11 | O10: 12 | P10: 13 | Q10: 14 | R10: 15 | S10: 16 | T10: 17 | U10: 18 | V10: 19 | W10: 20 | X10: 21 | Y10: 22 | Z10: 23 | AA10: 24 | AB10: 25 | AC10: 26 | AD10: 27 | AE10: 28 | AF10: 29 | AG10: 30 | AH10: 31 | AI10: Дни
A11: 19 | AI11: 0 | AJ11: 0 | AK11: 0 | AL11: 0 | AM11: 0 | AN11: 0
A12: 18 | AI12: 0 | AJ12: 0 | AK12: 0 | AL12: 0 | AM12: 0 | AN12: 0
A13: 17 | AI13: 0 | AJ13: 0 | AK13: 0 | AL13: 0 | AM13: 0 | AN13: 0
A14: 16 | AI14: 0 | AJ14: 0 | AK14: 0 | AL14: 0 | AM14: 0 | AN14: 0
A15: 15 | AI15: 0 | AJ15: 0 | AK15: 0 | AL15: 0 | AM15: 0 | AN15: 0
A16: 14 | AI16: 0 | AJ16: 0 | AK16: 0 | AL16: 0 | AM16: 0 | AN16: 0
A17: 13 | AI17: 0 | AJ17: 0 | AK17: 0 | AL17: 0 | AM17: 0 | AN17: 0
A18: 12 | AI18: 0 | AJ18: 0 | AK18: 0 | AL18: 0 | AM18: 0 | AN18: 0
A19: 11 | AI19: 0 | AJ19: 0 | AK19: 0 | AL19: 0 | AM19: 0 | AN19: 0
A20: 10 | AI20: 0 | AJ20: 0 | AK20: 0 | AL20: 0 | AM20: 0 | AN20: 0
A21: 9 | AI21: 0 | AJ21: 0 | AK21: 0 | AL21: 0 | AM21: 0 | AN21: 0
A22: 8 | AI22: =COUNTIF(D22:AH22, ">0") -> 0 | AJ22: 0 | AK22: 0 | AL22: 0 | AM22: 0 | AN22: 0
A23: 7 | AI23: =COUNTIF(D23:AH23, ">0") -> 0 | AJ23: 0 | AK23: 0 | AL23: 0 | AM23: 0 | AN23: 0
A24: 6 | AI24: =COUNTIF(D24:AH24, ">0") -> 0 | AJ24: 0 | AK24: 0 | AL24: 0 | AM24: 0 | AN24: 0
A25: 5 | AI25: =COUNTIF(D25:AH25,">0") -> 0 | AJ25: =SUMIF(D25:AH25,">0") -> 0 | AK25: =COUNTIF(D25:AH25,"В") -> 0 | AL25: =COUNTIF(E25:AI25,"о") -> 0 | AM25: =COUNTIF(F25:AJ25,"б") -> 0 | AN25: 0
A26: 4 | AI26: =COUNTIF(D26:AH26, ">0") -> 0 | AJ26: =SUMIF(D26:AH26,">0") -> 0 | AK26: =COUNTIF(D26:AH26, "В") -> 0 | AL26: 0 | AM26: 0 | AN26: 0
A27: 3 | B27: Самошкина Алина | C27: ПК | F27: 6с | G27: 11с | H27: в | I27: 11с | J27: 11с | K27: 11с | L27: 11с | M27: 11с | N27: в | O27: в | P27: 11 | Q27: 11 | R27: 11 | S27: в | T27: в | U27: 11 | V27: 11 | W27: 11 | X27: в | Y27: 11 | Z27: в | AA27: в | AB27: 11 | AC27: 11 | AD27: в | AE27: в | AF27: в | AG27: 11 | AH27: 11 | AI27: =COUNTIF(D27:AH27,">0") -> 11 | AJ27: =SUMIF(D27:AH27,">0") -> 121 | AK27: =COUNTIF(D27:AH27,"В") -> 11 | AL27: =COUNTIF(E27:AI27,"о") -> 0 | AM27: =COUNTIF(F27:AJ27,"б") -> 0 | AN27: 0
A28: 2 | B28: Уразгильдеева Екатерина | C28: ПК | D28: 11 | E28: в | F28: в | G28: 11 | H28: 11 | I28: 11 | J28: 11 | K28: 11 | L28: в | M28: в | N28: 11 | O28: 11 | P28: в | Q28: в | R28: в | S28: 11 | T28: 11 | U28: в | V28: в | W28: в | X28: 11 | Y28: 11 | Z28: 11 | AA28: 11 | AB28: в | AC28: в | AD28: 11 | AE28: 11 | AF28: 11 | AG28: в | AH28: в | AI28: =COUNTIF(D28:AH28,">0") -> 17 | AJ28: =SUMIF(D28:AH28,">0") -> 187 | AK28: =COUNTIF(D28:AH28,"В") -> 14 | AL28: =COUNTIF(E28:AI28,"о") -> 0 | AM28: =COUNTIF(F28:AJ28,"б") -> 0 | AN28: 0
A29: 1 | B29: Рогалевич Ирина | C29: УМ | D29: 8 | E29: 11 | F29: 11 | G29: 9 | H29: 9 | I29: 9 | J29: 9 | K29: 9 | L29: 11 | M29: 11 | N29: в | O29: 9 | P29: 11 | Q29: 11 | R29: 11 | S29: в | T29: с | U29: с | V29: с | W29: с | X29: с | Y29: с | Z29: с | AA29: с | AB29: с | AC29: с | AD29: с | AE29: с | AF29: с | AG29: с | AH29: в | AI29: =COUNTIF(D29:AH29,">0") -> 14 | AJ29: =SUMIF(D29:AH29,">0") -> 139 | AK29: =COUNTIF(D29:AH29,"В") -> 3 | AL29: =COUNTIF(E29:AI29,"о") -> 0 | AM29: =COUNTIF(F29:AJ29,"б") -> 0 | AN29: 0
B30: Итого магазин | D30: =COUNTIF(D11:D29, ">0") -> 2 | E30: =COUNTIF(E11:E29, ">0") -> 1 | F30: =COUNTIF(F11:F29, ">0") -> 1 | G30: =COUNTIF(G11:G29, ">0") -> 2 | H30: =COUNTIF(H11:H29, ">0") -> 2 | I30: =COUNTIF(I11:I29, ">0") -> 2 | J30: =COUNTIF(J11:J29, ">0") -> 2 | K30: =COUNTIF(K11:K29, ">0") -> 2 | ... AH30: =COUNTIF(AH11:AH29, ">0") -> 1 | AI30: =SUM(AI11:AI29) -> 42 | AJ30: =SUM(AJ11:AJ29) -> 447 | AK30: =SUM(AK11:AK29) -> 28 | AL30: =SUM(AL11:AL29) -> 0 | AM30: =SUM(AM11:AM29) -> 0 | AN30: =SUM(AN11:AN29) -> 0
