Workbook
Name маг: NA()

Sheet Ялта, Ленина, 18
B1: =TODAY()-1 -> 46171
B2: (отчетная дата)
C3: Осталось до выполнения плана!!! | I3: =График!B3 -> ул. Набережная Ленина, 18
C4: =I8-D56 -> 2009785.6 | E4: =IF(I8<>0, C4/I8, 0) -> 0.41924532
D5: =C4/(I14-J14) -> #DIV/0!
F6: Целевые показатели
F7: Показатель | I7: План | J7: Факт | K7: % выполнения | L7: Прогноз выполнения | M7: % выполнения по прогнозу | N7: Отклонение | O7: Факт аналогичного месяца прошлого года | P7: Отклонение LFL
F8: Выручка | I8: =I11*I12*I13 -> 4793817.6 | J8: =D56 -> 2784032 | K8: =IF(AND(I8<>"", I8<>0, J8<>""), J8/I8, "") -> 0.58075468 | L8: =IF(SUMIF($D$25:$D$55,">=0",$P$25:$P$55)<>0,I8*D56/SUMIF($D$25:$D$55,">=0",$P$25:$P$55),0) -> 2784032 | M8: =IF(AND(I8<>"", I8<>0, L8<>"", L8<>0), L8/I8, "") -> 0.58075468 | N8: =IF(AND(J8<>0, J8<>"", I8<>0, I8<>""), L8-I8, "") -> -2009785.6 | P8: =IF(AND(O8<>"", O8<>0, L8<>"", L8<>0), -O8+L8, "") | Q8: =IF(AND(P8<>"", P8<>0, O8<>0, O8<>""), P8/O8, "")
F9: Кол-во изделий | I9: =I8/I11 -> 921.888 | J9: =E56 -> 493 | K9: =IF(AND(I9<>"", I9<>0, J9<>""), J9/I9, "") -> 0.53477212 | L9: =IF(SUMIF($E$25:$E$55, ">=0", $Q$25:$Q$55)<>0, I9*E56/SUMIF($E$25:$E$55, ">=0", $Q$25:$Q$55), 0) -> 493 | M9: =IF(AND(I9<>"", I9<>0, L9<>"", L9<>0), L9/I9, "") -> 0.53477212 | N9: =IF(AND(J9<>0, J9<>"", I9<>0, I9<>""), L9-I9, "") -> -428.888 | O9: =O8/O11 -> #DIV/0! | P9: =IF(AND(O9<>"", O9<>0, L9<>"", L9<>0), -O9+L9, "") -> #DIV/0! | Q9: =IF(AND(P9<>"", P9<>0, O9<>0, O9<>""), P9/O9, "") -> #DIV/0!
F10: Средний чек | I10: =I11*I12 -> 10088 | J10: =H56 -> 10160.701 | K10: =IF(AND(I10<>"", I10<>0, J10<>""), J10/I10, "") -> 1.0072067 | L10: =J10 -> 10160.701 | M10: =IF(AND(I10<>"", I10<>0, L10<>"", L10<>0), L10/I10, "") -> 1.0072067 | N10: =IF(AND(J10<>0, J10<>"", I10<>0, I10<>""), L10-I10, "") -> 72.70073 | O10: =O11*O12 -> 0 | P10: =IF(AND(O10<>"", O10<>0, L10<>"", L10<>0), -O10+L10, "") | Q10: =IF(AND(P10<>"", P10<>0, O10<>0, O10<>""), P10/O10, "") | S10: IS
F11: Средняя стоимость изделия | I11: 5200 | J11: =F56 -> 5647.1237 | K11: =IF(AND(I11<>"", I11<>0, J11<>""), J11/I11, "") -> 1.0859853 | L11: =IF(L9>0, L8/L9, "") -> 5647.1237 | M11: =IF(AND(I11<>"", I11<>0, L11<>"", L11<>0), L11/I11, "") -> 1.0859853 | N11: =IF(AND(J11<>0, J11<>"", I11<>0, I11<>""), L11-I11, "") -> 447.12373 | P11: =IF(AND(O11<>"", O11<>0, L11<>"", L11<>0), -O11+L11, "") | Q11: =IF(AND(P11<>"", P11<>0, O11<>0, O11<>""), P11/O11, "")
F12: Длина чека | I12: 1.94 | J12: =J56 -> 1.7992701 | K12: =IF(AND(I12<>"", I12<>0, J12<>""), J12/I12, "") -> 0.9274588 | L12: =J12 -> 1.7992701 | M12: =IF(AND(I12<>"", I12<>0, L12<>"", L12<>0), L12/I12, "") -> 0.9274588 | N12: =IF(AND(J12<>0, J12<>"", I12<>0, I12<>""), L12-I12, "") -> -0.14072993 | P12: =IF(AND(O12<>"", O12<>0, L12<>"", L12<>0), -O12+L12, "") | Q12: =IF(AND(P12<>"", P12<>0, O12<>0, O12<>""), P12/O12, "") | S12: 680000 | T12: =L56 -> 573273
F13: Кол-во чеков | I13: =I17*I20 -> 475.2 | J13: =G56 -> 274 | K13: =IF(AND(I13<>"", I13<>0, J13<>""), J13/I13, "") -> 0.57659933 | L13: =IF(SUMIF($G$25:$G$55, ">=0", $R$25:$R$55)<>0, I13*G56/SUMIF($G$25:$G$55, ">=0", $R$25:$R$55), "") -> 274 | M13: =IF(AND(I13<>"", I13<>0, L13<>"", L13<>0), L13/I13, "") -> 0.57659933 | N13: =IF(AND(J13<>0, J13<>"", I13<>0, I13<>""), L13-I13, "") -> -201.2 | P13: =IF(AND(O13<>"", O13<>0, L13<>"", L13<>0), -O13+L13, "") | Q13: =IF(AND(P13<>"", P13<>0, O13<>0, O13<>""), P13/O13, "") | S13: =T12/S12 -> 0.84304853 | T13: =S13/J14*I14 -> 0.84304853
F14: Кол-во смен | I14: 31 | J14: 31 | K14: =IF(AND(I14<>"", I14<>0, J14<>""), J14/I14, "") -> 1 | L14: =I14 -> 31 | M14: =IF(AND(I14<>"", I14<>0, L14<>"", L14<>0), L14/I14, "") -> 1 | N14: =IF(AND(J14<>0, J14<>"", I14<>0, I14<>""), L14-I14, "") -> 0 | P14: =IF(AND(O14<>"", O14<>0, L14<>"", L14<>0), -O14+L14, "") | Q14: =IF(AND(P14<>"", P14<>0, O14<>0, O14<>""), P14/O14, "")
F15: Средние продажи в смену | I15: =I8/I14 -> 154639.28 | J15: =J8/J14 -> 89807.484 | K15: =IF(AND(I15<>"", I15<>0, J15<>""), J15/I15, "") -> 0.58075468 | L15: =J15 -> 89807.484 | M15: =IF(AND(I15<>"", I15<>0, L15<>"", L15<>0), L15/I15, "") -> 0.58075468 | N15: =IF(AND(J15<>0, J15<>"", I15<>0, I15<>""), L15-I15, "") -> -64831.794 | P15: =IF(AND(O15<>"", O15<>0, L15<>"", L15<>0), -O15+L15, "") | Q15: =IF(AND(P15<>"", P15<>0, O15<>0, O15<>""), P15/O15, "")
F16: Отставание/Перевыполнение | J16: =J8-I15*J14 -> -2009785.6 | K16: =IF(AND(I16<>"", I16<>0, J16<>""), J16/I16, "") | L16: =J16 -> -2009785.6 | M16: =IF(AND(I16<>"", I16<>0, L16<>"", L16<>0), L16/I16, "") | N16: =IF(AND(J16<>0, J16<>"", I16<>0, I16<>""), L16-I16, "") | P16: =IF(AND(O16<>"", O16<>0, L16<>"", L16<>0), -O16+L16, "") | Q16: =IF(AND(P16<>"", P16<>0, O16<>0, O16<>""), P16/O16, "") | S16: UNOde50
F17: Трафик | I17: 2160 | J17: =I56 -> 1195 | K17: =IF(AND(I17<>"", I17<>0, J17<>""), J17/I17, "") -> 0.55324074 | L17: =J17/J14*I14 -> 1195 | M17: =IF(AND(I17<>"", I17<>0, L17<>"", L17<>0), L17/I17, "") -> 0.55324074 | N17: =IF(AND(J17<>0, J17<>"", I17<>0, I17<>""), L17-I17, "") -> -965 | P17: =IF(AND(O17<>"", O17<>0, L17<>"", L17<>0), -O17+L17, "") | Q17: =IF(AND(P17<>"", P17<>0, O17<>0, O17<>""), P17/O17, "")
K18: =IF(AND(I18<>"", I18<>0, J18<>""), J18/I18, "") | L18: =J18 -> 0 | M18: =IF(AND(I18<>"", I18<>0, L18<>"", L18<>0), L18/I18, "") | N18: =IF(AND(J18<>0, J18<>"", I18<>0, I18<>""), L18-I18, "") | O18: 0 | P18: =IF(AND(O18<>"", O18<>0, L18<>"", L18<>0), -O18+L18, "") | Q18: =IF(AND(P18<>"", P18<>0, O18<>0, O18<>""), P18/O18, "") | S18: 480000 | T18: =K56 -> 535497
J19: =M56 -> 0 | K19: =IF(AND(I19<>"", I19<>0, J19<>""), J19/I19, "") | L19: =J19 -> 0 | M19: =IF(AND(I19<>"", I19<>0, L19<>"", L19<>0), L19/I19, "") | N19: =IF(AND(J19<>0, J19<>"", I19<>0, I19<>""), L19-I19, "") | O19: 0 | P19: =IF(AND(O19<>"", O19<>0, L19<>"", L19<>0), -O19+L19, "") | Q19: =IF(AND(P19<>"", P19<>0, O19<>0, O19<>""), P19/O19, "") | S19: =T18/S18 -> 1.1156188 | T19: =S19/J14*I14 -> 1.1156188
F20: Конверсия план/факт | I20: 0.22 | J20: =N56 -> 0.2292887 | K20: =J20/I20 -> 1.0422214 | L20: =IF(AND(K8<>0, I14<>0, I56<>0), (I56*N56+(I56/K8-I56)*I20)/(I56/K8), 0) -> 0.22539446 | M20: =IF(AND(I20<>"", I20<>0, L20<>"", L20<>0), L20/I20, "") -> 1.0245203 | N20: =IF(AND(J20<>0, J20<>"", I20<>0, I20<>""), L20-I20, "") -> 0.0053944577 | P20: =IF(AND(O20<>"", O20<>0, L20<>"", L20<>0), -O20+L20, "") | Q20: =IF(AND(P20<>"", P20<>0, O20<>0, O20<>""), P20/O20, "")
A22: Факт продаж за месяц | O22: % выполнения дневного плана | P22: Раcпределение плана по дням
A23: Сотрудник | B23: Дата | C23: День недели | D23: Выручка (руб) | E23: Кол-во единиц (шт.) | F23: Средняя стоимость изделия (руб.) | G23: Количество чеков (шт.) | H23: Средняя сумма чека (руб.) | I23: Трафик | J23: Длина чека (шт.) | K23: UNOde50 | L23: IS | M23: Запасной | N23: Конверсия (%) | P23: выручка, план | Q23: кол-во ед, план | R23: Кол-во чеков, план | S23: выручка, скорректир.план | T23: кол-во ед, скорр. план | U23: кол-во чеков, скорр. план | V23: Коэфф. Дня Недели | W23: Специфика месяца
B24: 1 | C24: 2 | D24: 3 | E24: 4 | F24: 5 | G24: 6 | H24: 7 | I24: 8 | J24: 9 | K24: 10 | L24: 11 | M24: 12 | N24: 13 | P24: 1 | Q24: 2 | R24: 3 | S24: 4 | T24: 5 | U24: 6 | V24: 10 | W24: 11
A25: Рогалевич, Уразгильдеева | B25: 45778 | C25: чт | D25: =104329+L25 -> 157504 | E25: 30 | F25: =IF(AND(E25<>"",E25<>0),D25/E25,"") -> 5250.1333 | G25: 19 | H25: =IF(AND(G25<>"",G25<>0),D25/G25,"") -> 8289.6842 | I25: 70 | J25: =IF(AND(G25<>"",G25<>0),E25/G25,"") -> 1.5789474 | K25: 0 | L25: 53175 | N25: =IF(AND(I25<>"",I25<>0),G25/I25,"") -> 0.27142857 | O25: =D25/P25 -> 1.1317973 | P25: =$I$8*V25*W25/SUMPRODUCT($W$25:$W$55,$V$25:$V$55) -> 139162.72 | Q25: =$I$9*V25*W25/SUMPRODUCT($W$25:$W$55,$V$25:$V$55) -> 26.762062 | R25: =IF($I$12="","",Q25/$I$12) -> 13.794877 | S25: =IF(D25<>"",D25,P25) -> 157504 | T25: =IF(E25<>"",E25,Q25) -> 30 | U25: =IF(G25<>"",G25,R25) -> 19 | V25: 0.9004852 | W25: 0.9004852
A26: Рогалевич, Уразгильдеева | B26: 45779 | C26: пт | D26: 133314 | E26: 31 | F26: =IF(AND(E26<>"",E26<>0),D26/E26,"") -> 4300.4516 | G26: 15 | H26: =IF(AND(G26<>"",G26<>0),D26/G26,"") -> 8887.6 | I26: 70 | J26: =IF(AND(G26<>"",G26<>0),E26/G26,"") -> 2.0666667 | N26: =IF(AND(I26<>"",I26<>0),G26/I26,"") -> 0.21428571 | O26: =D26/P26 -> 0.68979374 | P26: =$I$8*V26*W26/SUMPRODUCT($W$25:$W$55,$V$25:$V$55) -> 193266.47 | Q26: =$I$9*V26*W26/SUMPRODUCT($W$25:$W$55,$V$25:$V$55) -> 37.166629 | R26: =IF($I$12="","",Q26/$I$12) -> 19.158056 | S26: =IF(W26<>"",IF(D26<>"",D26,($I$8-SUM($S$25:S25))*V26*W26/SUMPRODUCT($W26:$W$55,$V26:$V$55)),"") -> 133314 | T26: =IF(W26<>"",IF(E26<>"",E26,($I$9-SUM($T$25:T25))*V26*W26/SUMPRODUCT($W26:$W$55,$V26:$V$55)),"") -> 31 | U26: =IF(W26<>"",IF($I$12<>"",IF(G26<>"",G26,($I$9/$I$12-SUM($U$25:U25))*V26*W26/SUMPRODUCT($W26:$W$55,$V26:$V$55)),""),"") -> 15 | V26: 1.0611906 | W26: 1.0611906
A27: Рогалевич, Уразгильдеева, Вафина | B27: 45780 | C27: сб | D27: =160306+L27 -> 195921 | E27: 36 | F27: =IF(AND(E27<>"",E27<>0),D27/E27,"") -> 5442.25 | G27: 21 | H27: =IF(AND(G27<>"",G27<>0),D27/G27,"") -> 9329.5714 | I27: 70 | J27: =IF(AND(G27<>"",G27<>0),E27/G27,"") -> 1.7142857 | K27: 42464 | L27: 35615 | N27: =IF(AND(I27<>"",I27<>0),G27/I27,"") -> 0.3 | O27: =D27/P27 -> 0.79515474 | P27: =$I$8*V27*W27/SUMPRODUCT($W$25:$W$55,$V$25:$V$55) -> 246393.55 | Q27: =$I$9*V27*W27/SUMPRODUCT($W$25:$W$55,$V$25:$V$55) -> 47.383375 | R27: =IF($I$12="","",Q27/$I$12) -> 24.42442 | S27: =IF(W27<>"",IF(D27<>"",D27,($I$8-SUM($S$25:S26))*V27*W27/SUMPRODUCT($W27:$W$55,$V27:$V$55)),"") -> 195921 | T27: =IF(W27<>"",IF(E27<>"",E27,($I$9-SUM($T$25:T26))*V27*W27/SUMPRODUCT($W27:$W$55,$V27:$V$55)),"") -> 36 | U27: =IF(W27<>"",IF($I$12<>"",IF(G27<>"",G27,($I$9/$I$12-SUM($U$25:U26))*V27*W27/SUMPRODUCT($W27:$W$55,$V27:$V$55)),""),"") -> 21 | V27: 1.1982013 | W27: 1.1982013
A28: Рогалевич,Вафина | B28: 45781 | C28: вс | D28: 91670 | E28: 20 | F28: =IF(AND(E28<>"",E28<>0),D28/E28,"") -> 4583.5 | G28: 9 | H28: =IF(AND(G28<>"",G28<>0),D28/G28,"") -> 10185.556 | I28: 40 | J28: =IF(AND(G28<>"",G28<>0),E28/G28,"") -> 2.2222222 | K28: 12992 | N28: =IF(AND(I28<>"",I28<>0),G28/I28,"") -> 0.225 | O28: =D28/P28 -> 0.87600559 | P28: =$I$8*V28*W28/SUMPRODUCT($W$25:$W$55,$V$25:$V$55) -> 104645.45 | Q28: =$I$9*V28*W28/SUMPRODUCT($W$25:$W$55,$V$25:$V$55) -> 20.124125 | R28: =IF($I$12="","",Q28/$I$12) -> 10.37326 | S28: =IF(W28<>"",IF(D28<>"",D28,($I$8-SUM($S$25:S27))*V28*W28/SUMPRODUCT($W28:$W$55,$V28:$V$55)),"") -> 91670 | T28: =IF(W28<>"",IF(E28<>"",E28,($I$9-SUM($T$25:T27))*V28*W28/SUMPRODUCT($W28:$W$55,$V28:$V$55)),"") -> 20 | U28: =IF(W28<>"",IF($I$12<>"",IF(G28<>"",G28,($I$9/$I$12-SUM($U$25:U27))*V28*W28/SUMPRODUCT($W28:$W$55,$V28:$V$55)),""),"") -> 9 | V28: 0.78086381 | W28: 0.78086381
A29: Рогалевич,Вафина | B29: 45782 | C29: пн | D29: 189255 | E29: 34 | F29: =IF(AND(E29<>"",E29<>0),D29/E29,"") -> 5566.3235 | G29: 13 | H29: =IF(AND(G29<>"",G29<>0),D29/G29,"") -> 14558.077 | I29: 70 | J29: =IF(AND(G29<>"",G29<>0),E29/G29,"") -> 2.6153846 | L29: 57708 | N29: =IF(AND(I29<>"",I29<>0),G29/I29,"") -> 0.18571429 | O29: =D29/P29 -> 1.0117612 | P29: =$I$8*V29*W29/SUMPRODUCT($W$25:$W$55,$V$25:$V$55) -> 187055.01 | Q29: =$I$9*V29*W29/SUMPRODUCT($W$25:$W$55,$V$25:$V$55) -> 35.972118 | R29: =IF($I$12="","",Q29/$I$12) -> 18.542329 | S29: =IF(W29<>"",IF(D29<>"",D29,($I$8-SUM($S$25:S28))*V29*W29/SUMPRODUCT($W29:$W$55,$V29:$V$55)),"") -> 189255 | T29: =IF(W29<>"",IF(E29<>"",E29,($I$9-SUM($T$25:T28))*V29*W29/SUMPRODUCT($W29:$W$55,$V29:$V$55)),"") -> 34 | U29: =IF(W29<>"",IF($I$12<>"",IF(G29<>"",G29,($I$9/$I$12-SUM($U$25:U28))*V29*W29/SUMPRODUCT($W29:$W$55,$V29:$V$55)),""),"") -> 13 | V29: 1.0439983 | W29: 1.0439983
A30: Рогалевич, Уразгильдеева | B30: 45783 | C30: вт | D30: 66218 | E30: 12 | F30: =IF(AND(E30<>"",E30<>0),D30/E30,"") -> 5518.1667 | G30: 8 | H30: =IF(AND(G30<>"",G30<>0),D30/G30,"") -> 8277.25 | I30: 40 | J30: =IF(AND(G30<>"",G30<>0),E30/G30,"") -> 1.5 | L30: 25902 | N30: =IF(AND(I30<>"",I30<>0),G30/I30,"") -> 0.2 | O30: =D30/P30 -> 0.63278431 | P30: =$I$8*V30*W30/SUMPRODUCT($W$25:$W$55,$V$25:$V$55) -> 104645.45 | Q30: =$I$9*V30*W30/SUMPRODUCT($W$25:$W$55,$V$25:$V$55) -> 20.124125 | R30: =IF($I$12="","",Q30/$I$12) -> 10.37326 | S30: =IF(W30<>"",IF(D30<>"",D30,($I$8-SUM($S$25:S29))*V30*W30/SUMPRODUCT($W30:$W$55,$V30:$V$55)),"") -> 66218 | T30: =IF(W30<>"",IF(E30<>"",E30,($I$9-SUM($T$25:T29))*V30*W30/SUMPRODUCT($W30:$W$55,$V30:$V$55)),"") -> 12 | U30: =IF(W30<>"",IF($I$12<>"",IF(G30<>"",G30,($I$9/$I$12-SUM($U$25:U29))*V30*W30/SUMPRODUCT($W30:$W$55,$V30:$V$55)),""),"") -> 8 | V30: 0.78086381 | W30: 0.78086381
A31: Рогалевич, Уразгильдеева | B31: 45784 | C31: ср | D31: 123218 | E31: 20 | F31: =IF(AND(E31<>"",E31<>0),D31/E31,"") -> 6160.9 | G31: 10 | H31: =IF(AND(G31<>"",G31<>0),D31/G31,"") -> 12321.8 | I31: 40 | J31: =IF(AND(G31<>"",G31<>0),E31/G31,"") -> 2 | K31: 45563 | L31: 24026 | N31: =IF(AND(I31<>"",I31<>0),G31/I31,"") -> 0.25 | O31: =D31/P31 -> 1.0825627 | P31: =$I$8*V31*W31/SUMPRODUCT($W$25:$W$55,$V$25:$V$55) -> 113820.66 | Q31: =$I$9*V31*W31/SUMPRODUCT($W$25:$W$55,$V$25:$V$55) -> 21.888589 | R31: =IF($I$12="","",Q31/$I$12) -> 11.282778 | S31: =IF(W31<>"",IF(D31<>"",D31,($I$8-SUM($S$25:S30))*V31*W31/SUMPRODUCT($W31:$W$55,$V31:$V$55)),"") -> 123218 | T31: =IF(W31<>"",IF(E31<>"",E31,($I$9-SUM($T$25:T30))*V31*W31/SUMPRODUCT($W31:$W$55,$V31:$V$55)),"") -> 20 | U31: =IF(W31<>"",IF($I$12<>"",IF(G31<>"",G31,($I$9/$I$12-SUM($U$25:U30))*V31*W31/SUMPRODUCT($W31:$W$55,$V31:$V$55)),""),"") -> 10 | V31: 0.81437733 | W31: 0.81437733
A32: Рогалевич,Вафина | B32: 45785 | C32: чт | D32: 91261 | E32: 20 | F32: =IF(AND(E32<>"",E32<>0),D32/E32,"") -> 4563.05 | G32: 11 | H32: =IF(AND(G32<>"",G32<>0),D32/G32,"") -> 8296.4545 | I32: 40 | J32: =IF(AND(G32<>"",G32<>0),E32/G32,"") -> 1.8181818 | K32: 11693 | L32: 8423 | N32: =IF(AND(I32<>"",I32<>0),G32/I32,"") -> 0.275 | O32: =D32/P32 -> 0.80179641 | P32: =$I$8*V32*W32/SUMPRODUCT($W$25:$W$55,$V$25:$V$55) -> 113820.66 | Q32: =$I$9*V32*W32/SUMPRODUCT($W$25:$W$55,$V$25:$V$55) -> 21.888589 | R32: =IF($I$12="","",Q32/$I$12) -> 11.282778 | S32: =IF(W32<>"",IF(D32<>"",D32,($I$8-SUM($S$25:S31))*V32*W32/SUMPRODUCT($W32:$W$55,$V32:$V$55)),"") -> 91261 | T32: =IF(W32<>"",IF(E32<>"",E32,($I$9-SUM($T$25:T31))*V32*W32/SUMPRODUCT($W32:$W$55,$V32:$V$55)),"") -> 20 | U32: =IF(W32<>"",IF($I$12<>"",IF(G32<>"",G32,($I$9/$I$12-SUM($U$25:U31))*V32*W32/SUMPRODUCT($W32:$W$55,$V32:$V$55)),""),"") -> 11 | V32: 0.81437733 | W32: 0.81437733
A33: Рогалевич,Уразгильдеева,Вафина | B33: 45786 | C33: пт | D33: =51383+106583+40551 -> 198517 | E33: 26 | F33: =IF(AND(E33<>"",E33<>0),D33/E33,"") -> 7635.2692 | G33: 11 | H33: =IF(AND(G33<>"",G33<>0),D33/G33,"") -> 18047 | I33: 60 | J33: =IF(AND(G33<>"",G33<>0),E33/G33,"") -> 2.3636364 | K33: 106583 | L33: 40551 | N33: =IF(AND(I33<>"",I33<>0),G33/I33,"") -> 0.18333333 | O33: =D33/P33 -> 1.7441209 | P33: =$I$8*V33*W33/SUMPRODUCT($W$25:$W$55,$V$25:$V$55) -> 113820.66 | Q33: =$I$9*V33*W33/SUMPRODUCT($W$25:$W$55,$V$25:$V$55) -> 21.888589 | R33: =IF($I$12="","",Q33/$I$12) -> 11.282778 | S33: =IF(W33<>"",IF(D33<>"",D33,($I$8-SUM($S$25:S32))*V33*W33/SUMPRODUCT($W33:$W$55,$V33:$V$55)),"") -> 198517 | T33: =IF(W33<>"",IF(E33<>"",E33,($I$9-SUM($T$25:T32))*V33*W33/SUMPRODUCT($W33:$W$55,$V33:$V$55)),"") -> 26 | U33: =IF(W33<>"",IF($I$12<>"",IF(G33<>"",G33,($I$9/$I$12-SUM($U$25:U32))*V33*W33/SUMPRODUCT($W33:$W$55,$V33:$V$55)),""),"") -> 11 | V33: 0.81437733 | W33: 0.81437733
A34: Рогалевич,Уразгильдеева,Вафина | B34: 45787 | C34: сб | D34: 77537 | E34: 12 | F34: =IF(AND(E34<>"",E34<>0),D34/E34,"") -> 6461.4167 | G34: 8 | H34: =IF(AND(G34<>"",G34<>0),D34/G34,"") -> 9692.125 | I34: 30 | J34: =IF(AND(G34<>"",G34<>0),E34/G34,"") -> 1.5 | L34: 42966 | N34: =IF(AND(I34<>"",I34<>0),G34/I34,"") -> 0.26666667 | O34: =D34/P34 -> 0.45179272 | P34: =$I$8*V34*W34/SUMPRODUCT($W$25:$W$55,$V$25:$V$55) -> 171620.74 | Q34: =$I$9*V34*W34/SUMPRODUCT($W$25:$W$55,$V$25:$V$55) -> 33.003988 | R34: =IF($I$12="","",Q34/$I$12) -> 17.012365 | S34: =IF(W34<>"",IF(D34<>"",D34,($I$8-SUM($S$25:S33))*V34*W34/SUMPRODUCT($W34:$W$55,$V34:$V$55)),"") -> 77537 | T34: =IF(W34<>"",IF(E34<>"",E34,($I$9-SUM($T$25:T33))*V34*W34/SUMPRODUCT($W34:$W$55,$V34:$V$55)),"") -> 12 | U34: =IF(W34<>"",IF($I$12<>"",IF(G34<>"",G34,($I$9/$I$12-SUM($U$25:U33))*V34*W34/SUMPRODUCT($W34:$W$55,$V34:$V$55)),""),"") -> 8 | V34: 1 | W34: 1
A35: Рогалевич,Уразгильдеева | B35: 45788 | C35: вс | D35: 123397 | E35: 17 | F35: =IF(AND(E35<>"",E35<>0),D35/E35,"") -> 7258.6471 | G35: 12 | H35: =IF(AND(G35<>"",G35<>0),D35/G35,"") -> 10283.083 | I35: 50 | J35: =IF(AND(G35<>"",G35<>0),E35/G35,"") -> 1.4166667 | K35: 63468 | L35: 20229 | N35: =IF(AND(I35<>"",I35<>0),G35/I35,"") -> 0.24 | O35: =D35/P35 -> 0.99516934 | P35: =$I$8*V35*W35/SUMPRODUCT($W$25:$W$55,$V$25:$V$55) -> 123995.98 | Q35: =$I$9*V35*W35/SUMPRODUCT($W$25:$W$55,$V$25:$V$55) -> 23.845381 | R35: =IF($I$12="","",Q35/$I$12) -> 12.291434 | S35: =IF(W35<>"",IF(D35<>"",D35,($I$8-SUM($S$25:S34))*V35*W35/SUMPRODUCT($W35:$W$55,$V35:$V$55)),"") -> 123397 | T35: =IF(W35<>"",IF(E35<>"",E35,($I$9-SUM($T$25:T34))*V35*W35/SUMPRODUCT($W35:$W$55,$V35:$V$55)),"") -> 17 | U35: =IF(W35<>"",IF($I$12<>"",IF(G35<>"",G35,($I$9/$I$12-SUM($U$25:U34))*V35*W35/SUMPRODUCT($W35:$W$55,$V35:$V$55)),""),"") -> 12 | V35: 0.85 | W35: 0.85
A36: Рогалевич,Вафина | B36: 45789 | C36: пн | D36: =46553+8903 -> 55456 | E36: 13 | F36: =IF(AND(E36<>"",E36<>0),D36/E36,"") -> 4265.8462 | G36: 6 | H36: =IF(AND(G36<>"",G36<>0),D36/G36,"") -> 9242.6667 | I36: 30 | J36: =IF(AND(G36<>"",G36<>0),E36/G36,"") -> 2.1666667 | L36: 8903 | N36: =IF(AND(I36<>"",I36<>0),G36/I36,"") -> 0.2 | O36: =D36/P36 -> 0.4472403 | P36: =$I$8*V36*W36/SUMPRODUCT($W$25:$W$55,$V$25:$V$55) -> 123995.98 | Q36: =$I$9*V36*W36/SUMPRODUCT($W$25:$W$55,$V$25:$V$55) -> 23.845381 | R36: =IF($I$12="","",Q36/$I$12) -> 12.291434 | S36: =IF(W36<>"",IF(D36<>"",D36,($I$8-SUM($S$25:S35))*V36*W36/SUMPRODUCT($W36:$W$55,$V36:$V$55)),"") -> 55456 | T36: =IF(W36<>"",IF(E36<>"",E36,($I$9-SUM($T$25:T35))*V36*W36/SUMPRODUCT($W36:$W$55,$V36:$V$55)),"") -> 13 | U36: =IF(W36<>"",IF($I$12<>"",IF(G36<>"",G36,($I$9/$I$12-SUM($U$25:U35))*V36*W36/SUMPRODUCT($W36:$W$55,$V36:$V$55)),""),"") -> 6 | V36: 0.85 | W36: 0.85
A37: Рогалевич,Вафина | B37: 45790 | C37: вт | D37: 46762 | E37: 2 | F37: =IF(AND(E37<>"",E37<>0),D37/E37,"") -> 23381 | G37: 3 | H37: =IF(AND(G37<>"",G37<>0),D37/G37,"") -> 15587.333 | I37: 22 | J37: =IF(AND(G37<>"",G37<>0),E37/G37,"") -> 0.66666667 | K37: 17469 | N37: =IF(AND(I37<>"",I37<>0),G37/I37,"") -> 0.13636364 | O37: =D37/P37 -> 0.37712512 | P37: =$I$8*V37*W37/SUMPRODUCT($W$25:$W$55,$V$25:$V$55) -> 123995.98 | Q37: =$I$9*V37*W37/SUMPRODUCT($W$25:$W$55,$V$25:$V$55) -> 23.845381 | R37: =IF($I$12="","",Q37/$I$12) -> 12.291434 | S37: =IF(W37<>"",IF(D37<>"",D37,($I$8-SUM($S$25:S36))*V37*W37/SUMPRODUCT($W37:$W$55,$V37:$V$55)),"") -> 46762 | T37: =IF(W37<>"",IF(E37<>"",E37,($I$9-SUM($T$25:T36))*V37*W37/SUMPRODUCT($W37:$W$55,$V37:$V$55)),"") -> 2 | U37: =IF(W37<>"",IF($I$12<>"",IF(G37<>"",G37,($I$9/$I$12-SUM($U$25:U36))*V37*W37/SUMPRODUCT($W37:$W$55,$V37:$V$55)),""),"") -> 3 | V37: 0.85 | W37: 0.85
A38: Уразгильдеева, Вафина | B38: 45791 | C38: ср | D38: =38738+67970+15403 -> 122111 | E38: 15 | F38: =IF(AND(E38<>"",E38<>0),D38/E38,"") -> 8140.7333 | G38: 8 | H38: =IF(AND(G38<>"",G38<>0),D38/G38,"") -> 15263.875 | I38: 20 | J38: =IF(AND(G38<>"",G38<>0),E38/G38,"") -> 1.875 | K38: 67970 | L38: 15403 | N38: =IF(AND(I38<>"",I38<>0),G38/I38,"") -> 0.4 | O38: =D38/P38 -> 0.98479803 | P38: =$I$8*V38*W38/SUMPRODUCT($W$25:$W$55,$V$25:$V$55) -> 123995.98 | Q38: =$I$9*V38*W38/SUMPRODUCT($W$25:$W$55,$V$25:$V$55) -> 23.845381 | R38: =IF($I$12="","",Q38/$I$12) -> 12.291434 | S38: =IF(W38<>"",IF(D38<>"",D38,($I$8-SUM($S$25:S37))*V38*W38/SUMPRODUCT($W38:$W$55,$V38:$V$55)),"") -> 122111 | T38: =IF(W38<>"",IF(E38<>"",E38,($I$9-SUM($T$25:T37))*V38*W38/SUMPRODUCT($W38:$W$55,$V38:$V$55)),"") -> 15 | U38: =IF(W38<>"",IF($I$12<>"",IF(G38<>"",G38,($I$9/$I$12-SUM($U$25:U37))*V38*W38/SUMPRODUCT($W38:$W$55,$V38:$V$55)),""),"") -> 8 | V38: 0.85 | W38: 0.85
A39: Рогалевич,Уразгильдеева | B39: 45792 | C39: чт | D39: =53662+7903 -> 61565 | E39: 17 | F39: =IF(AND(E39<>"",E39<>0),D39/E39,"") -> 3621.4706 | G39: 7 | H39: =IF(AND(G39<>"",G39<>0),D39/G39,"") -> 8795 | I39: 30 | J39: =IF(AND(G39<>"",G39<>0),E39/G39,"") -> 2.4285714 | L39: 7903 | N39: =IF(AND(I39<>"",I39<>0),G39/I39,"") -> 0.23333333 | O39: =D39/P39 -> 0.49650802 | P39: =$I$8*V39*W39/SUMPRODUCT($W$25:$W$55,$V$25:$V$55) -> 123995.98 | Q39: =$I$9*V39*W39/SUMPRODUCT($W$25:$W$55,$V$25:$V$55) -> 23.845381 | R39: =IF($I$12="","",Q39/$I$12) -> 12.291434 | S39: =IF(W39<>"",IF(D39<>"",D39,($I$8-SUM($S$25:S38))*V39*W39/SUMPRODUCT($W39:$W$55,$V39:$V$55)),"") -> 61565 | T39: =IF(W39<>"",IF(E39<>"",E39,($I$9-SUM($T$25:T38))*V39*W39/SUMPRODUCT($W39:$W$55,$V39:$V$55)),"") -> 17 | U39: =IF(W39<>"",IF($I$12<>"",IF(G39<>"",G39,($I$9/$I$12-SUM($U$25:U38))*V39*W39/SUMPRODUCT($W39:$W$55,$V39:$V$55)),""),"") -> 7 | V39: 0.85 | W39: 0.85
A40: Рогалевич,Уразгильдеева | B40: 45793 | C40: пт | D40: 82307 | E40: 11 | F40: =IF(AND(E40<>"",E40<>0),D40/E40,"") -> 7482.4545 | G40: 5 | H40: =IF(AND(G40<>"",G40<>0),D40/G40,"") -> 16461.4 | I40: 30 | J40: =IF(AND(G40<>"",G40<>0),E40/G40,"") -> 2.2 | K40: 55166 | N40: =IF(AND(I40<>"",I40<>0),G40/I40,"") -> 0.16666667 | O40: =D40/P40 -> 0.47958657 | P40: =$I$8*V40*W40/SUMPRODUCT($W$25:$W$55,$V$25:$V$55) -> 171620.74 | Q40: =$I$9*V40*W40/SUMPRODUCT($W$25:$W$55,$V$25:$V$55) -> 33.003988 | R40: =IF($I$12="","",Q40/$I$12) -> 17.012365 | S40: =IF(W40<>"",IF(D40<>"",D40,($I$8-SUM($S$25:S39))*V40*W40/SUMPRODUCT($W40:$W$55,$V40:$V$55)),"") -> 82307 | T40: =IF(W40<>"",IF(E40<>"",E40,($I$9-SUM($T$25:T39))*V40*W40/SUMPRODUCT($W40:$W$55,$V40:$V$55)),"") -> 11 | U40: =IF(W40<>"",IF($I$12<>"",IF(G40<>"",G40,($I$9/$I$12-SUM($U$25:U39))*V40*W40/SUMPRODUCT($W40:$W$55,$V40:$V$55)),""),"") -> 5 | V40: 1 | W40: 1
A41: Рогалевич,Вафина | B41: 45794 | C41: сб | D41: 41508 | E41: 11 | F41: =IF(AND(E41<>"",E41<>0),D41/E41,"") -> 3773.4545 | G41: 6 | H41: =IF(AND(G41<>"",G41<>0),D41/G41,"") -> 6918 | I41: 50 | J41: =IF(AND(G41<>"",G41<>0),E41/G41,"") -> 1.8333333 | K41: 5493 | N41: =IF(AND(I41<>"",I41<>0),G41/I41,"") -> 0.12 | O41: =D41/P41 -> 0.19988338 | P41: =$I$8*V41*W41/SUMPRODUCT($W$25:$W$55,$V$25:$V$55) -> 207661.09 | Q41: =$I$9*V41*W41/SUMPRODUCT($W$25:$W$55,$V$25:$V$55) -> 39.934825 | R41: =IF($I$12="","",Q41/$I$12) -> 20.584962 | S41: =IF(W41<>"",IF(D41<>"",D41,($I$8-SUM($S$25:S40))*V41*W41/SUMPRODUCT($W41:$W$55,$V41:$V$55)),"") -> 41508 | T41: =IF(W41<>"",IF(E41<>"",E41,($I$9-SUM($T$25:T40))*V41*W41/SUMPRODUCT($W41:$W$55,$V41:$V$55)),"") -> 11 | U41: =IF(W41<>"",IF($I$12<>"",IF(G41<>"",G41,($I$9/$I$12-SUM($U$25:U40))*V41*W41/SUMPRODUCT($W41:$W$55,$V41:$V$55)),""),"") -> 6 | V41: 1.1 | W41: 1.1
A42: Рогалевич,Вафина | B42: 45795 | C42: вс | D42: 56887 | E42: 12 | F42: =IF(AND(E42<>"",E42<>0),D42/E42,"") -> 4740.5833 | G42: 6 | H42: =IF(AND(G42<>"",G42<>0),D42/G42,"") -> 9481.1667 | I42: 34 | J42: =IF(AND(G42<>"",G42<>0),E42/G42,"") -> 2 | L42: 5501 | N42: =IF(AND(I42<>"",I42<>0),G42/I42,"") -> 0.17647059 | O42: =D42/P42 -> 0.27394154 | P42: =$I$8*V42*W42/SUMPRODUCT($W$25:$W$55,$V$25:$V$55) -> 207661.09 | Q42: =$I$9*V42*W42/SUMPRODUCT($W$25:$W$55,$V$25:$V$55) -> 39.934825 | R42: =IF($I$12="","",Q42/$I$12) -> 20.584962 | S42: =IF(W42<>"",IF(D42<>"",D42,($I$8-SUM($S$25:S41))*V42*W42/SUMPRODUCT($W42:$W$55,$V42:$V$55)),"") -> 56887 | T42: =IF(W42<>"",IF(E42<>"",E42,($I$9-SUM($T$25:T41))*V42*W42/SUMPRODUCT($W42:$W$55,$V42:$V$55)),"") -> 12 | U42: =IF(W42<>"",IF($I$12<>"",IF(G42<>"",G42,($I$9/$I$12-SUM($U$25:U41))*V42*W42/SUMPRODUCT($W42:$W$55,$V42:$V$55)),""),"") -> 6 | V42: 1.1 | W42: 1.1
A43: Уразгильдеева, Вафина | B43: 45796 | C43: пн | D43: 53198 | E43: 12 | F43: =IF(AND(E43<>"",E43<>0),D43/E43,"") -> 4433.1667 | G43: 6 | H43: =IF(AND(G43<>"",G43<>0),D43/G43,"") -> 8866.3333 | I43: 20 | J43: =IF(AND(G43<>"",G43<>0),E43/G43,"") -> 2 | N43: =IF(AND(I43<>"",I43<>0),G43/I43,"") -> 0.3 | O43: =D43/P43 -> 0.42903003 | P43: =$I$8*V43*W43/SUMPRODUCT($W$25:$W$55,$V$25:$V$55) -> 123995.98 | Q43: =$I$9*V43*W43/SUMPRODUCT($W$25:$W$55,$V$25:$V$55) -> 23.845381 | R43: =IF($I$12="","",Q43/$I$12) -> 12.291434 | S43: =IF(W43<>"",IF(D43<>"",D43,($I$8-SUM($S$25:S42))*V43*W43/SUMPRODUCT($W43:$W$55,$V43:$V$55)),"") -> 53198 | T43: =IF(W43<>"",IF(E43<>"",E43,($I$9-SUM($T$25:T42))*V43*W43/SUMPRODUCT($W43:$W$55,$V43:$V$55)),"") -> 12 | U43: =IF(W43<>"",IF($I$12<>"",IF(G43<>"",G43,($I$9/$I$12-SUM($U$25:U42))*V43*W43/SUMPRODUCT($W43:$W$55,$V43:$V$55)),""),"") -> 6 | V43: 0.85 | W43: 0.85
A44: Рогалевич,Уразгильдеева | B44: 45797 | C44: вт | D44: 35332 | E44: 8 | F44: =IF(AND(E44<>"",E44<>0),D44/E44,"") -> 4416.5 | G44: 4 | H44: =IF(AND(G44<>"",G44<>0),D44/G44,"") -> 8833 | I44: 14 | J44: =IF(AND(G44<>"",G44<>0),E44/G44,"") -> 2 | N44: =IF(AND(I44<>"",I44<>0),G44/I44,"") -> 0.28571429 | O44: =D44/P44 -> 0.28494472 | P44: =$I$8*V44*W44/SUMPRODUCT($W$25:$W$55,$V$25:$V$55) -> 123995.98 | Q44: =$I$9*V44*W44/SUMPRODUCT($W$25:$W$55,$V$25:$V$55) -> 23.845381 | R44: =IF($I$12="","",Q44/$I$12) -> 12.291434 | S44: =IF(W44<>"",IF(D44<>"",D44,($I$8-SUM($S$25:S43))*V44*W44/SUMPRODUCT($W44:$W$55,$V44:$V$55)),"") -> 35332 | T44: =IF(W44<>"",IF(E44<>"",E44,($I$9-SUM($T$25:T43))*V44*W44/SUMPRODUCT($W44:$W$55,$V44:$V$55)),"") -> 8 | U44: =IF(W44<>"",IF($I$12<>"",IF(G44<>"",G44,($I$9/$I$12-SUM($U$25:U43))*V44*W44/SUMPRODUCT($W44:$W$55,$V44:$V$55)),""),"") -> 4 | V44: 0.85 | W44: 0.85
A45: Рогалевич,Уразгильдеева | B45: 45798 | C45: ср | D45: =17856+40046 -> 57902 | E45: 12 | F45: =IF(AND(E45<>"",E45<>0),D45/E45,"") -> 4825.1667 | G45: 9 | H45: =IF(AND(G45<>"",G45<>0),D45/G45,"") -> 6433.5556 | I45: 30 | J45: =IF(AND(G45<>"",G45<>0),E45/G45,"") -> 1.3333333 | L45: 10503 | N45: =IF(AND(I45<>"",I45<>0),G45/I45,"") -> 0.3 | O45: =D45/P45 -> 0.36391479 | P45: =$I$8*V45*W45/SUMPRODUCT($W$25:$W$55,$V$25:$V$55) -> 159108.67 | Q45: =$I$9*V45*W45/SUMPRODUCT($W$25:$W$55,$V$25:$V$55) -> 30.597822 | R45: =IF($I$12="","",Q45/$I$12) -> 15.772073 | S45: =IF(W45<>"",IF(D45<>"",D45,($I$8-SUM($S$25:S44))*V45*W45/SUMPRODUCT($W45:$W$55,$V45:$V$55)),"") -> 57902 | T45: =IF(W45<>"",IF(E45<>"",E45,($I$9-SUM($T$25:T44))*V45*W45/SUMPRODUCT($W45:$W$55,$V45:$V$55)),"") -> 12 | U45: =IF(W45<>"",IF($I$12<>"",IF(G45<>"",G45,($I$9/$I$12-SUM($U$25:U44))*V45*W45/SUMPRODUCT($W45:$W$55,$V45:$V$55)),""),"") -> 9 | V45: 0.95 | W45: 0.97588915
A46: Рогалевич,Вафина | B46: 45799 | C46: чт | D46: 28687 | E46: 6 | F46: =IF(AND(E46<>"",E46<>0),D46/E46,"") -> 4781.1667 | G46: 3 | H46: =IF(AND(G46<>"",G46<>0),D46/G46,"") -> 9562.3333 | I46: 16 | J46: =IF(AND(G46<>"",G46<>0),E46/G46,"") -> 2 | L46: 20403 | N46: =IF(AND(I46<>"",I46<>0),G46/I46,"") -> 0.1875 | O46: =D46/P46 -> 0.18029815 | P46: =$I$8*V46*W46/SUMPRODUCT($W$25:$W$55,$V$25:$V$55) -> 159108.67 | Q46: =$I$9*V46*W46/SUMPRODUCT($W$25:$W$55,$V$25:$V$55) -> 30.597822 | R46: =IF($I$12="","",Q46/$I$12) -> 15.772073 | S46: =IF(W46<>"",IF(D46<>"",D46,($I$8-SUM($S$25:S45))*V46*W46/SUMPRODUCT($W46:$W$55,$V46:$V$55)),"") -> 28687 | T46: =IF(W46<>"",IF(E46<>"",E46,($I$9-SUM($T$25:T45))*V46*W46/SUMPRODUCT($W46:$W$55,$V46:$V$55)),"") -> 6 | U46: =IF(W46<>"",IF($I$12<>"",IF(G46<>"",G46,($I$9/$I$12-SUM($U$25:U45))*V46*W46/SUMPRODUCT($W46:$W$55,$V46:$V$55)),""),"") -> 3 | V46: 0.95 | W46: 0.97588915
A47: Рогалевич,Вафина | B47: 45800 | C47: пт | D47: 32069 | E47: 4 | F47: =IF(AND(E47<>"",E47<>0),D47/E47,"") -> 8017.25 | G47: 4 | H47: =IF(AND(G47<>"",G47<>0),D47/G47,"") -> 8017.25 | I47: 16 | J47: =IF(AND(G47<>"",G47<>0),E47/G47,"") -> 1 | N47: =IF(AND(I47<>"",I47<>0),G47/I47,"") -> 0.25 | O47: =D47/P47 -> 0.1868597 | P47: =$I$8*V47*W47/SUMPRODUCT($W$25:$W$55,$V$25:$V$55) -> 171620.74 | Q47: =$I$9*V47*W47/SUMPRODUCT($W$25:$W$55,$V$25:$V$55) -> 33.003988 | R47: =IF($I$12="","",Q47/$I$12) -> 17.012365 | S47: =IF(W47<>"",IF(D47<>"",D47,($I$8-SUM($S$25:S46))*V47*W47/SUMPRODUCT($W47:$W$55,$V47:$V$55)),"") -> 32069 | T47: =IF(W47<>"",IF(E47<>"",E47,($I$9-SUM($T$25:T46))*V47*W47/SUMPRODUCT($W47:$W$55,$V47:$V$55)),"") -> 4 | U47: =IF(W47<>"",IF($I$12<>"",IF(G47<>"",G47,($I$9/$I$12-SUM($U$25:U46))*V47*W47/SUMPRODUCT($W47:$W$55,$V47:$V$55)),""),"") -> 4 | V47: 1 | W47: 1
A48: Рогалевич,Уразгильдеева,Вафина | B48: 45801 | C48: сб | D48: 123588 | E48: 20 | F48: =IF(AND(E48<>"",E48<>0),D48/E48,"") -> 6179.4 | G48: 13 | H48: =IF(AND(G48<>"",G48<>0),D48/G48,"") -> 9506.7692 | I48: 51 | J48: =IF(AND(G48<>"",G48<>0),E48/G48,"") -> 1.5384615 | K48: 25684 | L48: 43712 | N48: =IF(AND(I48<>"",I48<>0),G48/I48,"") -> 0.25490196 | O48: =D48/P48 -> 0.59514278 | P48: =$I$8*V48*W48/SUMPRODUCT($W$25:$W$55,$V$25:$V$55) -> 207661.09 | Q48: =$I$9*V48*W48/SUMPRODUCT($W$25:$W$55,$V$25:$V$55) -> 39.934825 | R48: =IF($I$12="","",Q48/$I$12) -> 20.584962 | S48: =IF(W48<>"",IF(D48<>"",D48,($I$8-SUM($S$25:S47))*V48*W48/SUMPRODUCT($W48:$W$55,$V48:$V$55)),"") -> 123588 | T48: =IF(W48<>"",IF(E48<>"",E48,($I$9-SUM($T$25:T47))*V48*W48/SUMPRODUCT($W48:$W$55,$V48:$V$55)),"") -> 20 | U48: =IF(W48<>"",IF($I$12<>"",IF(G48<>"",G48,($I$9/$I$12-SUM($U$25:U47))*V48*W48/SUMPRODUCT($W48:$W$55,$V48:$V$55)),""),"") -> 13 | V48: 1.1 | W48: 1.1
A49: Рогалевич,Уразгильдеева | B49: 45802 | C49: вс | D49: 33852 | E49: 6 | F49: =IF(AND(E49<>"",E49<>0),D49/E49,"") -> 5642 | G49: 6 | H49: =IF(AND(G49<>"",G49<>0),D49/G49,"") -> 5642 | I49: 30 | J49: =IF(AND(G49<>"",G49<>0),E49/G49,"") -> 1 | K49: 8993 | N49: =IF(AND(I49<>"",I49<>0),G49/I49,"") -> 0.2 | O49: =D49/P49 -> 0.16301561 | P49: =$I$8*V49*W49/SUMPRODUCT($W$25:$W$55,$V$25:$V$55) -> 207661.09 | Q49: =$I$9*V49*W49/SUMPRODUCT($W$25:$W$55,$V$25:$V$55) -> 39.934825 | R49: =IF($I$12="","",Q49/$I$12) -> 20.584962 | S49: =IF(W49<>"",IF(D49<>"",D49,($I$8-SUM($S$25:S48))*V49*W49/SUMPRODUCT($W49:$W$55,$V49:$V$55)),"") -> 33852 | T49: =IF(W49<>"",IF(E49<>"",E49,($I$9-SUM($T$25:T48))*V49*W49/SUMPRODUCT($W49:$W$55,$V49:$V$55)),"") -> 6 | U49: =IF(W49<>"",IF($I$12<>"",IF(G49<>"",G49,($I$9/$I$12-SUM($U$25:U48))*V49*W49/SUMPRODUCT($W49:$W$55,$V49:$V$55)),""),"") -> 6 | V49: 1.1 | W49: 1.1
A50: Вафина,Уразгильдеева | B50: 45803 | C50: пн | D50: 71650 | E50: 10 | F50: =IF(AND(E50<>"",E50<>0),D50/E50,"") -> 7165 | G50: 8 | H50: =IF(AND(G50<>"",G50<>0),D50/G50,"") -> 8956.25 | I50: 20 | J50: =IF(AND(G50<>"",G50<>0),E50/G50,"") -> 1.25 | L50: 46509 | N50: =IF(AND(I50<>"",I50<>0),G50/I50,"") -> 0.4 | O50: =D50/P50 -> 0.5778413 | P50: =$I$8*V50*W50/SUMPRODUCT($W$25:$W$55,$V$25:$V$55) -> 123995.98 | Q50: =$I$9*V50*W50/SUMPRODUCT($W$25:$W$55,$V$25:$V$55) -> 23.845381 | R50: =IF($I$12="","",Q50/$I$12) -> 12.291434 | S50: =IF(W50<>"",IF(D50<>"",D50,($I$8-SUM($S$25:S49))*V50*W50/SUMPRODUCT($W50:$W$55,$V50:$V$55)),"") -> 71650 | T50: =IF(W50<>"",IF(E50<>"",E50,($I$9-SUM($T$25:T49))*V50*W50/SUMPRODUCT($W50:$W$55,$V50:$V$55)),"") -> 10 | U50: =IF(W50<>"",IF($I$12<>"",IF(G50<>"",G50,($I$9/$I$12-SUM($U$25:U49))*V50*W50/SUMPRODUCT($W50:$W$55,$V50:$V$55)),""),"") -> 8 | V50: 0.85 | W50: 0.85
A51: Рогалевич,Вафина | B51: 45804 | C51: вт | D51: =41578+31985+58411 -> 131974 | E51: 16 | F51: =IF(AND(E51<>"",E51<>0),D51/E51,"") -> 8248.375 | G51: 9 | H51: =IF(AND(G51<>"",G51<>0),D51/G51,"") -> 14663.778 | I51: 34 | J51: =IF(AND(G51<>"",G51<>0),E51/G51,"") -> 1.7777778 | K51: 31985 | L51: 58411 | N51: =IF(AND(I51<>"",I51<>0),G51/I51,"") -> 0.26470588 | O51: =D51/P51 -> 1.0643409 | P51: =$I$8*V51*W51/SUMPRODUCT($W$25:$W$55,$V$25:$V$55) -> 123995.98 | Q51: =$I$9*V51*W51/SUMPRODUCT($W$25:$W$55,$V$25:$V$55) -> 23.845381 | R51: =IF($I$12="","",Q51/$I$12) -> 12.291434 | S51: =IF(W51<>"",IF(D51<>"",D51,($I$8-SUM($S$25:S50))*V51*W51/SUMPRODUCT($W51:$W$55,$V51:$V$55)),"") -> 131974 | T51: =IF(W51<>"",IF(E51<>"",E51,($I$9-SUM($T$25:T50))*V51*W51/SUMPRODUCT($W51:$W$55,$V51:$V$55)),"") -> 16 | U51: =IF(W51<>"",IF($I$12<>"",IF(G51<>"",G51,($I$9/$I$12-SUM($U$25:U50))*V51*W51/SUMPRODUCT($W51:$W$55,$V51:$V$55)),""),"") -> 9 | V51: 0.85 | W51: 0.85
A52: Рогалевич,Вафина | B52: 45805 | C52: ср | D52: 37641 | E52: 7 | F52: =IF(AND(E52<>"",E52<>0),D52/E52,"") -> 5377.2857 | G52: 5 | H52: =IF(AND(G52<>"",G52<>0),D52/G52,"") -> 7528.2 | I52: 34 | J52: =IF(AND(G52<>"",G52<>0),E52/G52,"") -> 1.4 | N52: =IF(AND(I52<>"",I52<>0),G52/I52,"") -> 0.14705882 | O52: =D52/P52 -> 0.23657415 | P52: =$I$8*V52*W52/SUMPRODUCT($W$25:$W$55,$V$25:$V$55) -> 159108.67 | Q52: =$I$9*V52*W52/SUMPRODUCT($W$25:$W$55,$V$25:$V$55) -> 30.597822 | R52: =IF($I$12="","",Q52/$I$12) -> 15.772073 | S52: =IF(W52<>"",IF(D52<>"",D52,($I$8-SUM($S$25:S51))*V52*W52/SUMPRODUCT($W52:$W$55,$V52:$V$55)),"") -> 37641 | T52: =IF(W52<>"",IF(E52<>"",E52,($I$9-SUM($T$25:T51))*V52*W52/SUMPRODUCT($W52:$W$55,$V52:$V$55)),"") -> 7 | U52: =IF(W52<>"",IF($I$12<>"",IF(G52<>"",G52,($I$9/$I$12-SUM($U$25:U51))*V52*W52/SUMPRODUCT($W52:$W$55,$V52:$V$55)),""),"") -> 5 | V52: 0.95 | W52: 0.97588915
A53: Рогалевич,Уразгильдеева | B53: 45806 | C53: чт | D53: 71964 | E53: 18 | F53: =IF(AND(E53<>"",E53<>0),D53/E53,"") -> 3998 | G53: 10 | H53: =IF(AND(G53<>"",G53<>0),D53/G53,"") -> 7196.4 | I53: 40 | J53: =IF(AND(G53<>"",G53<>0),E53/G53,"") -> 1.8 | N53: =IF(AND(I53<>"",I53<>0),G53/I53,"") -> 0.25 | O53: =D53/P53 -> 0.45229464 | P53: =$I$8*V53*W53/SUMPRODUCT($W$25:$W$55,$V$25:$V$55) -> 159108.67 | Q53: =$I$9*V53*W53/SUMPRODUCT($W$25:$W$55,$V$25:$V$55) -> 30.597822 | R53: =IF($I$12="","",Q53/$I$12) -> 15.772073 | S53: =IF(W53<>"",IF(D53<>"",D53,($I$8-SUM($S$25:S52))*V53*W53/SUMPRODUCT($W53:$W$55,$V53:$V$55)),"") -> 71964 | T53: =IF(W53<>"",IF(E53<>"",E53,($I$9-SUM($T$25:T52))*V53*W53/SUMPRODUCT($W53:$W$55,$V53:$V$55)),"") -> 18 | U53: =IF(W53<>"",IF($I$12<>"",IF(G53<>"",G53,($I$9/$I$12-SUM($U$25:U52))*V53*W53/SUMPRODUCT($W53:$W$55,$V53:$V$55)),""),"") -> 10 | V53: 0.95 | W53: 0.97588915
A54: Рогалевич,Уразгильдеева | B54: 45807 | C54: пт | D54: =33433+27238+6203 -> 66874 | E54: 16 | F54: =IF(AND(E54<>"",E54<>0),D54/E54,"") -> 4179.625 | G54: 7 | H54: =IF(AND(G54<>"",G54<>0),D54/G54,"") -> 9553.4286 | I54: 34 | J54: =IF(AND(G54<>"",G54<>0),E54/G54,"") -> 2.2857143 | L54: 6203 | N54: =IF(AND(I54<>"",I54<>0),G54/I54,"") -> 0.20588235 | O54: =D54/P54 -> 0.38966154 | P54: =$I$8*V54*W54/SUMPRODUCT($W$25:$W$55,$V$25:$V$55) -> 171620.74 | Q54: =$I$9*V54*W54/SUMPRODUCT($W$25:$W$55,$V$25:$V$55) -> 33.003988 | R54: =IF($I$12="","",Q54/$I$12) -> 17.012365 | S54: =IF(W54<>"",IF(D54<>"",D54,($I$8-SUM($S$25:S53))*V54*W54/SUMPRODUCT($W54:$W$55,$V54:$V$55)),"") -> 66874 | T54: =IF(W54<>"",IF(E54<>"",E54,($I$9-SUM($T$25:T53))*V54*W54/SUMPRODUCT($W54:$W$55,$V54:$V$55)),"") -> 16 | U54: =IF(W54<>"",IF($I$12<>"",IF(G54<>"",G54,($I$9/$I$12-SUM($U$25:U53))*V54*W54/SUMPRODUCT($W54:$W$55,$V54:$V$55)),""),"") -> 7 | V54: 1 | W54: 1
A55: Рогалевич,Уразгильдеева,Вафина | B55: 45808 | C55: сб | D55: =83666+41227 -> 124893 | E55: 19 | F55: =IF(AND(E55<>"",E55<>0),D55/E55,"") -> 6573.3158 | G55: 12 | H55: =IF(AND(G55<>"",G55<>0),D55/G55,"") -> 10407.75 | I55: 60 | J55: =IF(AND(G55<>"",G55<>0),E55/G55,"") -> 1.5833333 | K55: 39974 | L55: 41227 | N55: =IF(AND(I55<>"",I55<>0),G55/I55,"") -> 0.2 | O55: =D55/P55 -> 0.60142706 | P55: =$I$8*V55*W55/SUMPRODUCT($W$25:$W$55,$V$25:$V$55) -> 207661.09 | Q55: =$I$9*V55*W55/SUMPRODUCT($W$25:$W$55,$V$25:$V$55) -> 39.934825 | R55: =IF($I$12="","",Q55/$I$12) -> 20.584962 | S55: =IF(W55<>"",IF(D55<>"",D55,($I$8-SUM($S$25:S54))*V55*W55/SUMPRODUCT($W55:$W$55,$V55:$V$55)),"") -> 124893 | T55: =IF(W55<>"",IF(E55<>"",E55,($I$9-SUM($T$25:T54))*V55*W55/SUMPRODUCT($W55:$W$55,$V55:$V$55)),0) -> 19 | U55: =IF(W55<>"",IF($I$12<>"",IF(G55<>"",G55,($I$9/$I$12-SUM($U$25:U54))*V55*W55/SUMPRODUCT($W55:$W$55,$V55:$V$55)),""),"") -> 12 | V55: 1.1 | W55: 1.1
B56: итого | D56: =SUM(D25:D55) -> 2784032 | E56: =SUM(E25:E55) -> 493 | F56: =IF(AND(E56<>"", E56<>0), D56/E56, "") -> 5647.1237 | G56: =SUM(G25:G55) -> 274 | H56: =IF(AND(G56<>"", G56<>0), D56/G56, "") -> 10160.701 | I56: =SUM(I25:I55) -> 1195 | J56: =E56/G56 -> 1.7992701 | K56: =SUM(K25:K55) -> 535497 | L56: =SUM(L25:L55) -> 573273 | M56: =SUM(M25:M55) -> 0 | N56: =IF(AND(I56<>"", I56<>0), G56/I56, "") -> 0.2292887 | O56: =D56/P56 -> 0.58075468 | P56: =SUM(P25:P55) -> 4793817.6 | Q56: =SUM(Q25:Q55) -> 921.888 | R56: =SUM(R25:R55) -> 475.2 | S56: =SUM(S25:S55) -> 2784032 | T56: =SUM(T25:T55) -> 493 | U56: =SUM(U25:U55) -> 274
D57: =SUMIF(D25:D55,"",P25:P55)+D56 -> 2784032 | I57: =I56/J14 -> 38.548387
D58: ='Рогалевич И. Е.'!J8+'Уразгильдеева Е. Р.'!J8+'Вафина Л. Ф.'!J8+'Доп сотрудник'!J8 -> 2784032

Sheet Св. по пок.
A2: Показатель | D2: ='Ялта, Ленина, 18'!I3 -> ул. Набережная Ленина, 18 | G2: =График!B29 -> Рогалевич Ирина | J2: =График!B28 -> Уразгильдеева Екатерина | M2: =График!B27 -> Вафина Ляйсан
D3: Факт | F3: Прогноз | G3: Факт | I3: Прогноз | J3: Факт | L3: Прогноз | M3: Факт | O3: Прогноз
A4: Выручка | D4: ='Ялта, Ленина, 18'!K8 -> 0.58075468 | E4: ='Ялта, Ленина, 18'!J8 -> 2784032 | F4: ='Ялта, Ленина, 18'!M8 -> 0.58075468 | G4: ='Рогалевич И. Е.'!K8 -> 0.72556134 | H4: ='Рогалевич И. Е.'!J8 -> 1358537 | I4: ='Рогалевич И. Е.'!M8 -> 0.75339644 | J4: ='Уразгильдеева Е. Р.'!K8 -> 0.4785407 | K4: ='Уразгильдеева Е. Р.'!J8 -> 717981 | L4: ='Уразгильдеева Е. Р.'!M8 -> 0.4785407 | M4: ='Вафина Л. Ф.'!K8 -> 0.49787481 | N4: ='Вафина Л. Ф.'!J8 -> 707514 | O4: ='Вафина Л. Ф.'!M8 -> 0.52642268
A5: Кол-во изделий | D5: ='Ялта, Ленина, 18'!K9 -> 0.53477212 | E5: ='Ялта, Ленина, 18'!J9 -> 493 | F5: ='Ялта, Ленина, 18'!M9 -> 0.53477212 | G5: ='Рогалевич И. Е.'!K9 -> 0.63319993 | H5: ='Рогалевич И. Е.'!J9 -> 228 | I5: ='Рогалевич И. Е.'!M9 -> 0.68372169 | J5: ='Уразгильдеева Е. Р.'!K9 -> 0.46442338 | K5: ='Уразгильдеева Е. Р.'!J9 -> 134 | L5: ='Уразгильдеева Е. Р.'!M9 -> 0.46442338 | M5: ='Вафина Л. Ф.'!K9 -> 0.48301698 | N5: ='Вафина Л. Ф.'!J9 -> 132 | O5: ='Вафина Л. Ф.'!M9 -> 0.48301698
A6: Средний чек | D6: ='Ялта, Ленина, 18'!K10 -> 1.0072067 | E6: ='Ялта, Ленина, 18'!J10 -> 10160.701 | F6: ='Ялта, Ленина, 18'!M10 -> 1.0072067 | G6: ='Рогалевич И. Е.'!K10 -> 1.0603828 | H6: ='Рогалевич И. Е.'!J10 -> 10697.142 | I6: ='Рогалевич И. Е.'!M10 -> 1.0603828 | J6: ='Уразгильдеева Е. Р.'!K10 -> 0.88964735 | K6: ='Уразгильдеева Е. Р.'!J10 -> 8974.7625 | L6: ='Уразгильдеева Е. Р.'!M10 -> 0.88964735 | M6: ='Вафина Л. Ф.'!K10 -> 1.016438 | N6: ='Вафина Л. Ф.'!J10 -> 10253.826 | O6: ='Вафина Л. Ф.'!M10 -> 1.016438
A7: Средняя стоимость изделия | D7: ='Ялта, Ленина, 18'!K11 -> 1.0859853 | E7: ='Ялта, Ленина, 18'!J11 -> 5647.1237 | F7: ='Ялта, Ленина, 18'!M11 -> 1.0859853 | G7: ='Рогалевич И. Е.'!K11 -> 1.1458645 | H7: ='Рогалевич И. Е.'!J11 -> 5958.4956 | I7: ='Рогалевич И. Е.'!M11 -> 1.1019051 | J7: ='Уразгильдеева Е. Р.'!K11 -> 1.0303975 | K7: ='Уразгильдеева Е. Р.'!J11 -> 5358.0672 | L7: ='Уразгильдеева Е. Р.'!M11 -> 1.0303975 | M7: ='Вафина Л. Ф.'!K11 -> 1.0307605 | N7: ='Вафина Л. Ф.'!J11 -> 5359.9545 | O7: ='Вафина Л. Ф.'!M11 -> 1.0898637
A8: Длина чека | D8: ='Ялта, Ленина, 18'!K12 -> 0.9274588 | E8: ='Ялта, Ленина, 18'!J12 -> 1.7992701 | F8: ='Ялта, Ленина, 18'!M12 -> 0.9274588 | G8: ='Рогалевич И. Е.'!K12 -> 0.92539979 | H8: ='Рогалевич И. Е.'!J12 -> 1.7952756 | I8: ='Рогалевич И. Е.'!M12 -> 0.92539979 | J8: ='Уразгильдеева Е. Р.'!K12 -> 0.86340206 | K8: ='Уразгильдеева Е. Р.'!J12 -> 1.675 | L8: ='Уразгильдеева Е. Р.'!M12 -> 0.86340206 | M8: ='Вафина Л. Ф.'!K12 -> 0.98610489 | N8: ='Вафина Л. Ф.'!J12 -> 1.9130435 | O8: ='Вафина Л. Ф.'!M12 -> 0.98610489
A9: Кол-во чеков | D9: ='Ялта, Ленина, 18'!K13 -> 0.57659933 | E9: ='Ялта, Ленина, 18'!J13 -> 274 | F9: ='Ялта, Ленина, 18'!M13 -> 0.57659933 | G9: ='Рогалевич И. Е.'!K13 -> 0.68424473 | H9: ='Рогалевич И. Е.'!J13 -> 127 | I9: ='Рогалевич И. Е.'!M13 -> 0.73883925 | J9: ='Уразгильдеева Е. Р.'!K13 -> 0.53789932 | K9: ='Уразгильдеева Е. Р.'!J13 -> 80 | L9: ='Уразгильдеева Е. Р.'!M13 -> 0.53789932 | M9: ='Вафина Л. Ф.'!K13 -> 0.48982312 | N9: ='Вафина Л. Ф.'!J13 -> 69 | O9: ='Вафина Л. Ф.'!M13 -> 0.48982312
A10: Кол-во смен план/отработано | D10: ='Ялта, Ленина, 18'!K14 -> 1 | E10: ='Ялта, Ленина, 18'!J14 -> 31 | G10: ='Рогалевич И. Е.'!K14 -> 1 | H10: ='Рогалевич И. Е.'!J14 -> 28 | J10: ='Уразгильдеева Е. Р.'!K14 -> 1 | K10: ='Уразгильдеева Е. Р.'!J14 -> 20 | M10: ='Вафина Л. Ф.'!K14 -> 1 | N10: ='Вафина Л. Ф.'!J14 -> 19
A11: Средние продажи в смену | D11: ='Ялта, Ленина, 18'!K15 -> 0.58075468 | E11: ='Ялта, Ленина, 18'!J15 -> 89807.484 | F11: ='Ялта, Ленина, 18'!M15 -> 0.58075468 | G11: ='Рогалевич И. Е.'!K15 -> 0.31375715 | H11: ='Рогалевич И. Е.'!J15 -> 48519.179 | I11: ='Рогалевич И. Е.'!M15 -> 0.31375715 | J11: ='Уразгильдеева Е. Р.'!K15 -> 0.23214704 | K11: ='Уразгильдеева Е. Р.'!J15 -> 35899.05 | L11: ='Уразгильдеева Е. Р.'!M15 -> 0.23214704 | M11: ='Вафина Л. Ф.'!K15 -> 0.24080285 | N11: ='Вафина Л. Ф.'!J15 -> 37237.579 | O11: ='Вафина Л. Ф.'!M15 -> 0.24080285
A12: Трафик | D12: ='Ялта, Ленина, 18'!K17 -> 0.55324074 | E12: ='Ялта, Ленина, 18'!J17 -> 1195 | F12: ='Ялта, Ленина, 18'!M17 -> 0.55324074 | G12: ='Рогалевич И. Е.'!K17 -> 0.61872964 | H12: ='Рогалевич И. Е.'!J17 -> 522 | I12: ='Рогалевич И. Е.'!M17 -> 0.61872964 | J12: ='Уразгильдеева Е. Р.'!K17 -> 0.5310411 | K12: ='Уразгильдеева Е. Р.'!J17 -> 359 | L12: ='Уразгильдеева Е. Р.'!M17 -> 0.5310411 | M12: ='Вафина Л. Ф.'!K17 -> 0.48882928 | N12: ='Вафина Л. Ф.'!J17 -> 313 | O12: ='Вафина Л. Ф.'!M17 -> 0.48882928
A13: UNOde50 | D13: ='Ялта, Ленина, 18'!S19 -> 1.1156188 | E13: ='Ялта, Ленина, 18'!T18 -> 535497 | F13: ='Ялта, Ленина, 18'!T19 -> 1.1156188 | G13: ='Рогалевич И. Е.'!S19 -> 1.3200064 | H13: ='Рогалевич И. Е.'!T18 -> 247476 | I13: ='Рогалевич И. Е.'!T19 -> 1.3200064 | J13: ='Уразгильдеева Е. Р.'!S19 -> 0.98598135 | K13: ='Уразгильдеева Е. Р.'!T18 -> 148123 | L13: ='Уразгильдеева Е. Р.'!T19 -> 0.98598135 | M13: ='Вафина Л. Ф.'!S19 -> 0.85346078 | N13: ='Вафина Л. Ф.'!T18 -> 121439 | O13: ='Вафина Л. Ф.'!T19 -> 0.85346078
A14: IS | D14: ='Ялта, Ленина, 18'!S13 -> 0.84304853 | E14: ='Ялта, Ленина, 18'!T12 -> 573273 | F14: ='Ялта, Ленина, 18'!T13 -> 0.84304853 | G14: ='Рогалевич И. Е.'!S13 -> 1.0983443 | H14: ='Рогалевич И. Е.'!T12 -> 291718 | I14: ='Рогалевич И. Е.'!T13 -> 1.0983443 | J14: ='Уразгильдеева Е. Р.'!S13 -> 0.60182941 | K14: ='Уразгильдеева Е. Р.'!T12 -> 128084 | L14: ='Уразгильдеева Е. Р.'!T13 -> 0.60182941 | M14: ='Вафина Л. Ф.'!S13 -> 0.76134944 | N14: ='Вафина Л. Ф.'!T12 -> 153471 | O14: ='Вафина Л. Ф.'!T13 -> 0.76134944
A15: Отклонение от плана | D15: ='Ялта, Ленина, 18'!J16 -> -2009785.6 | G15: ='Рогалевич И. Е.'!N8 -> -461739.13 | J15: ='Уразгильдеева Е. Р.'!N8 -> -782374.13 | M15: ='Вафина Л. Ф.'!N8 -> -672985.6
A37: Показатель | D37: ='Ялта, Ленина, 18'!I38 -> 20 | G37: =График!#REF! -> #REF! | J37: =График!#REF! -> #REF! | M37: =График!#REF! -> #REF!
D38: Факт | F38: Прогноз | G38: Факт | I38: Прогноз | J38: Факт | L38: Прогноз | M38: Факт | O38: Прогноз
A39: Выручка | D39: ='Ялта, Ленина, 18'!K43 -> 0 | E39: ='Ялта, Ленина, 18'!J43 -> 2 | F39: ='Ялта, Ленина, 18'!M43 -> 0 | G39: ='Рогалевич И. Е.'!K43 -> 0 | H39: ='Рогалевич И. Е.'!J43 -> 1.3333333 | I39: ='Рогалевич И. Е.'!M43 -> 0 | J39: ='Уразгильдеева Е. Р.'!K43 -> 0 | K39: ='Уразгильдеева Е. Р.'!J43 -> 1.5 | L39: ='Уразгильдеева Е. Р.'!M43 -> 0 | M39: ='Вафина Л. Ф.'!K43 -> 0 | N39: ='Вафина Л. Ф.'!J43 -> 1 | O39: ='Вафина Л. Ф.'!M43 -> 0
A40: Кол-во изделий | D40: ='Ялта, Ленина, 18'!K44 -> 0 | E40: ='Ялта, Ленина, 18'!J44 -> 2 | F40: ='Ялта, Ленина, 18'!M44 -> 0 | G40: ='Рогалевич И. Е.'!K44 -> 0 | H40: ='Рогалевич И. Е.'!J44 -> 1.5 | I40: ='Рогалевич И. Е.'!M44 -> 0 | J40: ='Уразгильдеева Е. Р.'!K44 -> 16991 | K40: ='Уразгильдеева Е. Р.'!J44 -> 1.8333333 | L40: ='Уразгильдеева Е. Р.'!M44 -> 0 | M40: ='Вафина Л. Ф.'!K44 -> 0 | N40: ='Вафина Л. Ф.'!J44 | O40: ='Вафина Л. Ф.'!M44 -> 0
A41: Средний чек | D41: ='Ялта, Ленина, 18'!K45 -> 0 | E41: ='Ялта, Ленина, 18'!J45 -> 1.3333333 | F41: ='Ялта, Ленина, 18'!M45 -> 0 | G41: ='Рогалевич И. Е.'!K45 -> 0 | H41: ='Рогалевич И. Е.'!J45 -> 1 | I41: ='Рогалевич И. Е.'!M45 -> 0 | J41: ='Уразгильдеева Е. Р.'!K45 -> 0 | K41: ='Уразгильдеева Е. Р.'!J45 | L41: ='Уразгильдеева Е. Р.'!M45 -> 0 | M41: ='Вафина Л. Ф.'!K45 -> 0 | N41: ='Вафина Л. Ф.'!J45 -> 1 | O41: ='Вафина Л. Ф.'!M45 -> 0
A42: Средняя стоимость изделия | D42: ='Ялта, Ленина, 18'!K46 -> 0 | E42: ='Ялта, Ленина, 18'!J46 -> 2 | F42: ='Ялта, Ленина, 18'!M46 -> 0 | G42: ='Рогалевич И. Е.'!K46 -> 25684 | H42: ='Рогалевич И. Е.'!J46 -> 1.6 | I42: ='Рогалевич И. Е.'!M46 -> 0 | J42: ='Уразгильдеева Е. Р.'!K46 -> 0 | K42: ='Уразгильдеева Е. Р.'!J46 | L42: ='Уразгильдеева Е. Р.'!M46 -> 0 | M42: ='Вафина Л. Ф.'!K46 -> 0 | N42: ='Вафина Л. Ф.'!J46 -> 2 | O42: ='Вафина Л. Ф.'!M46 -> 0
A43: Длина чека | D43: ='Ялта, Ленина, 18'!K47 -> 0 | E43: ='Ялта, Ленина, 18'!J47 -> 1 | F43: ='Ялта, Ленина, 18'!M47 -> 0 | G43: ='Рогалевич И. Е.'!K47 -> 8993 | H43: ='Рогалевич И. Е.'!J47 -> 1 | I43: ='Рогалевич И. Е.'!M47 -> 0 | J43: ='Уразгильдеева Е. Р.'!K47 -> 0 | K43: ='Уразгильдеева Е. Р.'!J47 | L43: ='Уразгильдеева Е. Р.'!M47 -> 0 | M43: ='Вафина Л. Ф.'!K47 -> 0 | N43: ='Вафина Л. Ф.'!J47 -> 2 | O43: ='Вафина Л. Ф.'!M47 -> 0
A44: Кол-во чеков | D44: ='Ялта, Ленина, 18'!K48 -> 25684 | E44: ='Ялта, Ленина, 18'!J48 -> 1.5384615 | F44: ='Ялта, Ленина, 18'!M48 -> 0 | G44: ='Рогалевич И. Е.'!K48 -> 31985 | H44: ='Рогалевич И. Е.'!J48 -> 1.5714286 | I44: ='Рогалевич И. Е.'!M48 -> 0 | J44: ='Уразгильдеева Е. Р.'!K48 -> 0 | K44: ='Уразгильдеева Е. Р.'!J48 | L44: ='Уразгильдеева Е. Р.'!M48 -> 0 | M44: ='Вафина Л. Ф.'!K48 -> 121439 | N44: ='Вафина Л. Ф.'!J48 -> 1.9130435 | O44: ='Вафина Л. Ф.'!M48 -> 0
A45: Кол-во смен план/отработано | D45: ='Ялта, Ленина, 18'!K49 -> 8993 | E45: ='Ялта, Ленина, 18'!J49 -> 1 | G45: ='Рогалевич И. Е.'!K49 -> 0 | H45: ='Рогалевич И. Е.'!J49 -> 2 | J45: ='Уразгильдеева Е. Р.'!K49 -> 0 | K45: ='Уразгильдеева Е. Р.'!J49 -> 3 | M45: ='Вафина Л. Ф.'!K49 -> 0 | N45: ='Вафина Л. Ф.'!J49 -> 0
A46: Средние продажи в смену | D46: ='Ялта, Ленина, 18'!K50 -> 0 | E46: ='Ялта, Ленина, 18'!J50 -> 1.25 | F46: ='Ялта, Ленина, 18'!M50 -> 0 | G46: ='Рогалевич И. Е.'!K50 -> 0 | H46: ='Рогалевич И. Е.'!J50 -> 2.4 | I46: ='Рогалевич И. Е.'!M50 -> 0 | J46: ='Уразгильдеева Е. Р.'!K50 -> 148123 | K46: ='Уразгильдеева Е. Р.'!J50 -> 1.675 | L46: ='Уразгильдеева Е. Р.'!M50 -> 0 | M46: ='Вафина Л. Ф.'!K50 -> 0 | N46: ='Вафина Л. Ф.'!J50 -> 0 | O46: ='Вафина Л. Ф.'!M50 -> 0
A47: Трафик | D47: ='Ялта, Ленина, 18'!K52 -> 0 | E47: ='Ялта, Ленина, 18'!J52 -> 1.4 | F47: ='Ялта, Ленина, 18'!M52 -> 0 | G47: ='Рогалевич И. Е.'!K52 -> 0 | H47: ='Рогалевич И. Е.'!J52 -> 1.6666667 | I47: ='Рогалевич И. Е.'!M52 -> 0 | J47: ='Уразгильдеева Е. Р.'!K52 -> 0 | K47: ='Уразгильдеева Е. Р.'!J52 -> 0 | L47: ='Уразгильдеева Е. Р.'!M52 -> 0 | M47: ='Вафина Л. Ф.'!K52 -> 0 | N47: ='Вафина Л. Ф.'!J52 -> 0 | O47: ='Вафина Л. Ф.'!M52 -> 0
A48: UNOde50 | D48: ='Ялта, Ленина, 18'!S54 -> 66874 | E48: ='Ялта, Ленина, 18'!T53 -> 18 | F48: ='Ялта, Ленина, 18'!T54 -> 16 | G48: ='Рогалевич И. Е.'!S54 -> 1872394.4 | H48: ='Рогалевич И. Е.'!T53 -> 136.07585 | I48: ='Рогалевич И. Е.'!T54 -> 224 | J48: ='Уразгильдеева Е. Р.'!S54 -> 0 | K48: ='Уразгильдеева Е. Р.'!T53 -> 0 | L48: ='Уразгильдеева Е. Р.'!T54 -> 0 | M48: ='Вафина Л. Ф.'!S54 -> 0 | N48: ='Вафина Л. Ф.'!T53 -> 0 | O48: ='Вафина Л. Ф.'!T54 -> 0
A49: IS | D49: ='Ялта, Ленина, 18'!S48 -> 123588 | E49: ='Ялта, Ленина, 18'!T47 -> 4 | F49: ='Ялта, Ленина, 18'!T48 -> 20 | G49: ='Рогалевич И. Е.'!S48 -> 93287 | H49: ='Рогалевич И. Е.'!T47 -> 4 | I49: ='Рогалевич И. Е.'!T48 -> 11 | J49: ='Уразгильдеева Е. Р.'!S48 | K49: ='Уразгильдеева Е. Р.'!T47 | L49: ='Уразгильдеева Е. Р.'!T48 | M49: ='Вафина Л. Ф.'!S48 -> 659093 | N49: ='Вафина Л. Ф.'!T47 | O49: ='Вафина Л. Ф.'!T48 -> 127
A50: Отклонение от плана | D50: ='Ялта, Ленина, 18'!J51 -> 1.7777778 | G50: ='Рогалевич И. Е.'!N43 -> 0.4 | J50: ='Уразгильдеева Е. Р.'!N43 -> 0.35294118 | M50: ='Вафина Л. Ф.'!N43 -> 0.15

Sheet План на день
A1: Выручка | D1: 207661
A2: Кол-во изделий | D2: =D1/D4 -> 39.934808
A3: Средний чек | D3: =D4*D5 -> 10088
A4: Средняя стоимость изделия | D4: ='Ялта, Ленина, 18'!I11 -> 5200
A5: Длина чека | D5: ='Ялта, Ленина, 18'!I12 -> 1.94
A6: Кол-во чеков | D6: =IF(D5<>0,D2/D5,"") -> 20.584952
A7: Конверсия | D7: ='Ялта, Ленина, 18'!I20 -> 0.22
A8: IS | D8: =('Ялта, Ленина, 18'!S12-'Ялта, Ленина, 18'!T12)/('Ялта, Ленина, 18'!I14-'Ялта, Ленина, 18'!J14) -> #DIV/0!
A9: UNOde50 | D9: =('Ялта, Ленина, 18'!S18-'Ялта, Ленина, 18'!T18)/('Ялта, Ленина, 18'!I14-'Ялта, Ленина, 18'!J14) -> #DIV/0!

Sheet Рогалевич И. Е.
B1: =TODAY()-1 -> 46171
B2: (отчетная дата) | J2: ЕЖЕДНЕВНЫЙ ОТЧЕТ О ПРОДАЖАХ
B3: Осталось до выполнения плана!!! | J3: =График!B29 -> Рогалевич Ирина
C4: =I8-D54 -> 513857.41 | E4: =IF(I8<>0,C4/I8,0) -> 0.27443866
F6: Целевые показатели
F7: Показатель | I7: План | J7: Факт | K7: % выполнения | L7: Прогноз выполнения | M7: % выполнения по прогнозу | N7: Отклонение | O7: Факт аналогичного месяца прошлого года | P7: Отклонение LFL
F8: Выручка | I8: ='Ялта, Ленина, 18'!I8/График!AJ31*График!AJ29 -> 1872394.4 | J8: =D54 -> 1358537 | K8: =IF(AND(I8<>"",I8<>0,J8<>""),J8/I8,"") -> 0.72556134 | L8: =IF(SUMIF($D$25:$D$53,">=0",$P$25:$P$53)<>0,I8*D54/SUMIF($D$25:$D$53,">=0",$P$25:$P$53),0) -> 1410655.3 | M8: =IF(AND(I8<>"",I8<>0,L8<>"",L8<>0),L8/I8,"") -> 0.75339644 | N8: =IF(AND(J8<>0,J8<>"",I8<>0,I8<>""),L8-I8,"") -> -461739.13 | P8: =IF(AND(O8<>"",O8<>0,L8<>"",L8<>0),-O8+L8,"") | Q8: =IF(AND(P8<>"",P8<>0,O8<>0,O8<>""),P8/O8,"")
F9: Кол-во изделий | I9: =I8/I11 -> 360.07585 | J9: =E54 -> 228 | K9: =IF(AND(I9<>"",I9<>0,J9<>""),J9/I9,"") -> 0.63319993 | L9: =IF(SUMIF($E$25:$E$51,">=0",$Q$25:$Q$51)<>0,I9*E54/SUMIF($E$25:$E$51,">=0",$Q$25:$Q$51),0) -> 246.19167 | M9: =IF(AND(I9<>"",I9<>0,L9<>"",L9<>0),L9/I9,"") -> 0.68372169 | N9: =IF(AND(J9<>0,J9<>"",I9<>0,I9<>""),L9-I9,"") -> -113.88418 | O9: =O8/O11 -> #DIV/0! | P9: =IF(AND(O9<>"",O9<>0,L9<>"",L9<>0),-O9+L9,"") -> #DIV/0! | Q9: =IF(AND(P9<>"",P9<>0,O9<>0,O9<>""),P9/O9,"") -> #DIV/0!
F10: Средний чек | I10: =I11*I12 -> 10088 | J10: =H54 -> 10697.142 | K10: =IF(AND(I10<>"",I10<>0,J10<>""),J10/I10,"") -> 1.0603828 | L10: =J10 -> 10697.142 | M10: =IF(AND(I10<>"",I10<>0,L10<>"",L10<>0),L10/I10,"") -> 1.0603828 | N10: =IF(AND(J10<>0,J10<>"",I10<>0,I10<>""),L10-I10,"") -> 609.14173 | O10: =O11*O12 -> 0 | P10: =IF(AND(O10<>"",O10<>0,L10<>"",L10<>0),-O10+L10,"") | Q10: =IF(AND(P10<>"",P10<>0,O10<>0,O10<>""),P10/O10,"") | S10: IS
F11: Средняя стоимость изделия | I11: ='Ялта, Ленина, 18'!I11 -> 5200 | J11: =F54 -> 5958.4956 | K11: =IF(AND(I11<>"",I11<>0,J11<>""),J11/I11,"") -> 1.1458645 | L11: =IF(L9>0,L8/L9,"") -> 5729.9067 | M11: =IF(AND(I11<>"",I11<>0,L11<>"",L11<>0),L11/I11,"") -> 1.1019051 | N11: =IF(AND(J11<>0,J11<>"",I11<>0,I11<>""),L11-I11,"") -> 529.90669 | P11: =IF(AND(O11<>"",O11<>0,L11<>"",L11<>0),-O11+L11,"") | Q11: =IF(AND(P11<>"",P11<>0,O11<>0,O11<>""),P11/O11,"")
F12: Длина чека | I12: ='Ялта, Ленина, 18'!I12 -> 1.94 | J12: =J54 -> 1.7952756 | K12: =IF(AND(I12<>"",I12<>0,J12<>""),J12/I12,"") -> 0.92539979 | L12: =J12 -> 1.7952756 | M12: =IF(AND(I12<>"",I12<>0,L12<>"",L12<>0),L12/I12,"") -> 0.92539979 | N12: =IF(AND(J12<>0,J12<>"",I12<>0,I12<>""),L12-I12,"") -> -0.14472441 | P12: =IF(AND(O12<>"",O12<>0,L12<>"",L12<>0),-O12+L12,"") | Q12: =IF(AND(P12<>"",P12<>0,O12<>0,O12<>""),P12/O12,"") | S12: ='Ялта, Ленина, 18'!S12*График!AJ29/График!AJ31 -> 265597.96 | T12: =L54 -> 291718
F13: Кол-во чеков | I13: =IF(I12<>0,I9/I12,"") -> 185.60611 | J13: =G54 -> 127 | K13: =IF(AND(I13<>"",I13<>0,J13<>""),J13/I13,"") -> 0.68424473 | L13: =IF(SUMIF($G$25:$G$51,">=0",$R$25:$R$51)<>0,I13*G54/SUMIF($G$25:$G$51,">=0",$R$25:$R$51),"") -> 137.13308 | M13: =IF(AND(I13<>"",I13<>0,L13<>"",L13<>0),L13/I13,"") -> 0.73883925 | N13: =IF(AND(J13<>0,J13<>"",I13<>0,I13<>""),L13-I13,"") -> -48.47303 | P13: =IF(AND(O13<>"",O13<>0,L13<>"",L13<>0),-O13+L13,"") | Q13: =IF(AND(P13<>"",P13<>0,O13<>0,O13<>""),P13/O13,"") | S13: =T12/S12 -> 1.0983443 | T13: =S13/J14*I14 -> 1.0983443
F14: Кол-во смен план/отработано | I14: =График!AI29 -> 28 | J14: 28 | K14: =IF(AND(I14<>"",I14<>0,J14<>""),J14/I14,"") -> 1 | L14: =I14 -> 28 | M14: =IF(AND(I14<>"",I14<>0,L14<>"",L14<>0),L14/I14,"") -> 1 | N14: =IF(AND(J14<>0,J14<>"",I14<>0,I14<>""),L14-I14,"") -> 0 | P14: =IF(AND(O14<>"",O14<>0,L14<>"",L14<>0),-O14+L14,"") | Q14: =IF(AND(P14<>"",P14<>0,O14<>0,O14<>""),P14/O14,"")
F15: Средние продажи в смену | I15: ='Ялта, Ленина, 18'!I15 -> 154639.28 | J15: =J8/J14 -> 48519.179 | K15: =IF(AND(I15<>"",I15<>0,J15<>""),J15/I15,"") -> 0.31375715 | L15: =J15 -> 48519.179 | M15: =IF(AND(I15<>"",I15<>0,L15<>"",L15<>0),L15/I15,"") -> 0.31375715 | N15: =IF(AND(J15<>0,J15<>"",I15<>0,I15<>""),L15-I15,"") -> -106120.1 | P15: =IF(AND(O15<>"",O15<>0,L15<>"",L15<>0),-O15+L15,"") | Q15: =IF(AND(P15<>"",P15<>0,O15<>0,O15<>""),P15/O15,"")
F16: Отставание/Перевыполнение | J16: =J8-I15*J14 -> -2971362.8 | K16: =IF(AND(I16<>"",I16<>0,J16<>""),J16/I16,"") | L16: =J16 -> -2971362.8 | M16: =IF(AND(I16<>"",I16<>0,L16<>"",L16<>0),L16/I16,"") | N16: =IF(AND(J16<>0,J16<>"",I16<>0,I16<>""),L16-I16,"") | P16: =IF(AND(O16<>"",O16<>0,L16<>"",L16<>0),-O16+L16,"") | Q16: =IF(AND(P16<>"",P16<>0,O16<>0,O16<>""),P16/O16,"") | S16: UNOde50
F17: Трафик | I17: ='Ялта, Ленина, 18'!I17/График!AJ31*График!AJ29 -> 843.66412 | J17: =I54 -> 522 | K17: =IF(AND(I17<>"",I17<>0,J17<>""),J17/I17,"") -> 0.61872964 | L17: =J17/J14*I14 -> 522 | M17: =IF(AND(I17<>"",I17<>0,L17<>"",L17<>0),L17/I17,"") -> 0.61872964 | N17: =IF(AND(J17<>0,J17<>"",I17<>0,I17<>""),L17-I17,"") -> -321.66412 | P17: =IF(AND(O17<>"",O17<>0,L17<>"",L17<>0),-O17+L17,"") | Q17: =IF(AND(P17<>"",P17<>0,O17<>0,O17<>""),P17/O17,"")
K18: =IF(AND(I18<>"",I18<>0,J18<>""),J18/I18,"") | L18: =J18 -> 0 | M18: =IF(AND(I18<>"",I18<>0,L18<>"",L18<>0),L18/I18,"") | N18: =IF(AND(J18<>0,J18<>"",I18<>0,I18<>""),L18-I18,"") | O18: 0 | P18: =IF(AND(O18<>"",O18<>0,L18<>"",L18<>0),-O18+L18,"") | Q18: =IF(AND(P18<>"",P18<>0,O18<>0,O18<>""),P18/O18,"") | S18: ='Ялта, Ленина, 18'!S18*График!AJ29/График!AJ31 -> 187480.92 | T18: =K54 -> 247476
J19: =M54 -> 0 | K19: =IF(AND(I19<>"",I19<>0,J19<>""),J19/I19,"") | L19: =J19 -> 0 | M19: =IF(AND(I19<>"",I19<>0,L19<>"",L19<>0),L19/I19,"") | N19: =IF(AND(J19<>0,J19<>"",I19<>0,I19<>""),L19-I19,"") | O19: 0 | P19: =IF(AND(O19<>"",O19<>0,L19<>"",L19<>0),-O19+L19,"") | Q19: =IF(AND(P19<>"",P19<>0,O19<>0,O19<>""),P19/O19,"") | S19: =T18/S18 -> 1.3200064 | T19: =S19/J14*I14 -> 1.3200064
F20: Конверсия план/факт | I20: ='Ялта, Ленина, 18'!I20 -> 0.22 | J20: =N54 -> 0.24329502 | K20: =J20/I20 -> 1.1058865 | L20: =IF(AND(K8<>0,I14<>0,I54<>0),(I54*N54+(I54/K8-I54)*I20)/(I54/K8),0) -> 0.23690197 | M20: =IF(AND(I20<>"",I20<>0,L20<>"",L20<>0),L20/I20,"") -> 1.0768271 | N20: =IF(AND(J20<>0,J20<>"",I20<>0,I20<>""),L20-I20,"") -> 0.016901965 | P20: =IF(AND(O20<>"",O20<>0,L20<>"",L20<>0),-O20+L20,"") | Q20: =IF(AND(P20<>"",P20<>0,O20<>0,O20<>""),P20/O20,"")
B22: Факт продаж за месяц | O22: % выполнения дневного плана | P22: Раcпределение плана по дням
B23: Дата | C23: День недели | D23: Выручка (руб) | E23: Кол-во единиц (шт.) | F23: Средняя стоимость изделия (руб.) | G23: Количество чеков (шт.) | H23: Средняя сумма чека (руб.) | I23: Трафик | J23: Длина чека (шт.) | K23: UNOde50 | L23: IS | M23: Запасной | N23: Конверсия (%) | P23: выручка, план | Q23: кол-во ед, план | R23: Кол-во чеков, план | S23: выручка, скорректир.план | T23: кол-во ед, скорр. план | U23: кол-во чеков, скорр. план | V23: Коэфф. Дня Недели | W23: Специфика месяца
B24: 1 | C24: 2 | D24: 3 | E24: 4 | F24: 5 | G24: 6 | H24: 7 | I24: 8 | J24: 9 | K24: 10 | L24: 11 | M24: 12 | N24: 13 | P24: 1 | Q24: 2 | R24: 3 | S24: 4 | T24: 5 | U24: 6 | V24: 10 | W24: 11
A25: 1 | B25: 45778 | C25: чт | D25: =83582+L25 -> 125351 | E25: 23 | F25: =IF(AND(E25<>"",E25<>0),D25/E25,"") -> 5450.0435 | G25: 14 | H25: =IF(AND(G25<>"",G25<>0),D25/G25,"") -> 8953.6429 | I25: 35 | J25: =IF(AND(G25<>"",G25<>0),E25/G25,"") -> 1.6428571 | K25: 0 | L25: =53175-11406 -> 41769 | N25: =IF(AND(I25<>"",I25<>0),G25/I25,"") -> 0.4 | O25: =D25/P25 -> 2.2346432 | P25: =$I$8*V25*W25/SUMPRODUCT($W$25:$W$55,$V$25:$V$55) -> 56094.414 | Q25: =$I$9*V25*W25/SUMPRODUCT($W$25:$W$55,$V$25:$V$55) -> 10.787387 | R25: =IF($I$12="","",Q25/$I$12) -> 5.5605089 | S25: =IF(D25<>"",D25,P25) -> 125351 | T25: =IF(E25<>"",E25,Q25) -> 23 | U25: =IF(G25<>"",G25,R25) -> 14 | V25: 0.9004852 | W25: 0.9004852
A26: 2 | B26: 45779 | C26: пт | D26: 88513 | E26: 20 | F26: =IF(AND(E26<>"",E26<>0),D26/E26,"") -> 4425.65 | G26: 8 | H26: =IF(AND(G26<>"",G26<>0),D26/G26,"") -> 11064.125 | I26: 35 | J26: =IF(AND(G26<>"",G26<>0),E26/G26,"") -> 2.5 | N26: =IF(AND(I26<>"",I26<>0),G26/I26,"") -> 0.22857143 | O26: =D26/P26 -> 1.1361975 | P26: =$I$8*V26*W26/SUMPRODUCT($W$25:$W$55,$V$25:$V$55) -> 77902.826 | Q26: =$I$9*V26*W26/SUMPRODUCT($W$25:$W$55,$V$25:$V$55) -> 14.981313 | R26: =IF($I$12="","",Q26/$I$12) -> 7.7223261 | S26: =IF(W26<>"",IF(D26<>"",D26,($I$8-SUM($S$25:S25))*V26*W26/SUMPRODUCT($W26:$W$55,$V26:$V$55)),"") -> 88513 | T26: =IF(W26<>"",IF(E26<>"",E26,($I$9-SUM($T$25:T25))*V26*W26/SUMPRODUCT($W26:$W$55,$V26:$V$55)),"") -> 20 | U26: =IF(W26<>"",IF($I$12<>"",IF(G26<>"",G26,($I$9/$I$12-SUM($U$25:U25))*V26*W26/SUMPRODUCT($W26:$W$55,$V26:$V$55)),""),"") -> 8 | V26: 1.0611906 | W26: 1.0611906
A27: 3 | B27: 45780 | C27: сб | D27: 99865 | E27: 16 | F27: =IF(AND(E27<>"",E27<>0),D27/E27,"") -> 6241.5625 | G27: 10 | H27: =IF(AND(G27<>"",G27<>0),D27/G27,"") -> 9986.5 | I27: 23 | J27: =IF(AND(G27<>"",G27<>0),E27/G27,"") -> 1.6 | K27: 31972 | L27: =5803+8903 -> 14706 | N27: =IF(AND(I27<>"",I27<>0),G27/I27,"") -> 0.43478261 | O27: =D27/P27 -> 2.3675341 | P27: =$I$8*V27*W27/SUMPRODUCT($W$25:$W$55,$V$25:$V$55) -> 42181.018 | Q27: =$I$9*V27*W27/SUMPRODUCT($W$25:$W$55,$V$25:$V$55) -> 8.1117342 | R27: =IF($I$12="","",Q27/$I$12) -> 4.1813063 | S27: =IF(W27<>"",IF(D27<>"",D27,($I$8-SUM($S$25:S26))*V27*W27/SUMPRODUCT($W27:$W$55,$V27:$V$55)),"") -> 99865 | T27: =IF(W27<>"",IF(E27<>"",E27,($I$9-SUM($T$25:T26))*V27*W27/SUMPRODUCT($W27:$W$55,$V27:$V$55)),"") -> 16 | U27: =IF(W27<>"",IF($I$12<>"",IF(G27<>"",G27,($I$9/$I$12-SUM($U$25:U26))*V27*W27/SUMPRODUCT($W27:$W$55,$V27:$V$55)),""),"") -> 10 | V27: 0.78086381 | W27: 0.78086381
A28: 4 | B28: 45781 | C28: вс | D28: 46148 | E28: 11 | F28: =IF(AND(E28<>"",E28<>0),D28/E28,"") -> 4195.2727 | G28: 6 | H28: =IF(AND(G28<>"",G28<>0),D28/G28,"") -> 7691.3333 | I28: 20 | J28: =IF(AND(G28<>"",G28<>0),E28/G28,"") -> 1.8333333 | N28: =IF(AND(I28<>"",I28<>0),G28/I28,"") -> 0.3 | O28: =D28/P28 -> 0.6120499 | P28: =$I$8*V28*W28/SUMPRODUCT($W$25:$W$55,$V$25:$V$55) -> 75399.081 | Q28: =$I$9*V28*W28/SUMPRODUCT($W$25:$W$55,$V$25:$V$55) -> 14.499823 | R28: =IF($I$12="","",Q28/$I$12) -> 7.4741357 | S28: =IF(W28<>"",IF(D28<>"",D28,($I$8-SUM($S$25:S27))*V28*W28/SUMPRODUCT($W28:$W$55,$V28:$V$55)),"") -> 46148 | T28: =IF(W28<>"",IF(E28<>"",E28,($I$9-SUM($T$25:T27))*V28*W28/SUMPRODUCT($W28:$W$55,$V28:$V$55)),"") -> 11 | U28: =IF(W28<>"",IF($I$12<>"",IF(G28<>"",G28,($I$9/$I$12-SUM($U$25:U27))*V28*W28/SUMPRODUCT($W28:$W$55,$V28:$V$55)),""),"") -> 6 | V28: 1.0439983 | W28: 1.0439983
A29: 5 | B29: 45782 | C29: пн | D29: =51615+47305 -> 98920 | E29: 16 | F29: =IF(AND(E29<>"",E29<>0),D29/E29,"") -> 6182.5 | G29: 6 | H29: =IF(AND(G29<>"",G29<>0),D29/G29,"") -> 16486.667 | I29: 35 | J29: =IF(AND(G29<>"",G29<>0),E29/G29,"") -> 2.6666667 | L29: 47305 | N29: =IF(AND(I29<>"",I29<>0),G29/I29,"") -> 0.17142857 | O29: =D29/P29 -> 2.3451307 | P29: =$I$8*V29*W29/SUMPRODUCT($W$25:$W$55,$V$25:$V$55) -> 42181.018 | Q29: =$I$9*V29*W29/SUMPRODUCT($W$25:$W$55,$V$25:$V$55) -> 8.1117342 | R29: =IF($I$12="","",Q29/$I$12) -> 4.1813063 | S29: =IF(W29<>"",IF(D29<>"",D29,($I$8-SUM($S$25:S28))*V29*W29/SUMPRODUCT($W29:$W$55,$V29:$V$55)),"") -> 98920 | T29: =IF(W29<>"",IF(E29<>"",E29,($I$9-SUM($T$25:T28))*V29*W29/SUMPRODUCT($W29:$W$55,$V29:$V$55)),"") -> 16 | U29: =IF(W29<>"",IF($I$12<>"",IF(G29<>"",G29,($I$9/$I$12-SUM($U$25:U28))*V29*W29/SUMPRODUCT($W29:$W$55,$V29:$V$55)),""),"") -> 6 | V29: 0.78086381 | W29: 0.78086381
A30: 6 | B30: 45783 | C30: вт | D30: =24394+25902 -> 50296 | E30: 8 | F30: =IF(AND(E30<>"",E30<>0),D30/E30,"") -> 6287 | G30: 6 | H30: =IF(AND(G30<>"",G30<>0),D30/G30,"") -> 8382.6667 | I30: 20 | J30: =IF(AND(G30<>"",G30<>0),E30/G30,"") -> 1.3333333 | L30: 25902 | N30: =IF(AND(I30<>"",I30<>0),G30/I30,"") -> 0.3 | O30: =D30/P30 -> 1.0962652 | P30: =$I$8*V30*W30/SUMPRODUCT($W$25:$W$55,$V$25:$V$55) -> 45879.409 | Q30: =$I$9*V30*W30/SUMPRODUCT($W$25:$W$55,$V$25:$V$55) -> 8.8229633 | R30: =IF($I$12="","",Q30/$I$12) -> 4.5479192 | S30: =IF(W30<>"",IF(D30<>"",D30,($I$8-SUM($S$25:S29))*V30*W30/SUMPRODUCT($W30:$W$55,$V30:$V$55)),"") -> 50296 | T30: =IF(W30<>"",IF(E30<>"",E30,($I$9-SUM($T$25:T29))*V30*W30/SUMPRODUCT($W30:$W$55,$V30:$V$55)),"") -> 8 | U30: =IF(W30<>"",IF($I$12<>"",IF(G30<>"",G30,($I$9/$I$12-SUM($U$25:U29))*V30*W30/SUMPRODUCT($W30:$W$55,$V30:$V$55)),""),"") -> 6 | V30: 0.81437733 | W30: 0.81437733
A31: 7 | B31: 45784 | C31: ср | D31: 64709 | E31: 7 | F31: 9244 | G31: 4 | H31: =IF(AND(G31<>"",G31<>0),D31/G31,"") -> 16177.25 | I31: 20 | J31: =IF(AND(G31<>"",G31<>0),E31/G31,"") -> 1.75 | K31: 45563 | L31: 10623 | N31: =IF(AND(I31<>"",I31<>0),G31/I31,"") -> 0.2 | O31: =D31/P31 -> 1.4104149 | P31: =$I$8*V31*W31/SUMPRODUCT($W$25:$W$55,$V$25:$V$55) -> 45879.409 | Q31: =$I$9*V31*W31/SUMPRODUCT($W$25:$W$55,$V$25:$V$55) -> 8.8229633 | R31: =IF($I$12="","",Q31/$I$12) -> 4.5479192 | S31: =IF(W31<>"",IF(D31<>"",D31,($I$8-SUM($S$25:S30))*V31*W31/SUMPRODUCT($W31:$W$55,$V31:$V$55)),"") -> 64709 | T31: =IF(W31<>"",IF(E31<>"",E31,($I$9-SUM($T$25:T30))*V31*W31/SUMPRODUCT($W31:$W$55,$V31:$V$55)),"") -> 7 | U31: =IF(W31<>"",IF($I$12<>"",IF(G31<>"",G31,($I$9/$I$12-SUM($U$25:U30))*V31*W31/SUMPRODUCT($W31:$W$55,$V31:$V$55)),""),"") -> 4 | V31: 0.81437733 | W31: 0.81437733
A32: 8 | B32: 45785 | C32: чт | D32: =35423+11693+8423 -> 55539 | E32: 11 | F32: =IF(AND(E32<>"",E32<>0),D32/E32,"") -> 5049 | G32: 6 | H32: =IF(AND(G32<>"",G32<>0),D32/G32,"") -> 9256.5 | I32: 20 | J32: =IF(AND(G32<>"",G32<>0),E32/G32,"") -> 1.8333333 | K32: 11693 | L32: 8423 | N32: =IF(AND(I32<>"",I32<>0),G32/I32,"") -> 0.3 | O32: =D32/P32 -> 1.2105431 | P32: =$I$8*V32*W32/SUMPRODUCT($W$25:$W$55,$V$25:$V$55) -> 45879.409 | Q32: =$I$9*V32*W32/SUMPRODUCT($W$25:$W$55,$V$25:$V$55) -> 8.8229633 | R32: =IF($I$12="","",Q32/$I$12) -> 4.5479192 | S32: =IF(W32<>"",IF(D32<>"",D32,($I$8-SUM($S$25:S31))*V32*W32/SUMPRODUCT($W32:$W$55,$V32:$V$55)),"") -> 55539 | T32: =IF(W32<>"",IF(E32<>"",E32,($I$9-SUM($T$25:T31))*V32*W32/SUMPRODUCT($W32:$W$55,$V32:$V$55)),"") -> 11 | U32: =IF(W32<>"",IF($I$12<>"",IF(G32<>"",G32,($I$9/$I$12-SUM($U$25:U31))*V32*W32/SUMPRODUCT($W32:$W$55,$V32:$V$55)),""),"") -> 6 | V32: 0.81437733 | W32: 0.81437733
A33: 9 | B33: 45786 | C33: пт | D33: =3792+61609+12724 -> 78125 | E33: 6 | F33: =IF(AND(E33<>"",E33<>0),D33/E33,"") -> 13020.833 | G33: 4 | H33: =IF(AND(G33<>"",G33<>0),D33/G33,"") -> 19531.25 | I33: 20 | J33: =IF(AND(G33<>"",G33<>0),E33/G33,"") -> 1.5 | K33: 61609 | L33: 12724 | N33: =IF(AND(I33<>"",I33<>0),G33/I33,"") -> 0.2 | O33: =D33/P33 -> 1.129337 | P33: =$I$8*V33*W33/SUMPRODUCT($W$25:$W$55,$V$25:$V$55) -> 69177.755 | Q33: =$I$9*V33*W33/SUMPRODUCT($W$25:$W$55,$V$25:$V$55) -> 13.303414 | R33: =IF($I$12="","",Q33/$I$12) -> 6.8574301 | S33: =IF(W33<>"",IF(D33<>"",D33,($I$8-SUM($S$25:S32))*V33*W33/SUMPRODUCT($W33:$W$55,$V33:$V$55)),"") -> 78125 | T33: =IF(W33<>"",IF(E33<>"",E33,($I$9-SUM($T$25:T32))*V33*W33/SUMPRODUCT($W33:$W$55,$V33:$V$55)),"") -> 6 | U33: =IF(W33<>"",IF($I$12<>"",IF(G33<>"",G33,($I$9/$I$12-SUM($U$25:U32))*V33*W33/SUMPRODUCT($W33:$W$55,$V33:$V$55)),""),"") -> 4 | V33: 1 | W33: 1
A34: 10 | B34: 45787 | C34: сб | D34: =7739+31843 -> 39582 | E34: 3 | F34: =IF(AND(E34<>"",E34<>0),D34/E34,"") -> 13194 | G34: 3 | H34: =IF(AND(G34<>"",G34<>0),D34/G34,"") -> 13194 | I34: 10 | J34: =IF(AND(G34<>"",G34<>0),E34/G34,"") -> 1 | L34: 31843 | N34: =IF(AND(I34<>"",I34<>0),G34/I34,"") -> 0.3 | O34: =D34/P34 -> 0.93838418 | P34: =$I$8*V34*W34/SUMPRODUCT($W$25:$W$55,$V$25:$V$55) -> 42181.018 | Q34: =$I$9*V34*W34/SUMPRODUCT($W$25:$W$55,$V$25:$V$55) -> 8.1117342 | R34: =IF($I$12="","",Q34/$I$12) -> 4.1813063 | S34: =IF(W34<>"",IF(D34<>"",D34,($I$8-SUM($S$25:S33))*V34*W34/SUMPRODUCT($W34:$W$55,$V34:$V$55)),"") -> 39582 | T34: =IF(W34<>"",IF(E34<>"",E34,($I$9-SUM($T$25:T33))*V34*W34/SUMPRODUCT($W34:$W$55,$V34:$V$55)),"") -> 3 | U34: =IF(W34<>"",IF($I$12<>"",IF(G34<>"",G34,($I$9/$I$12-SUM($U$25:U33))*V34*W34/SUMPRODUCT($W34:$W$55,$V34:$V$55)),""),"") -> 3 | V34: 0.78086381 | W34: 0.78086381
A35: 11 | B35: 45788 | C35: вс | D35: =18549+24484+6203 -> 49236 | E35: 7 | F35: =IF(AND(E35<>"",E35<>0),D35/E35,"") -> 7033.7143 | G35: 4 | H35: =IF(AND(G35<>"",G35<>0),D35/G35,"") -> 12309 | I35: 25 | J35: =IF(AND(G35<>"",G35<>0),E35/G35,"") -> 1.75 | K35: 24484 | L35: 6203 | N35: =IF(AND(I35<>"",I35<>0),G35/I35,"") -> 0.16 | O35: =D35/P35 -> 1.1672549 | P35: =$I$8*V35*W35/SUMPRODUCT($W$25:$W$55,$V$25:$V$55) -> 42181.018 | Q35: =$I$9*V35*W35/SUMPRODUCT($W$25:$W$55,$V$25:$V$55) -> 8.1117342 | R35: =IF($I$12="","",Q35/$I$12) -> 4.1813063 | S35: =IF(W35<>"",IF(D35<>"",D35,($I$8-SUM($S$25:S34))*V35*W35/SUMPRODUCT($W35:$W$55,$V35:$V$55)),"") -> 49236 | T35: =IF(W35<>"",IF(E34<>"",E34,($I$9-SUM($T$25:T34))*V35*W35/SUMPRODUCT($W35:$W$55,$V35:$V$55)),"") -> 3 | U35: =IF(W35<>"",IF($I$12<>"",IF(G35<>"",G35,($I$9/$I$12-SUM($U$25:U34))*V35*W35/SUMPRODUCT($W35:$W$55,$V35:$V$55)),""),"") -> 4 | V35: 0.78086381 | W35: 0.78086381
A36: 12 | B36: 45789 | C36: пн | D36: =30795+8903 -> 39698 | E36: 8 | F36: =IF(AND(E36<>"",E36<>0),D36/E36,"") -> 4962.25 | G36: 3 | H36: =IF(AND(G36<>"",G36<>0),D36/G36,"") -> 13232.667 | I36: 15 | J36: =IF(AND(G36<>"",G36<>0),E36/G36,"") -> 2.6666667 | L36: 8903 | N36: =IF(AND(I36<>"",I36<>0),G36/I36,"") -> 0.2 | O36: =D36/P36 -> 0.94113424 | P36: =$I$8*V36*W36/SUMPRODUCT($W$25:$W$55,$V$25:$V$55) -> 42181.018 | Q36: =$I$9*V36*W36/SUMPRODUCT($W$25:$W$55,$V$25:$V$55) -> 8.1117342 | R36: =IF($I$12="","",Q36/$I$12) -> 4.1813063 | S36: =IF(W36<>"",IF(D36<>"",D36,($I$8-SUM($S$25:S35))*V36*W36/SUMPRODUCT($W36:$W$55,$V36:$V$55)),"") -> 39698 | T36: =IF(W36<>"",IF(E36<>"",E36,($I$9-SUM($T$25:T35))*V36*W36/SUMPRODUCT($W36:$W$55,$V36:$V$55)),"") -> 8 | U36: =IF(W36<>"",IF($I$12<>"",IF(G36<>"",G36,($I$9/$I$12-SUM($U$25:U35))*V36*W36/SUMPRODUCT($W36:$W$55,$V36:$V$55)),""),"") -> 3 | V36: 0.78086381 | W36: 0.78086381
A37: 13 | B37: 45790 | C37: вт | D37: 46762 | E37: 2 | F37: =IF(AND(E37<>"",E37<>0),D37/E37,"") -> 23381 | G37: 3 | H37: =IF(AND(G37<>"",G37<>0),D37/G37,"") -> 15587.333 | I37: 11 | J37: =IF(AND(G37<>"",G37<>0),E37/G37,"") -> 0.66666667 | N37: =IF(AND(I37<>"",I37<>0),G37/I37,"") -> 0.27272727 | O37: =D37/P37 -> 0.70978307 | P37: =$I$8*V37*W37/SUMPRODUCT($W$25:$W$55,$V$25:$V$55) -> 65882.101 | Q37: =$I$9*V37*W37/SUMPRODUCT($W$25:$W$55,$V$25:$V$55) -> 12.669635 | R37: =IF($I$12="","",Q37/$I$12) -> 6.5307396 | S37: =IF(W37<>"",IF(D37<>"",D37,($I$8-SUM($S$25:S36))*V37*W37/SUMPRODUCT($W37:$W$55,$V37:$V$55)),"") -> 46762 | T37: =IF(W37<>"",IF(E37<>"",E37,($I$9-SUM($T$25:T36))*V37*W37/SUMPRODUCT($W37:$W$55,$V37:$V$55)),"") -> 2 | U37: =IF(W37<>"",IF($I$12<>"",IF(G37<>"",G37,($I$9/$I$12-SUM($U$25:U36))*V37*W37/SUMPRODUCT($W37:$W$55,$V37:$V$55)),""),"") -> 3 | V37: 0.97588915 | W37: 0.97588915
A38: 14 | B38: 45792 | C38: чт | D38: 19949 | E38: 6 | F38: =IF(AND(E38<>"",E38<>0),D38/E38,"") -> 3324.8333 | G38: 3 | H38: =IF(AND(G38<>"",G38<>0),D38/G38,"") -> 6649.6667 | I38: 15 | J38: =IF(AND(G38<>"",G38<>0),E38/G38,"") -> 2 | N38: =IF(AND(I38<>"",I38<>0),G38/I38,"") -> 0.2 | O38: =D38/P38 -> 0.30279848 | P38: =$I$8*V38*W38/SUMPRODUCT($W$25:$W$55,$V$25:$V$55) -> 65882.101 | Q38: =$I$9*V38*W38/SUMPRODUCT($W$25:$W$55,$V$25:$V$55) -> 12.669635 | R38: =IF($I$12="","",Q38/$I$12) -> 6.5307396 | S38: =IF(W38<>"",IF(D38<>"",D38,($I$8-SUM($S$25:S37))*V38*W38/SUMPRODUCT($W38:$W$55,$V38:$V$55)),"") -> 19949 | T38: =IF(W38<>"",IF(E38<>"",E38,($I$9-SUM($T$25:T37))*V38*W38/SUMPRODUCT($W38:$W$55,$V38:$V$55)),"") -> 6 | U38: =IF(W38<>"",IF($I$12<>"",IF(G38<>"",G38,($I$9/$I$12-SUM($U$25:U37))*V38*W38/SUMPRODUCT($W38:$W$55,$V38:$V$55)),""),"") -> 3 | V38: 0.97588915 | W38: 0.97588915
A39: 13 | B39: 45793 | C39: пт | D39: 15866 | E39: 4 | F39: =IF(AND(E39<>"",E39<>0),D39/E39,"") -> 3966.5 | G39: 2 | H39: =IF(AND(G39<>"",G39<>0),D39/G39,"") -> 7933 | I39: 15 | J39: =IF(AND(G39<>"",G39<>0),E39/G39,"") -> 2 | N39: =IF(AND(I39<>"",I39<>0),G39/I39,"") -> 0.13333333 | O39: =D39/P39 -> 0.24082414 | P39: =$I$8*V39*W39/SUMPRODUCT($W$25:$W$55,$V$25:$V$55) -> 65882.101 | Q39: =$I$9*V39*W39/SUMPRODUCT($W$25:$W$55,$V$25:$V$55) -> 12.669635 | R39: =IF($I$12="","",Q39/$I$12) -> 6.5307396 | S39: =IF(W39<>"",IF(D39<>"",D39,($I$8-SUM($S$25:S38))*V39*W39/SUMPRODUCT($W39:$W$55,$V39:$V$55)),"") -> 15866 | T39: =IF(W39<>"",IF(E39<>"",E39,($I$9-SUM($T$25:T38))*V39*W39/SUMPRODUCT($W39:$W$55,$V39:$V$55)),"") -> 4 | U39: =IF(W39<>"",IF($I$12<>"",IF(G39<>"",G39,($I$9/$I$12-SUM($U$25:U38))*V39*W39/SUMPRODUCT($W39:$W$55,$V39:$V$55)),""),"") -> 2 | V39: 0.97588915 | W39: 0.97588915
A40: 13 | B40: 45794 | C40: сб | D40: =5083+5493 -> 10576 | E40: 3 | F40: =IF(AND(E40<>"",E40<>0),D40/E40,"") -> 3525.3333 | G40: 2 | H40: =IF(AND(G40<>"",G40<>0),D40/G40,"") -> 5288 | I40: 25 | J40: =IF(AND(G40<>"",G40<>0),E40/G40,"") -> 1.5 | K40: 5493 | N40: =IF(AND(I40<>"",I40<>0),G40/I40,"") -> 0.08 | O40: =D40/P40 -> 0.16052919 | P40: =$I$8*V40*W40/SUMPRODUCT($W$25:$W$55,$V$25:$V$55) -> 65882.101 | Q40: =$I$9*V40*W40/SUMPRODUCT($W$25:$W$55,$V$25:$V$55) -> 12.669635 | R40: =IF($I$12="","",Q40/$I$12) -> 6.5307396 | S40: =IF(W40<>"",IF(D40<>"",D40,($I$8-SUM($S$25:S39))*V40*W40/SUMPRODUCT($W40:$W$55,$V40:$V$55)),"") -> 10576 | T40: =IF(W40<>"",IF(E40<>"",E40,($I$9-SUM($T$25:T39))*V40*W40/SUMPRODUCT($W40:$W$55,$V40:$V$55)),"") -> 3 | U40: =IF(W40<>"",IF($I$12<>"",IF(G40<>"",G40,($I$9/$I$12-SUM($U$25:U39))*V40*W40/SUMPRODUCT($W40:$W$55,$V40:$V$55)),""),"") -> 2 | V40: 0.97588915 | W40: 0.97588915
A41: 17 | B41: 45795 | C41: вс | D41: =29229+5501 -> 34730 | E41: 7 | F41: =IF(AND(E41<>"",E41<>0),D41/E41,"") -> 4961.4286 | G41: 4 | H41: =IF(AND(G41<>"",G41<>0),D41/G41,"") -> 8682.5 | I41: 17 | J41: =IF(AND(G41<>"",G41<>0),E41/G41,"") -> 1.75 | L41: 5501 | N41: =IF(AND(I41<>"",I41<>0),G41/I41,"") -> 0.23529412 | O41: =D41/P41 -> 0.36419123 | P41: =$I$8*V41*W41/SUMPRODUCT($W$25:$W$55,$V$25:$V$55) -> 95361.99 | Q41: =$I$9*V41*W41/SUMPRODUCT($W$25:$W$55,$V$25:$V$55) -> 18.338844 | R41: =IF($I$12="","",Q41/$I$12) -> 9.4530125 | S41: =IF(W41<>"",IF(D41<>"",D41,($I$8-SUM($S$25:S40))*V41*W41/SUMPRODUCT($W41:$W$55,$V41:$V$55)),"") -> 34730 | T41: =IF(W41<>"",IF(E41<>"",E41,($I$9-SUM($T$25:T40))*V41*W41/SUMPRODUCT($W41:$W$55,$V41:$V$55)),"") -> 7 | U41: =IF(W41<>"",IF($I$12<>"",IF(G41<>"",G41,($I$9/$I$12-SUM($U$25:U40))*V41*W41/SUMPRODUCT($W41:$W$55,$V41:$V$55)),""),"") -> 4 | V41: 1.1740982 | W41: 1.1740982
A42: 18 | B42: 45797 | C42: вт | D42: 24248 | E42: 6 | F42: =IF(AND(E42<>"",E42<>0),D42/E42,"") -> 4041.3333 | G42: 2 | H42: =IF(AND(G42<>"",G42<>0),D42/G42,"") -> 12124 | I42: 7 | J42: =IF(AND(G42<>"",G42<>0),E42/G42,"") -> 3 | N42: =IF(AND(I42<>"",I42<>0),G42/I42,"") -> 0.28571429 | O42: =D42/P42 -> 0.25427322 | P42: =$I$8*V42*W42/SUMPRODUCT($W$25:$W$55,$V$25:$V$55) -> 95361.99 | Q42: =$I$9*V42*W42/SUMPRODUCT($W$25:$W$55,$V$25:$V$55) -> 18.338844 | R42: =IF($I$12="","",Q42/$I$12) -> 9.4530125 | S42: =IF(W42<>"",IF(D42<>"",D42,($I$8-SUM($S$25:S41))*V42*W42/SUMPRODUCT($W42:$W$55,$V42:$V$55)),"") -> 24248 | T42: =IF(W42<>"",IF(E42<>"",E42,($I$9-SUM($T$25:T41))*V42*W42/SUMPRODUCT($W42:$W$55,$V42:$V$55)),"") -> 6 | U42: =IF(W42<>"",IF($I$12<>"",IF(G42<>"",G42,($I$9/$I$12-SUM($U$25:U41))*V42*W42/SUMPRODUCT($W42:$W$55,$V42:$V$55)),""),"") -> 2 | V42: 1.1740982 | W42: 1.1740982
A43: 19 | B43: 45798 | C43: ср | D43: =29543+10503 -> 40046 | E43: 8 | F43: =IF(AND(E43<>"",E43<>0),D43/E43,"") -> 5005.75 | G43: 6 | H43: =IF(AND(G43<>"",G43<>0),D43/G43,"") -> 6674.3333 | I43: 15 | J43: =IF(AND(G43<>"",G43<>0),E43/G43,"") -> 1.3333333 | L43: 10503 | N43: =IF(AND(I43<>"",I43<>0),G43/I43,"") -> 0.4 | O43: =D43/P43 -> 0.47553556 | P43: =$I$8*V43*W43/SUMPRODUCT($W$25:$W$55,$V$25:$V$55) -> 84212.419 | Q43: =$I$9*V43*W43/SUMPRODUCT($W$25:$W$55,$V$25:$V$55) -> 16.194696 | R43: =IF($I$12="","",Q43/$I$12) -> 8.3477814 | S43: =IF(W43<>"",IF(D43<>"",D43,($I$8-SUM($S$25:S42))*V43*W43/SUMPRODUCT($W43:$W$55,$V43:$V$55)),"") -> 40046 | T43: =IF(W43<>"",IF(E43<>"",E43,($I$9-SUM($T$25:T42))*V43*W43/SUMPRODUCT($W43:$W$55,$V43:$V$55)),"") -> 8 | U43: =IF(W43<>"",IF($I$12<>"",IF(G43<>"",G43,($I$9/$I$12-SUM($U$25:U42))*V43*W43/SUMPRODUCT($W43:$W$55,$V43:$V$55)),""),"") -> 6 | V43: 1.1033285 | W43: 1.1033285
A44: 20 | B44: 45799 | C44: чт | D44: =3892+11100 -> 14992 | E44: 3 | F44: =IF(AND(E44<>"",E44<>0),D44/E44,"") -> 4997.3333 | G44: 2 | H44: =IF(AND(G44<>"",G44<>0),D44/G44,"") -> 7496 | I44: 8 | J44: =IF(AND(G44<>"",G44<>0),E44/G44,"") -> 1.5 | L44: 11100 | N44: =IF(AND(I44<>"",I44<>0),G44/I44,"") -> 0.25 | O44: =D44/P44 -> 0.178026 | P44: =$I$8*V44*W44/SUMPRODUCT($W$25:$W$55,$V$25:$V$55) -> 84212.419 | Q44: =$I$9*V44*W44/SUMPRODUCT($W$25:$W$55,$V$25:$V$55) -> 16.194696 | R44: =IF($I$12="","",Q44/$I$12) -> 8.3477814 | S44: =IF(W44<>"",IF(D44<>"",D44,($I$8-SUM($S$25:S43))*V44*W44/SUMPRODUCT($W44:$W$55,$V44:$V$55)),"") -> 14992 | T44: =IF(W44<>"",IF(E44<>"",E44,($I$9-SUM($T$25:T43))*V44*W44/SUMPRODUCT($W44:$W$55,$V44:$V$55)),"") -> 3 | U44: =IF(W44<>"",IF($I$12<>"",IF(G44<>"",G44,($I$9/$I$12-SUM($U$25:U43))*V44*W44/SUMPRODUCT($W44:$W$55,$V44:$V$55)),""),"") -> 2 | V44: 1.1033285 | W44: 1.1033285
A45: 21 | B45: 45800 | C45: пт | D45: =3892+4492 -> 8384 | E45: 2 | F45: =IF(AND(E45<>"",E45<>0),D45/E45,"") -> 4192 | G45: 2 | H45: =IF(AND(G45<>"",G45<>0),D45/G45,"") -> 4192 | I45: 8 | J45: =IF(AND(G45<>"",G45<>0),E45/G45,"") -> 1 | N45: =IF(AND(I45<>"",I45<>0),G45/I45,"") -> 0.25 | O45: =D45/P45 -> 0.12119503 | P45: =$I$8*V45*W45/SUMPRODUCT($W$25:$W$55,$V$25:$V$55) -> 69177.755 | Q45: =$I$9*V45*W45/SUMPRODUCT($W$25:$W$55,$V$25:$V$55) -> 13.303414 | R45: =IF($I$12="","",Q45/$I$12) -> 6.8574301 | S45: =IF(W45<>"",IF(D45<>"",D45,($I$8-SUM($S$25:S44))*V45*W45/SUMPRODUCT($W45:$W$55,$V45:$V$55)),"") -> 8384 | T45: =IF(W45<>"",IF(E45<>"",E45,($I$9-SUM($T$25:T44))*V45*W45/SUMPRODUCT($W45:$W$55,$V45:$V$55)),"") -> 2 | U45: =IF(W45<>"",IF($I$12<>"",IF(G45<>"",G45,($I$9/$I$12-SUM($U$25:U44))*V45*W45/SUMPRODUCT($W45:$W$55,$V45:$V$55)),""),"") -> 2 | V45: 1 | W45: 1
A46: 22 | B46: 45801 | C46: сб | D46: =12775+25684+28906 -> 67365 | E46: 8 | F46: =IF(AND(E46<>"",E46<>0),D46/E46,"") -> 8420.625 | G46: 5 | H46: =IF(AND(G46<>"",G46<>0),D46/G46,"") -> 13473 | I46: 17 | J46: =IF(AND(G46<>"",G46<>0),E46/G46,"") -> 1.6 | K46: 25684 | L46: 28906 | N46: =IF(AND(I46<>"",I46<>0),G46/I46,"") -> 0.29411765 | O46: =D46/P46 -> 0.9737957 | P46: =$I$8*V46*W46/SUMPRODUCT($W$25:$W$55,$V$25:$V$55) -> 69177.755 | Q46: =$I$9*V46*W46/SUMPRODUCT($W$25:$W$55,$V$25:$V$55) -> 13.303414 | R46: =IF($I$12="","",Q46/$I$12) -> 6.8574301 | S46: =IF(W46<>"",IF(D46<>"",D46,($I$8-SUM($S$25:S45))*V46*W46/SUMPRODUCT($W46:$W$55,$V46:$V$55)),"") -> 67365 | T46: =IF(W46<>"",IF(E46<>"",E46,($I$9-SUM($T$25:T45))*V46*W46/SUMPRODUCT($W46:$W$55,$V46:$V$55)),"") -> 8 | U46: =IF(W46<>"",IF($I$12<>"",IF(G46<>"",G46,($I$9/$I$12-SUM($U$25:U45))*V46*W46/SUMPRODUCT($W46:$W$55,$V46:$V$55)),""),"") -> 5 | V46: 1 | W46: 1
A47: 23 | B47: 45802 | C47: вс | D47: 23568 | E47: 4 | F47: =IF(AND(E47<>"",E47<>0),D47/E47,"") -> 5892 | G47: 4 | H47: =IF(AND(G47<>"",G47<>0),D47/G47,"") -> 5892 | I47: 15 | J47: =IF(AND(G47<>"",G47<>0),E47/G47,"") -> 1 | K47: 8993 | N47: =IF(AND(I47<>"",I47<>0),G47/I47,"") -> 0.26666667 | O47: =D47/P47 -> 0.34068755 | P47: =$I$8*V47*W47/SUMPRODUCT($W$25:$W$55,$V$25:$V$55) -> 69177.755 | Q47: =$I$9*V47*W47/SUMPRODUCT($W$25:$W$55,$V$25:$V$55) -> 13.303414 | R47: =IF($I$12="","",Q47/$I$12) -> 6.8574301 | S47: =IF(W47<>"",IF(D47<>"",D47,($I$8-SUM($S$25:S46))*V47*W47/SUMPRODUCT($W47:$W$55,$V47:$V$55)),"") -> 23568 | T47: =IF(W47<>"",IF(E47<>"",E47,($I$9-SUM($T$25:T46))*V47*W47/SUMPRODUCT($W47:$W$55,$V47:$V$55)),"") -> 4 | U47: =IF(W47<>"",IF($I$12<>"",IF(G47<>"",G47,($I$9/$I$12-SUM($U$25:U46))*V47*W47/SUMPRODUCT($W47:$W$55,$V47:$V$55)),""),"") -> 4 | V47: 1 | W47: 1
A48: 24 | B48: 45804 | C48: вт | D48: =31985+33995+27307 -> 93287 | E48: 11 | F48: =IF(AND(E48<>"",E48<>0),D48/E48,"") -> 8480.6364 | G48: 7 | H48: =IF(AND(G48<>"",G48<>0),D48/G48,"") -> 13326.714 | I48: 17 | J48: =IF(AND(G48<>"",G48<>0),E48/G48,"") -> 1.5714286 | K48: 31985 | L48: 27307 | N48: =IF(AND(I48<>"",I48<>0),G48/I48,"") -> 0.41176471 | O48: =D48/P48 -> 1.3485115 | P48: =$I$8*V48*W48/SUMPRODUCT($W$25:$W$55,$V$25:$V$55) -> 69177.755 | Q48: =$I$9*V48*W48/SUMPRODUCT($W$25:$W$55,$V$25:$V$55) -> 13.303414 | R48: =IF($I$12="","",Q48/$I$12) -> 6.8574301 | S48: =IF(W48<>"",IF(D48<>"",D48,($I$8-SUM($S$25:S47))*V48*W48/SUMPRODUCT($W48:$W$55,$V48:$V$55)),"") -> 93287 | T48: =IF(W48<>"",IF(E48<>"",E48,($I$9-SUM($T$25:T47))*V48*W48/SUMPRODUCT($W48:$W$55,$V48:$V$55)),"") -> 11 | U48: =IF(W48<>"",IF($I$12<>"",IF(G48<>"",G48,($I$9/$I$12-SUM($U$25:U47))*V48*W48/SUMPRODUCT($W48:$W$55,$V48:$V$55)),""),"") -> 7 | V48: 1 | W48: 1
A49: 25 | B49: 28.мая | C49: ср | D49: 14373 | E49: 4 | F49: =IF(AND(E49<>"",E49<>0),D49/E49,"") -> 3593.25 | G49: 2 | H49: =IF(AND(G49<>"",G49<>0),D49/G49,"") -> 7186.5 | I49: 17 | J49: =IF(AND(G49<>"",G49<>0),E49/G49,"") -> 2 | N49: =IF(AND(I49<>"",I49<>0),G49/I49,"") -> 0.11764706 | O49: =D49/P49 -> 0.2077691 | P49: =$I$8*V49*W49/SUMPRODUCT($W$25:$W$55,$V$25:$V$55) -> 69177.755 | Q49: =$I$9*V49*W49/SUMPRODUCT($W$25:$W$55,$V$25:$V$55) -> 13.303414 | R49: =IF($I$12="","",Q49/$I$12) -> 6.8574301 | S49: =IF(W49<>"",IF(D49<>"",D49,($I$8-SUM($S$25:S48))*V49*W49/SUMPRODUCT($W49:$W$55,$V49:$V$55)),"") -> 14373 | T49: =IF(W49<>"",IF(E49<>"",E49,($I$9-SUM($T$25:T48))*V49*W49/SUMPRODUCT($W49:$W$55,$V49:$V$55)),"") -> 4 | U49: =IF(W49<>"",IF($I$12<>"",IF(G49<>"",G49,($I$9/$I$12-SUM($U$25:U48))*V49*W49/SUMPRODUCT($W49:$W$55,$V49:$V$55)),""),"") -> 2 | V49: 1 | W49: 1
A50: 26 | B50: 29.мая | C50: чт | D50: 46013 | E50: 12 | F50: =IF(AND(E50<>"",E50<>0),D50/E50,"") -> 3834.4167 | G50: 5 | H50: =IF(AND(G50<>"",G50<>0),D50/G50,"") -> 9202.6 | I50: 20 | J50: =IF(AND(G50<>"",G50<>0),E50/G50,"") -> 2.4 | N50: =IF(AND(I50<>"",I50<>0),G50/I50,"") -> 0.25 | O50: =D50/P50 -> 0.66514156 | P50: =$I$8*V50*W50/SUMPRODUCT($W$25:$W$55,$V$25:$V$55) -> 69177.755 | Q50: =$I$9*V50*W50/SUMPRODUCT($W$25:$W$55,$V$25:$V$55) -> 13.303414 | R50: =IF($I$12="","",Q50/$I$12) -> 6.8574301 | S50: =IF(W50<>"",IF(D50<>"",D50,($I$8-SUM($S$25:S49))*V50*W50/SUMPRODUCT($W50:$W$55,$V50:$V$55)),"") -> 46013 | T50: =IF(W50<>"",IF(E50<>"",E50,($I$9-SUM($T$25:T49))*V50*W50/SUMPRODUCT($W50:$W$55,$V50:$V$55)),"") -> 12 | U50: =IF(W50<>"",IF($I$12<>"",IF(G50<>"",G50,($I$9/$I$12-SUM($U$25:U49))*V50*W50/SUMPRODUCT($W50:$W$55,$V50:$V$55)),""),"") -> 5 | V50: 1 | W50: 1
A51: 27 | B51: 30мая | C51: пт | D51: 27238 | E51: 7 | F51: =IF(AND(E51<>"",E51<>0),D51/E51,"") -> 3891.1429 | G51: 1 | H51: =IF(AND(G51<>"",G51<>0),D51/G51,"") -> 27238 | I51: 17 | J51: =IF(AND(G51<>"",G51<>0),E51/G51,"") -> 7 | N51: =IF(AND(I51<>"",I51<>0),G51/I51,"") -> 0.058823529 | O51: =D51/P51 -> 0.39373929 | P51: =$I$8*V51*W51/SUMPRODUCT($W$25:$W$55,$V$25:$V$55) -> 69177.755 | Q51: =$I$9*V51*W51/SUMPRODUCT($W$25:$W$55,$V$25:$V$55) -> 13.303414 | R51: =IF($I$12="","",Q51/$I$12) -> 6.8574301 | S51: =IF(W51<>"",IF(D51<>"",D51,($I$8-SUM($S$25:S50))*V51*W51/SUMPRODUCT($W51:$W$55,$V51:$V$55)),"") -> 27238 | T51: =IF(W51<>"",IF(E51<>"",E51,($I$9-SUM($T$25:T50))*V51*W51/SUMPRODUCT($W51:$W$55,$V51:$V$55)),"") -> 7 | U51: =IF(W51<>"",IF($I$12<>"",IF(G51<>"",G51,($I$9/$I$12-SUM($U$25:U50))*V51*W51/SUMPRODUCT($W51:$W$55,$V51:$V$55)),""),"") -> 1 | V51: 1 | W51: 1
A52: 28 | B52: 31мая | C52: сб | D52: 35158 | E52: 5 | F52: =IF(AND(E52<>"",E52<>0),D52/E52,"") -> 7031.6 | G52: 3 | H52: =IF(AND(G52<>"",G52<>0),D52/G52,"") -> 11719.333 | I52: 20 | J52: =IF(AND(G52<>"",G52<>0),E52/G52,"") -> 1.6666667 | N52: =IF(AND(I52<>"",I52<>0),G52/I52,"") -> 0.15 | O52: =D52/P52 -> 0.50822696 | P52: =$I$8*V52*W52/SUMPRODUCT($W$25:$W$55,$V$25:$V$55) -> 69177.755 | Q52: =$I$9*V52*W52/SUMPRODUCT($W$25:$W$55,$V$25:$V$55) -> 13.303414 | R52: =IF($I$12="","",Q52/$I$12) -> 6.8574301 | S52: =IF(W52<>"",IF(D52<>"",D52,($I$8-SUM($S$25:S51))*V52*W52/SUMPRODUCT($W52:$W$55,$V52:$V$55)),"") -> 35158 | T52: =IF(W52<>"",IF(E52<>"",E52,($I$9-SUM($T$25:T51))*V52*W52/SUMPRODUCT($W52:$W$55,$V52:$V$55)),"") -> 5 | U52: =IF(W52<>"",IF($I$12<>"",IF(G52<>"",G52,($I$9/$I$12-SUM($U$25:U51))*V52*W52/SUMPRODUCT($W52:$W$55,$V52:$V$55)),""),"") -> 3 | V52: 1 | W52: 1
A53: 29 | F53: =IF(AND(E53<>"",E53<>0),D53/E53,"") | H53: =IF(AND(G53<>"",G53<>0),D53/G53,"") | J53: =IF(AND(G53<>"",G53<>0),E53/G53,"") | N53: =IF(AND(I53<>"",I53<>0),G53/I53,"") | O53: =D53/P53 -> 0 | P53: =$I$8*V53*W53/SUMPRODUCT($W$25:$W$55,$V$25:$V$55) -> 69177.755 | Q53: =$I$9*V53*W53/SUMPRODUCT($W$25:$W$55,$V$25:$V$55) -> 13.303414 | R53: =IF($I$12="","",Q53/$I$12) -> 6.8574301 | S53: =IF(W53<>"",IF(D53<>"",D53,($I$8-SUM($S$25:S52))*V53*W53/SUMPRODUCT($W53:$W$55,$V53:$V$55)),"") -> 513857.41 | T53: =IF(W53<>"",IF(E53<>"",E53,($I$9-SUM($T$25:T52))*V53*W53/SUMPRODUCT($W53:$W$55,$V53:$V$55)),"") -> 136.07585 | U53: =IF(W53<>"",IF($I$12<>"",IF(G53<>"",G53,($I$9/$I$12-SUM($U$25:U52))*V53*W53/SUMPRODUCT($W53:$W$55,$V53:$V$55)),""),"") -> 58.606107 | V53: 1 | W53: 1
B54: итого | D54: =SUM(D25:D53) -> 1358537 | E54: =SUM(E25:E53) -> 228 | F54: =IF(AND(E54<>"",E54<>0),D54/E54,"") -> 5958.4956 | G54: =SUM(G25:G53) -> 127 | H54: =IF(AND(G54<>"",G54<>0),D54/G54,"") -> 10697.142 | I54: =SUM(I25:I53) -> 522 | J54: =IF(AND(G54<>"",G54<>0),E54/G54,"") -> 1.7952756 | K54: =SUM(K25:K51) -> 247476 | L54: =SUM(L25:L51) -> 291718 | M54: =SUM(M25:M51) -> 0 | N54: =IF(AND(I54<>"",I54<>0),G54/I54,"") -> 0.24329502 | O54: =D54/P54 -> 0.72556134 | P54: =SUM(P25:P53) -> 1872394.4 | Q54: =SUM(Q25:Q52) -> 346.77243 | R54: =SUM(R25:R52) -> 178.74868 | S54: =SUM(S25:S53) -> 1872394.4 | T54: =SUM(T25:T52) -> 224 | U54: =SUM(U25:U52) -> 127
D55: =SUMIF(D25:D51,"",P25:P51)+D54 -> 1358537

Sheet Уразгильдеева Е. Р.
B1: =TODAY()-1 -> 46171
B2: (отчетная дата) | J2: ЕЖЕДНЕВНЫЙ ОТЧЕТ О ПРОДАЖАХ
B3: Осталось до выполнения плана!!! | J3: =График!B28 -> Уразгильдеева Екатерина
C4: =I8-D50 -> 782374.13 | E4: =IF(I8<>0, C4/I8, 0) -> 0.5214593
F6: Целевые показатели
F7: Показатель | I7: План | J7: Факт | K7: % выполнения | L7: Прогноз выполнения | M7: % выполнения по прогнозу | N7: Отклонение | O7: Факт аналогичного месяца прошлого года | P7: Отклонение LFL
F8: Выручка | I8: ='Ялта, Ленина, 18'!I8/График!AJ31*График!AJ28 -> 1500355.1 | J8: =D50 -> 717981 | K8: =J8/I8 -> 0.4785407 | L8: =IF(SUMIF($D$25:$D$49,">=0",$P$25:$P$49)<>0,I8*D50/SUMIF($D$25:$D$49,">=0",$P$25:$P$49),0) -> 717981 | M8: =IF(AND(I8<>"",I8<>0,L8<>"",L8<>0),L8/I8,"") -> 0.4785407 | N8: =IF(AND(J8<>0, J8<>"", I8<>0, I8<>""), L8-I8, "") -> -782374.13 | P8: =IF(AND(O8<>"", O8<>0, L8<>"", L8<>0), -O8+L8, "") | Q8: =IF(AND(P8<>"", P8<>0, O8<>0, O8<>""), P8/O8, "")
F9: Кол-во изделий | I9: =I8/I11 -> 288.52983 | J9: =E50 -> 134 | K9: =IF(AND(I9<>"", I9<>0, J9<>""), J9/I9, "") -> 0.46442338 | L9: =J9 -> 134 | M9: =IF(AND(I9<>"",I9<>0,L9<>"",L9<>0),L9/I9,"") -> 0.46442338 | N9: =IF(AND(J9<>0, J9<>"", I9<>0, I9<>""), L9-I9, "") -> -154.52983 | O9: =O8/O11 -> #DIV/0! | P9: =IF(AND(O9<>"", O9<>0, L9<>"", L9<>0), -O9+L9, "") -> #DIV/0! | Q9: =IF(AND(P9<>"", P9<>0, O9<>0, O9<>""), P9/O9, "") -> #DIV/0!
F10: Средний чек | I10: =I11*I12 -> 10088 | J10: =H50 -> 8974.7625 | K10: =IF(AND(I10<>"", I10<>0, J10<>""), J10/I10, "") -> 0.88964735 | L10: =J10 -> 8974.7625 | M10: =IF(AND(I10<>"",I10<>0,L10<>"",L10<>0),L10/I10,"") -> 0.88964735 | N10: =IF(AND(J10<>0, J10<>"", I10<>0, I10<>""), L10-I10, "") -> -1113.2375 | O10: =O11*O12 -> 0 | P10: =IF(AND(O10<>"", O10<>0, L10<>"", L10<>0), -O10+L10, "") | Q10: =IF(AND(P10<>"", P10<>0, O10<>0, O10<>""), P10/O10, "") | S10: IS
F11: Средняя стоимость изделия | I11: ='Ялта, Ленина, 18'!I11 -> 5200 | J11: =F50 -> 5358.0672 | K11: =IF(AND(I11<>"", I11<>0, J11<>""), J11/I11, "") -> 1.0303975 | L11: =J11 -> 5358.0672 | M11: =IF(AND(I11<>"",I11<>0,L11<>"",L11<>0),L11/I11,"") -> 1.0303975 | N11: =IF(AND(J11<>0, J11<>"", I11<>0, I11<>""), L11-I11, "") -> 158.06716 | P11: =IF(AND(O11<>"", O11<>0, L11<>"", L11<>0), -O11+L11, "") | Q11: =IF(AND(P11<>"", P11<>0, O11<>0, O11<>""), P11/O11, "")
F12: Длина чека | I12: ='Ялта, Ленина, 18'!I12 -> 1.94 | J12: =J50 -> 1.675 | K12: =IF(AND(I12<>"", I12<>0, J12<>""), J12/I12, "") -> 0.86340206 | L12: =J12 -> 1.675 | M12: =IF(AND(I12<>"",I12<>0,L12<>"",L12<>0),L12/I12,"") -> 0.86340206 | N12: =IF(AND(J12<>0, J12<>"", I12<>0, I12<>""), L12-I12, "") -> -0.265 | P12: =IF(AND(O12<>"", O12<>0, L12<>"", L12<>0), -O12+L12, "") | Q12: =IF(AND(P12<>"", P12<>0, O12<>0, O12<>""), P12/O12, "") | S12: ='Ялта, Ленина, 18'!S12*График!AJ28/График!AJ31 -> 212824.43 | T12: =L50 -> 128084
F13: Кол-во чеков | I13: =IF(I12<>0, I9/I12, "") -> 148.72672 | J13: =G50 -> 80 | K13: =IF(AND(I13<>"", I13<>0, J13<>""), J13/I13, "") -> 0.53789932 | L13: =J13 -> 80 | M13: =IF(AND(I13<>"",I13<>0,L13<>"",L13<>0),L13/I13,"") -> 0.53789932 | N13: =IF(AND(J13<>0, J13<>"", I13<>0, I13<>""), L13-I13, "") -> -68.726718 | P13: =IF(AND(O13<>"", O13<>0, L13<>"", L13<>0), -O13+L13, "") | Q13: =IF(AND(P13<>"", P13<>0, O13<>0, O13<>""), P13/O13, "") | S13: =T12/S12 -> 0.60182941 | T13: =S13/J14*I14 -> 0.60182941
F14: Кол-во смен план/отработано | I14: =График!AI28 -> 20 | J14: 20 | K14: =IF(AND(I14<>"", I14<>0, J14<>""), J14/I14, "") -> 1 | L14: =I14 -> 20 | M14: =IF(AND(I14<>"",I14<>0,L14<>"",L14<>0),L14/I14,"") -> 1 | N14: =IF(AND(J14<>0, J14<>"", I14<>0, I14<>""), L14-I14, "") -> 0 | P14: =IF(AND(O14<>"", O14<>0, L14<>"", L14<>0), -O14+L14, "") | Q14: =IF(AND(P14<>"", P14<>0, O14<>0, O14<>""), P14/O14, "")
F15: Средние продажи в смену | I15: ='Ялта, Ленина, 18'!I15 -> 154639.28 | J15: =J8/J14 -> 35899.05 | K15: =IF(AND(I15<>"", I15<>0, J15<>""), J15/I15, "") -> 0.23214704 | L15: =J15 -> 35899.05 | M15: =IF(AND(I15<>"",I15<>0,L15<>"",L15<>0),L15/I15,"") -> 0.23214704 | N15: =IF(AND(J15<>0, J15<>"", I15<>0, I15<>""), L15-I15, "") -> -118740.23 | P15: =IF(AND(O15<>"", O15<>0, L15<>"", L15<>0), -O15+L15, "") | Q15: =IF(AND(P15<>"", P15<>0, O15<>0, O15<>""), P15/O15, "")
F16: Отставание/Перевыполнение | J16: =J8-I15*J14 -> -2374804.5 | K16: =IF(AND(I16<>"", I16<>0, J16<>""), J16/I16, "") | L16: =J16 -> -2374804.5 | M16: =IF(AND(I16<>"",I16<>0,L16<>"",L16<>0),L16/I16,"") | N16: =IF(AND(J16<>0, J16<>"", I16<>0, I16<>""), L16-I16, "") | P16: =IF(AND(O16<>"", O16<>0, L16<>"", L16<>0), -O16+L16, "") | Q16: =IF(AND(P16<>"", P16<>0, O16<>0, O16<>""), P16/O16, "") | S16: UNOde50
F17: Трафик | I17: ='Ялта, Ленина, 18'!I17/График!AJ31*График!AJ28 -> 676.03053 | J17: =I50 -> 359 | K17: =IF(AND(I17<>"", I17<>0, J17<>""), J17/I17, "") -> 0.5310411 | L17: =J17/J14*I14 -> 359 | M17: =IF(AND(I17<>"",I17<>0,L17<>"",L17<>0),L17/I17,"") -> 0.5310411 | N17: =IF(AND(J17<>0, J17<>"", I17<>0, I17<>""), L17-I17, "") -> -317.03053 | P17: =IF(AND(O17<>"", O17<>0, L17<>"", L17<>0), -O17+L17, "") | Q17: =IF(AND(P17<>"", P17<>0, O17<>0, O17<>""), P17/O17, "")
K18: =IF(AND(I18<>"", I18<>0, J18<>""), J18/I18, "") | L18: =J18 -> 0 | M18: =IF(AND(I18<>"",I18<>0,L18<>"",L18<>0),L18/I18,"") | N18: =IF(AND(J18<>0, J18<>"", I18<>0, I18<>""), L18-I18, "") | O18: 0 | P18: =IF(AND(O18<>"", O18<>0, L18<>"", L18<>0), -O18+L18, "") | Q18: =IF(AND(P18<>"", P18<>0, O18<>0, O18<>""), P18/O18, "") | S18: ='Ялта, Ленина, 18'!S18*График!AJ28/График!AJ31 -> 150229.01 | T18: =K50 -> 148123
J19: =M50 -> 0 | K19: =IF(AND(I19<>"", I19<>0, J19<>""), J19/I19, "") | L19: =J19 -> 0 | M19: =IF(AND(I19<>"",I19<>0,L19<>"",L19<>0),L19/I19,"") | N19: =IF(AND(J19<>0, J19<>"", I19<>0, I19<>""), L19-I19, "") | O19: 0 | P19: =IF(AND(O19<>"", O19<>0, L19<>"", L19<>0), -O19+L19, "") | Q19: =IF(AND(P19<>"", P19<>0, O19<>0, O19<>""), P19/O19, "") | S19: =T18/S18 -> 0.98598135 | T19: =S19/J14*I14 -> 0.98598135
F20: Конверсия план/факт | I20: ='Ялта, Ленина, 18'!I20 -> 0.22 | J20: =N50 -> 0.22284123 | K20: =J20/I20 -> 1.0129147 | L20: =IF(AND(K8<>0,I14<>0,I50<>0),(I50*N50+(I50/K8-I50)*I20)/(I50/K8),0) -> 0.22135964 | M20: =IF(AND(I20<>"",I20<>0,L20<>"",L20<>0),L20/I20,"") -> 1.0061802 | N20: =IF(AND(J20<>0, J20<>"", I20<>0, I20<>""), L20-I20, "") -> 0.0013596421 | P20: =IF(AND(O20<>"", O20<>0, L20<>"", L20<>0), -O20+L20, "") | Q20: =IF(AND(P20<>"", P20<>0, O20<>0, O20<>""), P20/O20, "")
B22: Факт продаж за месяц | O22: % выполнения дневного плана | P22: Раcпределение плана по дням
B23: Дата | C23: День недели | D23: Выручка (руб) | E23: Кол-во единиц (шт.) | F23: Средняя стоимость изделия (руб.) | G23: Количество чеков (шт.) | H23: Средняя сумма чека (руб.) | I23: Трафик | J23: Длина чека (шт.) | K23: UNOde50 | L23: IS | M23: Запасной | N23: Конверсия (%) | P23: выручка, план | Q23: кол-во ед, план | R23: Кол-во чеков, план | S23: выручка, скорректир.план | T23: кол-во ед, скорр. план | U23: кол-во чеков, скорр. план | V23: Коэфф. Дня Недели | W23: Специфика месяца
B24: 1 | C24: 2 | D24: 3 | E24: в | F24: 5 | G24: 6 | H24: 7 | I24: 8 | J24: 9 | K24: 10 | L24: 11 | M24: 12 | N24: 13 | P24: 1 | Q24: 2 | R24: 3 | S24: 4 | T24: 5 | U24: 6 | V24: 10 | W24: 11
A25: 1 | B25: 45778 | C25: чт | D25: =20747+L25 -> 32153 | E25: 7 | F25: =IF(AND(E25<>"",E25<>0),D25/E25,"") -> 4593.2857 | G25: 5 | H25: =IF(AND(G25<>"",G25<>0),D25/G25,"") -> 6430.6 | I25: 35 | J25: =IF(AND(G25<>"",G25<>0),E25/G25,"") -> 1.4 | K25: 0 | L25: =5503+5903 -> 11406 | N25: =IF(AND(I25<>"",I25<>0),G25/I25,"") -> 0.14285714 | O25: =D25/P25 -> 0.53853571 | P25: =$I$8*V25*W25/SUMPRODUCT($W$25:$W$55,$V$25:$V$55) -> 59704.491 | Q25: =$I$9*V25*W25/SUMPRODUCT($W$25:$W$55,$V$25:$V$55) -> 11.481633 | R25: =IF($I$12="","",Q25/$I$12) -> 5.9183674 | S25: =IF(D25<>"",D25,P25) -> 32153 | T25: =IF(E25<>"",E25,Q25) -> 7 | U25: =IF(G25<>"",G25,R25) -> 5 | V25: 0.9004852 | W25: 0.9004852
A26: 2 | B26: 45779 | C26: пт | D26: 44801 | E26: 11 | F26: =IF(AND(E26<>"",E26<>0),D26/E26,"") -> 4072.8182 | G26: 7 | H26: =IF(AND(G26<>"",G26<>0),D26/G26,"") -> 6400.1429 | I26: 35 | J26: =IF(AND(G26<>"",G26<>0),E26/G26,"") -> 1.5714286 | N26: =IF(AND(I26<>"",I26<>0),G26/I26,"") -> 0.2 | O26: =D26/P26 -> 0.54031511 | P26: =$I$8*V26*W26/SUMPRODUCT($W$25:$W$55,$V$25:$V$55) -> 82916.43 | Q26: =$I$9*V26*W26/SUMPRODUCT($W$25:$W$55,$V$25:$V$55) -> 15.945467 | R26: =IF($I$12="","",Q26/$I$12) -> 8.219313 | S26: =IF(W26<>"",IF(D26<>"",D26,($I$8-SUM($S$25:S25))*V26*W26/SUMPRODUCT($W26:$W$55,$V26:$V$55)),"") -> 44801 | T26: =IF(W26<>"",IF(E26<>"",E26,($I$9-SUM($T$25:T25))*V26*W26/SUMPRODUCT($W26:$W$55,$V26:$V$55)),"") -> 11 | U26: =IF(W26<>"",IF($I$12<>"",IF(G26<>"",G26,($I$9/$I$12-SUM($U$25:U25))*V26*W26/SUMPRODUCT($W26:$W$55,$V26:$V$55)),""),"") -> 7 | V26: 1.0611906 | W26: 1.0611906
A27: 3 | B27: 45780 | C27: сб | D27: =38424+L27 -> 54830 | E27: 11 | F27: =IF(AND(E27<>"",E27<>0),D27/E27,"") -> 4984.5455 | G27: 7 | H27: =IF(AND(G27<>"",G27<>0),D27/G27,"") -> 7832.8571 | I27: 23 | J27: =IF(AND(G27<>"",G27<>0),E27/G27,"") -> 1.5714286 | L27: =8903+7503 -> 16406 | N27: =IF(AND(I27<>"",I27<>0),G27/I27,"") -> 0.30434783 | O27: =D27/P27 -> 0.51713259 | P27: =$I$8*V27*W27/SUMPRODUCT($W$25:$W$55,$V$25:$V$55) -> 106026.97 | Q27: =$I$9*V27*W27/SUMPRODUCT($W$25:$W$55,$V$25:$V$55) -> 20.389801 | R27: =IF($I$12="","",Q27/$I$12) -> 10.510207 | S27: =IF(W27<>"",IF(D27<>"",D27,($I$8-SUM($S$25:S26))*V27*W27/SUMPRODUCT($W27:$W$55,$V27:$V$55)),"") -> 54830 | T27: =IF(W27<>"",IF(E27<>"",E27,($I$9-SUM($T$25:T26))*V27*W27/SUMPRODUCT($W27:$W$55,$V27:$V$55)),"") -> 11 | U27: =IF(W27<>"",IF($I$12<>"",IF(G27<>"",G27,($I$9/$I$12-SUM($U$25:U26))*V27*W27/SUMPRODUCT($W27:$W$55,$V27:$V$55)),""),"") -> 7 | V27: 1.2 | W27: 1.2
A28: 4 | B28: 45783 | C28: вт | D28: 9983 | E28: 2 | F28: =IF(AND(E28<>"",E28<>0),D28/E28,"") -> 4991.5 | G28: 1 | H28: =IF(AND(G28<>"",G28<>0),D28/G28,"") -> 9983 | I28: 20 | J28: =IF(AND(G28<>"",G28<>0),E28/G28,"") -> 2 | N28: =IF(AND(I28<>"",I28<>0),G28/I28,"") -> 0.05 | O28: =D28/P28 -> 0.13558362 | P28: =$I$8*V28*W28/SUMPRODUCT($W$25:$W$60,$V$25:$V$60) -> 73629.838 | Q28: =$I$9*V28*W28/SUMPRODUCT($W$25:$W$60,$V$25:$V$60) -> 14.159584 | R28: =IF($I$12="","",Q28/$I$12) -> 7.2987547 | S28: =IF(W28<>"",IF(D28<>"",D28,($I$8-SUM($S$25:S27))*V28*W28/SUMPRODUCT($W28:$W$60,$V28:$V$60)),"") -> 9983 | T28: =IF(W28<>"",IF(E28<>"",E28,($I$9-SUM($T$25:T27))*V28*W28/SUMPRODUCT($W28:$W$60,$V28:$V$60)),"") -> 2 | U28: =IF(W28<>"",IF($I$12<>"",IF(G28<>"",G28,($I$9/$I$12-SUM($U$25:U27))*V28*W28/SUMPRODUCT($W28:$W$60,$V28:$V$60)),""),"") -> 1 | V28: 1 | W28: 1
A29: 5 | B29: 45784 | C29: ср | D29: =45106+13403 -> 58509 | E29: 13 | F29: =IF(AND(E29<>"",E29<>0),D29/E29,"") -> 4500.6923 | G29: 6 | H29: =IF(AND(G29<>"",G29<>0),D29/G29,"") -> 9751.5 | I29: 20 | J29: =IF(AND(G29<>"",G29<>0),E29/G29,"") -> 2.1666667 | L29: 13403 | N29: =IF(AND(I29<>"",I29<>0),G29/I29,"") -> 0.3 | O29: =D29/P29 -> 0.79463709 | P29: =$I$8*V29*W29/SUMPRODUCT($W$25:$W$55,$V$25:$V$55) -> 73629.838 | Q29: =$I$9*V29*W29/SUMPRODUCT($W$25:$W$55,$V$25:$V$55) -> 14.159584 | R29: =IF($I$12="","",Q29/$I$12) -> 7.2987547 | S29: =IF(W29<>"",IF(D29<>"",D29,($I$8-SUM($S$25:S28))*V29*W29/SUMPRODUCT($W29:$W$55,$V29:$V$55)),"") -> 58509 | T29: =IF(W29<>"",IF(E29<>"",E29,($I$9-SUM($T$25:T28))*V29*W29/SUMPRODUCT($W29:$W$55,$V29:$V$55)),"") -> 13 | U29: =IF(W29<>"",IF($I$12<>"",IF(G29<>"",G29,($I$9/$I$12-SUM($U$25:U28))*V29*W29/SUMPRODUCT($W29:$W$55,$V29:$V$55)),""),"") -> 6 | V29: 1 | W29: 1
A30: 6 | B30: 45786 | C30: пт | D30: =13066+36982+27827 -> 77875 | E30: 9 | F30: =IF(AND(E30<>"",E30<>0),D30/E30,"") -> 8652.7778 | G30: 3 | H30: =IF(AND(G30<>"",G30<>0),D30/G30,"") -> 25958.333 | I30: 20 | J30: =IF(AND(G30<>"",G30<>0),E30/G30,"") -> 3 | K30: 36982 | L30: 27827 | N30: =IF(AND(I30<>"",I30<>0),G30/I30,"") -> 0.15 | O30: =D30/P30 -> 1.0576555 | P30: =$I$8*V30*W30/SUMPRODUCT($W$25:$W$55,$V$25:$V$55) -> 73629.838 | Q30: =$I$9*V30*W30/SUMPRODUCT($W$25:$W$55,$V$25:$V$55) -> 14.159584 | R30: =IF($I$12="","",Q30/$I$12) -> 7.2987547 | S30: =IF(W30<>"",IF(D30<>"",D30,($I$8-SUM($S$25:S29))*V30*W30/SUMPRODUCT($W30:$W$55,$V30:$V$55)),"") -> 77875 | T30: =IF(W30<>"",IF(E30<>"",E30,($I$9-SUM($T$25:T29))*V30*W30/SUMPRODUCT($W30:$W$55,$V30:$V$55)),"") -> 9 | U30: =IF(W30<>"",IF($I$12<>"",IF(G30<>"",G30,($I$9/$I$12-SUM($U$25:U29))*V30*W30/SUMPRODUCT($W30:$W$55,$V30:$V$55)),""),"") -> 3 | V30: 1 | W30: 1
A31: 7 | B31: 45787 | C31: сб | D31: 2892 | E31: 1 | F31: =IF(AND(E31<>"",E31<>0),D31/E31,"") -> 2892 | G31: 1 | H31: =IF(AND(G31<>"",G31<>0),D31/G31,"") -> 2892 | I31: 10 | J31: =IF(AND(G31<>"",G31<>0),E31/G31,"") -> 1 | N31: =IF(AND(I31<>"",I31<>0),G31/I31,"") -> 0.1 | O31: =D31/P31 -> 0.039277555 | P31: =$I$8*V31*W31/SUMPRODUCT($W$25:$W$55,$V$25:$V$55) -> 73629.838 | Q31: =$I$9*V31*W31/SUMPRODUCT($W$25:$W$55,$V$25:$V$55) -> 14.159584 | R31: =IF($I$12="","",Q31/$I$12) -> 7.2987547 | S31: =IF(W31<>"",IF(D31<>"",D31,($I$8-SUM($S$25:S30))*V31*W31/SUMPRODUCT($W31:$W$55,$V31:$V$55)),"") -> 2892 | T31: =IF(W31<>"",IF(E31<>"",E31,($I$9-SUM($T$25:T30))*V31*W31/SUMPRODUCT($W31:$W$55,$V31:$V$55)),"") -> 1 | U31: =IF(W31<>"",IF($I$12<>"",IF(G31<>"",G31,($I$9/$I$12-SUM($U$25:U30))*V31*W31/SUMPRODUCT($W31:$W$55,$V31:$V$55)),""),"") -> 1 | V31: 1 | W31: 1
A32: 8 | B32: 45788 | C32: вс | D32: =15368+38984+14026 -> 68378 | E32: 8 | F32: =IF(AND(E32<>"",E32<>0),D32/E32,"") -> 8547.25 | G32: 7 | H32: =IF(AND(G32<>"",G32<>0),D32/G32,"") -> 9768.2857 | I32: 25 | J32: =IF(AND(G32<>"",G32<>0),E32/G32,"") -> 1.1428571 | K32: 38984 | L32: 14026 | N32: =IF(AND(I32<>"",I32<>0),G32/I32,"") -> 0.28 | O32: =D32/P32 -> 0.92867243 | P32: =$I$8*V32*W32/SUMPRODUCT($W$25:$W$55,$V$25:$V$55) -> 73629.838 | Q32: =$I$9*V32*W32/SUMPRODUCT($W$25:$W$55,$V$25:$V$55) -> 14.159584 | R32: =IF($I$12="","",Q32/$I$12) -> 7.2987547 | S32: =IF(W32<>"",IF(D32<>"",D32,($I$8-SUM($S$25:S31))*V32*W32/SUMPRODUCT($W32:$W$55,$V32:$V$55)),"") -> 68378 | T32: =IF(W32<>"",IF(E31<>"",E31,($I$9-SUM($T$25:T31))*V32*W32/SUMPRODUCT($W32:$W$55,$V32:$V$55)),"") -> 1 | U32: =IF(W32<>"",IF($I$12<>"",IF(G32<>"",G32,($I$9/$I$12-SUM($U$25:U31))*V32*W32/SUMPRODUCT($W32:$W$55,$V32:$V$55)),""),"") -> 7 | V32: 1 | W32: 1
A33: 9 | B33: 45791 | C33: ср | D33: 7084 | E33: 2 | F33: =IF(AND(E33<>"",E33<>0),D33/E33,"") -> 3542 | G33: 2 | H33: =IF(AND(G33<>"",G33<>0),D33/G33,"") -> 3542 | I33: 10 | J33: =IF(AND(G33<>"",G33<>0),E33/G33,"") -> 1 | N33: =IF(AND(I33<>"",I33<>0),G33/I33,"") -> 0.2 | O33: =D33/P33 -> 0.096210996 | P33: =$I$8*V33*W33/SUMPRODUCT($W$25:$W$55,$V$25:$V$55) -> 73629.838 | Q33: =$I$9*V33*W33/SUMPRODUCT($W$25:$W$55,$V$25:$V$55) -> 14.159584 | R33: =IF($I$12="","",Q33/$I$12) -> 7.2987547 | S33: =IF(W33<>"",IF(D33<>"",D33,($I$8-SUM($S$25:S32))*V33*W33/SUMPRODUCT($W33:$W$55,$V33:$V$55)),"") -> 7084 | T33: =IF(W33<>"",IF(E33<>"",E33,($I$9-SUM($T$25:T32))*V33*W33/SUMPRODUCT($W33:$W$55,$V33:$V$55)),"") -> 2 | U33: =IF(W33<>"",IF($I$12<>"",IF(G33<>"",G33,($I$9/$I$12-SUM($U$25:U32))*V33*W33/SUMPRODUCT($W33:$W$55,$V33:$V$55)),""),"") -> 2 | V33: 1 | W33: 1
A34: 10 | B34: 45792 | C34: чт | D34: =33713+7903 -> 41616 | E34: 11 | F34: =IF(AND(E34<>"",E34<>0),D34/E34,"") -> 3783.2727 | G34: 4 | H34: =IF(AND(G34<>"",G34<>0),D34/G34,"") -> 10404 | I34: 15 | J34: =IF(AND(G34<>"",G34<>0),E34/G34,"") -> 2.75 | L34: 7903 | N34: =IF(AND(I34<>"",I34<>0),G34/I34,"") -> 0.26666667 | O34: =D34/P34 -> 0.56520565 | P34: =$I$8*V34*W34/SUMPRODUCT($W$25:$W$60,$V$25:$V$60) -> 73629.838 | Q34: =$I$9*V34*W34/SUMPRODUCT($W$25:$W$60,$V$25:$V$60) -> 14.159584 | R34: =IF($I$12="","",Q34/$I$12) -> 7.2987547 | S34: =IF(W34<>"",IF(D34<>"",D34,($I$8-SUM($S$25:S33))*V34*W34/SUMPRODUCT($W34:$W$60,$V34:$V$60)),"") -> 41616 | T34: =IF(W34<>"",IF(E34<>"",E34,($I$9-SUM($T$25:T33))*V34*W34/SUMPRODUCT($W34:$W$60,$V34:$V$60)),"") -> 11 | U34: =IF(W34<>"",IF($I$12<>"",IF(G34<>"",G34,($I$9/$I$12-SUM($U$25:U33))*V34*W34/SUMPRODUCT($W34:$W$60,$V34:$V$60)),""),"") -> 4 | V34: 1 | W34: 1
A35: 11 | B35: 45793 | C35: пт | D35: =7383+3892+55166 -> 66441 | E35: 7 | F35: =IF(AND(E35<>"",E35<>0),D35/E35,"") -> 9491.5714 | G35: 3 | H35: =IF(AND(G35<>"",G35<>0),D35/G35,"") -> 22147 | I35: 15 | J35: =IF(AND(G35<>"",G35<>0),E35/G35,"") -> 2.3333333 | K35: 55166 | N35: =IF(AND(I35<>"",I35<>0),G35/I35,"") -> 0.2 | O35: =D35/P35 -> 0.90236516 | P35: =$I$8*V35*W35/SUMPRODUCT($W$25:$W$55,$V$25:$V$55) -> 73629.838 | Q35: =$I$9*V35*W35/SUMPRODUCT($W$25:$W$55,$V$25:$V$55) -> 14.159584 | R35: =IF($I$12="","",Q35/$I$12) -> 7.2987547 | S35: =IF(W35<>"",IF(D35<>"",D35,($I$8-SUM($S$25:S34))*V35*W35/SUMPRODUCT($W35:$W$55,$V35:$V$55)),"") -> 66441 | T35: =IF(W35<>"",IF(E35<>"",E35,($I$9-SUM($T$25:T34))*V35*W35/SUMPRODUCT($W35:$W$55,$V35:$V$55)),"") -> 7 | U35: =IF(W35<>"",IF($I$12<>"",IF(G35<>"",G35,($I$9/$I$12-SUM($U$25:U34))*V35*W35/SUMPRODUCT($W35:$W$55,$V35:$V$55)),""),"") -> 3 | V35: 1 | W35: 1
A36: 12 | B36: 45796 | C36: пн | D36: 22558 | E36: 5 | F36: =IF(AND(E36<>"",E36<>0),D36/E36,"") -> 4511.6 | G36: 3 | H36: =IF(AND(G36<>"",G36<>0),D36/G36,"") -> 7519.3333 | I36: 10 | J36: =IF(AND(G36<>"",G36<>0),E36/G36,"") -> 1.6666667 | N36: =IF(AND(I36<>"",I36<>0),G36/I36,"") -> 0.3 | O36: =D36/P36 -> 0.30637036 | P36: =$I$8*V36*W36/SUMPRODUCT($W$25:$W$55,$V$25:$V$55) -> 73629.838 | Q36: =$I$9*V36*W36/SUMPRODUCT($W$25:$W$55,$V$25:$V$55) -> 14.159584 | R36: =IF($I$12="","",Q36/$I$12) -> 7.2987547 | S36: =IF(W36<>"",IF(D36<>"",D36,($I$8-SUM($S$25:S35))*V36*W36/SUMPRODUCT($W36:$W$55,$V36:$V$55)),"") -> 22558 | T36: =IF(W36<>"",IF(E36<>"",E36,($I$9-SUM($T$25:T35))*V36*W36/SUMPRODUCT($W36:$W$55,$V36:$V$55)),"") -> 5 | U36: =IF(W36<>"",IF($I$12<>"",IF(G36<>"",G36,($I$9/$I$12-SUM($U$25:U35))*V36*W36/SUMPRODUCT($W36:$W$55,$V36:$V$55)),""),"") -> 3 | V36: 1 | W36: 1
A37: 13 | B37: 45797 | C37: вт | D37: 5692 | E37: 1 | F37: =IF(AND(E37<>"",E37<>0),D37/E37,"") -> 5692 | G37: 1 | H37: =IF(AND(G37<>"",G37<>0),D37/G37,"") -> 5692 | I37: 7 | J37: =IF(AND(G37<>"",G37<>0),E37/G37,"") -> 1 | N37: =IF(AND(I37<>"",I37<>0),G37/I37,"") -> 0.14285714 | O37: =D37/P37 -> 0.077305617 | P37: =$I$8*V37*W37/SUMPRODUCT($W$25:$W$55,$V$25:$V$55) -> 73629.838 | Q37: =$I$9*V37*W37/SUMPRODUCT($W$25:$W$55,$V$25:$V$55) -> 14.159584 | R37: =IF($I$12="","",Q37/$I$12) -> 7.2987547 | S37: =IF(W37<>"",IF(D37<>"",D37,($I$8-SUM($S$25:S36))*V37*W37/SUMPRODUCT($W37:$W$55,$V37:$V$55)),"") -> 5692 | T37: =IF(W37<>"",IF(E37<>"",E37,($I$9-SUM($T$25:T36))*V37*W37/SUMPRODUCT($W37:$W$55,$V37:$V$55)),"") -> 1 | U37: =IF(W37<>"",IF($I$12<>"",IF(G37<>"",G37,($I$9/$I$12-SUM($U$25:U36))*V37*W37/SUMPRODUCT($W37:$W$55,$V37:$V$55)),""),"") -> 1 | V37: 1 | W37: 1
A38: 14 | B38: 45798 | C38: ср | D38: 17856 | E38: 4 | F38: =IF(AND(E38<>"",E38<>0),D38/E38,"") -> 4464 | G38: 3 | H38: =IF(AND(G38<>"",G38<>0),D38/G38,"") -> 5952 | I38: 15 | J38: =IF(AND(G38<>"",G38<>0),E38/G38,"") -> 1.3333333 | N38: =IF(AND(I38<>"",I38<>0),G38/I38,"") -> 0.2 | O38: =D38/P38 -> 0.24251038 | P38: =$I$8*V38*W38/SUMPRODUCT($W$25:$W$55,$V$25:$V$55) -> 73629.838 | Q38: =$I$9*V38*W38/SUMPRODUCT($W$25:$W$55,$V$25:$V$55) -> 14.159584 | R38: =IF($I$12="","",Q38/$I$12) -> 7.2987547 | S38: =IF(W38<>"",IF(D38<>"",D38,($I$8-SUM($S$25:S37))*V38*W38/SUMPRODUCT($W38:$W$55,$V38:$V$55)),"") -> 17856 | T38: =IF(W38<>"",IF(E38<>"",E38,($I$9-SUM($T$25:T37))*V38*W38/SUMPRODUCT($W38:$W$55,$V38:$V$55)),"") -> 4 | U38: =IF(W38<>"",IF($I$12<>"",IF(G38<>"",G38,($I$9/$I$12-SUM($U$25:U37))*V38*W38/SUMPRODUCT($W38:$W$55,$V38:$V$55)),""),"") -> 3 | V38: 1 | W38: 1
A39: 15 | B39: 45801 | C39: сб | D39: =30772+14806 -> 45578 | E39: 9 | F39: =IF(AND(E39<>"",E39<>0),D39/E39,"") -> 5064.2222 | G39: 6 | H39: =IF(AND(G39<>"",G39<>0),D39/G39,"") -> 7596.3333 | I39: 17 | J39: =IF(AND(G39<>"",G39<>0),E39/G39,"") -> 1.5 | L39: 14806 | N39: =IF(AND(I39<>"",I39<>0),G39/I39,"") -> 0.35294118 | O39: =D39/P39 -> 0.61901535 | P39: =$I$8*V39*W39/SUMPRODUCT($W$25:$W$60,$V$25:$V$60) -> 73629.838 | Q39: =$I$9*V39*W39/SUMPRODUCT($W$25:$W$60,$V$25:$V$60) -> 14.159584 | R39: =IF($I$12="","",Q39/$I$12) -> 7.2987547 | S39: =IF(W39<>"",IF(D39<>"",D39,($I$8-SUM($S$25:S38))*V39*W39/SUMPRODUCT($W39:$W$60,$V39:$V$60)),"") -> 45578 | T39: =IF(W39<>"",IF(E39<>"",E39,($I$9-SUM($T$25:T38))*V39*W39/SUMPRODUCT($W39:$W$60,$V39:$V$60)),"") -> 9 | U39: =IF(W39<>"",IF($I$12<>"",IF(G39<>"",G39,($I$9/$I$12-SUM($U$25:U38))*V39*W39/SUMPRODUCT($W39:$W$60,$V39:$V$60)),""),"") -> 6 | V39: 1 | W39: 1
A40: 16 | B40: 45802 | C40: вс | D40: 10284 | E40: 2 | F40: =IF(AND(E40<>"",E40<>0),D40/E40,"") -> 5142 | G40: 2 | H40: =IF(AND(G40<>"",G40<>0),D40/G40,"") -> 5142 | I40: 15 | J40: =IF(AND(G40<>"",G40<>0),E40/G40,"") -> 1 | N40: =IF(AND(I40<>"",I40<>0),G40/I40,"") -> 0.13333333 | O40: =D40/P40 -> 0.13967164 | P40: =$I$8*V40*W40/SUMPRODUCT($W$25:$W$60,$V$25:$V$60) -> 73629.838 | Q40: =$I$9*V40*W40/SUMPRODUCT($W$25:$W$60,$V$25:$V$60) -> 14.159584 | R40: =IF($I$12="","",Q40/$I$12) -> 7.2987547 | S40: =IF(W40<>"",IF(D40<>"",D40,($I$8-SUM($S$25:S39))*V40*W40/SUMPRODUCT($W40:$W$60,$V40:$V$60)),"") -> 10284 | T40: =IF(W40<>"",IF(E40<>"",E40,($I$9-SUM($T$25:T39))*V40*W40/SUMPRODUCT($W40:$W$60,$V40:$V$60)),"") -> 2 | U40: =IF(W40<>"",IF($I$12<>"",IF(G40<>"",G40,($I$9/$I$12-SUM($U$25:U39))*V40*W40/SUMPRODUCT($W40:$W$60,$V40:$V$60)),""),"") -> 2 | V40: 1 | W40: 1
A41: 17 | B41: 45803 | C41: пн | D41: 5883 | E41: 2 | F41: =IF(AND(E41<>"",E41<>0),D41/E41,"") -> 2941.5 | G41: 1 | H41: =IF(AND(G41<>"",G41<>0),D41/G41,"") -> 5883 | I41: 10 | J41: =IF(AND(G41<>"",G41<>0),E41/G41,"") -> 2 | N41: =IF(AND(I41<>"",I41<>0),G41/I41,"") -> 0.1 | O41: =D41/P41 -> 0.079899674 | P41: =$I$8*V41*W41/SUMPRODUCT($W$25:$W$60,$V$25:$V$60) -> 73629.838 | Q41: =$I$9*V41*W41/SUMPRODUCT($W$25:$W$60,$V$25:$V$60) -> 14.159584 | R41: =IF($I$12="","",Q41/$I$12) -> 7.2987547 | S41: =IF(W41<>"",IF(D41<>"",D41,($I$8-SUM($S$25:S40))*V41*W41/SUMPRODUCT($W41:$W$60,$V41:$V$60)),"") -> 5883 | T41: =IF(W41<>"",IF(E41<>"",E41,($I$9-SUM($T$25:T40))*V41*W41/SUMPRODUCT($W41:$W$60,$V41:$V$60)),"") -> 2 | U41: =IF(W41<>"",IF($I$12<>"",IF(G41<>"",G41,($I$9/$I$12-SUM($U$25:U40))*V41*W41/SUMPRODUCT($W41:$W$60,$V41:$V$60)),""),"") -> 1 | V41: 1 | W41: 1
A42: 18 | B42: 29.мая | C42: чт | D42: 25951 | E42: 6 | F42: =IF(AND(E42<>"",E42<>0),D42/E42,"") -> 4325.1667 | G42: 5 | H42: =IF(AND(G42<>"",G42<>0),D42/G42,"") -> 5190.2 | I42: 20 | J42: =IF(AND(G42<>"",G42<>0),E42/G42,"") -> 1.2 | N42: =IF(AND(I42<>"",I42<>0),G42/I42,"") -> 0.25 | O42: =D42/P42 -> 0.35245222 | P42: =$I$8*V42*W42/SUMPRODUCT($W$25:$W$60,$V$25:$V$60) -> 73629.838 | Q42: =$I$9*V42*W42/SUMPRODUCT($W$25:$W$60,$V$25:$V$60) -> 14.159584 | R42: =IF($I$12="","",Q42/$I$12) -> 7.2987547 | S42: =IF(W42<>"",IF(D42<>"",D42,($I$8-SUM($S$25:S41))*V42*W42/SUMPRODUCT($W42:$W$60,$V42:$V$60)),"") -> 25951 | T42: =IF(W42<>"",IF(E42<>"",E42,($I$9-SUM($T$25:T41))*V42*W42/SUMPRODUCT($W42:$W$60,$V42:$V$60)),"") -> 6 | U42: =IF(W42<>"",IF($I$12<>"",IF(G42<>"",G42,($I$9/$I$12-SUM($U$25:U41))*V42*W42/SUMPRODUCT($W42:$W$60,$V42:$V$60)),""),"") -> 5 | V42: 1 | W42: 1
A43: 19 | B43: 30мая | C43: пт | D43: =33433+6203 -> 39636 | E43: 9 | F43: =IF(AND(E43<>"",E43<>0),D43/E43,"") -> 4404 | G43: 6 | H43: =IF(AND(G43<>"",G43<>0),D43/G43,"") -> 6606 | I43: 17 | J43: =IF(AND(G43<>"",G43<>0),E43/G43,"") -> 1.5 | L43: 6203 | N43: =IF(AND(I43<>"",I43<>0),G43/I43,"") -> 0.35294118 | O43: =D43/P43 -> 0.53831437 | P43: =$I$8*V43*W43/SUMPRODUCT($W$25:$W$60,$V$25:$V$60) -> 73629.838 | Q43: =$I$9*V43*W43/SUMPRODUCT($W$25:$W$60,$V$25:$V$60) -> 14.159584 | R43: =IF($I$12="","",Q43/$I$12) -> 7.2987547 | S43: =IF(W43<>"",IF(D43<>"",D43,($I$8-SUM($S$25:S42))*V43*W43/SUMPRODUCT($W43:$W$60,$V43:$V$60)),"") -> 39636 | T43: =IF(W43<>"",IF(E43<>"",E43,($I$9-SUM($T$25:T42))*V43*W43/SUMPRODUCT($W43:$W$60,$V43:$V$60)),"") -> 9 | U43: =IF(W43<>"",IF($I$12<>"",IF(G43<>"",G43,($I$9/$I$12-SUM($U$25:U42))*V43*W43/SUMPRODUCT($W43:$W$60,$V43:$V$60)),""),"") -> 6 | V43: 1 | W43: 1
A44: 20 | B44: 31мая | C44: сб | D44: =25333+16991+16104 -> 58428 | E44: 11 | F44: =IF(AND(E44<>"",E44<>0),D44/E44,"") -> 5311.6364 | G44: 6 | H44: =IF(AND(G44<>"",G44<>0),D44/G44,"") -> 9738 | I44: 20 | J44: =IF(AND(G44<>"",G44<>0),E44/G44,"") -> 1.8333333 | K44: 16991 | L44: 16104 | N44: =IF(AND(I44<>"",I44<>0),G44/I44,"") -> 0.3 | O44: =D44/P44 -> 0.79353699 | P44: =$I$8*V44*W44/SUMPRODUCT($W$25:$W$60,$V$25:$V$60) -> 73629.838 | Q44: =$I$9*V44*W44/SUMPRODUCT($W$25:$W$60,$V$25:$V$60) -> 14.159584 | R44: =IF($I$12="","",Q44/$I$12) -> 7.2987547 | S44: =IF(W44<>"",IF(D44<>"",D44,($I$8-SUM($S$25:S43))*V44*W44/SUMPRODUCT($W44:$W$60,$V44:$V$60)),"") -> 58428 | T44: =IF(W44<>"",IF(E44<>"",E44,($I$9-SUM($T$25:T43))*V44*W44/SUMPRODUCT($W44:$W$60,$V44:$V$60)),"") -> 11 | U44: =IF(W44<>"",IF($I$12<>"",IF(G44<>"",G44,($I$9/$I$12-SUM($U$25:U43))*V44*W44/SUMPRODUCT($W44:$W$60,$V44:$V$60)),""),"") -> 6 | V44: 1 | W44: 1
A45: 21 | F45: =IF(AND(E45<>"",E45<>0),D45/E45,"") | H45: =IF(AND(G45<>"",G45<>0),D45/G45,"") | J45: =IF(AND(G45<>"",G45<>0),E45/G45,"") | N45: =IF(AND(I45<>"",I45<>0),G45/I45,"") | O45: =D45/P45 -> #DIV/0! | P45: =$I$8*V45*W45/SUMPRODUCT($W$25:$W$60,$V$25:$V$60) -> 0 | Q45: =$I$9*V45*W45/SUMPRODUCT($W$25:$W$60,$V$25:$V$60) -> 0 | R45: =IF($I$12="","",Q45/$I$12) -> 0 | S45: =IF(W45<>"",IF(D45<>"",D45,($I$8-SUM($S$25:S44))*V45*W45/SUMPRODUCT($W45:$W$60,$V45:$V$60)),"") | T45: =IF(W45<>"",IF(E45<>"",E45,($I$9-SUM($T$25:T44))*V45*W45/SUMPRODUCT($W45:$W$60,$V45:$V$60)),"") | U45: =IF(W45<>"",IF($I$12<>"",IF(G45<>"",G45,($I$9/$I$12-SUM($U$25:U44))*V45*W45/SUMPRODUCT($W45:$W$60,$V45:$V$60)),""),"")
A46: 22 | F46: =IF(AND(E46<>"",E46<>0),D46/E46,"") | H46: =IF(AND(G46<>"",G46<>0),D46/G46,"") | J46: =IF(AND(G46<>"",G46<>0),E46/G46,"") | N46: =IF(AND(I46<>"",I46<>0),G46/I46,"") | O46: =D46/P46 -> #DIV/0! | P46: =$I$8*V46*W46/SUMPRODUCT($W$25:$W$60,$V$25:$V$60) -> 0 | Q46: =$I$9*V46*W46/SUMPRODUCT($W$25:$W$60,$V$25:$V$60) -> 0 | R46: =IF($I$12="","",Q46/$I$12) -> 0 | S46: =IF(W46<>"",IF(D46<>"",D46,($I$8-SUM($S$25:S45))*V46*W46/SUMPRODUCT($W46:$W$60,$V46:$V$60)),"") | T46: =IF(W46<>"",IF(E46<>"",E46,($I$9-SUM($T$25:T45))*V46*W46/SUMPRODUCT($W46:$W$60,$V46:$V$60)),"") | U46: =IF(W46<>"",IF($I$12<>"",IF(G46<>"",G46,($I$9/$I$12-SUM($U$25:U45))*V46*W46/SUMPRODUCT($W46:$W$60,$V46:$V$60)),""),"")
A47: 23 | F47: =IF(AND(E47<>"",E47<>0),D47/E47,"") | H47: =IF(AND(G47<>"",G47<>0),D47/G47,"") | J47: =IF(AND(G47<>"",G47<>0),E47/G47,"") | N47: =IF(AND(I47<>"",I47<>0),G47/I47,"") | O47: =D47/P47 -> #DIV/0! | P47: =$I$8*V47*W47/SUMPRODUCT($W$25:$W$60,$V$25:$V$60) -> 0 | Q47: =$I$9*V47*W47/SUMPRODUCT($W$25:$W$60,$V$25:$V$60) -> 0 | R47: =IF($I$12="","",Q47/$I$12) -> 0 | S47: =IF(W47<>"",IF(D47<>"",D47,($I$8-SUM($S$25:S46))*V47*W47/SUMPRODUCT($W47:$W$60,$V47:$V$60)),"") | T47: =IF(W47<>"",IF(E47<>"",E47,($I$9-SUM($T$25:T46))*V47*W47/SUMPRODUCT($W47:$W$60,$V47:$V$60)),"") | U47: =IF(W47<>"",IF($I$12<>"",IF(G47<>"",G47,($I$9/$I$12-SUM($U$25:U46))*V47*W47/SUMPRODUCT($W47:$W$60,$V47:$V$60)),""),"")
A48: 24 | F48: =IF(AND(E48<>"",E48<>0),D48/E48,"") | H48: =IF(AND(G48<>"",G48<>0),D48/G48,"") | J48: =IF(AND(G48<>"",G48<>0),E48/G48,"") | N48: =IF(AND(I48<>"",I48<>0),G48/I48,"") | O48: =D48/P48 -> #DIV/0! | P48: =$I$8*V48*W48/SUMPRODUCT($W$25:$W$60,$V$25:$V$60) -> 0 | Q48: =$I$9*V48*W48/SUMPRODUCT($W$25:$W$60,$V$25:$V$60) -> 0 | R48: =IF($I$12="","",Q48/$I$12) -> 0 | S48: =IF(W48<>"",IF(D48<>"",D48,($I$8-SUM($S$25:S47))*V48*W48/SUMPRODUCT($W48:$W$60,$V48:$V$60)),"") | T48: =IF(W48<>"",IF(E48<>"",E48,($I$9-SUM($T$25:T47))*V48*W48/SUMPRODUCT($W48:$W$60,$V48:$V$60)),"") | U48: =IF(W48<>"",IF($I$12<>"",IF(G48<>"",G48,($I$9/$I$12-SUM($U$25:U47))*V48*W48/SUMPRODUCT($W48:$W$60,$V48:$V$60)),""),"")
A49: 25 | B49: 45782 | C49: пн | D49: 21553 | E49: 3 | F49: =IF(AND(E49<>"",E49<>0),D49/E49,"") -> 7184.3333 | G49: 1 | H49: =IF(AND(G49<>"",G49<>0),D49/G49,"") -> 21553 | J49: =IF(AND(G49<>"",G49<>0),E49/G49,"") -> 3 | N49: =IF(AND(I49<>"",I49<>0),G49/I49,"") | O49: =D49/P49 -> #DIV/0! | P49: =$I$8*V49*W49/SUMPRODUCT($W$25:$W$60,$V$25:$V$60) -> 0 | Q49: =$I$9*V49*W49/SUMPRODUCT($W$25:$W$60,$V$25:$V$60) -> 0 | R49: =IF($I$12="","",Q49/$I$12) -> 0 | S49: =IF(W49<>"",IF(D49<>"",D49,($I$8-SUM($S$25:S48))*V49*W49/SUMPRODUCT($W49:$W$60,$V49:$V$60)),"") | T49: =IF(W49<>"",IF(E49<>"",E49,($I$9-SUM($T$25:T48))*V49*W49/SUMPRODUCT($W49:$W$60,$V49:$V$60)),"") | U49: =IF(W49<>"",IF($I$12<>"",IF(G49<>"",G49,($I$9/$I$12-SUM($U$25:U48))*V49*W49/SUMPRODUCT($W49:$W$60,$V49:$V$60)),""),"")
B50: итого | D50: =SUM(D25:D49) -> 717981 | E50: =SUM(E25:E49) -> 134 | F50: =IF(AND(E50<>"",E50<>0),D50/E50,"") -> 5358.0672 | G50: =SUM(G25:G49) -> 80 | H50: =IF(AND(G50<>"",G50<>0),D50/G50,"") -> 8974.7625 | I50: =SUM(I25:I49) -> 359 | J50: =IF(AND(G50<>"",G50<>0),E50/G50,"") -> 1.675 | K50: =SUM(K25:K49) -> 148123 | L50: =SUM(L25:L49) -> 128084 | M50: =SUM(M25:M49) -> 0 | N50: =IF(AND(I50<>"",I50<>0),G50/I50,"") -> 0.22284123 | O50: =D50/P50 -> 0.4785407 | P50: =SUM(P25:P49) -> 1500355.1 | Q50: =SUM(Q25:Q49) -> 288.52983 | R50: =SUM(R25:R49) -> 148.72672 | S50: =SUM(S25:S49) -> 696428 | T50: =SUM(T25:T49) -> 124 | U50: =SUM(U25:U49) -> 79
D51: =SUMIF(D25:D49,"",P25:P49)+D50 -> 717981

Sheet Вафина Л. Ф.
B1: =TODAY()-1 -> 46171
B2: (отчетная дата) | J2: ЕЖЕДНЕВНЫЙ ОТЧЕТ О ПРОДАЖАХ
B3: Осталось до выполнения плана!!! | J3: =График!B27 -> Вафина Ляйсан
C4: =I8-D48 -> 713554.07 | E4: =IF(I8<>0,C4/I8,0) -> 0.50212519
F6: Целевые показатели
F7: Показатель | I7: План | J7: Факт | K7: % выполнения | L7: Прогноз выполнения | M7: % выполнения по прогнозу | N7: Отклонение | O7: Факт аналогичного месяца прошлого года | P7: Отклонение LFL
F8: Выручка | I8: ='Ялта, Ленина, 18'!I8/График!AJ31*График!AJ27 -> 1421068.1 | J8: =D48 -> 707514 | K8: =IF(AND(I8<>"",I8<>0,J8<>""),J8/I8,"") -> 0.49787481 | L8: =IF(SUMIF($D$25:$D$47,">=0",$P$25:$P$47)<>0,I8*D48/SUMIF($D$25:$D$47,">=0",$P$25:$P$47),0) -> 748082.46 | M8: =IF(AND(I8<>"",I8<>0,L8<>"",L8<>0),L8/I8,"") -> 0.52642268 | N8: =IF(AND(J8<>0,J8<>"",I8<>0,I8<>""),L8-I8,"") -> -672985.6 | P8: =IF(AND(O8<>"",O8<>0,L8<>"",L8<>0),-O8+L8,"") | Q8: =IF(AND(P8<>"",P8<>0,O8<>0,O8<>""),P8/O8,"")
F9: Кол-во изделий | I9: =I8/I11 -> 273.28232 | J9: =E48 -> 132 | K9: =IF(AND(I9<>"",I9<>0,J9<>""),J9/I9,"") -> 0.48301698 | L9: =IF(SUMIF($E$25:$E$47,">=0",$Q$25:$Q$47)<>0,I9*E48/SUMIF($E$25:$E$47,">=0",$Q$25:$Q$47),0) -> 132 | M9: =IF(AND(I9<>"",I9<>0,L9<>"",L9<>0),L9/I9,"") -> 0.48301698 | N9: =IF(AND(J9<>0,J9<>"",I9<>0,I9<>""),L9-I9,"") -> -141.28232 | O9: =O8/O11 -> #DIV/0! | P9: =IF(AND(O9<>"",O9<>0,L9<>"",L9<>0),-O9+L9,"") -> #DIV/0! | Q9: =IF(AND(P9<>"",P9<>0,O9<>0,O9<>""),P9/O9,"") -> #DIV/0!
F10: Средний чек | I10: =I11*I12 -> 10088 | J10: =H48 -> 10253.826 | K10: =IF(AND(I10<>"",I10<>0,J10<>""),J10/I10,"") -> 1.016438 | L10: =J10 -> 10253.826 | M10: =IF(AND(I10<>"",I10<>0,L10<>"",L10<>0),L10/I10,"") -> 1.016438 | N10: =IF(AND(J10<>0,J10<>"",I10<>0,I10<>""),L10-I10,"") -> 165.82609 | O10: =O11*O12 -> 0 | P10: =IF(AND(O10<>"",O10<>0,L10<>"",L10<>0),-O10+L10,"") | Q10: =IF(AND(P10<>"",P10<>0,O10<>0,O10<>""),P10/O10,"") | S10: IS
F11: Средняя стоимость изделия | I11: ='Ялта, Ленина, 18'!I11 -> 5200 | J11: =F48 -> 5359.9545 | K11: =IF(AND(I11<>"",I11<>0,J11<>""),J11/I11,"") -> 1.0307605 | L11: =IF(L9>0,L8/L9,"") -> 5667.2914 | M11: =IF(AND(I11<>"",I11<>0,L11<>"",L11<>0),L11/I11,"") -> 1.0898637 | N11: =IF(AND(J11<>0,J11<>"",I11<>0,I11<>""),L11-I11,"") -> 467.29139 | P11: =IF(AND(O11<>"",O11<>0,L11<>"",L11<>0),-O11+L11,"") | Q11: =IF(AND(P11<>"",P11<>0,O11<>0,O11<>""),P11/O11,"")
F12: Длина чека | I12: ='Ялта, Ленина, 18'!I12 -> 1.94 | J12: =J48 -> 1.9130435 | K12: =IF(AND(I12<>"",I12<>0,J12<>""),J12/I12,"") -> 0.98610489 | L12: =J12 -> 1.9130435 | M12: =IF(AND(I12<>"",I12<>0,L12<>"",L12<>0),L12/I12,"") -> 0.98610489 | N12: =IF(AND(J12<>0,J12<>"",I12<>0,I12<>""),L12-I12,"") -> -0.026956522 | P12: =IF(AND(O12<>"",O12<>0,L12<>"",L12<>0),-O12+L12,"") | Q12: =IF(AND(P12<>"",P12<>0,O12<>0,O12<>""),P12/O12,"") | S12: ='Ялта, Ленина, 18'!S12*График!AJ27/График!AJ31 -> 201577.61 | T12: =L48 -> 153471
F13: Кол-во чеков | I13: =IF(I12<>0,I9/I12,"") -> 140.86718 | J13: =G48 -> 69 | K13: =IF(AND(I13<>"",I13<>0,J13<>""),J13/I13,"") -> 0.48982312 | L13: =IF(SUMIF($G$25:$G$47,">=0",$R$25:$R$47)<>0,I13*G48/SUMIF($G$25:$G$47,">=0",$R$25:$R$47),"") -> 69 | M13: =IF(AND(I13<>"",I13<>0,L13<>"",L13<>0),L13/I13,"") -> 0.48982312 | N13: =IF(AND(J13<>0,J13<>"",I13<>0,I13<>""),L13-I13,"") -> -71.867176 | P13: =IF(AND(O13<>"",O13<>0,L13<>"",L13<>0),-O13+L13,"") | Q13: =IF(AND(P13<>"",P13<>0,O13<>0,O13<>""),P13/O13,"") | S13: =T12/S12 -> 0.76134944 | T13: =S13/J14*I14 -> 0.76134944
F14: Кол-во смен план/отработано | I14: =График!AI27 -> 19 | J14: 19 | K14: =IF(AND(I14<>"",I14<>0,J14<>""),J14/I14,"") -> 1 | L14: =I14 -> 19 | M14: =IF(AND(I14<>"",I14<>0,L14<>"",L14<>0),L14/I14,"") -> 1 | N14: =IF(AND(J14<>0,J14<>"",I14<>0,I14<>""),L14-I14,"") -> 0 | P14: =IF(AND(O14<>"",O14<>0,L14<>"",L14<>0),-O14+L14,"") | Q14: =IF(AND(P14<>"",P14<>0,O14<>0,O14<>""),P14/O14,"")
F15: Средние продажи в смену | I15: ='Ялта, Ленина, 18'!I15 -> 154639.28 | J15: =J8/J14 -> 37237.579 | K15: =IF(AND(I15<>"",I15<>0,J15<>""),J15/I15,"") -> 0.24080285 | L15: =J15 -> 37237.579 | M15: =IF(AND(I15<>"",I15<>0,L15<>"",L15<>0),L15/I15,"") -> 0.24080285 | N15: =IF(AND(J15<>0,J15<>"",I15<>0,I15<>""),L15-I15,"") -> -117401.7 | P15: =IF(AND(O15<>"",O15<>0,L15<>"",L15<>0),-O15+L15,"") | Q15: =IF(AND(P15<>"",P15<>0,O15<>0,O15<>""),P15/O15,"")
F16: Отставание/Перевыполнение | J16: =J8-I15*J14 -> -2230632.3 | K16: =IF(AND(I16<>"",I16<>0,J16<>""),J16/I16,"") | L16: =J16 -> -2230632.3 | M16: =IF(AND(I16<>"",I16<>0,L16<>"",L16<>0),L16/I16,"") | N16: =IF(AND(J16<>0,J16<>"",I16<>0,I16<>""),L16-I16,"") | P16: =IF(AND(O16<>"",O16<>0,L16<>"",L16<>0),-O16+L16,"") | Q16: =IF(AND(P16<>"",P16<>0,O16<>0,O16<>""),P16/O16,"") | S16: UNOde50
F17: Трафик | I17: ='Ялта, Ленина, 18'!I17/График!AJ31*График!AJ27 -> 640.30534 | J17: =I48 -> 313 | K17: =IF(AND(I17<>"",I17<>0,J17<>""),J17/I17,"") -> 0.48882928 | L17: =J17/J14*I14 -> 313 | M17: =IF(AND(I17<>"",I17<>0,L17<>"",L17<>0),L17/I17,"") -> 0.48882928 | N17: =IF(AND(J17<>0,J17<>"",I17<>0,I17<>""),L17-I17,"") -> -327.30534 | P17: =IF(AND(O17<>"",O17<>0,L17<>"",L17<>0),-O17+L17,"") | Q17: =IF(AND(P17<>"",P17<>0,O17<>0,O17<>""),P17/O17,"")
K18: =IF(AND(I18<>"",I18<>0,J18<>""),J18/I18,"") | L18: =J18 -> 0 | M18: =IF(AND(I18<>"",I18<>0,L18<>"",L18<>0),L18/I18,"") | N18: =IF(AND(J18<>0,J18<>"",I18<>0,I18<>""),L18-I18,"") | O18: 0 | P18: =IF(AND(O18<>"",O18<>0,L18<>"",L18<>0),-O18+L18,"") | Q18: =IF(AND(P18<>"",P18<>0,O18<>0,O18<>""),P18/O18,"") | S18: ='Ялта, Ленина, 18'!S18*График!AJ27/График!AJ31 -> 142290.08 | T18: =K48 -> 121439
J19: =M48 -> 0 | K19: =IF(AND(I19<>"",I19<>0,J19<>""),J19/I19,"") | L19: =J19 -> 0 | M19: =IF(AND(I19<>"",I19<>0,L19<>"",L19<>0),L19/I19,"") | N19: =IF(AND(J19<>0,J19<>"",I19<>0,I19<>""),L19-I19,"") | O19: 0 | P19: =IF(AND(O19<>"",O19<>0,L19<>"",L19<>0),-O19+L19,"") | Q19: =IF(AND(P19<>"",P19<>0,O19<>0,O19<>""),P19/O19,"") | S19: =T18/S18 -> 0.85346078 | T19: =S19/J14*I14 -> 0.85346078
F20: Конверсия план/факт | I20: ='Ялта, Ленина, 18'!I20 -> 0.22 | J20: =N48 -> 0.22044728 | K20: =J20/I20 -> 1.0020331 | L20: =IF(AND(K8<>0,I14<>0,I48<>0),(I48*N48+(I48/K8-I48)*I20)/(I48/K8),0) -> 0.22022269 | M20: =IF(AND(I20<>"",I20<>0,L20<>"",L20<>0),L20/I20,"") -> 1.0010122 | N20: =IF(AND(J20<>0,J20<>"",I20<>0,I20<>""),L20-I20,"") -> 0.00022269161 | P20: =IF(AND(O20<>"",O20<>0,L20<>"",L20<>0),-O20+L20,"") | Q20: =IF(AND(P20<>"",P20<>0,O20<>0,O20<>""),P20/O20,"")
B22: Факт продаж за месяц | O22: % выполнения дневного плана | P22: Раcпределение плана по дням
B23: Дата | C23: День недели | D23: Выручка (руб) | E23: Кол-во единиц (шт.) | F23: Средняя стоимость изделия (руб.) | G23: Количество чеков (шт.) | H23: Средняя сумма чека (руб.) | I23: Трафик | J23: Длина чека (шт.) | K23: UNOde50 | L23: IS | M23: Запасной | N23: Конверсия (%) | P23: выручка, план | Q23: кол-во ед, план | R23: Кол-во чеков, план | S23: выручка, скорректир.план | T23: кол-во ед, скорр. план | U23: кол-во чеков, скорр. план | V23: Коэфф. Дня Недели | W23: Специфика месяца
B24: 1 | C24: 2 | D24: 3 | E24: 4 | F24: 5 | G24: 6 | H24: 7 | I24: 8 | J24: 9 | K24: 10 | L24: 11 | M24: 12 | N24: 13 | P24: 1 | Q24: 2 | R24: 3 | S24: 4 | T24: 5 | U24: 6 | V24: 10 | W24: 11
A25: 1 | B25: 45780 | C25: сб | D25: =36723+L25 -> 41226 | E25: 9 | F25: =IF(AND(E25<>"",E25<>0),D25/E25,"") -> 4580.6667 | G25: 4 | H25: =IF(AND(G25<>"",G25<>0),D25/G25,"") -> 10306.5 | I25: 23 | J25: =IF(AND(G25<>"",G25<>0),E25/G25,"") -> 2.25 | K25: 10492 | L25: 4503 | N25: =IF(AND(I25<>"",I25<>0),G25/I25,"") -> 0.17391304 | O25: =D25/P25 -> 0.37149651 | P25: =$I$8*V25*W25/SUMPRODUCT($W$25:$W$55,$V$25:$V$55) -> 110972.78 | Q25: =$I$9*V25*W25/SUMPRODUCT($W$25:$W$55,$V$25:$V$55) -> 21.340919 | R25: =IF($I$12="","",Q25/$I$12) -> 11.000474 | S25: =IF(W25<>"",IF(D25<>"",D25,($I$8-SUM($S24:S$25))*V25*W25/SUMPRODUCT($W25:$W$55,$V25:$V$55)),"") -> 41226 | T25: =IF(W25<>"",IF(E25<>"",E25,($I$9-SUM($T24:T$25))*V25*W25/SUMPRODUCT($W25:$W$55,$V25:$V$55)),"") -> 9 | U25: =IF(W25<>"",IF($I$12<>"",IF(G25<>"",G25,($I$9/$I$12-SUM($U24:U$25))*V25*W25/SUMPRODUCT($W25:$W$55,$V25:$V$55)),""),"") -> 4 | V25: 1.2 | W25: 1.2
A26: 2 | B26: 45781 | C26: вс | D26: 45522 | E26: 9 | F26: =IF(AND(E26<>"",E26<>0),D26/E26,"") -> 5058 | G26: 3 | H26: =IF(AND(G26<>"",G26<>0),D26/G26,"") -> 15174 | I26: 20 | J26: =IF(AND(G26<>"",G26<>0),E26/G26,"") -> 3 | K26: 12992 | N26: =IF(AND(I26<>"",I26<>0),G26/I26,"") -> 0.15 | O26: =D26/P26 -> 0.59070054 | P26: =$I$8*V26*W26/SUMPRODUCT($W$25:$W$55,$V$25:$V$55) -> 77064.429 | Q26: =$I$9*V26*W26/SUMPRODUCT($W$25:$W$55,$V$25:$V$55) -> 14.820082 | R26: =IF($I$12="","",Q26/$I$12) -> 7.6392178 | S26: =IF(W26<>"",IF(D26<>"",D26,($I$8-SUM($S25:S$25))*V26*W26/SUMPRODUCT($W26:$W$55,$V26:$V$55)),"") -> 45522 | T26: =IF(W26<>"",IF(E26<>"",E26,($I$9-SUM($T25:T$25))*V26*W26/SUMPRODUCT($W26:$W$55,$V26:$V$55)),"") -> 9 | U26: =IF(W26<>"",IF($I$12<>"",IF(G26<>"",G26,($I$9/$I$12-SUM($U25:U$25))*V26*W26/SUMPRODUCT($W26:$W$55,$V26:$V$55)),""),"") -> 3 | V26: 1 | W26: 1
A27: 3 | B27: 45782 | C27: пн | D27: =58379+10403 -> 68782 | E27: 15 | F27: 4585 | G27: 6 | H27: =IF(AND(G27<>"",G27<>0),D27/G27,"") -> 11463.667 | I27: 35 | J27: =IF(AND(G27<>"",G27<>0),E27/G27,"") -> 2.5 | L27: 10403 | N27: =IF(AND(I27<>"",I27<>0),G27/I27,"") -> 0.17142857 | O27: =D27/P27 -> 0.89252592 | P27: =$I$8*V27*W27/SUMPRODUCT($W$25:$W$55,$V$25:$V$55) -> 77064.429 | Q27: =$I$9*V27*W27/SUMPRODUCT($W$25:$W$55,$V$25:$V$55) -> 14.820082 | R27: =IF($I$12="","",Q27/$I$12) -> 7.6392178 | S27: =IF(W27<>"",IF(D27<>"",D27,($I$8-SUM($S$25:S26))*V27*W27/SUMPRODUCT($W27:$W$55,$V27:$V$55)),"") -> 68782 | T27: =IF(W27<>"",IF(E27<>"",E27,($I$9-SUM($T$25:T26))*V27*W27/SUMPRODUCT($W27:$W$55,$V27:$V$55)),"") -> 15 | U27: =IF(W27<>"",IF($I$12<>"",IF(G27<>"",G27,($I$9/$I$12-SUM($U$25:U26))*V27*W27/SUMPRODUCT($W27:$W$55,$V27:$V$55)),""),"") -> 6 | V27: 1 | W27: 1
A28: 4 | B28: 45785 | C28: чт | D28: 35722 | E28: 9 | F28: 3969 | G28: 5 | H28: =IF(AND(G28<>"",G28<>0),D28/G28,"") -> 7144.4 | I28: 20 | J28: =IF(AND(G28<>"",G28<>0),E28/G28,"") -> 1.8 | N28: =IF(AND(I28<>"",I28<>0),G28/I28,"") -> 0.25 | O28: =D28/P28 -> 0.46353422 | P28: =$I$8*V28*W28/SUMPRODUCT($W$25:$W$55,$V$25:$V$55) -> 77064.429 | Q28: =$I$9*V28*W28/SUMPRODUCT($W$25:$W$55,$V$25:$V$55) -> 14.820082 | R28: =IF($I$12="","",Q28/$I$12) -> 7.6392178 | S28: =IF(W28<>"",IF(D28<>"",D28,($I$8-SUM($S$25:S27))*V28*W28/SUMPRODUCT($W28:$W$55,$V28:$V$55)),"") -> 35722 | T28: =IF(W28<>"",IF(E28<>"",E28,($I$9-SUM($T$25:T27))*V28*W28/SUMPRODUCT($W28:$W$55,$V28:$V$55)),"") -> 9 | U28: =IF(W28<>"",IF($I$12<>"",IF(G28<>"",G28,($I$9/$I$12-SUM($U$25:U27))*V28*W28/SUMPRODUCT($W28:$W$55,$V28:$V$55)),""),"") -> 5 | V28: 1 | W28: 1
A29: 5 | B29: 45786 | C29: пт | D29: =34525+7992 -> 42517 | E29: 11 | F29: =IF(AND(E29<>"",E29<>0),D29/E29,"") -> 3865.1818 | G29: 4 | H29: =IF(AND(G29<>"",G29<>0),D29/G29,"") -> 10629.25 | I29: 20 | J29: =IF(AND(G29<>"",G29<>0),E29/G29,"") -> 2.75 | K29: 7992 | N29: =IF(AND(I29<>"",I29<>0),G29/I29,"") -> 0.2 | O29: =D29/P29 -> 0.5517072 | P29: =$I$8*V29*W29/SUMPRODUCT($W$25:$W$55,$V$25:$V$55) -> 77064.429 | Q29: =$I$9*V29*W29/SUMPRODUCT($W$25:$W$55,$V$25:$V$55) -> 14.820082 | R29: =IF($I$12="","",Q29/$I$12) -> 7.6392178 | S29: =IF(W29<>"",IF(D29<>"",D29,($I$8-SUM($S$25:S28))*V29*W29/SUMPRODUCT($W29:$W$55,$V29:$V$55)),"") -> 42517 | T29: =IF(W29<>"",IF(E29<>"",E29,($I$9-SUM($T$25:T28))*V29*W29/SUMPRODUCT($W29:$W$55,$V29:$V$55)),"") -> 11 | U29: =IF(W29<>"",IF($I$12<>"",IF(G29<>"",G29,($I$9/$I$12-SUM($U$25:U28))*V29*W29/SUMPRODUCT($W29:$W$55,$V29:$V$55)),""),"") -> 4 | V29: 1 | W29: 1
A30: 6 | B30: 45787 | C30: сб | D30: =23940+11123 -> 35063 | E30: 8 | F30: =IF(AND(E30<>"",E30<>0),D30/E30,"") -> 4382.875 | G30: 4 | H30: =IF(AND(G30<>"",G30<>0),D30/G30,"") -> 8765.75 | I30: 10 | J30: =IF(AND(G30<>"",G30<>0),E30/G30,"") -> 2 | L30: 11123 | N30: =IF(AND(I30<>"",I30<>0),G30/I30,"") -> 0.4 | O30: =D30/P30 -> 0.45498293 | P30: =$I$8*V30*W30/SUMPRODUCT($W$25:$W$55,$V$25:$V$55) -> 77064.429 | Q30: =$I$9*V30*W30/SUMPRODUCT($W$25:$W$55,$V$25:$V$55) -> 14.820082 | R30: =IF($I$12="","",Q30/$I$12) -> 7.6392178 | S30: =IF(W30<>"",IF(D30<>"",D30,($I$8-SUM($S$25:S29))*V30*W30/SUMPRODUCT($W30:$W$55,$V30:$V$55)),"") -> 35063 | T30: =IF(W30<>"",IF(E29<>"",E29,($I$9-SUM($T$25:T29))*V30*W30/SUMPRODUCT($W30:$W$55,$V30:$V$55)),"") -> 11 | U30: =IF(W30<>"",IF($I$12<>"",IF(G30<>"",G30,($I$9/$I$12-SUM($U$25:U29))*V30*W30/SUMPRODUCT($W30:$W$55,$V30:$V$55)),""),"") -> 4 | V30: 1 | W30: 1
A31: 7 | B31: 45789 | C31: пн | D31: 15758 | E31: 5 | F31: =IF(AND(E31<>"",E31<>0),D31/E31,"") -> 3151.6 | G31: 3 | H31: =IF(AND(G31<>"",G31<>0),D31/G31,"") -> 5252.6667 | I31: 15 | J31: =IF(AND(G31<>"",G31<>0),E31/G31,"") -> 1.6666667 | N31: =IF(AND(I31<>"",I31<>0),G31/I31,"") -> 0.2 | O31: =D31/P31 -> 0.20447826 | P31: =$I$8*V31*W31/SUMPRODUCT($W$25:$W$55,$V$25:$V$55) -> 77064.429 | Q31: =$I$9*V31*W31/SUMPRODUCT($W$25:$W$55,$V$25:$V$55) -> 14.820082 | R31: =IF($I$12="","",Q31/$I$12) -> 7.6392178 | S31: =IF(W31<>"",IF(D31<>"",D31,($I$8-SUM($S$25:S30))*V31*W31/SUMPRODUCT($W31:$W$55,$V31:$V$55)),"") -> 15758 | T31: =IF(W31<>"",IF(E31<>"",E31,($I$9-SUM($T$25:T30))*V31*W31/SUMPRODUCT($W31:$W$55,$V31:$V$55)),"") -> 5 | U31: =IF(W31<>"",IF($I$12<>"",IF(G31<>"",G31,($I$9/$I$12-SUM($U$25:U30))*V31*W31/SUMPRODUCT($W31:$W$55,$V31:$V$55)),""),"") -> 3 | V31: 1 | W31: 1
A32: 8 | B32: 45790 | C32: вт | D32: 0.00 | E32: 0 | F32: =IF(AND(E32<>"",E32<>0),D32/E32,"") | G32: 0 | H32: =IF(AND(G32<>"",G32<>0),D32/G32,"") | I32: 11 | J32: =IF(AND(G32<>"",G32<>0),E32/G32,"") | N32: =IF(AND(I32<>"",I32<>0),G32/I32,"") -> 0 | O32: =D32/P32 -> #VALUE! | P32: =$I$8*V32*W32/SUMPRODUCT($W$25:$W$55,$V$25:$V$55) -> 77064.429 | Q32: =$I$9*V32*W32/SUMPRODUCT($W$25:$W$55,$V$25:$V$55) -> 14.820082 | R32: =IF($I$12="","",Q32/$I$12) -> 7.6392178 | S32: =IF(W32<>"",IF(D32<>"",D32,($I$8-SUM($S$25:S31))*V32*W32/SUMPRODUCT($W32:$W$55,$V32:$V$55)),"") -> 0.00 | T32: =IF(W32<>"",IF(E32<>"",E32,($I$9-SUM($T$25:T31))*V32*W32/SUMPRODUCT($W32:$W$55,$V32:$V$55)),"") -> 0 | U32: =IF(W32<>"",IF($I$12<>"",IF(G32<>"",G32,($I$9/$I$12-SUM($U$25:U31))*V32*W32/SUMPRODUCT($W32:$W$55,$V32:$V$55)),""),"") -> 0 | V32: 1 | W32: 1
A33: 9 | B33: 45791 | C33: ср | D33: =31654+67970+15403 -> 115027 | E33: 13 | F33: =IF(AND(E33<>"",E33<>0),D33/E33,"") -> 8848.2308 | G33: 6 | H33: =IF(AND(G33<>"",G33<>0),D33/G33,"") -> 19171.167 | I33: 10 | J33: =IF(AND(G33<>"",G33<>0),E33/G33,"") -> 2.1666667 | K33: 67970 | L33: 15403 | N33: =IF(AND(I33<>"",I33<>0),G33/I33,"") -> 0.6 | O33: =D33/P33 -> 1.4926082 | P33: =$I$8*V33*W33/SUMPRODUCT($W$25:$W$55,$V$25:$V$55) -> 77064.429 | Q33: =$I$9*V33*W33/SUMPRODUCT($W$25:$W$55,$V$25:$V$55) -> 14.820082 | R33: =IF($I$12="","",Q33/$I$12) -> 7.6392178 | S33: =IF(W33<>"",IF(D33<>"",D33,($I$8-SUM($S$25:S32))*V33*W33/SUMPRODUCT($W33:$W$55,$V33:$V$55)),"") -> 115027 | T33: =IF(W33<>"",IF(E33<>"",E33,($I$9-SUM($T$25:T32))*V33*W33/SUMPRODUCT($W33:$W$55,$V33:$V$55)),"") -> 13 | U33: =IF(W33<>"",IF($I$12<>"",IF(G33<>"",G33,($I$9/$I$12-SUM($U$25:U32))*V33*W33/SUMPRODUCT($W33:$W$55,$V33:$V$55)),""),"") -> 6 | V33: 1 | W33: 1
A34: 10 | B34: 45794 | C34: сб | D34: 30932 | E34: 8 | F34: =IF(AND(E34<>"",E34<>0),D34/E34,"") -> 3866.5 | G34: 4 | H34: =IF(AND(G34<>"",G34<>0),D34/G34,"") -> 7733 | I34: 25 | J34: =IF(AND(G34<>"",G34<>0),E34/G34,"") -> 2 | N34: =IF(AND(I34<>"",I34<>0),G34/I34,"") -> 0.16 | O34: =D34/P34 -> 0.40137844 | P34: =$I$8*V34*W34/SUMPRODUCT($W$25:$W$55,$V$25:$V$55) -> 77064.429 | Q34: =$I$9*V34*W34/SUMPRODUCT($W$25:$W$55,$V$25:$V$55) -> 14.820082 | R34: =IF($I$12="","",Q34/$I$12) -> 7.6392178 | S34: =IF(W34<>"",IF(D34<>"",D34,($I$8-SUM($S$25:S33))*V34*W34/SUMPRODUCT($W34:$W$55,$V34:$V$55)),"") -> 30932 | T34: =IF(W34<>"",IF(E34<>"",E34,($I$9-SUM($T$25:T33))*V34*W34/SUMPRODUCT($W34:$W$55,$V34:$V$55)),"") -> 8 | U34: =IF(W34<>"",IF($I$12<>"",IF(G34<>"",G34,($I$9/$I$12-SUM($U$25:U33))*V34*W34/SUMPRODUCT($W34:$W$55,$V34:$V$55)),""),"") -> 4 | V34: 1 | W34: 1
A35: 11 | B35: 45795 | C35: вс | D35: 22157 | E35: 5 | F35: =IF(AND(E35<>"",E35<>0),D35/E35,"") -> 4431.4 | G35: 2 | H35: =IF(AND(G35<>"",G35<>0),D35/G35,"") -> 11078.5 | I35: 17 | J35: =IF(AND(G35<>"",G35<>0),E35/G35,"") -> 2.5 | N35: =IF(AND(I35<>"",I35<>0),G35/I35,"") -> 0.11764706 | O35: =D35/P35 -> 0.28751267 | P35: =$I$8*V35*W35/SUMPRODUCT($W$25:$W$55,$V$25:$V$55) -> 77064.429 | Q35: =$I$9*V35*W35/SUMPRODUCT($W$25:$W$55,$V$25:$V$55) -> 14.820082 | R35: =IF($I$12="","",Q35/$I$12) -> 7.6392178 | S35: =IF(W35<>"",IF(D35<>"",D35,($I$8-SUM($S$25:S34))*V35*W35/SUMPRODUCT($W35:$W$55,$V35:$V$55)),"") -> 22157 | T35: =IF(W35<>"",IF(E35<>"",E35,($I$9-SUM($T$25:T34))*V35*W35/SUMPRODUCT($W35:$W$55,$V35:$V$55)),"") -> 5 | U35: =IF(W35<>"",IF($I$12<>"",IF(G35<>"",G35,($I$9/$I$12-SUM($U$25:U34))*V35*W35/SUMPRODUCT($W35:$W$55,$V35:$V$55)),""),"") -> 2 | V35: 1 | W35: 1
A36: 12 | B36: 45796 | C36: пн | D36: 30640 | E36: 7 | F36: =IF(AND(E36<>"",E36<>0),D36/E36,"") -> 4377.1429 | G36: 3 | H36: =IF(AND(G36<>"",G36<>0),D36/G36,"") -> 10213.333 | I36: 10 | J36: =IF(AND(G36<>"",G36<>0),E36/G36,"") -> 2.3333333 | N36: =IF(AND(I36<>"",I36<>0),G36/I36,"") -> 0.3 | O36: =D36/P36 -> 0.3975894 | P36: =$I$8*V36*W36/SUMPRODUCT($W$25:$W$55,$V$25:$V$55) -> 77064.429 | Q36: =$I$9*V36*W36/SUMPRODUCT($W$25:$W$55,$V$25:$V$55) -> 14.820082 | R36: =IF($I$12="","",Q36/$I$12) -> 7.6392178 | S36: =IF(W36<>"",IF(D36<>"",D36,($I$8-SUM($S$25:S35))*V36*W36/SUMPRODUCT($W36:$W$55,$V36:$V$55)),"") -> 30640 | T36: =IF(W36<>"",IF(E36<>"",E36,($I$9-SUM($T$25:T35))*V36*W36/SUMPRODUCT($W36:$W$55,$V36:$V$55)),"") -> 7 | U36: =IF(W36<>"",IF($I$12<>"",IF(G36<>"",G36,($I$9/$I$12-SUM($U$25:U35))*V36*W36/SUMPRODUCT($W36:$W$55,$V36:$V$55)),""),"") -> 3 | V36: 1 | W36: 1
A37: 13 | B37: 45799 | C37: чт | D37: =4392+9303 -> 13695 | E37: 3 | F37: =IF(AND(E37<>"",E37<>0),D37/E37,"") -> 4565 | G37: 2 | H37: =IF(AND(G37<>"",G37<>0),D37/G37,"") -> 6847.5 | I37: 8 | J37: =IF(AND(G37<>"",G37<>0),E37/G37,"") -> 1.5 | L37: 9303 | N37: =IF(AND(I37<>"",I37<>0),G37/I37,"") -> 0.25 | O37: =D37/P37 -> 0.17770845 | P37: =$I$8*V37*W37/SUMPRODUCT($W$25:$W$55,$V$25:$V$55) -> 77064.429 | Q37: =$I$9*V37*W37/SUMPRODUCT($W$25:$W$55,$V$25:$V$55) -> 14.820082 | R37: =IF($I$12="","",Q37/$I$12) -> 7.6392178 | S37: =IF(W37<>"",IF(D37<>"",D37,($I$8-SUM($S$25:S36))*V37*W37/SUMPRODUCT($W37:$W$55,$V37:$V$55)),"") -> 13695 | T37: =IF(W37<>"",IF(E37<>"",E37,($I$9-SUM($T$25:T36))*V37*W37/SUMPRODUCT($W37:$W$55,$V37:$V$55)),"") -> 3 | U37: =IF(W37<>"",IF($I$12<>"",IF(G37<>"",G37,($I$9/$I$12-SUM($U$25:U36))*V37*W37/SUMPRODUCT($W37:$W$55,$V37:$V$55)),""),"") -> 2 | V37: 1 | W37: 1
A38: 14 | B38: 45800 | C38: пт | D38: =21993+1692 -> 23685 | E38: 2 | F38: =IF(AND(E38<>"",E38<>0),D38/E38,"") -> 11842.5 | G38: 2 | H38: =IF(AND(G38<>"",G38<>0),D38/G38,"") -> 11842.5 | I38: 8 | J38: =IF(AND(G38<>"",G38<>0),E38/G38,"") -> 1 | K38: 21993 | N38: =IF(AND(I38<>"",I38<>0),G38/I38,"") -> 0.25 | O38: =D38/P38 -> 0.30734024 | P38: =$I$8*V38*W38/SUMPRODUCT($W$25:$W$55,$V$25:$V$55) -> 77064.429 | Q38: =$I$9*V38*W38/SUMPRODUCT($W$25:$W$55,$V$25:$V$55) -> 14.820082 | R38: =IF($I$12="","",Q38/$I$12) -> 7.6392178 | S38: =IF(W38<>"",IF(D38<>"",D38,($I$8-SUM($S$25:S37))*V38*W38/SUMPRODUCT($W38:$W$55,$V38:$V$55)),"") -> 23685 | T38: =IF(W38<>"",IF(E38<>"",E38,($I$9-SUM($T$25:T37))*V38*W38/SUMPRODUCT($W38:$W$55,$V38:$V$55)),"") -> 2 | U38: =IF(W38<>"",IF($I$12<>"",IF(G38<>"",G38,($I$9/$I$12-SUM($U$25:U37))*V38*W38/SUMPRODUCT($W38:$W$55,$V38:$V$55)),""),"") -> 2 | V38: 1 | W38: 1
A39: 15 | B39: 45801 | C39: сб | D39: 10645 | E39: 3 | F39: =IF(AND(E39<>"",E39<>0),D39/E39,"") -> 3548.3333 | G39: 2 | H39: =IF(AND(G39<>"",G39<>0),D39/G39,"") -> 5322.5 | I39: 17 | J39: =IF(AND(G39<>"",G39<>0),E39/G39,"") -> 1.5 | N39: =IF(AND(I39<>"",I39<>0),G39/I39,"") -> 0.11764706 | O39: =D39/P39 -> 0.13813117 | P39: =$I$8*V39*W39/SUMPRODUCT($W$25:$W$55,$V$25:$V$55) -> 77064.429 | Q39: =$I$9*V39*W39/SUMPRODUCT($W$25:$W$55,$V$25:$V$55) -> 14.820082 | R39: =IF($I$12="","",Q39/$I$12) -> 7.6392178 | S39: =IF(W39<>"",IF(D39<>"",D39,($I$8-SUM($S$25:S38))*V39*W39/SUMPRODUCT($W39:$W$55,$V39:$V$55)),"") -> 10645 | T39: =IF(W39<>"",IF(E39<>"",E39,($I$9-SUM($T$25:T38))*V39*W39/SUMPRODUCT($W39:$W$55,$V39:$V$55)),"") -> 3 | U39: =IF(W39<>"",IF($I$12<>"",IF(G39<>"",G39,($I$9/$I$12-SUM($U$25:U38))*V39*W39/SUMPRODUCT($W39:$W$55,$V39:$V$55)),""),"") -> 2 | V39: 1 | W39: 1
A40: 16 | B40: 45803 | C40: пн | D40: =19258+46509 -> 65767 | E40: 8 | F40: =IF(AND(E40<>"",E40<>0),D40/E40,"") -> 8220.875 | G40: 7 | H40: =IF(AND(G40<>"",G40<>0),D40/G40,"") -> 9395.2857 | I40: 10 | J40: =IF(AND(G40<>"",G40<>0),E40/G40,"") -> 1.1428571 | L40: 46509 | N40: =IF(AND(I40<>"",I40<>0),G40/I40,"") -> 0.7 | O40: =D40/P40 -> 0.85340281 | P40: =$I$8*V40*W40/SUMPRODUCT($W$25:$W$55,$V$25:$V$55) -> 77064.429 | Q40: =$I$9*V40*W40/SUMPRODUCT($W$25:$W$55,$V$25:$V$55) -> 14.820082 | R40: =IF($I$12="","",Q40/$I$12) -> 7.6392178 | S40: =IF(W40<>"",IF(D40<>"",D40,($I$8-SUM($S$25:S39))*V40*W40/SUMPRODUCT($W40:$W$55,$V40:$V$55)),"") -> 65767 | T40: =IF(W40<>"",IF(E40<>"",E40,($I$9-SUM($T$25:T39))*V40*W40/SUMPRODUCT($W40:$W$55,$V40:$V$55)),"") -> 8 | U40: =IF(W40<>"",IF($I$12<>"",IF(G40<>"",G40,($I$9/$I$12-SUM($U$25:U39))*V40*W40/SUMPRODUCT($W40:$W$55,$V40:$V$55)),""),"") -> 7 | V40: 1 | W40: 1
A41: 17 | B41: 45804 | C41: вт | D41: =7583+31104 -> 38687 | E41: 5 | F41: =IF(AND(E41<>"",E41<>0),D41/E41,"") -> 7737.4 | G41: 2 | H41: =IF(AND(G41<>"",G41<>0),D41/G41,"") -> 19343.5 | I41: 17 | J41: =IF(AND(G41<>"",G41<>0),E41/G41,"") -> 2.5 | L41: 31104 | N41: =IF(AND(I41<>"",I41<>0),G41/I41,"") -> 0.11764706 | O41: =D41/P41 -> 0.50200852 | P41: =$I$8*V41*W41/SUMPRODUCT($W$25:$W$55,$V$25:$V$55) -> 77064.429 | Q41: =$I$9*V41*W41/SUMPRODUCT($W$25:$W$55,$V$25:$V$55) -> 14.820082 | R41: =IF($I$12="","",Q41/$I$12) -> 7.6392178 | S41: =IF(W41<>"",IF(D41<>"",D41,($I$8-SUM($S$25:S40))*V41*W41/SUMPRODUCT($W41:$W$55,$V41:$V$55)),"") -> 38687 | T41: =IF(W41<>"",IF(E41<>"",E41,($I$9-SUM($T$25:T40))*V41*W41/SUMPRODUCT($W41:$W$55,$V41:$V$55)),"") -> 5 | U41: =IF(W41<>"",IF($I$12<>"",IF(G41<>"",G41,($I$9/$I$12-SUM($U$25:U40))*V41*W41/SUMPRODUCT($W41:$W$55,$V41:$V$55)),""),"") -> 2 | V41: 1 | W41: 1
A42: 18 | B42: 28.мая | C42: ср | D42: 23268 | E42: 4 | F42: =IF(AND(E42<>"",E42<>0),D42/E42,"") -> 5817 | G42: 4 | H42: =IF(AND(G42<>"",G42<>0),D42/G42,"") -> 5817 | I42: 17 | J42: =IF(AND(G42<>"",G42<>0),E42/G42,"") -> 1 | N42: =IF(AND(I42<>"",I42<>0),G42/I42,"") -> 0.23529412 | O42: =D42/P42 -> 0.30192918 | P42: =$I$8*V42*W42/SUMPRODUCT($W$25:$W$55,$V$25:$V$55) -> 77064.429 | Q42: =$I$9*V42*W42/SUMPRODUCT($W$25:$W$55,$V$25:$V$55) -> 14.820082 | R42: =IF($I$12="","",Q42/$I$12) -> 7.6392178 | S42: =IF(W42<>"",IF(D42<>"",D42,($I$8-SUM($S$25:S41))*V42*W42/SUMPRODUCT($W42:$W$55,$V42:$V$55)),"") -> 23268 | T42: =IF(W42<>"",IF(E42<>"",E42,($I$9-SUM($T$25:T41))*V42*W42/SUMPRODUCT($W42:$W$55,$V42:$V$55)),"") -> 4 | U42: =IF(W42<>"",IF($I$12<>"",IF(G42<>"",G42,($I$9/$I$12-SUM($U$25:U41))*V42*W42/SUMPRODUCT($W42:$W$55,$V42:$V$55)),""),"") -> 4 | V42: 1 | W42: 1
B43: 31мая | C43: сб | D43: =6184+25123 -> 31307 | E43: 3 | F43: =IF(AND(E43<>"",E43<>0),D43/E43,"") -> 10435.667 | G43: 3 | H43: =IF(AND(G43<>"",G43<>0),D43/G43,"") -> 10435.667 | I43: 20 | J43: =IF(AND(G43<>"",G43<>0),E43/G43,"") -> 1 | L43: 25123 | N43: =IF(AND(I43<>"",I43<>0),G43/I43,"") -> 0.15 | O43: =D43/P43 -> #DIV/0! | P43: =$I$8*V43*W43/SUMPRODUCT($W$25:$W$55,$V$25:$V$55) -> 0 | Q43: =$I$9*V43*W43/SUMPRODUCT($W$25:$W$55,$V$25:$V$55) -> 0 | R43: =IF($I$12="","",Q43/$I$12) -> 0 | S43: =IF(W43<>"",IF(D43<>"",D43,($I$8-SUM($S$25:S42))*V43*W43/SUMPRODUCT($W43:$W$55,$V43:$V$55)),"") | T43: =IF(W43<>"",IF(E43<>"",E43,($I$9-SUM($T$25:T42))*V43*W43/SUMPRODUCT($W43:$W$55,$V43:$V$55)),"") | U43: =IF(W43<>"",IF($I$12<>"",IF(G43<>"",G43,($I$9/$I$12-SUM($U$25:U42))*V43*W43/SUMPRODUCT($W43:$W$55,$V43:$V$55)),""),"")
F44: =IF(AND(E44<>"",E44<>0),D44/E44,"") | H44: =IF(AND(G44<>"",G44<>0),D44/G44,"") | J44: =IF(AND(G44<>"",G44<>0),E44/G44,"") | N44: =IF(AND(I44<>"",I44<>0),G44/I44,"") | O44: =D44/P44 -> #DIV/0! | P44: =$I$8*V44*W44/SUMPRODUCT($W$25:$W$55,$V$25:$V$55) -> 0 | Q44: =$I$9*V44*W44/SUMPRODUCT($W$25:$W$55,$V$25:$V$55) -> 0 | R44: =IF($I$12="","",Q44/$I$12) -> 0 | S44: =IF(W44<>"",IF(D44<>"",D44,($I$8-SUM($S$25:S43))*V44*W44/SUMPRODUCT($W44:$W$55,$V44:$V$55)),"") | T44: =IF(W44<>"",IF(E44<>"",E44,($I$9-SUM($T$25:T43))*V44*W44/SUMPRODUCT($W44:$W$55,$V44:$V$55)),0) -> 0 | U44: =IF(W44<>"",IF($I$12<>"",IF(G44<>"",G44,($I$9/$I$12-SUM($U$25:U43))*V44*W44/SUMPRODUCT($W44:$W$55,$V44:$V$55)),""),"")
B45: 45797 | C45: вт | D45: 5392 | E45: 1 | F45: =IF(AND(E45<>"",E45<>0),D45/E45,"") -> 5392 | G45: 1 | H45: =IF(AND(G45<>"",G45<>0),D45/G45,"") -> 5392 | J45: =IF(AND(G45<>"",G45<>0),E45/G45,"") -> 1 | N45: =IF(AND(I45<>"",I45<>0),G45/I45,"") | O45: =D45/P45 -> #DIV/0! | P45: =$I$8*V45*W45/SUMPRODUCT($W$25:$W$44,$V$25:$V$44) -> 0 | Q45: =$I$9*V45*W45/SUMPRODUCT($W$25:$W$44,$V$25:$V$44) -> 0 | R45: =IF($I$12="","",Q45/$I$12) -> 0 | S45: =IF(W45<>"",IF(D45<>"",D45,($I$8-SUM($S$25:S44))*V45*W45/SUMPRODUCT($W$44:$W45,$V$44:$V45)),"") | T45: =IF(W45<>"",IF(E45<>"",E45,($I$9-SUM($T$25:T44))*V45*W45/SUMPRODUCT($W$44:$W45,$V$44:$V45)),"") | U45: =IF(W45<>"",IF($I$12<>"",IF(G45<>"",G45,($I$9/$I$12-SUM($U$25:U44))*V45*W45/SUMPRODUCT($W$44:$W45,$V$44:$V45)),""),"")
B46: 45783 | C46: вт | D46: 5939 | E46: 2 | F46: =IF(AND(E46<>"",E46<>0),D46/E46,"") -> 2969.5 | G46: 1 | H46: =IF(AND(G46<>"",G46<>0),D46/G46,"") -> 5939 | J46: =IF(AND(G46<>"",G46<>0),E46/G46,"") -> 2 | N46: =IF(AND(I46<>"",I46<>0),G46/I46,"") | O46: =D46/P46 -> #DIV/0! | P46: =$I$8*V46*W46/SUMPRODUCT($W$25:$W$44,$V$25:$V$44) -> 0 | Q46: =$I$9*V46*W46/SUMPRODUCT($W$25:$W$44,$V$25:$V$44) -> 0 | R46: =IF($I$12="","",Q46/$I$12) -> 0 | S46: =IF(W46<>"",IF(D46<>"",D46,($I$8-SUM($S$25:S45))*V46*W46/SUMPRODUCT($W$44:$W46,$V$44:$V46)),"") | T46: =IF(W46<>"",IF(E46<>"",E46,($I$9-SUM($T$25:T45))*V46*W46/SUMPRODUCT($W$44:$W46,$V$44:$V46)),"") | U46: =IF(W46<>"",IF($I$12<>"",IF(G46<>"",G46,($I$9/$I$12-SUM($U$25:U45))*V46*W46/SUMPRODUCT($W$44:$W46,$V$44:$V46)),""),"")
B47: 45788 | C47: вс | D47: 5783 | E47: 2 | F47: =IF(AND(E47<>"",E47<>0),D47/E47,"") -> 2891.5 | G47: 1 | H47: =IF(AND(G47<>"",G47<>0),D47/G47,"") -> 5783 | J47: =IF(AND(G47<>"",G47<>0),E47/G47,"") -> 2 | N47: =IF(AND(I47<>"",I47<>0),G47/I47,"") | O47: =D47/P47 -> #DIV/0! | P47: =$I$8*V47*W47/SUMPRODUCT($W$25:$W$47,$V$25:$V$47) -> 0 | Q47: =$I$9*V47*W47/SUMPRODUCT($W$25:$W$47,$V$25:$V$47) -> 0 | R47: =IF($I$12="","",Q47/$I$12) -> 0 | S47: =IF(W47<>"",IF(D47<>"",D47,($I$8-SUM($S$25:S46))*V47*W47/SUMPRODUCT($W47:$W$47,$V47:$V$47)),"") | T47: =IF(W47<>"",IF(E47<>"",E47,($I$9-SUM($T$25:T46))*V47*W47/SUMPRODUCT($W47:$W$47,$V47:$V$47)),"") | U47: =IF(W47<>"",IF($I$12<>"",IF(G47<>"",G47,($I$9/$I$12-SUM($U$25:U46))*V47*W47/SUMPRODUCT($W47:$W$47,$V47:$V$47)),""),"")
B48: итого | D48: =SUM(D25:D47) -> 707514 | E48: =SUM(E25:E47) -> 132 | F48: =IF(AND(E48<>"",E48<>0),D48/E48,"") -> 5359.9545 | G48: =SUM(G25:G47) -> 69 | H48: =IF(AND(G48<>"",G48<>0),D48/G48,"") -> 10253.826 | I48: =SUM(I25:I47) -> 313 | J48: =IF(AND(G48<>"",G48<>0),E48/G48,"") -> 1.9130435 | K48: =SUM(K25:K47) -> 121439 | L48: =SUM(L25:L47) -> 153471 | M48: =SUM(M25:M47) -> 0 | N48: =IF(AND(I48<>"",I48<>0),G48/I48,"") -> 0.22044728 | O48: =D48/P48 -> 0.49787481 | P48: =SUM(P25:P47) -> 1421068.1 | Q48: =SUM(Q25:Q47) -> 273.28232 | R48: =SUM(R25:R47) -> 140.86718 | S48: =SUM(S25:S47) -> 659093 | T48: =SUM(T25:T47) -> 127 | U48: =SUM(U25:U47) -> 63
D49: =SUMIF(D25:D47,"",P25:P47)+D48 -> 707514

Sheet ПК 3
B1: =TODAY()-1 -> 46171
B2: (отчетная дата) | J2: ЕЖЕДНЕВНЫЙ ОТЧЕТ О ПРОДАЖАХ
B3: Осталось до выполнения плана!!! | J3: =График!B26 -> Орешникова Елена
C4: =I8-D48 -> 0 | E4: =IF(I8<>0,C4/I8,0) -> 0
F6: Целевые показатели
F7: Показатель | I7: План | J7: Факт | K7: % выполнения | L7: Прогноз выполнения | M7: % выполнения по прогнозу | N7: Отклонение | O7: Факт аналогичного месяца прошлого года | P7: Отклонение LFL
F8: Выручка | I8: ='Ялта, Ленина, 18'!I8/График!AJ31*График!AJ26 -> 0 | J8: =D48 -> 0 | K8: =IF(AND(I8<>"",I8<>0,J8<>""),J8/I8,"") | L8: =IF(SUMIF($D$25:$D$47,">=0",$P$25:$P$47)<>0,I8*D48/SUMIF($D$25:$D$47,">=0",$P$25:$P$47),0) -> 0 | M8: =IF(AND(I8<>"",I8<>0,L8<>"",L8<>0),L8/I8,"") | N8: =IF(AND(J8<>0,J8<>"",I8<>0,I8<>""),L8-I8,"") | P8: =IF(AND(O8<>"",O8<>0,L8<>"",L8<>0),-O8+L8,"") | Q8: =IF(AND(P8<>"",P8<>0,O8<>0,O8<>""),P8/O8,"")
F9: Кол-во изделий | I9: =I8/I11 -> 0 | J9: =E48 -> 0 | K9: =IF(AND(I9<>"",I9<>0,J9<>""),J9/I9,"") | L9: =IF(SUMIF($E$25:$E$47,">=0",$Q$25:$Q$47)<>0,I9*E48/SUMIF($E$25:$E$47,">=0",$Q$25:$Q$47),0) -> 0 | M9: =IF(AND(I9<>"",I9<>0,L9<>"",L9<>0),L9/I9,"") | N9: =IF(AND(J9<>0,J9<>"",I9<>0,I9<>""),L9-I9,"") | O9: =O8/O11 -> #DIV/0! | P9: =IF(AND(O9<>"",O9<>0,L9<>"",L9<>0),-O9+L9,"") -> #DIV/0! | Q9: =IF(AND(P9<>"",P9<>0,O9<>0,O9<>""),P9/O9,"") -> #DIV/0!
F10: Средний чек | I10: =I11*I12 -> 10088 | J10: =H48 | K10: =IF(AND(I10<>"",I10<>0,J10<>""),J10/I10,"") | L10: =J10 | M10: =IF(AND(I10<>"",I10<>0,L10<>"",L10<>0),L10/I10,"") | N10: =IF(AND(J10<>0,J10<>"",I10<>0,I10<>""),L10-I10,"") | O10: =O11*O12 -> 0 | P10: =IF(AND(O10<>"",O10<>0,L10<>"",L10<>0),-O10+L10,"") | Q10: =IF(AND(P10<>"",P10<>0,O10<>0,O10<>""),P10/O10,"") | S10: IS
F11: Средняя стоимость изделия | I11: ='Ялта, Ленина, 18'!I11 -> 5200 | J11: =F48 | K11: =IF(AND(I11<>"",I11<>0,J11<>""),J11/I11,"") | L11: =IF(L9>0,L8/L9,"") | M11: =IF(AND(I11<>"",I11<>0,L11<>"",L11<>0),L11/I11,"") | N11: =IF(AND(J11<>0,J11<>"",I11<>0,I11<>""),L11-I11,"") | P11: =IF(AND(O11<>"",O11<>0,L11<>"",L11<>0),-O11+L11,"") | Q11: =IF(AND(P11<>"",P11<>0,O11<>0,O11<>""),P11/O11,"")
F12: Длина чека | I12: ='Ялта, Ленина, 18'!I12 -> 1.94 | J12: =J48 | K12: =IF(AND(I12<>"",I12<>0,J12<>""),J12/I12,"") | L12: =J12 | M12: =IF(AND(I12<>"",I12<>0,L12<>"",L12<>0),L12/I12,"") | N12: =IF(AND(J12<>0,J12<>"",I12<>0,I12<>""),L12-I12,"") | P12: =IF(AND(O12<>"",O12<>0,L12<>"",L12<>0),-O12+L12,"") | Q12: =IF(AND(P12<>"",P12<>0,O12<>0,O12<>""),P12/O12,"") | S12: ='Ялта, Ленина, 18'!S12*График!AJ26/График!AJ31 -> 0 | T12: =L54 -> 0
F13: Кол-во чеков | I13: =IF(I12<>0,I9/I12,"") -> 0 | J13: =G48 -> 0 | K13: =IF(AND(I13<>"",I13<>0,J13<>""),J13/I13,"") | L13: =IF(SUMIF($G$25:$G$47,">=0",$R$25:$R$47)<>0,I13*G48/SUMIF($G$25:$G$47,">=0",$R$25:$R$47),"") -> #DIV/0! | M13: =IF(AND(I13<>"",I13<>0,L13<>"",L13<>0),L13/I13,"") -> #DIV/0! | N13: =IF(AND(J13<>0,J13<>"",I13<>0,I13<>""),L13-I13,"") | P13: =IF(AND(O13<>"",O13<>0,L13<>"",L13<>0),-O13+L13,"") -> #DIV/0! | Q13: =IF(AND(P13<>"",P13<>0,O13<>0,O13<>""),P13/O13,"") -> #DIV/0! | S13: =T12/S12 -> #DIV/0! | T13: =S13/J14*I14 -> #DIV/0!
F14: Кол-во смен план/отработано | I14: =График!AI27 -> 19 | K14: =IF(AND(I14<>"",I14<>0,J14<>""),J14/I14,"") | L14: =I14 -> 19 | M14: =IF(AND(I14<>"",I14<>0,L14<>"",L14<>0),L14/I14,"") -> 1 | N14: =IF(AND(J14<>0,J14<>"",I14<>0,I14<>""),L14-I14,"") | P14: =IF(AND(O14<>"",O14<>0,L14<>"",L14<>0),-O14+L14,"") | Q14: =IF(AND(P14<>"",P14<>0,O14<>0,O14<>""),P14/O14,"")
F15: Средние продажи в смену | I15: ='Ялта, Ленина, 18'!I15 -> 154639.28 | J15: =J8/J14 -> #DIV/0! | K15: =IF(AND(I15<>"",I15<>0,J15<>""),J15/I15,"") -> #DIV/0! | L15: =J15 -> #DIV/0! | M15: =IF(AND(I15<>"",I15<>0,L15<>"",L15<>0),L15/I15,"") -> #DIV/0! | N15: =IF(AND(J15<>0,J15<>"",I15<>0,I15<>""),L15-I15,"") -> #DIV/0! | P15: =IF(AND(O15<>"",O15<>0,L15<>"",L15<>0),-O15+L15,"") -> #DIV/0! | Q15: =IF(AND(P15<>"",P15<>0,O15<>0,O15<>""),P15/O15,"") -> #DIV/0!
F16: Отставание/Перевыполнение | J16: =J8-I15*J14 -> 0 | K16: =IF(AND(I16<>"",I16<>0,J16<>""),J16/I16,"") | L16: =J16 -> 0 | M16: =IF(AND(I16<>"",I16<>0,L16<>"",L16<>0),L16/I16,"") | N16: =IF(AND(J16<>0,J16<>"",I16<>0,I16<>""),L16-I16,"") | P16: =IF(AND(O16<>"",O16<>0,L16<>"",L16<>0),-O16+L16,"") | Q16: =IF(AND(P16<>"",P16<>0,O16<>0,O16<>""),P16/O16,"") | S16: UNOde50
F17: Трафик | I17: ='Ялта, Ленина, 18'!I17/График!AJ31*График!AJ26 -> 0 | J17: =I48 -> 0 | K17: =IF(AND(I17<>"",I17<>0,J17<>""),J17/I17,"") | L17: =J17/J14*I14 -> #DIV/0! | M17: =IF(AND(I17<>"",I17<>0,L17<>"",L17<>0),L17/I17,"") -> #DIV/0! | N17: =IF(AND(J17<>0,J17<>"",I17<>0,I17<>""),L17-I17,"") | P17: =IF(AND(O17<>"",O17<>0,L17<>"",L17<>0),-O17+L17,"") -> #DIV/0! | Q17: =IF(AND(P17<>"",P17<>0,O17<>0,O17<>""),P17/O17,"") -> #DIV/0!
K18: =IF(AND(I18<>"",I18<>0,J18<>""),J18/I18,"") | L18: =J18 -> 0 | M18: =IF(AND(I18<>"",I18<>0,L18<>"",L18<>0),L18/I18,"") | N18: =IF(AND(J18<>0,J18<>"",I18<>0,I18<>""),L18-I18,"") | O18: 0 | P18: =IF(AND(O18<>"",O18<>0,L18<>"",L18<>0),-O18+L18,"") | Q18: =IF(AND(P18<>"",P18<>0,O18<>0,O18<>""),P18/O18,"") | S18: ='Ялта, Ленина, 18'!S18*График!AJ26/График!AJ31 -> 0 | T18: =K54 -> 0
J19: =M48 -> 0 | K19: =IF(AND(I19<>"",I19<>0,J19<>""),J19/I19,"") | L19: =J19 -> 0 | M19: =IF(AND(I19<>"",I19<>0,L19<>"",L19<>0),L19/I19,"") | N19: =IF(AND(J19<>0,J19<>"",I19<>0,I19<>""),L19-I19,"") | O19: 0 | P19: =IF(AND(O19<>"",O19<>0,L19<>"",L19<>0),-O19+L19,"") | Q19: =IF(AND(P19<>"",P19<>0,O19<>0,O19<>""),P19/O19,"") | S19: =T18/S18 -> #DIV/0! | T19: =S19/J14*I14 -> #DIV/0!
F20: Конверсия план/факт | I20: ='Ялта, Ленина, 18'!I20 -> 0.22 | J20: =N48 | K20: =J20/I20 -> #VALUE! | L20: =IF(AND(K8<>0,I14<>0,I48<>0),(I48*N48+(I48/K8-I48)*I20)/(I48/K8),0) -> 0 | M20: =IF(AND(I20<>"",I20<>0,L20<>"",L20<>0),L20/I20,"") | N20: =IF(AND(J20<>0,J20<>"",I20<>0,I20<>""),L20-I20,"") | P20: =IF(AND(O20<>"",O20<>0,L20<>"",L20<>0),-O20+L20,"") | Q20: =IF(AND(P20<>"",P20<>0,O20<>0,O20<>""),P20/O20,"")
B22: Факт продаж за месяц | O22: % выполнения дневного плана | P22: Раcпределение плана по дням
B23: Дата | C23: День недели | D23: Выручка (руб) | E23: Кол-во единиц (шт.) | F23: Средняя стоимость изделия (руб.) | G23: Количество чеков (шт.) | H23: Средняя сумма чека (руб.) | I23: Трафик | J23: Длина чека (шт.) | K23: UNOde50 | L23: IS | M23: Запасной | N23: Конверсия (%) | P23: выручка, план | Q23: кол-во ед, план | R23: Кол-во чеков, план | S23: выручка, скорректир.план | T23: кол-во ед, скорр. план | U23: кол-во чеков, скорр. план | V23: Коэфф. Дня Недели | W23: Специфика месяца
B24: 1 | C24: 2 | D24: 3 | E24: 4 | F24: 5 | G24: 6 | H24: 7 | I24: 8 | J24: 9 | K24: 10 | L24: 11 | M24: 12 | N24: 13 | P24: 1 | Q24: 2 | R24: 3 | S24: 4 | T24: 5 | U24: 6 | V24: 10 | W24: 11
A25: 1 | F25: =IF(AND(E25<>"",E25<>0),D25/E25,"") | H25: =IF(AND(G25<>"",G25<>0),D25/G25,"") | J25: =IF(AND(G25<>"",G25<>0),E25/G25,"") | N25: =IF(AND(I25<>"",I25<>0),G25/I25,"") | O25: =D25/P25 -> #DIV/0! | P25: =$I$8*V25*W25/SUMPRODUCT($W$25:$W$55,$V$25:$V$55) -> #DIV/0! | Q25: =$I$9*V25*W25/SUMPRODUCT($W$25:$W$55,$V$25:$V$55) -> #DIV/0! | R25: =IF($I$12="","",Q25/$I$12) -> #DIV/0! | S25: =IF(D25<>"",D25,P25) -> #DIV/0! | T25: =IF(E25<>"",E25,Q25) -> #DIV/0! | U25: =IF(G25<>"",G25,R25) -> #DIV/0!
A26: 2 | F26: =IF(AND(E26<>"",E26<>0),D26/E26,"") | G26: 0 | H26: =IF(AND(G26<>"",G26<>0),D26/G26,"") | J26: =IF(AND(G26<>"",G26<>0),E26/G26,"") | N26: =IF(AND(I26<>"",I26<>0),G26/I26,"") | O26: =D26/P26 -> #DIV/0! | P26: =$I$8*V26*W26/SUMPRODUCT($W$25:$W$55,$V$25:$V$55) -> #DIV/0! | Q26: =$I$9*V26*W26/SUMPRODUCT($W$25:$W$55,$V$25:$V$55) -> #DIV/0! | R26: =IF($I$12="","",Q26/$I$12) -> #DIV/0! | S26: =IF(W26<>"",IF(D26<>"",D26,($I$8-SUM($S$25:S25))*V26*W26/SUMPRODUCT($W26:$W$55,$V26:$V$55)),"") | T26: =IF(W26<>"",IF(E26<>"",E26,($I$9-SUM($T$25:T25))*V26*W26/SUMPRODUCT($W26:$W$55,$V26:$V$55)),"") | U26: =IF(W26<>"",IF($I$12<>"",IF(G26<>"",G26,($I$9/$I$12-SUM($U$25:U25))*V26*W26/SUMPRODUCT($W26:$W$55,$V26:$V$55)),""),"")
A27: 3 | F27: =IF(AND(E27<>"",E27<>0),D27/E27,"") | H27: =IF(AND(G27<>"",G27<>0),D27/G27,"") | J27: =IF(AND(G27<>"",G27<>0),E27/G27,"") | N27: =IF(AND(I27<>"",I27<>0),G27/I27,"") | O27: =D27/P27 -> #DIV/0! | P27: =$I$8*V27*W27/SUMPRODUCT($W$25:$W$55,$V$25:$V$55) -> #DIV/0! | Q27: =$I$9*V27*W27/SUMPRODUCT($W$25:$W$55,$V$25:$V$55) -> #DIV/0! | R27: =IF($I$12="","",Q27/$I$12) -> #DIV/0! | S27: =IF(W27<>"",IF(D27<>"",D27,($I$8-SUM($S$25:S26))*V27*W27/SUMPRODUCT($W27:$W$55,$V27:$V$55)),"") | T27: =IF(W27<>"",IF(E27<>"",E27,($I$9-SUM($T$25:T26))*V27*W27/SUMPRODUCT($W27:$W$55,$V27:$V$55)),"") | U27: =IF(W27<>"",IF($I$12<>"",IF(G27<>"",G27,($I$9/$I$12-SUM($U$25:U26))*V27*W27/SUMPRODUCT($W27:$W$55,$V27:$V$55)),""),"")
A28: 4 | F28: =IF(AND(E28<>"",E28<>0),D28/E28,"") | H28: =IF(AND(G28<>"",G28<>0),D28/G28,"") | J28: =IF(AND(G28<>"",G28<>0),E28/G28,"") | N28: =IF(AND(I28<>"",I28<>0),G28/I28,"") | O28: =D28/P28 -> #DIV/0! | P28: =$I$8*V28*W28/SUMPRODUCT($W$25:$W$55,$V$25:$V$55) -> #DIV/0! | Q28: =$I$9*V28*W28/SUMPRODUCT($W$25:$W$55,$V$25:$V$55) -> #DIV/0! | R28: =IF($I$12="","",Q28/$I$12) -> #DIV/0! | S28: =IF(W28<>"",IF(D28<>"",D28,($I$8-SUM($S$25:S27))*V28*W28/SUMPRODUCT($W28:$W$55,$V28:$V$55)),"") | T28: =IF(W28<>"",IF(E28<>"",E28,($I$9-SUM($T$25:T27))*V28*W28/SUMPRODUCT($W28:$W$55,$V28:$V$55)),"") | U28: =IF(W28<>"",IF($I$12<>"",IF(G28<>"",G28,($I$9/$I$12-SUM($U$25:U27))*V28*W28/SUMPRODUCT($W28:$W$55,$V28:$V$55)),""),"")
A29: 5 | F29: =IF(AND(E29<>"",E29<>0),D29/E29,"") | H29: =IF(AND(G29<>"",G29<>0),D29/G29,"") | J29: =IF(AND(G29<>"",G29<>0),E29/G29,"") | N29: =IF(AND(I29<>"",I29<>0),G29/I29,"") | O29: =D29/P29 -> #DIV/0! | P29: =$I$8*V29*W29/SUMPRODUCT($W$25:$W$55,$V$25:$V$55) -> #DIV/0! | Q29: =$I$9*V29*W29/SUMPRODUCT($W$25:$W$55,$V$25:$V$55) -> #DIV/0! | R29: =IF($I$12="","",Q29/$I$12) -> #DIV/0! | S29: =IF(W29<>"",IF(D29<>"",D29,($I$8-SUM($S$25:S28))*V29*W29/SUMPRODUCT($W29:$W$55,$V29:$V$55)),"") | T29: =IF(W29<>"",IF(E29<>"",E29,($I$9-SUM($T$25:T28))*V29*W29/SUMPRODUCT($W29:$W$55,$V29:$V$55)),"") | U29: =IF(W29<>"",IF($I$12<>"",IF(G29<>"",G29,($I$9/$I$12-SUM($U$25:U28))*V29*W29/SUMPRODUCT($W29:$W$55,$V29:$V$55)),""),"")
A30: 6 | F30: =IF(AND(E30<>"",E30<>0),D30/E30,"") | H30: =IF(AND(G30<>"",G30<>0),D30/G30,"") | J30: =IF(AND(G30<>"",G30<>0),E30/G30,"") | N30: =IF(AND(I30<>"",I30<>0),G30/I30,"") | O30: =D30/P30 -> #DIV/0! | P30: =$I$8*V30*W30/SUMPRODUCT($W$25:$W$55,$V$25:$V$55) -> #DIV/0! | Q30: =$I$9*V30*W30/SUMPRODUCT($W$25:$W$55,$V$25:$V$55) -> #DIV/0! | R30: =IF($I$12="","",Q30/$I$12) -> #DIV/0! | S30: =IF(W30<>"",IF(D30<>"",D30,($I$8-SUM($S$25:S29))*V30*W30/SUMPRODUCT($W30:$W$55,$V30:$V$55)),"") | T30: =IF(W30<>"",IF(E29<>"",E29,($I$9-SUM($T$25:T29))*V30*W30/SUMPRODUCT($W30:$W$55,$V30:$V$55)),"") | U30: =IF(W30<>"",IF($I$12<>"",IF(G30<>"",G30,($I$9/$I$12-SUM($U$25:U29))*V30*W30/SUMPRODUCT($W30:$W$55,$V30:$V$55)),""),"")
A31: 7 | F31: =IF(AND(E31<>"",E31<>0),D31/E31,"") | H31: =IF(AND(G31<>"",G31<>0),D31/G31,"") | J31: =IF(AND(G31<>"",G31<>0),E31/G31,"") | N31: =IF(AND(I31<>"",I31<>0),G31/I31,"") | O31: =D31/P31 -> #DIV/0! | P31: =$I$8*V31*W31/SUMPRODUCT($W$25:$W$55,$V$25:$V$55) -> #DIV/0! | Q31: =$I$9*V31*W31/SUMPRODUCT($W$25:$W$55,$V$25:$V$55) -> #DIV/0! | R31: =IF($I$12="","",Q31/$I$12) -> #DIV/0! | S31: =IF(W31<>"",IF(D31<>"",D31,($I$8-SUM($S$25:S30))*V31*W31/SUMPRODUCT($W31:$W$55,$V31:$V$55)),"") | T31: =IF(W31<>"",IF(E31<>"",E31,($I$9-SUM($T$25:T30))*V31*W31/SUMPRODUCT($W31:$W$55,$V31:$V$55)),"") | U31: =IF(W31<>"",IF($I$12<>"",IF(G31<>"",G31,($I$9/$I$12-SUM($U$25:U30))*V31*W31/SUMPRODUCT($W31:$W$55,$V31:$V$55)),""),"")
A32: 8 | F32: =IF(AND(E32<>"",E32<>0),D32/E32,"") | H32: =IF(AND(G32<>"",G32<>0),D32/G32,"") | J32: =IF(AND(G32<>"",G32<>0),E32/G32,"") | N32: =IF(AND(I32<>"",I32<>0),G32/I32,"") | O32: =D32/P32 -> #DIV/0! | P32: =$I$8*V32*W32/SUMPRODUCT($W$25:$W$55,$V$25:$V$55) -> #DIV/0! | Q32: =$I$9*V32*W32/SUMPRODUCT($W$25:$W$55,$V$25:$V$55) -> #DIV/0! | R32: =IF($I$12="","",Q32/$I$12) -> #DIV/0! | S32: =IF(W32<>"",IF(D32<>"",D32,($I$8-SUM($S$25:S31))*V32*W32/SUMPRODUCT($W32:$W$55,$V32:$V$55)),"") | T32: =IF(W32<>"",IF(E32<>"",E32,($I$9-SUM($T$25:T31))*V32*W32/SUMPRODUCT($W32:$W$55,$V32:$V$55)),"") | U32: =IF(W32<>"",IF($I$12<>"",IF(G32<>"",G32,($I$9/$I$12-SUM($U$25:U31))*V32*W32/SUMPRODUCT($W32:$W$55,$V32:$V$55)),""),"")
A33: 9 | F33: =IF(AND(E33<>"",E33<>0),D33/E33,"") | H33: =IF(AND(G33<>"",G33<>0),D33/G33,"") | J33: =IF(AND(G33<>"",G33<>0),E33/G33,"") | N33: =IF(AND(I33<>"",I33<>0),G33/I33,"") | O33: =D33/P33 -> #DIV/0! | P33: =$I$8*V33*W33/SUMPRODUCT($W$25:$W$55,$V$25:$V$55) -> #DIV/0! | Q33: =$I$9*V33*W33/SUMPRODUCT($W$25:$W$55,$V$25:$V$55) -> #DIV/0! | R33: =IF($I$12="","",Q33/$I$12) -> #DIV/0! | S33: =IF(W33<>"",IF(D33<>"",D33,($I$8-SUM($S$25:S32))*V33*W33/SUMPRODUCT($W33:$W$55,$V33:$V$55)),"") | T33: =IF(W33<>"",IF(E33<>"",E33,($I$9-SUM($T$25:T32))*V33*W33/SUMPRODUCT($W33:$W$55,$V33:$V$55)),"") | U33: =IF(W33<>"",IF($I$12<>"",IF(G33<>"",G33,($I$9/$I$12-SUM($U$25:U32))*V33*W33/SUMPRODUCT($W33:$W$55,$V33:$V$55)),""),"")
A34: 10 | F34: =IF(AND(E34<>"",E34<>0),D34/E34,"") | H34: =IF(AND(G34<>"",G34<>0),D34/G34,"") | J34: =IF(AND(G34<>"",G34<>0),E34/G34,"") | N34: =IF(AND(I34<>"",I34<>0),G34/I34,"") | O34: =D34/P34 -> #DIV/0! | P34: =$I$8*V34*W34/SUMPRODUCT($W$25:$W$55,$V$25:$V$55) -> #DIV/0! | Q34: =$I$9*V34*W34/SUMPRODUCT($W$25:$W$55,$V$25:$V$55) -> #DIV/0! | R34: =IF($I$12="","",Q34/$I$12) -> #DIV/0! | S34: =IF(W34<>"",IF(D34<>"",D34,($I$8-SUM($S$25:S33))*V34*W34/SUMPRODUCT($W34:$W$55,$V34:$V$55)),"") | T34: =IF(W34<>"",IF(E34<>"",E34,($I$9-SUM($T$25:T33))*V34*W34/SUMPRODUCT($W34:$W$55,$V34:$V$55)),"") | U34: =IF(W34<>"",IF($I$12<>"",IF(G34<>"",G34,($I$9/$I$12-SUM($U$25:U33))*V34*W34/SUMPRODUCT($W34:$W$55,$V34:$V$55)),""),"")
A35: 11 | F35: =IF(AND(E35<>"",E35<>0),D35/E35,"") | H35: =IF(AND(G35<>"",G35<>0),D35/G35,"") | J35: =IF(AND(G35<>"",G35<>0),E35/G35,"") | N35: =IF(AND(I35<>"",I35<>0),G35/I35,"") | O35: =D35/P35 -> #DIV/0! | P35: =$I$8*V35*W35/SUMPRODUCT($W$25:$W$55,$V$25:$V$55) -> #DIV/0! | Q35: =$I$9*V35*W35/SUMPRODUCT($W$25:$W$55,$V$25:$V$55) -> #DIV/0! | R35: =IF($I$12="","",Q35/$I$12) -> #DIV/0! | S35: =IF(W35<>"",IF(D35<>"",D35,($I$8-SUM($S$25:S34))*V35*W35/SUMPRODUCT($W35:$W$55,$V35:$V$55)),"") | T35: =IF(W35<>"",IF(E35<>"",E35,($I$9-SUM($T$25:T34))*V35*W35/SUMPRODUCT($W35:$W$55,$V35:$V$55)),"") | U35: =IF(W35<>"",IF($I$12<>"",IF(G35<>"",G35,($I$9/$I$12-SUM($U$25:U34))*V35*W35/SUMPRODUCT($W35:$W$55,$V35:$V$55)),""),"")
A36: 12 | F36: =IF(AND(E36<>"",E36<>0),D36/E36,"") | H36: =IF(AND(G36<>"",G36<>0),D36/G36,"") | J36: =IF(AND(G36<>"",G36<>0),E36/G36,"") | N36: =IF(AND(I36<>"",I36<>0),G36/I36,"") | O36: =D36/P36 -> #DIV/0! | P36: =$I$8*V36*W36/SUMPRODUCT($W$25:$W$55,$V$25:$V$55) -> #DIV/0! | Q36: =$I$9*V36*W36/SUMPRODUCT($W$25:$W$55,$V$25:$V$55) -> #DIV/0! | R36: =IF($I$12="","",Q36/$I$12) -> #DIV/0! | S36: =IF(W36<>"",IF(D36<>"",D36,($I$8-SUM($S$25:S35))*V36*W36/SUMPRODUCT($W36:$W$55,$V36:$V$55)),"") | T36: =IF(W36<>"",IF(E36<>"",E36,($I$9-SUM($T$25:T35))*V36*W36/SUMPRODUCT($W36:$W$55,$V36:$V$55)),"") | U36: =IF(W36<>"",IF($I$12<>"",IF(G36<>"",G36,($I$9/$I$12-SUM($U$25:U35))*V36*W36/SUMPRODUCT($W36:$W$55,$V36:$V$55)),""),"")
A37: 13 | F37: =IF(AND(E37<>"",E37<>0),D37/E37,"") | H37: =IF(AND(G37<>"",G37<>0),D37/G37,"") | J37: =IF(AND(G37<>"",G37<>0),E37/G37,"") | N37: =IF(AND(I37<>"",I37<>0),G37/I37,"") | O37: =D37/P37 -> #DIV/0! | P37: =$I$8*V37*W37/SUMPRODUCT($W$25:$W$55,$V$25:$V$55) -> #DIV/0! | Q37: =$I$9*V37*W37/SUMPRODUCT($W$25:$W$55,$V$25:$V$55) -> #DIV/0! | R37: =IF($I$12="","",Q37/$I$12) -> #DIV/0! | S37: =IF(W37<>"",IF(D37<>"",D37,($I$8-SUM($S$25:S36))*V37*W37/SUMPRODUCT($W37:$W$55,$V37:$V$55)),"") | T37: =IF(W37<>"",IF(E37<>"",E37,($I$9-SUM($T$25:T36))*V37*W37/SUMPRODUCT($W37:$W$55,$V37:$V$55)),"") | U37: =IF(W37<>"",IF($I$12<>"",IF(G37<>"",G37,($I$9/$I$12-SUM($U$25:U36))*V37*W37/SUMPRODUCT($W37:$W$55,$V37:$V$55)),""),"")
A38: 14 | F38: =IF(AND(E38<>"",E38<>0),D38/E38,"") | H38: =IF(AND(G38<>"",G38<>0),D38/G38,"") | J38: =IF(AND(G38<>"",G38<>0),E38/G38,"") | N38: =IF(AND(I38<>"",I38<>0),G38/I38,"") | O38: =D38/P38 -> #DIV/0! | P38: =$I$8*V38*W38/SUMPRODUCT($W$25:$W$55,$V$25:$V$55) -> #DIV/0! | Q38: =$I$9*V38*W38/SUMPRODUCT($W$25:$W$55,$V$25:$V$55) -> #DIV/0! | R38: =IF($I$12="","",Q38/$I$12) -> #DIV/0! | S38: =IF(W38<>"",IF(D38<>"",D38,($I$8-SUM($S$25:S37))*V38*W38/SUMPRODUCT($W38:$W$55,$V38:$V$55)),"") | T38: =IF(W38<>"",IF(E38<>"",E38,($I$9-SUM($T$25:T37))*V38*W38/SUMPRODUCT($W38:$W$55,$V38:$V$55)),"") | U38: =IF(W38<>"",IF($I$12<>"",IF(G38<>"",G38,($I$9/$I$12-SUM($U$25:U37))*V38*W38/SUMPRODUCT($W38:$W$55,$V38:$V$55)),""),"")
A39: 15 | F39: =IF(AND(E39<>"",E39<>0),D39/E39,"") | H39: =IF(AND(G39<>"",G39<>0),D39/G39,"") | J39: =IF(AND(G39<>"",G39<>0),E39/G39,"") | N39: =IF(AND(I39<>"",I39<>0),G39/I39,"") | O39: =D39/P39 -> #DIV/0! | P39: =$I$8*V39*W39/SUMPRODUCT($W$25:$W$55,$V$25:$V$55) -> #DIV/0! | Q39: =$I$9*V39*W39/SUMPRODUCT($W$25:$W$55,$V$25:$V$55) -> #DIV/0! | R39: =IF($I$12="","",Q39/$I$12) -> #DIV/0! | S39: =IF(W39<>"",IF(D39<>"",D39,($I$8-SUM($S$25:S38))*V39*W39/SUMPRODUCT($W39:$W$55,$V39:$V$55)),"") | T39: =IF(W39<>"",IF(E39<>"",E39,($I$9-SUM($T$25:T38))*V39*W39/SUMPRODUCT($W39:$W$55,$V39:$V$55)),"") | U39: =IF(W39<>"",IF($I$12<>"",IF(G39<>"",G39,($I$9/$I$12-SUM($U$25:U38))*V39*W39/SUMPRODUCT($W39:$W$55,$V39:$V$55)),""),"")
A40: 16 | F40: =IF(AND(E40<>"",E40<>0),D40/E40,"") | H40: =IF(AND(G40<>"",G40<>0),D40/G40,"") | J40: =IF(AND(G40<>"",G40<>0),E40/G40,"") | N40: =IF(AND(I40<>"",I40<>0),G40/I40,"") | O40: =D40/P40 -> #DIV/0! | P40: =$I$8*V40*W40/SUMPRODUCT($W$25:$W$55,$V$25:$V$55) -> #DIV/0! | Q40: =$I$9*V40*W40/SUMPRODUCT($W$25:$W$55,$V$25:$V$55) -> #DIV/0! | R40: =IF($I$12="","",Q40/$I$12) -> #DIV/0! | S40: =IF(W40<>"",IF(D40<>"",D40,($I$8-SUM($S$25:S39))*V40*W40/SUMPRODUCT($W40:$W$55,$V40:$V$55)),"") | T40: =IF(W40<>"",IF(E40<>"",E40,($I$9-SUM($T$25:T39))*V40*W40/SUMPRODUCT($W40:$W$55,$V40:$V$55)),"") | U40: =IF(W40<>"",IF($I$12<>"",IF(G40<>"",G40,($I$9/$I$12-SUM($U$25:U39))*V40*W40/SUMPRODUCT($W40:$W$55,$V40:$V$55)),""),"")
A41: 17 | F41: =IF(AND(E41<>"",E41<>0),D41/E41,"") | H41: =IF(AND(G41<>"",G41<>0),D41/G41,"") | J41: =IF(AND(G41<>"",G41<>0),E41/G41,"") | N41: =IF(AND(I41<>"",I41<>0),G41/I41,"") | O41: =D41/P41 -> #DIV/0! | P41: =$I$8*V41*W41/SUMPRODUCT($W$25:$W$55,$V$25:$V$55) -> #DIV/0! | Q41: =$I$9*V41*W41/SUMPRODUCT($W$25:$W$55,$V$25:$V$55) -> #DIV/0! | R41: =IF($I$12="","",Q41/$I$12) -> #DIV/0! | S41: =IF(W41<>"",IF(D41<>"",D41,($I$8-SUM($S$25:S40))*V41*W41/SUMPRODUCT($W41:$W$55,$V41:$V$55)),"") | T41: =IF(W41<>"",IF(E41<>"",E41,($I$9-SUM($T$25:T40))*V41*W41/SUMPRODUCT($W41:$W$55,$V41:$V$55)),"") | U41: =IF(W41<>"",IF($I$12<>"",IF(G41<>"",G41,($I$9/$I$12-SUM($U$25:U40))*V41*W41/SUMPRODUCT($W41:$W$55,$V41:$V$55)),""),"")
A42: 18 | F42: =IF(AND(E42<>"",E42<>0),D42/E42,"") | H42: =IF(AND(G42<>"",G42<>0),D42/G42,"") | J42: =IF(AND(G42<>"",G42<>0),E42/G42,"") | N42: =IF(AND(I42<>"",I42<>0),G42/I42,"") | O42: =D42/P42 -> #DIV/0! | P42: =$I$8*V42*W42/SUMPRODUCT($W$25:$W$55,$V$25:$V$55) -> #DIV/0! | Q42: =$I$9*V42*W42/SUMPRODUCT($W$25:$W$55,$V$25:$V$55) -> #DIV/0! | R42: =IF($I$12="","",Q42/$I$12) -> #DIV/0! | S42: =IF(W42<>"",IF(D42<>"",D42,($I$8-SUM($S$25:S41))*V42*W42/SUMPRODUCT($W42:$W$55,$V42:$V$55)),"") | T42: =IF(W42<>"",IF(E42<>"",E42,($I$9-SUM($T$25:T41))*V42*W42/SUMPRODUCT($W42:$W$55,$V42:$V$55)),"") | U42: =IF(W42<>"",IF($I$12<>"",IF(G42<>"",G42,($I$9/$I$12-SUM($U$25:U41))*V42*W42/SUMPRODUCT($W42:$W$55,$V42:$V$55)),""),"")
F43: =IF(AND(E43<>"",E43<>0),D43/E43,"") | H43: =IF(AND(G43<>"",G43<>0),D43/G43,"") | J43: =IF(AND(G43<>"",G43<>0),E43/G43,"") | N43: =IF(AND(I43<>"",I43<>0),G43/I43,"") | O43: =D43/P43 -> #DIV/0! | P43: =$I$8*V43*W43/SUMPRODUCT($W$25:$W$55,$V$25:$V$55) -> #DIV/0! | Q43: =$I$9*V43*W43/SUMPRODUCT($W$25:$W$55,$V$25:$V$55) -> #DIV/0! | R43: =IF($I$12="","",Q43/$I$12) -> #DIV/0! | S43: =IF(W43<>"",IF(D43<>"",D43,($I$8-SUM($S$25:S42))*V43*W43/SUMPRODUCT($W43:$W$55,$V43:$V$55)),"") | T43: =IF(W43<>"",IF(E43<>"",E43,($I$9-SUM($T$25:T42))*V43*W43/SUMPRODUCT($W43:$W$55,$V43:$V$55)),"") | U43: =IF(W43<>"",IF($I$12<>"",IF(G43<>"",G43,($I$9/$I$12-SUM($U$25:U42))*V43*W43/SUMPRODUCT($W43:$W$55,$V43:$V$55)),""),"")
F44: =IF(AND(E44<>"",E44<>0),D44/E44,"") | H44: =IF(AND(G44<>"",G44<>0),D44/G44,"") | J44: =IF(AND(G44<>"",G44<>0),E44/G44,"") | N44: =IF(AND(I44<>"",I44<>0),G44/I44,"") | O44: =D44/P44 -> #DIV/0! | P44: =$I$8*V44*W44/SUMPRODUCT($W$25:$W$55,$V$25:$V$55) -> #DIV/0! | Q44: =$I$9*V44*W44/SUMPRODUCT($W$25:$W$55,$V$25:$V$55) -> #DIV/0! | R44: =IF($I$12="","",Q44/$I$12) -> #DIV/0! | S44: =IF(W44<>"",IF(D44<>"",D44,($I$8-SUM($S$25:S43))*V44*W44/SUMPRODUCT($W44:$W$55,$V44:$V$55)),"") | T44: =IF(W44<>"",IF(E44<>"",E44,($I$9-SUM($T$25:T43))*V44*W44/SUMPRODUCT($W44:$W$55,$V44:$V$55)),0) -> 0 | U44: =IF(W44<>"",IF($I$12<>"",IF(G44<>"",G44,($I$9/$I$12-SUM($U$25:U43))*V44*W44/SUMPRODUCT($W44:$W$55,$V44:$V$55)),""),"")
F45: =IF(AND(E45<>"",E45<>0),D45/E45,"") | H45: =IF(AND(G45<>"",G45<>0),D45/G45,"") | J45: =IF(AND(G45<>"",G45<>0),E45/G45,"") | N45: =IF(AND(I45<>"",I45<>0),G45/I45,"") | O45: =D45/P45 -> #DIV/0! | P45: =$I$8*V45*W45/SUMPRODUCT($W$25:$W$44,$V$25:$V$44) -> #DIV/0! | Q45: =$I$9*V45*W45/SUMPRODUCT($W$25:$W$44,$V$25:$V$44) -> #DIV/0! | R45: =IF($I$12="","",Q45/$I$12) -> #DIV/0! | S45: =IF(W45<>"",IF(D45<>"",D45,($I$8-SUM($S$25:S44))*V45*W45/SUMPRODUCT($W$44:$W45,$V$44:$V45)),"") | T45: =IF(W45<>"",IF(E45<>"",E45,($I$9-SUM($T$25:T44))*V45*W45/SUMPRODUCT($W$44:$W45,$V$44:$V45)),"") | U45: =IF(W45<>"",IF($I$12<>"",IF(G45<>"",G45,($I$9/$I$12-SUM($U$25:U44))*V45*W45/SUMPRODUCT($W$44:$W45,$V$44:$V45)),""),"")
F46: =IF(AND(E46<>"",E46<>0),D46/E46,"") | H46: =IF(AND(G46<>"",G46<>0),D46/G46,"") | J46: =IF(AND(G46<>"",G46<>0),E46/G46,"") | N46: =IF(AND(I46<>"",I46<>0),G46/I46,"") | O46: =D46/P46 -> #DIV/0! | P46: =$I$8*V46*W46/SUMPRODUCT($W$25:$W$44,$V$25:$V$44) -> #DIV/0! | Q46: =$I$9*V46*W46/SUMPRODUCT($W$25:$W$44,$V$25:$V$44) -> #DIV/0! | R46: =IF($I$12="","",Q46/$I$12) -> #DIV/0! | S46: =IF(W46<>"",IF(D46<>"",D46,($I$8-SUM($S$25:S45))*V46*W46/SUMPRODUCT($W$44:$W46,$V$44:$V46)),"") | T46: =IF(W46<>"",IF(E46<>"",E46,($I$9-SUM($T$25:T45))*V46*W46/SUMPRODUCT($W$44:$W46,$V$44:$V46)),"") | U46: =IF(W46<>"",IF($I$12<>"",IF(G46<>"",G46,($I$9/$I$12-SUM($U$25:U45))*V46*W46/SUMPRODUCT($W$44:$W46,$V$44:$V46)),""),"")
F47: =IF(AND(E47<>"",E47<>0),D47/E47,"") | H47: =IF(AND(G47<>"",G47<>0),D47/G47,"") | J47: =IF(AND(G47<>"",G47<>0),E47/G47,"") | N47: =IF(AND(I47<>"",I47<>0),G47/I47,"") | O47: =D47/P47 -> #DIV/0! | P47: =$I$8*V47*W47/SUMPRODUCT($W$25:$W$47,$V$25:$V$47) -> #DIV/0! | Q47: =$I$9*V47*W47/SUMPRODUCT($W$25:$W$47,$V$25:$V$47) -> #DIV/0! | R47: =IF($I$12="","",Q47/$I$12) -> #DIV/0! | S47: =IF(W47<>"",IF(D47<>"",D47,($I$8-SUM($S$25:S46))*V47*W47/SUMPRODUCT($W47:$W$47,$V47:$V$47)),"") | T47: =IF(W47<>"",IF(E47<>"",E47,($I$9-SUM($T$25:T46))*V47*W47/SUMPRODUCT($W47:$W$47,$V47:$V$47)),"") | U47: =IF(W47<>"",IF($I$12<>"",IF(G47<>"",G47,($I$9/$I$12-SUM($U$25:U46))*V47*W47/SUMPRODUCT($W47:$W$47,$V47:$V$47)),""),"")
B48: итого | D48: =SUM(D25:D47) -> 0 | E48: =SUM(E25:E47) -> 0 | F48: =IF(AND(E48<>"",E48<>0),D48/E48,"") | G48: =SUM(G25:G47) -> 0 | H48: =IF(AND(G48<>"",G48<>0),D48/G48,"") | I48: =SUM(I25:I47) -> 0 | J48: =IF(AND(G48<>"",G48<>0),E48/G48,"") | K48: =SUM(K25:K47) -> 0 | L48: =SUM(L25:L47) -> 0 | M48: =SUM(M25:M47) -> 0 | N48: =IF(AND(I48<>"",I48<>0),G48/I48,"") | O48: =D48/P48 -> #DIV/0! | P48: =SUM(P25:P47) -> #DIV/0! | Q48: =SUM(Q25:Q47) -> #DIV/0! | R48: =SUM(R25:R47) -> #DIV/0! | S48: =SUM(S25:S47) -> #DIV/0! | T48: =SUM(T25:T47) -> #DIV/0! | U48: =SUM(U25:U47) -> #DIV/0!
D49: =SUMIF(D25:D47,"",P25:P47)+D48 -> #DIV/0!

Sheet Доп сотрудник
B1: =TODAY()-1 -> 46171
B2: (отчетная дата) | J2: ЕЖЕДНЕВНЫЙ ОТЧЕТ О ПРОДАЖАХ
B3: Осталось до выполнения плана!!! | J3: =График!B25 -> 0
C4: =I8-D48 -> 0 | E4: =IF(I8<>0,C4/I8,0) -> 0
F6: Целевые показатели
F7: Показатель | I7: План | J7: Факт | K7: % выполнения | L7: Прогноз выполнения | M7: % выполнения по прогнозу | N7: Отклонение | O7: Факт аналогичного месяца прошлого года | P7: Отклонение LFL
F8: Выручка | I8: ='Ялта, Ленина, 18'!I8/График!AI31*График!AI25 -> 0 | J8: =D48 -> 0 | K8: =IF(AND(I8<>"", I8<>0, J8<>""), J8/I8, "") | L8: =IF(SUMIF($D$25:$D$47,">=0",$P$25:$P$47)<>0,I8*D48/SUMIF($D$25:$D$47,">=0",$P$25:$P$47),0) -> 0 | M8: =IF(AND(I8<>"", I8<>0, L8<>"", L8<>0), L8/I8, "") | N8: =IF(AND(J8<>0, J8<>"", I8<>0, I8<>""), L8-I8, "") | P8: =IF(AND(O8<>"", O8<>0, L8<>"", L8<>0), -O8+L8, "") | Q8: =IF(AND(P8<>"", P8<>0, O8<>0, O8<>""), P8/O8, "")
F9: Кол-во изделий | I9: =I8/I11 -> 0 | J9: =E48 -> 0 | K9: =IF(AND(I9<>"", I9<>0, J9<>""), J9/I9, "") | L9: =IF(SUMIF($E$25:$E$47,">=0",$Q$25:$Q$47)<>0,I9*E48/SUMIF($E$25:$E$47,">=0",$Q$25:$Q$47),0) -> 0 | M9: =IF(AND(I9<>"", I9<>0, L9<>"", L9<>0), L9/I9, "") | N9: =IF(AND(J9<>0, J9<>"", I9<>0, I9<>""), L9-I9, "") | O9: =O8/O11 -> #DIV/0! | P9: =IF(AND(O9<>"", O9<>0, L9<>"", L9<>0), -O9+L9, "") -> #DIV/0! | Q9: =IF(AND(P9<>"", P9<>0, O9<>0, O9<>""), P9/O9, "") -> #DIV/0!
F10: Средний чек | I10: =I11*I12 -> 10088 | J10: =H48 | K10: =IF(AND(I10<>"", I10<>0, J10<>""), J10/I10, "") | L10: =J10 | M10: =IF(AND(I10<>"", I10<>0, L10<>"", L10<>0), L10/I10, "") | N10: =IF(AND(J10<>0, J10<>"", I10<>0, I10<>""), L10-I10, "") | O10: =O11*O12 -> 0 | P10: =IF(AND(O10<>"", O10<>0, L10<>"", L10<>0), -O10+L10, "") | Q10: =IF(AND(P10<>"", P10<>0, O10<>0, O10<>""), P10/O10, "") | S10: IS
F11: Средняя стоимость изделия | I11: ='Ялта, Ленина, 18'!I11 -> 5200 | J11: =F48 | K11: =IF(AND(I11<>"", I11<>0, J11<>""), J11/I11, "") | L11: =IF(L9>0, L8/L9, "") | M11: =IF(AND(I11<>"", I11<>0, L11<>"", L11<>0), L11/I11, "") | N11: =IF(AND(J11<>0, J11<>"", I11<>0, I11<>""), L11-I11, "") | P11: =IF(AND(O11<>"", O11<>0, L11<>"", L11<>0), -O11+L11, "") | Q11: =IF(AND(P11<>"", P11<>0, O11<>0, O11<>""), P11/O11, "")
F12: Длина чека | I12: ='Ялта, Ленина, 18'!I12 -> 1.94 | J12: =J48 | K12: =IF(AND(I12<>"", I12<>0, J12<>""), J12/I12, "") | L12: =J12 | M12: =IF(AND(I12<>"", I12<>0, L12<>"", L12<>0), L12/I12, "") | N12: =IF(AND(J12<>0, J12<>"", I12<>0, I12<>""), L12-I12, "") | P12: =IF(AND(O12<>"", O12<>0, L12<>"", L12<>0), -O12+L12, "") | Q12: =IF(AND(P12<>"", P12<>0, O12<>0, O12<>""), P12/O12, "") | S12: ='Ялта, Ленина, 18'!S12*График!AJ25/График!AJ31 -> 0 | T12: =L48 -> 0
F13: Кол-во чеков | I13: =IF(I12<>0, I9/I12, "") -> 0 | J13: =G48 -> 0 | K13: =IF(AND(I13<>"", I13<>0, J13<>""), J13/I13, "") | L13: =IF(SUMIF($G$25:$G$47,">=0",$R$25:$R$47)<>0,I13*G48/SUMIF($G$25:$G$47,">=0",$R$25:$R$47),"") | M13: =IF(AND(I13<>"", I13<>0, L13<>"", L13<>0), L13/I13, "") | N13: =IF(AND(J13<>0, J13<>"", I13<>0, I13<>""), L13-I13, "") | P13: =IF(AND(O13<>"", O13<>0, L13<>"", L13<>0), -O13+L13, "") | Q13: =IF(AND(P13<>"", P13<>0, O13<>0, O13<>""), P13/O13, "") | S13: =T12/S12 -> #DIV/0! | T13: =S13/J14*I14 -> #DIV/0!
F14: Кол-во смен план/отработано | I14: =График!AI25 -> 0 | K14: =IF(AND(I14<>"", I14<>0, J14<>""), J14/I14, "") | L14: =I14 -> 0 | M14: =IF(AND(I14<>"", I14<>0, L14<>"", L14<>0), L14/I14, "") | N14: =IF(AND(J14<>0, J14<>"", I14<>0, I14<>""), L14-I14, "") | P14: =IF(AND(O14<>"", O14<>0, L14<>"", L14<>0), -O14+L14, "") | Q14: =IF(AND(P14<>"", P14<>0, O14<>0, O14<>""), P14/O14, "")
F15: Средние продажи в смену | I15: ='Ялта, Ленина, 18'!I15 -> 154639.28 | J15: =J8/J14 -> #DIV/0! | K15: =IF(AND(I15<>"", I15<>0, J15<>""), J15/I15, "") -> #DIV/0! | L15: =J15 -> #DIV/0! | M15: =IF(AND(I15<>"", I15<>0, L15<>"", L15<>0), L15/I15, "") -> #DIV/0! | N15: =IF(AND(J15<>0, J15<>"", I15<>0, I15<>""), L15-I15, "") -> #DIV/0! | P15: =IF(AND(O15<>"", O15<>0, L15<>"", L15<>0), -O15+L15, "") -> #DIV/0! | Q15: =IF(AND(P15<>"", P15<>0, O15<>0, O15<>""), P15/O15, "") -> #DIV/0!
F16: Отставание/Перевыполнение | J16: =J8-I15*J14 -> 0 | K16: =IF(AND(I16<>"", I16<>0, J16<>""), J16/I16, "") | L16: =J16 -> 0 | M16: =IF(AND(I16<>"", I16<>0, L16<>"", L16<>0), L16/I16, "") | N16: =IF(AND(J16<>0, J16<>"", I16<>0, I16<>""), L16-I16, "") | P16: =IF(AND(O16<>"", O16<>0, L16<>"", L16<>0), -O16+L16, "") | Q16: =IF(AND(P16<>"", P16<>0, O16<>0, O16<>""), P16/O16, "") | S16: UNOde50
F17: Трафик | I17: ='Ялта, Ленина, 18'!I17/График!AJ31*График!AJ25 -> 0 | J17: =I48 -> 0 | K17: =IF(AND(I17<>"", I17<>0, J17<>""), J17/I17, "") | L17: =J17/J14*I14 -> #DIV/0! | M17: =IF(AND(I17<>"", I17<>0, L17<>"", L17<>0), L17/I17, "") -> #DIV/0! | N17: =IF(AND(J17<>0, J17<>"", I17<>0, I17<>""), L17-I17, "") | P17: =IF(AND(O17<>"", O17<>0, L17<>"", L17<>0), -O17+L17, "") -> #DIV/0! | Q17: =IF(AND(P17<>"", P17<>0, O17<>0, O17<>""), P17/O17, "") -> #DIV/0!
K18: =IF(AND(I18<>"", I18<>0, J18<>""), J18/I18, "") | L18: =J18 -> 0 | M18: =IF(AND(I18<>"", I18<>0, L18<>"", L18<>0), L18/I18, "") | N18: =IF(AND(J18<>0, J18<>"", I18<>0, I18<>""), L18-I18, "") | O18: 0 | P18: =IF(AND(O18<>"", O18<>0, L18<>"", L18<>0), -O18+L18, "") | Q18: =IF(AND(P18<>"", P18<>0, O18<>0, O18<>""), P18/O18, "") | S18: ='Ялта, Ленина, 18'!S18*График!AJ25/График!AJ31 -> 0 | T18: =K48 -> 0
K19: =IF(AND(I19<>"", I19<>0, J19<>""), J19/I19, "") | L19: =J19 -> 0 | M19: =IF(AND(I19<>"", I19<>0, L19<>"", L19<>0), L19/I19, "") | N19: =IF(AND(J19<>0, J19<>"", I19<>0, I19<>""), L19-I19, "") | O19: 0 | P19: =IF(AND(O19<>"", O19<>0, L19<>"", L19<>0), -O19+L19, "") | Q19: =IF(AND(P19<>"", P19<>0, O19<>0, O19<>""), P19/O19, "") | S19: =T18/S18 -> #DIV/0! | T19: =S19/J14*I14 -> #DIV/0!
F20: Конверсия план/факт | I20: ='Ялта, Ленина, 18'!I20 -> 0.22 | J20: =N48 | K20: =J20/I20 -> #VALUE! | L20: =IF(AND(K8<>0,I14<>0,I48<>0),(I48*N48+(I48/K8-I48)*I20)/(I48/K8),0) -> 0 | M20: =IF(AND(I20<>"", I20<>0, L20<>"", L20<>0), L20/I20, "") | N20: =IF(AND(J20<>0, J20<>"", I20<>0, I20<>""), L20-I20, "") | P20: =IF(AND(O20<>"", O20<>0, L20<>"", L20<>0), -O20+L20, "") | Q20: =IF(AND(P20<>"", P20<>0, O20<>0, O20<>""), P20/O20, "")
B22: Факт продаж за месяц | O22: % выполнения дневного плана | P22: Раcпределение плана по дням
B23: Дата | C23: День недели | D23: Выручка (руб) | E23: Кол-во единиц (шт.) | F23: Средняя стоимость изделия (руб.) | G23: Количество чеков (шт.) | H23: Средняя сумма чека (руб.) | I23: Трафик | J23: Длина чека (шт.) | K23: UNOde50 | L23: IS | M23: Запасной | N23: Конверсия (%) | P23: выручка, план | Q23: кол-во ед, план | R23: Кол-во чеков, план | S23: выручка, скорректир.план | T23: кол-во ед, скорр. план | U23: кол-во чеков, скорр. план | V23: Коэфф. Дня Недели | W23: Специфика месяца
B24: 1 | C24: 2 | D24: 3 | E24: в | F24: 5 | G24: 6 | H24: 7 | I24: 8 | J24: 9 | K24: 10 | L24: 11 | M24: 12 | N24: 13 | P24: 1 | Q24: 2 | R24: 3 | S24: 4 | T24: 5 | U24: 6 | V24: 10 | W24: 11
F25: =IF(AND(E25<>"",E25<>0),D25/E25,"") | H25: =IF(AND(G25<>"",G25<>0),D25/G25,"") | J25: =IF(AND(G25<>"",G25<>0),E25/G25,"") | N25: =IF(AND(I25<>"",I25<>0),G25/I25,"") | O25: =D25/P25 -> #DIV/0! | P25: =$I$8*V25*W25/SUMPRODUCT($W$25:$W$55,$V$25:$V$55) -> 0 | Q25: =$I$9*V25*W25/SUMPRODUCT($W$25:$W$55,$V$25:$V$55) -> 0 | R25: =IF($I$12="","",Q25/$I$12) -> 0 | S25: =IF(W25<>"",IF(D25<>"",D25,($I$8-SUM($S24:S$25))*V25*W25/SUMPRODUCT($W25:$W$55,$V25:$V$55)),"") -> #REF! | T25: =IF(W25<>"",IF(E25<>"",E25,($I$9-SUM($T24:T$25))*V25*W25/SUMPRODUCT($W25:$W$55,$V25:$V$55)),"") -> #REF! | U25: =IF(W25<>"",IF($I$12<>"",IF(G25<>"",G25,($I$9/$I$12-SUM($U24:U$25))*V25*W25/SUMPRODUCT($W25:$W$55,$V25:$V$55)),""),"") -> #REF! | V25: 1.1982013 | W25: 1.1982013
F26: =IF(AND(E26<>"",E26<>0),D26/E26,"") | H26: =IF(AND(G26<>"",G26<>0),D26/G26,"") | J26: =IF(AND(G26<>"",G26<>0),E26/G26,"") | N26: =IF(AND(I26<>"",I26<>0),G26/I26,"") | O26: =D26/P26 -> #DIV/0! | P26: =$I$8*V26*W26/SUMPRODUCT($W$25:$W$55,$V$25:$V$55) -> 0 | Q26: =$I$9*V26*W26/SUMPRODUCT($W$25:$W$55,$V$25:$V$55) -> 0 | R26: =IF($I$12="","",Q26/$I$12) -> 0 | S26: =IF(W26<>"",IF(D26<>"",D26,($I$8-SUM($S$25:S25))*V26*W26/SUMPRODUCT($W26:$W$55,$V26:$V$55)),"") | T26: =IF(W26<>"",IF(E25<>"",E25,($I$9-SUM($T$25:T25))*V26*W26/SUMPRODUCT($W26:$W$55,$V26:$V$55)),"") | U26: =IF(W26<>"",IF($I$12<>"",IF(G26<>"",G26,($I$9/$I$12-SUM($U$25:U25))*V26*W26/SUMPRODUCT($W26:$W$55,$V26:$V$55)),""),"")
F27: =IF(AND(E27<>"",E27<>0),D27/E27,"") | H27: =IF(AND(G27<>"",G27<>0),D27/G27,"") | J27: =IF(AND(G27<>"",G27<>0),E27/G27,"") | N27: =IF(AND(I27<>"",I27<>0),G27/I27,"") | O27: =D27/P27 -> #DIV/0! | P27: =$I$8*V27*W27/SUMPRODUCT($W$25:$W$55,$V$25:$V$55) -> 0 | Q27: =$I$9*V27*W27/SUMPRODUCT($W$25:$W$55,$V$25:$V$55) -> 0 | R27: =IF($I$12="","",Q27/$I$12) -> 0 | S27: =IF(W27<>"",IF(D27<>"",D27,($I$8-SUM($S$25:S26))*V27*W27/SUMPRODUCT($W27:$W$55,$V27:$V$55)),"") | T27: =IF(W27<>"",IF(E27<>"",E27,($I$9-SUM($T$25:T26))*V27*W27/SUMPRODUCT($W27:$W$55,$V27:$V$55)),"") | U27: =IF(W27<>"",IF($I$12<>"",IF(G27<>"",G27,($I$9/$I$12-SUM($U$25:U26))*V27*W27/SUMPRODUCT($W27:$W$55,$V27:$V$55)),""),"")
F28: =IF(AND(E28<>"",E28<>0),D28/E28,"") | H28: =IF(AND(G28<>"",G28<>0),D28/G28,"") | J28: =IF(AND(G28<>"",G28<>0),E28/G28,"") | N28: =IF(AND(I28<>"",I28<>0),G28/I28,"") | O28: =D28/P28 -> #DIV/0! | P28: =$I$8*V28*W28/SUMPRODUCT($W$25:$W$55,$V$25:$V$55) -> 0 | Q28: =$I$9*V28*W28/SUMPRODUCT($W$25:$W$55,$V$25:$V$55) -> 0 | R28: =IF($I$12="","",Q28/$I$12) -> 0 | S28: =IF(W28<>"",IF(D28<>"",D28,($I$8-SUM($S$25:S27))*V28*W28/SUMPRODUCT($W28:$W$55,$V28:$V$55)),"") | T28: =IF(W28<>"",IF(E28<>"",E28,($I$9-SUM($T$25:T27))*V28*W28/SUMPRODUCT($W28:$W$55,$V28:$V$55)),"") | U28: =IF(W28<>"",IF($I$12<>"",IF(G28<>"",G28,($I$9/$I$12-SUM($U$25:U27))*V28*W28/SUMPRODUCT($W28:$W$55,$V28:$V$55)),""),"")
F29: =IF(AND(E29<>"",E29<>0),D29/E29,"") | H29: =IF(AND(G29<>"",G29<>0),D29/G29,"") | J29: =IF(AND(G29<>"",G29<>0),E29/G29,"") | N29: =IF(AND(I29<>"",I29<>0),G29/I29,"") | O29: =D29/P29 -> #DIV/0! | P29: =$I$8*V29*W29/SUMPRODUCT($W$25:$W$55,$V$25:$V$55) -> 0 | Q29: =$I$9*V29*W29/SUMPRODUCT($W$25:$W$55,$V$25:$V$55) -> 0 | R29: =IF($I$12="","",Q29/$I$12) -> 0 | S29: =IF(W29<>"",IF(D29<>"",D29,($I$8-SUM($S$25:S28))*V29*W29/SUMPRODUCT($W29:$W$55,$V29:$V$55)),"") | T29: =IF(W29<>"",IF(E29<>"",E29,($I$9-SUM($T$25:T28))*V29*W29/SUMPRODUCT($W29:$W$55,$V29:$V$55)),"") | U29: =IF(W29<>"",IF($I$12<>"",IF(G29<>"",G29,($I$9/$I$12-SUM($U$25:U28))*V29*W29/SUMPRODUCT($W29:$W$55,$V29:$V$55)),""),"")
F30: =IF(AND(E30<>"",E30<>0),D30/E30,"") | H30: =IF(AND(G30<>"",G30<>0),D30/G30,"") | J30: =IF(AND(G30<>"",G30<>0),E30/G30,"") | N30: =IF(AND(I30<>"",I30<>0),G30/I30,"") | O30: =D30/P30 -> #DIV/0! | P30: =$I$8*V30*W30/SUMPRODUCT($W$25:$W$55,$V$25:$V$55) -> 0 | Q30: =$I$9*V30*W30/SUMPRODUCT($W$25:$W$55,$V$25:$V$55) -> 0 | R30: =IF($I$12="","",Q30/$I$12) -> 0 | S30: =IF(W30<>"",IF(D30<>"",D30,($I$8-SUM($S$25:S29))*V30*W30/SUMPRODUCT($W30:$W$55,$V30:$V$55)),"") | T30: =IF(W30<>"",IF(E30<>"",E30,($I$9-SUM($T$25:T29))*V30*W30/SUMPRODUCT($W30:$W$55,$V30:$V$55)),"") | U30: =IF(W30<>"",IF($I$12<>"",IF(G30<>"",G30,($I$9/$I$12-SUM($U$25:U29))*V30*W30/SUMPRODUCT($W30:$W$55,$V30:$V$55)),""),"")
F31: =IF(AND(E31<>"",E31<>0),D31/E31,"") | H31: =IF(AND(G31<>"",G31<>0),D31/G31,"") | J31: =IF(AND(G31<>"",G31<>0),E31/G31,"") | N31: =IF(AND(I31<>"",I31<>0),G31/I31,"") | O31: =D31/P31 -> #DIV/0! | P31: =$I$8*V31*W31/SUMPRODUCT($W$25:$W$55,$V$25:$V$55) -> 0 | Q31: =$I$9*V31*W31/SUMPRODUCT($W$25:$W$55,$V$25:$V$55) -> 0 | R31: =IF($I$12="","",Q31/$I$12) -> 0 | S31: =IF(W31<>"",IF(D31<>"",D31,($I$8-SUM($S$25:S30))*V31*W31/SUMPRODUCT($W31:$W$55,$V31:$V$55)),"") | T31: =IF(W31<>"",IF(E31<>"",E31,($I$9-SUM($T$25:T30))*V31*W31/SUMPRODUCT($W31:$W$55,$V31:$V$55)),"") | U31: =IF(W31<>"",IF($I$12<>"",IF(G31<>"",G31,($I$9/$I$12-SUM($U$25:U30))*V31*W31/SUMPRODUCT($W31:$W$55,$V31:$V$55)),""),"")
F32: =IF(AND(E32<>"",E32<>0),D32/E32,"") | H32: =IF(AND(G32<>"",G32<>0),D32/G32,"") | J32: =IF(AND(G32<>"",G32<>0),E32/G32,"") | N32: =IF(AND(I32<>"",I32<>0),G32/I32,"") | O32: =D32/P32 -> #DIV/0! | P32: =$I$8*V32*W32/SUMPRODUCT($W$25:$W$55,$V$25:$V$55) -> 0 | Q32: =$I$9*V32*W32/SUMPRODUCT($W$25:$W$55,$V$25:$V$55) -> 0 | R32: =IF($I$12="","",Q32/$I$12) -> 0 | S32: =IF(W32<>"",IF(D32<>"",D32,($I$8-SUM($S$25:S31))*V32*W32/SUMPRODUCT($W32:$W$55,$V32:$V$55)),"") | T32: =IF(W32<>"",IF(E32<>"",E32,($I$9-SUM($T$25:T31))*V32*W32/SUMPRODUCT($W32:$W$55,$V32:$V$55)),"") | U32: =IF(W32<>"",IF($I$12<>"",IF(G32<>"",G32,($I$9/$I$12-SUM($U$25:U31))*V32*W32/SUMPRODUCT($W32:$W$55,$V32:$V$55)),""),"")
F33: =IF(AND(E33<>"",E33<>0),D33/E33,"") | H33: =IF(AND(G33<>"",G33<>0),D33/G33,"") | J33: =IF(AND(G33<>"",G33<>0),E33/G33,"") | N33: =IF(AND(I33<>"",I33<>0),G33/I33,"") | O33: =D33/P33 -> #DIV/0! | P33: =$I$8*V33*W33/SUMPRODUCT($W$25:$W$55,$V$25:$V$55) -> 0 | Q33: =$I$9*V33*W33/SUMPRODUCT($W$25:$W$55,$V$25:$V$55) -> 0 | R33: =IF($I$12="","",Q33/$I$12) -> 0 | S33: =IF(W33<>"",IF(D33<>"",D33,($I$8-SUM($S$25:S32))*V33*W33/SUMPRODUCT($W33:$W$55,$V33:$V$55)),"") | T33: =IF(W33<>"",IF(E33<>"",E33,($I$9-SUM($T$25:T32))*V33*W33/SUMPRODUCT($W33:$W$55,$V33:$V$55)),"") | U33: =IF(W33<>"",IF($I$12<>"",IF(G33<>"",G33,($I$9/$I$12-SUM($U$25:U32))*V33*W33/SUMPRODUCT($W33:$W$55,$V33:$V$55)),""),"")
F34: =IF(AND(E34<>"",E34<>0),D34/E34,"") | H34: =IF(AND(G34<>"",G34<>0),D34/G34,"") | J34: =IF(AND(G34<>"",G34<>0),E34/G34,"") | N34: =IF(AND(I34<>"",I34<>0),G34/I34,"") | O34: =D34/P34 -> #DIV/0! | P34: =$I$8*V34*W34/SUMPRODUCT($W$25:$W$55,$V$25:$V$55) -> 0 | Q34: =$I$9*V34*W34/SUMPRODUCT($W$25:$W$55,$V$25:$V$55) -> 0 | R34: =IF($I$12="","",Q34/$I$12) -> 0 | S34: =IF(W34<>"",IF(D34<>"",D34,($I$8-SUM($S$25:S33))*V34*W34/SUMPRODUCT($W34:$W$55,$V34:$V$55)),"") | T34: =IF(W34<>"",IF(E34<>"",E34,($I$9-SUM($T$25:T33))*V34*W34/SUMPRODUCT($W34:$W$55,$V34:$V$55)),"") | U34: =IF(W34<>"",IF($I$12<>"",IF(G34<>"",G34,($I$9/$I$12-SUM($U$25:U33))*V34*W34/SUMPRODUCT($W34:$W$55,$V34:$V$55)),""),"")
F35: =IF(AND(E35<>"",E35<>0),D35/E35,"") | H35: =IF(AND(G35<>"",G35<>0),D35/G35,"") | J35: =IF(AND(G35<>"",G35<>0),E35/G35,"") | N35: =IF(AND(I35<>"",I35<>0),G35/I35,"") | O35: =D35/P35 -> #DIV/0! | P35: =$I$8*V35*W35/SUMPRODUCT($W$25:$W$55,$V$25:$V$55) -> 0 | Q35: =$I$9*V35*W35/SUMPRODUCT($W$25:$W$55,$V$25:$V$55) -> 0 | R35: =IF($I$12="","",Q35/$I$12) -> 0 | S35: =IF(W35<>"",IF(D35<>"",D35,($I$8-SUM($S$25:S34))*V35*W35/SUMPRODUCT($W35:$W$55,$V35:$V$55)),"") | T35: =IF(W35<>"",IF(E35<>"",E35,($I$9-SUM($T$25:T34))*V35*W35/SUMPRODUCT($W35:$W$55,$V35:$V$55)),"") | U35: =IF(W35<>"",IF($I$12<>"",IF(G35<>"",G35,($I$9/$I$12-SUM($U$25:U34))*V35*W35/SUMPRODUCT($W35:$W$55,$V35:$V$55)),""),"")
F36: =IF(AND(E36<>"",E36<>0),D36/E36,"") | H36: =IF(AND(G36<>"",G36<>0),D36/G36,"") | J36: =IF(AND(G36<>"",G36<>0),E36/G36,"") | N36: =IF(AND(I36<>"",I36<>0),G36/I36,"") | O36: =D36/P36 -> #DIV/0! | P36: =$I$8*V36*W36/SUMPRODUCT($W$25:$W$55,$V$25:$V$55) -> 0 | Q36: =$I$9*V36*W36/SUMPRODUCT($W$25:$W$55,$V$25:$V$55) -> 0 | R36: =IF($I$12="","",Q36/$I$12) -> 0 | S36: =IF(W36<>"",IF(D36<>"",D36,($I$8-SUM($S$25:S35))*V36*W36/SUMPRODUCT($W36:$W$55,$V36:$V$55)),"") | T36: =IF(W36<>"",IF(E36<>"",E36,($I$9-SUM($T$25:T35))*V36*W36/SUMPRODUCT($W36:$W$55,$V36:$V$55)),"") | U36: =IF(W36<>"",IF($I$12<>"",IF(G36<>"",G36,($I$9/$I$12-SUM($U$25:U35))*V36*W36/SUMPRODUCT($W36:$W$55,$V36:$V$55)),""),"")
F37: =IF(AND(E37<>"",E37<>0),D37/E37,"") | H37: =IF(AND(G37<>"",G37<>0),D37/G37,"") | J37: =IF(AND(G37<>"",G37<>0),E37/G37,"") | N37: =IF(AND(I37<>"",I37<>0),G37/I37,"") | O37: =D37/P37 -> #DIV/0! | P37: =$I$8*V37*W37/SUMPRODUCT($W$25:$W$55,$V$25:$V$55) -> 0 | Q37: =$I$9*V37*W37/SUMPRODUCT($W$25:$W$55,$V$25:$V$55) -> 0 | R37: =IF($I$12="","",Q37/$I$12) -> 0 | S37: =IF(W37<>"",IF(D37<>"",D37,($I$8-SUM($S$25:S36))*V37*W37/SUMPRODUCT($W37:$W$55,$V37:$V$55)),"") | T37: =IF(W37<>"",IF(E37<>"",E37,($I$9-SUM($T$25:T36))*V37*W37/SUMPRODUCT($W37:$W$55,$V37:$V$55)),"") | U37: =IF(W37<>"",IF($I$12<>"",IF(G37<>"",G37,($I$9/$I$12-SUM($U$25:U36))*V37*W37/SUMPRODUCT($W37:$W$55,$V37:$V$55)),""),"")
F38: =IF(AND(E38<>"",E38<>0),D38/E38,"") | H38: =IF(AND(G38<>"",G38<>0),D38/G38,"") | J38: =IF(AND(G38<>"",G38<>0),E38/G38,"") | N38: =IF(AND(I38<>"",I38<>0),G38/I38,"") | O38: =D38/P38 -> #DIV/0! | P38: =$I$8*V38*W38/SUMPRODUCT($W$25:$W$44,$V$25:$V$44) -> 0 | Q38: =$I$9*V38*W38/SUMPRODUCT($W$25:$W$44,$V$25:$V$44) -> 0 | R38: =IF($I$12="","",Q38/$I$12) -> 0 | S38: =IF(W38<>"",IF(D38<>"",D38,($I$8-SUM($S$25:S37))*V38*W38/SUMPRODUCT($W38:$W$55,$V38:$V$55)),"") | T38: =IF(W38<>"",IF(E38<>"",E38,($I$9-SUM($T$25:T37))*V38*W38/SUMPRODUCT($W38:$W$55,$V38:$V$55)),"") | U38: =IF(W38<>"",IF($I$12<>"",IF(G38<>"",G38,($I$9/$I$12-SUM($U$25:U37))*V38*W38/SUMPRODUCT($W38:$W$55,$V38:$V$55)),""),"")
F39: =IF(AND(E39<>"",E39<>0),D39/E39,"") | H39: =IF(AND(G39<>"",G39<>0),D39/G39,"") | J39: =IF(AND(G39<>"",G39<>0),E39/G39,"") | N39: =IF(AND(I39<>"",I39<>0),G39/I39,"") | O39: =D39/P39 -> #DIV/0! | P39: =$I$8*V39*W39/SUMPRODUCT($W$25:$W$44,$V$25:$V$44) -> 0 | Q39: =$I$9*V39*W39/SUMPRODUCT($W$25:$W$44,$V$25:$V$44) -> 0 | R39: =IF($I$12="","",Q39/$I$12) -> 0 | S39: =IF(W39<>"",IF(D39<>"",D39,($I$8-SUM($S$25:S38))*V39*W39/SUMPRODUCT($W39:$W$55,$V39:$V$55)),"") | T39: =IF(W39<>"",IF(E39<>"",E39,($I$9-SUM($T$25:T38))*V39*W39/SUMPRODUCT($W39:$W$55,$V39:$V$55)),"") | U39: =IF(W39<>"",IF($I$12<>"",IF(G39<>"",G39,($I$9/$I$12-SUM($U$25:U38))*V39*W39/SUMPRODUCT($W39:$W$55,$V39:$V$55)),""),"")
F40: =IF(AND(E40<>"",E40<>0),D40/E40,"") | H40: =IF(AND(G40<>"",G40<>0),D40/G40,"") | J40: =IF(AND(G40<>"",G40<>0),E40/G40,"") | N40: =IF(AND(I40<>"",I40<>0),G40/I40,"") | O40: =D40/P40 -> #DIV/0! | P40: =$I$8*V40*W40/SUMPRODUCT($W$25:$W$47,$V$25:$V$47) -> 0 | Q40: =$I$9*V40*W40/SUMPRODUCT($W$25:$W$47,$V$25:$V$47) -> 0 | R40: =IF($I$12="", "", Q40/$I$12) -> 0 | S40: =IF(W40<>"",IF(D40<>"",D40,($I$8-SUM($S$25:S39))*V40*W40/SUMPRODUCT($W40:$W$55,$V40:$V$55)),"") | T40: =IF(W40<>"",IF(E40<>"",E40,($I$9-SUM($T$25:T39))*V40*W40/SUMPRODUCT($W40:$W$55,$V40:$V$55)),"") | U40: =IF(W40<>"",IF($I$12<>"",IF(G40<>"",G40,($I$9/$I$12-SUM($U$25:U39))*V40*W40/SUMPRODUCT($W40:$W$55,$V40:$V$55)),""),"")
F41: =IF(AND(E41<>"",E41<>0),D41/E41,"") | H41: =IF(AND(G41<>"",G41<>0),D41/G41,"") | J41: =IF(AND(G41<>"",G41<>0),E41/G41,"") | N41: =IF(AND(I41<>"",I41<>0),G41/I41,"") | O41: =D41/P41 -> #DIV/0! | P41: =$I$8*V41*W41/SUMPRODUCT($W$25:$W$47,$V$25:$V$47) -> 0 | Q41: =$I$9*V41*W41/SUMPRODUCT($W$25:$W$47,$V$25:$V$47) -> 0 | R41: =IF($I$12="", "", Q41/$I$12) -> 0 | S41: =IF(W41<>"",IF(D41<>"",D41,($I$8-SUM($S$25:S40))*V41*W41/SUMPRODUCT($W41:$W$55,$V41:$V$55)),"") | T41: =IF(W41<>"",IF(E41<>"",E41,($I$9-SUM($T$25:T40))*V41*W41/SUMPRODUCT($W41:$W$55,$V41:$V$55)),"") | U41: =IF(W41<>"",IF($I$12<>"",IF(G41<>"",G41,($I$9/$I$12-SUM($U$25:U40))*V41*W41/SUMPRODUCT($W41:$W$55,$V41:$V$55)),""),"")
F42: =IF(AND(E42<>"",E42<>0),D42/E42,"") | H42: =IF(AND(G42<>"",G42<>0),D42/G42,"") | J42: =IF(AND(G42<>"",G42<>0),E42/G42,"") | N42: =IF(AND(I42<>"",I42<>0),G42/I42,"") | O42: =D42/P42 -> #DIV/0! | P42: =$I$8*V42*W42/SUMPRODUCT($W$25:$W$47,$V$25:$V$47) -> 0 | Q42: =$I$9*V42*W42/SUMPRODUCT($W$25:$W$47,$V$25:$V$47) -> 0 | R42: =IF($I$12="", "", Q42/$I$12) -> 0 | S42: =IF(W42<>"",IF(D42<>"",D42,($I$8-SUM($S$25:S41))*V42*W42/SUMPRODUCT($W42:$W$55,$V42:$V$55)),"") | T42: =IF(W42<>"",IF(E42<>"",E42,($I$9-SUM($T$25:T41))*V42*W42/SUMPRODUCT($W42:$W$55,$V42:$V$55)),"") | U42: =IF(W42<>"",IF($I$12<>"",IF(G42<>"",G42,($I$9/$I$12-SUM($U$25:U41))*V42*W42/SUMPRODUCT($W42:$W$55,$V42:$V$55)),""),"")
F43: =IF(AND(E43<>"",E43<>0),D43/E43,"") | H43: =IF(AND(G43<>"",G43<>0),D43/G43,"") | J43: =IF(AND(G43<>"",G43<>0),E43/G43,"") | N43: =IF(AND(I43<>"",I43<>0),G43/I43,"") | O43: =D43/P43 -> #DIV/0! | P43: =$I$8*V43*W43/SUMPRODUCT($W$25:$W$44, $V$25:$V$44) -> 0 | Q43: =$I$9*V43*W43/SUMPRODUCT($W$25:$W$44, $V$25:$V$44) -> 0 | R43: =IF($I$12="", "", Q43/$I$12) -> 0 | S43: =IF(W43<>"",IF(D43<>"",D43,($I$8-SUM($S$25:S42))*V43*W43/SUMPRODUCT($W43:$W$55,$V43:$V$55)),"") | T43: =IF(W43<>"",IF(E43<>"",E43,($I$9-SUM($T$25:T42))*V43*W43/SUMPRODUCT($W43:$W$55,$V43:$V$55)),"") | U43: =IF(W43<>"",IF($I$12<>"",IF(G43<>"",G43,($I$9/$I$12-SUM($U$25:U42))*V43*W43/SUMPRODUCT($W43:$W$55,$V43:$V$55)),""),"")
F44: =IF(AND(E44<>"",E44<>0),D44/E44,"") | H44: =IF(AND(G44<>"",G44<>0),D44/G44,"") | J44: =IF(AND(G44<>"",G44<>0),E44/G44,"") | N44: =IF(AND(I44<>"",I44<>0),G44/I44,"") | O44: =D44/P44 -> #DIV/0! | P44: =$I$8*V44*W44/SUMPRODUCT($W$25:$W$44, $V$25:$V$44) -> 0 | Q44: =$I$9*V44*W44/SUMPRODUCT($W$25:$W$44, $V$25:$V$44) -> 0 | R44: =IF($I$12="", "", Q44/$I$12) -> 0 | S44: =IF(W44<>"",IF(D44<>"",D44,($I$8-SUM($S$25:S43))*V44*W44/SUMPRODUCT($W44:$W$55,$V44:$V$55)),"") | T44: =IF(W44<>"",IF(E44<>"",E44,($I$9-SUM($T$25:T43))*V44*W44/SUMPRODUCT($W44:$W$55,$V44:$V$55)),"") | U44: =IF(W44<>"",IF($I$12<>"",IF(G44<>"",G44,($I$9/$I$12-SUM($U$25:U43))*V44*W44/SUMPRODUCT($W44:$W$55,$V44:$V$55)),""),"")
F45: =IF(AND(E45<>"",E45<>0),D45/E45,"") | H45: =IF(AND(G45<>"",G45<>0),D45/G45,"") | J45: =IF(AND(G45<>"",G45<>0),E45/G45,"") | N45: =IF(AND(I45<>"",I45<>0),G45/I45,"") | O45: =D45/P45 -> #DIV/0! | P45: =$I$8*V45*W45/SUMPRODUCT($W$25:$W$44, $V$25:$V$44) -> 0 | Q45: =$I$9*V45*W45/SUMPRODUCT($W$25:$W$44, $V$25:$V$44) -> 0 | R45: =IF($I$12="", "", Q45/$I$12) -> 0 | S45: =IF(W45<>"",IF(D45<>"",D45,($I$8-SUM($S$25:S44))*V45*W45/SUMPRODUCT($W45:$W$55,$V45:$V$55)),"") | T45: =IF(W45<>"",IF(E45<>"",E45,($I$9-SUM($T$25:T44))*V45*W45/SUMPRODUCT($W45:$W$55,$V45:$V$55)),"") | U45: =IF(W45<>"",IF($I$12<>"",IF(G45<>"",G45,($I$9/$I$12-SUM($U$25:U44))*V45*W45/SUMPRODUCT($W45:$W$55,$V45:$V$55)),""),"")
F46: =IF(AND(E46<>"",E46<>0),D46/E46,"") | H46: =IF(AND(G46<>"",G46<>0),D46/G46,"") | J46: =IF(AND(G46<>"",G46<>0),E46/G46,"") | N46: =IF(AND(I46<>"",I46<>0),G46/I46,"") | O46: =D46/P46 -> #DIV/0! | P46: =$I$8*V46*W46/SUMPRODUCT($W$25:$W$44, $V$25:$V$44) -> 0 | Q46: =$I$9*V46*W46/SUMPRODUCT($W$25:$W$44, $V$25:$V$44) -> 0 | R46: =IF($I$12="", "", Q46/$I$12) -> 0 | S46: =IF(W46<>"",IF(D46<>"",D46,($I$8-SUM($S$25:S45))*V46*W46/SUMPRODUCT($W46:$W$55,$V46:$V$55)),"") | T46: =IF(W46<>"",IF(E46<>"",E46,($I$9-SUM($T$25:T45))*V46*W46/SUMPRODUCT($W46:$W$55,$V46:$V$55)),"") | U46: =IF(W46<>"",IF($I$12<>"",IF(G46<>"",G46,($I$9/$I$12-SUM($U$25:U45))*V46*W46/SUMPRODUCT($W46:$W$55,$V46:$V$55)),""),"")
F47: =IF(AND(E47<>"",E47<>0),D47/E47,"") | H47: =IF(AND(G47<>"",G47<>0),D47/G47,"") | J47: =IF(AND(G47<>"",G47<>0),E47/G47,"") | N47: =IF(AND(I47<>"",I47<>0),G47/I47,"") | O47: =D47/P47 -> #DIV/0! | P47: =$I$8*V47*W47/SUMPRODUCT($W$25:$W$55,$V$25:$V$55) -> 0 | Q47: =$I$9*V47*W47/SUMPRODUCT($W$25:$W$55,$V$25:$V$55) -> 0 | R47: =IF($I$12="","",Q47/$I$12) -> 0 | S47: =IF(W47<>"",IF(D47<>"",D47,($I$8-SUM($S$25:S46))*V47*W47/SUMPRODUCT($W47:$W$55,$V47:$V$55)),"") | T47: =IF(W47<>"",IF(E47<>"",E47,($I$9-SUM($T$25:T46))*V47*W47/SUMPRODUCT($W47:$W$55,$V47:$V$55)),"") | U47: =IF(W47<>"",IF($I$12<>"",IF(G47<>"",G47,($I$9/$I$12-SUM($U$25:U46))*V47*W47/SUMPRODUCT($W47:$W$55,$V47:$V$55)),""),"")
B48: итого | D48: =SUM(D25:D47) -> 0 | E48: =SUM(E25:E47) -> 0 | F48: =IF(AND(E48<>"",E48<>0),D48/E48,"") | G48: =SUM(G25:G47) -> 0 | H48: =IF(AND(G48<>"",G48<>0),D48/G48,"") | I48: =SUM(I25:I47) -> 0 | J48: =IF(AND(G48<>"",G48<>0),E48/G48,"") | K48: =SUM(K25:K47) -> 0 | L48: =SUM(L25:L47) -> 0 | M48: =SUM(M25:M47) -> 0 | N48: =IF(AND(I48<>"",I48<>0),G48/I48,"") | O48: =D48/P48 -> #DIV/0! | P48: =SUM(P25:P47) -> 0 | Q48: =SUM(Q25:Q47) -> 0 | R48: =SUM(R25:R47) -> 0 | S48: =SUM(S25:S47) -> #REF! | T48: =SUM(T25:T47) -> #REF! | U48: =SUM(U25:U47) -> #REF!
D49: =SUMIF(D25:D47,"",P25:P47)+D48 -> 0

Sheet Вед-ть Рогалевич
A1: =График!B1 -> Май, 2025
A2: =График!B3 -> ул. Набережная Ленина, 18 | D2: =График!B4 -> GL-0005
A3: Сотрудник | D3: Выплачено на карту | E3: Выплачено наличными по платежной ведомости | F3: Дополнительные начисления, доплаты | G3: Оклад | H3: Бонусная часть от личных продаж | I3: Бонусная часть от общих продаж | J3: Базовый бонус за выполнение плана | K3: Итого: | L3: Вычеты | M3: Итого к выдаче с учетом авансов и вычетов | N3: Подпись
A4: =График!B29 -> Рогалевич Ирина | D4: =11136+27144 -> 38280 | F4: =H8+H9+G16+G24+L24 -> 27840.32 | G4: =D11 -> 30700 | H4: =D18 -> 74719.535 | I4: =L18 -> 21748.036 | J4: =L11 -> 0 | K4: =H4+J4+G4+F4+I4 -> 155007.89 | L4: =C8+C9 -> 5920 | M4: =K4-L4-D4-E4 -> 110807.89
B6: Вычеты | G6: Доп начисления
B7: Дата | C7: Сумма | D7: Описание | G7: Дата | H7: Сумма | J7: Описание
B8: 45808 | C8: =4056+1664 -> 5720 | D8: НДФЛ май 2025 | G8: 45808 | H8: ='Ялта, Ленина, 18'!J8*0.01 -> 27840.32 | J8: Административный %
B9: 45808 | C9: 200 | D9: Вычет согласно инвентаризационной ведомости от 28.05
A11: Оклад: | D11: =G15 -> 30700 | I11: Базовый бонус за выполнение плана | L11: =L15+L16 -> 0
B13: Оклад: | J13: Базовый бонус за выполнение плана
B14: Дней | C14: Магазин | D14: Должность | E14: Зачислено часов | F14: Ставка за час, руб | G14: Начислено за день, руб | J14: Магазин | K14: КВП | L14: Начисленный ББ
B15: =График!AI29 -> 28 | C15: =A2 -> ул. Набережная Ленина, 18 | D15: ПК | E15: =График!AJ29 -> 307 | F15: 100 | G15: =E15*F15 -> 30700 | J15: =График!B3 -> ул. Набережная Ленина, 18 | K15: ='Ялта, Ленина, 18'!K8 -> 0.58075468
D16: ПК | G16: =E16*F16 -> 0
A18: БонуснаяЧасть | D18: =G23 -> 74719.535 | I18: Бонусная часть от общих продаж | L18: =N23 -> 21748.036
B21: Бонус от личных продаж по категории товара | I21: Бонус от общих продаж
B22: Сотрудник | C22: Магазин | E22: Процент от продажи | F22: Продано на сумму, руб | G22: Начисленный бонус от продаж, руб | I22: Сотрудник | J22: Магазин | K22: Кол-во отработанных личных часов | L22: Кол-во отработанных общих часов | M22: Процент от продажи | N22: Начисленный бонус от продаж, руб
B23: =A4 -> Рогалевич Ирина | C23: =A2 -> ул. Набережная Ленина, 18 | E23: 0.055 | F23: ='Рогалевич И. Е.'!J8 -> 1358537 | G23: =F23*E23 -> 74719.535 | I23: =B23 -> Рогалевич Ирина | J23: =C23 -> ул. Набережная Ленина, 18 | K23: =E15 -> 307 | L23: =График!AJ31 -> 786 | M23: 0.02 | N23: ='Ялта, Ленина, 18'!J8*M23*K23/L23 -> 21748.036
B24: =B23 -> Рогалевич Ирина | C24: =C16 -> 0 | G24: =F24*E24 -> 0 | N24: =1477363.14*M24*K24/L24 -> #DIV/0!

Sheet Вед-ть Уразгильдеева
A1: =График!B1 -> Май, 2025
A2: =График!B3 -> ул. Набережная Ленина, 18 | D2: =График!B4 -> GL-0005
A3: Сотрудник | D3: Выплачено на карту | E3: Выплачено наличными по платежной ведомости | F3: Дополнительные начисления, доплаты | G3: Оклад | H3: Бонусная часть от личных продаж | I3: Бонусная часть от общих продаж | J3: Базовый бонус за выполнение плана | K3: Итого: | L3: Вычеты | M3: Итого к выдаче с учетом авансов и вычетов | N3: Подпись
A4: =График!B28 -> Уразгильдеева Екатерина | D4: =10440+24360 -> 34800 | F4: =H8+H9 -> 0 | G4: =D12 -> 24600 | H4: =D19 -> 39488.955 | I4: =L19 -> 17426.765 | J4: =L12 -> 0 | K4: =H4+J4+G4+F4+I4 -> 81515.72 | L4: =C8+C9+C10 -> 5200 | M4: =K4-L4-D4-E4 -> 41515.72
B6: Вычеты | G6: Доп начисления
B7: Дата | C7: Сумма | D7: Описание | G7: Дата | H7: Сумма | J7: Описание
B8: 45808 | C8: =3640+1560 -> 5200 | D8: НДФЛ май 2025
A12: Оклад: | D12: =G16 -> 24600 | I12: Базовый бонус за выполнение плана | L12: =L16+L17 -> 0
B14: Оклад: | J14: Базовый бонус за выполнение плана
B15: Дней | C15: Магазин | D15: Должность | E15: Зачислено часов | F15: Ставка за час, руб | G15: Начислено за день, руб | J15: Магазин | K15: КВП | L15: Начисленный ББ
B16: =График!AI28 -> 20 | C16: =A2 -> ул. Набережная Ленина, 18 | D16: ПК | E16: =График!AJ28 -> 246 | F16: 100 | G16: =E16*F16 -> 24600 | J16: =График!B3 -> ул. Набережная Ленина, 18 | K16: ='Ялта, Ленина, 18'!K8 -> 0.58075468 | L16: 0
A19: БонуснаяЧасть | D19: =G24 -> 39488.955 | I19: Бонусная часть от общих продаж | L19: =N24 -> 17426.765
B22: Бонус от личных продаж по категории товара | I22: Бонус от общих продаж
B23: Сотрудник | C23: Магазин | E23: Процент от продажи | F23: Продано на сумму, руб | G23: Начисленный бонус от продаж, руб | I23: Сотрудник | J23: Магазин | K23: Кол-во отработанных личных часов | L23: Кол-во отработанных общих часов | M23: Процент от продажи | N23: Начисленный бонус от продаж, руб
B24: =A4 -> Уразгильдеева Екатерина | C24: =A2 -> ул. Набережная Ленина, 18 | E24: 0.055 | F24: ='Уразгильдеева Е. Р.'!J8 -> 717981 | G24: =F24*E24 -> 39488.955 | I24: =B24 -> Уразгильдеева Екатерина | J24: =C24 -> ул. Набережная Ленина, 18 | K24: =E16 -> 246 | L24: =График!AJ31 -> 786 | M24: 0.02 | N24: ='Ялта, Ленина, 18'!J8*M24*K24/L24 -> 17426.765
B25: =B24 -> Уразгильдеева Екатерина | N25: =1477363.14*M25*K25/L25 -> #DIV/0!

Sheet Вед-ть Вафина
A1: =График!B1 -> Май, 2025
A2: =График!B3 -> ул. Набережная Ленина, 18 | D2: =График!B4 -> GL-0005
A3: Сотрудник | D3: Выплачено на карту | E3: Выплачено наличными по платежной ведомости | F3: Дополнительные начисления, доплаты | G3: Оклад | H3: Бонусная часть от личных продаж | I3: Бонусная часть от общих продаж | J3: Базовый бонус за выполнение плана | K3: Итого: | L3: Вычеты | M3: Итого к выдаче с учетом авансов и вычетов | N3: Подпись
A4: =График!B27 -> Вафина Ляйсан | D4: =10440+24360 -> 34800 | E4: 22000 | F4: =H8+H9 -> 0 | G4: =D12 -> 23300 | H4: =D19 -> 38913.27 | I4: =L19 -> 15679.322 | J4: =L12 -> 0 | K4: =H4+J4+G4+F4+I4 -> 77892.592 | L4: =C8+C9+C10 -> 5200 | M4: =K4-L4-D4-E4 -> 15892.592
B6: Вычеты | G6: Доп начисления
B7: Дата | C7: Сумма | D7: Описание | G7: Дата | H7: Сумма | J7: Описание
B8: 45808 | C8: =3640+1560 -> 5200 | D8: НДФЛ май 2025
A12: Оклад: | D12: =G16 -> 23300 | I12: Базовый бонус за выполнение плана | L12: =L16+L17 -> 0
B14: Оклад: | J14: Базовый бонус за выполнение плана
B15: Дней | C15: Магазин | D15: Должность | E15: Зачислено часов | F15: Ставка за час, руб | G15: Начислено за день, руб | J15: Магазин | K15: КВП | L15: Начисленный ББ
B16: =График!AI27 -> 19 | C16: =A2 -> ул. Набережная Ленина, 18 | D16: ПК | E16: =График!AJ27 -> 233 | F16: 100 | G16: =E16*F16 -> 23300 | J16: =График!B3 -> ул. Набережная Ленина, 18 | K16: ='Ялта, Ленина, 18'!K8 -> 0.58075468 | L16: 0
A19: БонуснаяЧасть | D19: =G24 -> 38913.27 | I19: Бонусная часть от общих продаж | L19: =N24 -> 15679.322
B22: Бонус от личных продаж по категории товара | I22: Бонус от общих продаж
B23: Сотрудник | C23: Магазин | E23: Процент от продажи | F23: Продано на сумму, руб | G23: Начисленный бонус от продаж, руб | I23: Сотрудник | J23: Магазин | K23: Кол-во отработанных личных часов | L23: Кол-во отработанных общих часов | M23: Процент от продажи | N23: Начисленный бонус от продаж, руб
B24: =A4 -> Вафина Ляйсан | C24: =A2 -> ул. Набережная Ленина, 18 | E24: 0.055 | F24: ='Вафина Л. Ф.'!J8 -> 707514 | G24: =F24*E24 -> 38913.27 | I24: =B24 -> Вафина Ляйсан | J24: =C24 -> ул. Набережная Ленина, 18 | K24: =E16 -> 233 | L24: 741 | M24: 0.02 | N24: =2493214*M24*K24/L24 -> 15679.322
B25: =B24 -> Вафина Ляйсан | N25: =1477363.14*M25*K25/L25 -> #DIV/0!

Sheet График
B1: Май, 2025 | T1: в
B2: г. Ялта
B3: ул. Набережная Ленина, 18
B4: GL-0005
B5: 10.00-22.00
B6: ФОТ | C6: Кол-во дней в месяц | AK6: 30
B7: =BT31*100/BH31 -> #DIV/0!
D8: чт | E8: пт | F8: сб | G8: вс | H8: пн | I8: вт | J8: ср | K8: чт | L8: пт | M8: сб | N8: вс | O8: пн | P8: вт | Q8: ср | R8: чт | S8: пт | T8: сб | U8: вс | V8: пн | W8: вт | X8: ср | Y8: чт | Z8: пт | AA8: сб | AB8: вс | AC8: пн | AD8: вт | AE8: ср | AF8: чт | AG8: пт | AH8: сб | AJ8: Часы | AK8: Выходные | AL8: Отпуск | AM8: Больничный (официальный) | AN8: Дни стажировки
A10: № | B10: ФИО | C10: Должность | D10: 1 | E10: 2 | F10: 3 | G10: 4 | H10: 5 | I10: 6 | J10: 7 | K10: 8 | L10: 9 | M10: 10 | N10: 11 | O10: 12 | P10: 13 | Q10: 14 | R10: 15 | S10: 16 | T10: 17 | U10: 18 | V10: 19 | W10: 20 | X10: 21 | Y10: 22 | Z10: 23 | AA10: 24 | AB10: 25 | AC10: 26 | AD10: 27 | AE10: 28 | AF10: 29 | AG10: 30 | AH10: 31 | AI10: Дни
A11: 20 | AI11: 0 | AJ11: 0 | AK11: 0 | AL11: 0 | AM11: 0 | AN11: 0
A12: 19 | AI12: 0 | AJ12: 0 | AK12: 0 | AL12: 0 | AM12: 0 | AN12: 0
A13: 18 | AI13: 0 | AJ13: 0 | AK13: 0 | AL13: 0 | AM13: 0 | AN13: 0
A14: 17 | AI14: 0 | AJ14: 0 | AK14: 0 | AL14: 0 | AM14: 0 | AN14: 0
A15: 16 | AI15: 0 | AJ15: 0 | AK15: 0 | AL15: 0 | AM15: 0 | AN15: 0
A16: 15 | AI16: 0 | AJ16: 0 | AK16: 0 | AL16: 0 | AM16: 0 | AN16: 0
A17: 14 | AI17: 0 | AJ17: 0 | AK17: 0 | AL17: 0 | AM17: 0 | AN17: 0
A18: 13 | AI18: 0 | AJ18: 0 | AK18: 0 | AL18: 0 | AM18: 0 | AN18: 0
A19: 12 | AI19: 0 | AJ19: 0 | AK19: 0 | AL19: 0 | AM19: 0 | AN19: 0
A20: 11 | AI20: 0 | AJ20: 0 | AK20: 0 | AL20: 0 | AM20: 0 | AN20: 0
A21: 10 | AI21: 0 | AJ21: 0 | AK21: 0 | AL21: 0 | AM21: 0 | AN21: 0
A22: 9 | AI22: =COUNTIF(D22:AH22, ">0") -> 0 | AJ22: 0 | AK22: 0 | AL22: 0 | AM22: 0 | AN22: 0
A23: 8 | AI23: =COUNTIF(D23:AH23, ">0") -> 0 | AJ23: 0 | AK23: 0 | AL23: 0 | AM23: 0 | AN23: 0
A24: 7 | AI24: =COUNTIF(D24:AH24, ">0") -> 0 | AJ24: 0 | AK24: 0 | AL24: 0 | AM24: 0 | AN24: 0
A25: 6 | AI25: =COUNTIF(D25:AH25,">0") -> 0 | AJ25: =SUMIF(D25:AH25,">0") -> 0 | AK25: =COUNTIF(D25:AH25,"В") -> 0 | AL25: =COUNTIF(E25:AI25,"о") -> 0 | AM25: =COUNTIF(F25:AJ25,"б") -> 0 | AN25: 0
A26: 5 | B26: Орешникова Елена | AI26: =COUNTIF(D26:AH26, ">0") -> 0 | AJ26: =SUMIF(D26:AH26, ">0") -> 0 | AK26: =COUNTIF(D26:AH26, "В") -> 0 | AL26: 0 | AM26: 0 | AN26: 0
A27: 4 | B27: Вафина Ляйсан | C27: ПК | D27: с12 | E27: в | F27: 12 | G27: 12 | H27: 12 | I27: в | J27: в | K27: 12 | L27: 12 | M27: 12 | N27: в | O27: 12 | P27: 12 | Q27: 12 | R27: в | S27: в | T27: 12 | U27: 12 | V27: 12 | W27: в | X27: в | Y27: 12 | Z27: 12 | AA27: 13 | AB27: в | AC27: 13 | AD27: 13 | AE27: 13 | AF27: в | AG27: в | AH27: 13 | AI27: =COUNTIF(D27:AH27,">0") -> 19 | AJ27: =SUMIF(D27:AH27,">0") -> 233 | AK27: =COUNTIF(D27:AH27,"В") -> 11 | AL27: =COUNTIF(E27:AI27,"о") -> 0 | AM27: =COUNTIF(F27:AJ27,"б") -> 0 | AN27: 0
A28: 3 | B28: Уразгильдеева Екатерина | C28: ПК | D28: 12 | E28: 12 | F28: 12 | G28: в | H28: в | I28: 12 | J28: 12 | K28: в | L28: 12 | M28: 12 | N28: 12 | O28: в | P28: в | Q28: 12 | R28: 12 | S28: 12 | T28: в | U28: в | V28: 12 | W28: 12 | X28: 12 | Y28: в | Z28: в | AA28: 13 | AB28: 13 | AC28: 13 | AD28: в | AE28: в | AF28: 13 | AG28: 13 | AH28: 13 | AI28: =COUNTIF(D28:AH28,">0") -> 20 | AJ28: =SUMIF(D28:AH28,">0") -> 246 | AK28: =COUNTIF(D28:AH28,"В") -> 11 | AL28: =COUNTIF(E28:AI28,"о") -> 0 | AM28: =COUNTIF(F28:AJ28,"б") -> 0 | AN28: 0
A29: 2 | B29: Рогалевич Ирина | C29: УМ | D29: 10 | E29: 11 | F29: 10 | G29: 12 | H29: 12 | I29: 10 | J29: 10 | K29: 12 | L29: 9 | M29: 9 | N29: 10 | O29: 12 | P29: 12 | Q29: в | R29: 10 | S29: 11 | T29: 12 | U29: 12 | V29: в | W29: 10 | X29: 10 | Y29: 12 | Z29: 12 | AA29: 11 | AB29: 11 | AC29: в | AD29: 13 | AE29: 13 | AF29: 11 | AG29: 11 | AH29: 9 | AI29: =COUNTIF(D29:AH29,">0") -> 28 | AJ29: =SUMIF(D29:AH29,">0") -> 307 | AK29: =COUNTIF(D29:AH29,"В") -> 3 | AL29: =COUNTIF(E29:AI29,"о") -> 0 | AM29: =COUNTIF(F29:AJ29,"б") -> 0 | AN29: 0
A30: 1 | AI30: =COUNTIF(D30:AH30, ">0") -> 0 | AJ30: =SUMIF(D30:AH30, ">0") -> 0 | AK30: =COUNTIF(D30:AH30, "В") -> 0 | AL30: =COUNTIF(E30:AI30, "о") -> 0 | AM30: =COUNTIF(F30:AJ30, "б") -> 0 | AN30: 0
B31: Итого магазин | D31: =COUNTIF(D11:D30, ">0") -> 2 | E31: =COUNTIF(E11:E30, ">0") -> 2 | F31: =COUNTIF(F11:F30, ">0") -> 3 | G31: =COUNTIF(G11:G30, ">0") -> 2 | H31: =COUNTIF(H11:H30, ">0") -> 2 | I31: =COUNTIF(I11:I30, ">0") -> 2 | J31: =COUNTIF(J11:J30, ">0") -> 2 | K31: =COUNTIF(K11:K29, ">0") -> 2 | L31: =COUNTIF(L11:L30, ">0") -> 3 | M31: =COUNTIF(M11:M30, ">0") -> 3 | N31: =COUNTIF(N11:N30, ">0") -> 2 | O31: =COUNTIF(O11:O30, ">0") -> 2 | P31: =COUNTIF(P11:P30, ">0") -> 2 | Q31: =COUNTIF(Q11:Q30, ">0") -> 2 | R31: =COUNTIF(R11:R30, ">0") -> 2 | S31: =COUNTIF(S11:S30, ">0") -> 2 | ... AH31: =COUNTIF(AH11:AH30, ">0") -> 3 | AI31: =SUM(AI11:AI30) -> 67 | AJ31: =SUM(AJ11:AJ30) -> 786 | AK31: =SUM(AK11:AK30) -> 25 | AL31: =SUM(AL11:AL30) -> 0 | AM31: =SUM(AM11:AM30) -> 0 | AN31: =SUM(AN11:AN30) -> 0
