Workbook
Name маг: NA()

Sheet Ялта, Ленина, 18
B1: =TODAY()-1 -> 45939
B2: (отчетная дата)
C3: Осталось до выполнения плана!!! | I3: =График!B3 -> ул. Набережная Ленина, 18
C4: =I8-D56 -> 332372.92 | E4: =IF(I8<>0, C4/I8, 0) -> 0.095873116
D5: =C4/(I14-J14) -> #DIV/0!
F6: Целевые показатели
F7: Показатель | I7: План | J7: Факт | K7: % выполнения | L7: Прогноз выполнения | M7: % выполнения по прогнозу | N7: Отклонение | O7: Факт аналогичного месяца прошлого года | P7: Отклонение LFL
F8: Выручка | I8: =I11*I12*I13 -> 3466800 | J8: =D56 -> 3134427.1 | K8: =IF(AND(I8<>"",I8<>0,J8<>""),J8/I8,"") -> 0.90412688 | L8: =IF(SUMIF($D$25:$D$55,">=0",$P$25:$P$55)<>0,I8*D56/SUMIF($D$25:$D$55,">=0",$P$25:$P$55),0) -> 3134427.1 | M8: =IF(AND(I8<>"", I8<>0, L8<>"", L8<>0), L8/I8, "") -> 0.90412688 | N8: =IF(AND(J8<>0, J8<>"", I8<>0, I8<>""), L8-I8, "") -> -332372.92 | P8: =IF(AND(O8<>"", O8<>0, L8<>"", L8<>0), -O8+L8, "") | Q8: =IF(AND(P8<>"", P8<>0, O8<>0, O8<>""), P8/O8, "")
F9: Кол-во изделий | I9: =I8/I11 -> 577.8 | J9: =E56 -> 482 | K9: =IF(AND(I9<>"", I9<>0, J9<>""), J9/I9, "") -> 0.83419868 | L9: =IF(SUMIF($E$25:$E$55, ">=0", $Q$25:$Q$55)<>0, I9*E56/SUMIF($E$25:$E$55, ">=0", $Q$25:$Q$55), 0) -> 482 | M9: =IF(AND(I9<>"", I9<>0, L9<>"", L9<>0), L9/I9, "") -> 0.83419868 | N9: =IF(AND(J9<>0, J9<>"", I9<>0, I9<>""), L9-I9, "") -> -95.8 | O9: =O8/O11 -> #DIV/0! | P9: =IF(AND(O9<>"", O9<>0, L9<>"", L9<>0), -O9+L9, "") -> #DIV/0! | Q9: =IF(AND(P9<>"", P9<>0, O9<>0, O9<>""), P9/O9, "") -> #DIV/0!
F10: Средний чек | I10: =I11*I12 -> 10800 | J10: =H56 -> 11481.418 | K10: =IF(AND(I10<>"", I10<>0, J10<>""), J10/I10, "") -> 1.0630942 | L10: =J10 -> 11481.418 | M10: =IF(AND(I10<>"", I10<>0, L10<>"", L10<>0), L10/I10, "") -> 1.0630942 | N10: =IF(AND(J10<>0, J10<>"", I10<>0, I10<>""), L10-I10, "") -> 681.41788 | O10: =O11*O12 -> 0 | P10: =IF(AND(O10<>"", O10<>0, L10<>"", L10<>0), -O10+L10, "") | Q10: =IF(AND(P10<>"", P10<>0, O10<>0, O10<>""), P10/O10, "") | S10: =L23 -> IS | V10: =M23 -> Agafi
F11: Средняя стоимость изделия | I11: 6000 | J11: =F56 -> 6502.9607 | K11: =IF(AND(I11<>"", I11<>0, J11<>""), J11/I11, "") -> 1.0838268 | L11: =IF(L9>0, L8/L9, "") -> 6502.9607 | M11: =IF(AND(I11<>"", I11<>0, L11<>"", L11<>0), L11/I11, "") -> 1.0838268 | N11: =IF(AND(J11<>0, J11<>"", I11<>0, I11<>""), L11-I11, "") -> 502.96075 | P11: =IF(AND(O11<>"", O11<>0, L11<>"", L11<>0), -O11+L11, "") | Q11: =IF(AND(P11<>"", P11<>0, O11<>0, O11<>""), P11/O11, "")
F12: Длина чека | I12: 1.8 | J12: =J56 -> 1.7655678 | K12: =IF(AND(I12<>"", I12<>0, J12<>""), J12/I12, "") -> 0.98087098 | L12: =J12 -> 1.7655678 | M12: =IF(AND(I12<>"", I12<>0, L12<>"", L12<>0), L12/I12, "") -> 0.98087098 | N12: =IF(AND(J12<>0, J12<>"", I12<>0, I12<>""), L12-I12, "") -> -0.034432234 | P12: =IF(AND(O12<>"", O12<>0, L12<>"", L12<>0), -O12+L12, "") | Q12: =IF(AND(P12<>"", P12<>0, O12<>0, O12<>""), P12/O12, "") | S12: 510000 | T12: =L56 -> 167876 | V12: 480000 | W12: =M56 -> 216811
F13: Кол-во чеков | I13: =I17*I20 -> 321 | J13: =G56 -> 273 | K13: =IF(AND(I13<>"", I13<>0, J13<>""), J13/I13, "") -> 0.85046729 | L13: =IF(SUMIF($G$25:$G$55, ">=0", $R$25:$R$55)<>0, I13*G56/SUMIF($G$25:$G$55, ">=0", $R$25:$R$55), "") -> 273 | M13: =IF(AND(I13<>"", I13<>0, L13<>"", L13<>0), L13/I13, "") -> 0.85046729 | N13: =IF(AND(J13<>0, J13<>"", I13<>0, I13<>""), L13-I13, "") -> -48 | P13: =IF(AND(O13<>"", O13<>0, L13<>"", L13<>0), -O13+L13, "") | Q13: =IF(AND(P13<>"", P13<>0, O13<>0, O13<>""), P13/O13, "") | S13: =T12/S12 -> 0.32916863 | T13: =S13/J14*I14 -> 0.32916863 | V13: =W12/V12 -> 0.45168958 | W13: =V13/J14*I14 -> 0.45168958
F14: Кол-во смен | I14: 30 | J14: 30 | K14: =IF(AND(I14<>"", I14<>0, J14<>""), J14/I14, "") -> 1 | L14: =I14 -> 30 | M14: =IF(AND(I14<>"", I14<>0, L14<>"", L14<>0), L14/I14, "") -> 1 | N14: =IF(AND(J14<>0, J14<>"", I14<>0, I14<>""), L14-I14, "") -> 0 | P14: =IF(AND(O14<>"", O14<>0, L14<>"", L14<>0), -O14+L14, "") | Q14: =IF(AND(P14<>"", P14<>0, O14<>0, O14<>""), P14/O14, "")
F15: Средние продажи в смену | I15: =I8/I14 -> 115560 | J15: =J8/J14 -> 104480.9 | K15: =IF(AND(I15<>"", I15<>0, J15<>""), J15/I15, "") -> 0.90412688 | L15: =J15 -> 104480.9 | M15: =IF(AND(I15<>"", I15<>0, L15<>"", L15<>0), L15/I15, "") -> 0.90412688 | N15: =IF(AND(J15<>0, J15<>"", I15<>0, I15<>""), L15-I15, "") -> -11079.097 | P15: =IF(AND(O15<>"", O15<>0, L15<>"", L15<>0), -O15+L15, "") | Q15: =IF(AND(P15<>"", P15<>0, O15<>0, O15<>""), P15/O15, "")
F16: Отставание/Перевыполнение | J16: =J8-I15*J14 -> -332372.92 | K16: =IF(AND(I16<>"", I16<>0, J16<>""), J16/I16, "") | L16: =J16 -> -332372.92 | M16: =IF(AND(I16<>"", I16<>0, L16<>"", L16<>0), L16/I16, "") | N16: =IF(AND(J16<>0, J16<>"", I16<>0, I16<>""), L16-I16, "") | P16: =IF(AND(O16<>"", O16<>0, L16<>"", L16<>0), -O16+L16, "") | Q16: =IF(AND(P16<>"", P16<>0, O16<>0, O16<>""), P16/O16, "") | S16: =K23 -> UNOde50
F17: Трафик | I17: 2140 | J17: =I56 -> 2186 | K17: =IF(AND(I17<>"", I17<>0, J17<>""), J17/I17, "") -> 1.0214953 | L17: =J17/J14*I14 -> 2186 | M17: =IF(AND(I17<>"", I17<>0, L17<>"", L17<>0), L17/I17, "") -> 1.0214953 | N17: =IF(AND(J17<>0, J17<>"", I17<>0, I17<>""), L17-I17, "") -> 46 | P17: =IF(AND(O17<>"", O17<>0, L17<>"", L17<>0), -O17+L17, "") | Q17: =IF(AND(P17<>"", P17<>0, O17<>0, O17<>""), P17/O17, "")
K18: =IF(AND(I18<>"", I18<>0, J18<>""), J18/I18, "") | L18: =J18 -> 0 | M18: =IF(AND(I18<>"", I18<>0, L18<>"", L18<>0), L18/I18, "") | N18: =IF(AND(J18<>0, J18<>"", I18<>0, I18<>""), L18-I18, "") | O18: 0 | P18: =IF(AND(O18<>"", O18<>0, L18<>"", L18<>0), -O18+L18, "") | Q18: =IF(AND(P18<>"", P18<>0, O18<>0, O18<>""), P18/O18, "") | S18: 1020000 | T18: =K56 -> 779065
K19: =IF(AND(I19<>"", I19<>0, J19<>""), J19/I19, "") | L19: =J19 -> 0 | M19: =IF(AND(I19<>"", I19<>0, L19<>"", L19<>0), L19/I19, "") | N19: =IF(AND(J19<>0, J19<>"", I19<>0, I19<>""), L19-I19, "") | O19: 0 | P19: =IF(AND(O19<>"", O19<>0, L19<>"", L19<>0), -O19+L19, "") | Q19: =IF(AND(P19<>"", P19<>0, O19<>0, O19<>""), P19/O19, "") | S19: =T18/S18 -> 0.76378922 | T19: =S19/J14*I14 -> 0.76378922
F20: Конверсия план/факт | I20: 0.15 | J20: =N56 -> 0.12488564 | K20: =J20/I20 -> 0.83257091 | L20: =IF(AND(K8<>0, I14<>0, I56<>0), (I56*N56+(I56/K8-I56)*I20)/(I56/K8), 0) -> 0.12729343 | M20: =IF(AND(I20<>"", I20<>0, L20<>"", L20<>0), L20/I20, "") -> 0.84862285 | N20: =IF(AND(J20<>0, J20<>"", I20<>0, I20<>""), L20-I20, "") -> -0.022706572 | P20: =IF(AND(O20<>"", O20<>0, L20<>"", L20<>0), -O20+L20, "") | Q20: =IF(AND(P20<>"", P20<>0, O20<>0, O20<>""), P20/O20, "")
A22: Факт продаж за месяц | O22: % выполнения дневного плана | P22: Раcпределение плана по дням
A23: Сотрудник | B23: Дата | C23: День недели | D23: Выручка (руб) | E23: Кол-во единиц (шт.) | F23: Средняя стоимость изделия (руб.) | G23: Количество чеков (шт.) | H23: Средняя сумма чека (руб.) | I23: Трафик | J23: Длина чека (шт.) | K23: UNOde50 | L23: IS | M23: Agafi | N23: Конверсия (%) | P23: выручка, план | Q23: кол-во ед, план | R23: Кол-во чеков, план | S23: выручка, скорректир.план | T23: кол-во ед, скорр. план | U23: кол-во чеков, скорр. план | V23: Коэфф. Дня Недели | W23: Специфика месяца
B24: 1 | C24: 2 | D24: 3 | E24: 4 | F24: 5 | G24: 6 | H24: 7 | I24: 8 | J24: 9 | K24: 10 | L24: 11 | M24: 12 | N24: 13 | P24: 1 | Q24: 2 | R24: 3 | S24: 4 | T24: 5 | U24: 6 | V24: 10 | W24: 11
A25: Рогалевич,Уразгильдеева | B25: 45901 | C25: пн | D25: =50580+17748+32073 -> 100401 | E25: 14 | F25: =IF(AND(E25<>"",E25<>0),D25/E25,"") -> 7171.5 | G25: 8 | H25: =IF(AND(G25<>"",G25<>0),D25/G25,"") -> 12550.125 | I25: 101 | J25: =IF(AND(G25<>"",G25<>0),E25/G25,"") -> 1.75 | K25: 17748 | M25: 32073 | N25: =IF(AND(I25<>"",I25<>0),G25/I25,"") -> 0.079207921 | O25: =D25/P25 -> 0.77522329 | P25: =$I$8*V25*W25/SUMPRODUCT($W$25:$W$55,$V$25:$V$55) -> 129512.36 | Q25: =$I$9*V25*W25/SUMPRODUCT($W$25:$W$55,$V$25:$V$55) -> 21.585394 | R25: =IF($I$12="","",Q25/$I$12) -> 11.991886 | S25: =IF(D25<>"",D25,P25) -> 100401 | T25: =IF(E25<>"",E25,Q25) -> 14 | U25: =IF(G25<>"",G25,R25) -> 8 | V25: 0.9414554 | W25: 0.9414554
A26: Рогалевич,Уразгильдеева | B26: 45902 | C26: вт | D26: =10690+13590+27659+42784 -> 94723 | E26: 16 | F26: =IF(AND(E26<>"",E26<>0),D26/E26,"") -> 5920.1875 | G26: 11 | H26: =IF(AND(G26<>"",G26<>0),D26/G26,"") -> 8611.1818 | I26: 77 | J26: =IF(AND(G26<>"",G26<>0),E26/G26,"") -> 1.4545455 | K26: 10690 | M26: 13590 | N26: =IF(AND(I26<>"",I26<>0),G26/I26,"") -> 0.14285714 | O26: =D26/P26 -> 0.89072052 | P26: =$I$8*V26*W26/SUMPRODUCT($W$25:$W$55,$V$25:$V$55) -> 106344.24 | Q26: =$I$9*V26*W26/SUMPRODUCT($W$25:$W$55,$V$25:$V$55) -> 17.724041 | R26: =IF($I$12="","",Q26/$I$12) -> 9.8466893 | S26: =IF(W26<>"",IF(D26<>"",D26,($I$8-SUM($S$25:S25))*V26*W26/SUMPRODUCT($W26:$W$55,$V26:$V$55)),"") -> 94723 | T26: =IF(W26<>"",IF(E26<>"",E26,($I$9-SUM($T$25:T25))*V26*W26/SUMPRODUCT($W26:$W$55,$V26:$V$55)),"") -> 16 | U26: =IF(W26<>"",IF(E26<>"",E26,($I$9-SUM($T$25:T25))*V26*W26/SUMPRODUCT($W26:$W$55,$V26:$V$55)),"") -> 16 | V26: 0.85310234 | W26: 0.85310234
A27: Рогалевич,Уразгильдеева | B27: 45903 | C27: ср | D27: =148210+31329.6+36942 -> 216481.6 | E27: 24 | F27: =IF(AND(E27<>"",E27<>0),D27/E27,"") -> 9020.0667 | G27: 14 | H27: =IF(AND(G27<>"",G27<>0),D27/G27,"") -> 15462.971 | I27: 78 | J27: =IF(AND(G27<>"",G27<>0),E27/G27,"") -> 1.7142857 | K27: 148210 | N27: =IF(AND(I27<>"",I27<>0),G27/I27,"") -> 0.17948718 | O27: =D27/P27 -> 2.0356682 | P27: =$I$8*V27*W27/SUMPRODUCT($W$25:$W$55,$V$25:$V$55) -> 106344.24 | Q27: =$I$9*V27*W27/SUMPRODUCT($W$25:$W$55,$V$25:$V$55) -> 17.724041 | R27: =IF($I$12="","",Q27/$I$12) -> 9.8466893 | S27: =IF(W27<>"",IF(D27<>"",D27,($I$8-SUM($S$25:S26))*V27*W27/SUMPRODUCT($W27:$W$55,$V27:$V$55)),"") -> 216481.6 | T27: =IF(W27<>"",IF(E27<>"",E27,($I$9-SUM($T$25:T26))*V27*W27/SUMPRODUCT($W27:$W$55,$V27:$V$55)),"") -> 24 | U27: =IF(W27<>"",IF(E27<>"",E27,($I$9-SUM($T$25:T26))*V27*W27/SUMPRODUCT($W27:$W$55,$V27:$V$55)),"") -> 24 | V27: 0.85310234 | W27: 0.85310234
A28: Рогалевич | B28: 45904 | C28: чт | D28: =55851+7492+51423 -> 114766 | E28: 16 | F28: =IF(AND(E28<>"",E28<>0),D28/E28,"") -> 7172.875 | G28: 11 | H28: =IF(AND(G28<>"",G28<>0),D28/G28,"") -> 10433.273 | I28: 86 | J28: =IF(AND(G28<>"",G28<>0),E28/G28,"") -> 1.4545455 | K28: 55851 | M28: 7492 | N28: =IF(AND(I28<>"",I28<>0),G28/I28,"") -> 0.12790698 | O28: =D28/P28 -> 1.0791933 | P28: =$I$8*V28*W28/SUMPRODUCT($W$25:$W$55,$V$25:$V$55) -> 106344.24 | Q28: =$I$9*V28*W28/SUMPRODUCT($W$25:$W$55,$V$25:$V$55) -> 17.724041 | R28: =IF($I$12="","",Q28/$I$12) -> 9.8466893 | S28: =IF(W28<>"",IF(D28<>"",D28,($I$8-SUM($S$25:S27))*V28*W28/SUMPRODUCT($W28:$W$55,$V28:$V$55)),"") -> 114766 | T28: =IF(W28<>"",IF(E28<>"",E28,($I$9-SUM($T$25:T27))*V28*W28/SUMPRODUCT($W28:$W$55,$V28:$V$55)),"") -> 16 | U28: =IF(W28<>"",IF(E28<>"",E28,($I$9-SUM($T$25:T27))*V28*W28/SUMPRODUCT($W28:$W$55,$V28:$V$55)),"") -> 16 | V28: 0.85310234 | W28: 0.85310234
A29: Рогалевич, Уразгильдеева | B29: 45905 | C29: пт | D29: =9903+41351 -> 51254 | E29: 7 | F29: =IF(AND(E29<>"",E29<>0),D29/E29,"") -> 7322 | G29: 6 | H29: =IF(AND(G29<>"",G29<>0),D29/G29,"") -> 8542.3333 | I29: 65 | J29: =IF(AND(G29<>"",G29<>0),E29/G29,"") -> 1.1666667 | L29: 9903 | N29: =IF(AND(I29<>"",I29<>0),G29/I29,"") -> 0.092307692 | O29: =D29/P29 -> 0.48548765 | P29: =$I$8*V29*W29/SUMPRODUCT($W$25:$W$55,$V$25:$V$55) -> 105572.2 | Q29: =$I$9*V29*W29/SUMPRODUCT($W$25:$W$55,$V$25:$V$55) -> 17.595367 | R29: =IF($I$12="","",Q29/$I$12) -> 9.7752038 | S29: =IF(W29<>"",IF(D29<>"",D29,($I$8-SUM($S$25:S28))*V29*W29/SUMPRODUCT($W29:$W$55,$V29:$V$55)),"") -> 51254 | T29: =IF(W29<>"",IF(E29<>"",E29,($I$9-SUM($T$25:T28))*V29*W29/SUMPRODUCT($W29:$W$55,$V29:$V$55)),"") -> 7 | U29: =IF(W29<>"",IF(E29<>"",E29,($I$9-SUM($T$25:T28))*V29*W29/SUMPRODUCT($W29:$W$55,$V29:$V$55)),"") -> 7 | V29: 0.85 | W29: 0.85
A30: Рогалевич, Уразгильдеева | B30: 45906 | C30: сб | D30: 44165 | E30: 8 | F30: =IF(AND(E30<>"",E30<>0),D30/E30,"") -> 5520.625 | G30: 5 | H30: =IF(AND(G30<>"",G30<>0),D30/G30,"") -> 8833 | I30: 50 | J30: =IF(AND(G30<>"",G30<>0),E30/G30,"") -> 1.6 | K30: 11992 | N30: =IF(AND(I30<>"",I30<>0),G30/I30,"") -> 0.1 | O30: =D30/P30 -> 0.30225014 | P30: =$I$8*V30*W30/SUMPRODUCT($W$25:$W$55,$V$25:$V$55) -> 146120.69 | Q30: =$I$9*V30*W30/SUMPRODUCT($W$25:$W$55,$V$25:$V$55) -> 24.353449 | R30: =IF($I$12="","",Q30/$I$12) -> 13.529694 | S30: =IF(W30<>"",IF(D30<>"",D30,($I$8-SUM($S$25:S29))*V30*W30/SUMPRODUCT($W30:$W$55,$V30:$V$55)),"") -> 44165 | T30: =IF(W30<>"",IF(E30<>"",E30,($I$9-SUM($T$25:T29))*V30*W30/SUMPRODUCT($W30:$W$55,$V30:$V$55)),"") -> 8 | U30: =IF(W30<>"",IF(E30<>"",E30,($I$9-SUM($T$25:T29))*V30*W30/SUMPRODUCT($W30:$W$55,$V30:$V$55)),"") -> 8 | V30: 1 | W30: 1
A31: Рогалевич,Уразгильдеева | B31: 45907 | C31: вс | D31: 29958 | E31: 5 | F31: =IF(AND(E31<>"",E31<>0),D31/E31,"") -> 5991.6 | G31: 3 | H31: =IF(AND(G31<>"",G31<>0),D31/G31,"") -> 9986 | I31: 45 | J31: =IF(AND(G31<>"",G31<>0),E31/G31,"") -> 1.6666667 | N31: =IF(AND(I31<>"",I31<>0),G31/I31,"") -> 0.066666667 | O31: =D31/P31 -> 0.20502229 | P31: =$I$8*V31*W31/SUMPRODUCT($W$25:$W$55,$V$25:$V$55) -> 146120.69 | Q31: =$I$9*V31*W31/SUMPRODUCT($W$25:$W$55,$V$25:$V$55) -> 24.353449 | R31: =IF($I$12="","",Q31/$I$12) -> 13.529694 | S31: =IF(W31<>"",IF(D31<>"",D31,($I$8-SUM($S$25:S30))*V31*W31/SUMPRODUCT($W31:$W$55,$V31:$V$55)),"") -> 29958 | T31: =IF(W31<>"",IF(E31<>"",E31,($I$9-SUM($T$25:T30))*V31*W31/SUMPRODUCT($W31:$W$55,$V31:$V$55)),"") -> 5 | U31: =IF(W31<>"",IF(E31<>"",E31,($I$9-SUM($T$25:T30))*V31*W31/SUMPRODUCT($W31:$W$55,$V31:$V$55)),"") -> 5 | V31: 1 | W31: 1
A32: Рогалевич,Уразгильдеева | B32: 45908 | C32: пн | D32: =83956+10903+14292+39335+65862 -> 214348 | E32: 28 | F32: =IF(AND(E32<>"",E32<>0),D32/E32,"") -> 7655.2857 | G32: 16 | H32: =IF(AND(G32<>"",G32<>0),D32/G32,"") -> 13396.75 | I32: 100 | J32: =IF(AND(G32<>"",G32<>0),E32/G32,"") -> 1.75 | K32: 83956 | L32: 10903 | M32: 14292 | N32: =IF(AND(I32<>"",I32<>0),G32/I32,"") -> 0.16 | O32: =D32/P32 -> 2.0156051 | P32: =$I$8*V32*W32/SUMPRODUCT($W$25:$W$55,$V$25:$V$55) -> 106344.24 | Q32: =$I$9*V32*W32/SUMPRODUCT($W$25:$W$55,$V$25:$V$55) -> 17.724041 | R32: =IF($I$12="","",Q32/$I$12) -> 9.8466893 | S32: =IF(W32<>"",IF(D32<>"",D32,($I$8-SUM($S$25:S31))*V32*W32/SUMPRODUCT($W32:$W$55,$V32:$V$55)),"") -> 214348 | T32: =IF(W32<>"",IF(E32<>"",E32,($I$9-SUM($T$25:T31))*V32*W32/SUMPRODUCT($W32:$W$55,$V32:$V$55)),"") -> 28 | U32: =IF(W32<>"",IF(E32<>"",E32,($I$9-SUM($T$25:T31))*V32*W32/SUMPRODUCT($W32:$W$55,$V32:$V$55)),"") -> 28 | V32: 0.85310234 | W32: 0.85310234
A33: Рогалевич | B33: 45909 | C33: вт | D33: =24992+65099+23902 -> 113993 | E33: 17 | F33: =IF(AND(E33<>"",E33<>0),D33/E33,"") -> 6705.4706 | G33: 13 | H33: =IF(AND(G33<>"",G33<>0),D33/G33,"") -> 8768.6923 | I33: 80 | J33: =IF(AND(G33<>"",G33<>0),E33/G33,"") -> 1.3076923 | K33: 24992 | L33: 23902 | N33: =IF(AND(I33<>"",I33<>0),G33/I33,"") -> 0.1625 | O33: =D33/P33 -> 1.0719245 | P33: =$I$8*V33*W33/SUMPRODUCT($W$25:$W$55,$V$25:$V$55) -> 106344.24 | Q33: =$I$9*V33*W33/SUMPRODUCT($W$25:$W$55,$V$25:$V$55) -> 17.724041 | R33: =IF($I$12="","",Q33/$I$12) -> 9.8466893 | S33: =IF(W33<>"",IF(D33<>"",D33,($I$8-SUM($S$25:S32))*V33*W33/SUMPRODUCT($W33:$W$55,$V33:$V$55)),"") -> 113993 | T33: =IF(W33<>"",IF(E33<>"",E33,($I$9-SUM($T$25:T32))*V33*W33/SUMPRODUCT($W33:$W$55,$V33:$V$55)),"") -> 17 | U33: =IF(W33<>"",IF(E33<>"",E33,($I$9-SUM($T$25:T32))*V33*W33/SUMPRODUCT($W33:$W$55,$V33:$V$55)),"") -> 17 | V33: 0.85310234 | W33: 0.85310234
A34: Рогалевич,Уразгильдеева | B34: 45910 | C34: ср | D34: =9992+4892+16403+7990+28243 -> 67520 | E34: 13 | F34: =IF(AND(E34<>"",E34<>0),D34/E34,"") -> 5193.8462 | G34: 7 | H34: =IF(AND(G34<>"",G34<>0),D34/G34,"") -> 9645.7143 | I34: =13+74 -> 87 | J34: =IF(AND(G34<>"",G34<>0),E34/G34,"") -> 1.8571429 | K34: 17982 | L34: 16403 | N34: =IF(AND(I34<>"",I34<>0),G34/I34,"") -> 0.08045977 | O34: =D34/P34 -> 0.63491918 | P34: =$I$8*V34*W34/SUMPRODUCT($W$25:$W$55,$V$25:$V$55) -> 106344.24 | Q34: =$I$9*V34*W34/SUMPRODUCT($W$25:$W$55,$V$25:$V$55) -> 17.724041 | R34: =IF($I$12="","",Q34/$I$12) -> 9.8466893 | S34: =IF(W34<>"",IF(D34<>"",D34,($I$8-SUM($S$25:S33))*V34*W34/SUMPRODUCT($W34:$W$55,$V34:$V$55)),"") -> 67520 | T34: =IF(W34<>"",IF(E34<>"",E34,($I$9-SUM($T$25:T33))*V34*W34/SUMPRODUCT($W34:$W$55,$V34:$V$55)),"") -> 13 | U34: =IF(W34<>"",IF(E34<>"",E34,($I$9-SUM($T$25:T33))*V34*W34/SUMPRODUCT($W34:$W$55,$V34:$V$55)),"") -> 13 | V34: 0.85310234 | W34: 0.85310234
A35: Рогалевич,Уразгильдеева | B35: 45911 | C35: чт | D35: 149353 | E35: 17 | F35: =IF(AND(E35<>"",E35<>0),D35/E35,"") -> 8785.4706 | G35: 6 | H35: =IF(AND(G35<>"",G35<>0),D35/G35,"") -> 24892.167 | I35: =12+79 -> 91 | J35: =IF(AND(G35<>"",G35<>0),E35/G35,"") -> 2.8333333 | K35: 70336 | N35: =IF(AND(I35<>"",I35<>0),G35/I35,"") -> 0.065934066 | O35: =D35/P35 -> 1.4044296 | P35: =$I$8*V35*W35/SUMPRODUCT($W$25:$W$55,$V$25:$V$55) -> 106344.24 | Q35: =$I$9*V35*W35/SUMPRODUCT($W$25:$W$55,$V$25:$V$55) -> 17.724041 | R35: =IF($I$12="","",Q35/$I$12) -> 9.8466893 | S35: =IF(W35<>"",IF(D35<>"",D35,($I$8-SUM($S$25:S34))*V35*W35/SUMPRODUCT($W35:$W$55,$V35:$V$55)),"") -> 149353 | T35: =IF(W35<>"",IF(E35<>"",E35,($I$9-SUM($T$25:T34))*V35*W35/SUMPRODUCT($W35:$W$55,$V35:$V$55)),"") -> 17 | U35: =IF(W35<>"",IF(E35<>"",E35,($I$9-SUM($T$25:T34))*V35*W35/SUMPRODUCT($W35:$W$55,$V35:$V$55)),"") -> 17 | V35: 0.85310234 | W35: 0.85310234
A36: Рогалевич | B36: 45912 | C36: пт | D36: =109604+20000+32175+102415 -> 264194 | E36: 31 | F36: =IF(AND(E36<>"",E36<>0),D36/E36,"") -> 8522.3871 | G36: 20 | H36: =IF(AND(G36<>"",G36<>0),D36/G36,"") -> 13209.7 | I36: 131 | J36: =IF(AND(G36<>"",G36<>0),E36/G36,"") -> 1.55 | K36: 109604 | L36: 20000 | M36: 32175 | N36: =IF(AND(I36<>"",I36<>0),G36/I36,"") -> 0.15267176 | O36: =D36/P36 -> 1.8080533 | P36: =$I$8*V36*W36/SUMPRODUCT($W$25:$W$55,$V$25:$V$55) -> 146120.69 | Q36: =$I$9*V36*W36/SUMPRODUCT($W$25:$W$55,$V$25:$V$55) -> 24.353449 | R36: =IF($I$12="","",Q36/$I$12) -> 13.529694 | S36: =IF(W36<>"",IF(D36<>"",D36,($I$8-SUM($S$25:S35))*V36*W36/SUMPRODUCT($W36:$W$55,$V36:$V$55)),"") -> 264194 | T36: =IF(W36<>"",IF(E36<>"",E36,($I$9-SUM($T$25:T35))*V36*W36/SUMPRODUCT($W36:$W$55,$V36:$V$55)),"") -> 31 | U36: =IF(W36<>"",IF(E36<>"",E36,($I$9-SUM($T$25:T35))*V36*W36/SUMPRODUCT($W36:$W$55,$V36:$V$55)),"") -> 31 | V36: 1 | W36: 1
A37: Рогалевич,Уразгильдеева | B37: 45913 | C37: сб | D37: =7992+68071+53126 -> 129189 | E37: 26 | F37: =IF(AND(E37<>"",E37<>0),D37/E37,"") -> 4968.8077 | G37: 15 | H37: =IF(AND(G37<>"",G37<>0),D37/G37,"") -> 8612.6 | I37: =55+93 -> 148 | J37: =IF(AND(G37<>"",G37<>0),E37/G37,"") -> 1.7333333 | K37: 7992 | N37: =IF(AND(I37<>"",I37<>0),G37/I37,"") -> 0.10135135 | O37: =D37/P37 -> 0.88412528 | P37: =$I$8*V37*W37/SUMPRODUCT($W$25:$W$55,$V$25:$V$55) -> 146120.69 | Q37: =$I$9*V37*W37/SUMPRODUCT($W$25:$W$55,$V$25:$V$55) -> 24.353449 | R37: =IF($I$12="","",Q37/$I$12) -> 13.529694 | S37: =IF(W37<>"",IF(D37<>"",D37,($I$8-SUM($S$25:S36))*V37*W37/SUMPRODUCT($W37:$W$55,$V37:$V$55)),"") -> 129189 | T37: =IF(W37<>"",IF(E37<>"",E37,($I$9-SUM($T$25:T36))*V37*W37/SUMPRODUCT($W37:$W$55,$V37:$V$55)),"") -> 26 | U37: =IF(W37<>"",IF(E37<>"",E37,($I$9-SUM($T$25:T36))*V37*W37/SUMPRODUCT($W37:$W$55,$V37:$V$55)),"") -> 26 | V37: 1 | W37: 1
A38: Рогалевич,Уразгильдеева | B38: 45914 | C38: вс | D38: 135071 | E38: 22 | F38: =IF(AND(E38<>"",E38<>0),D38/E38,"") -> 6139.5909 | G38: 14 | H38: =IF(AND(G38<>"",G38<>0),D38/G38,"") -> 9647.9286 | I38: =7+92 -> 99 | J38: =IF(AND(G38<>"",G38<>0),E38/G38,"") -> 1.5714286 | K38: 36719 | M38: 12384 | N38: =IF(AND(I38<>"",I38<>0),G38/I38,"") -> 0.14141414 | O38: =D38/P38 -> 0.92437968 | P38: =$I$8*V38*W38/SUMPRODUCT($W$25:$W$55,$V$25:$V$55) -> 146120.69 | Q38: =$I$9*V38*W38/SUMPRODUCT($W$25:$W$55,$V$25:$V$55) -> 24.353449 | R38: =IF($I$12="","",Q38/$I$12) -> 13.529694 | S38: =IF(W38<>"",IF(D38<>"",D38,($I$8-SUM($S$25:S37))*V38*W38/SUMPRODUCT($W38:$W$55,$V38:$V$55)),"") -> 135071 | T38: =IF(W38<>"",IF(E38<>"",E38,($I$9-SUM($T$25:T37))*V38*W38/SUMPRODUCT($W38:$W$55,$V38:$V$55)),"") -> 22 | U38: =IF(W38<>"",IF(E38<>"",E38,($I$9-SUM($T$25:T37))*V38*W38/SUMPRODUCT($W38:$W$55,$V38:$V$55)),"") -> 22 | V38: 1 | W38: 1
A39: Рогалевич,Уразгильдеева | B39: 45915 | C39: пн | D39: 14503 | E39: 1 | F39: =IF(AND(E39<>"",E39<>0),D39/E39,"") -> 14503 | G39: 1 | H39: =IF(AND(G39<>"",G39<>0),D39/G39,"") -> 14503 | I39: =8+41 -> 49 | J39: =IF(AND(G39<>"",G39<>0),E39/G39,"") -> 1 | L39: 14503 | N39: =IF(AND(I39<>"",I39<>0),G39/I39,"") -> 0.020408163 | O39: =D39/P39 -> 0.13637786 | P39: =$I$8*V39*W39/SUMPRODUCT($W$25:$W$55,$V$25:$V$55) -> 106344.24 | Q39: =$I$9*V39*W39/SUMPRODUCT($W$25:$W$55,$V$25:$V$55) -> 17.724041 | R39: =IF($I$12="","",Q39/$I$12) -> 9.8466893 | S39: =IF(W39<>"",IF(D39<>"",D39,($I$8-SUM($S$25:S38))*V39*W39/SUMPRODUCT($W39:$W$55,$V39:$V$55)),"") -> 14503 | T39: =IF(W39<>"",IF(E39<>"",E39,($I$9-SUM($T$25:T38))*V39*W39/SUMPRODUCT($W39:$W$55,$V39:$V$55)),"") -> 1 | U39: =IF(W39<>"",IF(E39<>"",E39,($I$9-SUM($T$25:T38))*V39*W39/SUMPRODUCT($W39:$W$55,$V39:$V$55)),"") -> 1 | V39: 0.85310234 | W39: 0.85310234
A40: Рогалевич,Уразгильдеева | B40: 45916 | C40: вт | D40: 40364 | E40: 8 | F40: =IF(AND(E40<>"",E40<>0),D40/E40,"") -> 5045.5 | G40: 6 | H40: =IF(AND(G40<>"",G40<>0),D40/G40,"") -> 6727.3333 | I40: =7+74 -> 81 | J40: =IF(AND(G40<>"",G40<>0),E40/G40,"") -> 1.3333333 | N40: =IF(AND(I40<>"",I40<>0),G40/I40,"") -> 0.074074074 | O40: =D40/P40 -> 0.3795598 | P40: =$I$8*V40*W40/SUMPRODUCT($W$25:$W$55,$V$25:$V$55) -> 106344.24 | Q40: =$I$9*V40*W40/SUMPRODUCT($W$25:$W$55,$V$25:$V$55) -> 17.724041 | R40: =IF($I$12="","",Q40/$I$12) -> 9.8466893 | S40: =IF(W40<>"",IF(D40<>"",D40,($I$8-SUM($S$25:S39))*V40*W40/SUMPRODUCT($W40:$W$55,$V40:$V$55)),"") -> 40364 | T40: =IF(W40<>"",IF(E40<>"",E40,($I$9-SUM($T$25:T39))*V40*W40/SUMPRODUCT($W40:$W$55,$V40:$V$55)),"") -> 8 | U40: =IF(W40<>"",IF(E40<>"",E40,($I$9-SUM($T$25:T39))*V40*W40/SUMPRODUCT($W40:$W$55,$V40:$V$55)),"") -> 8 | V40: 0.85310234 | W40: 0.85310234
A41: Рогалевич | B41: 45917 | C41: ср | D41: =8992+70868 -> 79860 | E41: 15 | F41: =IF(AND(E41<>"",E41<>0),D41/E41,"") -> 5324 | G41: 6 | H41: =IF(AND(G41<>"",G41<>0),D41/G41,"") -> 13310 | I41: 70 | J41: =IF(AND(G41<>"",G41<>0),E41/G41,"") -> 2.5 | K41: 8992 | N41: =IF(AND(I41<>"",I41<>0),G41/I41,"") -> 0.085714286 | O41: =D41/P41 -> 0.75095743 | P41: =$I$8*V41*W41/SUMPRODUCT($W$25:$W$55,$V$25:$V$55) -> 106344.24 | Q41: =$I$9*V41*W41/SUMPRODUCT($W$25:$W$55,$V$25:$V$55) -> 17.724041 | R41: =IF($I$12="","",Q41/$I$12) -> 9.8466893 | S41: =IF(W41<>"",IF(D41<>"",D41,($I$8-SUM($S$25:S40))*V41*W41/SUMPRODUCT($W41:$W$55,$V41:$V$55)),"") -> 79860 | T41: =IF(W41<>"",IF(E41<>"",E41,($I$9-SUM($T$25:T40))*V41*W41/SUMPRODUCT($W41:$W$55,$V41:$V$55)),"") -> 15 | U41: =IF(W41<>"",IF(E41<>"",E41,($I$9-SUM($T$25:T40))*V41*W41/SUMPRODUCT($W41:$W$55,$V41:$V$55)),"") -> 15 | V41: 0.85310234 | W41: 0.85310234
A42: Рогалевич | B42: 45918 | C42: чт | D42: 48423 | E42: 9 | F42: =IF(AND(E42<>"",E42<>0),D42/E42,"") -> 5380.3333 | G42: 4 | H42: =IF(AND(G42<>"",G42<>0),D42/G42,"") -> 12105.75 | I42: 29 | J42: =IF(AND(G42<>"",G42<>0),E42/G42,"") -> 2.25 | N42: =IF(AND(I42<>"",I42<>0),G42/I42,"") -> 0.13793103 | O42: =D42/P42 -> 0.45534199 | P42: =$I$8*V42*W42/SUMPRODUCT($W$25:$W$55,$V$25:$V$55) -> 106344.24 | Q42: =$I$9*V42*W42/SUMPRODUCT($W$25:$W$55,$V$25:$V$55) -> 17.724041 | R42: =IF($I$12="","",Q42/$I$12) -> 9.8466893 | S42: =IF(W42<>"",IF(D42<>"",D42,($I$8-SUM($S$25:S41))*V42*W42/SUMPRODUCT($W42:$W$55,$V42:$V$55)),"") -> 48423 | T42: =IF(W42<>"",IF(E42<>"",E42,($I$9-SUM($T$25:T41))*V42*W42/SUMPRODUCT($W42:$W$55,$V42:$V$55)),"") -> 9 | U42: =IF(W42<>"",IF(E42<>"",E42,($I$9-SUM($T$25:T41))*V42*W42/SUMPRODUCT($W42:$W$55,$V42:$V$55)),"") -> 9 | V42: 0.85310234 | W42: 0.85310234
A43: Рогалевич,Уразгильдеева | B43: 45919 | C43: пт | D43: =138485+18982+27473+9123 -> 194063 | E43: 36 | F43: 5391 | G43: 16 | H43: =IF(AND(G43<>"",G43<>0),D43/G43,"") -> 12128.938 | I43: 120 | J43: =IF(AND(G43<>"",G43<>0),E43/G43,"") -> 2.25 | K43: 18982 | L43: 9123 | M43: 27473 | N43: =IF(AND(I43<>"",I43<>0),G43/I43,"") -> 0.13333333 | O43: =D43/P43 -> 1.3281007 | P43: =$I$8*V43*W43/SUMPRODUCT($W$25:$W$55,$V$25:$V$55) -> 146120.69 | Q43: =$I$9*V43*W43/SUMPRODUCT($W$25:$W$55,$V$25:$V$55) -> 24.353449 | R43: =IF($I$12="","",Q43/$I$12) -> 13.529694 | S43: =IF(W43<>"",IF(D43<>"",D43,($I$8-SUM($S$25:S42))*V43*W43/SUMPRODUCT($W43:$W$55,$V43:$V$55)),"") -> 194063 | T43: =IF(W43<>"",IF(E43<>"",E43,($I$9-SUM($T$25:T42))*V43*W43/SUMPRODUCT($W43:$W$55,$V43:$V$55)),"") -> 36 | U43: =IF(W43<>"",IF(E43<>"",E43,($I$9-SUM($T$25:T42))*V43*W43/SUMPRODUCT($W43:$W$55,$V43:$V$55)),"") -> 36 | V43: 1 | W43: 1
A44: Рогалевич,Уразгильдеева | B44: 45920 | C44: сб | D44: =10990+31275+22767+57513+220 -> 122765 | E44: 18 | F44: 6808 | G44: 10 | H44: =IF(AND(G44<>"",G44<>0),D44/G44,"") -> 12276.5 | I44: 60 | J44: =IF(AND(G44<>"",G44<>0),E44/G44,"") -> 1.8 | K44: 10990 | L44: 220 | M44: 31275 | N44: =IF(AND(I44<>"",I44<>0),G44/I44,"") -> 0.16666667 | O44: =D44/P44 -> 0.84016163 | P44: =$I$8*V44*W44/SUMPRODUCT($W$25:$W$55,$V$25:$V$55) -> 146120.69 | Q44: =$I$9*V44*W44/SUMPRODUCT($W$25:$W$55,$V$25:$V$55) -> 24.353449 | R44: =IF($I$12="","",Q44/$I$12) -> 13.529694 | S44: =IF(W44<>"",IF(D44<>"",D44,($I$8-SUM($S$25:S43))*V44*W44/SUMPRODUCT($W44:$W$55,$V44:$V$55)),"") -> 122765 | T44: =IF(W44<>"",IF(E44<>"",E44,($I$9-SUM($T$25:T43))*V44*W44/SUMPRODUCT($W44:$W$55,$V44:$V$55)),"") -> 18 | U44: =IF(W44<>"",IF(E44<>"",E44,($I$9-SUM($T$25:T43))*V44*W44/SUMPRODUCT($W44:$W$55,$V44:$V$55)),"") -> 18 | V44: 1 | W44: 1
A45: Рогалевич,Уразгильдеева | B45: 45921 | C45: вс | D45: =87138+6801 -> 93939 | E45: 16 | F45: 5446 | G45: 9 | H45: =IF(AND(G45<>"",G45<>0),D45/G45,"") -> 10437.667 | I45: 50 | J45: =IF(AND(G45<>"",G45<>0),E45/G45,"") -> 1.7777778 | K45: 15990 | L45: 6801 | N45: =IF(AND(I45<>"",I45<>0),G45/I45,"") -> 0.18 | O45: =D45/P45 -> 0.64288635 | P45: =$I$8*V45*W45/SUMPRODUCT($W$25:$W$55,$V$25:$V$55) -> 146120.69 | Q45: =$I$9*V45*W45/SUMPRODUCT($W$25:$W$55,$V$25:$V$55) -> 24.353449 | R45: =IF($I$12="","",Q45/$I$12) -> 13.529694 | S45: =IF(W45<>"",IF(D45<>"",D45,($I$8-SUM($S$25:S44))*V45*W45/SUMPRODUCT($W45:$W$55,$V45:$V$55)),"") -> 93939 | T45: =IF(W45<>"",IF(E45<>"",E45,($I$9-SUM($T$25:T44))*V45*W45/SUMPRODUCT($W45:$W$55,$V45:$V$55)),"") -> 16 | U45: =IF(W45<>"",IF(E45<>"",E45,($I$9-SUM($T$25:T44))*V45*W45/SUMPRODUCT($W45:$W$55,$V45:$V$55)),"") -> 16 | V45: 1 | W45: 1
A46: Рогалевич | B46: 45922 | C46: пн | D46: =25583+85170 -> 110753 | E46: 17 | F46: 6515 | G46: 6 | H46: =IF(AND(G46<>"",G46<>0),D46/G46,"") -> 18458.833 | I46: 50 | J46: =IF(AND(G46<>"",G46<>0),E46/G46,"") -> 2.8333333 | K46: 25583 | N46: =IF(AND(I46<>"",I46<>0),G46/I46,"") -> 0.12 | O46: =D46/P46 -> 1.0414574 | P46: =$I$8*V46*W46/SUMPRODUCT($W$25:$W$55,$V$25:$V$55) -> 106344.24 | Q46: =$I$9*V46*W46/SUMPRODUCT($W$25:$W$55,$V$25:$V$55) -> 17.724041 | R46: =IF($I$12="","",Q46/$I$12) -> 9.8466893 | S46: =IF(W46<>"",IF(D46<>"",D46,($I$8-SUM($S$25:S45))*V46*W46/SUMPRODUCT($W46:$W$55,$V46:$V$55)),"") -> 110753 | T46: =IF(W46<>"",IF(E46<>"",E46,($I$9-SUM($T$25:T45))*V46*W46/SUMPRODUCT($W46:$W$55,$V46:$V$55)),"") -> 17 | U46: =IF(W46<>"",IF(E46<>"",E46,($I$9-SUM($T$25:T45))*V46*W46/SUMPRODUCT($W46:$W$55,$V46:$V$55)),"") -> 17 | V46: 0.85310234 | W46: 0.85310234
A47: Рогалевич,Уразгильдеева | B47: 45923 | C47: вт | D47: =8903+17867+77307 -> 104077 | E47: 19 | F47: 5478 | G47: 8 | H47: =IF(AND(G47<>"",G47<>0),D47/G47,"") -> 13009.625 | I47: 60 | J47: =IF(AND(G47<>"",G47<>0),E47/G47,"") -> 2.375 | L47: 8903 | N47: =IF(AND(I47<>"",I47<>0),G47/I47,"") -> 0.13333333 | O47: =D47/P47 -> 0.97868014 | P47: =$I$8*V47*W47/SUMPRODUCT($W$25:$W$55,$V$25:$V$55) -> 106344.24 | Q47: =$I$9*V47*W47/SUMPRODUCT($W$25:$W$55,$V$25:$V$55) -> 17.724041 | R47: =IF($I$12="","",Q47/$I$12) -> 9.8466893 | S47: =IF(W47<>"",IF(D47<>"",D47,($I$8-SUM($S$25:S46))*V47*W47/SUMPRODUCT($W47:$W$55,$V47:$V$55)),"") -> 104077 | T47: =IF(W47<>"",IF(E47<>"",E47,($I$9-SUM($T$25:T46))*V47*W47/SUMPRODUCT($W47:$W$55,$V47:$V$55)),"") -> 19 | U47: =IF(W47<>"",IF(E47<>"",E47,($I$9-SUM($T$25:T46))*V47*W47/SUMPRODUCT($W47:$W$55,$V47:$V$55)),"") -> 19 | V47: 0.85310234 | W47: 0.85310234
A48: Рогалевич,Уразгильдеева | B48: 45924 | C48: ср | D48: 49710 | E48: 11 | F48: 4519 | G48: 9 | H48: =IF(AND(G48<>"",G48<>0),D48/G48,"") -> 5523.3333 | I48: 50 | J48: =IF(AND(G48<>"",G48<>0),E48/G48,"") -> 1.2222222 | N48: =IF(AND(I48<>"",I48<>0),G48/I48,"") -> 0.18 | O48: =D48/P48 -> 0.4674442 | P48: =$I$8*V48*W48/SUMPRODUCT($W$25:$W$55,$V$25:$V$55) -> 106344.24 | Q48: =$I$9*V48*W48/SUMPRODUCT($W$25:$W$55,$V$25:$V$55) -> 17.724041 | R48: =IF($I$12="","",Q48/$I$12) -> 9.8466893 | S48: =IF(W48<>"",IF(D48<>"",D48,($I$8-SUM($S$25:S47))*V48*W48/SUMPRODUCT($W48:$W$55,$V48:$V$55)),"") -> 49710 | T48: =IF(W48<>"",IF(E48<>"",E48,($I$9-SUM($T$25:T47))*V48*W48/SUMPRODUCT($W48:$W$55,$V48:$V$55)),"") -> 11 | U48: =IF(W48<>"",IF(E48<>"",E48,($I$9-SUM($T$25:T47))*V48*W48/SUMPRODUCT($W48:$W$55,$V48:$V$55)),"") -> 11 | V48: 0.85310234 | W48: 0.85310234
A49: Рогалевич | B49: 45925 | C49: чт | D49: =46803+9503+8992+3692+35958 -> 104948 | E49: 13 | F49: =IF(AND(E49<>"",E49<>0),D49/E49,"") -> 8072.9231 | G49: 11 | H49: =IF(AND(G49<>"",G49<>0),D49/G49,"") -> 9540.7273 | I49: 60 | J49: =IF(AND(G49<>"",G49<>0),E49/G49,"") -> 1.1818182 | K49: 46803 | L49: 9503 | M49: 8992 | N49: =IF(AND(I49<>"",I49<>0),G49/I49,"") -> 0.18333333 | O49: =D49/P49 -> 0.98687052 | P49: =$I$8*V49*W49/SUMPRODUCT($W$25:$W$55,$V$25:$V$55) -> 106344.24 | Q49: =$I$9*V49*W49/SUMPRODUCT($W$25:$W$55,$V$25:$V$55) -> 17.724041 | R49: =IF($I$12="","",Q49/$I$12) -> 9.8466893 | S49: =IF(W49<>"",IF(D49<>"",D49,($I$8-SUM($S$25:S48))*V49*W49/SUMPRODUCT($W49:$W$55,$V49:$V$55)),"") -> 104948 | T49: =IF(W49<>"",IF(E49<>"",E49,($I$9-SUM($T$25:T48))*V49*W49/SUMPRODUCT($W49:$W$55,$V49:$V$55)),"") -> 13 | U49: =IF(W49<>"",IF(E49<>"",E49,($I$9-SUM($T$25:T48))*V49*W49/SUMPRODUCT($W49:$W$55,$V49:$V$55)),"") -> 13 | V49: 0.85310234 | W49: 0.85310234
A50: Рогалевич,Уразгильдеева | B50: 45926 | C50: пт | D50: 106746 | E50: 18 | F50: =IF(AND(E50<>"",E50<>0),D50/E50,"") -> 5930.3333 | G50: 7 | H50: =IF(AND(G50<>"",G50<>0),D50/G50,"") -> 15249.429 | I50: =19+47 -> 66 | J50: =IF(AND(G50<>"",G50<>0),E50/G50,"") -> 2.5714286 | K50: 11492 | N50: =IF(AND(I50<>"",I50<>0),G50/I50,"") -> 0.10606061 | O50: =D50/P50 -> 1.1414579 | P50: =$I$8*V50*W50/SUMPRODUCT($W$25:$W$55,$V$25:$V$55) -> 93517.244 | Q50: =$I$9*V50*W50/SUMPRODUCT($W$25:$W$55,$V$25:$V$55) -> 15.586207 | R50: =IF($I$12="","",Q50/$I$12) -> 8.6590041 | S50: =IF(W50<>"",IF(D50<>"",D50,($I$8-SUM($S$25:S49))*V50*W50/SUMPRODUCT($W50:$W$55,$V50:$V$55)),"") -> 106746 | T50: =IF(W50<>"",IF(E50<>"",E50,($I$9-SUM($T$25:T49))*V50*W50/SUMPRODUCT($W50:$W$55,$V50:$V$55)),"") -> 18 | U50: =IF(W50<>"",IF(E50<>"",E50,($I$9-SUM($T$25:T49))*V50*W50/SUMPRODUCT($W50:$W$55,$V50:$V$55)),"") -> 18 | V50: 0.8 | W50: 0.8
A51: Рогалевич,Уразгильдеева | B51: 45927 | C51: сб | D51: =20906+21082+48725+64088 -> 154801 | E51: 27 | F51: =IF(AND(E51<>"",E51<>0),D51/E51,"") -> 5733.3704 | G51: 15 | H51: =IF(AND(G51<>"",G51<>0),D51/G51,"") -> 10320.067 | I51: 86 | J51: =IF(AND(G51<>"",G51<>0),E51/G51,"") -> 1.8 | L51: 20906 | M51: 21082 | N51: =IF(AND(I51<>"",I51<>0),G51/I51,"") -> 0.1744186 | O51: =D51/P51 -> 1.6553204 | P51: =$I$8*V51*W51/SUMPRODUCT($W$25:$W$55,$V$25:$V$55) -> 93517.244 | Q51: =$I$9*V51*W51/SUMPRODUCT($W$25:$W$55,$V$25:$V$55) -> 15.586207 | R51: =IF($I$12="","",Q51/$I$12) -> 8.6590041 | S51: =IF(W51<>"",IF(D51<>"",D51,($I$8-SUM($S$25:S50))*V51*W51/SUMPRODUCT($W51:$W$55,$V51:$V$55)),"") -> 154801 | T51: =IF(W51<>"",IF(E51<>"",E51,($I$9-SUM($T$25:T50))*V51*W51/SUMPRODUCT($W51:$W$55,$V51:$V$55)),"") -> 27 | U51: =IF(W51<>"",IF(E51<>"",E51,($I$9-SUM($T$25:T50))*V51*W51/SUMPRODUCT($W51:$W$55,$V51:$V$55)),"") -> 27 | V51: 0.8 | W51: 0.8
A52: Рогалевич,Уразгальдеева | B52: 45928 | C52: вс | D52: 116268 | E52: 17 | F52: =IF(AND(E52<>"",E52<>0),D52/E52,"") -> 6839.2941 | G52: 9 | H52: =IF(AND(G52<>"",G52<>0),D52/G52,"") -> 12918.667 | I52: 70 | J52: =IF(AND(G52<>"",G52<>0),E52/G52,"") -> 1.8888889 | K52: 30671 | L52: 16806 | M52: 15983 | N52: =IF(AND(I52<>"",I52<>0),G52/I52,"") -> 0.12857143 | O52: =D52/P52 -> 1.2432787 | P52: =$I$8*V52*W52/SUMPRODUCT($W$25:$W$55,$V$25:$V$55) -> 93517.244 | Q52: =$I$9*V52*W52/SUMPRODUCT($W$25:$W$55,$V$25:$V$55) -> 15.586207 | R52: =IF($I$12="","",Q52/$I$12) -> 8.6590041 | S52: =IF(W52<>"",IF(D52<>"",D52,($I$8-SUM($S$25:S51))*V52*W52/SUMPRODUCT($W52:$W$55,$V52:$V$55)),"") -> 116268 | T52: =IF(W52<>"",IF(E52<>"",E52,($I$9-SUM($T$25:T51))*V52*W52/SUMPRODUCT($W52:$W$55,$V52:$V$55)),"") -> 17 | U52: =IF(W52<>"",IF(E52<>"",E52,($I$9-SUM($T$25:T51))*V52*W52/SUMPRODUCT($W52:$W$55,$V52:$V$55)),"") -> 17 | V52: 0.8 | W52: 0.8
A53: Рогалевич,Уразгильдеева | B53: 45929 | C53: пн | D53: 34846.48 | E53: 8 | F53: =IF(AND(E53<>"",E53<>0),D53/E53,"") -> 4355.81 | G53: 4 | H53: =IF(AND(G53<>"",G53<>0),D53/G53,"") -> 8711.62 | I53: 30 | J53: =IF(AND(G53<>"",G53<>0),E53/G53,"") -> 2 | N53: =IF(AND(I53<>"",I53<>0),G53/I53,"") -> 0.13333333 | O53: =D53/P53 -> 0.3726209 | P53: =$I$8*V53*W53/SUMPRODUCT($W$25:$W$55,$V$25:$V$55) -> 93517.244 | Q53: =$I$9*V53*W53/SUMPRODUCT($W$25:$W$55,$V$25:$V$55) -> 15.586207 | R53: =IF($I$12="","",Q53/$I$12) -> 8.6590041 | S53: =IF(W53<>"",IF(D53<>"",D53,($I$8-SUM($S$25:S52))*V53*W53/SUMPRODUCT($W53:$W$55,$V53:$V$55)),"") -> 34846.48 | T53: =IF(W53<>"",IF(E53<>"",E53,($I$9-SUM($T$25:T52))*V53*W53/SUMPRODUCT($W53:$W$55,$V53:$V$55)),"") -> 8 | U53: =IF(W53<>"",IF(E53<>"",E53,($I$9-SUM($T$25:T52))*V53*W53/SUMPRODUCT($W53:$W$55,$V53:$V$55)),"") -> 8 | V53: 0.8 | W53: 0.8
A54: Рогалевич | B54: 45930 | C54: вт | D54: 32944 | E54: 5 | F54: =IF(AND(E54<>"",E54<>0),D54/E54,"") -> 6588.8 | G54: 3 | H54: =IF(AND(G54<>"",G54<>0),D54/G54,"") -> 10981.333 | I54: 17 | J54: =IF(AND(G54<>"",G54<>0),E54/G54,"") -> 1.6666667 | K54: 13490 | N54: =IF(AND(I54<>"",I54<>0),G54/I54,"") -> 0.17647059 | O54: =D54/P54 -> 0.35227728 | P54: =$I$8*V54*W54/SUMPRODUCT($W$25:$W$55,$V$25:$V$55) -> 93517.244 | Q54: =$I$9*V54*W54/SUMPRODUCT($W$25:$W$55,$V$25:$V$55) -> 15.586207 | R54: =IF($I$12="","",Q54/$I$12) -> 8.6590041 | S54: =IF(W54<>"",IF(D54<>"",D54,($I$8-SUM($S$25:S53))*V54*W54/SUMPRODUCT($W54:$W$55,$V54:$V$55)),"") -> 32944 | T54: =IF(W54<>"",IF(E54<>"",E54,($I$9-SUM($T$25:T53))*V54*W54/SUMPRODUCT($W54:$W$55,$V54:$V$55)),"") -> 5 | U54: =IF(W54<>"",IF(E54<>"",E54,($I$9-SUM($T$25:T53))*V54*W54/SUMPRODUCT($W54:$W$55,$V54:$V$55)),"") -> 5 | V54: 0.8 | W54: 0.8
F55: =IF(AND(E55<>"",E55<>0),D55/E55,"") | H55: =IF(AND(G55<>"",G55<>0),D55/G55,"") | J55: =IF(AND(G55<>"",G55<>0),E55/G55,"") | N55: =IF(AND(I55<>"",I55<>0),G55/I55,"") | O55: =D55/P55 -> #DIV/0! | P55: =$I$8*V55*W55/SUMPRODUCT($W$25:$W$55,$V$25:$V$55) -> 0 | Q55: =$I$9*V55*W55/SUMPRODUCT($W$25:$W$55,$V$25:$V$55) -> 0 | R55: =IF($I$12="","",Q55/$I$12) -> 0 | S55: =IF(W55<>"",IF(D55<>"",D55,($I$8-SUM($S$25:S54))*V55*W55/SUMPRODUCT($W55:$W$55,$V55:$V$55)),"") | T55: =IF(W55<>"",IF(E55<>"",E55,($I$9-SUM($T$25:T54))*V55*W55/SUMPRODUCT($W55:$W$55,$V55:$V$55)),"") | U55: =IF(W55<>"",IF(E55<>"",E55,($I$9-SUM($T$25:T54))*V55*W55/SUMPRODUCT($W55:$W$55,$V55:$V$55)),"")
B56: итого | D56: =SUM(D25:D55) -> 3134427.1 | E56: =SUM(E25:E55) -> 482 | F56: =IF(AND(E56<>"", E56<>0), D56/E56, "") -> 6502.9607 | G56: =SUM(G25:G55) -> 273 | H56: =IF(AND(G56<>"", G56<>0), D56/G56, "") -> 11481.418 | I56: =SUM(I25:I55) -> 2186 | J56: =E56/G56 -> 1.7655678 | K56: =SUM(K25:K55) -> 779065 | L56: =SUM(L25:L55) -> 167876 | M56: =SUM(M25:M55) -> 216811 | N56: =IF(AND(I56<>"", I56<>0), G56/I56, "") -> 0.12488564 | O56: =D56/P56 -> 0.90412688 | P56: =SUM(P25:P55) -> 3466800 | Q56: =SUM(Q25:Q55) -> 577.8 | R56: =SUM(R25:R55) -> 321 | S56: =SUM(S25:S55) -> 3134427.1 | T56: =SUM(T25:T55) -> 482 | U56: =SUM(U25:U55) -> 476
D57: =SUMIF(D25:D55,"",P25:P55)+D56 -> 3134427.1 | I57: =I56/J14 -> 72.866667
D58: ='Рогалевич И. Е. '!J8+'Уразгильдеева Е. Р. '!J8 -> 3134427.1 | E58: ='Рогалевич И. Е. '!E57+'Уразгильдеева Е. Р. '!E57 -> 482 | G58: ='Рогалевич И. Е. '!G57+'Уразгильдеева Е. Р. '!G57 -> 273 | I58: ='Рогалевич И. Е. '!I57+'Уразгильдеева Е. Р. '!I57 -> 2186 | K58: ='Рогалевич И. Е. '!K57+'Уразгильдеева Е. Р. '!K57 -> 779065 | L58: ='Рогалевич И. Е. '!L57+'Уразгильдеева Е. Р. '!L57 -> 167876 | M58: ='Рогалевич И. Е. '!M57+'Уразгильдеева Е. Р. '!M57 -> 216811

Sheet Конкурс
A1: Сотрудник | B1: Длина чека | C1: КВП | Z1: Итого
D2: 9 | E2: 10 | F2: 11 | G2: 12 | H2: 13 | I2: 14 | J2: 15 | K2: 16 | L2: 17 | M2: 18 | N2: 19 | O2: 20 | P2: 21 | Q2: 22 | R2: 23 | S2: 24 | T2: 25 | U2: 26 | V2: 27 | W2: 28 | X2: 29 | Y2: 30
A3: =График!B29 -> Рогалевич Ирина | B3: ='Рогалевич И. Е. '!J12 -> 1.7514793 | C3: ='Рогалевич И. Е. '!K8 -> 0.96303343 | D3: 2 | E3: 2 | F3: 0 | G3: 0 | H3: 0 | I3: 0 | J3: 0 | K3: 0 | L3: 2 | M3: 0 | N3: 1 | O3: 0 | P3: 1 | Q3: 1 | R3: 1 | S3: 1 | T3: 2 | U3: 0 | V3: 0 | W3: 0 | X3: 0 | Y3: 0 | Z3: =SUM(D3:Y3) -> 13
A4: =График!B28 -> Уразгильдеева Екатерина | B4: ='Уразгильдеева Е. Р. '!J12 -> 1.7884615 | C4: ='Уразгильдеева Е. Р. '!K8 -> 0.82921047 | D4: 0 | E4: 0 | F4: 0 | G4: 0 | H4: 1 | I4: 0 | J4: 0 | K4: 0 | L4: 0 | M4: 0 | N4: 0 | O4: 1 | P4: 0 | Q4: 0 | R4: 1 | S4: 0 | T4: 0 | U4: 0 | V4: 0 | W4: 0 | X4: 0 | Y4: 0 | Z4: =SUM(D4:Y4) -> 3
A5: =График!B27 -> 0 | B5: ='[1]Яковенко А. К'!J12 -> #REF! | C5: ='[1]Яковенко А. К'!K8 -> #REF! | Z5: =SUM(D5:Y5) -> 0

Sheet Св. по пок.
A2: Показатель | D2: ='Ялта, Ленина, 18'!I3 -> ул. Набережная Ленина, 18 | G2: =График!B29 -> Рогалевич Ирина | J2: =График!B28 -> Уразгильдеева Екатерина | M2: =График!B27 -> 0
D3: Факт | F3: Прогноз | G3: Факт | I3: Прогноз | J3: Факт | L3: Прогноз | M3: Факт | O3: Прогноз
A4: Выручка | D4: ='Ялта, Ленина, 18'!K8 -> 0.90412688 | E4: ='Ялта, Ленина, 18'!J8 -> 3134427.1 | F4: ='Ялта, Ленина, 18'!M8 -> 0.90412688 | G4: ='Рогалевич И. Е. '!K8 -> 0.96303343 | H4: ='Рогалевич И. Е. '!J8 -> 1869031 | I4: ='Рогалевич И. Е. '!M8 -> 0.96303343 | J4: ='Уразгильдеева Е. Р. '!K8 -> 0.82921047 | K4: ='Уразгильдеева Е. Р. '!J8 -> 1265396.1 | L4: ='Уразгильдеева Е. Р. '!M8 -> 0.90131573 | M4: ='[1]Яковенко А. К'!K8 -> #REF! | N4: ='[1]Яковенко А. К'!J8 -> #REF! | O4: ='[1]Яковенко А. К'!M8 -> #REF!
A5: Кол-во изделий | D5: ='Ялта, Ленина, 18'!K9 -> 0.83419868 | E5: ='Ялта, Ленина, 18'!J9 -> 482 | F5: ='Ялта, Ленина, 18'!M9 -> 0.83419868 | G5: ='Рогалевич И. Е. '!K9 -> 0.91509845 | H5: ='Рогалевич И. Е. '!J9 -> 296 | I5: ='Рогалевич И. Е. '!M9 -> 0.91509845 | J5: ='Уразгильдеева Е. Р. '!K9 -> 0.73131164 | K5: ='Уразгильдеева Е. Р. '!J9 -> 186 | L5: ='Уразгильдеева Е. Р. '!M9 -> 0.83103596 | M5: ='[1]Яковенко А. К'!K9 -> #REF! | N5: ='[1]Яковенко А. К'!J9 -> #REF! | O5: ='[1]Яковенко А. К'!M9 -> #REF!
A6: Средний чек | D6: ='Ялта, Ленина, 18'!K10 -> 1.0630942 | E6: ='Ялта, Ленина, 18'!J10 -> 11481.418 | F6: ='Ялта, Ленина, 18'!M10 -> 1.0630942 | G6: ='Рогалевич И. Е. '!K10 -> 1.0240144 | H6: ='Рогалевич И. Е. '!J10 -> 11059.355 | I6: ='Рогалевич И. Е. '!M10 -> 1.0240144 | J6: ='Уразгильдеева Е. Р. '!K10 -> 1.1265991 | K6: ='Уразгильдеева Е. Р. '!J10 -> 12167.27 | L6: ='Уразгильдеева Е. Р. '!M10 -> 1.1265991 | M6: ='[1]Яковенко А. К'!K10 -> #REF! | N6: ='[1]Яковенко А. К'!J10 -> #REF! | O6: ='[1]Яковенко А. К'!M10 -> #REF!
A7: Средняя стоимость изделия | D7: ='Ялта, Ленина, 18'!K11 -> 1.0838268 | E7: ='Ялта, Ленина, 18'!J11 -> 6502.9607 | F7: ='Ялта, Ленина, 18'!M11 -> 1.0838268 | G7: ='Рогалевич И. Е. '!K11 -> 1.0523823 | H7: ='Рогалевич И. Е. '!J11 -> 6314.2939 | I7: ='Рогалевич И. Е. '!M11 -> 1.0523823 | J7: ='Уразгильдеева Е. Р. '!K11 -> 1.1338675 | K7: ='Уразгильдеева Е. Р. '!J11 -> 6803.2047 | L7: ='Уразгильдеева Е. Р. '!M11 -> 1.0845689 | M7: ='[1]Яковенко А. К'!K11 -> #REF! | N7: ='[1]Яковенко А. К'!J11 -> #REF! | O7: ='[1]Яковенко А. К'!M11 -> #REF!
A8: Длина чека | D8: ='Ялта, Ленина, 18'!K12 -> 0.98087098 | E8: ='Ялта, Ленина, 18'!J12 -> 1.7655678 | F8: ='Ялта, Ленина, 18'!M12 -> 0.98087098 | G8: ='Рогалевич И. Е. '!K12 -> 0.97304405 | H8: ='Рогалевич И. Е. '!J12 -> 1.7514793 | I8: ='Рогалевич И. Е. '!M12 -> 0.97304405 | J8: ='Уразгильдеева Е. Р. '!K12 -> 0.99358974 | K8: ='Уразгильдеева Е. Р. '!J12 -> 1.7884615 | L8: ='Уразгильдеева Е. Р. '!M12 -> 0.99358974 | M8: ='[1]Яковенко А. К'!K12 -> #REF! | N8: ='[1]Яковенко А. К'!J12 -> #REF! | O8: ='[1]Яковенко А. К'!M12 -> #REF!
A9: Кол-во чеков | D9: ='Ялта, Ленина, 18'!K13 -> 0.85046729 | E9: ='Ялта, Ленина, 18'!J13 -> 273 | F9: ='Ялта, Ленина, 18'!M13 -> 0.85046729 | G9: ='Рогалевич И. Е. '!K13 -> 0.94044915 | H9: ='Рогалевич И. Е. '!J13 -> 169 | I9: ='Рогалевич И. Е. '!M13 -> 0.94044915 | J9: ='Уразгильдеева Е. Р. '!K13 -> 0.73602978 | K9: ='Уразгильдеева Е. Р. '!J13 -> 104 | L9: ='Уразгильдеева Е. Р. '!M13 -> 0.83639748 | M9: ='[1]Яковенко А. К'!K13 -> #REF! | N9: ='[1]Яковенко А. К'!J13 -> #REF! | O9: ='[1]Яковенко А. К'!M13 -> #REF!
A10: Кол-во смен план/отработано | D10: ='Ялта, Ленина, 18'!K14 -> 1 | E10: ='Ялта, Ленина, 18'!J14 -> 30 | G10: ='Рогалевич И. Е. '!K14 -> 1 | H10: ='Рогалевич И. Е. '!J14 -> 30 | J10: ='Уразгильдеева Е. Р. '!K14 -> 1 | K10: ='Уразгильдеева Е. Р. '!J14 -> 22 | M10: ='[1]Яковенко А. К'!K14 -> #REF! | N10: ='[1]Яковенко А. К'!J14 -> #REF!
A11: Средние продажи в смену | D11: ='Ялта, Ленина, 18'!K15 -> 0.90412688 | E11: ='Ялта, Ленина, 18'!J15 -> 104480.9 | F11: ='Ялта, Ленина, 18'!M15 -> 0.90412688 | G11: ='Рогалевич И. Е. '!K15 -> 0.53912282 | H11: ='Рогалевич И. Е. '!J15 -> 62301.033 | I11: ='Рогалевич И. Е. '!M15 -> 0.53912282 | J11: ='Уразгильдеева Е. Р. '!K15 -> 0.49773281 | K11: ='Уразгильдеева Е. Р. '!J15 -> 57518.004 | L11: ='Уразгильдеева Е. Р. '!M15 -> 0.49773281 | M11: ='[1]Яковенко А. К'!K15 -> #REF! | N11: ='[1]Яковенко А. К'!J15 -> #REF! | O11: ='[1]Яковенко А. К'!M15 -> #REF!
A12: Трафик | D12: ='Ялта, Ленина, 18'!K17 -> 1.0214953 | E12: ='Ялта, Ленина, 18'!J17 -> 2186 | F12: ='Ялта, Ленина, 18'!M17 -> 1.0214953 | G12: ='Рогалевич И. Е. '!K17 -> 1.0680219 | H12: ='Рогалевич И. Е. '!J17 -> 1279.5 | I12: ='Рогалевич И. Е. '!M17 -> 1.0680219 | J12: ='Уразгильдеева Е. Р. '!K17 -> 0.96232355 | K12: ='Уразгильдеева Е. Р. '!J17 -> 906.5 | L12: ='Уразгильдеева Е. Р. '!M17 -> 0.96232355 | M12: ='[1]Яковенко А. К'!K17 -> #REF! | N12: ='[1]Яковенко А. К'!J17 -> #REF! | O12: ='[1]Яковенко А. К'!M17 -> #REF!
A13: UNOde50 | D13: ='Ялта, Ленина, 18'!S19 -> 0.76378922 | E13: ='Ялта, Ленина, 18'!T18 -> 779065 | F13: ='Ялта, Ленина, 18'!T19 -> 0.76378922 | G13: ='Рогалевич И. Е. '!S19 -> 0.70517047 | H13: ='Рогалевич И. Е. '!T18 -> 402662 | I13: ='Рогалевич И. Е. '!T19 -> 0.70517047 | J13: ='Уразгильдеева Е. Р. '!S19 -> 0.83833961 | K13: ='Уразгильдеева Е. Р. '!T18 -> 376403 | L13: ='Уразгильдеева Е. Р. '!T19 -> 0.83833961 | M13: ='[1]Яковенко А. К'!S19 -> #REF! | N13: ='[1]Яковенко А. К'!T18 -> #REF! | O13: ='[1]Яковенко А. К'!T19 -> #REF!
A14: IS | D14: ='Ялта, Ленина, 18'!S13 -> 0.32916863 | E14: ='Ялта, Ленина, 18'!T12 -> 167876 | F14: ='Ялта, Ленина, 18'!T13 -> 0.32916863 | G14: ='Рогалевич И. Е. '!S13 -> 0.38955633 | H14: ='Рогалевич И. Е. '!T12 -> 111221 | I14: ='Рогалевич И. Е. '!T13 -> 0.38955633 | J14: ='Уразгильдеева Е. Р. '!S13 -> 0.2523685 | K14: ='Уразгильдеева Е. Р. '!T12 -> 56655 | L14: ='Уразгильдеева Е. Р. '!T13 -> 0.2523685 | M14: ='[1]Яковенко А. К'!S13 -> #REF! | N14: ='[1]Яковенко А. К'!T12 -> #REF! | O14: ='[1]Яковенко А. К'!T13 -> #REF!
A15: ='Ялта, Ленина, 18'!M23 -> Agafi | D15: ='Ялта, Ленина, 18'!V13 -> 0.45168958 | E15: ='Ялта, Ленина, 18'!W12 -> 216811 | F15: ='Ялта, Ленина, 18'!W13 -> 0.45168958 | G15: ='Рогалевич И. Е. '!V13 -> 0.46554247 | H15: ='Рогалевич И. Е. '!W12 -> 125097 | I15: ='Рогалевич И. Е. '!W13 -> 0.46554247 | J15: ='Уразгильдеева Е. Р. '!V13 -> 0.43407171 | K15: ='Уразгильдеева Е. Р. '!W12 -> 91714 | L15: ='Уразгильдеева Е. Р. '!W13 -> 0.43407171 | M15: ='[1]Яковенко А. К'!V13 -> #REF! | N15: ='[1]Яковенко А. К'!W12 -> #REF! | O15: ='[1]Яковенко А. К'!W13 -> #REF!
A16: Отклонение от плана | D16: ='Ялта, Ленина, 18'!J16 -> -332372.92 | G16: ='Рогалевич И. Е. '!N8 -> -71743.795 | J16: ='Уразгильдеева Е. Р. '!N8 -> -150594.68 | M16: ='[1]Яковенко А. К'!N8 -> #REF!

Sheet План на день
A1: Выручка | D1: 135000
A2: Кол-во изделий | D2: =D1/D4 -> 22.5
A3: Средний чек | D3: =D4*D5 -> 10800
A4: Средняя стоимость изделия | D4: ='Ялта, Ленина, 18'!I11 -> 6000
A5: Длина чека | D5: ='Ялта, Ленина, 18'!I12 -> 1.8
A6: Кол-во чеков | D6: =IF(D5<>0,D2/D5,"") -> 12.5
A7: Конверсия | D7: ='Ялта, Ленина, 18'!I20 -> 0.15
A8: IS | D8: =('Ялта, Ленина, 18'!S12-'Ялта, Ленина, 18'!T12)/('Ялта, Ленина, 18'!I14-'Ялта, Ленина, 18'!J14) -> #DIV/0!
A9: UNOde50 | D9: =('Ялта, Ленина, 18'!S18-'Ялта, Ленина, 18'!T18)/('Ялта, Ленина, 18'!I14-'Ялта, Ленина, 18'!J14) -> #DIV/0!
A10: ='Ялта, Ленина, 18'!M23 -> Agafi | D10: =('Ялта, Ленина, 18'!V12-'Ялта, Ленина, 18'!W12)/('Ялта, Ленина, 18'!I14-'Ялта, Ленина, 18'!J14) -> #DIV/0!

Sheet Рогалевич И. Е. 
B1: =TODAY()-1 -> 45939
B2: (отчетная дата) | J2: ЕЖЕДНЕВНЫЙ ОТЧЕТ О ПРОДАЖАХ
B3: Осталось до выполнения плана!!! | J3: =График!B29 -> Рогалевич Ирина
C4: =I8-D57 -> 71743.795 | E4: =IF(I8<>0,C4/I8,0) -> 0.036966574
F6: Целевые показатели
F7: Показатель | I7: План | J7: Факт | K7: % выполнения | L7: Прогноз выполнения | M7: % выполнения по прогнозу | N7: Отклонение | O7: Факт аналогичного месяца прошлого года | P7: Отклонение LFL
F8: Выручка | I8: ='Ялта, Ленина, 18'!I8/График!AJ31*График!AJ29 -> 1940774.8 | J8: =D57 -> 1869031 | K8: =IF(AND(I8<>"",I8<>0,J8<>""),J8/I8,"") -> 0.96303343 | L8: =IF(SUMIF($D$25:$D$56,">=0",$P$25:$P$56)<>0,I8*D57/SUMIF($D$25:$D$56,">=0",$P$25:$P$56),0) -> 1869031 | M8: =IF(AND(I8<>"",I8<>0,L8<>"",L8<>0),L8/I8,"") -> 0.96303343 | N8: =IF(AND(J8<>0,J8<>"",I8<>0,I8<>""),L8-I8,"") -> -71743.795 | P8: =IF(AND(O8<>"",O8<>0,L8<>"",L8<>0),-O8+L8,"") | Q8: =IF(AND(P8<>"",P8<>0,O8<>0,O8<>""),P8/O8,"")
F9: Кол-во изделий | I9: =I8/I11 -> 323.46247 | J9: =E57 -> 296 | K9: =IF(AND(I9<>"",I9<>0,J9<>""),J9/I9,"") -> 0.91509845 | L9: =IF(SUMIF($E$25:$E$54,">=0",$Q$25:$Q$54)<>0,I9*E57/SUMIF($E$25:$E$54,">=0",$Q$25:$Q$54),0) -> 296 | M9: =IF(AND(I9<>"",I9<>0,L9<>"",L9<>0),L9/I9,"") -> 0.91509845 | N9: =IF(AND(J9<>0,J9<>"",I9<>0,I9<>""),L9-I9,"") -> -27.462466 | O9: =O8/O11 -> #DIV/0! | P9: =IF(AND(O9<>"",O9<>0,L9<>"",L9<>0),-O9+L9,"") -> #DIV/0! | Q9: =IF(AND(P9<>"",P9<>0,O9<>0,O9<>""),P9/O9,"") -> #DIV/0!
F10: Средний чек | I10: =I11*I12 -> 10800 | J10: =H57 -> 11059.355 | K10: =IF(AND(I10<>"",I10<>0,J10<>""),J10/I10,"") -> 1.0240144 | L10: =J10 -> 11059.355 | M10: =IF(AND(I10<>"",I10<>0,L10<>"",L10<>0),L10/I10,"") -> 1.0240144 | N10: =IF(AND(J10<>0,J10<>"",I10<>0,I10<>""),L10-I10,"") -> 259.35503 | O10: =O11*O12 -> 0 | P10: =IF(AND(O10<>"",O10<>0,L10<>"",L10<>0),-O10+L10,"") | Q10: =IF(AND(P10<>"",P10<>0,O10<>0,O10<>""),P10/O10,"") | S10: IS | V10: =M23 -> Agafi
F11: Средняя стоимость изделия | I11: ='Ялта, Ленина, 18'!I11 -> 6000 | J11: =F57 -> 6314.2939 | K11: =IF(AND(I11<>"",I11<>0,J11<>""),J11/I11,"") -> 1.0523823 | L11: =IF(L9>0,L8/L9,"") -> 6314.2939 | M11: =IF(AND(I11<>"",I11<>0,L11<>"",L11<>0),L11/I11,"") -> 1.0523823 | N11: =IF(AND(J11<>0,J11<>"",I11<>0,I11<>""),L11-I11,"") -> 314.29392 | P11: =IF(AND(O11<>"",O11<>0,L11<>"",L11<>0),-O11+L11,"") | Q11: =IF(AND(P11<>"",P11<>0,O11<>0,O11<>""),P11/O11,"")
F12: Длина чека | I12: ='Ялта, Ленина, 18'!I12 -> 1.8 | J12: =J57 -> 1.7514793 | K12: =IF(AND(I12<>"",I12<>0,J12<>""),J12/I12,"") -> 0.97304405 | L12: =J12 -> 1.7514793 | M12: =IF(AND(I12<>"",I12<>0,L12<>"",L12<>0),L12/I12,"") -> 0.97304405 | N12: =IF(AND(J12<>0,J12<>"",I12<>0,I12<>""),L12-I12,"") -> -0.04852071 | P12: =IF(AND(O12<>"",O12<>0,L12<>"",L12<>0),-O12+L12,"") | Q12: =IF(AND(P12<>"",P12<>0,O12<>0,O12<>""),P12/O12,"") | S12: ='Ялта, Ленина, 18'!S12*График!AJ29/График!AJ31 -> 285506.85 | T12: =L57 -> 111221 | V12: ='Ялта, Ленина, 18'!V12/График!AJ31*График!AJ29 -> 268712.33 | W12: =M57 -> 125097
F13: Кол-во чеков | I13: =IF(I12<>0,I9/I12,"") -> 179.70137 | J13: =G57 -> 169 | K13: =IF(AND(I13<>"",I13<>0,J13<>""),J13/I13,"") -> 0.94044915 | L13: =IF(SUMIF($G$25:$G$54,">=0",$R$25:$R$54)<>0,I13*G57/SUMIF($G$25:$G$54,">=0",$R$25:$R$54),"") -> 169 | M13: =IF(AND(I13<>"",I13<>0,L13<>"",L13<>0),L13/I13,"") -> 0.94044915 | N13: =IF(AND(J13<>0,J13<>"",I13<>0,I13<>""),L13-I13,"") -> -10.70137 | P13: =IF(AND(O13<>"",O13<>0,L13<>"",L13<>0),-O13+L13,"") | Q13: =IF(AND(P13<>"",P13<>0,O13<>0,O13<>""),P13/O13,"") | S13: =T12/S12 -> 0.38955633 | T13: =S13/J14*I14 -> 0.38955633 | V13: =W12/V12 -> 0.46554247 | W13: =V13/J14*I14 -> 0.46554247
F14: Кол-во смен план/отработано | I14: =График!AI29 -> 30 | J14: 30 | K14: =IF(AND(I14<>"",I14<>0,J14<>""),J14/I14,"") -> 1 | L14: =I14 -> 30 | M14: =IF(AND(I14<>"",I14<>0,L14<>"",L14<>0),L14/I14,"") -> 1 | N14: =IF(AND(J14<>0,J14<>"",I14<>0,I14<>""),L14-I14,"") -> 0 | P14: =IF(AND(O14<>"",O14<>0,L14<>"",L14<>0),-O14+L14,"") | Q14: =IF(AND(P14<>"",P14<>0,O14<>0,O14<>""),P14/O14,"")
F15: Средние продажи в смену | I15: ='Ялта, Ленина, 18'!I15 -> 115560 | J15: =J8/J14 -> 62301.033 | K15: =IF(AND(I15<>"",I15<>0,J15<>""),J15/I15,"") -> 0.53912282 | L15: =J15 -> 62301.033 | M15: =IF(AND(I15<>"",I15<>0,L15<>"",L15<>0),L15/I15,"") -> 0.53912282 | N15: =IF(AND(J15<>0,J15<>"",I15<>0,I15<>""),L15-I15,"") -> -53258.967 | P15: =IF(AND(O15<>"",O15<>0,L15<>"",L15<>0),-O15+L15,"") | Q15: =IF(AND(P15<>"",P15<>0,O15<>0,O15<>""),P15/O15,"")
F16: Отставание/Перевыполнение | J16: =J8-I15*J14 -> -1597769 | K16: =IF(AND(I16<>"",I16<>0,J16<>""),J16/I16,"") | L16: =J16 -> -1597769 | M16: =IF(AND(I16<>"",I16<>0,L16<>"",L16<>0),L16/I16,"") | N16: =IF(AND(J16<>0,J16<>"",I16<>0,I16<>""),L16-I16,"") | P16: =IF(AND(O16<>"",O16<>0,L16<>"",L16<>0),-O16+L16,"") | Q16: =IF(AND(P16<>"",P16<>0,O16<>0,O16<>""),P16/O16,"") | S16: UNOde50
F17: Трафик | I17: ='Ялта, Ленина, 18'!I17/График!AJ31*График!AJ29 -> 1198.0091 | J17: =I57 -> 1279.5 | K17: =IF(AND(I17<>"",I17<>0,J17<>""),J17/I17,"") -> 1.0680219 | L17: =J17/J14*I14 -> 1279.5 | M17: =IF(AND(I17<>"",I17<>0,L17<>"",L17<>0),L17/I17,"") -> 1.0680219 | N17: =IF(AND(J17<>0,J17<>"",I17<>0,I17<>""),L17-I17,"") -> 81.490868 | P17: =IF(AND(O17<>"",O17<>0,L17<>"",L17<>0),-O17+L17,"") | Q17: =IF(AND(P17<>"",P17<>0,O17<>0,O17<>""),P17/O17,"")
K18: =IF(AND(I18<>"",I18<>0,J18<>""),J18/I18,"") | L18: =J18 -> 0 | M18: =IF(AND(I18<>"",I18<>0,L18<>"",L18<>0),L18/I18,"") | N18: =IF(AND(J18<>0,J18<>"",I18<>0,I18<>""),L18-I18,"") | O18: 0 | P18: =IF(AND(O18<>"",O18<>0,L18<>"",L18<>0),-O18+L18,"") | Q18: =IF(AND(P18<>"",P18<>0,O18<>0,O18<>""),P18/O18,"") | S18: ='Ялта, Ленина, 18'!S18*График!AJ29/График!AJ31 -> 571013.7 | T18: =K57 -> 402662
K19: =IF(AND(I19<>"",I19<>0,J19<>""),J19/I19,"") | L19: =J19 -> 0 | M19: =IF(AND(I19<>"",I19<>0,L19<>"",L19<>0),L19/I19,"") | N19: =IF(AND(J19<>0,J19<>"",I19<>0,I19<>""),L19-I19,"") | O19: 0 | P19: =IF(AND(O19<>"",O19<>0,L19<>"",L19<>0),-O19+L19,"") | Q19: =IF(AND(P19<>"",P19<>0,O19<>0,O19<>""),P19/O19,"") | S19: =T18/S18 -> 0.70517047 | T19: =S19/J14*I14 -> 0.70517047
F20: Конверсия план/факт | I20: ='Ялта, Ленина, 18'!I20 -> 0.15 | J20: =N57 -> 0.13208284 | K20: =J20/I20 -> 0.8805523 | L20: =IF(AND(K8<>0,I14<>0,I57<>0),(I57*N57+(I57/K8-I57)*I20)/(I57/K8),0) -> 0.13274518 | M20: =IF(AND(I20<>"",I20<>0,L20<>"",L20<>0),L20/I20,"") -> 0.88496787 | N20: =IF(AND(J20<>0,J20<>"",I20<>0,I20<>""),L20-I20,"") -> -0.017254819 | P20: =IF(AND(O20<>"",O20<>0,L20<>"",L20<>0),-O20+L20,"") | Q20: =IF(AND(P20<>"",P20<>0,O20<>0,O20<>""),P20/O20,"")
B22: Факт продаж за месяц | O22: % выполнения дневного плана | P22: Раcпределение плана по дням
B23: Дата | C23: День недели | D23: Выручка (руб) | E23: Кол-во единиц (шт.) | F23: Средняя стоимость изделия (руб.) | G23: Количество чеков (шт.) | H23: Средняя сумма чека (руб.) | I23: Трафик | J23: Длина чека (шт.) | K23: UNOde50 | L23: IS | M23: Agafi | N23: Конверсия (%) | P23: выручка, план | Q23: кол-во ед, план | R23: Кол-во чеков, план | S23: выручка, скорректир.план | T23: кол-во ед, скорр. план | U23: кол-во чеков, скорр. план | V23: Коэфф. Дня Недели | W23: Специфика месяца
B24: 1 | C24: 2 | D24: 3 | E24: 4 | F24: 5 | G24: 6 | H24: 7 | I24: 8 | J24: 9 | K24: 10 | L24: 11 | M24: 12 | N24: 13 | P24: 1 | Q24: 2 | R24: 3 | S24: 4 | T24: 5 | U24: 6 | V24: 10 | W24: 11
A25: 1 | B25: 45901 | C25: пн | D25: =8592+36205 -> 44797 | E25: 7 | F25: =IF(AND(E25<>"",E25<>0),D25/E25,"") -> 6399.5714 | G25: 4 | H25: =IF(AND(G25<>"",G25<>0),D25/G25,"") -> 11199.25 | I25: 50 | J25: =IF(AND(G25<>"",G25<>0),E25/G25,"") -> 1.75 | K25: 8592 | N25: =IF(AND(I25<>"",I25<>0),G25/I25,"") -> 0.08 | O25: =D25/P25 -> 0.57705047 | P25: =$I$8*V25*W25/SUMPRODUCT($W$25:$W$56,$V$25:$V$56) -> 77630.992 | Q25: =$I$9*V25*W25/SUMPRODUCT($W$25:$W$56,$V$25:$V$56) -> 12.938499 | R25: =IF($I$12="","",Q25/$I$12) -> 7.1880548 | S25: =IF(D25<>"",D25,P25) -> 44797 | T25: =IF(E25<>"",E25,Q25) -> 7 | U25: =IF(G25<>"",G25,R25) -> 4 | V25: 1 | W25: 1
A26: 2 | B26: 45902 | C26: вт | D26: =13590+10690+42784 -> 67064 | E26: 11 | F26: =IF(AND(E26<>"",E26<>0),D26/E26,"") -> 6096.7273 | G26: 7 | H26: =IF(AND(G26<>"",G26<>0),D26/G26,"") -> 9580.5714 | I26: 40 | J26: =IF(AND(G26<>"",G26<>0),E26/G26,"") -> 1.5714286 | K26: 10690 | M26: 13590 | N26: =IF(AND(I26<>"",I26<>0),G26/I26,"") -> 0.175 | O26: =D26/P26 -> 0.86388179 | P26: =$I$8*V26*W26/SUMPRODUCT($W$25:$W$56,$V$25:$V$56) -> 77630.992 | Q26: =$I$9*V26*W26/SUMPRODUCT($W$25:$W$58,$V$25:$V$58) -> 12.938499 | R26: =IF($I$12="","",Q26/$I$12) -> 7.1880548 | S26: =IF(W26<>"",IF(D26<>"",D26,($I$8-SUM($S$25:S25))*V26*W26/SUMPRODUCT($W26:$W$56,$V26:$V$56)),"") -> 67064 | T26: =IF(W26<>"",IF(E26<>"",E26,($I$9-SUM($T$25:T25))*V26*W26/SUMPRODUCT($W26:$W$58,$V26:$V$58)),"") -> 11 | U26: =IF(W26<>"",IF($I$12<>"",IF(G26<>"",G26,($I$9/$I$12-SUM($U$25:U25))*V26*W26/SUMPRODUCT($W26:$W$58,$V26:$V$58)),""),"") -> 7 | V26: 1 | W26: 1
A27: 3 | B27: 45903 | C27: ср | D27: =35475+36942 -> 72417 | E27: 10 | F27: =IF(AND(E27<>"",E27<>0),D27/E27,"") -> 7241.7 | G27: 7 | H27: =IF(AND(G27<>"",G27<>0),D27/G27,"") -> 10345.286 | I27: 35 | J27: =IF(AND(G27<>"",G27<>0),E27/G27,"") -> 1.4285714 | K27: 35475 | N27: =IF(AND(I27<>"",I27<>0),G27/I27,"") -> 0.2 | O27: =D27/P27 -> 0.93283621 | P27: =$I$8*V27*W27/SUMPRODUCT($W$25:$W$56,$V$25:$V$56) -> 77630.992 | Q27: =$I$9*V27*W27/SUMPRODUCT($W$25:$W$58,$V$25:$V$58) -> 12.938499 | R27: =IF($I$12="","",Q27/$I$12) -> 7.1880548 | S27: =IF(W27<>"",IF(D27<>"",D27,($I$8-SUM($S$25:S26))*V27*W27/SUMPRODUCT($W27:$W$58,$V27:$V$58)),"") -> 72417 | T27: =IF(W27<>"",IF(E27<>"",E27,($I$9-SUM($T$25:T26))*V27*W27/SUMPRODUCT($W27:$W$58,$V27:$V$58)),"") -> 10 | U27: =IF(W27<>"",IF($I$12<>"",IF(G27<>"",G27,($I$9/$I$12-SUM($U$25:U26))*V27*W27/SUMPRODUCT($W27:$W$58,$V27:$V$58)),""),"") -> 7 | V27: 1 | W27: 1
A28: 4 | B28: 45904 | C28: чт | D28: =55851+7492+51423 -> 114766 | E28: 16 | F28: =IF(AND(E28<>"",E28<>0),D28/E28,"") -> 7172.875 | G28: 11 | H28: =IF(AND(G28<>"",G28<>0),D28/G28,"") -> 10433.273 | I28: 86 | J28: =IF(AND(G28<>"",G28<>0),E28/G28,"") -> 1.4545455 | K28: 55851 | M28: 7492 | N28: =IF(AND(I28<>"",I28<>0),G28/I28,"") -> 0.12790698 | O28: =D28/P28 -> 1.4783529 | P28: =$I$8*V28*W28/SUMPRODUCT($W$25:$W$56,$V$25:$V$56) -> 77630.992 | Q28: =$I$9*V28*W28/SUMPRODUCT($W$25:$W$58,$V$25:$V$58) -> 12.938499 | R28: =IF($I$12="","",Q28/$I$12) -> 7.1880548 | S28: =IF(W28<>"",IF(D28<>"",D28,($I$8-SUM($S$25:S27))*V28*W28/SUMPRODUCT($W28:$W$58,$V28:$V$58)),"") -> 114766 | T28: =IF(W28<>"",IF(E28<>"",E28,($I$9-SUM($T$25:T27))*V28*W28/SUMPRODUCT($W28:$W$58,$V28:$V$58)),"") -> 16 | U28: =IF(W28<>"",IF($I$12<>"",IF(G28<>"",G28,($I$9/$I$12-SUM($U$25:U27))*V28*W28/SUMPRODUCT($W28:$W$58,$V28:$V$58)),""),"") -> 11 | V28: 1 | W28: 1
A29: 5 | B29: 45905 | C29: пт | D29: =16476+9903 -> 26379 | E29: 4 | F29: =IF(AND(E29<>"",E29<>0),D29/E29,"") -> 6594.75 | G29: 4 | H29: =IF(AND(G29<>"",G29<>0),D29/G29,"") -> 6594.75 | I29: 26 | J29: =IF(AND(G29<>"",G29<>0),E29/G29,"") -> 1 | L29: 9903 | N29: =IF(AND(I29<>"",I29<>0),G29/I29,"") -> 0.15384615 | O29: =D29/P29 -> 0.33979986 | P29: =$I$8*V29*W29/SUMPRODUCT($W$25:$W$56,$V$25:$V$56) -> 77630.992 | Q29: =$I$9*V29*W29/SUMPRODUCT($W$25:$W$58,$V$25:$V$58) -> 12.938499 | R29: =IF($I$12="","",Q29/$I$12) -> 7.1880548 | S29: =IF(W29<>"",IF(D29<>"",D29,($I$8-SUM($S$25:S28))*V29*W29/SUMPRODUCT($W29:$W$58,$V29:$V$58)),"") -> 26379 | T29: =IF(W29<>"",IF(E29<>"",E29,($I$9-SUM($T$25:T28))*V29*W29/SUMPRODUCT($W29:$W$58,$V29:$V$58)),"") -> 4 | U29: =IF(W29<>"",IF($I$12<>"",IF(G29<>"",G29,($I$9/$I$12-SUM($U$25:U28))*V29*W29/SUMPRODUCT($W29:$W$58,$V29:$V$58)),""),"") -> 4 | V29: 1 | W29: 1
A30: 6 | B30: 45906 | C30: сб | D30: 27581 | E30: 6 | F30: =IF(AND(E30<>"",E30<>0),D30/E30,"") -> 4596.8333 | G30: 3 | H30: =IF(AND(G30<>"",G30<>0),D30/G30,"") -> 9193.6667 | I30: 27 | J30: =IF(AND(G30<>"",G30<>0),E30/G30,"") -> 2 | N30: =IF(AND(I30<>"",I30<>0),G30/I30,"") -> 0.11111111 | O30: =D30/P30 -> 0.35528337 | P30: =$I$8*V30*W30/SUMPRODUCT($W$25:$W$56,$V$25:$V$56) -> 77630.992 | Q30: =$I$9*V30*W30/SUMPRODUCT($W$25:$W$58,$V$25:$V$58) -> 12.938499 | R30: =IF($I$12="","",Q30/$I$12) -> 7.1880548 | S30: =IF(W30<>"",IF(D30<>"",D30,($I$8-SUM($S$25:S29))*V30*W30/SUMPRODUCT($W30:$W$58,$V30:$V$58)),"") -> 27581 | T30: =IF(W30<>"",IF(E30<>"",E30,($I$9-SUM($T$25:T29))*V30*W30/SUMPRODUCT($W30:$W$58,$V30:$V$58)),"") -> 6 | U30: =IF(W30<>"",IF($I$12<>"",IF(G30<>"",G30,($I$9/$I$12-SUM($U$25:U29))*V30*W30/SUMPRODUCT($W30:$W$58,$V30:$V$58)),""),"") -> 3 | V30: 1 | W30: 1
A31: 7 | B31: 45907 | C31: вс | D31: 19075 | E31: 3 | F31: =IF(AND(E31<>"",E31<>0),D31/E31,"") -> 6358.3333 | G31: 2 | H31: =IF(AND(G31<>"",G31<>0),D31/G31,"") -> 9537.5 | I31: 20 | J31: =IF(AND(G31<>"",G31<>0),E31/G31,"") -> 1.5 | N31: =IF(AND(I31<>"",I31<>0),G31/I31,"") -> 0.1 | O31: =D31/P31 -> 0.24571372 | P31: =$I$8*V31*W31/SUMPRODUCT($W$25:$W$56,$V$25:$V$56) -> 77630.992 | Q31: =$I$9*V31*W31/SUMPRODUCT($W$25:$W$58,$V$25:$V$58) -> 12.938499 | R31: =IF($I$12="","",Q31/$I$12) -> 7.1880548 | S31: =IF(W31<>"",IF(D31<>"",D31,($I$8-SUM($S$25:S30))*V31*W31/SUMPRODUCT($W31:$W$58,$V31:$V$58)),"") -> 19075 | T31: =IF(W31<>"",IF(E31<>"",E31,($I$9-SUM($T$25:T30))*V31*W31/SUMPRODUCT($W31:$W$58,$V31:$V$58)),"") -> 3 | U31: =IF(W31<>"",IF($I$12<>"",IF(G31<>"",G31,($I$9/$I$12-SUM($U$25:U30))*V31*W31/SUMPRODUCT($W31:$W$58,$V31:$V$58)),""),"") -> 2 | V31: 1 | W31: 1
A32: 8 | B32: 45908 | C32: пн | D32: =10903+65862 -> 76765 | E32: 14 | F32: =IF(AND(E32<>"",E32<>0),D32/E32,"") -> 5483.2143 | G32: 7 | H32: =IF(AND(G32<>"",G32<>0),D32/G32,"") -> 10966.429 | I32: 45 | J32: =IF(AND(G32<>"",G32<>0),E32/G32,"") -> 2 | L32: 10903 | N32: =IF(AND(I32<>"",I32<>0),G32/I32,"") -> 0.15555556 | O32: =D32/P32 -> 0.98884477 | P32: =$I$8*V32*W32/SUMPRODUCT($W$25:$W$56,$V$25:$V$56) -> 77630.992 | Q32: =$I$9*V32*W32/SUMPRODUCT($W$25:$W$58,$V$25:$V$58) -> 12.938499 | R32: =IF($I$12="","",Q32/$I$12) -> 7.1880548 | S32: =IF(W32<>"",IF(D32<>"",D32,($I$8-SUM($S$25:S31))*V32*W32/SUMPRODUCT($W32:$W$58,$V32:$V$58)),"") -> 76765 | T32: =IF(W32<>"",IF(E32<>"",E32,($I$9-SUM($T$25:T31))*V32*W32/SUMPRODUCT($W32:$W$58,$V32:$V$58)),"") -> 14 | U32: =IF(W32<>"",IF($I$12<>"",IF(G32<>"",G32,($I$9/$I$12-SUM($U$25:U31))*V32*W32/SUMPRODUCT($W32:$W$58,$V32:$V$58)),""),"") -> 7 | V32: 1 | W32: 1
A33: 9 | B33: 45909 | C33: вт | D33: =24992+23902+65099 -> 113993 | E33: 17 | F33: =IF(AND(E33<>"",E33<>0),D33/E33,"") -> 6705.4706 | G33: 13 | H33: =IF(AND(G33<>"",G33<>0),D33/G33,"") -> 8768.6923 | I33: 80 | J33: =IF(AND(G33<>"",G33<>0),E33/G33,"") -> 1.3076923 | K33: 24992 | L33: 23902 | N33: =IF(AND(I33<>"",I33<>0),G33/I33,"") -> 0.1625 | O33: =D33/P33 -> 1.4683955 | P33: =$I$8*V33*W33/SUMPRODUCT($W$25:$W$56,$V$25:$V$56) -> 77630.992 | Q33: =$I$9*V33*W33/SUMPRODUCT($W$25:$W$58,$V$25:$V$58) -> 12.938499 | R33: =IF($I$12="","",Q33/$I$12) -> 7.1880548 | S33: =IF(W33<>"",IF(D33<>"",D33,($I$8-SUM($S$25:S32))*V33*W33/SUMPRODUCT($W33:$W$58,$V33:$V$58)),"") -> 113993 | T33: =IF(W33<>"",IF(E33<>"",E33,($I$9-SUM($T$25:T32))*V33*W33/SUMPRODUCT($W33:$W$58,$V33:$V$58)),"") -> 17 | U33: =IF(W33<>"",IF($I$12<>"",IF(G33<>"",G33,($I$9/$I$12-SUM($U$25:U32))*V33*W33/SUMPRODUCT($W33:$W$58,$V33:$V$58)),""),"") -> 13 | V33: 1 | W33: 1
A34: 10 | B34: 45910 | C34: ср | D34: =7990+28243 -> 36233 | E34: 9 | F34: =IF(AND(E34<>"",E34<>0),D34/E34,"") -> 4025.8889 | G34: 4 | H34: =IF(AND(G34<>"",G34<>0),D34/G34,"") -> 9058.25 | I34: =74/2 -> 37 | J34: =IF(AND(G34<>"",G34<>0),E34/G34,"") -> 2.25 | K34: 7990 | N34: =IF(AND(I34<>"",I34<>0),G34/I34,"") -> 0.10810811 | O34: =D34/P34 -> 0.4667337 | P34: =$I$8*V34*W34/SUMPRODUCT($W$25:$W$56,$V$25:$V$56) -> 77630.992 | Q34: =$I$9*V34*W34/SUMPRODUCT($W$25:$W$58,$V$25:$V$58) -> 12.938499 | R34: =IF($I$12="","",Q34/$I$12) -> 7.1880548 | S34: =IF(W34<>"",IF(D34<>"",D34,($I$8-SUM($S$25:S33))*V34*W34/SUMPRODUCT($W34:$W$58,$V34:$V$58)),"") -> 36233 | T34: =IF(W34<>"",IF(E34<>"",E34,($I$9-SUM($T$25:T33))*V34*W34/SUMPRODUCT($W34:$W$58,$V34:$V$58)),"") -> 9 | U34: =IF(W34<>"",IF($I$12<>"",IF(G34<>"",G34,($I$9/$I$12-SUM($U$25:U33))*V34*W34/SUMPRODUCT($W34:$W$58,$V34:$V$58)),""),"") -> 4 | V34: 1 | W34: 1
A35: 11 | B35: 45911 | C35: чт | D35: 35549 | E35: 6 | F35: =IF(AND(E35<>"",E35<>0),D35/E35,"") -> 5924.8333 | G35: 3 | H35: =IF(AND(G35<>"",G35<>0),D35/G35,"") -> 11849.667 | I35: =79/2 -> 39.5 | J35: =IF(AND(G35<>"",G35<>0),E35/G35,"") -> 2 | N35: =IF(AND(I35<>"",I35<>0),G35/I35,"") -> 0.075949367 | O35: =D35/P35 -> 0.45792279 | P35: =$I$8*V35*W35/SUMPRODUCT($W$25:$W$56,$V$25:$V$56) -> 77630.992 | Q35: =$I$9*V35*W35/SUMPRODUCT($W$25:$W$58,$V$25:$V$58) -> 12.938499 | R35: =IF($I$12="","",Q35/$I$12) -> 7.1880548 | S35: =IF(W35<>"",IF(D35<>"",D35,($I$8-SUM($S$25:S34))*V35*W35/SUMPRODUCT($W35:$W$58,$V35:$V$58)),"") -> 35549 | T35: =IF(W35<>"",IF(E34<>"",E34,($I$9-SUM($T$25:T34))*V35*W35/SUMPRODUCT($W35:$W$58,$V35:$V$58)),"") -> 9 | U35: =IF(W35<>"",IF($I$12<>"",IF(G35<>"",G35,($I$9/$I$12-SUM($U$25:U34))*V35*W35/SUMPRODUCT($W35:$W$58,$V35:$V$58)),""),"") -> 3 | V35: 1 | W35: 1
A36: 11 | B36: 45912 | C36: пт | D36: =109604+20000+32175+102415 -> 264194 | E36: 31 | F36: =IF(AND(E36<>"",E36<>0),D36/E36,"") -> 8522.3871 | G36: 20 | H36: =IF(AND(G36<>"",G36<>0),D36/G36,"") -> 13209.7 | I36: 131 | J36: =IF(AND(G36<>"",G36<>0),E36/G36,"") -> 1.55 | K36: 109604 | L36: 20000 | M36: 32175 | N36: =IF(AND(I36<>"",I36<>0),G36/I36,"") -> 0.15267176 | O36: =D36/P36 -> 3.4032027 | P36: =$I$8*V36*W36/SUMPRODUCT($W$25:$W$56,$V$25:$V$56) -> 77630.992 | Q36: =$I$9*V36*W36/SUMPRODUCT($W$25:$W$58,$V$25:$V$58) -> 12.938499 | R36: =IF($I$12="","",Q36/$I$12) -> 7.1880548 | S36: =IF(W36<>"",IF(D36<>"",D36,($I$8-SUM($S$25:S35))*V36*W36/SUMPRODUCT($W36:$W$58,$V36:$V$58)),"") -> 264194 | T36: =IF(W36<>"",IF(E35<>"",E35,($I$9-SUM($T$25:T35))*V36*W36/SUMPRODUCT($W36:$W$58,$V36:$V$58)),"") -> 6 | U36: =IF(W36<>"",IF($I$12<>"",IF(G36<>"",G36,($I$9/$I$12-SUM($U$25:U35))*V36*W36/SUMPRODUCT($W36:$W$58,$V36:$V$58)),""),"") -> 20 | V36: 1 | W36: 1
A37: 13 | B37: 45913 | C37: сб | D37: =7992+53126 -> 61118 | E37: 12 | F37: =IF(AND(E37<>"",E37<>0),D37/E37,"") -> 5093.1667 | G37: 7 | H37: =IF(AND(G37<>"",G37<>0),D37/G37,"") -> 8731.1429 | I37: =93/2 -> 46.5 | J37: =IF(AND(G37<>"",G37<>0),E37/G37,"") -> 1.7142857 | K37: 7992 | N37: =IF(AND(I37<>"",I37<>0),G37/I37,"") -> 0.15053763 | O37: =D37/P37 -> 0.78728867 | P37: =$I$8*V37*W37/SUMPRODUCT($W$25:$W$56,$V$25:$V$56) -> 77630.992 | Q37: =$I$9*V37*W37/SUMPRODUCT($W$25:$W$58,$V$25:$V$58) -> 12.938499 | R37: =IF($I$12="","",Q37/$I$12) -> 7.1880548 | S37: =IF(W37<>"",IF(D37<>"",D37,($I$8-SUM($S$25:S36))*V37*W37/SUMPRODUCT($W37:$W$58,$V37:$V$58)),"") -> 61118 | T37: =IF(W37<>"",IF(E37<>"",E37,($I$9-SUM($T$25:T36))*V37*W37/SUMPRODUCT($W37:$W$58,$V37:$V$58)),"") -> 12 | U37: =IF(W37<>"",IF($I$12<>"",IF(G37<>"",G37,($I$9/$I$12-SUM($U$25:U36))*V37*W37/SUMPRODUCT($W37:$W$58,$V37:$V$58)),""),"") -> 7 | V37: 1 | W37: 1
A38: 14 | B38: 45914 | C38: вс | D38: 62462 | E38: 10 | F38: =IF(AND(E38<>"",E38<>0),D38/E38,"") -> 6246.2 | G38: 7 | H38: =IF(AND(G38<>"",G38<>0),D38/G38,"") -> 8923.1429 | I38: =7+92/2 -> 53 | J38: =IF(AND(G38<>"",G38<>0),E38/G38,"") -> 1.4285714 | K38: 11637 | N38: =IF(AND(I38<>"",I38<>0),G38/I38,"") -> 0.13207547 | O38: =D38/P38 -> 0.80460134 | P38: =$I$8*V38*W38/SUMPRODUCT($W$25:$W$56,$V$25:$V$56) -> 77630.992 | Q38: =$I$9*V38*W38/SUMPRODUCT($W$25:$W$58,$V$25:$V$58) -> 12.938499 | R38: =IF($I$12="","",Q38/$I$12) -> 7.1880548 | S38: =IF(W38<>"",IF(D38<>"",D38,($I$8-SUM($S$25:S37))*V38*W38/SUMPRODUCT($W38:$W$58,$V38:$V$58)),"") -> 62462 | T38: =IF(W38<>"",IF(E38<>"",E38,($I$9-SUM($T$25:T37))*V38*W38/SUMPRODUCT($W38:$W$58,$V38:$V$58)),"") -> 10 | U38: =IF(W38<>"",IF($I$12<>"",IF(G38<>"",G38,($I$9/$I$12-SUM($U$25:U37))*V38*W38/SUMPRODUCT($W38:$W$58,$V38:$V$58)),""),"") -> 7 | V38: 1 | W38: 1
A39: 15 | B39: 45915 | C39: пн | D39: 14503 | E39: 1 | F39: =IF(AND(E39<>"",E39<>0),D39/E39,"") -> 14503 | G39: 1 | H39: =IF(AND(G39<>"",G39<>0),D39/G39,"") -> 14503 | I39: =41/2 -> 20.5 | J39: =IF(AND(G39<>"",G39<>0),E39/G39,"") -> 1 | L39: 14503 | N39: =IF(AND(I39<>"",I39<>0),G39/I39,"") -> 0.048780488 | O39: =D39/P39 -> 0.18681972 | P39: =$I$8*V39*W39/SUMPRODUCT($W$25:$W$56,$V$25:$V$56) -> 77630.992 | Q39: =$I$9*V39*W39/SUMPRODUCT($W$25:$W$58,$V$25:$V$58) -> 12.938499 | R39: =IF($I$12="","",Q39/$I$12) -> 7.1880548 | S39: =IF(W39<>"",IF(D39<>"",D39,($I$8-SUM($S$25:S38))*V39*W39/SUMPRODUCT($W39:$W$58,$V39:$V$58)),"") -> 14503 | T39: =IF(W39<>"",IF(E39<>"",E39,($I$9-SUM($T$25:T38))*V39*W39/SUMPRODUCT($W39:$W$58,$V39:$V$58)),"") -> 1 | U39: =IF(W39<>"",IF($I$12<>"",IF(G39<>"",G39,($I$9/$I$12-SUM($U$25:U38))*V39*W39/SUMPRODUCT($W39:$W$58,$V39:$V$58)),""),"") -> 1 | V39: 1 | W39: 1
A40: 16 | B40: 45916 | C40: вт | D40: 17275 | E40: 3 | F40: =IF(AND(E40<>"",E40<>0),D40/E40,"") -> 5758.3333 | G40: 2 | H40: =IF(AND(G40<>"",G40<>0),D40/G40,"") -> 8637.5 | I40: =74/2 -> 37 | J40: =IF(AND(G40<>"",G40<>0),E40/G40,"") -> 1.5 | N40: =IF(AND(I40<>"",I40<>0),G40/I40,"") -> 0.054054054 | O40: =D40/P40 -> 0.22252711 | P40: =$I$8*V40*W40/SUMPRODUCT($W$25:$W$56,$V$25:$V$56) -> 77630.992 | Q40: =$I$9*V40*W40/SUMPRODUCT($W$25:$W$58,$V$25:$V$58) -> 12.938499 | R40: =IF($I$12="","",Q40/$I$12) -> 7.1880548 | S40: =IF(W40<>"",IF(D40<>"",D40,($I$8-SUM($S$25:S39))*V40*W40/SUMPRODUCT($W40:$W$58,$V40:$V$58)),"") -> 17275 | T40: =IF(W40<>"",IF(E40<>"",E40,($I$9-SUM($T$25:T39))*V40*W40/SUMPRODUCT($W40:$W$58,$V40:$V$58)),"") -> 3 | U40: =IF(W40<>"",IF($I$12<>"",IF(G40<>"",G40,($I$9/$I$12-SUM($U$25:U39))*V40*W40/SUMPRODUCT($W40:$W$58,$V40:$V$58)),""),"") -> 2 | V40: 1 | W40: 1
A41: 17 | B41: 45917 | C41: ср | D41: =8992+70868 -> 79860 | E41: 15 | F41: =IF(AND(E41<>"",E41<>0),D41/E41,"") -> 5324 | G41: 6 | H41: =IF(AND(G41<>"",G41<>0),D41/G41,"") -> 13310 | I41: 70 | J41: =IF(AND(G41<>"",G41<>0),E41/G41,"") -> 2.5 | K41: 8992 | N41: =IF(AND(I41<>"",I41<>0),G41/I41,"") -> 0.085714286 | O41: =D41/P41 -> 1.0287129 | P41: =$I$8*V41*W41/SUMPRODUCT($W$25:$W$56,$V$25:$V$56) -> 77630.992 | Q41: =$I$9*V41*W41/SUMPRODUCT($W$25:$W$58,$V$25:$V$58) -> 12.938499 | R41: =IF($I$12="","",Q41/$I$12) -> 7.1880548 | S41: =IF(W41<>"",IF(D41<>"",D41,($I$8-SUM($S$25:S40))*V41*W41/SUMPRODUCT($W41:$W$58,$V41:$V$58)),"") -> 79860 | T41: =IF(W41<>"",IF(E41<>"",E41,($I$9-SUM($T$25:T40))*V41*W41/SUMPRODUCT($W41:$W$58,$V41:$V$58)),"") -> 15 | U41: =IF(W41<>"",IF($I$12<>"",IF(G41<>"",G41,($I$9/$I$12-SUM($U$25:U40))*V41*W41/SUMPRODUCT($W41:$W$58,$V41:$V$58)),""),"") -> 6 | V41: 1 | W41: 1
A42: 18 | B42: 45918 | C42: чт | D42: 48423 | E42: 9 | F42: =IF(AND(E42<>"",E42<>0),D42/E42,"") -> 5380.3333 | G42: 4 | H42: =IF(AND(G42<>"",G42<>0),D42/G42,"") -> 12105.75 | I42: 29 | J42: =IF(AND(G42<>"",G42<>0),E42/G42,"") -> 2.25 | N42: =IF(AND(I42<>"",I42<>0),G42/I42,"") -> 0.13793103 | O42: =D42/P42 -> 0.62375862 | P42: =$I$8*V42*W42/SUMPRODUCT($W$25:$W$56,$V$25:$V$56) -> 77630.992 | Q42: =$I$9*V42*W42/SUMPRODUCT($W$25:$W$58,$V$25:$V$58) -> 12.938499 | R42: =IF($I$12="","",Q42/$I$12) -> 7.1880548 | S42: =IF(W42<>"",IF(D42<>"",D42,($I$8-SUM($S$25:S41))*V42*W42/SUMPRODUCT($W42:$W$58,$V42:$V$58)),"") -> 48423 | T42: =IF(W42<>"",IF(E42<>"",E42,($I$9-SUM($T$25:T41))*V42*W42/SUMPRODUCT($W42:$W$58,$V42:$V$58)),"") -> 9 | U42: =IF(W42<>"",IF($I$12<>"",IF(G42<>"",G42,($I$9/$I$12-SUM($U$25:U41))*V42*W42/SUMPRODUCT($W42:$W$58,$V42:$V$58)),""),"") -> 4 | V42: 1 | W42: 1
A43: 19 | B43: 45919 | C43: пт | D43: =27473+84278 -> 111751 | E43: 22 | F43: =IF(AND(E43<>"",E43<>0),D43/E43,"") -> 5079.5909 | G43: 8 | H43: =IF(AND(G43<>"",G43<>0),D43/G43,"") -> 13968.875 | I43: 60 | J43: =IF(AND(G43<>"",G43<>0),E43/G43,"") -> 2.75 | M43: 27473 | N43: =IF(AND(I43<>"",I43<>0),G43/I43,"") -> 0.13333333 | O43: =D43/P43 -> 1.4395153 | P43: =$I$8*V43*W43/SUMPRODUCT($W$25:$W$56,$V$25:$V$56) -> 77630.992 | Q43: =$I$9*V43*W43/SUMPRODUCT($W$25:$W$58,$V$25:$V$58) -> 12.938499 | R43: =IF($I$12="","",Q43/$I$12) -> 7.1880548 | S43: =IF(W43<>"",IF(D43<>"",D43,($I$8-SUM($S$25:S42))*V43*W43/SUMPRODUCT($W43:$W$58,$V43:$V$58)),"") -> 111751 | T43: =IF(W43<>"",IF(E43<>"",E43,($I$9-SUM($T$25:T42))*V43*W43/SUMPRODUCT($W43:$W$58,$V43:$V$58)),"") -> 22 | U43: =IF(W43<>"",IF($I$12<>"",IF(G43<>"",G43,($I$9/$I$12-SUM($U$25:U42))*V43*W43/SUMPRODUCT($W43:$W$58,$V43:$V$58)),""),"") -> 8 | V43: 1 | W43: 1
A44: 20 | B44: 45920 | C44: сб | D44: =10990+31275+22767 -> 65032 | E44: 8 | F44: =IF(AND(E44<>"",E44<>0),D44/E44,"") -> 8129 | G44: 4 | H44: =IF(AND(G44<>"",G44<>0),D44/G44,"") -> 16258 | I44: 27 | J44: =IF(AND(G44<>"",G44<>0),E44/G44,"") -> 2 | K44: 10990 | M44: 31275 | N44: =IF(AND(I44<>"",I44<>0),G44/I44,"") -> 0.14814815 | O44: =D44/P44 -> 0.83770667 | P44: =$I$8*V44*W44/SUMPRODUCT($W$25:$W$56,$V$25:$V$56) -> 77630.992 | Q44: =$I$9*V44*W44/SUMPRODUCT($W$25:$W$58,$V$25:$V$58) -> 12.938499 | R44: =IF($I$12="","",Q44/$I$12) -> 7.1880548 | S44: =IF(W44<>"",IF(D44<>"",D44,($I$8-SUM($S$25:S43))*V44*W44/SUMPRODUCT($W44:$W$58,$V44:$V$58)),"") -> 65032 | T44: =IF(W44<>"",IF(E44<>"",E44,($I$9-SUM($T$25:T43))*V44*W44/SUMPRODUCT($W44:$W$58,$V44:$V$58)),"") -> 8 | U44: =IF(W44<>"",IF($I$12<>"",IF(G44<>"",G44,($I$9/$I$12-SUM($U$25:U43))*V44*W44/SUMPRODUCT($W44:$W$58,$V44:$V$58)),""),"") -> 4 | V44: 1 | W44: 1
A45: 21 | B45: 45921 | C45: вс | D45: 47840 | E45: 8 | F45: =IF(AND(E45<>"",E45<>0),D45/E45,"") -> 5980 | G45: 5 | H45: =IF(AND(G45<>"",G45<>0),D45/G45,"") -> 9568 | I45: 28 | J45: =IF(AND(G45<>"",G45<>0),E45/G45,"") -> 1.6 | K45: 15990 | L45: 6801 | N45: =IF(AND(I45<>"",I45<>0),G45/I45,"") -> 0.17857143 | O45: =D45/P45 -> 0.61624873 | P45: =$I$8*V45*W45/SUMPRODUCT($W$25:$W$56,$V$25:$V$56) -> 77630.992 | Q45: =$I$9*V45*W45/SUMPRODUCT($W$25:$W$58,$V$25:$V$58) -> 12.938499 | R45: =IF($I$12="","",Q45/$I$12) -> 7.1880548 | S45: =IF(W45<>"",IF(D45<>"",D45,($I$8-SUM($S$25:S44))*V45*W45/SUMPRODUCT($W45:$W$58,$V45:$V$58)),"") -> 47840 | T45: =IF(W45<>"",IF(E45<>"",E45,($I$9-SUM($T$25:T44))*V45*W45/SUMPRODUCT($W45:$W$58,$V45:$V$58)),"") -> 8 | U45: =IF(W45<>"",IF($I$12<>"",IF(G45<>"",G45,($I$9/$I$12-SUM($U$25:U44))*V45*W45/SUMPRODUCT($W45:$W$58,$V45:$V$58)),""),"") -> 5 | V45: 1 | W45: 1
A46: 22 | B46: 45922 | C46: пн | D46: =25583+85170 -> 110753 | E46: 17 | F46: =IF(AND(E46<>"",E46<>0),D46/E46,"") -> 6514.8824 | G46: 6 | H46: =IF(AND(G46<>"",G46<>0),D46/G46,"") -> 18458.833 | I46: 50 | J46: =IF(AND(G46<>"",G46<>0),E46/G46,"") -> 2.8333333 | K46: 25583 | N46: =IF(AND(I46<>"",I46<>0),G46/I46,"") -> 0.12 | O46: =D46/P46 -> 1.4266596 | P46: =$I$8*V46*W46/SUMPRODUCT($W$25:$W$56,$V$25:$V$56) -> 77630.992 | Q46: =$I$9*V46*W46/SUMPRODUCT($W$25:$W$58,$V$25:$V$58) -> 12.938499 | R46: =IF($I$12="","",Q46/$I$12) -> 7.1880548 | S46: =IF(W46<>"",IF(D46<>"",D46,($I$8-SUM($S$25:S45))*V46*W46/SUMPRODUCT($W46:$W$58,$V46:$V$58)),"") -> 110753 | T46: =IF(W46<>"",IF(E46<>"",E46,($I$9-SUM($T$25:T45))*V46*W46/SUMPRODUCT($W46:$W$58,$V46:$V$58)),"") -> 17 | U46: =IF(W46<>"",IF($I$12<>"",IF(G46<>"",G46,($I$9/$I$12-SUM($U$25:U45))*V46*W46/SUMPRODUCT($W46:$W$58,$V46:$V$58)),""),"") -> 6 | V46: 1 | W46: 1
A47: 23 | B47: 45923 | C47: вт | D47: 77307 | E47: 14 | F47: =IF(AND(E47<>"",E47<>0),D47/E47,"") -> 5521.9286 | G47: 4 | H47: =IF(AND(G47<>"",G47<>0),D47/G47,"") -> 19326.75 | I47: 30 | J47: =IF(AND(G47<>"",G47<>0),E47/G47,"") -> 3.5 | N47: =IF(AND(I47<>"",I47<>0),G47/I47,"") -> 0.13333333 | O47: =D47/P47 -> 0.99582651 | P47: =$I$8*V47*W47/SUMPRODUCT($W$25:$W$56,$V$25:$V$56) -> 77630.992 | Q47: =$I$9*V47*W47/SUMPRODUCT($W$25:$W$58,$V$25:$V$58) -> 12.938499 | R47: =IF($I$12="","",Q47/$I$12) -> 7.1880548 | S47: =IF(W47<>"",IF(D47<>"",D47,($I$8-SUM($S$25:S46))*V47*W47/SUMPRODUCT($W47:$W$58,$V47:$V$58)),"") -> 77307 | T47: =IF(W47<>"",IF(E47<>"",E47,($I$9-SUM($T$25:T46))*V47*W47/SUMPRODUCT($W47:$W$58,$V47:$V$58)),"") -> 14 | U47: =IF(W47<>"",IF($I$12<>"",IF(G47<>"",G47,($I$9/$I$12-SUM($U$25:U46))*V47*W47/SUMPRODUCT($W47:$W$58,$V47:$V$58)),""),"") -> 4 | V47: 1 | W47: 1
A48: 24 | B48: 45924 | C48: ср | D48: 24360 | E48: 5 | F48: =IF(AND(E48<>"",E48<>0),D48/E48,"") -> 4872 | G48: 5 | H48: =IF(AND(G48<>"",G48<>0),D48/G48,"") -> 4872 | I48: 27 | J48: =IF(AND(G48<>"",G48<>0),E48/G48,"") -> 1 | N48: =IF(AND(I48<>"",I48<>0),G48/I48,"") -> 0.18518519 | O48: =D48/P48 -> 0.3137922 | P48: =$I$8*V48*W48/SUMPRODUCT($W$25:$W$56,$V$25:$V$56) -> 77630.992 | Q48: =$I$9*V48*W48/SUMPRODUCT($W$25:$W$58,$V$25:$V$58) -> 12.938499 | R48: =IF($I$12="","",Q48/$I$12) -> 7.1880548 | S48: =IF(W48<>"",IF(D48<>"",D48,($I$8-SUM($S$25:S47))*V48*W48/SUMPRODUCT($W48:$W$58,$V48:$V$58)),"") -> 24360 | T48: =IF(W48<>"",IF(E48<>"",E48,($I$9-SUM($T$25:T47))*V48*W48/SUMPRODUCT($W48:$W$58,$V48:$V$58)),"") -> 5 | U48: =IF(W48<>"",IF($I$12<>"",IF(G48<>"",G48,($I$9/$I$12-SUM($U$25:U47))*V48*W48/SUMPRODUCT($W48:$W$58,$V48:$V$58)),""),"") -> 5 | V48: 1 | W48: 1
A49: 25 | B49: 45925 | C49: чт | D49: =46803+9503+35958 -> 92264 | E49: 11 | F49: =IF(AND(E49<>"",E49<>0),D49/E49,"") -> 8387.6364 | G49: 9 | H49: =IF(AND(G49<>"",G49<>0),D49/G49,"") -> 10251.556 | I49: 60 | J49: =IF(AND(G49<>"",G49<>0),E49/G49,"") -> 1.2222222 | K49: 46803 | L49: 9503 | N49: =IF(AND(I49<>"",I49<>0),G49/I49,"") -> 0.15 | O49: =D49/P49 -> 1.1884944 | P49: =$I$8*V49*W49/SUMPRODUCT($W$25:$W$56,$V$25:$V$56) -> 77630.992 | Q49: =$I$9*V49*W49/SUMPRODUCT($W$25:$W$58,$V$25:$V$58) -> 12.938499 | R49: =IF($I$12="","",Q49/$I$12) -> 7.1880548 | S49: =IF(W49<>"",IF(D49<>"",D49,($I$8-SUM($S$25:S48))*V49*W49/SUMPRODUCT($W49:$W$58,$V49:$V$58)),"") -> 92264 | T49: =IF(W49<>"",IF(E49<>"",E49,($I$9-SUM($T$25:T48))*V49*W49/SUMPRODUCT($W49:$W$58,$V49:$V$58)),"") -> 11 | U49: =IF(W49<>"",IF($I$12<>"",IF(G49<>"",G49,($I$9/$I$12-SUM($U$25:U48))*V49*W49/SUMPRODUCT($W49:$W$58,$V49:$V$58)),""),"") -> 9 | V49: 1 | W49: 1
A50: 26 | B50: 45773 | C50: пт | D50: 14875 | E50: 3 | F50: =IF(AND(E50<>"",E50<>0),D50/E50,"") -> 4958.3333 | G50: 2 | H50: =IF(AND(G50<>"",G50<>0),D50/G50,"") -> 7437.5 | I50: 23 | J50: =IF(AND(G50<>"",G50<>0),E50/G50,"") -> 1.5 | N50: =IF(AND(I50<>"",I50<>0),G50/I50,"") -> 0.086956522 | O50: =D50/P50 -> #DIV/0! | P50: =$I$8*V50*W50/SUMPRODUCT($W$25:$W$56,$V$25:$V$56) -> 0 | Q50: =$I$9*V50*W50/SUMPRODUCT($W$25:$W$58,$V$25:$V$58) -> 0 | R50: =IF($I$12="","",Q50/$I$12) -> 0 | S50: =IF(W50<>"",IF(D50<>"",D50,($I$8-SUM($S$25:S49))*V50*W50/SUMPRODUCT($W50:$W$58,$V50:$V$58)),"") | T50: =IF(W50<>"",IF(E50<>"",E50,($I$9-SUM($T$25:T49))*V50*W50/SUMPRODUCT($W50:$W$58,$V50:$V$58)),"") | U50: =IF(W50<>"",IF($I$12<>"",IF(G50<>"",G50,($I$9/$I$12-SUM($U$25:U49))*V50*W50/SUMPRODUCT($W50:$W$58,$V50:$V$58)),""),"")
A51: 27 | B51: 45927 | C51: сб | D51: =6803+13092+64088 -> 83983 | E51: 15 | F51: =IF(AND(E51<>"",E51<>0),D51/E51,"") -> 5598.8667 | G51: 8 | H51: =IF(AND(G51<>"",G51<>0),D51/G51,"") -> 10497.875 | I51: 45 | J51: =IF(AND(G51<>"",G51<>0),E51/G51,"") -> 1.875 | L51: 6803 | M51: 13092 | N51: =IF(AND(I51<>"",I51<>0),G51/I51,"") -> 0.17777778 | O51: =D51/P51 -> #DIV/0! | P51: =$I$8*V51*W51/SUMPRODUCT($W$25:$W$56,$V$25:$V$56) -> 0 | Q51: =$I$9*V51*W51/SUMPRODUCT($W$25:$W$58,$V$25:$V$58) -> 0 | R51: =IF($I$12="","",Q51/$I$12) -> 0 | S51: =IF(W51<>"",IF(D51<>"",D51,($I$8-SUM($S$25:S50))*V51*W51/SUMPRODUCT($W51:$W$58,$V51:$V$58)),"") | T51: =IF(W51<>"",IF(E51<>"",E51,($I$9-SUM($T$25:T50))*V51*W51/SUMPRODUCT($W51:$W$58,$V51:$V$58)),"") | U51: =IF(W51<>"",IF($I$12<>"",IF(G51<>"",G51,($I$9/$I$12-SUM($U$25:U50))*V51*W51/SUMPRODUCT($W51:$W$58,$V51:$V$58)),""),"")
A52: 28 | B52: 45928 | C52: вс | D52: 25468 | E52: 4 | F52: =IF(AND(E52<>"",E52<>0),D52/E52,"") -> 6367 | G52: 3 | H52: =IF(AND(G52<>"",G52<>0),D52/G52,"") -> 8489.3333 | I52: 30 | J52: =IF(AND(G52<>"",G52<>0),E52/G52,"") -> 1.3333333 | K52: 7991 | L52: 8903 | N52: =IF(AND(I52<>"",I52<>0),G52/I52,"") -> 0.1 | O52: =D52/P52 -> #DIV/0! | P52: =$I$8*V52*W52/SUMPRODUCT($W$25:$W$56,$V$25:$V$56) -> 0 | Q52: =$I$9*V52*W52/SUMPRODUCT($W$25:$W$58,$V$25:$V$58) -> 0 | R52: =IF($I$12="","",Q52/$I$12) -> 0 | S52: =IF(W52<>"",IF(D52<>"",D52,($I$8-SUM($S$25:S51))*V52*W52/SUMPRODUCT($W52:$W$58,$V52:$V$58)),"") | T52: =IF(W52<>"",IF(E52<>"",E52,($I$9-SUM($T$25:T51))*V52*W52/SUMPRODUCT($W52:$W$58,$V52:$V$58)),"") | U52: =IF(W52<>"",IF($I$12<>"",IF(G52<>"",G52,($I$9/$I$12-SUM($U$25:U51))*V52*W52/SUMPRODUCT($W52:$W$58,$V52:$V$58)),""),"")
A53: 29 | B53: 45929 | C53: пн | F53: =IF(AND(E53<>"",E53<>0),D53/E53,"") | H53: =IF(AND(G53<>"",G53<>0),D53/G53,"") | I53: 10 | J53: =IF(AND(G53<>"",G53<>0),E53/G53,"") | N53: =IF(AND(I53<>"",I53<>0),G53/I53,"") -> 0 | O53: =D53/P53 -> #DIV/0! | P53: =$I$8*V53*W53/SUMPRODUCT($W$25:$W$56,$V$25:$V$56) -> 0 | Q53: =$I$9*V53*W53/SUMPRODUCT($W$25:$W$58,$V$25:$V$58) -> 0 | R53: =IF($I$12="","",Q53/$I$12) -> 0 | S53: =IF(W53<>"",IF(D53<>"",D53,($I$8-SUM($S$25:S52))*V53*W53/SUMPRODUCT($W53:$W$58,$V53:$V$58)),"") | T53: =IF(W53<>"",IF(E53<>"",E53,($I$9-SUM($T$25:T52))*V53*W53/SUMPRODUCT($W53:$W$58,$V53:$V$58)),"") | U53: =IF(W53<>"",IF($I$12<>"",IF(G53<>"",G53,($I$9/$I$12-SUM($U$25:U52))*V53*W53/SUMPRODUCT($W53:$W$58,$V53:$V$58)),""),"")
B54: 45930 | C54: вт | D54: 32944 | E54: 5 | F54: =IF(AND(E54<>"",E54<>0),D54/E54,"") -> 6588.8 | G54: 3 | H54: =IF(AND(G54<>"",G54<>0),D54/G54,"") -> 10981.333 | I54: 17 | J54: =IF(AND(G54<>"",G54<>0),E54/G54,"") -> 1.6666667 | K54: 13490 | N54: =IF(AND(I54<>"",I54<>0),G54/I54,"") -> 0.17647059 | O54: =D54/P54 -> #DIV/0! | P54: =$I$8*V54*W54/SUMPRODUCT($W$25:$W$56,$V$25:$V$56) -> 0 | Q54: =$I$9*V54*W54/SUMPRODUCT($W$25:$W$58,$V$25:$V$58) -> 0 | R54: =IF($I$12="","",Q54/$I$12) -> 0 | S54: =IF(W54<>"",IF(D54<>"",D54,($I$8-SUM($S$25:S50))*V54*W54/SUMPRODUCT($W54:$W$58,$V54:$V$58)),"") | T54: =IF(W54<>"",IF(E54<>"",E54,($I$9-SUM($T$25:T50))*V54*W54/SUMPRODUCT($W54:$W$58,$V54:$V$58)),"") | U54: =IF(W54<>"",IF($I$12<>"",IF(G54<>"",G54,($I$9/$I$12-SUM($U$25:U50))*V54*W54/SUMPRODUCT($W54:$W$58,$V54:$V$58)),""),"")
F55: =IF(AND(E55<>"",E55<>0),D55/E55,"") | H55: =IF(AND(G55<>"",G55<>0),D55/G55,"") | J55: =IF(AND(G55<>"",G55<>0),E55/G55,"") | N55: =IF(AND(I55<>"",I55<>0),G55/I55,"") | O55: =D55/P55 -> #DIV/0! | P55: =$I$8*V55*W55/SUMPRODUCT($W$25:$W$56,$V$25:$V$56) -> 0 | Q55: =$I$9*V55*W55/SUMPRODUCT($W$25:$W$58,$V$25:$V$58) -> 0 | R55: =IF($I$12="","",Q55/$I$12) -> 0 | S55: =IF(W55<>"",IF(D55<>"",D55,($I$8-SUM($S$25:S54))*V55*W55/SUMPRODUCT($W55:$W$58,$V55:$V$58)),"") | T55: =IF(W55<>"",IF(E55<>"",E55,($I$9-SUM($T$25:T54))*V55*W55/SUMPRODUCT($W55:$W$58,$V55:$V$58)),"") | U55: =IF(W55<>"",IF($I$12<>"",IF(G55<>"",G55,($I$9/$I$12-SUM($U$25:U54))*V55*W55/SUMPRODUCT($W55:$W$58,$V55:$V$58)),""),"")
F56: =IF(AND(E56<>"",E56<>0),D56/E56,"") | H56: =IF(AND(G56<>"",G56<>0),D56/G56,"") | J56: =IF(AND(G56<>"",G56<>0),E56/G56,"") | N56: =IF(AND(I56<>"",I56<>0),G56/I56,"") | O56: =D56/P56 -> #DIV/0! | P56: =$I$8*V56*W56/SUMPRODUCT($W$25:$W$56,$V$25:$V$56) -> 0 | Q56: =$I$9*V56*W56/SUMPRODUCT($W$25:$W$58,$V$25:$V$58) -> 0 | R56: =IF($I$12="","",Q56/$I$12) -> 0 | S56: =IF(W56<>"",IF(D56<>"",D56,($I$8-SUM($S$25:S55))*V56*W56/SUMPRODUCT($W56:$W$58,$V56:$V$58)),"") | T56: =IF(W56<>"",IF(E56<>"",E56,($I$9-SUM($T$25:T55))*V56*W56/SUMPRODUCT($W56:$W$58,$V56:$V$58)),"") | U56: =IF(W56<>"",IF($I$12<>"",IF(G56<>"",G56,($I$9/$I$12-SUM($U$25:U55))*V56*W56/SUMPRODUCT($W56:$W$58,$V56:$V$58)),""),"")
D57: =SUM(D25:D56) -> 1869031 | E57: =SUM(E25:E56) -> 296 | F57: =IF(AND(E57<>"",E57<>0),D57/E57,"") -> 6314.2939 | G57: =SUM(G25:G56) -> 169 | H57: =IF(AND(G57<>"",G57<>0),D57/G57,"") -> 11059.355 | I57: =SUM(I25:I56) -> 1279.5 | J57: =IF(AND(G57<>"",G57<>0),E57/G57,"") -> 1.7514793 | K57: =SUM(K25:K56) -> 402662 | L57: =SUM(L25:L56) -> 111221 | M57: =SUM(M25:M56) -> 125097 | N57: =IF(AND(I57<>"",I57<>0),G57/I57,"") -> 0.13208284 | O57: =D57/P57 -> 0.96303343 | P57: =SUM(P25:P56) -> 1940774.8 | Q57: =SUM(Q25:Q55) -> 323.46247 | R57: =SUM(R25:R55) -> 179.70137 | S57: =SUM(S25:S56) -> 1711761 | T57: =SUM(T25:T55) -> 247 | U57: =SUM(U25:U55) -> 153
D58: =SUMIF(D25:D54,"",P25:P54)+D57 -> 1869031

Sheet Уразгильдеева Е. Р. 
B1: =TODAY()-1 -> 45939
B2: (отчетная дата) | J2: ЕЖЕДНЕВНЫЙ ОТЧЕТ О ПРОДАЖАХ
B3: Осталось до выполнения плана!!! | J3: =График!B28 -> Уразгильдеева Екатерина
C4: =I8-D50 -> 1526025.2 | E4: =IF(I8<>0, C4/I8, 0) -> 1
F6: Целевые показатели
F7: Показатель | I7: План | J7: Факт | K7: % выполнения | L7: Прогноз выполнения | M7: % выполнения по прогнозу | N7: Отклонение | O7: Факт аналогичного месяца прошлого года | P7: Отклонение LFL
F8: Выручка | I8: ='Ялта, Ленина, 18'!I8/График!AJ31*График!AJ28 -> 1526025.2 | J8: =D57 -> 1265396.1 | K8: =IF(AND(I8<>"",I8<>0,J8<>""),J8/I8,"") -> 0.82921047 | L8: =IF(SUMIF($D$25:$D$56,">=0",$P$25:$P$56)<>0,I8*D57/SUMIF($D$25:$D$56,">=0",$P$25:$P$56),0) -> 1375430.5 | M8: =IF(AND(I8<>"",I8<>0,L8<>"",L8<>0),L8/I8,"") -> 0.90131573 | N8: =IF(AND(J8<>0,J8<>"",I8<>0,I8<>""),L8-I8,"") -> -150594.68 | P8: =IF(AND(O8<>"", O8<>0, L8<>"", L8<>0), -O8+L8, "") | Q8: =IF(AND(P8<>"", P8<>0, O8<>0, O8<>""), P8/O8, "")
F9: Кол-во изделий | I9: =I8/I11 -> 254.33753 | J9: =E57 -> 186 | K9: =IF(AND(I9<>"", I9<>0, J9<>""), J9/I9, "") -> 0.73131164 | L9: =IF(SUMIF($E$25:$E$54,">=0",$Q$25:$Q$54)<>0,I9*E57/SUMIF($E$25:$E$54,">=0",$Q$25:$Q$54),0) -> 211.36364 | M9: =IF(AND(I9<>"",I9<>0,L9<>"",L9<>0),L9/I9,"") -> 0.83103596 | N9: =IF(AND(J9<>0,J9<>"",I9<>0,I9<>""),L9-I9,"") -> -42.973898 | O9: =O8/O11 -> #DIV/0! | P9: =IF(AND(O9<>"", O9<>0, L9<>"", L9<>0), -O9+L9, "") -> #DIV/0! | Q9: =IF(AND(P9<>"", P9<>0, O9<>0, O9<>""), P9/O9, "") -> #DIV/0!
F10: Средний чек | I10: =I11*I12 -> 10800 | J10: =H57 -> 12167.27 | K10: =IF(AND(I10<>"", I10<>0, J10<>""), J10/I10, "") -> 1.1265991 | L10: =J10 -> 12167.27 | M10: =IF(AND(I10<>"",I10<>0,L10<>"",L10<>0),L10/I10,"") -> 1.1265991 | N10: =IF(AND(J10<>0,J10<>"",I10<>0,I10<>""),L10-I10,"") -> 1367.27 | O10: =O11*O12 -> 0 | P10: =IF(AND(O10<>"", O10<>0, L10<>"", L10<>0), -O10+L10, "") | Q10: =IF(AND(P10<>"", P10<>0, O10<>0, O10<>""), P10/O10, "") | S10: IS | V10: =M23 -> Agafi
F11: Средняя стоимость изделия | I11: ='Ялта, Ленина, 18'!I11 -> 6000 | J11: =F57 -> 6803.2047 | K11: =IF(AND(I11<>"", I11<>0, J11<>""), J11/I11, "") -> 1.1338675 | L11: =IF(L9>0,L8/L9,"") -> 6507.4132 | M11: =IF(AND(I11<>"",I11<>0,L11<>"",L11<>0),L11/I11,"") -> 1.0845689 | N11: =IF(AND(J11<>0,J11<>"",I11<>0,I11<>""),L11-I11,"") -> 507.41322 | P11: =IF(AND(O11<>"", O11<>0, L11<>"", L11<>0), -O11+L11, "") | Q11: =IF(AND(P11<>"", P11<>0, O11<>0, O11<>""), P11/O11, "")
F12: Длина чека | I12: ='Ялта, Ленина, 18'!I12 -> 1.8 | J12: =J57 -> 1.7884615 | K12: =IF(AND(I12<>"", I12<>0, J12<>""), J12/I12, "") -> 0.99358974 | L12: =J12 -> 1.7884615 | M12: =IF(AND(I12<>"",I12<>0,L12<>"",L12<>0),L12/I12,"") -> 0.99358974 | N12: =IF(AND(J12<>0,J12<>"",I12<>0,I12<>""),L12-I12,"") -> -0.011538462 | P12: =IF(AND(O12<>"", O12<>0, L12<>"", L12<>0), -O12+L12, "") | Q12: =IF(AND(P12<>"", P12<>0, O12<>0, O12<>""), P12/O12, "") | S12: ='Ялта, Ленина, 18'!S12*График!AJ28/График!AJ31 -> 224493.15 | T12: =L57 -> 56655 | U12: =S12-T12 -> 167838.15 | V12: ='Ялта, Ленина, 18'!V12/График!AJ31*График!AJ28 -> 211287.67 | W12: =M57 -> 91714 | X12: =V12-W12 -> 119573.67
F13: Кол-во чеков | I13: =IF(I12<>0, I9/I12, "") -> 141.29863 | J13: =G57 -> 104 | K13: =IF(AND(I13<>"", I13<>0, J13<>""), J13/I13, "") -> 0.73602978 | L13: =IF(SUMIF($G$25:$G$54,">=0",$R$25:$R$54)<>0,I13*G57/SUMIF($G$25:$G$54,">=0",$R$25:$R$54),"") -> 118.18182 | M13: =IF(AND(I13<>"",I13<>0,L13<>"",L13<>0),L13/I13,"") -> 0.83639748 | N13: =IF(AND(J13<>0,J13<>"",I13<>0,I13<>""),L13-I13,"") -> -23.116812 | P13: =IF(AND(O13<>"", O13<>0, L13<>"", L13<>0), -O13+L13, "") | Q13: =IF(AND(P13<>"", P13<>0, O13<>0, O13<>""), P13/O13, "") | S13: =T12/S12 -> 0.2523685 | T13: =S13/J14*I14 -> 0.2523685 | V13: =W12/V12 -> 0.43407171 | W13: =V13/J14*I14 -> 0.43407171
F14: Кол-во смен план/отработано | I14: =График!AI28 -> 22 | J14: 22 | K14: =IF(AND(I14<>"", I14<>0, J14<>""), J14/I14, "") -> 1 | L14: =I14 -> 22 | M14: =IF(AND(I14<>"",I14<>0,L14<>"",L14<>0),L14/I14,"") -> 1 | N14: =IF(AND(J14<>0,J14<>"",I14<>0,I14<>""),L14-I14,"") -> 0 | P14: =IF(AND(O14<>"", O14<>0, L14<>"", L14<>0), -O14+L14, "") | Q14: =IF(AND(P14<>"", P14<>0, O14<>0, O14<>""), P14/O14, "")
F15: Средние продажи в смену | I15: ='Ялта, Ленина, 18'!I15 -> 115560 | J15: =J8/J14 -> 57518.004 | K15: =IF(AND(I15<>"", I15<>0, J15<>""), J15/I15, "") -> 0.49773281 | L15: =J15 -> 57518.004 | M15: =IF(AND(I15<>"",I15<>0,L15<>"",L15<>0),L15/I15,"") -> 0.49773281 | N15: =IF(AND(J15<>0,J15<>"",I15<>0,I15<>""),L15-I15,"") -> -58041.996 | P15: =IF(AND(O15<>"", O15<>0, L15<>"", L15<>0), -O15+L15, "") | Q15: =IF(AND(P15<>"", P15<>0, O15<>0, O15<>""), P15/O15, "")
F16: Отставание/Перевыполнение | J16: =J8-I15*J14 -> -1276923.9 | K16: =IF(AND(I16<>"", I16<>0, J16<>""), J16/I16, "") | L16: =J16 -> -1276923.9 | M16: =IF(AND(I16<>"",I16<>0,L16<>"",L16<>0),L16/I16,"") | N16: =IF(AND(J16<>0,J16<>"",I16<>0,I16<>""),L16-I16,"") | P16: =IF(AND(O16<>"", O16<>0, L16<>"", L16<>0), -O16+L16, "") | Q16: =IF(AND(P16<>"", P16<>0, O16<>0, O16<>""), P16/O16, "") | S16: UNOde50
F17: Трафик | I17: ='Ялта, Ленина, 18'!I17/График!AJ31*График!AJ28 -> 941.99087 | J17: =I57 -> 906.5 | K17: =IF(AND(I17<>"", I17<>0, J17<>""), J17/I17, "") -> 0.96232355 | L17: =J17/J14*I14 -> 906.5 | M17: =IF(AND(I17<>"",I17<>0,L17<>"",L17<>0),L17/I17,"") -> 0.96232355 | N17: =IF(AND(J17<>0,J17<>"",I17<>0,I17<>""),L17-I17,"") -> -35.490868 | P17: =IF(AND(O17<>"", O17<>0, L17<>"", L17<>0), -O17+L17, "") | Q17: =IF(AND(P17<>"", P17<>0, O17<>0, O17<>""), P17/O17, "")
K18: =IF(AND(I18<>"", I18<>0, J18<>""), J18/I18, "") | L18: =J18 -> 0 | M18: =IF(AND(I18<>"",I18<>0,L18<>"",L18<>0),L18/I18,"") | N18: =IF(AND(J18<>0,J18<>"",I18<>0,I18<>""),L18-I18,"") | O18: 0 | P18: =IF(AND(O18<>"", O18<>0, L18<>"", L18<>0), -O18+L18, "") | Q18: =IF(AND(P18<>"", P18<>0, O18<>0, O18<>""), P18/O18, "") | S18: ='Ялта, Ленина, 18'!S18*График!AJ28/График!AJ31 -> 448986.3 | T18: =K57 -> 376403
K19: =IF(AND(I19<>"", I19<>0, J19<>""), J19/I19, "") | L19: =J19 -> 0 | M19: =IF(AND(I19<>"",I19<>0,L19<>"",L19<>0),L19/I19,"") | N19: =IF(AND(J19<>0,J19<>"",I19<>0,I19<>""),L19-I19,"") | O19: 0 | P19: =IF(AND(O19<>"", O19<>0, L19<>"", L19<>0), -O19+L19, "") | Q19: =IF(AND(P19<>"", P19<>0, O19<>0, O19<>""), P19/O19, "") | S19: =T18/S18 -> 0.83833961 | T19: =S19/J14*I14 -> 0.83833961
F20: Конверсия план/факт | I20: ='Ялта, Ленина, 18'!I20 -> 0.15 | J20: =N57 -> 0.11472697 | K20: =J20/I20 -> 0.76484648 | L20: =IF(AND(K8<>0,I14<>0,I57<>0),(I57*N57+(I57/K8-I57)*I20)/(I57/K8),0) -> 0.12075124 | M20: =IF(AND(I20<>"",I20<>0,L20<>"",L20<>0),L20/I20,"") -> 0.80500824 | N20: =IF(AND(J20<>0,J20<>"",I20<>0,I20<>""),L20-I20,"") -> -0.029248764 | P20: =IF(AND(O20<>"", O20<>0, L20<>"", L20<>0), -O20+L20, "") | Q20: =IF(AND(P20<>"", P20<>0, O20<>0, O20<>""), P20/O20, "")
B22: Факт продаж за месяц | O22: % выполнения дневного плана | P22: Раcпределение плана по дням
B23: Дата | C23: День недели | D23: Выручка (руб) | E23: Кол-во единиц (шт.) | F23: Средняя стоимость изделия (руб.) | G23: Количество чеков (шт.) | H23: Средняя сумма чека (руб.) | I23: Трафик | J23: Длина чека (шт.) | K23: UNOde50 | L23: IS | M23: Agafi | N23: Конверсия (%) | P23: выручка, план | Q23: кол-во ед, план | R23: Кол-во чеков, план | S23: выручка, скорректир.план | T23: кол-во ед, скорр. план | U23: кол-во чеков, скорр. план | V23: Коэфф. Дня Недели | W23: Специфика месяца
B24: 1 | C24: 2 | D24: 3 | E24: в | F24: 5 | G24: 6 | H24: 7 | I24: 8 | J24: 9 | K24: 10 | L24: 11 | M24: 12 | N24: 13 | P24: 1 | Q24: 2 | R24: 3 | S24: 4 | T24: 5 | U24: 6 | V24: 10 | W24: 11
A25: 1 | B25: 45901 | C25: пн | D25: =9156+32073+14375 -> 55604 | E25: 7 | F25: =IF(AND(E25<>"",E25<>0),D25/E25,"") -> 7943.4286 | G25: 4 | H25: =IF(AND(G25<>"",G25<>0),D25/G25,"") -> 13901 | I25: 51 | J25: =IF(AND(G25<>"",G25<>0),E25/G25,"") -> 1.75 | K25: 9156 | M25: 32073 | N25: =IF(AND(I25<>"",I25<>0),G25/I25,"") -> 0.078431373 | O25: =D25/P25 -> 0.9109286 | P25: =$I$8*V25*W25/SUMPRODUCT($W$25:$W$56,$V$25:$V$56) -> 61041.008 | Q25: =$I$9*V25*W25/SUMPRODUCT($W$25:$W$56,$V$25:$V$56) -> 10.173501 | R25: =IF($I$12="","",Q25/$I$12) -> 5.6519452 | S25: =IF(D25<>"",D25,P25) -> 55604 | T25: =IF(E25<>"",E25,Q25) -> 7 | U25: =IF(G25<>"",G25,R25) -> 4 | V25: 1 | W25: 1
A26: 2 | B26: 45902 | C26: вт | D26: 27659 | E26: 5 | F26: =IF(AND(E26<>"",E26<>0),D26/E26,"") -> 5531.8 | G26: 4 | H26: =IF(AND(G26<>"",G26<>0),D26/G26,"") -> 6914.75 | I26: 37 | J26: =IF(AND(G26<>"",G26<>0),E26/G26,"") -> 1.25 | N26: =IF(AND(I26<>"",I26<>0),G26/I26,"") -> 0.10810811 | O26: =D26/P26 -> 0.45312161 | P26: =$I$8*V26*W26/SUMPRODUCT($W$25:$W$56,$V$25:$V$56) -> 61041.008 | Q26: =$I$9*V26*W26/SUMPRODUCT($W$25:$W$58,$V$25:$V$58) -> 10.173501 | R26: =IF($I$12="","",Q26/$I$12) -> 5.6519452 | S26: =IF(W26<>"",IF(D26<>"",D26,($I$8-SUM($S$25:S25))*V26*W26/SUMPRODUCT($W26:$W$56,$V26:$V$56)),"") -> 27659 | T26: =IF(W26<>"",IF(E26<>"",E26,($I$9-SUM($T$25:T25))*V26*W26/SUMPRODUCT($W26:$W$55,$V26:$V$55)),"") -> 5 | U26: =IF(W26<>"",IF($I$12<>"",IF(G26<>"",G26,($I$9/$I$12-SUM($U$25:U25))*V26*W26/SUMPRODUCT($W26:$W$55,$V26:$V$55)),""),"") -> 4 | V26: 1 | W26: 1
A27: 3 | B27: 45903 | C27: ср | D27: =112735+31329.6 -> 144064.6 | E27: 14 | F27: =IF(AND(E27<>"",E27<>0),D27/E27,"") -> 10290.329 | G27: 7 | H27: =IF(AND(G27<>"",G27<>0),D27/G27,"") -> 20580.657 | I27: 43 | J27: =IF(AND(G27<>"",G27<>0),E27/G27,"") -> 2 | K27: 112735 | N27: =IF(AND(I27<>"",I27<>0),G27/I27,"") -> 0.1627907 | O27: =D27/P27 -> 2.3601281 | P27: =$I$8*V27*W27/SUMPRODUCT($W$25:$W$56,$V$25:$V$56) -> 61041.008 | Q27: =$I$9*V27*W27/SUMPRODUCT($W$25:$W$58,$V$25:$V$58) -> 10.173501 | R27: =IF($I$12="","",Q27/$I$12) -> 5.6519452 | S27: =IF(W27<>"",IF(D27<>"",D27,($I$8-SUM($S$25:S26))*V27*W27/SUMPRODUCT($W27:$W$58,$V27:$V$58)),"") -> 144064.6 | T27: =IF(W27<>"",IF(E27<>"",E27,($I$9-SUM($T$25:T26))*V27*W27/SUMPRODUCT($W27:$W$55,$V27:$V$55)),"") -> 14 | U27: =IF(W27<>"",IF($I$12<>"",IF(G27<>"",G27,($I$9/$I$12-SUM($U$25:U26))*V27*W27/SUMPRODUCT($W27:$W$55,$V27:$V$55)),""),"") -> 7 | V27: 1 | W27: 1
A28: 4 | B28: 45905 | C28: пт | D28: 24875 | E28: 3 | F28: =IF(AND(E28<>"",E28<>0),D28/E28,"") -> 8291.6667 | G28: 2 | H28: =IF(AND(G28<>"",G28<>0),D28/G28,"") -> 12437.5 | I28: 39 | J28: =IF(AND(G28<>"",G28<>0),E28/G28,"") -> 1.5 | N28: =IF(AND(I28<>"",I28<>0),G28/I28,"") -> 0.051282051 | O28: =D28/P28 -> 0.40751293 | P28: =$I$8*V28*W28/SUMPRODUCT($W$25:$W$56,$V$25:$V$56) -> 61041.008 | Q28: =$I$9*V28*W28/SUMPRODUCT($W$25:$W$58,$V$25:$V$58) -> 10.173501 | R28: =IF($I$12="","",Q28/$I$12) -> 5.6519452 | S28: =IF(W28<>"",IF(D28<>"",D28,($I$8-SUM($S$25:S27))*V28*W28/SUMPRODUCT($W28:$W$58,$V28:$V$58)),"") -> 24875 | T28: =IF(W28<>"",IF(E28<>"",E28,($I$9-SUM($T$25:T27))*V28*W28/SUMPRODUCT($W28:$W$58,$V28:$V$58)),"") -> 3 | U28: =IF(W28<>"",IF($I$12<>"",IF(G28<>"",G28,($I$9/$I$12-SUM($U$25:U27))*V28*W28/SUMPRODUCT($W28:$W$58,$V28:$V$58)),""),"") -> 2 | V28: 1 | W28: 1
A29: 5 | B29: 45906 | C29: сб | D29: 16584 | E29: 2 | F29: =IF(AND(E29<>"",E29<>0),D29/E29,"") -> 8292 | G29: 2 | H29: =IF(AND(G29<>"",G29<>0),D29/G29,"") -> 8292 | I29: 23 | J29: =IF(AND(G29<>"",G29<>0),E29/G29,"") -> 1 | K29: 11992 | N29: =IF(AND(I29<>"",I29<>0),G29/I29,"") -> 0.086956522 | O29: =D29/P29 -> 0.27168621 | P29: =$I$8*V29*W29/SUMPRODUCT($W$25:$W$56,$V$25:$V$56) -> 61041.008 | Q29: =$I$9*V29*W29/SUMPRODUCT($W$25:$W$58,$V$25:$V$58) -> 10.173501 | R29: =IF($I$12="","",Q29/$I$12) -> 5.6519452 | S29: =IF(W29<>"",IF(D29<>"",D29,($I$8-SUM($S$25:S28))*V29*W29/SUMPRODUCT($W29:$W$58,$V29:$V$58)),"") -> 16584 | T29: =IF(W29<>"",IF(E29<>"",E29,($I$9-SUM($T$25:T28))*V29*W29/SUMPRODUCT($W29:$W$58,$V29:$V$58)),"") -> 2 | U29: =IF(W29<>"",IF($I$12<>"",IF(G29<>"",G29,($I$9/$I$12-SUM($U$25:U28))*V29*W29/SUMPRODUCT($W29:$W$58,$V29:$V$58)),""),"") -> 2 | V29: 1 | W29: 1
A30: 6 | B30: 45907 | C30: вс | D30: 10883 | E30: 2 | F30: =IF(AND(E30<>"",E30<>0),D30/E30,"") -> 5441.5 | G30: 1 | H30: =IF(AND(G30<>"",G30<>0),D30/G30,"") -> 10883 | I30: 25 | J30: =IF(AND(G30<>"",G30<>0),E30/G30,"") -> 2 | N30: =IF(AND(I30<>"",I30<>0),G30/I30,"") -> 0.04 | O30: =D30/P30 -> 0.17828998 | P30: =$I$8*V30*W30/SUMPRODUCT($W$25:$W$56,$V$25:$V$56) -> 61041.008 | Q30: =$I$9*V30*W30/SUMPRODUCT($W$25:$W$58,$V$25:$V$58) -> 10.173501 | R30: =IF($I$12="","",Q30/$I$12) -> 5.6519452 | S30: =IF(W30<>"",IF(D30<>"",D30,($I$8-SUM($S$25:S29))*V30*W30/SUMPRODUCT($W30:$W$58,$V30:$V$58)),"") -> 10883 | T30: =IF(W30<>"",IF(E30<>"",E30,($I$9-SUM($T$25:T29))*V30*W30/SUMPRODUCT($W30:$W$58,$V30:$V$58)),"") -> 2 | U30: =IF(W30<>"",IF($I$12<>"",IF(G30<>"",G30,($I$9/$I$12-SUM($U$25:U29))*V30*W30/SUMPRODUCT($W30:$W$58,$V30:$V$58)),""),"") -> 1 | V30: 1 | W30: 1
A31: 7 | B31: 45908 | C31: пн | D31: =83956+14292+39335 -> 137583 | E31: 14 | F31: =IF(AND(E31<>"",E31<>0),D31/E31,"") -> 9827.3571 | G31: 9 | H31: =IF(AND(G31<>"",G31<>0),D31/G31,"") -> 15287 | I31: 55 | J31: =IF(AND(G31<>"",G31<>0),E31/G31,"") -> 1.5555556 | K31: 83956 | M31: 14292 | N31: =IF(AND(I31<>"",I31<>0),G31/I31,"") -> 0.16363636 | O31: =D31/P31 -> 2.2539438 | P31: =$I$8*V31*W31/SUMPRODUCT($W$25:$W$56,$V$25:$V$56) -> 61041.008 | Q31: =$I$9*V31*W31/SUMPRODUCT($W$25:$W$58,$V$25:$V$58) -> 10.173501 | R31: =IF($I$12="","",Q31/$I$12) -> 5.6519452 | S31: =IF(W31<>"",IF(D31<>"",D31,($I$8-SUM($S$25:S30))*V31*W31/SUMPRODUCT($W31:$W$58,$V31:$V$58)),"") -> 137583 | T31: =IF(W31<>"",IF(E31<>"",E31,($I$9-SUM($T$25:T30))*V31*W31/SUMPRODUCT($W31:$W$58,$V31:$V$58)),"") -> 14 | U31: =IF(W31<>"",IF($I$12<>"",IF(G31<>"",G31,($I$9/$I$12-SUM($U$25:U30))*V31*W31/SUMPRODUCT($W31:$W$58,$V31:$V$58)),""),"") -> 9 | V31: 1 | W31: 1
A32: 8 | B32: 45910 | C32: ср | D32: =16403+9992+4892 -> 31287 | E32: 4 | F32: =IF(AND(E32<>"",E32<>0),D32/E32,"") -> 7821.75 | G32: 3 | H32: =IF(AND(G32<>"",G32<>0),D32/G32,"") -> 10429 | I32: =13+74/2 -> 50 | J32: =IF(AND(G32<>"",G32<>0),E32/G32,"") -> 1.3333333 | K32: 9992 | L32: 16403 | N32: =IF(AND(I32<>"",I32<>0),G32/I32,"") -> 0.06 | O32: =D32/P32 -> 0.51255706 | P32: =$I$8*V32*W32/SUMPRODUCT($W$25:$W$56,$V$25:$V$56) -> 61041.008 | Q32: =$I$9*V32*W32/SUMPRODUCT($W$25:$W$58,$V$25:$V$58) -> 10.173501 | R32: =IF($I$12="","",Q32/$I$12) -> 5.6519452 | S32: =IF(W32<>"",IF(D32<>"",D32,($I$8-SUM($S$25:S31))*V32*W32/SUMPRODUCT($W32:$W$58,$V32:$V$58)),"") -> 31287 | T32: =IF(W32<>"",IF(E32<>"",E32,($I$9-SUM($T$25:T31))*V32*W32/SUMPRODUCT($W32:$W$58,$V32:$V$58)),"") -> 4 | U32: =IF(W32<>"",IF($I$12<>"",IF(G32<>"",G32,($I$9/$I$12-SUM($U$25:U31))*V32*W32/SUMPRODUCT($W32:$W$58,$V32:$V$58)),""),"") -> 3 | V32: 1 | W32: 1
A33: 9 | B33: 45911 | C33: чт | D33: =70336+43468 -> 113804 | E33: 11 | F33: =IF(AND(E33<>"",E33<>0),D33/E33,"") -> 10345.818 | G33: 3 | H33: =IF(AND(G33<>"",G33<>0),D33/G33,"") -> 37934.667 | I33: =12+79/2 -> 51.5 | J33: =IF(AND(G33<>"",G33<>0),E33/G33,"") -> 3.6666667 | K33: 70336 | N33: =IF(AND(I33<>"",I33<>0),G33/I33,"") -> 0.058252427 | O33: =D33/P33 -> 1.864386 | P33: =$I$8*V33*W33/SUMPRODUCT($W$25:$W$56,$V$25:$V$56) -> 61041.008 | Q33: =$I$9*V33*W33/SUMPRODUCT($W$25:$W$58,$V$25:$V$58) -> 10.173501 | R33: =IF($I$12="","",Q33/$I$12) -> 5.6519452 | S33: =IF(W33<>"",IF(D33<>"",D33,($I$8-SUM($S$25:S32))*V33*W33/SUMPRODUCT($W33:$W$58,$V33:$V$58)),"") -> 113804 | T33: =IF(W33<>"",IF(E33<>"",E33,($I$9-SUM($T$25:T32))*V33*W33/SUMPRODUCT($W33:$W$58,$V33:$V$58)),"") -> 11 | U33: =IF(W33<>"",IF($I$12<>"",IF(G33<>"",G33,($I$9/$I$12-SUM($U$25:U32))*V33*W33/SUMPRODUCT($W33:$W$58,$V33:$V$58)),""),"") -> 3 | V33: 1 | W33: 1
A34: 10 | B34: 45913 | C34: сб | D34: 68071 | E34: 14 | F34: =IF(AND(E34<>"",E34<>0),D34/E34,"") -> 4862.2143 | G34: 8 | H34: =IF(AND(G34<>"",G34<>0),D34/G34,"") -> 8508.875 | I34: =55+93/2 -> 101.5 | J34: =IF(AND(G34<>"",G34<>0),E34/G34,"") -> 1.75 | N34: =IF(AND(I34<>"",I34<>0),G34/I34,"") -> 0.078817734 | O34: =D34/P34 -> 1.1151683 | P34: =$I$8*V34*W34/SUMPRODUCT($W$25:$W$56,$V$25:$V$56) -> 61041.008 | Q34: =$I$9*V34*W34/SUMPRODUCT($W$25:$W$58,$V$25:$V$58) -> 10.173501 | R34: =IF($I$12="","",Q34/$I$12) -> 5.6519452 | S34: =IF(W34<>"",IF(D34<>"",D34,($I$8-SUM($S$25:S33))*V34*W34/SUMPRODUCT($W34:$W$58,$V34:$V$58)),"") -> 68071 | T34: =IF(W34<>"",IF(E34<>"",E34,($I$9-SUM($T$25:T33))*V34*W34/SUMPRODUCT($W34:$W$58,$V34:$V$58)),"") -> 14 | U34: =IF(W34<>"",IF($I$12<>"",IF(G34<>"",G34,($I$9/$I$12-SUM($U$25:U33))*V34*W34/SUMPRODUCT($W34:$W$58,$V34:$V$58)),""),"") -> 8 | V34: 1 | W34: 1
A35: 11 | B35: 45914 | C35: вс | D35: 72609 | E35: 12 | F35: =IF(AND(E35<>"",E35<>0),D35/E35,"") -> 6050.75 | G35: 7 | H35: =IF(AND(G35<>"",G35<>0),D35/G35,"") -> 10372.714 | I35: 46 | J35: =IF(AND(G35<>"",G35<>0),E35/G35,"") -> 1.7142857 | K35: 25082 | M35: 12384 | N35: =IF(AND(I35<>"",I35<>0),G35/I35,"") -> 0.15217391 | O35: =D35/P35 -> 1.1895118 | P35: =$I$8*V35*W35/SUMPRODUCT($W$25:$W$56,$V$25:$V$56) -> 61041.008 | Q35: =$I$9*V35*W35/SUMPRODUCT($W$25:$W$58,$V$25:$V$58) -> 10.173501 | R35: =IF($I$12="","",Q35/$I$12) -> 5.6519452 | S35: =IF(W35<>"",IF(D35<>"",D35,($I$8-SUM($S$25:S34))*V35*W35/SUMPRODUCT($W35:$W$58,$V35:$V$58)),"") -> 72609 | T35: =IF(W35<>"",IF(E34<>"",E34,($I$9-SUM($T$25:T34))*V35*W35/SUMPRODUCT($W35:$W$58,$V35:$V$58)),"") -> 14 | U35: =IF(W35<>"",IF($I$12<>"",IF(G35<>"",G35,($I$9/$I$12-SUM($U$25:U34))*V35*W35/SUMPRODUCT($W35:$W$58,$V35:$V$58)),""),"") -> 7 | V35: 1 | W35: 1
A36: 11 | B36: 45915 | C36: пн | D36: 0 | F36: =IF(AND(E36<>"",E36<>0),D36/E36,"") | H36: =IF(AND(G36<>"",G36<>0),D36/G36,"") | I36: =8+41/2 -> 28.5 | J36: =IF(AND(G36<>"",G36<>0),E36/G36,"") | N36: =IF(AND(I36<>"",I36<>0),G36/I36,"") -> 0 | O36: =D36/P36 -> 0 | P36: =$I$8*V36*W36/SUMPRODUCT($W$25:$W$56,$V$25:$V$56) -> 61041.008 | Q36: =$I$9*V36*W36/SUMPRODUCT($W$25:$W$58,$V$25:$V$58) -> 10.173501 | R36: =IF($I$12="","",Q36/$I$12) -> 5.6519452 | S36: =IF(W36<>"",IF(D36<>"",D36,($I$8-SUM($S$25:S35))*V36*W36/SUMPRODUCT($W36:$W$58,$V36:$V$58)),"") -> 0 | T36: =IF(W36<>"",IF(E35<>"",E35,($I$9-SUM($T$25:T35))*V36*W36/SUMPRODUCT($W36:$W$58,$V36:$V$58)),"") -> 12 | U36: =IF(W36<>"",IF($I$12<>"",IF(G36<>"",G36,($I$9/$I$12-SUM($U$25:U35))*V36*W36/SUMPRODUCT($W36:$W$58,$V36:$V$58)),""),"") -> 6.5213307 | V36: 1 | W36: 1
A37: 13 | B37: 45916 | C37: вт | D37: 23089 | E37: 5 | F37: =IF(AND(E37<>"",E37<>0),D37/E37,"") -> 4617.8 | G37: 4 | H37: =IF(AND(G37<>"",G37<>0),D37/G37,"") -> 5772.25 | I37: =7+74/2 -> 44 | J37: =IF(AND(G37<>"",G37<>0),E37/G37,"") -> 1.25 | N37: =IF(AND(I37<>"",I37<>0),G37/I37,"") -> 0.090909091 | O37: =D37/P37 -> 0.37825391 | P37: =$I$8*V37*W37/SUMPRODUCT($W$25:$W$56,$V$25:$V$56) -> 61041.008 | Q37: =$I$9*V37*W37/SUMPRODUCT($W$25:$W$58,$V$25:$V$58) -> 10.173501 | R37: =IF($I$12="","",Q37/$I$12) -> 5.6519452 | S37: =IF(W37<>"",IF(D37<>"",D37,($I$8-SUM($S$25:S36))*V37*W37/SUMPRODUCT($W37:$W$58,$V37:$V$58)),"") -> 23089 | T37: =IF(W37<>"",IF(E37<>"",E37,($I$9-SUM($T$25:T36))*V37*W37/SUMPRODUCT($W37:$W$58,$V37:$V$58)),"") -> 5 | U37: =IF(W37<>"",IF($I$12<>"",IF(G37<>"",G37,($I$9/$I$12-SUM($U$25:U36))*V37*W37/SUMPRODUCT($W37:$W$58,$V37:$V$58)),""),"") -> 4 | V37: 1 | W37: 1
A38: 14 | B38: 45919 | C38: пт | D38: =18982+9123+54207 -> 82312 | E38: 14 | F38: =IF(AND(E38<>"",E38<>0),D38/E38,"") -> 5879.4286 | G38: 8 | H38: =IF(AND(G38<>"",G38<>0),D38/G38,"") -> 10289 | I38: 60 | J38: =IF(AND(G38<>"",G38<>0),E38/G38,"") -> 1.75 | K38: 18982 | L38: 9123 | N38: =IF(AND(I38<>"",I38<>0),G38/I38,"") -> 0.13333333 | O38: =D38/P38 -> 1.3484705 | P38: =$I$8*V38*W38/SUMPRODUCT($W$25:$W$56,$V$25:$V$56) -> 61041.008 | Q38: =$I$9*V38*W38/SUMPRODUCT($W$25:$W$58,$V$25:$V$58) -> 10.173501 | R38: =IF($I$12="","",Q38/$I$12) -> 5.6519452 | S38: =IF(W38<>"",IF(D38<>"",D38,($I$8-SUM($S$25:S37))*V38*W38/SUMPRODUCT($W38:$W$58,$V38:$V$58)),"") -> 82312 | T38: =IF(W38<>"",IF(E38<>"",E38,($I$9-SUM($T$25:T37))*V38*W38/SUMPRODUCT($W38:$W$58,$V38:$V$58)),"") -> 14 | U38: =IF(W38<>"",IF($I$12<>"",IF(G38<>"",G38,($I$9/$I$12-SUM($U$25:U37))*V38*W38/SUMPRODUCT($W38:$W$58,$V38:$V$58)),""),"") -> 8 | V38: 1 | W38: 1
A39: 15 | B39: 45920 | C39: сб | D39: =57513+220 -> 57733 | E39: 10 | F39: =IF(AND(E39<>"",E39<>0),D39/E39,"") -> 5773.3 | G39: 6 | H39: =IF(AND(G39<>"",G39<>0),D39/G39,"") -> 9622.1667 | I39: 33 | J39: =IF(AND(G39<>"",G39<>0),E39/G39,"") -> 1.6666667 | L39: 220 | N39: =IF(AND(I39<>"",I39<>0),G39/I39,"") -> 0.18181818 | O39: =D39/P39 -> 0.94580679 | P39: =$I$8*V39*W39/SUMPRODUCT($W$25:$W$56,$V$25:$V$56) -> 61041.008 | Q39: =$I$9*V39*W39/SUMPRODUCT($W$25:$W$58,$V$25:$V$58) -> 10.173501 | R39: =IF($I$12="","",Q39/$I$12) -> 5.6519452 | S39: =IF(W39<>"",IF(D39<>"",D39,($I$8-SUM($S$25:S38))*V39*W39/SUMPRODUCT($W39:$W$58,$V39:$V$58)),"") -> 57733 | T39: =IF(W39<>"",IF(E39<>"",E39,($I$9-SUM($T$25:T38))*V39*W39/SUMPRODUCT($W39:$W$58,$V39:$V$58)),"") -> 10 | U39: =IF(W39<>"",IF($I$12<>"",IF(G39<>"",G39,($I$9/$I$12-SUM($U$25:U38))*V39*W39/SUMPRODUCT($W39:$W$58,$V39:$V$58)),""),"") -> 6 | V39: 1 | W39: 1
A40: 16 | B40: 45921 | C40: вс | D40: 46099 | E40: 8 | F40: =IF(AND(E40<>"",E40<>0),D40/E40,"") -> 5762.375 | G40: 4 | H40: =IF(AND(G40<>"",G40<>0),D40/G40,"") -> 11524.75 | I40: 22 | J40: =IF(AND(G40<>"",G40<>0),E40/G40,"") -> 2 | N40: =IF(AND(I40<>"",I40<>0),G40/I40,"") -> 0.18181818 | O40: =D40/P40 -> 0.75521361 | P40: =$I$8*V40*W40/SUMPRODUCT($W$25:$W$56,$V$25:$V$56) -> 61041.008 | Q40: =$I$9*V40*W40/SUMPRODUCT($W$25:$W$58,$V$25:$V$58) -> 10.173501 | R40: =IF($I$12="","",Q40/$I$12) -> 5.6519452 | S40: =IF(W40<>"",IF(D40<>"",D40,($I$8-SUM($S$25:S39))*V40*W40/SUMPRODUCT($W40:$W$58,$V40:$V$58)),"") -> 46099 | T40: =IF(W40<>"",IF(E40<>"",E40,($I$9-SUM($T$25:T39))*V40*W40/SUMPRODUCT($W40:$W$58,$V40:$V$58)),"") -> 8 | U40: =IF(W40<>"",IF($I$12<>"",IF(G40<>"",G40,($I$9/$I$12-SUM($U$25:U39))*V40*W40/SUMPRODUCT($W40:$W$58,$V40:$V$58)),""),"") -> 4 | V40: 1 | W40: 1
A41: 17 | B41: 45923 | C41: вт | D41: =8903+17867 -> 26770 | E41: 5 | F41: =IF(AND(E41<>"",E41<>0),D41/E41,"") -> 5354 | G41: 4 | H41: =IF(AND(G41<>"",G41<>0),D41/G41,"") -> 6692.5 | I41: 30 | J41: =IF(AND(G41<>"",G41<>0),E41/G41,"") -> 1.25 | L41: 8903 | N41: =IF(AND(I41<>"",I41<>0),G41/I41,"") -> 0.13333333 | O41: =D41/P41 -> 0.43855763 | P41: =$I$8*V41*W41/SUMPRODUCT($W$25:$W$56,$V$25:$V$56) -> 61041.008 | Q41: =$I$9*V41*W41/SUMPRODUCT($W$25:$W$58,$V$25:$V$58) -> 10.173501 | R41: =IF($I$12="","",Q41/$I$12) -> 5.6519452 | S41: =IF(W41<>"",IF(D41<>"",D41,($I$8-SUM($S$25:S40))*V41*W41/SUMPRODUCT($W41:$W$58,$V41:$V$58)),"") -> 26770 | T41: =IF(W41<>"",IF(E41<>"",E41,($I$9-SUM($T$25:T40))*V41*W41/SUMPRODUCT($W41:$W$58,$V41:$V$58)),"") -> 5 | U41: =IF(W41<>"",IF($I$12<>"",IF(G41<>"",G41,($I$9/$I$12-SUM($U$25:U40))*V41*W41/SUMPRODUCT($W41:$W$58,$V41:$V$58)),""),"") -> 4 | V41: 1 | W41: 1
A42: 18 | B42: 45924 | C42: ср | D42: 25350 | E42: 6 | F42: =IF(AND(E42<>"",E42<>0),D42/E42,"") -> 4225 | G42: 4 | H42: =IF(AND(G42<>"",G42<>0),D42/G42,"") -> 6337.5 | I42: 23 | J42: =IF(AND(G42<>"",G42<>0),E42/G42,"") -> 1.5 | N42: =IF(AND(I42<>"",I42<>0),G42/I42,"") -> 0.17391304 | O42: =D42/P42 -> 0.41529458 | P42: =$I$8*V42*W42/SUMPRODUCT($W$25:$W$56,$V$25:$V$56) -> 61041.008 | Q42: =$I$9*V42*W42/SUMPRODUCT($W$25:$W$58,$V$25:$V$58) -> 10.173501 | R42: =IF($I$12="","",Q42/$I$12) -> 5.6519452 | S42: =IF(W42<>"",IF(D42<>"",D42,($I$8-SUM($S$25:S41))*V42*W42/SUMPRODUCT($W42:$W$58,$V42:$V$58)),"") -> 25350 | T42: =IF(W42<>"",IF(E42<>"",E42,($I$9-SUM($T$25:T41))*V42*W42/SUMPRODUCT($W42:$W$58,$V42:$V$58)),"") -> 6 | U42: =IF(W42<>"",IF($I$12<>"",IF(G42<>"",G42,($I$9/$I$12-SUM($U$25:U41))*V42*W42/SUMPRODUCT($W42:$W$58,$V42:$V$58)),""),"") -> 4 | V42: 1 | W42: 1
A43: 19 | B43: 45926 | C43: пт | D43: =80379+11492 -> 91871 | E43: 15 | F43: =IF(AND(E43<>"",E43<>0),D43/E43,"") -> 6124.7333 | G43: 5 | H43: =IF(AND(G43<>"",G43<>0),D43/G43,"") -> 18374.2 | I43: =19+24 -> 43 | J43: =IF(AND(G43<>"",G43<>0),E43/G43,"") -> 3 | K43: 11492 | N43: =IF(AND(I43<>"",I43<>0),G43/I43,"") -> 0.11627907 | O43: =D43/P43 -> 1.5050702 | P43: =$I$8*V43*W43/SUMPRODUCT($W$25:$W$56,$V$25:$V$56) -> 61041.008 | Q43: =$I$9*V43*W43/SUMPRODUCT($W$25:$W$58,$V$25:$V$58) -> 10.173501 | R43: =IF($I$12="","",Q43/$I$12) -> 5.6519452 | S43: =IF(W43<>"",IF(D43<>"",D43,($I$8-SUM($S$25:S42))*V43*W43/SUMPRODUCT($W43:$W$58,$V43:$V$58)),"") -> 91871 | T43: =IF(W43<>"",IF(E43<>"",E43,($I$9-SUM($T$25:T42))*V43*W43/SUMPRODUCT($W43:$W$58,$V43:$V$58)),"") -> 15 | U43: =IF(W43<>"",IF($I$12<>"",IF(G43<>"",G43,($I$9/$I$12-SUM($U$25:U42))*V43*W43/SUMPRODUCT($W43:$W$58,$V43:$V$58)),""),"") -> 5 | V43: 1 | W43: 1
A44: 20 | B44: 45927 | C44: сб | D44: =14103+7990+48725 -> 70818 | E44: 12 | F44: =IF(AND(E44<>"",E44<>0),D44/E44,"") -> 5901.5 | G44: 7 | H44: =IF(AND(G44<>"",G44<>0),D44/G44,"") -> 10116.857 | I44: 41 | J44: =IF(AND(G44<>"",G44<>0),E44/G44,"") -> 1.7142857 | L44: 14103 | M44: 7990 | N44: =IF(AND(I44<>"",I44<>0),G44/I44,"") -> 0.17073171 | O44: =D44/P44 -> 1.1601709 | P44: =$I$8*V44*W44/SUMPRODUCT($W$25:$W$56,$V$25:$V$56) -> 61041.008 | Q44: =$I$9*V44*W44/SUMPRODUCT($W$25:$W$58,$V$25:$V$58) -> 10.173501 | R44: =IF($I$12="","",Q44/$I$12) -> 5.6519452 | S44: =IF(W44<>"",IF(D44<>"",D44,($I$8-SUM($S$25:S43))*V44*W44/SUMPRODUCT($W44:$W$58,$V44:$V$58)),"") -> 70818 | T44: =IF(W44<>"",IF(E44<>"",E44,($I$9-SUM($T$25:T43))*V44*W44/SUMPRODUCT($W44:$W$58,$V44:$V$58)),"") -> 12 | U44: =IF(W44<>"",IF($I$12<>"",IF(G44<>"",G44,($I$9/$I$12-SUM($U$25:U43))*V44*W44/SUMPRODUCT($W44:$W$58,$V44:$V$58)),""),"") -> 7 | V44: 1 | W44: 1
A45: 21 | B45: 45928 | C45: вс | D45: 90800 | E45: 13 | F45: =IF(AND(E45<>"",E45<>0),D45/E45,"") -> 6984.6154 | G45: 6 | H45: =IF(AND(G45<>"",G45<>0),D45/G45,"") -> 15133.333 | I45: 40 | J45: =IF(AND(G45<>"",G45<>0),E45/G45,"") -> 2.1666667 | K45: 22680 | L45: 7903 | M45: 15983 | N45: =IF(AND(I45<>"",I45<>0),G45/I45,"") -> 0.15 | O45: =D45/P45 -> 1.4875246 | P45: =$I$8*V45*W45/SUMPRODUCT($W$25:$W$56,$V$25:$V$56) -> 61041.008 | Q45: =$I$9*V45*W45/SUMPRODUCT($W$25:$W$58,$V$25:$V$58) -> 10.173501 | R45: =IF($I$12="","",Q45/$I$12) -> 5.6519452 | S45: =IF(W45<>"",IF(D45<>"",D45,($I$8-SUM($S$25:S44))*V45*W45/SUMPRODUCT($W45:$W$58,$V45:$V$58)),"") -> 90800 | T45: =IF(W45<>"",IF(E45<>"",E45,($I$9-SUM($T$25:T44))*V45*W45/SUMPRODUCT($W45:$W$58,$V45:$V$58)),"") -> 13 | U45: =IF(W45<>"",IF($I$12<>"",IF(G45<>"",G45,($I$9/$I$12-SUM($U$25:U44))*V45*W45/SUMPRODUCT($W45:$W$58,$V45:$V$58)),""),"") -> 6 | V45: 1 | W45: 1
A46: 22 | B46: 45929 | C46: пн | D46: 34846.48 | E46: 8 | F46: =IF(AND(E46<>"",E46<>0),D46/E46,"") -> 4355.81 | G46: 4 | H46: =IF(AND(G46<>"",G46<>0),D46/G46,"") -> 8711.62 | I46: 20 | J46: =IF(AND(G46<>"",G46<>0),E46/G46,"") -> 2 | N46: =IF(AND(I46<>"",I46<>0),G46/I46,"") -> 0.2 | O46: =D46/P46 -> 0.57086999 | P46: =$I$8*V46*W46/SUMPRODUCT($W$25:$W$56,$V$25:$V$56) -> 61041.008 | Q46: =$I$9*V46*W46/SUMPRODUCT($W$25:$W$58,$V$25:$V$58) -> 10.173501 | R46: =IF($I$12="","",Q46/$I$12) -> 5.6519452 | S46: =IF(W46<>"",IF(D46<>"",D46,($I$8-SUM($S$25:S45))*V46*W46/SUMPRODUCT($W46:$W$58,$V46:$V$58)),"") -> 34846.48 | T46: =IF(W46<>"",IF(E46<>"",E46,($I$9-SUM($T$25:T45))*V46*W46/SUMPRODUCT($W46:$W$58,$V46:$V$58)),"") -> 8 | U46: =IF(W46<>"",IF($I$12<>"",IF(G46<>"",G46,($I$9/$I$12-SUM($U$25:U45))*V46*W46/SUMPRODUCT($W46:$W$58,$V46:$V$58)),""),"") -> 4 | V46: 1 | W46: 1
A47: 23 | B47: 45925 | C47: чт | D47: =8992+3692 -> 12684 | E47: 2 | F47: =IF(AND(E47<>"",E47<>0),D47/E47,"") -> 6342 | G47: 2 | H47: =IF(AND(G47<>"",G47<>0),D47/G47,"") -> 6342 | J47: =IF(AND(G47<>"",G47<>0),E47/G47,"") -> 1 | M47: 8992 | N47: =IF(AND(I47<>"",I47<>0),G47/I47,"") | O47: =D47/P47 -> 0.20779473 | P47: =$I$8*V47*W47/SUMPRODUCT($W$25:$W$56,$V$25:$V$56) -> 61041.008 | Q47: =$I$9*V47*W47/SUMPRODUCT($W$25:$W$58,$V$25:$V$58) -> 10.173501 | R47: =IF($I$12="","",Q47/$I$12) -> 5.6519452 | S47: =IF(W47<>"",IF(D47<>"",D47,($I$8-SUM($S$25:S46))*V47*W47/SUMPRODUCT($W47:$W$58,$V47:$V$58)),"") -> 12684 | T47: =IF(W47<>"",IF(E47<>"",E47,($I$9-SUM($T$25:T46))*V47*W47/SUMPRODUCT($W47:$W$58,$V47:$V$58)),"") -> 2 | U47: =IF(W47<>"",IF($I$12<>"",IF(G47<>"",G47,($I$9/$I$12-SUM($U$25:U46))*V47*W47/SUMPRODUCT($W47:$W$58,$V47:$V$58)),""),"") -> 2 | V47: 1 | W47: 1
A48: 24 | F48: =IF(AND(E48<>"",E48<>0),D48/E48,"") | H48: =IF(AND(G48<>"",G48<>0),D48/G48,"") | J48: =IF(AND(G48<>"",G48<>0),E48/G48,"") | N48: =IF(AND(I48<>"",I48<>0),G48/I48,"") | O48: =D48/P48 -> 0 | P48: =$I$8*V48*W48/SUMPRODUCT($W$25:$W$56,$V$25:$V$56) -> 61041.008 | Q48: =$I$9*V48*W48/SUMPRODUCT($W$25:$W$58,$V$25:$V$58) -> 10.173501 | R48: =IF($I$12="","",Q48/$I$12) -> 5.6519452 | S48: =IF(W48<>"",IF(D48<>"",D48,($I$8-SUM($S$25:S47))*V48*W48/SUMPRODUCT($W48:$W$58,$V48:$V$58)),"") -> 130314.56 | T48: =IF(W48<>"",IF(E48<>"",E48,($I$9-SUM($T$25:T47))*V48*W48/SUMPRODUCT($W48:$W$58,$V48:$V$58)),"") -> 27.168767 | U48: =IF(W48<>"",IF($I$12<>"",IF(G48<>"",G48,($I$9/$I$12-SUM($U$25:U47))*V48*W48/SUMPRODUCT($W48:$W$58,$V48:$V$58)),""),"") -> 15.38865 | V48: 1 | W48: 1
A49: 25 | F49: =IF(AND(E49<>"",E49<>0),D49/E49,"") | H49: =IF(AND(G49<>"",G49<>0),D49/G49,"") | J49: =IF(AND(G49<>"",G49<>0),E49/G49,"") | N49: =IF(AND(I49<>"",I49<>0),G49/I49,"") | O49: =D49/P49 -> 0 | P49: =$I$8*V49*W49/SUMPRODUCT($W$25:$W$56,$V$25:$V$56) -> 61041.008 | Q49: =$I$9*V49*W49/SUMPRODUCT($W$25:$W$58,$V$25:$V$58) -> 10.173501 | R49: =IF($I$12="","",Q49/$I$12) -> 5.6519452 | S49: =IF(W49<>"",IF(D49<>"",D49,($I$8-SUM($S$25:S48))*V49*W49/SUMPRODUCT($W49:$W$58,$V49:$V$58)),"") -> 130314.56 | T49: =IF(W49<>"",IF(E49<>"",E49,($I$9-SUM($T$25:T48))*V49*W49/SUMPRODUCT($W49:$W$58,$V49:$V$58)),"") -> 27.168767 | U49: =IF(W49<>"",IF($I$12<>"",IF(G49<>"",G49,($I$9/$I$12-SUM($U$25:U48))*V49*W49/SUMPRODUCT($W49:$W$58,$V49:$V$58)),""),"") -> 15.38865 | V49: 1 | W49: 1
A50: 26 | F50: =IF(AND(E50<>"",E50<>0),D50/E50,"") | H50: =IF(AND(G50<>"",G50<>0),D50/G50,"") | J50: =IF(AND(G50<>"",G50<>0),E50/G50,"") | N50: =IF(AND(I50<>"",I50<>0),G50/I50,"") | O50: =D50/P50 -> #DIV/0! | P50: =$I$8*V50*W50/SUMPRODUCT($W$25:$W$56,$V$25:$V$56) -> 0 | Q50: =$I$9*V50*W50/SUMPRODUCT($W$25:$W$58,$V$25:$V$58) -> 0 | R50: =IF($I$12="","",Q50/$I$12) -> 0 | S50: =IF(W50<>"",IF(D50<>"",D50,($I$8-SUM($S$25:S49))*V50*W50/SUMPRODUCT($W50:$W$58,$V50:$V$58)),"") | T50: =IF(W50<>"",IF(E50<>"",E50,($I$9-SUM($T$25:T49))*V50*W50/SUMPRODUCT($W50:$W$58,$V50:$V$58)),"") | U50: =IF(W50<>"",IF($I$12<>"",IF(G50<>"",G50,($I$9/$I$12-SUM($U$25:U49))*V50*W50/SUMPRODUCT($W50:$W$58,$V50:$V$58)),""),"")
A51: 27 | F51: =IF(AND(E51<>"",E51<>0),D51/E51,"") | H51: =IF(AND(G51<>"",G51<>0),D51/G51,"") | J51: =IF(AND(G51<>"",G51<>0),E51/G51,"") | N51: =IF(AND(I51<>"",I51<>0),G51/I51,"") | O51: =D51/P51 -> #DIV/0! | P51: =$I$8*V51*W51/SUMPRODUCT($W$25:$W$56,$V$25:$V$56) -> 0 | Q51: =$I$9*V51*W51/SUMPRODUCT($W$25:$W$58,$V$25:$V$58) -> 0 | R51: =IF($I$12="","",Q51/$I$12) -> 0 | S51: =IF(W51<>"",IF(D51<>"",D51,($I$8-SUM($S$25:S50))*V51*W51/SUMPRODUCT($W51:$W$58,$V51:$V$58)),"") | T51: =IF(W51<>"",IF(E51<>"",E51,($I$9-SUM($T$25:T50))*V51*W51/SUMPRODUCT($W51:$W$58,$V51:$V$58)),"") | U51: =IF(W51<>"",IF($I$12<>"",IF(G51<>"",G51,($I$9/$I$12-SUM($U$25:U50))*V51*W51/SUMPRODUCT($W51:$W$58,$V51:$V$58)),""),"")
A52: 28 | F52: =IF(AND(E52<>"",E52<>0),D52/E52,"") | H52: =IF(AND(G52<>"",G52<>0),D52/G52,"") | J52: =IF(AND(G52<>"",G52<>0),E52/G52,"") | N52: =IF(AND(I52<>"",I52<>0),G52/I52,"") | O52: =D52/P52 -> #DIV/0! | P52: =$I$8*V52*W52/SUMPRODUCT($W$25:$W$56,$V$25:$V$56) -> 0 | Q52: =$I$9*V52*W52/SUMPRODUCT($W$25:$W$58,$V$25:$V$58) -> 0 | R52: =IF($I$12="","",Q52/$I$12) -> 0 | S52: =IF(W52<>"",IF(D52<>"",D52,($I$8-SUM($S$25:S51))*V52*W52/SUMPRODUCT($W52:$W$58,$V52:$V$58)),"") | T52: =IF(W52<>"",IF(E52<>"",E52,($I$9-SUM($T$25:T51))*V52*W52/SUMPRODUCT($W52:$W$58,$V52:$V$58)),"") | U52: =IF(W52<>"",IF($I$12<>"",IF(G52<>"",G52,($I$9/$I$12-SUM($U$25:U51))*V52*W52/SUMPRODUCT($W52:$W$58,$V52:$V$58)),""),"")
A53: 29 | F53: =IF(AND(E53<>"",E53<>0),D53/E53,"") | H53: =IF(AND(G53<>"",G53<>0),D53/G53,"") | J53: =IF(AND(G53<>"",G53<>0),E53/G53,"") | N53: =IF(AND(I53<>"",I53<>0),G53/I53,"") | O53: =D53/P53 -> #DIV/0! | P53: =$I$8*V53*W53/SUMPRODUCT($W$25:$W$56,$V$25:$V$56) -> 0 | Q53: =$I$9*V53*W53/SUMPRODUCT($W$25:$W$58,$V$25:$V$58) -> 0 | R53: =IF($I$12="","",Q53/$I$12) -> 0 | S53: =IF(W53<>"",IF(D53<>"",D53,($I$8-SUM($S$25:S52))*V53*W53/SUMPRODUCT($W53:$W$58,$V53:$V$58)),"") | T53: =IF(W53<>"",IF(E53<>"",E53,($I$9-SUM($T$25:T52))*V53*W53/SUMPRODUCT($W53:$W$58,$V53:$V$58)),"") | U53: =IF(W53<>"",IF($I$12<>"",IF(G53<>"",G53,($I$9/$I$12-SUM($U$25:U52))*V53*W53/SUMPRODUCT($W53:$W$58,$V53:$V$58)),""),"")
F54: =IF(AND(E54<>"",E54<>0),D54/E54,"") | H54: =IF(AND(G54<>"",G54<>0),D54/G54,"") | J54: =IF(AND(G54<>"",G54<>0),E54/G54,"") | N54: =IF(AND(I54<>"",I54<>0),G54/I54,"") | O54: =D54/P54 -> #DIV/0! | P54: =$I$8*V54*W54/SUMPRODUCT($W$25:$W$56,$V$25:$V$56) -> 0 | Q54: =$I$9*V54*W54/SUMPRODUCT($W$25:$W$58,$V$25:$V$58) -> 0 | R54: =IF($I$12="","",Q54/$I$12) -> 0 | S54: =IF(W54<>"",IF(D54<>"",D54,($I$8-SUM($S$25:S50))*V54*W54/SUMPRODUCT($W54:$W$58,$V54:$V$58)),"") | T54: =IF(W54<>"",IF(E54<>"",E54,($I$9-SUM($T$25:T50))*V54*W54/SUMPRODUCT($W54:$W$58,$V54:$V$58)),"") | U54: =IF(W54<>"",IF($I$12<>"",IF(G54<>"",G54,($I$9/$I$12-SUM($U$25:U50))*V54*W54/SUMPRODUCT($W54:$W$58,$V54:$V$58)),""),"")
F55: =IF(AND(E55<>"",E55<>0),D55/E55,"") | H55: =IF(AND(G55<>"",G55<>0),D55/G55,"") | J55: =IF(AND(G55<>"",G55<>0),E55/G55,"") | N55: =IF(AND(I55<>"",I55<>0),G55/I55,"") | O55: =D55/P55 -> #DIV/0! | P55: =$I$8*V55*W55/SUMPRODUCT($W$25:$W$56,$V$25:$V$56) -> 0 | Q55: =$I$9*V55*W55/SUMPRODUCT($W$25:$W$58,$V$25:$V$58) -> 0 | R55: =IF($I$12="","",Q55/$I$12) -> 0 | S55: =IF(W55<>"",IF(D55<>"",D55,($I$8-SUM($S$25:S54))*V55*W55/SUMPRODUCT($W55:$W$58,$V55:$V$58)),"") | T55: =IF(W55<>"",IF(E55<>"",E55,($I$9-SUM($T$25:T54))*V55*W55/SUMPRODUCT($W55:$W$58,$V55:$V$58)),"") | U55: =IF(W55<>"",IF($I$12<>"",IF(G55<>"",G55,($I$9/$I$12-SUM($U$25:U54))*V55*W55/SUMPRODUCT($W55:$W$58,$V55:$V$58)),""),"")
F56: =IF(AND(E56<>"",E56<>0),D56/E56,"") | H56: =IF(AND(G56<>"",G56<>0),D56/G56,"") | J56: =IF(AND(G56<>"",G56<>0),E56/G56,"") | N56: =IF(AND(I56<>"",I56<>0),G56/I56,"") | O56: =D56/P56 -> #DIV/0! | P56: =$I$8*V56*W56/SUMPRODUCT($W$25:$W$56,$V$25:$V$56) -> 0 | Q56: =$I$9*V56*W56/SUMPRODUCT($W$25:$W$58,$V$25:$V$58) -> 0 | R56: =IF($I$12="","",Q56/$I$12) -> 0 | S56: =IF(W56<>"",IF(D56<>"",D56,($I$8-SUM($S$25:S55))*V56*W56/SUMPRODUCT($W56:$W$58,$V56:$V$58)),"") | T56: =IF(W56<>"",IF(E56<>"",E56,($I$9-SUM($T$25:T55))*V56*W56/SUMPRODUCT($W56:$W$58,$V56:$V$58)),"") | U56: =IF(W56<>"",IF($I$12<>"",IF(G56<>"",G56,($I$9/$I$12-SUM($U$25:U55))*V56*W56/SUMPRODUCT($W56:$W$58,$V56:$V$58)),""),"")
D57: =SUM(D25:D56) -> 1265396.1 | E57: =SUM(E25:E56) -> 186 | F57: =IF(AND(E57<>"",E57<>0),D57/E57,"") -> 6803.2047 | G57: =SUM(G25:G56) -> 104 | H57: =IF(AND(G57<>"",G57<>0),D57/G57,"") -> 12167.27 | I57: =SUM(I25:I56) -> 906.5 | J57: =IF(AND(G57<>"",G57<>0),E57/G57,"") -> 1.7884615 | K57: =SUM(K25:K56) -> 376403 | L57: =SUM(L25:L56) -> 56655 | M57: =SUM(M25:M56) -> 91714 | N57: =IF(AND(I57<>"",I57<>0),G57/I57,"") -> 0.11472697 | O57: =D57/P57 -> 0.82921047 | P57: =SUM(P25:P56) -> 1526025.2 | Q57: =SUM(Q25:Q55) -> 254.33753 | R57: =SUM(R25:R55) -> 141.29863 | S57: =SUM(S25:S56) -> 1526025.2 | T57: =SUM(T25:T55) -> 254.33753 | U57: =SUM(U25:U55) -> 141.29863

Sheet Вед-ть Рогалевич
A1: =График!B1 -> Сентябрь, 2025
A2: =График!B3 -> ул. Набережная Ленина, 18 | D2: =График!B4 -> GL-0005
A3: Сотрудник | D3: Выплачено на карту | E3: Выплачено наличными по платежной ведомости | F3: Дополнительные начисления, доплаты | G3: Оклад | H3: Бонусная часть от личных продаж | I3: Бонусная часть от общих продаж | J3: Базовый бонус за выполнение плана | K3: Итого: | L3: Вычеты | M3: Итого к выдаче с учетом авансов и вычетов | N3: Подпись
A4: =График!B29 -> Рогалевич Ирина | D4: =19140*2 -> 38280 | F4: =H8+H9+G16+G24+L24 -> 38344.271 | G4: =D11 -> 30650 | H4: =D18 -> 112141.86 | I4: =L18 -> 35094.133 | J4: =L11 -> 2310 | K4: =H4+J4+G4+F4+I4 -> 218540.26 | L4: =C8+C9 -> 5720 | M4: =K4-L4-D4-E4 -> 174540.26
B6: Вычеты | G6: Доп начисления
B7: Дата | C7: Сумма | D7: Описание | G7: Дата | H7: Сумма | J7: Описание
B8: 45930 | C8: =44000-D4 -> 5720 | D8: НДФЛ июль 2025 | G8: 45930 | H8: ='Ялта, Ленина, 18'!J8*0.01 -> 31344.271 | J8: Административный %
G9: 45930 | H9: 7000 | J9: Конкурс КВП, Акция
A11: Оклад: | D11: =G15 -> 30650 | I11: Базовый бонус за выполнение плана | L11: =L15+L16 -> 2310
B13: Оклад: | J13: Базовый бонус за выполнение плана
B14: Дней | C14: Магазин | D14: Должность | E14: Зачислено часов | F14: Ставка за час, руб | G14: Начислено за день, руб | J14: Магазин | K14: КВП | L14: Начисленный ББ
B15: =График!AI29 -> 30 | C15: =A2 -> ул. Набережная Ленина, 18 | D15: =График!C29 -> УМ | E15: =График!AJ29 -> 306.5 | F15: 100 | G15: =E15*F15 -> 30650 | J15: =График!B3 -> ул. Набережная Ленина, 18 | K15: ='Ялта, Ленина, 18'!K8 -> 0.90412688 | L15: 2310
G16: =E16*F16 -> 0
A18: БонуснаяЧасть | D18: =G23 -> 112141.86 | I18: Бонусная часть от общих продаж | L18: =N23 -> 35094.133
B21: Бонус от личных продаж по категории товара | I21: Бонус от общих продаж
B22: Сотрудник | C22: Магазин | E22: Процент от продажи | F22: Продано на сумму, руб | G22: Начисленный бонус от продаж, руб | I22: Сотрудник | J22: Магазин | K22: Кол-во отработанных личных часов | L22: Кол-во отработанных общих часов | M22: Процент от продажи | N22: Начисленный бонус от продаж, руб
B23: =A4 -> Рогалевич Ирина | C23: =A2 -> ул. Набережная Ленина, 18 | E23: 0.06 | F23: ='Рогалевич И. Е. '!J8 -> 1869031 | G23: =F23*E23 -> 112141.86 | I23: =B23 -> Рогалевич Ирина | J23: =C23 -> ул. Набережная Ленина, 18 | K23: =E15 -> 306.5 | L23: =График!AJ31 -> 547.5 | M23: 0.02 | N23: ='Ялта, Ленина, 18'!J8*M23*K23/L23 -> 35094.133
B24: =B23 -> Рогалевич Ирина | C24: =C16 -> 0 | G24: =F24*E24 -> 0 | N24: =1477363.14*M24*K24/L24 -> #DIV/0!

Sheet Вед-ть Уразгильдеева
A1: =График!B1 -> Сентябрь, 2025
A2: =График!B3 -> ул. Набережная Ленина, 18 | D2: =График!B4 -> GL-0005
A3: Сотрудник | D3: Выплачено на карту | E3: Выплачено наличными по платежной ведомости | F3: Дополнительные начисления, доплаты | G3: Оклад | H3: Бонусная часть от личных продаж | I3: Бонусная часть от общих продаж | J3: Базовый бонус за выполнение плана | K3: Итого: | L3: Вычеты | M3: Итого к выдаче с учетом авансов и вычетов | N3: Подпись
A4: =График!B28 -> Уразгильдеева Екатерина | D4: =17400*2 -> 34800 | F4: =H8+H9 -> 0 | G4: =D12 -> 24100 | H4: =D19 -> 75923.765 | I4: =L19 -> 27594.408 | J4: =L12 -> 2310 | K4: =H4+J4+G4+F4+I4 -> 129928.17 | L4: =C8+C9+C10 -> 5200 | M4: =K4-L4-D4-E4 -> 89928.173
B6: Вычеты | G6: Доп начисления
B7: Дата | C7: Сумма | D7: Описание | G7: Дата | H7: Сумма | J7: Описание
B8: 45930 | C8: =40000-D4 -> 5200 | D8: НДФЛ сентябрь 2025
A12: Оклад: | D12: =G16 -> 24100 | I12: Базовый бонус за выполнение плана | L12: =L16+L17 -> 2310
B14: Оклад: | J14: Базовый бонус за выполнение плана
B15: Дней | C15: Магазин | D15: Должность | E15: Зачислено часов | F15: Ставка за час, руб | G15: Начислено за день, руб | J15: Магазин | K15: КВП | L15: Начисленный ББ
B16: =График!AI28 -> 22 | C16: =A2 -> ул. Набережная Ленина, 18 | D16: ПК | E16: =График!AJ28 -> 241 | F16: 100 | G16: =E16*F16 -> 24100 | J16: =График!B3 -> ул. Набережная Ленина, 18 | K16: ='Ялта, Ленина, 18'!K8 -> 0.90412688 | L16: 2310
A19: БонуснаяЧасть | D19: =G24 -> 75923.765 | I19: Бонусная часть от общих продаж | L19: =N24 -> 27594.408
B22: Бонус от личных продаж по категории товара | I22: Бонус от общих продаж
B23: Сотрудник | C23: Магазин | E23: Процент от продажи | F23: Продано на сумму, руб | G23: Начисленный бонус от продаж, руб | I23: Сотрудник | J23: Магазин | K23: Кол-во отработанных личных часов | L23: Кол-во отработанных общих часов | M23: Процент от продажи | N23: Начисленный бонус от продаж, руб
B24: =A4 -> Уразгильдеева Екатерина | C24: =A2 -> ул. Набережная Ленина, 18 | E24: 0.06 | F24: ='Уразгильдеева Е. Р. '!J8 -> 1265396.1 | G24: =F24*E24 -> 75923.765 | I24: =B24 -> Уразгильдеева Екатерина | J24: =C24 -> ул. Набережная Ленина, 18 | K24: =E16 -> 241 | L24: =График!AJ31 -> 547.5 | M24: 0.02 | N24: ='Ялта, Ленина, 18'!J8*M24*K24/L24 -> 27594.408
B25: =B24 -> Уразгильдеева Екатерина | N25: =1477363.14*M25*K25/L25 -> #DIV/0!

Sheet Вед-ть ПК2
A1: =График!B1 -> Сентябрь, 2025
A2: =График!B3 -> ул. Набережная Ленина, 18 | D2: =График!B4 -> GL-0005
A3: Сотрудник | D3: Выплачено на карту | E3: Выплачено наличными по платежной ведомости | F3: Дополнительные начисления, доплаты | G3: Оклад | H3: Бонусная часть от личных продаж | I3: Бонусная часть от общих продаж | J3: Базовый бонус за выполнение плана | K3: Итого: | L3: Вычеты | M3: Итого к выдаче с учетом авансов и вычетов | N3: Подпись
A4: =График!B27 -> 0 | F4: =H8+H9 -> 0 | G4: =D12 -> 0 | H4: =D19 -> #REF! | I4: =L19 -> 0 | J4: =L12 -> 0 | K4: =H4+J4+G4+F4+I4 -> #REF! | L4: =C8+C9+C10 -> 0 | M4: =K4-L4-D4-E4 -> #REF!
B6: Вычеты | G6: Доп начисления
B7: Дата | C7: Сумма | D7: Описание | G7: Дата | H7: Сумма | J7: Описание
D8: НДФЛ июнь 2025 | G8: 45830
A12: Оклад: | D12: =G16 -> 0 | I12: Базовый бонус за выполнение плана | L12: =L16+L17 -> 0
B14: Оклад: | J14: Базовый бонус за выполнение плана
B15: Дней | C15: Магазин | D15: Должность | E15: Зачислено часов | F15: Ставка за час, руб | G15: Начислено за день, руб | J15: Магазин | K15: КВП | L15: Начисленный ББ
B16: =График!AI27 -> 0 | C16: =A2 -> ул. Набережная Ленина, 18 | D16: ПК | E16: =График!AJ27 -> 0 | F16: 100 | G16: =E16*F16 -> 0 | J16: =График!B3 -> ул. Набережная Ленина, 18 | K16: ='Ялта, Ленина, 18'!K8 -> 0.90412688 | L16: 0
A19: БонуснаяЧасть | D19: =G24 -> #REF! | I19: Бонусная часть от общих продаж | L19: =N24 -> 0
B22: Бонус от личных продаж по категории товара | I22: Бонус от общих продаж
B23: Сотрудник | C23: Магазин | E23: Процент от продажи | F23: Продано на сумму, руб | G23: Начисленный бонус от продаж, руб | I23: Сотрудник | J23: Магазин | K23: Кол-во отработанных личных часов | L23: Кол-во отработанных общих часов | M23: Процент от продажи | N23: Начисленный бонус от продаж, руб
B24: =A4 -> 0 | C24: =A2 -> ул. Набережная Ленина, 18 | E24: 0.045 | F24: =#REF! -> #REF! | G24: =F24*E24 -> #REF! | I24: =B24 -> 0 | J24: =C24 -> ул. Набережная Ленина, 18 | K24: =E16 -> 0 | L24: =График!AJ31 -> 547.5 | M24: 0.02 | N24: =1880591*M24*K24/L24 -> 0
B25: =B24 -> 0

Sheet График
B1: Сентябрь, 2025 | T1: в
B2: г. Ялта
B3: ул. Набережная Ленина, 18
B4: GL-0005
B5: 10.00-23.00
B6: ФОТ | C6: Кол-во дней в месяц | AK6: 30
B7: =BT31*100/BH31 -> #DIV/0!
D8: пн | E8: вт | F8: ср | G8: чт | H8: пт | I8: сб | J8: вс | K8: пн | L8: вт | M8: ср | N8: чт | O8: пт | P8: сб | Q8: вс | R8: пн | S8: вт | T8: ср | U8: чт | V8: пт | W8: сб | X8: вс | Y8: пн | Z8: вт | AA8: ср | AB8: чт | AC8: пт | AD8: сб | AE8: вс | AF8: пн | AG8: вт | AJ8: Часы | AK8: Выходные | AL8: Отпуск | AM8: Больничный (официальный) | AN8: Дни стажировки
A10: № | B10: ФИО | C10: Должность | D10: 1 | E10: 2 | F10: 3 | G10: 4 | H10: 5 | I10: 6 | J10: 7 | K10: 8 | L10: 9 | M10: 10 | N10: 11 | O10: 12 | P10: 13 | Q10: 14 | R10: 15 | S10: 16 | T10: 17 | U10: 18 | V10: 19 | W10: 20 | X10: 21 | Y10: 22 | Z10: 23 | AA10: 24 | AB10: 25 | AC10: 26 | AD10: 27 | AE10: 28 | AF10: 29 | AG10: 30 | AI10: Дни
A11: 20 | AI11: 0 | AJ11: 0 | AK11: 0 | AL11: 0 | AM11: 0 | AN11: 0
A12: 19 | AI12: 0 | AJ12: 0 | AK12: 0 | AL12: 0 | AM12: 0 | AN12: 0
A13: 18 | AI13: 0 | AJ13: 0 | AK13: 0 | AL13: 0 | AM13: 0 | AN13: 0
A14: 17 | AI14: 0 | AJ14: 0 | AK14: 0 | AL14: 0 | AM14: 0 | AN14: 0
A15: 16 | AI15: 0 | AJ15: 0 | AK15: 0 | AL15: 0 | AM15: 0 | AN15: 0
A16: 15 | AI16: 0 | AJ16: 0 | AK16: 0 | AL16: 0 | AM16: 0 | AN16: 0
A17: 14 | AI17: 0 | AJ17: 0 | AK17: 0 | AL17: 0 | AM17: 0 | AN17: 0
A18: 13 | AI18: 0 | AJ18: 0 | AK18: 0 | AL18: 0 | AM18: 0 | AN18: 0
A19: 12 | AI19: 0 | AJ19: 0 | AK19: 0 | AL19: 0 | AM19: 0 | AN19: 0
A20: 11 | AI20: 0 | AJ20: 0 | AK20: 0 | AL20: 0 | AM20: 0 | AN20: 0
A21: 10 | AI21: 0 | AJ21: 0 | AK21: 0 | AL21: 0 | AM21: 0 | AN21: 0
A22: 9 | AI22: =COUNTIF(D22:AH22, ">0") -> 0 | AJ22: 0 | AK22: 0 | AL22: 0 | AM22: 0 | AN22: 0
A23: 8 | AI23: =COUNTIF(D23:AH23, ">0") -> 0 | AJ23: 0 | AK23: 0 | AL23: 0 | AM23: 0 | AN23: 0
A24: 7 | AI24: =COUNTIF(D24:AH24, ">0") -> 0 | AJ24: 0 | AK24: 0 | AL24: 0 | AM24: 0 | AN24: 0
A25: 6 | AI25: =COUNTIF(D25:AH25,">0") -> 0 | AJ25: =SUMIF(D25:AH25,">0") -> 0 | AK25: =COUNTIF(D25:AH25,"В") -> 0 | AL25: =COUNTIF(E25:AI25,"о") -> 0 | AM25: =COUNTIF(F25:AJ25,"б") -> 0 | AN25: 0
A26: 5 | AI26: =COUNTIF(D26:AH26, ">0") -> 0 | AJ26: =SUMIF(D26:AH26,">0") -> 0 | AK26: =COUNTIF(D26:AH26, "В") -> 0 | AL26: 0 | AM26: 0 | AN26: 0
A27: 4 | AI27: =COUNTIF(D27:AH27,">0") -> 0 | AJ27: =SUMIF(D27:AH27,">0") -> 0 | AK27: =COUNTIF(D27:AH27,"В") -> 0 | AL27: =COUNTIF(E27:AI27,"о") -> 0 | AM27: =COUNTIF(F27:AJ27,"б") -> 0 | AN27: 0
A28: 3 | B28: Уразгильдеева Екатерина | C28: ПК | D28: 13 | E28: 9 | F28: 13 | G28: в | H28: 11 | I28: 9 | J28: 10 | K28: 13 | L28: в | M28: 13 | N28: 11 | O28: в | P28: 13 | Q28: 9 | R28: 10 | S28: 13 | T28: в | U28: в | V28: 13 | W28: 13 | X28: 10 | Y28: в | Z28: 12 | AA28: 9 | AB28: в | AC28: 12 | AD28: 6 | AE28: 12 | AF28: 7 | AG28: в | AI28: =COUNTIF(D28:AH28,">0") -> 22 | AJ28: =SUMIF(D28:AH28,">0") -> 241 | AK28: =COUNTIF(D28:AH28,"В") -> 8 | AL28: =COUNTIF(E28:AI28,"о") -> 0 | AM28: =COUNTIF(F28:AJ28,"б") -> 0 | AN28: 0
A29: 2 | B29: Рогалевич Ирина | C29: УМ | D29: 9 | E29: 13 | F29: 9 | G29: 13 | H29: 9 | I29: 11 | J29: 8 | K29: 9 | L29: 13 | M29: 9 | N29: 9 | O29: 13 | P29: 9 | Q29: 11 | R29: 10 | S29: 10 | T29: 13 | U29: 12.5 | V29: 8 | W29: 11 | X29: 11 | Y29: 12 | Z29: 8 | AA29: 10 | AB29: 12 | AC29: 5 | AD29: 12 | AE29: 6 | AF29: 9 | AG29: 12 | AI29: =COUNTIF(D29:AH29,">0") -> 30 | AJ29: =SUMIF(D29:AH29,">0") -> 306.5 | AK29: =COUNTIF(D29:AH29,"В") -> 0 | AL29: =COUNTIF(E29:AI29,"о") -> 0 | AM29: =COUNTIF(F29:AJ29,"б") -> 0 | AN29: 0
A30: 1 | AI30: =COUNTIF(D30:AH30, ">0") -> 0 | AJ30: =SUMIF(D30:AH30,">0") -> 0 | AK30: =COUNTIF(D30:AH30, "В") -> 0 | AL30: =COUNTIF(E30:AI30, "о") -> 0 | AM30: =COUNTIF(F30:AJ30, "б") -> 0 | AN30: 0
B31: Итого магазин | D31: =COUNTIF(D11:D30, ">0") -> 2 | E31: =COUNTIF(E11:E30, ">0") -> 2 | F31: =COUNTIF(F11:F30, ">0") -> 2 | G31: =COUNTIF(G11:G30, ">0") -> 1 | H31: =COUNTIF(H11:H30, ">0") -> 2 | I31: =COUNTIF(I11:I30, ">0") -> 2 | J31: =COUNTIF(J11:J30, ">0") -> 2 | K31: =COUNTIF(K11:K29, ">0") -> 2 | L31: =COUNTIF(L11:L30, ">0") -> 1 | M31: =COUNTIF(M11:M30, ">0") -> 2 | N31: =COUNTIF(N11:N30, ">0") -> 2 | O31: =COUNTIF(O11:O30, ">0") -> 1 | P31: =COUNTIF(P11:P30, ">0") -> 2 | Q31: =COUNTIF(Q11:Q30, ">0") -> 2 | R31: =COUNTIF(R11:R30, ">0") -> 2 | S31: =COUNTIF(S11:S30, ">0") -> 2 | ... AH31: =COUNTIF(AH11:AH30, ">0") -> 0 | AJ31: =SUM(AJ11:AJ30) -> 547.5 | AK31: =SUM(AK11:AK30) -> 8 | AL31: =SUM(AL11:AL30) -> 0 | AM31: =SUM(AM11:AM30) -> 0 | AN31: =SUM(AN11:AN30) -> 0
B33: График рандомный для приблизительного прогноза по продажам.
