Workbook
Name маг: NA()

Sheet Ялта, Ленина, 18
B1: =TODAY()-1 -> 45696
B2: (отчетная дата)
C3: Осталось до выполнения плана!!! | I3: =График!B3 -> ул. Набережная Ленина, 18
C4: =I8-D56 -> 229032.36 | E4: =IF(I8<>0, C4/I8, 0) -> 0.1272402
F6: Целевые показатели
F7: Показатель | I7: План | J7: Факт | K7: % выполнения | L7: Прогноз выполнения | M7: % выполнения по прогнозу | N7: Отклонение | O7: Факт аналогичного месяца прошлого года | P7: Отклонение LFL
F8: Выручка | I8: 1800000 | J8: =D56 -> 1570967.6 | K8: =IF(AND(I8<>"", I8<>0, J8<>""), J8/I8, "") -> 0.8727598 | L8: =IF(SUMIF($D$25:$D$55,">=0",$P$25:$P$55)<>0,I8*D56/SUMIF($D$25:$D$55,">=0",$P$25:$P$55),0) -> 1570967.6 | M8: =IF(AND(I8<>"", I8<>0, L8<>"", L8<>0), L8/I8, "") -> 0.8727598 | N8: =IF(AND(J8<>0, J8<>"", I8<>0, I8<>""), L8-I8, "") -> -229032.36 | P8: =IF(AND(O8<>"", O8<>0, L8<>"", L8<>0), -O8+L8, "") | Q8: =IF(AND(P8<>"", P8<>0, O8<>0, O8<>""), P8/O8, "")
F9: Кол-во изделий | I9: =I8/I11 -> 487.80488 | J9: =E56 -> 409 | K9: =IF(AND(I9<>"", I9<>0, J9<>""), J9/I9, "") -> 0.83845 | L9: =IF(SUMIF($E$25:$E$55, ">=0", $Q$25:$Q$55)<>0, I9*E56/SUMIF($E$25:$E$55, ">=0", $Q$25:$Q$55), 0) -> 409 | M9: =IF(AND(I9<>"", I9<>0, L9<>"", L9<>0), L9/I9, "") -> 0.83845 | N9: =IF(AND(J9<>0, J9<>"", I9<>0, I9<>""), L9-I9, "") -> -78.804878 | O9: =O8/O11 -> #DIV/0! | P9: =IF(AND(O9<>"", O9<>0, L9<>"", L9<>0), -O9+L9, "") -> #DIV/0! | Q9: =IF(AND(P9<>"", P9<>0, O9<>0, O9<>""), P9/O9, "") -> #DIV/0!
F10: Средний чек | I10: =I11*I12 -> 5904 | J10: =H56 -> 7777.0675 | K10: =IF(AND(I10<>"", I10<>0, J10<>""), J10/I10, "") -> 1.317254 | L10: =J10 -> 7777.0675 | M10: =IF(AND(I10<>"", I10<>0, L10<>"", L10<>0), L10/I10, "") -> 1.317254 | N10: =IF(AND(J10<>0, J10<>"", I10<>0, I10<>""), L10-I10, "") -> 1873.0675 | O10: =O11*O12 -> 0 | P10: =IF(AND(O10<>"", O10<>0, L10<>"", L10<>0), -O10+L10, "") | Q10: =IF(AND(P10<>"", P10<>0, O10<>0, O10<>""), P10/O10, "")
F11: Средняя стоимость изделия | I11: 3690 | J11: =F56 -> 3840.9967 | K11: =IF(AND(I11<>"", I11<>0, J11<>""), J11/I11, "") -> 1.0409205 | L11: =IF(L9>0, L8/L9, "") -> 3840.9967 | M11: =IF(AND(I11<>"", I11<>0, L11<>"", L11<>0), L11/I11, "") -> 1.0409205 | N11: =IF(AND(J11<>0, J11<>"", I11<>0, I11<>""), L11-I11, "") -> 150.99667 | P11: =IF(AND(O11<>"", O11<>0, L11<>"", L11<>0), -O11+L11, "") | Q11: =IF(AND(P11<>"", P11<>0, O11<>0, O11<>""), P11/O11, "")
F12: Длина чека | I12: 1.6 | J12: =J56 -> 2.0247525 | K12: =IF(AND(I12<>"", I12<>0, J12<>""), J12/I12, "") -> 1.2654703 | L12: =J12 -> 2.0247525 | M12: =IF(AND(I12<>"", I12<>0, L12<>"", L12<>0), L12/I12, "") -> 1.2654703 | N12: =IF(AND(J12<>0, J12<>"", I12<>0, I12<>""), L12-I12, "") -> 0.42475248 | P12: =IF(AND(O12<>"", O12<>0, L12<>"", L12<>0), -O12+L12, "") | Q12: =IF(AND(P12<>"", P12<>0, O12<>0, O12<>""), P12/O12, "")
F13: Кол-во чеков | I13: =I17*I20 -> 0 | J13: =G56 -> 202 | K13: =IF(AND(I13<>"", I13<>0, J13<>""), J13/I13, "") | L13: =IF(SUMIF($G$25:$G$55, ">=0", $R$25:$R$55)<>0, I13*G56/SUMIF($G$25:$G$55, ">=0", $R$25:$R$55), "") -> 0 | M13: =IF(AND(I13<>"", I13<>0, L13<>"", L13<>0), L13/I13, "") | N13: =IF(AND(J13<>0, J13<>"", I13<>0, I13<>""), L13-I13, "") | P13: =IF(AND(O13<>"", O13<>0, L13<>"", L13<>0), -O13+L13, "") | Q13: =IF(AND(P13<>"", P13<>0, O13<>0, O13<>""), P13/O13, "")
F14: Кол-во смен | I14: 30 | J14: 30 | K14: =IF(AND(I14<>"", I14<>0, J14<>""), J14/I14, "") -> 1 | L14: =IF(SUMIF($D$25:$D$55,">=0",$P$25:$P$55),I56*I8/SUMIF($D$25:$D$55,">=0",$P$25:$P$55),"") -> 0 | M14: =IF(AND(I14<>"", I14<>0, L14<>"", L14<>0), L14/I14, "") | N14: =IF(AND(J14<>0, J14<>"", I14<>0, I14<>""), L14-I14, "") -> -30 | P14: =IF(AND(O14<>"", O14<>0, L14<>"", L14<>0), -O14+L14, "") | Q14: =IF(AND(P14<>"", P14<>0, O14<>0, O14<>""), P14/O14, "")
F15: Средние продажи в смену | I15: =I8/I14 -> 60000 | J15: =J8/J14 -> 52365.588 | K15: =IF(AND(I15<>"", I15<>0, J15<>""), J15/I15, "") -> 0.8727598 | L15: =J15 -> 52365.588 | M15: =IF(AND(I15<>"", I15<>0, L15<>"", L15<>0), L15/I15, "") -> 0.8727598 | N15: =IF(AND(J15<>0, J15<>"", I15<>0, I15<>""), L15-I15, "") -> -7634.412 | P15: =IF(AND(O15<>"", O15<>0, L15<>"", L15<>0), -O15+L15, "") | Q15: =IF(AND(P15<>"", P15<>0, O15<>0, O15<>""), P15/O15, "")
F16: Отставание/Перевыполнение | J16: =J8-I15*J14 -> -229032.36 | K16: =IF(AND(I16<>"", I16<>0, J16<>""), J16/I16, "") | L16: =J16 -> -229032.36 | M16: =IF(AND(I16<>"", I16<>0, L16<>"", L16<>0), L16/I16, "") | N16: =IF(AND(J16<>0, J16<>"", I16<>0, I16<>""), L16-I16, "") | P16: =IF(AND(O16<>"", O16<>0, L16<>"", L16<>0), -O16+L16, "") | Q16: =IF(AND(P16<>"", P16<>0, O16<>0, O16<>""), P16/O16, "") | S16: Подарочные сертификаты
F17: Трафик | J17: =I56 -> 0 | K17: =IF(AND(I17<>"", I17<>0, J17<>""), J17/I17, "") | L17: =J17 -> 0 | M17: =IF(AND(I17<>"", I17<>0, L17<>"", L17<>0), L17/I17, "") | N17: =IF(AND(J17<>0, J17<>"", I17<>0, I17<>""), L17-I17, "") | P17: =IF(AND(O17<>"", O17<>0, L17<>"", L17<>0), -O17+L17, "") | Q17: =IF(AND(P17<>"", P17<>0, O17<>0, O17<>""), P17/O17, "")
K18: =IF(AND(I18<>"", I18<>0, J18<>""), J18/I18, "") | L18: =J18 -> 0 | M18: =IF(AND(I18<>"", I18<>0, L18<>"", L18<>0), L18/I18, "") | N18: =IF(AND(J18<>0, J18<>"", I18<>0, I18<>""), L18-I18, "") | O18: 0 | P18: =IF(AND(O18<>"", O18<>0, L18<>"", L18<>0), -O18+L18, "") | Q18: =IF(AND(P18<>"", P18<>0, O18<>0, O18<>""), P18/O18, "")
J19: =M56 -> 0 | K19: =IF(AND(I19<>"", I19<>0, J19<>""), J19/I19, "") | L19: =J19 -> 0 | M19: =IF(AND(I19<>"", I19<>0, L19<>"", L19<>0), L19/I19, "") | N19: =IF(AND(J19<>0, J19<>"", I19<>0, I19<>""), L19-I19, "") | O19: 0 | P19: =IF(AND(O19<>"", O19<>0, L19<>"", L19<>0), -O19+L19, "") | Q19: =IF(AND(P19<>"", P19<>0, O19<>0, O19<>""), P19/O19, "") | S19: =S18/I16 -> #DIV/0!
F20: Конверсия план/факт | I20: 0.257 | J20: =N56 | K20: =J20/I20 -> #VALUE! | L20: =IF(AND(K8<>0, I14<>0, I56<>0), (I56*N56+(I56/K8-I56)*I20)/(I56/K8), 0) -> 0 | M20: =IF(AND(I20<>"", I20<>0, L20<>"", L20<>0), L20/I20, "") | N20: =IF(AND(J20<>0, J20<>"", I20<>0, I20<>""), L20-I20, "") | P20: =IF(AND(O20<>"", O20<>0, L20<>"", L20<>0), -O20+L20, "") | Q20: =IF(AND(P20<>"", P20<>0, O20<>0, O20<>""), P20/O20, "")
A22: Факт продаж за месяц | O22: % выполнения дневного плана | P22: Раcпределение плана по дням
A23: Сотрудник | B23: Дата | C23: День недели | D23: Выручка (руб) | E23: Кол-во единиц (шт.) | F23: Средняя стоимость изделия (руб.) | G23: Количество чеков (шт.) | H23: Средняя сумма чека (руб.) | I23: Трафик | J23: Длина чека (шт.) | K23: Запасной | L23: Запасной | M23: Запасной | N23: Конверсия (%) | P23: выручка, план | Q23: кол-во ед, план | R23: Кол-во чеков, план | S23: выручка, скорректир.план | T23: кол-во ед, скорр. план | U23: кол-во чеков, скорр. план | V23: Коэфф. Дня Недели | W23: Специфика месяца
B24: 1 | C24: 2 | D24: 3 | E24: 4 | F24: 5 | G24: 6 | H24: 7 | I24: 8 | J24: 9 | K24: 10 | L24: 11 | M24: 12 | N24: 13 | P24: 1 | Q24: 2 | R24: 3 | S24: 4 | T24: 5 | U24: 6 | V24: 10 | W24: 11
B25: 45658 | C25: ср | F25: =IF(AND(E25<>"",E25<>0),D25/E25,"") | H25: =IF(AND(G25<>"",G25<>0),D25/G25,"") | J25: =IF(AND(G25<>"",G25<>0),E25/G25,"") | N25: =IF(AND(I25<>"",I25<>0),G25/I25,"") | O25: =D25/P25 -> #DIV/0! | P25: =$I$8*V25*W25/SUMPRODUCT($W$25:$W$55,$V$25:$V$55) -> 0 | Q25: =$I$9*V25*W25/SUMPRODUCT($W$25:$W$55,$V$25:$V$55) -> 0 | R25: =IF($I$12="","",Q25/$I$12) -> 0 | S25: =IF(D25<>"",D25,P25) -> 0 | T25: =IF(E25<>"",E25,Q25) -> 0 | U25: =IF(G25<>"",G25,R25) -> 0
A26: Кекош, Орешникова | B26: 45659 | C26: чт | D26: 140171.7 | E26: 36 | F26: =IF(AND(E26<>"",E26<>0),D26/E26,"") -> 3893.6583 | G26: 19 | H26: =IF(AND(G26<>"",G26<>0),D26/G26,"") -> 7377.4579 | J26: =IF(AND(G26<>"",G26<>0),E26/G26,"") -> 1.8947368 | N26: =IF(AND(I26<>"",I26<>0),G26/I26,"") | O26: =D26/P26 -> 1.4271339 | P26: =$I$8*V26*W26/SUMPRODUCT($W$25:$W$55,$V$25:$V$55) -> 98219.022 | Q26: =$I$9*V26*W26/SUMPRODUCT($W$25:$W$55,$V$25:$V$55) -> 26.617621 | R26: =IF($I$12="","",Q26/$I$12) -> 16.636013 | S26: =IF(W26<>"",IF(D26<>"",D26,($I$8-SUM($S$25:S25))*V26*W26/SUMPRODUCT($W26:$W$55,$V26:$V$55)),"") -> 140171.7 | T26: =IF(W26<>"",IF(E26<>"",E26,($I$9-SUM($T$25:T25))*V26*W26/SUMPRODUCT($W26:$W$55,$V26:$V$55)),"") -> 36 | U26: =IF(W26<>"",IF($I$12<>"",IF(G26<>"",G26,($I$9/$I$12-SUM($U$25:U25))*V26*W26/SUMPRODUCT($W26:$W$55,$V26:$V$55)),""),"") -> 19 | V26: 1.2 | W26: 1.2
A27: Кекош, Орешникова | B27: 45660 | C27: пт | D27: 91852 | E27: 25 | F27: =IF(AND(E27<>"",E27<>0),D27/E27,"") -> 3674.08 | G27: 13 | H27: =IF(AND(G27<>"",G27<>0),D27/G27,"") -> 7065.5385 | J27: =IF(AND(G27<>"",G27<>0),E27/G27,"") -> 1.9230769 | N27: =IF(AND(I27<>"",I27<>0),G27/I27,"") | O27: =D27/P27 -> 0.93517526 | P27: =$I$8*V27*W27/SUMPRODUCT($W$25:$W$55,$V$25:$V$55) -> 98219.022 | Q27: =$I$9*V27*W27/SUMPRODUCT($W$25:$W$55,$V$25:$V$55) -> 26.617621 | R27: =IF($I$12="","",Q27/$I$12) -> 16.636013 | S27: =IF(W27<>"",IF(D27<>"",D27,($I$8-SUM($S$25:S26))*V27*W27/SUMPRODUCT($W27:$W$55,$V27:$V$55)),"") -> 91852 | T27: =IF(W27<>"",IF(E27<>"",E27,($I$9-SUM($T$25:T26))*V27*W27/SUMPRODUCT($W27:$W$55,$V27:$V$55)),"") -> 25 | U27: =IF(W27<>"",IF($I$12<>"",IF(G27<>"",G27,($I$9/$I$12-SUM($U$25:U26))*V27*W27/SUMPRODUCT($W27:$W$55,$V27:$V$55)),""),"") -> 13 | V27: 1.2 | W27: 1.2
A28: Кекош, Орешникова | B28: 45661 | C28: сб | D28: 141443 | E28: 34 | F28: =IF(AND(E28<>"",E28<>0),D28/E28,"") -> 4160.0882 | G28: 18 | H28: =IF(AND(G28<>"",G28<>0),D28/G28,"") -> 7857.9444 | J28: =IF(AND(G28<>"",G28<>0),E28/G28,"") -> 1.8888889 | N28: =IF(AND(I28<>"",I28<>0),G28/I28,"") | O28: =D28/P28 -> 1.4400775 | P28: =$I$8*V28*W28/SUMPRODUCT($W$25:$W$55,$V$25:$V$55) -> 98219.022 | Q28: =$I$9*V28*W28/SUMPRODUCT($W$25:$W$55,$V$25:$V$55) -> 26.617621 | R28: =IF($I$12="","",Q28/$I$12) -> 16.636013 | S28: =IF(W28<>"",IF(D28<>"",D28,($I$8-SUM($S$25:S27))*V28*W28/SUMPRODUCT($W28:$W$55,$V28:$V$55)),"") -> 141443 | T28: =IF(W28<>"",IF(E28<>"",E28,($I$9-SUM($T$25:T27))*V28*W28/SUMPRODUCT($W28:$W$55,$V28:$V$55)),"") -> 34 | U28: =IF(W28<>"",IF($I$12<>"",IF(G28<>"",G28,($I$9/$I$12-SUM($U$25:U27))*V28*W28/SUMPRODUCT($W28:$W$55,$V28:$V$55)),""),"") -> 18 | V28: 1.2 | W28: 1.2
A29: Кекош, Орешникова | B29: 45662 | C29: вс | D29: 165681 | E29: 39 | F29: =IF(AND(E29<>"",E29<>0),D29/E29,"") -> 4248.2308 | G29: 11 | H29: =IF(AND(G29<>"",G29<>0),D29/G29,"") -> 15061.909 | J29: =IF(AND(G29<>"",G29<>0),E29/G29,"") -> 3.5454545 | N29: =IF(AND(I29<>"",I29<>0),G29/I29,"") | O29: =D29/P29 -> 1.6868525 | P29: =$I$8*V29*W29/SUMPRODUCT($W$25:$W$55,$V$25:$V$55) -> 98219.022 | Q29: =$I$9*V29*W29/SUMPRODUCT($W$25:$W$55,$V$25:$V$55) -> 26.617621 | R29: =IF($I$12="","",Q29/$I$12) -> 16.636013 | S29: =IF(W29<>"",IF(D29<>"",D29,($I$8-SUM($S$25:S28))*V29*W29/SUMPRODUCT($W29:$W$55,$V29:$V$55)),"") -> 165681 | T29: =IF(W29<>"",IF(E29<>"",E29,($I$9-SUM($T$25:T28))*V29*W29/SUMPRODUCT($W29:$W$55,$V29:$V$55)),"") -> 39 | U29: =IF(W29<>"",IF($I$12<>"",IF(G29<>"",G29,($I$9/$I$12-SUM($U$25:U28))*V29*W29/SUMPRODUCT($W29:$W$55,$V29:$V$55)),""),"") -> 11 | V29: 1.2 | W29: 1.2
A30: Рогалевич, Орешникова | B30: 45663 | C30: пн | D30: 37861 | E30: 12 | F30: =IF(AND(E30<>"",E30<>0),D30/E30,"") -> 3155.0833 | G30: 9 | H30: =IF(AND(G30<>"",G30<>0),D30/G30,"") -> 4206.7778 | J30: =IF(AND(G30<>"",G30<>0),E30/G30,"") -> 1.3333333 | N30: =IF(AND(I30<>"",I30<>0),G30/I30,"") | O30: =D30/P30 -> 0.38547523 | P30: =$I$8*V30*W30/SUMPRODUCT($W$25:$W$55,$V$25:$V$55) -> 98219.022 | Q30: =$I$9*V30*W30/SUMPRODUCT($W$25:$W$55,$V$25:$V$55) -> 26.617621 | R30: =IF($I$12="","",Q30/$I$12) -> 16.636013 | S30: =IF(W30<>"",IF(D30<>"",D30,($I$8-SUM($S$25:S29))*V30*W30/SUMPRODUCT($W30:$W$55,$V30:$V$55)),"") -> 37861 | T30: =IF(W30<>"",IF(E30<>"",E30,($I$9-SUM($T$25:T29))*V30*W30/SUMPRODUCT($W30:$W$55,$V30:$V$55)),"") -> 12 | U30: =IF(W30<>"",IF($I$12<>"",IF(G30<>"",G30,($I$9/$I$12-SUM($U$25:U29))*V30*W30/SUMPRODUCT($W30:$W$55,$V30:$V$55)),""),"") -> 9 | V30: 1.2 | W30: 1.2
A31: Рогалевич | B31: 45664 | C31: вт | D31: 65247 | E31: 16 | F31: =IF(AND(E31<>"",E31<>0),D31/E31,"") -> 4077.9375 | G31: 10 | H31: =IF(AND(G31<>"",G31<>0),D31/G31,"") -> 6524.7 | J31: =IF(AND(G31<>"",G31<>0),E31/G31,"") -> 1.6 | N31: =IF(AND(I31<>"",I31<>0),G31/I31,"") | O31: =D31/P31 -> 0.66430105 | P31: =$I$8*V31*W31/SUMPRODUCT($W$25:$W$55,$V$25:$V$55) -> 98219.022 | Q31: =$I$9*V31*W31/SUMPRODUCT($W$25:$W$55,$V$25:$V$55) -> 26.617621 | R31: =IF($I$12="","",Q31/$I$12) -> 16.636013 | S31: =IF(W31<>"",IF(D31<>"",D31,($I$8-SUM($S$25:S30))*V31*W31/SUMPRODUCT($W31:$W$55,$V31:$V$55)),"") -> 65247 | T31: =IF(W31<>"",IF(E31<>"",E31,($I$9-SUM($T$25:T30))*V31*W31/SUMPRODUCT($W31:$W$55,$V31:$V$55)),"") -> 16 | U31: =IF(W31<>"",IF($I$12<>"",IF(G31<>"",G31,($I$9/$I$12-SUM($U$25:U30))*V31*W31/SUMPRODUCT($W31:$W$55,$V31:$V$55)),""),"") -> 10 | V31: 1.2 | W31: 1.2
A32: Кекош, Рогалевич | B32: 45665 | C32: ср | D32: 101885 | E32: 29 | F32: =IF(AND(E32<>"",E32<>0),D32/E32,"") -> 3513.2759 | G32: 14 | H32: =IF(AND(G32<>"",G32<>0),D32/G32,"") -> 7277.5 | J32: =IF(AND(G32<>"",G32<>0),E32/G32,"") -> 2.0714286 | N32: =IF(AND(I32<>"",I32<>0),G32/I32,"") | O32: =D32/P32 -> 1.0373245 | P32: =$I$8*V32*W32/SUMPRODUCT($W$25:$W$55,$V$25:$V$55) -> 98219.022 | Q32: =$I$9*V32*W32/SUMPRODUCT($W$25:$W$55,$V$25:$V$55) -> 26.617621 | R32: =IF($I$12="","",Q32/$I$12) -> 16.636013 | S32: =IF(W32<>"",IF(D32<>"",D32,($I$8-SUM($S$25:S31))*V32*W32/SUMPRODUCT($W32:$W$55,$V32:$V$55)),"") -> 101885 | T32: =IF(W32<>"",IF(E32<>"",E32,($I$9-SUM($T$25:T31))*V32*W32/SUMPRODUCT($W32:$W$55,$V32:$V$55)),"") -> 29 | U32: =IF(W32<>"",IF($I$12<>"",IF(G32<>"",G32,($I$9/$I$12-SUM($U$25:U31))*V32*W32/SUMPRODUCT($W32:$W$55,$V32:$V$55)),""),"") -> 14 | V32: 1.2 | W32: 1.2
A33: Рогалевич | B33: 45666 | C33: чт | D33: 93262 | E33: 27 | F33: =IF(AND(E33<>"",E33<>0),D33/E33,"") -> 3454.1481 | G33: 5 | H33: =IF(AND(G33<>"",G33<>0),D33/G33,"") -> 18652.4 | J33: =IF(AND(G33<>"",G33<>0),E33/G33,"") -> 5.4 | N33: =IF(AND(I33<>"",I33<>0),G33/I33,"") | O33: =D33/P33 -> 1.3673245 | P33: =$I$8*V33*W33/SUMPRODUCT($W$25:$W$55,$V$25:$V$55) -> 68207.654 | Q33: =$I$9*V33*W33/SUMPRODUCT($W$25:$W$55,$V$25:$V$55) -> 18.484459 | R33: =IF($I$12="","",Q33/$I$12) -> 11.552787 | S33: =IF(W33<>"",IF(D33<>"",D33,($I$8-SUM($S$25:S32))*V33*W33/SUMPRODUCT($W33:$W$55,$V33:$V$55)),"") -> 93262 | T33: =IF(W33<>"",IF(E33<>"",E33,($I$9-SUM($T$25:T32))*V33*W33/SUMPRODUCT($W33:$W$55,$V33:$V$55)),"") -> 27 | U33: =IF(W33<>"",IF($I$12<>"",IF(G33<>"",G33,($I$9/$I$12-SUM($U$25:U32))*V33*W33/SUMPRODUCT($W33:$W$55,$V33:$V$55)),""),"") -> 5 | V33: 1 | W33: 1
A34: Кекош, Рогалевич | B34: 45667 | C34: пт | D34: 78019 | E34: 22 | F34: =IF(AND(E34<>"",E34<>0),D34/E34,"") -> 3546.3182 | G34: 15 | H34: =IF(AND(G34<>"",G34<>0),D34/G34,"") -> 5201.2667 | J34: =IF(AND(G34<>"",G34<>0),E34/G34,"") -> 1.4666667 | N34: =IF(AND(I34<>"",I34<>0),G34/I34,"") | O34: =D34/P34 -> 1.1438452 | P34: =$I$8*V34*W34/SUMPRODUCT($W$25:$W$55,$V$25:$V$55) -> 68207.654 | Q34: =$I$9*V34*W34/SUMPRODUCT($W$25:$W$55,$V$25:$V$55) -> 18.484459 | R34: =IF($I$12="","",Q34/$I$12) -> 11.552787 | S34: =IF(W34<>"",IF(D34<>"",D34,($I$8-SUM($S$25:S33))*V34*W34/SUMPRODUCT($W34:$W$55,$V34:$V$55)),"") -> 78019 | T34: =IF(W34<>"",IF(E34<>"",E34,($I$9-SUM($T$25:T33))*V34*W34/SUMPRODUCT($W34:$W$55,$V34:$V$55)),"") -> 22 | U34: =IF(W34<>"",IF($I$12<>"",IF(G34<>"",G34,($I$9/$I$12-SUM($U$25:U33))*V34*W34/SUMPRODUCT($W34:$W$55,$V34:$V$55)),""),"") -> 15 | V34: 1 | W34: 1
A35: Кекош, Рогалевич | B35: 45668 | C35: сб | D35: 29453 | E35: 7 | F35: =IF(AND(E35<>"",E35<>0),D35/E35,"") -> 4207.5714 | G35: 3 | H35: =IF(AND(G35<>"",G35<>0),D35/G35,"") -> 9817.6667 | J35: =IF(AND(G35<>"",G35<>0),E35/G35,"") -> 2.3333333 | N35: =IF(AND(I35<>"",I35<>0),G35/I35,"") | O35: =D35/P35 -> 0.43181371 | P35: =$I$8*V35*W35/SUMPRODUCT($W$25:$W$55,$V$25:$V$55) -> 68207.654 | Q35: =$I$9*V35*W35/SUMPRODUCT($W$25:$W$55,$V$25:$V$55) -> 18.484459 | R35: =IF($I$12="","",Q35/$I$12) -> 11.552787 | S35: =IF(W35<>"",IF(D35<>"",D35,($I$8-SUM($S$25:S34))*V35*W35/SUMPRODUCT($W35:$W$55,$V35:$V$55)),"") -> 29453 | T35: =IF(W35<>"",IF(E35<>"",E35,($I$9-SUM($T$25:T34))*V35*W35/SUMPRODUCT($W35:$W$55,$V35:$V$55)),"") -> 7 | U35: =IF(W35<>"",IF($I$12<>"",IF(G35<>"",G35,($I$9/$I$12-SUM($U$25:U34))*V35*W35/SUMPRODUCT($W35:$W$55,$V35:$V$55)),""),"") -> 3 | V35: 1 | W35: 1
A36: Кекош | B36: 45669 | C36: вс | D36: 7884 | E36: 2 | F36: =IF(AND(E36<>"",E36<>0),D36/E36,"") -> 3942 | G36: 2 | H36: =IF(AND(G36<>"",G36<>0),D36/G36,"") -> 3942 | J36: =IF(AND(G36<>"",G36<>0),E36/G36,"") -> 1 | N36: =IF(AND(I36<>"",I36<>0),G36/I36,"") | O36: =D36/P36 -> 0.14270148 | P36: =$I$8*V36*W36/SUMPRODUCT($W$25:$W$55,$V$25:$V$55) -> 55248.2 | Q36: =$I$9*V36*W36/SUMPRODUCT($W$25:$W$55,$V$25:$V$55) -> 14.972412 | R36: =IF($I$12="","",Q36/$I$12) -> 9.3577575 | S36: =IF(W36<>"",IF(D36<>"",D36,($I$8-SUM($S$25:S35))*V36*W36/SUMPRODUCT($W36:$W$55,$V36:$V$55)),"") -> 7884 | T36: =IF(W36<>"",IF(E35<>"",E35,($I$9-SUM($T$25:T35))*V36*W36/SUMPRODUCT($W36:$W$55,$V36:$V$55)),"") -> 7 | U36: =IF(W36<>"",IF($I$12<>"",IF(G36<>"",G36,($I$9/$I$12-SUM($U$25:U35))*V36*W36/SUMPRODUCT($W36:$W$55,$V36:$V$55)),""),"") -> 2 | V36: 0.9 | W36: 0.9
A37: Рогалевич | B37: 45670 | C37: пн | D37: 18667 | E37: 4 | F37: =IF(AND(E37<>"",E37<>0),D37/E37,"") -> 4666.75 | G37: 3 | H37: =IF(AND(G37<>"",G37<>0),D37/G37,"") -> 6222.3333 | J37: =IF(AND(G37<>"",G37<>0),E37/G37,"") -> 1.3333333 | N37: =IF(AND(I37<>"",I37<>0),G37/I37,"") | O37: =D37/P37 -> 0.42762338 | P37: =$I$8*V37*W37/SUMPRODUCT($W$25:$W$55,$V$25:$V$55) -> 43652.899 | Q37: =$I$9*V37*W37/SUMPRODUCT($W$25:$W$55,$V$25:$V$55) -> 11.830054 | R37: =IF($I$12="","",Q37/$I$12) -> 7.3937837 | S37: =IF(W37<>"",IF(D37<>"",D37,($I$8-SUM($S$25:S36))*V37*W37/SUMPRODUCT($W37:$W$55,$V37:$V$55)),"") -> 18667 | T37: =IF(W37<>"",IF(E37<>"",E37,($I$9-SUM($T$25:T36))*V37*W37/SUMPRODUCT($W37:$W$55,$V37:$V$55)),"") -> 4 | U37: =IF(W37<>"",IF($I$12<>"",IF(G37<>"",G37,($I$9/$I$12-SUM($U$25:U36))*V37*W37/SUMPRODUCT($W37:$W$55,$V37:$V$55)),""),"") -> 3 | V37: 0.8 | W37: 0.8
A38: Кекош, Рогалевич | B38: 45671 | C38: вт | D38: 4382 | E38: 1 | F38: =IF(AND(E38<>"",E38<>0),D38/E38,"") -> 4382 | G38: 1 | H38: =IF(AND(G38<>"",G38<>0),D38/G38,"") -> 4382 | J38: =IF(AND(G38<>"",G38<>0),E38/G38,"") -> 1 | N38: =IF(AND(I38<>"",I38<>0),G38/I38,"") | O38: =D38/P38 -> 0.1003828 | P38: =$I$8*V38*W38/SUMPRODUCT($W$25:$W$55,$V$25:$V$55) -> 43652.899 | Q38: =$I$9*V38*W38/SUMPRODUCT($W$25:$W$55,$V$25:$V$55) -> 11.830054 | R38: =IF($I$12="","",Q38/$I$12) -> 7.3937837 | S38: =IF(W38<>"",IF(D38<>"",D38,($I$8-SUM($S$25:S37))*V38*W38/SUMPRODUCT($W38:$W$55,$V38:$V$55)),"") -> 4382 | T38: =IF(W38<>"",IF(E38<>"",E38,($I$9-SUM($T$25:T37))*V38*W38/SUMPRODUCT($W38:$W$55,$V38:$V$55)),"") -> 1 | U38: =IF(W38<>"",IF($I$12<>"",IF(G38<>"",G38,($I$9/$I$12-SUM($U$25:U37))*V38*W38/SUMPRODUCT($W38:$W$55,$V38:$V$55)),""),"") -> 1 | V38: 0.8 | W38: 0.8
A39: Кекош, Рогалевич | B39: 45672 | C39: ср | D39: 45624 | E39: 9 | F39: =IF(AND(E39<>"",E39<>0),D39/E39,"") -> 5069.3333 | G39: 5 | H39: =IF(AND(G39<>"",G39<>0),D39/G39,"") -> 9124.8 | J39: =IF(AND(G39<>"",G39<>0),E39/G39,"") -> 1.8 | N39: =IF(AND(I39<>"",I39<>0),G39/I39,"") | O39: =D39/P39 -> 1.045154 | P39: =$I$8*V39*W39/SUMPRODUCT($W$25:$W$55,$V$25:$V$55) -> 43652.899 | Q39: =$I$9*V39*W39/SUMPRODUCT($W$25:$W$55,$V$25:$V$55) -> 11.830054 | R39: =IF($I$12="","",Q39/$I$12) -> 7.3937837 | S39: =IF(W39<>"",IF(D39<>"",D39,($I$8-SUM($S$25:S38))*V39*W39/SUMPRODUCT($W39:$W$55,$V39:$V$55)),"") -> 45624 | T39: =IF(W39<>"",IF(E39<>"",E39,($I$9-SUM($T$25:T38))*V39*W39/SUMPRODUCT($W39:$W$55,$V39:$V$55)),"") -> 9 | U39: =IF(W39<>"",IF($I$12<>"",IF(G39<>"",G39,($I$9/$I$12-SUM($U$25:U38))*V39*W39/SUMPRODUCT($W39:$W$55,$V39:$V$55)),""),"") -> 5 | V39: 0.8 | W39: 0.8
A40: Кекош, Рогалевич | B40: 45673 | C40: чт | D40: 28397 | E40: 8 | F40: =IF(AND(E40<>"",E40<>0),D40/E40,"") -> 3549.625 | G40: 7 | H40: =IF(AND(G40<>"",G40<>0),D40/G40,"") -> 4056.7143 | J40: =IF(AND(G40<>"",G40<>0),E40/G40,"") -> 1.1428571 | N40: =IF(AND(I40<>"",I40<>0),G40/I40,"") | O40: =D40/P40 -> 0.65051808 | P40: =$I$8*V40*W40/SUMPRODUCT($W$25:$W$55,$V$25:$V$55) -> 43652.899 | Q40: =$I$9*V40*W40/SUMPRODUCT($W$25:$W$55,$V$25:$V$55) -> 11.830054 | R40: =IF($I$12="","",Q40/$I$12) -> 7.3937837 | S40: =IF(W40<>"",IF(D40<>"",D40,($I$8-SUM($S$25:S39))*V40*W40/SUMPRODUCT($W40:$W$55,$V40:$V$55)),"") -> 28397 | T40: =IF(W40<>"",IF(E40<>"",E40,($I$9-SUM($T$25:T39))*V40*W40/SUMPRODUCT($W40:$W$55,$V40:$V$55)),"") -> 8 | U40: =IF(W40<>"",IF($I$12<>"",IF(G40<>"",G40,($I$9/$I$12-SUM($U$25:U39))*V40*W40/SUMPRODUCT($W40:$W$55,$V40:$V$55)),""),"") -> 7 | V40: 0.8 | W40: 0.8
A41: Кекош, Рогалевич | B41: 45674 | C41: пт | D41: 27760 | E41: 6 | F41: =IF(AND(E41<>"",E41<>0),D41/E41,"") -> 4626.6667 | G41: 3 | H41: =IF(AND(G41<>"",G41<>0),D41/G41,"") -> 9253.3333 | J41: =IF(AND(G41<>"",G41<>0),E41/G41,"") -> 2 | N41: =IF(AND(I41<>"",I41<>0),G41/I41,"") | O41: =D41/P41 -> 0.50245981 | P41: =$I$8*V41*W41/SUMPRODUCT($W$25:$W$55,$V$25:$V$55) -> 55248.2 | Q41: =$I$9*V41*W41/SUMPRODUCT($W$25:$W$55,$V$25:$V$55) -> 14.972412 | R41: =IF($I$12="","",Q41/$I$12) -> 9.3577575 | S41: =IF(W41<>"",IF(D41<>"",D41,($I$8-SUM($S$25:S40))*V41*W41/SUMPRODUCT($W41:$W$55,$V41:$V$55)),"") -> 27760 | T41: =IF(W41<>"",IF(E41<>"",E41,($I$9-SUM($T$25:T40))*V41*W41/SUMPRODUCT($W41:$W$55,$V41:$V$55)),"") -> 6 | U41: =IF(W41<>"",IF($I$12<>"",IF(G41<>"",G41,($I$9/$I$12-SUM($U$25:U40))*V41*W41/SUMPRODUCT($W41:$W$55,$V41:$V$55)),""),"") -> 3 | V41: 0.9 | W41: 0.9
A42: Рогалевич | B42: 45675 | C42: сб | D42: 39780 | E42: 12 | F42: =IF(AND(E42<>"",E42<>0),D42/E42,"") -> 3315 | G42: 7 | H42: =IF(AND(G42<>"",G42<>0),D42/G42,"") -> 5682.8571 | J42: =IF(AND(G42<>"",G42<>0),E42/G42,"") -> 1.7142857 | N42: =IF(AND(I42<>"",I42<>0),G42/I42,"") | O42: =D42/P42 -> 0.72002346 | P42: =$I$8*V42*W42/SUMPRODUCT($W$25:$W$55,$V$25:$V$55) -> 55248.2 | Q42: =$I$9*V42*W42/SUMPRODUCT($W$25:$W$55,$V$25:$V$55) -> 14.972412 | R42: =IF($I$12="","",Q42/$I$12) -> 9.3577575 | S42: =IF(W42<>"",IF(D42<>"",D42,($I$8-SUM($S$25:S41))*V42*W42/SUMPRODUCT($W42:$W$55,$V42:$V$55)),"") -> 39780 | T42: =IF(W42<>"",IF(E42<>"",E42,($I$9-SUM($T$25:T41))*V42*W42/SUMPRODUCT($W42:$W$55,$V42:$V$55)),"") -> 12 | U42: =IF(W42<>"",IF($I$12<>"",IF(G42<>"",G42,($I$9/$I$12-SUM($U$25:U41))*V42*W42/SUMPRODUCT($W42:$W$55,$V42:$V$55)),""),"") -> 7 | V42: 0.9 | W42: 0.9
A43: Рогалевич | B43: 45676 | C43: вс | D43: 7293 | E43: 1 | F43: =IF(AND(E43<>"",E43<>0),D43/E43,"") -> 7293 | G43: 2 | H43: =IF(AND(G43<>"",G43<>0),D43/G43,"") -> 3646.5 | J43: =IF(AND(G43<>"",G43<>0),E43/G43,"") -> 0.5 | N43: =IF(AND(I43<>"",I43<>0),G43/I43,"") | O43: =D43/P43 -> 0.16706794 | P43: =$I$8*V43*W43/SUMPRODUCT($W$25:$W$55,$V$25:$V$55) -> 43652.899 | Q43: =$I$9*V43*W43/SUMPRODUCT($W$25:$W$55,$V$25:$V$55) -> 11.830054 | R43: =IF($I$12="","",Q43/$I$12) -> 7.3937837 | S43: =IF(W43<>"",IF(D43<>"",D43,($I$8-SUM($S$25:S42))*V43*W43/SUMPRODUCT($W43:$W$55,$V43:$V$55)),"") -> 7293 | T43: =IF(W43<>"",IF(E43<>"",E43,($I$9-SUM($T$25:T42))*V43*W43/SUMPRODUCT($W43:$W$55,$V43:$V$55)),"") -> 1 | U43: =IF(W43<>"",IF($I$12<>"",IF(G43<>"",G43,($I$9/$I$12-SUM($U$25:U42))*V43*W43/SUMPRODUCT($W43:$W$55,$V43:$V$55)),""),"") -> 2 | V43: 0.8 | W43: 0.8
A44: Кекош | B44: 45677 | C44: пн | D44: 26748 | E44: 6 | F44: =IF(AND(E44<>"",E44<>0),D44/E44,"") -> 4458 | G44: 2 | H44: =IF(AND(G44<>"",G44<>0),D44/G44,"") -> 13374 | J44: =IF(AND(G44<>"",G44<>0),E44/G44,"") -> 3 | N44: =IF(AND(I44<>"",I44<>0),G44/I44,"") | O44: =D44/P44 -> 0.61274281 | P44: =$I$8*V44*W44/SUMPRODUCT($W$25:$W$55,$V$25:$V$55) -> 43652.899 | Q44: =$I$9*V44*W44/SUMPRODUCT($W$25:$W$55,$V$25:$V$55) -> 11.830054 | R44: =IF($I$12="","",Q44/$I$12) -> 7.3937837 | S44: =IF(W44<>"",IF(D44<>"",D44,($I$8-SUM($S$25:S43))*V44*W44/SUMPRODUCT($W44:$W$55,$V44:$V$55)),"") -> 26748 | T44: =IF(W44<>"",IF(E44<>"",E44,($I$9-SUM($T$25:T43))*V44*W44/SUMPRODUCT($W44:$W$55,$V44:$V$55)),"") -> 6 | U44: =IF(W44<>"",IF($I$12<>"",IF(G44<>"",G44,($I$9/$I$12-SUM($U$25:U43))*V44*W44/SUMPRODUCT($W44:$W$55,$V44:$V$55)),""),"") -> 2 | V44: 0.8 | W44: 0.8
A45: Кекош, Рогалевич | B45: 45678 | C45: вт | D45: 11075 | E45: 3 | F45: =IF(AND(E45<>"",E45<>0),D45/E45,"") -> 3691.6667 | G45: 2 | H45: =IF(AND(G45<>"",G45<>0),D45/G45,"") -> 5537.5 | J45: =IF(AND(G45<>"",G45<>0),E45/G45,"") -> 1.5 | N45: =IF(AND(I45<>"",I45<>0),G45/I45,"") | O45: =D45/P45 -> 0.25370595 | P45: =$I$8*V45*W45/SUMPRODUCT($W$25:$W$55,$V$25:$V$55) -> 43652.899 | Q45: =$I$9*V45*W45/SUMPRODUCT($W$25:$W$55,$V$25:$V$55) -> 11.830054 | R45: =IF($I$12="","",Q45/$I$12) -> 7.3937837 | S45: =IF(W45<>"",IF(D45<>"",D45,($I$8-SUM($S$25:S44))*V45*W45/SUMPRODUCT($W45:$W$55,$V45:$V$55)),"") -> 11075 | T45: =IF(W45<>"",IF(E45<>"",E45,($I$9-SUM($T$25:T44))*V45*W45/SUMPRODUCT($W45:$W$55,$V45:$V$55)),"") -> 3 | U45: =IF(W45<>"",IF($I$12<>"",IF(G45<>"",G45,($I$9/$I$12-SUM($U$25:U44))*V45*W45/SUMPRODUCT($W45:$W$55,$V45:$V$55)),""),"") -> 2 | V45: 0.8 | W45: 0.8
A46: Рогалевич | B46: 45679 | C46: ср | D46: 27780 | E46: 8 | F46: =IF(AND(E46<>"",E46<>0),D46/E46,"") -> 3472.5 | G46: 4 | H46: =IF(AND(G46<>"",G46<>0),D46/G46,"") -> 6945 | J46: =IF(AND(G46<>"",G46<>0),E46/G46,"") -> 2 | N46: =IF(AND(I46<>"",I46<>0),G46/I46,"") | O46: =D46/P46 -> 0.63638385 | P46: =$I$8*V46*W46/SUMPRODUCT($W$25:$W$55,$V$25:$V$55) -> 43652.899 | Q46: =$I$9*V46*W46/SUMPRODUCT($W$25:$W$55,$V$25:$V$55) -> 11.830054 | R46: =IF($I$12="","",Q46/$I$12) -> 7.3937837 | S46: =IF(W46<>"",IF(D46<>"",D46,($I$8-SUM($S$25:S45))*V46*W46/SUMPRODUCT($W46:$W$55,$V46:$V$55)),"") -> 27780 | T46: =IF(W46<>"",IF(E46<>"",E46,($I$9-SUM($T$25:T45))*V46*W46/SUMPRODUCT($W46:$W$55,$V46:$V$55)),"") -> 8 | U46: =IF(W46<>"",IF($I$12<>"",IF(G46<>"",G46,($I$9/$I$12-SUM($U$25:U45))*V46*W46/SUMPRODUCT($W46:$W$55,$V46:$V$55)),""),"") -> 4 | V46: 0.8 | W46: 0.8
A47: Рогалевич | B47: 45680 | C47: чт | D47: 72178 | E47: 19 | F47: =IF(AND(E47<>"",E47<>0),D47/E47,"") -> 3798.8421 | G47: 8 | H47: =IF(AND(G47<>"",G47<>0),D47/G47,"") -> 9022.25 | J47: =IF(AND(G47<>"",G47<>0),E47/G47,"") -> 2.375 | N47: =IF(AND(I47<>"",I47<>0),G47/I47,"") | O47: =D47/P47 -> 1.6534526 | P47: =$I$8*V47*W47/SUMPRODUCT($W$25:$W$55,$V$25:$V$55) -> 43652.899 | Q47: =$I$9*V47*W47/SUMPRODUCT($W$25:$W$55,$V$25:$V$55) -> 11.830054 | R47: =IF($I$12="","",Q47/$I$12) -> 7.3937837 | S47: =IF(W47<>"",IF(D47<>"",D47,($I$8-SUM($S$25:S46))*V47*W47/SUMPRODUCT($W47:$W$55,$V47:$V$55)),"") -> 72178 | T47: =IF(W47<>"",IF(E47<>"",E47,($I$9-SUM($T$25:T46))*V47*W47/SUMPRODUCT($W47:$W$55,$V47:$V$55)),"") -> 19 | U47: =IF(W47<>"",IF($I$12<>"",IF(G47<>"",G47,($I$9/$I$12-SUM($U$25:U46))*V47*W47/SUMPRODUCT($W47:$W$55,$V47:$V$55)),""),"") -> 8 | V47: 0.8 | W47: 0.8
A48: Рогалевич | B48: 45681 | C48: пт | D48: 48873 | E48: 15 | F48: =IF(AND(E48<>"",E48<>0),D48/E48,"") -> 3258.2 | G48: 7 | H48: =IF(AND(G48<>"",G48<>0),D48/G48,"") -> 6981.8571 | J48: =IF(AND(G48<>"",G48<>0),E48/G48,"") -> 2.1428571 | N48: =IF(AND(I48<>"",I48<>0),G48/I48,"") | O48: =D48/P48 -> 1.119582 | P48: =$I$8*V48*W48/SUMPRODUCT($W$25:$W$55,$V$25:$V$55) -> 43652.899 | Q48: =$I$9*V48*W48/SUMPRODUCT($W$25:$W$55,$V$25:$V$55) -> 11.830054 | R48: =IF($I$12="","",Q48/$I$12) -> 7.3937837 | S48: =IF(W48<>"",IF(D48<>"",D48,($I$8-SUM($S$25:S47))*V48*W48/SUMPRODUCT($W48:$W$55,$V48:$V$55)),"") -> 48873 | T48: =IF(W48<>"",IF(E48<>"",E48,($I$9-SUM($T$25:T47))*V48*W48/SUMPRODUCT($W48:$W$55,$V48:$V$55)),"") -> 15 | U48: =IF(W48<>"",IF($I$12<>"",IF(G48<>"",G48,($I$9/$I$12-SUM($U$25:U47))*V48*W48/SUMPRODUCT($W48:$W$55,$V48:$V$55)),""),"") -> 7 | V48: 0.8 | W48: 0.8
... A54: Рогалевич | B54: 45687 | C54: чт | D54: 31031 | E54: 8 | F54: =IF(AND(E54<>"",E54<>0),D54/E54,"") -> 3878.875 | G54: 3 | H54: =IF(AND(G54<>"",G54<>0),D54/G54,"") -> 10343.667 | J54: =IF(AND(G54<>"",G54<>0),E54/G54,"") -> 2.6666667 | N54: =IF(AND(I54<>"",I54<>0),G54/I54,"") | O54: =D54/P54 -> 0.71085772 | P54: =$I$8*V54*W54/SUMPRODUCT($W$25:$W$55,$V$25:$V$55) -> 43652.899 | Q54: =$I$9*V54*W54/SUMPRODUCT($W$25:$W$55,$V$25:$V$55) -> 11.830054 | R54: =IF($I$12="","",Q54/$I$12) -> 7.3937837 | S54: =IF(W54<>"",IF(D54<>"",D54,($I$8-SUM($S$25:S53))*V54*W54/SUMPRODUCT($W54:$W$55,$V54:$V$55)),"") -> 31031 | T54: =IF(W54<>"",IF(E54<>"",E54,($I$9-SUM($T$25:T53))*V54*W54/SUMPRODUCT($W54:$W$55,$V54:$V$55)),"") -> 8 | U54: =IF(W54<>"",IF($I$12<>"",IF(G54<>"",G54,($I$9/$I$12-SUM($U$25:U53))*V54*W54/SUMPRODUCT($W54:$W$55,$V54:$V$55)),""),"") -> 3 | V54: 0.8 | W54: 0.8
A55: Рогалевич, Стекольщикова | B55: 45688 | C55: пт | D55: 30873 | E55: 8 | F55: =IF(AND(E55<>"",E55<>0),D55/E55,"") -> 3859.125 | G55: 7 | H55: =IF(AND(G55<>"",G55<>0),D55/G55,"") -> 4410.4286 | J55: =IF(AND(G55<>"",G55<>0),E55/G55,"") -> 1.1428571 | N55: =IF(AND(I55<>"",I55<>0),G55/I55,"") | O55: =D55/P55 -> 0.70723826 | P55: =$I$8*V55*W55/SUMPRODUCT($W$25:$W$55,$V$25:$V$55) -> 43652.899 | Q55: =$I$9*V55*W55/SUMPRODUCT($W$25:$W$55,$V$25:$V$55) -> 11.830054 | R55: =IF($I$12="","",Q55/$I$12) -> 7.3937837 | S55: =IF(W55<>"",IF(D55<>"",D55,($I$8-SUM($S$25:S54))*V55*W55/SUMPRODUCT($W55:$W$55,$V55:$V$55)),"") -> 30873 | T55: =IF(W55<>"",IF(E55<>"",E55,($I$9-SUM($T$25:T54))*V55*W55/SUMPRODUCT($W55:$W$55,$V55:$V$55)),0) -> 8 | U55: =IF(W55<>"",IF($I$12<>"",IF(G55<>"",G55,($I$9/$I$12-SUM($U$25:U54))*V55*W55/SUMPRODUCT($W55:$W$55,$V55:$V$55)),""),"") -> 7 | V55: 0.8 | W55: 0.8
B56: итого | D56: =SUM(D25:D55) -> 1570967.6 | E56: =SUM(E25:E55) -> 409 | F56: =IF(AND(E56<>"", E56<>0), D56/E56, "") -> 3840.9967 | G56: =SUM(G25:G55) -> 202 | H56: =IF(AND(G56<>"", G56<>0), D56/G56, "") -> 7777.0675 | I56: =SUM(I25:I55) -> 0 | J56: =E56/G56 -> 2.0247525 | K56: =SUM(K25:K55) -> 0 | L56: =SUM(L25:L55) -> 0 | M56: =SUM(M25:M55) -> 0 | N56: =IF(AND(I56<>"", I56<>0), G56/I56, "") | O56: =D56/P56 -> 0.8727598 | P56: =SUM(P25:P55) -> 1800000 | Q56: =SUM(Q25:Q55) -> 487.80488 | R56: =SUM(R25:R55) -> 304.87805 | S56: =SUM(S25:S55) -> 1570967.6 | T56: =SUM(T25:T55) -> 414 | U56: =SUM(U25:U55) -> 202
D57: =SUMIF(D25:D55,"",P25:P55)+D56 -> 1570967.6 | I57: =I56/J14 -> 0
D58: ='Доп сотрудник'!D48+'Кекош А. И.'!J8+'ПК 2'!J8+'Рогалевич И. Е.'!J8 -> 1570967.6 | I58: =I57*(I14-J14) -> 0

Sheet Св. по пок.
A1: Сводная по показателям
A2: Показатель | D2: ='Ялта, Ленина, 18'!I3 -> ул. Набережная Ленина, 18 | G2: =График!B26 -> Орешникова Елена | J2: =График!B30 -> Кекош Анна
D3: Факт | F3: Прогноз | G3: Факт | I3: Прогноз | J3: Факт | L3: Прогноз
A4: Выручка | D4: ='Ялта, Ленина, 18'!K8 -> 0.8727598 | E4: ='Ялта, Ленина, 18'!J8 -> 1570967.6 | F4: ='Ялта, Ленина, 18'!M8 -> 0.8727598 | G4: ='Рогалевич И. Е.'!K8 -> 0.90672296 | H4: ='Рогалевич И. Е.'!J8 -> 833967.94 | I4: ='Рогалевич И. Е.'!M8 -> 0.88896059 | J4: ='Кекош А. И.'!K8 -> 0.97359796 | K4: ='Кекош А. И.'!J8 -> 517697.6 | L4: ='Кекош А. И.'!M8 -> 1.3610517
A5: Кол-во изделий | D5: ='Ялта, Ленина, 18'!K9 -> 0.83845 | E5: ='Ялта, Ленина, 18'!J9 -> 409 | F5: ='Ялта, Ленина, 18'!M9 -> 0.83845 | G5: ='Рогалевич И. Е.'!K9 -> 0.82244238 | H5: ='Рогалевич И. Е.'!J9 -> 205 | I5: ='Рогалевич И. Е.'!M9 -> 0.86965916 | J5: ='Кекош А. И.'!K9 -> 0.80498514 | K5: ='Кекош А. И.'!J9 -> 116 | L5: ='Кекош А. И.'!M9 -> 0.80498514
A6: Средний чек | D6: ='Ялта, Ленина, 18'!K10 -> 1.317254 | E6: ='Ялта, Ленина, 18'!J10 -> 7777.0675 | F6: ='Ялта, Ленина, 18'!M10 -> 1.317254 | G6: ='Рогалевич И. Е.'!K10 -> 1.3985617 | H6: ='Рогалевич И. Е.'!J10 -> 8257.1083 | I6: ='Рогалевич И. Е.'!M10 -> 1.3985617 | J6: ='Кекош А. И.'!K10 -> 1.4614318 | K6: ='Кекош А. И.'!J10 -> 8628.2933 | L6: ='Кекош А. И.'!M10 -> 1.4614318
A7: Средняя стоимость изделия | D7: ='Ялта, Ленина, 18'!K11 -> 1.0409205 | E7: ='Ялта, Ленина, 18'!J11 -> 3840.9967 | F7: ='Ялта, Ленина, 18'!M11 -> 1.0409205 | G7: ='Рогалевич И. Е.'!K11 -> 1.102476 | H7: ='Рогалевич И. Е.'!J11 -> 4068.1363 | I7: ='Рогалевич И. Е.'!M11 -> 1.0221942 | J7: ='Кекош А. И.'!K11 -> 1.2094608 | K7: ='Кекош А. И.'!J11 -> 4462.9103 | L7: ='Кекош А. И.'!M11 -> 1.2094608
A8: Длина чека | D8: ='Ялта, Ленина, 18'!K12 -> 1.2654703 | E8: ='Ялта, Ленина, 18'!J12 -> 2.0247525 | F8: ='Ялта, Ленина, 18'!M12 -> 1.2654703 | G8: ='Рогалевич И. Е.'!K12 -> 1.2685644 | H8: ='Рогалевич И. Е.'!J12 -> 2.029703 | I8: ='Рогалевич И. Е.'!M12 -> 1.2685644 | J8: ='Кекош А. И.'!K12 -> 1.2083333 | K8: ='Кекош А. И.'!J12 -> 1.9333333 | L8: ='Кекош А. И.'!M12 -> 1.2083333
A9: Кол-во чеков | D9: ='Ялта, Ленина, 18'!K13 | E9: ='Ялта, Ленина, 18'!J13 -> 202 | F9: ='Ялта, Ленина, 18'!M13 | G9: ='Рогалевич И. Е.'!K13 -> 0.64832531 | H9: ='Рогалевич И. Е.'!J13 -> 101 | I9: ='Рогалевич И. Е.'!M13 -> 0.6861281 | J9: ='Кекош А. И.'!K13 -> 0.66619459 | K9: ='Кекош А. И.'!J13 -> 60 | L9: ='Кекош А. И.'!M13 -> 0.66619459
A10: Кол-во смен план/отработано | D10: ='Ялта, Ленина, 18'!K14 -> 1 | E10: ='Ялта, Ленина, 18'!J14 -> 30 | F10: ='Ялта, Ленина, 18'!M14 | G10: ='Рогалевич И. Е.'!K14 -> 1 | H10: ='Рогалевич И. Е.'!J14 -> 24 | I10: ='Рогалевич И. Е.'!M14 | J10: ='Кекош А. И.'!K14 -> 1 | K10: ='Кекош А. И.'!J14 -> 15 | L10: ='Кекош А. И.'!M14 -> 1
A11: Средние продажи в смену | D11: ='Ялта, Ленина, 18'!K15 -> 0.8727598 | E11: ='Ялта, Ленина, 18'!J15 -> 52365.588 | F11: ='Ялта, Ленина, 18'!M15 -> 0.8727598 | G11: ='Рогалевич И. Е.'!K15 -> 0.5791444 | H11: ='Рогалевич И. Е.'!J15 -> 34748.664 | I11: ='Рогалевич И. Е.'!M15 -> 0.5791444 | J11: ='Кекош А. И.'!K15 -> 0.57521956 | K11: ='Кекош А. И.'!J15 -> 34513.173 | L11: ='Кекош А. И.'!M15 -> 0.57521956
A12: Отставание/Перевыполнение | D12: ='Ялта, Ленина, 18'!J16 -> -229032.36 | G12: ='Рогалевич И. Е.'!J16 -> -606032.06 | J12: ='Кекош А. И.'!J16 -> -382302.4

Sheet План на день
A1: Выручка | D1: 75468
A2: Кол-во изделий | D2: =D1/D4 -> 20.452033
A3: Средний чек | D3: =D4*D5 -> 5904
A4: Средняя стоимость изделия | D4: ='Ялта, Ленина, 18'!I11 -> 3690
A5: Длина чека | D5: ='Ялта, Ленина, 18'!I12 -> 1.6
A6: Кол-во чеков | D6: =IF(D5<>0,D2/D5,"") -> 12.78252
A7: Конверсия | D7: ='Ялта, Ленина, 18'!I20 -> 0.257

Sheet Кекош А. И.
B1: =TODAY()-1 -> 45696
B2: (отчетная дата) | J2: ЕЖЕДНЕВНЫЙ ОТЧЕТ О ПРОДАЖАХ
B3: Осталось до выполнения плана!!! | J3: =График!B30 -> Кекош Анна
C4: =I8-D50 -> 14038.927 | E4: =IF(I8<>0, C4/I8, 0) -> 0.026402036
F6: Целевые показатели
F7: Показатель | I7: План | J7: Факт | K7: % выполнения | L7: Прогноз выполнения | M7: % выполнения по прогнозу | N7: Отклонение | O7: Факт аналогичного месяца прошлого года | P7: Отклонение LFL
F8: Выручка | I8: ='Ялта, Ленина, 18'!I8/График!AJ31*График!AJ30 -> 531736.53 | J8: =D50 -> 517697.6 | K8: =J8/I8 -> 0.97359796 | L8: =IF(SUMIF($D$25:$D$49,">=0",$P$25:$P$49)<>0,I8*D50/SUMIF($D$25:$D$49,">=0",$P$25:$P$49),0) -> 723720.91 | M8: =IF(AND(I8<>"",I8<>0,L8<>"",L8<>0),L8/I8,"") -> 1.3610517 | N8: =IF(AND(J8<>0, J8<>"", I8<>0, I8<>""), L8-I8, "") -> 191984.38 | P8: =IF(AND(O8<>"", O8<>0, L8<>"", L8<>0), -O8+L8, "") | Q8: =IF(AND(P8<>"", P8<>0, O8<>0, O8<>""), P8/O8, "")
F9: Кол-во изделий | I9: =I8/I11 -> 144.10204 | J9: =E50 -> 116 | K9: =IF(AND(I9<>"", I9<>0, J9<>""), J9/I9, "") -> 0.80498514 | L9: =J9 -> 116 | M9: =IF(AND(I9<>"",I9<>0,L9<>"",L9<>0),L9/I9,"") -> 0.80498514 | N9: =IF(AND(J9<>0, J9<>"", I9<>0, I9<>""), L9-I9, "") -> -28.10204 | O9: =O8/O11 -> #DIV/0! | P9: =IF(AND(O9<>"", O9<>0, L9<>"", L9<>0), -O9+L9, "") -> #DIV/0! | Q9: =IF(AND(P9<>"", P9<>0, O9<>0, O9<>""), P9/O9, "") -> #DIV/0!
F10: Средний чек | I10: =I11*I12 -> 5904 | J10: =H50 -> 8628.2933 | K10: =IF(AND(I10<>"", I10<>0, J10<>""), J10/I10, "") -> 1.4614318 | L10: =J10 -> 8628.2933 | M10: =IF(AND(I10<>"",I10<>0,L10<>"",L10<>0),L10/I10,"") -> 1.4614318 | N10: =IF(AND(J10<>0, J10<>"", I10<>0, I10<>""), L10-I10, "") -> 2724.2933 | O10: =O11*O12 -> 0 | P10: =IF(AND(O10<>"", O10<>0, L10<>"", L10<>0), -O10+L10, "") | Q10: =IF(AND(P10<>"", P10<>0, O10<>0, O10<>""), P10/O10, "")
F11: Средняя стоимость изделия | I11: ='Ялта, Ленина, 18'!I11 -> 3690 | J11: =F50 -> 4462.9103 | K11: =IF(AND(I11<>"", I11<>0, J11<>""), J11/I11, "") -> 1.2094608 | L11: =J11 -> 4462.9103 | M11: =IF(AND(I11<>"",I11<>0,L11<>"",L11<>0),L11/I11,"") -> 1.2094608 | N11: =IF(AND(J11<>0, J11<>"", I11<>0, I11<>""), L11-I11, "") -> 772.91034 | P11: =IF(AND(O11<>"", O11<>0, L11<>"", L11<>0), -O11+L11, "") | Q11: =IF(AND(P11<>"", P11<>0, O11<>0, O11<>""), P11/O11, "")
F12: Длина чека | I12: ='Ялта, Ленина, 18'!I12 -> 1.6 | J12: =J50 -> 1.9333333 | K12: =IF(AND(I12<>"", I12<>0, J12<>""), J12/I12, "") -> 1.2083333 | L12: =J12 -> 1.9333333 | M12: =IF(AND(I12<>"",I12<>0,L12<>"",L12<>0),L12/I12,"") -> 1.2083333 | N12: =IF(AND(J12<>0, J12<>"", I12<>0, I12<>""), L12-I12, "") -> 0.33333333 | P12: =IF(AND(O12<>"", O12<>0, L12<>"", L12<>0), -O12+L12, "") | Q12: =IF(AND(P12<>"", P12<>0, O12<>0, O12<>""), P12/O12, "")
F13: Кол-во чеков | I13: =IF(I12<>0, I9/I12, "") -> 90.063775 | J13: =G50 -> 60 | K13: =IF(AND(I13<>"", I13<>0, J13<>""), J13/I13, "") -> 0.66619459 | L13: =J13 -> 60 | M13: =IF(AND(I13<>"",I13<>0,L13<>"",L13<>0),L13/I13,"") -> 0.66619459 | N13: =IF(AND(J13<>0, J13<>"", I13<>0, I13<>""), L13-I13, "") -> -30.063775 | P13: =IF(AND(O13<>"", O13<>0, L13<>"", L13<>0), -O13+L13, "") | Q13: =IF(AND(P13<>"", P13<>0, O13<>0, O13<>""), P13/O13, "")
F14: Кол-во смен план/отработано | I14: =График!AI30 -> 15 | J14: 15 | K14: =IF(AND(I14<>"", I14<>0, J14<>""), J14/I14, "") -> 1 | L14: =J14 -> 15 | M14: =IF(AND(I14<>"",I14<>0,L14<>"",L14<>0),L14/I14,"") -> 1 | N14: =IF(AND(J14<>0, J14<>"", I14<>0, I14<>""), L14-I14, "") -> 0 | P14: =IF(AND(O14<>"", O14<>0, L14<>"", L14<>0), -O14+L14, "") | Q14: =IF(AND(P14<>"", P14<>0, O14<>0, O14<>""), P14/O14, "")
F15: Средние продажи в смену | I15: ='Ялта, Ленина, 18'!I15 -> 60000 | J15: =J8/J14 -> 34513.173 | K15: =IF(AND(I15<>"", I15<>0, J15<>""), J15/I15, "") -> 0.57521956 | L15: =J15 -> 34513.173 | M15: =IF(AND(I15<>"",I15<>0,L15<>"",L15<>0),L15/I15,"") -> 0.57521956 | N15: =IF(AND(J15<>0, J15<>"", I15<>0, I15<>""), L15-I15, "") -> -25486.827 | P15: =IF(AND(O15<>"", O15<>0, L15<>"", L15<>0), -O15+L15, "") | Q15: =IF(AND(P15<>"", P15<>0, O15<>0, O15<>""), P15/O15, "")
F16: Отставание/Перевыполнение | J16: =J8-I15*J14 -> -382302.4 | K16: =IF(AND(I16<>"", I16<>0, J16<>""), J16/I16, "") | L16: =J16 -> -382302.4 | M16: =IF(AND(I16<>"",I16<>0,L16<>"",L16<>0),L16/I16,"") | N16: =IF(AND(J16<>0, J16<>"", I16<>0, I16<>""), L16-I16, "") | P16: =IF(AND(O16<>"", O16<>0, L16<>"", L16<>0), -O16+L16, "") | Q16: =IF(AND(P16<>"", P16<>0, O16<>0, O16<>""), P16/O16, "") | S16: Подарочные сертификаты
F17: Трафик | I17: ='Ялта, Ленина, 18'!I17/График!AJ31*График!AJ30 -> 0 | J17: =I50 -> 0 | K17: =IF(AND(I17<>"", I17<>0, J17<>""), J17/I17, "") | L17: =J17 -> 0 | M17: =IF(AND(I17<>"",I17<>0,L17<>"",L17<>0),L17/I17,"") | N17: =IF(AND(J17<>0, J17<>"", I17<>0, I17<>""), L17-I17, "") | P17: =IF(AND(O17<>"", O17<>0, L17<>"", L17<>0), -O17+L17, "") | Q17: =IF(AND(P17<>"", P17<>0, O17<>0, O17<>""), P17/O17, "")
K18: =IF(AND(I18<>"", I18<>0, J18<>""), J18/I18, "") | L18: =J18 -> 0 | M18: =IF(AND(I18<>"",I18<>0,L18<>"",L18<>0),L18/I18,"") | N18: =IF(AND(J18<>0, J18<>"", I18<>0, I18<>""), L18-I18, "") | O18: 0 | P18: =IF(AND(O18<>"", O18<>0, L18<>"", L18<>0), -O18+L18, "") | Q18: =IF(AND(P18<>"", P18<>0, O18<>0, O18<>""), P18/O18, "") | S18: 3000
J19: =M50 -> 0 | K19: =IF(AND(I19<>"", I19<>0, J19<>""), J19/I19, "") | L19: =J19 -> 0 | M19: =IF(AND(I19<>"",I19<>0,L19<>"",L19<>0),L19/I19,"") | N19: =IF(AND(J19<>0, J19<>"", I19<>0, I19<>""), L19-I19, "") | O19: 0 | P19: =IF(AND(O19<>"", O19<>0, L19<>"", L19<>0), -O19+L19, "") | Q19: =IF(AND(P19<>"", P19<>0, O19<>0, O19<>""), P19/O19, "") | S19: =S18/I16 -> #DIV/0!
F20: Конверсия план/факт | I20: ='Ялта, Ленина, 18'!I20 -> 0.257 | J20: =N50 | K20: =J20/I20 -> #VALUE! | L20: =IF(AND(K8<>0,I14<>0,I50<>0),(I50*N50+(I50/K8-I50)*I20)/(I50/K8),0) -> 0 | M20: =IF(AND(I20<>"",I20<>0,L20<>"",L20<>0),L20/I20,"") | N20: =IF(AND(J20<>0, J20<>"", I20<>0, I20<>""), L20-I20, "") | P20: =IF(AND(O20<>"", O20<>0, L20<>"", L20<>0), -O20+L20, "") | Q20: =IF(AND(P20<>"", P20<>0, O20<>0, O20<>""), P20/O20, "")
B22: Факт продаж за месяц | O22: % выполнения дневного плана | P22: Раcпределение плана по дням
B23: Дата | C23: День недели | D23: Выручка (руб) | E23: Кол-во единиц (шт.) | F23: Средняя стоимость изделия (руб.) | G23: Количество чеков (шт.) | H23: Средняя сумма чека (руб.) | I23: Трафик | J23: Длина чека (шт.) | K23: Запасной | L23: Запасной | M23: Запасной | N23: Конверсия (%) | P23: выручка, план | Q23: кол-во ед, план | R23: Кол-во чеков, план | S23: выручка, скорректир.план | T23: кол-во ед, скорр. план | U23: кол-во чеков, скорр. план | V23: Коэфф. Дня Недели | W23: Специфика месяца
B24: 1 | C24: 2 | D24: 3 | E24: в | F24: 5 | G24: 6 | H24: 7 | I24: 8 | J24: 9 | K24: 10 | L24: 11 | M24: 12 | N24: 13 | P24: 1 | Q24: 2 | R24: 3 | S24: 4 | T24: 5 | U24: 6 | V24: 10 | W24: 11
A25: 1 | B25: 45659 | C25: чт | E25: 18 | F25: =IF(AND(E25<>"",E25<>0),D25/E25,"") -> 0 | G25: 8 | H25: =IF(AND(G25<>"",G25<>0),D25/G25,"") -> 0 | J25: =IF(AND(G25<>"",G25<>0),E25/G25,"") -> 2.25 | N25: =IF(AND(I25<>"",I25<>0),G25/I25,"") | O25: =D25/P25 -> 0 | P25: =$I$8*V25*W25/SUMPRODUCT($W$25:$W$60,$V$25:$V$60) -> 23507.362 | Q25: =$I$9*V25*W25/SUMPRODUCT($W$25:$W$60,$V$25:$V$60) -> 6.3705588 | R25: =IF($I$12="","",Q25/$I$12) -> 3.9815992 | S25: =IF(W25<>"",IF(D25<>"",D25,($I$8-SUM($S24:S$25))*V25*W25/SUMPRODUCT($W25:$W$60,$V25:$V$60)),"") -> 70085.85 | T25: =IF(W25<>"",IF(E25<>"",E25,($I$9-SUM($T24:T$25))*V25*W25/SUMPRODUCT($W25:$W$60,$V25:$V$60)),"") -> 18 | U25: =IF(W25<>"",IF($I$12<>"",IF(G25<>"",G25,($I$9/$I$12-SUM($U24:U$25))*V25*W25/SUMPRODUCT($W25:$W$60,$V25:$V$60)),""),"") -> 8 | V25: 1 | W25: 1
A26: 2 | B26: 45660 | C26: пт | E26: 12 | F26: =IF(AND(E26<>"",E26<>0),D26/E26,"") -> 0 | G26: 6 | H26: =IF(AND(G26<>"",G26<>0),D26/G26,"") -> 0 | J26: =IF(AND(G26<>"",G26<>0),E26/G26,"") -> 2 | N26: =IF(AND(I26<>"",I26<>0),G26/I26,"") | O26: =D26/P26 -> 0 | P26: =$I$8*V26*W26/SUMPRODUCT($W$25:$W$60,$V$25:$V$60) -> 23507.362 | Q26: =$I$9*V26*W26/SUMPRODUCT($W$25:$W$60,$V$25:$V$60) -> 6.3705588 | R26: =IF($I$12="","",Q26/$I$12) -> 3.9815992 | S26: =IF(W26<>"",IF(D26<>"",D26,($I$8-SUM($S$25:S25))*V26*W26/SUMPRODUCT($W26:$W$60,$V26:$V$60)),"") -> 45926 | T26: =IF(W26<>"",IF(E26<>"",E26,($I$9-SUM($T$25:T25))*V26*W26/SUMPRODUCT($W26:$W$60,$V26:$V$60)),"") -> 12 | U26: =IF(W26<>"",IF($I$12<>"",IF(G26<>"",G26,($I$9/$I$12-SUM($U$25:U25))*V26*W26/SUMPRODUCT($W26:$W$60,$V26:$V$60)),""),"") -> 6 | V26: 1 | W26: 1
A27: 3 | B27: 45661 | C27: сб | E27: 17 | F27: =IF(AND(E27<>"",E27<>0),D27/E27,"") -> 0 | G27: 9 | H27: =IF(AND(G27<>"",G27<>0),D27/G27,"") -> 0 | J27: =IF(AND(G27<>"",G27<>0),E27/G27,"") -> 1.8888889 | N27: =IF(AND(I27<>"",I27<>0),G27/I27,"") | O27: =D27/P27 -> 0 | P27: =$I$8*V27*W27/SUMPRODUCT($W$25:$W$60,$V$25:$V$60) -> 23507.362 | Q27: =$I$9*V27*W27/SUMPRODUCT($W$25:$W$60,$V$25:$V$60) -> 6.3705588 | R27: =IF($I$12="","",Q27/$I$12) -> 3.9815992 | S27: =IF(W27<>"",IF(D27<>"",D27,($I$8-SUM($S$25:S26))*V27*W27/SUMPRODUCT($W27:$W$60,$V27:$V$60)),"") -> 70721.5 | T27: =IF(W27<>"",IF(E27<>"",E27,($I$9-SUM($T$25:T26))*V27*W27/SUMPRODUCT($W27:$W$60,$V27:$V$60)),"") -> 17 | U27: =IF(W27<>"",IF($I$12<>"",IF(G27<>"",G27,($I$9/$I$12-SUM($U$25:U26))*V27*W27/SUMPRODUCT($W27:$W$60,$V27:$V$60)),""),"") -> 9 | V27: 1 | W27: 1
A28: 4 | B28: 45662 | C28: вс | D28: 327758.6 | E28: 19 | F28: =IF(AND(E28<>"",E28<>0),D28/E28,"") -> 17250.453 | G28: 5 | H28: =IF(AND(G28<>"",G28<>0),D28/G28,"") -> 65551.72 | J28: =IF(AND(G28<>"",G28<>0),E28/G28,"") -> 3.8 | N28: =IF(AND(I28<>"",I28<>0),G28/I28,"") | O28: =D28/P28 -> 13.942807 | P28: =$I$8*V28*W28/SUMPRODUCT($W$25:$W$60,$V$25:$V$60) -> 23507.362 | Q28: =$I$9*V28*W28/SUMPRODUCT($W$25:$W$60,$V$25:$V$60) -> 6.3705588 | R28: =IF($I$12="","",Q28/$I$12) -> 3.9815992 | S28: =IF(W28<>"",IF(D28<>"",D28,($I$8-SUM($S$25:S27))*V28*W28/SUMPRODUCT($W28:$W$60,$V28:$V$60)),"") -> 327758.6 | T28: =IF(W28<>"",IF(E28<>"",E28,($I$9-SUM($T$25:T27))*V28*W28/SUMPRODUCT($W28:$W$60,$V28:$V$60)),"") -> 19 | U28: =IF(W28<>"",IF($I$12<>"",IF(G28<>"",G28,($I$9/$I$12-SUM($U$25:U27))*V28*W28/SUMPRODUCT($W28:$W$60,$V28:$V$60)),""),"") -> 5 | V28: 1 | W28: 1
A29: 5 | B29: 45665 | C29: ср | D29: 29826 | E29: 9 | F29: 3513 | G29: 6 | H29: 7278 | J29: 2.07 | O29: 0.8 | P29: 127742 | Q29: 35 | R29: 22 | S29: 101885 | T29: 29 | U29: 14 | V29: 1.2 | W29: 1.2
A30: 6 | B30: 45667 | C30: сб | D30: 38280 | E30: 12 | F30: =IF(AND(E30<>"",E30<>0),D30/E30,"") -> 3190 | G30: 8 | H30: =IF(AND(G30<>"",G30<>0),D30/G30,"") -> 4785 | P30: =$I$8*V30*W30/SUMPRODUCT($W$25:$W$60,$V$25:$V$60) -> 23507.362 | V30: 1 | W30: 1
A31: 7 | B31: 45668 | C31: сб | D31: 24761 | E31: 6 | F31: 4208 | G31: 2 | H31: 9818 | J31: 2.33 | O31: 0.35 | P31: 83841 | Q31: 23 | R31: 14 | S31: 29453 | T31: 7 | U31: 3 | V31: 1 | W31: 1
A32: 8 | B32: 45669 | C32: вс | D32: 7884 | E32: 2 | F32: =IF(AND(E32<>"",E32<>0),D32/E32,"") -> 3942 | G32: 2 | H32: =IF(AND(G32<>"",G32<>0),D32/G32,"") -> 3942 | J32: =IF(AND(G32<>"",G32<>0),E32/G32,"") -> 1 | N32: =IF(AND(I32<>"",I32<>0),G32/I32,"") | O32: =D32/P32 -> 0.41405468 | P32: =$I$8*V32*W32/SUMPRODUCT($W$25:$W$55,$V$25:$V$55) -> 19040.963 | Q32: =$I$9*V32*W32/SUMPRODUCT($W$25:$W$55,$V$25:$V$55) -> 5.1601526 | R32: =IF($I$12="","",Q32/$I$12) -> 3.2250954 | S32: =IF(W32<>"",IF(D32<>"",D32,($I$8-SUM($S$25:S31))*V32*W32/SUMPRODUCT($W32:$W$55,$V32:$V$55)),"") -> 7884 | T32: =IF(W32<>"",IF(E31<>"",E31,($I$9-SUM($T$25:T31))*V32*W32/SUMPRODUCT($W32:$W$55,$V32:$V$55)),"") -> 6 | U32: =IF(W32<>"",IF($I$12<>"",IF(G32<>"",G32,($I$9/$I$12-SUM($U$25:U31))*V32*W32/SUMPRODUCT($W32:$W$55,$V32:$V$55)),""),"") -> 2 | V32: 0.9 | W32: 0.9
A33: 9 | B33: 45671 | C33: вт | D33: 4382 | E33: 1 | F33: =IF(AND(E33<>"",E33<>0),D33/E33,"") -> 4382 | G33: 1 | H33: =IF(AND(G33<>"",G33<>0),D33/G33,"") -> 4382 | J33: =IF(AND(G33<>"",G33<>0),E33/G33,"") -> 1 | N33: =IF(AND(I33<>"",I33<>0),G33/I33,"") | O33: =D33/P33 -> 0.29126514 | P33: =$I$8*V33*W33/SUMPRODUCT($W$25:$W$55,$V$25:$V$55) -> 15044.712 | Q33: =$I$9*V33*W33/SUMPRODUCT($W$25:$W$55,$V$25:$V$55) -> 4.0771576 | R33: =IF($I$12="","",Q33/$I$12) -> 2.5482235 | S33: =IF(W33<>"",IF(D33<>"",D33,($I$8-SUM($S$25:S32))*V33*W33/SUMPRODUCT($W33:$W$55,$V33:$V$55)),"") -> 4382 | T33: =IF(W33<>"",IF(E33<>"",E33,($I$9-SUM($T$25:T32))*V33*W33/SUMPRODUCT($W33:$W$55,$V33:$V$55)),"") -> 1 | U33: =IF(W33<>"",IF($I$12<>"",IF(G33<>"",G33,($I$9/$I$12-SUM($U$25:U32))*V33*W33/SUMPRODUCT($W33:$W$55,$V33:$V$55)),""),"") -> 1 | V33: 0.8 | W33: 0.8
A34: 10 | B34: 45672 | C34: ср | D34: =5992+5092 -> 11084 | E34: 2 | F34: =IF(AND(E34<>"",E34<>0),D34/E34,"") -> 5542 | G34: 2 | H34: =IF(AND(G34<>"",G34<>0),D34/G34,"") -> 5542 | J34: =IF(AND(G34<>"",G34<>0),E34/G34,"") -> 1 | N34: =IF(AND(I34<>"",I34<>0),G34/I34,"") | O34: =D34/P34 -> 0.47151186 | P34: =$I$8*V34*W34/SUMPRODUCT($W$25:$W$60,$V$25:$V$60) -> 23507.362 | Q34: =$I$9*V34*W34/SUMPRODUCT($W$25:$W$60,$V$25:$V$60) -> 6.3705588 | R34: =IF($I$12="","",Q34/$I$12) -> 3.9815992 | S34: =IF(W34<>"",IF(D34<>"",D34,($I$8-SUM($S$25:S33))*V34*W34/SUMPRODUCT($W34:$W$60,$V34:$V$60)),"") -> 11084 | T34: =IF(W34<>"",IF(E34<>"",E34,($I$9-SUM($T$25:T33))*V34*W34/SUMPRODUCT($W34:$W$60,$V34:$V$60)),"") -> 2 | U34: =IF(W34<>"",IF($I$12<>"",IF(G34<>"",G34,($I$9/$I$12-SUM($U$25:U33))*V34*W34/SUMPRODUCT($W34:$W$60,$V34:$V$60)),""),"") -> 2 | V34: 1 | W34: 1
A35: 11 | B35: 45673 | C35: чт | D35: 16522 | E35: 5 | F35: =IF(AND(E35<>"",E35<>0),D35/E35,"") -> 3304.4 | G35: 5 | H35: =IF(AND(G35<>"",G35<>0),D35/G35,"") -> 3304.4 | J35: =IF(AND(G35<>"",G35<>0),E35/G35,"") -> 1 | N35: =IF(AND(I35<>"",I35<>0),G35/I35,"") | O35: =D35/P35 -> 1.0981932 | P35: =$I$8*V35*W35/SUMPRODUCT($W$25:$W$55,$V$25:$V$55) -> 15044.712 | Q35: =$I$9*V35*W35/SUMPRODUCT($W$25:$W$55,$V$25:$V$55) -> 4.0771576 | R35: =IF($I$12="","",Q35/$I$12) -> 2.5482235 | S35: =IF(W35<>"",IF(D35<>"",D35,($I$8-SUM($S$25:S34))*V35*W35/SUMPRODUCT($W35:$W$55,$V35:$V$55)),"") -> 16522 | T35: =IF(W35<>"",IF(E35<>"",E35,($I$9-SUM($T$25:T34))*V35*W35/SUMPRODUCT($W35:$W$55,$V35:$V$55)),"") -> 5 | U35: =IF(W35<>"",IF($I$12<>"",IF(G35<>"",G35,($I$9/$I$12-SUM($U$25:U34))*V35*W35/SUMPRODUCT($W35:$W$55,$V35:$V$55)),""),"") -> 5 | V35: 0.8 | W35: 0.8
A36: 12 | B36: 45674 | C36: пт | D36: 19377 | E36: 4 | F36: =IF(AND(E36<>"",E36<>0),D36/E36,"") -> 4844.25 | G36: 2 | H36: =IF(AND(G36<>"",G36<>0),D36/G36,"") -> 9688.5 | J36: =IF(AND(G36<>"",G36<>0),E36/G36,"") -> 2 | N36: =IF(AND(I36<>"",I36<>0),G36/I36,"") | O36: =D36/P36 -> 1.0176481 | P36: =$I$8*V36*W36/SUMPRODUCT($W$25:$W$55,$V$25:$V$55) -> 19040.963 | Q36: =$I$9*V36*W36/SUMPRODUCT($W$25:$W$55,$V$25:$V$55) -> 5.1601526 | R36: =IF($I$12="","",Q36/$I$12) -> 3.2250954 | S36: =IF(W36<>"",IF(D36<>"",D36,($I$8-SUM($S$25:S35))*V36*W36/SUMPRODUCT($W36:$W$55,$V36:$V$55)),"") -> 19377 | T36: =IF(W36<>"",IF(E36<>"",E36,($I$9-SUM($T$25:T35))*V36*W36/SUMPRODUCT($W36:$W$55,$V36:$V$55)),"") -> 4 | U36: =IF(W36<>"",IF($I$12<>"",IF(G36<>"",G36,($I$9/$I$12-SUM($U$25:U35))*V36*W36/SUMPRODUCT($W36:$W$55,$V36:$V$55)),""),"") -> 2 | V36: 0.9 | W36: 0.9
A37: 13 | B37: 45677 | C37: пн | D37: 26748 | E37: 6 | F37: =IF(AND(E37<>"",E37<>0),D37/E37,"") -> 4458 | G37: 2 | H37: =IF(AND(G37<>"",G37<>0),D37/G37,"") -> 13374 | J37: =IF(AND(G37<>"",G37<>0),E37/G37,"") -> 3 | N37: =IF(AND(I37<>"",I37<>0),G37/I37,"") | O37: =D37/P37 -> 1.7779005 | P37: =$I$8*V37*W37/SUMPRODUCT($W$25:$W$55,$V$25:$V$55) -> 15044.712 | Q37: =$I$9*V37*W37/SUMPRODUCT($W$25:$W$55,$V$25:$V$55) -> 4.0771576 | R37: =IF($I$12="","",Q37/$I$12) -> 2.5482235 | S37: =IF(W37<>"",IF(D37<>"",D37,($I$8-SUM($S$25:S36))*V37*W37/SUMPRODUCT($W37:$W$55,$V37:$V$55)),"") -> 26748 | T37: =IF(W37<>"",IF(E37<>"",E37,($I$9-SUM($T$25:T36))*V37*W37/SUMPRODUCT($W37:$W$55,$V37:$V$55)),"") -> 6 | U37: =IF(W37<>"",IF($I$12<>"",IF(G37<>"",G37,($I$9/$I$12-SUM($U$25:U36))*V37*W37/SUMPRODUCT($W37:$W$55,$V37:$V$55)),""),"") -> 2 | V37: 0.8 | W37: 0.8
A38: 14 | B38: 45678 | C38: вт | D38: 11075 | E38: 3 | F38: =IF(AND(E38<>"",E38<>0),D38/E38,"") -> 3691.6667 | G38: 2 | H38: =IF(AND(G38<>"",G38<>0),D38/G38,"") -> 5537.5 | J38: =IF(AND(G38<>"",G38<>0),E38/G38,"") -> 1.5 | N38: =IF(AND(I38<>"",I38<>0),G38/I38,"") | O38: =D38/P38 -> 0.73613907 | P38: =$I$8*V38*W38/SUMPRODUCT($W$25:$W$55,$V$25:$V$55) -> 15044.712 | Q38: =$I$9*V38*W38/SUMPRODUCT($W$25:$W$55,$V$25:$V$55) -> 4.0771576 | R38: =IF($I$12="","",Q38/$I$12) -> 2.5482235 | S38: =IF(W38<>"",IF(D38<>"",D38,($I$8-SUM($S$25:S37))*V38*W38/SUMPRODUCT($W38:$W$55,$V38:$V$55)),"") -> 11075 | T38: =IF(W38<>"",IF(E38<>"",E38,($I$9-SUM($T$25:T37))*V38*W38/SUMPRODUCT($W38:$W$55,$V38:$V$55)),"") -> 3 | U38: =IF(W38<>"",IF($I$12<>"",IF(G38<>"",G38,($I$9/$I$12-SUM($U$25:U37))*V38*W38/SUMPRODUCT($W38:$W$55,$V38:$V$55)),""),"") -> 2 | V38: 0.8 | W38: 0.8
A39: 15 | F39: =IF(AND(E39<>"",E39<>0),D39/E39,"") | H39: =IF(AND(G39<>"",G39<>0),D39/G39,"") | J39: =IF(AND(G39<>"",G39<>0),E39/G39,"") | N39: =IF(AND(I39<>"",I39<>0),G39/I39,"") | O39: =D39/P39 -> 0 | P39: =$I$8*V39*W39/SUMPRODUCT($W$25:$W$60,$V$25:$V$60) -> 23507.362 | Q39: =$I$9*V39*W39/SUMPRODUCT($W$25:$W$60,$V$25:$V$60) -> 6.3705588 | R39: =IF($I$12="","",Q39/$I$12) -> 3.9815992 | S39: =IF(W39<>"",IF(D39<>"",D39,($I$8-SUM($S$25:S38))*V39*W39/SUMPRODUCT($W39:$W$60,$V39:$V$60)),"") -> 5801.615 | T39: =IF(W39<>"",IF(E39<>"",E39,($I$9-SUM($T$25:T38))*V39*W39/SUMPRODUCT($W39:$W$60,$V39:$V$60)),"") -> 1.510204 | U39: =IF(W39<>"",IF($I$12<>"",IF(G39<>"",G39,($I$9/$I$12-SUM($U$25:U38))*V39*W39/SUMPRODUCT($W39:$W$60,$V39:$V$60)),""),"") -> 2.9063775 | V39: 1 | W39: 1
A40: 16 | F40: =IF(AND(E40<>"",E40<>0),D40/E40,"") | H40: =IF(AND(G40<>"",G40<>0),D40/G40,"") | J40: =IF(AND(G40<>"",G40<>0),E40/G40,"") | N40: =IF(AND(I40<>"",I40<>0),G40/I40,"") | O40: =D40/P40 -> 0 | P40: =$I$8*V40*W40/SUMPRODUCT($W$25:$W$60,$V$25:$V$60) -> 23507.362 | Q40: =$I$9*V40*W40/SUMPRODUCT($W$25:$W$60,$V$25:$V$60) -> 6.3705588 | R40: =IF($I$12="","",Q40/$I$12) -> 3.9815992 | S40: =IF(W40<>"",IF(D40<>"",D40,($I$8-SUM($S$25:S39))*V40*W40/SUMPRODUCT($W40:$W$60,$V40:$V$60)),"") -> 5801.615 | T40: =IF(W40<>"",IF(E40<>"",E40,($I$9-SUM($T$25:T39))*V40*W40/SUMPRODUCT($W40:$W$60,$V40:$V$60)),"") -> 1.510204 | U40: =IF(W40<>"",IF($I$12<>"",IF(G40<>"",G40,($I$9/$I$12-SUM($U$25:U39))*V40*W40/SUMPRODUCT($W40:$W$60,$V40:$V$60)),""),"") -> 2.9063775 | V40: 1 | W40: 1
A41: 17 | F41: =IF(AND(E41<>"",E41<>0),D41/E41,"") | H41: =IF(AND(G41<>"",G41<>0),D41/G41,"") | J41: =IF(AND(G41<>"",G41<>0),E41/G41,"") | N41: =IF(AND(I41<>"",I41<>0),G41/I41,"") | O41: =D41/P41 -> 0 | P41: =$I$8*V41*W41/SUMPRODUCT($W$25:$W$60,$V$25:$V$60) -> 23507.362 | Q41: =$I$9*V41*W41/SUMPRODUCT($W$25:$W$60,$V$25:$V$60) -> 6.3705588 | R41: =IF($I$12="","",Q41/$I$12) -> 3.9815992 | S41: =IF(W41<>"",IF(D41<>"",D41,($I$8-SUM($S$25:S40))*V41*W41/SUMPRODUCT($W41:$W$60,$V41:$V$60)),"") -> 5801.615 | T41: =IF(W41<>"",IF(E41<>"",E41,($I$9-SUM($T$25:T40))*V41*W41/SUMPRODUCT($W41:$W$60,$V41:$V$60)),"") -> 1.510204 | U41: =IF(W41<>"",IF($I$12<>"",IF(G41<>"",G41,($I$9/$I$12-SUM($U$25:U40))*V41*W41/SUMPRODUCT($W41:$W$60,$V41:$V$60)),""),"") -> 2.9063775 | V41: 1 | W41: 1
A42: 18 | F42: =IF(AND(E42<>"",E42<>0),D42/E42,"") | H42: =IF(AND(G42<>"",G42<>0),D42/G42,"") | J42: =IF(AND(G42<>"",G42<>0),E42/G42,"") | N42: =IF(AND(I42<>"",I42<>0),G42/I42,"") | O42: =D42/P42 -> 0 | P42: =$I$8*V42*W42/SUMPRODUCT($W$25:$W$60,$V$25:$V$60) -> 23507.362 | Q42: =$I$9*V42*W42/SUMPRODUCT($W$25:$W$60,$V$25:$V$60) -> 6.3705588 | R42: =IF($I$12="","",Q42/$I$12) -> 3.9815992 | S42: =IF(W42<>"",IF(D42<>"",D42,($I$8-SUM($S$25:S41))*V42*W42/SUMPRODUCT($W42:$W$60,$V42:$V$60)),"") -> 5801.615 | T42: =IF(W42<>"",IF(E42<>"",E42,($I$9-SUM($T$25:T41))*V42*W42/SUMPRODUCT($W42:$W$60,$V42:$V$60)),"") -> 1.510204 | U42: =IF(W42<>"",IF($I$12<>"",IF(G42<>"",G42,($I$9/$I$12-SUM($U$25:U41))*V42*W42/SUMPRODUCT($W42:$W$60,$V42:$V$60)),""),"") -> 2.9063775 | V42: 1 | W42: 1
A43: 19 | F43: =IF(AND(E43<>"",E43<>0),D43/E43,"") | H43: =IF(AND(G43<>"",G43<>0),D43/G43,"") | J43: =IF(AND(G43<>"",G43<>0),E43/G43,"") | N43: =IF(AND(I43<>"",I43<>0),G43/I43,"") | O43: =D43/P43 -> 0 | P43: =$I$8*V43*W43/SUMPRODUCT($W$25:$W$60,$V$25:$V$60) -> 23507.362 | Q43: =$I$9*V43*W43/SUMPRODUCT($W$25:$W$60,$V$25:$V$60) -> 6.3705588 | R43: =IF($I$12="","",Q43/$I$12) -> 3.9815992 | S43: =IF(W43<>"",IF(D43<>"",D43,($I$8-SUM($S$25:S42))*V43*W43/SUMPRODUCT($W43:$W$60,$V43:$V$60)),"") -> 5801.615 | T43: =IF(W43<>"",IF(E43<>"",E43,($I$9-SUM($T$25:T42))*V43*W43/SUMPRODUCT($W43:$W$60,$V43:$V$60)),"") -> 1.510204 | U43: =IF(W43<>"",IF($I$12<>"",IF(G43<>"",G43,($I$9/$I$12-SUM($U$25:U42))*V43*W43/SUMPRODUCT($W43:$W$60,$V43:$V$60)),""),"") -> 2.9063775 | V43: 1 | W43: 1
A44: 20 | F44: =IF(AND(E44<>"",E44<>0),D44/E44,"") | H44: =IF(AND(G44<>"",G44<>0),D44/G44,"") | J44: =IF(AND(G44<>"",G44<>0),E44/G44,"") | N44: =IF(AND(I44<>"",I44<>0),G44/I44,"") | O44: =D44/P44 -> 0 | P44: =$I$8*V44*W44/SUMPRODUCT($W$25:$W$60,$V$25:$V$60) -> 23507.362 | Q44: =$I$9*V44*W44/SUMPRODUCT($W$25:$W$60,$V$25:$V$60) -> 6.3705588 | R44: =IF($I$12="","",Q44/$I$12) -> 3.9815992 | S44: =IF(W44<>"",IF(D44<>"",D44,($I$8-SUM($S$25:S43))*V44*W44/SUMPRODUCT($W44:$W$60,$V44:$V$60)),"") -> 5801.615 | T44: =IF(W44<>"",IF(E44<>"",E44,($I$9-SUM($T$25:T43))*V44*W44/SUMPRODUCT($W44:$W$60,$V44:$V$60)),"") -> 1.510204 | U44: =IF(W44<>"",IF($I$12<>"",IF(G44<>"",G44,($I$9/$I$12-SUM($U$25:U43))*V44*W44/SUMPRODUCT($W44:$W$60,$V44:$V$60)),""),"") -> 2.9063775 | V44: 1 | W44: 1
A45: 21 | F45: =IF(AND(E45<>"",E45<>0),D45/E45,"") | H45: =IF(AND(G45<>"",G45<>0),D45/G45,"") | J45: =IF(AND(G45<>"",G45<>0),E45/G45,"") | N45: =IF(AND(I45<>"",I45<>0),G45/I45,"") | O45: =D45/P45 -> 0 | P45: =$I$8*V45*W45/SUMPRODUCT($W$25:$W$60,$V$25:$V$60) -> 23507.362 | Q45: =$I$9*V45*W45/SUMPRODUCT($W$25:$W$60,$V$25:$V$60) -> 6.3705588 | R45: =IF($I$12="","",Q45/$I$12) -> 3.9815992 | S45: =IF(W45<>"",IF(D45<>"",D45,($I$8-SUM($S$25:S44))*V45*W45/SUMPRODUCT($W45:$W$60,$V45:$V$60)),"") -> 5801.615 | T45: =IF(W45<>"",IF(E45<>"",E45,($I$9-SUM($T$25:T44))*V45*W45/SUMPRODUCT($W45:$W$60,$V45:$V$60)),"") -> 1.510204 | U45: =IF(W45<>"",IF($I$12<>"",IF(G45<>"",G45,($I$9/$I$12-SUM($U$25:U44))*V45*W45/SUMPRODUCT($W45:$W$60,$V45:$V$60)),""),"") -> 2.9063775 | V45: 1 | W45: 1
A46: 22 | F46: =IF(AND(E46<>"",E46<>0),D46/E46,"") | H46: =IF(AND(G46<>"",G46<>0),D46/G46,"") | J46: =IF(AND(G46<>"",G46<>0),E46/G46,"") | N46: =IF(AND(I46<>"",I46<>0),G46/I46,"") | O46: =D46/P46 -> 0 | P46: =$I$8*V46*W46/SUMPRODUCT($W$25:$W$60,$V$25:$V$60) -> 23507.362 | Q46: =$I$9*V46*W46/SUMPRODUCT($W$25:$W$60,$V$25:$V$60) -> 6.3705588 | R46: =IF($I$12="","",Q46/$I$12) -> 3.9815992 | S46: =IF(W46<>"",IF(D46<>"",D46,($I$8-SUM($S$25:S45))*V46*W46/SUMPRODUCT($W46:$W$60,$V46:$V$60)),"") -> 5801.615 | T46: =IF(W46<>"",IF(E46<>"",E46,($I$9-SUM($T$25:T45))*V46*W46/SUMPRODUCT($W46:$W$60,$V46:$V$60)),"") -> 1.510204 | U46: =IF(W46<>"",IF($I$12<>"",IF(G46<>"",G46,($I$9/$I$12-SUM($U$25:U45))*V46*W46/SUMPRODUCT($W46:$W$60,$V46:$V$60)),""),"") -> 2.9063775 | V46: 1 | W46: 1
A47: 23 | F47: =IF(AND(E47<>"",E47<>0),D47/E47,"") | H47: =IF(AND(G47<>"",G47<>0),D47/G47,"") | J47: =IF(AND(G47<>"",G47<>0),E47/G47,"") | N47: =IF(AND(I47<>"",I47<>0),G47/I47,"") | O47: =D47/P47 -> 0 | P47: =$I$8*V47*W47/SUMPRODUCT($W$25:$W$60,$V$25:$V$60) -> 23507.362 | Q47: =$I$9*V47*W47/SUMPRODUCT($W$25:$W$60,$V$25:$V$60) -> 6.3705588 | R47: =IF($I$12="","",Q47/$I$12) -> 3.9815992 | S47: =IF(W47<>"",IF(D47<>"",D47,($I$8-SUM($S$25:S46))*V47*W47/SUMPRODUCT($W47:$W$60,$V47:$V$60)),"") -> 5801.615 | T47: =IF(W47<>"",IF(E47<>"",E47,($I$9-SUM($T$25:T46))*V47*W47/SUMPRODUCT($W47:$W$60,$V47:$V$60)),"") -> 1.510204 | U47: =IF(W47<>"",IF($I$12<>"",IF(G47<>"",G47,($I$9/$I$12-SUM($U$25:U46))*V47*W47/SUMPRODUCT($W47:$W$60,$V47:$V$60)),""),"") -> 2.9063775 | V47: 1 | W47: 1
A48: 24 | F48: =IF(AND(E48<>"",E48<>0),D48/E48,"") | H48: =IF(AND(G48<>"",G48<>0),D48/G48,"") | J48: =IF(AND(G48<>"",G48<>0),E48/G48,"") | N48: =IF(AND(I48<>"",I48<>0),G48/I48,"") | O48: =D48/P48 -> 0 | P48: =$I$8*V48*W48/SUMPRODUCT($W$25:$W$60,$V$25:$V$60) -> 23507.362 | Q48: =$I$9*V48*W48/SUMPRODUCT($W$25:$W$60,$V$25:$V$60) -> 6.3705588 | R48: =IF($I$12="","",Q48/$I$12) -> 3.9815992 | S48: =IF(W48<>"",IF(D48<>"",D48,($I$8-SUM($S$25:S47))*V48*W48/SUMPRODUCT($W48:$W$60,$V48:$V$60)),"") -> 5801.615 | T48: =IF(W48<>"",IF(E48<>"",E48,($I$9-SUM($T$25:T47))*V48*W48/SUMPRODUCT($W48:$W$60,$V48:$V$60)),"") -> 1.510204 | U48: =IF(W48<>"",IF($I$12<>"",IF(G48<>"",G48,($I$9/$I$12-SUM($U$25:U47))*V48*W48/SUMPRODUCT($W48:$W$60,$V48:$V$60)),""),"") -> 2.9063775 | V48: 1 | W48: 1
F49: =IF(AND(E49<>"",E49<>0),D49/E49,"") | H49: =IF(AND(G49<>"",G49<>0),D49/G49,"") | J49: =IF(AND(G49<>"",G49<>0),E49/G49,"") | N49: =IF(AND(I49<>"",I49<>0),G49/I49,"") | O49: =D49/P49 -> #DIV/0! | P49: =$I$8*V49*W49/SUMPRODUCT($W$25:$W$60,$V$25:$V$60) -> 0 | Q49: =$I$9*V49*W49/SUMPRODUCT($W$25:$W$49,$V$25:$V$49) -> 0 | R49: =IF($I$12="","",Q49/$I$12) -> 0 | S49: =IF(W49<>"",IF(D49<>"",D49,($I$8-SUM($S$25:S44))*V49*W49/SUMPRODUCT($W49:$W$60,$V49:$V$60)),"") | T49: =IF(W49<>"",IF(E49<>"",E49,($I$9-SUM($T$25:T44))*V49*W49/SUMPRODUCT($W49:$W$49,$V49:$V$49)),"") | U49: =IF(W49<>"",IF($I$12<>"",IF(G49<>"",G49,($I$9/$I$12-SUM($U$25:U44))*V49*W49/SUMPRODUCT($W49:$W$49,$V49:$V$49)),""),"")
B50: итого | D50: =SUM(D25:D49) -> 517697.6 | E50: =SUM(E25:E49) -> 116 | F50: =IF(AND(E50<>"",E50<>0),D50/E50,"") -> 4462.9103 | G50: =SUM(G25:G49) -> 60 | H50: =IF(AND(G50<>"",G50<>0),D50/G50,"") -> 8628.2933 | I50: =SUM(I25:I49) -> 0 | J50: =IF(AND(G50<>"",G50<>0),E50/G50,"") -> 1.9333333 | K50: =SUM(K25:K49) -> 0 | L50: =SUM(L25:L49) -> 0 | M50: =SUM(M25:M49) -> 0 | N50: =IF(AND(I50<>"",I50<>0),G50/I50,"") | O50: =D50/P50 -> 0.75470351 | P50: =SUM(P25:P49) -> 685961.56 | Q50: =SUM(Q25:Q49) -> 180.18732 | R50: =SUM(R25:R49) -> 112.36707 | S50: =SUM(S25:S49) -> 556000 | T50: =SUM(T25:T49) -> 144.10204 | U50: =SUM(U25:U49) -> 90.063775
D51: =SUMIF(D25:D49,"",P25:P49)+D50 -> 823293.31

Sheet Рогалевич И. Е.
B1: =TODAY()-1 -> 45696
B2: (отчетная дата) | J2: ЕЖЕДНЕВНЫЙ ОТЧЕТ О ПРОДАЖАХ
B3: Осталось до выполнения плана!!! | J3: =График!B29 -> Рогалевич Ирина
C4: =I8-D50 -> 85792.539 | E4: =IF(I8<>0,C4/I8,0) -> 0.093277044
F6: Целевые показатели
F7: Показатель | I7: План | J7: Факт | K7: % выполнения | L7: Прогноз выполнения | M7: % выполнения по прогнозу | N7: Отклонение | O7: Факт аналогичного месяца прошлого года | P7: Отклонение LFL
F8: Выручка | I8: ='Ялта, Ленина, 18'!I8/График!AJ31*График!AJ29 -> 919760.48 | J8: =D50 -> 833967.94 | K8: =IF(AND(I8<>"",I8<>0,J8<>""),J8/I8,"") -> 0.90672296 | L8: =IF(SUMIF($D$25:$D$49,">=0",$P$25:$P$49)<>0,I8*D50/SUMIF($D$25:$D$49,">=0",$P$25:$P$49),0) -> 817630.81 | M8: =IF(AND(I8<>"",I8<>0,L8<>"",L8<>0),L8/I8,"") -> 0.88896059 | N8: =IF(AND(J8<>0,J8<>"",I8<>0,I8<>""),L8-I8,"") -> -102129.67 | P8: =IF(AND(O8<>"",O8<>0,L8<>"",L8<>0),-O8+L8,"") | Q8: =IF(AND(P8<>"",P8<>0,O8<>0,O8<>""),P8/O8,"")
F9: Кол-во изделий | I9: =I8/I11 -> 249.25758 | J9: =E50 -> 205 | K9: =IF(AND(I9<>"",I9<>0,J9<>""),J9/I9,"") -> 0.82244238 | L9: =IF(SUMIF($E$25:$E$48,">=0",$Q$25:$Q$48)<>0,I9*E50/SUMIF($E$25:$E$48,">=0",$Q$25:$Q$48),0) -> 216.76914 | M9: =IF(AND(I9<>"",I9<>0,L9<>"",L9<>0),L9/I9,"") -> 0.86965916 | N9: =IF(AND(J9<>0,J9<>"",I9<>0,I9<>""),L9-I9,"") -> -32.488443 | O9: =O8/O11 -> #DIV/0! | P9: =IF(AND(O9<>"",O9<>0,L9<>"",L9<>0),-O9+L9,"") -> #DIV/0! | Q9: =IF(AND(P9<>"",P9<>0,O9<>0,O9<>""),P9/O9,"") -> #DIV/0!
F10: Средний чек | I10: =I11*I12 -> 5904 | J10: =H50 -> 8257.1083 | K10: =IF(AND(I10<>"",I10<>0,J10<>""),J10/I10,"") -> 1.3985617 | L10: =J10 -> 8257.1083 | M10: =IF(AND(I10<>"",I10<>0,L10<>"",L10<>0),L10/I10,"") -> 1.3985617 | N10: =IF(AND(J10<>0,J10<>"",I10<>0,I10<>""),L10-I10,"") -> 2353.1083 | O10: =O11*O12 -> 0 | P10: =IF(AND(O10<>"",O10<>0,L10<>"",L10<>0),-O10+L10,"") | Q10: =IF(AND(P10<>"",P10<>0,O10<>0,O10<>""),P10/O10,"")
F11: Средняя стоимость изделия | I11: ='Ялта, Ленина, 18'!I11 -> 3690 | J11: =F50 -> 4068.1363 | K11: =IF(AND(I11<>"",I11<>0,J11<>""),J11/I11,"") -> 1.102476 | L11: =IF(L9>0,L8/L9,"") -> 3771.8967 | M11: =IF(AND(I11<>"",I11<>0,L11<>"",L11<>0),L11/I11,"") -> 1.0221942 | N11: =IF(AND(J11<>0,J11<>"",I11<>0,I11<>""),L11-I11,"") -> 81.89675 | P11: =IF(AND(O11<>"",O11<>0,L11<>"",L11<>0),-O11+L11,"") | Q11: =IF(AND(P11<>"",P11<>0,O11<>0,O11<>""),P11/O11,"")
F12: Длина чека | I12: ='Ялта, Ленина, 18'!I12 -> 1.6 | J12: =J50 -> 2.029703 | K12: =IF(AND(I12<>"",I12<>0,J12<>""),J12/I12,"") -> 1.2685644 | L12: =J12 -> 2.029703 | M12: =IF(AND(I12<>"",I12<>0,L12<>"",L12<>0),L12/I12,"") -> 1.2685644 | N12: =IF(AND(J12<>0,J12<>"",I12<>0,I12<>""),L12-I12,"") -> 0.42970297 | P12: =IF(AND(O12<>"",O12<>0,L12<>"",L12<>0),-O12+L12,"") | Q12: =IF(AND(P12<>"",P12<>0,O12<>0,O12<>""),P12/O12,"")
F13: Кол-во чеков | I13: =IF(I12<>0,I9/I12,"") -> 155.78599 | J13: =G50 -> 101 | K13: =IF(AND(I13<>"",I13<>0,J13<>""),J13/I13,"") -> 0.64832531 | L13: =IF(SUMIF($G$25:$G$48,">=0",$R$25:$R$48)<>0,I13*G50/SUMIF($G$25:$G$48,">=0",$R$25:$R$48),"") -> 106.88914 | M13: =IF(AND(I13<>"",I13<>0,L13<>"",L13<>0),L13/I13,"") -> 0.6861281 | N13: =IF(AND(J13<>0,J13<>"",I13<>0,I13<>""),L13-I13,"") -> -48.896845 | P13: =IF(AND(O13<>"",O13<>0,L13<>"",L13<>0),-O13+L13,"") | Q13: =IF(AND(P13<>"",P13<>0,O13<>0,O13<>""),P13/O13,"")
F14: Кол-во смен план/отработано | I14: =График!AI29 -> 24 | J14: 24 | K14: =IF(AND(I14<>"",I14<>0,J14<>""),J14/I14,"") -> 1 | L14: =IF(SUMIF($D$25:$D$48,">=0",$P$25:$P$48),I50*I8/SUMIF($D$25:$D$48,">=0",$P$25:$P$48),"") -> 0 | M14: =IF(AND(I14<>"",I14<>0,L14<>"",L14<>0),L14/I14,"") | N14: =IF(AND(J14<>0,J14<>"",I14<>0,I14<>""),L14-I14,"") -> -24 | P14: =IF(AND(O14<>"",O14<>0,L14<>"",L14<>0),-O14+L14,"") | Q14: =IF(AND(P14<>"",P14<>0,O14<>0,O14<>""),P14/O14,"")
F15: Средние продажи в смену | I15: ='Ялта, Ленина, 18'!I15 -> 60000 | J15: =J8/J14 -> 34748.664 | K15: =IF(AND(I15<>"",I15<>0,J15<>""),J15/I15,"") -> 0.5791444 | L15: =J15 -> 34748.664 | M15: =IF(AND(I15<>"",I15<>0,L15<>"",L15<>0),L15/I15,"") -> 0.5791444 | N15: =IF(AND(J15<>0,J15<>"",I15<>0,I15<>""),L15-I15,"") -> -25251.336 | P15: =IF(AND(O15<>"",O15<>0,L15<>"",L15<>0),-O15+L15,"") | Q15: =IF(AND(P15<>"",P15<>0,O15<>0,O15<>""),P15/O15,"")
F16: Отставание/Перевыполнение | J16: =J8-I15*J14 -> -606032.06 | K16: =IF(AND(I16<>"",I16<>0,J16<>""),J16/I16,"") | L16: =J16 -> -606032.06 | M16: =IF(AND(I16<>"",I16<>0,L16<>"",L16<>0),L16/I16,"") | N16: =IF(AND(J16<>0,J16<>"",I16<>0,I16<>""),L16-I16,"") | P16: =IF(AND(O16<>"",O16<>0,L16<>"",L16<>0),-O16+L16,"") | Q16: =IF(AND(P16<>"",P16<>0,O16<>0,O16<>""),P16/O16,"") | S16: Подарочные сертификаты
F17: Трафик | I17: ='Ялта, Ленина, 18'!I17/График!AJ31*График!AJ26 -> 0 | J17: =I50 -> 0 | K17: =IF(AND(I17<>"",I17<>0,J17<>""),J17/I17,"") | L17: =J17 -> 0 | M17: =IF(AND(I17<>"",I17<>0,L17<>"",L17<>0),L17/I17,"") | N17: =IF(AND(J17<>0,J17<>"",I17<>0,I17<>""),L17-I17,"") | P17: =IF(AND(O17<>"",O17<>0,L17<>"",L17<>0),-O17+L17,"") | Q17: =IF(AND(P17<>"",P17<>0,O17<>0,O17<>""),P17/O17,"")
K18: =IF(AND(I18<>"",I18<>0,J18<>""),J18/I18,"") | L18: =J18 -> 0 | M18: =IF(AND(I18<>"",I18<>0,L18<>"",L18<>0),L18/I18,"") | N18: =IF(AND(J18<>0,J18<>"",I18<>0,I18<>""),L18-I18,"") | O18: 0 | P18: =IF(AND(O18<>"",O18<>0,L18<>"",L18<>0),-O18+L18,"") | Q18: =IF(AND(P18<>"",P18<>0,O18<>0,O18<>""),P18/O18,"")
J19: =M50 -> 0 | K19: =IF(AND(I19<>"",I19<>0,J19<>""),J19/I19,"") | L19: =J19 -> 0 | M19: =IF(AND(I19<>"",I19<>0,L19<>"",L19<>0),L19/I19,"") | N19: =IF(AND(J19<>0,J19<>"",I19<>0,I19<>""),L19-I19,"") | O19: 0 | P19: =IF(AND(O19<>"",O19<>0,L19<>"",L19<>0),-O19+L19,"") | Q19: =IF(AND(P19<>"",P19<>0,O19<>0,O19<>""),P19/O19,"") | S19: =S18/I16 -> #DIV/0!
F20: Конверсия план/факт | I20: ='Ялта, Ленина, 18'!I20 -> 0.257 | J20: =N50 | K20: =J20/I20 -> #VALUE! | L20: =IF(AND(K8<>0,I14<>0,I50<>0),(I50*N50+(I50/K8-I50)*I20)/(I50/K8),0) -> 0 | M20: =IF(AND(I20<>"",I20<>0,L20<>"",L20<>0),L20/I20,"") | N20: =IF(AND(J20<>0,J20<>"",I20<>0,I20<>""),L20-I20,"") | P20: =IF(AND(O20<>"",O20<>0,L20<>"",L20<>0),-O20+L20,"") | Q20: =IF(AND(P20<>"",P20<>0,O20<>0,O20<>""),P20/O20,"")
B22: Факт продаж за месяц | O22: % выполнения дневного плана | P22: Раcпределение плана по дням
B23: Дата | C23: День недели | D23: Выручка (руб) | E23: Кол-во единиц (шт.) | F23: Средняя стоимость изделия (руб.) | G23: Количество чеков (шт.) | H23: Средняя сумма чека (руб.) | I23: Трафик | J23: Длина чека (шт.) | K23: Запасной | L23: Запасной | M23: Запасной | N23: Конверсия (%) | P23: выручка, план | Q23: кол-во ед, план | R23: Кол-во чеков, план | S23: выручка, скорректир.план | T23: кол-во ед, скорр. план | U23: кол-во чеков, скорр. план | V23: Коэфф. Дня Недели | W23: Специфика месяца
B24: 1 | C24: 2 | D24: 3 | E24: 4 | F24: 5 | G24: 6 | H24: 7 | I24: 8 | J24: 9 | K24: 10 | L24: 11 | M24: 12 | N24: 13 | P24: 1 | Q24: 2 | R24: 3 | S24: 4 | T24: 5 | U24: 6 | V24: 10 | W24: 11
A25: 1 | B25: 45663 | C25: пн | D25: 37861 | E25: 12 | F25: =IF(AND(E25<>"",E25<>0),D25/E25,"") -> 3155.0833 | G25: 9 | H25: =IF(AND(G25<>"",G25<>0),D25/G25,"") -> 4206.7778 | J25: =IF(AND(G25<>"",G25<>0),E25/G25,"") -> 1.3333333 | N25: =IF(AND(I25<>"",I25<>0),G25/I25,"") | O25: =D25/P25 -> 0.55857231 | P25: =$I$8*V25*W25/SUMPRODUCT($W$25:$W$57,$V$25:$V$57) -> 67781.734 | Q25: =$I$9*V25*W25/SUMPRODUCT($W$25:$W$57,$V$25:$V$57) -> 18.369034 | R25: =IF($I$12="","",Q25/$I$12) -> 11.480646 | S25: =IF(W25<>"",IF(D25<>"",D25,($I$8-SUM($S24:S$25))*V25*W25/SUMPRODUCT($W25:$W$57,$V25:$V$57)),"") -> 37861 | T25: =IF(W25<>"",IF(E25<>"",E25,($I$9-SUM($T24:T$25))*V25*W25/SUMPRODUCT($W25:$W$57,$V25:$V$57)),"") -> 12 | U25: =IF(W25<>"",IF($I$12<>"",IF(G25<>"",G25,($I$9/$I$12-SUM($U24:U$25))*V25*W25/SUMPRODUCT($W25:$W$57,$V25:$V$57)),""),"") -> 9 | V25: 1.2 | W25: 1.2
A26: 2 | B26: 45664 | C26: вт | D26: 65247 | E26: 16 | F26: =IF(AND(E26<>"",E26<>0),D26/E26,"") -> 4077.9375 | G26: 10 | H26: =IF(AND(G26<>"",G26<>0),D26/G26,"") -> 6524.7 | J26: =IF(AND(G26<>"",G26<>0),E26/G26,"") -> 1.6 | N26: =IF(AND(I26<>"",I26<>0),G26/I26,"") | O26: =D26/P26 -> 0.96260446 | P26: =$I$8*V26*W26/SUMPRODUCT($W$25:$W$57,$V$25:$V$57) -> 67781.734 | Q26: =$I$9*V26*W26/SUMPRODUCT($W$25:$W$57,$V$25:$V$57) -> 18.369034 | R26: =IF($I$12="","",Q26/$I$12) -> 11.480646 | S26: =IF(W26<>"",IF(D26<>"",D26,($I$8-SUM($S$25:S25))*V26*W26/SUMPRODUCT($W26:$W$57,$V26:$V$57)),"") -> 65247 | T26: =IF(W26<>"",IF(E26<>"",E26,($I$9-SUM($T$25:T25))*V26*W26/SUMPRODUCT($W26:$W$57,$V26:$V$57)),"") -> 16 | U26: =IF(W26<>"",IF($I$12<>"",IF(G26<>"",G26,($I$9/$I$12-SUM($U$25:U25))*V26*W26/SUMPRODUCT($W26:$W$57,$V26:$V$57)),""),"") -> 10 | V26: 1.2 | W26: 1.2
A27: 3 | B27: 45665 | C27: ср | D27: 64146 | F27: =IF(AND(E27<>"",E27<>0),D27/E27,"") | H27: =IF(AND(G27<>"",G27<>0),D27/G27,"") | J27: =IF(AND(G27<>"",G27<>0),E27/G27,"") | N27: =IF(AND(I27<>"",I27<>0),G27/I27,"") | O27: =D27/P27 -> 0.94636115 | P27: =$I$8*V27*W27/SUMPRODUCT($W$25:$W$57,$V$25:$V$57) -> 67781.734 | Q27: =$I$9*V27*W27/SUMPRODUCT($W$25:$W$57,$V$25:$V$57) -> 18.369034 | R27: =IF($I$12="","",Q27/$I$12) -> 11.480646 | S27: =IF(W27<>"",IF(D27<>"",D27,($I$8-SUM($S$25:S26))*V27*W27/SUMPRODUCT($W27:$W$57,$V27:$V$57)),"") -> 64146 | T27: =IF(W27<>"",IF(E27<>"",E27,($I$9-SUM($T$25:T26))*V27*W27/SUMPRODUCT($W27:$W$57,$V27:$V$57)),"") -> 19.124305 | U27: =IF(W27<>"",IF($I$12<>"",IF(G27<>"",G27,($I$9/$I$12-SUM($U$25:U26))*V27*W27/SUMPRODUCT($W27:$W$57,$V27:$V$57)),""),"") -> 11.823039 | V27: 1.2 | W27: 1.2
A28: 4 | B28: 45666 | C28: чт | D28: 93262 | E28: 27 | F28: =IF(AND(E28<>"",E28<>0),D28/E28,"") -> 3454.1481 | G28: 5 | H28: =IF(AND(G28<>"",G28<>0),D28/G28,"") -> 18652.4 | J28: =IF(AND(G28<>"",G28<>0),E28/G28,"") -> 5.4 | N28: =IF(AND(I28<>"",I28<>0),G28/I28,"") | O28: =D28/P28 -> 1.9813196 | P28: =$I$8*V28*W28/SUMPRODUCT($W$25:$W$57,$V$25:$V$57) -> 47070.649 | Q28: =$I$9*V28*W28/SUMPRODUCT($W$25:$W$57,$V$25:$V$57) -> 12.756273 | R28: =IF($I$12="","",Q28/$I$12) -> 7.9726709 | S28: =IF(W28<>"",IF(D28<>"",D28,($I$8-SUM($S$25:S27))*V28*W28/SUMPRODUCT($W28:$W$57,$V28:$V$57)),"") -> 93262 | T28: =IF(W28<>"",IF(E28<>"",E28,($I$9-SUM($T$25:T27))*V28*W28/SUMPRODUCT($W28:$W$57,$V28:$V$57)),"") -> 27 | U28: =IF(W28<>"",IF($I$12<>"",IF(G28<>"",G28,($I$9/$I$12-SUM($U$25:U27))*V28*W28/SUMPRODUCT($W28:$W$57,$V28:$V$57)),""),"") -> 5 | V28: 1 | W28: 1
A29: 5 | B29: 45667 | C29: пт | D29: 39739 | E29: 10 | F29: =IF(AND(E29<>"",E29<>0),D29/E29,"") -> 3973.9 | G29: 7 | H29: =IF(AND(G29<>"",G29<>0),D29/G29,"") -> 5677 | J29: =IF(AND(G29<>"",G29<>0),E29/G29,"") -> 1.4285714 | N29: =IF(AND(I29<>"",I29<>0),G29/I29,"") | O29: =D29/P29 -> 0.8442416 | P29: =$I$8*V29*W29/SUMPRODUCT($W$25:$W$57,$V$25:$V$57) -> 47070.649 | Q29: =$I$9*V29*W29/SUMPRODUCT($W$25:$W$57,$V$25:$V$57) -> 12.756273 | R29: =IF($I$12="","",Q29/$I$12) -> 7.9726709 | S29: =IF(W29<>"",IF(D29<>"",D29,($I$8-SUM($S$25:S28))*V29*W29/SUMPRODUCT($W29:$W$57,$V29:$V$57)),"") -> 39739 | T29: =IF(W29<>"",IF(E29<>"",E29,($I$9-SUM($T$25:T28))*V29*W29/SUMPRODUCT($W29:$W$57,$V29:$V$57)),"") -> 10 | U29: =IF(W29<>"",IF($I$12<>"",IF(G29<>"",G29,($I$9/$I$12-SUM($U$25:U28))*V29*W29/SUMPRODUCT($W29:$W$57,$V29:$V$57)),""),"") -> 7 | V29: 1 | W29: 1
A30: 6 | B30: 45668 | C30: сб | D30: 4692 | E30: 1 | F30: =IF(AND(E30<>"",E30<>0),D30/E30,"") -> 4692 | G30: 1 | H30: =IF(AND(G30<>"",G30<>0),D30/G30,"") -> 4692 | J30: =IF(AND(G30<>"",G30<>0),E30/G30,"") -> 1 | N30: =IF(AND(I30<>"",I30<>0),G30/I30,"") | O30: =D30/P30 -> 0.099679952 | P30: =$I$8*V30*W30/SUMPRODUCT($W$25:$W$57,$V$25:$V$57) -> 47070.649 | Q30: =$I$9*V30*W30/SUMPRODUCT($W$25:$W$57,$V$25:$V$57) -> 12.756273 | R30: =IF($I$12="","",Q30/$I$12) -> 7.9726709 | S30: =IF(W30<>"",IF(D30<>"",D30,($I$8-SUM($S$25:S29))*V30*W30/SUMPRODUCT($W30:$W$57,$V30:$V$57)),"") -> 4692 | T30: =IF(W30<>"",IF(E30<>"",E30,($I$9-SUM($T$25:T29))*V30*W30/SUMPRODUCT($W30:$W$57,$V30:$V$57)),"") -> 1 | U30: =IF(W30<>"",IF($I$12<>"",IF(G30<>"",G30,($I$9/$I$12-SUM($U$25:U29))*V30*W30/SUMPRODUCT($W30:$W$57,$V30:$V$57)),""),"") -> 1 | V30: 1 | W30: 1
A31: 7 | B31: 45670 | C31: пн | D31: 18667 | E31: 4 | F31: =IF(AND(E31<>"",E31<>0),D31/E31,"") -> 4666.75 | G31: 3 | H31: =IF(AND(G31<>"",G31<>0),D31/G31,"") -> 6222.3333 | J31: =IF(AND(G31<>"",G31<>0),E31/G31,"") -> 1.3333333 | N31: =IF(AND(I31<>"",I31<>0),G31/I31,"") | O31: =D31/P31 -> 0.61964702 | P31: =$I$8*V31*W31/SUMPRODUCT($W$25:$W$57,$V$25:$V$57) -> 30125.215 | Q31: =$I$9*V31*W31/SUMPRODUCT($W$25:$W$57,$V$25:$V$57) -> 8.164015 | R31: =IF($I$12="","",Q31/$I$12) -> 5.1025094 | S31: =IF(W31<>"",IF(D31<>"",D31,($I$8-SUM($S$25:S30))*V31*W31/SUMPRODUCT($W31:$W$57,$V31:$V$57)),"") -> 18667 | T31: =IF(W31<>"",IF(E31<>"",E31,($I$9-SUM($T$25:T30))*V31*W31/SUMPRODUCT($W31:$W$57,$V31:$V$57)),"") -> 4 | U31: =IF(W31<>"",IF($I$12<>"",IF(G31<>"",G31,($I$9/$I$12-SUM($U$25:U30))*V31*W31/SUMPRODUCT($W31:$W$57,$V31:$V$57)),""),"") -> 3 | V31: 0.8 | W31: 0.8
A32: 8 | B32: 45671 | C32: вт | D32: 0 | E32: 0 | F32: =IF(AND(E32<>"",E32<>0),D32/E32,"") | G32: 0 | H32: =IF(AND(G32<>"",G32<>0),D32/G32,"") | J32: =IF(AND(G32<>"",G32<>0),E32/G32,"") | N32: =IF(AND(I32<>"",I32<>0),G32/I32,"") | O32: =D32/P32 -> 0 | P32: =$I$8*V32*W32/SUMPRODUCT($W$25:$W$57,$V$25:$V$57) -> 47070.649 | Q32: =$I$9*V32*W32/SUMPRODUCT($W$25:$W$57,$V$25:$V$57) -> 12.756273 | R32: =IF($I$12="","",Q32/$I$12) -> 7.9726709 | S32: =IF(W32<>"",IF(D32<>"",D32,($I$8-SUM($S$25:S31))*V32*W32/SUMPRODUCT($W32:$W$57,$V32:$V$57)),"") -> 0 | T32: =IF(W32<>"",IF(E32<>"",E32,($I$9-SUM($T$25:T31))*V32*W32/SUMPRODUCT($W32:$W$57,$V32:$V$57)),"") -> 0 | U32: =IF(W32<>"",IF($I$12<>"",IF(G32<>"",G32,($I$9/$I$12-SUM($U$25:U31))*V32*W32/SUMPRODUCT($W32:$W$57,$V32:$V$57)),""),"") -> 0 | V32: 1 | W32: 1
A33: 9 | B33: 45672 | C33: ср | D33: =45624-11084 -> 34540 | E33: 7 | F33: =IF(AND(E33<>"",E33<>0),D33/E33,"") -> 4934.2857 | G33: 3 | H33: =IF(AND(G33<>"",G33<>0),D33/G33,"") -> 11513.333 | J33: =IF(AND(G33<>"",G33<>0),E33/G33,"") -> 2.3333333 | N33: =IF(AND(I33<>"",I33<>0),G33/I33,"") | O33: =D33/P33 -> 1.1465478 | P33: =$I$8*V33*W33/SUMPRODUCT($W$25:$W$57,$V$25:$V$57) -> 30125.215 | Q33: =$I$9*V33*W33/SUMPRODUCT($W$25:$W$57,$V$25:$V$57) -> 8.164015 | R33: =IF($I$12="","",Q33/$I$12) -> 5.1025094 | S33: =IF(W33<>"",IF(D33<>"",D33,($I$8-SUM($S$25:S32))*V33*W33/SUMPRODUCT($W33:$W$57,$V33:$V$57)),"") -> 34540 | T33: =IF(W33<>"",IF(E33<>"",E33,($I$9-SUM($T$25:T32))*V33*W33/SUMPRODUCT($W33:$W$57,$V33:$V$57)),"") -> 7 | U33: =IF(W33<>"",IF($I$12<>"",IF(G33<>"",G33,($I$9/$I$12-SUM($U$25:U32))*V33*W33/SUMPRODUCT($W33:$W$57,$V33:$V$57)),""),"") -> 3 | V33: 0.8 | W33: 0.8
A34: 10 | B34: 45673 | C34: чт | D34: 11875 | E34: 3 | F34: =IF(AND(E34<>"",E34<>0),D34/E34,"") -> 3958.3333 | G34: 2 | H34: =IF(AND(G34<>"",G34<>0),D34/G34,"") -> 5937.5 | J34: =IF(AND(G34<>"",G34<>0),E34/G34,"") -> 1.5 | N34: =IF(AND(I34<>"",I34<>0),G34/I34,"") | O34: =D34/P34 -> 0.39418805 | P34: =$I$8*V34*W34/SUMPRODUCT($W$25:$W$57,$V$25:$V$57) -> 30125.215 | Q34: =$I$9*V34*W34/SUMPRODUCT($W$25:$W$57,$V$25:$V$57) -> 8.164015 | R34: =IF($I$12="","",Q34/$I$12) -> 5.1025094 | S34: =IF(W34<>"",IF(D34<>"",D34,($I$8-SUM($S$25:S33))*V34*W34/SUMPRODUCT($W34:$W$57,$V34:$V$57)),"") -> 11875 | T34: =IF(W34<>"",IF(E34<>"",E34,($I$9-SUM($T$25:T33))*V34*W34/SUMPRODUCT($W34:$W$57,$V34:$V$57)),"") -> 3 | U34: =IF(W34<>"",IF($I$12<>"",IF(G34<>"",G34,($I$9/$I$12-SUM($U$25:U33))*V34*W34/SUMPRODUCT($W34:$W$57,$V34:$V$57)),""),"") -> 2 | V34: 0.8 | W34: 0.8
A35: 11 | B35: 45674 | C35: пт | D35: 8383 | E35: 2 | F35: =IF(AND(E35<>"",E35<>0),D35/E35,"") -> 4191.5 | G35: 1 | H35: =IF(AND(G35<>"",G35<>0),D35/G35,"") -> 8383 | J35: =IF(AND(G35<>"",G35<>0),E35/G35,"") -> 2 | N35: =IF(AND(I35<>"",I35<>0),G35/I35,"") | O35: =D35/P35 -> 0.21986913 | P35: =$I$8*V35*W35/SUMPRODUCT($W$25:$W$57,$V$25:$V$57) -> 38127.226 | Q35: =$I$9*V35*W35/SUMPRODUCT($W$25:$W$57,$V$25:$V$57) -> 10.332581 | R35: =IF($I$12="","",Q35/$I$12) -> 6.4578634 | S35: =IF(W35<>"",IF(D35<>"",D35,($I$8-SUM($S$25:S34))*V35*W35/SUMPRODUCT($W35:$W$57,$V35:$V$57)),"") -> 8383 | T35: =IF(W35<>"",IF(E35<>"",E35,($I$9-SUM($T$25:T34))*V35*W35/SUMPRODUCT($W35:$W$57,$V35:$V$57)),"") -> 2 | U35: =IF(W35<>"",IF($I$12<>"",IF(G35<>"",G35,($I$9/$I$12-SUM($U$25:U34))*V35*W35/SUMPRODUCT($W35:$W$57,$V35:$V$57)),""),"") -> 1 | V35: 0.9 | W35: 0.9
A36: 12 | B36: 45675 | C36: сб | D36: 39780 | E36: 12 | F36: =IF(AND(E36<>"",E36<>0),D36/E36,"") -> 3315 | G36: 7 | H36: =IF(AND(G36<>"",G36<>0),D36/G36,"") -> 5682.8571 | J36: =IF(AND(G36<>"",G36<>0),E36/G36,"") -> 1.7142857 | N36: =IF(AND(I36<>"",I36<>0),G36/I36,"") | O36: =D36/P36 -> 1.0433489 | P36: =$I$8*V36*W36/SUMPRODUCT($W$25:$W$57,$V$25:$V$57) -> 38127.226 | Q36: =$I$9*V36*W36/SUMPRODUCT($W$25:$W$57,$V$25:$V$57) -> 10.332581 | R36: =IF($I$12="","",Q36/$I$12) -> 6.4578634 | S36: =IF(W36<>"",IF(D36<>"",D36,($I$8-SUM($S$25:S35))*V36*W36/SUMPRODUCT($W36:$W$57,$V36:$V$57)),"") -> 39780 | T36: =IF(W36<>"",IF(E36<>"",E36,($I$9-SUM($T$25:T35))*V36*W36/SUMPRODUCT($W36:$W$57,$V36:$V$57)),"") -> 12 | U36: =IF(W36<>"",IF($I$12<>"",IF(G36<>"",G36,($I$9/$I$12-SUM($U$25:U35))*V36*W36/SUMPRODUCT($W36:$W$57,$V36:$V$57)),""),"") -> 7 | V36: 0.9 | W36: 0.9
A37: 13 | B37: 45676 | C37: вс | D37: 7293 | E37: 1 | F37: =IF(AND(E37<>"",E37<>0),D37/E37,"") -> 7293 | G37: 2 | H37: =IF(AND(G37<>"",G37<>0),D37/G37,"") -> 3646.5 | J37: =IF(AND(G37<>"",G37<>0),E37/G37,"") -> 0.5 | N37: =IF(AND(I37<>"",I37<>0),G37/I37,"") | O37: =D37/P37 -> 0.24208956 | P37: =$I$8*V37*W37/SUMPRODUCT($W$25:$W$57,$V$25:$V$57) -> 30125.215 | Q37: =$I$9*V37*W37/SUMPRODUCT($W$25:$W$57,$V$25:$V$57) -> 8.164015 | R37: =IF($I$12="","",Q37/$I$12) -> 5.1025094 | S37: =IF(W37<>"",IF(D37<>"",D37,($I$8-SUM($S$25:S36))*V37*W37/SUMPRODUCT($W37:$W$57,$V37:$V$57)),"") -> 7293 | T37: =IF(W37<>"",IF(E37<>"",E37,($I$9-SUM($T$25:T36))*V37*W37/SUMPRODUCT($W37:$W$57,$V37:$V$57)),"") -> 1 | U37: =IF(W37<>"",IF($I$12<>"",IF(G37<>"",G37,($I$9/$I$12-SUM($U$25:U36))*V37*W37/SUMPRODUCT($W37:$W$57,$V37:$V$57)),""),"") -> 2 | V37: 0.8 | W37: 0.8
A38: 14 | B38: 45678 | C38: вт | D38: 0 | E38: 0 | F38: 3692 | G38: 0 | H38: 5538 | J38: 1.5 | O38: 0.23 | P38: 48503 | Q38: 13 | R38: 8 | S38: 11075 | T38: 3 | U38: 2 | V38: 0.8 | W38: 0.8
A39: 15 | B39: 45679 | C39: ср | D39: 27780 | E39: 8 | F39: =IF(AND(E39<>"",E39<>0),D39/E39,"") -> 3472.5 | G39: 4 | H39: =IF(AND(G39<>"",G39<>0),D39/G39,"") -> 6945 | J39: =IF(AND(G39<>"",G39<>0),E39/G39,"") -> 2 | N39: =IF(AND(I39<>"",I39<>0),G39/I39,"") | O39: =D39/P39 -> 0.92215109 | P39: =$I$8*V39*W39/SUMPRODUCT($W$25:$W$57,$V$25:$V$57) -> 30125.215 | Q39: =$I$9*V39*W39/SUMPRODUCT($W$25:$W$57,$V$25:$V$57) -> 8.164015 | R39: =IF($I$12="","",Q39/$I$12) -> 5.1025094 | S39: =IF(W39<>"",IF(D39<>"",D39,($I$8-SUM($S$25:S38))*V39*W39/SUMPRODUCT($W39:$W$57,$V39:$V$57)),"") -> 27780 | T39: =IF(W39<>"",IF(E39<>"",E39,($I$9-SUM($T$25:T38))*V39*W39/SUMPRODUCT($W39:$W$57,$V39:$V$57)),"") -> 8 | U39: =IF(W39<>"",IF($I$12<>"",IF(G39<>"",G39,($I$9/$I$12-SUM($U$25:U38))*V39*W39/SUMPRODUCT($W39:$W$57,$V39:$V$57)),""),"") -> 4 | V39: 0.8 | W39: 0.8
A40: 16 | B40: 45680 | C40: чт | D40: 72178 | E40: 19 | F40: =IF(AND(E40<>"",E40<>0),D40/E40,"") -> 3798.8421 | G40: 8 | H40: =IF(AND(G40<>"",G40<>0),D40/G40,"") -> 9022.25 | J40: =IF(AND(G40<>"",G40<>0),E40/G40,"") -> 2.375 | N40: =IF(AND(I40<>"",I40<>0),G40/I40,"") | O40: =D40/P40 -> 2.3959331 | P40: =$I$8*V40*W40/SUMPRODUCT($W$25:$W$57,$V$25:$V$57) -> 30125.215 | Q40: =$I$9*V40*W40/SUMPRODUCT($W$25:$W$57,$V$25:$V$57) -> 8.164015 | R40: =IF($I$12="","",Q40/$I$12) -> 5.1025094 | S40: =IF(W40<>"",IF(D40<>"",D40,($I$8-SUM($S$25:S39))*V40*W40/SUMPRODUCT($W40:$W$57,$V40:$V$57)),"") -> 72178 | T40: =IF(W40<>"",IF(E40<>"",E40,($I$9-SUM($T$25:T39))*V40*W40/SUMPRODUCT($W40:$W$57,$V40:$V$57)),"") -> 19 | U40: =IF(W40<>"",IF($I$12<>"",IF(G40<>"",G40,($I$9/$I$12-SUM($U$25:U39))*V40*W40/SUMPRODUCT($W40:$W$57,$V40:$V$57)),""),"") -> 8 | V40: 0.8 | W40: 0.8
A41: 17 | B41: 45681 | C41: пт | D41: 48873 | E41: 15 | F41: =IF(AND(E41<>"",E41<>0),D41/E41,"") -> 3258.2 | G41: 7 | H41: =IF(AND(G41<>"",G41<>0),D41/G41,"") -> 6981.8571 | J41: =IF(AND(G41<>"",G41<>0),E41/G41,"") -> 2.1428571 | N41: =IF(AND(I41<>"",I41<>0),G41/I41,"") | O41: =D41/P41 -> 1.6223287 | P41: =$I$8*V41*W41/SUMPRODUCT($W$25:$W$57,$V$25:$V$57) -> 30125.215 | Q41: =$I$9*V41*W41/SUMPRODUCT($W$25:$W$57,$V$25:$V$57) -> 8.164015 | R41: =IF($I$12="","",Q41/$I$12) -> 5.1025094 | S41: =IF(W41<>"",IF(D41<>"",D41,($I$8-SUM($S$25:S40))*V41*W41/SUMPRODUCT($W41:$W$57,$V41:$V$57)),"") -> 48873 | T41: =IF(W41<>"",IF(E41<>"",E41,($I$9-SUM($T$25:T40))*V41*W41/SUMPRODUCT($W41:$W$57,$V41:$V$57)),"") -> 15 | U41: =IF(W41<>"",IF($I$12<>"",IF(G41<>"",G41,($I$9/$I$12-SUM($U$25:U40))*V41*W41/SUMPRODUCT($W41:$W$57,$V41:$V$57)),""),"") -> 7 | V41: 0.8 | W41: 0.8
A42: 18 | B42: 45682 | C42: сб | D42: 21044 | E42: 7 | F42: =IF(AND(E42<>"",E42<>0),D42/E42,"") -> 3006.2857 | G42: 3 | H42: =IF(AND(G42<>"",G42<>0),D42/G42,"") -> 7014.6667 | J42: =IF(AND(G42<>"",G42<>0),E42/G42,"") -> 2.3333333 | N42: =IF(AND(I42<>"",I42<>0),G42/I42,"") | O42: =D42/P42 -> 0.69855102 | P42: =$I$8*V42*W42/SUMPRODUCT($W$25:$W$57,$V$25:$V$57) -> 30125.215 | Q42: =$I$9*V42*W42/SUMPRODUCT($W$25:$W$57,$V$25:$V$57) -> 8.164015 | R42: =IF($I$12="","",Q42/$I$12) -> 5.1025094 | S42: =IF(W42<>"",IF(D42<>"",D42,($I$8-SUM($S$25:S41))*V42*W42/SUMPRODUCT($W42:$W$57,$V42:$V$57)),"") -> 21044 | T42: =IF(W42<>"",IF(E42<>"",E42,($I$9-SUM($T$25:T41))*V42*W42/SUMPRODUCT($W42:$W$57,$V42:$V$57)),"") -> 7 | U42: =IF(W42<>"",IF($I$12<>"",IF(G42<>"",G42,($I$9/$I$12-SUM($U$25:U41))*V42*W42/SUMPRODUCT($W42:$W$57,$V42:$V$57)),""),"") -> 3 | V42: 0.8 | W42: 0.8
A43: 19 | B43: 45683 | C43: вс | D43: 89532 | E43: 23 | F43: =IF(AND(E43<>"",E43<>0),D43/E43,"") -> 3892.6957 | G43: 9 | H43: =IF(AND(G43<>"",G43<>0),D43/G43,"") -> 9948 | J43: =IF(AND(G43<>"",G43<>0),E43/G43,"") -> 2.5555556 | N43: =IF(AND(I43<>"",I43<>0),G43/I43,"") | O43: =D43/P43 -> 2.9719954 | P43: =$I$8*V43*W43/SUMPRODUCT($W$25:$W$57,$V$25:$V$57) -> 30125.215 | Q43: =$I$9*V43*W43/SUMPRODUCT($W$25:$W$57,$V$25:$V$57) -> 8.164015 | R43: =IF($I$12="","",Q43/$I$12) -> 5.1025094 | S43: =IF(W43<>"",IF(D43<>"",D43,($I$8-SUM($S$25:S42))*V43*W43/SUMPRODUCT($W43:$W$57,$V43:$V$57)),"") -> 89532 | T43: =IF(W43<>"",IF(E43<>"",E43,($I$9-SUM($T$25:T42))*V43*W43/SUMPRODUCT($W43:$W$57,$V43:$V$57)),"") -> 23 | U43: =IF(W43<>"",IF($I$12<>"",IF(G43<>"",G43,($I$9/$I$12-SUM($U$25:U42))*V43*W43/SUMPRODUCT($W43:$W$57,$V43:$V$57)),""),"") -> 9 | V43: 0.8 | W43: 0.8
A44: 20 | B44: 45684 | C44: пн | D44: 57952.94 | E44: 14 | F44: =IF(AND(E44<>"",E44<>0),D44/E44,"") -> 4139.4957 | G44: 6 | H44: =IF(AND(G44<>"",G44<>0),D44/G44,"") -> 9658.8233 | J44: =IF(AND(G44<>"",G44<>0),E44/G44,"") -> 2.3333333 | N44: =IF(AND(I44<>"",I44<>0),G44/I44,"") | O44: =D44/P44 -> 1.9237353 | P44: =$I$8*V44*W44/SUMPRODUCT($W$25:$W$57,$V$25:$V$57) -> 30125.215 | Q44: =$I$9*V44*W44/SUMPRODUCT($W$25:$W$57,$V$25:$V$57) -> 8.164015 | R44: =IF($I$12="","",Q44/$I$12) -> 5.1025094 | S44: =IF(W44<>"",IF(D44<>"",D44,($I$8-SUM($S$25:S43))*V44*W44/SUMPRODUCT($W44:$W$57,$V44:$V$57)),"") -> 57952.94 | T44: =IF(W44<>"",IF(E44<>"",E44,($I$9-SUM($T$25:T43))*V44*W44/SUMPRODUCT($W44:$W$57,$V44:$V$57)),"") -> 14 | U44: =IF(W44<>"",IF($I$12<>"",IF(G44<>"",G44,($I$9/$I$12-SUM($U$25:U43))*V44*W44/SUMPRODUCT($W44:$W$57,$V44:$V$57)),""),"") -> 6 | V44: 0.8 | W44: 0.8
A45: 21 | B45: 45685 | C45: вт | D45: 7975 | E45: 3 | F45: =IF(AND(E45<>"",E45<>0),D45/E45,"") -> 2658.3333 | G45: 2 | H45: =IF(AND(G45<>"",G45<>0),D45/G45,"") -> 3987.5 | J45: =IF(AND(G45<>"",G45<>0),E45/G45,"") -> 1.5 | N45: =IF(AND(I45<>"",I45<>0),G45/I45,"") | O45: =D45/P45 -> 0.2647284 | P45: =$I$8*V45*W45/SUMPRODUCT($W$25:$W$55,$V$25:$V$55) -> 30125.215 | Q45: =$I$9*V45*W45/SUMPRODUCT($W$25:$W$55,$V$25:$V$55) -> 8.164015 | R45: =IF($I$12="","",Q45/$I$12) -> 5.1025094 | S45: =IF(W45<>"",IF(D45<>"",D45,($I$8-SUM($S$25:S44))*V45*W45/SUMPRODUCT($W45:$W$55,$V45:$V$55)),"") -> 7975 | T45: =IF(W45<>"",IF(E45<>"",E45,($I$9-SUM($T$25:T44))*V45*W45/SUMPRODUCT($W45:$W$55,$V45:$V$55)),"") -> 3 | U45: =IF(W45<>"",IF($I$12<>"",IF(G45<>"",G45,($I$9/$I$12-SUM($U$25:U44))*V45*W45/SUMPRODUCT($W45:$W$55,$V45:$V$55)),""),"") -> 2 | V45: 0.8 | W45: 0.8
A46: 22 | B46: 45686 | C46: ср | D46: 21244 | E46: 5 | F46: =IF(AND(E46<>"",E46<>0),D46/E46,"") -> 4248.8 | G46: 2 | H46: =IF(AND(G46<>"",G46<>0),D46/G46,"") -> 10622 | J46: =IF(AND(G46<>"",G46<>0),E46/G46,"") -> 2.5 | N46: =IF(AND(I46<>"",I46<>0),G46/I46,"") | O46: =D46/P46 -> 0.70518998 | P46: =$I$8*V46*W46/SUMPRODUCT($W$25:$W$55,$V$25:$V$55) -> 30125.215 | Q46: =$I$9*V46*W46/SUMPRODUCT($W$25:$W$55,$V$25:$V$55) -> 8.164015 | R46: =IF($I$12="","",Q46/$I$12) -> 5.1025094 | S46: =IF(W46<>"",IF(D46<>"",D46,($I$8-SUM($S$25:S45))*V46*W46/SUMPRODUCT($W46:$W$55,$V46:$V$55)),"") -> 21244 | T46: =IF(W46<>"",IF(E46<>"",E46,($I$9-SUM($T$25:T45))*V46*W46/SUMPRODUCT($W46:$W$55,$V46:$V$55)),"") -> 5 | U46: =IF(W46<>"",IF($I$12<>"",IF(G46<>"",G46,($I$9/$I$12-SUM($U$25:U45))*V46*W46/SUMPRODUCT($W46:$W$55,$V46:$V$55)),""),"") -> 2 | V46: 0.8 | W46: 0.8
A47: 23 | B47: 45687 | C47: чт | D47: 31031 | E47: 8 | F47: =IF(AND(E47<>"",E47<>0),D47/E47,"") -> 3878.875 | G47: 3 | H47: =IF(AND(G47<>"",G47<>0),D47/G47,"") -> 10343.667 | J47: =IF(AND(G47<>"",G47<>0),E47/G47,"") -> 2.6666667 | N47: =IF(AND(I47<>"",I47<>0),G47/I47,"") | O47: =D47/P47 -> 1.0300673 | P47: =$I$8*V47*W47/SUMPRODUCT($W$25:$W$55,$V$25:$V$55) -> 30125.215 | Q47: =$I$9*V47*W47/SUMPRODUCT($W$25:$W$55,$V$25:$V$55) -> 8.164015 | R47: =IF($I$12="","",Q47/$I$12) -> 5.1025094 | S47: =IF(W47<>"",IF(D47<>"",D47,($I$8-SUM($S$25:S46))*V47*W47/SUMPRODUCT($W47:$W$55,$V47:$V$55)),"") -> 31031 | T47: =IF(W47<>"",IF(E47<>"",E47,($I$9-SUM($T$25:T46))*V47*W47/SUMPRODUCT($W47:$W$55,$V47:$V$55)),"") -> 8 | U47: =IF(W47<>"",IF($I$12<>"",IF(G47<>"",G47,($I$9/$I$12-SUM($U$25:U46))*V47*W47/SUMPRODUCT($W47:$W$55,$V47:$V$55)),""),"") -> 3 | V47: 0.8 | W47: 0.8
A48: 24 | B48: 45688 | C48: пт | D48: 30873 | E48: 8 | F48: =IF(AND(E48<>"",E48<>0),D48/E48,"") -> 3859.125 | G48: 7 | H48: =IF(AND(G48<>"",G48<>0),D48/G48,"") -> 4410.4286 | J48: =IF(AND(G48<>"",G48<>0),E48/G48,"") -> 1.1428571 | N48: =IF(AND(I48<>"",I48<>0),G48/I48,"") | O48: =D48/P48 -> 1.0248226 | P48: =$I$8*V48*W48/SUMPRODUCT($W$25:$W$55,$V$25:$V$55) -> 30125.215 | Q48: =$I$9*V48*W48/SUMPRODUCT($W$25:$W$55,$V$25:$V$55) -> 8.164015 | R48: =IF($I$12="","",Q48/$I$12) -> 5.1025094 | S48: =IF(W48<>"",IF(D48<>"",D48,($I$8-SUM($S$25:S47))*V48*W48/SUMPRODUCT($W48:$W$55,$V48:$V$55)),"") -> 30873 | T48: =IF(W48<>"",IF(E48<>"",E48,($I$9-SUM($T$25:T47))*V48*W48/SUMPRODUCT($W48:$W$55,$V48:$V$55)),0) -> 8 | U48: =IF(W48<>"",IF($I$12<>"",IF(G48<>"",G48,($I$9/$I$12-SUM($U$25:U47))*V48*W48/SUMPRODUCT($W48:$W$55,$V48:$V$55)),""),"") -> 7 | V48: 0.8 | W48: 0.8
A49: 25 | F49: =IF(AND(E49<>"",E49<>0),D49/E49,"") | H49: =IF(AND(G49<>"",G49<>0),D49/G49,"") | J49: =IF(AND(G49<>"",G49<>0),E49/G49,"") | N49: =IF(AND(I49<>"",I49<>0),G49/I49,"") | O49: =D49/P49 -> #DIV/0! | P49: =$I$8*V49*W49/SUMPRODUCT($W$25:$W$48,$V$25:$V$48) -> 0 | Q49: =$I$9*V49*W49/SUMPRODUCT($W$25:$W$48,$V$25:$V$48) -> 0 | R49: =IF($I$12="","",Q49/$I$12) -> 0 | S49: =IF(W49<>"",IF(D49<>"",D49,($I$8-SUM($S$25:S48))*V49*W49/SUMPRODUCT($W$48:$W49,$V$48:$V49)),"") | T49: =IF(W49<>"",IF(E49<>"",E49,($I$9-SUM($T$25:T48))*V49*W49/SUMPRODUCT($W$48:$W49,$V$48:$V49)),"") | U49: =IF(W49<>"",IF($I$12<>"",IF(G49<>"",G49,($I$9/$I$12-SUM($U$25:U48))*V49*W49/SUMPRODUCT($W$48:$W49,$V$48:$V49)),""),"")
B50: итого | D50: =SUM(D25:D48) -> 833967.94 | E50: =SUM(E25:E48) -> 205 | F50: =IF(AND(E50<>"",E50<>0),D50/E50,"") -> 4068.1363 | G50: =SUM(G25:G48) -> 101 | H50: =IF(AND(G50<>"",G50<>0),D50/G50,"") -> 8257.1083 | I50: =SUM(I25:I48) -> 0 | J50: =IF(AND(G50<>"",G50<>0),E50/G50,"") -> 2.029703 | K50: =SUM(K25:K48) -> 0 | L50: =SUM(L25:L48) -> 0 | M50: =SUM(M25:M48) -> 0 | N50: =IF(AND(I50<>"",I50<>0),G50/I50,"") | O50: =D50/P50 -> 0.88896059 | P50: =SUM(P25:P49) -> 938138.26 | Q50: =SUM(Q25:Q49) -> 254.09357 | R50: =SUM(R25:R49) -> 158.68348 | S50: =SUM(S25:S49) -> 845042.94 | T50: =SUM(T25:T49) -> 227.1243 | U50: =SUM(U25:U49) -> 114.82304
D51: =SUMIF(D25:D48,"",P25:P48)+D50 -> 833967.94

Sheet ПК 2
B1: =TODAY()-1 -> 45696
B2: (отчетная дата) | J2: ЕЖЕДНЕВНЫЙ ОТЧЕТ О ПРОДАЖАХ
B3: Осталось до выполнения плана!!! | J3: =График!B29 -> Рогалевич Ирина
C4: =I8-D48 -> 919760.48 | E4: =IF(I8<>0,C4/I8,0) -> 1
F6: Целевые показатели
F7: Показатель | I7: План | J7: Факт | K7: % выполнения | L7: Прогноз выполнения | M7: % выполнения по прогнозу | N7: Отклонение | O7: Факт аналогичного месяца прошлого года | P7: Отклонение LFL
F8: Выручка | I8: ='Ялта, Ленина, 18'!I8/График!AJ31*График!AJ29 -> 919760.48 | J8: =D48 -> 0 | K8: =IF(AND(I8<>"",I8<>0,J8<>""),J8/I8,"") -> 0 | L8: =IF(SUMIF($D$25:$D$47,">=0",$P$25:$P$47)<>0,I8*D48/SUMIF($D$25:$D$47,">=0",$P$25:$P$47),0) -> 0 | M8: =IF(AND(I8<>"",I8<>0,L8<>"",L8<>0),L8/I8,"") | N8: =IF(AND(J8<>0,J8<>"",I8<>0,I8<>""),L8-I8,"") | P8: =IF(AND(O8<>"",O8<>0,L8<>"",L8<>0),-O8+L8,"") | Q8: =IF(AND(P8<>"",P8<>0,O8<>0,O8<>""),P8/O8,"")
F9: Кол-во изделий | I9: =I8/I11 -> 249.25758 | J9: =E48 -> 0 | K9: =IF(AND(I9<>"",I9<>0,J9<>""),J9/I9,"") -> 0 | L9: =IF(SUMIF($E$25:$E$47,">=0",$Q$25:$Q$47)<>0,I9*E48/SUMIF($E$25:$E$47,">=0",$Q$25:$Q$47),0) -> 0 | M9: =IF(AND(I9<>"",I9<>0,L9<>"",L9<>0),L9/I9,"") | N9: =IF(AND(J9<>0,J9<>"",I9<>0,I9<>""),L9-I9,"") | O9: =O8/O11 -> #DIV/0! | P9: =IF(AND(O9<>"",O9<>0,L9<>"",L9<>0),-O9+L9,"") -> #DIV/0! | Q9: =IF(AND(P9<>"",P9<>0,O9<>0,O9<>""),P9/O9,"") -> #DIV/0!
F10: Средний чек | I10: =I11*I12 -> 5904 | J10: =H48 | K10: =IF(AND(I10<>"",I10<>0,J10<>""),J10/I10,"") | L10: =J10 | M10: =IF(AND(I10<>"",I10<>0,L10<>"",L10<>0),L10/I10,"") | N10: =IF(AND(J10<>0,J10<>"",I10<>0,I10<>""),L10-I10,"") | O10: =O11*O12 -> 0 | P10: =IF(AND(O10<>"",O10<>0,L10<>"",L10<>0),-O10+L10,"") | Q10: =IF(AND(P10<>"",P10<>0,O10<>0,O10<>""),P10/O10,"")
F11: Средняя стоимость изделия | I11: ='Ялта, Ленина, 18'!I11 -> 3690 | J11: =F48 | K11: =IF(AND(I11<>"",I11<>0,J11<>""),J11/I11,"") | L11: =IF(L9>0,L8/L9,"") | M11: =IF(AND(I11<>"",I11<>0,L11<>"",L11<>0),L11/I11,"") | N11: =IF(AND(J11<>0,J11<>"",I11<>0,I11<>""),L11-I11,"") | P11: =IF(AND(O11<>"",O11<>0,L11<>"",L11<>0),-O11+L11,"") | Q11: =IF(AND(P11<>"",P11<>0,O11<>0,O11<>""),P11/O11,"")
F12: Длина чека | I12: ='Ялта, Ленина, 18'!I12 -> 1.6 | J12: =J48 | K12: =IF(AND(I12<>"",I12<>0,J12<>""),J12/I12,"") | L12: =J12 | M12: =IF(AND(I12<>"",I12<>0,L12<>"",L12<>0),L12/I12,"") | N12: =IF(AND(J12<>0,J12<>"",I12<>0,I12<>""),L12-I12,"") | P12: =IF(AND(O12<>"",O12<>0,L12<>"",L12<>0),-O12+L12,"") | Q12: =IF(AND(P12<>"",P12<>0,O12<>0,O12<>""),P12/O12,"")
F13: Кол-во чеков | I13: =IF(I12<>0,I9/I12,"") -> 155.78599 | J13: =G48 -> 0 | K13: =IF(AND(I13<>"",I13<>0,J13<>""),J13/I13,"") -> 0 | L13: =IF(SUMIF($G$25:$G$47,">=0",$R$25:$R$47)<>0,I13*G48/SUMIF($G$25:$G$47,">=0",$R$25:$R$47),"") -> 0 | M13: =IF(AND(I13<>"",I13<>0,L13<>"",L13<>0),L13/I13,"") | N13: =IF(AND(J13<>0,J13<>"",I13<>0,I13<>""),L13-I13,"") | P13: =IF(AND(O13<>"",O13<>0,L13<>"",L13<>0),-O13+L13,"") | Q13: =IF(AND(P13<>"",P13<>0,O13<>0,O13<>""),P13/O13,"")
F14: Кол-во смен план/отработано | I14: =График!AI29 -> 24 | K14: =IF(AND(I14<>"",I14<>0,J14<>""),J14/I14,"") | L14: =IF(SUMIF($D$25:$D$47,">=0",$P$25:$P$47),I48*I8/SUMIF($D$25:$D$47,">=0",$P$25:$P$47),"") | M14: =IF(AND(I14<>"",I14<>0,L14<>"",L14<>0),L14/I14,"") | N14: =IF(AND(J14<>0,J14<>"",I14<>0,I14<>""),L14-I14,"") | P14: =IF(AND(O14<>"",O14<>0,L14<>"",L14<>0),-O14+L14,"") | Q14: =IF(AND(P14<>"",P14<>0,O14<>0,O14<>""),P14/O14,"")
F15: Средние продажи в смену | I15: ='Ялта, Ленина, 18'!I15 -> 60000 | J15: =J8/J14 -> #DIV/0! | K15: =IF(AND(I15<>"",I15<>0,J15<>""),J15/I15,"") -> #DIV/0! | L15: =J15 -> #DIV/0! | M15: =IF(AND(I15<>"",I15<>0,L15<>"",L15<>0),L15/I15,"") -> #DIV/0! | N15: =IF(AND(J15<>0,J15<>"",I15<>0,I15<>""),L15-I15,"") -> #DIV/0! | P15: =IF(AND(O15<>"",O15<>0,L15<>"",L15<>0),-O15+L15,"") -> #DIV/0! | Q15: =IF(AND(P15<>"",P15<>0,O15<>0,O15<>""),P15/O15,"") -> #DIV/0!
F16: Отставание/Перевыполнение | J16: =J8-I15*J14 -> 0 | K16: =IF(AND(I16<>"",I16<>0,J16<>""),J16/I16,"") | L16: =J16 -> 0 | M16: =IF(AND(I16<>"",I16<>0,L16<>"",L16<>0),L16/I16,"") | N16: =IF(AND(J16<>0,J16<>"",I16<>0,I16<>""),L16-I16,"") | P16: =IF(AND(O16<>"",O16<>0,L16<>"",L16<>0),-O16+L16,"") | Q16: =IF(AND(P16<>"",P16<>0,O16<>0,O16<>""),P16/O16,"") | S16: Подарочные сертификаты
F17: Трафик | I17: ='Ялта, Ленина, 18'!I17/График!AJ31*График!AJ29 -> 0 | J17: =I48 -> 0 | K17: =IF(AND(I17<>"",I17<>0,J17<>""),J17/I17,"") | L17: =J17 -> 0 | M17: =IF(AND(I17<>"",I17<>0,L17<>"",L17<>0),L17/I17,"") | N17: =IF(AND(J17<>0,J17<>"",I17<>0,I17<>""),L17-I17,"") | P17: =IF(AND(O17<>"",O17<>0,L17<>"",L17<>0),-O17+L17,"") | Q17: =IF(AND(P17<>"",P17<>0,O17<>0,O17<>""),P17/O17,"")
K18: =IF(AND(I18<>"",I18<>0,J18<>""),J18/I18,"") | L18: =J18 -> 0 | M18: =IF(AND(I18<>"",I18<>0,L18<>"",L18<>0),L18/I18,"") | N18: =IF(AND(J18<>0,J18<>"",I18<>0,I18<>""),L18-I18,"") | O18: 0 | P18: =IF(AND(O18<>"",O18<>0,L18<>"",L18<>0),-O18+L18,"") | Q18: =IF(AND(P18<>"",P18<>0,O18<>0,O18<>""),P18/O18,"")
J19: =M48 -> 0 | K19: =IF(AND(I19<>"",I19<>0,J19<>""),J19/I19,"") | L19: =J19 -> 0 | M19: =IF(AND(I19<>"",I19<>0,L19<>"",L19<>0),L19/I19,"") | N19: =IF(AND(J19<>0,J19<>"",I19<>0,I19<>""),L19-I19,"") | O19: 0 | P19: =IF(AND(O19<>"",O19<>0,L19<>"",L19<>0),-O19+L19,"") | Q19: =IF(AND(P19<>"",P19<>0,O19<>0,O19<>""),P19/O19,"") | S19: =S18/I16 -> #DIV/0!
F20: Конверсия план/факт | I20: ='Ялта, Ленина, 18'!I20 -> 0.257 | J20: =N48 | K20: =J20/I20 -> #VALUE! | L20: =IF(AND(K8<>0,I14<>0,I48<>0),(I48*N48+(I48/K8-I48)*I20)/(I48/K8),0) -> 0 | M20: =IF(AND(I20<>"",I20<>0,L20<>"",L20<>0),L20/I20,"") | N20: =IF(AND(J20<>0,J20<>"",I20<>0,I20<>""),L20-I20,"") | P20: =IF(AND(O20<>"",O20<>0,L20<>"",L20<>0),-O20+L20,"") | Q20: =IF(AND(P20<>"",P20<>0,O20<>0,O20<>""),P20/O20,"")
B22: Факт продаж за месяц | O22: % выполнения дневного плана | P22: Раcпределение плана по дням
B23: Дата | C23: День недели | D23: Выручка (руб) | E23: Кол-во единиц (шт.) | F23: Средняя стоимость изделия (руб.) | G23: Количество чеков (шт.) | H23: Средняя сумма чека (руб.) | I23: Трафик | J23: Длина чека (шт.) | K23: Запасной | L23: Запасной | M23: Запасной | N23: Конверсия (%) | P23: выручка, план | Q23: кол-во ед, план | R23: Кол-во чеков, план | S23: выручка, скорректир.план | T23: кол-во ед, скорр. план | U23: кол-во чеков, скорр. план | V23: Коэфф. Дня Недели | W23: Специфика месяца
B24: 1 | C24: 2 | D24: 3 | E24: 4 | F24: 5 | G24: 6 | H24: 7 | I24: 8 | J24: 9 | K24: 10 | L24: 11 | M24: 12 | N24: 13 | P24: 1 | Q24: 2 | R24: 3 | S24: 4 | T24: 5 | U24: 6 | V24: 10 | W24: 11
A25: 1 | F25: =IF(AND(E25<>"",E25<>0),D25/E25,"") | H25: =IF(AND(G25<>"",G25<>0),D25/G25,"") | J25: =IF(AND(G25<>"",G25<>0),E25/G25,"") | N25: =IF(AND(I25<>"",I25<>0),G25/I25,"") | O25: =D25/P25 -> 0 | P25: =$I$8*V25*W25/SUMPRODUCT($W$25:$W$55,$V$25:$V$55) -> 181055.21 | Q25: =$I$9*V25*W25/SUMPRODUCT($W$25:$W$55,$V$25:$V$55) -> 49.066453 | R25: =IF($I$12="","",Q25/$I$12) -> 30.666533 | S25: =IF(D25<>"",D25,P25) -> 181055.21 | T25: =IF(E25<>"",E25,Q25) -> 49.066453 | U25: =IF(G25<>"",G25,R25) -> 30.666533 | V25: 1 | W25: 1
A26: 2 | F26: =IF(AND(E26<>"",E26<>0),D26/E26,"") | G26: 0 | H26: =IF(AND(G26<>"",G26<>0),D26/G26,"") | J26: =IF(AND(G26<>"",G26<>0),E26/G26,"") | N26: =IF(AND(I26<>"",I26<>0),G26/I26,"") | O26: =D26/P26 -> 0 | P26: =$I$8*V26*W26/SUMPRODUCT($W$25:$W$55,$V$25:$V$55) -> 115875.34 | Q26: =$I$9*V26*W26/SUMPRODUCT($W$25:$W$55,$V$25:$V$55) -> 31.40253 | R26: =IF($I$12="","",Q26/$I$12) -> 19.626581 | S26: =IF(W26<>"",IF(D26<>"",D26,($I$8-SUM($S$25:S25))*V26*W26/SUMPRODUCT($W26:$W$55,$V26:$V$55)),"") -> 115875.34 | T26: =IF(W26<>"",IF(E26<>"",E26,($I$9-SUM($T$25:T25))*V26*W26/SUMPRODUCT($W26:$W$55,$V26:$V$55)),"") -> 31.40253 | U26: =IF(W26<>"",IF($I$12<>"",IF(G26<>"",G26,($I$9/$I$12-SUM($U$25:U25))*V26*W26/SUMPRODUCT($W26:$W$55,$V26:$V$55)),""),"") -> 0 | V26: 0.8 | W26: 0.8
A27: 3 | F27: =IF(AND(E27<>"",E27<>0),D27/E27,"") | H27: =IF(AND(G27<>"",G27<>0),D27/G27,"") | J27: =IF(AND(G27<>"",G27<>0),E27/G27,"") | N27: =IF(AND(I27<>"",I27<>0),G27/I27,"") | O27: =D27/P27 -> 0 | P27: =$I$8*V27*W27/SUMPRODUCT($W$25:$W$55,$V$25:$V$55) -> 260719.51 | Q27: =$I$9*V27*W27/SUMPRODUCT($W$25:$W$55,$V$25:$V$55) -> 70.655693 | R27: =IF($I$12="","",Q27/$I$12) -> 44.159808 | S27: =IF(W27<>"",IF(D27<>"",D27,($I$8-SUM($S$25:S26))*V27*W27/SUMPRODUCT($W27:$W$55,$V27:$V$55)),"") -> 260719.51 | T27: =IF(W27<>"",IF(E27<>"",E27,($I$9-SUM($T$25:T26))*V27*W27/SUMPRODUCT($W27:$W$55,$V27:$V$55)),"") -> 70.655693 | U27: =IF(W27<>"",IF($I$12<>"",IF(G27<>"",G27,($I$9/$I$12-SUM($U$25:U26))*V27*W27/SUMPRODUCT($W27:$W$55,$V27:$V$55)),""),"") -> 52.375586 | V27: 1.2 | W27: 1.2
A28: 4 | F28: =IF(AND(E28<>"",E28<>0),D28/E28,"") | H28: =IF(AND(G28<>"",G28<>0),D28/G28,"") | J28: =IF(AND(G28<>"",G28<>0),E28/G28,"") | N28: =IF(AND(I28<>"",I28<>0),G28/I28,"") | O28: =D28/P28 -> 0 | P28: =$I$8*V28*W28/SUMPRODUCT($W$25:$W$55,$V$25:$V$55) -> 181055.21 | Q28: =$I$9*V28*W28/SUMPRODUCT($W$25:$W$55,$V$25:$V$55) -> 49.066453 | R28: =IF($I$12="","",Q28/$I$12) -> 30.666533 | S28: =IF(W28<>"",IF(D28<>"",D28,($I$8-SUM($S$25:S27))*V28*W28/SUMPRODUCT($W28:$W$55,$V28:$V$55)),"") -> 181055.21 | T28: =IF(W28<>"",IF(E28<>"",E28,($I$9-SUM($T$25:T27))*V28*W28/SUMPRODUCT($W28:$W$55,$V28:$V$55)),"") -> 49.066453 | U28: =IF(W28<>"",IF($I$12<>"",IF(G28<>"",G28,($I$9/$I$12-SUM($U$25:U27))*V28*W28/SUMPRODUCT($W28:$W$55,$V28:$V$55)),""),"") -> 36.371935 | V28: 1 | W28: 1
A29: 5 | F29: =IF(AND(E29<>"",E29<>0),D29/E29,"") | H29: =IF(AND(G29<>"",G29<>0),D29/G29,"") | J29: =IF(AND(G29<>"",G29<>0),E29/G29,"") | N29: =IF(AND(I29<>"",I29<>0),G29/I29,"") | O29: =D29/P29 -> 0 | P29: =$I$8*V29*W29/SUMPRODUCT($W$25:$W$55,$V$25:$V$55) -> 181055.21 | Q29: =$I$9*V29*W29/SUMPRODUCT($W$25:$W$55,$V$25:$V$55) -> 49.066453 | R29: =IF($I$12="","",Q29/$I$12) -> 30.666533 | S29: =IF(W29<>"",IF(D29<>"",D29,($I$8-SUM($S$25:S28))*V29*W29/SUMPRODUCT($W29:$W$55,$V29:$V$55)),"") -> 181055.21 | T29: =IF(W29<>"",IF(E29<>"",E29,($I$9-SUM($T$25:T28))*V29*W29/SUMPRODUCT($W29:$W$55,$V29:$V$55)),"") -> 49.066453 | U29: =IF(W29<>"",IF($I$12<>"",IF(G29<>"",G29,($I$9/$I$12-SUM($U$25:U28))*V29*W29/SUMPRODUCT($W29:$W$55,$V29:$V$55)),""),"") -> 36.371935 | V29: 1 | W29: 1
A30: 6 | F30: =IF(AND(E30<>"",E30<>0),D30/E30,"") | H30: =IF(AND(G30<>"",G30<>0),D30/G30,"") | J30: =IF(AND(G30<>"",G30<>0),E30/G30,"") | N30: =IF(AND(I30<>"",I30<>0),G30/I30,"") | O30: =D30/P30 -> #DIV/0! | P30: =$I$8*V30*W30/SUMPRODUCT($W$25:$W$55,$V$25:$V$55) -> 0 | Q30: =$I$9*V30*W30/SUMPRODUCT($W$25:$W$55,$V$25:$V$55) -> 0 | R30: =IF($I$12="","",Q30/$I$12) -> 0 | S30: =IF(W30<>"",IF(D30<>"",D30,($I$8-SUM($S$25:S29))*V30*W30/SUMPRODUCT($W30:$W$55,$V30:$V$55)),"") | T30: =IF(W30<>"",IF(E29<>"",E29,($I$9-SUM($T$25:T29))*V30*W30/SUMPRODUCT($W30:$W$55,$V30:$V$55)),"") | U30: =IF(W30<>"",IF($I$12<>"",IF(G30<>"",G30,($I$9/$I$12-SUM($U$25:U29))*V30*W30/SUMPRODUCT($W30:$W$55,$V30:$V$55)),""),"")
A31: 7 | F31: =IF(AND(E31<>"",E31<>0),D31/E31,"") | H31: =IF(AND(G31<>"",G31<>0),D31/G31,"") | J31: =IF(AND(G31<>"",G31<>0),E31/G31,"") | N31: =IF(AND(I31<>"",I31<>0),G31/I31,"") | O31: =D31/P31 -> #DIV/0! | P31: =$I$8*V31*W31/SUMPRODUCT($W$25:$W$55,$V$25:$V$55) -> 0 | Q31: =$I$9*V31*W31/SUMPRODUCT($W$25:$W$55,$V$25:$V$55) -> 0 | R31: =IF($I$12="","",Q31/$I$12) -> 0 | S31: =IF(W31<>"",IF(D31<>"",D31,($I$8-SUM($S$25:S30))*V31*W31/SUMPRODUCT($W31:$W$55,$V31:$V$55)),"") | T31: =IF(W31<>"",IF(E31<>"",E31,($I$9-SUM($T$25:T30))*V31*W31/SUMPRODUCT($W31:$W$55,$V31:$V$55)),"") | U31: =IF(W31<>"",IF($I$12<>"",IF(G31<>"",G31,($I$9/$I$12-SUM($U$25:U30))*V31*W31/SUMPRODUCT($W31:$W$55,$V31:$V$55)),""),"")
A32: 8 | F32: =IF(AND(E32<>"",E32<>0),D32/E32,"") | H32: =IF(AND(G32<>"",G32<>0),D32/G32,"") | J32: =IF(AND(G32<>"",G32<>0),E32/G32,"") | N32: =IF(AND(I32<>"",I32<>0),G32/I32,"") | O32: =D32/P32 -> #DIV/0! | P32: =$I$8*V32*W32/SUMPRODUCT($W$25:$W$55,$V$25:$V$55) -> 0 | Q32: =$I$9*V32*W32/SUMPRODUCT($W$25:$W$55,$V$25:$V$55) -> 0 | R32: =IF($I$12="","",Q32/$I$12) -> 0 | S32: =IF(W32<>"",IF(D32<>"",D32,($I$8-SUM($S$25:S31))*V32*W32/SUMPRODUCT($W32:$W$55,$V32:$V$55)),"") | T32: =IF(W32<>"",IF(E32<>"",E32,($I$9-SUM($T$25:T31))*V32*W32/SUMPRODUCT($W32:$W$55,$V32:$V$55)),"") | U32: =IF(W32<>"",IF($I$12<>"",IF(G32<>"",G32,($I$9/$I$12-SUM($U$25:U31))*V32*W32/SUMPRODUCT($W32:$W$55,$V32:$V$55)),""),"")
A33: 9 | F33: =IF(AND(E33<>"",E33<>0),D33/E33,"") | H33: =IF(AND(G33<>"",G33<>0),D33/G33,"") | J33: =IF(AND(G33<>"",G33<>0),E33/G33,"") | N33: =IF(AND(I33<>"",I33<>0),G33/I33,"") | O33: =D33/P33 -> #DIV/0! | P33: =$I$8*V33*W33/SUMPRODUCT($W$25:$W$55,$V$25:$V$55) -> 0 | Q33: =$I$9*V33*W33/SUMPRODUCT($W$25:$W$55,$V$25:$V$55) -> 0 | R33: =IF($I$12="","",Q33/$I$12) -> 0 | S33: =IF(W33<>"",IF(D33<>"",D33,($I$8-SUM($S$25:S32))*V33*W33/SUMPRODUCT($W33:$W$55,$V33:$V$55)),"") | T33: =IF(W33<>"",IF(E33<>"",E33,($I$9-SUM($T$25:T32))*V33*W33/SUMPRODUCT($W33:$W$55,$V33:$V$55)),"") | U33: =IF(W33<>"",IF($I$12<>"",IF(G33<>"",G33,($I$9/$I$12-SUM($U$25:U32))*V33*W33/SUMPRODUCT($W33:$W$55,$V33:$V$55)),""),"")
A34: 10 | F34: =IF(AND(E34<>"",E34<>0),D34/E34,"") | H34: =IF(AND(G34<>"",G34<>0),D34/G34,"") | J34: =IF(AND(G34<>"",G34<>0),E34/G34,"") | N34: =IF(AND(I34<>"",I34<>0),G34/I34,"") | O34: =D34/P34 -> #DIV/0! | P34: =$I$8*V34*W34/SUMPRODUCT($W$25:$W$55,$V$25:$V$55) -> 0 | Q34: =$I$9*V34*W34/SUMPRODUCT($W$25:$W$55,$V$25:$V$55) -> 0 | R34: =IF($I$12="","",Q34/$I$12) -> 0 | S34: =IF(W34<>"",IF(D34<>"",D34,($I$8-SUM($S$25:S33))*V34*W34/SUMPRODUCT($W34:$W$55,$V34:$V$55)),"") | T34: =IF(W34<>"",IF(E34<>"",E34,($I$9-SUM($T$25:T33))*V34*W34/SUMPRODUCT($W34:$W$55,$V34:$V$55)),"") | U34: =IF(W34<>"",IF($I$12<>"",IF(G34<>"",G34,($I$9/$I$12-SUM($U$25:U33))*V34*W34/SUMPRODUCT($W34:$W$55,$V34:$V$55)),""),"")
A35: 11 | F35: =IF(AND(E35<>"",E35<>0),D35/E35,"") | H35: =IF(AND(G35<>"",G35<>0),D35/G35,"") | J35: =IF(AND(G35<>"",G35<>0),E35/G35,"") | N35: =IF(AND(I35<>"",I35<>0),G35/I35,"") | O35: =D35/P35 -> #DIV/0! | P35: =$I$8*V35*W35/SUMPRODUCT($W$25:$W$55,$V$25:$V$55) -> 0 | Q35: =$I$9*V35*W35/SUMPRODUCT($W$25:$W$55,$V$25:$V$55) -> 0 | R35: =IF($I$12="","",Q35/$I$12) -> 0 | S35: =IF(W35<>"",IF(D35<>"",D35,($I$8-SUM($S$25:S34))*V35*W35/SUMPRODUCT($W35:$W$55,$V35:$V$55)),"") | T35: =IF(W35<>"",IF(E35<>"",E35,($I$9-SUM($T$25:T34))*V35*W35/SUMPRODUCT($W35:$W$55,$V35:$V$55)),"") | U35: =IF(W35<>"",IF($I$12<>"",IF(G35<>"",G35,($I$9/$I$12-SUM($U$25:U34))*V35*W35/SUMPRODUCT($W35:$W$55,$V35:$V$55)),""),"")
A36: 12 | F36: =IF(AND(E36<>"",E36<>0),D36/E36,"") | H36: =IF(AND(G36<>"",G36<>0),D36/G36,"") | J36: =IF(AND(G36<>"",G36<>0),E36/G36,"") | N36: =IF(AND(I36<>"",I36<>0),G36/I36,"") | O36: =D36/P36 -> #DIV/0! | P36: =$I$8*V36*W36/SUMPRODUCT($W$25:$W$55,$V$25:$V$55) -> 0 | Q36: =$I$9*V36*W36/SUMPRODUCT($W$25:$W$55,$V$25:$V$55) -> 0 | R36: =IF($I$12="","",Q36/$I$12) -> 0 | S36: =IF(W36<>"",IF(D36<>"",D36,($I$8-SUM($S$25:S35))*V36*W36/SUMPRODUCT($W36:$W$55,$V36:$V$55)),"") | T36: =IF(W36<>"",IF(E36<>"",E36,($I$9-SUM($T$25:T35))*V36*W36/SUMPRODUCT($W36:$W$55,$V36:$V$55)),"") | U36: =IF(W36<>"",IF($I$12<>"",IF(G36<>"",G36,($I$9/$I$12-SUM($U$25:U35))*V36*W36/SUMPRODUCT($W36:$W$55,$V36:$V$55)),""),"")
A37: 13 | F37: =IF(AND(E37<>"",E37<>0),D37/E37,"") | H37: =IF(AND(G37<>"",G37<>0),D37/G37,"") | J37: =IF(AND(G37<>"",G37<>0),E37/G37,"") | N37: =IF(AND(I37<>"",I37<>0),G37/I37,"") | O37: =D37/P37 -> #DIV/0! | P37: =$I$8*V37*W37/SUMPRODUCT($W$25:$W$55,$V$25:$V$55) -> 0 | Q37: =$I$9*V37*W37/SUMPRODUCT($W$25:$W$55,$V$25:$V$55) -> 0 | R37: =IF($I$12="","",Q37/$I$12) -> 0 | S37: =IF(W37<>"",IF(D37<>"",D37,($I$8-SUM($S$25:S36))*V37*W37/SUMPRODUCT($W37:$W$55,$V37:$V$55)),"") | T37: =IF(W37<>"",IF(E37<>"",E37,($I$9-SUM($T$25:T36))*V37*W37/SUMPRODUCT($W37:$W$55,$V37:$V$55)),"") | U37: =IF(W37<>"",IF($I$12<>"",IF(G37<>"",G37,($I$9/$I$12-SUM($U$25:U36))*V37*W37/SUMPRODUCT($W37:$W$55,$V37:$V$55)),""),"")
A38: 14 | F38: =IF(AND(E38<>"",E38<>0),D38/E38,"") | H38: =IF(AND(G38<>"",G38<>0),D38/G38,"") | J38: =IF(AND(G38<>"",G38<>0),E38/G38,"") | N38: =IF(AND(I38<>"",I38<>0),G38/I38,"") | O38: =D38/P38 -> #DIV/0! | P38: =$I$8*V38*W38/SUMPRODUCT($W$25:$W$55,$V$25:$V$55) -> 0 | Q38: =$I$9*V38*W38/SUMPRODUCT($W$25:$W$55,$V$25:$V$55) -> 0 | R38: =IF($I$12="","",Q38/$I$12) -> 0 | S38: =IF(W38<>"",IF(D38<>"",D38,($I$8-SUM($S$25:S37))*V38*W38/SUMPRODUCT($W38:$W$55,$V38:$V$55)),"") | T38: =IF(W38<>"",IF(E38<>"",E38,($I$9-SUM($T$25:T37))*V38*W38/SUMPRODUCT($W38:$W$55,$V38:$V$55)),"") | U38: =IF(W38<>"",IF($I$12<>"",IF(G38<>"",G38,($I$9/$I$12-SUM($U$25:U37))*V38*W38/SUMPRODUCT($W38:$W$55,$V38:$V$55)),""),"")
A39: 15 | F39: =IF(AND(E39<>"",E39<>0),D39/E39,"") | H39: =IF(AND(G39<>"",G39<>0),D39/G39,"") | J39: =IF(AND(G39<>"",G39<>0),E39/G39,"") | N39: =IF(AND(I39<>"",I39<>0),G39/I39,"") | O39: =D39/P39 -> #DIV/0! | P39: =$I$8*V39*W39/SUMPRODUCT($W$25:$W$55,$V$25:$V$55) -> 0 | Q39: =$I$9*V39*W39/SUMPRODUCT($W$25:$W$55,$V$25:$V$55) -> 0 | R39: =IF($I$12="","",Q39/$I$12) -> 0 | S39: =IF(W39<>"",IF(D39<>"",D39,($I$8-SUM($S$25:S38))*V39*W39/SUMPRODUCT($W39:$W$55,$V39:$V$55)),"") | T39: =IF(W39<>"",IF(E39<>"",E39,($I$9-SUM($T$25:T38))*V39*W39/SUMPRODUCT($W39:$W$55,$V39:$V$55)),"") | U39: =IF(W39<>"",IF($I$12<>"",IF(G39<>"",G39,($I$9/$I$12-SUM($U$25:U38))*V39*W39/SUMPRODUCT($W39:$W$55,$V39:$V$55)),""),"")
A40: 16 | F40: =IF(AND(E40<>"",E40<>0),D40/E40,"") | H40: =IF(AND(G40<>"",G40<>0),D40/G40,"") | J40: =IF(AND(G40<>"",G40<>0),E40/G40,"") | N40: =IF(AND(I40<>"",I40<>0),G40/I40,"") | O40: =D40/P40 -> #DIV/0! | P40: =$I$8*V40*W40/SUMPRODUCT($W$25:$W$55,$V$25:$V$55) -> 0 | Q40: =$I$9*V40*W40/SUMPRODUCT($W$25:$W$55,$V$25:$V$55) -> 0 | R40: =IF($I$12="","",Q40/$I$12) -> 0 | S40: =IF(W40<>"",IF(D40<>"",D40,($I$8-SUM($S$25:S39))*V40*W40/SUMPRODUCT($W40:$W$55,$V40:$V$55)),"") | T40: =IF(W40<>"",IF(E40<>"",E40,($I$9-SUM($T$25:T39))*V40*W40/SUMPRODUCT($W40:$W$55,$V40:$V$55)),"") | U40: =IF(W40<>"",IF($I$12<>"",IF(G40<>"",G40,($I$9/$I$12-SUM($U$25:U39))*V40*W40/SUMPRODUCT($W40:$W$55,$V40:$V$55)),""),"")
A41: 17 | F41: =IF(AND(E41<>"",E41<>0),D41/E41,"") | H41: =IF(AND(G41<>"",G41<>0),D41/G41,"") | J41: =IF(AND(G41<>"",G41<>0),E41/G41,"") | N41: =IF(AND(I41<>"",I41<>0),G41/I41,"") | O41: =D41/P41 -> #DIV/0! | P41: =$I$8*V41*W41/SUMPRODUCT($W$25:$W$55,$V$25:$V$55) -> 0 | Q41: =$I$9*V41*W41/SUMPRODUCT($W$25:$W$55,$V$25:$V$55) -> 0 | R41: =IF($I$12="","",Q41/$I$12) -> 0 | S41: =IF(W41<>"",IF(D41<>"",D41,($I$8-SUM($S$25:S40))*V41*W41/SUMPRODUCT($W41:$W$55,$V41:$V$55)),"") | T41: =IF(W41<>"",IF(E41<>"",E41,($I$9-SUM($T$25:T40))*V41*W41/SUMPRODUCT($W41:$W$55,$V41:$V$55)),"") | U41: =IF(W41<>"",IF($I$12<>"",IF(G41<>"",G41,($I$9/$I$12-SUM($U$25:U40))*V41*W41/SUMPRODUCT($W41:$W$55,$V41:$V$55)),""),"")
A42: 18 | F42: =IF(AND(E42<>"",E42<>0),D42/E42,"") | H42: =IF(AND(G42<>"",G42<>0),D42/G42,"") | J42: =IF(AND(G42<>"",G42<>0),E42/G42,"") | N42: =IF(AND(I42<>"",I42<>0),G42/I42,"") | O42: =D42/P42 -> #DIV/0! | P42: =$I$8*V42*W42/SUMPRODUCT($W$25:$W$55,$V$25:$V$55) -> 0 | Q42: =$I$9*V42*W42/SUMPRODUCT($W$25:$W$55,$V$25:$V$55) -> 0 | R42: =IF($I$12="","",Q42/$I$12) -> 0 | S42: =IF(W42<>"",IF(D42<>"",D42,($I$8-SUM($S$25:S41))*V42*W42/SUMPRODUCT($W42:$W$55,$V42:$V$55)),"") | T42: =IF(W42<>"",IF(E42<>"",E42,($I$9-SUM($T$25:T41))*V42*W42/SUMPRODUCT($W42:$W$55,$V42:$V$55)),"") | U42: =IF(W42<>"",IF($I$12<>"",IF(G42<>"",G42,($I$9/$I$12-SUM($U$25:U41))*V42*W42/SUMPRODUCT($W42:$W$55,$V42:$V$55)),""),"")
F43: =IF(AND(E43<>"",E43<>0),D43/E43,"") | H43: =IF(AND(G43<>"",G43<>0),D43/G43,"") | J43: =IF(AND(G43<>"",G43<>0),E43/G43,"") | N43: =IF(AND(I43<>"",I43<>0),G43/I43,"") | O43: =D43/P43 -> #DIV/0! | P43: =$I$8*V43*W43/SUMPRODUCT($W$25:$W$55,$V$25:$V$55) -> 0 | Q43: =$I$9*V43*W43/SUMPRODUCT($W$25:$W$55,$V$25:$V$55) -> 0 | R43: =IF($I$12="","",Q43/$I$12) -> 0 | S43: =IF(W43<>"",IF(D43<>"",D43,($I$8-SUM($S$25:S42))*V43*W43/SUMPRODUCT($W43:$W$55,$V43:$V$55)),"") | T43: =IF(W43<>"",IF(E43<>"",E43,($I$9-SUM($T$25:T42))*V43*W43/SUMPRODUCT($W43:$W$55,$V43:$V$55)),"") | U43: =IF(W43<>"",IF($I$12<>"",IF(G43<>"",G43,($I$9/$I$12-SUM($U$25:U42))*V43*W43/SUMPRODUCT($W43:$W$55,$V43:$V$55)),""),"")
F44: =IF(AND(E44<>"",E44<>0),D44/E44,"") | H44: =IF(AND(G44<>"",G44<>0),D44/G44,"") | J44: =IF(AND(G44<>"",G44<>0),E44/G44,"") | N44: =IF(AND(I44<>"",I44<>0),G44/I44,"") | O44: =D44/P44 -> #DIV/0! | P44: =$I$8*V44*W44/SUMPRODUCT($W$25:$W$55,$V$25:$V$55) -> 0 | Q44: =$I$9*V44*W44/SUMPRODUCT($W$25:$W$55,$V$25:$V$55) -> 0 | R44: =IF($I$12="","",Q44/$I$12) -> 0 | S44: =IF(W44<>"",IF(D44<>"",D44,($I$8-SUM($S$25:S43))*V44*W44/SUMPRODUCT($W44:$W$55,$V44:$V$55)),"") | T44: =IF(W44<>"",IF(E44<>"",E44,($I$9-SUM($T$25:T43))*V44*W44/SUMPRODUCT($W44:$W$55,$V44:$V$55)),0) -> 0 | U44: =IF(W44<>"",IF($I$12<>"",IF(G44<>"",G44,($I$9/$I$12-SUM($U$25:U43))*V44*W44/SUMPRODUCT($W44:$W$55,$V44:$V$55)),""),"")
F45: =IF(AND(E45<>"",E45<>0),D45/E45,"") | H45: =IF(AND(G45<>"",G45<>0),D45/G45,"") | J45: =IF(AND(G45<>"",G45<>0),E45/G45,"") | N45: =IF(AND(I45<>"",I45<>0),G45/I45,"") | O45: =D45/P45 -> #DIV/0! | P45: =$I$8*V45*W45/SUMPRODUCT($W$25:$W$44,$V$25:$V$44) -> 0 | Q45: =$I$9*V45*W45/SUMPRODUCT($W$25:$W$44,$V$25:$V$44) -> 0 | R45: =IF($I$12="","",Q45/$I$12) -> 0 | S45: =IF(W45<>"",IF(D45<>"",D45,($I$8-SUM($S$25:S44))*V45*W45/SUMPRODUCT($W$44:$W45,$V$44:$V45)),"") | T45: =IF(W45<>"",IF(E45<>"",E45,($I$9-SUM($T$25:T44))*V45*W45/SUMPRODUCT($W$44:$W45,$V$44:$V45)),"") | U45: =IF(W45<>"",IF($I$12<>"",IF(G45<>"",G45,($I$9/$I$12-SUM($U$25:U44))*V45*W45/SUMPRODUCT($W$44:$W45,$V$44:$V45)),""),"")
F46: =IF(AND(E46<>"",E46<>0),D46/E46,"") | H46: =IF(AND(G46<>"",G46<>0),D46/G46,"") | J46: =IF(AND(G46<>"",G46<>0),E46/G46,"") | N46: =IF(AND(I46<>"",I46<>0),G46/I46,"") | O46: =D46/P46 -> #DIV/0! | P46: =$I$8*V46*W46/SUMPRODUCT($W$25:$W$44,$V$25:$V$44) -> 0 | Q46: =$I$9*V46*W46/SUMPRODUCT($W$25:$W$44,$V$25:$V$44) -> 0 | R46: =IF($I$12="","",Q46/$I$12) -> 0 | S46: =IF(W46<>"",IF(D46<>"",D46,($I$8-SUM($S$25:S45))*V46*W46/SUMPRODUCT($W$44:$W46,$V$44:$V46)),"") | T46: =IF(W46<>"",IF(E46<>"",E46,($I$9-SUM($T$25:T45))*V46*W46/SUMPRODUCT($W$44:$W46,$V$44:$V46)),"") | U46: =IF(W46<>"",IF($I$12<>"",IF(G46<>"",G46,($I$9/$I$12-SUM($U$25:U45))*V46*W46/SUMPRODUCT($W$44:$W46,$V$44:$V46)),""),"")
F47: =IF(AND(E47<>"",E47<>0),D47/E47,"") | H47: =IF(AND(G47<>"",G47<>0),D47/G47,"") | J47: =IF(AND(G47<>"",G47<>0),E47/G47,"") | N47: =IF(AND(I47<>"",I47<>0),G47/I47,"") | O47: =D47/P47 -> #DIV/0! | P47: =$I$8*V47*W47/SUMPRODUCT($W$25:$W$47,$V$25:$V$47) -> 0 | Q47: =$I$9*V47*W47/SUMPRODUCT($W$25:$W$47,$V$25:$V$47) -> 0 | R47: =IF($I$12="","",Q47/$I$12) -> 0 | S47: =IF(W47<>"",IF(D47<>"",D47,($I$8-SUM($S$25:S46))*V47*W47/SUMPRODUCT($W47:$W$47,$V47:$V$47)),"") | T47: =IF(W47<>"",IF(E47<>"",E47,($I$9-SUM($T$25:T46))*V47*W47/SUMPRODUCT($W47:$W$47,$V47:$V$47)),"") | U47: =IF(W47<>"",IF($I$12<>"",IF(G47<>"",G47,($I$9/$I$12-SUM($U$25:U46))*V47*W47/SUMPRODUCT($W47:$W$47,$V47:$V$47)),""),"")
B48: итого | D48: =SUM(D25:D47) -> 0 | E48: =SUM(E25:E47) -> 0 | F48: =IF(AND(E48<>"",E48<>0),D48/E48,"") | G48: =SUM(G25:G47) -> 0 | H48: =IF(AND(G48<>"",G48<>0),D48/G48,"") | I48: =SUM(I25:I47) -> 0 | J48: =IF(AND(G48<>"",G48<>0),E48/G48,"") | K48: =SUM(K25:K47) -> 0 | L48: =SUM(L25:L47) -> 0 | M48: =SUM(M25:M47) -> 0 | N48: =IF(AND(I48<>"",I48<>0),G48/I48,"") | O48: =D48/P48 -> 0 | P48: =SUM(P25:P47) -> 919760.48 | Q48: =SUM(Q25:Q47) -> 249.25758 | R48: =SUM(R25:R47) -> 155.78599 | S48: =SUM(S25:S47) -> 919760.48 | T48: =SUM(T25:T47) -> 249.25758 | U48: =SUM(U25:U47) -> 155.78599
D49: =SUMIF(D25:D47,"",P25:P47)+D48 -> 919760.48

Sheet Вед-ть Кекош
A1: =График!B1 -> Январь, 2025
A2: =График!B3 -> ул. Набережная Ленина, 18 | D2: =График!B4 -> GL-0005
A3: Сотрудник | D3: Выплачено на карту | E3: Выплачено наличными по платежной ведомости | F3: Дополнительные начисления, доплаты | G3: Оклад | H3: Бонусная часть от личных продаж | I3: Бонусная часть от общих продаж | J3: Базовый бонус за выполнение плана | K3: Итого: | L3: Вычеты | M3: Итого к выдаче с учетом авансов и вычетов | N3: Подпись
A4: =График!B30 -> Кекош Анна | D4: 16376.53 | F4: =H8+H9 -> 2576.17 | G4: =D12 -> 14800 | H4: =D19 -> 20707.904 | I4: =L19 -> 9831.3017 | J4: =L12 -> 0 | K4: =H4+J4+G4+F4+I4 -> 47915.376 | L4: =C8+C9+C10 -> 4246 | M4: =K4-L4-D4-E4 -> 27292.846
B6: Вычеты | G6: Доп начисления
B7: Дата | C7: Сумма | D7: Описание | G7: Дата | H7: Сумма | J7: Описание
B8: 45679 | C8: 2447 | D8: НДФЛ январь 2025 | G8: 45679 | H8: 400 | J8: Оплата 4 часа 31.12.2024
B9: 45679 | C9: 1799 | D9: Форма зима 2024 | G9: 45679 | H9: =217617*0.01 -> 2176.17 | J9: Административный %
A12: Оклад: | D12: =G16 -> 14800 | I12: Базовый бонус за выполнение плана | L12: =L16+L17 -> 0
B14: Оклад: | J14: Базовый бонус за выполнение плана
B15: Дней | C15: Магазин | D15: Должность | E15: Зачислено часов | F15: Ставка за час, руб | G15: Начислено за день, руб | J15: Магазин | K15: КВП | L15: Начисленный ББ
B16: =График!AI30 -> 15 | C16: =A2 -> ул. Набережная Ленина, 18 | D16: ПК | E16: =График!AJ30 -> 148 | F16: 100 | G16: =E16*F16 -> 14800 | J16: =График!B3 -> ул. Набережная Ленина, 18 | K16: 0.5284 | L16: 0
A19: БонуснаяЧасть | D19: =G24 -> 20707.904 | I19: Бонусная часть от общих продаж | L19: =N24 -> 9831.3017
B22: Бонус от личных продаж по категории товара | I22: Бонус от общих продаж
B23: Сотрудник | C23: Магазин | E23: Процент от продажи | F23: Продано на сумму, руб | G23: Начисленный бонус от продаж, руб | I23: Сотрудник | J23: Магазин | K23: Кол-во отработанных личных часов | L23: Кол-во отработанных общих часов | M23: Процент от продажи | N23: Начисленный бонус от продаж, руб
B24: =A4 -> Кекош Анна | C24: =A2 -> ул. Набережная Ленина, 18 | E24: 0.04 | F24: ='Кекош А. И.'!J8 -> 517697.6 | G24: =F24*E24 -> 20707.904 | I24: =B24 -> Кекош Анна | J24: =C24 -> ул. Набережная Ленина, 18 | K24: =E16 -> 148 | L24: 350 | M24: 0.02 | N24: =1162485*M24*K24/L24 -> 9831.3017
B25: =B24 -> Кекош Анна | N25: =1477363.14*M25*K25/L25 -> #DIV/0!

Sheet Вед-ть Рогалевич
A1: =График!B1 -> Январь, 2025
A2: =График!B3 -> ул. Набережная Ленина, 18 | D2: =График!B4 -> GL-0005
A3: Сотрудник | D3: Выплачено на карту | E3: Выплачено наличными по платежной ведомости | F3: Дополнительные начисления, доплаты | G3: Оклад | H3: Бонусная часть от личных продаж | I3: Бонусная часть от общих продаж | J3: Базовый бонус за выполнение плана | K3: Итого: | L3: Вычеты | M3: Итого к выдаче с учетом авансов и вычетов | N3: Подпись
A4: =График!B29 -> Рогалевич Ирина | D4: =5220+7830 -> 13050 | F4: =H8+H9 -> 0 | G4: =D12 -> 41200 | H4: =D19 -> 40315.818 | I4: =L19 -> 17889.284 | J4: =L12 -> 11550 | K4: =H4+J4+G4+F4+I4 -> 110955.1 | L4: =C8+C9 -> 2250 | M4: =K4-L4-D4-E4 -> 95655.101
B6: Вычеты | G6: Доп начисления
B7: Дата | C7: Сумма | D7: Описание | G7: Дата | H7: Сумма | J7: Описание
B8: 45688 | C8: =15000-D4 -> 1950 | D8: НДФЛ январь 2025
B9: 45688 | C9: 300 | D9: Вычет согласно инвентаризационной ведомости от 31.01.2025
B10: 45688 | C10: 2997 | D10: Вычет согласно инвентаризационной ведомости за январь ТРК Меганом
A12: Оклад: | D12: =G16+G17 -> 41200 | I12: Базовый бонус за выполнение плана | L12: =L16+L17 -> 11550
B14: Оклад: | J14: Базовый бонус за выполнение плана
B15: Дней | C15: Магазин | D15: Должность | E15: Зачислено часов | F15: Ставка за час, руб | G15: Начислено за день, руб | J15: Магазин | K15: КВП | L15: Начисленный ББ
B16: =График!AI29 -> 24 | C16: =A2 -> ул. Набережная Ленина, 18 | D16: ПК | E16: =График!AJ29 -> 256 | F16: 150 | G16: =E16*F16 -> 38400 | J16: =График!B3 -> ул. Набережная Ленина, 18 | K16: 1 | L16: 11550
B17: 3 | C17: Евпаторийское шоссе, 8 | D17: ПК | E17: 28 | F17: 100 | G17: =E17*F17 -> 2800 | J17: =C25 -> Евпаторийское шоссе, 8 | K17: 0.728 | L17: 0
A19: БонуснаяЧасть | D19: =G24+G25 -> 40315.818 | I19: Бонусная часть от общих продаж | L19: =N24+N25 -> 17889.284
B22: Бонус от личных продаж по категории товара | I22: Бонус от общих продаж
B23: Сотрудник | C23: Магазин | E23: Процент от продажи | F23: Продано на сумму, руб | G23: Начисленный бонус от продаж, руб | I23: Сотрудник | J23: Магазин | K23: Кол-во отработанных личных часов | L23: Кол-во отработанных общих часов | M23: Процент от продажи | N23: Начисленный бонус от продаж, руб
B24: =A4 -> Рогалевич Ирина | C24: =A2 -> ул. Набережная Ленина, 18 | E24: 0.04 | F24: ='Рогалевич И. Е.'!J8 -> 833967.94 | G24: =F24*E24 -> 33358.718 | I24: =B24 -> Рогалевич Ирина | J24: =C24 -> ул. Набережная Ленина, 18 | K24: =E16 -> 256 | L24: =График!AJ31 -> 501 | M24: 0.02 | N24: ='Ялта, Ленина, 18'!J8*M24*K24/L24 -> 16054.599
B25: =B24 -> Рогалевич Ирина | C25: =C17 -> Евпаторийское шоссе, 8 | E25: 0.05 | F25: 139142 | G25: =F25*E25 -> 6957.1 | I25: =I24 -> Рогалевич Ирина | J25: =C25 -> Евпаторийское шоссе, 8 | K25: =E17 -> 28 | L25: 974 | M25: 0.04 | N25: =(3166487-1570966.94)*M25*K25/L25 -> 1834.6843

Sheet Доп сотрудник
B1: =TODAY()-1 -> 45696
B2: (отчетная дата) | J2: ЕЖЕДНЕВНЫЙ ОТЧЕТ О ПРОДАЖАХ
B3: Осталось до выполнения плана!!! | J3: =График!B27 -> 0
C4: =I8-D48 -> -219302.1 | E4: =IF(I8<>0,C4/I8,0) -> 0
F6: Целевые показатели
F7: Показатель | I7: План | J7: Факт | K7: % выполнения | L7: Прогноз выполнения | M7: % выполнения по прогнозу | N7: Отклонение | O7: Факт аналогичного месяца прошлого года | P7: Отклонение LFL
F8: Выручка | I8: ='Ялта, Ленина, 18'!I8/График!AJ31*График!AJ27 -> 0 | J8: =D48 -> 219302.1 | K8: =IF(AND(I8<>"", I8<>0, J8<>""), J8/I8, "") | L8: =IF(SUMIF($D$25:$D$47,">=0",$P$25:$P$47)<>0,I8*D48/SUMIF($D$25:$D$47,">=0",$P$25:$P$47),0) -> 0 | M8: =IF(AND(I8<>"", I8<>0, L8<>"", L8<>0), L8/I8, "") | N8: =IF(AND(J8<>0, J8<>"", I8<>0, I8<>""), L8-I8, "") | P8: =IF(AND(O8<>"", O8<>0, L8<>"", L8<>0), -O8+L8, "") | Q8: =IF(AND(P8<>"", P8<>0, O8<>0, O8<>""), P8/O8, "")
F9: Кол-во изделий | I9: =I8/I11 -> 0 | J9: =E48 -> 70 | K9: =IF(AND(I9<>"", I9<>0, J9<>""), J9/I9, "") | L9: =IF(SUMIF($E$25:$E$47,">=0",$Q$25:$Q$47)<>0,I9*E48/SUMIF($E$25:$E$47,">=0",$Q$25:$Q$47),0) -> 0 | M9: =IF(AND(I9<>"", I9<>0, L9<>"", L9<>0), L9/I9, "") | N9: =IF(AND(J9<>0, J9<>"", I9<>0, I9<>""), L9-I9, "") | O9: =O8/O11 -> #DIV/0! | P9: =IF(AND(O9<>"", O9<>0, L9<>"", L9<>0), -O9+L9, "") -> #DIV/0! | Q9: =IF(AND(P9<>"", P9<>0, O9<>0, O9<>""), P9/O9, "") -> #DIV/0!
F10: Средний чек | I10: =I11*I12 -> 5904 | J10: =H48 -> 6645.5182 | K10: =IF(AND(I10<>"", I10<>0, J10<>""), J10/I10, "") -> 1.1255959 | L10: =J10 -> 6645.5182 | M10: =IF(AND(I10<>"", I10<>0, L10<>"", L10<>0), L10/I10, "") -> 1.1255959 | N10: =IF(AND(J10<>0, J10<>"", I10<>0, I10<>""), L10-I10, "") -> 741.51818 | O10: =O11*O12 -> 0 | P10: =IF(AND(O10<>"", O10<>0, L10<>"", L10<>0), -O10+L10, "") | Q10: =IF(AND(P10<>"", P10<>0, O10<>0, O10<>""), P10/O10, "")
F11: Средняя стоимость изделия | I11: ='Ялта, Ленина, 18'!I11 -> 3690 | J11: =F48 -> 3132.8871 | K11: =IF(AND(I11<>"", I11<>0, J11<>""), J11/I11, "") -> 0.84902091 | L11: =IF(L9>0, L8/L9, "") | M11: =IF(AND(I11<>"", I11<>0, L11<>"", L11<>0), L11/I11, "") | N11: =IF(AND(J11<>0, J11<>"", I11<>0, I11<>""), L11-I11, "") -> #VALUE! | P11: =IF(AND(O11<>"", O11<>0, L11<>"", L11<>0), -O11+L11, "") | Q11: =IF(AND(P11<>"", P11<>0, O11<>0, O11<>""), P11/O11, "")
F12: Длина чека | I12: ='Ялта, Ленина, 18'!I12 -> 1.6 | J12: =J48 -> 2.1212121 | K12: =IF(AND(I12<>"", I12<>0, J12<>""), J12/I12, "") -> 1.3257576 | L12: =J12 -> 2.1212121 | M12: =IF(AND(I12<>"", I12<>0, L12<>"", L12<>0), L12/I12, "") -> 1.3257576 | N12: =IF(AND(J12<>0, J12<>"", I12<>0, I12<>""), L12-I12, "") -> 0.52121212 | P12: =IF(AND(O12<>"", O12<>0, L12<>"", L12<>0), -O12+L12, "") | Q12: =IF(AND(P12<>"", P12<>0, O12<>0, O12<>""), P12/O12, "")
F13: Кол-во чеков | I13: =IF(I12<>0, I9/I12, "") -> 0 | J13: =G48 -> 33 | K13: =IF(AND(I13<>"", I13<>0, J13<>""), J13/I13, "") | L13: =IF(SUMIF($G$25:$G$47,">=0",$R$25:$R$47)<>0,I13*G48/SUMIF($G$25:$G$47,">=0",$R$25:$R$47),"") | M13: =IF(AND(I13<>"", I13<>0, L13<>"", L13<>0), L13/I13, "") | N13: =IF(AND(J13<>0, J13<>"", I13<>0, I13<>""), L13-I13, "") | P13: =IF(AND(O13<>"", O13<>0, L13<>"", L13<>0), -O13+L13, "") | Q13: =IF(AND(P13<>"", P13<>0, O13<>0, O13<>""), P13/O13, "")
F14: Кол-во смен план/отработано | J14: 5 | K14: =IF(AND(I14<>"", I14<>0, J14<>""), J14/I14, "") | L14: =IF(SUMIF($D$25:$D$47,">=0",$P$25:$P$47),I48*I8/SUMIF($D$25:$D$47,">=0",$P$25:$P$47),"") | M14: =IF(AND(I14<>"", I14<>0, L14<>"", L14<>0), L14/I14, "") | N14: =IF(AND(J14<>0, J14<>"", I14<>0, I14<>""), L14-I14, "") | P14: =IF(AND(O14<>"", O14<>0, L14<>"", L14<>0), -O14+L14, "") | Q14: =IF(AND(P14<>"", P14<>0, O14<>0, O14<>""), P14/O14, "")
F15: Средние продажи в смену | I15: ='Ялта, Ленина, 18'!I15 -> 60000 | J15: =J8/J14 -> 43860.42 | K15: =IF(AND(I15<>"", I15<>0, J15<>""), J15/I15, "") -> 0.731007 | L15: =J15 -> 43860.42 | M15: =IF(AND(I15<>"", I15<>0, L15<>"", L15<>0), L15/I15, "") -> 0.731007 | N15: =IF(AND(J15<>0, J15<>"", I15<>0, I15<>""), L15-I15, "") -> -16139.58 | P15: =IF(AND(O15<>"", O15<>0, L15<>"", L15<>0), -O15+L15, "") | Q15: =IF(AND(P15<>"", P15<>0, O15<>0, O15<>""), P15/O15, "")
F16: Отставание/Перевыполнение | J16: =J8-I15*J14 -> -80697.9 | K16: =IF(AND(I16<>"", I16<>0, J16<>""), J16/I16, "") | L16: =J16 -> -80697.9 | M16: =IF(AND(I16<>"", I16<>0, L16<>"", L16<>0), L16/I16, "") | N16: =IF(AND(J16<>0, J16<>"", I16<>0, I16<>""), L16-I16, "") | P16: =IF(AND(O16<>"", O16<>0, L16<>"", L16<>0), -O16+L16, "") | Q16: =IF(AND(P16<>"", P16<>0, O16<>0, O16<>""), P16/O16, "") | S16: Подарочные сертификаты
F17: Трафик | I17: ='Ялта, Ленина, 18'!I17/График!AJ31*График!AJ27 -> 0 | J17: =I48 -> 0 | K17: =IF(AND(I17<>"", I17<>0, J17<>""), J17/I17, "") | L17: =J17 -> 0 | M17: =IF(AND(I17<>"", I17<>0, L17<>"", L17<>0), L17/I17, "") | N17: =IF(AND(J17<>0, J17<>"", I17<>0, I17<>""), L17-I17, "") | P17: =IF(AND(O17<>"", O17<>0, L17<>"", L17<>0), -O17+L17, "") | Q17: =IF(AND(P17<>"", P17<>0, O17<>0, O17<>""), P17/O17, "")
K18: =IF(AND(I18<>"", I18<>0, J18<>""), J18/I18, "") | L18: =J18 -> 0 | M18: =IF(AND(I18<>"", I18<>0, L18<>"", L18<>0), L18/I18, "") | N18: =IF(AND(J18<>0, J18<>"", I18<>0, I18<>""), L18-I18, "") | O18: 0 | P18: =IF(AND(O18<>"", O18<>0, L18<>"", L18<>0), -O18+L18, "") | Q18: =IF(AND(P18<>"", P18<>0, O18<>0, O18<>""), P18/O18, "") | S18: 5000
K19: =IF(AND(I19<>"", I19<>0, J19<>""), J19/I19, "") | L19: =J19 -> 0 | M19: =IF(AND(I19<>"", I19<>0, L19<>"", L19<>0), L19/I19, "") | N19: =IF(AND(J19<>0, J19<>"", I19<>0, I19<>""), L19-I19, "") | O19: 0 | P19: =IF(AND(O19<>"", O19<>0, L19<>"", L19<>0), -O19+L19, "") | Q19: =IF(AND(P19<>"", P19<>0, O19<>0, O19<>""), P19/O19, "") | S19: =S18/I16 -> #DIV/0!
F20: Конверсия план/факт | I20: ='Ялта, Ленина, 18'!I20 -> 0.257 | J20: =N48 | K20: =J20/I20 -> #VALUE! | L20: =IF(AND(K8<>0,I14<>0,I48<>0),(I48*N48+(I48/K8-I48)*I20)/(I48/K8),0) -> 0 | M20: =IF(AND(I20<>"", I20<>0, L20<>"", L20<>0), L20/I20, "") | N20: =IF(AND(J20<>0, J20<>"", I20<>0, I20<>""), L20-I20, "") | P20: =IF(AND(O20<>"", O20<>0, L20<>"", L20<>0), -O20+L20, "") | Q20: =IF(AND(P20<>"", P20<>0, O20<>0, O20<>""), P20/O20, "")
B22: Факт продаж за месяц | O22: % выполнения дневного плана | P22: Раcпределение плана по дням
B23: Дата | C23: День недели | D23: Выручка (руб) | E23: Кол-во единиц (шт.) | F23: Средняя стоимость изделия (руб.) | G23: Количество чеков (шт.) | H23: Средняя сумма чека (руб.) | I23: Трафик | J23: Длина чека (шт.) | K23: Запасной | L23: Запасной | M23: Запасной | N23: Конверсия (%) | P23: выручка, план | Q23: кол-во ед, план | R23: Кол-во чеков, план | S23: выручка, скорректир.план | T23: кол-во ед, скорр. план | U23: кол-во чеков, скорр. план | V23: Коэфф. Дня Недели | W23: Специфика месяца
B24: 1 | C24: 2 | D24: 3 | E24: в | F24: 5 | G24: 6 | H24: 7 | I24: 8 | J24: 9 | K24: 10 | L24: 11 | M24: 12 | N24: 13 | P24: 1 | Q24: 2 | R24: 3 | S24: 4 | T24: 5 | U24: 6 | V24: 10 | W24: 11
A25: Стекольщикова | B25: 45665 | C25: ср | D25: 7913 | E25: 2 | F25: =IF(AND(E25<>"",E25<>0),D25/E25,"") -> 3956.5 | G25: 1 | H25: =IF(AND(G25<>"",G25<>0),D25/G25,"") -> 7913 | J25: =IF(AND(G25<>"",G25<>0),E25/G25,"") -> 2 | N25: =IF(AND(I25<>"",I25<>0),G25/I25,"") | O25: =D25/P25 -> #DIV/0! | P25: =$I$8*V25*W25/SUMPRODUCT($W$25:$W$55,$V$25:$V$55) -> 0 | Q25: =$I$9*V25*W25/SUMPRODUCT($W$25:$W$55,$V$25:$V$55) -> 0 | R25: =IF($I$12="","",Q25/$I$12) -> 0 | S25: =IF(W25<>"",IF(D25<>"",D25,($I$8-SUM($S24:S$25))*V25*W25/SUMPRODUCT($W25:$W$55,$V25:$V$55)),"") -> 7913 | T25: =IF(W25<>"",IF(E25<>"",E25,($I$9-SUM($T24:T$25))*V25*W25/SUMPRODUCT($W25:$W$55,$V25:$V$55)),"") -> 2 | U25: =IF(W25<>"",IF($I$12<>"",IF(G25<>"",G25,($I$9/$I$12-SUM($U24:U$25))*V25*W25/SUMPRODUCT($W25:$W$55,$V25:$V$55)),""),"") -> 1 | V25: 1 | W25: 1
A26: Орешникова | B26: 45659 | E26: 18 | F26: =IF(AND(E26<>"",E26<>0),D26/E26,"") -> 0 | G26: 10 | H26: =IF(AND(G26<>"",G26<>0),D26/G26,"") -> 0 | J26: =IF(AND(G26<>"",G26<>0),E26/G26,"") -> 1.8 | N26: =IF(AND(I26<>"",I26<>0),G26/I26,"") | O26: =D26/P26 -> #DIV/0! | P26: =$I$8*V26*W26/SUMPRODUCT($W$25:$W$55,$V$25:$V$55) -> 0 | Q26: =$I$9*V26*W26/SUMPRODUCT($W$25:$W$55,$V$25:$V$55) -> 0 | R26: =IF($I$12="","",Q26/$I$12) -> 0 | S26: =IF(W26<>"",IF(D26<>"",D26,($I$8-SUM($S$25:S25))*V26*W26/SUMPRODUCT($W26:$W$55,$V26:$V$55)),"") -> -879.22222 | T26: =IF(W26<>"",IF(E26<>"",E26,($I$9-SUM($T$25:T25))*V26*W26/SUMPRODUCT($W26:$W$55,$V26:$V$55)),"") -> 18 | U26: =IF(W26<>"",IF($I$12<>"",IF(G26<>"",G26,($I$9/$I$12-SUM($U$25:U25))*V26*W26/SUMPRODUCT($W26:$W$55,$V26:$V$55)),""),"") -> 10 | V26: 1 | W26: 1
A27: Орешникова | B27: 45660 | E27: 13 | F27: =IF(AND(E27<>"",E27<>0),D27/E27,"") -> 0 | G27: 7 | H27: =IF(AND(G27<>"",G27<>0),D27/G27,"") -> 0 | J27: =IF(AND(G27<>"",G27<>0),E27/G27,"") -> 1.8571429 | N27: =IF(AND(I27<>"",I27<>0),G27/I27,"") | O27: =D27/P27 -> #DIV/0! | P27: =$I$8*V27*W27/SUMPRODUCT($W$25:$W$55,$V$25:$V$55) -> 0 | Q27: =$I$9*V27*W27/SUMPRODUCT($W$25:$W$55,$V$25:$V$55) -> 0 | R27: =IF($I$12="","",Q27/$I$12) -> 0 | S27: =IF(W27<>"",IF(D27<>"",D27,($I$8-SUM($S$25:S26))*V27*W27/SUMPRODUCT($W27:$W$55,$V27:$V$55)),"") -> -879.22222 | T27: =IF(W27<>"",IF(E27<>"",E27,($I$9-SUM($T$25:T26))*V27*W27/SUMPRODUCT($W27:$W$55,$V27:$V$55)),"") -> 13 | U27: =IF(W27<>"",IF($I$12<>"",IF(G27<>"",G27,($I$9/$I$12-SUM($U$25:U26))*V27*W27/SUMPRODUCT($W27:$W$55,$V27:$V$55)),""),"") -> 7 | V27: 1 | W27: 1
A28: Орешникова | B28: 45661 | E28: 17 | F28: =IF(AND(E28<>"",E28<>0),D28/E28,"") -> 0 | G28: 9 | H28: =IF(AND(G28<>"",G28<>0),D28/G28,"") -> 0 | J28: =IF(AND(G28<>"",G28<>0),E28/G28,"") -> 1.8888889 | N28: =IF(AND(I28<>"",I28<>0),G28/I28,"") | O28: =D28/P28 -> #DIV/0! | P28: =$I$8*V28*W28/SUMPRODUCT($W$25:$W$55,$V$25:$V$55) -> 0 | Q28: =$I$9*V28*W28/SUMPRODUCT($W$25:$W$55,$V$25:$V$55) -> 0 | R28: =IF($I$12="","",Q28/$I$12) -> 0 | S28: =IF(W28<>"",IF(D28<>"",D28,($I$8-SUM($S$25:S27))*V28*W28/SUMPRODUCT($W28:$W$55,$V28:$V$55)),"") -> -879.22222 | T28: =IF(W28<>"",IF(E28<>"",E28,($I$9-SUM($T$25:T27))*V28*W28/SUMPRODUCT($W28:$W$55,$V28:$V$55)),"") -> 17 | U28: =IF(W28<>"",IF($I$12<>"",IF(G28<>"",G28,($I$9/$I$12-SUM($U$25:U27))*V28*W28/SUMPRODUCT($W28:$W$55,$V28:$V$55)),""),"") -> 9 | V28: 1 | W28: 1
A29: Орешникова | B29: 45662 | D29: 211389.1 | E29: 20 | F29: =IF(AND(E29<>"",E29<>0),D29/E29,"") -> 10569.455 | G29: 6 | H29: =IF(AND(G29<>"",G29<>0),D29/G29,"") -> 35231.517 | J29: =IF(AND(G29<>"",G29<>0),E29/G29,"") -> 3.3333333 | N29: =IF(AND(I29<>"",I29<>0),G29/I29,"") | O29: =D29/P29 -> #DIV/0! | P29: =$I$8*V29*W29/SUMPRODUCT($W$25:$W$55,$V$25:$V$55) -> 0 | Q29: =$I$9*V29*W29/SUMPRODUCT($W$25:$W$55,$V$25:$V$55) -> 0 | R29: =IF($I$12="","",Q29/$I$12) -> 0 | S29: =IF(W29<>"",IF(D29<>"",D29,($I$8-SUM($S$25:S28))*V29*W29/SUMPRODUCT($W29:$W$55,$V29:$V$55)),"") -> 211389.1 | T29: =IF(W29<>"",IF(E29<>"",E29,($I$9-SUM($T$25:T28))*V29*W29/SUMPRODUCT($W29:$W$55,$V29:$V$55)),"") -> 20 | U29: =IF(W29<>"",IF($I$12<>"",IF(G29<>"",G29,($I$9/$I$12-SUM($U$25:U28))*V29*W29/SUMPRODUCT($W29:$W$55,$V29:$V$55)),""),"") -> 6 | V29: 1 | W29: 1
F30: =IF(AND(E30<>"",E30<>0),D30/E30,"") | H30: =IF(AND(G30<>"",G30<>0),D30/G30,"") | J30: =IF(AND(G30<>"",G30<>0),E30/G30,"") | N30: =IF(AND(I30<>"",I30<>0),G30/I30,"") | O30: =D30/P30 -> #DIV/0! | P30: =$I$8*V30*W30/SUMPRODUCT($W$25:$W$55,$V$25:$V$55) -> 0 | Q30: =$I$9*V30*W30/SUMPRODUCT($W$25:$W$55,$V$25:$V$55) -> 0 | R30: =IF($I$12="","",Q30/$I$12) -> 0 | S30: =IF(W30<>"",IF(D30<>"",D30,($I$8-SUM($S$25:S29))*V30*W30/SUMPRODUCT($W30:$W$55,$V30:$V$55)),"") -> -43332.887 | T30: =IF(W30<>"",IF(E30<>"",E30,($I$9-SUM($T$25:T29))*V30*W30/SUMPRODUCT($W30:$W$55,$V30:$V$55)),"") -> -14 | U30: =IF(W30<>"",IF($I$12<>"",IF(G30<>"",G30,($I$9/$I$12-SUM($U$25:U29))*V30*W30/SUMPRODUCT($W30:$W$55,$V30:$V$55)),""),"") -> -6.6 | V30: 1 | W30: 1
F31: =IF(AND(E31<>"",E31<>0),D31/E31,"") | H31: =IF(AND(G31<>"",G31<>0),D31/G31,"") | J31: =IF(AND(G31<>"",G31<>0),E31/G31,"") | N31: =IF(AND(I31<>"",I31<>0),G31/I31,"") | O31: =D31/P31 -> #DIV/0! | P31: =$I$8*V31*W31/SUMPRODUCT($W$25:$W$55,$V$25:$V$55) -> 0 | Q31: =$I$9*V31*W31/SUMPRODUCT($W$25:$W$55,$V$25:$V$55) -> 0 | R31: =IF($I$12="","",Q31/$I$12) -> 0 | S31: =IF(W31<>"",IF(D31<>"",D31,($I$8-SUM($S$25:S30))*V31*W31/SUMPRODUCT($W31:$W$55,$V31:$V$55)),"") -> -43332.887 | T31: =IF(W31<>"",IF(E31<>"",E31,($I$9-SUM($T$25:T30))*V31*W31/SUMPRODUCT($W31:$W$55,$V31:$V$55)),"") -> -14 | U31: =IF(W31<>"",IF($I$12<>"",IF(G31<>"",G31,($I$9/$I$12-SUM($U$25:U30))*V31*W31/SUMPRODUCT($W31:$W$55,$V31:$V$55)),""),"") -> -6.6 | V31: 1 | W31: 1
F32: =IF(AND(E32<>"",E32<>0),D32/E32,"") | H32: =IF(AND(G32<>"",G32<>0),D32/G32,"") | J32: =IF(AND(G32<>"",G32<>0),E32/G32,"") | N32: =IF(AND(I32<>"",I32<>0),G32/I32,"") | O32: =D32/P32 -> #DIV/0! | P32: =$I$8*V32*W32/SUMPRODUCT($W$25:$W$55,$V$25:$V$55) -> 0 | Q32: =$I$9*V32*W32/SUMPRODUCT($W$25:$W$55,$V$25:$V$55) -> 0 | R32: =IF($I$12="","",Q32/$I$12) -> 0 | S32: =IF(W32<>"",IF(D32<>"",D32,($I$8-SUM($S$25:S31))*V32*W32/SUMPRODUCT($W32:$W$55,$V32:$V$55)),"") -> -43332.887 | T32: =IF(W32<>"",IF(E32<>"",E32,($I$9-SUM($T$25:T31))*V32*W32/SUMPRODUCT($W32:$W$55,$V32:$V$55)),"") -> -14 | U32: =IF(W32<>"",IF($I$12<>"",IF(G32<>"",G32,($I$9/$I$12-SUM($U$25:U31))*V32*W32/SUMPRODUCT($W32:$W$55,$V32:$V$55)),""),"") -> -6.6 | V32: 1 | W32: 1
F33: =IF(AND(E33<>"",E33<>0),D33/E33,"") | H33: =IF(AND(G33<>"",G33<>0),D33/G33,"") | J33: =IF(AND(G33<>"",G33<>0),E33/G33,"") | N33: =IF(AND(I33<>"",I33<>0),G33/I33,"") | O33: =D33/P33 -> #DIV/0! | P33: =$I$8*V33*W33/SUMPRODUCT($W$25:$W$55,$V$25:$V$55) -> 0 | Q33: =$I$9*V33*W33/SUMPRODUCT($W$25:$W$55,$V$25:$V$55) -> 0 | R33: =IF($I$12="","",Q33/$I$12) -> 0 | S33: =IF(W33<>"",IF(D33<>"",D33,($I$8-SUM($S$25:S32))*V33*W33/SUMPRODUCT($W33:$W$55,$V33:$V$55)),"") -> -43332.887 | T33: =IF(W33<>"",IF(E33<>"",E33,($I$9-SUM($T$25:T32))*V33*W33/SUMPRODUCT($W33:$W$55,$V33:$V$55)),"") -> -14 | U33: =IF(W33<>"",IF($I$12<>"",IF(G33<>"",G33,($I$9/$I$12-SUM($U$25:U32))*V33*W33/SUMPRODUCT($W33:$W$55,$V33:$V$55)),""),"") -> -6.6 | V33: 1 | W33: 1
F34: =IF(AND(E34<>"",E34<>0),D34/E34,"") | H34: =IF(AND(G34<>"",G34<>0),D34/G34,"") | J34: =IF(AND(G34<>"",G34<>0),E34/G34,"") | N34: =IF(AND(I34<>"",I34<>0),G34/I34,"") | O34: =D34/P34 -> #DIV/0! | P34: =$I$8*V34*W34/SUMPRODUCT($W$25:$W$55,$V$25:$V$55) -> 0 | Q34: =$I$9*V34*W34/SUMPRODUCT($W$25:$W$55,$V$25:$V$55) -> 0 | R34: =IF($I$12="","",Q34/$I$12) -> 0 | S34: =IF(W34<>"",IF(D34<>"",D34,($I$8-SUM($S$25:S33))*V34*W34/SUMPRODUCT($W34:$W$55,$V34:$V$55)),"") -> -43332.887 | T34: =IF(W34<>"",IF(E34<>"",E34,($I$9-SUM($T$25:T33))*V34*W34/SUMPRODUCT($W34:$W$55,$V34:$V$55)),"") -> -14 | U34: =IF(W34<>"",IF($I$12<>"",IF(G34<>"",G34,($I$9/$I$12-SUM($U$25:U33))*V34*W34/SUMPRODUCT($W34:$W$55,$V34:$V$55)),""),"") -> -6.6 | V34: 1 | W34: 1
F35: =IF(AND(E35<>"",E35<>0),D35/E35,"") | H35: =IF(AND(G35<>"",G35<>0),D35/G35,"") | J35: =IF(AND(G35<>"",G35<>0),E35/G35,"") | N35: =IF(AND(I35<>"",I35<>0),G35/I35,"") | O35: =D35/P35 -> #DIV/0! | P35: =$I$8*V35*W35/SUMPRODUCT($W$25:$W$55,$V$25:$V$55) -> 0 | Q35: =$I$9*V35*W35/SUMPRODUCT($W$25:$W$55,$V$25:$V$55) -> 0 | R35: =IF($I$12="","",Q35/$I$12) -> 0 | S35: =IF(W35<>"",IF(D35<>"",D35,($I$8-SUM($S$25:S34))*V35*W35/SUMPRODUCT($W35:$W$55,$V35:$V$55)),"") | T35: =IF(W35<>"",IF(E35<>"",E35,($I$9-SUM($T$25:T34))*V35*W35/SUMPRODUCT($W35:$W$55,$V35:$V$55)),"") | U35: =IF(W35<>"",IF($I$12<>"",IF(G35<>"",G35,($I$9/$I$12-SUM($U$25:U34))*V35*W35/SUMPRODUCT($W35:$W$55,$V35:$V$55)),""),"")
F36: =IF(AND(E36<>"",E36<>0),D36/E36,"") | H36: =IF(AND(G36<>"",G36<>0),D36/G36,"") | J36: =IF(AND(G36<>"",G36<>0),E36/G36,"") | N36: =IF(AND(I36<>"",I36<>0),G36/I36,"") | O36: =D36/P36 -> #DIV/0! | P36: =$I$8*V36*W36/SUMPRODUCT($W$25:$W$55,$V$25:$V$55) -> 0 | Q36: =$I$9*V36*W36/SUMPRODUCT($W$25:$W$55,$V$25:$V$55) -> 0 | R36: =IF($I$12="","",Q36/$I$12) -> 0 | S36: =IF(W36<>"",IF(D36<>"",D36,($I$8-SUM($S$25:S35))*V36*W36/SUMPRODUCT($W36:$W$55,$V36:$V$55)),"") | T36: =IF(W36<>"",IF(E36<>"",E36,($I$9-SUM($T$25:T35))*V36*W36/SUMPRODUCT($W36:$W$55,$V36:$V$55)),"") | U36: =IF(W36<>"",IF($I$12<>"",IF(G36<>"",G36,($I$9/$I$12-SUM($U$25:U35))*V36*W36/SUMPRODUCT($W36:$W$55,$V36:$V$55)),""),"")
F37: =IF(AND(E37<>"",E37<>0),D37/E37,"") | H37: =IF(AND(G37<>"",G37<>0),D37/G37,"") | J37: =IF(AND(G37<>"",G37<>0),E37/G37,"") | N37: =IF(AND(I37<>"",I37<>0),G37/I37,"") | O37: =D37/P37 -> #DIV/0! | P37: =$I$8*V37*W37/SUMPRODUCT($W$25:$W$55,$V$25:$V$55) -> 0 | Q37: =$I$9*V37*W37/SUMPRODUCT($W$25:$W$55,$V$25:$V$55) -> 0 | R37: =IF($I$12="","",Q37/$I$12) -> 0 | S37: =IF(W37<>"",IF(D37<>"",D37,($I$8-SUM($S$25:S36))*V37*W37/SUMPRODUCT($W37:$W$55,$V37:$V$55)),"") | T37: =IF(W37<>"",IF(E37<>"",E37,($I$9-SUM($T$25:T36))*V37*W37/SUMPRODUCT($W37:$W$55,$V37:$V$55)),"") | U37: =IF(W37<>"",IF($I$12<>"",IF(G37<>"",G37,($I$9/$I$12-SUM($U$25:U36))*V37*W37/SUMPRODUCT($W37:$W$55,$V37:$V$55)),""),"")
F38: =IF(AND(E38<>"",E38<>0),D38/E38,"") | H38: =IF(AND(G38<>"",G38<>0),D38/G38,"") | J38: =IF(AND(G38<>"",G38<>0),E38/G38,"") | N38: =IF(AND(I38<>"",I38<>0),G38/I38,"") | O38: =D38/P38 -> #DIV/0! | P38: =$I$8*V38*W38/SUMPRODUCT($W$25:$W$44,$V$25:$V$44) -> 0 | Q38: =$I$9*V38*W38/SUMPRODUCT($W$25:$W$44,$V$25:$V$44) -> 0 | R38: =IF($I$12="","",Q38/$I$12) -> 0 | S38: =IF(W38<>"",IF(D38<>"",D38,($I$8-SUM($S$25:S37))*V38*W38/SUMPRODUCT($W38:$W$55,$V38:$V$55)),"") | T38: =IF(W38<>"",IF(E38<>"",E38,($I$9-SUM($T$25:T37))*V38*W38/SUMPRODUCT($W38:$W$55,$V38:$V$55)),"") | U38: =IF(W38<>"",IF($I$12<>"",IF(G38<>"",G38,($I$9/$I$12-SUM($U$25:U37))*V38*W38/SUMPRODUCT($W38:$W$55,$V38:$V$55)),""),"")
F39: =IF(AND(E39<>"",E39<>0),D39/E39,"") | H39: =IF(AND(G39<>"",G39<>0),D39/G39,"") | J39: =IF(AND(G39<>"",G39<>0),E39/G39,"") | N39: =IF(AND(I39<>"",I39<>0),G39/I39,"") | O39: =D39/P39 -> #DIV/0! | P39: =$I$8*V39*W39/SUMPRODUCT($W$25:$W$44,$V$25:$V$44) -> 0 | Q39: =$I$9*V39*W39/SUMPRODUCT($W$25:$W$44,$V$25:$V$44) -> 0 | R39: =IF($I$12="","",Q39/$I$12) -> 0 | S39: =IF(W39<>"",IF(D39<>"",D39,($I$8-SUM($S$25:S38))*V39*W39/SUMPRODUCT($W39:$W$55,$V39:$V$55)),"") | T39: =IF(W39<>"",IF(E39<>"",E39,($I$9-SUM($T$25:T38))*V39*W39/SUMPRODUCT($W39:$W$55,$V39:$V$55)),"") | U39: =IF(W39<>"",IF($I$12<>"",IF(G39<>"",G39,($I$9/$I$12-SUM($U$25:U38))*V39*W39/SUMPRODUCT($W39:$W$55,$V39:$V$55)),""),"")
F40: =IF(AND(E40<>"",E40<>0),D40/E40,"") | H40: =IF(AND(G40<>"",G40<>0),D40/G40,"") | J40: =IF(AND(G40<>"",G40<>0),E40/G40,"") | N40: =IF(AND(I40<>"",I40<>0),G40/I40,"") | O40: =D40/P40 -> #DIV/0! | P40: =$I$8*V40*W40/SUMPRODUCT($W$25:$W$47,$V$25:$V$47) -> 0 | Q40: =$I$9*V40*W40/SUMPRODUCT($W$25:$W$47,$V$25:$V$47) -> 0 | R40: =IF($I$12="", "", Q40/$I$12) -> 0 | S40: =IF(W40<>"",IF(D40<>"",D40,($I$8-SUM($S$25:S39))*V40*W40/SUMPRODUCT($W40:$W$55,$V40:$V$55)),"") | T40: =IF(W40<>"",IF(E40<>"",E40,($I$9-SUM($T$25:T39))*V40*W40/SUMPRODUCT($W40:$W$55,$V40:$V$55)),"") | U40: =IF(W40<>"",IF($I$12<>"",IF(G40<>"",G40,($I$9/$I$12-SUM($U$25:U39))*V40*W40/SUMPRODUCT($W40:$W$55,$V40:$V$55)),""),"")
F41: =IF(AND(E41<>"",E41<>0),D41/E41,"") | H41: =IF(AND(G41<>"",G41<>0),D41/G41,"") | J41: =IF(AND(G41<>"",G41<>0),E41/G41,"") | N41: =IF(AND(I41<>"",I41<>0),G41/I41,"") | O41: =D41/P41 -> #DIV/0! | P41: =$I$8*V41*W41/SUMPRODUCT($W$25:$W$47,$V$25:$V$47) -> 0 | Q41: =$I$9*V41*W41/SUMPRODUCT($W$25:$W$47,$V$25:$V$47) -> 0 | R41: =IF($I$12="", "", Q41/$I$12) -> 0 | S41: =IF(W41<>"",IF(D41<>"",D41,($I$8-SUM($S$25:S40))*V41*W41/SUMPRODUCT($W41:$W$55,$V41:$V$55)),"") | T41: =IF(W41<>"",IF(E41<>"",E41,($I$9-SUM($T$25:T40))*V41*W41/SUMPRODUCT($W41:$W$55,$V41:$V$55)),"") | U41: =IF(W41<>"",IF($I$12<>"",IF(G41<>"",G41,($I$9/$I$12-SUM($U$25:U40))*V41*W41/SUMPRODUCT($W41:$W$55,$V41:$V$55)),""),"")
F42: =IF(AND(E42<>"",E42<>0),D42/E42,"") | H42: =IF(AND(G42<>"",G42<>0),D42/G42,"") | J42: =IF(AND(G42<>"",G42<>0),E42/G42,"") | N42: =IF(AND(I42<>"",I42<>0),G42/I42,"") | O42: =D42/P42 -> #DIV/0! | P42: =$I$8*V42*W42/SUMPRODUCT($W$25:$W$47,$V$25:$V$47) -> 0 | Q42: =$I$9*V42*W42/SUMPRODUCT($W$25:$W$47,$V$25:$V$47) -> 0 | R42: =IF($I$12="", "", Q42/$I$12) -> 0 | S42: =IF(W42<>"",IF(D42<>"",D42,($I$8-SUM($S$25:S41))*V42*W42/SUMPRODUCT($W42:$W$55,$V42:$V$55)),"") | T42: =IF(W42<>"",IF(E42<>"",E42,($I$9-SUM($T$25:T41))*V42*W42/SUMPRODUCT($W42:$W$55,$V42:$V$55)),"") | U42: =IF(W42<>"",IF($I$12<>"",IF(G42<>"",G42,($I$9/$I$12-SUM($U$25:U41))*V42*W42/SUMPRODUCT($W42:$W$55,$V42:$V$55)),""),"")
F43: =IF(AND(E43<>"",E43<>0),D43/E43,"") | H43: =IF(AND(G43<>"",G43<>0),D43/G43,"") | J43: =IF(AND(G43<>"",G43<>0),E43/G43,"") | N43: =IF(AND(I43<>"",I43<>0),G43/I43,"") | O43: =D43/P43 -> #DIV/0! | P43: =$I$8*V43*W43/SUMPRODUCT($W$25:$W$44, $V$25:$V$44) -> 0 | Q43: =$I$9*V43*W43/SUMPRODUCT($W$25:$W$44, $V$25:$V$44) -> 0 | R43: =IF($I$12="", "", Q43/$I$12) -> 0 | S43: =IF(W43<>"",IF(D43<>"",D43,($I$8-SUM($S$25:S42))*V43*W43/SUMPRODUCT($W43:$W$55,$V43:$V$55)),"") | T43: =IF(W43<>"",IF(E43<>"",E43,($I$9-SUM($T$25:T42))*V43*W43/SUMPRODUCT($W43:$W$55,$V43:$V$55)),"") | U43: =IF(W43<>"",IF($I$12<>"",IF(G43<>"",G43,($I$9/$I$12-SUM($U$25:U42))*V43*W43/SUMPRODUCT($W43:$W$55,$V43:$V$55)),""),"")
F44: =IF(AND(E44<>"",E44<>0),D44/E44,"") | H44: =IF(AND(G44<>"",G44<>0),D44/G44,"") | J44: =IF(AND(G44<>"",G44<>0),E44/G44,"") | N44: =IF(AND(I44<>"",I44<>0),G44/I44,"") | O44: =D44/P44 -> #DIV/0! | P44: =$I$8*V44*W44/SUMPRODUCT($W$25:$W$44, $V$25:$V$44) -> 0 | Q44: =$I$9*V44*W44/SUMPRODUCT($W$25:$W$44, $V$25:$V$44) -> 0 | R44: =IF($I$12="", "", Q44/$I$12) -> 0 | S44: =IF(W44<>"",IF(D44<>"",D44,($I$8-SUM($S$25:S43))*V44*W44/SUMPRODUCT($W44:$W$55,$V44:$V$55)),"") | T44: =IF(W44<>"",IF(E44<>"",E44,($I$9-SUM($T$25:T43))*V44*W44/SUMPRODUCT($W44:$W$55,$V44:$V$55)),"") | U44: =IF(W44<>"",IF($I$12<>"",IF(G44<>"",G44,($I$9/$I$12-SUM($U$25:U43))*V44*W44/SUMPRODUCT($W44:$W$55,$V44:$V$55)),""),"")
F45: =IF(AND(E45<>"",E45<>0),D45/E45,"") | H45: =IF(AND(G45<>"",G45<>0),D45/G45,"") | J45: =IF(AND(G45<>"",G45<>0),E45/G45,"") | N45: =IF(AND(I45<>"",I45<>0),G45/I45,"") | O45: =D45/P45 -> #DIV/0! | P45: =$I$8*V45*W45/SUMPRODUCT($W$25:$W$44, $V$25:$V$44) -> 0 | Q45: =$I$9*V45*W45/SUMPRODUCT($W$25:$W$44, $V$25:$V$44) -> 0 | R45: =IF($I$12="", "", Q45/$I$12) -> 0 | S45: =IF(W45<>"",IF(D45<>"",D45,($I$8-SUM($S$25:S44))*V45*W45/SUMPRODUCT($W45:$W$55,$V45:$V$55)),"") | T45: =IF(W45<>"",IF(E45<>"",E45,($I$9-SUM($T$25:T44))*V45*W45/SUMPRODUCT($W45:$W$55,$V45:$V$55)),"") | U45: =IF(W45<>"",IF($I$12<>"",IF(G45<>"",G45,($I$9/$I$12-SUM($U$25:U44))*V45*W45/SUMPRODUCT($W45:$W$55,$V45:$V$55)),""),"")
F46: =IF(AND(E46<>"",E46<>0),D46/E46,"") | H46: =IF(AND(G46<>"",G46<>0),D46/G46,"") | J46: =IF(AND(G46<>"",G46<>0),E46/G46,"") | N46: =IF(AND(I46<>"",I46<>0),G46/I46,"") | O46: =D46/P46 -> #DIV/0! | P46: =$I$8*V46*W46/SUMPRODUCT($W$25:$W$44, $V$25:$V$44) -> 0 | Q46: =$I$9*V46*W46/SUMPRODUCT($W$25:$W$44, $V$25:$V$44) -> 0 | R46: =IF($I$12="", "", Q46/$I$12) -> 0 | S46: =IF(W46<>"",IF(D46<>"",D46,($I$8-SUM($S$25:S45))*V46*W46/SUMPRODUCT($W46:$W$55,$V46:$V$55)),"") | T46: =IF(W46<>"",IF(E46<>"",E46,($I$9-SUM($T$25:T45))*V46*W46/SUMPRODUCT($W46:$W$55,$V46:$V$55)),"") | U46: =IF(W46<>"",IF($I$12<>"",IF(G46<>"",G46,($I$9/$I$12-SUM($U$25:U45))*V46*W46/SUMPRODUCT($W46:$W$55,$V46:$V$55)),""),"")
F47: =IF(AND(E47<>"",E47<>0),D47/E47,"") | H47: =IF(AND(G47<>"",G47<>0),D47/G47,"") | J47: =IF(AND(G47<>"",G47<>0),E47/G47,"") | N47: =IF(AND(I47<>"",I47<>0),G47/I47,"") | O47: =D47/P47 -> #DIV/0! | P47: =$I$8*V47*W47/SUMPRODUCT($W$25:$W$55,$V$25:$V$55) -> 0 | Q47: =$I$9*V47*W47/SUMPRODUCT($W$25:$W$55,$V$25:$V$55) -> 0 | R47: =IF($I$12="","",Q47/$I$12) -> 0 | S47: =IF(W47<>"",IF(D47<>"",D47,($I$8-SUM($S$25:S46))*V47*W47/SUMPRODUCT($W47:$W$55,$V47:$V$55)),"") | T47: =IF(W47<>"",IF(E47<>"",E47,($I$9-SUM($T$25:T46))*V47*W47/SUMPRODUCT($W47:$W$55,$V47:$V$55)),"") | U47: =IF(W47<>"",IF($I$12<>"",IF(G47<>"",G47,($I$9/$I$12-SUM($U$25:U46))*V47*W47/SUMPRODUCT($W47:$W$55,$V47:$V$55)),""),"")
B48: итого | D48: =SUM(D25:D47) -> 219302.1 | E48: =SUM(E25:E47) -> 70 | F48: =IF(AND(E48<>"",E48<>0),D48/E48,"") -> 3132.8871 | G48: =SUM(G25:G47) -> 33 | H48: =IF(AND(G48<>"",G48<>0),D48/G48,"") -> 6645.5182 | I48: =SUM(I25:I47) -> 0 | J48: =IF(AND(G48<>"",G48<>0),E48/G48,"") -> 2.1212121 | K48: =SUM(K25:K47) -> 0 | L48: =SUM(L25:L47) -> 0 | M48: =SUM(M25:M47) -> 0 | N48: =IF(AND(I48<>"",I48<>0),G48/I48,"") | O48: =D48/P48 -> #DIV/0! | P48: =SUM(P25:P47) -> 0 | Q48: =SUM(Q25:Q47) -> 0 | R48: =SUM(R25:R47) -> 0 | S48: =SUM(S25:S47) -> 0 | T48: =SUM(T25:T47) -> 0 | U48: =SUM(U25:U47) -> 0
D49: =SUMIF(D25:D47,"",P25:P47)+D48 -> 219302.1

Sheet График
B1: Январь, 2025 | T1: в
B2: г. Ялта
B3: ул. Набережная Ленина, 18
B4: GL-0005
B5: 10.00-21.00
B6: ФОТ | C6: Кол-во дней в месяц | AK6: 30
B7: =BT31*100/BH31 -> #DIV/0!
D8: ср | E8: чт | F8: пт | G8: сб | H8: вс | I8: пн | J8: вт | K8: ср | L8: чт | M8: пт | N8: сб | O8: вс | P8: пн | Q8: вт | R8: ср | S8: чт | T8: пт | U8: сб | V8: вс | W8: пн | X8: вт | Y8: ср | Z8: чт | AA8: пт | AB8: сб | AC8: вс | AD8: пн | AE8: вт | AF8: ср | AG8: чт | AH8: пт | AJ8: Часы | AK8: Выходные | AL8: Отпуск | AM8: Больничный (официальный) | AN8: Дни стажировки
A10: № | B10: ФИО | C10: Должность | D10: 1 | E10: 2 | F10: 3 | G10: 4 | H10: 5 | I10: 6 | J10: 7 | K10: 8 | L10: 9 | M10: 10 | N10: 11 | O10: 12 | P10: 13 | Q10: 14 | R10: 15 | S10: 16 | T10: 17 | U10: 18 | V10: 19 | W10: 20 | X10: 21 | Y10: 22 | Z10: 23 | AA10: 24 | AB10: 25 | AC10: 26 | AD10: 27 | AE10: 28 | AF10: 29 | AG10: 30 | AH10: 31 | AI10: Дни
A11: 20 | AI11: 0 | AJ11: 0 | AK11: 0 | AL11: 0 | AM11: 0 | AN11: 0
A12: 19 | AI12: 0 | AJ12: 0 | AK12: 0 | AL12: 0 | AM12: 0 | AN12: 0
A13: 18 | AI13: 0 | AJ13: 0 | AK13: 0 | AL13: 0 | AM13: 0 | AN13: 0
A14: 17 | AI14: 0 | AJ14: 0 | AK14: 0 | AL14: 0 | AM14: 0 | AN14: 0
A15: 16 | AI15: 0 | AJ15: 0 | AK15: 0 | AL15: 0 | AM15: 0 | AN15: 0
A16: 15 | AI16: 0 | AJ16: 0 | AK16: 0 | AL16: 0 | AM16: 0 | AN16: 0
A17: 14 | AI17: 0 | AJ17: 0 | AK17: 0 | AL17: 0 | AM17: 0 | AN17: 0
A18: 13 | AI18: 0 | AJ18: 0 | AK18: 0 | AL18: 0 | AM18: 0 | AN18: 0
A19: 12 | AI19: 0 | AJ19: 0 | AK19: 0 | AL19: 0 | AM19: 0 | AN19: 0
A20: 11 | AI20: 0 | AJ20: 0 | AK20: 0 | AL20: 0 | AM20: 0 | AN20: 0
A21: 10 | AI21: 0 | AJ21: 0 | AK21: 0 | AL21: 0 | AM21: 0 | AN21: 0
A22: 9 | AI22: =COUNTIF(D22:AH22, ">0") -> 0 | AJ22: 0 | AK22: 0 | AL22: 0 | AM22: 0 | AN22: 0
A23: 8 | AI23: =COUNTIF(D23:AH23, ">0") -> 0 | AJ23: 0 | AK23: 0 | AL23: 0 | AM23: 0 | AN23: 0
A24: 7 | AI24: =COUNTIF(D24:AH24, ">0") -> 0 | AJ24: 0 | AK24: 0 | AL24: 0 | AM24: 0 | AN24: 0
A25: 6 | AI25: =COUNTIF(D25:AH25,">0") -> 0 | AJ25: =SUMIF(D25:AH25,">0") -> 0 | AK25: =COUNTIF(D25:AH25,"В") -> 0 | AL25: =COUNTIF(E25:AI25,"о") -> 0 | AM25: =COUNTIF(F25:AJ25,"б") -> 0 | AN25: 0
A26: 5 | B26: Орешникова Елена | D26: в | E26: 7 | F26: 9 | G26: 9 | H26: 9 | I26: 11 | AI26: =COUNTIF(D26:AH26, ">0") -> 5 | AJ26: =SUMIF(D26:AH26, ">0") -> 45 | AK26: =COUNTIF(D26:AH26, "В") -> 1 | AL26: 0 | AM26: 0 | AN26: 0
A27: 4 | AI27: =COUNTIF(D27:AH27,">0") -> 0 | AJ27: =SUMIF(D27:AH27,">0") -> 0 | AK27: =COUNTIF(D27:AH27,"В") -> 0 | AL27: =COUNTIF(E27:AI27,"о") -> 0 | AM27: =COUNTIF(F27:AJ27,"б") -> 0 | AN27: 0
A28: 3 | B28: Стекольщикова Алла | C28: ДМ | D28: в | K28: 10 | L28: 11 | M28: 11 | N28: 9 | AH28: 11 | AI28: =COUNTIF(D28:AH28,">0") -> 5 | AJ28: =SUMIF(D28:AH28,">0") -> 52 | AK28: =COUNTIF(D28:AH28,"В") -> 1 | AL28: =COUNTIF(E28:AI28,"о") -> 0 | AM28: =COUNTIF(F28:AJ28,"б") -> 0 | AN28: 0
A29: 2 | B29: Рогалевич Ирина | C29: ПК | D29: в | E29: в | I29: 10 | J29: 11 | K29: 11 | L29: 11 | M29: 11 | N29: 11 | O29: в | P29: 11 | Q29: 11 | R29: 10 | S29: 9 | T29: 9 | U29: 11 | V29: 11 | W29: в | X29: 9 | Y29: 11 | Z29: 11 | AA29: 11 | AB29: 11 | AC29: 11 | AD29: 11 | AE29: 11 | AF29: 11 | AG29: 11 | AH29: 11 | AI29: =COUNTIF(D29:AH29,">0") -> 24 | AJ29: =SUMIF(D29:AH29,">0") -> 256 | AK29: =COUNTIF(D29:AH29,"В") -> 4 | AL29: =COUNTIF(E29:AI29,"о") -> 0 | AM29: =COUNTIF(F29:AJ29,"б") -> 0 | AN29: 0
A30: 1 | B30: Кекош Анна | C30: ПК | D30: в | E30: 11 | F30: 11 | G30: 11 | H30: 11 | I30: в | J30: в | K30: 11 | L30: в | M30: 11 | N30: 11 | O30: 11 | P30: в | Q30: 9 | R30: 11 | S30: 9 | T30: 9 | U30: в | V30: в | W30: 11 | X30: 9 | Y30: 2 | Z30: у | AA30: у | AB30: у | AC30: у | AD30: у | AE30: у | AF30: у | AG30: у | AH30: у | AI30: =COUNTIF(D30:AH30, ">0") -> 15 | AJ30: =SUMIF(D30:AH30, ">0") -> 148 | AK30: =COUNTIF(D30:AH30, "В") -> 7 | AL30: =COUNTIF(E30:AI30, "о") -> 0 | AM30: =COUNTIF(F30:AJ30, "б") -> 0 | AN30: 0
B31: Итого магазин | D31: =COUNTIF(D11:D30, ">0") -> 0 | E31: =COUNTIF(E11:E30, ">0") -> 2 | F31: =COUNTIF(F11:F30, ">0") -> 2 | G31: =COUNTIF(G11:G30, ">0") -> 2 | H31: =COUNTIF(H11:H30, ">0") -> 2 | I31: =COUNTIF(I11:I30, ">0") -> 2 | J31: =COUNTIF(J11:J30, ">0") -> 1 | K31: =COUNTIF(K11:K29, ">0") -> 2 | L31: =COUNTIF(L11:L30, ">0") -> 2 | M31: =COUNTIF(M11:M30, ">0") -> 3 | N31: =COUNTIF(N11:N30, ">0") -> 3 | O31: =COUNTIF(O11:O30, ">0") -> 1 | P31: =COUNTIF(P11:P30, ">0") -> 1 | Q31: =COUNTIF(Q11:Q30, ">0") -> 2 | R31: =COUNTIF(R11:R30, ">0") -> 2 | S31: =COUNTIF(S11:S30, ">0") -> 2 | ... AH31: =COUNTIF(AH11:AH30, ">0") -> 2 | AI31: =SUM(AI11:AI30) -> 49 | AJ31: =SUM(AJ11:AJ30) -> 501 | AK31: =SUM(AK11:AK30) -> 13 | AL31: =SUM(AL11:AL30) -> 0 | AM31: =SUM(AM11:AM30) -> 0 | AN31: =SUM(AN11:AN30) -> 0
