Workbook
Name маг: NA()

Sheet Центрум
A1: =TODAY()-1 -> 46151
A2: (01.03.2026-31.03.2026) | I2: ЕЖЕДНЕВНЫЙ ОТЧЕТ О ПРОДАЖАХ
C3: Осталось до выполнения плана!!! | I3: ТРК Центрум
C4: =I8-D56 -> 622617 | E4: =IF(I8<>0,C4/I8,0) -> 0.33174393
F6: Целевые показатели
F7: Показатель | I7: План | J7: Факт | K7: % выполнения | L7: Прогноз выполнения | M7: % выполнения по прогнозу | N7: Отклонение | O7: Факт аналогичного месяца прошлого года | P7: Отклонение LFL
F8: Выручка | I8: =I13*I10 -> 1876800 | J8: =D56 -> 1254183 | K8: =IF(AND(I8<>"",I8<>0,J8<>""),J8/I8,"") -> 0.66825607 | L8: =IF(SUMIF($D$25:$D$55,">=0",$V$25:$V$55)<>0,I8*D56/SUMIF($D$25:$D$55,">=0",$V$25:$V$55),0) -> 1254183 | M8: =L8/I8 -> 0.66825607 | N8: =IF(AND(J8<>0,J8<>"",I8<>0,I8<>""),L8-I8,"") -> -622617 | P8: =IF(AND(O8<>"",O8<>0,L8<>"",L8<>0),-O8+L8,"") | Q8: =IF(AND(O8<>"",O8<>0,N8<>0,N8<>""),O8/N8,"")
F9: Кол-во изделий | I9: =I8/I11 -> 272 | J9: =E56 -> 159 | K9: =IF(AND(I9<>"",I9<>0,J9<>""),J9/I9,"") -> 0.58455882 | L9: =IF(SUMIF($E$25:$E$55,">=0",$W$25:$W$55)<>0,I9*E56/SUMIF($E$25:$E$55,">=0",$W$25:$W$55),0) -> 159 | M9: =IF(AND(I9<>"",I9<>0,L9<>"",L9<>0),L9/I9,"") -> 0.58455882 | N9: =IF(AND(J9<>0,J9<>"",I9<>0,I9<>""),L9-I9,"") -> -113 | P9: =IF(AND(O9<>"",O9<>0,L9<>"",L9<>0),-O9+L9,"") | Q9: =IF(AND(O9<>"",O9<>0,N9<>0,N9<>""),O9/N9,"")
F10: Средний чек | I10: =I11*I12 -> 11730 | J10: =H56 -> 15677.288 | K10: =IF(AND(I10<>"",I10<>0,J10<>""),J10/I10,"") -> 1.3365121 | L10: =J10 -> 15677.288 | M10: =IF(AND(I10<>"",I10<>0,L10<>"",L10<>0),L10/I10,"") -> 1.3365121 | N10: =IF(AND(J10<>0,J10<>"",I10<>0,I10<>""),L10-I10,"") -> 3947.2875 | P10: =IF(AND(O10<>"",O10<>0,L10<>"",L10<>0),-O10+L10,"") | Q10: =IF(AND(O10<>"",O10<>0,N10<>0,N10<>""),O10/N10,"")
F11: Средняя стоимость изделия | I11: 6900 | J11: =F56 -> 7887.9434 | K11: =IF(AND(I11<>"",I11<>0,J11<>""),J11/I11,"") -> 1.1431802 | L11: =IF(L9>0,L8/L9,"") -> 7887.9434 | M11: =IF(AND(I11<>"",I11<>0,L11<>"",L11<>0),L11/I11,"") -> 1.1431802 | N11: =IF(AND(J11<>0,J11<>"",I11<>0,I11<>""),L11-I11,"") -> 987.9434 | P11: =IF(AND(O11<>"",O11<>0,L11<>"",L11<>0),-O11+L11,"") | Q11: =IF(AND(O11<>"",O11<>0,N11<>0,N11<>""),O11/N11,"")
F12: Длина чека | I12: 1.7 | J12: =J56 -> 1.9875 | K12: =IF(AND(I12<>"",I12<>0,J12<>""),J12/I12,"") -> 1.1691176 | L12: =J12 -> 1.9875 | M12: =IF(AND(I12<>"",I12<>0,L12<>"",L12<>0),L12/I12,"") -> 1.1691176 | N12: =IF(AND(J12<>0,J12<>"",I12<>0,I12<>""),L12-I12,"") -> 0.2875 | P12: =IF(AND(O12<>"",O12<>0,L12<>"",L12<>0),-O12+L12,"") | Q12: =IF(AND(O12<>"",O12<>0,N12<>0,N12<>""),O12/N12,"")
F13: Кол-во чеков | I13: =I17*I20 -> 160 | J13: =G56 -> 80 | K13: =IF(AND(I13<>"",I13<>0,J13<>""),J13/I13,"") -> 0.5 | L13: =IF(SUMIF($G$25:$G$55,">=0",$X$25:$X$55)<>0,I13*G56/SUMIF($G$25:$G$55,">=0",$X$25:$X$55),"") -> 80 | M13: =IF(AND(I13<>"",I13<>0,L13<>"",L13<>0),L13/I13,"") -> 0.5 | N13: =IF(AND(J13<>0,J13<>"",I13<>0,I13<>""),L13-I13,"") -> -80 | P13: =IF(AND(O13<>"",O13<>0,L13<>"",L13<>0),-O13+L13,"") | Q13: =IF(AND(O13<>"",O13<>0,N13<>0,N13<>""),O13/N13,"")
F14: Кол-во смен | I14: 30 | J14: 30 | K14: =IF(AND(I14<>"",I14<>0,J14<>""),J14/I14,"") -> 1 | L14: =IF(SUMIF($D$25:$D$55,">=0",$V$25:$V$55),I56*I8/SUMIF($D$25:$D$55,">=0",$V$25:$V$55),"") -> 1041.25 | N14: =IF(AND(J14<>0,J14<>"",I14<>0,I14<>""),L14-I14,"") -> 1011.25 | P14: =IF(AND(O14<>"",O14<>0,L14<>"",L14<>0),-O14+L14,"") | Q14: =IF(AND(O14<>"",O14<>0,N14<>0,N14<>""),O14/N14,"")
F15: Средние продажи в смену | I15: =I8/I14 -> 62560 | J15: =J8/J14 -> 41806.1 | K15: =IF(AND(I15<>"",I15<>0,J15<>""),J15/I15,"") -> 0.66825607 | L15: =J15 -> 41806.1 | M15: =IF(AND(I15<>"",I15<>0,L15<>"",L15<>0),L15/I15,"") -> 0.66825607 | N15: =IF(AND(J15<>0,J15<>"",I15<>0,I15<>""),L15-I15,"") -> -20753.9 | P15: =IF(AND(O15<>"",O15<>0,L15<>"",L15<>0),-O15+L15,"") | Q15: =IF(AND(O15<>"",O15<>0,N15<>0,N15<>""),O15/N15,"")
F16: Отставание/Перевыполнение | J16: =J8-I15*J14 -> -622617 | K16: =IF(AND(I16<>"",I16<>0,J16<>""),J16/I16,"") | L16: =J16 -> -622617 | M16: =IF(AND(I16<>"",I16<>0,L16<>"",L16<>0),L16/I16,"") | N16: =IF(AND(J16<>0,J16<>"",I16<>0,I16<>""),L16-I16,"") | P16: =IF(AND(O16<>"",O16<>0,L16<>"",L16<>0),-O16+L16,"") | Q16: =IF(AND(O16<>"",O16<>0,N16<>0,N16<>""),O16/N16,"") | S16: Подарочные сертификаты
F17: Трафик | I17: 1600 | J17: =I56 -> 1041.25 | K17: =IF(AND(I17<>"",I17<>0,J17<>""),J17/I17,"") -> 0.65078125 | L17: =J17/J14*I14 -> 1041.25 | M17: =IF(AND(I17<>"",I17<>0,L17<>"",L17<>0),L17/I17,"") -> 0.65078125 | N17: =IF(AND(J17<>0,J17<>"",I17<>0,I17<>""),L17-I17,"") -> -558.75 | P17: =IF(AND(O17<>"",O17<>0,L17<>"",L17<>0),-O17+L17,"") | Q17: =IF(AND(O17<>"",O17<>0,N17<>0,N17<>""),O17/N17,"")
F18: Выручка на вошедшего | I18: =I8/I17 -> 1173 | J18: =J8/J17 -> 1204.4975 | K18: =IF(AND(I18<>"",I18<>0,J18<>""),J18/I18,"") -> 1.0268521 | L18: =J18 -> 1204.4975 | M18: =IF(AND(I18<>"",I18<>0,L18<>"",L18<>0),L18/I18,"") -> 1.0268521 | N18: =IF(AND(J18<>0,J18<>"",I18<>0,I18<>""),L18-I18,"") -> 31.497479 | P18: =IF(AND(O18<>"",O18<>0,L18<>"",L18<>0),-O18+L18,"") | Q18: =IF(AND(O18<>"",O18<>0,N18<>0,N18<>""),O18/N18,"")
K19: =IF(AND(I19<>"",I19<>0,J19<>""),J19/I19,"") | L19: =J19 -> 0 | M19: =IF(AND(I19<>"",I19<>0,L19<>"",L19<>0),L19/I19,"") | N19: =IF(AND(J19<>0,J19<>"",I19<>0,I19<>""),L19-I19,"") | O19: 0 | P19: =IF(AND(O19<>"",O19<>0,L19<>"",L19<>0),-O19+L19,"") | Q19: =IF(AND(O19<>"",O19<>0,N19<>0,N19<>""),O19/N19,"") | S19: =S18/I16 -> #DIV/0!
F20: Конверсия | I20: 0.1 | J20: =T56 -> 0.076830732 | K20: =J20/I20 -> 0.76830732 | L20: =J20/I20 -> 0.76830732 | M20: =J20/I20 -> 0.76830732 | N20: =IF(AND(J20<>0,J20<>"",I20<>0,I20<>""),L20-I20,"") -> 0.66830732 | P20: =IF(AND(O20<>"",O20<>0,L20<>"",L20<>0),-O20+L20,"") | Q20: =IF(AND(O20<>"",O20<>0,N20<>0,N20<>""),O20/N20,"")
A22: Факт продаж за месяц | U22: % выполнения дневного плана | V22: Раcпределение плана по дням
A23: Сотрудник | B23: Дата | C23: День недели | D23: Выручка (руб) | E23: Кол-во единиц (шт.) | F23: Средняя стоимость изделия (руб.) | G23: Количество чеков (шт.) | H23: Средняя сумма чека (руб.) | I23: Трафик | J23: Длина чека (шт.) | K23: UNOde50 | L23: IS | M23: Agafi | N23: Kalliope | O23: Raganella | P23: CC/MP | Q23: Eva Rites | R23: Antura | S23: SALE | T23: Конверсия (%) | V23: выручка, план | W23: кол-во ед, план | X23: Кол-во чеков, план | Y23: выручка, скорректир.план | Z23: кол-во ед, скорр. план | AA23: кол-во чеков, скорр. план | AB23: Коэфф. Дня Недели | AC23: Специфика месяца
B24: 1 | C24: 2 | D24: 3 | E24: 4 | F24: 5 | H24: 7 | J24: 9 | K24: 10 | L24: 11 | M24: 12 | N24: 13 | O24: 14 | P24: 15 | Q24: 16 | R24: 17 | T24: 13 | V24: 1 | W24: 2 | X24: 3 | Y24: 4 | Z24: 5 | AA24: 6 | AB24: 10 | AC24: 11
A25: Маркова | B25: 46113 | C25: ср | D25: 27636 | E25: 6 | F25: =IF(AND(E25<>"",E25<>0),D25/E25,"") -> 4606 | G25: 4 | H25: =IF(AND(G25<>"",G25<>0),D25/G25,"") -> 6909 | I25: 35 | J25: =IF(AND(G25<>"",G25<>0),E25/G25,"") -> 1.5 | T25: =IF(AND(I25<>"",I25<>0),G25/I25,"") -> 0.11428571 | U25: =D25/V25 -> 0.32151463 | V25: =$I$8*AB25*AC25/SUMPRODUCT($AC$25:$AC$55,$AB$25:$AB$55) -> 85955.654 | W25: =$I$9*AB25*AC25/SUMPRODUCT($AC$25:$AC$55,$AB$25:$AB$55) -> 12.457341 | X25: =IF($I$12="","",W25/$I$12) -> 7.3278478 | Y25: =IF(D25<>"",D25,V25) -> 27636 | Z25: =IF(E25<>"",E25,W25) -> 6 | AA25: =IF(G25<>"",G25,X25) -> 4 | AB25: 1 | AC25: 0.75349421
A26: Бешлиева | B26: 46114 | C26: чт | D26: 29523 | E26: 3 | F26: =IF(AND(E26<>"",E26<>0),D26/E26,"") -> 9841 | G26: 2 | H26: =IF(AND(G26<>"",G26<>0),D26/G26,"") -> 14761.5 | I26: 40 | J26: =IF(AND(G26<>"",G26<>0),E26/G26,"") -> 1.5 | P26: 12391 | T26: =IF(AND(I26<>"",I26<>0),G26/I26,"") -> 0.05 | U26: =D26/V26 -> 0.19321479 | V26: =$I$8*AB26*AC26/SUMPRODUCT($AC$25:$AC$55,$AB$25:$AB$55) -> 152798.86 | W26: =$I$9*AB26*AC26/SUMPRODUCT($AC$25:$AC$55,$AB$25:$AB$55) -> 22.144763 | X26: =IF($I$12="","",W26/$I$12) -> 13.026331 | Y26: =IF(AB26<>"",IF(D26<>"",D26,($I$8-SUM($Y$25:Y25))*AA26*AB26/SUMPRODUCT($AB26:$AB$55,$AA26:$AA$55)),"") -> 29523 | Z26: =IF(AC26<>"",IF(E26<>"",E26,($I$9-SUM($Z$25:Z25))*AB26*AC26/SUMPRODUCT($AC26:$AC$55,$AB26:$AB$55)),"") -> 3 | AA26: =IF(AC26<>"",IF($I$12<>"",IF(G26<>"",G26,($I$9/$I$12-SUM($AA$25:AA25))*AB26*AC26/SUMPRODUCT($AC26:$AC$55,$AB26:$AB$55)),""),"") -> 2 | AB26: 1 | AC26: 1.3394472
A27: Бешлиева | B27: 46115 | C27: пт | D27: 14876 | E27: 3 | F27: =IF(AND(E27<>"",E27<>0),D27/E27,"") -> 4958.6667 | G27: 2 | H27: =IF(AND(G27<>"",G27<>0),D27/G27,"") -> 7438 | I27: 44 | J27: =IF(AND(G27<>"",G27<>0),E27/G27,"") -> 1.5 | T27: =IF(AND(I27<>"",I27<>0),G27/I27,"") -> 0.045454545 | U27: =D27/V27 -> 0.080452006 | V27: =$I$8*AB27*AC27/SUMPRODUCT($AC$25:$AC$55,$AB$25:$AB$55) -> 184905.27 | W27: =$I$9*AB27*AC27/SUMPRODUCT($AC$25:$AC$55,$AB$25:$AB$55) -> 26.797865 | X27: =IF($I$12="","",W27/$I$12) -> 15.76345 | Y27: =IF(AB27<>"",IF(D27<>"",D27,($I$8-SUM($Y$25:Y26))*AA27*AB27/SUMPRODUCT($AB27:$AB$55,$AA27:$AA$55)),"") -> 14876 | Z27: =IF(AC27<>"",IF(E27<>"",E27,($I$9-SUM($Z$25:Z26))*AB27*AC27/SUMPRODUCT($AC27:$AC$55,$AB27:$AB$55)),"") -> 3 | AA27: =IF(AC27<>"",IF($I$12<>"",IF(G27<>"",G27,($I$9/$I$12-SUM($AA$25:AA26))*AB27*AC27/SUMPRODUCT($AC27:$AC$55,$AB27:$AB$55)),""),"") -> 2 | AB27: 1 | AC27: 1.6208945
A28: Маркова | B28: 46116 | C28: сб | D28: 30939 | E28: 5 | F28: =IF(AND(E28<>"",E28<>0),D28/E28,"") -> 6187.8 | G28: 4 | H28: =IF(AND(G28<>"",G28<>0),D28/G28,"") -> 7734.75 | I28: 51 | J28: =IF(AND(G28<>"",G28<>0),E28/G28,"") -> 1.25 | S28: 4263 | T28: =IF(AND(I28<>"",I28<>0),G28/I28,"") -> 0.078431373 | U28: =D28/V28 -> 0.28181778 | V28: =$I$8*AB28*AC28/SUMPRODUCT($AC$25:$AC$55,$AB$25:$AB$55) -> 109783.71 | W28: =$I$9*AB28*AC28/SUMPRODUCT($AC$25:$AC$55,$AB$25:$AB$55) -> 15.910682 | X28: =IF($I$12="","",W28/$I$12) -> 9.3592248 | Y28: =IF(AB28<>"",IF(D28<>"",D28,($I$8-SUM($Y$25:Y27))*AA28*AB28/SUMPRODUCT($AB28:$AB$55,$AA28:$AA$55)),"") -> 30939 | Z28: =IF(AC28<>"",IF(E28<>"",E28,($I$9-SUM($Z$25:Z27))*AB28*AC28/SUMPRODUCT($AC28:$AC$55,$AB28:$AB$55)),"") -> 5 | AA28: =IF(AC28<>"",IF($I$12<>"",IF(G28<>"",G28,($I$9/$I$12-SUM($AA$25:AA27))*AB28*AC28/SUMPRODUCT($AC28:$AC$55,$AB28:$AB$55)),""),"") -> 4 | AB28: 1 | AC28: 0.96237284
A29: Маркова | B29: 46117 | C29: вс | D29: 18674 | E29: 3 | F29: =IF(AND(E29<>"",E29<>0),D29/E29,"") -> 6224.6667 | G29: 3 | H29: =IF(AND(G29<>"",G29<>0),D29/G29,"") -> 6224.6667 | I29: 34 | J29: =IF(AND(G29<>"",G29<>0),E29/G29,"") -> 1 | T29: =IF(AND(I29<>"",I29<>0),G29/I29,"") -> 0.088235294 | U29: =D29/V29 -> 0.25177848 | V29: =$I$8*AB29*AC29/SUMPRODUCT($AC$25:$AC$55,$AB$25:$AB$55) -> 74168.373 | W29: =$I$9*AB29*AC29/SUMPRODUCT($AC$25:$AC$55,$AB$25:$AB$55) -> 10.74904 | X29: =IF($I$12="","",W29/$I$12) -> 6.3229644 | Y29: =IF(AB29<>"",IF(D29<>"",D29,($I$8-SUM($Y$25:Y28))*AA29*AB29/SUMPRODUCT($AB29:$AB$55,$AA29:$AA$55)),"") -> 18674 | Z29: =IF(AC29<>"",IF(E29<>"",E29,($I$9-SUM($Z$25:Z28))*AB29*AC29/SUMPRODUCT($AC29:$AC$55,$AB29:$AB$55)),"") -> 3 | AA29: =IF(AC29<>"",IF($I$12<>"",IF(G29<>"",G29,($I$9/$I$12-SUM($AA$25:AA28))*AB29*AC29/SUMPRODUCT($AC29:$AC$55,$AB29:$AB$55)),""),"") -> 3 | AB29: 1 | AC29: 0.65016595
A30: Маркова,Рогалевич | B30: 46118 | C30: пн | D30: 8055 | E30: 2 | F30: =IF(AND(E30<>"",E30<>0),D30/E30,"") -> 4027.5 | G30: 1 | H30: =IF(AND(G30<>"",G30<>0),D30/G30,"") -> 8055 | I30: 31 | J30: =IF(AND(G30<>"",G30<>0),E30/G30,"") -> 2 | S30: 8051.17 | T30: =IF(AND(I30<>"",I30<>0),G30/I30,"") -> 0.032258065 | U30: =D30/V30 -> 0.097903561 | V30: =$I$8*AB30*AC30/SUMPRODUCT($AC$25:$AC$55,$AB$25:$AB$55) -> 82274.842 | W30: =$I$9*AB30*AC30/SUMPRODUCT($AC$25:$AC$55,$AB$25:$AB$55) -> 11.92389 | X30: =IF($I$12="","",W30/$I$12) -> 7.014053 | Y30: =IF(AB30<>"",IF(D30<>"",D30,($I$8-SUM($Y$25:Y29))*AA30*AB30/SUMPRODUCT($AB30:$AB$55,$AA30:$AA$55)),"") -> 8055 | Z30: =IF(AC30<>"",IF(E30<>"",E30,($I$9-SUM($Z$25:Z29))*AB30*AC30/SUMPRODUCT($AC30:$AC$55,$AB30:$AB$55)),"") -> 2 | AA30: =IF(AC30<>"",IF($I$12<>"",IF(G30<>"",G30,($I$9/$I$12-SUM($AA$25:AA29))*AB30*AC30/SUMPRODUCT($AC30:$AC$55,$AB30:$AB$55)),""),"") -> 1 | AB30: 1 | AC30: 0.72122791
A31: Бешлиева,Рогалевич | B31: 46119 | C31: вт | D31: 16967 | E31: 3 | F31: =IF(AND(E31<>"",E31<>0),D31/E31,"") -> 5655.6667 | G31: 2 | H31: =IF(AND(G31<>"",G31<>0),D31/G31,"") -> 8483.5 | I31: 34 | J31: =IF(AND(G31<>"",G31<>0),E31/G31,"") -> 1.5 | T31: =IF(AND(I31<>"",I31<>0),G31/I31,"") -> 0.058823529 | U31: =D31/V31 -> 0.20622343 | V31: =$I$8*AB31*AC31/SUMPRODUCT($AC$25:$AC$55,$AB$25:$AB$55) -> 82274.842 | W31: =$I$9*AB31*AC31/SUMPRODUCT($AC$25:$AC$55,$AB$25:$AB$55) -> 11.92389 | X31: =IF($I$12="","",W31/$I$12) -> 7.014053 | Y31: =IF(AB31<>"",IF(D31<>"",D31,($I$8-SUM($Y$25:Y30))*AA31*AB31/SUMPRODUCT($AB31:$AB$55,$AA31:$AA$55)),"") -> 16967 | Z31: =IF(AC31<>"",IF(E31<>"",E31,($I$9-SUM($Z$25:Z30))*AB31*AC31/SUMPRODUCT($AC31:$AC$55,$AB31:$AB$55)),"") -> 3 | AA31: =IF(AC31<>"",IF($I$12<>"",IF(G31<>"",G31,($I$9/$I$12-SUM($AA$25:AA30))*AB31*AC31/SUMPRODUCT($AC31:$AC$55,$AB31:$AB$55)),""),"") -> 2 | AB31: 1 | AC31: 0.72122791
A32: Бешлиева,Рогалевич | B32: 46120 | C32: ср | D32: 90013 | E32: 9 | F32: =IF(AND(E32<>"",E32<>0),D32/E32,"") -> 10001.444 | G32: 6 | H32: =IF(AND(G32<>"",G32<>0),D32/G32,"") -> 15002.167 | I32: 42 | J32: =IF(AND(G32<>"",G32<>0),E32/G32,"") -> 1.5 | K32: 51415 | M32: 7093 | R32: 6440 | T32: =IF(AND(I32<>"",I32<>0),G32/I32,"") -> 0.14285714 | U32: =D32/V32 -> 1.4790559 | V32: =$I$8*AB32*AC32/SUMPRODUCT($AC$25:$AC$55,$AB$25:$AB$55) -> 60858.416 | W32: =$I$9*AB32*AC32/SUMPRODUCT($AC$25:$AC$55,$AB$25:$AB$55) -> 8.8200603 | X32: =IF($I$12="","",W32/$I$12) -> 5.1882707 | Y32: =IF(AB32<>"",IF(D32<>"",D32,($I$8-SUM($Y$25:Y31))*AA32*AB32/SUMPRODUCT($AB32:$AB$55,$AA32:$AA$55)),"") -> 90013 | Z32: =IF(AC32<>"",IF(E32<>"",E32,($I$9-SUM($Z$25:Z31))*AB32*AC32/SUMPRODUCT($AC32:$AC$55,$AB32:$AB$55)),"") -> 9 | AA32: =IF(AC32<>"",IF($I$12<>"",IF(G32<>"",G32,($I$9/$I$12-SUM($AA$25:AA31))*AB32*AC32/SUMPRODUCT($AC32:$AC$55,$AB32:$AB$55)),""),"") -> 6 | AB32: 1 | AC32: 0.53348979
A33: Маркова,Рогалевич | B33: 46121 | C33: чт | D33: 37609 | E33: 5 | F33: =IF(AND(E33<>"",E33<>0),D33/E33,"") -> 7521.8 | G33: 3 | H33: =IF(AND(G33<>"",G33<>0),D33/G33,"") -> 12536.333 | I33: 46 | J33: =IF(AND(G33<>"",G33<>0),E33/G33,"") -> 1.6666667 | S33: 4123 | T33: =IF(AND(I33<>"",I33<>0),G33/I33,"") -> 0.065217391 | U33: =D33/V33 -> 0.82420883 | V33: =$I$8*AB33*AC33/SUMPRODUCT($AC$25:$AC$55,$AB$25:$AB$55) -> 45630.426 | W33: =$I$9*AB33*AC33/SUMPRODUCT($AC$25:$AC$55,$AB$25:$AB$55) -> 6.6131052 | X33: =IF($I$12="","",W33/$I$12) -> 3.8900619 | Y33: =IF(AB33<>"",IF(D33<>"",D33,($I$8-SUM($Y$25:Y32))*AA33*AB33/SUMPRODUCT($AB33:$AB$55,$AA33:$AA$55)),"") -> 37609 | Z33: =IF(AC33<>"",IF(E33<>"",E33,($I$9-SUM($Z$25:Z32))*AB33*AC33/SUMPRODUCT($AC33:$AC$55,$AB33:$AB$55)),"") -> 5 | AA33: =IF(AC33<>"",IF($I$12<>"",IF(G33<>"",G33,($I$9/$I$12-SUM($AA$25:AA32))*AB33*AC33/SUMPRODUCT($AC33:$AC$55,$AB33:$AB$55)),""),"") -> 3 | AB33: 1 | AC33: 0.4
A34: Бешлиева,Рогалевич | B34: 46122 | C34: пт | D34: 23175 | E34: 4 | F34: =IF(AND(E34<>"",E34<>0),D34/E34,"") -> 5793.75 | G34: 2 | H34: =IF(AND(G34<>"",G34<>0),D34/G34,"") -> 11587.5 | I34: 51 | J34: =IF(AND(G34<>"",G34<>0),E34/G34,"") -> 2 | T34: =IF(AND(I34<>"",I34<>0),G34/I34,"") -> 0.039215686 | U34: =D34/V34 -> 0.5078848 | V34: =$I$8*AB34*AC34/SUMPRODUCT($AC$25:$AC$55,$AB$25:$AB$55) -> 45630.426 | W34: =$I$9*AB34*AC34/SUMPRODUCT($AC$25:$AC$55,$AB$25:$AB$55) -> 6.6131052 | X34: =IF($I$12="","",W34/$I$12) -> 3.8900619 | Y34: =IF(AB34<>"",IF(D34<>"",D34,($I$8-SUM($Y$25:Y33))*AA34*AB34/SUMPRODUCT($AB34:$AB$55,$AA34:$AA$55)),"") -> 23175 | Z34: =IF(AC34<>"",IF(E34<>"",E34,($I$9-SUM($Z$25:Z33))*AB34*AC34/SUMPRODUCT($AC34:$AC$55,$AB34:$AB$55)),"") -> 4 | AA34: =IF(AC34<>"",IF($I$12<>"",IF(G34<>"",G34,($I$9/$I$12-SUM($AA$25:AA33))*AB34*AC34/SUMPRODUCT($AC34:$AC$55,$AB34:$AB$55)),""),"") -> 2 | AB34: 1 | AC34: 0.4
A35: Бешлиева | B35: 46123 | C35: сб | D35: 77762 | E35: 10 | F35: =IF(AND(E35<>"",E35<>0),D35/E35,"") -> 7776.2 | G35: 6 | H35: =IF(AND(G35<>"",G35<>0),D35/G35,"") -> 12960.333 | I35: 36 | J35: =IF(AND(G35<>"",G35<>0),E35/G35,"") -> 1.6666667 | R35: 25513 | T35: =IF(AND(I35<>"",I35<>0),G35/I35,"") -> 0.16666667 | U35: =D35/V35 -> 1.7041699 | V35: =$I$8*AB35*AC35/SUMPRODUCT($AC$25:$AC$55,$AB$25:$AB$55) -> 45630.426 | W35: =$I$9*AB35*AC35/SUMPRODUCT($AC$25:$AC$55,$AB$25:$AB$55) -> 6.6131052 | X35: =IF($I$12="","",W35/$I$12) -> 3.8900619 | Y35: =IF(AB35<>"",IF(D35<>"",D35,($I$8-SUM($Y$25:Y34))*AA35*AB35/SUMPRODUCT($AB35:$AB$55,$AA35:$AA$55)),"") -> 77762 | Z35: =IF(AC35<>"",IF(E35<>"",E35,($I$9-SUM($Z$25:Z34))*AB35*AC35/SUMPRODUCT($AC35:$AC$55,$AB35:$AB$55)),"") -> 10 | AA35: =IF(AC35<>"",IF($I$12<>"",IF(G35<>"",G35,($I$9/$I$12-SUM($AA$25:AA34))*AB35*AC35/SUMPRODUCT($AC35:$AC$55,$AB35:$AB$55)),""),"") -> 6 | AB35: 1 | AC35: 0.4
A36: Маркова | B36: 46124 | C36: вс | D36: 28377 | E36: 3 | F36: =IF(AND(E36<>"",E36<>0),D36/E36,"") -> 9459 | G36: 2 | H36: =IF(AND(G36<>"",G36<>0),D36/G36,"") -> 14188.5 | I36: 46 | J36: =IF(AND(G36<>"",G36<>0),E36/G36,"") -> 1.5 | M36: 14992 | T36: =IF(AND(I36<>"",I36<>0),G36/I36,"") -> 0.043478261 | U36: =D36/V36 -> 0.62188768 | V36: =$I$8*AB36*AC36/SUMPRODUCT($AC$25:$AC$55,$AB$25:$AB$55) -> 45630.426 | W36: =$I$9*AB36*AC36/SUMPRODUCT($AC$25:$AC$55,$AB$25:$AB$55) -> 6.6131052 | X36: =IF($I$12="","",W36/$I$12) -> 3.8900619 | Y36: =IF(AB36<>"",IF(D36<>"",D36,($I$8-SUM($Y$25:Y35))*AA36*AB36/SUMPRODUCT($AB36:$AB$55,$AA36:$AA$55)),"") -> 28377 | Z36: =IF(AC36<>"",IF(E35<>"",E35,($I$9-SUM($Z$25:Z35))*AB36*AC36/SUMPRODUCT($AC36:$AC$55,$AB36:$AB$55)),"") -> 10 | AA36: =IF(AC36<>"",IF($I$12<>"",IF(G36<>"",G36,($I$9/$I$12-SUM($AA$25:AA35))*AB36*AC36/SUMPRODUCT($AC36:$AC$55,$AB36:$AB$55)),""),"") -> 2 | AB36: 1 | AC36: 0.4
A37: Бешлиева | B37: 46125 | C37: пн | D37: 44417 | E37: 6 | F37: =IF(AND(E37<>"",E37<>0),D37/E37,"") -> 7402.8333 | G37: 5 | H37: =IF(AND(G37<>"",G37<>0),D37/G37,"") -> 8883.4 | I37: 42 | J37: =IF(AND(G37<>"",G37<>0),E37/G37,"") -> 1.2 | K37: 10993 | O37: 7658 | T37: =IF(AND(I37<>"",I37<>0),G37/I37,"") -> 0.11904762 | U37: =D37/V37 -> 0.97340752 | V37: =$I$8*AB37*AC37/SUMPRODUCT($AC$25:$AC$55,$AB$25:$AB$55) -> 45630.426 | W37: =$I$9*AB37*AC37/SUMPRODUCT($AC$25:$AC$55,$AB$25:$AB$55) -> 6.6131052 | X37: =IF($I$12="","",W37/$I$12) -> 3.8900619 | Y37: =IF(AB37<>"",IF(D37<>"",D37,($I$8-SUM($Y$25:Y36))*AA37*AB37/SUMPRODUCT($AB37:$AB$55,$AA37:$AA$55)),"") -> 44417 | Z37: =IF(AC37<>"",IF(E37<>"",E37,($I$9-SUM($Z$25:Z36))*AB37*AC37/SUMPRODUCT($AC37:$AC$55,$AB37:$AB$55)),"") -> 6 | AA37: =IF(AC37<>"",IF($I$12<>"",IF(G37<>"",G37,($I$9/$I$12-SUM($AA$25:AA36))*AB37*AC37/SUMPRODUCT($AC37:$AC$55,$AB37:$AB$55)),""),"") -> 5 | AB37: 1 | AC37: 0.4
A38: Маркова | B38: 46126 | C38: вт | D38: 4692 | E38: 1 | F38: =IF(AND(E38<>"",E38<>0),D38/E38,"") -> 4692 | G38: 1 | H38: =IF(AND(G38<>"",G38<>0),D38/G38,"") -> 4692 | I38: 34 | J38: =IF(AND(G38<>"",G38<>0),E38/G38,"") -> 1 | T38: =IF(AND(I38<>"",I38<>0),G38/I38,"") -> 0.029411765 | U38: =D38/V38 -> 0.10221277 | V38: =$I$8*AB38*AC38/SUMPRODUCT($AC$25:$AC$55,$AB$25:$AB$55) -> 45904.247 | W38: =$I$9*AB38*AC38/SUMPRODUCT($AC$25:$AC$55,$AB$25:$AB$55) -> 6.6527894 | X38: =IF($I$12="","",W38/$I$12) -> 3.9134055 | Y38: =IF(AB38<>"",IF(D38<>"",D38,($I$8-SUM($Y$25:Y37))*AA38*AB38/SUMPRODUCT($AB38:$AB$55,$AA38:$AA$55)),"") -> 4692 | Z38: =IF(AC38<>"",IF(E38<>"",E38,($I$9-SUM($Z$25:Z37))*AB38*AC38/SUMPRODUCT($AC38:$AC$55,$AB38:$AB$55)),"") -> 1 | AA38: =IF(AC38<>"",IF($I$12<>"",IF(G38<>"",G38,($I$9/$I$12-SUM($AA$25:AA37))*AB38*AC38/SUMPRODUCT($AC38:$AC$55,$AB38:$AB$55)),""),"") -> 1 | AB38: 1 | AC38: 0.40240033
A39: Бешлиева | B39: 46127 | C39: ср | D39: 4196 | E39: 1 | F39: =IF(AND(E39<>"",E39<>0),D39/E39,"") -> 4196 | G39: 1 | H39: =IF(AND(G39<>"",G39<>0),D39/G39,"") -> 4196 | I39: 36 | J39: =IF(AND(G39<>"",G39<>0),E39/G39,"") -> 1 | S39: 4193 | T39: =IF(AND(I39<>"",I39<>0),G39/I39,"") -> 0.027777778 | U39: =D39/V39 -> 0.045541057 | V39: =$I$8*AB39*AC39/SUMPRODUCT($AC$25:$AC$55,$AB$25:$AB$55) -> 92136.641 | W39: =$I$9*AB39*AC39/SUMPRODUCT($AC$25:$AC$55,$AB$25:$AB$55) -> 13.353136 | X39: =IF($I$12="","",W39/$I$12) -> 7.8547861 | Y39: =IF(AB39<>"",IF(D39<>"",D39,($I$8-SUM($Y$25:Y38))*AA39*AB39/SUMPRODUCT($AB39:$AB$55,$AA39:$AA$55)),"") -> 4196 | Z39: =IF(AC39<>"",IF(E39<>"",E39,($I$9-SUM($Z$25:Z38))*AB39*AC39/SUMPRODUCT($AC39:$AC$55,$AB39:$AB$55)),"") -> 1 | AA39: =IF(AC39<>"",IF($I$12<>"",IF(G39<>"",G39,($I$9/$I$12-SUM($AA$25:AA38))*AB39*AC39/SUMPRODUCT($AC39:$AC$55,$AB39:$AB$55)),""),"") -> 1 | AB39: 1 | AC39: 0.80767724
A40: Маркова | B40: 46128 | C40: чт | D40: 11286 | E40: 2 | F40: =IF(AND(E40<>"",E40<>0),D40/E40,"") -> 5643 | G40: 2 | H40: =IF(AND(G40<>"",G40<>0),D40/G40,"") -> 5643 | I40: 18 | J40: =IF(AND(G40<>"",G40<>0),E40/G40,"") -> 1 | T40: =IF(AND(I40<>"",I40<>0),G40/I40,"") -> 0.11111111 | U40: =D40/V40 -> 0.12249198 | V40: =$I$8*AB40*AC40/SUMPRODUCT($AC$25:$AC$55,$AB$25:$AB$55) -> 92136.641 | W40: =$I$9*AB40*AC40/SUMPRODUCT($AC$25:$AC$55,$AB$25:$AB$55) -> 13.353136 | X40: =IF($I$12="","",W40/$I$12) -> 7.8547861 | Y40: =IF(AB40<>"",IF(D40<>"",D40,($I$8-SUM($Y$25:Y39))*AA40*AB40/SUMPRODUCT($AB40:$AB$55,$AA40:$AA$55)),"") -> 11286 | Z40: =IF(AC40<>"",IF(E40<>"",E40,($I$9-SUM($Z$25:Z39))*AB40*AC40/SUMPRODUCT($AC40:$AC$55,$AB40:$AB$55)),"") -> 2 | AA40: =IF(AC40<>"",IF($I$12<>"",IF(G40<>"",G40,($I$9/$I$12-SUM($AA$25:AA39))*AB40*AC40/SUMPRODUCT($AC40:$AC$55,$AB40:$AB$55)),""),"") -> 2 | AB40: 1 | AC40: 0.80767724
A41: Маркова | B41: 46129 | C41: пт | D41: 0 | E41: 0 | F41: 0 | G41: 0 | H41: 0 | I41: 20 | J41: =IF(AND(G41<>"",G41<>0),E41/G41,"") | T41: =IF(AND(I41<>"",I41<>0),G41/I41,"") -> 0 | U41: =D41/V41 -> 0 | V41: =$I$8*AB41*AC41/SUMPRODUCT($AC$25:$AC$55,$AB$25:$AB$55) -> 77491.522 | W41: =$I$9*AB41*AC41/SUMPRODUCT($AC$25:$AC$55,$AB$25:$AB$55) -> 11.230655 | X41: =IF($I$12="","",W41/$I$12) -> 6.6062678 | Y41: =IF(AB41<>"",IF(D41<>"",D41,($I$8-SUM($Y$25:Y40))*AA41*AB41/SUMPRODUCT($AB41:$AB$55,$AA41:$AA$55)),"") -> 0 | Z41: =IF(AC41<>"",IF(E41<>"",E41,($I$9-SUM($Z$25:Z40))*AB41*AC41/SUMPRODUCT($AC41:$AC$55,$AB41:$AB$55)),"") -> 0 | AA41: =IF(AC41<>"",IF($I$12<>"",IF(G41<>"",G41,($I$9/$I$12-SUM($AA$25:AA40))*AB41*AC41/SUMPRODUCT($AC41:$AC$55,$AB41:$AB$55)),""),"") -> 0 | AB41: 1 | AC41: 0.67929694
A42: Бешлиева | B42: 46130 | C42: сб | D42: 38263 | E42: 7 | F42: =IF(AND(E42<>"",E42<>0),D42/E42,"") -> 5466.1429 | G42: 4 | H42: =IF(AND(G42<>"",G42<>0),D42/G42,"") -> 9565.75 | I42: 35 | J42: =IF(AND(G42<>"",G42<>0),E42/G42,"") -> 1.75 | T42: =IF(AND(I42<>"",I42<>0),G42/I42,"") -> 0.11428571 | U42: =D42/V42 -> 0.91576768 | V42: =$I$8*AB42*AC42/SUMPRODUCT($AC$25:$AC$55,$AB$25:$AB$55) -> 41782.431 | W42: =$I$9*AB42*AC42/SUMPRODUCT($AC$25:$AC$55,$AB$25:$AB$55) -> 6.0554248 | X42: =IF($I$12="","",W42/$I$12) -> 3.5620146 | Y42: =IF(AB42<>"",IF(D42<>"",D42,($I$8-SUM($Y$25:Y41))*AA42*AB42/SUMPRODUCT($AB42:$AB$55,$AA42:$AA$55)),"") -> 38263 | Z42: =IF(AC42<>"",IF(E42<>"",E42,($I$9-SUM($Z$25:Z41))*AB42*AC42/SUMPRODUCT($AC42:$AC$55,$AB42:$AB$55)),"") -> 7 | AA42: =IF(AC42<>"",IF($I$12<>"",IF(G42<>"",G42,($I$9/$I$12-SUM($AA$25:AA41))*AB42*AC42/SUMPRODUCT($AC42:$AC$55,$AB42:$AB$55)),""),"") -> 4 | AB42: 1 | AC42: 0.36626817
A43: Бешлиева | B43: 46131 | C43: вс | D43: 38216 | E43: 6 | F43: =IF(AND(E43<>"",E43<>0),D43/E43,"") -> 6369.3333 | G43: 4 | H43: =IF(AND(G43<>"",G43<>0),D43/G43,"") -> 9554 | I43: 40 | J43: =IF(AND(G43<>"",G43<>0),E43/G43,"") -> 1.5 | T43: =IF(AND(I43<>"",I43<>0),G43/I43,"") -> 0.1 | U43: =D43/V43 -> 0.55363531 | V43: =$I$8*AB43*AC43/SUMPRODUCT($AC$25:$AC$55,$AB$25:$AB$55) -> 69027.389 | W43: =$I$9*AB43*AC43/SUMPRODUCT($AC$25:$AC$55,$AB$25:$AB$55) -> 10.003969 | X43: =IF($I$12="","",W43/$I$12) -> 5.8846879 | Y43: =IF(AB43<>"",IF(D43<>"",D43,($I$8-SUM($Y$25:Y42))*AA43*AB43/SUMPRODUCT($AB43:$AB$55,$AA43:$AA$55)),"") -> 38216 | Z43: =IF(AC43<>"",IF(E43<>"",E43,($I$9-SUM($Z$25:Z42))*AB43*AC43/SUMPRODUCT($AC43:$AC$55,$AB43:$AB$55)),"") -> 6 | AA43: =IF(AC43<>"",IF($I$12<>"",IF(G43<>"",G43,($I$9/$I$12-SUM($AA$25:AA42))*AB43*AC43/SUMPRODUCT($AC43:$AC$55,$AB43:$AB$55)),""),"") -> 4 | AB43: 1 | AC43: 0.60509967
A44: Маркова,Рогалевич | B44: 46132 | C44: пн | D44: 8793 | E44: 1 | F44: =IF(AND(E44<>"",E44<>0),D44/E44,"") -> 8793 | G44: 1 | H44: =IF(AND(G44<>"",G44<>0),D44/G44,"") -> 8793 | I44: 44 | J44: =IF(AND(G44<>"",G44<>0),E44/G44,"") -> 1 | M44: 8793 | T44: =IF(AND(I44<>"",I44<>0),G44/I44,"") -> 0.022727273 | U44: =D44/V44 -> 0.17487015 | V44: =$I$8*AB44*AC44/SUMPRODUCT($AC$25:$AC$55,$AB$25:$AB$55) -> 50283.025 | W44: =$I$9*AB44*AC44/SUMPRODUCT($AC$25:$AC$55,$AB$25:$AB$55) -> 7.2873949 | X44: =IF($I$12="","",W44/$I$12) -> 4.2867029 | Y44: =IF(AB44<>"",IF(D44<>"",D44,($I$8-SUM($Y$25:Y43))*AA44*AB44/SUMPRODUCT($AB44:$AB$55,$AA44:$AA$55)),"") -> 8793 | Z44: =IF(AC44<>"",IF(E44<>"",E44,($I$9-SUM($Z$25:Z43))*AB44*AC44/SUMPRODUCT($AC44:$AC$55,$AB44:$AB$55)),"") -> 1 | AA44: =IF(AC44<>"",IF($I$12<>"",IF(G44<>"",G44,($I$9/$I$12-SUM($AA$25:AA43))*AB44*AC44/SUMPRODUCT($AC44:$AC$55,$AB44:$AB$55)),""),"") -> 1 | AB44: 1 | AC44: 0.44078505
A45: Бешлиева,Рогалевич | B45: 46133 | C45: вт | D45: 0 | E45: 0 | F45: 0 | G45: 0 | H45: 0 | I45: 41 | J45: =IF(AND(G45<>"",G45<>0),E45/G45,"") | T45: =IF(AND(I45<>"",I45<>0),G45/I45,"") -> 0 | U45: =D45/V45 -> 0 | V45: =$I$8*AB45*AC45/SUMPRODUCT($AC$25:$AC$55,$AB$25:$AB$55) -> 13021.743 | W45: =$I$9*AB45*AC45/SUMPRODUCT($AC$25:$AC$55,$AB$25:$AB$55) -> 1.8872091 | X45: =IF($I$12="","",W45/$I$12) -> 1.110123 | Y45: =IF(AB45<>"",IF(D45<>"",D45,($I$8-SUM($Y$25:Y44))*AA45*AB45/SUMPRODUCT($AB45:$AB$55,$AA45:$AA$55)),"") -> 0 | Z45: =IF(AC45<>"",IF(E45<>"",E45,($I$9-SUM($Z$25:Z44))*AB45*AC45/SUMPRODUCT($AC45:$AC$55,$AB45:$AB$55)),"") -> 0 | AA45: =IF(AC45<>"",IF($I$12<>"",IF(G45<>"",G45,($I$9/$I$12-SUM($AA$25:AA44))*AB45*AC45/SUMPRODUCT($AC45:$AC$55,$AB45:$AB$55)),""),"") -> 0 | AB45: 1 | AC45: 0.11414965
A46: Бешлиева,Рогалевич | B46: 46134 | C46: ср | D46: 57904 | E46: 9 | F46: =IF(AND(E46<>"",E46<>0),D46/E46,"") -> 6433.7778 | G46: 4 | H46: =IF(AND(G46<>"",G46<>0),D46/G46,"") -> 14476 | I46: 48 | J46: =IF(AND(G46<>"",G46<>0),E46/G46,"") -> 2.25 | O46: 9682 | S46: 7890 | T46: =IF(AND(I46<>"",I46<>0),G46/I46,"") -> 0.083333333 | U46: =D46/V46 -> 0.80313968 | V46: =$I$8*AB46*AC46/SUMPRODUCT($AC$25:$AC$55,$AB$25:$AB$55) -> 72097.048 | W46: =$I$9*AB46*AC46/SUMPRODUCT($AC$25:$AC$55,$AB$25:$AB$55) -> 10.448847 | X46: =IF($I$12="","",W46/$I$12) -> 6.1463809 | Y46: =IF(AB46<>"",IF(D46<>"",D46,($I$8-SUM($Y$25:Y45))*AA46*AB46/SUMPRODUCT($AB46:$AB$55,$AA46:$AA$55)),"") -> 57904 | Z46: =IF(AC45<>"",IF(E45<>"",E45,($I$9-SUM($Z$25:Z44))*AB45*AC45/SUMPRODUCT($AC45:$AC$55,$AB45:$AB$55)),"") -> 0 | AA46: =IF(AC45<>"",IF($I$12<>"",IF(G45<>"",G45,($I$9/$I$12-SUM($AA$25:AA44))*AB45*AC45/SUMPRODUCT($AC45:$AC$55,$AB45:$AB$55)),""),"") -> 0 | AB46: 1 | AC46: 0.63200854
A47: Бешлиева,Рогалевич | B47: 46135 | C47: чт | D47: 12086 | E47: 2 | F47: =IF(AND(E47<>"",E47<>0),D47/E47,"") -> 6043 | G47: 2 | H47: =IF(AND(G47<>"",G47<>0),D47/G47,"") -> 6043 | I47: 52 | J47: =IF(AND(G47<>"",G47<>0),E47/G47,"") -> 1 | T47: =IF(AND(I47<>"",I47<>0),G47/I47,"") -> 0.038461538 | U47: =D47/V47 -> 0.21566595 | V47: =$I$8*AB47*AC47/SUMPRODUCT($AC$25:$AC$55,$AB$25:$AB$55) -> 56040.371 | W47: =$I$9*AB47*AC47/SUMPRODUCT($AC$25:$AC$55,$AB$25:$AB$55) -> 8.1217929 | X47: =IF($I$12="","",W47/$I$12) -> 4.7775252 | Y47: =IF(AB47<>"",IF(D47<>"",D47,($I$8-SUM($Y$25:Y46))*AA47*AB47/SUMPRODUCT($AB47:$AB$55,$AA47:$AA$55)),"") -> 12086 | Z47: =IF(AC47<>"",IF(E47<>"",E47,($I$9-SUM($Z$25:Z46))*AB47*AC47/SUMPRODUCT($AC47:$AC$55,$AB47:$AB$55)),"") -> 2 | AA47: =IF(AC47<>"",IF($I$12<>"",IF(G47<>"",G47,($I$9/$I$12-SUM($AA$25:AA46))*AB47*AC47/SUMPRODUCT($AC47:$AC$55,$AB47:$AB$55)),""),"") -> 2 | AB47: 1 | AC47: 0.49125442
A48: Бешлиева | B48: 46136 | C48: пт | D48: 27886 | E48: 4 | F48: =IF(AND(E48<>"",E48<>0),D48/E48,"") -> 6971.5 | G48: 3 | H48: =IF(AND(G48<>"",G48<>0),D48/G48,"") -> 9295.3333 | I48: 44 | J48: =IF(AND(G48<>"",G48<>0),E48/G48,"") -> 1.3333333 | O48: 12593 | T48: =IF(AND(I48<>"",I48<>0),G48/I48,"") -> 0.068181818 | U48: =D48/V48 -> 0.83656516 | V48: =$I$8*AB48*AC48/SUMPRODUCT($AC$25:$AC$55,$AB$25:$AB$55) -> 33333.925 | W48: =$I$9*AB48*AC48/SUMPRODUCT($AC$25:$AC$55,$AB$25:$AB$55) -> 4.8310036 | X48: =IF($I$12="","",W48/$I$12) -> 2.8417668 | Y48: =IF(AB48<>"",IF(D48<>"",D48,($I$8-SUM($Y$25:Y47))*AA48*AB48/SUMPRODUCT($AB48:$AB$55,$AA48:$AA$55)),"") -> 27886 | Z48: =IF(AC48<>"",IF(E48<>"",E48,($I$9-SUM($Z$25:Z47))*AB48*AC48/SUMPRODUCT($AC48:$AC$55,$AB48:$AB$55)),"") -> 4 | AA48: =IF(AC48<>"",IF($I$12<>"",IF(G48<>"",G48,($I$9/$I$12-SUM($AA$25:AA47))*AB48*AC48/SUMPRODUCT($AC48:$AC$55,$AB48:$AB$55)),""),"") -> 3 | AB48: 1 | AC48: 0.29220788
A49: Бешлиева | B49: 46137 | C49: сб | D49: 9920 | E49: 2 | F49: =IF(AND(E49<>"",E49<>0),D49/E49,"") -> 4960 | G49: 2 | H49: =IF(AND(G49<>"",G49<>0),D49/G49,"") -> 4960 | I49: 69 | J49: =IF(AND(G49<>"",G49<>0),E49/G49,"") -> 1 | T49: =IF(AND(I49<>"",I49<>0),G49/I49,"") -> 0.028985507 | U49: =D49/V49 -> 1.1486773 | V49: =$I$8*AB49*AC49/SUMPRODUCT($AC$25:$AC$55,$AB$25:$AB$55) -> 8636.0196 | W49: =$I$9*AB49*AC49/SUMPRODUCT($AC$25:$AC$55,$AB$25:$AB$55) -> 1.251597 | X49: =IF($I$12="","",W49/$I$12) -> 0.73623356 | Y49: =IF(AB49<>"",IF(D49<>"",D49,($I$8-SUM($Y$25:Y48))*AA49*AB49/SUMPRODUCT($AB49:$AB$55,$AA49:$AA$55)),"") -> 9920 | Z49: =IF(AC49<>"",IF(E49<>"",E49,($I$9-SUM($Z$25:Z48))*AB49*AC49/SUMPRODUCT($AC49:$AC$55,$AB49:$AB$55)),"") -> 2 | AA49: =IF(AC49<>"",IF($I$12<>"",IF(G49<>"",G49,($I$9/$I$12-SUM($AA$25:AA48))*AB49*AC49/SUMPRODUCT($AC49:$AC$55,$AB49:$AB$55)),""),"") -> 2 | AB49: 1 | AC49: 0.075704046
A50: Маркова | B50: 46138 | C50: вс | D50: 27559 | E50: 5 | F50: =IF(AND(E50<>"",E50<>0),D50/E50,"") -> 5511.8 | G50: 2 | H50: =IF(AND(G50<>"",G50<>0),D50/G50,"") -> 13779.5 | I50: 58 | J50: =IF(AND(G50<>"",G50<>0),E50/G50,"") -> 2.5 | T50: =IF(AND(I50<>"",I50<>0),G50/I50,"") -> 0.034482759 | U50: =D50/V50 -> 2.4487621 | V50: =$I$8*AB50*AC50/SUMPRODUCT($AC$25:$AC$55,$AB$25:$AB$55) -> 11254.258 | W50: =$I$9*AB50*AC50/SUMPRODUCT($AC$25:$AC$55,$AB$25:$AB$55) -> 1.6310519 | X50: =IF($I$12="","",W50/$I$12) -> 0.95944228 | Y50: =IF(AB50<>"",IF(D50<>"",D50,($I$8-SUM($Y$25:Y49))*AA50*AB50/SUMPRODUCT($AB50:$AB$55,$AA50:$AA$55)),"") -> 27559 | Z50: =IF(AC50<>"",IF(E50<>"",E50,($I$9-SUM($Z$25:Z49))*AB50*AC50/SUMPRODUCT($AC50:$AC$55,$AB50:$AB$55)),"") -> 5 | AA50: =IF(AC50<>"",IF($I$12<>"",IF(G50<>"",G50,($I$9/$I$12-SUM($AA$25:AA49))*AB50*AC50/SUMPRODUCT($AC50:$AC$55,$AB50:$AB$55)),""),"") -> 2 | AB50: 1 | AC50: 0.098655734
A51: Бешлиева | B51: 46139 | C51: пн | D51: 48248 | E51: 7 | F51: =IF(AND(E51<>"",E51<>0),D51/E51,"") -> 6892.5714 | G51: 2 | H51: =IF(AND(G51<>"",G51<>0),D51/G51,"") -> 24124 | I51: 41 | J51: =IF(AND(G51<>"",G51<>0),E51/G51,"") -> 3.5 | T51: =IF(AND(I51<>"",I51<>0),G51/I51,"") -> 0.048780488 | U51: =D51/V51 -> 3.0945331 | V51: =$I$8*AB51*AC51/SUMPRODUCT($AC$25:$AC$55,$AB$25:$AB$55) -> 15591.366 | W51: =$I$9*AB51*AC51/SUMPRODUCT($AC$25:$AC$55,$AB$25:$AB$55) -> 2.2596183 | X51: =IF($I$12="","",W51/$I$12) -> 1.3291872 | Y51: =IF(AB51<>"",IF(D51<>"",D51,($I$8-SUM($Y$25:Y50))*AA51*AB51/SUMPRODUCT($AB51:$AB$55,$AA51:$AA$55)),"") -> 48248 | Z51: =IF(AC51<>"",IF(E51<>"",E51,($I$9-SUM($Z$25:Z50))*AB51*AC51/SUMPRODUCT($AC51:$AC$55,$AB51:$AB$55)),"") -> 7 | AA51: =IF(AC51<>"",IF($I$12<>"",IF(G51<>"",G51,($I$9/$I$12-SUM($AA$25:AA50))*AB51*AC51/SUMPRODUCT($AC51:$AC$55,$AB51:$AB$55)),""),"") -> 2 | AB51: 1 | AC51: 0.13667518
A52: Бешлиева | B52: 46140 | C52: вт | D52: 63080 | E52: 13 | F52: =IF(AND(E52<>"",E52<>0),D52/E52,"") -> 4852.3077 | G52: 7 | H52: =IF(AND(G52<>"",G52<>0),D52/G52,"") -> 9011.4286 | I52: 37 | J52: =IF(AND(G52<>"",G52<>0),E52/G52,"") -> 1.8571429 | S52: 25135 | T52: =IF(AND(I52<>"",I52<>0),G52/I52,"") -> 0.18918919 | U52: =D52/V52 -> 1.3824109 | V52: =$I$8*AB52*AC52/SUMPRODUCT($AC$25:$AC$55,$AB$25:$AB$55) -> 45630.426 | W52: =$I$9*AB52*AC52/SUMPRODUCT($AC$25:$AC$55,$AB$25:$AB$55) -> 6.6131052 | X52: =IF($I$12="","",W52/$I$12) -> 3.8900619 | Y52: =IF(AB52<>"",IF(D52<>"",D52,($I$8-SUM($Y$25:Y51))*AA52*AB52/SUMPRODUCT($AB52:$AB$55,$AA52:$AA$55)),"") -> 63080 | Z52: =IF(AC52<>"",IF(E52<>"",E52,($I$9-SUM($Z$25:Z51))*AB52*AC52/SUMPRODUCT($AC52:$AC$55,$AB52:$AB$55)),"") -> 13 | AA52: =IF(AC52<>"",IF($I$12<>"",IF(G52<>"",G52,($I$9/$I$12-SUM($AA$25:AA51))*AB52*AC52/SUMPRODUCT($AC52:$AC$55,$AB52:$AB$55)),""),"") -> 7 | AB52: 1 | AC52: 0.4
A53: Бешлиева | B53: 46141 | C53: ср | D53: 0 | E53: 0 | F53: 0 | G53: 0 | H53: 0 | I53: 41 | J53: =IF(AND(G53<>"",G53<>0),E53/G53,"") | T53: =IF(AND(I53<>"",I53<>0),G53/I53,"") -> 0 | U53: =D53/V53 -> 0 | V53: =$I$8*AB53*AC53/SUMPRODUCT($AC$25:$AC$55,$AB$25:$AB$55) -> 45630.426 | W53: =$I$9*AB53*AC53/SUMPRODUCT($AC$25:$AC$55,$AB$25:$AB$55) -> 6.6131052 | X53: =IF($I$12="","",W53/$I$12) -> 3.8900619 | Y53: =IF(AB53<>"",IF(D53<>"",D53,($I$8-SUM($Y$25:Y52))*AA53*AB53/SUMPRODUCT($AB53:$AB$55,$AA53:$AA$55)),"") -> 0 | Z53: =IF(AC53<>"",IF(E53<>"",E53,($I$9-SUM($Z$25:Z52))*AB53*AC53/SUMPRODUCT($AC53:$AC$55,$AB53:$AB$55)),"") -> 0 | AA53: =IF(AC53<>"",IF($I$12<>"",IF(G53<>"",G53,($I$9/$I$12-SUM($AA$25:AA52))*AB53*AC53/SUMPRODUCT($AC53:$AC$55,$AB53:$AB$55)),""),"") -> 0 | AB53: 1 | AC53: 0.4
A54: Рогалевич | B54: 46142 | C54: чт | D54: 454031 | E54: 37 | F54: =IF(AND(E54<>"",E54<>0),D54/E54,"") -> 12271.108 | G54: 3 | H54: =IF(AND(G54<>"",G54<>0),D54/G54,"") -> 151343.67 | I54: 35 | J54: =IF(AND(G54<>"",G54<>0),E54/G54,"") -> 12.333333 | N54: 227591 | O54: 190704 | P54: 26543 | T54: =IF(AND(I54<>"",I54<>0),G54/I54,"") -> 0.085714286 | U54: =D54/V54 -> 9.950181 | V54: =$I$8*AB54*AC54/SUMPRODUCT($AC$25:$AC$55,$AB$25:$AB$55) -> 45630.426 | W54: =$I$9*AB54*AC54/SUMPRODUCT($AC$25:$AC$55,$AB$25:$AB$55) -> 6.6131052 | X54: =IF($I$12="","",W54/$I$12) -> 3.8900619 | Y54: =IF(AB54<>"",IF(D54<>"",D54,($I$8-SUM($Y$25:Y53))*AA54*AB54/SUMPRODUCT($AB54:$AB$55,$AA54:$AA$55)),"") -> 454031 | Z54: =IF(AC54<>"",IF(E54<>"",E54,($I$9-SUM($Z$25:Z53))*AB54*AC54/SUMPRODUCT($AC54:$AC$55,$AB54:$AB$55)),"") -> 37 | AA54: =IF(AC54<>"",IF($I$12<>"",IF(G54<>"",G54,($I$9/$I$12-SUM($AA$25:AA53))*AB54*AC54/SUMPRODUCT($AC54:$AC$55,$AB54:$AB$55)),""),"") -> 3 | AB54: 1 | AC54: 0.4
F55: =IF(AND(E55<>"",E55<>0),D55/E55,"") | H55: =IF(AND(G55<>"",G55<>0),D55/G55,"") | J55: =IF(AND(G55<>"",G55<>0),E55/G55,"") | T55: =IF(AND(I55<>"",I55<>0),G55/I55,"") | U55: =D55/V55 -> #DIV/0! | V55: =$I$8*AB55*AC55/SUMPRODUCT($AC$25:$AC$55,$AB$25:$AB$55) -> 0 | W55: =$I$9*AB55*AC55/SUMPRODUCT($AC$25:$AC$55,$AB$25:$AB$55) -> 0 | X55: =IF($I$12="","",W55/$I$12) -> 0 | Y55: =IF(AB55<>"",IF(D55<>"",D55,($I$8-SUM($Y$25:Y54))*AA55*AB55/SUMPRODUCT($AB55:$AB$55,$AA55:$AA$55)),"") | Z55: =IF(AC55<>"",IF(E55<>"",E55,($I$9-SUM($Z$25:Z54))*AB55*AC55/SUMPRODUCT($AC55:$AC$55,$AB55:$AB$55)),"") | AA55: =IF(AC55<>"",IF($I$12<>"",IF(G55<>"",G55,($I$9/$I$12-SUM($AA$25:AA54))*AB55*AC55/SUMPRODUCT($AC55:$AC$55,$AB55:$AB$55)),""),"")
D56: =SUM(D25:D55) -> 1254183 | E56: =SUM(E25:E55) -> 159 | F56: =IF(AND(E56<>"", E56<>0), D56/E56, "") -> 7887.9434 | G56: =SUM(G25:G55) -> 80 | H56: =IF(AND(G56<>"", G56<>0), D56/G56, "") -> 15677.288 | I56: =SUM(I25:I55)*0.85 -> 1041.25 | J56: =E56/G56 -> 1.9875 | K56: =SUM(K25:K55) -> 62408 | L56: =SUM(L25:L55) -> 0 | M56: =SUM(M25:M55) -> 30878 | N56: =SUM(N25:N55) -> 227591 | O56: =SUM(O25:O55) -> 220637 | P56: =SUM(P25:P55) -> 38934 | Q56: =SUM(Q25:Q55) -> 0 | R56: =SUM(R25:R55) -> 31953 | S56: =SUM(S25:S55) -> 53655.17 | T56: =IF(AND(I56<>"",I56<>0),G56/I56,"") -> 0.076830732 | U56: =D56/V56 -> 0.66825607 | V56: =SUM(V25:V55) -> 1876800 | W56: =SUM(W25:W55) -> 272 | X56: =SUM(X25:X55) -> 160 | Y56: =SUM(Y25:Y55) -> 1254183 | Z56: =SUM(Z25:Z55) -> 157 | AA56: =SUM(AA25:AA55) -> 76
D57: =SUMIF(D25:D55,"",V25:V55)+D56 -> 1254183
D58: =Рогалевич!D48+Маркова!D48+Бешлиева!D48 -> 1254183 | I58: =Рогалевич!I48+Маркова!I48+Бешлиева!I48 -> 709.6 | K58: =Рогалевич!K48+Маркова!K48+Бешлиева!K48 -> 62408 | L58: =Рогалевич!L48+Маркова!L48+Бешлиева!L48 -> 0 | M58: =Рогалевич!M48+Маркова!M48+Бешлиева!M48 -> 30878 | N58: =Рогалевич!N48+Маркова!N48+Бешлиева!N48 -> 227591 | O58: =Рогалевич!O48+Маркова!O48+Бешлиева!O48 -> 220637 | P58: =Рогалевич!P48+Маркова!P48+Бешлиева!P48 -> 38934 | Q58: =Рогалевич!Q48+Маркова!Q48+Бешлиева!Q48 -> 0 | R58: =Рогалевич!R48+Маркова!R48+Бешлиева!R48 -> 31953 | S58: =Рогалевич!S48+Маркова!S48+Бешлиева!S48 -> 53655.17
K59: =K58/$J$8 -> 0.049759884 | L59: =L58/$J$8 -> 0 | M59: =M58/$J$8 -> 0.024620012 | N59: =N58/$J$8 -> 0.18146554 | O59: =O58/$J$8 -> 0.1759209 | P59: =P58/$J$8 -> 0.031043317 | Q59: =Q58/$J$8 -> 0 | R59: =R58/$J$8 -> 0.025477143 | S59: =S58/$J$8 -> 0.042780974
D60: =SUM(D45:D49) -> 107796
D61: =SUM(D51:D54) -> 565359
D62: =D60+D61 -> 673155

Sheet Справочник магазинов
A1: МЕГА Белая Дача
A2: Гагаринский
A3: Марфино

Sheet Сводная
A2: Показатель | D2: =Центрум!I3 -> ТРК Центрум | G2: =[1]График!B28 -> Рогалевич Ирина | J2: =График!B27 -> Маркова Диана | M2: =График!B26 -> Бешлиева Аджере
D3: Факт | F3: Прогноз | G3: Факт | I3: Прогноз | J3: Факт | L3: Прогноз | M3: Факт | O3: Прогноз
A4: Выручка | D4: =Центрум!K8 -> 0.66825607 | E4: =Центрум!J8 -> 1254183 | F4: =Центрум!M8 -> 0.66825607 | G4: =Рогалевич!N8 -> #DIV/0! | H4: =Рогалевич!M8 -> #DIV/0! | I4: =Рогалевич!P8 -> #DIV/0! | J4: =Маркова!N8 -> 0.34306653 | K4: =Маркова!M8 -> 191420 | L4: =Маркова!P8 -> 0.34306653 | M4: =Бешлиева!N8 -> 0.59231937 | N4: =Бешлиева!M8 -> 540810 | O4: =Бешлиева!P8 -> 0.59231937
A5: Кол-во изделий | D5: =Центрум!K9 -> 0.58455882 | E5: =Центрум!J9 -> 159 | F5: =Центрум!M9 -> 0.58455882 | G5: =Рогалевич!N9 -> #DIV/0! | H5: =Рогалевич!M9 -> #DIV/0! | I5: =Рогалевич!P9 -> #DIV/0! | J5: =Маркова!N9 -> 0.38335561 | K5: =Маркова!M9 -> 31 | L5: =Маркова!P9 -> 0.38335561 | M5: =Бешлиева!N9 -> 0.60457516 | N5: =Бешлиева!M9 -> 80 | O5: =Бешлиева!P9 -> 0.60457516
A6: Средний чек | D6: =Центрум!K10 -> 1.3365121 | E6: =Центрум!J10 -> 15677.288 | F6: =Центрум!M10 -> 1.3365121 | G6: =Рогалевич!N10 -> 53514.125 | H6: =Рогалевич!M10 -> 5.562159 | I6: =Рогалевич!P10 | J6: =Маркова!N10 -> 0.74176548 | K6: =Маркова!M10 -> 8700.9091 | L6: =Маркова!P10 -> 0.74176548 | M6: =Бешлиева!N10 -> 0.92209719 | N6: =Бешлиева!M10 -> 10816.2 | O6: =Бешлиева!P10 -> 0.92209719
A7: Средняя стоимость изделия | D7: =Центрум!K11 -> 1.1431802 | E7: =Центрум!J11 -> 7887.9434 | F7: =Центрум!M11 -> 1.1431802 | G7: =Рогалевич!N11 -> #DIV/0! | H7: =Рогалевич!M11 -> #DIV/0! | I7: =Рогалевич!P11 -> #DIV/0! | J7: =Маркова!N11 -> 0.89490416 | K7: =Маркова!M11 -> 6174.8387 | L7: =Маркова!P11 -> 0.89490416 | M7: =Бешлиева!N11 -> 0.97972826 | N7: =Бешлиева!M11 -> 6760.125 | O7: =Бешлиева!P11 -> 0.97972826
A8: Длина чека | D8: =Центрум!K12 -> 1.1691176 | E8: =Центрум!J12 -> 1.9875 | F8: =Центрум!M12 -> 1.1691176 | G8: =Рогалевич!N12 -> 4.3 | H8: =Рогалевич!M12 -> 3.5294118 | I8: =Рогалевич!P12 | J8: =Маркова!N12 -> 0.82887701 | K8: =Маркова!M12 -> 1.4090909 | L8: =Маркова!P12 -> 0.82887701 | M8: =Бешлиева!N12 -> 0.94117647 | N8: =Бешлиева!M12 -> 1.6 | O8: =Бешлиева!P12 -> 0.94117647
A9: Кол-во чеков | D9: =Центрум!K13 -> 0.5 | E9: =Центрум!J13 -> 80 | F9: =Центрум!M13 -> 0.5 | G9: =Рогалевич!N13 -> #DIV/0! | H9: =Рогалевич!M13 -> #DIV/0! | I9: =Рогалевич!P13 -> #DIV/0! | J9: =Маркова!N13 -> 0.4625 | K9: =Маркова!M13 -> 22 | L9: =Маркова!P13 -> 0.4625 | M9: =Бешлиева!N13 -> 0.64236111 | N9: =Бешлиева!M13 -> 50 | O9: =Бешлиева!P13 -> 0.64236111
A10: Кол-во смен план/отработано | D10: =Центрум!K14 -> 1 | E10: =Центрум!J14 -> 30 | G10: =Рогалевич!N14 -> #DIV/0! | H10: =Рогалевич!M14 -> #DIV/0! | I10: =Рогалевич!P14 -> #DIV/0! | J10: =Маркова!N14 -> 1 | K10: =Маркова!M14 -> 11 | M10: =Бешлиева!N14 -> 1 | N10: =Бешлиева!M14 -> 18 | O10: =Бешлиева!P14 -> 0
A11: Средние продажи в смену | D11: =Центрум!K15 -> 0.66825607 | E11: =Центрум!J15 -> 41806.1 | F11: =Центрум!M15 -> 0.66825607 | G11: =Рогалевич!N15 -> -10364.7 | H11: =Рогалевич!M15 -> 0.83432385 | I11: =Рогалевич!P15 | J11: =Маркова!N15 -> 0.55632411 | K11: =Маркова!M15 -> 17401.818 | L11: =Маркова!P15 -> 0.55632411 | M11: =Бешлиева!N15 -> 0.9605179 | N11: =Бешлиева!M15 -> 30045 | O11: =Бешлиева!P15 -> 0.9605179
A12: Трафик | D12: =Центрум!K17 -> 0.65078125 | E12: =Центрум!J17 -> 1041.25 | F12: =Центрум!M17 -> 0.65078125 | G12: =Рогалевич!N17 | H12: =Рогалевич!M17 | I12: =Рогалевич!P17 | J12: =Маркова!N17 -> 0.42381818 | K12: =Маркова!M17 -> 201.6 | L12: =Маркова!P17 -> 0.42381818 | M12: =Бешлиева!N17 -> 0.54472222 | N12: =Бешлиева!M17 -> 424 | O12: =Бешлиева!P17 -> 0.54472222
A13: ='[1]Ялта, Ленина, 18'!F18 -> Выручка на вошедшего | D13: =Центрум!K18 -> 1.0268521 | E13: =Центрум!J18 -> 1204.4975 | F13: ='[1]Ялта, Ленина, 18'!M18 -> 0.75390061 | G13: =Рогалевич!N18 -> #DIV/0! | H13: =Рогалевич!M18 -> #DIV/0! | I13: =Рогалевич!P18 | J13: =Маркова!N18 -> 0.8094663 | K13: =Маркова!M18 -> 949.50397 | L13: =Маркова!P18 -> 0.8094663 | M13: =Бешлиева!N18 -> 1.0873788 | N13: =Бешлиева!M18 -> 1275.4953 | O13: =Бешлиева!P18 -> 1.0873788
A14: ='[1]Ялта, Ленина, 18'!F20 -> Конверсия план/факт | D14: =Центрум!K20 -> 0.76830732 | E14: =Центрум!J20 -> 0.076830732 | G14: =Рогалевич!N20 -> -0.0061249965 | H14: =Рогалевич!M20 -> 0.93875003 | J14: =Маркова!N20 -> 1.0912698 | K14: =Маркова!M20 -> 0.10912698 | L14: =Маркова!T13 | M14: =Бешлиева!N20 -> 1.1792453 | N14: =Бешлиева!M20 -> 0.11792453
A15: Доп. KPI | D15: =Центрум!L56+Центрум!S56 -> 53655.17 | G15: =[1]Рогалевич!R57 -> 0 | J15: =[1]Уразгильдеева!R57 -> 0 | M15: =Бешлиева!L48+Бешлиева!S48 -> 37218

Sheet План на день
A1: Выручка | D1: =86000 -> 86000
A2: Кол-во изделий | D2: =D1/D4 -> 12.463768
A3: Средний чек | D3: =D4*D5 -> 11730
A4: Средняя стоимость изделия | D4: =Центрум!I11 -> 6900
A5: Длина чека | D5: =Центрум!I12 -> 1.7
A6: Кол-во чеков | D6: =IF(D5<>0,D2/D5,"") -> 7.3316283
A7: Конверсия | D7: =Центрум!I20 -> 0.1

Sheet Рогалевич
C1: =TODAY()-1 -> 46151
C2: (отчетная дата) | J2: ЕЖЕДНЕВНЫЙ ОТЧЕТ О ПРОДАЖАХ
C3: Осталось до выполнения плана!!! | J3: =График!B28 -> Рогалевич Ирина
C4: =I8-D48 -> -116158.41 | E4: =IF(I8<>0,C4/I8,0) -> -0.28624927
F6: Целевые показатели
F7: Показатель | I7: План | J7: Факт | K7: % выполнения | L7: Прогноз выполнения | M7: % выполнения по прогнозу | N7: Отклонение | O7: Факт аналогичного месяца прошлого года | P7: Отклонение LFL
F8: Выручка | I8: =Центрум!I8/График!AJ29*График!AJ28 -> 405794.59 | J8: =D48 -> 521953 | K8: =IF(AND(I8<>"",I8<>0,J8<>""),J8/I8,"") -> 1.2862493 | L8: =IF(SUMIF($D$25:$D$47,">=0",$V$25:$V$47)<>0,I8*D48/SUMIF($D$25:$D$47,">=0",$V$25:$V$47),0) -> #DIV/0! | M8: =L8/I8 -> #DIV/0! | N8: =IF(AND(J8<>0,J8<>"",I8<>0,I8<>""),L8-I8,"") -> #DIV/0! | P8: =IF(AND(O8<>"",O8<>0,L8<>"",L8<>0),-O8+L8,"") -> #DIV/0! | Q8: =IF(AND(P8<>"",P8<>0,O8<>0,O8<>""),P8/O8,"") -> #DIV/0!
F9: Кол-во изделий | I9: =I8/I11 -> 58.810811 | J9: =E48 -> 48 | K9: =IF(AND(I9<>"",I9<>0,J9<>""),J9/I9,"") -> 0.81617647 | L9: =IF(SUMIF($E$25:$E$47,">=0",$W$25:$W$47)<>0,I9*E48/SUMIF($E$25:$E$47,">=0",$W$25:$W$47),0) -> #DIV/0! | M9: =IF(AND(I9<>"",I9<>0,L9<>"",L9<>0),L9/I9,"") -> #DIV/0! | N9: =IF(AND(J9<>0,J9<>"",I9<>0,I9<>""),L9-I9,"") -> #DIV/0! | P9: =IF(AND(O9<>"",O9<>0,L9<>"",L9<>0),-O9+L9,"") -> #DIV/0! | Q9: =IF(AND(P9<>"",P9<>0,O9<>0,O9<>""),P9/O9,"") -> #DIV/0!
F10: Средний чек | I10: =I11*I12 -> 11730 | J10: =H48 -> 65244.125 | K10: =IF(AND(I10<>"",I10<>0,J10<>""),J10/I10,"") -> 5.562159 | L10: =J10 -> 65244.125 | M10: =IF(AND(I10<>"",I10<>0,L10<>"",L10<>0),L10/I10,"") -> 5.562159 | N10: =IF(AND(J10<>0,J10<>"",I10<>0,I10<>""),L10-I10,"") -> 53514.125 | O10: =O11*O12 -> 0 | P10: =IF(AND(O10<>"",O10<>0,L10<>"",L10<>0),-O10+L10,"") | Q10: =IF(AND(P10<>"",P10<>0,O10<>0,O10<>""),P10/O10,"")
F11: Средняя стоимость изделия | I11: =Центрум!I11 -> 6900 | J11: =F48 -> 10874.021 | K11: =IF(AND(I11<>"",I11<>0,J11<>""),J11/I11,"") -> 1.575945 | L11: =IF(L9>0,L8/L9,"") -> #DIV/0! | M11: =IF(AND(I11<>"",I11<>0,L11<>"",L11<>0),L11/I11,"") -> #DIV/0! | N11: =IF(AND(J11<>0,J11<>"",I11<>0,I11<>""),L11-I11,"") -> #DIV/0! | P11: =IF(AND(O11<>"",O11<>0,L11<>"",L11<>0),-O11+L11,"") -> #DIV/0! | Q11: =IF(AND(P11<>"",P11<>0,O11<>0,O11<>""),P11/O11,"") -> #DIV/0!
F12: Длина чека | I12: =Центрум!I12 -> 1.7 | J12: =J48 -> 6 | K12: =IF(AND(I12<>"",I12<>0,J12<>""),J12/I12,"") -> 3.5294118 | L12: =J12 -> 6 | M12: =IF(AND(I12<>"",I12<>0,L12<>"",L12<>0),L12/I12,"") -> 3.5294118 | N12: =IF(AND(J12<>0,J12<>"",I12<>0,I12<>""),L12-I12,"") -> 4.3 | P12: =IF(AND(O12<>"",O12<>0,L12<>"",L12<>0),-O12+L12,"") | Q12: =IF(AND(P12<>"",P12<>0,O12<>0,O12<>""),P12/O12,"")
F13: Кол-во чеков | I13: =IF(I12<>0,I9/I12,"") -> 34.594595 | J13: =G48 -> 8 | K13: =IF(AND(I13<>"",I13<>0,J13<>""),J13/I13,"") -> 0.23125 | L13: =IF(SUMIF($G$25:$G$47,">=0",$X$25:$X$47)<>0,I13*G48/SUMIF($G$25:$G$47,">=0",$X$25:$X$47),"") -> #DIV/0! | M13: =IF(AND(I13<>"",I13<>0,L13<>"",L13<>0),L13/I13,"") -> #DIV/0! | N13: =IF(AND(J13<>0,J13<>"",I13<>0,I13<>""),L13-I13,"") -> #DIV/0! | P13: =IF(AND(O13<>"",O13<>0,L13<>"",L13<>0),-O13+L13,"") -> #DIV/0! | Q13: =IF(AND(P13<>"",P13<>0,O13<>0,O13<>""),P13/O13,"") -> #DIV/0!
F14: Кол-во смен | I14: =График!AI28 -> 10 | J14: 10 | K14: =IF(AND(I14<>"",I14<>0,J14<>""),J14/I14,"") -> 1 | L14: =IF(SUMIF($D$25:$D$47,">=0",$V$25:$V$47),I48*I8/SUMIF($D$25:$D$47,">=0",$V$25:$V$47),"") -> #DIV/0! | M14: =IF(AND(I14<>"",I14<>0,L14<>"",L14<>0),L14/I14,"") -> #DIV/0! | N14: =IF(AND(J14<>0,J14<>"",I14<>0,I14<>""),L14-I14,"") -> #DIV/0! | P14: =IF(AND(O14<>"",O14<>0,L14<>"",L14<>0),-O14+L14,"") -> #DIV/0! | Q14: =IF(AND(P14<>"",P14<>0,O14<>0,O14<>""),P14/O14,"") -> #DIV/0!
F15: Средние продажи в смену | I15: =Центрум!I15 -> 62560 | J15: =J8/J14 -> 52195.3 | K15: =IF(AND(I15<>"",I15<>0,J15<>""),J15/I15,"") -> 0.83432385 | L15: =J15 -> 52195.3 | M15: =IF(AND(I15<>"",I15<>0,L15<>"",L15<>0),L15/I15,"") -> 0.83432385 | N15: =IF(AND(J15<>0,J15<>"",I15<>0,I15<>""),L15-I15,"") -> -10364.7 | P15: =IF(AND(O15<>"",O15<>0,L15<>"",L15<>0),-O15+L15,"") | Q15: =IF(AND(P15<>"",P15<>0,O15<>0,O15<>""),P15/O15,"")
F16: Отставание/Перевыполнение | J16: =J8-I15*J14 -> -103647 | K16: =IF(AND(I16<>"",I16<>0,J16<>""),J16/I16,"") | L16: =J16 -> -103647 | M16: =IF(AND(I16<>"",I16<>0,L16<>"",L16<>0),L16/I16,"") | N16: =IF(AND(J16<>0,J16<>"",I16<>0,I16<>""),L16-I16,"") | P16: =IF(AND(O16<>"",O16<>0,L16<>"",L16<>0),-O16+L16,"") | Q16: =IF(AND(P16<>"",P16<>0,O16<>0,O16<>""),P16/O16,"") | S16: Подарочные сертификаты
F17: Трафик | I17: =Центрум!I17/График!AJ29*График!AJ25 -> 0 | J17: =I48 -> 84 | K17: =IF(AND(I17<>"",I17<>0,J17<>""),J17/I17,"") | L17: =J17/J14*I14 -> 84 | M17: =IF(AND(I17<>"",I17<>0,L17<>"",L17<>0),L17/I17,"") | N17: =IF(AND(J17<>0,J17<>"",I17<>0,I17<>""),L17-I17,"") | P17: =IF(AND(O17<>"",O17<>0,L17<>"",L17<>0),-O17+L17,"") | Q17: =IF(AND(P17<>"",P17<>0,O17<>0,O17<>""),P17/O17,"")
F18: Выручка на вошедшего | I18: =I8/I17 -> #DIV/0! | J18: =J8/J17 -> 6213.7262 | K18: =IF(AND(I18<>"",I18<>0,J18<>""),J18/I18,"") -> #DIV/0! | L18: =J18 -> 6213.7262 | M18: =IF(AND(I18<>"",I18<>0,L18<>"",L18<>0),L18/I18,"") -> #DIV/0! | N18: =IF(AND(J18<>0,J18<>"",I18<>0,I18<>""),L18-I18,"") -> #DIV/0! | O18: 0 | P18: =IF(AND(O18<>"",O18<>0,L18<>"",L18<>0),-O18+L18,"") | Q18: =IF(AND(P18<>"",P18<>0,O18<>0,O18<>""),P18/O18,"")
J19: =Q48 -> 0 | K19: =IF(AND(I19<>"",I19<>0,J19<>""),J19/I19,"") | L19: =J19 -> 0 | M19: =IF(AND(I19<>"",I19<>0,L19<>"",L19<>0),L19/I19,"") | N19: =IF(AND(J19<>0,J19<>"",I19<>0,I19<>""),L19-I19,"") | O19: 0 | P19: =IF(AND(O19<>"",O19<>0,L19<>"",L19<>0),-O19+L19,"") | Q19: =IF(AND(P19<>"",P19<>0,O19<>0,O19<>""),P19/O19,"") | S19: =S18/I16 -> #DIV/0!
F20: Конверсия | I20: =Центрум!I20 -> 0.1 | J20: =T48 -> 0.095238095 | K20: =J20/I20 -> 0.95238095 | L20: =IF(AND(K8<>0,I14<>0,I48<>0),(I48*T48+(I48/K8-I48)*I20)/(I48/K8),0) -> 0.093875003 | M20: =IF(AND(I20<>"",I20<>0,L20<>"",L20<>0),L20/I20,"") -> 0.93875003 | N20: =IF(AND(J20<>0,J20<>"",I20<>0,I20<>""),L20-I20,"") -> -0.0061249965 | P20: =IF(AND(O20<>"",O20<>0,L20<>"",L20<>0),-O20+L20,"") | Q20: =IF(AND(P20<>"",P20<>0,O20<>0,O20<>""),P20/O20,"")
A22: Факт продаж за месяц | V22: Раcпределение плана по дням
B23: Дата | C23: День недели | D23: Выручка (руб) | E23: Кол-во единиц (шт.) | F23: Средняя стоимость изделия (руб.) | G23: Количество чеков (шт.) | H23: Средняя сумма чека (руб.) | I23: Трафик | J23: Длина чека (шт.) | K23: UNOde50 | L23: IS | M23: Agafi | N23: Kalliope | O23: Raganella | P23: CC/MP | Q23: Eva Rites | R23: Antura | S23: SALE | T23: Конверсия (%) | U23: % выполнения дневного плана | V23: выручка, план | W23: кол-во ед, план | X23: Кол-во чеков, план | Y23: выручка, скорректир.план | Z23: кол-во ед, скорр. план | AA23: кол-во чеков, скорр. план | AB23: Коэфф. Дня Недели | AC23: Специфика месяца
B24: 1 | C24: 2 | D24: 3 | E24: в | F24: 5 | G24: 6 | H24: 7 | I24: 8 | J24: 9 | K24: 10 | L24: 11 | M24: 12 | N24: 13 | O24: 14 | P24: 15 | Q24: 16 | R24: 17 | S24: 18 | T24: 19 | V24: 1 | W24: 2 | X24: 3 | Y24: 4 | Z24: 5 | AA24: 6 | AB24: 10 | AC24: 11
A25: 1 | B25: 46118 | C25: пн | D25: 0 | E25: 0 | F25: 0 | G25: 0 | H25: 0 | J25: =IF(AND(G25<>"",G25<>0),E25/G25,"") | T25: =IF(AND(I25<>"",I25<>0),G25/I25,"") | U25: =D25/V25 -> #DIV/0! | V25: =$I$8*AB25*AC25/SUMPRODUCT($AC$25:$AC$55,$AB$25:$AB$55) -> #DIV/0! | W25: =$I$9*AB25*AC25/SUMPRODUCT($AC$25:$AC$55,$AB$25:$AB$55) -> #DIV/0! | X25: =IF($I$12="","",W25/$I$12) -> #DIV/0! | Y25: =IF(AC25<>"",IF(D25<>"",D25,($I$8-SUM($Y24:Y$25))*AB25*AC25/SUMPRODUCT($AC25:$AC$55,$AB25:$AB$55)),"") | Z25: =IF(AC25<>"",IF(E25<>"",E25,($I$9-SUM($Z24:Z$25))*AB25*AC25/SUMPRODUCT($AC25:$AC$55,$AB25:$AB$55)),"") | AA25: =IF(AC25<>"",IF($I$12<>"",IF(G25<>"",G25,($I$9/$I$12-SUM($AA24:AA$25))*AB25*AC25/SUMPRODUCT($AC25:$AC$55,$AB25:$AB$55)),""),"")
A26: 2 | B26: 46119 | C26: вт | D26: 0 | E26: 0 | F26: 0 | G26: 0 | H26: 0 | I26: 8 | J26: =IF(AND(G26<>"",G26<>0),E26/G26,"") | T26: =IF(AND(I26<>"",I26<>0),G26/I26,"") -> 0 | U26: =D26/V26 -> #DIV/0! | V26: =$I$8*AB26*AC26/SUMPRODUCT($AC$25:$AC$55,$AB$25:$AB$55) -> #DIV/0! | W26: =$I$9*AB26*AC26/SUMPRODUCT($AC$25:$AC$55,$AB$25:$AB$55) -> #DIV/0! | X26: =IF($I$12="","",W26/$I$12) -> #DIV/0! | Y26: =IF(AC26<>"",IF(D26<>"",D26,($I$8-SUM($Y$25:Y25))*AB26*AC26/SUMPRODUCT($AC26:$AC$55,$AB26:$AB$55)),"") | Z26: =IF(AC26<>"",IF(E26<>"",E26,($I$9-SUM($Z$25:Z25))*AB26*AC26/SUMPRODUCT($AC26:$AC$55,$AB26:$AB$55)),"") | AA26: =IF(AC26<>"",IF($I$12<>"",IF(G26<>"",G26,($I$9/$I$12-SUM($AA$25:AA25))*AB26*AC26/SUMPRODUCT($AC26:$AC$55,$AB26:$AB$55)),""),"")
A27: 3 | B27: 46120 | C27: ср | D27: 21072 | E27: 3 | F27: =IF(AND(E27<>"",E27<>0),D27/E27,"") -> 7024 | G27: 2 | H27: =IF(AND(G27<>"",G27<>0),D27/G27,"") -> 10536 | I27: 20 | J27: =IF(AND(G27<>"",G27<>0),E27/G27,"") -> 1.5 | T27: =IF(AND(I27<>"",I27<>0),G27/I27,"") -> 0.1 | U27: =D27/V27 -> #DIV/0! | V27: =$I$8*AB27*AC27/SUMPRODUCT($AC$25:$AC$55,$AB$25:$AB$55) -> #DIV/0! | W27: =$I$9*AB27*AC27/SUMPRODUCT($AC$25:$AC$55,$AB$25:$AB$55) -> #DIV/0! | X27: =IF($I$12="","",W27/$I$12) -> #DIV/0! | Y27: =IF(AC27<>"",IF(D27<>"",D27,($I$8-SUM($Y$25:Y26))*AB27*AC27/SUMPRODUCT($AC27:$AC$55,$AB27:$AB$55)),"") | Z27: =IF(AC27<>"",IF(E27<>"",E27,($I$9-SUM($Z$25:Z26))*AB27*AC27/SUMPRODUCT($AC27:$AC$55,$AB27:$AB$55)),"") | AA27: =IF(AC27<>"",IF($I$12<>"",IF(G27<>"",G27,($I$9/$I$12-SUM($AA$25:AA26))*AB27*AC27/SUMPRODUCT($AC27:$AC$55,$AB27:$AB$55)),""),"")
A28: 4 | B28: 46121 | C28: чт | D28: 12200 | E28: 2 | F28: =IF(AND(E28<>"",E28<>0),D28/E28,"") -> 6100 | G28: 1 | H28: =IF(AND(G28<>"",G28<>0),D28/G28,"") -> 12200 | I28: 15 | J28: =IF(AND(G28<>"",G28<>0),E28/G28,"") -> 2 | T28: =IF(AND(I28<>"",I28<>0),G28/I28,"") -> 0.066666667 | U28: =D28/V28 -> #DIV/0! | V28: =$I$8*AB28*AC28/SUMPRODUCT($AC$25:$AC$55,$AB$25:$AB$55) -> #DIV/0! | W28: =$I$9*AB28*AC28/SUMPRODUCT($AC$25:$AC$55,$AB$25:$AB$55) -> #DIV/0! | X28: =IF($I$12="","",W28/$I$12) -> #DIV/0! | Y28: =IF(AC28<>"",IF(D28<>"",D28,($I$8-SUM($Y$25:Y27))*AB28*AC28/SUMPRODUCT($AC28:$AC$55,$AB28:$AB$55)),"") | Z28: =IF(AC28<>"",IF(E27<>"",E27,($I$9-SUM($Z$25:Z27))*AB28*AC28/SUMPRODUCT($AC28:$AC$55,$AB28:$AB$55)),"") | AA28: =IF(AC28<>"",IF($I$12<>"",IF(G28<>"",G28,($I$9/$I$12-SUM($AA$25:AA27))*AB28*AC28/SUMPRODUCT($AC28:$AC$55,$AB28:$AB$55)),""),"")
A29: 5 | B29: 46122 | C29: пт | D29: 0 | E29: 0 | F29: 0 | G29: 0 | H29: =IF(AND(G29<>"",G29<>0),D29/G29,"") | I29: 15 | J29: =IF(AND(G29<>"",G29<>0),E29/G29,"") | T29: =IF(AND(I29<>"",I29<>0),G29/I29,"") -> 0 | U29: =D29/V29 -> #DIV/0! | V29: =$I$8*AB29*AC29/SUMPRODUCT($AC$25:$AC$55,$AB$25:$AB$55) -> #DIV/0! | W29: =$I$9*AB29*AC29/SUMPRODUCT($AC$25:$AC$55,$AB$25:$AB$55) -> #DIV/0! | X29: =IF($I$12="","",W29/$I$12) -> #DIV/0! | Y29: =IF(AC29<>"",IF(D29<>"",D29,($I$8-SUM($Y$25:Y28))*AB29*AC29/SUMPRODUCT($AC29:$AC$55,$AB29:$AB$55)),"") | Z29: =IF(AC29<>"",IF(E29<>"",E29,($I$9-SUM($Z$25:Z28))*AB29*AC29/SUMPRODUCT($AC29:$AC$55,$AB29:$AB$55)),"") | AA29: =IF(AC29<>"",IF($I$12<>"",IF(G29<>"",G29,($I$9/$I$12-SUM($AA$25:AA28))*AB29*AC29/SUMPRODUCT($AC29:$AC$55,$AB29:$AB$55)),""),"")
A30: 6 | B30: 46132 | C30: пн | D30: 0 | E30: 0 | F30: 0 | G30: 0 | H30: 0 | I30: 10 | J30: =IF(AND(G30<>"",G30<>0),E30/G30,"") | T30: =IF(AND(I30<>"",I30<>0),G30/I30,"") -> 0 | U30: =D30/V30 -> #DIV/0! | V30: =$I$8*AB30*AC30/SUMPRODUCT($AC$25:$AC$55,$AB$25:$AB$55) -> #DIV/0! | W30: =$I$9*AB30*AC30/SUMPRODUCT($AC$25:$AC$55,$AB$25:$AB$55) -> #DIV/0! | X30: =IF($I$12="","",W30/$I$12) -> #DIV/0! | Y30: =IF(AC30<>"",IF(D30<>"",D30,($I$8-SUM($Y$25:Y29))*AB30*AC30/SUMPRODUCT($AC30:$AC$55,$AB30:$AB$55)),"") | Z30: =IF(AC30<>"",IF(E30<>"",E30,($I$9-SUM($Z$25:Z29))*AB30*AC30/SUMPRODUCT($AC30:$AC$55,$AB30:$AB$55)),"") | AA30: =IF(AC30<>"",IF($I$12<>"",IF(G30<>"",G30,($I$9/$I$12-SUM($AA$25:AA29))*AB30*AC30/SUMPRODUCT($AC30:$AC$55,$AB30:$AB$55)),""),"")
A31: 7 | B31: 46133 | C31: вт | D31: 0 | E31: 0 | F31: 0 | G31: 0 | H31: 0 | I31: 7 | J31: =IF(AND(G31<>"",G31<>0),E31/G31,"") | T31: =IF(AND(I31<>"",I31<>0),G31/I31,"") -> 0 | U31: =D31/V31 -> #DIV/0! | V31: =$I$8*AB31*AC31/SUMPRODUCT($AC$25:$AC$55,$AB$25:$AB$55) -> #DIV/0! | W31: =$I$9*AB31*AC31/SUMPRODUCT($AC$25:$AC$55,$AB$25:$AB$55) -> #DIV/0! | X31: =IF($I$12="","",W31/$I$12) -> #DIV/0! | Y31: =IF(AC31<>"",IF(D31<>"",D31,($I$8-SUM($Y$25:Y30))*AB31*AC31/SUMPRODUCT($AC31:$AC$55,$AB31:$AB$55)),"") | Z31: =IF(AC31<>"",IF(E31<>"",E31,($I$9-SUM($Z$25:Z30))*AB31*AC31/SUMPRODUCT($AC31:$AC$55,$AB31:$AB$55)),"") | AA31: =IF(AC31<>"",IF($I$12<>"",IF(G31<>"",G31,($I$9/$I$12-SUM($AA$25:AA30))*AB31*AC31/SUMPRODUCT($AC31:$AC$55,$AB31:$AB$55)),""),"")
A32: 8 | B32: 46134 | C32: ср | D32: 34650 | E32: 6 | F32: =IF(AND(E32<>"",E32<>0),D32/E32,"") -> 5775 | G32: 2 | H32: =IF(AND(G32<>"",G32<>0),D32/G32,"") -> 17325 | I32: 13 | J32: =IF(AND(G32<>"",G32<>0),E32/G32,"") -> 3 | T32: =IF(AND(I32<>"",I32<>0),G32/I32,"") -> 0.15384615 | U32: =D32/V32 -> #DIV/0! | V32: =$I$8*AB32*AC32/SUMPRODUCT($AC$25:$AC$55,$AB$25:$AB$55) -> #DIV/0! | W32: =$I$9*AB32*AC32/SUMPRODUCT($AC$25:$AC$55,$AB$25:$AB$55) -> #DIV/0! | X32: =IF($I$12="","",W32/$I$12) -> #DIV/0! | Y32: =IF(AC32<>"",IF(D32<>"",D32,($I$8-SUM($Y$25:Y31))*AB32*AC32/SUMPRODUCT($AC32:$AC$55,$AB32:$AB$55)),"") | Z32: =IF(AC32<>"",IF(E32<>"",E32,($I$9-SUM($Z$25:Z31))*AB32*AC32/SUMPRODUCT($AC32:$AC$55,$AB32:$AB$55)),"") | AA32: =IF(AC32<>"",IF($I$12<>"",IF(G32<>"",G32,($I$9/$I$12-SUM($AA$25:AA31))*AB32*AC32/SUMPRODUCT($AC32:$AC$55,$AB32:$AB$55)),""),"")
A33: 9 | B33: 46135 | C33: чт | D33: 0 | E33: 0 | F33: 0 | G33: 0 | H33: 0 | I33: 0 | J33: =IF(AND(G33<>"",G33<>0),E33/G33,"") | T33: =IF(AND(I33<>"",I33<>0),G33/I33,"") | U33: =D33/V33 -> #DIV/0! | V33: =$I$8*AB33*AC33/SUMPRODUCT($AC$25:$AC$55,$AB$25:$AB$55) -> #DIV/0! | W33: =$I$9*AB33*AC33/SUMPRODUCT($AC$25:$AC$55,$AB$25:$AB$55) -> #DIV/0! | X33: =IF($I$12="","",W33/$I$12) -> #DIV/0! | Y33: =IF(AC33<>"",IF(D33<>"",D33,($I$8-SUM($Y$25:Y32))*AB33*AC33/SUMPRODUCT($AC33:$AC$55,$AB33:$AB$55)),"") | Z33: =IF(AC33<>"",IF(E33<>"",E33,($I$9-SUM($Z$25:Z32))*AB33*AC33/SUMPRODUCT($AC33:$AC$55,$AB33:$AB$55)),"") | AA33: =IF(AC33<>"",IF($I$12<>"",IF(G33<>"",G33,($I$9/$I$12-SUM($AA$25:AA32))*AB33*AC33/SUMPRODUCT($AC33:$AC$55,$AB33:$AB$55)),""),"")
A34: 10 | B34: 46142 | C34: чт | D34: 454031 | E34: 37 | F34: =IF(AND(E34<>"",E34<>0),D34/E34,"") -> 12271.108 | G34: 3 | H34: =IF(AND(G34<>"",G34<>0),D34/G34,"") -> 151343.67 | I34: 17 | J34: =IF(AND(G34<>"",G34<>0),E34/G34,"") -> 12.333333 | N34: 227591 | O34: 190704 | P34: 26543 | T34: =IF(AND(I34<>"",I34<>0),G34/I34,"") -> 0.17647059 | U34: =D34/V34 -> #DIV/0! | V34: =$I$8*AB34*AC34/SUMPRODUCT($AC$25:$AC$55,$AB$25:$AB$55) -> #DIV/0! | W34: =$I$9*AB34*AC34/SUMPRODUCT($AC$25:$AC$55,$AB$25:$AB$55) -> #DIV/0! | X34: =IF($I$12="","",W34/$I$12) -> #DIV/0! | Y34: =IF(AC34<>"",IF(D34<>"",D34,($I$8-SUM($Y$25:Y33))*AB34*AC34/SUMPRODUCT($AC34:$AC$55,$AB34:$AB$55)),"") | Z34: =IF(AC34<>"",IF(E34<>"",E34,($I$9-SUM($Z$25:Z33))*AB34*AC34/SUMPRODUCT($AC34:$AC$55,$AB34:$AB$55)),"") | AA34: =IF(AC34<>"",IF($I$12<>"",IF(G34<>"",G34,($I$9/$I$12-SUM($AA$25:AA33))*AB34*AC34/SUMPRODUCT($AC34:$AC$55,$AB34:$AB$55)),""),"")
A35: 11 | F35: =IF(AND(E35<>"",E35<>0),D35/E35,"") | H35: =IF(AND(G35<>"",G35<>0),D35/G35,"") | J35: =IF(AND(G35<>"",G35<>0),E35/G35,"") | T35: =IF(AND(I35<>"",I35<>0),G35/I35,"") | U35: =D35/V35 -> #DIV/0! | V35: =$I$8*AB35*AC35/SUMPRODUCT($AC$25:$AC$55,$AB$25:$AB$55) -> #DIV/0! | W35: =$I$9*AB35*AC35/SUMPRODUCT($AC$25:$AC$55,$AB$25:$AB$55) -> #DIV/0! | X35: =IF($I$12="","",W35/$I$12) -> #DIV/0! | Y35: =IF(AC35<>"",IF(D35<>"",D35,($I$8-SUM($Y$25:Y34))*AB35*AC35/SUMPRODUCT($AC35:$AC$55,$AB35:$AB$55)),"") | Z35: =IF(AC34<>"",IF(E34<>"",E34,($I$9-SUM($Z$25:Z33))*AB34*AC34/SUMPRODUCT($AC34:$AC$55,$AB34:$AB$55)),"") | AA35: =IF(AC34<>"",IF($I$12<>"",IF(G34<>"",G34,($I$9/$I$12-SUM($AA$25:AA33))*AB34*AC34/SUMPRODUCT($AC34:$AC$55,$AB34:$AB$55)),""),"")
A36: 12 | F36: =IF(AND(E36<>"",E36<>0),D36/E36,"") | H36: =IF(AND(G36<>"",G36<>0),D36/G36,"") | J36: =IF(AND(G36<>"",G36<>0),E36/G36,"") | T36: =IF(AND(I36<>"",I36<>0),G36/I36,"") | U36: =D36/V36 -> #DIV/0! | V36: =$I$8*AB36*AC36/SUMPRODUCT($AC$25:$AC$55,$AB$25:$AB$55) -> #DIV/0! | W36: =$I$9*AB36*AC36/SUMPRODUCT($AC$25:$AC$55,$AB$25:$AB$55) -> #DIV/0! | X36: =IF($I$12="","",W36/$I$12) -> #DIV/0! | Y36: =IF(AC36<>"",IF(D36<>"",D36,($I$8-SUM($Y$25:Y35))*AB36*AC36/SUMPRODUCT($AC36:$AC$55,$AB36:$AB$55)),"") | Z36: =IF(AC36<>"",IF(E36<>"",E36,($I$9-SUM($Z$25:Z35))*AB36*AC36/SUMPRODUCT($AC36:$AC$55,$AB36:$AB$55)),"") | AA36: =IF(AC36<>"",IF($I$12<>"",IF(G36<>"",G36,($I$9/$I$12-SUM($AA$25:AA35))*AB36*AC36/SUMPRODUCT($AC36:$AC$55,$AB36:$AB$55)),""),"")
A37: 13 | F37: =IF(AND(E37<>"",E37<>0),D37/E37,"") | H37: =IF(AND(G37<>"",G37<>0),D37/G37,"") | J37: =IF(AND(G37<>"",G37<>0),E37/G37,"") | T37: =IF(AND(I37<>"",I37<>0),G37/I37,"") | U37: =D37/V37 -> #DIV/0! | V37: =$I$8*AB37*AC37/SUMPRODUCT($AC$25:$AC$55,$AB$25:$AB$55) -> #DIV/0! | W37: =$I$9*AB37*AC37/SUMPRODUCT($AC$25:$AC$55,$AB$25:$AB$55) -> #DIV/0! | X37: =IF($I$12="","",W37/$I$12) -> #DIV/0! | Y37: =IF(AC37<>"",IF(D37<>"",D37,($I$8-SUM($Y$25:Y36))*AB37*AC37/SUMPRODUCT($AC37:$AC$55,$AB37:$AB$55)),"") | Z37: =IF(AC37<>"",IF(E37<>"",E37,($I$9-SUM($Z$25:Z36))*AB37*AC37/SUMPRODUCT($AC37:$AC$55,$AB37:$AB$55)),"") | AA37: =IF(AC37<>"",IF($I$12<>"",IF(G37<>"",G37,($I$9/$I$12-SUM($AA$25:AA36))*AB37*AC37/SUMPRODUCT($AC37:$AC$55,$AB37:$AB$55)),""),"")
A38: 14 | F38: =IF(AND(E38<>"",E38<>0),D38/E38,"") | H38: =IF(AND(G38<>"",G38<>0),D38/G38,"") | J38: =IF(AND(G38<>"",G38<>0),E38/G38,"") | T38: =IF(AND(I38<>"",I38<>0),G38/I38,"") | U38: =D38/V38 -> #DIV/0! | V38: =$I$8*AB38*AC38/SUMPRODUCT($AC$25:$AC$46,$AB$25:$AB$46) -> #DIV/0! | W38: =$I$9*AB38*AC38/SUMPRODUCT($AC$25:$AC$46,$AB$25:$AB$46) -> #DIV/0! | X38: =IF($I$12="","",W38/$I$12) -> #DIV/0! | Y38: =IF(AC38<>"",IF(D38<>"",D38,($I$8-SUM($Y$25:Y37))*AB38*AC38/SUMPRODUCT($AC38:$AC$55,$AB38:$AB$55)),"") | Z38: =IF(AC38<>"",IF(E38<>"",E38,($I$9-SUM($Z$25:Z37))*AB38*AC38/SUMPRODUCT($AC38:$AC$55,$AB38:$AB$55)),"") | AA38: =IF(AC38<>"",IF($I$12<>"",IF(G38<>"",G38,($I$9/$I$12-SUM($AA$25:AA37))*AB38*AC38/SUMPRODUCT($AC38:$AC$55,$AB38:$AB$55)),""),"")
F39: =IF(AND(E39<>"",E39<>0),D39/E39,"") | H39: =IF(AND(G39<>"",G39<>0),D39/G39,"") | J39: =IF(AND(G39<>"",G39<>0),E39/G39,"") | T39: =IF(AND(I39<>"",I39<>0),G39/I39,"") | U39: =D39/V39 -> #DIV/0! | V39: =$I$8*AB39*AC39/SUMPRODUCT($AC$25:$AC$46,$AB$25:$AB$46) -> #DIV/0! | W39: =$I$9*AB39*AC39/SUMPRODUCT($AC$25:$AC$46,$AB$25:$AB$46) -> #DIV/0! | X39: =IF($I$12="","",W39/$I$12) -> #DIV/0! | Y39: =IF(AC39<>"",IF(D39<>"",D39,($I$8-SUM($Y$25:Y38))*AB39*AC39/SUMPRODUCT($AC39:$AC$47,$AB39:$AB$47)),"") | Z39: =IF(AC39<>"",IF(E39<>"",E39,($I$9-SUM($Z$25:Z38))*AB39*AC39/SUMPRODUCT($AC39:$AC$55,$AB39:$AB$55)),"") | AA39: =IF(AC39<>"",IF($I$12<>"",IF(G39<>"",G39,($I$9/$I$12-SUM($AA$25:AA38))*AB39*AC39/SUMPRODUCT($AC39:$AC$55,$AB39:$AB$55)),""),"")
F40: =IF(AND(E40<>"",E40<>0),D40/E40,"") | H40: =IF(AND(G40<>"",G40<>0),D40/G40,"") | J40: =IF(AND(G40<>"",G40<>0),E40/G40,"") | T40: =IF(AND(I40<>"",I40<>0),G40/I40,"") | U40: =D40/V40 -> #DIV/0! | V40: =$I$8*AB40*AC40/SUMPRODUCT($AC$25:$AC$46,$AB$25:$AB$46) -> #DIV/0! | W40: =$I$9*AB40*AC40/SUMPRODUCT($AC$25:$AC$46,$AB$25:$AB$46) -> #DIV/0! | X40: =IF($I$12="","",W40/$I$12) -> #DIV/0! | Y40: =IF(AC40<>"",IF(D40<>"",D40,($I$8-SUM($Y$25:Y39))*AB40*AC40/SUMPRODUCT($AC40:$AC$46,$AB40:$AB$46)),"") | Z40: =IF(AC40<>"",IF(E40<>"",E40,($I$9-SUM($Z$25:Z39))*AB40*AC40/SUMPRODUCT($AC40:$AC$46,$AB40:$AB$46)),"") | AA40: =IF(AC40<>"",IF($I$12<>"",IF(G40<>"",G40,($I$9/$I$12-SUM($AA$25:AA39))*AB40*AC40/SUMPRODUCT($AC40:$AC$55,$AB40:$AB$55)),""),"")
F41: =IF(AND(E41<>"",E41<>0),D41/E41,"") | H41: =IF(AND(G41<>"",G41<>0),D41/G41,"") | J41: =IF(AND(G41<>"",G41<>0),E41/G41,"") | T41: =IF(AND(I41<>"",I41<>0),G41/I41,"") | U41: =D41/V41 -> #DIV/0! | V41: =$I$8*AB41*AC41/SUMPRODUCT($AC$25:$AC$46,$AB$25:$AB$46) -> #DIV/0! | W41: =$I$9*AB41*AC41/SUMPRODUCT($AC$25:$AC$46,$AB$25:$AB$46) -> #DIV/0! | X41: =IF($I$12="","",W41/$I$12) -> #DIV/0! | Y41: =IF(AC41<>"",IF(D41<>"",D41,($I$8-SUM($Y$25:Y40))*AB41*AC41/SUMPRODUCT($AC41:$AC$46,$AB41:$AB$46)),"") | Z41: =IF(AC41<>"",IF(E41<>"",E41,($I$9-SUM($Z$25:Z40))*AB41*AC41/SUMPRODUCT($AC41:$AC$46,$AB41:$AB$46)),"") | AA41: =IF(AC41<>"",IF($I$12<>"",IF(G41<>"",G41,($I$9/$I$12-SUM($AA$25:AA40))*AB41*AC41/SUMPRODUCT($AC41:$AC$55,$AB41:$AB$55)),""),"")
F42: =IF(AND(E42<>"",E42<>0),D42/E42,"") | H42: =IF(AND(G42<>"",G42<>0),D42/G42,"") | J42: =IF(AND(G42<>"",G42<>0),E42/G42,"") | T42: =IF(AND(I42<>"",I42<>0),G42/I42,"") | U42: =D42/V42 -> #DIV/0! | V42: =$I$8*AB42*AC42/SUMPRODUCT($AC$25:$AC$46,$AB$25:$AB$46) -> #DIV/0! | W42: =$I$9*AB42*AC42/SUMPRODUCT($AC$25:$AC$46,$AB$25:$AB$46) -> #DIV/0! | X42: =IF($I$12="","",W42/$I$12) -> #DIV/0! | Y42: =IF(AC42<>"",IF(D42<>"",D42,($I$8-SUM($Y$25:Y41))*AB42*AC42/SUMPRODUCT($AC42:$AC$46,$AB42:$AB$46)),"") | Z42: =IF(AC42<>"",IF(E42<>"",E42,($I$9-SUM($Z$25:Z41))*AB42*AC42/SUMPRODUCT($AC42:$AC$46,$AB42:$AB$46)),"") | AA42: =IF(AC42<>"",IF($I$12<>"",IF(G42<>"",G42,($I$9/$I$12-SUM($AA$25:AA41))*AB42*AC42/SUMPRODUCT($AC42:$AC$46,$AB42:$AB$46)),""),"")
F43: =IF(AND(E43<>"",E43<>0),D43/E43,"") | H43: =IF(AND(G43<>"",G43<>0),D43/G43,"") | J43: =IF(AND(G43<>"",G43<>0),E43/G43,"") | T43: =IF(AND(I43<>"",I43<>0),G43/I43,"") | U43: =D43/V43 -> #DIV/0! | V43: =$I$8*AB43*AC43/SUMPRODUCT($AC$25:$AC$46,$AB$25:$AB$46) -> #DIV/0! | W43: =$I$9*AB43*AC43/SUMPRODUCT($AC$25:$AC$46,$AB$25:$AB$46) -> #DIV/0! | X43: =IF($I$12="","",W43/$I$12) -> #DIV/0! | Y43: =IF(AC43<>"",IF(D43<>"",D43,($I$8-SUM($Y$25:Y42))*AB43*AC43/SUMPRODUCT($AC43:$AC$46,$AB43:$AB$46)),"") | Z43: =IF(AC43<>"",IF(E43<>"",E43,($I$9-SUM($Z$25:Z42))*AB43*AC43/SUMPRODUCT($AC43:$AC$46,$AB43:$AB$46)),"") | AA43: =IF(AC43<>"",IF($I$12<>"",IF(G43<>"",G43,($I$9/$I$12-SUM($AA$25:AA42))*AB43*AC43/SUMPRODUCT($AC43:$AC$46,$AB43:$AB$46)),""),"")
F44: =IF(AND(E44<>"",E44<>0),D44/E44,"") | H44: =IF(AND(G44<>"",G44<>0),D44/G44,"") | J44: =IF(AND(G44<>"",G44<>0),E44/G44,"") | T44: =IF(AND(I44<>"",I44<>0),G44/I44,"") | U44: =D44/V44 -> #DIV/0! | V44: =$I$8*AB44*AC44/SUMPRODUCT($AC$25:$AC$46,$AB$25:$AB$46) -> #DIV/0! | W44: =$I$9*AB44*AC44/SUMPRODUCT($AC$25:$AC$46,$AB$25:$AB$46) -> #DIV/0! | X44: =IF($I$12="","",W44/$I$12) -> #DIV/0! | Y44: =IF(AC44<>"",IF(D44<>"",D44,($I$8-SUM($Y$25:Y43))*AB44*AC44/SUMPRODUCT($AC44:$AC$46,$AB44:$AB$46)),"") | Z44: =IF(AC44<>"",IF(E44<>"",E44,($I$9-SUM($Z$25:Z43))*AB44*AC44/SUMPRODUCT($AC44:$AC$46,$AB44:$AB$46)),"") | AA44: =IF(AC44<>"",IF($I$12<>"",IF(G44<>"",G44,($I$9/$I$12-SUM($AA$25:AA43))*AB44*AC44/SUMPRODUCT($AC44:$AC$46,$AB44:$AB$46)),""),"")
F45: =IF(AND(E45<>"",E45<>0),D45/E45,"") | H45: =IF(AND(G45<>"",G45<>0),D45/G45,"") | J45: =IF(AND(G45<>"",G45<>0),E45/G45,"") | T45: =IF(AND(I45<>"",I45<>0),G45/I45,"") | U45: =D45/V45 -> #DIV/0! | V45: =$I$8*AB45*AC45/SUMPRODUCT($AC$25:$AC$46,$AB$25:$AB$46) -> #DIV/0! | W45: =$I$9*AB45*AC45/SUMPRODUCT($AC$25:$AC$46,$AB$25:$AB$46) -> #DIV/0! | X45: =IF($I$12="","",W45/$I$12) -> #DIV/0! | Y45: =IF(AC45<>"",IF(D45<>"",D45,($I$8-SUM($Y$25:Y44))*AB45*AC45/SUMPRODUCT($AC45:$AC$46,$AB45:$AB$46)),"") | Z45: =IF(AC45<>"",IF(E45<>"",E45,($I$9-SUM($Z$25:Z44))*AB45*AC45/SUMPRODUCT($AC45:$AC$46,$AB45:$AB$46)),"") | AA45: =IF(AC45<>"",IF($I$12<>"",IF(G45<>"",G45,($I$9/$I$12-SUM($AA$25:AA44))*AB45*AC45/SUMPRODUCT($AC45:$AC$46,$AB45:$AB$46)),""),"")
F46: =IF(AND(E46<>"",E46<>0),D46/E46,"") | H46: =IF(AND(G46<>"",G46<>0),D46/G46,"") | J46: =IF(AND(G46<>"",G46<>0),E46/G46,"") | T46: =IF(AND(I46<>"",I46<>0),G46/I46,"") | U46: =D46/V46 -> #DIV/0! | V46: =$I$8*AB46*AC46/SUMPRODUCT($AC$25:$AC$46,$AB$25:$AB$46) -> #DIV/0! | W46: =$I$9*AB46*AC46/SUMPRODUCT($AC$25:$AC$46,$AB$25:$AB$46) -> #DIV/0! | X46: =IF($I$12="","",W46/$I$12) -> #DIV/0! | Y46: =IF(AC46<>"",IF(D46<>"",D46,($I$8-SUM($Y$25:Y45))*AB46*AC46/SUMPRODUCT($AC46:$AC$46,$AB46:$AB$46)),"") | Z46: =IF(AC46<>"",IF(E46<>"",E46,($I$9-SUM($Z$25:Z39))*AB46*AC46/SUMPRODUCT($AC46:$AC$46,$AB46:$AB$46)),"") | AA46: =IF(AC46<>"",IF($I$12<>"",IF(G46<>"",G46,($I$9/$I$12-SUM($AA$25:AA39))*AB46*AC46/SUMPRODUCT($AC46:$AC$46,$AB46:$AB$46)),""),"")
F47: =IF(AND(E47<>"",E47<>0),D47/E47,"") | H47: =IF(AND(G47<>"",G47<>0),D47/G47,"") | J47: =IF(AND(G47<>"",G47<>0),E47/G47,"") | T47: =IF(AND(I47<>"",I47<>0),G47/I47,"") | U47: =D47/V47 -> #DIV/0! | V47: =$I$8*AB47*AC47/SUMPRODUCT($AC$25:$AC$46,$AB$25:$AB$46) -> #DIV/0! | W47: =$I$9*AB47*AC47/SUMPRODUCT($AC$25:$AC$46,$AB$25:$AB$46) -> #DIV/0! | X47: =IF($I$12="","",W47/$I$12) -> #DIV/0! | Y47: =IF(AC47<>"",IF(D47<>"",D47,($I$8-SUM($Y$25:Y46))*AB47*AC47/SUMPRODUCT($AC$47:$AC47,$AB$47:$AB47)),"") | Z47: =IF(AC47<>"",IF(E47<>"",E47,($I$9-SUM(#REF!))*AB47*AC47/SUMPRODUCT($AC$47:$AC47,$AB$47:$AB47)),"") | AA47: =IF(AC47<>"",IF($I$12<>"",IF(G47<>"",G47,($I$9/$I$12-SUM(#REF!))*AB47*AC47/SUMPRODUCT($AC$47:$AC47,$AB$47:$AB47)),""),"")
B48: итого | D48: =SUM(D25:D47) -> 521953 | E48: =SUM(E25:E47) -> 48 | F48: =IF(AND(E48<>"",E48<>0),D48/E48,"") -> 10874.021 | G48: =SUM(G25:G47) -> 8 | H48: =IF(AND(G48<>"",G48<>0),D48/G48,"") -> 65244.125 | I48: =SUM(I25:I47)*0.8 -> 84 | J48: =IF(AND(G48<>"",G48<>0),E48/G48,"") -> 6 | K48: =SUM(K25:K47) -> 0 | L48: =SUM(L25:L47) -> 0 | M48: =SUM(M25:M47) -> 0 | N48: =SUM(N25:N47) -> 227591 | O48: =SUM(O25:O47) -> 190704 | P48: =SUM(P25:P47) -> 26543 | Q48: =SUM(Q25:Q47) -> 0 | R48: =SUM(R25:R47) -> 0 | S48: =SUM(S25:S47) -> 0 | T48: =IF(AND(I48<>"",I48<>0),G48/I48,"") -> 0.095238095 | U48: =D48/V48 -> #DIV/0! | V48: =SUM(V25:V47) -> #DIV/0! | W48: =SUM(W25:W47) -> #DIV/0! | X48: =SUM(X25:X47) -> #DIV/0! | Y48: =SUM(Y25:Y47) -> 0 | Z48: =SUM(Z25:Z47) -> 0 | AA48: =SUM(AA25:AA47) -> 0
D49: =SUMIF(D25:D47,"",V25:V47)+D48 -> #DIV/0!
D51: =D26+D27+D29+D31+D32+D33 -> 55722

Sheet Маркова
C1: =TODAY()-1 -> 46151
C2: (отчетная дата) | M2: ЕЖЕДНЕВНЫЙ ОТЧЕТ О ПРОДАЖАХ
C3: Осталось до выполнения плана!!! | M3: =График!B27 -> Маркова Диана
C4: =L8-D48 -> 366547.57 | E4: =IF(L8<>0,C4/L8,0) -> 0.65693347
I6: Целевые показатели
I7: Показатель | L7: План | M7: Факт | N7: % выполнения | O7: Прогноз выполнения | P7: % выполнения по прогнозу | Q7: Отклонение | R7: Факт аналогичного месяца прошлого года | S7: Отклонение LFL
I8: Выручка | L8: =Центрум!I8/График!AJ29*График!AJ27 -> 557967.57 | M8: =D48 -> 191420 | N8: =IF(AND(L8<>"",L8<>0,M8<>""),M8/L8,"") -> 0.34306653 | O8: =IF(SUMIF($D$25:$D$47,">=0",$V$25:$V$47)<>0,L8*D48/SUMIF($D$25:$D$47,">=0",$V$25:$V$47),0) -> 191420 | P8: =O8/L8 -> 0.34306653 | Q8: =IF(AND(M8<>0,M8<>"",L8<>0,L8<>""),O8-L8,"") -> -366547.57 | S8: =IF(AND(R8<>"",R8<>0,O8<>"",O8<>0),-R8+O8,"") | T8: =IF(AND(S8<>"",S8<>0,R8<>0,R8<>""),S8/R8,"")
I9: Кол-во изделий | L9: =L8/L11 -> 80.864865 | M9: =E48 -> 31 | N9: =IF(AND(L9<>"",L9<>0,M9<>""),M9/L9,"") -> 0.38335561 | O9: =IF(SUMIF($E$25:$E$47,">=0",$W$25:$W$47)<>0,L9*E48/SUMIF($E$25:$E$47,">=0",$W$25:$W$47),0) -> 31 | P9: =IF(AND(L9<>"",L9<>0,O9<>"",O9<>0),O9/L9,"") -> 0.38335561 | Q9: =IF(AND(M9<>0,M9<>"",L9<>0,L9<>""),O9-L9,"") -> -49.864865 | R9: =R8/R11 -> #DIV/0! | S9: =IF(AND(R9<>"",R9<>0,O9<>"",O9<>0),-R9+O9,"") -> #DIV/0! | T9: =IF(AND(S9<>"",S9<>0,R9<>0,R9<>""),S9/R9,"") -> #DIV/0!
I10: Средний чек | L10: =L11*L12 -> 11730 | M10: =H48 -> 8700.9091 | N10: =IF(AND(L10<>"",L10<>0,M10<>""),M10/L10,"") -> 0.74176548 | O10: =M10 -> 8700.9091 | P10: =IF(AND(L10<>"",L10<>0,O10<>"",O10<>0),O10/L10,"") -> 0.74176548 | Q10: =IF(AND(M10<>0,M10<>"",L10<>0,L10<>""),O10-L10,"") -> -3029.0909 | R10: =R11*R12 -> 0 | S10: =IF(AND(R10<>"",R10<>0,O10<>"",O10<>0),-R10+O10,"") | T10: =IF(AND(S10<>"",S10<>0,R10<>0,R10<>""),S10/R10,"")
I11: Средняя стоимость изделия | L11: =Центрум!I11 -> 6900 | M11: =F48 -> 6174.8387 | N11: =IF(AND(L11<>"",L11<>0,M11<>""),M11/L11,"") -> 0.89490416 | O11: =M11 -> 6174.8387 | P11: =IF(AND(L11<>"",L11<>0,O11<>"",O11<>0),O11/L11,"") -> 0.89490416 | Q11: =IF(AND(M11<>0,M11<>"",L11<>0,L11<>""),O11-L11,"") -> -725.16129 | S11: =IF(AND(R11<>"",R11<>0,O11<>"",O11<>0),-R11+O11,"") | T11: =IF(AND(S11<>"",S11<>0,R11<>0,R11<>""),S11/R11,"")
I12: Длина чека | L12: =Центрум!I12 -> 1.7 | M12: =J48 -> 1.4090909 | N12: =IF(AND(L12<>"",L12<>0,M12<>""),M12/L12,"") -> 0.82887701 | O12: =M12 -> 1.4090909 | P12: =IF(AND(L12<>"",L12<>0,O12<>"",O12<>0),O12/L12,"") -> 0.82887701 | Q12: =IF(AND(M12<>0,M12<>"",L12<>0,L12<>""),O12-L12,"") -> -0.29090909 | S12: =IF(AND(R12<>"",R12<>0,O12<>"",O12<>0),-R12+O12,"") | T12: =IF(AND(S12<>"",S12<>0,R12<>0,R12<>""),S12/R12,"")
I13: Кол-во чеков | L13: =IF(L12<>0,L9/L12,"") -> 47.567568 | M13: =G48 -> 22 | N13: =IF(AND(L13<>"",L13<>0,M13<>""),M13/L13,"") -> 0.4625 | O13: =IF(SUMIF($G$25:$G$47,">=0",$X$25:$X$47)<>0,L13*G48/SUMIF($G$25:$G$47,">=0",$X$25:$X$47),"") -> 22 | P13: =IF(AND(L13<>"",L13<>0,O13<>"",O13<>0),O13/L13,"") -> 0.4625 | Q13: =IF(AND(M13<>0,M13<>"",L13<>0,L13<>""),O13-L13,"") -> -25.567568 | S13: =IF(AND(R13<>"",R13<>0,O13<>"",O13<>0),-R13+O13,"") | T13: =IF(AND(S13<>"",S13<>0,R13<>0,R13<>""),S13/R13,"")
I14: Кол-во смен план/отработано | L14: =График!AI27 -> 11 | M14: 11 | N14: =IF(AND(L14<>"",L14<>0,M14<>""),M14/L14,"") -> 1 | O14: =IF(SUMIF($D$25:$D$47,">=0",$V$25:$V$47),I48*L8/SUMIF($D$25:$D$47,">=0",$V$25:$V$47),"") -> 201.6 | Q14: =IF(AND(M14<>0,M14<>"",L14<>0,L14<>""),O14-L14,"") -> 190.6 | S14: =IF(AND(R14<>"",R14<>0,O14<>"",O14<>0),-R14+O14,"") | T14: =IF(AND(S14<>"",S14<>0,R14<>0,R14<>""),S14/R14,"")
I15: Средние продажи в смену | L15: =Центрум!I15/2 -> 31280 | M15: =M8/M14 -> 17401.818 | N15: =IF(AND(L15<>"",L15<>0,M15<>""),M15/L15,"") -> 0.55632411 | O15: =M15 -> 17401.818 | P15: =IF(AND(L15<>"",L15<>0,O15<>"",O15<>0),O15/L15,"") -> 0.55632411 | Q15: =IF(AND(M15<>0,M15<>"",L15<>0,L15<>""),O15-L15,"") -> -13878.182 | S15: =IF(AND(R15<>"",R15<>0,O15<>"",O15<>0),-R15+O15,"") | T15: =IF(AND(S15<>"",S15<>0,R15<>0,R15<>""),S15/R15,"")
I16: Отставание/Перевыполнение | M16: =M8-L15*M14 -> -152660 | N16: =IF(AND(L16<>"",L16<>0,M16<>""),M16/L16,"") | O16: =M16 -> -152660 | P16: =IF(AND(L16<>"",L16<>0,O16<>"",O16<>0),O16/L16,"") | Q16: =IF(AND(M16<>0,M16<>"",L16<>0,L16<>""),O16-L16,"") | S16: =IF(AND(R16<>"",R16<>0,O16<>"",O16<>0),-R16+O16,"") | T16: =IF(AND(S16<>"",S16<>0,R16<>0,R16<>""),S16/R16,"") | V16: Подарочные сертификаты
I17: Трафик | L17: =Центрум!I17/График!AJ29*График!AJ27 -> 475.67568 | M17: =I48 -> 201.6 | N17: =IF(AND(L17<>"",L17<>0,M17<>""),M17/L17,"") -> 0.42381818 | O17: =M17/M14*L14 -> 201.6 | P17: =IF(AND(L17<>"",L17<>0,O17<>"",O17<>0),O17/L17,"") -> 0.42381818 | Q17: =IF(AND(M17<>0,M17<>"",L17<>0,L17<>""),O17-L17,"") -> -274.07568 | S17: =IF(AND(R17<>"",R17<>0,O17<>"",O17<>0),-R17+O17,"") | T17: =IF(AND(S17<>"",S17<>0,R17<>0,R17<>""),S17/R17,"")
I18: Выручка на вошедшего | L18: =L8/L17 -> 1173 | M18: =M8/M17 -> 949.50397 | N18: =IF(AND(L18<>"",L18<>0,M18<>""),M18/L18,"") -> 0.8094663 | O18: =M18 -> 949.50397 | P18: =IF(AND(L18<>"",L18<>0,O18<>"",O18<>0),O18/L18,"") -> 0.8094663 | Q18: =IF(AND(M18<>0,M18<>"",L18<>0,L18<>""),O18-L18,"") -> -223.49603 | R18: 0 | S18: =IF(AND(R18<>"",R18<>0,O18<>"",O18<>0),-R18+O18,"") | T18: =IF(AND(S18<>"",S18<>0,R18<>0,R18<>""),S18/R18,"")
N19: =IF(AND(L19<>"",L19<>0,M19<>""),M19/L19,"") | O19: =M19 -> 0 | P19: =IF(AND(L19<>"",L19<>0,O19<>"",O19<>0),O19/L19,"") | Q19: =IF(AND(M19<>0,M19<>"",L19<>0,L19<>""),O19-L19,"") | R19: 0 | S19: =IF(AND(R19<>"",R19<>0,O19<>"",O19<>0),-R19+O19,"") | T19: =IF(AND(S19<>"",S19<>0,R19<>0,R19<>""),S19/R19,"") | V19: =V18/L16 -> #DIV/0!
I20: Конверсия план/факт | L20: =Центрум!I20 -> 0.1 | M20: =T48 -> 0.10912698 | N20: =M20/L20 -> 1.0912698 | O20: =IF(AND(N8<>0,L14<>0,I48<>0),(I48*T48+(I48/N8-I48)*L20)/(I48/N8),0) -> 0.10313116 | P20: =IF(AND(L20<>"",L20<>0,O20<>"",O20<>0),O20/L20,"") -> 1.0313116 | Q20: =IF(AND(M20<>0,M20<>"",L20<>0,L20<>""),O20-L20,"") -> 0.0031311628 | S20: =IF(AND(R20<>"",R20<>0,O20<>"",O20<>0),-R20+O20,"") | T20: =IF(AND(S20<>"",S20<>0,R20<>0,R20<>""),S20/R20,"")
A22: Факт продаж за месяц | V22: Раcпределение плана по дням
B23: Дата | C23: День недели | D23: Выручка (руб) | E23: Кол-во единиц (шт.) | F23: Средняя стоимость изделия (руб.) | G23: Количество чеков (шт.) | H23: Средняя сумма чека (руб.) | I23: Трафик | J23: Длина чека (шт.) | K23: UNOde50 | L23: IS | M23: Agafi | N23: Kalliope | O23: Raganella | P23: CC/MP | Q23: Eva Rites | R23: Antura | S23: SALE | T23: Конверсия (%) | U23: % выполнения дневного плана | V23: выручка, план | W23: кол-во ед, план | X23: Кол-во чеков, план | Y23: выручка, скорректир.план | Z23: кол-во ед, скорр. план | AA23: кол-во чеков, скорр. план | AB23: Коэфф. Дня Недели | AC23: Специфика месяца
B24: 1 | C24: 2 | D24: 3 | E24: в | F24: 5 | G24: 6 | H24: 7 | I24: 8 | J24: 9 | K24: 10 | L24: 11 | M24: 12 | N24: 13 | O24: 14 | P24: 15 | Q24: 16 | R24: 17 | T24: 18 | V24: 1 | W24: 2 | X24: 3 | Y24: 4 | Z24: 5 | AA24: 6 | AB24: 10 | AC24: 11
A25: 1 | B25: 46113 | C25: ср | D25: 27636 | E25: 6 | F25: =IF(AND(E25<>"",E25<>0),D25/E25,"") -> 4606 | G25: 4 | H25: =IF(AND(G25<>"",G25<>0),D25/G25,"") -> 6909 | I25: 35 | J25: =IF(AND(G25<>"",G25<>0),E25/G25,"") -> 1.5 | T25: =IF(AND(I25<>"",I25<>0),G25/I25,"") -> 0.11428571 | U25: =D25/V25 -> 0.49529761 | V25: =$L$8*AB25*AC25/SUMPRODUCT($AC$25:$AC$55,$AB$25:$AB$55) -> 55796.757 | W25: =$L$9*AB25*AC25/SUMPRODUCT($AC$25:$AC$55,$AB$25:$AB$55) -> 8.0864865 | X25: =IF($L$12="","",W25/$L$12) -> 4.7567568 | Y25: =IF(AC25<>"",IF(D25<>"",D25,($L$8-SUM($Y24:Y$25))*AB25*AC25/SUMPRODUCT($AC25:$AC$55,$AB25:$AB$55)),"") -> 27636 | Z25: =IF(AC25<>"",IF(E25<>"",E25,($L$9-SUM($Z24:Z$25))*AB25*AC25/SUMPRODUCT($AC25:$AC$55,$AB25:$AB$55)),"") -> 6 | AA25: =IF(AC25<>"",IF($L$12<>"",IF(G25<>"",G25,($L$9/$L$12-SUM($AA24:AA$25))*AB25*AC25/SUMPRODUCT($AC25:$AC$55,$AB25:$AB$55)),""),"") -> 4 | AB25: 1 | AC25: 1
A26: 2 | B26: 46116 | C26: сб | D26: 30939 | E26: 5 | F26: =IF(AND(E26<>"",E26<>0),D26/E26,"") -> 6187.8 | G26: 4 | H26: =IF(AND(G26<>"",G26<>0),D26/G26,"") -> 7734.75 | I26: 30 | J26: =IF(AND(G26<>"",G26<>0),E26/G26,"") -> 1.25 | S26: 4263 | T26: =IF(AND(I26<>"",I26<>0),G26/I26,"") -> 0.13333333 | U26: =D26/V26 -> 0.55449459 | V26: =$L$8*AB26*AC26/SUMPRODUCT($AC$25:$AC$55,$AB$25:$AB$55) -> 55796.757 | W26: =$L$9*AB26*AC26/SUMPRODUCT($AC$25:$AC$55,$AB$25:$AB$55) -> 8.0864865 | X26: =IF($L$12="","",W26/$L$12) -> 4.7567568 | Y26: =IF(AC26<>"",IF(D26<>"",D26,($L$8-SUM($Y$25:Y25))*AB26*AC26/SUMPRODUCT($AC26:$AC$55,$AB26:$AB$55)),"") -> 30939 | Z26: =IF(AC26<>"",IF(E26<>"",E26,($L$9-SUM($Z$25:Z25))*AB26*AC26/SUMPRODUCT($AC26:$AC$55,$AB26:$AB$55)),"") -> 5 | AA26: =IF(AC26<>"",IF($L$12<>"",IF(G26<>"",G26,($L$9/$L$12-SUM($AA$25:AA25))*AB26*AC26/SUMPRODUCT($AC26:$AC$55,$AB26:$AB$55)),""),"") -> 4 | AB26: 1 | AC26: 1
A27: 3 | B27: 46117 | C27: вс | D27: 18674 | E27: 3 | F27: =IF(AND(E27<>"",E27<>0),D27/E27,"") -> 6224.6667 | G27: 3 | H27: =IF(AND(G27<>"",G27<>0),D27/G27,"") -> 6224.6667 | I27: 22 | J27: =IF(AND(G27<>"",G27<>0),E27/G27,"") -> 1 | T27: =IF(AND(I27<>"",I27<>0),G27/I27,"") -> 0.13636364 | U27: =D27/V27 -> 0.33467895 | V27: =$L$8*AB27*AC27/SUMPRODUCT($AC$25:$AC$55,$AB$25:$AB$55) -> 55796.757 | W27: =$L$9*AB27*AC27/SUMPRODUCT($AC$25:$AC$55,$AB$25:$AB$55) -> 8.0864865 | X27: =IF($L$12="","",W27/$L$12) -> 4.7567568 | Y27: =IF(AC27<>"",IF(D27<>"",D27,($L$8-SUM($Y$25:Y26))*AB27*AC27/SUMPRODUCT($AC27:$AC$55,$AB27:$AB$55)),"") -> 18674 | Z27: =IF(AC27<>"",IF(E27<>"",E27,($L$9-SUM($Z$25:Z26))*AB27*AC27/SUMPRODUCT($AC27:$AC$55,$AB27:$AB$55)),"") -> 3 | AA27: =IF(AC27<>"",IF($L$12<>"",IF(G27<>"",G27,($L$9/$L$12-SUM($AA$25:AA26))*AB27*AC27/SUMPRODUCT($AC27:$AC$55,$AB27:$AB$55)),""),"") -> 3 | AB27: 1 | AC27: 1
A28: 4 | B28: 46118 | C28: пн | D28: 8055 | E28: 2 | F28: =IF(AND(E28<>"",E28<>0),D28/E28,"") -> 4027.5 | G28: 1 | H28: =IF(AND(G28<>"",G28<>0),D28/G28,"") -> 8055 | I28: 8 | J28: =IF(AND(G28<>"",G28<>0),E28/G28,"") -> 2 | S28: 8051.17 | T28: =IF(AND(I28<>"",I28<>0),G28/I28,"") -> 0.125 | U28: =D28/V28 -> 0.14436323 | V28: =$L$8*AB28*AC28/SUMPRODUCT($AC$25:$AC$55,$AB$25:$AB$55) -> 55796.757 | W28: =$L$9*AB28*AC28/SUMPRODUCT($AC$25:$AC$55,$AB$25:$AB$55) -> 8.0864865 | X28: =IF($L$12="","",W28/$L$12) -> 4.7567568 | Y28: =IF(AC28<>"",IF(D28<>"",D28,($L$8-SUM($Y$25:Y27))*AB28*AC28/SUMPRODUCT($AC28:$AC$55,$AB28:$AB$55)),"") -> 8055 | Z28: =IF(AC28<>"",IF(E28<>"",E28,($L$9-SUM($Z$25:Z27))*AB28*AC28/SUMPRODUCT($AC28:$AC$55,$AB28:$AB$55)),"") -> 2 | AA28: =IF(AC28<>"",IF($L$12<>"",IF(G28<>"",G28,($L$9/$L$12-SUM($AA$25:AA27))*AB28*AC28/SUMPRODUCT($AC28:$AC$55,$AB28:$AB$55)),""),"") -> 1 | AB28: 1 | AC28: 1
A29: 5 | B29: 46121 | C29: чт | D29: 25409 | E29: 3 | F29: =IF(AND(E29<>"",E29<>0),D29/E29,"") -> 8469.6667 | G29: 2 | H29: =IF(AND(G29<>"",G29<>0),D29/G29,"") -> 12704.5 | I29: 15 | J29: =IF(AND(G29<>"",G29<>0),E29/G29,"") -> 1.5 | S29: 4123 | T29: =IF(AND(I29<>"",I29<>0),G29/I29,"") -> 0.13333333 | U29: =D29/V29 -> 0.45538489 | V29: =$L$8*AB29*AC29/SUMPRODUCT($AC$25:$AC$55,$AB$25:$AB$55) -> 55796.757 | W29: =$L$9*AB29*AC29/SUMPRODUCT($AC$25:$AC$55,$AB$25:$AB$55) -> 8.0864865 | X29: =IF($L$12="","",W29/$L$12) -> 4.7567568 | Y29: =IF(AC29<>"",IF(D29<>"",D29,($L$8-SUM($Y$25:Y28))*AB29*AC29/SUMPRODUCT($AC29:$AC$55,$AB29:$AB$55)),"") -> 25409 | Z29: =IF(AC29<>"",IF(E29<>"",E29,($L$9-SUM($Z$25:Z28))*AB29*AC29/SUMPRODUCT($AC29:$AC$55,$AB29:$AB$55)),"") -> 3 | AA29: =IF(AC29<>"",IF($L$12<>"",IF(G29<>"",G29,($L$9/$L$12-SUM($AA$25:AA28))*AB29*AC29/SUMPRODUCT($AC29:$AC$55,$AB29:$AB$55)),""),"") -> 2 | AB29: 1 | AC29: 1
A30: 6 | B30: 46124 | C30: вс | D30: 28377 | E30: 3 | F30: =IF(AND(E30<>"",E30<>0),D30/E30,"") -> 9459 | G30: 2 | H30: =IF(AND(G30<>"",G30<>0),D30/G30,"") -> 14188.5 | I30: 20 | J30: =IF(AND(G30<>"",G30<>0),E30/G30,"") -> 1.5 | M30: 14992 | T30: =IF(AND(I30<>"",I30<>0),G30/I30,"") -> 0.1 | U30: =D30/V30 -> 0.50857795 | V30: =$L$8*AB30*AC30/SUMPRODUCT($AC$25:$AC$55,$AB$25:$AB$55) -> 55796.757 | W30: =$L$9*AB30*AC30/SUMPRODUCT($AC$25:$AC$55,$AB$25:$AB$55) -> 8.0864865 | X30: =IF($L$12="","",W30/$L$12) -> 4.7567568 | Y30: =IF(AC30<>"",IF(D30<>"",D30,($L$8-SUM($Y$25:Y29))*AB30*AC30/SUMPRODUCT($AC30:$AC$55,$AB30:$AB$55)),"") -> 28377 | Z30: =IF(AC30<>"",IF(E30<>"",E30,($L$9-SUM($Z$25:Z29))*AB30*AC30/SUMPRODUCT($AC30:$AC$55,$AB30:$AB$55)),"") -> 3 | AA30: =IF(AC30<>"",IF($L$12<>"",IF(G30<>"",G30,($L$9/$L$12-SUM($AA$25:AA29))*AB30*AC30/SUMPRODUCT($AC30:$AC$55,$AB30:$AB$55)),""),"") -> 2 | AB30: 1 | AC30: 1
A31: 7 | B31: 46126 | C31: вт | D31: 4692 | E31: 1 | F31: =IF(AND(E31<>"",E31<>0),D31/E31,"") -> 4692 | G31: 1 | H31: =IF(AND(G31<>"",G31<>0),D31/G31,"") -> 4692 | I31: 34 | J31: =IF(AND(G31<>"",G31<>0),E31/G31,"") -> 1 | T31: =IF(AND(I31<>"",I31<>0),G31/I31,"") -> 0.029411765 | U31: =D31/V31 -> 0.084090909 | V31: =$L$8*AB31*AC31/SUMPRODUCT($AC$25:$AC$55,$AB$25:$AB$55) -> 55796.757 | W31: =$L$9*AB31*AC31/SUMPRODUCT($AC$25:$AC$55,$AB$25:$AB$55) -> 8.0864865 | X31: =IF($L$12="","",W31/$L$12) -> 4.7567568 | Y31: =IF(AC31<>"",IF(D31<>"",D31,($L$8-SUM($Y$25:Y30))*AB31*AC31/SUMPRODUCT($AC31:$AC$55,$AB31:$AB$55)),"") -> 4692 | Z31: =IF(AC31<>"",IF(E31<>"",E31,($L$9-SUM($Z$25:Z30))*AB31*AC31/SUMPRODUCT($AC31:$AC$55,$AB31:$AB$55)),"") -> 1 | AA31: =IF(AC31<>"",IF($L$12<>"",IF(G31<>"",G31,($L$9/$L$12-SUM($AA$25:AA30))*AB31*AC31/SUMPRODUCT($AC31:$AC$55,$AB31:$AB$55)),""),"") -> 1 | AB31: 1 | AC31: 1
A32: 8 | B32: 46128 | C32: чт | D32: 11286 | E32: 2 | F32: =IF(AND(E32<>"",E32<>0),D32/E32,"") -> 5643 | G32: 2 | H32: =IF(AND(G32<>"",G32<>0),D32/G32,"") -> 5643 | I32: 18 | J32: =IF(AND(G32<>"",G32<>0),E32/G32,"") -> 1 | T32: =IF(AND(I32<>"",I32<>0),G32/I32,"") -> 0.11111111 | U32: =D32/V32 -> 0.20226982 | V32: =$L$8*AB32*AC32/SUMPRODUCT($AC$25:$AC$55,$AB$25:$AB$55) -> 55796.757 | W32: =$L$9*AB32*AC32/SUMPRODUCT($AC$25:$AC$55,$AB$25:$AB$55) -> 8.0864865 | X32: =IF($L$12="","",W32/$L$12) -> 4.7567568 | Y32: =IF(AC32<>"",IF(D32<>"",D32,($L$8-SUM($Y$25:Y31))*AB32*AC32/SUMPRODUCT($AC32:$AC$55,$AB32:$AB$55)),"") -> 11286 | Z32: =IF(AC32<>"",IF(E32<>"",E32,($L$9-SUM($Z$25:Z31))*AB32*AC32/SUMPRODUCT($AC32:$AC$55,$AB32:$AB$55)),"") -> 2 | AA32: =IF(AC32<>"",IF($L$12<>"",IF(G32<>"",G32,($L$9/$L$12-SUM($AA$25:AA31))*AB32*AC32/SUMPRODUCT($AC32:$AC$55,$AB32:$AB$55)),""),"") -> 2 | AB32: 1 | AC32: 1
A33: 9 | B33: 46129 | C33: пт | D33: 0 | E33: 0 | F33: 0 | G33: 0 | H33: 0 | I33: 20 | J33: =IF(AND(G33<>"",G33<>0),E33/G33,"") | T33: =IF(AND(I33<>"",I33<>0),G33/I33,"") -> 0 | U33: =D33/V33 -> 0 | V33: =$L$8*AB33*AC33/SUMPRODUCT($AC$25:$AC$55,$AB$25:$AB$55) -> 55796.757 | W33: =$L$9*AB33*AC33/SUMPRODUCT($AC$25:$AC$55,$AB$25:$AB$55) -> 8.0864865 | X33: =IF($L$12="","",W33/$L$12) -> 4.7567568 | Y33: =IF(AC33<>"",IF(D33<>"",D33,($L$8-SUM($Y$25:Y32))*AB33*AC33/SUMPRODUCT($AC33:$AC$55,$AB33:$AB$55)),"") -> 0 | Z33: =IF(AC33<>"",IF(E33<>"",E33,($L$9-SUM($Z$25:Z32))*AB33*AC33/SUMPRODUCT($AC33:$AC$55,$AB33:$AB$55)),"") -> 0 | AA33: =IF(AC33<>"",IF($L$12<>"",IF(G33<>"",G33,($L$9/$L$12-SUM($AA$25:AA32))*AB33*AC33/SUMPRODUCT($AC33:$AC$55,$AB33:$AB$55)),""),"") -> 0 | AB33: 1 | AC33: 1
A34: 10 | B34: 46132 | C34: пн | D34: 8793 | E34: 1 | F34: 8793 | G34: 1 | H34: =IF(AND(G34<>"",G34<>0),D34/G34,"") -> 8793 | I34: 20 | J34: =IF(AND(G34<>"",G34<>0),E34/G34,"") -> 1 | M34: 8793 | T34: =IF(AND(I34<>"",I34<>0),G34/I34,"") -> 0.05 | U34: =D34/V34 -> 0.1575898 | V34: =$L$8*AB34*AC34/SUMPRODUCT($AC$25:$AC$55,$AB$25:$AB$55) -> 55796.757 | W34: =$L$9*AB34*AC34/SUMPRODUCT($AC$25:$AC$55,$AB$25:$AB$55) -> 8.0864865 | X34: =IF($L$12="","",W34/$L$12) -> 4.7567568 | Y34: =IF(AC34<>"",IF(D34<>"",D34,($L$8-SUM($Y$25:Y33))*AB34*AC34/SUMPRODUCT($AC34:$AC$55,$AB34:$AB$55)),"") -> 8793 | Z34: =IF(AC34<>"",IF(E34<>"",E34,($L$9-SUM($Z$25:Z33))*AB34*AC34/SUMPRODUCT($AC34:$AC$55,$AB34:$AB$55)),"") -> 1 | AA34: =IF(AC34<>"",IF($L$12<>"",IF(G34<>"",G34,($L$9/$L$12-SUM($AA$25:AA33))*AB34*AC34/SUMPRODUCT($AC34:$AC$55,$AB34:$AB$55)),""),"") -> 1 | AB34: 1 | AC34: 1
B35: 46138 | C35: вс | D35: 27559 | E35: 5 | F35: =IF(AND(E35<>"",E35<>0),D35/E35,"") -> 5511.8 | G35: 2 | H35: =IF(AND(G35<>"",G35<>0),D35/G35,"") -> 13779.5 | I35: 30 | J35: =IF(AND(G35<>"",G35<>0),E35/G35,"") -> 2.5 | T35: =IF(AND(I35<>"",I35<>0),G35/I35,"") -> 0.066666667 | U35: =D35/V35 -> #DIV/0! | V35: =$L$8*AB35*AC35/SUMPRODUCT($AC$25:$AC$55,$AB$25:$AB$55) -> 0 | W35: =$L$9*AB35*AC35/SUMPRODUCT($AC$25:$AC$55,$AB$25:$AB$55) -> 0 | X35: =IF($L$12="","",W35/$L$12) -> 0 | Y35: =IF(AC35<>"",IF(D35<>"",D35,($L$8-SUM($Y$25:Y34))*AB35*AC35/SUMPRODUCT($AC35:$AC$55,$AB35:$AB$55)),"") | Z35: =IF(AC35<>"",IF(E35<>"",E35,($L$9-SUM($Z$25:Z34))*AB35*AC35/SUMPRODUCT($AC35:$AC$55,$AB35:$AB$55)),"") | AA35: =IF(AC35<>"",IF($L$12<>"",IF(G35<>"",G35,($L$9/$L$12-SUM($AA$25:AA34))*AB35*AC35/SUMPRODUCT($AC35:$AC$55,$AB35:$AB$55)),""),"")
F36: =IF(AND(E36<>"",E36<>0),D36/E36,"") | H36: =IF(AND(G36<>"",G36<>0),D36/G36,"") | J36: =IF(AND(G36<>"",G36<>0),E36/G36,"") | T36: =IF(AND(I36<>"",I36<>0),G36/I36,"") | U36: =D36/V36 -> #DIV/0! | V36: =$L$8*AB36*AC36/SUMPRODUCT($AC$25:$AC$55,$AB$25:$AB$55) -> 0 | W36: =$L$9*AB36*AC36/SUMPRODUCT($AC$25:$AC$55,$AB$25:$AB$55) -> 0 | X36: =IF($L$12="","",W36/$L$12) -> 0 | Y36: =IF(AC36<>"",IF(D36<>"",D36,($L$8-SUM($Y$25:Y35))*AB36*AC36/SUMPRODUCT($AC36:$AC$55,$AB36:$AB$55)),"") | Z36: =IF(AC36<>"",IF(E36<>"",E36,($L$9-SUM($Z$25:Z35))*AB36*AC36/SUMPRODUCT($AC36:$AC$55,$AB36:$AB$55)),"") | AA36: =IF(AC36<>"",IF($L$12<>"",IF(G36<>"",G36,($L$9/$L$12-SUM($AA$25:AA35))*AB36*AC36/SUMPRODUCT($AC36:$AC$55,$AB36:$AB$55)),""),"")
F37: =IF(AND(E37<>"",E37<>0),D37/E37,"") | H37: =IF(AND(G37<>"",G37<>0),D37/G37,"") | J37: =IF(AND(G37<>"",G37<>0),E37/G37,"") | T37: =IF(AND(I37<>"",I37<>0),G37/I37,"") | U37: =D37/V37 -> #DIV/0! | V37: =$L$8*AB37*AC37/SUMPRODUCT($AC$25:$AC$55,$AB$25:$AB$55) -> 0 | W37: =$L$9*AB37*AC37/SUMPRODUCT($AC$25:$AC$55,$AB$25:$AB$55) -> 0 | X37: =IF($L$12="","",W37/$L$12) -> 0 | Y37: =IF(AC37<>"",IF(D37<>"",D37,($L$8-SUM($Y$25:Y36))*AB37*AC37/SUMPRODUCT($AC37:$AC$55,$AB37:$AB$55)),"") | Z37: =IF(AC37<>"",IF(E37<>"",E37,($L$9-SUM($Z$25:Z36))*AB37*AC37/SUMPRODUCT($AC37:$AC$55,$AB37:$AB$55)),"") | AA37: =IF(AC37<>"",IF($L$12<>"",IF(G37<>"",G37,($L$9/$L$12-SUM($AA$25:AA36))*AB37*AC37/SUMPRODUCT($AC37:$AC$55,$AB37:$AB$55)),""),"")
F38: =IF(AND(E38<>"",E38<>0),D38/E38,"") | H38: =IF(AND(G38<>"",G38<>0),D38/G38,"") | J38: =IF(AND(G38<>"",G38<>0),E38/G38,"") | T38: =IF(AND(I38<>"",I38<>0),G38/I38,"") | U38: =D38/V38 -> #DIV/0! | V38: =$L$8*AB38*AC38/SUMPRODUCT($AC$25:$AC$46,$AB$25:$AB$46) -> 0 | W38: =$L$9*AB38*AC38/SUMPRODUCT($AC$25:$AC$46,$AB$25:$AB$46) -> 0 | X38: =IF($L$12="","",W38/$L$12) -> 0 | Y38: =IF(AC38<>"",IF(D38<>"",D38,($L$8-SUM($Y$25:Y37))*AB38*AC38/SUMPRODUCT($AC38:$AC$55,$AB38:$AB$55)),"") | Z38: =IF(AC38<>"",IF(E38<>"",E38,($L$9-SUM($Z$25:Z37))*AB38*AC38/SUMPRODUCT($AC38:$AC$55,$AB38:$AB$55)),"") | AA38: =IF(AC38<>"",IF($L$12<>"",IF(G38<>"",G38,($L$9/$L$12-SUM($AA$25:AA37))*AB38*AC38/SUMPRODUCT($AC38:$AC$55,$AB38:$AB$55)),""),"")
F39: =IF(AND(E39<>"",E39<>0),D39/E39,"") | H39: =IF(AND(G39<>"",G39<>0),D39/G39,"") | J39: =IF(AND(G39<>"",G39<>0),E39/G39,"") | T39: =IF(AND(I39<>"",I39<>0),G39/I39,"") | U39: =D39/V39 -> #DIV/0! | V39: =$L$8*AB39*AC39/SUMPRODUCT($AC$25:$AC$46,$AB$25:$AB$46) -> 0 | W39: =$L$9*AB39*AC39/SUMPRODUCT($AC$25:$AC$46,$AB$25:$AB$46) -> 0 | X39: =IF($L$12="","",W39/$L$12) -> 0 | Y39: =IF(AC39<>"",IF(D39<>"",D39,($L$8-SUM($Y$25:Y38))*AB39*AC39/SUMPRODUCT($AC39:$AC$55,$AB39:$AB$55)),"") | Z39: =IF(AC39<>"",IF(E39<>"",E39,($L$9-SUM($Z$25:Z38))*AB39*AC39/SUMPRODUCT($AC39:$AC$55,$AB39:$AB$55)),"") | AA39: =IF(AC39<>"",IF($L$12<>"",IF(G39<>"",G39,($L$9/$L$12-SUM($AA$25:AA38))*AB39*AC39/SUMPRODUCT($AC39:$AC$55,$AB39:$AB$55)),""),"")
F40: =IF(AND(E40<>"",E40<>0),D40/E40,"") | H40: =IF(AND(G40<>"",G40<>0),D40/G40,"") | J40: =IF(AND(G40<>"",G40<>0),E40/G40,"") | T40: =IF(AND(I40<>"",I40<>0),G40/I40,"") | U40: =D40/V40 -> #DIV/0! | V40: =$L$8*AB40*AC40/SUMPRODUCT($AC$25:$AC$46,$AB$25:$AB$46) -> 0 | W40: =$L$9*AB40*AC40/SUMPRODUCT($AC$25:$AC$46,$AB$25:$AB$46) -> 0 | X40: =IF($L$12="","",W40/$L$12) -> 0 | Y40: =IF(AC40<>"",IF(D40<>"",D40,($L$8-SUM($Y$25:Y39))*AB40*AC40/SUMPRODUCT($AC40:$AC$55,$AB40:$AB$55)),"") | Z40: =IF(AC40<>"",IF(E40<>"",E40,($L$9-SUM($Z$25:Z39))*AB40*AC40/SUMPRODUCT($AC40:$AC$55,$AB40:$AB$55)),"") | AA40: =IF(AC40<>"",IF($L$12<>"",IF(G40<>"",G40,($L$9/$L$12-SUM($AA$25:AA39))*AB40*AC40/SUMPRODUCT($AC40:$AC$55,$AB40:$AB$55)),""),"")
F41: =IF(AND(E41<>"",E41<>0),D41/E41,"") | H41: =IF(AND(G41<>"",G41<>0),D41/G41,"") | J41: =IF(AND(G41<>"",G41<>0),E41/G41,"") | T41: =IF(AND(I41<>"",I41<>0),G41/I41,"") | U41: =D41/V41 -> #DIV/0! | V41: =$L$8*AB41*AC41/SUMPRODUCT($AC$25:$AC$46,$AB$25:$AB$46) -> 0 | W41: =$L$9*AB41*AC41/SUMPRODUCT($AC$25:$AC$46,$AB$25:$AB$46) -> 0 | X41: =IF($L$12="","",W41/$L$12) -> 0 | Y41: =IF(AC41<>"",IF(D41<>"",D41,($L$8-SUM($Y$25:Y40))*AB41*AC41/SUMPRODUCT($AC41:$AC$55,$AB41:$AB$55)),"") | Z41: =IF(AC41<>"",IF(E41<>"",E41,($L$9-SUM($Z$25:Z40))*AB41*AC41/SUMPRODUCT($AC41:$AC$55,$AB41:$AB$55)),"") | AA41: =IF(AC41<>"",IF($L$12<>"",IF(G41<>"",G41,($L$9/$L$12-SUM($AA$25:AA40))*AB41*AC41/SUMPRODUCT($AC41:$AC$55,$AB41:$AB$55)),""),"")
F42: =IF(AND(E42<>"",E42<>0),D42/E42,"") | H42: =IF(AND(G42<>"",G42<>0),D42/G42,"") | J42: =IF(AND(G42<>"",G42<>0),E42/G42,"") | T42: =IF(AND(I42<>"",I42<>0),G42/I42,"") | U42: =D42/V42 -> #DIV/0! | V42: =$L$8*AB42*AC42/SUMPRODUCT($AC$25:$AC$46,$AB$25:$AB$46) -> 0 | W42: =$L$9*AB42*AC42/SUMPRODUCT($AC$25:$AC$46,$AB$25:$AB$46) -> 0 | X42: =IF($L$12="","",W42/$L$12) -> 0 | Y42: =IF(AC42<>"",IF(D42<>"",D42,($L$8-SUM($Y$25:Y41))*AB42*AC42/SUMPRODUCT($AC42:$AC$55,$AB42:$AB$55)),"") | Z42: =IF(AC42<>"",IF(E42<>"",E42,($L$9-SUM($Z$25:Z41))*AB42*AC42/SUMPRODUCT($AC42:$AC$55,$AB42:$AB$55)),"") | AA42: =IF(AC42<>"",IF($L$12<>"",IF(G42<>"",G42,($L$9/$L$12-SUM($AA$25:AA41))*AB42*AC42/SUMPRODUCT($AC42:$AC$55,$AB42:$AB$55)),""),"")
F43: =IF(AND(E43<>"",E43<>0),D43/E43,"") | H43: =IF(AND(G43<>"",G43<>0),D43/G43,"") | J43: =IF(AND(G43<>"",G43<>0),E43/G43,"") | T43: =IF(AND(I43<>"",I43<>0),G43/I43,"") | U43: =D43/V43 -> #DIV/0! | V43: =$L$8*AB43*AC43/SUMPRODUCT($AC$25:$AC$46,$AB$25:$AB$46) -> 0 | W43: =$L$9*AB43*AC43/SUMPRODUCT($AC$25:$AC$46,$AB$25:$AB$46) -> 0 | X43: =IF($L$12="","",W43/$L$12) -> 0 | Y43: =IF(AC43<>"",IF(D43<>"",D43,($L$8-SUM($Y$25:Y42))*AB43*AC43/SUMPRODUCT($AC43:$AC$55,$AB43:$AB$55)),"") | Z43: =IF(AC43<>"",IF(E43<>"",E43,($L$9-SUM($Z$25:Z42))*AB43*AC43/SUMPRODUCT($AC43:$AC$46,$AB43:$AB$46)),"") | AA43: =IF(AC43<>"",IF($L$12<>"",IF(G43<>"",G43,($L$9/$L$12-SUM($AA$25:AA42))*AB43*AC43/SUMPRODUCT($AC43:$AC$46,$AB43:$AB$46)),""),"")
F44: =IF(AND(E44<>"",E44<>0),D44/E44,"") | H44: =IF(AND(G44<>"",G44<>0),D44/G44,"") | J44: =IF(AND(G44<>"",G44<>0),E44/G44,"") | T44: =IF(AND(I44<>"",I44<>0),G44/I44,"") | U44: =D44/V44 -> #DIV/0! | V44: =$L$8*AB44*AC44/SUMPRODUCT($AC$25:$AC$46,$AB$25:$AB$46) -> 0 | W44: =$L$9*AB44*AC44/SUMPRODUCT($AC$25:$AC$46,$AB$25:$AB$46) -> 0 | X44: =IF($L$12="","",W44/$L$12) -> 0 | Y44: =IF(AC44<>"",IF(D44<>"",D44,($L$8-SUM($Y$25:Y43))*AB44*AC44/SUMPRODUCT($AC44:$AC$46,$AB44:$AB$46)),"") | Z44: =IF(AC44<>"",IF(E44<>"",E44,($L$9-SUM($Z$25:Z43))*AB44*AC44/SUMPRODUCT($AC44:$AC$46,$AB44:$AB$46)),"") | AA44: =IF(AC44<>"",IF($L$12<>"",IF(G44<>"",G44,($L$9/$L$12-SUM($AA$25:AA43))*AB44*AC44/SUMPRODUCT($AC44:$AC$46,$AB44:$AB$46)),""),"")
J45: =IF(AND(G45<>"",G45<>0),E45/G45,"") | T45: =IF(AND(I45<>"",I45<>0),G45/I45,"") | U45: =D45/V45 -> #DIV/0! | V45: =$L$8*AB45*AC45/SUMPRODUCT($AC$25:$AC$46,$AB$25:$AB$46) -> 0 | W45: =$L$9*AB45*AC45/SUMPRODUCT($AC$25:$AC$46,$AB$25:$AB$46) -> 0 | X45: =IF($L$12="","",W45/$L$12) -> 0 | Y45: =IF(AC45<>"",IF(D45<>"",D45,($L$8-SUM($Y$25:Y44))*AB45*AC45/SUMPRODUCT($AC45:$AC$46,$AB45:$AB$46)),"") | Z45: =IF(AC45<>"",IF(E45<>"",E45,($L$9-SUM($Z$25:Z44))*AB45*AC45/SUMPRODUCT($AC45:$AC$46,$AB45:$AB$46)),"") | AA45: =IF(AC45<>"",IF($L$12<>"",IF(G45<>"",G45,($L$9/$L$12-SUM($AA$25:AA44))*AB45*AC45/SUMPRODUCT($AC45:$AC$46,$AB45:$AB$46)),""),"")
F46: =IF(AND(E46<>"",E46<>0),D46/E46,"") | H46: =IF(AND(G46<>"",G46<>0),D46/G46,"") | J46: =IF(AND(G46<>"",G46<>0),E46/G46,"") | T46: =IF(AND(I46<>"",I46<>0),G46/I46,"") | U46: =D46/V46 -> #DIV/0! | V46: =$L$8*AB46*AC46/SUMPRODUCT($AC$25:$AC$46,$AB$25:$AB$46) -> 0 | W46: =$L$9*AB46*AC46/SUMPRODUCT($AC$25:$AC$46,$AB$25:$AB$46) -> 0 | X46: =IF($L$12="","",W46/$L$12) -> 0 | Y46: =IF(AC46<>"",IF(D46<>"",D46,($L$8-SUM($Y$25:Y45))*AB46*AC46/SUMPRODUCT($AC46:$AC$46,$AB46:$AB$46)),"") | Z46: =IF(AC46<>"",IF(E46<>"",E46,($L$9-SUM($Z$25:Z39))*AB46*AC46/SUMPRODUCT($AC46:$AC$46,$AB46:$AB$46)),"") | AA46: =IF(AC46<>"",IF($L$12<>"",IF(G46<>"",G46,($L$9/$L$12-SUM($AA$25:AA39))*AB46*AC46/SUMPRODUCT($AC46:$AC$46,$AB46:$AB$46)),""),"")
F47: =IF(AND(E47<>"",E47<>0),D47/E47,"") | H47: =IF(AND(G47<>"",G47<>0),D47/G47,"") | J47: =IF(AND(G47<>"",G47<>0),E47/G47,"") | T47: =IF(AND(I47<>"",I47<>0),G47/I47,"") | U47: =D47/V47 -> #DIV/0! | V47: =$L$8*AB47*AC47/SUMPRODUCT($AC$25:$AC$46,$AB$25:$AB$46) -> 0 | W47: =$L$9*AB47*AC47/SUMPRODUCT($AC$25:$AC$46,$AB$25:$AB$46) -> 0 | X47: =IF($L$12="","",W47/$L$12) -> 0 | Y47: =IF(AC47<>"",IF(D47<>"",D47,($L$8-SUM($Y$25:Y46))*AB47*AC47/SUMPRODUCT($AC$46:$AC47,$AB$46:$AB47)),"") | Z47: =IF(AC47<>"",IF(E47<>"",E47,($L$9-SUM($Z$25:Z40))*AB47*AC47/SUMPRODUCT($AC$46:$AC47,$AB$46:$AB47)),"") | AA47: =IF(AC47<>"",IF($L$12<>"",IF(G47<>"",G47,($L$9/$L$12-SUM($AA$25:AA40))*AB47*AC47/SUMPRODUCT($AC$46:$AC47,$AB$46:$AB47)),""),"")
B48: итого | D48: =SUM(D25:D47) -> 191420 | E48: =SUM(E25:E47) -> 31 | F48: =IF(AND(E48<>"",E48<>0),D48/E48,"") -> 6174.8387 | G48: =SUM(G25:G47) -> 22 | H48: =IF(AND(G48<>"",G48<>0),D48/G48,"") -> 8700.9091 | I48: =SUM(I25:I47)*0.8 -> 201.6 | J48: =IF(AND(G48<>"",G48<>0),E48/G48,"") -> 1.4090909 | K48: =SUM(K25:K47) -> 0 | L48: =SUM(L25:L47) -> 0 | M48: =SUM(M25:M47) -> 23785 | N48: =SUM(N25:N47) -> 0 | O48: =SUM(O25:O47) -> 0 | P48: =SUM(P25:P47) -> 0 | Q48: =SUM(Q25:Q47) -> 0 | R48: =SUM(R25:R47) -> 0 | S48: =SUM(S25:S47) -> 16437.17 | T48: =IF(AND(I48<>"",I48<>0),G48/I48,"") -> 0.10912698 | U48: =D48/V48 -> 0.34306653 | V48: =SUM(V25:V47) -> 557967.57 | W48: =SUM(W25:W47) -> 80.864865 | X48: =SUM(X25:X47) -> 47.567568 | Y48: =SUM(Y25:Y47) -> 163861 | Z48: =SUM(Z25:Z47) -> 26 | AA48: =SUM(AA25:AA47) -> 20
D49: =SUMIF(D25:D47,"",V25:V47)+D48 -> 191420

Sheet Бешлиева
C1: =TODAY()-1 -> 46151
C2: (отчетная дата) | M2: ЕЖЕДНЕВНЫЙ ОТЧЕТ О ПРОДАЖАХ
C3: Осталось до выполнения плана!!! | M3: =График!B26 -> Бешлиева Аджере
C4: =L8-D48 -> 372227.84 | E4: =IF(L8<>0,C4/L8,0) -> 0.40768063
I6: Целевые показатели
I7: Показатель | L7: План | M7: Факт | N7: % выполнения | O7: Прогноз выполнения | P7: % выполнения по прогнозу | Q7: Отклонение | R7: Факт аналогичного месяца прошлого года | S7: Отклонение LFL
I8: Выручка | L8: =Центрум!I8/График!AJ29*График!AJ26 -> 913037.84 | M8: =D48 -> 540810 | N8: =IF(AND(L8<>"",L8<>0,M8<>""),M8/L8,"") -> 0.59231937 | O8: =IF(SUMIF($D$25:$D$47,">=0",$V$25:$V$47)<>0,L8*D48/SUMIF($D$25:$D$47,">=0",$V$25:$V$47),0) -> 540810 | P8: =O8/L8 -> 0.59231937 | Q8: =IF(AND(M8<>0,M8<>"",L8<>0,L8<>""),O8-L8,"") -> -372227.84 | S8: =IF(AND(R8<>"",R8<>0,O8<>"",O8<>0),-R8+O8,"") | T8: =IF(AND(S8<>"",S8<>0,R8<>0,R8<>""),S8/R8,"")
I9: Кол-во изделий | L9: =L8/L11 -> 132.32432 | M9: =E48 -> 80 | N9: =IF(AND(L9<>"",L9<>0,M9<>""),M9/L9,"") -> 0.60457516 | O9: =IF(SUMIF($E$25:$E$47,">=0",$W$25:$W$47)<>0,L9*E48/SUMIF($E$25:$E$47,">=0",$W$25:$W$47),0) -> 80 | P9: =IF(AND(L9<>"",L9<>0,O9<>"",O9<>0),O9/L9,"") -> 0.60457516 | Q9: =IF(AND(M9<>0,M9<>"",L9<>0,L9<>""),O9-L9,"") -> -52.324324 | R9: =R8/R11 -> #DIV/0! | S9: =IF(AND(R9<>"",R9<>0,O9<>"",O9<>0),-R9+O9,"") -> #DIV/0! | T9: =IF(AND(S9<>"",S9<>0,R9<>0,R9<>""),S9/R9,"") -> #DIV/0!
I10: Средний чек | L10: =L11*L12 -> 11730 | M10: =H48 -> 10816.2 | N10: =IF(AND(L10<>"",L10<>0,M10<>""),M10/L10,"") -> 0.92209719 | O10: =M10 -> 10816.2 | P10: =IF(AND(L10<>"",L10<>0,O10<>"",O10<>0),O10/L10,"") -> 0.92209719 | Q10: =IF(AND(M10<>0,M10<>"",L10<>0,L10<>""),O10-L10,"") -> -913.8 | R10: =R11*R12 -> 0 | S10: =IF(AND(R10<>"",R10<>0,O10<>"",O10<>0),-R10+O10,"") | T10: =IF(AND(S10<>"",S10<>0,R10<>0,R10<>""),S10/R10,"")
I11: Средняя стоимость изделия | L11: =Центрум!I11 -> 6900 | M11: =F48 -> 6760.125 | N11: =IF(AND(L11<>"",L11<>0,M11<>""),M11/L11,"") -> 0.97972826 | O11: =M11 -> 6760.125 | P11: =IF(AND(L11<>"",L11<>0,O11<>"",O11<>0),O11/L11,"") -> 0.97972826 | Q11: =IF(AND(M11<>0,M11<>"",L11<>0,L11<>""),O11-L11,"") -> -139.875 | S11: =IF(AND(R11<>"",R11<>0,O11<>"",O11<>0),-R11+O11,"") | T11: =IF(AND(S11<>"",S11<>0,R11<>0,R11<>""),S11/R11,"")
I12: Длина чека | L12: =Центрум!I12 -> 1.7 | M12: =J48 -> 1.6 | N12: =IF(AND(L12<>"",L12<>0,M12<>""),M12/L12,"") -> 0.94117647 | O12: =M12 -> 1.6 | P12: =IF(AND(L12<>"",L12<>0,O12<>"",O12<>0),O12/L12,"") -> 0.94117647 | Q12: =IF(AND(M12<>0,M12<>"",L12<>0,L12<>""),O12-L12,"") -> -0.1 | S12: =IF(AND(R12<>"",R12<>0,O12<>"",O12<>0),-R12+O12,"") | T12: =IF(AND(S12<>"",S12<>0,R12<>0,R12<>""),S12/R12,"")
I13: Кол-во чеков | L13: =IF(L12<>0,L9/L12,"") -> 77.837838 | M13: =G48 -> 50 | N13: =IF(AND(L13<>"",L13<>0,M13<>""),M13/L13,"") -> 0.64236111 | O13: =IF(SUMIF($G$25:$G$47,">=0",$X$25:$X$47)<>0,L13*G48/SUMIF($G$25:$G$47,">=0",$X$25:$X$47),"") -> 50 | P13: =IF(AND(L13<>"",L13<>0,O13<>"",O13<>0),O13/L13,"") -> 0.64236111 | Q13: =IF(AND(M13<>0,M13<>"",L13<>0,L13<>""),O13-L13,"") -> -27.837838 | S13: =IF(AND(R13<>"",R13<>0,O13<>"",O13<>0),-R13+O13,"") | T13: =IF(AND(S13<>"",S13<>0,R13<>0,R13<>""),S13/R13,"")
I14: Кол-во смен план/отработано | L14: =График!AI26 -> 18 | M14: 18 | N14: =IF(AND(L14<>"",L14<>0,M14<>""),M14/L14,"") -> 1 | O14: =IF(SUMIF($D$25:$D$47,">=0",$V$25:$V$47),I48*L8/SUMIF($D$25:$D$47,">=0",$V$25:$V$47),"") -> 424 | Q14: =IF(AND(M14<>0,M14<>"",L14<>0,L14<>""),O14-L14,"") -> 406 | S14: =IF(AND(R14<>"",R14<>0,O14<>"",O14<>0),-R14+O14,"") | T14: =IF(AND(S14<>"",S14<>0,R14<>0,R14<>""),S14/R14,"")
I15: Средние продажи в смену | L15: =Центрум!I15/2 -> 31280 | M15: =M8/M14 -> 30045 | N15: =IF(AND(L15<>"",L15<>0,M15<>""),M15/L15,"") -> 0.9605179 | O15: =M15 -> 30045 | P15: =IF(AND(L15<>"",L15<>0,O15<>"",O15<>0),O15/L15,"") -> 0.9605179 | Q15: =IF(AND(M15<>0,M15<>"",L15<>0,L15<>""),O15-L15,"") -> -1235 | S15: =IF(AND(R15<>"",R15<>0,O15<>"",O15<>0),-R15+O15,"") | T15: =IF(AND(S15<>"",S15<>0,R15<>0,R15<>""),S15/R15,"") | V15: Подарочные сертификаты
I16: Отставание/Перевыполнение | M16: =M8-L15*M14 -> -22230 | N16: =IF(AND(L16<>"",L16<>0,M16<>""),M16/L16,"") | O16: =M16 -> -22230 | P16: =IF(AND(L16<>"",L16<>0,O16<>"",O16<>0),O16/L16,"") | Q16: =IF(AND(M16<>0,M16<>"",L16<>0,L16<>""),O16-L16,"") | S16: =IF(AND(R16<>"",R16<>0,O16<>"",O16<>0),-R16+O16,"") | T16: =IF(AND(S16<>"",S16<>0,R16<>0,R16<>""),S16/R16,"")
I17: Трафик | L17: =Центрум!I17/График!AJ29*График!AJ26 -> 778.37838 | M17: =I48 -> 424 | N17: =IF(AND(L17<>"",L17<>0,M17<>""),M17/L17,"") -> 0.54472222 | O17: =M17/M14*L14 -> 424 | P17: =IF(AND(L17<>"",L17<>0,O17<>"",O17<>0),O17/L17,"") -> 0.54472222 | Q17: =IF(AND(M17<>0,M17<>"",L17<>0,L17<>""),O17-L17,"") -> -354.37838 | S17: =IF(AND(R17<>"",R17<>0,O17<>"",O17<>0),-R17+O17,"") | T17: =IF(AND(S17<>"",S17<>0,R17<>0,R17<>""),S17/R17,"")
I18: Выручка на вошедшего | L18: =L8/L17 -> 1173 | M18: =M8/M17 -> 1275.4953 | N18: =IF(AND(L18<>"",L18<>0,M18<>""),M18/L18,"") -> 1.0873788 | O18: =M18 -> 1275.4953 | P18: =IF(AND(L18<>"",L18<>0,O18<>"",O18<>0),O18/L18,"") -> 1.0873788 | Q18: =IF(AND(M18<>0,M18<>"",L18<>0,L18<>""),O18-L18,"") -> 102.49528 | R18: 0 | S18: =IF(AND(R18<>"",R18<>0,O18<>"",O18<>0),-R18+O18,"") | T18: =IF(AND(S18<>"",S18<>0,R18<>0,R18<>""),S18/R18,"") | V18: =V17/L16 -> #DIV/0!
N19: =IF(AND(L19<>"",L19<>0,M19<>""),M19/L19,"") | O19: =M19 -> 0 | P19: =IF(AND(L19<>"",L19<>0,O19<>"",O19<>0),O19/L19,"") | Q19: =IF(AND(M19<>0,M19<>"",L19<>0,L19<>""),O19-L19,"") | R19: 0 | S19: =IF(AND(R19<>"",R19<>0,O19<>"",O19<>0),-R19+O19,"") | T19: =IF(AND(S19<>"",S19<>0,R19<>0,R19<>""),S19/R19,"")
I20: Конверсия план/факт | L20: =Центрум!I20 -> 0.1 | M20: =T48 -> 0.11792453 | N20: =M20/L20 -> 1.1792453 | O20: =IF(AND(N8<>0,L14<>0,I48<>0),(I48*T48+(I48/N8-I48)*L20)/(I48/N8),0) -> 0.11061705 | P20: =IF(AND(L20<>"",L20<>0,O20<>"",O20<>0),O20/L20,"") -> 1.1061705 | Q20: =IF(AND(M20<>0,M20<>"",L20<>0,L20<>""),O20-L20,"") -> 0.010617045 | S20: =IF(AND(R20<>"",R20<>0,O20<>"",O20<>0),-R20+O20,"") | T20: =IF(AND(S20<>"",S20<>0,R20<>0,R20<>""),S20/R20,"")
A22: Факт продаж за месяц | U22: % выполнения дневного плана | V22: Раcпределение плана по дням
B23: Дата | C23: День недели | D23: Выручка (руб) | E23: Кол-во единиц (шт.) | F23: Средняя стоимость изделия (руб.) | G23: Количество чеков (шт.) | H23: Средняя сумма чека (руб.) | I23: Трафик | J23: Длина чека (шт.) | K23: UNOde50 | L23: IS | M23: Agafi | N23: Kalliope | O23: Raganella | P23: CC/MP | Q23: Eva Rites | R23: Antura | S23: SALE | T23: Конверсия (%) | V23: выручка, план | W23: кол-во ед, план | X23: Кол-во чеков, план | Y23: выручка, скорректир.план | Z23: кол-во ед, скорр. план | AA23: кол-во чеков, скорр. план | AB23: Коэфф. Дня Недели | AC23: Специфика месяца
B24: 1 | C24: 2 | D24: 3 | E24: в | F24: 5 | G24: 6 | H24: 7 | I24: 8 | J24: 9 | K24: 10 | L24: 11 | M24: 12 | N24: 13 | O24: 14 | P24: 15 | Q24: 16 | R24: 17 | T24: 18 | V24: 1 | W24: 2 | X24: 3 | Y24: 4 | Z24: 5 | AA24: 6 | AB24: 10 | AC24: 11
A25: 1 | B25: 46114 | C25: чт | D25: 29523 | E25: 3 | F25: =IF(AND(E25<>"",E25<>0),D25/E25,"") -> 9841 | G25: 2 | H25: =IF(AND(G25<>"",G25<>0),D25/G25,"") -> 14761.5 | I25: 40 | J25: =IF(AND(G25<>"",G25<>0),E25/G25,"") -> 1.5 | P25: 12391 | T25: =IF(AND(I25<>"",I25<>0),G25/I25,"") -> 0.05 | U25: =D25/V25 -> 0.48502371 | V25: =$L$8*AB25*AC25/SUMPRODUCT($AC$25:$AC$55,$AB$25:$AB$55) -> 60869.189 | W25: =$L$9*AB25*AC25/SUMPRODUCT($AC$25:$AC$55,$AB$25:$AB$55) -> 8.8216216 | X25: =IF($L$12="","",W25/$L$12) -> 5.1891892 | Y25: =IF(AC25<>"",IF(D25<>"",D25,($L$8-SUM($Y24:Y$25))*AB25*AC25/SUMPRODUCT($AC25:$AC$47,$AB25:$AB$47)),"") -> 29523 | Z25: =IF(AC25<>"",IF(E25<>"",E25,($L$9-SUM($Z24:Z$25))*AB25*AC25/SUMPRODUCT($AC25:$AC$55,$AB25:$AB$55)),"") -> 3 | AA25: =IF(AC25<>"",IF($L$12<>"",IF(G25<>"",G25,($L$9/$L$12-SUM($AA24:AA$25))*AB25*AC25/SUMPRODUCT($AC25:$AC$55,$AB25:$AB$55)),""),"") -> 2 | AB25: 1 | AC25: 1
A26: 2 | B26: 46115 | C26: пт | D26: 14876 | E26: 3 | F26: =IF(AND(E26<>"",E26<>0),D26/E26,"") -> 4958.6667 | G26: 2 | H26: =IF(AND(G26<>"",G26<>0),D26/G26,"") -> 7438 | I26: 44 | J26: =IF(AND(G26<>"",G26<>0),E26/G26,"") -> 1.5 | T26: =IF(AND(I26<>"",I26<>0),G26/I26,"") -> 0.045454545 | U26: =D26/V26 -> 0.24439294 | V26: =$L$8*AB26*AC26/SUMPRODUCT($AC$25:$AC$55,$AB$25:$AB$55) -> 60869.189 | W26: =$L$9*AB26*AC26/SUMPRODUCT($AC$25:$AC$55,$AB$25:$AB$55) -> 8.8216216 | X26: =IF($L$12="","",W26/$L$12) -> 5.1891892 | Y26: =IF(AC26<>"",IF(D26<>"",D26,($L$8-SUM($Y$25:Y25))*AB26*AC26/SUMPRODUCT($AC26:$AC$55,$AB26:$AB$55)),"") -> 14876 | Z26: =IF(AC26<>"",IF(E26<>"",E26,($L$9-SUM($Z$25:Z25))*AB26*AC26/SUMPRODUCT($AC26:$AC$55,$AB26:$AB$55)),"") -> 3 | AA26: =IF(AC26<>"",IF($L$12<>"",IF(G26<>"",G26,($L$9/$L$12-SUM($AA$25:AA25))*AB26*AC26/SUMPRODUCT($AC26:$AC$55,$AB26:$AB$55)),""),"") -> 2 | AB26: 1 | AC26: 1
A27: 3 | B27: 46119 | C27: вт | D27: 16967 | E27: 3 | F27: =IF(AND(E27<>"",E27<>0),D27/E27,"") -> 5655.6667 | G27: 2 | H27: =IF(AND(G27<>"",G27<>0),D27/G27,"") -> 8483.5 | I27: 20 | J27: =IF(AND(G27<>"",G27<>0),E27/G27,"") -> 1.5 | T27: =IF(AND(I27<>"",I27<>0),G27/I27,"") -> 0.1 | U27: =D27/V27 -> 0.27874529 | V27: =$L$8*AB27*AC27/SUMPRODUCT($AC$25:$AC$55,$AB$25:$AB$55) -> 60869.189 | W27: =$L$9*AB27*AC27/SUMPRODUCT($AC$25:$AC$55,$AB$25:$AB$55) -> 8.8216216 | X27: =IF($L$12="","",W27/$L$12) -> 5.1891892 | Y27: =IF(AC27<>"",IF(D27<>"",D27,($L$8-SUM($Y$25:Y26))*AB27*AC27/SUMPRODUCT($AC27:$AC$55,$AB27:$AB$55)),"") -> 16967 | Z27: =IF(AC27<>"",IF(E27<>"",E27,($L$9-SUM($Z$25:Z26))*AB27*AC27/SUMPRODUCT($AC27:$AC$55,$AB27:$AB$55)),"") -> 3 | AA27: =IF(AC27<>"",IF($L$12<>"",IF(G27<>"",G27,($L$9/$L$12-SUM($AA$25:AA26))*AB27*AC27/SUMPRODUCT($AC27:$AC$55,$AB27:$AB$55)),""),"") -> 2 | AB27: 1 | AC27: 1
A28: 4 | B28: 46120 | C28: ср | D28: 68941 | E28: 6 | F28: =IF(AND(E28<>"",E28<>0),D28/E28,"") -> 11490.167 | G28: 4 | H28: =IF(AND(G28<>"",G28<>0),D28/G28,"") -> 17235.25 | I28: 20 | J28: =IF(AND(G28<>"",G28<>0),E28/G28,"") -> 1.5 | K28: 51415 | M28: 7093 | R28: 6440 | T28: =IF(AND(I28<>"",I28<>0),G28/I28,"") -> 0.2 | U28: =D28/V28 -> 1.1326091 | V28: =$L$8*AB28*AC28/SUMPRODUCT($AC$25:$AC$55,$AB$25:$AB$55) -> 60869.189 | W28: =$L$9*AB28*AC28/SUMPRODUCT($AC$25:$AC$55,$AB$25:$AB$55) -> 8.8216216 | X28: =IF($L$12="","",W28/$L$12) -> 5.1891892 | Y28: =IF(AC28<>"",IF(D28<>"",D28,($L$8-SUM($Y$25:Y27))*AB28*AC28/SUMPRODUCT($AC28:$AC$55,$AB28:$AB$55)),"") -> 68941 | Z28: =IF(AC28<>"",IF(E28<>"",E28,($L$9-SUM($Z$25:Z27))*AB28*AC28/SUMPRODUCT($AC28:$AC$55,$AB28:$AB$55)),"") -> 6 | AA28: =IF(AC28<>"",IF($L$12<>"",IF(G28<>"",G28,($L$9/$L$12-SUM($AA$25:AA27))*AB28*AC28/SUMPRODUCT($AC28:$AC$55,$AB28:$AB$55)),""),"") -> 4 | AB28: 1 | AC28: 1
A29: 5 | B29: 46122 | C29: пт | D29: 23175 | E29: 4 | F29: =IF(AND(E29<>"",E29<>0),D29/E29,"") -> 5793.75 | G29: 2 | H29: =IF(AND(G29<>"",G29<>0),D29/G29,"") -> 11587.5 | I29: 15 | J29: =IF(AND(G29<>"",G29<>0),E29/G29,"") -> 2 | T29: =IF(AND(I29<>"",I29<>0),G29/I29,"") -> 0.13333333 | U29: =D29/V29 -> 0.38073449 | V29: =$L$8*AB29*AC29/SUMPRODUCT($AC$25:$AC$55,$AB$25:$AB$55) -> 60869.189 | W29: =$L$9*AB29*AC29/SUMPRODUCT($AC$25:$AC$55,$AB$25:$AB$55) -> 8.8216216 | X29: =IF($L$12="","",W29/$L$12) -> 5.1891892 | Y29: =IF(AC29<>"",IF(D29<>"",D29,($L$8-SUM($Y$25:Y28))*AB29*AC29/SUMPRODUCT($AC29:$AC$55,$AB29:$AB$55)),"") -> 23175 | Z29: =IF(AC29<>"",IF(E29<>"",E29,($L$9-SUM($Z$25:Z28))*AB29*AC29/SUMPRODUCT($AC29:$AC$55,$AB29:$AB$55)),"") -> 4 | AA29: =IF(AC29<>"",IF($L$12<>"",IF(G29<>"",G29,($L$9/$L$12-SUM($AA$25:AA28))*AB29*AC29/SUMPRODUCT($AC29:$AC$55,$AB29:$AB$55)),""),"") -> 2 | AB29: 1 | AC29: 1
A30: 6 | B30: 46123 | C30: сб | D30: 77762 | E30: 10 | F30: =IF(AND(E30<>"",E30<>0),D30/E30,"") -> 7776.2 | G30: 6 | H30: =IF(AND(G30<>"",G30<>0),D30/G30,"") -> 12960.333 | I30: 40 | J30: =IF(AND(G30<>"",G30<>0),E30/G30,"") -> 1.6666667 | R30: 25513 | T30: =IF(AND(I30<>"",I30<>0),G30/I30,"") -> 0.15 | U30: =D30/V30 -> 1.2775265 | V30: =$L$8*AB30*AC30/SUMPRODUCT($AC$25:$AC$55,$AB$25:$AB$55) -> 60869.189 | W30: =$L$9*AB30*AC30/SUMPRODUCT($AC$25:$AC$55,$AB$25:$AB$55) -> 8.8216216 | X30: =IF($L$12="","",W30/$L$12) -> 5.1891892 | Y30: =IF(AC30<>"",IF(D30<>"",D30,($L$8-SUM($Y$25:Y29))*AB30*AC30/SUMPRODUCT($AC30:$AC$55,$AB30:$AB$55)),"") -> 77762 | Z30: =IF(AC30<>"",IF(E30<>"",E30,($L$9-SUM($Z$25:Z29))*AB30*AC30/SUMPRODUCT($AC30:$AC$55,$AB30:$AB$55)),"") -> 10 | AA30: =IF(AC30<>"",IF($L$12<>"",IF(G30<>"",G30,($L$9/$L$12-SUM($AA$25:AA29))*AB30*AC30/SUMPRODUCT($AC30:$AC$55,$AB30:$AB$55)),""),"") -> 6 | AB30: 1 | AC30: 1
A31: 7 | B31: 46125 | C31: пн | D31: 44417 | E31: 6 | F31: =IF(AND(E31<>"",E31<>0),D31/E31,"") -> 7402.8333 | G31: 5 | H31: =IF(AND(G31<>"",G31<>0),D31/G31,"") -> 8883.4 | I31: 30 | J31: =IF(AND(G31<>"",G31<>0),E31/G31,"") -> 1.2 | K31: 10993 | O31: 7658 | T31: =IF(AND(I31<>"",I31<>0),G31/I31,"") -> 0.16666667 | U31: =D31/V31 -> 0.72971237 | V31: =$L$8*AB31*AC31/SUMPRODUCT($AC$25:$AC$55,$AB$25:$AB$55) -> 60869.189 | W31: =$L$9*AB31*AC31/SUMPRODUCT($AC$25:$AC$55,$AB$25:$AB$55) -> 8.8216216 | X31: =IF($L$12="","",W31/$L$12) -> 5.1891892 | Y31: =IF(AC31<>"",IF(D31<>"",D31,($L$8-SUM($Y$25:Y30))*AB31*AC31/SUMPRODUCT($AC31:$AC$55,$AB31:$AB$55)),"") -> 44417 | Z31: =IF(AC31<>"",IF(E31<>"",E31,($L$9-SUM($Z$25:Z30))*AB31*AC31/SUMPRODUCT($AC31:$AC$55,$AB31:$AB$55)),"") -> 6 | AA31: =IF(AC31<>"",IF($L$12<>"",IF(G31<>"",G31,($L$9/$L$12-SUM($AA$25:AA30))*AB31*AC31/SUMPRODUCT($AC31:$AC$55,$AB31:$AB$55)),""),"") -> 5 | AB31: 1 | AC31: 1
A32: 8 | B32: 46127 | C32: ср | D32: 4196 | E32: 1 | F32: =IF(AND(E32<>"",E32<>0),D32/E32,"") -> 4196 | G32: 1 | H32: =IF(AND(G32<>"",G32<>0),D32/G32,"") -> 4196 | I32: 20 | J32: =IF(AND(G32<>"",G32<>0),E32/G32,"") -> 1 | S32: 4193 | T32: =IF(AND(I32<>"",I32<>0),G32/I32,"") -> 0.05 | U32: =D32/V32 -> 0.068934712 | V32: =$L$8*AB32*AC32/SUMPRODUCT($AC$25:$AC$55,$AB$25:$AB$55) -> 60869.189 | W32: =$L$9*AB32*AC32/SUMPRODUCT($AC$25:$AC$55,$AB$25:$AB$55) -> 8.8216216 | X32: =IF($L$12="","",W32/$L$12) -> 5.1891892 | Y32: =IF(AC32<>"",IF(D32<>"",D32,($L$8-SUM($Y$25:Y31))*AB32*AC32/SUMPRODUCT($AC32:$AC$55,$AB32:$AB$55)),"") -> 4196 | Z32: =IF(AC32<>"",IF(E32<>"",E32,($L$9-SUM($Z$25:Z31))*AB32*AC32/SUMPRODUCT($AC32:$AC$55,$AB32:$AB$55)),"") -> 1 | AA32: =IF(AC32<>"",IF($L$12<>"",IF(G32<>"",G32,($L$9/$L$12-SUM($AA$25:AA31))*AB32*AC32/SUMPRODUCT($AC32:$AC$55,$AB32:$AB$55)),""),"") -> 1 | AB32: 1 | AC32: 1
A33: 9 | B33: 46128 | C33: сб | D33: 38263 | E33: 7 | F33: =IF(AND(E33<>"",E33<>0),D33/E33,"") -> 5466.1429 | G33: 4 | H33: =IF(AND(G33<>"",G33<>0),D33/G33,"") -> 9565.75 | I33: 35 | J33: =IF(AND(G33<>"",G33<>0),E33/G33,"") -> 1.75 | T33: =IF(AND(I33<>"",I33<>0),G33/I33,"") -> 0.11428571 | U33: =D33/V33 -> 0.62861031 | V33: =$L$8*AB33*AC33/SUMPRODUCT($AC$25:$AC$55,$AB$25:$AB$55) -> 60869.189 | W33: =$L$9*AB33*AC33/SUMPRODUCT($AC$25:$AC$55,$AB$25:$AB$55) -> 8.8216216 | X33: =IF($L$12="","",W33/$L$12) -> 5.1891892 | Y33: =IF(AC33<>"",IF(D33<>"",D33,($L$8-SUM($Y$25:Y32))*AB33*AC33/SUMPRODUCT($AC33:$AC$55,$AB33:$AB$55)),"") -> 38263 | Z33: =IF(AC33<>"",IF(E33<>"",E33,($L$9-SUM($Z$25:Z32))*AB33*AC33/SUMPRODUCT($AC33:$AC$55,$AB33:$AB$55)),"") -> 7 | AA33: =IF(AC33<>"",IF($L$12<>"",IF(G33<>"",G33,($L$9/$L$12-SUM($AA$25:AA32))*AB33*AC33/SUMPRODUCT($AC33:$AC$55,$AB33:$AB$55)),""),"") -> 4 | AB33: 1 | AC33: 1
A34: 10 | B34: 46131 | C34: вс | D34: 38216 | E34: 6 | F34: =IF(AND(E34<>"",E34<>0),D34/E34,"") -> 6369.3333 | G34: 4 | H34: =IF(AND(G34<>"",G34<>0),D34/G34,"") -> 9554 | I34: 40 | J34: =IF(AND(G34<>"",G34<>0),E34/G34,"") -> 1.5 | T34: =IF(AND(I34<>"",I34<>0),G34/I34,"") -> 0.1 | U34: =D34/V34 -> 0.62783816 | V34: =$L$8*AB34*AC34/SUMPRODUCT($AC$25:$AC$55,$AB$25:$AB$55) -> 60869.189 | W34: =$L$9*AB34*AC34/SUMPRODUCT($AC$25:$AC$55,$AB$25:$AB$55) -> 8.8216216 | X34: =IF($L$12="","",W34/$L$12) -> 5.1891892 | Y34: =IF(AC34<>"",IF(D34<>"",D34,($L$8-SUM($Y$25:Y33))*AB34*AC34/SUMPRODUCT($AC34:$AC$55,$AB34:$AB$55)),"") -> 38216 | Z34: =IF(AC34<>"",IF(E34<>"",E34,($L$9-SUM($Z$25:Z33))*AB34*AC34/SUMPRODUCT($AC34:$AC$55,$AB34:$AB$55)),"") -> 6 | AA34: =IF(AC34<>"",IF($L$12<>"",IF(G34<>"",G34,($L$9/$L$12-SUM($AA$25:AA33))*AB34*AC34/SUMPRODUCT($AC34:$AC$55,$AB34:$AB$55)),""),"") -> 4 | AB34: 1 | AC34: 1
A35: 11 | B35: 46133 | C35: вт | D35: 0 | E35: 0 | F35: 0 | G35: 0 | H35: 0 | I35: 8 | J35: =IF(AND(G35<>"",G35<>0),E35/G35,"") | T35: =IF(AND(I35<>"",I35<>0),G35/I35,"") -> 0 | U35: =D35/V35 -> 0 | V35: =$L$8*AB35*AC35/SUMPRODUCT($AC$25:$AC$55,$AB$25:$AB$55) -> 60869.189 | W35: =$L$9*AB35*AC35/SUMPRODUCT($AC$25:$AC$55,$AB$25:$AB$55) -> 8.8216216 | X35: =IF($L$12="","",W35/$L$12) -> 5.1891892 | Y35: =IF(AC35<>"",IF(D35<>"",D35,($L$8-SUM($Y$25:Y34))*AB35*AC35/SUMPRODUCT($AC35:$AC$55,$AB35:$AB$55)),"") -> 0 | Z35: =IF(AC35<>"",IF(E35<>"",E35,($L$9-SUM($Z$25:Z34))*AB35*AC35/SUMPRODUCT($AC35:$AC$55,$AB35:$AB$55)),"") -> 0 | AA35: =IF(AC35<>"",IF($L$12<>"",IF(G35<>"",G35,($L$9/$L$12-SUM($AA$25:AA34))*AB35*AC35/SUMPRODUCT($AC35:$AC$55,$AB35:$AB$55)),""),"") -> 0 | AB35: 1 | AC35: 1
A36: 12 | B36: 46134 | C36: ср | D36: 23254 | E36: 3 | F36: =IF(AND(E36<>"",E36<>0),D36/E36,"") -> 7751.3333 | G36: 2 | H36: =IF(AND(G36<>"",G36<>0),D36/G36,"") -> 11627 | I36: 12 | J36: =IF(AND(G36<>"",G36<>0),E36/G36,"") -> 1.5 | O36: 9682 | S36: 7890 | T36: =IF(AND(I36<>"",I36<>0),G36/I36,"") -> 0.16666667 | U36: =D36/V36 -> 0.38203236 | V36: =$L$8*AB36*AC36/SUMPRODUCT($AC$25:$AC$55,$AB$25:$AB$55) -> 60869.189 | W36: =$L$9*AB36*AC36/SUMPRODUCT($AC$25:$AC$55,$AB$25:$AB$55) -> 8.8216216 | X36: =IF($L$12="","",W36/$L$12) -> 5.1891892 | Y36: =IF(AC36<>"",IF(D36<>"",D36,($L$8-SUM($Y$25:Y35))*AB36*AC36/SUMPRODUCT($AC36:$AC$55,$AB36:$AB$55)),"") -> 23254 | Z36: =IF(AC36<>"",IF(E36<>"",E36,($L$9-SUM($Z$25:Z35))*AB36*AC36/SUMPRODUCT($AC36:$AC$55,$AB36:$AB$55)),"") -> 3 | AA36: =IF(AC36<>"",IF($L$12<>"",IF(G36<>"",G36,($L$9/$L$12-SUM($AA$25:AA35))*AB36*AC36/SUMPRODUCT($AC36:$AC$55,$AB36:$AB$55)),""),"") -> 2 | AB36: 1 | AC36: 1
A37: 13 | B37: 46135 | C37: чт | D37: 12086 | E37: 2 | F37: =IF(AND(E37<>"",E37<>0),D37/E37,"") -> 6043 | G37: 2 | H37: =IF(AND(G37<>"",G37<>0),D37/G37,"") -> 6043 | I37: 20 | J37: =IF(AND(G37<>"",G37<>0),E37/G37,"") -> 1 | T37: =IF(AND(I37<>"",I37<>0),G37/I37,"") -> 0.1 | U37: =D37/V37 -> 0.19855694 | V37: =$L$8*AB37*AC37/SUMPRODUCT($AC$25:$AC$55,$AB$25:$AB$55) -> 60869.189 | W37: =$L$9*AB37*AC37/SUMPRODUCT($AC$25:$AC$55,$AB$25:$AB$55) -> 8.8216216 | X37: =IF($L$12="","",W37/$L$12) -> 5.1891892 | Y37: =IF(AC37<>"",IF(D37<>"",D37,($L$8-SUM($Y$25:Y36))*AB37*AC37/SUMPRODUCT($AC37:$AC$55,$AB37:$AB$55)),"") -> 12086 | Z37: =IF(AC37<>"",IF(E37<>"",E37,($L$9-SUM($Z$25:Z36))*AB37*AC37/SUMPRODUCT($AC37:$AC$55,$AB37:$AB$55)),"") -> 2 | AA37: =IF(AC37<>"",IF($L$12<>"",IF(G37<>"",G37,($L$9/$L$12-SUM($AA$25:AA36))*AB37*AC37/SUMPRODUCT($AC37:$AC$55,$AB37:$AB$55)),""),"") -> 2 | AB37: 1 | AC37: 1
A38: 14 | B38: 46136 | C38: пт | D38: 27886 | E38: 4 | F38: =IF(AND(E38<>"",E38<>0),D38/E38,"") -> 6971.5 | G38: 3 | H38: =IF(AND(G38<>"",G38<>0),D38/G38,"") -> 9295.3333 | I38: 30 | J38: =IF(AND(G38<>"",G38<>0),E38/G38,"") -> 1.3333333 | O38: 12593 | T38: =IF(AND(I38<>"",I38<>0),G38/I38,"") -> 0.1 | U38: =D38/V38 -> 0.45812997 | V38: =$L$8*AB38*AC38/SUMPRODUCT($AC$25:$AC$46,$AB$25:$AB$46) -> 60869.189 | W38: =$L$9*AB38*AC38/SUMPRODUCT($AC$25:$AC$46,$AB$25:$AB$46) -> 8.8216216 | X38: =IF($L$12="","",W38/$L$12) -> 5.1891892 | Y38: =IF(AC38<>"",IF(D38<>"",D38,($L$8-SUM($Y$25:Y37))*AB38*AC38/SUMPRODUCT($AC38:$AC$55,$AB38:$AB$55)),"") -> 27886 | Z38: =IF(AC38<>"",IF(E38<>"",E38,($L$9-SUM($Z$25:Z37))*AB38*AC38/SUMPRODUCT($AC38:$AC$55,$AB38:$AB$55)),"") -> 4 | AA38: =IF(AC38<>"",IF($L$12<>"",IF(G38<>"",G38,($L$9/$L$12-SUM($AA$25:AA37))*AB38*AC38/SUMPRODUCT($AC38:$AC$55,$AB38:$AB$55)),""),"") -> 3 | AB38: 1 | AC38: 1
A39: 15 | B39: 46137 | C39: сб | D39: 9920 | E39: 2 | F39: =IF(AND(E39<>"",E39<>0),D39/E39,"") -> 4960 | G39: 2 | H39: =IF(AND(G39<>"",G39<>0),D39/G39,"") -> 4960 | I39: 40 | J39: =IF(AND(G39<>"",G39<>0),E39/G39,"") -> 1 | T39: =IF(AND(I39<>"",I39<>0),G39/I39,"") -> 0.05 | U39: =D39/V39 -> 0.16297244 | V39: =$L$8*AB39*AC39/SUMPRODUCT($AC$25:$AC$46,$AB$25:$AB$46) -> 60869.189 | W39: =$L$9*AB39*AC39/SUMPRODUCT($AC$25:$AC$46,$AB$25:$AB$46) -> 8.8216216 | X39: =IF($L$12="","",W39/$L$12) -> 5.1891892 | Y39: =IF(AC39<>"",IF(D39<>"",D39,($L$8-SUM($Y$25:Y38))*AB39*AC39/SUMPRODUCT($AC39:$AC$55,$AB39:$AB$55)),"") -> 9920 | Z39: =IF(AC39<>"",IF(E39<>"",E39,($L$9-SUM($Z$25:Z38))*AB39*AC39/SUMPRODUCT($AC39:$AC$55,$AB39:$AB$55)),"") -> 2 | AA39: =IF(AC39<>"",IF($L$12<>"",IF(G39<>"",G39,($L$9/$L$12-SUM($AA$25:AA38))*AB39*AC39/SUMPRODUCT($AC39:$AC$55,$AB39:$AB$55)),""),"") -> 2 | AB39: 1 | AC39: 1
A40: 16 | B40: 46139 | C40: пн | D40: 48248 | E40: 7 | F40: =IF(AND(E40<>"",E40<>0),D40/E40,"") -> 6892.5714 | G40: 2 | H40: =IF(AND(G40<>"",G40<>0),D40/G40,"") -> 24124 | I40: 30 | J40: =IF(AND(G40<>"",G40<>0),E40/G40,"") -> 3.5 | T40: =IF(AND(I40<>"",I40<>0),G40/I40,"") -> 0.066666667 | U40: =D40/V40 -> #DIV/0! | V40: =$L$8*AB40*AC40/SUMPRODUCT($AC$25:$AC$46,$AB$25:$AB$46) -> 0 | W40: =$L$9*AB40*AC40/SUMPRODUCT($AC$25:$AC$46,$AB$25:$AB$46) -> 0 | X40: =IF($L$12="","",W40/$L$12) -> 0 | Y40: =IF(AC40<>"",IF(D40<>"",D40,($L$8-SUM($Y$25:Y39))*AB40*AC40/SUMPRODUCT($AC40:$AC$55,$AB40:$AB$55)),"") | Z40: =IF(AC40<>"",IF(E40<>"",E40,($L$9-SUM($Z$25:Z39))*AB40*AC40/SUMPRODUCT($AC40:$AC$55,$AB40:$AB$55)),"") | AA40: =IF(AC40<>"",IF($L$12<>"",IF(G40<>"",G40,($L$9/$L$12-SUM($AA$25:AA39))*AB40*AC40/SUMPRODUCT($AC40:$AC$55,$AB40:$AB$55)),""),"")
A41: 17 | B41: 46140 | C41: вт | D41: 63080 | E41: 13 | F41: =IF(AND(E41<>"",E41<>0),D41/E41,"") -> 4852.3077 | G41: 7 | H41: =IF(AND(G41<>"",G41<>0),D41/G41,"") -> 9011.4286 | I41: 45 | J41: =IF(AND(G41<>"",G41<>0),E41/G41,"") -> 1.8571429 | S41: 25135 | T41: =IF(AND(I41<>"",I41<>0),G41/I41,"") -> 0.15555556 | U41: =D41/V41 -> #DIV/0! | V41: =$L$8*AB41*AC41/SUMPRODUCT($AC$25:$AC$46,$AB$25:$AB$46) -> 0 | W41: =$L$9*AB41*AC41/SUMPRODUCT($AC$25:$AC$46,$AB$25:$AB$46) -> 0 | X41: =IF($L$12="","",W41/$L$12) -> 0 | Y41: =IF(AC41<>"",IF(D41<>"",D41,($L$8-SUM($Y$25:Y40))*AB41*AC41/SUMPRODUCT($AC41:$AC$55,$AB41:$AB$55)),"") | Z41: =IF(AC41<>"",IF(E41<>"",E41,($L$9-SUM($Z$25:Z40))*AB41*AC41/SUMPRODUCT($AC41:$AC$55,$AB41:$AB$55)),"") | AA41: =IF(AC41<>"",IF($L$12<>"",IF(G41<>"",G41,($L$9/$L$12-SUM($AA$25:AA40))*AB41*AC41/SUMPRODUCT($AC41:$AC$55,$AB41:$AB$55)),""),"")
A42: 18 | B42: 46141 | C42: ср | D42: 0 | E42: 0 | F42: 0 | G42: 0 | H42: 0 | I42: 41 | J42: =IF(AND(G42<>"",G42<>0),E42/G42,"") | T42: =IF(AND(I42<>"",I42<>0),G42/I42,"") -> 0 | U42: =D42/V42 -> #DIV/0! | V42: =$L$8*AB42*AC42/SUMPRODUCT($AC$25:$AC$46,$AB$25:$AB$46) -> 0 | W42: =$L$9*AB42*AC42/SUMPRODUCT($AC$25:$AC$46,$AB$25:$AB$46) -> 0 | X42: =IF($L$12="","",W42/$L$12) -> 0 | Y42: =IF(AC42<>"",IF(D42<>"",D42,($L$8-SUM($Y$25:Y41))*AB42*AC42/SUMPRODUCT($AC42:$AC$55,$AB42:$AB$55)),"") | Z42: =IF(AC42<>"",IF(E42<>"",E42,($L$9-SUM($Z$25:Z41))*AB42*AC42/SUMPRODUCT($AC42:$AC$55,$AB42:$AB$55)),"") | AA42: =IF(AC42<>"",IF($L$12<>"",IF(G42<>"",G42,($L$9/$L$12-SUM($AA$25:AA41))*AB42*AC42/SUMPRODUCT($AC42:$AC$55,$AB42:$AB$55)),""),"")
A43: 19 | F43: =IF(AND(E43<>"",E43<>0),D43/E43,"") | H43: =IF(AND(G43<>"",G43<>0),D43/G43,"") | J43: =IF(AND(G43<>"",G43<>0),E43/G43,"") | T43: =IF(AND(I43<>"",I43<>0),G43/I43,"") | U43: =D43/V43 -> #DIV/0! | V43: =$L$8*AB43*AC43/SUMPRODUCT($AC$25:$AC$46,$AB$25:$AB$46) -> 0 | W43: =$L$9*AB43*AC43/SUMPRODUCT($AC$25:$AC$46,$AB$25:$AB$46) -> 0 | X43: =IF($L$12="","",W43/$L$12) -> 0 | Y43: =IF(AC43<>"",IF(D43<>"",D43,($L$8-SUM($Y$25:Y42))*AB43*AC43/SUMPRODUCT($AC43:$AC$55,$AB43:$AB$55)),"") | Z43: =IF(AC43<>"",IF(E43<>"",E43,($L$9-SUM($Z$25:Z42))*AB43*AC43/SUMPRODUCT($AC43:$AC$46,$AB43:$AB$46)),"") | AA43: =IF(AC43<>"",IF($L$12<>"",IF(G43<>"",G43,($L$9/$L$12-SUM($AA$25:AA42))*AB43*AC43/SUMPRODUCT($AC43:$AC$46,$AB43:$AB$46)),""),"")
A44: 20 | F44: =IF(AND(E44<>"",E44<>0),D44/E44,"") | H44: =IF(AND(G44<>"",G44<>0),D44/G44,"") | J44: =IF(AND(G44<>"",G44<>0),E44/G44,"") | T44: =IF(AND(I44<>"",I44<>0),G44/I44,"") | U44: =D44/V44 -> #DIV/0! | V44: =$L$8*AB44*AC44/SUMPRODUCT($AC$25:$AC$46,$AB$25:$AB$46) -> 0 | W44: =$L$9*AB44*AC44/SUMPRODUCT($AC$25:$AC$46,$AB$25:$AB$46) -> 0 | X44: =IF($L$12="","",W44/$L$12) -> 0 | Y44: =IF(AC44<>"",IF(D44<>"",D44,($L$8-SUM($Y$25:Y43))*AB44*AC44/SUMPRODUCT($AC44:$AC$46,$AB44:$AB$46)),"") | Z44: =IF(AC44<>"",IF(E44<>"",E44,($L$9-SUM($Z$25:Z43))*AB44*AC44/SUMPRODUCT($AC44:$AC$46,$AB44:$AB$46)),"") | AA44: =IF(AC44<>"",IF($L$12<>"",IF(G44<>"",G44,($L$9/$L$12-SUM($AA$25:AA43))*AB44*AC44/SUMPRODUCT($AC44:$AC$46,$AB44:$AB$46)),""),"")
A45: 21 | F45: =IF(AND(E45<>"",E45<>0),D45/E45,"") | H45: =IF(AND(G45<>"",G45<>0),D45/G45,"") | J45: =IF(AND(G45<>"",G45<>0),E45/G45,"") | T45: =IF(AND(I45<>"",I45<>0),G45/I45,"") | U45: =D45/V45 -> #DIV/0! | V45: =$L$8*AB45*AC45/SUMPRODUCT($AC$25:$AC$46,$AB$25:$AB$46) -> 0 | W45: =$L$9*AB45*AC45/SUMPRODUCT($AC$25:$AC$46,$AB$25:$AB$46) -> 0 | X45: =IF($L$12="","",W45/$L$12) -> 0 | Y45: =IF(AC45<>"",IF(D45<>"",D45,($L$8-SUM($Y$25:Y44))*AB45*AC45/SUMPRODUCT($AC45:$AC$46,$AB45:$AB$46)),"") | Z45: =IF(AC45<>"",IF(E45<>"",E45,($L$9-SUM($Z$25:Z44))*AB45*AC45/SUMPRODUCT($AC45:$AC$46,$AB45:$AB$46)),"") | AA45: =IF(AC45<>"",IF($L$12<>"",IF(G45<>"",G45,($L$9/$L$12-SUM($AA$25:AA44))*AB45*AC45/SUMPRODUCT($AC45:$AC$46,$AB45:$AB$46)),""),"")
A46: 22 | F46: =IF(AND(E46<>"",E46<>0),D46/E46,"") | H46: =IF(AND(G46<>"",G46<>0),D46/G46,"") | J46: =IF(AND(G46<>"",G46<>0),E46/G46,"") | T46: =IF(AND(I46<>"",I46<>0),G46/I46,"") | U46: =D46/V46 -> #DIV/0! | V46: =$L$8*AB46*AC46/SUMPRODUCT($AC$25:$AC$46,$AB$25:$AB$46) -> 0 | W46: =$L$9*AB46*AC46/SUMPRODUCT($AC$25:$AC$46,$AB$25:$AB$46) -> 0 | X46: =IF($L$12="","",W46/$L$12) -> 0 | Y46: =IF(AC46<>"",IF(D46<>"",D46,($L$8-SUM($Y$25:Y45))*AB46*AC46/SUMPRODUCT($AC46:$AC$46,$AB46:$AB$46)),"") | Z46: =IF(AC46<>"",IF(E46<>"",E46,($L$9-SUM($Z$25:Z39))*AB46*AC46/SUMPRODUCT($AC46:$AC$46,$AB46:$AB$46)),"") | AA46: =IF(AC46<>"",IF($L$12<>"",IF(G46<>"",G46,($L$9/$L$12-SUM($AA$25:AA39))*AB46*AC46/SUMPRODUCT($AC46:$AC$46,$AB46:$AB$46)),""),"")
A47: 23 | F47: =IF(AND(E47<>"",E47<>0),D47/E47,"") | H47: =IF(AND(G47<>"",G47<>0),D47/G47,"") | J47: =IF(AND(G47<>"",G47<>0),E47/G47,"") | T47: =IF(AND(I47<>"",I47<>0),G47/I47,"") | U47: =D47/V47 -> #DIV/0! | V47: =$L$8*AB47*AC47/SUMPRODUCT($AC$25:$AC$46,$AB$25:$AB$46) -> 0 | W47: =$L$9*AB47*AC47/SUMPRODUCT($AC$25:$AC$46,$AB$25:$AB$46) -> 0 | X47: =IF($L$12="","",W47/$L$12) -> 0 | Y47: =IF(AC47<>"",IF(D47<>"",D47,($L$8-SUM($Y$25:Y46))*AB47*AC47/SUMPRODUCT($AC$46:$AC47,$AB$46:$AB47)),"") | Z47: =IF(AC47<>"",IF(E47<>"",E47,($L$9-SUM($Z$25:Z40))*AB47*AC47/SUMPRODUCT($AC$46:$AC47,$AB$46:$AB47)),"") | AA47: =IF(AC47<>"",IF($L$12<>"",IF(G47<>"",G47,($L$9/$L$12-SUM($AA$25:AA40))*AB47*AC47/SUMPRODUCT($AC$46:$AC47,$AB$46:$AB47)),""),"")
B48: итого | D48: =SUM(D25:D47) -> 540810 | E48: =SUM(E25:E47) -> 80 | F48: =IF(AND(E48<>"",E48<>0),D48/E48,"") -> 6760.125 | G48: =SUM(G25:G47) -> 50 | H48: =IF(AND(G48<>"",G48<>0),D48/G48,"") -> 10816.2 | I48: =SUM(I25:I47)*0.8 -> 424 | J48: =IF(AND(G48<>"",G48<>0),E48/G48,"") -> 1.6 | K48: =SUM(K25:K47) -> 62408 | L48: =SUM(L25:L47) -> 0 | M48: =SUM(M25:M47) -> 7093 | N48: =SUM(N25:N47) -> 0 | O48: =SUM(O25:O47) -> 29933 | P48: =SUM(P25:P47) -> 12391 | Q48: =SUM(Q25:Q47) -> 0 | R48: =SUM(R25:R47) -> 31953 | S48: =SUM(S25:S47) -> 37218 | T48: =IF(AND(I48<>"",I48<>0),G48/I48,"") -> 0.11792453 | U48: =D48/V48 -> 0.59231937 | V48: =SUM(V25:V47) -> 913037.84 | W48: =SUM(W25:W47) -> 132.32432 | X48: =SUM(X25:X47) -> 77.837838 | Y48: =SUM(Y25:Y47) -> 429482 | Z48: =SUM(Z25:Z47) -> 60 | AA48: =SUM(AA25:AA47) -> 41
D49: =SUMIF(D25:D47,"",V25:V47)+D48 -> 540810

Sheet Вед-ть Рогалевич
A1: =График!B1 -> Апрель, 2026
A2: =График!B3 -> ул. Севастопольская, 62 | D2: =График!B4 -> GL-0004
A3: Сотрудник | D3: Выплачено на карту | E3: Выплачено наличными по платежной ведомости | F3: Оклад | G3: Бонус от личных продаж по категории товара | H3: Бонусная часть от общих продаж | I3: Дополнительные начисления, доплаты | J3: Итого: | K3: Вычеты | L3: Итого к выдаче с учетом авансов и вычетов | M3: Подпись
A4: =График!B28 -> Рогалевич Ирина | F4: =G7 -> 17600 | G4: =G14 -> 26097.65 | H4: =G20 -> 5191.4717 | I4: =L14 -> 15541.83 | J4: =G4+F4+I4+H4 -> 64430.952 | K4: =L20 -> 0 | L4: =J4-K4-D4-E4 -> 64430.952
B7: Оклад: | G7: =G9+G10 -> 17600
B8: Дней | C8: Магазин | D8: Должность | E8: Зачислено часов | F8: Ставка за час, руб | G8: Начислено за день, руб | I8: КВП | J8: % выполнения
B9: =График!AI28 -> 10 | C9: =A2 -> ул. Севастопольская, 62 | D9: УМ | E9: =График!AJ28 -> 88 | F9: 200 | G9: =E9*F9 -> 17600 | I9: Магазин | J9: =Центрум!K8 -> 0.66825607
B14: Бонус от личных продаж по категории товара | G14: =G16+G17 -> 26097.65 | I14: Доп начисления | L14: =J16+J17+J18 -> 15541.83
B15: Категория товара | C15: Магазин | E15: Процент от продажи | F15: Продано на сумму, руб | G15: Начисленный бонус от продаж, руб | I15: Дата | J15: Сумма | K15: Описание
B16: Категория A | C16: =A2 -> ул. Севастопольская, 62 | E16: 0.05 | F16: =Рогалевич!J8-'Вед-ть Рогалевич'!F17 -> 521953 | G16: =F16*E16 -> 26097.65 | I16: 46142 | J16: =Центрум!J8*0.01 -> 12541.83 | K16: Административный %
B17: Категория N (SALE, IS) | C17: =A2 -> ул. Севастопольская, 62 | E17: 0.1 | F17: =Рогалевич!L48+Рогалевич!S48 -> 0 | G17: =F17*E17 -> 0 | I17: 46142 | J17: 3000 | K17: % наличного оборота > 60%
F18: =F16+F17 -> 521953
B20: Бонус от общих продаж | G20: =G22+G23 -> 5191.4717 | I20: Вычеты | L20: =J22+J23+J24 -> 0
B21: Сотрудник | C21: Магазин | D21: Кол-во отработанных личных часов | E21: Кол-во отработанных общих часов | F21: Процент от продажи | G21: Начисленный бонус от продаж, руб | I21: Дата | J21: Сумма | K21: Описание
B22: =A4 -> Рогалевич Ирина | C22: =C16 -> ул. Севастопольская, 62 | D22: =E9 -> 88 | E22: =График!AJ29 -> 407 | F22: 0.02 | G22: =(Центрум!J8-Центрум!L56-Центрум!S56)*F22*D22/E22 -> 5191.4717

Sheet Вед-ть Маркова
A1: =График!B1 -> Апрель, 2026
A2: =График!B3 -> ул. Севастопольская, 62 | D2: =График!B4 -> GL-0004
A3: Сотрудник | D3: Выплачено на карту | E3: Выплачено наличными по платежной ведомости | F3: Оклад | G3: Бонус от личных продаж по категории товара | H3: Бонусная часть от общих продаж | I3: Дополнительные начисления, доплаты | J3: Итого: | K3: Вычеты | L3: Итого к выдаче с учетом авансов и вычетов | M3: Подпись
A4: =График!B27 -> Маркова Диана | D4: 17555.69 | F4: =G7 -> 12100 | G4: =G14 -> 10392.859 | H4: =G20 -> 3155.9347 | I4: =L14 -> 4729.07 | J4: =G4+F4+I4+H4 -> 30377.863 | K4: =L20 -> 9241 | L4: =J4-K4-D4-E4 -> 3581.1732
B7: Оклад: | G7: =G9+G10 -> 12100
B8: Дней | C8: Магазин | D8: Должность | E8: Зачислено часов | F8: Ставка за час, руб | G8: Начислено за день, руб | I8: КВП | J8: % выполнения
B9: =График!AI27 -> 11 | C9: =A2 -> ул. Севастопольская, 62 | D9: =График!C27 -> АМ | E9: =График!AJ27 -> 121 | F9: 100 | G9: =E9*F9 -> 12100 | I9: Магазин | J9: =Центрум!K8 -> 0.66825607
I10: Смены | J10: =Маркова!N8 -> 0.34306653
B14: Бонус от личных продаж по категории товара | G14: =G16+G17 -> 10392.859 | I14: Доп начисления | L14: =J16+J17+J18 -> 4729.07
B15: Категория товара | C15: Магазин | E15: Процент от продажи | F15: Продано на сумму, руб | G15: Начисленный бонус от продаж, руб | I15: Дата | J15: Сумма | K15: Описание
B16: Категория A | C16: =A2 -> ул. Севастопольская, 62 | E16: 0.05 | F16: =Маркова!M8-'Вед-ть Маркова'!F17 -> 174982.83 | G16: =F16*E16 -> 8749.1415 | I16: 46132 | J16: =F18*0.01 -> 1914.2 | K16: Административный % (смены)
B17: Категория N (SALE, IS) | C17: =A2 -> ул. Севастопольская, 62 | E17: 0.1 | F17: =Маркова!L48+Маркова!S48 -> 16437.17 | G17: =F17*E17 -> 1643.717 | I17: 46132 | J17: 2814.87 | K17: Компенсация отпуска при увольнении
F18: =F16+F17 -> 191420
B20: Бонус от общих продаж | G20: =G22+G23 -> 3155.9347 | I20: Вычеты | L20: =J22+J23+J24 -> 9241
B21: Сотрудник | C21: Магазин | D21: Кол-во отработанных личных часов | E21: Кол-во отработанных общих часов | F21: Процент от продажи | G21: Начисленный бонус от продаж, руб | I21: Дата | J21: Сумма | K21: Описание
B22: =A4 -> Маркова Диана | C22: =C16 -> ул. Севастопольская, 62 | D22: =E9 -> 121 | E22: =График!AJ29 -> 407 | F22: 0.02 | G22: =(Центрум!J8-Центрум!L56-Центрум!S56-669757)*F22*D22/E22 -> 3155.9347 | I22: 46132 | J22: 2729 | K22: НДФЛ
I23: 46133 | J23: =890*0.8 -> 712 | K23: Вычет согласно инвентаризационной ведомости
I24: 46134 | J24: =2500+3300 -> 5800 | K24: Вычет за униформу, стажировку (33 часа)

Sheet Вед-ть Бешлиева
A1: =График!B1 -> Апрель, 2026
A2: =График!B3 -> ул. Севастопольская, 62 | D2: =График!B4 -> GL-0004
A3: Сотрудник | D3: Выплачено на карту | E3: Выплачено наличными по платежной ведомости | F3: Оклад | G3: Бонус от личных продаж по категории товара | H3: Бонусная часть от общих продаж | I3: Дополнительные начисления, доплаты | J3: Итого: | K3: Вычеты | L3: Итого к выдаче с учетом авансов и вычетов | M3: Подпись
A4: =График!B26 -> Бешлиева Аджере | D4: =40000-J22 -> 34800 | F4: =G7 -> 19800 | G4: =G14 -> 28901.4 | H4: =G20 -> 11680.811 | I4: =L14 -> 5965.32 | J4: =G4+F4+I4+H4 -> 66347.531 | K4: =L20 -> 5200 | L4: =J4-K4-D4-E4 -> 26347.531
B7: Оклад: | G7: =G9+G10 -> 19800
B8: Дней | C8: Магазин | D8: Должность | E8: Зачислено часов | F8: Ставка за час, руб | G8: Начислено за день, руб | I8: КВП | J8: % выполнения
B9: =График!AI26 -> 18 | C9: =A2 -> ул. Севастопольская, 62 | D9: =График!C26 -> АМ | E9: =График!AJ26 -> 198 | F9: 100 | G9: =E9*F9 -> 19800 | I9: Магазин | J9: =Центрум!K8 -> 0.66825607
I10: Смены | J10: =Бешлиева!N8 -> 0.59231937
B14: Бонус от личных продаж по категории товара | G14: =G16+G17 -> 28901.4 | I14: Доп начисления | L14: =J16+J17+J18 -> 5965.32
B15: Категория товара | C15: Магазин | E15: Процент от продажи | F15: Продано на сумму, руб | G15: Начисленный бонус от продаж, руб | I15: Дата | J15: Сумма | K15: Описание
B16: Категория A | C16: =A2 -> ул. Севастопольская, 62 | E16: 0.05 | F16: =Бешлиева!M8-'Вед-ть Бешлиева'!F17 -> 503592 | G16: =F16*E16 -> 25179.6 | I16: 46142 | J16: =(F18+55722)*0.01 -> 5965.32 | K16: Административный % (смены)
B17: Категория N (SALE, IS) | C17: =A2 -> ул. Севастопольская, 62 | E17: 0.1 | F17: =Бешлиева!L48+Бешлиева!S48 -> 37218 | G17: =F17*E17 -> 3721.8 | I17: 46142 | J17: 0 | K17: % наличного оборота < 60%
F18: =F16+F17 -> 540810
B20: Бонус от общих продаж | G20: =G22+G23 -> 11680.811 | I20: Вычеты | L20: =J22+J23+J24 -> 5200
B21: Сотрудник | C21: Магазин | D21: Кол-во отработанных личных часов | E21: Кол-во отработанных общих часов | F21: Процент от продажи | G21: Начисленный бонус от продаж, руб | I21: Дата | J21: Сумма | K21: Описание
B22: =A4 -> Бешлиева Аджере | C22: =C16 -> ул. Севастопольская, 62 | D22: =E9 -> 198 | E22: =График!AJ29 -> 407 | F22: 0.02 | G22: =(Центрум!J8-Центрум!L56-Центрум!S56)*F22*D22/E22 -> 11680.811 | I22: 46142 | J22: 5200 | K22: НДФЛ

Sheet График
B1: Апрель, 2026
B2: г. Симферополь
B3: ул. Севастопольская, 62
B4: GL-0004
B5: 10.00-21.00
B6: ФОТ | C6: Кол-во дней в месяц | AK6: 30
C7: Премия Директора, грн.
D8: ср | E8: чт | F8: пт | G8: сб | H8: вс | I8: пн | J8: вт | K8: ср | L8: чт | M8: пт | N8: сб | O8: вс | P8: пн | Q8: вт | R8: ср | S8: чт | T8: пт | U8: сб | V8: вс | W8: пн | X8: вт | Y8: ср | Z8: чт | AA8: пт | AB8: сб | AC8: вс | AD8: пн | AE8: вт | AF8: ср | AG8: чт | AJ8: Часы | AK8: Выходные | AL8: Отпуск | AM8: Больничный (официальный) | AN8: Дни стажировки
A10: № | B10: ФИО | C10: Должность | D10: 1 | E10: 2 | F10: 3 | G10: 4 | H10: 5 | I10: 6 | J10: 7 | K10: 8 | L10: 9 | M10: 10 | N10: 11 | O10: 12 | P10: 13 | Q10: 14 | R10: 15 | S10: 16 | T10: 17 | U10: 18 | V10: 19 | W10: 20 | X10: 21 | Y10: 22 | Z10: 23 | AA10: 24 | AB10: 25 | AC10: 26 | AD10: 27 | AE10: 28 | AF10: 29 | AG10: 30 | AI10: Дни
A11: 18 | AI11: =COUNTIF(D11:AH11,">0") -> 0 | AJ11: =SUMIF(D11:AH11,">0") -> 0 | AK11: 0 | AL11: 0 | AM11: 0 | AN11: 0
A12: 17 | AI12: =COUNTIF(D12:AH12,">0") -> 0 | AJ12: =SUMIF(D12:AH12,">0") -> 0 | AK12: =COUNTIF(D12:AH12,"В") -> 0 | AL12: 0 | AM12: 0 | AN12: 0
A13: 16 | AI13: =COUNTIF(D13:AH13,">0") -> 0 | AJ13: =SUMIF(D13:AH13,">0") -> 0 | AK13: =COUNTIF(D13:AH13,"В") -> 0 | AL13: 0 | AM13: 0 | AN13: 0
A14: 15 | AI14: =COUNTIF(D14:AH14,">0") -> 0 | AJ14: =SUMIF(D14:AH14,">0") -> 0 | AK14: =COUNTIF(D14:AH14,"В") -> 0 | AL14: 0 | AM14: 0 | AN14: 0
A15: 14 | AI15: =COUNTIF(D15:AH15,">0") -> 0 | AJ15: =SUMIF(D15:AH15,">0") -> 0 | AK15: =COUNTIF(D15:AH15,"В") -> 0 | AL15: 0 | AM15: 0 | AN15: 0
A16: 13 | AI16: =COUNTIF(D16:AH16,">0") -> 0 | AJ16: =SUMIF(D16:AH16,">0") -> 0 | AK16: =COUNTIF(D16:AH16,"В") -> 0 | AL16: 0 | AM16: 0 | AN16: 0
A17: 12 | AI17: =COUNTIF(D17:AH17,">0") -> 0 | AJ17: =SUMIF(D17:AH17,">0") -> 0 | AK17: =COUNTIF(D17:AH17,"В") -> 0 | AL17: 0 | AM17: 0 | AN17: 0
A18: 11 | AI18: =COUNTIF(D18:AH18,">0") -> 0 | AJ18: =SUMIF(D18:AH18,">0") -> 0 | AK18: =COUNTIF(D18:AH18,"В") -> 0 | AL18: 0 | AM18: 0 | AN18: 0
A19: 10 | AI19: =COUNTIF(D19:AH19,">0") -> 0 | AJ19: =SUMIF(D19:AH19,">0") -> 0 | AK19: =COUNTIF(D19:AH19,"В") -> 0 | AL19: 0 | AM19: 0 | AN19: 0
A20: 9 | AI20: =COUNTIF(D20:AH20,">0") -> 0 | AJ20: =SUMIF(D20:AH20,">0") -> 0 | AK20: =COUNTIF(D20:AH20,"В") -> 0 | AL20: 0 | AM20: 0 | AN20: 0
A21: 8 | AI21: =COUNTIF(D21:AH21,">0") -> 0 | AJ21: =SUMIF(D21:AH21,">0") -> 0 | AK21: =COUNTIF(D21:AH21,"В") -> 0 | AL21: 0 | AM21: 0 | AN21: 0
A22: 7 | AI22: =COUNTIF(D22:AH22,">0") -> 0 | AJ22: =SUMIF(D22:AH22,">0") -> 0 | AK22: =COUNTIF(D22:AH22,"В") -> 0 | AL22: 0 | AM22: 0 | AN22: 0
A23: 6 | AI23: =COUNTIF(D23:AH23,">0") -> 0 | AJ23: =SUMIF(D23:AH23,">0") -> 0 | AK23: =COUNTIF(D23:AH23,"В") -> 0 | AL23: 0 | AM23: 0 | AN23: 0
... A25: 4 | AI25: =COUNTIF(D25:AH25,">0") -> 0 | AJ25: =SUMIF(D25:AH25,">0") -> 0 | AK25: =COUNTIF(D25:AH25,"В") -> 0 | AL25: 0 | AM25: 0 | AN25: 0
A26: 3 | B26: Бешлиева Аджере | C26: АМ | D26: в | E26: 11 | F26: 11 | G26: в | H26: в | I26: в | J26: 11 | K26: 11 | L26: в | M26: 11 | N26: 11 | O26: в | P26: 11 | Q26: в | R26: 11 | S26: в | T26: в | U26: 11 | V26: 11 | W26: в | X26: 11 | Y26: 11 | Z26: 11 | AA26: 11 | AB26: 11 | AC26: в | AD26: 11 | AE26: 11 | AF26: 11 | AG26: в | AI26: =COUNTIF(D26:AH26,">0") -> 18 | AJ26: =SUMIF(D26:AH26,">0") -> 198 | AK26: =COUNTIF(D26:AH26,"В") -> 12 | AL26: 0 | AM26: 0 | AN26: 0
A27: 2 | B27: Маркова Диана | C27: АМ | D27: 11 | E27: в | F27: в | G27: 11 | H27: 11 | I27: 11 | J27: в | K27: в | L27: 11 | M27: в | N27: в | O27: 11 | P27: в | Q27: 11 | R27: в | S27: 11 | T27: 11 | U27: в | V27: в | W27: 11 | X27: у | Y27: у | Z27: у | AA27: у | AB27: у | AC27: 11 | AD27: у | AE27: у | AF27: у | AG27: у | AI27: =COUNTIF(D27:AH27,">0") -> 11 | AJ27: =SUMIF(D27:AH27,">0") -> 121 | AK27: =COUNTIF(D27:AH27,"В") -> 10 | AL27: 0 | AM27: 0 | AN27: 0
A28: 1 | B28: Рогалевич Ирина | C28: УМ | I28: 9 | J28: 9 | K28: 8.5 | L28: 8.5 | M28: 9 | W28: 8 | X28: 10 | Y28: 7 | Z28: 8 | AG28: 11 | AI28: =COUNTIF(D28:AH28,">0") -> 10 | AJ28: =SUMIF(D28:AH28,">0") -> 88 | AK28: =COUNTIF(D28:AH28,"В") -> 0 | AL28: =COUNTIF(E28:AI28,"о") -> 0 | AM28: =COUNTIF(F28:AJ28,"б") -> 0 | AN28: 0
B29: Итого магазин | D29: =COUNTIF(D11:D28,">0") -> 1 | E29: =COUNTIF(E11:E28,">0") -> 1 | F29: =COUNTIF(F11:F28,">0") -> 1 | G29: =COUNTIF(G11:G28,">0") -> 1 | H29: =COUNTIF(H11:H28,">0") -> 1 | I29: =COUNTIF(I11:I28,">0") -> 2 | J29: =COUNTIF(J11:J28,">0") -> 2 | K29: =COUNTIF(K11:K28,">0") -> 2 | ... AH29: =COUNTIF(AH11:AH28,">0") -> 0 | AI29: =SUM(AI11:AI28) -> 39 | AJ29: =SUM(AJ11:AJ28) -> 407 | AK29: =SUM(AK11:AK28) -> 22 | AL29: =SUM(AL11:AL28) -> 0 | AM29: =SUM(AM11:AM28) -> 0 | AN29: =SUM(AN11:AN28) -> 0
T32: .
Q54: .
