Workbook
Name маг: NA()

Sheet Центрум
B1: =TODAY()-1 -> 46170
B2: (отчетная дата) | J2: ЕЖЕДНЕВНЫЙ ОТЧЕТ О ПРОДАЖАХ
C3: Осталось до выполнения плана!!! | I3: ТРК Центрум
C4: =I8-D56 -> 496100.02 | E4: =IF(I8<>0,C4/I8,0) -> 0.25857128
F6: Целевые показатели
F7: Показатель | I7: План | J7: Факт | K7: % выполнения | L7: Прогноз выполнения | M7: % выполнения по прогнозу | N7: Отклонение | O7: Факт аналогичного месяца прошлого года | P7: Отклонение LFL
F8: Выручка | I8: =I13*I10 -> 1918620 | J8: =D56 -> 1422520 | K8: =IF(AND(I8<>"",I8<>0,J8<>""),J8/I8,"") -> 0.74142872 | L8: =IF(SUMIF($D$25:$D$55,">=0",$U$25:$U$55)<>0,I8*D56/SUMIF($D$25:$D$55,">=0",$U$25:$U$55),0) -> 1422520 | M8: =L8/I8 -> 0.74142872 | N8: =IF(AND(J8<>0,J8<>"",I8<>0,I8<>""),L8-I8,"") -> -496100.02 | P8: =IF(AND(O8<>"",O8<>0,L8<>"",L8<>0),-O8+L8,"") | Q8: =IF(AND(O8<>"",O8<>0,N8<>0,N8<>""),O8/N8,"")
F9: Кол-во изделий | I9: =I8/I11 -> 290.7 | J9: =E56 -> 202 | K9: =IF(AND(I9<>"",I9<>0,J9<>""),J9/I9,"") -> 0.69487444 | L9: =IF(SUMIF($E$25:$E$55,">=0",$V$25:$V$55)<>0,I9*E56/SUMIF($E$25:$E$55,">=0",$V$25:$V$55),0) -> 202 | M9: =IF(AND(I9<>"",I9<>0,L9<>"",L9<>0),L9/I9,"") -> 0.69487444 | N9: =IF(AND(J9<>0,J9<>"",I9<>0,I9<>""),L9-I9,"") -> -88.7 | P9: =IF(AND(O9<>"",O9<>0,L9<>"",L9<>0),-O9+L9,"") | Q9: =IF(AND(O9<>"",O9<>0,N9<>0,N9<>""),O9/N9,"")
F10: Средний чек | I10: =I11*I12 -> 11220 | J10: =H56 -> 12932 | K10: =IF(AND(I10<>"",I10<>0,J10<>""),J10/I10,"") -> 1.1525847 | L10: =J10 -> 12932 | M10: =IF(AND(I10<>"",I10<>0,L10<>"",L10<>0),L10/I10,"") -> 1.1525847 | N10: =IF(AND(J10<>0,J10<>"",I10<>0,I10<>""),L10-I10,"") -> 1711.9998 | P10: =IF(AND(O10<>"",O10<>0,L10<>"",L10<>0),-O10+L10,"") | Q10: =IF(AND(O10<>"",O10<>0,N10<>0,N10<>""),O10/N10,"")
F11: Средняя стоимость изделия | I11: 6600 | J11: =F56 -> 7042.1781 | K11: =IF(AND(I11<>"",I11<>0,J11<>""),J11/I11,"") -> 1.0669967 | L11: =IF(L9>0,L8/L9,"") -> 7042.1781 | M11: =IF(AND(I11<>"",I11<>0,L11<>"",L11<>0),L11/I11,"") -> 1.0669967 | N11: =IF(AND(J11<>0,J11<>"",I11<>0,I11<>""),L11-I11,"") -> 442.17812 | P11: =IF(AND(O11<>"",O11<>0,L11<>"",L11<>0),-O11+L11,"") | Q11: =IF(AND(O11<>"",O11<>0,N11<>0,N11<>""),O11/N11,"")
F12: Длина чека | I12: 1.7 | J12: =J56 -> 1.8363636 | K12: =IF(AND(I12<>"",I12<>0,J12<>""),J12/I12,"") -> 1.0802139 | L12: =J12 -> 1.8363636 | M12: =IF(AND(I12<>"",I12<>0,L12<>"",L12<>0),L12/I12,"") -> 1.0802139 | N12: =IF(AND(J12<>0,J12<>"",I12<>0,I12<>""),L12-I12,"") -> 0.13636364 | P12: =IF(AND(O12<>"",O12<>0,L12<>"",L12<>0),-O12+L12,"") | Q12: =IF(AND(O12<>"",O12<>0,N12<>0,N12<>""),O12/N12,"")
F13: Кол-во чеков | I13: =I17*I20 -> 171 | J13: =G56 -> 110 | K13: =IF(AND(I13<>"",I13<>0,J13<>""),J13/I13,"") -> 0.64327485 | L13: =IF(SUMIF($G$25:$G$55,">=0",$W$25:$W$55)<>0,I13*G56/SUMIF($G$25:$G$55,">=0",$W$25:$W$55),"") -> 110 | M13: =IF(AND(I13<>"",I13<>0,L13<>"",L13<>0),L13/I13,"") -> 0.64327485 | N13: =IF(AND(J13<>0,J13<>"",I13<>0,I13<>""),L13-I13,"") -> -61 | P13: =IF(AND(O13<>"",O13<>0,L13<>"",L13<>0),-O13+L13,"") | Q13: =IF(AND(O13<>"",O13<>0,N13<>0,N13<>""),O13/N13,"")
F14: Кол-во смен | I14: 31 | J14: 31 | K14: =IF(AND(I14<>"",I14<>0,J14<>""),J14/I14,"") -> 1 | L14: =IF(SUMIF($D$25:$D$55,">=0",$U$25:$U$55),I56*I8/SUMIF($D$25:$D$55,">=0",$U$25:$U$55),"") -> 1421.6 | N14: =IF(AND(J14<>0,J14<>"",I14<>0,I14<>""),L14-I14,"") -> 1390.6 | P14: =IF(AND(O14<>"",O14<>0,L14<>"",L14<>0),-O14+L14,"") | Q14: =IF(AND(O14<>"",O14<>0,N14<>0,N14<>""),O14/N14,"")
F15: Средние продажи в смену | I15: =I8/I14 -> 61890.968 | J15: =J8/J14 -> 45887.741 | K15: =IF(AND(I15<>"",I15<>0,J15<>""),J15/I15,"") -> 0.74142872 | L15: =J15 -> 45887.741 | M15: =IF(AND(I15<>"",I15<>0,L15<>"",L15<>0),L15/I15,"") -> 0.74142872 | N15: =IF(AND(J15<>0,J15<>"",I15<>0,I15<>""),L15-I15,"") -> -16003.226 | P15: =IF(AND(O15<>"",O15<>0,L15<>"",L15<>0),-O15+L15,"") | Q15: =IF(AND(O15<>"",O15<>0,N15<>0,N15<>""),O15/N15,"")
F16: Отставание/Перевыполнение | J16: =J8-I15*J14 -> -496100.02 | K16: =IF(AND(I16<>"",I16<>0,J16<>""),J16/I16,"") | L16: =J16 -> -496100.02 | M16: =IF(AND(I16<>"",I16<>0,L16<>"",L16<>0),L16/I16,"") | N16: =IF(AND(J16<>0,J16<>"",I16<>0,I16<>""),L16-I16,"") | P16: =IF(AND(O16<>"",O16<>0,L16<>"",L16<>0),-O16+L16,"") | Q16: =IF(AND(O16<>"",O16<>0,N16<>0,N16<>""),O16/N16,"") | W16: Подарочные сертификаты
F17: Трафик | I17: 1900 | J17: =I56 -> 1421.6 | K17: =IF(AND(I17<>"",I17<>0,J17<>""),J17/I17,"") -> 0.74821053 | L17: =J17/J14*I14 -> 1421.6 | M17: =IF(AND(I17<>"",I17<>0,L17<>"",L17<>0),L17/I17,"") -> 0.74821053 | N17: =IF(AND(J17<>0,J17<>"",I17<>0,I17<>""),L17-I17,"") -> -478.4 | P17: =IF(AND(O17<>"",O17<>0,L17<>"",L17<>0),-O17+L17,"") | Q17: =IF(AND(O17<>"",O17<>0,N17<>0,N17<>""),O17/N17,"")
K18: =IF(AND(I18<>"",I18<>0,J18<>""),J18/I18,"") | L18: =J18 -> 0 | M18: =IF(AND(I18<>"",I18<>0,L18<>"",L18<>0),L18/I18,"") | N18: =IF(AND(J18<>0,J18<>"",I18<>0,I18<>""),L18-I18,"") | P18: =IF(AND(O18<>"",O18<>0,L18<>"",L18<>0),-O18+L18,"") | Q18: =IF(AND(O18<>"",O18<>0,N18<>0,N18<>""),O18/N18,"")
K19: =IF(AND(I19<>"",I19<>0,J19<>""),J19/I19,"") | L19: =J19 -> 0 | M19: =IF(AND(I19<>"",I19<>0,L19<>"",L19<>0),L19/I19,"") | N19: =IF(AND(J19<>0,J19<>"",I19<>0,I19<>""),L19-I19,"") | O19: 0 | P19: =IF(AND(O19<>"",O19<>0,L19<>"",L19<>0),-O19+L19,"") | Q19: =IF(AND(O19<>"",O19<>0,N19<>0,N19<>""),O19/N19,"") | W19: =W18/I16 -> #DIV/0!
F20: Конверсия | I20: 0.09 | J20: =S56 -> 0.077377603 | K20: =J20/I20 -> 0.85975114 | L20: =J20/I20 -> 0.85975114 | M20: =J20/I20 -> 0.85975114 | N20: =IF(AND(J20<>0,J20<>"",I20<>0,I20<>""),L20-I20,"") -> 0.76975114 | P20: =IF(AND(O20<>"",O20<>0,L20<>"",L20<>0),-O20+L20,"") | Q20: =IF(AND(O20<>"",O20<>0,N20<>0,N20<>""),O20/N20,"")
A22: Факт продаж за месяц | U22: Раcпределение плана по дням
A23: Сотрудник | B23: Дата | C23: День недели | D23: Выручка (руб) | E23: Кол-во единиц (шт.) | F23: Средняя стоимость изделия (руб.) | G23: Количество чеков (шт.) | H23: Средняя сумма чека (руб.) | I23: Трафик | J23: Длина чека (шт.) | K23: UNOde50 | L23: IS | M23: Agafi | N23: Kalliope | O23: Raganella | P23: CC/MP | Q23: Eva Rites | R23: Antura | S23: Конверсия (%) | T23: % выполнения дневного плана | U23: выручка, план | V23: кол-во ед, план | W23: Кол-во чеков, план | X23: выручка, скорректир.план | Y23: кол-во ед, скорр. план | Z23: кол-во чеков, скорр. план | AA23: Коэфф. Дня Недели | AB23: Специфика месяца
B24: 1 | C24: 2 | D24: 3 | E24: 4 | F24: 5 | G24: 6 | H24: 7 | I24: 8 | J24: 9 | K24: 10 | L24: 11 | M24: 12 | N24: 13 | O24: 14 | P24: 15 | Q24: 16 | R24: 17 | S24: 13 | U24: 1 | V24: 2 | W24: 3 | X24: 4 | Y24: 5 | Z24: 6 | AA24: 10 | AB24: 11
B25: 46023 | C25: чт | D25: 0 | E25: 0 | F25: =IF(AND(E25<>"",E25<>0),D25/E25,"") | G25: 0 | H25: =IF(AND(G25<>"",G25<>0),D25/G25,"") | I25: 0 | J25: =IF(AND(G25<>"",G25<>0),E25/G25,"") | S25: =IF(AND(I25<>"",I25<>0),G25/I25,"") | T25: =D25/U25 -> 0 | U25: =$I$8*AA25*AB25/SUMPRODUCT($AB$25:$AB$55,$AA$25:$AA$55) -> 64505.635 | V25: =$I$9*AA25*AB25/SUMPRODUCT($AB$25:$AB$55,$AA$25:$AA$55) -> 9.7735811 | W25: =IF($I$12="","",V25/$I$12) -> 5.7491654 | X25: =IF(D25<>"",D25,U25) -> 0 | Y25: =IF(E25<>"",E25,V25) -> 0 | Z25: =IF(G25<>"",G25,W25) -> 0 | AA25: 0.9414554 | AB25: 0.9414554
A26: Свидовская, Корж, Козлова | B26: 46024 | C26: пт | D26: 52276 | E26: 7 | F26: =IF(AND(E26<>"",E26<>0),D26/E26,"") -> 7468 | G26: 3 | H26: =IF(AND(G26<>"",G26<>0),D26/G26,"") -> 17425.333 | I26: 77 | J26: =IF(AND(G26<>"",G26<>0),E26/G26,"") -> 2.3333333 | Q26: 15180 | S26: =IF(AND(I26<>"",I26<>0),G26/I26,"") -> 0.038961039 | T26: =D26/U26 -> 0.98696541 | U26: =$I$8*AA26*AB26/SUMPRODUCT($AB$25:$AB$55,$AA$25:$AA$55) -> 52966.395 | V26: =$I$9*AA26*AB26/SUMPRODUCT($AB$25:$AB$55,$AA$25:$AA$55) -> 8.0252114 | W26: =IF($I$12="","",V26/$I$12) -> 4.7207126 | X26: =IF(AB26<>"",IF(D26<>"",D26,($I$8-SUM($X$25:X25))*AA26*AB26/SUMPRODUCT($AB26:$AB$55,$AA26:$AA$55)),"") -> 52276 | Y26: =IF(AB26<>"",IF(E26<>"",E26,($I$9-SUM($Y$25:Y25))*AA26*AB26/SUMPRODUCT($AB26:$AB$55,$AA26:$AA$55)),"") -> 7 | Z26: =IF(AB26<>"",IF($I$12<>"",IF(G26<>"",G26,($I$9/$I$12-SUM($Z$25:Z25))*AA26*AB26/SUMPRODUCT($AB26:$AB$55,$AA26:$AA$55)),""),"") -> 3 | AA26: 0.85310234 | AB26: 0.85310234
A27: Свидовская, Корж, Козлова | B27: 46025 | C27: сб | D27: 21059 | E27: 4 | F27: =IF(AND(E27<>"",E27<>0),D27/E27,"") -> 5264.75 | G27: 3 | H27: =IF(AND(G27<>"",G27<>0),D27/G27,"") -> 7019.6667 | I27: 76 | J27: =IF(AND(G27<>"",G27<>0),E27/G27,"") -> 1.3333333 | Q27: 8693 | S27: =IF(AND(I27<>"",I27<>0),G27/I27,"") -> 0.039473684 | T27: =D27/U27 -> 0.39759172 | U27: =$I$8*AA27*AB27/SUMPRODUCT($AB$25:$AB$55,$AA$25:$AA$55) -> 52966.395 | V27: =$I$9*AA27*AB27/SUMPRODUCT($AB$25:$AB$55,$AA$25:$AA$55) -> 8.0252114 | W27: =IF($I$12="","",V27/$I$12) -> 4.7207126 | X27: =IF(AB27<>"",IF(D27<>"",D27,($I$8-SUM($X$25:X26))*AA27*AB27/SUMPRODUCT($AB27:$AB$55,$AA27:$AA$55)),"") -> 21059 | Y27: =IF(AB27<>"",IF(E27<>"",E27,($I$9-SUM($Y$25:Y26))*AA27*AB27/SUMPRODUCT($AB27:$AB$55,$AA27:$AA$55)),"") -> 4 | Z27: =IF(AB27<>"",IF($I$12<>"",IF(G27<>"",G27,($I$9/$I$12-SUM($Z$25:Z26))*AA27*AB27/SUMPRODUCT($AB27:$AB$55,$AA27:$AA$55)),""),"") -> 3 | AA27: 0.85310234 | AB27: 0.85310234
A28: Свидовская, Корж, Козлова | B28: 46026 | C28: вс | D28: 73715 | E28: 10 | F28: =IF(AND(E28<>"",E28<>0),D28/E28,"") -> 7371.5 | G28: 2 | H28: =IF(AND(G28<>"",G28<>0),D28/G28,"") -> 36857.5 | I28: 90 | J28: =IF(AND(G28<>"",G28<>0),E28/G28,"") -> 5 | S28: =IF(AND(I28<>"",I28<>0),G28/I28,"") -> 0.022222222 | T28: =D28/U28 -> 1.3917315 | U28: =$I$8*AA28*AB28/SUMPRODUCT($AB$25:$AB$55,$AA$25:$AA$55) -> 52966.395 | V28: =$I$9*AA28*AB28/SUMPRODUCT($AB$25:$AB$55,$AA$25:$AA$55) -> 8.0252114 | W28: =IF($I$12="","",V28/$I$12) -> 4.7207126 | X28: =IF(AB28<>"",IF(D28<>"",D28,($I$8-SUM($X$25:X27))*AA28*AB28/SUMPRODUCT($AB28:$AB$55,$AA28:$AA$55)),"") -> 73715 | Y28: =IF(AB28<>"",IF(E28<>"",E28,($I$9-SUM($Y$25:Y27))*AA28*AB28/SUMPRODUCT($AB28:$AB$55,$AA28:$AA$55)),"") -> 10 | Z28: =IF(AB28<>"",IF($I$12<>"",IF(G28<>"",G28,($I$9/$I$12-SUM($Z$25:Z27))*AA28*AB28/SUMPRODUCT($AB28:$AB$55,$AA28:$AA$55)),""),"") -> 2 | AA28: 0.85310234 | AB28: 0.85310234
A29: Козлова, Корж | B29: 46027 | C29: пн | D29: 28155 | E29: 4 | F29: =IF(AND(E29<>"",E29<>0),D29/E29,"") -> 7038.75 | G29: 4 | H29: =IF(AND(G29<>"",G29<>0),D29/G29,"") -> 7038.75 | I29: 100 | J29: =IF(AND(G29<>"",G29<>0),E29/G29,"") -> 1 | M29: 7093 | S29: =IF(AND(I29<>"",I29<>0),G29/I29,"") -> 0.04 | T29: =D29/U29 -> 0.53545075 | U29: =$I$8*AA29*AB29/SUMPRODUCT($AB$25:$AB$55,$AA$25:$AA$55) -> 52581.867 | V29: =$I$9*AA29*AB29/SUMPRODUCT($AB$25:$AB$55,$AA$25:$AA$55) -> 7.9669496 | W29: =IF($I$12="","",V29/$I$12) -> 4.6864409 | X29: =IF(AB29<>"",IF(D29<>"",D29,($I$8-SUM($X$25:X28))*AA29*AB29/SUMPRODUCT($AB29:$AB$55,$AA29:$AA$55)),"") -> 28155 | Y29: =IF(AB29<>"",IF(E29<>"",E29,($I$9-SUM($Y$25:Y28))*AA29*AB29/SUMPRODUCT($AB29:$AB$55,$AA29:$AA$55)),"") -> 4 | Z29: =IF(AB29<>"",IF($I$12<>"",IF(G29<>"",G29,($I$9/$I$12-SUM($Z$25:Z28))*AA29*AB29/SUMPRODUCT($AB29:$AB$55,$AA29:$AA$55)),""),"") -> 4 | AA29: 0.85 | AB29: 0.85
A30: Козлова, Стекольщикова | B30: 46028 | C30: вт | D30: 113842.98 | E30: ='Козлова В. Э.'!E29+'Стекольщикова А. А.'!E25 -> 19 | F30: =IF(AND(E30<>"",E30<>0),D30/E30,"") -> 5991.7358 | G30: 7 | H30: =IF(AND(G30<>"",G30<>0),D30/G30,"") -> 16263.283 | I30: 73 | J30: =IF(AND(G30<>"",G30<>0),E30/G30,"") -> 2.7142857 | M30: 14590 | Q30: 9390 | S30: =IF(AND(I30<>"",I30<>0),G30/I30,"") -> 0.095890411 | T30: =D30/U30 -> 1.564257 | U30: =$I$8*AA30*AB30/SUMPRODUCT($AB$25:$AB$55,$AA$25:$AA$55) -> 72777.671 | V30: =$I$9*AA30*AB30/SUMPRODUCT($AB$25:$AB$55,$AA$25:$AA$55) -> 11.02692 | W30: =IF($I$12="","",V30/$I$12) -> 6.4864234 | X30: =IF(AB30<>"",IF(D30<>"",D30,($I$8-SUM($X$25:X29))*AA30*AB30/SUMPRODUCT($AB30:$AB$55,$AA30:$AA$55)),"") -> 113842.98 | Y30: =IF(AB30<>"",IF(E30<>"",E30,($I$9-SUM($Y$25:Y29))*AA30*AB30/SUMPRODUCT($AB30:$AB$55,$AA30:$AA$55)),"") -> 19 | Z30: =IF(AB30<>"",IF($I$12<>"",IF(G30<>"",G30,($I$9/$I$12-SUM($Z$25:Z29))*AA30*AB30/SUMPRODUCT($AB30:$AB$55,$AA30:$AA$55)),""),"") -> 7 | AA30: 1 | AB30: 1
A31: Стекольщикова, Корж, Свидовская | B31: 46029 | C31: ср | D31: 12278 | E31: 3 | F31: =IF(AND(E31<>"",E31<>0),D31/E31,"") -> 4092.6667 | G31: 3 | H31: =IF(AND(G31<>"",G31<>0),D31/G31,"") -> 4092.6667 | I31: 51 | J31: =IF(AND(G31<>"",G31<>0),E31/G31,"") -> 1 | S31: =IF(AND(I31<>"",I31<>0),G31/I31,"") -> 0.058823529 | T31: =D31/U31 -> 0.16870559 | U31: =$I$8*AA31*AB31/SUMPRODUCT($AB$25:$AB$55,$AA$25:$AA$55) -> 72777.671 | V31: =$I$9*AA31*AB31/SUMPRODUCT($AB$25:$AB$55,$AA$25:$AA$55) -> 11.02692 | W31: =IF($I$12="","",V31/$I$12) -> 6.4864234 | X31: =IF(AB31<>"",IF(D31<>"",D31,($I$8-SUM($X$25:X30))*AA31*AB31/SUMPRODUCT($AB31:$AB$55,$AA31:$AA$55)),"") -> 12278 | Y31: =IF(AB31<>"",IF(E31<>"",E31,($I$9-SUM($Y$25:Y30))*AA31*AB31/SUMPRODUCT($AB31:$AB$55,$AA31:$AA$55)),"") -> 3 | Z31: =IF(AB31<>"",IF($I$12<>"",IF(G31<>"",G31,($I$9/$I$12-SUM($Z$25:Z30))*AA31*AB31/SUMPRODUCT($AB31:$AB$55,$AA31:$AA$55)),""),"") -> 3 | AA31: 1 | AB31: 1
A32: Стекольщикова, Корж, Свидовская | B32: 46030 | C32: чт | D32: 16971 | E32: 4 | F32: =IF(AND(E32<>"",E32<>0),D32/E32,"") -> 4242.75 | G32: 3 | H32: =IF(AND(G32<>"",G32<>0),D32/G32,"") -> 5657 | I32: 65 | J32: =IF(AND(G32<>"",G32<>0),E32/G32,"") -> 1.3333333 | S32: =IF(AND(I32<>"",I32<>0),G32/I32,"") -> 0.046153846 | T32: =D32/U32 -> 0.3204107 | U32: =$I$8*AA32*AB32/SUMPRODUCT($AB$25:$AB$55,$AA$25:$AA$55) -> 52966.395 | V32: =$I$9*AA32*AB32/SUMPRODUCT($AB$25:$AB$55,$AA$25:$AA$55) -> 8.0252114 | W32: =IF($I$12="","",V32/$I$12) -> 4.7207126 | X32: =IF(AB32<>"",IF(D32<>"",D32,($I$8-SUM($X$25:X31))*AA32*AB32/SUMPRODUCT($AB32:$AB$55,$AA32:$AA$55)),"") -> 16971 | Y32: =IF(AB32<>"",IF(E32<>"",E32,($I$9-SUM($Y$25:Y31))*AA32*AB32/SUMPRODUCT($AB32:$AB$55,$AA32:$AA$55)),"") -> 4 | Z32: =IF(AB32<>"",IF($I$12<>"",IF(G32<>"",G32,($I$9/$I$12-SUM($Z$25:Z31))*AA32*AB32/SUMPRODUCT($AB32:$AB$55,$AA32:$AA$55)),""),"") -> 3 | AA32: 0.85310234 | AB32: 0.85310234
A33: Стекольщикова, Свидовская, Козлова | B33: 46031 | C33: пт | D33: 46753 | E33: 8 | F33: =IF(AND(E33<>"",E33<>0),D33/E33,"") -> 5844.125 | G33: 6 | H33: =IF(AND(G33<>"",G33<>0),D33/G33,"") -> 7792.1667 | I33: 77 | J33: =IF(AND(G33<>"",G33<>0),E33/G33,"") -> 1.3333333 | S33: =IF(AND(I33<>"",I33<>0),G33/I33,"") -> 0.077922078 | T33: =D33/U33 -> 0.88269175 | U33: =$I$8*AA33*AB33/SUMPRODUCT($AB$25:$AB$55,$AA$25:$AA$55) -> 52966.395 | V33: =$I$9*AA33*AB33/SUMPRODUCT($AB$25:$AB$55,$AA$25:$AA$55) -> 8.0252114 | W33: =IF($I$12="","",V33/$I$12) -> 4.7207126 | X33: =IF(AB33<>"",IF(D33<>"",D33,($I$8-SUM($X$25:X32))*AA33*AB33/SUMPRODUCT($AB33:$AB$55,$AA33:$AA$55)),"") -> 46753 | Y33: =IF(AB33<>"",IF(E33<>"",E33,($I$9-SUM($Y$25:Y32))*AA33*AB33/SUMPRODUCT($AB33:$AB$55,$AA33:$AA$55)),"") -> 8 | Z33: =IF(AB33<>"",IF($I$12<>"",IF(G33<>"",G33,($I$9/$I$12-SUM($Z$25:Z32))*AA33*AB33/SUMPRODUCT($AB33:$AB$55,$AA33:$AA$55)),""),"") -> 6 | AA33: 0.85310234 | AB33: 0.85310234
A34: Стекольщикова, Козлова | B34: 46032 | C34: сб | D34: =32079+7503 -> 39582 | E34: 6 | F34: =IF(AND(E34<>"",E34<>0),D34/E34,"") -> 6597 | G34: 5 | H34: =IF(AND(G34<>"",G34<>0),D34/G34,"") -> 7916.4 | I34: 64 | J34: =IF(AND(G34<>"",G34<>0),E34/G34,"") -> 1.2 | L34: 7503 | M34: 8393 | S34: =IF(AND(I34<>"",I34<>0),G34/I34,"") -> 0.078125 | T34: =D34/U34 -> 1.3945528 | U34: =$I$8*AA34*AB34/SUMPRODUCT($AB$25:$AB$55,$AA$25:$AA$55) -> 28383.292 | V34: =$I$9*AA34*AB34/SUMPRODUCT($AB$25:$AB$55,$AA$25:$AA$55) -> 4.3004987 | W34: =IF($I$12="","",V34/$I$12) -> 2.5297051 | X34: =IF(AB34<>"",IF(D34<>"",D34,($I$8-SUM($X$25:X33))*AA34*AB34/SUMPRODUCT($AB34:$AB$55,$AA34:$AA$55)),"") -> 39582 | Y34: =IF(AB34<>"",IF(E34<>"",E34,($I$9-SUM($Y$25:Y33))*AA34*AB34/SUMPRODUCT($AB34:$AB$55,$AA34:$AA$55)),"") -> 6 | Z34: =IF(AB34<>"",IF($I$12<>"",IF(G34<>"",G34,($I$9/$I$12-SUM($Z$25:Z33))*AA34*AB34/SUMPRODUCT($AB34:$AB$55,$AA34:$AA$55)),""),"") -> 5 | AA34: 0.65 | AB34: 0.6
A35: Козлова, Корж, Свидовская | B35: 46033 | C35: вс | D35: =11984+220 -> 12204 | E35: 2 | F35: =IF(AND(E35<>"",E35<>0),D35/E35,"") -> 6102 | G35: 2 | H35: =IF(AND(G35<>"",G35<>0),D35/G35,"") -> 6102 | I35: 44 | J35: =IF(AND(G35<>"",G35<>0),E35/G35,"") -> 1 | L35: 220 | S35: =IF(AND(I35<>"",I35<>0),G35/I35,"") -> 0.045454545 | T35: =D35/U35 -> 0.31940723 | U35: =$I$8*AA35*AB35/SUMPRODUCT($AB$25:$AB$55,$AA$25:$AA$55) -> 38208.277 | V35: =$I$9*AA35*AB35/SUMPRODUCT($AB$25:$AB$55,$AA$25:$AA$55) -> 5.7891329 | W35: =IF($I$12="","",V35/$I$12) -> 3.4053723 | X35: =IF(AB35<>"",IF(D35<>"",D35,($I$8-SUM($X$25:X34))*AA35*AB35/SUMPRODUCT($AB35:$AB$55,$AA35:$AA$55)),"") -> 12204 | Y35: =IF(AB35<>"",IF(E35<>"",E35,($I$9-SUM($Y$25:Y34))*AA35*AB35/SUMPRODUCT($AB35:$AB$55,$AA35:$AA$55)),"") -> 2 | Z35: =IF(AB35<>"",IF($I$12<>"",IF(G35<>"",G35,($I$9/$I$12-SUM($Z$25:Z34))*AA35*AB35/SUMPRODUCT($AB35:$AB$55,$AA35:$AA$55)),""),"") -> 2 | AA35: 0.75 | AB35: 0.7
A36: Свидовская, Корж | B36: 46034 | C36: пн | D36: 10158 | E36: 2 | F36: =IF(AND(E36<>"",E36<>0),D36/E36,"") -> 5079 | G36: 2 | H36: =IF(AND(G36<>"",G36<>0),D36/G36,"") -> 5079 | I36: 52 | J36: =IF(AND(G36<>"",G36<>0),E36/G36,"") -> 1 | S36: =IF(AND(I36<>"",I36<>0),G36/I36,"") -> 0.038461538 | T36: =D36/U36 -> 0.13957578 | U36: =$I$8*AA36*AB36/SUMPRODUCT($AB$25:$AB$55,$AA$25:$AA$55) -> 72777.671 | V36: =$I$9*AA36*AB36/SUMPRODUCT($AB$25:$AB$55,$AA$25:$AA$55) -> 11.02692 | W36: =IF($I$12="","",V36/$I$12) -> 6.4864234 | X36: =IF(AB36<>"",IF(D36<>"",D36,($I$8-SUM($X$25:X35))*AA36*AB36/SUMPRODUCT($AB36:$AB$55,$AA36:$AA$55)),"") -> 10158 | Y36: =IF(AB36<>"",IF(E35<>"",E35,($I$9-SUM($Y$25:Y35))*AA36*AB36/SUMPRODUCT($AB36:$AB$55,$AA36:$AA$55)),"") -> 2 | Z36: =IF(AB36<>"",IF($I$12<>"",IF(G36<>"",G36,($I$9/$I$12-SUM($Z$25:Z35))*AA36*AB36/SUMPRODUCT($AB36:$AB$55,$AA36:$AA$55)),""),"") -> 2 | AA36: 1 | AB36: 1
A37: Корж | B37: 46035 | C37: вт | D37: 5393 | E37: 1 | F37: =IF(AND(E37<>"",E37<>0),D37/E37,"") -> 5393 | G37: 1 | H37: =IF(AND(G37<>"",G37<>0),D37/G37,"") -> 5393 | I37: 38 | J37: =IF(AND(G37<>"",G37<>0),E37/G37,"") -> 1 | S37: =IF(AND(I37<>"",I37<>0),G37/I37,"") -> 0.026315789 | T37: =D37/U37 -> 0.074102399 | U37: =$I$8*AA37*AB37/SUMPRODUCT($AB$25:$AB$55,$AA$25:$AA$55) -> 72777.671 | V37: =$I$9*AA37*AB37/SUMPRODUCT($AB$25:$AB$55,$AA$25:$AA$55) -> 11.02692 | W37: =IF($I$12="","",V37/$I$12) -> 6.4864234 | X37: =IF(AB37<>"",IF(D37<>"",D37,($I$8-SUM($X$25:X36))*AA37*AB37/SUMPRODUCT($AB37:$AB$55,$AA37:$AA$55)),"") -> 5393 | Y37: =IF(AB37<>"",IF(E37<>"",E37,($I$9-SUM($Y$25:Y36))*AA37*AB37/SUMPRODUCT($AB37:$AB$55,$AA37:$AA$55)),"") -> 1 | Z37: =IF(AB37<>"",IF($I$12<>"",IF(G37<>"",G37,($I$9/$I$12-SUM($Z$25:Z36))*AA37*AB37/SUMPRODUCT($AB37:$AB$55,$AA37:$AA$55)),""),"") -> 1 | AA37: 1 | AB37: 1
A38: Козлова,Рогалевич | B38: 46036 | C38: ср | D38: =6443+44640 -> 51083 | E38: 9 | F38: =IF(AND(E38<>"",E38<>0),D38/E38,"") -> 5675.8889 | G38: 6 | H38: =IF(AND(G38<>"",G38<>0),D38/G38,"") -> 8513.8333 | I38: 61 | J38: =IF(AND(G38<>"",G38<>0),E38/G38,"") -> 1.5 | K38: 7220 | L38: 6443 | M38: 11393 | S38: =IF(AND(I38<>"",I38<>0),G38/I38,"") -> 0.098360656 | T38: =D38/U38 -> 0.70190485 | U38: =$I$8*AA38*AB38/SUMPRODUCT($AB$25:$AB$55,$AA$25:$AA$55) -> 72777.671 | V38: =$I$9*AA38*AB38/SUMPRODUCT($AB$25:$AB$55,$AA$25:$AA$55) -> 11.02692 | W38: =IF($I$12="","",V38/$I$12) -> 6.4864234 | X38: =IF(AB38<>"",IF(D38<>"",D38,($I$8-SUM($X$25:X37))*AA38*AB38/SUMPRODUCT($AB38:$AB$55,$AA38:$AA$55)),"") -> 51083 | Y38: =IF(AB38<>"",IF(E38<>"",E38,($I$9-SUM($Y$25:Y37))*AA38*AB38/SUMPRODUCT($AB38:$AB$55,$AA38:$AA$55)),"") -> 9 | Z38: =IF(AB38<>"",IF($I$12<>"",IF(G38<>"",G38,($I$9/$I$12-SUM($Z$25:Z37))*AA38*AB38/SUMPRODUCT($AB38:$AB$55,$AA38:$AA$55)),""),"") -> 6 | AA38: 1 | AB38: 1
A39: Свидовская, Козлова,Рогалевич | B39: 46037 | C39: чт | D39: =17806+63046 -> 80852 | E39: 8 | F39: =IF(AND(E39<>"",E39<>0),D39/E39,"") -> 10106.5 | G39: 4 | H39: =IF(AND(G39<>"",G39<>0),D39/G39,"") -> 20213 | I39: 51 | J39: =IF(AND(G39<>"",G39<>0),E39/G39,"") -> 2 | L39: 17806 | R39: 38380 | S39: =IF(AND(I39<>"",I39<>0),G39/I39,"") -> 0.078431373 | T39: =D39/U39 -> 1.1109451 | U39: =$I$8*AA39*AB39/SUMPRODUCT($AB$25:$AB$55,$AA$25:$AA$55) -> 72777.671 | V39: =$I$9*AA39*AB39/SUMPRODUCT($AB$25:$AB$55,$AA$25:$AA$55) -> 11.02692 | W39: =IF($I$12="","",V39/$I$12) -> 6.4864234 | X39: =IF(AB39<>"",IF(D39<>"",D39,($I$8-SUM($X$25:X38))*AA39*AB39/SUMPRODUCT($AB39:$AB$55,$AA39:$AA$55)),"") -> 80852 | Y39: =IF(AB39<>"",IF(E39<>"",E39,($I$9-SUM($Y$25:Y38))*AA39*AB39/SUMPRODUCT($AB39:$AB$55,$AA39:$AA$55)),"") -> 8 | Z39: =IF(AB39<>"",IF($I$12<>"",IF(G39<>"",G39,($I$9/$I$12-SUM($Z$25:Z38))*AA39*AB39/SUMPRODUCT($AB39:$AB$55,$AA39:$AA$55)),""),"") -> 4 | AA39: 1 | AB39: 1
A40: Корж, Свидовская, Рогалевич, Сейтджелилова | B40: 46038 | C40: пт | D40: =26501+62037+11502 -> 100040 | E40: 8 | F40: =IF(AND(E40<>"",E40<>0),D40/E40,"") -> 12505 | G40: 3 | H40: =IF(AND(G40<>"",G40<>0),D40/G40,"") -> 33346.667 | I40: 46 | J40: =IF(AND(G40<>"",G40<>0),E40/G40,"") -> 2.6666667 | L40: 26501 | N40: 62037 | S40: =IF(AND(I40<>"",I40<>0),G40/I40,"") -> 0.065217391 | T40: =D40/U40 -> 1.3745974 | U40: =$I$8*AA40*AB40/SUMPRODUCT($AB$25:$AB$55,$AA$25:$AA$55) -> 72777.671 | V40: =$I$9*AA40*AB40/SUMPRODUCT($AB$25:$AB$55,$AA$25:$AA$55) -> 11.02692 | W40: =IF($I$12="","",V40/$I$12) -> 6.4864234 | X40: =IF(AB40<>"",IF(D40<>"",D40,($I$8-SUM($X$25:X39))*AA40*AB40/SUMPRODUCT($AB40:$AB$55,$AA40:$AA$55)),"") -> 100040 | Y40: =IF(AB40<>"",IF(E40<>"",E40,($I$9-SUM($Y$25:Y39))*AA40*AB40/SUMPRODUCT($AB40:$AB$55,$AA40:$AA$55)),"") -> 8 | Z40: =IF(AB40<>"",IF($I$12<>"",IF(G40<>"",G40,($I$9/$I$12-SUM($Z$25:Z39))*AA40*AB40/SUMPRODUCT($AB40:$AB$55,$AA40:$AA$55)),""),"") -> 3 | AA40: 1 | AB40: 1
A41: Корж, Рогалевич, Сейтджелилова | B41: 46039 | C41: сб | D41: 58965 | E41: 7 | F41: =IF(AND(E41<>"",E41<>0),D41/E41,"") -> 8423.5714 | G41: 4 | H41: =IF(AND(G41<>"",G41<>0),D41/G41,"") -> 14741.25 | I41: 56 | J41: =IF(AND(G41<>"",G41<>0),E41/G41,"") -> 1.75 | R41: 23229 | S41: =IF(AND(I41<>"",I41<>0),G41/I41,"") -> 0.071428571 | T41: =D41/U41 -> 0.8102073 | U41: =$I$8*AA41*AB41/SUMPRODUCT($AB$25:$AB$55,$AA$25:$AA$55) -> 72777.671 | V41: =$I$9*AA41*AB41/SUMPRODUCT($AB$25:$AB$55,$AA$25:$AA$55) -> 11.02692 | W41: =IF($I$12="","",V41/$I$12) -> 6.4864234 | X41: =IF(AB41<>"",IF(D41<>"",D41,($I$8-SUM($X$25:X40))*AA41*AB41/SUMPRODUCT($AB41:$AB$55,$AA41:$AA$55)),"") -> 58965 | Y41: =IF(AB41<>"",IF(E41<>"",E41,($I$9-SUM($Y$25:Y40))*AA41*AB41/SUMPRODUCT($AB41:$AB$55,$AA41:$AA$55)),"") -> 7 | Z41: =IF(AB41<>"",IF($I$12<>"",IF(G41<>"",G41,($I$9/$I$12-SUM($Z$25:Z40))*AA41*AB41/SUMPRODUCT($AB41:$AB$55,$AA41:$AA$55)),""),"") -> 4 | AA41: 1 | AB41: 1
A42: Корж, Рогалевич, Сейтджелилова, Козлова | B42: 46040 | C42: вс | D42: 21509 | E42: 5 | F42: =IF(AND(E42<>"",E42<>0),D42/E42,"") -> 4301.8 | G42: 3 | H42: =IF(AND(G42<>"",G42<>0),D42/G42,"") -> 7169.6667 | I42: 96 | J42: =IF(AND(G42<>"",G42<>0),E42/G42,"") -> 1.6666667 | R42: 19276 | S42: =IF(AND(I42<>"",I42<>0),G42/I42,"") -> 0.03125 | T42: =D42/U42 -> 0.29554395 | U42: =$I$8*AA42*AB42/SUMPRODUCT($AB$25:$AB$55,$AA$25:$AA$55) -> 72777.671 | V42: =$I$9*AA42*AB42/SUMPRODUCT($AB$25:$AB$55,$AA$25:$AA$55) -> 11.02692 | W42: =IF($I$12="","",V42/$I$12) -> 6.4864234 | X42: =IF(AB42<>"",IF(D42<>"",D42,($I$8-SUM($X$25:X41))*AA42*AB42/SUMPRODUCT($AB42:$AB$55,$AA42:$AA$55)),"") -> 21509 | Y42: =IF(AB42<>"",IF(E42<>"",E42,($I$9-SUM($Y$25:Y41))*AA42*AB42/SUMPRODUCT($AB42:$AB$55,$AA42:$AA$55)),"") -> 5 | Z42: =IF(AB42<>"",IF($I$12<>"",IF(G42<>"",G42,($I$9/$I$12-SUM($Z$25:Z41))*AA42*AB42/SUMPRODUCT($AB42:$AB$55,$AA42:$AA$55)),""),"") -> 3 | AA42: 1 | AB42: 1
A43: Свидовская, Козлова | B43: 46041 | C43: пн | D43: 43401 | E43: 6 | F43: =IF(AND(E43<>"",E43<>0),D43/E43,"") -> 7233.5 | G43: 3 | H43: =IF(AND(G43<>"",G43<>0),D43/G43,"") -> 14467 | I43: 34 | J43: =IF(AND(G43<>"",G43<>0),E43/G43,"") -> 2 | S43: =IF(AND(I43<>"",I43<>0),G43/I43,"") -> 0.088235294 | T43: =D43/U43 -> 0.59635049 | U43: =$I$8*AA43*AB43/SUMPRODUCT($AB$25:$AB$55,$AA$25:$AA$55) -> 72777.671 | V43: =$I$9*AA43*AB43/SUMPRODUCT($AB$25:$AB$55,$AA$25:$AA$55) -> 11.02692 | W43: =IF($I$12="","",V43/$I$12) -> 6.4864234 | X43: =IF(AB43<>"",IF(D43<>"",D43,($I$8-SUM($X$25:X42))*AA43*AB43/SUMPRODUCT($AB43:$AB$55,$AA43:$AA$55)),"") -> 43401 | Y43: =IF(AB43<>"",IF(E43<>"",E43,($I$9-SUM($Y$25:Y42))*AA43*AB43/SUMPRODUCT($AB43:$AB$55,$AA43:$AA$55)),"") -> 6 | Z43: =IF(AB43<>"",IF($I$12<>"",IF(G43<>"",G43,($I$9/$I$12-SUM($Z$25:Z42))*AA43*AB43/SUMPRODUCT($AB43:$AB$55,$AA43:$AA$55)),""),"") -> 3 | AA43: 1 | AB43: 1
A44: Свидовская, Козлова, Сейтджелилова | B44: 46042 | C44: вт | D44: 17518 | E44: 3 | F44: =IF(AND(E44<>"",E44<>0),D44/E44,"") -> 5839.3333 | G44: 2 | H44: =IF(AND(G44<>"",G44<>0),D44/G44,"") -> 8759 | I44: 49 | J44: =IF(AND(G44<>"",G44<>0),E44/G44,"") -> 1.5 | R44: 9390 | S44: =IF(AND(I44<>"",I44<>0),G44/I44,"") -> 0.040816327 | T44: =D44/U44 -> 0.2407057 | U44: =$I$8*AA44*AB44/SUMPRODUCT($AB$25:$AB$55,$AA$25:$AA$55) -> 72777.671 | V44: =$I$9*AA44*AB44/SUMPRODUCT($AB$25:$AB$55,$AA$25:$AA$55) -> 11.02692 | W44: =IF($I$12="","",V44/$I$12) -> 6.4864234 | X44: =IF(AB44<>"",IF(D44<>"",D44,($I$8-SUM($X$25:X43))*AA44*AB44/SUMPRODUCT($AB44:$AB$55,$AA44:$AA$55)),"") -> 17518 | Y44: =IF(AB44<>"",IF(E44<>"",E44,($I$9-SUM($Y$25:Y43))*AA44*AB44/SUMPRODUCT($AB44:$AB$55,$AA44:$AA$55)),"") -> 3 | Z44: =IF(AB44<>"",IF($I$12<>"",IF(G44<>"",G44,($I$9/$I$12-SUM($Z$25:Z43))*AA44*AB44/SUMPRODUCT($AB44:$AB$55,$AA44:$AA$55)),""),"") -> 2 | AA44: 1 | AB44: 1
A45: Свидовская, Корж, Сейтджелилова | B45: 46043 | C45: ср | D45: 102418 | E45: 10 | F45: =IF(AND(E45<>"",E45<>0),D45/E45,"") -> 10241.8 | G45: 4 | H45: =IF(AND(G45<>"",G45<>0),D45/G45,"") -> 25604.5 | I45: 36 | J45: =IF(AND(G45<>"",G45<>0),E45/G45,"") -> 2.5 | M45: 31570 | O45: 36688 | S45: =IF(AND(I45<>"",I45<>0),G45/I45,"") -> 0.11111111 | T45: =D45/U45 -> 1.4072723 | U45: =$I$8*AA45*AB45/SUMPRODUCT($AB$25:$AB$55,$AA$25:$AA$55) -> 72777.671 | V45: =$I$9*AA45*AB45/SUMPRODUCT($AB$25:$AB$55,$AA$25:$AA$55) -> 11.02692 | W45: =IF($I$12="","",V45/$I$12) -> 6.4864234 | X45: =IF(AB45<>"",IF(D45<>"",D45,($I$8-SUM($X$25:X44))*AA45*AB45/SUMPRODUCT($AB45:$AB$55,$AA45:$AA$55)),"") -> 102418 | Y45: =IF(AB45<>"",IF(E45<>"",E45,($I$9-SUM($Y$25:Y44))*AA45*AB45/SUMPRODUCT($AB45:$AB$55,$AA45:$AA$55)),"") -> 10 | Z45: =IF(AB45<>"",IF($I$12<>"",IF(G45<>"",G45,($I$9/$I$12-SUM($Z$25:Z44))*AA45*AB45/SUMPRODUCT($AB45:$AB$55,$AA45:$AA$55)),""),"") -> 4 | AA45: 1 | AB45: 1
A46: Корж, Сейтджелилова | B46: 46044 | C46: чт | D46: =14500+31191 -> 45691 | E46: 6 | F46: =IF(AND(E46<>"",E46<>0),D46/E46,"") -> 7615.1667 | G46: 2 | H46: =IF(AND(G46<>"",G46<>0),D46/G46,"") -> 22845.5 | I46: 37 | J46: =IF(AND(G46<>"",G46<>0),E46/G46,"") -> 3 | L46: 14500 | S46: =IF(AND(I46<>"",I46<>0),G46/I46,"") -> 0.054054054 | T46: =D46/U46 -> 0.62781619 | U46: =$I$8*AA46*AB46/SUMPRODUCT($AB$25:$AB$55,$AA$25:$AA$55) -> 72777.671 | V46: =$I$9*AA46*AB46/SUMPRODUCT($AB$25:$AB$55,$AA$25:$AA$55) -> 11.02692 | W46: =IF($I$12="","",V46/$I$12) -> 6.4864234 | X46: =IF(AB46<>"",IF(D46<>"",D46,($I$8-SUM($X$25:X45))*AA46*AB46/SUMPRODUCT($AB46:$AB$55,$AA46:$AA$55)),"") -> 45691 | Y46: =IF(AB45<>"",IF(E45<>"",E45,($I$9-SUM($Y$25:Y44))*AA45*AB45/SUMPRODUCT($AB45:$AB$55,$AA45:$AA$55)),"") -> 10 | Z46: =IF(AB45<>"",IF($I$12<>"",IF(G45<>"",G45,($I$9/$I$12-SUM($Z$25:Z44))*AA45*AB45/SUMPRODUCT($AB45:$AB$55,$AA45:$AA$55)),""),"") -> 4 | AA46: 1 | AB46: 1
A47: Корж, Козлова, Сейтджелилова | B47: 46045 | C47: пт | D47: 79502 | E47: 14 | F47: =IF(AND(E47<>"",E47<>0),D47/E47,"") -> 5678.7143 | G47: 7 | H47: =IF(AND(G47<>"",G47<>0),D47/G47,"") -> 11357.429 | I47: 59 | J47: =IF(AND(G47<>"",G47<>0),E47/G47,"") -> 2 | O47: 8990 | Q47: 8893 | R47: 35432 | S47: =IF(AND(I47<>"",I47<>0),G47/I47,"") -> 0.11864407 | T47: =D47/U47 -> 1.0923955 | U47: =$I$8*AA47*AB47/SUMPRODUCT($AB$25:$AB$55,$AA$25:$AA$55) -> 72777.671 | V47: =$I$9*AA47*AB47/SUMPRODUCT($AB$25:$AB$55,$AA$25:$AA$55) -> 11.02692 | W47: =IF($I$12="","",V47/$I$12) -> 6.4864234 | X47: =IF(AB47<>"",IF(D47<>"",D47,($I$8-SUM($X$25:X46))*AA47*AB47/SUMPRODUCT($AB47:$AB$55,$AA47:$AA$55)),"") -> 79502 | Y47: =IF(AB47<>"",IF(E47<>"",E47,($I$9-SUM($Y$25:Y46))*AA47*AB47/SUMPRODUCT($AB47:$AB$55,$AA47:$AA$55)),"") -> 14 | Z47: =IF(AB47<>"",IF($I$12<>"",IF(G47<>"",G47,($I$9/$I$12-SUM($Z$25:Z46))*AA47*AB47/SUMPRODUCT($AB47:$AB$55,$AA47:$AA$55)),""),"") -> 7 | AA47: 1 | AB47: 1
A48: Свидовская, Козлова, Сейтджелилова | B48: 46046 | C48: сб | D48: 111505 | E48: 18 | F48: =IF(AND(E48<>"",E48<>0),D48/E48,"") -> 6194.7222 | G48: 9 | H48: =IF(AND(G48<>"",G48<>0),D48/G48,"") -> 12389.444 | I48: 83 | J48: =IF(AND(G48<>"",G48<>0),E48/G48,"") -> 2 | L48: 8702 | S48: =IF(AND(I48<>"",I48<>0),G48/I48,"") -> 0.10843373 | T48: =D48/U48 -> 1.532132 | U48: =$I$8*AA48*AB48/SUMPRODUCT($AB$25:$AB$55,$AA$25:$AA$55) -> 72777.671 | V48: =$I$9*AA48*AB48/SUMPRODUCT($AB$25:$AB$55,$AA$25:$AA$55) -> 11.02692 | W48: =IF($I$12="","",V48/$I$12) -> 6.4864234 | X48: =IF(AB48<>"",IF(D48<>"",D48,($I$8-SUM($X$25:X47))*AA48*AB48/SUMPRODUCT($AB48:$AB$55,$AA48:$AA$55)),"") -> 111505 | Y48: =IF(AB48<>"",IF(E48<>"",E48,($I$9-SUM($Y$25:Y47))*AA48*AB48/SUMPRODUCT($AB48:$AB$55,$AA48:$AA$55)),"") -> 18 | Z48: =IF(AB48<>"",IF($I$12<>"",IF(G48<>"",G48,($I$9/$I$12-SUM($Z$25:Z47))*AA48*AB48/SUMPRODUCT($AB48:$AB$55,$AA48:$AA$55)),""),"") -> 9 | AA48: 1 | AB48: 1
A49: Свидовская, Козлова | B49: 46047 | C49: вс | D49: 23266 | E49: 4 | F49: =IF(AND(E49<>"",E49<>0),D49/E49,"") -> 5816.5 | G49: 1 | H49: =IF(AND(G49<>"",G49<>0),D49/G49,"") -> 23266 | I49: 49 | J49: =IF(AND(G49<>"",G49<>0),E49/G49,"") -> 4 | S49: =IF(AND(I49<>"",I49<>0),G49/I49,"") -> 0.020408163 | T49: =D49/U49 -> 0.31968597 | U49: =$I$8*AA49*AB49/SUMPRODUCT($AB$25:$AB$55,$AA$25:$AA$55) -> 72777.671 | V49: =$I$9*AA49*AB49/SUMPRODUCT($AB$25:$AB$55,$AA$25:$AA$55) -> 11.02692 | W49: =IF($I$12="","",V49/$I$12) -> 6.4864234 | X49: =IF(AB49<>"",IF(D49<>"",D49,($I$8-SUM($X$25:X48))*AA49*AB49/SUMPRODUCT($AB49:$AB$55,$AA49:$AA$55)),"") -> 23266 | Y49: =IF(AB49<>"",IF(E49<>"",E49,($I$9-SUM($Y$25:Y48))*AA49*AB49/SUMPRODUCT($AB49:$AB$55,$AA49:$AA$55)),"") -> 4 | Z49: =IF(AB49<>"",IF($I$12<>"",IF(G49<>"",G49,($I$9/$I$12-SUM($Z$25:Z48))*AA49*AB49/SUMPRODUCT($AB49:$AB$55,$AA49:$AA$55)),""),"") -> 1 | AA49: 1 | AB49: 1
A50: Свидовская, Козлова, Корж | B50: 46048 | C50: пн | D50: 18770 | E50: 3 | F50: =IF(AND(E50<>"",E50<>0),D50/E50,"") -> 6256.6667 | G50: 2 | H50: =IF(AND(G50<>"",G50<>0),D50/G50,"") -> 9385 | I50: 35 | J50: =IF(AND(G50<>"",G50<>0),E50/G50,"") -> 1.5 | S50: =IF(AND(I50<>"",I50<>0),G50/I50,"") -> 0.057142857 | T50: =D50/U50 -> 0.25790878 | U50: =$I$8*AA50*AB50/SUMPRODUCT($AB$25:$AB$55,$AA$25:$AA$55) -> 72777.671 | V50: =$I$9*AA50*AB50/SUMPRODUCT($AB$25:$AB$55,$AA$25:$AA$55) -> 11.02692 | W50: =IF($I$12="","",V50/$I$12) -> 6.4864234 | X50: =IF(AB50<>"",IF(D50<>"",D50,($I$8-SUM($X$25:X49))*AA50*AB50/SUMPRODUCT($AB50:$AB$55,$AA50:$AA$55)),"") -> 18770 | Y50: =IF(AB50<>"",IF(E50<>"",E50,($I$9-SUM($Y$25:Y49))*AA50*AB50/SUMPRODUCT($AB50:$AB$55,$AA50:$AA$55)),"") -> 3 | Z50: =IF(AB50<>"",IF($I$12<>"",IF(G50<>"",G50,($I$9/$I$12-SUM($Z$25:Z49))*AA50*AB50/SUMPRODUCT($AB50:$AB$55,$AA50:$AA$55)),""),"") -> 2 | AA50: 1 | AB50: 1
A51: Сейтджелилова, Корж | B51: 46049 | C51: вт | D51: =131198 -> 131198 | E51: 12 | F51: =IF(AND(E51<>"",E51<>0),D51/E51,"") -> 10933.167 | G51: 3 | H51: =IF(AND(G51<>"",G51<>0),D51/G51,"") -> 43732.667 | I51: 55 | J51: =IF(AND(G51<>"",G51<>0),E51/G51,"") -> 4 | S51: =IF(AND(I51<>"",I51<>0),G51/I51,"") -> 0.054545455 | T51: =D51/U51 -> 2.8167551 | U51: =$I$8*AA51*AB51/SUMPRODUCT($AB$25:$AB$55,$AA$25:$AA$55) -> 46577.709 | V51: =$I$9*AA51*AB51/SUMPRODUCT($AB$25:$AB$55,$AA$25:$AA$55) -> 7.0572287 | W51: =IF($I$12="","",V51/$I$12) -> 4.151311 | X51: =IF(AB51<>"",IF(D51<>"",D51,($I$8-SUM($X$25:X50))*AA51*AB51/SUMPRODUCT($AB51:$AB$55,$AA51:$AA$55)),"") -> 131198 | Y51: =IF(AB51<>"",IF(E51<>"",E51,($I$9-SUM($Y$25:Y50))*AA51*AB51/SUMPRODUCT($AB51:$AB$55,$AA51:$AA$55)),"") -> 12 | Z51: =IF(AB51<>"",IF($I$12<>"",IF(G51<>"",G51,($I$9/$I$12-SUM($Z$25:Z50))*AA51*AB51/SUMPRODUCT($AB51:$AB$55,$AA51:$AA$55)),""),"") -> 3 | AA51: 0.8 | AB51: 0.8
A52: Сейтджелилова, Корж | B52: 46050 | C52: ср | D52: =38384-28856 -> 9528 | E52: 5 | F52: =IF(AND(E52<>"",E52<>0),D52/E52,"") -> 1905.6 | G52: 2 | H52: =IF(AND(G52<>"",G52<>0),D52/G52,"") -> 4764 | I52: 47 | J52: =IF(AND(G52<>"",G52<>0),E52/G52,"") -> 2.5 | S52: =IF(AND(I52<>"",I52<>0),G52/I52,"") -> 0.042553191 | T52: =D52/U52 -> 0.20456137 | U52: =$I$8*AA52*AB52/SUMPRODUCT($AB$25:$AB$55,$AA$25:$AA$55) -> 46577.709 | V52: =$I$9*AA52*AB52/SUMPRODUCT($AB$25:$AB$55,$AA$25:$AA$55) -> 7.0572287 | W52: =IF($I$12="","",V52/$I$12) -> 4.151311 | X52: =IF(AB52<>"",IF(D52<>"",D52,($I$8-SUM($X$25:X51))*AA52*AB52/SUMPRODUCT($AB52:$AB$55,$AA52:$AA$55)),"") -> 9528 | Y52: =IF(AB52<>"",IF(E52<>"",E52,($I$9-SUM($Y$25:Y51))*AA52*AB52/SUMPRODUCT($AB52:$AB$55,$AA52:$AA$55)),"") -> 5 | Z52: =IF(AB52<>"",IF($I$12<>"",IF(G52<>"",G52,($I$9/$I$12-SUM($Z$25:Z51))*AA52*AB52/SUMPRODUCT($AB52:$AB$55,$AA52:$AA$55)),""),"") -> 2 | AA52: 0.8 | AB52: 0.8
A53: Козлова, Свидовская, Сейтджелилова | B53: 46051 | C53: чт | D53: 28447 | E53: 5 | F53: =IF(AND(E53<>"",E53<>0),D53/E53,"") -> 5689.4 | G53: 4 | H53: =IF(AND(G53<>"",G53<>0),D53/G53,"") -> 7111.75 | I53: 59 | J53: =IF(AND(G53<>"",G53<>0),E53/G53,"") -> 1.25 | S53: =IF(AND(I53<>"",I53<>0),G53/I53,"") -> 0.06779661 | T53: =D53/U53 -> 0.61074279 | U53: =$I$8*AA53*AB53/SUMPRODUCT($AB$25:$AB$55,$AA$25:$AA$55) -> 46577.709 | V53: =$I$9*AA53*AB53/SUMPRODUCT($AB$25:$AB$55,$AA$25:$AA$55) -> 7.0572287 | W53: =IF($I$12="","",V53/$I$12) -> 4.151311 | X53: =IF(AB53<>"",IF(D53<>"",D53,($I$8-SUM($X$25:X52))*AA53*AB53/SUMPRODUCT($AB53:$AB$55,$AA53:$AA$55)),"") -> 28447 | Y53: =IF(AB53<>"",IF(E53<>"",E53,($I$9-SUM($Y$25:Y52))*AA53*AB53/SUMPRODUCT($AB53:$AB$55,$AA53:$AA$55)),"") -> 5 | Z53: =IF(AB53<>"",IF($I$12<>"",IF(G53<>"",G53,($I$9/$I$12-SUM($Z$25:Z52))*AA53*AB53/SUMPRODUCT($AB53:$AB$55,$AA53:$AA$55)),""),"") -> 4 | AA53: 0.8 | AB53: 0.8
A54: Свидовская, Козлова, Сейтджелилова | B54: 46052 | C54: пт | D54: 20478 | E54: 4 | F54: =IF(AND(E54<>"",E54<>0),D54/E54,"") -> 5119.5 | G54: 3 | H54: =IF(AND(G54<>"",G54<>0),D54/G54,"") -> 6826 | I54: 55 | J54: =IF(AND(G54<>"",G54<>0),E54/G54,"") -> 1.3333333 | S54: =IF(AND(I54<>"",I54<>0),G54/I54,"") -> 0.054545455 | T54: =D54/U54 -> 0.43965236 | U54: =$I$8*AA54*AB54/SUMPRODUCT($AB$25:$AB$55,$AA$25:$AA$55) -> 46577.709 | V54: =$I$9*AA54*AB54/SUMPRODUCT($AB$25:$AB$55,$AA$25:$AA$55) -> 7.0572287 | W54: =IF($I$12="","",V54/$I$12) -> 4.151311 | X54: =IF(AB54<>"",IF(D54<>"",D54,($I$8-SUM($X$25:X53))*AA54*AB54/SUMPRODUCT($AB54:$AB$55,$AA54:$AA$55)),"") -> 20478 | Y54: =IF(AB54<>"",IF(E54<>"",E54,($I$9-SUM($Y$25:Y53))*AA54*AB54/SUMPRODUCT($AB54:$AB$55,$AA54:$AA$55)),"") -> 4 | Z54: =IF(AB54<>"",IF($I$12<>"",IF(G54<>"",G54,($I$9/$I$12-SUM($Z$25:Z53))*AA54*AB54/SUMPRODUCT($AB54:$AB$55,$AA54:$AA$55)),""),"") -> 3 | AA54: 0.8 | AB54: 0.8
A55: Корж, Сейтджелилова | B55: 46053 | C55: сб | D55: 45962 | E55: 5 | F55: =IF(AND(E55<>"",E55<>0),D55/E55,"") -> 9192.4 | G55: 7 | H55: =IF(AND(G55<>"",G55<>0),D55/G55,"") -> 6566 | I55: 62 | J55: =IF(AND(G55<>"",G55<>0),E55/G55,"") -> 0.71428571 | L55: 220 | M55: 10892 | S55: =IF(AND(I55<>"",I55<>0),G55/I55,"") -> 0.11290323 | T55: =D55/U55 -> 0.98678103 | U55: =$I$8*AA55*AB55/SUMPRODUCT($AB$25:$AB$55,$AA$25:$AA$55) -> 46577.709 | V55: =$I$9*AA55*AB55/SUMPRODUCT($AB$25:$AB$55,$AA$25:$AA$55) -> 7.0572287 | W55: =IF($I$12="","",V55/$I$12) -> 4.151311 | X55: =IF(AB55<>"",IF(D55<>"",D55,($I$8-SUM($X$25:X54))*AA55*AB55/SUMPRODUCT($AB55:$AB$55,$AA55:$AA$55)),"") -> 45962 | Y55: =IF(AB55<>"",IF(E55<>"",E55,($I$9-SUM($Y$25:Y54))*AA55*AB55/SUMPRODUCT($AB55:$AB$55,$AA55:$AA$55)),"") -> 5 | Z55: =IF(AB55<>"",IF($I$12<>"",IF(G55<>"",G55,($I$9/$I$12-SUM($Z$25:Z54))*AA55*AB55/SUMPRODUCT($AB55:$AB$55,$AA55:$AA$55)),""),"") -> 7 | AA55: 0.8 | AB55: 0.8
B56: итого | D56: =SUM(D25:D55) -> 1422520 | E56: =SUM(E25:E55) -> 202 | F56: =IF(AND(E56<>"", E56<>0), D56/E56, "") -> 7042.1781 | G56: =SUM(G25:G55) -> 110 | H56: =IF(AND(G56<>"", G56<>0), D56/G56, "") -> 12932 | I56: =SUM(I25:I55)*0.8 -> 1421.6 | J56: =E56/G56 -> 1.8363636 | K56: =SUM(K25:K55) -> 7220 | L56: =SUM(L25:L55) -> 81895 | M56: =SUM(M25:M55) -> 83931 | N56: =SUM(N25:N55) -> 62037 | O56: =SUM(O25:O55) -> 45678 | P56: =SUM(P25:P55) -> 0 | Q56: =SUM(Q25:Q55) -> 42156 | R56: =SUM(R25:R55) -> 125707 | S56: =IF(AND(I56<>"",I56<>0),G56/I56,"") -> 0.077377603 | T56: =D56/U56 -> 0.74142872 | U56: =SUM(U25:U55) -> 1918620 | V56: =SUM(V25:V55) -> 290.7 | W56: =SUM(W25:W55) -> 171 | X56: =SUM(X25:X55) -> 1422520 | Y56: =SUM(Y25:Y55) -> 206 | Z56: =SUM(Z25:Z55) -> 112
D57: =SUMIF(D25:D55,"",U25:U55)+D56 -> 1422520
D58: ='Доп сотрудник'!D48+'Свидовская С. А.'!J8+'Корж А. А.'!J8+'Козлова В. Э.'!J8+'Стекольщикова А. А.'!J8+'Сейтджелилова А.Э.'!D49 -> 1422520 | I58: ='Козлова В. Э.'!I49+'Корж А. А.'!I48+'Свидовская С. А.'!I48+'Стекольщикова А. А.'!I50+'Доп сотрудник'!I48+'Сейтджелилова А.Э.'!I49 -> 1237.6 | K58: ='Козлова В. Э.'!K49+'Корж А. А.'!K48+'Сейтджелилова А.Э.'!K49+'Свидовская С. А.'!K48+'Доп сотрудник'!K48+'Стекольщикова А. А.'!K50 -> 7220 | L58: ='Козлова В. Э.'!L49+'Корж А. А.'!L48+'Сейтджелилова А.Э.'!L49+'Свидовская С. А.'!L48+'Стекольщикова А. А.'!L50 -> 81895 | M58: ='Козлова В. Э.'!M49+'Корж А. А.'!M48+'Сейтджелилова А.Э.'!M49+'Свидовская С. А.'!M48+'Доп сотрудник'!M48+'Стекольщикова А. А.'!M50 -> 83931 | N58: ='Козлова В. Э.'!N49+'Корж А. А.'!N48+'Сейтджелилова А.Э.'!N49+'Свидовская С. А.'!N48+'Доп сотрудник'!N48+'Стекольщикова А. А.'!N50 -> 62037 | O58: ='Козлова В. Э.'!O49+'Корж А. А.'!O48+'Сейтджелилова А.Э.'!O49+'Свидовская С. А.'!O48+'Доп сотрудник'!O48+'Стекольщикова А. А.'!O50 -> 45678 | P58: ='Козлова В. Э.'!P49+'Корж А. А.'!P48+'Сейтджелилова А.Э.'!P49+'Свидовская С. А.'!P48+'Доп сотрудник'!P48+'Стекольщикова А. А.'!P50 -> 0 | Q58: ='Сейтджелилова А.Э.'!Q49+'Козлова В. Э.'!Q49+'Корж А. А.'!Q48+'Свидовская С. А.'!Q48+'Доп сотрудник'!Q48+'Стекольщикова А. А.'!Q50 -> 42156 | R58: ='Сейтджелилова А.Э.'!R49+'Козлова В. Э.'!R49+'Корж А. А.'!R48+'Свидовская С. А.'!R48+'Доп сотрудник'!R48 -> 112879
K59: =K58/$J$8 -> 0.0050754999 | L59: =L58/$J$8 -> 0.057570369 | M59: =M58/$J$8 -> 0.059001632 | N59: =N58/$J$8 -> 0.043610635 | O59: =O58/$J$8 -> 0.032110621 | P59: =P58/$J$8 -> 0 | Q59: =Q58/$J$8 -> 0.029634733 | R59: =R58/$J$8 -> 0.079351434

Sheet Конкурс
A1: Личный ежедневный КВП, %
A3: Сотруник | B3: 45282 | C3: 45283 | D3: 45284 | E3: 45285 | F3: 45286 | G3: 45287 | H3: 45288 | I3: 45289 | J3: 45290 | K3: 45291 | L3: Итого:
A4: Доп сотрудник | B4: ='Доп сотрудник'!T35 -> #DIV/0! | D4: 0.27 | E4: 0.57 | F4: 0.73 | G4: 0.88 | H4: 0.98
A5: Стекольщикова Алла | C5: 0.25 | D5: 0.79 | E5: 0.33 | F5: 0.13 | G5: 0.75 | H5: 0.67 | I5: 0.74 | J5: 1.72 | K5: 0.33
A6: Свидовская София | B6: ='Свидовская С. А.'!T39 -> 1.2450573 | E6: 0.25 | F6: 0.25 | H6: 0.38 | I6: 1.11 | J6: 1.17 | K6: 0.34
A7: Корж Анастасия | C7: 0.33 | D7: 0.57 | E7: 0.08 | F7: 0.45 | G7: 0.4 | H7: 0.24 | I7: 0.25 | J7: 0.28 | K7: 0.23
A8: Козлова Валерия | B8: ='Козлова В. Э.'!T39 -> 1.2945013 | C8: 0.52 | D8: 0.31 | G8: 0.29 | I8: 0.49 | J8: 0.23 | K8: 0.1
A10: Личный КВП, баллы
A12: Сотруник | B12: 45282 | C12: 45283 | D12: 45284 | E12: 45285 | F12: 45286 | G12: 45287 | H12: 45288 | I12: 45289 | J12: 45290 | K12: 45291 | L12: Итого:
A13: Доп сотрудник | B13: 0 | D13: 0 | E13: 1 | F13: 1 | G13: 1 | H13: 1 | L13: =SUM(B13:K13) -> 4
A14: Стекольщикова Алла | C14: 0 | D14: 1 | E14: 0 | F14: 0 | G14: 0 | H14: 0 | I14: 0 | J14: 2 | K14: 0 | L14: =SUM(B14:K14) -> 3
A15: Свидовская София | B15: 1 | E15: 0 | F15: 0 | H15: 0 | I15: 2 | J15: 1 | K15: 1 | L15: =SUM(B15:K15) -> 5
A16: Корж Анастасия | C16: 0 | D16: 0 | E16: 0 | F16: 0 | G16: 0 | H16: 0 | I16: 0 | J16: 0 | K16: 0 | L16: =SUM(B16:K16) -> 0
A17: Козлова Валерия | B17: 0 | C17: 1 | D17: 0 | G17: 0 | I17: 0 | J17: 0 | K17: 0 | L17: =SUM(B17:K17) -> 1

Sheet Сводная
A1: Сводная по показателям
A2: Показатель | D2: =Центрум!I3 -> ТРК Центрум | G2: =График!B27 -> Свидовская София | J2: =График!B25 -> Корж Анастасия | M2: =График!B26 -> Козлова Валерия | P2: =График!B28 -> Сейтджелилова Алина
D3: Факт | F3: Прогноз | G3: Факт | I3: Прогноз | J3: Факт | L3: Прогноз | M3: Факт | O3: Прогноз | P3: Факт | R3: Прогноз
A4: Выручка | D4: =Центрум!K8 -> 0.74142872 | E4: =Центрум!J8 -> 1422520 | F4: =Центрум!M8 -> 0.74142872 | G4: ='Свидовская С. А.'!K8 -> 0.75489417 | H4: ='Свидовская С. А.'!J8 -> 268023 | I4: ='Свидовская С. А.'!M8 -> 0.80775624 | J4: ='Корж А. А.'!K8 -> 0.7998031 | K4: ='Корж А. А.'!J8 -> 505135 | L4: ='Корж А. А.'!M8 -> 0.82474864 | M4: ='Козлова В. Э.'!K8 -> 0.42070029 | N4: ='Козлова В. Э.'!J8 -> 262830.98 | O4: ='Козлова В. Э.'!M8 -> 0.4995816 | P4: ='Стекольщикова А. А.'!K8 -> 0.28779604 | Q4: ='Стекольщикова А. А.'!J8 -> 88426 | R4: ='Стекольщикова А. А.'!M8 -> 1.5238114
A5: Кол-во изделий | D5: ='Центрум'!K9 -> 0.69487444 | E5: ='Центрум'!J9 -> 202 | F5: ='Центрум'!M9 -> 0.69487444 | G5: ='Свидовская С. А.'!K9 -> 0.76215236 | H5: ='Свидовская С. А.'!J9 -> 41 | I5: ='Свидовская С. А.'!M9 -> 0.78645933 | J5: ='Корж А. А.'!K9 -> 0.67925511 | K5: ='Корж А. А.'!J9 -> 65 | L5: ='Корж А. А.'!M9 -> 0.72528367 | M5: ='Козлова В. Э.'!K9 -> 0.47539292 | N5: ='Козлова В. Э.'!J9 -> 45 | O5: ='Козлова В. Э.'!M9 -> 0.56452909 | P5: ='Стекольщикова А. А.'!K9 -> 0.30073004 | Q5: ='Стекольщикова А. А.'!J9 -> 14 | R5: ='Стекольщикова А. А.'!M9 -> 1.3145261
A6: Средний чек | D6: =Центрум!K10 -> 1.1525847 | E6: =Центрум!J10 -> 12932 | F6: =Центрум!M10 -> 1.1525847 | G6: ='Свидовская С. А.'!K10 -> 0.77057961 | H6: ='Свидовская С. А.'!J10 -> 8645.9032 | I6: ='Свидовская С. А.'!M10 -> 0.77057961 | J6: ='Корж А. А.'!K10 -> 1.6674424 | K6: ='Корж А. А.'!J10 -> 18708.704 | L6: ='Корж А. А.'!M10 -> 1.6674424 | M6: ='Козлова В. Э.'!K10 -> 0.90097004 | N6: ='Козлова В. Э.'!J10 -> 10108.884 | O6: ='Козлова В. Э.'!M10 -> 0.90097004 | P6: ='Стекольщикова А. А.'!K10 -> 0.87567835 | Q6: ='Стекольщикова А. А.'!J10 -> 9825.1111 | R6: ='Стекольщикова А. А.'!M10 -> 0.87567835
A7: Средняя стоимость изделия | D7: ='Центрум'!K11 -> 1.0669967 | E7: ='Центрум'!J11 -> 7042.1781 | F7: ='Центрум'!M11 -> 1.0669967 | G7: ='Свидовская С. А.'!K11 -> 0.99047672 | H7: ='Свидовская С. А.'!J11 -> 6537.1463 | I7: ='Свидовская С. А.'!M11 -> 0.99047672 | J7: ='Корж А. А.'!K11 -> 1.1774709 | K7: ='Корж А. А.'!J11 -> 7771.3077 | L7: ='Корж А. А.'!M11 -> 1.1774709 | M7: ='Козлова В. Э.'!K11 -> 0.88495279 | N7: ='Козлова В. Э.'!J11 -> 5840.6884 | O7: ='Козлова В. Э.'!M11 -> 0.88495279 | P7: ='Стекольщикова А. А.'!K11 -> 0.95699134 | Q7: ='Стекольщикова А. А.'!J11 -> 6316.1429 | R7: ='Стекольщикова А. А.'!M11 -> 0.95699134
A8: Длина чека | D8: ='Центрум'!K12 -> 1.0802139 | E8: ='Центрум'!J12 -> 1.8363636 | F8: ='Центрум'!M12 -> 1.0802139 | G8: ='Свидовская С. А.'!K12 -> 0.77798861 | H8: ='Свидовская С. А.'!J12 -> 1.3225806 | I8: ='Свидовская С. А.'!M12 -> 0.77798861 | J8: ='Корж А. А.'!K12 -> 1.416122 | K8: ='Корж А. А.'!J12 -> 2.4074074 | L8: ='Корж А. А.'!M12 -> 1.416122 | M8: ='Козлова В. Э.'!K12 -> 1.0180995 | N8: ='Козлова В. Э.'!J12 -> 1.7307692 | O8: ='Козлова В. Э.'!M12 -> 1.0180995 | P8: ='Стекольщикова А. А.'!K12 -> 0.91503268 | Q8: ='Стекольщикова А. А.'!J12 -> 1.5555556 | R8: ='Стекольщикова А. А.'!M12 -> 0.91503268
A9: Кол-во чеков | D9: ='Центрум'!K13 -> 0.64327485 | E9: ='Центрум'!J13 -> 110 | F9: ='Центрум'!M13 -> 0.64327485 | G9: ='Свидовская С. А.'!K13 -> 0.97964462 | H9: ='Свидовская С. А.'!J13 -> 31 | I9: ='Свидовская С. А.'!M13 -> 1.0226579 | J9: ='Корж А. А.'!K13 -> 0.47965861 | K9: ='Корж А. А.'!J13 -> 27 | L9: ='Корж А. А.'!M13 -> 0.51561385 | M9: ='Козлова В. Э.'!K13 -> 0.46694149 | N9: ='Козлова В. Э.'!J13 -> 26 | O9: ='Козлова В. Э.'!M13 -> 0.55449302 | P9: ='Стекольщикова А. А.'!K13 -> 0.32865497 | Q9: ='Стекольщикова А. А.'!J13 -> 9 | R9: ='Стекольщикова А. А.'!M13 -> 1.5223538
A10: Кол-во смен план/отработано | D10: ='Центрум'!K14 -> 1 | E10: ='Центрум'!J14 -> 31 | G10: ='Свидовская С. А.'!K14 -> 1.8 | H10: ='Свидовская С. А.'!J14 -> 18 | J10: ='Корж А. А.'!K14 -> 1.0555556 | K10: ='Корж А. А.'!J14 -> 19 | M10: ='Козлова В. Э.'!K14 -> 1 | N10: ='Козлова В. Э.'!J14 -> 19 | P10: ='Стекольщикова А. А.'!K14 -> 0.5 | Q10: ='Стекольщикова А. А.'!J14 -> 5
A11: Средние продажи в смену | D11: ='Центрум'!K15 -> 0.74142872 | E11: ='Центрум'!J15 -> 45887.741 | F11: ='Центрум'!M15 -> 0.74142872 | G11: ='Свидовская С. А.'!K15 -> 0.48117414 | H11: ='Свидовская С. А.'!J15 -> 14890.167 | I11: ='Свидовская С. А.'!M15 -> 0.48117414 | J11: ='Корж А. А.'!K15 -> 0.85912545 | K11: ='Корж А. А.'!J15 -> 26586.053 | L11: ='Корж А. А.'!M15 -> 0.85912545 | M11: ='Козлова В. Э.'!K15 -> 0.44701868 | N11: ='Козлова В. Э.'!J15 -> 13833.209 | O11: ='Козлова В. Э.'!M15 -> 0.44701868 | P11: ='Стекольщикова А. А.'!K15 -> 0.28574767 | Q11: ='Стекольщикова А. А.'!J15 -> 17685.2 | R11: ='Стекольщикова А. А.'!M15 -> 0.28574767
A12: Отставание/Перевыполнение | D12: =Центрум!J16 -> -496100.02 | G12: ='Свидовская С. А.'!N8 -> -68255.594 | J12: ='Корж А. А.'!N8 -> -110684.23 | M12: ='Козлова В. Э.'!N8 -> -312634.58 | P12: ='Стекольщикова А. А.'!N8 -> 160942.26

Sheet Справочник магазинов
A1: МЕГА Белая Дача
A2: Гагаринский
A3: Марфино

Sheet План на день
A1: Выручка | D1: =86000 -> 86000
A2: Кол-во изделий | D2: =D1/D4 -> 13.030303
A3: Средний чек | D3: =D4*D5 -> 11220
A4: Средняя стоимость изделия | D4: =Центрум!I11 -> 6600
A5: Длина чека | D5: ='Центрум'!I12 -> 1.7
A6: Кол-во чеков | D6: =IF(D5<>0,D2/D5,"") -> 7.6648841
A7: Конверсия | D7: =Центрум!I20 -> 0.09

Sheet Сейтджелилова А.Э.
B1: =TODAY()-1 -> 46170
B2: (отчетная дата) | J2: ЕЖЕДНЕВНЫЙ ОТЧЕТ О ПРОДАЖАХ
B3: Осталось до выполнения плана!!! | J3: =График!B23 -> 0
C4: =I8-D49 -> -165233 | E4: =IF(I8<>0,C4/I8,0) -> 0
F6: Целевые показатели
F7: Показатель | I7: План | J7: Факт | K7: % выполнения | L7: Прогноз выполнения | M7: % выполнения по прогнозу | N7: Отклонение | O7: Факт аналогичного месяца прошлого года | P7: Отклонение LFL
F8: Выручка | I8: =Центрум!I8/График!AJ29*График!AJ23 -> 0 | J8: =D49 -> 165233 | K8: =IF(AND(I8<>"",I8<>0,J8<>""),J8/I8,"") | L8: =IF(SUMIF($D$25:$D$47,">=0",$U$25:$U$47)<>0,I8*D49/SUMIF($D$25:$D$47,">=0",$U$25:$U$47),0) -> 0 | M8: =L8/I8 -> #DIV/0! | N8: =IF(AND(J8<>0,J8<>"",I8<>0,I8<>""),L8-I8,"") | P8: =IF(AND(O8<>"",O8<>0,L8<>"",L8<>0),-O8+L8,"") | Q8: =IF(AND(P8<>"",P8<>0,O8<>0,O8<>""),P8/O8,"")
F9: Кол-во изделий | I9: =I8/I11 -> 0 | J9: =E49 -> 19 | K9: =IF(AND(I9<>"",I9<>0,J9<>""),J9/I9,"") | L9: =IF(SUMIF($E$25:$E$47,">=0",$V$25:$V$47)<>0,I9*E49/SUMIF($E$25:$E$47,">=0",$V$25:$V$47),0) -> 0 | M9: =IF(AND(I9<>"",I9<>0,L9<>"",L9<>0),L9/I9,"") | N9: =IF(AND(J9<>0,J9<>"",I9<>0,I9<>""),L9-I9,"") | O9: =O8/O11 -> #DIV/0! | P9: =IF(AND(O9<>"",O9<>0,L9<>"",L9<>0),-O9+L9,"") -> #DIV/0! | Q9: =IF(AND(P9<>"",P9<>0,O9<>0,O9<>""),P9/O9,"") -> #DIV/0!
F10: Средний чек | I10: =I11*I12 -> 11220 | J10: =H49 -> 23604.714 | K10: =IF(AND(I10<>"",I10<>0,J10<>""),J10/I10,"") -> 2.103807 | L10: =J10 -> 23604.714 | M10: =IF(AND(I10<>"",I10<>0,L10<>"",L10<>0),L10/I10,"") -> 2.103807 | N10: =IF(AND(J10<>0,J10<>"",I10<>0,I10<>""),L10-I10,"") -> 12384.714 | O10: =O11*O12 -> 0 | P10: =IF(AND(O10<>"",O10<>0,L10<>"",L10<>0),-O10+L10,"") | Q10: =IF(AND(P10<>"",P10<>0,O10<>0,O10<>""),P10/O10,"")
F11: Средняя стоимость изделия | I11: =Центрум!I11 -> 6600 | J11: =F49 -> 8696.4737 | K11: =IF(AND(I11<>"",I11<>0,J11<>""),J11/I11,"") -> 1.3176475 | L11: =J11 -> 8696.4737 | M11: =IF(AND(I11<>"",I11<>0,L11<>"",L11<>0),L11/I11,"") -> 1.3176475 | N11: =IF(AND(J11<>0,J11<>"",I11<>0,I11<>""),L11-I11,"") -> 2096.4737 | P11: =IF(AND(O11<>"",O11<>0,L11<>"",L11<>0),-O11+L11,"") | Q11: =IF(AND(P11<>"",P11<>0,O11<>0,O11<>""),P11/O11,"")
F12: Длина чека | I12: ='Центрум'!I12 -> 1.7 | J12: =J49 -> 2.7142857 | K12: =IF(AND(I12<>"",I12<>0,J12<>""),J12/I12,"") -> 1.5966387 | L12: =J12 -> 2.7142857 | M12: =IF(AND(I12<>"",I12<>0,L12<>"",L12<>0),L12/I12,"") -> 1.5966387 | N12: =IF(AND(J12<>0,J12<>"",I12<>0,I12<>""),L12-I12,"") -> 1.0142857 | P12: =IF(AND(O12<>"",O12<>0,L12<>"",L12<>0),-O12+L12,"") | Q12: =IF(AND(P12<>"",P12<>0,O12<>0,O12<>""),P12/O12,"")
F13: Кол-во чеков | I13: =IF(I12<>0,I9/I12,"") -> 0 | J13: =G49 -> 7 | K13: =IF(AND(I13<>"",I13<>0,J13<>""),J13/I13,"") | L13: =IF(SUMIF($G$25:$G$47,">=0",$W$25:$W$47)<>0,I13*G49/SUMIF($G$25:$G$47,">=0",$W$25:$W$47),"") | M13: =IF(AND(I13<>"",I13<>0,L13<>"",L13<>0),L13/I13,"") | N13: =IF(AND(J13<>0,J13<>"",I13<>0,I13<>""),L13-I13,"") | P13: =IF(AND(O13<>"",O13<>0,L13<>"",L13<>0),-O13+L13,"") | Q13: =IF(AND(P13<>"",P13<>0,O13<>0,O13<>""),P13/O13,"")
F14: Кол-во смен план/отработано | I14: =График!AI23 -> 0 | J14: 13 | K14: =IF(AND(I14<>"",I14<>0,J14<>""),J14/I14,"") | L14: =IF(SUMIF($D$25:$D$47,">=0",$U$25:$U$47),I49*I8/SUMIF($D$25:$D$47,">=0",$U$25:$U$47),"") | N14: =IF(AND(J14<>0,J14<>"",I14<>0,I14<>""),L14-I14,"") | P14: =IF(AND(O14<>"",O14<>0,L14<>"",L14<>0),-O14+L14,"") | Q14: =IF(AND(P14<>"",P14<>0,O14<>0,O14<>""),P14/O14,"")
F15: Средние продажи в смену | I15: =Центрум!I15/2 -> 30945.484 | J15: =J8/J14 -> 12710.231 | K15: =IF(AND(I15<>"",I15<>0,J15<>""),J15/I15,"") -> 0.41072975 | L15: =J15 -> 12710.231 | M15: =IF(AND(I15<>"",I15<>0,L15<>"",L15<>0),L15/I15,"") -> 0.41072975 | N15: =IF(AND(J15<>0,J15<>"",I15<>0,I15<>""),L15-I15,"") -> -18235.253 | P15: =IF(AND(O15<>"",O15<>0,L15<>"",L15<>0),-O15+L15,"") | Q15: =IF(AND(P15<>"",P15<>0,O15<>0,O15<>""),P15/O15,"")
F16: Отставание/Перевыполнение | J16: =J8-I15*J14 -> -237058.29 | K16: =IF(AND(I16<>"",I16<>0,J16<>""),J16/I16,"") | L16: =J16 -> -237058.29 | M16: =IF(AND(I16<>"",I16<>0,L16<>"",L16<>0),L16/I16,"") | N16: =IF(AND(J16<>0,J16<>"",I16<>0,I16<>""),L16-I16,"") | P16: =IF(AND(O16<>"",O16<>0,L16<>"",L16<>0),-O16+L16,"") | Q16: =IF(AND(P16<>"",P16<>0,O16<>0,O16<>""),P16/O16,"") | T16: Подарочные сертификаты
F17: Трафик | I17: =Центрум!I17/График!AJ29*График!AJ23 -> 0 | J17: =I49 -> 139.2 | K17: =IF(AND(I17<>"",I17<>0,J17<>""),J17/I17,"") | L17: =J17/J14*I14 -> 0 | M17: =IF(AND(I17<>"",I17<>0,L17<>"",L17<>0),L17/I17,"") | N17: =IF(AND(J17<>0,J17<>"",I17<>0,I17<>""),L17-I17,"") | P17: =IF(AND(O17<>"",O17<>0,L17<>"",L17<>0),-O17+L17,"") | Q17: =IF(AND(P17<>"",P17<>0,O17<>0,O17<>""),P17/O17,"")
K18: =IF(AND(I18<>"",I18<>0,J18<>""),J18/I18,"") | L18: =J18 -> 0 | M18: =IF(AND(I18<>"",I18<>0,L18<>"",L18<>0),L18/I18,"") | N18: =IF(AND(J18<>0,J18<>"",I18<>0,I18<>""),L18-I18,"") | O18: 0 | P18: =IF(AND(O18<>"",O18<>0,L18<>"",L18<>0),-O18+L18,"") | Q18: =IF(AND(P18<>"",P18<>0,O18<>0,O18<>""),P18/O18,"")
J19: =P49 -> 0 | K19: =IF(AND(I19<>"",I19<>0,J19<>""),J19/I19,"") | L19: =J19 -> 0 | M19: =IF(AND(I19<>"",I19<>0,L19<>"",L19<>0),L19/I19,"") | N19: =IF(AND(J19<>0,J19<>"",I19<>0,I19<>""),L19-I19,"") | O19: 0 | P19: =IF(AND(O19<>"",O19<>0,L19<>"",L19<>0),-O19+L19,"") | Q19: =IF(AND(P19<>"",P19<>0,O19<>0,O19<>""),P19/O19,"") | T19: =T18/I16 -> #DIV/0!
F20: Конверсия план/факт | I20: =Центрум!I20 -> 0.09 | J20: =S49 -> 0.050287356 | K20: =J20/I20 -> 0.5587484 | L20: =IF(AND(K8<>0,I14<>0,I49<>0),(I49*S49+(I49/K8-I49)*I20)/(I49/K8),0) -> 0 | M20: =IF(AND(I20<>"",I20<>0,L20<>"",L20<>0),L20/I20,"") | N20: =IF(AND(J20<>0,J20<>"",I20<>0,I20<>""),L20-I20,"") -> -0.09 | P20: =IF(AND(O20<>"",O20<>0,L20<>"",L20<>0),-O20+L20,"") | Q20: =IF(AND(P20<>"",P20<>0,O20<>0,O20<>""),P20/O20,"")
B22: Факт продаж за месяц | T22: % выполнения дневного плана | U22: Раcпределение плана по дням
B23: Дата | C23: День недели | D23: Выручка (руб) | E23: Кол-во единиц (шт.) | F23: Средняя стоимость изделия (руб.) | G23: Количество чеков (шт.) | H23: Средняя сумма чека (руб.) | I23: Трафик | J23: Длина чека (шт.) | K23: UNOde50 | L23: IS | M23: Agafi | N23: Kalliope | O23: Raganella | P23: CC/MP | Q23: Eva Rites | R23: Antura | S23: Конверсия (%) | U23: выручка, план | V23: кол-во ед, план | W23: Кол-во чеков, план | X23: выручка, скорректир.план | Y23: кол-во ед, скорр. план | Z23: кол-во чеков, скорр. план | AA23: Коэфф. Дня Недели | AB23: Специфика месяца
B24: 1 | C24: 2 | D24: 3 | E24: в | F24: 5 | G24: 6 | H24: 7 | I24: 8 | J24: 9 | K24: 10 | L24: 11 | M24: 12 | N24: 13 | O24: 14 | P24: 15 | Q24: 16 | R24: 17 | S24: 18 | U24: 1 | V24: 2 | W24: 3 | X24: 4 | Y24: 5 | Z24: 6 | AA24: 10 | AB24: 11
A25: 1 | B25: 46038 | C25: пт | D25: 0 | E25: 0 | F25: =IF(AND(E25<>"",E25<>0),D25/E25,"") | G25: 0 | H25: =IF(AND(G25<>"",G25<>0),D25/G25,"") | I25: 12 | J25: =IF(AND(G25<>"",G25<>0),E25/G25,"") | S25: =IF(AND(I25<>"",I25<>0),G25/I25,"") -> 0 | T25: =D25/U25 -> #DIV/0! | U25: =$I$8*AA25*AB25/SUMPRODUCT($AB$25:$AB$56,$AA$25:$AA$56) -> 0 | V25: =$I$9*AA25*AB25/SUMPRODUCT($AB$25:$AB$56,$AA$25:$AA$56) -> 0 | W25: =IF($I$12="","",V25/$I$12) -> 0 | X25: =IF(AB25<>"",IF(D25<>"",D25,($I$8-SUM($X24:X$25))*AA25*AB25/SUMPRODUCT($AB25:$AB$56,$AA25:$AA$56)),"") -> 0 | Y25: =IF(AB25<>"",IF(E25<>"",E25,($I$9-SUM($Y24:Y$25))*AA25*AB25/SUMPRODUCT($AB25:$AB$56,$AA25:$AA$56)),"") -> 0 | Z25: =IF(AB25<>"",IF($I$12<>"",IF(G25<>"",G25,($I$9/$I$12-SUM($Z24:Z$25))*AA25*AB25/SUMPRODUCT($AB25:$AB$56,$AA25:$AA$56)),""),"") -> 0 | AA25: 1 | AB25: 1
A26: 2 | B26: 46039 | C26: сб | D26: 15970 | E26: 2 | F26: =IF(AND(E26<>"",E26<>0),D26/E26,"") -> 7985 | G26: 1 | H26: =IF(AND(G26<>"",G26<>0),D26/G26,"") -> 15970 | I26: 19 | J26: =IF(AND(G26<>"",G26<>0),E26/G26,"") -> 2 | S26: =IF(AND(I26<>"",I26<>0),G26/I26,"") -> 0.052631579 | T26: =D26/U26 -> #DIV/0! | U26: =$I$8*AA26*AB26/SUMPRODUCT($AB$25:$AB$56,$AA$25:$AA$56) -> 0 | V26: =$I$9*AA26*AB26/SUMPRODUCT($AB$25:$AB$56,$AA$25:$AA$56) -> 0 | W26: =IF($I$12="","",V26/$I$12) -> 0 | X26: =IF(AB26<>"",IF(D26<>"",D26,($I$8-SUM($X25:X$25))*AA26*AB26/SUMPRODUCT($AB26:$AB$56,$AA26:$AA$56)),"") -> 15970 | Y26: =IF(AB26<>"",IF(E26<>"",E26,($I$9-SUM($Y25:Y$25))*AA26*AB26/SUMPRODUCT($AB26:$AB$56,$AA26:$AA$56)),"") -> 2 | Z26: =IF(AB26<>"",IF($I$12<>"",IF(G26<>"",G26,($I$9/$I$12-SUM($Z25:Z$25))*AA26*AB26/SUMPRODUCT($AB26:$AB$56,$AA26:$AA$56)),""),"") -> 1 | AA26: 1 | AB26: 1
A27: 3 | B27: 46040 | C27: вс | D27: 0 | E27: 0 | F27: =IF(AND(E27<>"",E27<>0),D27/E27,"") | G27: 0 | H27: =IF(AND(G27<>"",G27<>0),D27/G27,"") | I27: 24 | J27: =IF(AND(G27<>"",G27<>0),E27/G27,"") | S27: =IF(AND(I27<>"",I27<>0),G27/I27,"") -> 0 | T27: =D27/U27 -> #DIV/0! | U27: =$I$8*AA27*AB27/SUMPRODUCT($AB$25:$AB$56,$AA$25:$AA$56) -> 0 | V27: =$I$9*AA27*AB27/SUMPRODUCT($AB$25:$AB$56,$AA$25:$AA$56) -> 0 | W27: =IF($I$12="","",V27/$I$12) -> 0 | X27: =IF(AB27<>"",IF(D27<>"",D27,($I$8-SUM($X$25:X26))*AA27*AB27/SUMPRODUCT($AB27:$AB$56,$AA27:$AA$56)),"") -> 0 | Y27: =IF(AB27<>"",IF(E27<>"",E27,($I$9-SUM($Y$25:Y26))*AA27*AB27/SUMPRODUCT($AB27:$AB$56,$AA27:$AA$56)),"") -> 0 | Z27: =IF(AB27<>"",IF($I$12<>"",IF(G27<>"",G27,($I$9/$I$12-SUM($Z$25:Z26))*AA27*AB27/SUMPRODUCT($AB27:$AB$56,$AA27:$AA$56)),""),"") -> 0 | AA27: 1 | AB27: 1
A28: 4 | B28: 46042 | C28: вт | D28: 0 | E28: 0 | F28: =IF(AND(E28<>"",E28<>0),D28/E28,"") | G28: 0 | H28: =IF(AND(G28<>"",G28<>0),D28/G28,"") | I28: 16 | J28: =IF(AND(G28<>"",G28<>0),E28/G28,"") | S28: =IF(AND(I28<>"",I28<>0),G28/I28,"") -> 0 | T28: =D28/U28 -> #DIV/0! | U28: =$I$8*AA28*AB28/SUMPRODUCT($AB$25:$AB$56,$AA$25:$AA$56) -> 0 | V28: =$I$9*AA28*AB28/SUMPRODUCT($AB$25:$AB$56,$AA$25:$AA$56) -> 0 | W28: =IF($I$12="","",V28/$I$12) -> 0 | X28: =IF(AB28<>"",IF(D28<>"",D28,($I$8-SUM($X$25:X27))*AA28*AB28/SUMPRODUCT($AB28:$AB$56,$AA28:$AA$56)),"") -> 0 | Y28: =IF(AB28<>"",IF(E28<>"",E28,($I$9-SUM($Y$25:Y27))*AA28*AB28/SUMPRODUCT($AB28:$AB$56,$AA28:$AA$56)),"") -> 0 | Z28: =IF(AB28<>"",IF($I$12<>"",IF(G28<>"",G28,($I$9/$I$12-SUM($Z$25:Z27))*AA28*AB28/SUMPRODUCT($AB28:$AB$56,$AA28:$AA$56)),""),"") -> 0 | AA28: 1 | AB28: 1
A29: 5 | B29: 46043 | C29: ср | D29: 68258 | E29: 5 | F29: =IF(AND(E29<>"",E29<>0),D29/E29,"") -> 13651.6 | G29: 1 | H29: =IF(AND(G29<>"",G29<>0),D29/G29,"") -> 68258 | I29: 12 | J29: =IF(AND(G29<>"",G29<>0),E29/G29,"") -> 5 | M29: 31570 | O29: 36688 | S29: =IF(AND(I29<>"",I29<>0),G29/I29,"") -> 0.083333333 | T29: =D29/U29 -> #DIV/0! | U29: =$I$8*AA29*AB29/SUMPRODUCT($AB$25:$AB$56,$AA$25:$AA$56) -> 0 | V29: =$I$9*AA29*AB29/SUMPRODUCT($AB$25:$AB$56,$AA$25:$AA$56) -> 0 | W29: =IF($I$12="","",V29/$I$12) -> 0 | X29: =IF(AB29<>"",IF(D29<>"",D29,($I$8-SUM($X$25:X28))*AA29*AB29/SUMPRODUCT($AB29:$AB$56,$AA29:$AA$56)),"") -> 68258 | Y29: =IF(AB29<>"",IF(E29<>"",E29,($I$9-SUM($Y$25:Y28))*AA29*AB29/SUMPRODUCT($AB29:$AB$56,$AA29:$AA$56)),"") -> 5 | Z29: =IF(AB29<>"",IF($I$12<>"",IF(G29<>"",G29,($I$9/$I$12-SUM($Z$25:Z28))*AA29*AB29/SUMPRODUCT($AB29:$AB$56,$AA29:$AA$56)),""),"") -> 1 | AA29: 1 | AB29: 1
A30: 6 | B30: 46044 | C30: чт | D30: 0 | E30: 0 | F30: =IF(AND(E30<>"",E30<>0),D30/E30,"") | G30: 0 | H30: =IF(AND(G30<>"",G30<>0),D30/G30,"") | I30: 18 | J30: =IF(AND(G30<>"",G30<>0),E30/G30,"") | S30: =IF(AND(I30<>"",I30<>0),G30/I30,"") -> 0 | T30: =D30/U30 -> #DIV/0! | U30: =$I$8*AA30*AB30/SUMPRODUCT($AB$25:$AB$56,$AA$25:$AA$56) -> 0 | V30: =$I$9*AA30*AB30/SUMPRODUCT($AB$25:$AB$56,$AA$25:$AA$56) -> 0 | W30: =IF($I$12="","",V30/$I$12) -> 0 | X30: =IF(AB30<>"",IF(D30<>"",D30,($I$8-SUM($X$25:X29))*AA30*AB30/SUMPRODUCT($AB30:$AB$56,$AA30:$AA$56)),"") -> 0 | Y30: =IF(AB30<>"",IF(E30<>"",E30,($I$9-SUM($Y$25:Y29))*AA30*AB30/SUMPRODUCT($AB30:$AB$56,$AA30:$AA$56)),"") -> 0 | Z30: =IF(AB30<>"",IF($I$12<>"",IF(G30<>"",G30,($I$9/$I$12-SUM($Z$25:Z29))*AA30*AB30/SUMPRODUCT($AB30:$AB$56,$AA30:$AA$56)),""),"") -> 0 | AA30: 1 | AB30: 1
A31: 7 | B31: 46045 | C31: пт | D31: =19277+3951 -> 23228 | E31: 4 | F31: =IF(AND(E31<>"",E31<>0),D31/E31,"") -> 5807 | G31: 2 | H31: =IF(AND(G31<>"",G31<>0),D31/G31,"") -> 11614 | I31: 19 | J31: =IF(AND(G31<>"",G31<>0),E31/G31,"") -> 2 | S31: =IF(AND(I31<>"",I31<>0),G31/I31,"") -> 0.10526316 | T31: =D31/U31 -> #DIV/0! | U31: =$I$8*AA31*AB31/SUMPRODUCT($AB$25:$AB$56,$AA$25:$AA$56) -> 0 | V31: =$I$9*AA31*AB31/SUMPRODUCT($AB$25:$AB$56,$AA$25:$AA$56) -> 0 | W31: =IF($I$12="","",V31/$I$12) -> 0 | X31: =IF(AB31<>"",IF(D31<>"",D31,($I$8-SUM($X$25:X30))*AA31*AB31/SUMPRODUCT($AB31:$AB$56,$AA31:$AA$56)),"") -> 23228 | Y31: =IF(AB31<>"",IF(E31<>"",E31,($I$9-SUM($Y$25:Y30))*AA31*AB31/SUMPRODUCT($AB31:$AB$56,$AA31:$AA$56)),"") -> 4 | Z31: =IF(AB31<>"",IF($I$12<>"",IF(G31<>"",G31,($I$9/$I$12-SUM($Z$25:Z30))*AA31*AB31/SUMPRODUCT($AB31:$AB$56,$AA31:$AA$56)),""),"") -> 2 | AA31: 1 | AB31: 1
A32: 8 | B32: 46046 | C32: сб | D32: 16272 | E32: 3 | F32: =IF(AND(E32<>"",E32<>0),D32/E32,"") -> 5424 | G32: 1 | H32: =IF(AND(G32<>"",G32<>0),D32/G32,"") -> 16272 | I32: 27 | J32: =IF(AND(G32<>"",G32<>0),E32/G32,"") -> 3 | S32: =IF(AND(I32<>"",I32<>0),G32/I32,"") -> 0.037037037 | T32: =D32/U32 -> #DIV/0! | U32: =$I$8*AA32*AB32/SUMPRODUCT($AB$25:$AB$56,$AA$25:$AA$56) -> 0 | V32: =$I$9*AA32*AB32/SUMPRODUCT($AB$25:$AB$56,$AA$25:$AA$56) -> 0 | W32: =IF($I$12="","",V32/$I$12) -> 0 | X32: =IF(AB32<>"",IF(D32<>"",D32,($I$8-SUM($X$25:X31))*AA32*AB32/SUMPRODUCT($AB32:$AB$56,$AA32:$AA$56)),"") -> 16272 | Y32: =IF(AB32<>"",IF(E32<>"",E32,($I$9-SUM($Y$25:Y31))*AA32*AB32/SUMPRODUCT($AB32:$AB$56,$AA32:$AA$56)),"") -> 3 | Z32: =IF(AB32<>"",IF($I$12<>"",IF(G32<>"",G32,($I$9/$I$12-SUM($Z$25:Z31))*AA32*AB32/SUMPRODUCT($AB32:$AB$56,$AA32:$AA$56)),""),"") -> 1 | AA32: 1 | AB32: 1
A33: 9 | B33: 46049 | C33: вт | D33: 28856 | E33: 2 | F33: =IF(AND(E33<>"",E33<>0),D33/E33,"") -> 14428 | G33: 1 | H33: =IF(AND(G33<>"",G33<>0),D33/G33,"") -> 28856 | J33: =IF(AND(G33<>"",G33<>0),E33/G33,"") -> 2 | S33: =IF(AND(I33<>"",I33<>0),G33/I33,"") | T33: =D33/U33 -> #DIV/0! | U33: =$I$8*AA33*AB33/SUMPRODUCT($AB$25:$AB$56,$AA$25:$AA$56) -> 0 | V33: =$I$9*AA33*AB33/SUMPRODUCT($AB$25:$AB$56,$AA$25:$AA$56) -> 0 | W33: =IF($I$12="","",V33/$I$12) -> 0 | X33: =IF(AB33<>"",IF(D33<>"",D33,($I$8-SUM($X$25:X32))*AA33*AB33/SUMPRODUCT($AB33:$AB$56,$AA33:$AA$56)),"") -> 28856 | Y33: =IF(AB33<>"",IF(E33<>"",E33,($I$9-SUM($Y$25:Y32))*AA33*AB33/SUMPRODUCT($AB33:$AB$56,$AA33:$AA$56)),"") -> 2 | Z33: =IF(AB33<>"",IF($I$12<>"",IF(G33<>"",G33,($I$9/$I$12-SUM($Z$25:Z32))*AA33*AB33/SUMPRODUCT($AB33:$AB$56,$AA33:$AA$56)),""),"") -> 1 | AA33: 1 | AB33: 1
A34: 10 | B34: 46050 | C34: ср | D34: =22501-28856 -> -6355 | E34: 3 | F34: =IF(AND(E34<>"",E34<>0),D34/E34,"") -> -2118.3333 | G34: 1 | H34: =IF(AND(G34<>"",G34<>0),D34/G34,"") -> -6355 | I34: 27 | J34: =IF(AND(G34<>"",G34<>0),E34/G34,"") -> 3 | S34: =IF(AND(I34<>"",I34<>0),G34/I34,"") -> 0.037037037 | T34: =D34/U34 -> #DIV/0! | U34: =$I$8*AA34*AB34/SUMPRODUCT($AB$25:$AB$56,$AA$25:$AA$56) -> 0 | V34: =$I$9*AA34*AB34/SUMPRODUCT($AB$25:$AB$56,$AA$25:$AA$56) -> 0 | W34: =IF($I$12="","",V34/$I$12) -> 0 | X34: =IF(AB34<>"",IF(D34<>"",D34,($I$8-SUM($X$25:X33))*AA34*AB34/SUMPRODUCT($AB34:$AB$56,$AA34:$AA$56)),"") -> -6355 | Y34: =IF(AB34<>"",IF(E34<>"",E34,($I$9-SUM($Y$25:Y33))*AA34*AB34/SUMPRODUCT($AB34:$AB$56,$AA34:$AA$56)),"") -> 3 | Z34: =IF(AB34<>"",IF($I$12<>"",IF(G34<>"",G34,($I$9/$I$12-SUM($Z$25:Z33))*AA34*AB34/SUMPRODUCT($AB34:$AB$56,$AA34:$AA$56)),""),"") -> 1 | AA34: 1 | AB34: 1
A35: 11 | B35: 29.янв. | C35: чт | F35: =IF(AND(E35<>"",E35<>0),D35/E35,"") | H35: =IF(AND(G35<>"",G35<>0),D35/G35,"") | J35: =IF(AND(G35<>"",G35<>0),E35/G35,"") | S35: =IF(AND(I35<>"",I35<>0),G35/I35,"") | T35: =D35/U35 -> #DIV/0! | U35: =$I$8*AA35*AB35/SUMPRODUCT($AB$25:$AB$56,$AA$25:$AA$56) -> 0 | V35: =$I$9*AA35*AB35/SUMPRODUCT($AB$25:$AB$56,$AA$25:$AA$56) -> 0 | W35: =IF($I$12="","",V35/$I$12) -> 0 | X35: =IF(AB35<>"",IF(D35<>"",D35,($I$8-SUM($X$25:X34))*AA35*AB35/SUMPRODUCT($AB35:$AB$56,$AA35:$AA$56)),"") -> -73114.5 | Y35: =IF(AB35<>"",IF(E35<>"",E35,($I$9-SUM($Y$25:Y34))*AA35*AB35/SUMPRODUCT($AB35:$AB$56,$AA35:$AA$56)),"") -> -9.5 | Z35: =IF(AB35<>"",IF($I$12<>"",IF(G35<>"",G35,($I$9/$I$12-SUM($Z$25:Z34))*AA35*AB35/SUMPRODUCT($AB35:$AB$56,$AA35:$AA$56)),""),"") -> -3.5 | AA35: 1 | AB35: 1
A36: 12 | B36: 46052 | C36: пт | F36: =IF(AND(E36<>"",E36<>0),D36/E36,"") | H36: =IF(AND(G36<>"",G36<>0),D36/G36,"") | J36: =IF(AND(G36<>"",G36<>0),E36/G36,"") | S36: =IF(AND(I36<>"",I36<>0),G36/I36,"") | T36: =D36/U36 -> #DIV/0! | U36: =$I$8*AA36*AB36/SUMPRODUCT($AB$25:$AB$56,$AA$25:$AA$56) -> 0 | V36: =$I$9*AA36*AB36/SUMPRODUCT($AB$25:$AB$56,$AA$25:$AA$56) -> 0 | W36: =IF($I$12="","",V36/$I$12) -> 0 | X36: =IF(AB36<>"",IF(D36<>"",D36,($I$8-SUM($X$25:X35))*AA36*AB36/SUMPRODUCT($AB36:$AB$56,$AA36:$AA$56)),"") -> -73114.5 | Y36: =IF(AB36<>"",IF(E36<>"",E36,($I$9-SUM($Y$25:Y35))*AA36*AB36/SUMPRODUCT($AB36:$AB$56,$AA36:$AA$56)),"") -> -9.5 | Z36: =IF(AB36<>"",IF($I$12<>"",IF(G36<>"",G36,($I$9/$I$12-SUM($Z$25:Z35))*AA36*AB36/SUMPRODUCT($AB36:$AB$56,$AA36:$AA$56)),""),"") -> -3.5 | AA36: 1 | AB36: 1
A37: 13 | B37: 46053 | C37: сб | D37: 19004 | F37: =IF(AND(E37<>"",E37<>0),D37/E37,"") | H37: =IF(AND(G37<>"",G37<>0),D37/G37,"") | J37: =IF(AND(G37<>"",G37<>0),E37/G37,"") | L37: 220 | M37: 10892 | S37: =IF(AND(I37<>"",I37<>0),G37/I37,"") | T37: =D37/U37 -> #DIV/0! | U37: =$I$8*AA37*AB37/SUMPRODUCT($AB$25:$AB$56,$AA$25:$AA$56) -> 0 | V37: =$I$9*AA37*AB37/SUMPRODUCT($AB$25:$AB$56,$AA$25:$AA$56) -> 0 | W37: =IF($I$12="","",V37/$I$12) -> 0 | X37: =IF(AB37<>"",IF(D37<>"",D37,($I$8-SUM($X$25:X36))*AA37*AB37/SUMPRODUCT($AB37:$AB$56,$AA37:$AA$56)),"") | Y37: =IF(AB37<>"",IF(E37<>"",E37,($I$9-SUM($Y$25:Y36))*AA37*AB37/SUMPRODUCT($AB37:$AB$56,$AA37:$AA$56)),"") | Z37: =IF(AB37<>"",IF($I$12<>"",IF(G37<>"",G37,($I$9/$I$12-SUM($Z$25:Z36))*AA37*AB37/SUMPRODUCT($AB37:$AB$56,$AA37:$AA$56)),""),"")
F38: =IF(AND(E38<>"",E38<>0),D38/E38,"") | H38: =IF(AND(G38<>"",G38<>0),D38/G38,"") | J38: =IF(AND(G38<>"",G38<>0),E38/G38,"") | S38: =IF(AND(I38<>"",I38<>0),G38/I38,"") | T38: =D38/U38 -> #DIV/0! | U38: =$I$8*AA38*AB38/SUMPRODUCT($AB$25:$AB$46,$AA$25:$AA$46) -> 0 | V38: =$I$9*AA38*AB38/SUMPRODUCT($AB$25:$AB$46,$AA$25:$AA$46) -> 0 | W38: =IF($I$12="","",V38/$I$12) -> 0 | X38: =IF(AB38<>"",IF(D38<>"",D38,($I$8-SUM($X$25:X37))*AA38*AB38/SUMPRODUCT($AB38:$AB$56,$AA38:$AA$56)),"") | Y38: =IF(AB38<>"",IF(E38<>"",E38,($I$9-SUM($Y$25:Y37))*AA38*AB38/SUMPRODUCT($AB38:$AB$56,$AA38:$AA$56)),"") | Z38: =IF(AB38<>"",IF($I$12<>"",IF(G38<>"",G38,($I$9/$I$12-SUM($Z$25:Z37))*AA38*AB38/SUMPRODUCT($AB38:$AB$56,$AA38:$AA$56)),""),"")
F39: =IF(AND(E39<>"",E39<>0),D39/E39,"") | H39: =IF(AND(G39<>"",G39<>0),D39/G39,"") | J39: =IF(AND(G39<>"",G39<>0),E39/G39,"") | S39: =IF(AND(I39<>"",I39<>0),G39/I39,"") | T39: =D39/U39 -> #DIV/0! | U39: =$I$8*AA39*AB39/SUMPRODUCT($AB$25:$AB$46,$AA$25:$AA$46) -> 0 | V39: =$I$9*AA39*AB39/SUMPRODUCT($AB$25:$AB$46,$AA$25:$AA$46) -> 0 | W39: =IF($I$12="","",V39/$I$12) -> 0 | X39: =IF(AB39<>"",IF(D39<>"",D39,($I$8-SUM($X$25:X38))*AA39*AB39/SUMPRODUCT($AB39:$AB$56,$AA39:$AA$56)),"") | Y39: =IF(AB39<>"",IF(E39<>"",E39,($I$9-SUM($Y$25:Y38))*AA39*AB39/SUMPRODUCT($AB39:$AB$56,$AA39:$AA$56)),"") | Z39: =IF(AB39<>"",IF($I$12<>"",IF(G39<>"",G39,($I$9/$I$12-SUM($Z$25:Z38))*AA39*AB39/SUMPRODUCT($AB39:$AB$56,$AA39:$AA$56)),""),"")
F40: =IF(AND(E40<>"",E40<>0),D40/E40,"") | H40: =IF(AND(G40<>"",G40<>0),D40/G40,"") | J40: =IF(AND(G40<>"",G40<>0),E40/G40,"") | S40: =IF(AND(I40<>"",I40<>0),G40/I40,"") | T40: =D40/U40 -> #DIV/0! | U40: =$I$8*AA40*AB40/SUMPRODUCT($AB$25:$AB$46,$AA$25:$AA$46) -> 0 | V40: =$I$9*AA40*AB40/SUMPRODUCT($AB$25:$AB$46,$AA$25:$AA$46) -> 0 | W40: =IF($I$12="","",V40/$I$12) -> 0 | X40: =IF(AB40<>"",IF(D40<>"",D40,($I$8-SUM($X$25:X39))*AA40*AB40/SUMPRODUCT($AB40:$AB$56,$AA40:$AA$56)),"") | Y40: =IF(AB40<>"",IF(E40<>"",E40,($I$9-SUM($Y$25:Y39))*AA40*AB40/SUMPRODUCT($AB40:$AB$56,$AA40:$AA$56)),"") | Z40: =IF(AB40<>"",IF($I$12<>"",IF(G40<>"",G40,($I$9/$I$12-SUM($Z$25:Z39))*AA40*AB40/SUMPRODUCT($AB40:$AB$56,$AA40:$AA$56)),""),"")
F41: =IF(AND(E41<>"",E41<>0),D41/E41,"") | H41: =IF(AND(G41<>"",G41<>0),D41/G41,"") | J41: =IF(AND(G41<>"",G41<>0),E41/G41,"") | S41: =IF(AND(I41<>"",I41<>0),G41/I41,"") | T41: =D41/U41 -> #DIV/0! | U41: =$I$8*AA41*AB41/SUMPRODUCT($AB$25:$AB$46,$AA$25:$AA$46) -> 0 | V41: =$I$9*AA41*AB41/SUMPRODUCT($AB$25:$AB$46,$AA$25:$AA$46) -> 0 | W41: =IF($I$12="","",V41/$I$12) -> 0 | X41: =IF(AB41<>"",IF(D41<>"",D41,($I$8-SUM($X$25:X40))*AA41*AB41/SUMPRODUCT($AB41:$AB$56,$AA41:$AA$56)),"") | Y41: =IF(AB41<>"",IF(E41<>"",E41,($I$9-SUM($Y$25:Y40))*AA41*AB41/SUMPRODUCT($AB41:$AB$56,$AA41:$AA$56)),"") | Z41: =IF(AB41<>"",IF($I$12<>"",IF(G41<>"",G41,($I$9/$I$12-SUM($Z$25:Z40))*AA41*AB41/SUMPRODUCT($AB41:$AB$56,$AA41:$AA$56)),""),"")
F42: =IF(AND(E42<>"",E42<>0),D42/E42,"") | H42: =IF(AND(G42<>"",G42<>0),D42/G42,"") | J42: =IF(AND(G42<>"",G42<>0),E42/G42,"") | S42: =IF(AND(I42<>"",I42<>0),G42/I42,"") | T42: =D42/U42 -> #DIV/0! | U42: =$I$8*AA42*AB42/SUMPRODUCT($AB$25:$AB$46,$AA$25:$AA$46) -> 0 | V42: =$I$9*AA42*AB42/SUMPRODUCT($AB$25:$AB$46,$AA$25:$AA$46) -> 0 | W42: =IF($I$12="","",V42/$I$12) -> 0 | X42: =IF(AB42<>"",IF(D42<>"",D42,($I$8-SUM($X$25:X41))*AA42*AB42/SUMPRODUCT($AB42:$AB$56,$AA42:$AA$56)),"") | Y42: =IF(AB42<>"",IF(E42<>"",E42,($I$9-SUM($Y$25:Y41))*AA42*AB42/SUMPRODUCT($AB42:$AB$56,$AA42:$AA$56)),"") | Z42: =IF(AB42<>"",IF($I$12<>"",IF(G42<>"",G42,($I$9/$I$12-SUM($Z$25:Z41))*AA42*AB42/SUMPRODUCT($AB42:$AB$56,$AA42:$AA$56)),""),"")
F43: =IF(AND(E43<>"",E43<>0),D43/E43,"") | H43: =IF(AND(G43<>"",G43<>0),D43/G43,"") | J43: =IF(AND(G43<>"",G43<>0),E43/G43,"") | S43: =IF(AND(I43<>"",I43<>0),G43/I43,"") | T43: =D43/U43 -> #DIV/0! | U43: =$I$8*AA43*AB43/SUMPRODUCT($AB$25:$AB$46,$AA$25:$AA$46) -> 0 | V43: =$I$9*AA43*AB43/SUMPRODUCT($AB$25:$AB$46,$AA$25:$AA$46) -> 0 | W43: =IF($I$12="","",V43/$I$12) -> 0 | X43: =IF(AB43<>"",IF(D43<>"",D43,($I$8-SUM($X$25:X42))*AA43*AB43/SUMPRODUCT($AB43:$AB$56,$AA43:$AA$56)),"") | Y43: =IF(AB43<>"",IF(E43<>"",E43,($I$9-SUM($Y$25:Y42))*AA43*AB43/SUMPRODUCT($AB43:$AB$56,$AA43:$AA$56)),"") | Z43: =IF(AB43<>"",IF($I$12<>"",IF(G43<>"",G43,($I$9/$I$12-SUM($Z$25:Z42))*AA43*AB43/SUMPRODUCT($AB43:$AB$56,$AA43:$AA$56)),""),"")
F44: =IF(AND(E44<>"",E44<>0),D44/E44,"") | H44: =IF(AND(G44<>"",G44<>0),D44/G44,"") | J44: =IF(AND(G44<>"",G44<>0),E44/G44,"") | S44: =IF(AND(I44<>"",I44<>0),G44/I44,"") | T44: =D44/U44 -> #DIV/0! | U44: =$I$8*AA44*AB44/SUMPRODUCT($AB$25:$AB$46,$AA$25:$AA$46) -> 0 | V44: =$I$9*AA44*AB44/SUMPRODUCT($AB$25:$AB$46,$AA$25:$AA$46) -> 0 | W44: =IF($I$12="","",V44/$I$12) -> 0 | X44: =IF(AB44<>"",IF(D44<>"",D44,($I$8-SUM($X$25:X43))*AA44*AB44/SUMPRODUCT($AB44:$AB$56,$AA44:$AA$56)),"") | Y44: =IF(AB44<>"",IF(E44<>"",E44,($I$9-SUM($Y$25:Y43))*AA44*AB44/SUMPRODUCT($AB44:$AB$56,$AA44:$AA$56)),"") | Z44: =IF(AB44<>"",IF($I$12<>"",IF(G44<>"",G44,($I$9/$I$12-SUM($Z$25:Z43))*AA44*AB44/SUMPRODUCT($AB44:$AB$56,$AA44:$AA$56)),""),"")
F45: =IF(AND(E45<>"",E45<>0),D45/E45,"") | H45: =IF(AND(G45<>"",G45<>0),D45/G45,"") | J45: =IF(AND(G45<>"",G45<>0),E45/G45,"") | S45: =IF(AND(I45<>"",I45<>0),G45/I45,"") | T45: =D45/U45 -> #DIV/0! | U45: =$I$8*AA45*AB45/SUMPRODUCT($AB$25:$AB$46,$AA$25:$AA$46) -> 0 | V45: =$I$9*AA45*AB45/SUMPRODUCT($AB$25:$AB$46,$AA$25:$AA$46) -> 0 | W45: =IF($I$12="","",V45/$I$12) -> 0 | X45: =IF(AB45<>"",IF(D45<>"",D45,($I$8-SUM($X$25:X44))*AA45*AB45/SUMPRODUCT($AB45:$AB$56,$AA45:$AA$56)),"") | Y45: =IF(AB45<>"",IF(E45<>"",E45,($I$9-SUM($Y$25:Y44))*AA45*AB45/SUMPRODUCT($AB45:$AB$56,$AA45:$AA$56)),"") | Z45: =IF(AB45<>"",IF($I$12<>"",IF(G45<>"",G45,($I$9/$I$12-SUM($Z$25:Z44))*AA45*AB45/SUMPRODUCT($AB45:$AB$56,$AA45:$AA$56)),""),"")
F46: =IF(AND(E46<>"",E46<>0),D46/E46,"") | H46: =IF(AND(G46<>"",G46<>0),D46/G46,"") | J46: =IF(AND(G46<>"",G46<>0),E46/G46,"") | S46: =IF(AND(I46<>"",I46<>0),G46/I46,"") | T46: =D46/U46 -> #DIV/0! | U46: =$I$8*AA46*AB46/SUMPRODUCT($AB$25:$AB$46,$AA$25:$AA$46) -> 0 | V46: =$I$9*AA46*AB46/SUMPRODUCT($AB$25:$AB$46,$AA$25:$AA$46) -> 0 | W46: =IF($I$12="","",V46/$I$12) -> 0 | X46: =IF(AB46<>"",IF(D46<>"",D46,($I$8-SUM($X$25:X45))*AA46*AB46/SUMPRODUCT($AB46:$AB$56,$AA46:$AA$56)),"") | Y46: =IF(AB46<>"",IF(E46<>"",E46,($I$9-SUM($Y$25:Y45))*AA46*AB46/SUMPRODUCT($AB46:$AB$56,$AA46:$AA$56)),"") | Z46: =IF(AB46<>"",IF($I$12<>"",IF(G46<>"",G46,($I$9/$I$12-SUM($Z$25:Z45))*AA46*AB46/SUMPRODUCT($AB46:$AB$56,$AA46:$AA$56)),""),"")
F47: =IF(AND(E47<>"",E47<>0),D47/E47,"") | H47: =IF(AND(G47<>"",G47<>0),D47/G47,"") | J47: =IF(AND(G47<>"",G47<>0),E47/G47,"") | S47: =IF(AND(I47<>"",I47<>0),G47/I47,"") | T47: =D47/U47 -> #DIV/0! | U47: =$I$8*AA47*AB47/SUMPRODUCT($AB$25:$AB$46,$AA$25:$AA$46) -> 0 | V47: =$I$9*AA47*AB47/SUMPRODUCT($AB$25:$AB$46,$AA$25:$AA$46) -> 0 | W47: =IF($I$12="","",V47/$I$12) -> 0 | X47: =IF(AB47<>"",IF(D47<>"",D47,($I$8-SUM($X$25:X46))*AA47*AB47/SUMPRODUCT($AB47:$AB$56,$AA47:$AA$56)),"") | Y47: =IF(AB47<>"",IF(E47<>"",E47,($I$9-SUM($Y$25:Y46))*AA47*AB47/SUMPRODUCT($AB47:$AB$56,$AA47:$AA$56)),"") | Z47: =IF(AB47<>"",IF($I$12<>"",IF(G47<>"",G47,($I$9/$I$12-SUM($Z$25:Z46))*AA47*AB47/SUMPRODUCT($AB47:$AB$56,$AA47:$AA$56)),""),"")
F48: =IF(AND(E48<>"",E48<>0),D48/E48,"") | H48: =IF(AND(G48<>"",G48<>0),D48/G48,"") | J48: =IF(AND(G48<>"",G48<>0),E48/G48,"") | S48: =IF(AND(I48<>"",I48<>0),G48/I48,"") | T48: =D48/U48 -> #DIV/0! | U48: =$I$8*AA48*AB48/SUMPRODUCT($AB$25:$AB$46,$AA$25:$AA$46) -> 0 | V48: =$I$9*AA48*AB48/SUMPRODUCT($AB$25:$AB$46,$AA$25:$AA$46) -> 0 | W48: =IF($I$12="","",V48/$I$12) -> 0 | X48: =IF(AB48<>"",IF(D48<>"",D48,($I$8-SUM($X$25:X47))*AA48*AB48/SUMPRODUCT($AB48:$AB$56,$AA48:$AA$56)),"") | Y48: =IF(AB48<>"",IF(E48<>"",E48,($I$9-SUM($Y$25:Y47))*AA48*AB48/SUMPRODUCT($AB48:$AB$56,$AA48:$AA$56)),"") | Z48: =IF(AB48<>"",IF($I$12<>"",IF(G48<>"",G48,($I$9/$I$12-SUM($Z$25:Z47))*AA48*AB48/SUMPRODUCT($AB48:$AB$56,$AA48:$AA$56)),""),"")
B49: итого | D49: =SUM(D25:D47) -> 165233 | E49: =SUM(E25:E47) -> 19 | F49: =IF(AND(E49<>"",E49<>0),D49/E49,"") -> 8696.4737 | G49: =SUM(G25:G47) -> 7 | H49: =IF(AND(G49<>"",G49<>0),D49/G49,"") -> 23604.714 | I49: =SUM(I25:I47)*0.8 -> 139.2 | J49: =IF(AND(G49<>"",G49<>0),E49/G49,"") -> 2.7142857 | K49: =SUM(K25:K48) -> 0 | L49: =SUM(L25:L48) -> 220 | M49: =SUM(M25:M48) -> 42462 | N49: =SUM(N25:N48) -> 0 | O49: =SUM(O25:O48) -> 36688 | P49: =SUM(P25:P48) -> 0 | Q49: =SUM(Q25:Q48) -> 0 | R49: =SUM(R25:R48) -> 0 | S49: =IF(AND(I49<>"",I49<>0),G49/I49,"") -> 0.050287356 | T49: =D49/U49 -> #DIV/0! | U49: =SUM(U25:U47) -> 0 | V49: =SUM(V25:V47) -> 0 | W49: =SUM(W25:W47) -> 0 | X49: =SUM(X25:X47) -> 0 | Y49: =SUM(Y25:Y47) -> 0 | Z49: =SUM(Z25:Z47) -> 0
D50: =SUMIF(D25:D47,"",U25:U47)+D49 -> 165233

Sheet Козлова В. Э.
B1: =TODAY()-1 -> 46170
B2: (отчетная дата) | J2: ЕЖЕДНЕВНЫЙ ОТЧЕТ О ПРОДАЖАХ
B3: Осталось до выполнения плана!!! | J3: =График!B26 -> Козлова Валерия
C4: =I8-D49 -> 361915.39 | E4: =IF(I8<>0,C4/I8,0) -> 0.57929971
F6: Целевые показатели
F7: Показатель | I7: План | J7: Факт | K7: % выполнения | L7: Прогноз выполнения | M7: % выполнения по прогнозу | N7: Отклонение | O7: Факт аналогичного месяца прошлого года | P7: Отклонение LFL
F8: Выручка | I8: =Центрум!I8/График!AJ29*График!AJ26 -> 624746.37 | J8: =D49 -> 262830.98 | K8: =IF(AND(I8<>"",I8<>0,J8<>""),J8/I8,"") -> 0.42070029 | L8: =IF(SUMIF($D$25:$D$47,">=0",$U$25:$U$47)<>0,I8*D49/SUMIF($D$25:$D$47,">=0",$U$25:$U$47),0) -> 312111.79 | M8: =L8/I8 -> 0.4995816 | N8: =IF(AND(J8<>0,J8<>"",I8<>0,I8<>""),L8-I8,"") -> -312634.58 | P8: =IF(AND(O8<>"",O8<>0,L8<>"",L8<>0),-O8+L8,"") | Q8: =IF(AND(P8<>"",P8<>0,O8<>0,O8<>""),P8/O8,"")
F9: Кол-во изделий | I9: =I8/I11 -> 94.658541 | J9: =E49 -> 45 | K9: =IF(AND(I9<>"",I9<>0,J9<>""),J9/I9,"") -> 0.47539292 | L9: =IF(SUMIF($E$25:$E$47,">=0",$V$25:$V$47)<>0,I9*E49/SUMIF($E$25:$E$47,">=0",$V$25:$V$47),0) -> 53.4375 | M9: =IF(AND(I9<>"",I9<>0,L9<>"",L9<>0),L9/I9,"") -> 0.56452909 | N9: =IF(AND(J9<>0,J9<>"",I9<>0,I9<>""),L9-I9,"") -> -41.221041 | O9: =O8/O11 -> #DIV/0! | P9: =IF(AND(O9<>"",O9<>0,L9<>"",L9<>0),-O9+L9,"") -> #DIV/0! | Q9: =IF(AND(P9<>"",P9<>0,O9<>0,O9<>""),P9/O9,"") -> #DIV/0!
F10: Средний чек | I10: =I11*I12 -> 11220 | J10: =H49 -> 10108.884 | K10: =IF(AND(I10<>"",I10<>0,J10<>""),J10/I10,"") -> 0.90097004 | L10: =J10 -> 10108.884 | M10: =IF(AND(I10<>"",I10<>0,L10<>"",L10<>0),L10/I10,"") -> 0.90097004 | N10: =IF(AND(J10<>0,J10<>"",I10<>0,I10<>""),L10-I10,"") -> -1111.1162 | O10: =O11*O12 -> 0 | P10: =IF(AND(O10<>"",O10<>0,L10<>"",L10<>0),-O10+L10,"") | Q10: =IF(AND(P10<>"",P10<>0,O10<>0,O10<>""),P10/O10,"")
F11: Средняя стоимость изделия | I11: =Центрум!I11 -> 6600 | J11: =F49 -> 5840.6884 | K11: =IF(AND(I11<>"",I11<>0,J11<>""),J11/I11,"") -> 0.88495279 | L11: =J11 -> 5840.6884 | M11: =IF(AND(I11<>"",I11<>0,L11<>"",L11<>0),L11/I11,"") -> 0.88495279 | N11: =IF(AND(J11<>0,J11<>"",I11<>0,I11<>""),L11-I11,"") -> -759.31156 | P11: =IF(AND(O11<>"",O11<>0,L11<>"",L11<>0),-O11+L11,"") | Q11: =IF(AND(P11<>"",P11<>0,O11<>0,O11<>""),P11/O11,"")
F12: Длина чека | I12: ='Центрум'!I12 -> 1.7 | J12: =J49 -> 1.7307692 | K12: =IF(AND(I12<>"",I12<>0,J12<>""),J12/I12,"") -> 1.0180995 | L12: =J12 -> 1.7307692 | M12: =IF(AND(I12<>"",I12<>0,L12<>"",L12<>0),L12/I12,"") -> 1.0180995 | N12: =IF(AND(J12<>0,J12<>"",I12<>0,I12<>""),L12-I12,"") -> 0.030769231 | P12: =IF(AND(O12<>"",O12<>0,L12<>"",L12<>0),-O12+L12,"") | Q12: =IF(AND(P12<>"",P12<>0,O12<>0,O12<>""),P12/O12,"")
F13: Кол-во чеков | I13: =IF(I12<>0,I9/I12,"") -> 55.681495 | J13: =G49 -> 26 | K13: =IF(AND(I13<>"",I13<>0,J13<>""),J13/I13,"") -> 0.46694149 | L13: =IF(SUMIF($G$25:$G$47,">=0",$W$25:$W$47)<>0,I13*G49/SUMIF($G$25:$G$47,">=0",$W$25:$W$47),"") -> 30.875 | M13: =IF(AND(I13<>"",I13<>0,L13<>"",L13<>0),L13/I13,"") -> 0.55449302 | N13: =IF(AND(J13<>0,J13<>"",I13<>0,I13<>""),L13-I13,"") -> -24.806495 | P13: =IF(AND(O13<>"",O13<>0,L13<>"",L13<>0),-O13+L13,"") | Q13: =IF(AND(P13<>"",P13<>0,O13<>0,O13<>""),P13/O13,"")
F14: Кол-во смен план/отработано | I14: =График!AI26 -> 19 | J14: 19 | K14: =IF(AND(I14<>"",I14<>0,J14<>""),J14/I14,"") -> 1 | L14: =IF(SUMIF($D$25:$D$47,">=0",$U$25:$U$47),I49*I8/SUMIF($D$25:$D$47,">=0",$U$25:$U$47),"") -> 404.7 | N14: =IF(AND(J14<>0,J14<>"",I14<>0,I14<>""),L14-I14,"") -> 385.7 | P14: =IF(AND(O14<>"",O14<>0,L14<>"",L14<>0),-O14+L14,"") | Q14: =IF(AND(P14<>"",P14<>0,O14<>0,O14<>""),P14/O14,"")
F15: Средние продажи в смену | I15: =Центрум!I15/2 -> 30945.484 | J15: =J8/J14 -> 13833.209 | K15: =IF(AND(I15<>"",I15<>0,J15<>""),J15/I15,"") -> 0.44701868 | L15: =J15 -> 13833.209 | M15: =IF(AND(I15<>"",I15<>0,L15<>"",L15<>0),L15/I15,"") -> 0.44701868 | N15: =IF(AND(J15<>0,J15<>"",I15<>0,I15<>""),L15-I15,"") -> -17112.274 | P15: =IF(AND(O15<>"",O15<>0,L15<>"",L15<>0),-O15+L15,"") | Q15: =IF(AND(P15<>"",P15<>0,O15<>0,O15<>""),P15/O15,"")
F16: Отставание/Перевыполнение | J16: =J8-I15*J14 -> -325133.21 | K16: =IF(AND(I16<>"",I16<>0,J16<>""),J16/I16,"") | L16: =J16 -> -325133.21 | M16: =IF(AND(I16<>"",I16<>0,L16<>"",L16<>0),L16/I16,"") | N16: =IF(AND(J16<>0,J16<>"",I16<>0,I16<>""),L16-I16,"") | P16: =IF(AND(O16<>"",O16<>0,L16<>"",L16<>0),-O16+L16,"") | Q16: =IF(AND(P16<>"",P16<>0,O16<>0,O16<>""),P16/O16,"") | T16: Подарочные сертификаты
F17: Трафик | I17: =Центрум!I17/График!AJ29*График!AJ26 -> 618.68327 | J17: =I49 -> 340.8 | K17: =IF(AND(I17<>"",I17<>0,J17<>""),J17/I17,"") -> 0.55084728 | L17: =J17/J14*I14 -> 340.8 | M17: =IF(AND(I17<>"",I17<>0,L17<>"",L17<>0),L17/I17,"") -> 0.55084728 | N17: =IF(AND(J17<>0,J17<>"",I17<>0,I17<>""),L17-I17,"") -> -277.88327 | P17: =IF(AND(O17<>"",O17<>0,L17<>"",L17<>0),-O17+L17,"") | Q17: =IF(AND(P17<>"",P17<>0,O17<>0,O17<>""),P17/O17,"")
K18: =IF(AND(I18<>"",I18<>0,J18<>""),J18/I18,"") | L18: =J18 -> 0 | M18: =IF(AND(I18<>"",I18<>0,L18<>"",L18<>0),L18/I18,"") | N18: =IF(AND(J18<>0,J18<>"",I18<>0,I18<>""),L18-I18,"") | O18: 0 | P18: =IF(AND(O18<>"",O18<>0,L18<>"",L18<>0),-O18+L18,"") | Q18: =IF(AND(P18<>"",P18<>0,O18<>0,O18<>""),P18/O18,"")
J19: =P49 -> 0 | K19: =IF(AND(I19<>"",I19<>0,J19<>""),J19/I19,"") | L19: =J19 -> 0 | M19: =IF(AND(I19<>"",I19<>0,L19<>"",L19<>0),L19/I19,"") | N19: =IF(AND(J19<>0,J19<>"",I19<>0,I19<>""),L19-I19,"") | O19: 0 | P19: =IF(AND(O19<>"",O19<>0,L19<>"",L19<>0),-O19+L19,"") | Q19: =IF(AND(P19<>"",P19<>0,O19<>0,O19<>""),P19/O19,"") | T19: =T18/I16 -> #DIV/0!
F20: Конверсия план/факт | I20: =Центрум!I20 -> 0.09 | J20: =S49 -> 0.07629108 | K20: =J20/I20 -> 0.84767866 | L20: =IF(AND(K8<>0,I14<>0,I49<>0),(I49*S49+(I49/K8-I49)*I20)/(I49/K8),0) -> 0.084232653 | M20: =IF(AND(I20<>"",I20<>0,L20<>"",L20<>0),L20/I20,"") -> 0.93591837 | N20: =IF(AND(J20<>0,J20<>"",I20<>0,I20<>""),L20-I20,"") -> -0.0057673467 | P20: =IF(AND(O20<>"",O20<>0,L20<>"",L20<>0),-O20+L20,"") | Q20: =IF(AND(P20<>"",P20<>0,O20<>0,O20<>""),P20/O20,"")
B22: Факт продаж за месяц | T22: % выполнения дневного плана | U22: Раcпределение плана по дням
B23: Дата | C23: День недели | D23: Выручка (руб) | E23: Кол-во единиц (шт.) | F23: Средняя стоимость изделия (руб.) | G23: Количество чеков (шт.) | H23: Средняя сумма чека (руб.) | I23: Трафик | J23: Длина чека (шт.) | K23: UNOde50 | L23: IS | M23: Agafi | N23: Kalliope | O23: Raganella | P23: CC/MP | Q23: Eva Rites | R23: Antura | S23: Конверсия (%) | U23: выручка, план | V23: кол-во ед, план | W23: Кол-во чеков, план | X23: выручка, скорректир.план | Y23: кол-во ед, скорр. план | Z23: кол-во чеков, скорр. план | AA23: Коэфф. Дня Недели | AB23: Специфика месяца
B24: 1 | C24: 2 | D24: 3 | E24: в | F24: 5 | G24: 6 | H24: 7 | I24: 8 | J24: 9 | K24: 10 | L24: 11 | M24: 12 | N24: 13 | O24: 14 | P24: 15 | Q24: 16 | R24: 17 | S24: 18 | U24: 1 | V24: 2 | W24: 3 | X24: 4 | Y24: 5 | Z24: 6 | AA24: 10 | AB24: 11
A25: 1 | B25: 46024 | C25: пт | D25: 0 | E25: 0 | F25: =IF(AND(E25<>"",E25<>0),D25/E25,"") | G25: 0 | H25: =IF(AND(G25<>"",G25<>0),D25/G25,"") | I25: 25 | J25: =IF(AND(G25<>"",G25<>0),E25/G25,"") | S25: =IF(AND(I25<>"",I25<>0),G25/I25,"") -> 0 | T25: =D25/U25 -> #REF! | U25: =$I$8*AA25*AB25/SUMPRODUCT($AA$25:$AA$55,$Z$25:$Z$55) -> #REF! | V25: =$I$9*AA25*AB25/SUMPRODUCT($AA$25:$AA$55,$Z$25:$Z$55) -> #REF! | W25: =IF($I$12="","",V25/$I$12) -> #REF! | X25: =IF(AB25<>"",IF(E25<>"",E25,($I$8-SUM($W24:X$25))*AA25*AB25/SUMPRODUCT($AA25:$AA$48,$Z25:$Z$48)),"") -> 0 | Y25: =IF(AB25<>"",IF(F25<>"",F25,($I$9-SUM($X24:Y$25))*AA25*AB25/SUMPRODUCT($AA25:$AA$55,$Z25:$Z$55)),"") -> #REF! | Z25: =IF(AB25<>"",IF($I$12<>"",IF(H25<>"",H25,($I$9/$I$12-SUM($Y24:Z$25))*AA25*AB25/SUMPRODUCT($AA25:$AA$55,$Z25:$Z$55)),""),"") -> #REF! | AA25: 1 | AB25: 1
A26: 2 | B26: 46025 | C26: сб | D26: 0 | E26: 0 | F26: =IF(AND(E26<>"",E26<>0),D26/E26,"") | G26: 0 | H26: =IF(AND(G26<>"",G26<>0),D26/G26,"") | I26: 25 | J26: =IF(AND(G26<>"",G26<>0),E26/G26,"") | S26: =IF(AND(I26<>"",I26<>0),G26/I26,"") -> 0 | T26: =D26/U26 -> 0 | U26: =$I$8*AA26*AB26/SUMPRODUCT($AB$25:$AB$56,$AA$25:$AA$56) -> 32881.388 | V26: =$I$9*AA26*AB26/SUMPRODUCT($AB$25:$AB$56,$AA$25:$AA$56) -> 4.9820285 | W26: =IF($I$12="","",V26/$I$12) -> 2.930605 | X26: =IF(AB26<>"",IF(D26<>"",D26,($I$8-SUM($X$25:X25))*AA26*AB26/SUMPRODUCT($AB26:$AB$56,$AA26:$AA$56)),"") -> 0 | Y26: =IF(AB26<>"",IF(E26<>"",E26,($I$9-SUM($Y$25:Y25))*AA26*AB26/SUMPRODUCT($AB26:$AB$56,$AA26:$AA$56)),"") -> 0 | Z26: =IF(AB26<>"",IF($I$12<>"",IF(G26<>"",G26,($I$9/$I$12-SUM($Z$25:Z25))*AA26*AB26/SUMPRODUCT($AB26:$AB$56,$AA26:$AA$56)),""),"") -> 0 | AA26: 1 | AB26: 1
A27: 3 | B27: 46026 | C27: вс | D27: 0 | E27: 0 | F27: =IF(AND(E27<>"",E27<>0),D27/E27,"") | G27: 0 | H27: =IF(AND(G27<>"",G27<>0),D27/G27,"") | I27: 30 | J27: =IF(AND(G27<>"",G27<>0),E27/G27,"") | S27: =IF(AND(I27<>"",I27<>0),G27/I27,"") -> 0 | T27: =D27/U27 -> 0 | U27: =$I$8*AA27*AB27/SUMPRODUCT($AB$25:$AB$56,$AA$25:$AA$56) -> 32881.388 | V27: =$I$9*AA27*AB27/SUMPRODUCT($AB$25:$AB$56,$AA$25:$AA$56) -> 4.9820285 | W27: =IF($I$12="","",V27/$I$12) -> 2.930605 | X27: =IF(AB27<>"",IF(D27<>"",D27,($I$8-SUM($X$25:X26))*AA27*AB27/SUMPRODUCT($AB27:$AB$56,$AA27:$AA$56)),"") -> 0 | Y27: =IF(AB27<>"",IF(E27<>"",E27,($I$9-SUM($Y$25:Y26))*AA27*AB27/SUMPRODUCT($AB27:$AB$56,$AA27:$AA$56)),"") -> 0 | Z27: =IF(AB27<>"",IF($I$12<>"",IF(G27<>"",G27,($I$9/$I$12-SUM($Z$25:Z26))*AA27*AB27/SUMPRODUCT($AB27:$AB$56,$AA27:$AA$56)),""),"") -> 0 | AA27: 1 | AB27: 1
A28: 4 | B28: 46027 | C28: пн | D28: =5890+7093 -> 12983 | E28: 2 | F28: =IF(AND(E28<>"",E28<>0),D28/E28,"") -> 6491.5 | G28: 2 | H28: =IF(AND(G28<>"",G28<>0),D28/G28,"") -> 6491.5 | I28: 50 | J28: =IF(AND(G28<>"",G28<>0),E28/G28,"") -> 1 | M28: 7093 | S28: =IF(AND(I28<>"",I28<>0),G28/I28,"") -> 0.04 | T28: =D28/U28 -> 0.39484343 | U28: =$I$8*AA28*AB28/SUMPRODUCT($AB$25:$AB$56,$AA$25:$AA$56) -> 32881.388 | V28: =$I$9*AA28*AB28/SUMPRODUCT($AB$25:$AB$56,$AA$25:$AA$56) -> 4.9820285 | W28: =IF($I$12="","",V28/$I$12) -> 2.930605 | X28: =IF(AB28<>"",IF(D28<>"",D28,($I$8-SUM($X$25:X27))*AA28*AB28/SUMPRODUCT($AB28:$AB$56,$AA28:$AA$56)),"") -> 12983 | Y28: =IF(AB28<>"",IF(E28<>"",E28,($I$9-SUM($Y$25:Y27))*AA28*AB28/SUMPRODUCT($AB28:$AB$56,$AA28:$AA$56)),"") -> 2 | Z28: =IF(AB28<>"",IF($I$12<>"",IF(G28<>"",G28,($I$9/$I$12-SUM($Z$25:Z27))*AA28*AB28/SUMPRODUCT($AB28:$AB$56,$AA28:$AA$56)),""),"") -> 2 | AA28: 1 | AB28: 1
A29: 5 | B29: 46028 | C29: вт | D29: =5236.98+55522+4293 -> 65051.98 | E29: 12 | F29: =IF(AND(E29<>"",E29<>0),D29/E29,"") -> 5420.9983 | G29: 3 | H29: =IF(AND(G29<>"",G29<>0),D29/G29,"") -> 21683.993 | I29: 37 | J29: =IF(AND(G29<>"",G29<>0),E29/G29,"") -> 4 | Q29: 9390 | S29: =IF(AND(I29<>"",I29<>0),G29/I29,"") -> 0.081081081 | T29: =D29/U29 -> 1.978383 | U29: =$I$8*AA29*AB29/SUMPRODUCT($AB$25:$AB$56,$AA$25:$AA$56) -> 32881.388 | V29: =$I$9*AA29*AB29/SUMPRODUCT($AB$25:$AB$56,$AA$25:$AA$56) -> 4.9820285 | W29: =IF($I$12="","",V29/$I$12) -> 2.930605 | X29: =IF(AB29<>"",IF(D29<>"",D29,($I$8-SUM($X$25:X28))*AA29*AB29/SUMPRODUCT($AB29:$AB$56,$AA29:$AA$56)),"") -> 65051.98 | Y29: =IF(AB29<>"",IF(E29<>"",E29,($I$9-SUM($Y$25:Y28))*AA29*AB29/SUMPRODUCT($AB29:$AB$56,$AA29:$AA$56)),"") -> 12 | Z29: =IF(AB29<>"",IF($I$12<>"",IF(G29<>"",G29,($I$9/$I$12-SUM($Z$25:Z28))*AA29*AB29/SUMPRODUCT($AB29:$AB$56,$AA29:$AA$56)),""),"") -> 3 | AA29: 1 | AB29: 1
A30: 6 | B30: 46031 | C30: пт | D30: 0 | E30: 0 | F30: =IF(AND(E30<>"",E30<>0),D30/E30,"") | G30: 0 | H30: =IF(AND(G30<>"",G30<>0),D30/G30,"") | I30: 26 | J30: =IF(AND(G30<>"",G30<>0),E30/G30,"") | S30: =IF(AND(I30<>"",I30<>0),G30/I30,"") -> 0 | T30: =D30/U30 -> 0 | U30: =$I$8*AA30*AB30/SUMPRODUCT($AB$25:$AB$56,$AA$25:$AA$56) -> 32881.388 | V30: =$I$9*AA30*AB30/SUMPRODUCT($AB$25:$AB$56,$AA$25:$AA$56) -> 4.9820285 | W30: =IF($I$12="","",V30/$I$12) -> 2.930605 | X30: =IF(AB30<>"",IF(D30<>"",D30,($I$8-SUM($X$25:X29))*AA30*AB30/SUMPRODUCT($AB30:$AB$56,$AA30:$AA$56)),"") -> 0 | Y30: =IF(AB30<>"",IF(E30<>"",E30,($I$9-SUM($Y$25:Y29))*AA30*AB30/SUMPRODUCT($AB30:$AB$56,$AA30:$AA$56)),"") -> 0 | Z30: =IF(AB30<>"",IF($I$12<>"",IF(G30<>"",G30,($I$9/$I$12-SUM($Z$25:Z29))*AA30*AB30/SUMPRODUCT($AB30:$AB$56,$AA30:$AA$56)),""),"") -> 0 | AA30: 1 | AB30: 1
A31: 7 | B31: 46032 | C31: сб | D31: =4693+8393 -> 13086 | E31: 2 | F31: =IF(AND(E31<>"",E31<>0),D31/E31,"") -> 6543 | G31: 2 | H31: =IF(AND(G31<>"",G31<>0),D31/G31,"") -> 6543 | I31: 32 | J31: =IF(AND(G31<>"",G31<>0),E31/G31,"") -> 1 | M31: 8393 | S31: =IF(AND(I31<>"",I31<>0),G31/I31,"") -> 0.0625 | T31: =D31/U31 -> 0.3979759 | U31: =$I$8*AA31*AB31/SUMPRODUCT($AB$25:$AB$56,$AA$25:$AA$56) -> 32881.388 | V31: =$I$9*AA31*AB31/SUMPRODUCT($AB$25:$AB$56,$AA$25:$AA$56) -> 4.9820285 | W31: =IF($I$12="","",V31/$I$12) -> 2.930605 | X31: =IF(AB31<>"",IF(D31<>"",D31,($I$8-SUM($X$25:X30))*AA31*AB31/SUMPRODUCT($AB31:$AB$56,$AA31:$AA$56)),"") -> 13086 | Y31: =IF(AB31<>"",IF(E31<>"",E31,($I$9-SUM($Y$25:Y30))*AA31*AB31/SUMPRODUCT($AB31:$AB$56,$AA31:$AA$56)),"") -> 2 | Z31: =IF(AB31<>"",IF($I$12<>"",IF(G31<>"",G31,($I$9/$I$12-SUM($Z$25:Z30))*AA31*AB31/SUMPRODUCT($AB31:$AB$56,$AA31:$AA$56)),""),"") -> 2 | AA31: 1 | AB31: 1
A32: 8 | B32: 46033 | C32: вс | D32: 0 | E32: 0 | F32: =IF(AND(E32<>"",E32<>0),D32/E32,"") | G32: 0 | H32: =IF(AND(G32<>"",G32<>0),D32/G32,"") | I32: 15 | J32: =IF(AND(G32<>"",G32<>0),E32/G32,"") | S32: =IF(AND(I32<>"",I32<>0),G32/I32,"") -> 0 | T32: =D32/U32 -> 0 | U32: =$I$8*AA32*AB32/SUMPRODUCT($AB$25:$AB$56,$AA$25:$AA$56) -> 32881.388 | V32: =$I$9*AA32*AB32/SUMPRODUCT($AB$25:$AB$56,$AA$25:$AA$56) -> 4.9820285 | W32: =IF($I$12="","",V32/$I$12) -> 2.930605 | X32: =IF(AB32<>"",IF(D32<>"",D32,($I$8-SUM($X$25:X31))*AA32*AB32/SUMPRODUCT($AB32:$AB$56,$AA32:$AA$56)),"") -> 0 | Y32: =IF(AB32<>"",IF(E32<>"",E32,($I$9-SUM($Y$25:Y31))*AA32*AB32/SUMPRODUCT($AB32:$AB$56,$AA32:$AA$56)),"") -> 0 | Z32: =IF(AB32<>"",IF($I$12<>"",IF(G32<>"",G32,($I$9/$I$12-SUM($Z$25:Z31))*AA32*AB32/SUMPRODUCT($AB32:$AB$56,$AA32:$AA$56)),""),"") -> 0 | AA32: 1 | AB32: 1
A33: 9 | B33: 46036 | C33: ср | D33: =6443+20361 -> 26804 | E33: 6 | F33: =IF(AND(E33<>"",E33<>0),D33/E33,"") -> 4467.3333 | G33: 3 | H33: =IF(AND(G33<>"",G33<>0),D33/G33,"") -> 8934.6667 | I33: 30 | J33: =IF(AND(G33<>"",G33<>0),E33/G33,"") -> 2 | L33: 6443 | S33: =IF(AND(I33<>"",I33<>0),G33/I33,"") -> 0.1 | T33: =D33/U33 -> 0.8151724 | U33: =$I$8*AA33*AB33/SUMPRODUCT($AB$25:$AB$56,$AA$25:$AA$56) -> 32881.388 | V33: =$I$9*AA33*AB33/SUMPRODUCT($AB$25:$AB$56,$AA$25:$AA$56) -> 4.9820285 | W33: =IF($I$12="","",V33/$I$12) -> 2.930605 | X33: =IF(AB33<>"",IF(D33<>"",D33,($I$8-SUM($X$25:X32))*AA33*AB33/SUMPRODUCT($AB33:$AB$56,$AA33:$AA$56)),"") -> 26804 | Y33: =IF(AB33<>"",IF(E33<>"",E33,($I$9-SUM($Y$25:Y32))*AA33*AB33/SUMPRODUCT($AB33:$AB$56,$AA33:$AA$56)),"") -> 6 | Z33: =IF(AB33<>"",IF($I$12<>"",IF(G33<>"",G33,($I$9/$I$12-SUM($Z$25:Z32))*AA33*AB33/SUMPRODUCT($AB33:$AB$56,$AA33:$AA$56)),""),"") -> 3 | AA33: 1 | AB33: 1
A34: 10 | B34: 46037 | C34: чт | D34: 0 | E34: 0 | F34: =IF(AND(E34<>"",E34<>0),D34/E34,"") | G34: 0 | H34: =IF(AND(G34<>"",G34<>0),D34/G34,"") | I34: 17 | J34: =IF(AND(G34<>"",G34<>0),E34/G34,"") | S34: =IF(AND(I34<>"",I34<>0),G34/I34,"") -> 0 | T34: =D34/U34 -> 0 | U34: =$I$8*AA34*AB34/SUMPRODUCT($AB$25:$AB$56,$AA$25:$AA$56) -> 32881.388 | V34: =$I$9*AA34*AB34/SUMPRODUCT($AB$25:$AB$56,$AA$25:$AA$56) -> 4.9820285 | W34: =IF($I$12="","",V34/$I$12) -> 2.930605 | X34: =IF(AB34<>"",IF(D34<>"",D34,($I$8-SUM($X$25:X33))*AA34*AB34/SUMPRODUCT($AB34:$AB$56,$AA34:$AA$56)),"") -> 0 | Y34: =IF(AB34<>"",IF(E34<>"",E34,($I$9-SUM($Y$25:Y33))*AA34*AB34/SUMPRODUCT($AB34:$AB$56,$AA34:$AA$56)),"") -> 0 | Z34: =IF(AB34<>"",IF($I$12<>"",IF(G34<>"",G34,($I$9/$I$12-SUM($Z$25:Z33))*AA34*AB34/SUMPRODUCT($AB34:$AB$56,$AA34:$AA$56)),""),"") -> 0 | AA34: 1 | AB34: 1
A35: 11 | B35: 46040 | C35: вс | D35: 21509 | E35: 5 | F35: =IF(AND(E35<>"",E35<>0),D35/E35,"") -> 4301.8 | G35: 3 | H35: =IF(AND(G35<>"",G35<>0),D35/G35,"") -> 7169.6667 | I35: 24 | J35: =IF(AND(G35<>"",G35<>0),E35/G35,"") -> 1.6666667 | S35: =IF(AND(I35<>"",I35<>0),G35/I35,"") -> 0.125 | T35: =D35/U35 -> 0.65413905 | U35: =$I$8*AA35*AB35/SUMPRODUCT($AB$25:$AB$56,$AA$25:$AA$56) -> 32881.388 | V35: =$I$9*AA35*AB35/SUMPRODUCT($AB$25:$AB$56,$AA$25:$AA$56) -> 4.9820285 | W35: =IF($I$12="","",V35/$I$12) -> 2.930605 | X35: =IF(AB35<>"",IF(D35<>"",D35,($I$8-SUM($X$25:X34))*AA35*AB35/SUMPRODUCT($AB35:$AB$56,$AA35:$AA$56)),"") -> 21509 | Y35: =IF(AB35<>"",IF(E35<>"",E35,($I$9-SUM($Y$25:Y34))*AA35*AB35/SUMPRODUCT($AB35:$AB$56,$AA35:$AA$56)),"") -> 5 | Z35: =IF(AB35<>"",IF($I$12<>"",IF(G35<>"",G35,($I$9/$I$12-SUM($Z$25:Z34))*AA35*AB35/SUMPRODUCT($AB35:$AB$56,$AA35:$AA$56)),""),"") -> 3 | AA35: 1 | AB35: 1
A36: 12 | B36: 46041 | C36: пн | D36: 24125 | E36: 4 | F36: =IF(AND(E36<>"",E36<>0),D36/E36,"") -> 6031.25 | G36: 2 | H36: =IF(AND(G36<>"",G36<>0),D36/G36,"") -> 12062.5 | I36: 17 | J36: =IF(AND(G36<>"",G36<>0),E36/G36,"") -> 2 | S36: =IF(AND(I36<>"",I36<>0),G36/I36,"") -> 0.11764706 | T36: =D36/U36 -> 0.73369774 | U36: =$I$8*AA36*AB36/SUMPRODUCT($AB$25:$AB$56,$AA$25:$AA$56) -> 32881.388 | V36: =$I$9*AA36*AB36/SUMPRODUCT($AB$25:$AB$56,$AA$25:$AA$56) -> 4.9820285 | W36: =IF($I$12="","",V36/$I$12) -> 2.930605 | X36: =IF(AB36<>"",IF(D36<>"",D36,($I$8-SUM($X$25:X35))*AA36*AB36/SUMPRODUCT($AB36:$AB$56,$AA36:$AA$56)),"") -> 24125 | Y36: =IF(AB36<>"",IF(E36<>"",E36,($I$9-SUM($Y$25:Y35))*AA36*AB36/SUMPRODUCT($AB36:$AB$56,$AA36:$AA$56)),"") -> 4 | Z36: =IF(AB36<>"",IF($I$12<>"",IF(G36<>"",G36,($I$9/$I$12-SUM($Z$25:Z35))*AA36*AB36/SUMPRODUCT($AB36:$AB$56,$AA36:$AA$56)),""),"") -> 2 | AA36: 1 | AB36: 1
A37: 13 | B37: 46042 | C37: вт | D37: 17518 | E37: 3 | F37: =IF(AND(E37<>"",E37<>0),D37/E37,"") -> 5839.3333 | G37: 2 | H37: =IF(AND(G37<>"",G37<>0),D37/G37,"") -> 8759 | I37: 16 | J37: =IF(AND(G37<>"",G37<>0),E37/G37,"") -> 1.5 | R37: 9390 | S37: =IF(AND(I37<>"",I37<>0),G37/I37,"") -> 0.125 | T37: =D37/U37 -> 0.5327634 | U37: =$I$8*AA37*AB37/SUMPRODUCT($AB$25:$AB$56,$AA$25:$AA$56) -> 32881.388 | V37: =$I$9*AA37*AB37/SUMPRODUCT($AB$25:$AB$56,$AA$25:$AA$56) -> 4.9820285 | W37: =IF($I$12="","",V37/$I$12) -> 2.930605 | X37: =IF(AB37<>"",IF(D37<>"",D37,($I$8-SUM($X$25:X36))*AA37*AB37/SUMPRODUCT($AB37:$AB$56,$AA37:$AA$56)),"") -> 17518 | Y37: =IF(AB37<>"",IF(E37<>"",E37,($I$9-SUM($Y$25:Y36))*AA37*AB37/SUMPRODUCT($AB37:$AB$56,$AA37:$AA$56)),"") -> 3 | Z37: =IF(AB37<>"",IF($I$12<>"",IF(G37<>"",G37,($I$9/$I$12-SUM($Z$25:Z36))*AA37*AB37/SUMPRODUCT($AB37:$AB$56,$AA37:$AA$56)),""),"") -> 2 | AA37: 1 | AB37: 1
A38: 14 | B38: 46045 | C38: пт | D38: =2945+26242 -> 29187 | E38: 2 | F38: =IF(AND(E38<>"",E38<>0),D38/E38,"") -> 14593.5 | G38: 3 | H38: =IF(AND(G38<>"",G38<>0),D38/G38,"") -> 9729 | I38: 19 | J38: =IF(AND(G38<>"",G38<>0),E38/G38,"") -> 0.66666667 | R38: 26242 | S38: =IF(AND(I38<>"",I38<>0),G38/I38,"") -> 0.15789474 | T38: =D38/U38 -> 0.88764501 | U38: =$I$8*AA38*AB38/SUMPRODUCT($AB$25:$AB$46,$AA$25:$AA$46) -> 32881.388 | V38: =$I$9*AA38*AB38/SUMPRODUCT($AB$25:$AB$46,$AA$25:$AA$46) -> 4.9820285 | W38: =IF($I$12="","",V38/$I$12) -> 2.930605 | X38: =IF(AB38<>"",IF(D38<>"",D38,($I$8-SUM($X$25:X37))*AA38*AB38/SUMPRODUCT($AB38:$AB$56,$AA38:$AA$56)),"") -> 29187 | Y38: =IF(AB38<>"",IF(E38<>"",E38,($I$9-SUM($Y$25:Y37))*AA38*AB38/SUMPRODUCT($AB38:$AB$56,$AA38:$AA$56)),"") -> 2 | Z38: =IF(AB38<>"",IF($I$12<>"",IF(G38<>"",G38,($I$9/$I$12-SUM($Z$25:Z37))*AA38*AB38/SUMPRODUCT($AB38:$AB$56,$AA38:$AA$56)),""),"") -> 3 | AA38: 1 | AB38: 1
A39: 15 | B39: 46046 | C39: сб | D39: 42565 | E39: 7 | F39: =IF(AND(E39<>"",E39<>0),D39/E39,"") -> 6080.7143 | G39: 4 | H39: =IF(AND(G39<>"",G39<>0),D39/G39,"") -> 10641.25 | I39: 27 | J39: =IF(AND(G39<>"",G39<>0),E39/G39,"") -> 1.75 | S39: =IF(AND(I39<>"",I39<>0),G39/I39,"") -> 0.14814815 | T39: =D39/U39 -> 1.2945013 | U39: =$I$8*AA39*AB39/SUMPRODUCT($AB$25:$AB$46,$AA$25:$AA$46) -> 32881.388 | V39: =$I$9*AA39*AB39/SUMPRODUCT($AB$25:$AB$46,$AA$25:$AA$46) -> 4.9820285 | W39: =IF($I$12="","",V39/$I$12) -> 2.930605 | X39: =IF(AB39<>"",IF(D39<>"",D39,($I$8-SUM($X$25:X38))*AA39*AB39/SUMPRODUCT($AB39:$AB$56,$AA39:$AA$56)),"") -> 42565 | Y39: =IF(AB39<>"",IF(E39<>"",E39,($I$9-SUM($Y$25:Y38))*AA39*AB39/SUMPRODUCT($AB39:$AB$56,$AA39:$AA$56)),"") -> 7 | Z39: =IF(AB39<>"",IF($I$12<>"",IF(G39<>"",G39,($I$9/$I$12-SUM($Z$25:Z38))*AA39*AB39/SUMPRODUCT($AB39:$AB$56,$AA39:$AA$56)),""),"") -> 4 | AA39: 1 | AB39: 1
A40: 16 | B40: 46047 | C40: вс | F40: =IF(AND(E40<>"",E40<>0),D40/E40,"") | H40: =IF(AND(G40<>"",G40<>0),D40/G40,"") | I40: 25 | J40: =IF(AND(G40<>"",G40<>0),E40/G40,"") | S40: =IF(AND(I40<>"",I40<>0),G40/I40,"") -> 0 | T40: =D40/U40 -> 0 | U40: =$I$8*AA40*AB40/SUMPRODUCT($AB$25:$AB$46,$AA$25:$AA$46) -> 32881.388 | V40: =$I$9*AA40*AB40/SUMPRODUCT($AB$25:$AB$46,$AA$25:$AA$46) -> 4.9820285 | W40: =IF($I$12="","",V40/$I$12) -> 2.930605 | X40: =IF(AB40<>"",IF(D40<>"",D40,($I$8-SUM($X$25:X39))*AA40*AB40/SUMPRODUCT($AB40:$AB$56,$AA40:$AA$56)),"") -> 92979.348 | Y40: =IF(AB40<>"",IF(E40<>"",E40,($I$9-SUM($Y$25:Y39))*AA40*AB40/SUMPRODUCT($AB40:$AB$56,$AA40:$AA$56)),"") -> #REF! | Z40: =IF(AB40<>"",IF($I$12<>"",IF(G40<>"",G40,($I$9/$I$12-SUM($Z$25:Z39))*AA40*AB40/SUMPRODUCT($AB40:$AB$56,$AA40:$AA$56)),""),"") -> #REF! | AA40: 1 | AB40: 1
A41: 17 | B41: 46048 | C41: пн | D41: 5001 | E41: 1 | F41: =IF(AND(E41<>"",E41<>0),D41/E41,"") -> 5001 | G41: 1 | H41: =IF(AND(G41<>"",G41<>0),D41/G41,"") -> 5001 | I41: 11 | J41: =IF(AND(G41<>"",G41<>0),E41/G41,"") -> 1 | S41: =IF(AND(I41<>"",I41<>0),G41/I41,"") -> 0.090909091 | T41: =D41/U41 -> 0.15209212 | U41: =$I$8*AA41*AB41/SUMPRODUCT($AB$25:$AB$46,$AA$25:$AA$46) -> 32881.388 | V41: =$I$9*AA41*AB41/SUMPRODUCT($AB$25:$AB$46,$AA$25:$AA$46) -> 4.9820285 | W41: =IF($I$12="","",V41/$I$12) -> 2.930605 | X41: =IF(AB41<>"",IF(D41<>"",D41,($I$8-SUM($X$25:X40))*AA41*AB41/SUMPRODUCT($AB41:$AB$56,$AA41:$AA$56)),"") -> 5001 | Y41: =IF(AB41<>"",IF(E41<>"",E41,($I$9-SUM($Y$25:Y40))*AA41*AB41/SUMPRODUCT($AB41:$AB$56,$AA41:$AA$56)),"") -> 1 | Z41: =IF(AB41<>"",IF($I$12<>"",IF(G41<>"",G41,($I$9/$I$12-SUM($Z$25:Z40))*AA41*AB41/SUMPRODUCT($AB41:$AB$56,$AA41:$AA$56)),""),"") -> 1 | AA41: 1 | AB41: 1
A42: 18 | B42: 46051 | C42: чт | F42: =IF(AND(E42<>"",E42<>0),D42/E42,"") | H42: =IF(AND(G42<>"",G42<>0),D42/G42,"") | J42: =IF(AND(G42<>"",G42<>0),E42/G42,"") | S42: =IF(AND(I42<>"",I42<>0),G42/I42,"") | T42: =D42/U42 -> 0 | U42: =$I$8*AA42*AB42/SUMPRODUCT($AB$25:$AB$46,$AA$25:$AA$46) -> 32881.388 | V42: =$I$9*AA42*AB42/SUMPRODUCT($AB$25:$AB$46,$AA$25:$AA$46) -> 4.9820285 | W42: =IF($I$12="","",V42/$I$12) -> 2.930605 | X42: =IF(AB42<>"",IF(D42<>"",D42,($I$8-SUM($X$25:X41))*AA42*AB42/SUMPRODUCT($AB42:$AB$56,$AA42:$AA$56)),"") -> 136968.52 | Y42: =IF(AB42<>"",IF(E42<>"",E42,($I$9-SUM($Y$25:Y41))*AA42*AB42/SUMPRODUCT($AB42:$AB$56,$AA42:$AA$56)),"") -> #REF! | Z42: =IF(AB42<>"",IF($I$12<>"",IF(G42<>"",G42,($I$9/$I$12-SUM($Z$25:Z41))*AA42*AB42/SUMPRODUCT($AB42:$AB$56,$AA42:$AA$56)),""),"") -> #REF! | AA42: 1 | AB42: 1
A43: 19 | B43: 46052 | C43: пт | D43: 5001 | E43: 1 | F43: =IF(AND(E43<>"",E43<>0),D43/E43,"") -> 5001 | G43: 1 | H43: =IF(AND(G43<>"",G43<>0),D43/G43,"") -> 5001 | J43: =IF(AND(G43<>"",G43<>0),E43/G43,"") -> 1 | S43: =IF(AND(I43<>"",I43<>0),G43/I43,"") | T43: =D43/U43 -> 0.15209212 | U43: =$I$8*AA43*AB43/SUMPRODUCT($AB$25:$AB$46,$AA$25:$AA$46) -> 32881.388 | V43: =$I$9*AA43*AB43/SUMPRODUCT($AB$25:$AB$46,$AA$25:$AA$46) -> 4.9820285 | W43: =IF($I$12="","",V43/$I$12) -> 2.930605 | X43: =IF(AB43<>"",IF(D43<>"",D43,($I$8-SUM($X$25:X42))*AA43*AB43/SUMPRODUCT($AB43:$AB$56,$AA43:$AA$56)),"") -> 5001 | Y43: =IF(AB43<>"",IF(E43<>"",E43,($I$9-SUM($Y$25:Y42))*AA43*AB43/SUMPRODUCT($AB43:$AB$56,$AA43:$AA$56)),"") -> 1 | Z43: =IF(AB43<>"",IF($I$12<>"",IF(G43<>"",G43,($I$9/$I$12-SUM($Z$25:Z42))*AA43*AB43/SUMPRODUCT($AB43:$AB$56,$AA43:$AA$56)),""),"") -> 1 | AA43: 1 | AB43: 1
F44: =IF(AND(E44<>"",E44<>0),D44/E44,"") | H44: =IF(AND(G44<>"",G44<>0),D44/G44,"") | J44: =IF(AND(G44<>"",G44<>0),E44/G44,"") | S44: =IF(AND(I44<>"",I44<>0),G44/I44,"") | T44: =D44/U44 -> #DIV/0! | U44: =$I$8*AA44*AB44/SUMPRODUCT($AB$25:$AB$46,$AA$25:$AA$46) -> 0 | V44: =$I$9*AA44*AB44/SUMPRODUCT($AB$25:$AB$46,$AA$25:$AA$46) -> 0 | W44: =IF($I$12="","",V44/$I$12) -> 0 | X44: =IF(AB44<>"",IF(D44<>"",D44,($I$8-SUM($X$25:X43))*AA44*AB44/SUMPRODUCT($AB44:$AB$56,$AA44:$AA$56)),"") | Y44: =IF(AB44<>"",IF(E44<>"",E44,($I$9-SUM($Y$25:Y43))*AA44*AB44/SUMPRODUCT($AB44:$AB$56,$AA44:$AA$56)),"") | Z44: =IF(AB44<>"",IF($I$12<>"",IF(G44<>"",G44,($I$9/$I$12-SUM($Z$25:Z43))*AA44*AB44/SUMPRODUCT($AB44:$AB$56,$AA44:$AA$56)),""),"")
F45: =IF(AND(E45<>"",E45<>0),D45/E45,"") | H45: =IF(AND(G45<>"",G45<>0),D45/G45,"") | J45: =IF(AND(G45<>"",G45<>0),E45/G45,"") | S45: =IF(AND(I45<>"",I45<>0),G45/I45,"") | T45: =D45/U45 -> #DIV/0! | U45: =$I$8*AA45*AB45/SUMPRODUCT($AB$25:$AB$46,$AA$25:$AA$46) -> 0 | V45: =$I$9*AA45*AB45/SUMPRODUCT($AB$25:$AB$46,$AA$25:$AA$46) -> 0 | W45: =IF($I$12="","",V45/$I$12) -> 0 | X45: =IF(AB45<>"",IF(D45<>"",D45,($I$8-SUM($X$25:X44))*AA45*AB45/SUMPRODUCT($AB45:$AB$56,$AA45:$AA$56)),"") | Y45: =IF(AB45<>"",IF(E45<>"",E45,($I$9-SUM($Y$25:Y44))*AA45*AB45/SUMPRODUCT($AB45:$AB$56,$AA45:$AA$56)),"") | Z45: =IF(AB45<>"",IF($I$12<>"",IF(G45<>"",G45,($I$9/$I$12-SUM($Z$25:Z44))*AA45*AB45/SUMPRODUCT($AB45:$AB$56,$AA45:$AA$56)),""),"")
F46: =IF(AND(E46<>"",E46<>0),D46/E46,"") | H46: =IF(AND(G46<>"",G46<>0),D46/G46,"") | J46: =IF(AND(G46<>"",G46<>0),E46/G46,"") | S46: =IF(AND(I46<>"",I46<>0),G46/I46,"") | T46: =D46/U46 -> #DIV/0! | U46: =$I$8*AA46*AB46/SUMPRODUCT($AB$25:$AB$46,$AA$25:$AA$46) -> 0 | V46: =$I$9*AA46*AB46/SUMPRODUCT($AB$25:$AB$46,$AA$25:$AA$46) -> 0 | W46: =IF($I$12="","",V46/$I$12) -> 0 | X46: =IF(AB46<>"",IF(D46<>"",D46,($I$8-SUM($X$25:X45))*AA46*AB46/SUMPRODUCT($AB46:$AB$56,$AA46:$AA$56)),"") | Y46: =IF(AB46<>"",IF(E46<>"",E46,($I$9-SUM($Y$25:Y45))*AA46*AB46/SUMPRODUCT($AB46:$AB$56,$AA46:$AA$56)),"") | Z46: =IF(AB46<>"",IF($I$12<>"",IF(G46<>"",G46,($I$9/$I$12-SUM($Z$25:Z45))*AA46*AB46/SUMPRODUCT($AB46:$AB$56,$AA46:$AA$56)),""),"")
F47: =IF(AND(E47<>"",E47<>0),D47/E47,"") | H47: =IF(AND(G47<>"",G47<>0),D47/G47,"") | J47: =IF(AND(G47<>"",G47<>0),E47/G47,"") | S47: =IF(AND(I47<>"",I47<>0),G47/I47,"") | T47: =D47/U47 -> #DIV/0! | U47: =$I$8*AA47*AB47/SUMPRODUCT($AB$25:$AB$46,$AA$25:$AA$46) -> 0 | V47: =$I$9*AA47*AB47/SUMPRODUCT($AB$25:$AB$46,$AA$25:$AA$46) -> 0 | W47: =IF($I$12="","",V47/$I$12) -> 0 | X47: =IF(AB47<>"",IF(D47<>"",D47,($I$8-SUM($X$25:X46))*AA47*AB47/SUMPRODUCT($AB47:$AB$56,$AA47:$AA$56)),"") | Y47: =IF(AB47<>"",IF(E47<>"",E47,($I$9-SUM($Y$25:Y46))*AA47*AB47/SUMPRODUCT($AB47:$AB$56,$AA47:$AA$56)),"") | Z47: =IF(AB47<>"",IF($I$12<>"",IF(G47<>"",G47,($I$9/$I$12-SUM($Z$25:Z46))*AA47*AB47/SUMPRODUCT($AB47:$AB$56,$AA47:$AA$56)),""),"")
F48: =IF(AND(E48<>"",E48<>0),D48/E48,"") | H48: =IF(AND(G48<>"",G48<>0),D48/G48,"") | J48: =IF(AND(G48<>"",G48<>0),E48/G48,"") | S48: =IF(AND(I48<>"",I48<>0),G48/I48,"") | T48: =D48/U48 -> #DIV/0! | U48: =$I$8*AA48*AB48/SUMPRODUCT($AB$25:$AB$46,$AA$25:$AA$46) -> 0 | V48: =$I$9*AA48*AB48/SUMPRODUCT($AB$25:$AB$46,$AA$25:$AA$46) -> 0 | W48: =IF($I$12="","",V48/$I$12) -> 0 | X48: =IF(AB48<>"",IF(D48<>"",D48,($I$8-SUM($X$25:X47))*AA48*AB48/SUMPRODUCT($AB48:$AB$56,$AA48:$AA$56)),"") | Y48: =IF(AB48<>"",IF(E48<>"",E48,($I$9-SUM($Y$25:Y47))*AA48*AB48/SUMPRODUCT($AB48:$AB$56,$AA48:$AA$56)),"") | Z48: =IF(AB48<>"",IF($I$12<>"",IF(G48<>"",G48,($I$9/$I$12-SUM($Z$25:Z47))*AA48*AB48/SUMPRODUCT($AB48:$AB$56,$AA48:$AA$56)),""),"")
B49: итого | D49: =SUM(D25:D47) -> 262830.98 | E49: =SUM(E25:E47) -> 45 | F49: =IF(AND(E49<>"",E49<>0),D49/E49,"") -> 5840.6884 | G49: =SUM(G25:G47) -> 26 | H49: =IF(AND(G49<>"",G49<>0),D49/G49,"") -> 10108.884 | I49: =SUM(I25:I47)*0.8 -> 340.8 | J49: =IF(AND(G49<>"",G49<>0),E49/G49,"") -> 1.7307692 | K49: =SUM(K25:K48) -> 0 | L49: =SUM(L25:L48) -> 6443 | M49: =SUM(M25:M48) -> 15486 | N49: =SUM(N25:N48) -> 0 | O49: =SUM(O25:O48) -> 0 | P49: =SUM(P25:P48) -> 0 | Q49: =SUM(Q25:Q48) -> 9390 | R49: =SUM(R25:R48) -> 35632 | S49: =IF(AND(I49<>"",I49<>0),G49/I49,"") -> 0.07629108 | T49: =D49/U49 -> #REF! | U49: =SUM(U25:U47) -> #REF! | V49: =SUM(V25:V47) -> #REF! | W49: =SUM(W25:W47) -> #REF! | X49: =SUM(X25:X47) -> 492778.85 | Y49: =SUM(Y25:Y47) -> #REF! | Z49: =SUM(Z25:Z47) -> #REF!
D50: =SUMIF(D25:D47,"",U25:U47)+D49 -> 328593.76

Sheet Корж А. А.
B1: =TODAY()-1 -> 46170
B2: (отчетная дата) | J2: ЕЖЕДНЕВНЫЙ ОТЧЕТ О ПРОДАЖАХ
B3: Осталось до выполнения плана!!! | J3: =График!B25 -> Корж Анастасия
C4: =I8-D48 -> 126439.2 | E4: =IF(I8<>0,C4/I8,0) -> 0.2001969
F6: Целевые показатели
F7: Показатель | I7: План | J7: Факт | K7: % выполнения | L7: Прогноз выполнения | M7: % выполнения по прогнозу | N7: Отклонение | O7: Факт аналогичного месяца прошлого года | P7: Отклонение LFL
F8: Выручка | I8: =Центрум!I8/График!AJ29*График!AJ25 -> 631574.2 | J8: =D48 -> 505135 | K8: =IF(AND(I8<>"",I8<>0,J8<>""),J8/I8,"") -> 0.7998031 | L8: =IF(SUMIF($D$25:$D$47,">=0",$U$25:$U$47)<>0,I8*D48/SUMIF($D$25:$D$47,">=0",$U$25:$U$47),0) -> 520889.96 | M8: =L8/I8 -> 0.82474864 | N8: =IF(AND(J8<>0,J8<>"",I8<>0,I8<>""),L8-I8,"") -> -110684.23 | P8: =IF(AND(O8<>"",O8<>0,L8<>"",L8<>0),-O8+L8,"") | Q8: =IF(AND(P8<>"",P8<>0,O8<>0,O8<>""),P8/O8,"")
F9: Кол-во изделий | I9: =I8/I11 -> 95.69306 | J9: =E48 -> 65 | K9: =IF(AND(I9<>"",I9<>0,J9<>""),J9/I9,"") -> 0.67925511 | L9: =IF(SUMIF($E$25:$E$47,">=0",$V$25:$V$47)<>0,I9*E48/SUMIF($E$25:$E$47,">=0",$V$25:$V$47),0) -> 69.404614 | M9: =IF(AND(I9<>"",I9<>0,L9<>"",L9<>0),L9/I9,"") -> 0.72528367 | N9: =IF(AND(J9<>0,J9<>"",I9<>0,I9<>""),L9-I9,"") -> -26.288446 | O9: =O8/O11 -> #DIV/0! | P9: =IF(AND(O9<>"",O9<>0,L9<>"",L9<>0),-O9+L9,"") -> #DIV/0! | Q9: =IF(AND(P9<>"",P9<>0,O9<>0,O9<>""),P9/O9,"") -> #DIV/0!
F10: Средний чек | I10: =I11*I12 -> 11220 | J10: =H48 -> 18708.704 | K10: =IF(AND(I10<>"",I10<>0,J10<>""),J10/I10,"") -> 1.6674424 | L10: =J10 -> 18708.704 | M10: =IF(AND(I10<>"",I10<>0,L10<>"",L10<>0),L10/I10,"") -> 1.6674424 | N10: =IF(AND(J10<>0,J10<>"",I10<>0,I10<>""),L10-I10,"") -> 7488.7037 | O10: =O11*O12 -> 0 | P10: =IF(AND(O10<>"",O10<>0,L10<>"",L10<>0),-O10+L10,"") | Q10: =IF(AND(P10<>"",P10<>0,O10<>0,O10<>""),P10/O10,"")
F11: Средняя стоимость изделия | I11: =Центрум!I11 -> 6600 | J11: =F48 -> 7771.3077 | K11: =IF(AND(I11<>"",I11<>0,J11<>""),J11/I11,"") -> 1.1774709 | L11: =J11 -> 7771.3077 | M11: =IF(AND(I11<>"",I11<>0,L11<>"",L11<>0),L11/I11,"") -> 1.1774709 | N11: =IF(AND(J11<>0,J11<>"",I11<>0,I11<>""),L11-I11,"") -> 1171.3077 | P11: =IF(AND(O11<>"",O11<>0,L11<>"",L11<>0),-O11+L11,"") | Q11: =IF(AND(P11<>"",P11<>0,O11<>0,O11<>""),P11/O11,"")
F12: Длина чека | I12: ='Центрум'!I12 -> 1.7 | J12: =J48 -> 2.4074074 | K12: =IF(AND(I12<>"",I12<>0,J12<>""),J12/I12,"") -> 1.416122 | L12: =J12 -> 2.4074074 | M12: =IF(AND(I12<>"",I12<>0,L12<>"",L12<>0),L12/I12,"") -> 1.416122 | N12: =IF(AND(J12<>0,J12<>"",I12<>0,I12<>""),L12-I12,"") -> 0.70740741 | P12: =IF(AND(O12<>"",O12<>0,L12<>"",L12<>0),-O12+L12,"") | Q12: =IF(AND(P12<>"",P12<>0,O12<>0,O12<>""),P12/O12,"")
F13: Кол-во чеков | I13: =IF(I12<>0,I9/I12,"") -> 56.290036 | J13: =G48 -> 27 | K13: =IF(AND(I13<>"",I13<>0,J13<>""),J13/I13,"") -> 0.47965861 | L13: =IF(SUMIF($G$25:$G$47,">=0",$W$25:$W$47)<>0,I13*G48/SUMIF($G$25:$G$47,">=0",$W$25:$W$47),"") -> 29.023922 | M13: =IF(AND(I13<>"",I13<>0,L13<>"",L13<>0),L13/I13,"") -> 0.51561385 | N13: =IF(AND(J13<>0,J13<>"",I13<>0,I13<>""),L13-I13,"") -> -27.266114 | P13: =IF(AND(O13<>"",O13<>0,L13<>"",L13<>0),-O13+L13,"") | Q13: =IF(AND(P13<>"",P13<>0,O13<>0,O13<>""),P13/O13,"")
F14: Кол-во смен план/отработано | I14: =График!AI25 -> 18 | J14: 19 | K14: =IF(AND(I14<>"",I14<>0,J14<>""),J14/I14,"") -> 1.0555556 | L14: =IF(SUMIF($D$25:$D$47,">=0",$U$25:$U$47),I48*I8/SUMIF($D$25:$D$47,">=0",$U$25:$U$47),"") -> 320.90621 | N14: =IF(AND(J14<>0,J14<>"",I14<>0,I14<>""),L14-I14,"") -> 302.90621 | P14: =IF(AND(O14<>"",O14<>0,L14<>"",L14<>0),-O14+L14,"") | Q14: =IF(AND(P14<>"",P14<>0,O14<>0,O14<>""),P14/O14,"")
F15: Средние продажи в смену | I15: =Центрум!I15/2 -> 30945.484 | J15: =J8/J14 -> 26586.053 | K15: =IF(AND(I15<>"",I15<>0,J15<>""),J15/I15,"") -> 0.85912545 | L15: =J15 -> 26586.053 | M15: =IF(AND(I15<>"",I15<>0,L15<>"",L15<>0),L15/I15,"") -> 0.85912545 | N15: =IF(AND(J15<>0,J15<>"",I15<>0,I15<>""),L15-I15,"") -> -4359.4312 | P15: =IF(AND(O15<>"",O15<>0,L15<>"",L15<>0),-O15+L15,"") | Q15: =IF(AND(P15<>"",P15<>0,O15<>0,O15<>""),P15/O15,"")
F16: Отставание/Перевыполнение | J16: =J8-I15*J14 -> -82829.194 | K16: =IF(AND(I16<>"",I16<>0,J16<>""),J16/I16,"") | L16: =J16 -> -82829.194 | M16: =IF(AND(I16<>"",I16<>0,L16<>"",L16<>0),L16/I16,"") | N16: =IF(AND(J16<>0,J16<>"",I16<>0,I16<>""),L16-I16,"") | P16: =IF(AND(O16<>"",O16<>0,L16<>"",L16<>0),-O16+L16,"") | Q16: =IF(AND(P16<>"",P16<>0,O16<>0,O16<>""),P16/O16,"") | U16: Подарочные сертификаты
F17: Трафик | I17: =Центрум!I17/График!AJ29*График!AJ25 -> 625.44484 | J17: =I48 -> 311.2 | K17: =IF(AND(I17<>"",I17<>0,J17<>""),J17/I17,"") -> 0.49756586 | L17: =J17/J14*I14 -> 294.82105 | M17: =IF(AND(I17<>"",I17<>0,L17<>"",L17<>0),L17/I17,"") -> 0.47137818 | N17: =IF(AND(J17<>0,J17<>"",I17<>0,I17<>""),L17-I17,"") -> -330.62379 | P17: =IF(AND(O17<>"",O17<>0,L17<>"",L17<>0),-O17+L17,"") | Q17: =IF(AND(P17<>"",P17<>0,O17<>0,O17<>""),P17/O17,"")
K18: =IF(AND(I18<>"",I18<>0,J18<>""),J18/I18,"") | L18: =J18 -> 0 | M18: =IF(AND(I18<>"",I18<>0,L18<>"",L18<>0),L18/I18,"") | N18: =IF(AND(J18<>0,J18<>"",I18<>0,I18<>""),L18-I18,"") | O18: 0 | P18: =IF(AND(O18<>"",O18<>0,L18<>"",L18<>0),-O18+L18,"") | Q18: =IF(AND(P18<>"",P18<>0,O18<>0,O18<>""),P18/O18,"")
J19: =P48 -> 0 | K19: =IF(AND(I19<>"",I19<>0,J19<>""),J19/I19,"") | L19: =J19 -> 0 | M19: =IF(AND(I19<>"",I19<>0,L19<>"",L19<>0),L19/I19,"") | N19: =IF(AND(J19<>0,J19<>"",I19<>0,I19<>""),L19-I19,"") | O19: 0 | P19: =IF(AND(O19<>"",O19<>0,L19<>"",L19<>0),-O19+L19,"") | Q19: =IF(AND(P19<>"",P19<>0,O19<>0,O19<>""),P19/O19,"") | U19: =U18/I16 -> #DIV/0!
F20: Конверсия план/факт | I20: =Центрум!I20 -> 0.09 | J20: =S48 -> 0.086760925 | K20: =J20/I20 -> 0.96401028 | L20: =IF(AND(K8<>0,I14<>0,I48<>0),(I48*S48+(I48/K8-I48)*I20)/(I48/K8),0) -> 0.087409378 | M20: =IF(AND(I20<>"",I20<>0,L20<>"",L20<>0),L20/I20,"") -> 0.97121531 | N20: =IF(AND(J20<>0,J20<>"",I20<>0,I20<>""),L20-I20,"") -> -0.0025906219 | P20: =IF(AND(O20<>"",O20<>0,L20<>"",L20<>0),-O20+L20,"") | Q20: =IF(AND(P20<>"",P20<>0,O20<>0,O20<>""),P20/O20,"")
B22: Факт продаж за месяц | T22: % выполнения дневного плана | U22: Раcпределение плана по дням
B23: Дата | C23: День недели | D23: Выручка (руб) | E23: Кол-во единиц (шт.) | F23: Средняя стоимость изделия (руб.) | G23: Количество чеков (шт.) | H23: Средняя сумма чека (руб.) | I23: Трафик | J23: Длина чека (шт.) | K23: UNOde50 | L23: IS | M23: Agafi | N23: Kalliope | O23: Raganella | P23: CC/MP | Q23: Eva Rites | R23: Antura | S23: Конверсия (%) | U23: выручка, план | V23: кол-во ед, план | W23: Кол-во чеков, план | X23: выручка, скорректир.план | Y23: кол-во ед, скорр. план | Z23: кол-во чеков, скорр. план | AA23: Коэфф. Дня Недели | AB23: Специфика месяца
B24: 1 | C24: 2 | D24: 3 | E24: в | F24: 5 | G24: 6 | H24: 7 | I24: 8 | J24: 9 | K24: 10 | L24: 11 | M24: 12 | N24: 13 | O24: 14 | P24: 15 | Q24: 16 | R24: 17 | S24: 18 | U24: 1 | V24: 2 | W24: 3 | X24: 4 | Y24: 5 | Z24: 6 | AA24: 10 | AB24: 11
A25: 1 | B25: 46024 | C25: пт | D25: 29366 | E25: 4 | F25: =IF(AND(E25<>"",E25<>0),D25/E25,"") -> 7341.5 | G25: 1 | H25: =IF(AND(G25<>"",G25<>0),D25/G25,"") -> 29366 | I25: 26 | J25: =IF(AND(G25<>"",G25<>0),E25/G25,"") -> 4 | Q25: 15180 | S25: =IF(AND(I25<>"",I25<>0),G25/I25,"") -> 0.038461538 | T25: =D25/U25 -> 0.88343381 | U25: =$I$8*AA25*AB25/SUMPRODUCT($AB$25:$AB$55,$AA$25:$AA$55) -> 33240.747 | V25: =$I$9*AA25*AB25/SUMPRODUCT($AB$25:$AB$55,$AA$25:$AA$55) -> 5.0364769 | W25: =IF($I$12="","",V25/$I$12) -> 2.9626335 | X25: =IF(AB25<>"",IF(D25<>"",D25,($I$8-SUM($X24:X$25))*AA25*AB25/SUMPRODUCT($AB25:$AB$55,$AA25:$AA$55)),"") -> 29366 | Y25: =IF(AB25<>"",IF(E25<>"",E25,($I$9-SUM($Y24:Y$25))*AA25*AB25/SUMPRODUCT($AB25:$AB$55,$AA25:$AA$55)),"") -> 4 | Z25: =IF(AB25<>"",IF($I$12<>"",IF(G25<>"",G25,($I$9/$I$12-SUM($Z24:Z$25))*AA25*AB25/SUMPRODUCT($AB25:$AB$55,$AA25:$AA$55)),""),"") -> 1 | AA25: 1 | AB25: 1
A26: 2 | B26: 46025 | C26: сб | D26: 6284 | E26: 2 | F26: =IF(AND(E26<>"",E26<>0),D26/E26,"") -> 3142 | G26: 1 | H26: =IF(AND(G26<>"",G26<>0),D26/G26,"") -> 6284 | I26: 25 | J26: =IF(AND(G26<>"",G26<>0),E26/G26,"") -> 2 | S26: =IF(AND(I26<>"",I26<>0),G26/I26,"") -> 0.04 | T26: =D26/U26 -> 0.18904509 | U26: =$I$8*AA26*AB26/SUMPRODUCT($AB$25:$AB$55,$AA$25:$AA$55) -> 33240.747 | V26: =$I$9*AA26*AB26/SUMPRODUCT($AB$25:$AB$55,$AA$25:$AA$55) -> 5.0364769 | W26: =IF($I$12="","",V26/$I$12) -> 2.9626335 | X26: =IF(AB26<>"",IF(D26<>"",D26,($I$8-SUM($X$25:X25))*AA26*AB26/SUMPRODUCT($AB26:$AB$55,$AA26:$AA$55)),"") -> 6284 | Y26: =IF(AB26<>"",IF(E26<>"",E26,($I$9-SUM($Y$25:Y25))*AA26*AB26/SUMPRODUCT($AB26:$AB$55,$AA26:$AA$55)),"") -> 2 | Z26: =IF(AB26<>"",IF($I$12<>"",IF(G26<>"",G26,($I$9/$I$12-SUM($Z$25:Z25))*AA26*AB26/SUMPRODUCT($AB26:$AB$55,$AA26:$AA$55)),""),"") -> 1 | AA26: 1 | AB26: 1
A27: 3 | B27: 46026 | C27: вс | D27: 63331 | E27: 8 | F27: =IF(AND(E27<>"",E27<>0),D27/E27,"") -> 7916.375 | G27: 1 | H27: =IF(AND(G27<>"",G27<>0),D27/G27,"") -> 63331 | I27: 30 | J27: =IF(AND(G27<>"",G27<>0),E27/G27,"") -> 8 | S27: =IF(AND(I27<>"",I27<>0),G27/I27,"") -> 0.033333333 | T27: =D27/U27 -> 4.4794879 | U27: 14138 | V27: 4 | W27: 2 | X27: 16611 | Y27: 3 | Z27: 3 | AA27: 1 | AB27: 1
A28: 4 | B28: 46027 | C28: пн | D28: =7693+7479 -> 15172 | E28: 2 | F28: =IF(AND(E28<>"",E28<>0),D28/E28,"") -> 7586 | G28: 2 | H28: =IF(AND(G28<>"",G28<>0),D28/G28,"") -> 7586 | I28: 50 | J28: =IF(AND(G28<>"",G28<>0),E28/G28,"") -> 1 | S28: =IF(AND(I28<>"",I28<>0),G28/I28,"") -> 0.04 | T28: =D28/U28 -> 0.45642776 | U28: =$I$8*AA28*AB28/SUMPRODUCT($AB$25:$AB$55,$AA$25:$AA$55) -> 33240.747 | V28: =$I$9*AA28*AB28/SUMPRODUCT($AB$25:$AB$55,$AA$25:$AA$55) -> 5.0364769 | W28: =IF($I$12="","",V28/$I$12) -> 2.9626335 | X28: =IF(AB28<>"",IF(D28<>"",D28,($I$8-SUM($X$25:X27))*AA28*AB28/SUMPRODUCT($AB28:$AB$55,$AA28:$AA$55)),"") -> 15172 | Y28: =IF(AB28<>"",IF(E28<>"",E28,($I$9-SUM($Y$25:Y27))*AA28*AB28/SUMPRODUCT($AB28:$AB$55,$AA28:$AA$55)),"") -> 2 | Z28: =IF(AB28<>"",IF($I$12<>"",IF(G28<>"",G28,($I$9/$I$12-SUM($Z$25:Z27))*AA28*AB28/SUMPRODUCT($AB28:$AB$55,$AA28:$AA$55)),""),"") -> 2 | AA28: 1 | AB28: 1
A29: 5 | B29: 46029 | C29: ср | D29: 3893 | E29: 1 | F29: =IF(AND(E29<>"",E29<>0),D29/E29,"") -> 3893 | G29: 1 | H29: =IF(AND(G29<>"",G29<>0),D29/G29,"") -> 3893 | I29: 17 | J29: =IF(AND(G29<>"",G29<>0),E29/G29,"") -> 1 | S29: =IF(AND(I29<>"",I29<>0),G29/I29,"") -> 0.058823529 | T29: =D29/U29 -> 0.1171153 | U29: =$I$8*AA29*AB29/SUMPRODUCT($AB$25:$AB$55,$AA$25:$AA$55) -> 33240.747 | V29: =$I$9*AA29*AB29/SUMPRODUCT($AB$25:$AB$55,$AA$25:$AA$55) -> 5.0364769 | W29: =IF($I$12="","",V29/$I$12) -> 2.9626335 | X29: =IF(AB29<>"",IF(D29<>"",D29,($I$8-SUM($X$25:X28))*AA29*AB29/SUMPRODUCT($AB29:$AB$55,$AA29:$AA$55)),"") -> 3893 | Y29: =IF(AB29<>"",IF(E29<>"",E29,($I$9-SUM($Y$25:Y28))*AA29*AB29/SUMPRODUCT($AB29:$AB$55,$AA29:$AA$55)),"") -> 1 | Z29: =IF(AB29<>"",IF($I$12<>"",IF(G29<>"",G29,($I$9/$I$12-SUM($Z$25:Z28))*AA29*AB29/SUMPRODUCT($AB29:$AB$55,$AA29:$AA$55)),""),"") -> 1 | AA29: 1 | AB29: 1
A30: 6 | B30: 46030 | C30: чт | D30: 0 | E30: 0 | F30: =IF(AND(E30<>"",E30<>0),D30/E30,"") | G30: 0 | H30: =IF(AND(G30<>"",G30<>0),D30/G30,"") | I30: 21 | J30: =IF(AND(G30<>"",G30<>0),E30/G30,"") | S30: =IF(AND(I30<>"",I30<>0),G30/I30,"") -> 0 | T30: =D30/U30 -> 0 | U30: =$I$8*AA30*AB30/SUMPRODUCT($AB$25:$AB$55,$AA$25:$AA$55) -> 33240.747 | V30: =$I$9*AA30*AB30/SUMPRODUCT($AB$25:$AB$55,$AA$25:$AA$55) -> 5.0364769 | W30: =IF($I$12="","",V30/$I$12) -> 2.9626335 | X30: =IF(AB30<>"",IF(D30<>"",D30,($I$8-SUM($X$25:X29))*AA30*AB30/SUMPRODUCT($AB30:$AB$55,$AA30:$AA$55)),"") -> 0 | Y30: =IF(AB30<>"",IF(E30<>"",E30,($I$9-SUM($Y$25:Y29))*AA30*AB30/SUMPRODUCT($AB30:$AB$55,$AA30:$AA$55)),"") -> 0 | Z30: =IF(AB30<>"",IF($I$12<>"",IF(G30<>"",G30,($I$9/$I$12-SUM($Z$25:Z29))*AA30*AB30/SUMPRODUCT($AB30:$AB$55,$AA30:$AA$55)),""),"") -> 0 | AA30: 1 | AB30: 1
A31: 7 | B31: 46033 | C31: вс | D31: =11984+220 -> 12204 | E31: 2 | F31: =IF(AND(E31<>"",E31<>0),D31/E31,"") -> 6102 | G31: 2 | H31: =IF(AND(G31<>"",G31<>0),D31/G31,"") -> 6102 | I31: 14 | J31: =IF(AND(G31<>"",G31<>0),E31/G31,"") -> 1 | L31: 220 | S31: =IF(AND(I31<>"",I31<>0),G31/I31,"") -> 0.14285714 | T31: =D31/U31 -> 0.36713976 | U31: =$I$8*AA31*AB31/SUMPRODUCT($AB$25:$AB$55,$AA$25:$AA$55) -> 33240.747 | V31: =$I$9*AA31*AB31/SUMPRODUCT($AB$25:$AB$55,$AA$25:$AA$55) -> 5.0364769 | W31: =IF($I$12="","",V31/$I$12) -> 2.9626335 | X31: =IF(AB31<>"",IF(D31<>"",D31,($I$8-SUM($X$25:X30))*AA31*AB31/SUMPRODUCT($AB31:$AB$55,$AA31:$AA$55)),"") -> 12204 | Y31: =IF(AB31<>"",IF(E31<>"",E31,($I$9-SUM($Y$25:Y30))*AA31*AB31/SUMPRODUCT($AB31:$AB$55,$AA31:$AA$55)),"") -> 2 | Z31: =IF(AB31<>"",IF($I$12<>"",IF(G31<>"",G31,($I$9/$I$12-SUM($Z$25:Z30))*AA31*AB31/SUMPRODUCT($AB31:$AB$55,$AA31:$AA$55)),""),"") -> 2 | AA31: 1 | AB31: 1
A32: 8 | B32: 46034 | C32: пн | D32: 3593 | E32: 1 | F32: =IF(AND(E32<>"",E32<>0),D32/E32,"") -> 3593 | G32: 1 | H32: =IF(AND(G32<>"",G32<>0),D32/G32,"") -> 3593 | I32: 26 | J32: =IF(AND(G32<>"",G32<>0),E32/G32,"") -> 1 | S32: =IF(AND(I32<>"",I32<>0),G32/I32,"") -> 0.038461538 | T32: =D32/U32 -> 0.10809023 | U32: =$I$8*AA32*AB32/SUMPRODUCT($AB$25:$AB$55,$AA$25:$AA$55) -> 33240.747 | V32: =$I$9*AA32*AB32/SUMPRODUCT($AB$25:$AB$55,$AA$25:$AA$55) -> 5.0364769 | W32: =IF($I$12="","",V32/$I$12) -> 2.9626335 | X32: =IF(AB32<>"",IF(D32<>"",D32,($I$8-SUM($X$25:X31))*AA32*AB32/SUMPRODUCT($AB32:$AB$55,$AA32:$AA$55)),"") -> 3593 | Y32: =IF(AB32<>"",IF(E32<>"",E32,($I$9-SUM($Y$25:Y31))*AA32*AB32/SUMPRODUCT($AB32:$AB$55,$AA32:$AA$55)),"") -> 1 | Z32: =IF(AB32<>"",IF($I$12<>"",IF(G32<>"",G32,($I$9/$I$12-SUM($Z$25:Z31))*AA32*AB32/SUMPRODUCT($AB32:$AB$55,$AA32:$AA$55)),""),"") -> 1 | AA32: 1 | AB32: 1
A33: 9 | B33: 46035 | C33: вт | D33: 5393 | E33: 1 | F33: =IF(AND(E33<>"",E33<>0),D33/E33,"") -> 5393 | G33: 1 | H33: =IF(AND(G33<>"",G33<>0),D33/G33,"") -> 5393 | I33: 38 | J33: =IF(AND(G33<>"",G33<>0),E33/G33,"") -> 1 | S33: =IF(AND(I33<>"",I33<>0),G33/I33,"") -> 0.026315789 | T33: =D33/U33 -> 0.16224064 | U33: =$I$8*AA33*AB33/SUMPRODUCT($AB$25:$AB$55,$AA$25:$AA$55) -> 33240.747 | V33: =$I$9*AA33*AB33/SUMPRODUCT($AB$25:$AB$55,$AA$25:$AA$55) -> 5.0364769 | W33: =IF($I$12="","",V33/$I$12) -> 2.9626335 | X33: =IF(AB33<>"",IF(D33<>"",D33,($I$8-SUM($X$25:X32))*AA33*AB33/SUMPRODUCT($AB33:$AB$55,$AA33:$AA$55)),"") -> 5393 | Y33: =IF(AB33<>"",IF(E33<>"",E33,($I$9-SUM($Y$25:Y32))*AA33*AB33/SUMPRODUCT($AB33:$AB$55,$AA33:$AA$55)),"") -> 1 | Z33: =IF(AB33<>"",IF($I$12<>"",IF(G33<>"",G33,($I$9/$I$12-SUM($Z$25:Z32))*AA33*AB33/SUMPRODUCT($AB33:$AB$55,$AA33:$AA$55)),""),"") -> 1 | AA33: 1 | AB33: 1
A34: 10 | B34: 46038 | C34: пт | D34: =26501+62037+5180 -> 93718 | E34: 7 | F34: =IF(AND(E34<>"",E34<>0),D34/E34,"") -> 13388.286 | G34: 2 | H34: =IF(AND(G34<>"",G34<>0),D34/G34,"") -> 46859 | I34: 12 | J34: =IF(AND(G34<>"",G34<>0),E34/G34,"") -> 3.5 | L34: 26501 | N34: 62037 | S34: =IF(AND(I34<>"",I34<>0),G34/I34,"") -> 0.16666667 | T34: =D34/U34 -> 2.819371 | U34: =$I$8*AA34*AB34/SUMPRODUCT($AB$25:$AB$55,$AA$25:$AA$55) -> 33240.747 | V34: =$I$9*AA34*AB34/SUMPRODUCT($AB$25:$AB$55,$AA$25:$AA$55) -> 5.0364769 | W34: =IF($I$12="","",V34/$I$12) -> 2.9626335 | X34: =IF(AB34<>"",IF(D34<>"",D34,($I$8-SUM($X$25:X33))*AA34*AB34/SUMPRODUCT($AB34:$AB$55,$AA34:$AA$55)),"") -> 93718 | Y34: =IF(AB34<>"",IF(E34<>"",E34,($I$9-SUM($Y$25:Y33))*AA34*AB34/SUMPRODUCT($AB34:$AB$55,$AA34:$AA$55)),"") -> 7 | Z34: =IF(AB34<>"",IF($I$12<>"",IF(G34<>"",G34,($I$9/$I$12-SUM($Z$25:Z33))*AA34*AB34/SUMPRODUCT($AB34:$AB$55,$AA34:$AA$55)),""),"") -> 2 | AA34: 1 | AB34: 1
A35: 11 | B35: 46039 | C35: сб | D35: 14784 | E35: 2 | F35: =IF(AND(E35<>"",E35<>0),D35/E35,"") -> 7392 | G35: 1 | H35: =IF(AND(G35<>"",G35<>0),D35/G35,"") -> 14784 | I35: 19 | J35: =IF(AND(G35<>"",G35<>0),E35/G35,"") -> 2 | S35: =IF(AND(I35<>"",I35<>0),G35/I35,"") -> 0.052631579 | T35: =D35/U35 -> 0.44475534 | U35: =$I$8*AA35*AB35/SUMPRODUCT($AB$25:$AB$55,$AA$25:$AA$55) -> 33240.747 | V35: =$I$9*AA35*AB35/SUMPRODUCT($AB$25:$AB$55,$AA$25:$AA$55) -> 5.0364769 | W35: =IF($I$12="","",V35/$I$12) -> 2.9626335 | X35: =IF(AB35<>"",IF(D35<>"",D35,($I$8-SUM($X$25:X34))*AA35*AB35/SUMPRODUCT($AB35:$AB$55,$AA35:$AA$55)),"") -> 14784 | Y35: =IF(AB35<>"",IF(E35<>"",E35,($I$9-SUM($Y$25:Y34))*AA35*AB35/SUMPRODUCT($AB35:$AB$55,$AA35:$AA$55)),"") -> 2 | Z35: =IF(AB35<>"",IF($I$12<>"",IF(G35<>"",G35,($I$9/$I$12-SUM($Z$25:Z34))*AA35*AB35/SUMPRODUCT($AB35:$AB$55,$AA35:$AA$55)),""),"") -> 1 | AA35: 1 | AB35: 1
A36: 12 | B36: 46040 | C36: вс | D36: 0 | F36: =IF(AND(E36<>"",E36<>0),D36/E36,"") | H36: =IF(AND(G36<>"",G36<>0),D36/G36,"") | I36: 24 | J36: =IF(AND(G36<>"",G36<>0),E36/G36,"") | S36: =IF(AND(I36<>"",I36<>0),G36/I36,"") -> 0 | T36: =D36/U36 -> 0 | U36: =$I$8*AA36*AB36/SUMPRODUCT($AB$25:$AB$55,$AA$25:$AA$55) -> 33240.747 | V36: =$I$9*AA36*AB36/SUMPRODUCT($AB$25:$AB$55,$AA$25:$AA$55) -> 5.0364769 | W36: =IF($I$12="","",V36/$I$12) -> 2.9626335 | X36: =IF(AB36<>"",IF(D36<>"",D36,($I$8-SUM($X$25:X35))*AA36*AB36/SUMPRODUCT($AB36:$AB$55,$AA36:$AA$55)),"") -> 0 | Y36: =IF(AB36<>"",IF(E36<>"",E36,($I$9-SUM($Y$25:Y35))*AA36*AB36/SUMPRODUCT($AB36:$AB$55,$AA36:$AA$55)),"") -> 8.8366326 | Z36: =IF(AB36<>"",IF($I$12<>"",IF(G36<>"",G36,($I$9/$I$12-SUM($Z$25:Z35))*AA36*AB36/SUMPRODUCT($AB36:$AB$55,$AA36:$AA$55)),""),"") -> 5.1612544 | AA36: 1 | AB36: 1
A37: 13 | B37: 46043 | C37: ср | D37: 25667 | E37: 4 | F37: =IF(AND(E37<>"",E37<>0),D37/E37,"") -> 6416.75 | G37: 2 | H37: =IF(AND(G37<>"",G37<>0),D37/G37,"") -> 12833.5 | I37: 12 | J37: =IF(AND(G37<>"",G37<>0),E37/G37,"") -> 2 | S37: =IF(AND(I37<>"",I37<>0),G37/I37,"") -> 0.16666667 | T37: =D37/U37 -> 0.77215472 | U37: =$I$8*AA37*AB37/SUMPRODUCT($AB$25:$AB$55,$AA$25:$AA$55) -> 33240.747 | V37: =$I$9*AA37*AB37/SUMPRODUCT($AB$25:$AB$55,$AA$25:$AA$55) -> 5.0364769 | W37: =IF($I$12="","",V37/$I$12) -> 2.9626335 | X37: =IF(AB37<>"",IF(D37<>"",D37,($I$8-SUM($X$25:X36))*AA37*AB37/SUMPRODUCT($AB37:$AB$55,$AA37:$AA$55)),"") -> 25667 | Y37: =IF(AB37<>"",IF(E37<>"",E37,($I$9-SUM($Y$25:Y36))*AA37*AB37/SUMPRODUCT($AB37:$AB$55,$AA37:$AA$55)),"") -> 4 | Z37: =IF(AB37<>"",IF($I$12<>"",IF(G37<>"",G37,($I$9/$I$12-SUM($Z$25:Z36))*AA37*AB37/SUMPRODUCT($AB37:$AB$55,$AA37:$AA$55)),""),"") -> 2 | AA37: 1 | AB37: 1
A38: 14 | B38: 46044 | C38: чт | D38: =14500+31191 -> 45691 | E38: 6 | F38: =IF(AND(E38<>"",E38<>0),D38/E38,"") -> 7615.1667 | G38: 2 | H38: =IF(AND(G38<>"",G38<>0),D38/G38,"") -> 22845.5 | I38: 18 | J38: =IF(AND(G38<>"",G38<>0),E38/G38,"") -> 3 | L38: 14500 | S38: =IF(AND(I38<>"",I38<>0),G38/I38,"") -> 0.11111111 | T38: =D38/U38 -> 1.3745479 | U38: =$I$8*AA38*AB38/SUMPRODUCT($AB$25:$AB$55,$AA$25:$AA$55) -> 33240.747 | V38: =$I$9*AA38*AB38/SUMPRODUCT($AB$25:$AB$55,$AA$25:$AA$55) -> 5.0364769 | W38: =IF($I$12="","",V38/$I$12) -> 2.9626335 | X38: =IF(AB38<>"",IF(D38<>"",D38,($I$8-SUM($X$25:X37))*AA38*AB38/SUMPRODUCT($AB38:$AB$55,$AA38:$AA$55)),"") -> 45691 | Y38: =IF(AB38<>"",IF(E38<>"",E38,($I$9-SUM($Y$25:Y37))*AA38*AB38/SUMPRODUCT($AB38:$AB$55,$AA38:$AA$55)),"") -> 6 | Z38: =IF(AB38<>"",IF($I$12<>"",IF(G38<>"",G38,($I$9/$I$12-SUM($Z$25:Z37))*AA38*AB38/SUMPRODUCT($AB38:$AB$55,$AA38:$AA$55)),""),"") -> 2 | AA38: 1 | AB38: 1
A39: 15 | B39: 46045 | C39: пт | D39: 27087 | E39: 6 | F39: =IF(AND(E39<>"",E39<>0),D39/E39,"") -> 4514.5 | G39: 4 | H39: =IF(AND(G39<>"",G39<>0),D39/G39,"") -> 6771.75 | I39: 19 | J39: =IF(AND(G39<>"",G39<>0),E39/G39,"") -> 1.5 | O39: 8990 | Q39: 8893 | R39: 9194 | S39: =IF(AND(I39<>"",I39<>0),G39/I39,"") -> 0.21052632 | T39: =D39/U39 -> 0.81487338 | U39: =$I$8*AA39*AB39/SUMPRODUCT($AB$25:$AB$55,$AA$25:$AA$55) -> 33240.747 | V39: =$I$9*AA39*AB39/SUMPRODUCT($AB$25:$AB$55,$AA$25:$AA$55) -> 5.0364769 | W39: =IF($I$12="","",V39/$I$12) -> 2.9626335 | X39: =IF(AB39<>"",IF(D39<>"",D39,($I$8-SUM($X$25:X38))*AA39*AB39/SUMPRODUCT($AB39:$AB$55,$AA39:$AA$55)),"") -> 27087 | Y39: =IF(AB39<>"",IF(E39<>"",E39,($I$9-SUM($Y$25:Y38))*AA39*AB39/SUMPRODUCT($AB39:$AB$55,$AA39:$AA$55)),"") -> 6 | Z39: =IF(AB39<>"",IF($I$12<>"",IF(G39<>"",G39,($I$9/$I$12-SUM($Z$25:Z38))*AA39*AB39/SUMPRODUCT($AB39:$AB$55,$AA39:$AA$55)),""),"") -> 4 | AA39: 1 | AB39: 1
A40: 16 | B40: 46048 | C40: пн | D40: 13769 | E40: 2 | F40: =IF(AND(E40<>"",E40<>0),D40/E40,"") -> 6884.5 | G40: 1 | H40: =IF(AND(G40<>"",G40<>0),D40/G40,"") -> 13769 | I40: 11 | J40: =IF(AND(G40<>"",G40<>0),E40/G40,"") -> 2 | S40: =IF(AND(I40<>"",I40<>0),G40/I40,"") -> 0.090909091 | T40: =D40/U40 -> 0.41422053 | U40: =$I$8*AA40*AB40/SUMPRODUCT($AB$25:$AB$55,$AA$25:$AA$55) -> 33240.747 | V40: =$I$9*AA40*AB40/SUMPRODUCT($AB$25:$AB$55,$AA$25:$AA$55) -> 5.0364769 | W40: =IF($I$12="","",V40/$I$12) -> 2.9626335 | X40: =IF(AB40<>"",IF(D40<>"",D40,($I$8-SUM($X$25:X39))*AA40*AB40/SUMPRODUCT($AB40:$AB$55,$AA40:$AA$55)),"") -> 13769 | Y40: =IF(AB40<>"",IF(E40<>"",E40,($I$9-SUM($Y$25:Y39))*AA40*AB40/SUMPRODUCT($AB40:$AB$55,$AA40:$AA$55)),"") -> 2 | Z40: =IF(AB40<>"",IF($I$12<>"",IF(G40<>"",G40,($I$9/$I$12-SUM($Z$25:Z39))*AA40*AB40/SUMPRODUCT($AB40:$AB$55,$AA40:$AA$55)),""),"") -> 1 | AA40: 1 | AB40: 1
A41: 17 | B41: 46049 | C41: вт | D41: 102342 | E41: 10 | F41: =IF(AND(E41<>"",E41<>0),D41/E41,"") -> 10234.2 | G41: 2 | H41: =IF(AND(G41<>"",G41<>0),D41/G41,"") -> 51171 | I41: 27 | J41: =IF(AND(G41<>"",G41<>0),E41/G41,"") -> 5 | S41: =IF(AND(I41<>"",I41<>0),G41/I41,"") -> 0.074074074 | T41: =D41/U41 -> 3.0788116 | U41: =$I$8*AA41*AB41/SUMPRODUCT($AB$25:$AB$55,$AA$25:$AA$55) -> 33240.747 | V41: =$I$9*AA41*AB41/SUMPRODUCT($AB$25:$AB$55,$AA$25:$AA$55) -> 5.0364769 | W41: =IF($I$12="","",V41/$I$12) -> 2.9626335 | X41: =IF(AB41<>"",IF(D41<>"",D41,($I$8-SUM($X$25:X40))*AA41*AB41/SUMPRODUCT($AB41:$AB$55,$AA41:$AA$55)),"") -> 102342 | Y41: =IF(AB41<>"",IF(E41<>"",E41,($I$9-SUM($Y$25:Y40))*AA41*AB41/SUMPRODUCT($AB41:$AB$55,$AA41:$AA$55)),"") -> 10 | Z41: =IF(AB41<>"",IF($I$12<>"",IF(G41<>"",G41,($I$9/$I$12-SUM($Z$25:Z40))*AA41*AB41/SUMPRODUCT($AB41:$AB$55,$AA41:$AA$55)),""),"") -> 2 | AA41: 1 | AB41: 1
A42: 18 | B42: 46050 | C42: ср | D42: 15883 | E42: 2 | F42: =IF(AND(E42<>"",E42<>0),D42/E42,"") -> 7941.5 | G42: 1 | H42: =IF(AND(G42<>"",G42<>0),D42/G42,"") -> 15883 | J42: =IF(AND(G42<>"",G42<>0),E42/G42,"") -> 2 | S42: =IF(AND(I42<>"",I42<>0),G42/I42,"") | T42: =D42/U42 -> 0.47781718 | U42: =$I$8*AA42*AB42/SUMPRODUCT($AB$25:$AB$55,$AA$25:$AA$55) -> 33240.747 | V42: =$I$9*AA42*AB42/SUMPRODUCT($AB$25:$AB$55,$AA$25:$AA$55) -> 5.0364769 | W42: =IF($I$12="","",V42/$I$12) -> 2.9626335 | X42: =IF(AB42<>"",IF(D42<>"",D42,($I$8-SUM($X$25:X41))*AA42*AB42/SUMPRODUCT($AB42:$AB$55,$AA42:$AA$55)),"") -> 15883 | Y42: =IF(AB42<>"",IF(E42<>"",E42,($I$9-SUM($Y$25:Y41))*AA42*AB42/SUMPRODUCT($AB42:$AB$55,$AA42:$AA$55)),"") -> 2 | Z42: =IF(AB42<>"",IF($I$12<>"",IF(G42<>"",G42,($I$9/$I$12-SUM($Z$25:Z41))*AA42*AB42/SUMPRODUCT($AB42:$AB$55,$AA42:$AA$55)),""),"") -> 1 | AA42: 1 | AB42: 1
A43: 19 | B43: 46053 | C43: сб | D43: 26958 | E43: 5 | F43: =IF(AND(E43<>"",E43<>0),D43/E43,"") -> 5391.6 | G43: 2 | H43: =IF(AND(G43<>"",G43<>0),D43/G43,"") -> 13479 | J43: =IF(AND(G43<>"",G43<>0),E43/G43,"") -> 2.5 | S43: =IF(AND(I43<>"",I43<>0),G43/I43,"") | T43: =D43/U43 -> 0.8109926 | U43: =$I$8*AA43*AB43/SUMPRODUCT($AB$25:$AB$55,$AA$25:$AA$55) -> 33240.747 | V43: =$I$9*AA43*AB43/SUMPRODUCT($AB$25:$AB$55,$AA$25:$AA$55) -> 5.0364769 | W43: =IF($I$12="","",V43/$I$12) -> 2.9626335 | X43: =IF(AB43<>"",IF(D43<>"",D43,($I$8-SUM($X$25:X42))*AA43*AB43/SUMPRODUCT($AB43:$AB$55,$AA43:$AA$55)),"") -> 26958 | Y43: =IF(AB43<>"",IF(E43<>"",E43,($I$9-SUM($Y$25:Y42))*AA43*AB43/SUMPRODUCT($AB43:$AB$55,$AA43:$AA$55)),"") -> 5 | Z43: =IF(AB43<>"",IF($I$12<>"",IF(G43<>"",G43,($I$9/$I$12-SUM($Z$25:Z42))*AA43*AB43/SUMPRODUCT($AB43:$AB$55,$AA43:$AA$55)),""),"") -> 2 | AA43: 1 | AB43: 1
F44: =IF(AND(E44<>"",E44<>0),D44/E44,"") | H44: =IF(AND(G44<>"",G44<>0),D44/G44,"") | J44: =IF(AND(G44<>"",G44<>0),E44/G44,"") | S44: =IF(AND(I44<>"",I44<>0),G44/I44,"") | T44: =D44/U44 -> #DIV/0! | U44: =$I$8*AA44*AB44/SUMPRODUCT($AB$25:$AB$55,$AA$25:$AA$55) -> 0 | V44: =$I$9*AA44*AB44/SUMPRODUCT($AB$25:$AB$55,$AA$25:$AA$55) -> 0 | W44: =IF($I$12="","",V44/$I$12) -> 0 | X44: =IF(AB44<>"",IF(D44<>"",D44,($I$8-SUM($X$25:X43))*AA44*AB44/SUMPRODUCT($AB44:$AB$55,$AA44:$AA$55)),"") | Y44: =IF(AB44<>"",IF(E44<>"",E44,($I$9-SUM($Y$25:Y43))*AA44*AB44/SUMPRODUCT($AB44:$AB$55,$AA44:$AA$55)),"") | Z44: =IF(AB44<>"",IF($I$12<>"",IF(G44<>"",G44,($I$9/$I$12-SUM($Z$25:Z43))*AA44*AB44/SUMPRODUCT($AB44:$AB$55,$AA44:$AA$55)),""),"")
F45: =IF(AND(E45<>"",E45<>0),D45/E45,"") | H45: =IF(AND(G45<>"",G45<>0),D45/G45,"") | J45: =IF(AND(G45<>"",G45<>0),E45/G45,"") | S45: =IF(AND(I45<>"",I45<>0),G45/I45,"") | T45: =D45/U45 -> #DIV/0! | U45: =$I$8*AA45*AB45/SUMPRODUCT($AB$25:$AB$55,$AA$25:$AA$55) -> 0 | V45: =$I$9*AA45*AB45/SUMPRODUCT($AB$25:$AB$55,$AA$25:$AA$55) -> 0 | W45: =IF($I$12="","",V45/$I$12) -> 0 | X45: =IF(AB45<>"",IF(D45<>"",D45,($I$8-SUM($X$25:X44))*AA45*AB45/SUMPRODUCT($AB45:$AB$55,$AA45:$AA$55)),"") | Y45: =IF(AB45<>"",IF(E45<>"",E45,($I$9-SUM($Y$25:Y44))*AA45*AB45/SUMPRODUCT($AB45:$AB$55,$AA45:$AA$55)),"") | Z45: =IF(AB45<>"",IF($I$12<>"",IF(G45<>"",G45,($I$9/$I$12-SUM($Z$25:Z44))*AA45*AB45/SUMPRODUCT($AB45:$AB$55,$AA45:$AA$55)),""),"")
F46: =IF(AND(E46<>"",E46<>0),D46/E46,"") | H46: =IF(AND(G46<>"",G46<>0),D46/G46,"") | J46: =IF(AND(G46<>"",G46<>0),E46/G46,"") | S46: =IF(AND(I46<>"",I46<>0),G46/I46,"") | T46: =D46/U46 -> #DIV/0! | U46: =$I$8*AA46*AB46/SUMPRODUCT($AB$25:$AB$46,$AA$25:$AA$46) -> 0 | V46: =$I$9*AA46*AB46/SUMPRODUCT($AB$25:$AB$46,$AA$25:$AA$46) -> 0 | W46: =IF($I$12="","",V46/$I$12) -> 0 | X46: =IF(AB46<>"",IF(D46<>"",D46,($I$8-SUM($X$25:X45))*AA46*AB46/SUMPRODUCT($AB46:$AB$46,$AA46:$AA$46)),"") | Y46: =IF(AB46<>"",IF(E46<>"",E46,($I$9-SUM($Y$25:Y39))*AA46*AB46/SUMPRODUCT($AB46:$AB$46,$AA46:$AA$46)),"") | Z46: =IF(AB46<>"",IF($I$12<>"",IF(G46<>"",G46,($I$9/$I$12-SUM($Z$25:Z39))*AA46*AB46/SUMPRODUCT($AB46:$AB$46,$AA46:$AA$46)),""),"")
F47: =IF(AND(E47<>"",E47<>0),D47/E47,"") | H47: =IF(AND(G47<>"",G47<>0),D47/G47,"") | J47: =IF(AND(G47<>"",G47<>0),E47/G47,"") | S47: =IF(AND(I47<>"",I47<>0),G47/I47,"") | T47: =D47/U47 -> #DIV/0! | U47: =$I$8*AA47*AB47/SUMPRODUCT($AB$25:$AB$46,$AA$25:$AA$46) -> 0 | V47: =$I$9*AA47*AB47/SUMPRODUCT($AB$25:$AB$46,$AA$25:$AA$46) -> 0 | W47: =IF($I$12="","",V47/$I$12) -> 0 | X47: =IF(AB47<>"",IF(D47<>"",D47,($I$8-SUM($X$25:X46))*AA47*AB47/SUMPRODUCT($AB$47:$AB47,$AA$47:$AA47)),"") | Y47: =IF(AB47<>"",IF(E47<>"",E47,($I$9-SUM(#REF!))*AA47*AB47/SUMPRODUCT($AB$47:$AB47,$AA$47:$AA47)),"") | Z47: =IF(AB47<>"",IF($I$12<>"",IF(G47<>"",G47,($I$9/$I$12-SUM(#REF!))*AA47*AB47/SUMPRODUCT($AB$47:$AB47,$AA$47:$AA47)),""),"")
B48: итого | D48: =SUM(D25:D47) -> 505135 | E48: =SUM(E25:E47) -> 65 | F48: =IF(AND(E48<>"",E48<>0),D48/E48,"") -> 7771.3077 | G48: =SUM(G25:G47) -> 27 | H48: =IF(AND(G48<>"",G48<>0),D48/G48,"") -> 18708.704 | I48: =SUM(I25:I47)*0.8 -> 311.2 | J48: =IF(AND(G48<>"",G48<>0),E48/G48,"") -> 2.4074074 | K48: =SUM(K25:K47) -> 0 | L48: =SUM(L25:L47) -> 41221 | M48: =SUM(M25:M47) -> 0 | N48: =SUM(N25:N47) -> 62037 | O48: =SUM(O25:O47) -> 8990 | P48: =SUM(P25:P47) -> 0 | Q48: =SUM(Q25:Q47) -> 24073 | R48: =SUM(R25:R47) -> 9194 | S48: =IF(AND(I48<>"",I48<>0),G48/I48,"") -> 0.086760925 | T48: =D48/U48 -> 0.82474864 | U48: =SUM(U25:U47) -> 612471.45 | V48: =SUM(V25:V47) -> 94.656584 | W48: =SUM(W25:W47) -> 55.327402 | X48: =SUM(X25:X47) -> 458415 | Y48: =SUM(Y25:Y47) -> 68.836633 | Z48: =SUM(Z25:Z47) -> 34.161254
D49: =SUMIF(D25:D47,"",U25:U47)+D48 -> 505135

Sheet Свидовская С. А.
B1: =TODAY()-1 -> 46170
B2: (отчетная дата) | J2: ЕЖЕДНЕВНЫЙ ОТЧЕТ О ПРОДАЖАХ
B3: Осталось до выполнения плана!!! | J3: =График!B27 -> Свидовская София
C4: =I8-D48 -> 87024.117 | E4: =IF(I8<>0,C4/I8,0) -> 0.24510583
F6: Целевые показатели
F7: Показатель | I7: План | J7: Факт | K7: % выполнения | L7: Прогноз выполнения | M7: % выполнения по прогнозу | N7: Отклонение | O7: Факт аналогичного месяца прошлого года | P7: Отклонение LFL
F8: Выручка | I8: =Центрум!I8/График!AJ29*График!AJ27 -> 355047.12 | J8: =D48 -> 268023 | K8: =IF(AND(I8<>"",I8<>0,J8<>""),J8/I8,"") -> 0.75489417 | L8: =IF(SUMIF($D$25:$D$47,">=0",$U$25:$U$47)<>0,I8*D48/SUMIF($D$25:$D$47,">=0",$U$25:$U$47),0) -> 286791.52 | M8: =L8/I8 -> 0.80775624 | N8: =IF(AND(J8<>0,J8<>"",I8<>0,I8<>""),L8-I8,"") -> -68255.594 | P8: =IF(AND(O8<>"",O8<>0,L8<>"",L8<>0),-O8+L8,"") | Q8: =IF(AND(P8<>"",P8<>0,O8<>0,O8<>""),P8/O8,"")
F9: Кол-во изделий | I9: =I8/I11 -> 53.795018 | J9: =E48 -> 41 | K9: =IF(AND(I9<>"",I9<>0,J9<>""),J9/I9,"") -> 0.76215236 | L9: =IF(SUMIF($E$25:$E$47,">=0",$V$25:$V$47)<>0,I9*E48/SUMIF($E$25:$E$47,">=0",$V$25:$V$47),0) -> 42.307594 | M9: =IF(AND(I9<>"",I9<>0,L9<>"",L9<>0),L9/I9,"") -> 0.78645933 | N9: =IF(AND(J9<>0,J9<>"",I9<>0,I9<>""),L9-I9,"") -> -11.487424 | O9: =O8/O11 -> #DIV/0! | P9: =IF(AND(O9<>"",O9<>0,L9<>"",L9<>0),-O9+L9,"") -> #DIV/0! | Q9: =IF(AND(P9<>"",P9<>0,O9<>0,O9<>""),P9/O9,"") -> #DIV/0!
F10: Средний чек | I10: =I11*I12 -> 11220 | J10: =H48 -> 8645.9032 | K10: =IF(AND(I10<>"",I10<>0,J10<>""),J10/I10,"") -> 0.77057961 | L10: =J10 -> 8645.9032 | M10: =IF(AND(I10<>"",I10<>0,L10<>"",L10<>0),L10/I10,"") -> 0.77057961 | N10: =IF(AND(J10<>0,J10<>"",I10<>0,I10<>""),L10-I10,"") -> -2574.0968 | O10: =O11*O12 -> 0 | P10: =IF(AND(O10<>"",O10<>0,L10<>"",L10<>0),-O10+L10,"") | Q10: =IF(AND(P10<>"",P10<>0,O10<>0,O10<>""),P10/O10,"")
F11: Средняя стоимость изделия | I11: =Центрум!I11 -> 6600 | J11: =F48 -> 6537.1463 | K11: =IF(AND(I11<>"",I11<>0,J11<>""),J11/I11,"") -> 0.99047672 | L11: =J11 -> 6537.1463 | M11: =IF(AND(I11<>"",I11<>0,L11<>"",L11<>0),L11/I11,"") -> 0.99047672 | N11: =IF(AND(J11<>0,J11<>"",I11<>0,I11<>""),L11-I11,"") -> -62.853659 | P11: =IF(AND(O11<>"",O11<>0,L11<>"",L11<>0),-O11+L11,"") | Q11: =IF(AND(P11<>"",P11<>0,O11<>0,O11<>""),P11/O11,"")
F12: Длина чека | I12: ='Центрум'!I12 -> 1.7 | J12: =J48 -> 1.3225806 | K12: =IF(AND(I12<>"",I12<>0,J12<>""),J12/I12,"") -> 0.77798861 | L12: =J12 -> 1.3225806 | M12: =IF(AND(I12<>"",I12<>0,L12<>"",L12<>0),L12/I12,"") -> 0.77798861 | N12: =IF(AND(J12<>0,J12<>"",I12<>0,I12<>""),L12-I12,"") -> -0.37741935 | P12: =IF(AND(O12<>"",O12<>0,L12<>"",L12<>0),-O12+L12,"") | Q12: =IF(AND(P12<>"",P12<>0,O12<>0,O12<>""),P12/O12,"")
F13: Кол-во чеков | I13: =IF(I12<>0,I9/I12,"") -> 31.644128 | J13: =G48 -> 31 | K13: =IF(AND(I13<>"",I13<>0,J13<>""),J13/I13,"") -> 0.97964462 | L13: =IF(SUMIF($G$25:$G$47,">=0",$W$25:$W$47)<>0,I13*G48/SUMIF($G$25:$G$47,">=0",$W$25:$W$47),"") -> 32.361118 | M13: =IF(AND(I13<>"",I13<>0,L13<>"",L13<>0),L13/I13,"") -> 1.0226579 | N13: =IF(AND(J13<>0,J13<>"",I13<>0,I13<>""),L13-I13,"") -> 0.71698952 | P13: =IF(AND(O13<>"",O13<>0,L13<>"",L13<>0),-O13+L13,"") | Q13: =IF(AND(P13<>"",P13<>0,O13<>0,O13<>""),P13/O13,"")
F14: Кол-во смен план/отработано | I14: =График!AI27 -> 10 | J14: 18 | K14: =IF(AND(I14<>"",I14<>0,J14<>""),J14/I14,"") -> 1.8 | L14: =IF(SUMIF($D$25:$D$47,">=0",$U$25:$U$47),I48*I8/SUMIF($D$25:$D$47,">=0",$U$25:$U$47),"") -> 276.49467 | N14: =IF(AND(J14<>0,J14<>"",I14<>0,I14<>""),L14-I14,"") -> 266.49467 | P14: =IF(AND(O14<>"",O14<>0,L14<>"",L14<>0),-O14+L14,"") | Q14: =IF(AND(P14<>"",P14<>0,O14<>0,O14<>""),P14/O14,"")
F15: Средние продажи в смену | I15: =Центрум!I15/2 -> 30945.484 | J15: =J8/J14 -> 14890.167 | K15: =IF(AND(I15<>"",I15<>0,J15<>""),J15/I15,"") -> 0.48117414 | L15: =J15 -> 14890.167 | M15: =IF(AND(I15<>"",I15<>0,L15<>"",L15<>0),L15/I15,"") -> 0.48117414 | N15: =IF(AND(J15<>0,J15<>"",I15<>0,I15<>""),L15-I15,"") -> -16055.317 | P15: =IF(AND(O15<>"",O15<>0,L15<>"",L15<>0),-O15+L15,"") | Q15: =IF(AND(P15<>"",P15<>0,O15<>0,O15<>""),P15/O15,"")
F16: Отставание/Перевыполнение | J16: =J8-I15*J14 -> -288995.71 | K16: =IF(AND(I16<>"",I16<>0,J16<>""),J16/I16,"") | L16: =J16 -> -288995.71 | M16: =IF(AND(I16<>"",I16<>0,L16<>"",L16<>0),L16/I16,"") | N16: =IF(AND(J16<>0,J16<>"",I16<>0,I16<>""),L16-I16,"") | P16: =IF(AND(O16<>"",O16<>0,L16<>"",L16<>0),-O16+L16,"") | Q16: =IF(AND(P16<>"",P16<>0,O16<>0,O16<>""),P16/O16,"") | U16: Подарочные сертификаты
F17: Трафик | I17: =Центрум!I17/График!AJ29*График!AJ27 -> 351.60142 | J17: =I48 -> 258.4 | K17: =IF(AND(I17<>"",I17<>0,J17<>""),J17/I17,"") -> 0.73492308 | L17: =J17/J14*I14 -> 143.55556 | M17: =IF(AND(I17<>"",I17<>0,L17<>"",L17<>0),L17/I17,"") -> 0.4082906 | N17: =IF(AND(J17<>0,J17<>"",I17<>0,I17<>""),L17-I17,"") -> -208.04587 | P17: =IF(AND(O17<>"",O17<>0,L17<>"",L17<>0),-O17+L17,"") | Q17: =IF(AND(P17<>"",P17<>0,O17<>0,O17<>""),P17/O17,"")
K18: =IF(AND(I18<>"",I18<>0,J18<>""),J18/I18,"") | L18: =J18 -> 0 | M18: =IF(AND(I18<>"",I18<>0,L18<>"",L18<>0),L18/I18,"") | N18: =IF(AND(J18<>0,J18<>"",I18<>0,I18<>""),L18-I18,"") | O18: 0 | P18: =IF(AND(O18<>"",O18<>0,L18<>"",L18<>0),-O18+L18,"") | Q18: =IF(AND(P18<>"",P18<>0,O18<>0,O18<>""),P18/O18,"")
K19: =IF(AND(I19<>"",I19<>0,J19<>""),J19/I19,"") | L19: =J19 -> 0 | M19: =IF(AND(I19<>"",I19<>0,L19<>"",L19<>0),L19/I19,"") | N19: =IF(AND(J19<>0,J19<>"",I19<>0,I19<>""),L19-I19,"") | O19: 0 | P19: =IF(AND(O19<>"",O19<>0,L19<>"",L19<>0),-O19+L19,"") | Q19: =IF(AND(P19<>"",P19<>0,O19<>0,O19<>""),P19/O19,"") | U19: =U18/I16 -> #DIV/0!
F20: Конверсия план/факт | I20: =Центрум!I20 -> 0.09 | J20: =S48 -> 0.11996904 | K20: =J20/I20 -> 1.3329893 | L20: =IF(AND(K8<>0,I14<>0,I48<>0),(I48*S48+(I48/K8-I48)*I20)/(I48/K8),0) -> 0.11262345 | M20: =IF(AND(I20<>"",I20<>0,L20<>"",L20<>0),L20/I20,"") -> 1.2513717 | N20: =IF(AND(J20<>0,J20<>"",I20<>0,I20<>""),L20-I20,"") -> 0.022623454 | P20: =IF(AND(O20<>"",O20<>0,L20<>"",L20<>0),-O20+L20,"") | Q20: =IF(AND(P20<>"",P20<>0,O20<>0,O20<>""),P20/O20,"")
B22: Факт продаж за месяц | T22: % выполнения дневного плана | U22: Раcпределение плана по дням
B23: Дата | C23: День недели | D23: Выручка (руб) | E23: Кол-во единиц (шт.) | F23: Средняя стоимость изделия (руб.) | G23: Количество чеков (шт.) | H23: Средняя сумма чека (руб.) | I23: Трафик | J23: Длина чека (шт.) | K23: UNOde50 | L23: IS | M23: Agafi | N23: Kalliope | O23: Raganella | P23: CC/MP | Q23: Eva Rites | R23: Antura | S23: Конверсия (%) | U23: выручка, план | V23: кол-во ед, план | W23: Кол-во чеков, план | X23: выручка, скорректир.план | Y23: кол-во ед, скорр. план | Z23: кол-во чеков, скорр. план | AA23: Коэфф. Дня Недели | AB23: Специфика месяца
B24: 1 | C24: 2 | D24: 3 | E24: в | F24: 5 | G24: 6 | H24: 7 | I24: 8 | J24: 9 | K24: 10 | L24: 11 | M24: 12 | N24: 13 | O24: 14 | P24: 15 | Q24: 16 | R24: 17 | S24: 18 | U24: 1 | V24: 2 | W24: 3 | X24: 4 | Y24: 5 | Z24: 6 | AA24: 10 | AB24: 11
A25: 1 | B25: 46024 | C25: пт | D25: =8593+12006+2311 -> 22910 | E25: 3 | F25: =IF(AND(E25<>"",E25<>0),D25/E25,"") -> 7636.6667 | G25: 2 | H25: =IF(AND(G25<>"",G25<>0),D25/G25,"") -> 11455 | I25: 26 | J25: =IF(AND(G25<>"",G25<>0),E25/G25,"") -> 1.5 | S25: =IF(AND(I25<>"",I25<>0),G25/I25,"") -> 0.076923077 | T25: =D25/U25 -> 1.2260063 | U25: =$I$8*AA25*AB25/SUMPRODUCT($AB$25:$AB$55,$AA$25:$AA$55) -> 18686.69 | V25: =$I$9*AA25*AB25/SUMPRODUCT($AB$25:$AB$55,$AA$25:$AA$55) -> 2.8313167 | W25: =IF($I$12="","",V25/$I$12) -> 1.6654804 | X25: =IF(AB25<>"",IF(D25<>"",D25,($I$8-SUM($X24:X$25))*AA25*AB25/SUMPRODUCT($AB25:$AB$55,$AA25:$AA$55)),"") -> 22910 | Y25: =IF(AB25<>"",IF(E25<>"",E25,($I$9-SUM($Y24:Y$25))*AA25*AB25/SUMPRODUCT($AB25:$AB$55,$AA25:$AA$55)),"") -> 3 | Z25: =IF(AB25<>"",IF($I$12<>"",IF(G25<>"",G25,($I$9/$I$12-SUM($Z24:Z$25))*AA25*AB25/SUMPRODUCT($AB25:$AB$55,$AA25:$AA$55)),""),"") -> 2 | AA25: 1 | AB25: 1
A26: 2 | B26: 46025 | C26: сб | D26: =6082+8693 -> 14775 | E26: 2 | F26: =IF(AND(E26<>"",E26<>0),D26/E26,"") -> 7387.5 | G26: 2 | H26: =IF(AND(G26<>"",G26<>0),D26/G26,"") -> 7387.5 | I26: 25 | J26: =IF(AND(G26<>"",G26<>0),E26/G26,"") -> 1 | Q26: 8693 | S26: =IF(AND(I26<>"",I26<>0),G26/I26,"") -> 0.08 | T26: =D26/U26 -> 0.79066971 | U26: =$I$8*AA26*AB26/SUMPRODUCT($AB$25:$AB$55,$AA$25:$AA$55) -> 18686.69 | V26: =$I$9*AA26*AB26/SUMPRODUCT($AB$25:$AB$55,$AA$25:$AA$55) -> 2.8313167 | W26: =IF($I$12="","",V26/$I$12) -> 1.6654804 | X26: =IF(AB26<>"",IF(D26<>"",D26,($I$8-SUM($X$25:X25))*AA26*AB26/SUMPRODUCT($AB26:$AB$55,$AA26:$AA$55)),"") -> 14775 | Y26: =IF(AB26<>"",IF(E26<>"",E26,($I$9-SUM($Y$25:Y25))*AA26*AB26/SUMPRODUCT($AB26:$AB$55,$AA26:$AA$55)),"") -> 2 | Z26: =IF(AB26<>"",IF($I$12<>"",IF(G26<>"",G26,($I$9/$I$12-SUM($Z$25:Z25))*AA26*AB26/SUMPRODUCT($AB26:$AB$55,$AA26:$AA$55)),""),"") -> 2 | AA26: 1 | AB26: 1
A27: 3 | B27: 46026 | C27: вс | D27: 10384 | E27: 2 | F27: =IF(AND(E27<>"",E27<>0),D27/E27,"") -> 5192 | G27: 1 | H27: =IF(AND(G27<>"",G27<>0),D27/G27,"") -> 10384 | I27: 30 | J27: =IF(AND(G27<>"",G27<>0),E27/G27,"") -> 2 | S27: =IF(AND(I27<>"",I27<>0),G27/I27,"") -> 0.033333333 | T27: =D27/U27 -> 0.73447447 | U27: 14138 | V27: 4 | W27: 2 | X27: 16611 | Y27: 3 | Z27: 3 | AA27: 1 | AB27: 1
A28: 4 | B28: 46029 | C28: ср | D28: =5693+2692 -> 8385 | E28: 2 | F28: =IF(AND(E28<>"",E28<>0),D28/E28,"") -> 4192.5 | G28: 2 | H28: =IF(AND(G28<>"",G28<>0),D28/G28,"") -> 4192.5 | I28: 17 | J28: =IF(AND(G28<>"",G28<>0),E28/G28,"") -> 1 | S28: =IF(AND(I28<>"",I28<>0),G28/I28,"") -> 0.11764706 | T28: =D28/U28 -> 0.44871509 | U28: =$I$8*AA28*AB28/SUMPRODUCT($AB$25:$AB$55,$AA$25:$AA$55) -> 18686.69 | V28: =$I$9*AA28*AB28/SUMPRODUCT($AB$25:$AB$55,$AA$25:$AA$55) -> 2.8313167 | W28: =IF($I$12="","",V28/$I$12) -> 1.6654804 | X28: =IF(AB28<>"",IF(D28<>"",D28,($I$8-SUM($X$25:X27))*AA28*AB28/SUMPRODUCT($AB28:$AB$55,$AA28:$AA$55)),"") -> 8385 | Y28: =IF(AB28<>"",IF(E28<>"",E28,($I$9-SUM($Y$25:Y27))*AA28*AB28/SUMPRODUCT($AB28:$AB$55,$AA28:$AA$55)),"") -> 2 | Z28: =IF(AB28<>"",IF($I$12<>"",IF(G28<>"",G28,($I$9/$I$12-SUM($Z$25:Z27))*AA28*AB28/SUMPRODUCT($AB28:$AB$55,$AA28:$AA$55)),""),"") -> 2 | AA28: 1 | AB28: 1
A29: 5 | B29: 46030 | C29: чт | D29: =8085+5293 -> 13378 | E29: 3 | F29: =IF(AND(E29<>"",E29<>0),D29/E29,"") -> 4459.3333 | G29: 2 | H29: =IF(AND(G29<>"",G29<>0),D29/G29,"") -> 6689 | I29: 21 | J29: =IF(AND(G29<>"",G29<>0),E29/G29,"") -> 1.5 | S29: =IF(AND(I29<>"",I29<>0),G29/I29,"") -> 0.095238095 | T29: =D29/U29 -> 0.71591061 | U29: =$I$8*AA29*AB29/SUMPRODUCT($AB$25:$AB$55,$AA$25:$AA$55) -> 18686.69 | V29: =$I$9*AA29*AB29/SUMPRODUCT($AB$25:$AB$55,$AA$25:$AA$55) -> 2.8313167 | W29: =IF($I$12="","",V29/$I$12) -> 1.6654804 | X29: =IF(AB29<>"",IF(D29<>"",D29,($I$8-SUM($X$25:X28))*AA29*AB29/SUMPRODUCT($AB29:$AB$55,$AA29:$AA$55)),"") -> 13378 | Y29: =IF(AB29<>"",IF(E29<>"",E29,($I$9-SUM($Y$25:Y28))*AA29*AB29/SUMPRODUCT($AB29:$AB$55,$AA29:$AA$55)),"") -> 3 | Z29: =IF(AB29<>"",IF($I$12<>"",IF(G29<>"",G29,($I$9/$I$12-SUM($Z$25:Z28))*AA29*AB29/SUMPRODUCT($AB29:$AB$55,$AA29:$AA$55)),""),"") -> 2 | AA29: 1 | AB29: 1
A30: 6 | B30: 46031 | C30: пт | D30: =4806+10684+4693 -> 20183 | E30: 4 | F30: =IF(AND(E30<>"",E30<>0),D30/E30,"") -> 5045.75 | G30: 3 | H30: =IF(AND(G30<>"",G30<>0),D30/G30,"") -> 6727.6667 | I30: 25 | J30: =IF(AND(G30<>"",G30<>0),E30/G30,"") -> 1.3333333 | S30: =IF(AND(I30<>"",I30<>0),G30/I30,"") -> 0.12 | T30: =D30/U30 -> 1.0800735 | U30: =$I$8*AA30*AB30/SUMPRODUCT($AB$25:$AB$55,$AA$25:$AA$55) -> 18686.69 | V30: =$I$9*AA30*AB30/SUMPRODUCT($AB$25:$AB$55,$AA$25:$AA$55) -> 2.8313167 | W30: =IF($I$12="","",V30/$I$12) -> 1.6654804 | X30: =IF(AB30<>"",IF(D30<>"",D30,($I$8-SUM($X$25:X29))*AA30*AB30/SUMPRODUCT($AB30:$AB$55,$AA30:$AA$55)),"") -> 20183 | Y30: =IF(AB30<>"",IF(E30<>"",E30,($I$9-SUM($Y$25:Y29))*AA30*AB30/SUMPRODUCT($AB30:$AB$55,$AA30:$AA$55)),"") -> 4 | Z30: =IF(AB30<>"",IF($I$12<>"",IF(G30<>"",G30,($I$9/$I$12-SUM($Z$25:Z29))*AA30*AB30/SUMPRODUCT($AB30:$AB$55,$AA30:$AA$55)),""),"") -> 3 | AA30: 1 | AB30: 1
A31: 7 | B31: 46033 | C31: вс | D31: 0 | E31: 0 | F31: =IF(AND(E31<>"",E31<>0),D31/E31,"") | G31: 0 | H31: =IF(AND(G31<>"",G31<>0),D31/G31,"") | I31: 15 | J31: =IF(AND(G31<>"",G31<>0),E31/G31,"") | S31: =IF(AND(I31<>"",I31<>0),G31/I31,"") -> 0 | T31: =D31/U31 -> 0 | U31: =$I$8*AA31*AB31/SUMPRODUCT($AB$25:$AB$55,$AA$25:$AA$55) -> 18686.69 | V31: =$I$9*AA31*AB31/SUMPRODUCT($AB$25:$AB$55,$AA$25:$AA$55) -> 2.8313167 | W31: =IF($I$12="","",V31/$I$12) -> 1.6654804 | X31: =IF(AB31<>"",IF(D31<>"",D31,($I$8-SUM($X$25:X30))*AA31*AB31/SUMPRODUCT($AB31:$AB$55,$AA31:$AA$55)),"") -> 0 | Y31: =IF(AB31<>"",IF(E31<>"",E31,($I$9-SUM($Y$25:Y30))*AA31*AB31/SUMPRODUCT($AB31:$AB$55,$AA31:$AA$55)),"") -> 0 | Z31: =IF(AB31<>"",IF($I$12<>"",IF(G31<>"",G31,($I$9/$I$12-SUM($Z$25:Z30))*AA31*AB31/SUMPRODUCT($AB31:$AB$55,$AA31:$AA$55)),""),"") -> 0 | AA31: 1 | AB31: 1
A32: 8 | B32: 46034 | C32: пн | D32: 6565 | E32: 1 | F32: =IF(AND(E32<>"",E32<>0),D32/E32,"") -> 6565 | G32: 1 | H32: =IF(AND(G32<>"",G32<>0),D32/G32,"") -> 6565 | I32: 26 | J32: =IF(AND(G32<>"",G32<>0),E32/G32,"") -> 1 | S32: =IF(AND(I32<>"",I32<>0),G32/I32,"") -> 0.038461538 | T32: =D32/U32 -> 0.35131957 | U32: =$I$8*AA32*AB32/SUMPRODUCT($AB$25:$AB$55,$AA$25:$AA$55) -> 18686.69 | V32: =$I$9*AA32*AB32/SUMPRODUCT($AB$25:$AB$55,$AA$25:$AA$55) -> 2.8313167 | W32: =IF($I$12="","",V32/$I$12) -> 1.6654804 | X32: =IF(AB32<>"",IF(D32<>"",D32,($I$8-SUM($X$25:X31))*AA32*AB32/SUMPRODUCT($AB32:$AB$55,$AA32:$AA$55)),"") -> 6565 | Y32: =IF(AB32<>"",IF(E32<>"",E32,($I$9-SUM($Y$25:Y31))*AA32*AB32/SUMPRODUCT($AB32:$AB$55,$AA32:$AA$55)),"") -> 1 | Z32: =IF(AB32<>"",IF($I$12<>"",IF(G32<>"",G32,($I$9/$I$12-SUM($Z$25:Z31))*AA32*AB32/SUMPRODUCT($AB32:$AB$55,$AA32:$AA$55)),""),"") -> 1 | AA32: 1 | AB32: 1
A33: 9 | B33: 46037 | C33: чт | D33: 17806 | E33: 2 | F33: =IF(AND(E33<>"",E33<>0),D33/E33,"") -> 8903 | G33: 2 | H33: =IF(AND(G33<>"",G33<>0),D33/G33,"") -> 8903 | I33: 17 | J33: =IF(AND(G33<>"",G33<>0),E33/G33,"") -> 1 | L33: 17806 | S33: =IF(AND(I33<>"",I33<>0),G33/I33,"") -> 0.11764706 | T33: =D33/U33 -> 0.95287071 | U33: =$I$8*AA33*AB33/SUMPRODUCT($AB$25:$AB$55,$AA$25:$AA$55) -> 18686.69 | V33: =$I$9*AA33*AB33/SUMPRODUCT($AB$25:$AB$55,$AA$25:$AA$55) -> 2.8313167 | W33: =IF($I$12="","",V33/$I$12) -> 1.6654804 | X33: =IF(AB33<>"",IF(D33<>"",D33,($I$8-SUM($X$25:X32))*AA33*AB33/SUMPRODUCT($AB33:$AB$55,$AA33:$AA$55)),"") -> 17806 | Y33: =IF(AB33<>"",IF(E33<>"",E33,($I$9-SUM($Y$25:Y32))*AA33*AB33/SUMPRODUCT($AB33:$AB$55,$AA33:$AA$55)),"") -> 2 | Z33: =IF(AB33<>"",IF($I$12<>"",IF(G33<>"",G33,($I$9/$I$12-SUM($Z$25:Z32))*AA33*AB33/SUMPRODUCT($AB33:$AB$55,$AA33:$AA$55)),""),"") -> 2 | AA33: 1 | AB33: 1
A34: 10 | B34: 46038 | C34: пт | D34: 6322 | E34: 1 | F34: =IF(AND(E34<>"",E34<>0),D34/E34,"") -> 6322 | G34: 1 | H34: =IF(AND(G34<>"",G34<>0),D34/G34,"") -> 6322 | I34: 12 | J34: =IF(AND(G34<>"",G34<>0),E34/G34,"") -> 1 | S34: =IF(AND(I34<>"",I34<>0),G34/I34,"") -> 0.083333333 | T34: =D34/U34 -> 0.33831566 | U34: =$I$8*AA34*AB34/SUMPRODUCT($AB$25:$AB$55,$AA$25:$AA$55) -> 18686.69 | V34: =$I$9*AA34*AB34/SUMPRODUCT($AB$25:$AB$55,$AA$25:$AA$55) -> 2.8313167 | W34: =IF($I$12="","",V34/$I$12) -> 1.6654804 | X34: =IF(AB34<>"",IF(D34<>"",D34,($I$8-SUM($X$25:X33))*AA34*AB34/SUMPRODUCT($AB34:$AB$55,$AA34:$AA$55)),"") -> 6322 | Y34: =IF(AB34<>"",IF(E34<>"",E34,($I$9-SUM($Y$25:Y33))*AA34*AB34/SUMPRODUCT($AB34:$AB$55,$AA34:$AA$55)),"") -> 1 | Z34: =IF(AB34<>"",IF($I$12<>"",IF(G34<>"",G34,($I$9/$I$12-SUM($Z$25:Z33))*AA34*AB34/SUMPRODUCT($AB34:$AB$55,$AA34:$AA$55)),""),"") -> 1 | AA34: 1 | AB34: 1
A35: 11 | B35: 46041 | C35: пн | D35: 6267 | E35: 1 | F35: =IF(AND(E35<>"",E35<>0),D35/E35,"") -> 6267 | G35: 1 | H35: =IF(AND(G35<>"",G35<>0),D35/G35,"") -> 6267 | I35: 17 | J35: =IF(AND(G35<>"",G35<>0),E35/G35,"") -> 1 | R35: 6267 | S35: =IF(AND(I35<>"",I35<>0),G35/I35,"") -> 0.058823529 | T35: =D35/U35 -> 0.33537239 | U35: =$I$8*AA35*AB35/SUMPRODUCT($AB$25:$AB$55,$AA$25:$AA$55) -> 18686.69 | V35: =$I$9*AA35*AB35/SUMPRODUCT($AB$25:$AB$55,$AA$25:$AA$55) -> 2.8313167 | W35: =IF($I$12="","",V35/$I$12) -> 1.6654804 | X35: =IF(AB35<>"",IF(D35<>"",D35,($I$8-SUM($X$25:X34))*AA35*AB35/SUMPRODUCT($AB35:$AB$55,$AA35:$AA$55)),"") -> 6267 | Y35: =IF(AB35<>"",IF(E35<>"",E35,($I$9-SUM($Y$25:Y34))*AA35*AB35/SUMPRODUCT($AB35:$AB$55,$AA35:$AA$55)),"") -> 1 | Z35: =IF(AB35<>"",IF($I$12<>"",IF(G35<>"",G35,($I$9/$I$12-SUM($Z$25:Z34))*AA35*AB35/SUMPRODUCT($AB35:$AB$55,$AA35:$AA$55)),""),"") -> 1 | AA35: 1 | AB35: 1
A36: 12 | B36: 46042 | C36: вт | D36: 0 | E36: 0 | F36: =IF(AND(E36<>"",E36<>0),D36/E36,"") | G36: 0 | H36: =IF(AND(G36<>"",G36<>0),D36/G36,"") | I36: 16 | J36: =IF(AND(G36<>"",G36<>0),E36/G36,"") | S36: =IF(AND(I36<>"",I36<>0),G36/I36,"") -> 0 | T36: =D36/U36 -> 0 | U36: =$I$8*AA36*AB36/SUMPRODUCT($AB$25:$AB$55,$AA$25:$AA$55) -> 18686.69 | V36: =$I$9*AA36*AB36/SUMPRODUCT($AB$25:$AB$55,$AA$25:$AA$55) -> 2.8313167 | W36: =IF($I$12="","",V36/$I$12) -> 1.6654804 | X36: =IF(AB36<>"",IF(D36<>"",D36,($I$8-SUM($X$25:X35))*AA36*AB36/SUMPRODUCT($AB36:$AB$55,$AA36:$AA$55)),"") -> 0 | Y36: =IF(AB36<>"",IF(E36<>"",E36,($I$9-SUM($Y$25:Y35))*AA36*AB36/SUMPRODUCT($AB36:$AB$55,$AA36:$AA$55)),"") -> 0 | Z36: =IF(AB36<>"",IF($I$12<>"",IF(G36<>"",G36,($I$9/$I$12-SUM($Z$25:Z35))*AA36*AB36/SUMPRODUCT($AB36:$AB$55,$AA36:$AA$55)),""),"") -> 0 | AA36: 1 | AB36: 1
A37: 13 | B37: 46043 | C37: ср | D37: 8493 | E37: 1 | F37: =IF(AND(E37<>"",E37<>0),D37/E37,"") -> 8493 | G37: 1 | H37: =IF(AND(G37<>"",G37<>0),D37/G37,"") -> 8493 | I37: 12 | J37: =IF(AND(G37<>"",G37<>0),E37/G37,"") -> 1 | S37: =IF(AND(I37<>"",I37<>0),G37/I37,"") -> 0.083333333 | T37: =D37/U37 -> 0.45449461 | U37: =$I$8*AA37*AB37/SUMPRODUCT($AB$25:$AB$55,$AA$25:$AA$55) -> 18686.69 | V37: =$I$9*AA37*AB37/SUMPRODUCT($AB$25:$AB$55,$AA$25:$AA$55) -> 2.8313167 | W37: =IF($I$12="","",V37/$I$12) -> 1.6654804 | X37: =IF(AB37<>"",IF(D37<>"",D37,($I$8-SUM($X$25:X36))*AA37*AB37/SUMPRODUCT($AB37:$AB$55,$AA37:$AA$55)),"") -> 8493 | Y37: =IF(AB37<>"",IF(E37<>"",E37,($I$9-SUM($Y$25:Y36))*AA37*AB37/SUMPRODUCT($AB37:$AB$55,$AA37:$AA$55)),"") -> 1 | Z37: =IF(AB37<>"",IF($I$12<>"",IF(G37<>"",G37,($I$9/$I$12-SUM($Z$25:Z36))*AA37*AB37/SUMPRODUCT($AB37:$AB$55,$AA37:$AA$55)),""),"") -> 1 | AA37: 1 | AB37: 1
A38: 14 | B38: 46046 | C38: сб | D38: =27583+16383+8702 -> 52668 | E38: 5 | F38: =IF(AND(E38<>"",E38<>0),D38/E38,"") -> 10533.6 | G38: 4 | H38: =IF(AND(G38<>"",G38<>0),D38/G38,"") -> 13167 | I38: 27 | J38: =IF(AND(G38<>"",G38<>0),E38/G38,"") -> 1.25 | L38: 8702 | S38: =IF(AND(I38<>"",I38<>0),G38/I38,"") -> 0.14814815 | T38: =D38/U38 -> 2.8184766 | U38: =$I$8*AA38*AB38/SUMPRODUCT($AB$25:$AB$46,$AA$25:$AA$46) -> 18686.69 | V38: =$I$9*AA38*AB38/SUMPRODUCT($AB$25:$AB$46,$AA$25:$AA$46) -> 2.8313167 | W38: =IF($I$12="","",V38/$I$12) -> 1.6654804 | X38: =IF(AB38<>"",IF(D38<>"",D38,($I$8-SUM($X$25:X37))*AA38*AB38/SUMPRODUCT($AB38:$AB$55,$AA38:$AA$55)),"") -> 52668 | Y38: =IF(AB38<>"",IF(E38<>"",E38,($I$9-SUM($Y$25:Y37))*AA38*AB38/SUMPRODUCT($AB38:$AB$55,$AA38:$AA$55)),"") -> 5 | Z38: =IF(AB38<>"",IF($I$12<>"",IF(G38<>"",G38,($I$9/$I$12-SUM($Z$25:Z37))*AA38*AB38/SUMPRODUCT($AB38:$AB$55,$AA38:$AA$55)),""),"") -> 4 | AA38: 1 | AB38: 1
A39: 15 | B39: 46047 | C39: вс | D39: 23266 | E39: 4 | F39: =IF(AND(E39<>"",E39<>0),D39/E39,"") -> 5816.5 | G39: 1 | H39: =IF(AND(G39<>"",G39<>0),D39/G39,"") -> 23266 | I39: 24 | J39: =IF(AND(G39<>"",G39<>0),E39/G39,"") -> 4 | S39: =IF(AND(I39<>"",I39<>0),G39/I39,"") -> 0.041666667 | T39: =D39/U39 -> 1.2450573 | U39: =$I$8*AA39*AB39/SUMPRODUCT($AB$25:$AB$46,$AA$25:$AA$46) -> 18686.69 | V39: =$I$9*AA39*AB39/SUMPRODUCT($AB$25:$AB$46,$AA$25:$AA$46) -> 2.8313167 | W39: =IF($I$12="","",V39/$I$12) -> 1.6654804 | X39: =IF(AB39<>"",IF(D39<>"",D39,($I$8-SUM($X$25:X38))*AA39*AB39/SUMPRODUCT($AB39:$AB$55,$AA39:$AA$55)),"") -> 23266 | Y39: =IF(AB39<>"",IF(E39<>"",E39,($I$9-SUM($Y$25:Y38))*AA39*AB39/SUMPRODUCT($AB39:$AB$55,$AA39:$AA$55)),"") -> 4 | Z39: =IF(AB39<>"",IF($I$12<>"",IF(G39<>"",G39,($I$9/$I$12-SUM($Z$25:Z38))*AA39*AB39/SUMPRODUCT($AB39:$AB$55,$AA39:$AA$55)),""),"") -> 1 | AA39: 1 | AB39: 1
A40: 16 | B40: 46048 | C40: пн | D40: 0 | E40: 0 | F40: =IF(AND(E40<>"",E40<>0),D40/E40,"") | G40: 0 | H40: =IF(AND(G40<>"",G40<>0),D40/G40,"") | I40: 11 | J40: =IF(AND(G40<>"",G40<>0),E40/G40,"") | S40: =IF(AND(I40<>"",I40<>0),G40/I40,"") -> 0 | T40: =D40/U40 -> 0 | U40: =$I$8*AA40*AB40/SUMPRODUCT($AB$25:$AB$46,$AA$25:$AA$46) -> 18686.69 | V40: =$I$9*AA40*AB40/SUMPRODUCT($AB$25:$AB$46,$AA$25:$AA$46) -> 2.8313167 | W40: =IF($I$12="","",V40/$I$12) -> 1.6654804 | X40: =IF(AB40<>"",IF(D40<>"",D40,($I$8-SUM($X$25:X39))*AA40*AB40/SUMPRODUCT($AB40:$AB$55,$AA40:$AA$55)),"") -> 0 | Y40: =IF(AB40<>"",IF(E40<>"",E40,($I$9-SUM($Y$25:Y39))*AA40*AB40/SUMPRODUCT($AB40:$AB$55,$AA40:$AA$55)),"") -> 0 | Z40: =IF(AB40<>"",IF($I$12<>"",IF(G40<>"",G40,($I$9/$I$12-SUM($Z$25:Z39))*AA40*AB40/SUMPRODUCT($AB40:$AB$55,$AA40:$AA$55)),""),"") -> 0 | AA40: 1 | AB40: 1
A41: 17 | B41: 46051 | C41: чт | D41: 28447 | E41: 5 | F41: =IF(AND(E41<>"",E41<>0),D41/E41,"") -> 5689.4 | G41: 4 | H41: =IF(AND(G41<>"",G41<>0),D41/G41,"") -> 7111.75 | J41: =IF(AND(G41<>"",G41<>0),E41/G41,"") -> 1.25 | S41: =IF(AND(I41<>"",I41<>0),G41/I41,"") | T41: =D41/U41 -> 1.5223134 | U41: =$I$8*AA41*AB41/SUMPRODUCT($AB$25:$AB$46,$AA$25:$AA$46) -> 18686.69 | V41: =$I$9*AA41*AB41/SUMPRODUCT($AB$25:$AB$46,$AA$25:$AA$46) -> 2.8313167 | W41: =IF($I$12="","",V41/$I$12) -> 1.6654804 | X41: =IF(AB41<>"",IF(D41<>"",D41,($I$8-SUM($X$25:X40))*AA41*AB41/SUMPRODUCT($AB41:$AB$55,$AA41:$AA$55)),"") -> 28447 | Y41: =IF(AB41<>"",IF(E41<>"",E41,($I$9-SUM($Y$25:Y40))*AA41*AB41/SUMPRODUCT($AB41:$AB$55,$AA41:$AA$55)),"") -> 5 | Z41: =IF(AB41<>"",IF($I$12<>"",IF(G41<>"",G41,($I$9/$I$12-SUM($Z$25:Z40))*AA41*AB41/SUMPRODUCT($AB41:$AB$55,$AA41:$AA$55)),""),"") -> 4 | AA41: 1 | AB41: 1
A42: 18 | B42: 46052 | C42: пт | D42: 15477 | E42: 3 | F42: =IF(AND(E42<>"",E42<>0),D42/E42,"") -> 5159 | G42: 2 | H42: =IF(AND(G42<>"",G42<>0),D42/G42,"") -> 7738.5 | J42: =IF(AND(G42<>"",G42<>0),E42/G42,"") -> 1.5 | S42: =IF(AND(I42<>"",I42<>0),G42/I42,"") | T42: =D42/U42 -> 0.82823655 | U42: =$I$8*AA42*AB42/SUMPRODUCT($AB$25:$AB$46,$AA$25:$AA$46) -> 18686.69 | V42: =$I$9*AA42*AB42/SUMPRODUCT($AB$25:$AB$46,$AA$25:$AA$46) -> 2.8313167 | W42: =IF($I$12="","",V42/$I$12) -> 1.6654804 | X42: =IF(AB42<>"",IF(D42<>"",D42,($I$8-SUM($X$25:X41))*AA42*AB42/SUMPRODUCT($AB42:$AB$55,$AA42:$AA$55)),"") -> 15477 | Y42: =IF(AB42<>"",IF(E42<>"",E42,($I$9-SUM($Y$25:Y41))*AA42*AB42/SUMPRODUCT($AB42:$AB$55,$AA42:$AA$55)),"") -> 3 | Z42: =IF(AB42<>"",IF($I$12<>"",IF(G42<>"",G42,($I$9/$I$12-SUM($Z$25:Z41))*AA42*AB42/SUMPRODUCT($AB42:$AB$55,$AA42:$AA$55)),""),"") -> 2 | AA42: 1 | AB42: 1
A43: 19 | F43: =IF(AND(E43<>"",E43<>0),D43/E43,"") | H43: =IF(AND(G43<>"",G43<>0),D43/G43,"") | J43: =IF(AND(G43<>"",G43<>0),E43/G43,"") | S43: =IF(AND(I43<>"",I43<>0),G43/I43,"") | T43: =D43/U43 -> 0 | U43: =$I$8*AA43*AB43/SUMPRODUCT($AB$25:$AB$46,$AA$25:$AA$46) -> 18686.69 | V43: =$I$9*AA43*AB43/SUMPRODUCT($AB$25:$AB$46,$AA$25:$AA$46) -> 2.8313167 | W43: =IF($I$12="","",V43/$I$12) -> 1.6654804 | X43: =IF(AB43<>"",IF(D43<>"",D43,($I$8-SUM($X$25:X42))*AA43*AB43/SUMPRODUCT($AB43:$AB$55,$AA43:$AA$55)),"") -> 93494.117 | Y43: =IF(AB43<>"",IF(E43<>"",E43,($I$9-SUM($Y$25:Y42))*AA43*AB43/SUMPRODUCT($AB43:$AB$46,$AA43:$AA$46)),"") -> 13.795018 | Z43: =IF(AB43<>"",IF($I$12<>"",IF(G43<>"",G43,($I$9/$I$12-SUM($Z$25:Z42))*AA43*AB43/SUMPRODUCT($AB43:$AB$46,$AA43:$AA$46)),""),"") -> 0.64412811 | AA43: 1 | AB43: 1
F44: =IF(AND(E44<>"",E44<>0),D44/E44,"") | H44: =IF(AND(G44<>"",G44<>0),D44/G44,"") | J44: =IF(AND(G44<>"",G44<>0),E44/G44,"") | S44: =IF(AND(I44<>"",I44<>0),G44/I44,"") | T44: =D44/U44 -> #DIV/0! | U44: =$I$8*AA44*AB44/SUMPRODUCT($AB$25:$AB$46,$AA$25:$AA$46) -> 0 | V44: =$I$9*AA44*AB44/SUMPRODUCT($AB$25:$AB$46,$AA$25:$AA$46) -> 0 | W44: =IF($I$12="","",V44/$I$12) -> 0 | X44: =IF(AB44<>"",IF(D44<>"",D44,($I$8-SUM($X$25:X43))*AA44*AB44/SUMPRODUCT($AB44:$AB$46,$AA44:$AA$46)),"") | Y44: =IF(AB44<>"",IF(E44<>"",E44,($I$9-SUM($Y$25:Y43))*AA44*AB44/SUMPRODUCT($AB44:$AB$46,$AA44:$AA$46)),"") | Z44: =IF(AB44<>"",IF($I$12<>"",IF(G44<>"",G44,($I$9/$I$12-SUM($Z$25:Z43))*AA44*AB44/SUMPRODUCT($AB44:$AB$46,$AA44:$AA$46)),""),"")
J45: =IF(AND(G45<>"",G45<>0),E45/G45,"") | S45: =IF(AND(I45<>"",I45<>0),G45/I45,"") | T45: =D45/U45 -> #DIV/0! | U45: =$I$8*AA45*AB45/SUMPRODUCT($AB$25:$AB$46,$AA$25:$AA$46) -> 0 | V45: =$I$9*AA45*AB45/SUMPRODUCT($AB$25:$AB$46,$AA$25:$AA$46) -> 0 | W45: =IF($I$12="","",V45/$I$12) -> 0 | X45: =IF(AB45<>"",IF(D45<>"",D45,($I$8-SUM($X$25:X44))*AA45*AB45/SUMPRODUCT($AB45:$AB$46,$AA45:$AA$46)),"") | Y45: =IF(AB45<>"",IF(E45<>"",E45,($I$9-SUM($Y$25:Y44))*AA45*AB45/SUMPRODUCT($AB45:$AB$46,$AA45:$AA$46)),"") | Z45: =IF(AB45<>"",IF($I$12<>"",IF(G45<>"",G45,($I$9/$I$12-SUM($Z$25:Z44))*AA45*AB45/SUMPRODUCT($AB45:$AB$46,$AA45:$AA$46)),""),"")
C46: ср | D46: 5666 | E46: 1 | F46: =IF(AND(E46<>"",E46<>0),D46/E46,"") -> 5666 | G46: 1 | H46: =IF(AND(G46<>"",G46<>0),D46/G46,"") -> 5666 | I46: 1 | J46: =IF(AND(G46<>"",G46<>0),E46/G46,"") -> 1 | S46: =IF(AND(I46<>"",I46<>0),G46/I46,"") -> 1 | T46: =D46/U46 -> #DIV/0! | U46: =$I$8*AA46*AB46/SUMPRODUCT($AB$25:$AB$46,$AA$25:$AA$46) -> 0 | V46: =$I$9*AA46*AB46/SUMPRODUCT($AB$25:$AB$46,$AA$25:$AA$46) -> 0 | W46: =IF($I$12="","",V46/$I$12) -> 0 | X46: =IF(AB46<>"",IF(D46<>"",D46,($I$8-SUM($X$25:X45))*AA46*AB46/SUMPRODUCT($AB46:$AB$46,$AA46:$AA$46)),"") | Y46: =IF(AB46<>"",IF(E46<>"",E46,($I$9-SUM($Y$25:Y39))*AA46*AB46/SUMPRODUCT($AB46:$AB$46,$AA46:$AA$46)),"") | Z46: =IF(AB46<>"",IF($I$12<>"",IF(G46<>"",G46,($I$9/$I$12-SUM($Z$25:Z39))*AA46*AB46/SUMPRODUCT($AB46:$AB$46,$AA46:$AA$46)),""),"")
B47: 46036 | C47: сб | D47: 7031 | E47: 1 | F47: =IF(AND(E47<>"",E47<>0),D47/E47,"") -> 7031 | G47: 1 | H47: =IF(AND(G47<>"",G47<>0),D47/G47,"") -> 7031 | I47: 1 | J47: =IF(AND(G47<>"",G47<>0),E47/G47,"") -> 1 | S47: =IF(AND(I47<>"",I47<>0),G47/I47,"") -> 1 | T47: =D47/U47 -> #DIV/0! | U47: =$I$8*AA47*AB47/SUMPRODUCT($AB$25:$AB$46,$AA$25:$AA$46) -> 0 | V47: =$I$9*AA47*AB47/SUMPRODUCT($AB$25:$AB$46,$AA$25:$AA$46) -> 0 | W47: =IF($I$12="","",V47/$I$12) -> 0 | X47: =IF(AB47<>"",IF(D47<>"",D47,($I$8-SUM($X$25:X46))*AA47*AB47/SUMPRODUCT($AB$46:$AB47,$AA$46:$AA47)),"") | Y47: =IF(AB47<>"",IF(E47<>"",E47,($I$9-SUM($Y$25:Y40))*AA47*AB47/SUMPRODUCT($AB$46:$AB47,$AA$46:$AA47)),"") | Z47: =IF(AB47<>"",IF($I$12<>"",IF(G47<>"",G47,($I$9/$I$12-SUM($Z$25:Z40))*AA47*AB47/SUMPRODUCT($AB$46:$AB47,$AA$46:$AA47)),""),"")
B48: 46032 | D48: =SUM(D25:D47) -> 268023 | E48: =SUM(E25:E47) -> 41 | F48: =IF(AND(E48<>"",E48<>0),D48/E48,"") -> 6537.1463 | G48: =SUM(G25:G47) -> 31 | H48: =IF(AND(G48<>"",G48<>0),D48/G48,"") -> 8645.9032 | I48: =SUM(I25:I47)*0.8 -> 258.4 | J48: =IF(AND(G48<>"",G48<>0),E48/G48,"") -> 1.3225806 | K48: =SUM(K25:K47) -> 0 | L48: =SUM(L25:L47) -> 26508 | M48: =SUM(M25:M47) -> 0 | N48: =SUM(N25:N47) -> 0 | O48: =SUM(O25:O47) -> 0 | P48: =SUM(P25:P47) -> 0 | Q48: =SUM(Q25:Q47) -> 8693 | R48: =SUM(R25:R47) -> 6267 | S48: =IF(AND(I48<>"",I48<>0),G48/I48,"") -> 0.11996904 | T48: =D48/U48 -> 0.76469102 | U48: =SUM(U25:U47) -> 350498.43 | V48: =SUM(V25:V47) -> 54.963701 | W48: =SUM(W25:W47) -> 31.978648 | X48: =SUM(X25:X47) -> 355047.12 | Y48: =SUM(Y25:Y47) -> 53.795018 | Z48: =SUM(Z25:Z47) -> 31.644128
B49: итого | D49: =SUMIF(D25:D47,"",U25:U47)+D48 -> 286709.69

Sheet Доп сотрудник
B1: =TODAY()-1 -> 46170
B2: (отчетная дата) | J2: ЕЖЕДНЕВНЫЙ ОТЧЕТ О ПРОДАЖАХ
B3: Осталось до выполнения плана!!! | J3: =График!B24 -> 0
C4: =I8-D48 -> -132872 | E4: =IF(I8<>0,C4/I8,0) -> 0
F6: Целевые показатели
F7: Показатель | I7: План | J7: Факт | K7: % выполнения | L7: Прогноз выполнения | M7: % выполнения по прогнозу | N7: Отклонение | O7: Факт аналогичного месяца прошлого года | P7: Отклонение LFL
F8: Выручка | I8: =Центрум!I8/График!AJ29*График!AJ24 -> 0 | J8: =D48 -> 132872 | K8: =IF(AND(I8<>"",I8<>0,J8<>""),J8/I8,"") | L8: =IF(SUMIF($D$25:$D$47,">=0",$U$25:$U$47)<>0,I8*D48/SUMIF($D$25:$D$47,">=0",$U$25:$U$47),0) -> 0 | M8: =L8/I8 -> #DIV/0! | N8: =IF(AND(J8<>0,J8<>"",I8<>0,I8<>""),L8-I8,"") | P8: =IF(AND(O8<>"",O8<>0,L8<>"",L8<>0),-O8+L8,"") | Q8: =IF(AND(P8<>"",P8<>0,O8<>0,O8<>""),P8/O8,"")
F9: Кол-во изделий | I9: =I8/I11 -> 0 | J9: =E48 -> 13 | K9: =IF(AND(I9<>"",I9<>0,J9<>""),J9/I9,"") | L9: =IF(SUMIF($E$25:$E$47,">=0",$V$25:$V$47)<>0,I9*E48/SUMIF($E$25:$E$47,">=0",$V$25:$V$47),0) -> 0 | M9: =IF(AND(I9<>"",I9<>0,L9<>"",L9<>0),L9/I9,"") | N9: =IF(AND(J9<>0,J9<>"",I9<>0,I9<>""),L9-I9,"") | P9: =IF(AND(O9<>"",O9<>0,L9<>"",L9<>0),-O9+L9,"") | Q9: =IF(AND(P9<>"",P9<>0,O9<>0,O9<>""),P9/O9,"")
F10: Средний чек | I10: =I11*I12 -> 11220 | J10: =H48 -> 16609 | K10: =IF(AND(I10<>"",I10<>0,J10<>""),J10/I10,"") -> 1.480303 | L10: =J10 -> 16609 | M10: =IF(AND(I10<>"",I10<>0,L10<>"",L10<>0),L10/I10,"") -> 1.480303 | N10: =IF(AND(J10<>0,J10<>"",I10<>0,I10<>""),L10-I10,"") -> 5389 | O10: =O11*O12 -> 0 | P10: =IF(AND(O10<>"",O10<>0,L10<>"",L10<>0),-O10+L10,"") | Q10: =IF(AND(P10<>"",P10<>0,O10<>0,O10<>""),P10/O10,"")
F11: Средняя стоимость изделия | I11: =Центрум!I11 -> 6600 | J11: =F48 -> 10220.923 | K11: =IF(AND(I11<>"",I11<>0,J11<>""),J11/I11,"") -> 1.5486247 | L11: =IF(L9>0,L8/L9,"") | M11: =IF(AND(I11<>"",I11<>0,L11<>"",L11<>0),L11/I11,"") | N11: =IF(AND(J11<>0,J11<>"",I11<>0,I11<>""),L11-I11,"") -> #VALUE! | P11: =IF(AND(O11<>"",O11<>0,L11<>"",L11<>0),-O11+L11,"") | Q11: =IF(AND(P11<>"",P11<>0,O11<>0,O11<>""),P11/O11,"")
F12: Длина чека | I12: ='Центрум'!I12 -> 1.7 | J12: =J48 -> 1.625 | K12: =IF(AND(I12<>"",I12<>0,J12<>""),J12/I12,"") -> 0.95588235 | L12: =J12 -> 1.625 | M12: =IF(AND(I12<>"",I12<>0,L12<>"",L12<>0),L12/I12,"") -> 0.95588235 | N12: =IF(AND(J12<>0,J12<>"",I12<>0,I12<>""),L12-I12,"") -> -0.075 | P12: =IF(AND(O12<>"",O12<>0,L12<>"",L12<>0),-O12+L12,"") | Q12: =IF(AND(P12<>"",P12<>0,O12<>0,O12<>""),P12/O12,"")
F13: Кол-во чеков | I13: =IF(I12<>0,I9/I12,"") -> 0 | J13: =G48 -> 8 | K13: =IF(AND(I13<>"",I13<>0,J13<>""),J13/I13,"") | L13: =IF(SUMIF($G$25:$G$47,">=0",$W$25:$W$47)<>0,I13*G48/SUMIF($G$25:$G$47,">=0",$W$25:$W$47),"") | M13: =IF(AND(I13<>"",I13<>0,L13<>"",L13<>0),L13/I13,"") | N13: =IF(AND(J13<>0,J13<>"",I13<>0,I13<>""),L13-I13,"") | P13: =IF(AND(O13<>"",O13<>0,L13<>"",L13<>0),-O13+L13,"") | Q13: =IF(AND(P13<>"",P13<>0,O13<>0,O13<>""),P13/O13,"")
F14: Кол-во смен план/отработано | I14: =График!AI24 -> 0 | J14: 5 | K14: =IF(AND(I14<>"",I14<>0,J14<>""),J14/I14,"") | L14: =IF(SUMIF($D$25:$D$47,">=0",$U$25:$U$47),I48*I8/SUMIF($D$25:$D$47,">=0",$U$25:$U$47),"") | M14: =IF(AND(I14<>"",I14<>0,L14<>"",L14<>0),L14/I14,"") | N14: =IF(AND(J14<>0,J14<>"",I14<>0,I14<>""),L14-I14,"") | P14: =IF(AND(O14<>"",O14<>0,L14<>"",L14<>0),-O14+L14,"") | Q14: =IF(AND(P14<>"",P14<>0,O14<>0,O14<>""),P14/O14,"")
F15: Средние продажи в смену | I15: =Центрум!I15 -> 61890.968 | J15: =J8/J14 -> 26574.4 | K15: =IF(AND(I15<>"",I15<>0,J15<>""),J15/I15,"") -> 0.42937445 | L15: =J15 -> 26574.4 | M15: =IF(AND(I15<>"",I15<>0,L15<>"",L15<>0),L15/I15,"") -> 0.42937445 | N15: =IF(AND(J15<>0,J15<>"",I15<>0,I15<>""),L15-I15,"") -> -35316.568 | P15: =IF(AND(O15<>"",O15<>0,L15<>"",L15<>0),-O15+L15,"") | Q15: =IF(AND(P15<>"",P15<>0,O15<>0,O15<>""),P15/O15,"")
F16: Отставание/Перевыполнение | J16: =J8-I15*J14 -> -176582.84 | K16: =IF(AND(I16<>"",I16<>0,J16<>""),J16/I16,"") | L16: =J16 -> -176582.84 | M16: =IF(AND(I16<>"",I16<>0,L16<>"",L16<>0),L16/I16,"") | N16: =IF(AND(J16<>0,J16<>"",I16<>0,I16<>""),L16-I16,"") | P16: =IF(AND(O16<>"",O16<>0,L16<>"",L16<>0),-O16+L16,"") | Q16: =IF(AND(P16<>"",P16<>0,O16<>0,O16<>""),P16/O16,"") | T16: Подарочные сертификаты
F17: Трафик | I17: =Центрум!I17/График!AJ29*График!AJ24 -> 0 | J17: =I48 -> 82.4 | K17: =IF(AND(I17<>"",I17<>0,J17<>""),J17/I17,"") | L17: =J17/J14*I14 -> 0 | M17: =IF(AND(I17<>"",I17<>0,L17<>"",L17<>0),L17/I17,"") | N17: =IF(AND(J17<>0,J17<>"",I17<>0,I17<>""),L17-I17,"") | P17: =IF(AND(O17<>"",O17<>0,L17<>"",L17<>0),-O17+L17,"") | Q17: =IF(AND(P17<>"",P17<>0,O17<>0,O17<>""),P17/O17,"")
K18: =IF(AND(I18<>"",I18<>0,J18<>""),J18/I18,"") | L18: =J18 -> 0 | M18: =IF(AND(I18<>"",I18<>0,L18<>"",L18<>0),L18/I18,"") | N18: =IF(AND(J18<>0,J18<>"",I18<>0,I18<>""),L18-I18,"") | O18: 0 | P18: =IF(AND(O18<>"",O18<>0,L18<>"",L18<>0),-O18+L18,"") | Q18: =IF(AND(P18<>"",P18<>0,O18<>0,O18<>""),P18/O18,"")
J19: =Q48 -> 0 | K19: =IF(AND(I19<>"",I19<>0,J19<>""),J19/I19,"") | L19: =J19 -> 0 | M19: =IF(AND(I19<>"",I19<>0,L19<>"",L19<>0),L19/I19,"") | N19: =IF(AND(J19<>0,J19<>"",I19<>0,I19<>""),L19-I19,"") | O19: 0 | P19: =IF(AND(O19<>"",O19<>0,L19<>"",L19<>0),-O19+L19,"") | Q19: =IF(AND(P19<>"",P19<>0,O19<>0,O19<>""),P19/O19,"") | T19: =T18/I16 -> #DIV/0!
F20: Конверсия план/факт | I20: =Центрум!I20 -> 0.09 | J20: =S48 -> 0.097087379 | K20: =J20/I20 -> 1.0787487 | L20: =IF(AND(K8<>0,I14<>0,I48<>0),(I48*S48+(I48/K8-I48)*I20)/(I48/K8),0) -> 0 | M20: =IF(AND(I20<>"",I20<>0,L20<>"",L20<>0),L20/I20,"") | N20: =IF(AND(J20<>0,J20<>"",I20<>0,I20<>""),L20-I20,"") -> -0.09 | P20: =IF(AND(O20<>"",O20<>0,L20<>"",L20<>0),-O20+L20,"") | Q20: =IF(AND(P20<>"",P20<>0,O20<>0,O20<>""),P20/O20,"")
B22: Факт продаж за месяц | T22: % выполнения дневного плана | U22: Раcпределение плана по дням
B23: Дата | C23: День недели | D23: Выручка (руб) | E23: Кол-во единиц (шт.) | F23: Средняя стоимость изделия (руб.) | G23: Количество чеков (шт.) | H23: Средняя сумма чека (руб.) | I23: Трафик | J23: Длина чека (шт.) | K23: UNOde50 | L23: IS | M23: Agafi | N23: Kalliope | O23: Raganella | P23: CC/MP | Q23: Eva Rites | R23: Antura | S23: Конверсия (%) | U23: выручка, план | V23: кол-во ед, план | W23: Кол-во чеков, план | X23: выручка, скорректир.план | Y23: кол-во ед, скорр. план | Z23: кол-во чеков, скорр. план | AA23: Коэфф. Дня Недели | AB23: Специфика месяца
B24: 1 | C24: 2 | D24: 3 | E24: в | F24: 5 | G24: 6 | H24: 7 | I24: 8 | J24: 9 | K24: 10 | L24: 11 | M24: 12 | N24: 13 | O24: 14 | P24: 15 | Q24: 16 | R24: 17 | S24: 18 | U24: 1 | V24: 2 | W24: 3 | X24: 4 | Y24: 5 | Z24: 6 | AA24: 10 | AB24: 11
A25: 1 | B25: 46036 | C25: ср | D25: =7220+11393 -> 18613 | E25: 2 | F25: 9306 | G25: 2 | H25: 9306 | I25: 30 | J25: =IF(AND(G25<>"",G25<>0),E25/G25,"") -> 1 | K25: 7220 | M25: 11393 | S25: =IF(AND(I25<>"",I25<>0),G25/I25,"") -> 0.066666667 | T25: =D25/U25 -> #DIV/0! | U25: =$I$8*AA25*AB25/SUMPRODUCT($AB$25:$AB$55,$AA$25:$AA$55) -> 0 | V25: =$I$9*AA25*AB25/SUMPRODUCT($AB$25:$AB$55,$AA$25:$AA$55) -> 0 | W25: =IF($I$12="","",V25/$I$12) -> 0 | X25: =IF(AB25<>"",IF(D25<>"",D25,($I$8-SUM($X24:X$25))*AA25*AB25/SUMPRODUCT($AB25:$AB$55,$AA25:$AA$55)),"") -> 18613 | Y25: =IF(AB25<>"",IF(E25<>"",E25,($I$9-SUM($Y24:Y$25))*AA25*AB25/SUMPRODUCT($AB25:$AB$55,$AA25:$AA$55)),"") -> 2 | Z25: =IF(AB25<>"",IF($I$12<>"",IF(G25<>"",G25,($I$9/$I$12-SUM($Z24:Z$25))*AA25*AB25/SUMPRODUCT($AB25:$AB$55,$AA25:$AA$55)),""),"") -> 2 | AA25: 1 | AB25: 1
A26: 2 | B26: 46037 | C26: чт | D26: 63046 | E26: 6 | F26: 10508 | G26: 2 | H26: 31523 | I26: 17 | J26: =IF(AND(G26<>"",G26<>0),E26/G26,"") -> 3 | R26: 38380 | S26: =IF(AND(I26<>"",I26<>0),G26/I26,"") -> 0.11764706 | T26: =D26/U26 -> #DIV/0! | U26: =$I$8*AA26*AB26/SUMPRODUCT($AB$25:$AB$55,$AA$25:$AA$55) -> 0 | V26: =$I$9*AA26*AB26/SUMPRODUCT($AB$25:$AB$55,$AA$25:$AA$55) -> 0 | W26: =IF($I$12="","",V26/$I$12) -> 0 | X26: =IF(AB26<>"",IF(D26<>"",D26,($I$8-SUM($X$25:X25))*AA26*AB26/SUMPRODUCT($AB26:$AB$55,$AA26:$AA$55)),"") -> 63046 | Y26: =IF(AB26<>"",IF(E26<>"",E26,($I$9-SUM($Y$25:Y25))*AA26*AB26/SUMPRODUCT($AB26:$AB$55,$AA26:$AA$55)),"") -> 6 | Z26: =IF(AB26<>"",IF($I$12<>"",IF(G26<>"",G26,($I$9/$I$12-SUM($Z$25:Z25))*AA26*AB26/SUMPRODUCT($AB26:$AB$55,$AA26:$AA$55)),""),"") -> 2 | AA26: 1 | AB26: 1
A27: 3 | B27: 46038 | C27: пт | D27: 0 | E27: 0 | G27: 0 | I27: 12 | J27: =IF(AND(G27<>"",G27<>0),E27/G27,"") | S27: =IF(AND(I27<>"",I27<>0),G27/I27,"") -> 0 | T27: =D27/U27 -> #DIV/0! | U27: =$I$8*AA27*AB27/SUMPRODUCT($AB$25:$AB$55,$AA$25:$AA$55) -> 0 | V27: =$I$9*AA27*AB27/SUMPRODUCT($AB$25:$AB$55,$AA$25:$AA$55) -> 0 | W27: =IF($I$12="","",V27/$I$12) -> 0 | X27: =IF(AB27<>"",IF(D27<>"",D27,($I$8-SUM($X$25:X26))*AA27*AB27/SUMPRODUCT($AB27:$AB$55,$AA27:$AA$55)),"") -> 0 | Y27: =IF(AB27<>"",IF(E27<>"",E27,($I$9-SUM($Y$25:Y26))*AA27*AB27/SUMPRODUCT($AB27:$AB$55,$AA27:$AA$55)),"") -> 0 | Z27: =IF(AB27<>"",IF($I$12<>"",IF(G27<>"",G27,($I$9/$I$12-SUM($Z$25:Z26))*AA27*AB27/SUMPRODUCT($AB27:$AB$55,$AA27:$AA$55)),""),"") -> 0 | AA27: 1 | AB27: 1
A28: 4 | B28: 46039 | C28: сб | D28: =23406+4805 -> 28211 | E28: 3 | F28: 9342 | G28: 2 | H28: 14013 | I28: 19 | J28: =IF(AND(G28<>"",G28<>0),E28/G28,"") -> 1.5 | R28: 23406 | S28: =IF(AND(I28<>"",I28<>0),G28/I28,"") -> 0.10526316 | T28: =D28/U28 -> #DIV/0! | U28: =$I$8*AA28*AB28/SUMPRODUCT($AB$25:$AB$55,$AA$25:$AA$55) -> 0 | V28: =$I$9*AA28*AB28/SUMPRODUCT($AB$25:$AB$55,$AA$25:$AA$55) -> 0 | W28: =IF($I$12="","",V28/$I$12) -> 0 | X28: =IF(AB28<>"",IF(D28<>"",D28,($I$8-SUM($X$25:X27))*AA28*AB28/SUMPRODUCT($AB28:$AB$55,$AA28:$AA$55)),"") -> 28211 | Y28: =IF(AB28<>"",IF(E27<>"",E27,($I$9-SUM($Y$25:Y27))*AA28*AB28/SUMPRODUCT($AB28:$AB$55,$AA28:$AA$55)),"") -> 0 | Z28: =IF(AB28<>"",IF($I$12<>"",IF(G28<>"",G28,($I$9/$I$12-SUM($Z$25:Z27))*AA28*AB28/SUMPRODUCT($AB28:$AB$55,$AA28:$AA$55)),""),"") -> 2 | AA28: 1 | AB28: 1
A29: 5 | B29: 46040 | C29: вс | I29: 24 | J29: =IF(AND(G29<>"",G29<>0),E29/G29,"") | S29: =IF(AND(I29<>"",I29<>0),G29/I29,"") -> 0 | T29: =D29/U29 -> #DIV/0! | U29: =$I$8*AA29*AB29/SUMPRODUCT($AB$25:$AB$55,$AA$25:$AA$55) -> 0 | V29: =$I$9*AA29*AB29/SUMPRODUCT($AB$25:$AB$55,$AA$25:$AA$55) -> 0 | W29: =IF($I$12="","",V29/$I$12) -> 0 | X29: =IF(AB29<>"",IF(D29<>"",D29,($I$8-SUM($X$25:X28))*AA29*AB29/SUMPRODUCT($AB29:$AB$55,$AA29:$AA$55)),"") -> -109870 | Y29: =IF(AB29<>"",IF(E29<>"",E29,($I$9-SUM($Y$25:Y28))*AA29*AB29/SUMPRODUCT($AB29:$AB$55,$AA29:$AA$55)),"") -> -8 | Z29: =IF(AB29<>"",IF($I$12<>"",IF(G29<>"",G29,($I$9/$I$12-SUM($Z$25:Z28))*AA29*AB29/SUMPRODUCT($AB29:$AB$55,$AA29:$AA$55)),""),"") -> -6 | AA29: 1 | AB29: 1
J30: =IF(AND(G30<>"",G30<>0),E30/G30,"") | S30: =IF(AND(I30<>"",I30<>0),G30/I30,"") | T30: =D30/U30 -> #DIV/0! | U30: =$I$8*AA30*AB30/SUMPRODUCT($AB$25:$AB$55,$AA$25:$AA$55) -> 0 | V30: =$I$9*AA30*AB30/SUMPRODUCT($AB$25:$AB$55,$AA$25:$AA$55) -> 0 | W30: =IF($I$12="","",V30/$I$12) -> 0 | X30: =IF(AB30<>"",IF(D30<>"",D30,($I$8-SUM($X$25:X29))*AA30*AB30/SUMPRODUCT($AB30:$AB$55,$AA30:$AA$55)),"") | Y30: =IF(AB30<>"",IF(E30<>"",E30,($I$9-SUM($Y$25:Y29))*AA30*AB30/SUMPRODUCT($AB30:$AB$55,$AA30:$AA$55)),"") | Z30: =IF(AB30<>"",IF($I$12<>"",IF(G30<>"",G30,($I$9/$I$12-SUM($Z$25:Z29))*AA30*AB30/SUMPRODUCT($AB30:$AB$55,$AA30:$AA$55)),""),"")
J31: =IF(AND(G31<>"",G31<>0),E31/G31,"") | S31: =IF(AND(I31<>"",I31<>0),G31/I31,"") | T31: =D31/U31 -> #DIV/0! | U31: =$I$8*AA31*AB31/SUMPRODUCT($AB$25:$AB$55,$AA$25:$AA$55) -> 0 | V31: =$I$9*AA31*AB31/SUMPRODUCT($AB$25:$AB$55,$AA$25:$AA$55) -> 0 | W31: =IF($I$12="","",V31/$I$12) -> 0 | X31: =IF(AB31<>"",IF(D31<>"",D31,($I$8-SUM($X$25:X30))*AA31*AB31/SUMPRODUCT($AB31:$AB$55,$AA31:$AA$55)),"") | Y31: =IF(AB31<>"",IF(E31<>"",E31,($I$9-SUM($Y$25:Y30))*AA31*AB31/SUMPRODUCT($AB31:$AB$55,$AA31:$AA$55)),"") | Z31: =IF(AB31<>"",IF($I$12<>"",IF(G31<>"",G31,($I$9/$I$12-SUM($Z$25:Z30))*AA31*AB31/SUMPRODUCT($AB31:$AB$55,$AA31:$AA$55)),""),"")
J32: =IF(AND(G32<>"",G32<>0),E32/G32,"") | S32: =IF(AND(I32<>"",I32<>0),G32/I32,"") | T32: =D32/U32 -> #DIV/0! | U32: =$I$8*AA32*AB32/SUMPRODUCT($AB$25:$AB$55,$AA$25:$AA$55) -> 0 | V32: =$I$9*AA32*AB32/SUMPRODUCT($AB$25:$AB$55,$AA$25:$AA$55) -> 0 | W32: =IF($I$12="","",V32/$I$12) -> 0 | X32: =IF(AB32<>"",IF(D32<>"",D32,($I$8-SUM($X$25:X31))*AA32*AB32/SUMPRODUCT($AB32:$AB$55,$AA32:$AA$55)),"") | Y32: =IF(AB32<>"",IF(E32<>"",E32,($I$9-SUM($Y$25:Y31))*AA32*AB32/SUMPRODUCT($AB32:$AB$55,$AA32:$AA$55)),"") | Z32: =IF(AB32<>"",IF($I$12<>"",IF(G32<>"",G32,($I$9/$I$12-SUM($Z$25:Z31))*AA32*AB32/SUMPRODUCT($AB32:$AB$55,$AA32:$AA$55)),""),"")
J33: =IF(AND(G33<>"",G33<>0),E33/G33,"") | S33: =IF(AND(I33<>"",I33<>0),G33/I33,"") | T33: =D33/U33 -> #DIV/0! | U33: =$I$8*AA33*AB33/SUMPRODUCT($AB$25:$AB$55,$AA$25:$AA$55) -> 0 | V33: =$I$9*AA33*AB33/SUMPRODUCT($AB$25:$AB$55,$AA$25:$AA$55) -> 0 | W33: =IF($I$12="","",V33/$I$12) -> 0 | X33: =IF(AB33<>"",IF(D33<>"",D33,($I$8-SUM($X$25:X32))*AA33*AB33/SUMPRODUCT($AB33:$AB$55,$AA33:$AA$55)),"") | Y33: =IF(AB33<>"",IF(E33<>"",E33,($I$9-SUM($Y$25:Y32))*AA33*AB33/SUMPRODUCT($AB33:$AB$55,$AA33:$AA$55)),"") | Z33: =IF(AB33<>"",IF($I$12<>"",IF(G33<>"",G33,($I$9/$I$12-SUM($Z$25:Z32))*AA33*AB33/SUMPRODUCT($AB33:$AB$55,$AA33:$AA$55)),""),"")
J34: =IF(AND(G34<>"",G34<>0),E34/G34,"") | S34: =IF(AND(I34<>"",I34<>0),G34/I34,"") | T34: =D34/U34 -> #DIV/0! | U34: =$I$8*AA34*AB34/SUMPRODUCT($AB$25:$AB$55,$AA$25:$AA$55) -> 0 | V34: =$I$9*AA34*AB34/SUMPRODUCT($AB$25:$AB$55,$AA$25:$AA$55) -> 0 | W34: =IF($I$12="","",V34/$I$12) -> 0 | X34: =IF(AB34<>"",IF(D34<>"",D34,($I$8-SUM($X$25:X33))*AA34*AB34/SUMPRODUCT($AB34:$AB$55,$AA34:$AA$55)),"") | Y34: =IF(AB34<>"",IF(E34<>"",E34,($I$9-SUM($Y$25:Y33))*AA34*AB34/SUMPRODUCT($AB34:$AB$55,$AA34:$AA$55)),"") | Z34: =IF(AB34<>"",IF($I$12<>"",IF(G34<>"",G34,($I$9/$I$12-SUM($Z$25:Z33))*AA34*AB34/SUMPRODUCT($AB34:$AB$55,$AA34:$AA$55)),""),"")
J35: =IF(AND(G35<>"",G35<>0),E35/G35,"") | S35: =IF(AND(I35<>"",I35<>0),G35/I35,"") | T35: =D35/U35 -> #DIV/0! | U35: =$I$8*AA35*AB35/SUMPRODUCT($AB$25:$AB$55,$AA$25:$AA$55) -> 0 | V35: =$I$9*AA35*AB35/SUMPRODUCT($AB$25:$AB$55,$AA$25:$AA$55) -> 0 | W35: =IF($I$12="","",V35/$I$12) -> 0 | X35: =IF(AB35<>"",IF(D35<>"",D35,($I$8-SUM($X$25:X34))*AA35*AB35/SUMPRODUCT($AB35:$AB$55,$AA35:$AA$55)),"") | Y35: =IF(AB34<>"",IF(E34<>"",E34,($I$9-SUM($Y$25:Y33))*AA34*AB34/SUMPRODUCT($AB34:$AB$55,$AA34:$AA$55)),"") | Z35: =IF(AB34<>"",IF($I$12<>"",IF(G34<>"",G34,($I$9/$I$12-SUM($Z$25:Z33))*AA34*AB34/SUMPRODUCT($AB34:$AB$55,$AA34:$AA$55)),""),"")
J36: =IF(AND(G36<>"",G36<>0),E36/G36,"") | S36: =IF(AND(I36<>"",I36<>0),G36/I36,"") | T36: =D36/U36 -> #DIV/0! | U36: =$I$8*AA36*AB36/SUMPRODUCT($AB$25:$AB$55,$AA$25:$AA$55) -> 0 | V36: =$I$9*AA36*AB36/SUMPRODUCT($AB$25:$AB$55,$AA$25:$AA$55) -> 0 | W36: =IF($I$12="","",V36/$I$12) -> 0 | X36: =IF(AB36<>"",IF(D36<>"",D36,($I$8-SUM($X$25:X35))*AA36*AB36/SUMPRODUCT($AB36:$AB$55,$AA36:$AA$55)),"") | Y36: =IF(AB36<>"",IF(E36<>"",E36,($I$9-SUM($Y$25:Y35))*AA36*AB36/SUMPRODUCT($AB36:$AB$55,$AA36:$AA$55)),"") | Z36: =IF(AB36<>"",IF($I$12<>"",IF(G36<>"",G36,($I$9/$I$12-SUM($Z$25:Z35))*AA36*AB36/SUMPRODUCT($AB36:$AB$55,$AA36:$AA$55)),""),"")
J37: =IF(AND(G37<>"",G37<>0),E37/G37,"") | S37: =IF(AND(I37<>"",I37<>0),G37/I37,"") | T37: =D37/U37 -> #DIV/0! | U37: =$I$8*AA37*AB37/SUMPRODUCT($AB$25:$AB$55,$AA$25:$AA$55) -> 0 | V37: =$I$9*AA37*AB37/SUMPRODUCT($AB$25:$AB$55,$AA$25:$AA$55) -> 0 | W37: =IF($I$12="","",V37/$I$12) -> 0 | X37: =IF(AB37<>"",IF(D37<>"",D37,($I$8-SUM($X$25:X36))*AA37*AB37/SUMPRODUCT($AB37:$AB$55,$AA37:$AA$55)),"") | Y37: =IF(AB37<>"",IF(E37<>"",E37,($I$9-SUM($Y$25:Y36))*AA37*AB37/SUMPRODUCT($AB37:$AB$55,$AA37:$AA$55)),"") | Z37: =IF(AB37<>"",IF($I$12<>"",IF(G37<>"",G37,($I$9/$I$12-SUM($Z$25:Z36))*AA37*AB37/SUMPRODUCT($AB37:$AB$55,$AA37:$AA$55)),""),"")
J38: =IF(AND(G38<>"",G38<>0),E38/G38,"") | S38: =IF(AND(I38<>"",I38<>0),G38/I38,"") | T38: =D38/U38 -> #DIV/0! | U38: =$I$8*AA38*AB38/SUMPRODUCT($AB$25:$AB$46,$AA$25:$AA$46) -> 0 | V38: =$I$9*AA38*AB38/SUMPRODUCT($AB$25:$AB$46,$AA$25:$AA$46) -> 0 | W38: =IF($I$12="","",V38/$I$12) -> 0 | X38: =IF(AB38<>"",IF(D38<>"",D38,($I$8-SUM($X$25:X37))*AA38*AB38/SUMPRODUCT($AB38:$AB$55,$AA38:$AA$55)),"") | Y38: =IF(AB38<>"",IF(E38<>"",E38,($I$9-SUM($Y$25:Y37))*AA38*AB38/SUMPRODUCT($AB38:$AB$55,$AA38:$AA$55)),"") | Z38: =IF(AB38<>"",IF($I$12<>"",IF(G38<>"",G38,($I$9/$I$12-SUM($Z$25:Z37))*AA38*AB38/SUMPRODUCT($AB38:$AB$55,$AA38:$AA$55)),""),"")
J39: =IF(AND(G39<>"",G39<>0),E39/G39,"") | S39: =IF(AND(I39<>"",I39<>0),G39/I39,"") | T39: =D39/U39 -> #DIV/0! | U39: =$I$8*AA39*AB39/SUMPRODUCT($AB$25:$AB$46,$AA$25:$AA$46) -> 0 | V39: =$I$9*AA39*AB39/SUMPRODUCT($AB$25:$AB$46,$AA$25:$AA$46) -> 0 | W39: =IF($I$12="","",V39/$I$12) -> 0 | X39: =IF(AB39<>"",IF(D39<>"",D39,($I$8-SUM($X$25:X38))*AA39*AB39/SUMPRODUCT($AB39:$AB$47,$AA39:$AA$47)),"") | Y39: =IF(AB39<>"",IF(E39<>"",E39,($I$9-SUM($Y$25:Y38))*AA39*AB39/SUMPRODUCT($AB39:$AB$55,$AA39:$AA$55)),"") | Z39: =IF(AB39<>"",IF($I$12<>"",IF(G39<>"",G39,($I$9/$I$12-SUM($Z$25:Z38))*AA39*AB39/SUMPRODUCT($AB39:$AB$55,$AA39:$AA$55)),""),"")
J40: =IF(AND(G40<>"",G40<>0),E40/G40,"") | S40: =IF(AND(I40<>"",I40<>0),G40/I40,"") | T40: =D40/U40 -> #DIV/0! | U40: =$I$8*AA40*AB40/SUMPRODUCT($AB$25:$AB$46,$AA$25:$AA$46) -> 0 | V40: =$I$9*AA40*AB40/SUMPRODUCT($AB$25:$AB$46,$AA$25:$AA$46) -> 0 | W40: =IF($I$12="","",V40/$I$12) -> 0 | X40: =IF(AB40<>"",IF(D40<>"",D40,($I$8-SUM($X$25:X39))*AA40*AB40/SUMPRODUCT($AB40:$AB$46,$AA40:$AA$46)),"") | Y40: =IF(AB40<>"",IF(E40<>"",E40,($I$9-SUM($Y$25:Y39))*AA40*AB40/SUMPRODUCT($AB40:$AB$46,$AA40:$AA$46)),"") | Z40: =IF(AB40<>"",IF($I$12<>"",IF(G40<>"",G40,($I$9/$I$12-SUM($Z$25:Z39))*AA40*AB40/SUMPRODUCT($AB40:$AB$55,$AA40:$AA$55)),""),"")
F41: =IF(AND(E41<>"",E41<>0),D41/E41,"") | H41: =IF(AND(G41<>"",G41<>0),D41/G41,"") | J41: =IF(AND(G41<>"",G41<>0),E41/G41,"") | S41: =IF(AND(I41<>"",I41<>0),G41/I41,"") | T41: =D41/U41 -> #DIV/0! | U41: =$I$8*AA41*AB41/SUMPRODUCT($AB$25:$AB$46,$AA$25:$AA$46) -> 0 | V41: =$I$9*AA41*AB41/SUMPRODUCT($AB$25:$AB$46,$AA$25:$AA$46) -> 0 | W41: =IF($I$12="","",V41/$I$12) -> 0 | X41: =IF(AB41<>"",IF(D41<>"",D41,($I$8-SUM($X$25:X40))*AA41*AB41/SUMPRODUCT($AB41:$AB$46,$AA41:$AA$46)),"") | Y41: =IF(AB41<>"",IF(E41<>"",E41,($I$9-SUM($Y$25:Y40))*AA41*AB41/SUMPRODUCT($AB41:$AB$46,$AA41:$AA$46)),"") | Z41: =IF(AB41<>"",IF($I$12<>"",IF(G41<>"",G41,($I$9/$I$12-SUM($Z$25:Z40))*AA41*AB41/SUMPRODUCT($AB41:$AB$55,$AA41:$AA$55)),""),"")
F42: =IF(AND(E42<>"",E42<>0),D42/E42,"") | H42: =IF(AND(G42<>"",G42<>0),D42/G42,"") | J42: =IF(AND(G42<>"",G42<>0),E42/G42,"") | S42: =IF(AND(I42<>"",I42<>0),G42/I42,"") | T42: =D42/U42 -> #DIV/0! | U42: =$I$8*AA42*AB42/SUMPRODUCT($AB$25:$AB$46,$AA$25:$AA$46) -> 0 | V42: =$I$9*AA42*AB42/SUMPRODUCT($AB$25:$AB$46,$AA$25:$AA$46) -> 0 | W42: =IF($I$12="","",V42/$I$12) -> 0 | X42: =IF(AB42<>"",IF(D42<>"",D42,($I$8-SUM($X$25:X41))*AA42*AB42/SUMPRODUCT($AB42:$AB$46,$AA42:$AA$46)),"") | Y42: =IF(AB42<>"",IF(E42<>"",E42,($I$9-SUM($Y$25:Y41))*AA42*AB42/SUMPRODUCT($AB42:$AB$46,$AA42:$AA$46)),"") | Z42: =IF(AB42<>"",IF($I$12<>"",IF(G42<>"",G42,($I$9/$I$12-SUM($Z$25:Z41))*AA42*AB42/SUMPRODUCT($AB42:$AB$46,$AA42:$AA$46)),""),"")
F43: =IF(AND(E43<>"",E43<>0),D43/E43,"") | H43: =IF(AND(G43<>"",G43<>0),D43/G43,"") | J43: =IF(AND(G43<>"",G43<>0),E43/G43,"") | S43: =IF(AND(I43<>"",I43<>0),G43/I43,"") | T43: =D43/U43 -> #DIV/0! | U43: =$I$8*AA43*AB43/SUMPRODUCT($AB$25:$AB$46,$AA$25:$AA$46) -> 0 | V43: =$I$9*AA43*AB43/SUMPRODUCT($AB$25:$AB$46,$AA$25:$AA$46) -> 0 | W43: =IF($I$12="","",V43/$I$12) -> 0 | X43: =IF(AB43<>"",IF(D43<>"",D43,($I$8-SUM($X$25:X42))*AA43*AB43/SUMPRODUCT($AB43:$AB$46,$AA43:$AA$46)),"") | Y43: =IF(AB43<>"",IF(E43<>"",E43,($I$9-SUM($Y$25:Y42))*AA43*AB43/SUMPRODUCT($AB43:$AB$46,$AA43:$AA$46)),"") | Z43: =IF(AB43<>"",IF($I$12<>"",IF(G43<>"",G43,($I$9/$I$12-SUM($Z$25:Z42))*AA43*AB43/SUMPRODUCT($AB43:$AB$46,$AA43:$AA$46)),""),"")
F44: =IF(AND(E44<>"",E44<>0),D44/E44,"") | H44: =IF(AND(G44<>"",G44<>0),D44/G44,"") | J44: =IF(AND(G44<>"",G44<>0),E44/G44,"") | S44: =IF(AND(I44<>"",I44<>0),G44/I44,"") | T44: =D44/U44 -> #DIV/0! | U44: =$I$8*AA44*AB44/SUMPRODUCT($AB$25:$AB$46,$AA$25:$AA$46) -> 0 | V44: =$I$9*AA44*AB44/SUMPRODUCT($AB$25:$AB$46,$AA$25:$AA$46) -> 0 | W44: =IF($I$12="","",V44/$I$12) -> 0 | X44: =IF(AB44<>"",IF(D44<>"",D44,($I$8-SUM($X$25:X43))*AA44*AB44/SUMPRODUCT($AB44:$AB$46,$AA44:$AA$46)),"") | Y44: =IF(AB44<>"",IF(E44<>"",E44,($I$9-SUM($Y$25:Y43))*AA44*AB44/SUMPRODUCT($AB44:$AB$46,$AA44:$AA$46)),"") | Z44: =IF(AB44<>"",IF($I$12<>"",IF(G44<>"",G44,($I$9/$I$12-SUM($Z$25:Z43))*AA44*AB44/SUMPRODUCT($AB44:$AB$46,$AA44:$AA$46)),""),"")
F45: =IF(AND(E45<>"",E45<>0),D45/E45,"") | H45: =IF(AND(G45<>"",G45<>0),D45/G45,"") | J45: =IF(AND(G45<>"",G45<>0),E45/G45,"") | S45: =IF(AND(I45<>"",I45<>0),G45/I45,"") | T45: =D45/U45 -> #DIV/0! | U45: =$I$8*AA45*AB45/SUMPRODUCT($AB$25:$AB$46,$AA$25:$AA$46) -> 0 | V45: =$I$9*AA45*AB45/SUMPRODUCT($AB$25:$AB$46,$AA$25:$AA$46) -> 0 | W45: =IF($I$12="","",V45/$I$12) -> 0 | X45: =IF(AB45<>"",IF(D45<>"",D45,($I$8-SUM($X$25:X44))*AA45*AB45/SUMPRODUCT($AB45:$AB$46,$AA45:$AA$46)),"") | Y45: =IF(AB45<>"",IF(E45<>"",E45,($I$9-SUM($Y$25:Y44))*AA45*AB45/SUMPRODUCT($AB45:$AB$46,$AA45:$AA$46)),"") | Z45: =IF(AB45<>"",IF($I$12<>"",IF(G45<>"",G45,($I$9/$I$12-SUM($Z$25:Z44))*AA45*AB45/SUMPRODUCT($AB45:$AB$46,$AA45:$AA$46)),""),"")
B46: 46041 | C46: пн | D46: 13009 | E46: 1 | F46: =IF(AND(E46<>"",E46<>0),D46/E46,"") -> 13009 | G46: 1 | H46: =IF(AND(G46<>"",G46<>0),D46/G46,"") -> 13009 | J46: =IF(AND(G46<>"",G46<>0),E46/G46,"") -> 1 | S46: =IF(AND(I46<>"",I46<>0),G46/I46,"") | T46: =D46/U46 -> #DIV/0! | U46: =$I$8*AA46*AB46/SUMPRODUCT($AB$25:$AB$46,$AA$25:$AA$46) -> 0 | V46: =$I$9*AA46*AB46/SUMPRODUCT($AB$25:$AB$46,$AA$25:$AA$46) -> 0 | W46: =IF($I$12="","",V46/$I$12) -> 0 | X46: =IF(AB46<>"",IF(D46<>"",D46,($I$8-SUM($X$25:X45))*AA46*AB46/SUMPRODUCT($AB46:$AB$46,$AA46:$AA$46)),"") | Y46: =IF(AB46<>"",IF(E46<>"",E46,($I$9-SUM($Y$25:Y39))*AA46*AB46/SUMPRODUCT($AB46:$AB$46,$AA46:$AA$46)),"") | Z46: =IF(AB46<>"",IF($I$12<>"",IF(G46<>"",G46,($I$9/$I$12-SUM($Z$25:Z39))*AA46*AB46/SUMPRODUCT($AB46:$AB$46,$AA46:$AA$46)),""),"")
A47: Рогалевич | B47: 46031 | C47: пт | D47: 9993 | E47: 1 | F47: =IF(AND(E47<>"",E47<>0),D47/E47,"") -> 9993 | G47: 1 | H47: =IF(AND(G47<>"",G47<>0),D47/G47,"") -> 9993 | I47: 1 | J47: =IF(AND(G47<>"",G47<>0),E47/G47,"") -> 1 | S47: =IF(AND(I47<>"",I47<>0),G47/I47,"") -> 1 | T47: =D47/U47 -> #DIV/0! | U47: =$I$8*AA47*AB47/SUMPRODUCT($AB$25:$AB$46,$AA$25:$AA$46) -> 0 | V47: =$I$9*AA47*AB47/SUMPRODUCT($AB$25:$AB$46,$AA$25:$AA$46) -> 0 | W47: =IF($I$12="","",V47/$I$12) -> 0 | X47: =IF(AB47<>"",IF(D47<>"",D47,($I$8-SUM($X$25:X46))*AA47*AB47/SUMPRODUCT($AB$47:$AB47,$AA$47:$AA47)),"") | Y47: =IF(AB47<>"",IF(E47<>"",E47,($I$9-SUM(#REF!))*AA47*AB47/SUMPRODUCT($AB$47:$AB47,$AA$47:$AA47)),"") | Z47: =IF(AB47<>"",IF($I$12<>"",IF(G47<>"",G47,($I$9/$I$12-SUM(#REF!))*AA47*AB47/SUMPRODUCT($AB$47:$AB47,$AA$47:$AA47)),""),"")
B48: итого | D48: =SUM(D25:D47) -> 132872 | E48: =SUM(E25:E47) -> 13 | F48: =IF(AND(E48<>"",E48<>0),D48/E48,"") -> 10220.923 | G48: =SUM(G25:G47) -> 8 | H48: =IF(AND(G48<>"",G48<>0),D48/G48,"") -> 16609 | I48: =SUM(I25:I47)*0.8 -> 82.4 | J48: =IF(AND(G48<>"",G48<>0),E48/G48,"") -> 1.625 | K48: =SUM(K25:K47) -> 7220 | L48: =SUM(L25:L47) -> 0 | M48: =SUM(M25:M47) -> 11393 | N48: =SUM(N25:N47) -> 0 | O48: =SUM(O25:O47) -> 0 | P48: =SUM(P25:P47) -> 0 | Q48: =SUM(Q25:Q47) -> 0 | R48: =SUM(R25:R47) -> 61786 | S48: =IF(AND(I48<>"",I48<>0),G48/I48,"") -> 0.097087379 | T48: =D48/U48 -> #DIV/0! | U48: =SUM(U25:U47) -> 0 | V48: =SUM(V25:V47) -> 0 | W48: =SUM(W25:W47) -> 0 | X48: =SUM(X25:X47) -> 0 | Y48: =SUM(Y25:Y47) -> 0 | Z48: =SUM(Z25:Z47) -> 0
D49: =SUMIF(D25:D47,"",U25:U47)+D48 -> 132872

Sheet Вед-ть Козлова
A1: =График!B1 -> Январь, 2026
A2: =График!B3 -> ул. Севастопольская, 62 | D2: =График!B4 -> GL-0004
A3: Сотрудник | D3: Выплачено на карту | E3: Выплачено наличными по платежной ведомости | F3: Дополнительные начисления, доплаты | G3: Оклад | H3: Бонусная часть от личных продаж | I3: Бонусная часть от общих продаж | J3: Базовый бонус за выполнение плана | K3: Итого: | L3: Вычеты | M3: Итого к выдаче с учетом авансов и вычетов | N3: Подпись
A4: =График!B26 -> Козлова Валерия | F4: =H8+H9 -> 0 | G4: =D13 -> 18300 | H4: =D21 -> 13141.549 | I4: =M21 -> 9264.0981 | J4: =M13 -> 0 | K4: =H4+J4+G4+F4+I4 -> 40705.647 | L4: =C8+C9 -> 0 | M4: =K4-L4-D4-E4 -> 40705.647
B6: Вычеты | G6: Доп начисления
B7: Дата | C7: Сумма | D7: Описание | G7: Дата | H7: Сумма | J7: Описание
B8: 46022 | D8: НДФЛ декабрь 2025
B9: 46053 | D9: Вычет по инвентаризационной ведомости от 13.01
A13: Оклад: | D13: =G17+G19+G18 -> 18300 | I13: Базовый бонус | M13: =K17+K19+K18 -> 0
B15: Оклад: | I15: Базовый бонус за выполнение плана
B16: Дней | C16: Магазин | D16: Должность | E16: Зачислено часов | F16: Ставка за час, руб | G16: Начислено за день, руб | I16: Магазин | J16: КВП | K16: Начисленный ББ
B17: =График!AI26 -> 19 | C17: =A2 -> ул. Севастопольская, 62 | D17: ПК | E17: =График!AJ26 -> 183 | F17: 100 | G17: =E17*F17 -> 18300 | I17: =C17 -> ул. Севастопольская, 62 | J17: =Центрум!K8 -> 0.74142872
G18: =E18*F18 -> 0
A21: БонуснаяЧасть | D21: =G26+G27+G28 -> 13141.549 | I21: Бонусная часть от общих продаж | M21: =N26+N27+N28 -> 9264.0981
B24: Бонус от личных продаж по категории товара | I24: Бонус от общих продаж
B25: Сотрудник | C25: Магазин | E25: Процент от продажи | F25: Продано на сумму, руб | G25: Начисленный бонус от продаж, руб | I25: Сотрудник | J25: Магазин | K25: Кол-во отработанных личных часов | L25: Кол-во отработанных общих часов | M25: Процент от продажи | N25: Начисленный бонус от продаж, руб
B26: =A4 -> Козлова Валерия | C26: =A2 -> ул. Севастопольская, 62 | E26: 0.05 | F26: ='Козлова В. Э.'!J8 -> 262830.98 | G26: =F26*E26 -> 13141.549 | I26: =B26 -> Козлова Валерия | J26: =C26 -> ул. Севастопольская, 62 | K26: =E17 -> 183 | L26: =График!AJ29 -> 562 | M26: 0.02 | N26: =Центрум!J8*M26*K26/L26 -> 9264.0981

Sheet Вед-ть Свидовская
A1: =График!B1 -> Январь, 2026
A2: =График!B3 -> ул. Севастопольская, 62 | D2: =График!B4 -> GL-0004
A3: Сотрудник | D3: Выплачено на карту | E3: Выплачено наличными по платежной ведомости | F3: Дополнительные начисления, доплаты | G3: Оклад | H3: Бонусная часть от личных продаж | I3: Бонусная часть от общих продаж | J3: Базовый бонус за выполнение плана | K3: Итого: | L3: Вычеты | M3: Итого к выдаче с учетом авансов и вычетов | N3: Подпись
A4: =График!B27 -> Свидовская София | F4: =H8+H9 -> 0 | G4: =D13 -> 10400 | H4: =D20 -> 13401.15 | I4: =M20 -> 5264.8426 | J4: =M13 -> 0 | K4: =H4+J4+G4+F4+I4 -> 29065.993 | L4: =C8+C9+C10+C11 -> 0 | M4: =K4-L4-D4-E4 -> 29065.993
B6: Вычеты | G6: Доп начисления
B7: Дата | C7: Сумма | D7: Описание | G7: Дата | H7: Сумма | J7: Описание
B8: 46022 | D8: НДФЛ декабрь 2025
B9: 46053 | D9: Вычет по инвентаризационной ведомости от 13.01
A13: Оклад: | D13: =G17+G18 -> 10400 | I13: Базовый бонус | M13: =K17+K18 -> 0
B15: Оклад: | I15: Базовый бонус за выполнение плана
B16: Дней | C16: Магазин | D16: Должность | E16: Зачислено часов | F16: Ставка за час, руб | G16: Начислено за день, руб | I16: Магазин | J16: КВП | K16: Начисленный ББ
B17: =График!AI27 -> 10 | C17: =A2 -> ул. Севастопольская, 62 | D17: ПК | E17: =График!AJ27 -> 104 | F17: 100 | G17: =E17*F17 -> 10400 | I17: =C17 -> ул. Севастопольская, 62 | J17: =Центрум!K8 -> 0.74142872
A20: БонуснаяЧасть | D20: =G25+G26 -> 13401.15 | I20: Бонусная часть от общих продаж | M20: =N25+N26 -> 5264.8426
B23: Бонус от личных продаж по категории товара | I23: Бонус от общих продаж
B24: Сотрудник | C24: Магазин | E24: Процент от продажи | F24: Продано на сумму, руб | G24: Начисленный бонус от продаж, руб | I24: Сотрудник | J24: Магазин | K24: Кол-во отработанных личных часов | L24: Кол-во отработанных общих часов | M24: Процент от продажи | N24: Начисленный бонус от продаж, руб
B25: =A4 -> Свидовская София | C25: =A2 -> ул. Севастопольская, 62 | E25: 0.05 | F25: ='Свидовская С. А.'!J8 -> 268023 | G25: =F25*E25 -> 13401.15 | I25: =B25 -> Свидовская София | J25: =C25 -> ул. Севастопольская, 62 | K25: =E17 -> 104 | L25: =График!AJ29 -> 562 | M25: 0.02 | N25: =Центрум!J8*M25*K25/L25 -> 5264.8426

Sheet Вед-ть Корж
A1: =График!B1 -> Январь, 2026
A2: =График!B3 -> ул. Севастопольская, 62 | D2: =График!B4 -> GL-0004
A3: Сотрудник | D3: Выплачено на карту | E3: Выплачено наличными по платежной ведомости | F3: Дополнительные начисления, доплаты | G3: Оклад | H3: Бонусная часть от личных продаж | I3: Бонусная часть от общих продаж | J3: Базовый бонус за выполнение плана | K3: Итого: | L3: Вычеты | M3: Итого к выдаче с учетом авансов и вычетов | N3: Подпись
A4: =График!B25 -> Корж Анастасия | F4: =H8+H9 -> 0 | G4: =D13 -> 18500 | H4: =D21 -> 25256.75 | I4: =M21 -> 9365.3451 | J4: =M13 -> 0 | K4: =H4+J4+G4+F4+I4 -> 53122.095 | L4: =C8+C9+C10+C11 -> 0 | M4: =K4-L4-D4-E4 -> 53122.095
B6: Вычеты | G6: Доп начисления
B7: Дата | C7: Сумма | D7: Описание | G7: Дата | H7: Сумма | J7: Описание
B8: 46022 | D8: НДФЛ декабрь 2025
B9: 46053 | D9: Вычет по инвентаризационной ведомости от 13.01
A13: Оклад: | D13: =G17+G19+G18 -> 18500 | I13: Базовый бонус | M13: =K17+K19+K18 -> 0
B15: Оклад: | I15: Базовый бонус за выполнение плана
B16: Дней | C16: Магазин | D16: Должность | E16: Зачислено часов | F16: Ставка за час, руб | G16: Начислено за день, руб | I16: Магазин | J16: КВП | K16: Начисленный ББ
B17: =График!AI25 -> 18 | C17: =A2 -> ул. Севастопольская, 62 | D17: ПК | E17: =График!AJ25 -> 185 | F17: 100 | G17: =E17*F17 -> 18500 | I17: =C17 -> ул. Севастопольская, 62 | J17: =Центрум!K8 -> 0.74142872
A21: БонуснаяЧасть | D21: =G26+G27+G28 -> 25256.75 | I21: Бонусная часть от общих продаж | M21: =N26+N27+N28 -> 9365.3451
B24: Бонус от личных продаж по категории товара | I24: Бонус от общих продаж
B25: Сотрудник | C25: Магазин | E25: Процент от продажи | F25: Продано на сумму, руб | G25: Начисленный бонус от продаж, руб | I25: Сотрудник | J25: Магазин | K25: Кол-во отработанных личных часов | L25: Кол-во отработанных общих часов | M25: Процент от продажи | N25: Начисленный бонус от продаж, руб
B26: =A4 -> Корж Анастасия | C26: =A2 -> ул. Севастопольская, 62 | E26: 0.05 | F26: ='Корж А. А.'!J8 -> 505135 | G26: =F26*E26 -> 25256.75 | I26: =B26 -> Корж Анастасия | J26: =C26 -> ул. Севастопольская, 62 | K26: =E17 -> 185 | L26: =График!AJ29 -> 562 | M26: 0.02 | N26: =Центрум!J8*M26*K26/L26 -> 9365.3451

Sheet Вед-ть Сейтджелилова
A1: =График!B1 -> Январь, 2026
A2: =График!B3 -> ул. Севастопольская, 62 | D2: =График!B4 -> GL-0004
A3: Сотрудник | D3: Выплачено на карту | E3: Выплачено наличными по платежной ведомости | F3: Дополнительные начисления, доплаты | G3: Оклад | H3: Бонусная часть от личных продаж | I3: Бонусная часть от общих продаж | J3: Базовый бонус за выполнение плана | K3: Итого: | L3: Вычеты | M3: Итого к выдаче с учетом авансов и вычетов | N3: Подпись
A4: =График!B23 -> 0 | F4: =H8+H9 -> 0 | G4: =D13 -> 0 | H4: =D20 -> 6609.32 | I4: =M20 -> 0 | J4: =M13 -> 0 | K4: =H4+J4+G4+F4+I4 -> 6609.32 | L4: =C8+C9+C10+C11 -> 0 | M4: =K4-L4-D4-E4 -> 6609.32
B6: Вычеты | G6: Доп начисления
B7: Дата | C7: Сумма | D7: Описание | G7: Дата | H7: Сумма | J7: Описание
B8: 46032 | D8: НДФЛ декабрь 2025
B9: 46031 | D9: Вычет по инвентаризационной ведомости от 09.01 | J9: Административный %
G10: 46053 | J10: % наличного оборота < 60%
A13: Оклад: | D13: =G17+G18 -> 0 | I13: Базовый бонус | M13: =K17+K18 -> 0
B15: Оклад: | I15: Базовый бонус за выполнение плана
B16: Дней | C16: Магазин | D16: Должность | E16: Зачислено часов | F16: Ставка за час, руб | G16: Начислено за день, руб | I16: Магазин | J16: КВП | K16: Начисленный ББ
B17: =График!AI23 -> 0 | C17: =A2 -> ул. Севастопольская, 62 | D17: УМ | E17: =График!AJ23 -> 0 | F17: 100 | G17: =E17*F17 -> 0 | I17: =C17 -> ул. Севастопольская, 62
A20: БонуснаяЧасть | D20: =G25+G26 -> 6609.32 | I20: Бонусная часть от общих продаж | M20: =N25+N26 -> 0
B23: Бонус от личных продаж по категории товара | I23: Бонус от общих продаж
B24: Сотрудник | C24: Магазин | E24: Процент от продажи | F24: Продано на сумму, руб | G24: Начисленный бонус от продаж, руб | I24: Сотрудник | J24: Магазин | K24: Кол-во отработанных личных часов | L24: Кол-во отработанных общих часов | M24: Процент от продажи | N24: Начисленный бонус от продаж, руб
B25: =A4 -> 0 | C25: =A2 -> ул. Севастопольская, 62 | E25: 0.04 | F25: ='Сейтджелилова А.Э.'!J8 -> 165233 | G25: =F25*E25 -> 6609.32 | I25: =B25 -> 0 | J25: =C25 -> ул. Севастопольская, 62 | K25: =E17 -> 0 | L25: =График!AJ29 -> 562 | M25: 0.02 | N25: =Центрум!J8*M25*K25/L25 -> 0

Sheet Вед-ть Доп сотрудник
A1: =График!B1 -> Январь, 2026
A2: =График!B3 -> ул. Севастопольская, 62 | D2: =График!B4 -> GL-0004
A3: Сотрудник | D3: Выплачено на карту | E3: Выплачено наличными по платежной ведомости | F3: Дополнительные начисления, доплаты | G3: Оклад | H3: Бонусная часть от личных продаж | I3: Бонусная часть от общих продаж | J3: Базовый бонус за выполнение плана | K3: Итого: | L3: Вычеты | M3: Итого к выдаче с учетом авансов и вычетов | N3: Подпись
A4: =График!B24 -> 0 | F4: =H8+H9 -> 0 | G4: =D13 -> 0 | H4: =D20 -> 6360.95 | I4: =M20 -> 0 | J4: =M13 -> 0 | K4: =H4+J4+G4+F4+I4 -> 6360.95 | L4: =C8+C9+C10+C11 -> 200 | M4: =K4-L4-D4-E4 -> 6160.95
B6: Вычеты | G6: Доп начисления
B7: Дата | C7: Сумма | D7: Описание | G7: Дата | H7: Сумма | J7: Описание
B8: 46031 | C8: 200 | D8: Вычет по инвентаризационной ведомости от 09.01 | G8: 46053 | H8: =Центрум!D62*1%/2 -> 0 | J8: Администартивный %
A13: Оклад: | D13: =G17+G18 -> 0 | I13: Базовый бонус | M13: =K17+K18 -> 0
B15: Оклад: | I15: Базовый бонус за выполнение плана
B16: Дней | C16: Магазин | D16: Должность | E16: Зачислено часов | F16: Ставка за час, руб | G16: Начислено за день, руб | I16: Магазин | J16: КВП | K16: Начисленный ББ
B17: =График!AI24 -> 0 | C17: =A2 -> ул. Севастопольская, 62 | D17: УМ | E17: =График!AJ24 -> 0 | F17: 200 | G17: =E17*F17 -> 0 | I17: =C17 -> ул. Севастопольская, 62 | J17: =Центрум!K8 -> 0.74142872
A20: БонуснаяЧасть | D20: =G25+G26 -> 6360.95 | I20: Бонусная часть от общих продаж | M20: =N25+N26 -> 0
B23: Бонус от личных продаж по категории товара | I23: Бонус от общих продаж
B24: Сотрудник | C24: Магазин | E24: Процент от продажи | F24: Продано на сумму, руб | G24: Начисленный бонус от продаж, руб | I24: Сотрудник | J24: Магазин | K24: Кол-во отработанных личных часов | L24: Кол-во отработанных общих часов | M24: Процент от продажи | N24: Начисленный бонус от продаж, руб
B25: =A4 -> 0 | C25: =A2 -> ул. Севастопольская, 62 | E25: 0.05 | F25: ='Доп сотрудник'!J8-5653 -> 127219 | G25: =F25*E25 -> 6360.95 | I25: =B25 -> 0 | J25: =C25 -> ул. Севастопольская, 62 | K25: =E17 -> 0 | L25: =График!AJ29 -> 562 | M25: 0.02 | N25: =Центрум!J8*M25*K25/L25 -> 0

Sheet График
B1: Январь, 2026
B2: г. Симферополь
B3: ул. Севастопольская, 62
B4: GL-0004
B5: 10.00-21.00
B6: ФОТ | C6: Кол-во дней в месяц | AK6: 30
C7: Премия Директора, грн.
D8: вс | E8: пн | F8: вт | G8: ср | H8: чт | I8: пт | J8: сб | K8: вс | L8: пн | M8: вт | N8: ср | O8: чт | P8: пт | Q8: сб | R8: вс | S8: пн | T8: вт | U8: ср | V8: чт | W8: пт | X8: сб | Y8: вс | Z8: пн | AA8: вт | AB8: ср | AC8: чт | AD8: пт | AE8: сб | AJ8: Часы | AK8: Выходные | AL8: Отпуск | AM8: Больничный (официальный) | AN8: Дни стажировки
A10: № | B10: ФИО | C10: Должность | D10: 1 | E10: 2 | F10: 3 | G10: 4 | H10: 5 | I10: 6 | J10: 7 | K10: 8 | L10: 9 | M10: 10 | N10: 11 | O10: 12 | P10: 13 | Q10: 14 | R10: 15 | S10: 16 | T10: 17 | U10: 18 | V10: 19 | W10: 20 | X10: 21 | Y10: 22 | Z10: 23 | AA10: 24 | AB10: 25 | AC10: 26 | AD10: 27 | AE10: 28 | AI10: Дни
A11: 18 | AI11: =COUNTIF(D11:AH11,">0") -> 0 | AJ11: =SUMIF(D11:AH11,">0") -> 0 | AK11: 0 | AL11: 0 | AM11: 0 | AN11: 0
A12: 17 | AI12: =COUNTIF(D12:AH12,">0") -> 0 | AJ12: =SUMIF(D12:AH12,">0") -> 0 | AK12: =COUNTIF(D12:AH12,"В") -> 0 | AL12: 0 | AM12: 0 | AN12: 0
A13: 16 | AI13: =COUNTIF(D13:AH13,">0") -> 0 | AJ13: =SUMIF(D13:AH13,">0") -> 0 | AK13: =COUNTIF(D13:AH13,"В") -> 0 | AL13: 0 | AM13: 0 | AN13: 0
A14: 15 | AI14: =COUNTIF(D14:AH14,">0") -> 0 | AJ14: =SUMIF(D14:AH14,">0") -> 0 | AK14: =COUNTIF(D14:AH14,"В") -> 0 | AL14: 0 | AM14: 0 | AN14: 0
A15: 14 | AI15: =COUNTIF(D15:AH15,">0") -> 0 | AJ15: =SUMIF(D15:AH15,">0") -> 0 | AK15: =COUNTIF(D15:AH15,"В") -> 0 | AL15: 0 | AM15: 0 | AN15: 0
A16: 13 | AI16: =COUNTIF(D16:AH16,">0") -> 0 | AJ16: =SUMIF(D16:AH16,">0") -> 0 | AK16: =COUNTIF(D16:AH16,"В") -> 0 | AL16: 0 | AM16: 0 | AN16: 0
A17: 12 | AI17: =COUNTIF(D17:AH17,">0") -> 0 | AJ17: =SUMIF(D17:AH17,">0") -> 0 | AK17: =COUNTIF(D17:AH17,"В") -> 0 | AL17: 0 | AM17: 0 | AN17: 0
A18: 11 | AI18: =COUNTIF(D18:AH18,">0") -> 0 | AJ18: =SUMIF(D18:AH18,">0") -> 0 | AK18: =COUNTIF(D18:AH18,"В") -> 0 | AL18: 0 | AM18: 0 | AN18: 0
A19: 10 | AI19: =COUNTIF(D19:AH19,">0") -> 0 | AJ19: =SUMIF(D19:AH19,">0") -> 0 | AK19: =COUNTIF(D19:AH19,"В") -> 0 | AL19: 0 | AM19: 0 | AN19: 0
A20: 9 | AI20: =COUNTIF(D20:AH20,">0") -> 0 | AJ20: =SUMIF(D20:AH20,">0") -> 0 | AK20: =COUNTIF(D20:AH20,"В") -> 0 | AL20: 0 | AM20: 0 | AN20: 0
A21: 8 | AI21: =COUNTIF(D21:AH21,">0") -> 0 | AJ21: =SUMIF(D21:AH21,">0") -> 0 | AK21: =COUNTIF(D21:AH21,"В") -> 0 | AL21: 0 | AM21: 0 | AN21: 0
A22: 7 | AI22: =COUNTIF(D22:AH22,">0") -> 0 | AJ22: =SUMIF(D22:AH22,">0") -> 0 | AK22: =COUNTIF(D22:AH22,"В") -> 0 | AL22: 0 | AM22: 0 | AN22: 0
A23: 6 | AI23: =COUNTIF(D23:AH23,">0") -> 0 | AJ23: =SUMIF(D23:AH23,">0") -> 0 | AK23: =COUNTIF(D23:AH23,"В") -> 0 | AL23: 0 | AM23: 0 | AN23: 0
A24: 5 | AI24: =COUNTIF(D24:AH24,">0") -> 0 | AJ24: =SUMIF(D24:AH24,">0") -> 0 | AK24: =COUNTIF(D24:AH24,"В") -> 0 | AL24: 0 | AM24: 0 | AN24: 0
A25: 4 | B25: Корж Анастасия | C25: ПК | D25: в | E25: 9 | F25: 9 | G25: 9 | H25: 11 | I25: в | J25: 10 | K25: 9 | L25: в | M25: в | N25: 11 | O25: 11 | P25: 11 | Q25: в | R25: в | S25: 11 | T25: 11 | U25: 9 | V25: в | W25: в | X25: 11 | Y25: 11 | Z25: 11 | AA25: в | AB25: в | AC25: 9 | AD25: 11 | AE25: 11 | AI25: =COUNTIF(D25:AH25,">0") -> 18 | AJ25: =SUMIF(D25:AH25,">0") -> 185 | AK25: =COUNTIF(D25:AH25,"В") -> 10 | AL25: 0 | AM25: 0 | AN25: 0
A26: 3 | B26: Козлова Валерия | C26: ПК | D26: 11 | E26: 11 | F26: 9 | G26: 11 | H26: 11 | I26: 11 | J26: 1 | K26: в | L26: 9 | M26: 11 | N26: 9 | O26: в | P26: в | Q26: 11 | R26: 9 | S26: в | T26: в | U26: 9 | V26: 9 | W26: 9 | X26: в | Y26: в | Z26: 9 | AA26: 11 | AB26: 11 | AC26: 11 | AD26: в | AE26: в | AI26: =COUNTIF(D26:AH26,">0") -> 19 | AJ26: =SUMIF(D26:AH26,">0") -> 183 | AK26: =COUNTIF(D26:AH26,"В") -> 9 | AL26: 0 | AM26: 0 | AN26: 0
A27: 2 | B27: Свидовская София | C27: ПК | D27: о | E27: о | F27: о | G27: о | H27: о | I27: о | J27: о | K27: о | L27: о | M27: в | N27: 9 | O27: 11 | P27: в | Q27: в | R27: 11 | S27: 9 | T27: в | U27: в | V27: 11 | W27: 11 | X27: 11 | Y27: в | Z27: в | AA27: 11 | AB27: 11 | AC27: 9 | AD27: в | AE27: в | AI27: =COUNTIF(D27:AH27,">0") -> 10 | AJ27: =SUMIF(D27:AH27,">0") -> 104 | AK27: =COUNTIF(D27:AH27,"В") -> 9 | AL27: 0 | AM27: 0 | AN27: 0
A28: 1 | B28: Сейтджелилова Алина | C28: УМ | D28: 9 | E28: 9 | F28: 9 | G28: 9 | H28: 9 | I28: 9 | J28: 9 | K28: 9 | L28: 8 | M28: 10 | N28: у | O28: у | P28: у | Q28: у | R28: у | S28: у | T28: у | U28: у | V28: у | W28: у | X28: у | Y28: у | Z28: у | AA28: у | AB28: у | AC28: у | AD28: у | AE28: у | AI28: =COUNTIF(D28:AH28,">0") -> 10 | AJ28: =SUMIF(D28:AH28,">0") -> 90 | AK28: =COUNTIF(D28:AH28,"В") -> 0 | AL28: =COUNTIF(E28:AI28,"о") -> 0 | AM28: =COUNTIF(F28:AJ28,"б") -> 0 | AN28: 0
B29: Итого магазин | D29: =COUNTIF(D11:D28,">0") -> 2 | E29: =COUNTIF(E11:E28,">0") -> 3 | F29: =COUNTIF(F11:F28,">0") -> 3 | G29: =COUNTIF(G11:G28,">0") -> 3 | H29: =COUNTIF(H11:H28,">0") -> 3 | I29: =COUNTIF(I11:I28,">0") -> 2 | J29: =COUNTIF(J11:J28,">0") -> 3 | K29: =COUNTIF(K11:K28,">0") -> 2 | ... AH29: =COUNTIF(AH11:AH28,">0") -> 0 | AI29: =SUM(AI11:AI28) -> 57 | AJ29: =SUM(AJ11:AJ28) -> 562 | AK29: =SUM(AK11:AK28) -> 28 | AL29: =SUM(AL11:AL28) -> 0 | AM29: =SUM(AM11:AM28) -> 0 | AN29: =SUM(AN11:AN28) -> 0
T32: .
Q54: .

Sheet Стекольщикова А. А.
B1: =TODAY()-1 -> 46170
B2: (отчетная дата) | J2: ЕЖЕДНЕВНЫЙ ОТЧЕТ О ПРОДАЖАХ
B3: Осталось до выполнения плана!!! | J3: =График!B28 -> Сейтджелилова Алина
C4: =I8-D50 -> 218826.31 | E4: =IF(I8<>0,C4/I8,0) -> 0.71220396
F6: Целевые показатели
F7: Показатель | I7: План | J7: Факт | K7: % выполнения | L7: Прогноз выполнения | M7: % выполнения по прогнозу | N7: Отклонение | O7: Факт аналогичного месяца прошлого года | P7: Отклонение LFL
F8: Выручка | I8: =Центрум!I8/График!AJ29*График!AJ28 -> 307252.31 | J8: =D50 -> 88426 | K8: =IF(AND(I8<>"",I8<>0,J8<>""),J8/I8,"") -> 0.28779604 | L8: =IF(SUMIF($D$25:$D$49,">=0",$T$25:$T$49)<>0,I8*D50/SUMIF($D$25:$D$49,">=0",$T$25:$T$49),0) -> 468194.57 | M8: =L8/I8 -> 1.5238114 | N8: =IF(AND(J8<>0,J8<>"",I8<>0,I8<>""),L8-I8,"") -> 160942.26 | P8: =IF(AND(O8<>"",O8<>0,L8<>"",L8<>0),-O8+L8,"") | Q8: =IF(AND(P8<>"",P8<>0,O8<>0,O8<>""),P8/O8,"")
F9: Кол-во изделий | I9: =I8/I11 -> 46.553381 | J9: =E50 -> 14 | K9: =IF(AND(I9<>"",I9<>0,J9<>""),J9/I9,"") -> 0.30073004 | L9: =IF(SUMIF($E$25:$E$49,">=0",$U$25:$U$49)<>0,I9*E50/SUMIF($E$25:$E$49,">=0",$U$25:$U$49),0) -> 61.195633 | M9: =IF(AND(I9<>"",I9<>0,L9<>"",L9<>0),L9/I9,"") -> 1.3145261 | N9: =IF(AND(J9<>0,J9<>"",I9<>0,I9<>""),L9-I9,"") -> 14.642253 | O9: =O8/O11 -> #DIV/0! | P9: =IF(AND(O9<>"",O9<>0,L9<>"",L9<>0),-O9+L9,"") -> #DIV/0! | Q9: =IF(AND(P9<>"",P9<>0,O9<>0,O9<>""),P9/O9,"") -> #DIV/0!
F10: Средний чек | I10: =I11*I12 -> 11220 | J10: =H50 -> 9825.1111 | K10: =IF(AND(I10<>"",I10<>0,J10<>""),J10/I10,"") -> 0.87567835 | L10: =J10 -> 9825.1111 | M10: =IF(AND(I10<>"",I10<>0,L10<>"",L10<>0),L10/I10,"") -> 0.87567835 | N10: =IF(AND(J10<>0,J10<>"",I10<>0,I10<>""),L10-I10,"") -> -1394.8889 | O10: =O11*O12 -> 0 | P10: =IF(AND(O10<>"",O10<>0,L10<>"",L10<>0),-O10+L10,"") | Q10: =IF(AND(P10<>"",P10<>0,O10<>0,O10<>""),P10/O10,"")
F11: Средняя стоимость изделия | I11: =Центрум!I11 -> 6600 | J11: =F50 -> 6316.1429 | K11: =IF(AND(I11<>"",I11<>0,J11<>""),J11/I11,"") -> 0.95699134 | L11: =J11 -> 6316.1429 | M11: =IF(AND(I11<>"",I11<>0,L11<>"",L11<>0),L11/I11,"") -> 0.95699134 | N11: =IF(AND(J11<>0,J11<>"",I11<>0,I11<>""),L11-I11,"") -> -283.85714 | P11: =IF(AND(O11<>"",O11<>0,L11<>"",L11<>0),-O11+L11,"") | Q11: =IF(AND(P11<>"",P11<>0,O11<>0,O11<>""),P11/O11,"")
F12: Длина чека | I12: ='Центрум'!I12 -> 1.7 | J12: =J50 -> 1.5555556 | K12: =IF(AND(I12<>"",I12<>0,J12<>""),J12/I12,"") -> 0.91503268 | L12: =J12 -> 1.5555556 | M12: =IF(AND(I12<>"",I12<>0,L12<>"",L12<>0),L12/I12,"") -> 0.91503268 | N12: =IF(AND(J12<>0,J12<>"",I12<>0,I12<>""),L12-I12,"") -> -0.14444444 | P12: =IF(AND(O12<>"",O12<>0,L12<>"",L12<>0),-O12+L12,"") | Q12: =IF(AND(P12<>"",P12<>0,O12<>0,O12<>""),P12/O12,"")
F13: Кол-во чеков | I13: =IF(I12<>0,I9/I12,"") -> 27.384342 | J13: =G50 -> 9 | K13: =IF(AND(I13<>"",I13<>0,J13<>""),J13/I13,"") -> 0.32865497 | L13: =IF(SUMIF($G$25:$G$49,">=0",$V$25:$V$49)<>0,I13*G50/SUMIF($G$25:$G$49,">=0",$V$25:$V$49),"") -> 41.688657 | M13: =IF(AND(I13<>"",I13<>0,L13<>"",L13<>0),L13/I13,"") -> 1.5223538 | N13: =IF(AND(J13<>0,J13<>"",I13<>0,I13<>""),L13-I13,"") -> 14.304315 | P13: =IF(AND(O13<>"",O13<>0,L13<>"",L13<>0),-O13+L13,"") | Q13: =IF(AND(P13<>"",P13<>0,O13<>0,O13<>""),P13/O13,"")
F14: Кол-во смен план/отработано | I14: =График!AI28 -> 10 | J14: 5 | K14: =IF(AND(I14<>"",I14<>0,J14<>""),J14/I14,"") -> 0.5 | L14: =IF(SUMIF($D$25:$D$49,">=0",$T$25:$T$49),I50*I8/SUMIF($D$25:$D$49,">=0",$T$25:$T$49),"") -> 559.1268 | N14: =IF(AND(J14<>0,J14<>"",I14<>0,I14<>""),L14-I14,"") -> 549.1268 | P14: =IF(AND(O14<>"",O14<>0,L14<>"",L14<>0),-O14+L14,"") | Q14: =IF(AND(P14<>"",P14<>0,O14<>0,O14<>""),P14/O14,"")
F15: Средние продажи в смену | I15: =Центрум!I15 -> 61890.968 | J15: =J8/J14 -> 17685.2 | K15: =IF(AND(I15<>"",I15<>0,J15<>""),J15/I15,"") -> 0.28574767 | L15: =J15 -> 17685.2 | M15: =IF(AND(I15<>"",I15<>0,L15<>"",L15<>0),L15/I15,"") -> 0.28574767 | N15: =IF(AND(J15<>0,J15<>"",I15<>0,I15<>""),L15-I15,"") -> -44205.768 | P15: =IF(AND(O15<>"",O15<>0,L15<>"",L15<>0),-O15+L15,"") | Q15: =IF(AND(P15<>"",P15<>0,O15<>0,O15<>""),P15/O15,"")
F16: Отставание/Перевыполнение | J16: =J8-I15*J14 -> -221028.84 | K16: =IF(AND(I16<>"",I16<>0,J16<>""),J16/I16,"") | L16: =J16 -> -221028.84 | M16: =IF(AND(I16<>"",I16<>0,L16<>"",L16<>0),L16/I16,"") | N16: =IF(AND(J16<>0,J16<>"",I16<>0,I16<>""),L16-I16,"") | P16: =IF(AND(O16<>"",O16<>0,L16<>"",L16<>0),-O16+L16,"") | Q16: =IF(AND(P16<>"",P16<>0,O16<>0,O16<>""),P16/O16,"") | S16: Подарочные сертификаты
F17: Трафик | I17: =Центрум!I17/График!AJ29*График!AJ28 -> 304.27046 | J17: =I50 -> 105.6 | K17: =IF(AND(I17<>"",I17<>0,J17<>""),J17/I17,"") -> 0.34705965 | L17: =J17/J14*I14 -> 211.2 | M17: =IF(AND(I17<>"",I17<>0,L17<>"",L17<>0),L17/I17,"") -> 0.6941193 | N17: =IF(AND(J17<>0,J17<>"",I17<>0,I17<>""),L17-I17,"") -> -93.070463 | P17: =IF(AND(O17<>"",O17<>0,L17<>"",L17<>0),-O17+L17,"") | Q17: =IF(AND(P17<>"",P17<>0,O17<>0,O17<>""),P17/O17,"")
