Workbook
Name маг: NA()

Sheet Центрум
B1: =TODAY()-1 -> 46171
B2: (01.02.2026-28.02.2026) | J2: ЕЖЕДНЕВНЫЙ ОТЧЕТ О ПРОДАЖАХ
C3: Осталось до выполнения плана!!! | I3: ТРК Центрум
C4: =I8-D56 -> 1025637 | E4: =IF(I8<>0,C4/I8,0) -> 0.54841737
F6: Целевые показатели
F7: Показатель | I7: План | J7: Факт | K7: % выполнения | L7: Прогноз выполнения | M7: % выполнения по прогнозу | N7: Отклонение | O7: Факт аналогичного месяца прошлого года | P7: Отклонение LFL
F8: Выручка | I8: =I13*I10 -> 1870176 | J8: =D56 -> 844539 | K8: =IF(AND(I8<>"",I8<>0,J8<>""),J8/I8,"") -> 0.45158263 | L8: =IF(SUMIF($D$25:$D$55,">=0",$V$25:$V$55)<>0,I8*D56/SUMIF($D$25:$D$55,">=0",$V$25:$V$55),0) -> 844539 | M8: =L8/I8 -> 0.45158263 | N8: =IF(AND(J8<>0,J8<>"",I8<>0,I8<>""),L8-I8,"") -> -1025637 | P8: =IF(AND(O8<>"",O8<>0,L8<>"",L8<>0),-O8+L8,"") | Q8: =IF(AND(O8<>"",O8<>0,N8<>0,N8<>""),O8/N8,"")
F9: Кол-во изделий | I9: =I8/I11 -> 257.6 | J9: =E56 -> 106 | K9: =IF(AND(I9<>"",I9<>0,J9<>""),J9/I9,"") -> 0.41149068 | L9: =IF(SUMIF($E$25:$E$55,">=0",$W$25:$W$55)<>0,I9*E56/SUMIF($E$25:$E$55,">=0",$W$25:$W$55),0) -> 106 | M9: =IF(AND(I9<>"",I9<>0,L9<>"",L9<>0),L9/I9,"") -> 0.41149068 | N9: =IF(AND(J9<>0,J9<>"",I9<>0,I9<>""),L9-I9,"") -> -151.6 | P9: =IF(AND(O9<>"",O9<>0,L9<>"",L9<>0),-O9+L9,"") | Q9: =IF(AND(O9<>"",O9<>0,N9<>0,N9<>""),O9/N9,"")
F10: Средний чек | I10: =I11*I12 -> 13358.4 | J10: =H56 -> 12239.696 | K10: =IF(AND(I10<>"",I10<>0,J10<>""),J10/I10,"") -> 0.91625462 | L10: =J10 -> 12239.696 | M10: =IF(AND(I10<>"",I10<>0,L10<>"",L10<>0),L10/I10,"") -> 0.91625462 | N10: =IF(AND(J10<>0,J10<>"",I10<>0,I10<>""),L10-I10,"") -> -1118.7043 | P10: =IF(AND(O10<>"",O10<>0,L10<>"",L10<>0),-O10+L10,"") | Q10: =IF(AND(O10<>"",O10<>0,N10<>0,N10<>""),O10/N10,"")
F11: Средняя стоимость изделия | I11: 7260 | J11: =F56 -> 7967.3491 | K11: =IF(AND(I11<>"",I11<>0,J11<>""),J11/I11,"") -> 1.097431 | L11: =IF(L9>0,L8/L9,"") -> 7967.3491 | M11: =IF(AND(I11<>"",I11<>0,L11<>"",L11<>0),L11/I11,"") -> 1.097431 | N11: =IF(AND(J11<>0,J11<>"",I11<>0,I11<>""),L11-I11,"") -> 707.34906 | P11: =IF(AND(O11<>"",O11<>0,L11<>"",L11<>0),-O11+L11,"") | Q11: =IF(AND(O11<>"",O11<>0,N11<>0,N11<>""),O11/N11,"")
F12: Длина чека | I12: 1.84 | J12: =J56 -> 1.5362319 | K12: =IF(AND(I12<>"",I12<>0,J12<>""),J12/I12,"") -> 0.83490863 | L12: =J12 -> 1.5362319 | M12: =IF(AND(I12<>"",I12<>0,L12<>"",L12<>0),L12/I12,"") -> 0.83490863 | N12: =IF(AND(J12<>0,J12<>"",I12<>0,I12<>""),L12-I12,"") -> -0.30376812 | P12: =IF(AND(O12<>"",O12<>0,L12<>"",L12<>0),-O12+L12,"") | Q12: =IF(AND(O12<>"",O12<>0,N12<>0,N12<>""),O12/N12,"")
F13: Кол-во чеков | I13: =I17*I20 -> 140 | J13: =G56 -> 69 | K13: =IF(AND(I13<>"",I13<>0,J13<>""),J13/I13,"") -> 0.49285714 | L13: =IF(SUMIF($G$25:$G$55,">=0",$X$25:$X$55)<>0,I13*G56/SUMIF($G$25:$G$55,">=0",$X$25:$X$55),"") -> 69 | M13: =IF(AND(I13<>"",I13<>0,L13<>"",L13<>0),L13/I13,"") -> 0.49285714 | N13: =IF(AND(J13<>0,J13<>"",I13<>0,I13<>""),L13-I13,"") -> -71 | P13: =IF(AND(O13<>"",O13<>0,L13<>"",L13<>0),-O13+L13,"") | Q13: =IF(AND(O13<>"",O13<>0,N13<>0,N13<>""),O13/N13,"")
F14: Кол-во смен | I14: 28 | J14: 28 | K14: =IF(AND(I14<>"",I14<>0,J14<>""),J14/I14,"") -> 1 | L14: =IF(SUMIF($D$25:$D$55,">=0",$V$25:$V$55),I56*I8/SUMIF($D$25:$D$55,">=0",$V$25:$V$55),"") -> 1338 | N14: =IF(AND(J14<>0,J14<>"",I14<>0,I14<>""),L14-I14,"") -> 1310 | P14: =IF(AND(O14<>"",O14<>0,L14<>"",L14<>0),-O14+L14,"") | Q14: =IF(AND(O14<>"",O14<>0,N14<>0,N14<>""),O14/N14,"")
F15: Средние продажи в смену | I15: =I8/I14 -> 66792 | J15: =J8/J14 -> 30162.107 | K15: =IF(AND(I15<>"",I15<>0,J15<>""),J15/I15,"") -> 0.45158263 | L15: =J15 -> 30162.107 | M15: =IF(AND(I15<>"",I15<>0,L15<>"",L15<>0),L15/I15,"") -> 0.45158263 | N15: =IF(AND(J15<>0,J15<>"",I15<>0,I15<>""),L15-I15,"") -> -36629.893 | P15: =IF(AND(O15<>"",O15<>0,L15<>"",L15<>0),-O15+L15,"") | Q15: =IF(AND(O15<>"",O15<>0,N15<>0,N15<>""),O15/N15,"")
F16: Отставание/Перевыполнение | J16: =J8-I15*J14 -> -1025637 | K16: =IF(AND(I16<>"",I16<>0,J16<>""),J16/I16,"") | L16: =J16 -> -1025637 | M16: =IF(AND(I16<>"",I16<>0,L16<>"",L16<>0),L16/I16,"") | N16: =IF(AND(J16<>0,J16<>"",I16<>0,I16<>""),L16-I16,"") | P16: =IF(AND(O16<>"",O16<>0,L16<>"",L16<>0),-O16+L16,"") | Q16: =IF(AND(O16<>"",O16<>0,N16<>0,N16<>""),O16/N16,"") | W16: Подарочные сертификаты
F17: Трафик | I17: 1400 | J17: =I56 -> 1338 | K17: =IF(AND(I17<>"",I17<>0,J17<>""),J17/I17,"") -> 0.95571429 | L17: =J17/J14*I14 -> 1338 | M17: =IF(AND(I17<>"",I17<>0,L17<>"",L17<>0),L17/I17,"") -> 0.95571429 | N17: =IF(AND(J17<>0,J17<>"",I17<>0,I17<>""),L17-I17,"") -> -62 | P17: =IF(AND(O17<>"",O17<>0,L17<>"",L17<>0),-O17+L17,"") | Q17: =IF(AND(O17<>"",O17<>0,N17<>0,N17<>""),O17/N17,"")
K18: =IF(AND(I18<>"",I18<>0,J18<>""),J18/I18,"") | L18: =J18 -> 0 | M18: =IF(AND(I18<>"",I18<>0,L18<>"",L18<>0),L18/I18,"") | N18: =IF(AND(J18<>0,J18<>"",I18<>0,I18<>""),L18-I18,"") | P18: =IF(AND(O18<>"",O18<>0,L18<>"",L18<>0),-O18+L18,"") | Q18: =IF(AND(O18<>"",O18<>0,N18<>0,N18<>""),O18/N18,"")
K19: =IF(AND(I19<>"",I19<>0,J19<>""),J19/I19,"") | L19: =J19 -> 0 | M19: =IF(AND(I19<>"",I19<>0,L19<>"",L19<>0),L19/I19,"") | N19: =IF(AND(J19<>0,J19<>"",I19<>0,I19<>""),L19-I19,"") | O19: 0 | P19: =IF(AND(O19<>"",O19<>0,L19<>"",L19<>0),-O19+L19,"") | Q19: =IF(AND(O19<>"",O19<>0,N19<>0,N19<>""),O19/N19,"") | W19: =W18/I16 -> #DIV/0!
F20: Конверсия | I20: 0.1 | J20: =T56 -> 0.051569507 | K20: =J20/I20 -> 0.51569507 | L20: =J20/I20 -> 0.51569507 | M20: =J20/I20 -> 0.51569507 | N20: =IF(AND(J20<>0,J20<>"",I20<>0,I20<>""),L20-I20,"") -> 0.41569507 | P20: =IF(AND(O20<>"",O20<>0,L20<>"",L20<>0),-O20+L20,"") | Q20: =IF(AND(O20<>"",O20<>0,N20<>0,N20<>""),O20/N20,"")
A22: Факт продаж за месяц | U22: Раcпределение плана по дням
A23: Сотрудник | B23: Дата | C23: День недели | D23: Выручка (руб) | E23: Кол-во единиц (шт.) | F23: Средняя стоимость изделия (руб.) | G23: Количество чеков (шт.) | H23: Средняя сумма чека (руб.) | I23: Трафик | J23: Длина чека (шт.) | K23: UNOde50 | L23: IS | M23: Agafi | N23: Kalliope | O23: Raganella | P23: CC/MP | Q23: Eva Rites | R23: Antura | S23: SALE | T23: Конверсия (%) | U23: % выполнения дневного плана | V23: выручка, план | W23: кол-во ед, план | X23: Кол-во чеков, план | Y23: выручка, скорректир.план | Z23: кол-во ед, скорр. план | AA23: кол-во чеков, скорр. план | AB23: Коэфф. Дня Недели | AC23: Специфика месяца
B24: 1 | C24: 2 | D24: 3 | E24: 4 | F24: 5 | G24: 6 | H24: 7 | I24: 8 | J24: 9 | K24: 10 | L24: 11 | M24: 12 | N24: 13 | O24: 14 | P24: 15 | Q24: 16 | R24: 17 | T24: 13 | V24: 1 | W24: 2 | X24: 3 | Y24: 4 | Z24: 5 | AA24: 6 | AB24: 10 | AC24: 11
A25: Козлова, Сейтджеилова | B25: 46054 | C25: вс | D25: =42903-10892+7503 -> 39514 | E25: 8 | F25: =IF(AND(E25<>"",E25<>0),D25/E25,"") -> 4939.25 | G25: 6 | H25: =IF(AND(G25<>"",G25<>0),D25/G25,"") -> 6585.6667 | I25: 57 | J25: =IF(AND(G25<>"",G25<>0),E25/G25,"") -> 1.3333333 | L25: 7503 | M25: 8592 | T25: =IF(AND(I25<>"",I25<>0),G25/I25,"") -> 0.10526316 | U25: =D25/V25 -> 0.52837185 | V25: =$I$8*AB25*AC25/SUMPRODUCT($AC$25:$AC$55,$AB$25:$AB$55) -> 74784.453 | W25: =$I$9*AB25*AC25/SUMPRODUCT($AC$25:$AC$55,$AB$25:$AB$55) -> 10.300889 | X25: =IF($I$12="","",W25/$I$12) -> 5.5983092 | Y25: =IF(D25<>"",D25,V25) -> 39514 | Z25: =IF(E25<>"",E25,W25) -> 8 | AA25: =IF(G25<>"",G25,X25) -> 6 | AB25: 0.9414554 | AC25: 0.9414554
A26: Козлова, Сейтджеилова | B26: 46055 | C26: пн | D26: 6492 | E26: 1 | F26: =IF(AND(E26<>"",E26<>0),D26/E26,"") -> 6492 | G26: 1 | H26: =IF(AND(G26<>"",G26<>0),D26/G26,"") -> 6492 | I26: 34 | J26: =IF(AND(G26<>"",G26<>0),E26/G26,"") -> 1 | T26: =IF(AND(I26<>"",I26<>0),G26/I26,"") -> 0.029411765 | U26: =D26/V26 -> 0.10572177 | V26: =$I$8*AB26*AC26/SUMPRODUCT($AC$25:$AC$55,$AB$25:$AB$55) -> 61406.463 | W26: =$I$9*AB26*AC26/SUMPRODUCT($AC$25:$AC$55,$AB$25:$AB$55) -> 8.4581905 | X26: =IF($I$12="","",W26/$I$12) -> 4.5968427 | Y26: =IF(AC26<>"",IF(D26<>"",D26,($I$8-SUM($Y$25:Y25))*AB26*AC26/SUMPRODUCT($AC26:$AC$55,$AB26:$AB$55)),"") -> 6492 | Z26: =IF(AC26<>"",IF(E26<>"",E26,($I$9-SUM($Z$25:Z25))*AB26*AC26/SUMPRODUCT($AC26:$AC$55,$AB26:$AB$55)),"") -> 1 | AA26: =IF(AC26<>"",IF($I$12<>"",IF(G26<>"",G26,($I$9/$I$12-SUM($AA$25:AA25))*AB26*AC26/SUMPRODUCT($AC26:$AC$55,$AB26:$AB$55)),""),"") -> 1 | AB26: 0.85310234 | AC26: 0.85310234
A27: Корж, Сейтджелилова | B27: 46056 | C27: вт | D27: 30122 | E27: 5 | F27: =IF(AND(E27<>"",E27<>0),D27/E27,"") -> 6024.4 | G27: 2 | H27: =IF(AND(G27<>"",G27<>0),D27/G27,"") -> 15061 | I27: 37 | J27: =IF(AND(G27<>"",G27<>0),E27/G27,"") -> 2.5 | M27: 23903 | S27: 6219 | T27: =IF(AND(I27<>"",I27<>0),G27/I27,"") -> 0.054054054 | U27: =D27/V27 -> 0.49053468 | V27: =$I$8*AB27*AC27/SUMPRODUCT($AC$25:$AC$55,$AB$25:$AB$55) -> 61406.463 | W27: =$I$9*AB27*AC27/SUMPRODUCT($AC$25:$AC$55,$AB$25:$AB$55) -> 8.4581905 | X27: =IF($I$12="","",W27/$I$12) -> 4.5968427 | Y27: =IF(AC27<>"",IF(D27<>"",D27,($I$8-SUM($Y$25:Y26))*AB27*AC27/SUMPRODUCT($AC27:$AC$55,$AB27:$AB$55)),"") -> 30122 | Z27: =IF(AC27<>"",IF(E27<>"",E27,($I$9-SUM($Z$25:Z26))*AB27*AC27/SUMPRODUCT($AC27:$AC$55,$AB27:$AB$55)),"") -> 5 | AA27: =IF(AC27<>"",IF($I$12<>"",IF(G27<>"",G27,($I$9/$I$12-SUM($AA$25:AA26))*AB27*AC27/SUMPRODUCT($AC27:$AC$55,$AB27:$AB$55)),""),"") -> 2 | AB27: 0.85310234 | AC27: 0.85310234
A28: Корж, Козлова | B28: 46057 | C28: ср | D28: 61757 | E28: 6 | F28: =IF(AND(E28<>"",E28<>0),D28/E28,"") -> 10292.833 | G28: 4 | H28: =IF(AND(G28<>"",G28<>0),D28/G28,"") -> 15439.25 | I28: 37 | J28: =IF(AND(G28<>"",G28<>0),E28/G28,"") -> 1.5 | R28: =14445+35593 -> 50038 | T28: =IF(AND(I28<>"",I28<>0),G28/I28,"") -> 0.10810811 | U28: =D28/V28 -> 1.0057085 | V28: =$I$8*AB28*AC28/SUMPRODUCT($AC$25:$AC$55,$AB$25:$AB$55) -> 61406.463 | W28: =$I$9*AB28*AC28/SUMPRODUCT($AC$25:$AC$55,$AB$25:$AB$55) -> 8.4581905 | X28: =IF($I$12="","",W28/$I$12) -> 4.5968427 | Y28: =IF(AC28<>"",IF(D28<>"",D28,($I$8-SUM($Y$25:Y27))*AB28*AC28/SUMPRODUCT($AC28:$AC$55,$AB28:$AB$55)),"") -> 61757 | Z28: =IF(AC28<>"",IF(E28<>"",E28,($I$9-SUM($Z$25:Z27))*AB28*AC28/SUMPRODUCT($AC28:$AC$55,$AB28:$AB$55)),"") -> 6 | AA28: =IF(AC28<>"",IF($I$12<>"",IF(G28<>"",G28,($I$9/$I$12-SUM($AA$25:AA27))*AB28*AC28/SUMPRODUCT($AC28:$AC$55,$AB28:$AB$55)),""),"") -> 4 | AB28: 0.85310234 | AC28: 0.85310234
A29: Корж, Козлова | B29: 46058 | C29: чт | D29: 8335 | E29: 2 | F29: =IF(AND(E29<>"",E29<>0),D29/E29,"") -> 4167.5 | G29: 2 | H29: =IF(AND(G29<>"",G29<>0),D29/G29,"") -> 4167.5 | I29: 34 | J29: =IF(AND(G29<>"",G29<>0),E29/G29,"") -> 1 | T29: =IF(AND(I29<>"",I29<>0),G29/I29,"") -> 0.058823529 | U29: =D29/V29 -> 0.13672752 | V29: =$I$8*AB29*AC29/SUMPRODUCT($AC$25:$AC$55,$AB$25:$AB$55) -> 60960.662 | W29: =$I$9*AB29*AC29/SUMPRODUCT($AC$25:$AC$55,$AB$25:$AB$55) -> 8.3967853 | X29: =IF($I$12="","",W29/$I$12) -> 4.5634703 | Y29: =IF(AC29<>"",IF(D29<>"",D29,($I$8-SUM($Y$25:Y28))*AB29*AC29/SUMPRODUCT($AC29:$AC$55,$AB29:$AB$55)),"") -> 8335 | Z29: =IF(AC29<>"",IF(E29<>"",E29,($I$9-SUM($Z$25:Z28))*AB29*AC29/SUMPRODUCT($AC29:$AC$55,$AB29:$AB$55)),"") -> 2 | AA29: =IF(AC29<>"",IF($I$12<>"",IF(G29<>"",G29,($I$9/$I$12-SUM($AA$25:AA28))*AB29*AC29/SUMPRODUCT($AC29:$AC$55,$AB29:$AB$55)),""),"") -> 2 | AB29: 0.85 | AC29: 0.85
A30: Корж, Сейтджелилова | B30: 46059 | C30: пт | D30: 4529 | E30: 1 | F30: =IF(AND(E30<>"",E30<>0),D30/E30,"") -> 4529 | G30: 1 | H30: =IF(AND(G30<>"",G30<>0),D30/G30,"") -> 4529 | I30: 51 | J30: =IF(AND(G30<>"",G30<>0),E30/G30,"") -> 1 | T30: =IF(AND(I30<>"",I30<>0),G30/I30,"") -> 0.019607843 | U30: =D30/V30 -> 0.05367728 | V30: =$I$8*AB30*AC30/SUMPRODUCT($AC$25:$AC$55,$AB$25:$AB$55) -> 84374.618 | W30: =$I$9*AB30*AC30/SUMPRODUCT($AC$25:$AC$55,$AB$25:$AB$55) -> 11.621848 | X30: =IF($I$12="","",W30/$I$12) -> 6.3162219 | Y30: =IF(AC30<>"",IF(D30<>"",D30,($I$8-SUM($Y$25:Y29))*AB30*AC30/SUMPRODUCT($AC30:$AC$55,$AB30:$AB$55)),"") -> 4529 | Z30: =IF(AC30<>"",IF(E30<>"",E30,($I$9-SUM($Z$25:Z29))*AB30*AC30/SUMPRODUCT($AC30:$AC$55,$AB30:$AB$55)),"") -> 1 | AA30: =IF(AC30<>"",IF($I$12<>"",IF(G30<>"",G30,($I$9/$I$12-SUM($AA$25:AA29))*AB30*AC30/SUMPRODUCT($AC30:$AC$55,$AB30:$AB$55)),""),"") -> 1 | AB30: 1 | AC30: 1
A31: Сейтджелилова, Козлова | B31: 46060 | C31: сб | D31: 42752 | E31: 6 | F31: =IF(AND(E31<>"",E31<>0),D31/E31,"") -> 7125.3333 | G31: 3 | H31: =IF(AND(G31<>"",G31<>0),D31/G31,"") -> 14250.667 | I31: 56 | J31: =IF(AND(G31<>"",G31<>0),E31/G31,"") -> 2 | M31: 15984 | T31: =IF(AND(I31<>"",I31<>0),G31/I31,"") -> 0.053571429 | U31: =D31/V31 -> 0.41875427 | V31: =$I$8*AB31*AC31/SUMPRODUCT($AC$25:$AC$55,$AB$25:$AB$55) -> 102093.29 | W31: =$I$9*AB31*AC31/SUMPRODUCT($AC$25:$AC$55,$AB$25:$AB$55) -> 14.062436 | X31: =IF($I$12="","",W31/$I$12) -> 7.6426285 | Y31: =IF(AC31<>"",IF(D31<>"",D31,($I$8-SUM($Y$25:Y30))*AB31*AC31/SUMPRODUCT($AC31:$AC$55,$AB31:$AB$55)),"") -> 42752 | Z31: =IF(AC31<>"",IF(E31<>"",E31,($I$9-SUM($Z$25:Z30))*AB31*AC31/SUMPRODUCT($AC31:$AC$55,$AB31:$AB$55)),"") -> 6 | AA31: =IF(AC31<>"",IF($I$12<>"",IF(G31<>"",G31,($I$9/$I$12-SUM($AA$25:AA30))*AB31*AC31/SUMPRODUCT($AC31:$AC$55,$AB31:$AB$55)),""),"") -> 3 | AB31: 1.1 | AC31: 1.1
A32: Сейтджелилова, Козлова | B32: 46061 | C32: вс | D32: 31503 | E32: 5 | F32: =IF(AND(E32<>"",E32<>0),D32/E32,"") -> 6300.6 | G32: 3 | H32: =IF(AND(G32<>"",G32<>0),D32/G32,"") -> 10501 | I32: 60 | J32: =IF(AND(G32<>"",G32<>0),E32/G32,"") -> 1.6666667 | T32: =IF(AND(I32<>"",I32<>0),G32/I32,"") -> 0.05 | U32: =D32/V32 -> 0.42125066 | V32: =$I$8*AB32*AC32/SUMPRODUCT($AC$25:$AC$55,$AB$25:$AB$55) -> 74784.453 | W32: =$I$9*AB32*AC32/SUMPRODUCT($AC$25:$AC$55,$AB$25:$AB$55) -> 10.300889 | X32: =IF($I$12="","",W32/$I$12) -> 5.5983092 | Y32: =IF(AC32<>"",IF(D32<>"",D32,($I$8-SUM($Y$25:Y31))*AB32*AC32/SUMPRODUCT($AC32:$AC$55,$AB32:$AB$55)),"") -> 31503 | Z32: =IF(AC32<>"",IF(E32<>"",E32,($I$9-SUM($Z$25:Z31))*AB32*AC32/SUMPRODUCT($AC32:$AC$55,$AB32:$AB$55)),"") -> 5 | AA32: =IF(AC32<>"",IF($I$12<>"",IF(G32<>"",G32,($I$9/$I$12-SUM($AA$25:AA31))*AB32*AC32/SUMPRODUCT($AC32:$AC$55,$AB32:$AB$55)),""),"") -> 3 | AB32: 0.9414554 | AC32: 0.9414554
A33: Козлова, Корж | B33: 46062 | C33: пн | D33: 0 | E33: 0 | F33: =IF(AND(E33<>"",E33<>0),D33/E33,"") | G33: 0 | H33: =IF(AND(G33<>"",G33<>0),D33/G33,"") | I33: 39 | J33: =IF(AND(G33<>"",G33<>0),E33/G33,"") | T33: =IF(AND(I33<>"",I33<>0),G33/I33,"") -> 0 | U33: =D33/V33 -> 0 | V33: =$I$8*AB33*AC33/SUMPRODUCT($AC$25:$AC$55,$AB$25:$AB$55) -> 47460.723 | W33: =$I$9*AB33*AC33/SUMPRODUCT($AC$25:$AC$55,$AB$25:$AB$55) -> 6.5372896 | X33: =IF($I$12="","",W33/$I$12) -> 3.5528748 | Y33: =IF(AC33<>"",IF(D33<>"",D33,($I$8-SUM($Y$25:Y32))*AB33*AC33/SUMPRODUCT($AC33:$AC$55,$AB33:$AB$55)),"") -> 0 | Z33: =IF(AC33<>"",IF(E33<>"",E33,($I$9-SUM($Z$25:Z32))*AB33*AC33/SUMPRODUCT($AC33:$AC$55,$AB33:$AB$55)),"") -> 0 | AA33: =IF(AC33<>"",IF($I$12<>"",IF(G33<>"",G33,($I$9/$I$12-SUM($AA$25:AA32))*AB33*AC33/SUMPRODUCT($AC33:$AC$55,$AB33:$AB$55)),""),"") -> 0 | AB33: 0.75 | AC33: 0.75
A34: Свидовская, Сейтджелилова | B34: 46063 | C34: вт | D34: 44550 | E34: 6 | F34: =IF(AND(E34<>"",E34<>0),D34/E34,"") -> 7425 | G34: 4 | H34: =IF(AND(G34<>"",G34<>0),D34/G34,"") -> 11137.5 | I34: 51 | J34: =IF(AND(G34<>"",G34<>0),E34/G34,"") -> 1.5 | Q34: 9776.78 | T34: =IF(AND(I34<>"",I34<>0),G34/I34,"") -> 0.078431373 | U34: =D34/V34 -> 0.93867092 | V34: =$I$8*AB34*AC34/SUMPRODUCT($AC$25:$AC$55,$AB$25:$AB$55) -> 47460.723 | W34: =$I$9*AB34*AC34/SUMPRODUCT($AC$25:$AC$55,$AB$25:$AB$55) -> 6.5372896 | X34: =IF($I$12="","",W34/$I$12) -> 3.5528748 | Y34: =IF(AC34<>"",IF(D34<>"",D34,($I$8-SUM($Y$25:Y33))*AB34*AC34/SUMPRODUCT($AC34:$AC$55,$AB34:$AB$55)),"") -> 44550 | Z34: =IF(AC34<>"",IF(E34<>"",E34,($I$9-SUM($Z$25:Z33))*AB34*AC34/SUMPRODUCT($AC34:$AC$55,$AB34:$AB$55)),"") -> 6 | AA34: =IF(AC34<>"",IF($I$12<>"",IF(G34<>"",G34,($I$9/$I$12-SUM($AA$25:AA33))*AB34*AC34/SUMPRODUCT($AC34:$AC$55,$AB34:$AB$55)),""),"") -> 4 | AB34: 0.75 | AC34: 0.75
A35: Свидовская, Сейтджелилова | B35: 46064 | C35: ср | D35: =5692+4741 -> 10433 | E35: 2 | F35: =IF(AND(E35<>"",E35<>0),D35/E35,"") -> 5216.5 | G35: 2 | H35: =IF(AND(G35<>"",G35<>0),D35/G35,"") -> 5216.5 | I35: 54 | J35: =IF(AND(G35<>"",G35<>0),E35/G35,"") -> 1 | T35: =IF(AND(I35<>"",I35<>0),G35/I35,"") -> 0.037037037 | U35: =D35/V35 -> 0.19320458 | V35: =$I$8*AB35*AC35/SUMPRODUCT($AC$25:$AC$55,$AB$25:$AB$55) -> 53999.756 | W35: =$I$9*AB35*AC35/SUMPRODUCT($AC$25:$AC$55,$AB$25:$AB$55) -> 7.4379829 | X35: =IF($I$12="","",W35/$I$12) -> 4.042382 | Y35: =IF(AC35<>"",IF(D35<>"",D35,($I$8-SUM($Y$25:Y34))*AB35*AC35/SUMPRODUCT($AC35:$AC$55,$AB35:$AB$55)),"") -> 10433 | Z35: =IF(AC35<>"",IF(E35<>"",E35,($I$9-SUM($Z$25:Z34))*AB35*AC35/SUMPRODUCT($AC35:$AC$55,$AB35:$AB$55)),"") -> 2 | AA35: =IF(AC35<>"",IF($I$12<>"",IF(G35<>"",G35,($I$9/$I$12-SUM($AA$25:AA34))*AB35*AC35/SUMPRODUCT($AC35:$AC$55,$AB35:$AB$55)),""),"") -> 2 | AB35: 0.8 | AC35: 0.8
A36: Корж, Свидовская | B36: 46065 | C36: чт | D36: =181056+27344 -> 208400 | E36: 14 | F36: =IF(AND(E36<>"",E36<>0),D36/E36,"") -> 14885.714 | G36: 4 | H36: =IF(AND(G36<>"",G36<>0),D36/G36,"") -> 52100 | I36: 41 | J36: =IF(AND(G36<>"",G36<>0),E36/G36,"") -> 3.5 | K36: 62658 | L36: 15902 | M36: 23181 | R36: 79315 | S36: 1647 | T36: =IF(AND(I36<>"",I36<>0),G36/I36,"") -> 0.097560976 | U36: =D36/V36 -> 3.8592767 | V36: =$I$8*AB36*AC36/SUMPRODUCT($AC$25:$AC$55,$AB$25:$AB$55) -> 53999.756 | W36: =$I$9*AB36*AC36/SUMPRODUCT($AC$25:$AC$55,$AB$25:$AB$55) -> 7.4379829 | X36: =IF($I$12="","",W36/$I$12) -> 4.042382 | Y36: =IF(AC36<>"",IF(D36<>"",D36,($I$8-SUM($Y$25:Y35))*AB36*AC36/SUMPRODUCT($AC36:$AC$55,$AB36:$AB$55)),"") -> 208400 | Z36: =IF(AC36<>"",IF(E35<>"",E35,($I$9-SUM($Z$25:Z35))*AB36*AC36/SUMPRODUCT($AC36:$AC$55,$AB36:$AB$55)),"") -> 2 | AA36: =IF(AC36<>"",IF($I$12<>"",IF(G36<>"",G36,($I$9/$I$12-SUM($AA$25:AA35))*AB36*AC36/SUMPRODUCT($AC36:$AC$55,$AB36:$AB$55)),""),"") -> 4 | AB36: 0.8 | AC36: 0.8
A37: Корж, Свидовская | B37: 46066 | C37: пт | D37: =48975+10982 -> 59957 | E37: 9 | F37: =IF(AND(E37<>"",E37<>0),D37/E37,"") -> 6661.8889 | G37: 6 | H37: =IF(AND(G37<>"",G37<>0),D37/G37,"") -> 9992.8333 | I37: 71 | J37: =IF(AND(G37<>"",G37<>0),E37/G37,"") -> 1.5 | M37: 10982 | T37: =IF(AND(I37<>"",I37<>0),G37/I37,"") -> 0.084507042 | U37: =D37/V37 -> 0.7106047 | V37: =$I$8*AB37*AC37/SUMPRODUCT($AC$25:$AC$55,$AB$25:$AB$55) -> 84374.618 | W37: =$I$9*AB37*AC37/SUMPRODUCT($AC$25:$AC$55,$AB$25:$AB$55) -> 11.621848 | X37: =IF($I$12="","",W37/$I$12) -> 6.3162219 | Y37: =IF(AC37<>"",IF(D37<>"",D37,($I$8-SUM($Y$25:Y36))*AB37*AC37/SUMPRODUCT($AC37:$AC$55,$AB37:$AB$55)),"") -> 59957 | Z37: =IF(AC37<>"",IF(E37<>"",E37,($I$9-SUM($Z$25:Z36))*AB37*AC37/SUMPRODUCT($AC37:$AC$55,$AB37:$AB$55)),"") -> 9 | AA37: =IF(AC37<>"",IF($I$12<>"",IF(G37<>"",G37,($I$9/$I$12-SUM($AA$25:AA36))*AB37*AC37/SUMPRODUCT($AC37:$AC$55,$AB37:$AB$55)),""),"") -> 6 | AB37: 1 | AC37: 1
A38: Корж, Сейтджелилова | B38: 46067 | C38: сб | D38: 38589 | E38: 4 | F38: =IF(AND(E38<>"",E38<>0),D38/E38,"") -> 9647.25 | G38: 3 | H38: =IF(AND(G38<>"",G38<>0),D38/G38,"") -> 12863 | I38: 51 | J38: =IF(AND(G38<>"",G38<>0),E38/G38,"") -> 1.3333333 | T38: =IF(AND(I38<>"",I38<>0),G38/I38,"") -> 0.058823529 | U38: =D38/V38 -> 0.37797784 | V38: =$I$8*AB38*AC38/SUMPRODUCT($AC$25:$AC$55,$AB$25:$AB$55) -> 102093.29 | W38: =$I$9*AB38*AC38/SUMPRODUCT($AC$25:$AC$55,$AB$25:$AB$55) -> 14.062436 | X38: =IF($I$12="","",W38/$I$12) -> 7.6426285 | Y38: =IF(AC38<>"",IF(D38<>"",D38,($I$8-SUM($Y$25:Y37))*AB38*AC38/SUMPRODUCT($AC38:$AC$55,$AB38:$AB$55)),"") -> 38589 | Z38: =IF(AC38<>"",IF(E38<>"",E38,($I$9-SUM($Z$25:Z37))*AB38*AC38/SUMPRODUCT($AC38:$AC$55,$AB38:$AB$55)),"") -> 4 | AA38: =IF(AC38<>"",IF($I$12<>"",IF(G38<>"",G38,($I$9/$I$12-SUM($AA$25:AA37))*AB38*AC38/SUMPRODUCT($AC38:$AC$55,$AB38:$AB$55)),""),"") -> 3 | AB38: 1.1 | AC38: 1.1
A39: Корж, Сейтджелилова | B39: 46068 | C39: вс | D39: 3193 | E39: 1 | F39: =IF(AND(E39<>"",E39<>0),D39/E39,"") -> 3193 | G39: 1 | H39: =IF(AND(G39<>"",G39<>0),D39/G39,"") -> 3193 | I39: 67 | J39: =IF(AND(G39<>"",G39<>0),E39/G39,"") -> 1 | T39: =IF(AND(I39<>"",I39<>0),G39/I39,"") -> 0.014925373 | U39: =D39/V39 -> 0.04269604 | V39: =$I$8*AB39*AC39/SUMPRODUCT($AC$25:$AC$55,$AB$25:$AB$55) -> 74784.453 | W39: =$I$9*AB39*AC39/SUMPRODUCT($AC$25:$AC$55,$AB$25:$AB$55) -> 10.300889 | X39: =IF($I$12="","",W39/$I$12) -> 5.5983092 | Y39: =IF(AC39<>"",IF(D39<>"",D39,($I$8-SUM($Y$25:Y38))*AB39*AC39/SUMPRODUCT($AC39:$AC$55,$AB39:$AB$55)),"") -> 3193 | Z39: =IF(AC39<>"",IF(E39<>"",E39,($I$9-SUM($Z$25:Z38))*AB39*AC39/SUMPRODUCT($AC39:$AC$55,$AB39:$AB$55)),"") -> 1 | AA39: =IF(AC39<>"",IF($I$12<>"",IF(G39<>"",G39,($I$9/$I$12-SUM($AA$25:AA38))*AB39*AC39/SUMPRODUCT($AC39:$AC$55,$AB39:$AB$55)),""),"") -> 1 | AB39: 0.9414554 | AC39: 0.9414554
A40: Свидовская, Сейтджелилова | B40: 46069 | C40: пн | D40: 32673 | E40: 3 | F40: =IF(AND(E40<>"",E40<>0),D40/E40,"") -> 10891 | G40: 2 | H40: =IF(AND(G40<>"",G40<>0),D40/G40,"") -> 16336.5 | I40: 42 | J40: =IF(AND(G40<>"",G40<>0),E40/G40,"") -> 1.5 | M40: 27672 | T40: =IF(AND(I40<>"",I40<>0),G40/I40,"") -> 0.047619048 | U40: =D40/V40 -> 0.68842188 | V40: =$I$8*AB40*AC40/SUMPRODUCT($AC$25:$AC$55,$AB$25:$AB$55) -> 47460.723 | W40: =$I$9*AB40*AC40/SUMPRODUCT($AC$25:$AC$55,$AB$25:$AB$55) -> 6.5372896 | X40: =IF($I$12="","",W40/$I$12) -> 3.5528748 | Y40: =IF(AC40<>"",IF(D40<>"",D40,($I$8-SUM($Y$25:Y39))*AB40*AC40/SUMPRODUCT($AC40:$AC$55,$AB40:$AB$55)),"") -> 32673 | Z40: =IF(AC40<>"",IF(E40<>"",E40,($I$9-SUM($Z$25:Z39))*AB40*AC40/SUMPRODUCT($AC40:$AC$55,$AB40:$AB$55)),"") -> 3 | AA40: =IF(AC40<>"",IF($I$12<>"",IF(G40<>"",G40,($I$9/$I$12-SUM($AA$25:AA39))*AB40*AC40/SUMPRODUCT($AC40:$AC$55,$AB40:$AB$55)),""),"") -> 2 | AB40: 0.75 | AC40: 0.75
A41: Свидовская, Сейтджелилова | B41: 46070 | C41: вт | D41: 21121 | E41: 3 | F41: =IF(AND(E41<>"",E41<>0),D41/E41,"") -> 7040.3333 | G41: 2 | H41: =IF(AND(G41<>"",G41<>0),D41/G41,"") -> 10560.5 | I41: 35 | J41: =IF(AND(G41<>"",G41<>0),E41/G41,"") -> 1.5 | Q41: 7605 | T41: =IF(AND(I41<>"",I41<>0),G41/I41,"") -> 0.057142857 | U41: =D41/V41 -> 0.3911314 | V41: =$I$8*AB41*AC41/SUMPRODUCT($AC$25:$AC$55,$AB$25:$AB$55) -> 53999.756 | W41: =$I$9*AB41*AC41/SUMPRODUCT($AC$25:$AC$55,$AB$25:$AB$55) -> 7.4379829 | X41: =IF($I$12="","",W41/$I$12) -> 4.042382 | Y41: =IF(AC41<>"",IF(D41<>"",D41,($I$8-SUM($Y$25:Y40))*AB41*AC41/SUMPRODUCT($AC41:$AC$55,$AB41:$AB$55)),"") -> 21121 | Z41: =IF(AC41<>"",IF(E41<>"",E41,($I$9-SUM($Z$25:Z40))*AB41*AC41/SUMPRODUCT($AC41:$AC$55,$AB41:$AB$55)),"") -> 3 | AA41: =IF(AC41<>"",IF($I$12<>"",IF(G41<>"",G41,($I$9/$I$12-SUM($AA$25:AA40))*AB41*AC41/SUMPRODUCT($AC41:$AC$55,$AB41:$AB$55)),""),"") -> 2 | AB41: 0.8 | AC41: 0.8
A42: Свидовская, Корж | B42: 46071 | C42: ср | D42: 0 | E42: 0 | F42: =IF(AND(E42<>"",E42<>0),D42/E42,"") | G42: 0 | H42: =IF(AND(G42<>"",G42<>0),D42/G42,"") | I42: 49 | J42: =IF(AND(G42<>"",G42<>0),E42/G42,"") | T42: =IF(AND(I42<>"",I42<>0),G42/I42,"") -> 0 | U42: =D42/V42 -> 0 | V42: =$I$8*AB42*AC42/SUMPRODUCT($AC$25:$AC$55,$AB$25:$AB$55) -> 61406.463 | W42: =$I$9*AB42*AC42/SUMPRODUCT($AC$25:$AC$55,$AB$25:$AB$55) -> 8.4581905 | X42: =IF($I$12="","",W42/$I$12) -> 4.5968427 | Y42: =IF(AC42<>"",IF(D42<>"",D42,($I$8-SUM($Y$25:Y41))*AB42*AC42/SUMPRODUCT($AC42:$AC$55,$AB42:$AB$55)),"") -> 0 | Z42: =IF(AC42<>"",IF(E42<>"",E42,($I$9-SUM($Z$25:Z41))*AB42*AC42/SUMPRODUCT($AC42:$AC$55,$AB42:$AB$55)),"") -> 0 | AA42: =IF(AC42<>"",IF($I$12<>"",IF(G42<>"",G42,($I$9/$I$12-SUM($AA$25:AA41))*AB42*AC42/SUMPRODUCT($AC42:$AC$55,$AB42:$AB$55)),""),"") -> 0 | AB42: 0.85310234 | AC42: 0.85310234
A43: Свидовская, Корж | B43: 46072 | C43: чт | D43: =8883+7139 -> 16022 | E43: 3 | F43: =IF(AND(E43<>"",E43<>0),D43/E43,"") -> 5340.6667 | G43: 2 | H43: =IF(AND(G43<>"",G43<>0),D43/G43,"") -> 8011 | I43: 32 | J43: =IF(AND(G43<>"",G43<>0),E43/G43,"") -> 1.5 | T43: =IF(AND(I43<>"",I43<>0),G43/I43,"") -> 0.0625 | U43: =D43/V43 -> 0.26282523 | V43: =$I$8*AB43*AC43/SUMPRODUCT($AC$25:$AC$55,$AB$25:$AB$55) -> 60960.662 | W43: =$I$9*AB43*AC43/SUMPRODUCT($AC$25:$AC$55,$AB$25:$AB$55) -> 8.3967853 | X43: =IF($I$12="","",W43/$I$12) -> 4.5634703 | Y43: =IF(AC43<>"",IF(D43<>"",D43,($I$8-SUM($Y$25:Y42))*AB43*AC43/SUMPRODUCT($AC43:$AC$55,$AB43:$AB$55)),"") -> 16022 | Z43: =IF(AC43<>"",IF(E43<>"",E43,($I$9-SUM($Z$25:Z42))*AB43*AC43/SUMPRODUCT($AC43:$AC$55,$AB43:$AB$55)),"") -> 3 | AA43: =IF(AC43<>"",IF($I$12<>"",IF(G43<>"",G43,($I$9/$I$12-SUM($AA$25:AA42))*AB43*AC43/SUMPRODUCT($AC43:$AC$55,$AB43:$AB$55)),""),"") -> 2 | AB43: 0.85 | AC43: 0.85
A44: Корж, Сейтджелилова | B44: 46073 | C44: пт | D44: 26461 | E44: 5 | F44: =IF(AND(E44<>"",E44<>0),D44/E44,"") -> 5292.2 | G44: 2 | H44: =IF(AND(G44<>"",G44<>0),D44/G44,"") -> 13230.5 | I44: 63 | J44: =IF(AND(G44<>"",G44<>0),E44/G44,"") -> 2.5 | T44: =IF(AND(I44<>"",I44<>0),G44/I44,"") -> 0.031746032 | U44: =D44/V44 -> 0.38717688 | V44: =$I$8*AB44*AC44/SUMPRODUCT($AC$25:$AC$55,$AB$25:$AB$55) -> 68343.441 | W44: =$I$9*AB44*AC44/SUMPRODUCT($AC$25:$AC$55,$AB$25:$AB$55) -> 9.4136971 | X44: =IF($I$12="","",W44/$I$12) -> 5.1161397 | Y44: =IF(AC44<>"",IF(D44<>"",D44,($I$8-SUM($Y$25:Y43))*AB44*AC44/SUMPRODUCT($AC44:$AC$55,$AB44:$AB$55)),"") -> 26461 | Z44: =IF(AC44<>"",IF(E44<>"",E44,($I$9-SUM($Z$25:Z43))*AB44*AC44/SUMPRODUCT($AC44:$AC$55,$AB44:$AB$55)),"") -> 5 | AA44: =IF(AC44<>"",IF($I$12<>"",IF(G44<>"",G44,($I$9/$I$12-SUM($AA$25:AA43))*AB44*AC44/SUMPRODUCT($AC44:$AC$55,$AB44:$AB$55)),""),"") -> 2 | AB44: 0.9 | AC44: 0.9
A45: Корж, Сейтджелилова | B45: 46074 | C45: сб | D45: 27942 | E45: 3 | F45: =IF(AND(E45<>"",E45<>0),D45/E45,"") -> 9314 | G45: 3 | H45: =IF(AND(G45<>"",G45<>0),D45/G45,"") -> 9314 | I45: 51 | J45: =IF(AND(G45<>"",G45<>0),E45/G45,"") -> 1 | T45: =IF(AND(I45<>"",I45<>0),G45/I45,"") -> 0.058823529 | U45: =D45/V45 -> 0.27369086 | V45: =$I$8*AB45*AC45/SUMPRODUCT($AC$25:$AC$55,$AB$25:$AB$55) -> 102093.29 | W45: =$I$9*AB45*AC45/SUMPRODUCT($AC$25:$AC$55,$AB$25:$AB$55) -> 14.062436 | X45: =IF($I$12="","",W45/$I$12) -> 7.6426285 | Y45: =IF(AC45<>"",IF(D45<>"",D45,($I$8-SUM($Y$25:Y44))*AB45*AC45/SUMPRODUCT($AC45:$AC$55,$AB45:$AB$55)),"") -> 27942 | Z45: =IF(AC45<>"",IF(E45<>"",E45,($I$9-SUM($Z$25:Z44))*AB45*AC45/SUMPRODUCT($AC45:$AC$55,$AB45:$AB$55)),"") -> 3 | AA45: =IF(AC45<>"",IF($I$12<>"",IF(G45<>"",G45,($I$9/$I$12-SUM($AA$25:AA44))*AB45*AC45/SUMPRODUCT($AC45:$AC$55,$AB45:$AB$55)),""),"") -> 3 | AB45: 1.1 | AC45: 1.1
A46: Свидовская, Сейтджелилова | B46: 46075 | C46: вс | D46: 27856 | E46: 5 | F46: =IF(AND(E46<>"",E46<>0),D46/E46,"") -> 5571.2 | G46: 3 | H46: =IF(AND(G46<>"",G46<>0),D46/G46,"") -> 9285.3333 | I46: 53 | J46: =IF(AND(G46<>"",G46<>0),E46/G46,"") -> 1.6666667 | S46: 2147 | T46: =IF(AND(I46<>"",I46<>0),G46/I46,"") -> 0.056603774 | U46: =D46/V46 -> 0.33014668 | V46: =$I$8*AB46*AC46/SUMPRODUCT($AC$25:$AC$55,$AB$25:$AB$55) -> 84374.618 | W46: =$I$9*AB46*AC46/SUMPRODUCT($AC$25:$AC$55,$AB$25:$AB$55) -> 11.621848 | X46: =IF($I$12="","",W46/$I$12) -> 6.3162219 | Y46: =IF(AC46<>"",IF(D46<>"",D46,($I$8-SUM($Y$25:Y45))*AB46*AC46/SUMPRODUCT($AC46:$AC$55,$AB46:$AB$55)),"") -> 27856 | Z46: =IF(AC45<>"",IF(E45<>"",E45,($I$9-SUM($Z$25:Z44))*AB45*AC45/SUMPRODUCT($AC45:$AC$55,$AB45:$AB$55)),"") -> 3 | AA46: =IF(AC45<>"",IF($I$12<>"",IF(G45<>"",G45,($I$9/$I$12-SUM($AA$25:AA44))*AB45*AC45/SUMPRODUCT($AC45:$AC$55,$AB45:$AB$55)),""),"") -> 3 | AB46: 1 | AC46: 1
A47: Свидовская, Сейтджелилова | B47: 46076 | C47: пн | D47: 18806 | E47: 2 | F47: =IF(AND(E47<>"",E47<>0),D47/E47,"") -> 9403 | G47: 2 | H47: =IF(AND(G47<>"",G47<>0),D47/G47,"") -> 9403 | I47: 29 | J47: =IF(AND(G47<>"",G47<>0),E47/G47,"") -> 1 | M47: 10903 | T47: =IF(AND(I47<>"",I47<>0),G47/I47,"") -> 0.068965517 | U47: =D47/V47 -> 0.39624344 | V47: =$I$8*AB47*AC47/SUMPRODUCT($AC$25:$AC$55,$AB$25:$AB$55) -> 47460.723 | W47: =$I$9*AB47*AC47/SUMPRODUCT($AC$25:$AC$55,$AB$25:$AB$55) -> 6.5372896 | X47: =IF($I$12="","",W47/$I$12) -> 3.5528748 | Y47: =IF(AC47<>"",IF(D47<>"",D47,($I$8-SUM($Y$25:Y46))*AB47*AC47/SUMPRODUCT($AC47:$AC$55,$AB47:$AB$55)),"") -> 18806 | Z47: =IF(AC47<>"",IF(E47<>"",E47,($I$9-SUM($Z$25:Z46))*AB47*AC47/SUMPRODUCT($AC47:$AC$55,$AB47:$AB$55)),"") -> 2 | AA47: =IF(AC47<>"",IF($I$12<>"",IF(G47<>"",G47,($I$9/$I$12-SUM($AA$25:AA46))*AB47*AC47/SUMPRODUCT($AC47:$AC$55,$AB47:$AB$55)),""),"") -> 2 | AB47: 0.75 | AC47: 0.75
A48: Свидовская, Корж, Сейтджелилова | B48: 46077 | C48: вт | D48: 16803 | E48: 1 | F48: =IF(AND(E48<>"",E48<>0),D48/E48,"") -> 16803 | G48: 1 | H48: =IF(AND(G48<>"",G48<>0),D48/G48,"") -> 16803 | I48: 33 | J48: =IF(AND(G48<>"",G48<>0),E48/G48,"") -> 1 | T48: =IF(AND(I48<>"",I48<>0),G48/I48,"") -> 0.03030303 | U48: =D48/V48 -> 0.31116808 | V48: =$I$8*AB48*AC48/SUMPRODUCT($AC$25:$AC$55,$AB$25:$AB$55) -> 53999.756 | W48: =$I$9*AB48*AC48/SUMPRODUCT($AC$25:$AC$55,$AB$25:$AB$55) -> 7.4379829 | X48: =IF($I$12="","",W48/$I$12) -> 4.042382 | Y48: =IF(AC48<>"",IF(D48<>"",D48,($I$8-SUM($Y$25:Y47))*AB48*AC48/SUMPRODUCT($AC48:$AC$55,$AB48:$AB$55)),"") -> 16803 | Z48: =IF(AC48<>"",IF(E48<>"",E48,($I$9-SUM($Z$25:Z47))*AB48*AC48/SUMPRODUCT($AC48:$AC$55,$AB48:$AB$55)),"") -> 1 | AA48: =IF(AC48<>"",IF($I$12<>"",IF(G48<>"",G48,($I$9/$I$12-SUM($AA$25:AA47))*AB48*AC48/SUMPRODUCT($AC48:$AC$55,$AB48:$AB$55)),""),"") -> 1 | AB48: 0.8 | AC48: 0.8
A49: Корж, Свидовская | B49: 46078 | C49: ср | D49: 0 | E49: 0 | F49: =IF(AND(E49<>"",E49<>0),D49/E49,"") | G49: 0 | H49: =IF(AND(G49<>"",G49<>0),D49/G49,"") | I49: 43 | J49: =IF(AND(G49<>"",G49<>0),E49/G49,"") | T49: =IF(AND(I49<>"",I49<>0),G49/I49,"") -> 0 | U49: =D49/V49 -> 0 | V49: =$I$8*AB49*AC49/SUMPRODUCT($AC$25:$AC$55,$AB$25:$AB$55) -> 53999.756 | W49: =$I$9*AB49*AC49/SUMPRODUCT($AC$25:$AC$55,$AB$25:$AB$55) -> 7.4379829 | X49: =IF($I$12="","",W49/$I$12) -> 4.042382 | Y49: =IF(AC49<>"",IF(D49<>"",D49,($I$8-SUM($Y$25:Y48))*AB49*AC49/SUMPRODUCT($AC49:$AC$55,$AB49:$AB$55)),"") -> 0 | Z49: =IF(AC49<>"",IF(E49<>"",E49,($I$9-SUM($Z$25:Z48))*AB49*AC49/SUMPRODUCT($AC49:$AC$55,$AB49:$AB$55)),"") -> 0 | AA49: =IF(AC49<>"",IF($I$12<>"",IF(G49<>"",G49,($I$9/$I$12-SUM($AA$25:AA48))*AB49*AC49/SUMPRODUCT($AC49:$AC$55,$AB49:$AB$55)),""),"") -> 0 | AB49: 0.8 | AC49: 0.8
A50: Корж, Сейтджелилова | B50: 46079 | C50: чт | D50: 17422 | E50: 3 | F50: =IF(AND(E50<>"",E50<>0),D50/E50,"") -> 5807.3333 | G50: 3 | H50: =IF(AND(G50<>"",G50<>0),D50/G50,"") -> 5807.3333 | I50: 57 | J50: =IF(AND(G50<>"",G50<>0),E50/G50,"") -> 1 | T50: =IF(AND(I50<>"",I50<>0),G50/I50,"") -> 0.052631579 | U50: =D50/V50 -> 0.32263109 | V50: =$I$8*AB50*AC50/SUMPRODUCT($AC$25:$AC$55,$AB$25:$AB$55) -> 53999.756 | W50: =$I$9*AB50*AC50/SUMPRODUCT($AC$25:$AC$55,$AB$25:$AB$55) -> 7.4379829 | X50: =IF($I$12="","",W50/$I$12) -> 4.042382 | Y50: =IF(AC50<>"",IF(D50<>"",D50,($I$8-SUM($Y$25:Y49))*AB50*AC50/SUMPRODUCT($AC50:$AC$55,$AB50:$AB$55)),"") -> 17422 | Z50: =IF(AC50<>"",IF(E50<>"",E50,($I$9-SUM($Z$25:Z49))*AB50*AC50/SUMPRODUCT($AC50:$AC$55,$AB50:$AB$55)),"") -> 3 | AA50: =IF(AC50<>"",IF($I$12<>"",IF(G50<>"",G50,($I$9/$I$12-SUM($AA$25:AA49))*AB50*AC50/SUMPRODUCT($AC50:$AC$55,$AB50:$AB$55)),""),"") -> 3 | AB50: 0.8 | AC50: 0.8
A51: Корж, Сейтджелилова | B51: 46080 | C51: пт | D51: 12444 | E51: 3 | F51: =IF(AND(E51<>"",E51<>0),D51/E51,"") -> 4148 | G51: 3 | H51: =IF(AND(G51<>"",G51<>0),D51/G51,"") -> 4148 | I51: 58 | J51: =IF(AND(G51<>"",G51<>0),E51/G51,"") -> 1 | T51: =IF(AND(I51<>"",I51<>0),G51/I51,"") -> 0.051724138 | U51: =D51/V51 -> 0.18208039 | V51: =$I$8*AB51*AC51/SUMPRODUCT($AC$25:$AC$55,$AB$25:$AB$55) -> 68343.441 | W51: =$I$9*AB51*AC51/SUMPRODUCT($AC$25:$AC$55,$AB$25:$AB$55) -> 9.4136971 | X51: =IF($I$12="","",W51/$I$12) -> 5.1161397 | Y51: =IF(AC51<>"",IF(D51<>"",D51,($I$8-SUM($Y$25:Y50))*AB51*AC51/SUMPRODUCT($AC51:$AC$55,$AB51:$AB$55)),"") -> 12444 | Z51: =IF(AC51<>"",IF(E51<>"",E51,($I$9-SUM($Z$25:Z50))*AB51*AC51/SUMPRODUCT($AC51:$AC$55,$AB51:$AB$55)),"") -> 3 | AA51: =IF(AC51<>"",IF($I$12<>"",IF(G51<>"",G51,($I$9/$I$12-SUM($AA$25:AA50))*AB51*AC51/SUMPRODUCT($AC51:$AC$55,$AB51:$AB$55)),""),"") -> 3 | AB51: 0.9 | AC51: 0.9
A52: Свидовская, Сейтджелилова | B52: 46081 | C52: сб | D52: 36863 | E52: 5 | F52: =IF(AND(E52<>"",E52<>0),D52/E52,"") -> 7372.6 | G52: 4 | H52: =IF(AND(G52<>"",G52<>0),D52/G52,"") -> 9215.75 | I52: 53 | J52: =IF(AND(G52<>"",G52<>0),E52/G52,"") -> 1.25 | O52: 10993 | T52: =IF(AND(I52<>"",I52<>0),G52/I52,"") -> 0.075471698 | U52: =D52/V52 -> 0.53937876 | V52: =$I$8*AB52*AC52/SUMPRODUCT($AC$25:$AC$55,$AB$25:$AB$55) -> 68343.441 | W52: =$I$9*AB52*AC52/SUMPRODUCT($AC$25:$AC$55,$AB$25:$AB$55) -> 9.4136971 | X52: =IF($I$12="","",W52/$I$12) -> 5.1161397 | Y52: =IF(AC52<>"",IF(D52<>"",D52,($I$8-SUM($Y$25:Y51))*AB52*AC52/SUMPRODUCT($AC52:$AC$55,$AB52:$AB$55)),"") -> 36863 | Z52: =IF(AC52<>"",IF(E52<>"",E52,($I$9-SUM($Z$25:Z51))*AB52*AC52/SUMPRODUCT($AC52:$AC$55,$AB52:$AB$55)),"") -> 5 | AA52: =IF(AC52<>"",IF($I$12<>"",IF(G52<>"",G52,($I$9/$I$12-SUM($AA$25:AA51))*AB52*AC52/SUMPRODUCT($AC52:$AC$55,$AB52:$AB$55)),""),"") -> 4 | AB52: 0.9 | AC52: 0.9
F53: =IF(AND(E53<>"",E53<>0),D53/E53,"") | H53: =IF(AND(G53<>"",G53<>0),D53/G53,"") | J53: =IF(AND(G53<>"",G53<>0),E53/G53,"") | T53: =IF(AND(I53<>"",I53<>0),G53/I53,"") | U53: =D53/V53 -> #DIV/0! | V53: =$I$8*AB53*AC53/SUMPRODUCT($AC$25:$AC$55,$AB$25:$AB$55) -> 0 | W53: =$I$9*AB53*AC53/SUMPRODUCT($AC$25:$AC$55,$AB$25:$AB$55) -> 0 | X53: =IF($I$12="","",W53/$I$12) -> 0 | Y53: =IF(AC53<>"",IF(D53<>"",D53,($I$8-SUM($Y$25:Y52))*AB53*AC53/SUMPRODUCT($AC53:$AC$55,$AB53:$AB$55)),"") | Z53: =IF(AC53<>"",IF(E53<>"",E53,($I$9-SUM($Z$25:Z52))*AB53*AC53/SUMPRODUCT($AC53:$AC$55,$AB53:$AB$55)),"") | AA53: =IF(AC53<>"",IF($I$12<>"",IF(G53<>"",G53,($I$9/$I$12-SUM($AA$25:AA52))*AB53*AC53/SUMPRODUCT($AC53:$AC$55,$AB53:$AB$55)),""),"")
F54: =IF(AND(E54<>"",E54<>0),D54/E54,"") | H54: =IF(AND(G54<>"",G54<>0),D54/G54,"") | J54: =IF(AND(G54<>"",G54<>0),E54/G54,"") | T54: =IF(AND(I54<>"",I54<>0),G54/I54,"") | U54: =D54/V54 -> #DIV/0! | V54: =$I$8*AB54*AC54/SUMPRODUCT($AC$25:$AC$55,$AB$25:$AB$55) -> 0 | W54: =$I$9*AB54*AC54/SUMPRODUCT($AC$25:$AC$55,$AB$25:$AB$55) -> 0 | X54: =IF($I$12="","",W54/$I$12) -> 0 | Y54: =IF(AC54<>"",IF(D54<>"",D54,($I$8-SUM($Y$25:Y53))*AB54*AC54/SUMPRODUCT($AC54:$AC$55,$AB54:$AB$55)),"") | Z54: =IF(AC54<>"",IF(E54<>"",E54,($I$9-SUM($Z$25:Z53))*AB54*AC54/SUMPRODUCT($AC54:$AC$55,$AB54:$AB$55)),"") | AA54: =IF(AC54<>"",IF($I$12<>"",IF(G54<>"",G54,($I$9/$I$12-SUM($AA$25:AA53))*AB54*AC54/SUMPRODUCT($AC54:$AC$55,$AB54:$AB$55)),""),"")
F55: =IF(AND(E55<>"",E55<>0),D55/E55,"") | H55: =IF(AND(G55<>"",G55<>0),D55/G55,"") | J55: =IF(AND(G55<>"",G55<>0),E55/G55,"") | T55: =IF(AND(I55<>"",I55<>0),G55/I55,"") | U55: =D55/V55 -> #DIV/0! | V55: =$I$8*AB55*AC55/SUMPRODUCT($AC$25:$AC$55,$AB$25:$AB$55) -> 0 | W55: =$I$9*AB55*AC55/SUMPRODUCT($AC$25:$AC$55,$AB$25:$AB$55) -> 0 | X55: =IF($I$12="","",W55/$I$12) -> 0 | Y55: =IF(AC55<>"",IF(D55<>"",D55,($I$8-SUM($Y$25:Y54))*AB55*AC55/SUMPRODUCT($AC55:$AC$55,$AB55:$AB$55)),"") | Z55: =IF(AC55<>"",IF(E55<>"",E55,($I$9-SUM($Z$25:Z54))*AB55*AC55/SUMPRODUCT($AC55:$AC$55,$AB55:$AB$55)),"") | AA55: =IF(AC55<>"",IF($I$12<>"",IF(G55<>"",G55,($I$9/$I$12-SUM($AA$25:AA54))*AB55*AC55/SUMPRODUCT($AC55:$AC$55,$AB55:$AB$55)),""),"")
B56: итого | D56: =SUM(D25:D55) -> 844539 | E56: =SUM(E25:E55) -> 106 | F56: =IF(AND(E56<>"", E56<>0), D56/E56, "") -> 7967.3491 | G56: =SUM(G25:G55) -> 69 | H56: =IF(AND(G56<>"", G56<>0), D56/G56, "") -> 12239.696 | I56: =SUM(I25:I55) -> 1338 | J56: =E56/G56 -> 1.5362319 | K56: =SUM(K25:K55) -> 62658 | L56: =SUM(L25:L55) -> 23405 | M56: =SUM(M25:M55) -> 121217 | N56: =SUM(N25:N55) -> 0 | O56: =SUM(O25:O55) -> 10993 | P56: =SUM(P25:P55) -> 0 | Q56: =SUM(Q25:Q55) -> 17381.78 | R56: =SUM(R25:R55) -> 129353 | S56: =SUM(S25:S55) -> 10013 | T56: =IF(AND(I56<>"",I56<>0),G56/I56,"") -> 0.051569507 | U56: =D56/V56 -> 0.45158263 | V56: =SUM(V25:V55) -> 1870176 | W56: =SUM(W25:W55) -> 257.6 | X56: =SUM(X25:X55) -> 140 | Y56: =SUM(Y25:Y55) -> 844539 | Z56: =SUM(Z25:Z55) -> 92 | AA56: =SUM(AA25:AA55) -> 69
D57: =SUMIF(D25:D55,"",V25:V55)+D56 -> 844539
D58: ='Доп сотрудник'!D48+'Свидовская С. А.'!J8+'Корж А. А.'!J8+'Козлова В. Э.'!J8+ПК4!J8+'Сейтджелилова А.Э.'!D49 -> 844539 | I58: ='Козлова В. Э.'!I49+'Корж А. А.'!I48+'Свидовская С. А.'!I48+ПК4!I50+'Доп сотрудник'!I48+'Сейтджелилова А.Э.'!I49 -> 798.4 | K58: ='Козлова В. Э.'!K49+'Корж А. А.'!K48+'Сейтджелилова А.Э.'!K49+'Свидовская С. А.'!K48+'Доп сотрудник'!K48+ПК4!K50 -> 62658 | L58: ='Козлова В. Э.'!L49+'Корж А. А.'!L48+'Сейтджелилова А.Э.'!L49+'Свидовская С. А.'!L48+ПК4!L50 -> 23405 | M58: ='Козлова В. Э.'!M49+'Корж А. А.'!M48+'Сейтджелилова А.Э.'!M49+'Свидовская С. А.'!M48+'Доп сотрудник'!M48+ПК4!M50 -> 121217 | N58: ='Козлова В. Э.'!N49+'Корж А. А.'!N48+'Сейтджелилова А.Э.'!N49+'Свидовская С. А.'!N48+'Доп сотрудник'!N48+ПК4!N50 -> 0 | O58: ='Козлова В. Э.'!O49+'Корж А. А.'!O48+'Сейтджелилова А.Э.'!O49+'Свидовская С. А.'!O48+'Доп сотрудник'!O48+ПК4!O50 -> 10993 | P58: ='Козлова В. Э.'!P49+'Корж А. А.'!P48+'Сейтджелилова А.Э.'!P49+'Свидовская С. А.'!P48+'Доп сотрудник'!P48+ПК4!P50 -> 0 | Q58: ='Сейтджелилова А.Э.'!Q49+'Козлова В. Э.'!Q49+'Корж А. А.'!Q48+'Свидовская С. А.'!Q48+'Доп сотрудник'!Q48+ПК4!Q50 -> 17382 | R58: ='Сейтджелилова А.Э.'!R49+'Козлова В. Э.'!R49+'Корж А. А.'!R48+'Свидовская С. А.'!R48+'Доп сотрудник'!R48 -> 129353 | S58: ='Сейтджелилова А.Э.'!S49+'Козлова В. Э.'!S49+'Корж А. А.'!S48+'Свидовская С. А.'!S48 -> 10013
K59: =K58/$J$8 -> 0.074191956 | L59: =L58/$J$8 -> 0.027713344 | M59: =M58/$J$8 -> 0.14353038 | N59: =N58/$J$8 -> 0 | O59: =O58/$J$8 -> 0.013016569 | P59: =P58/$J$8 -> 0 | Q59: =Q58/$J$8 -> 0.020581643 | R59: =R58/$J$8 -> 0.15316403
L60: =806057+L58 -> 829462
L61: =D58-L60 -> 15077

Sheet Сводная
A1: Сводная по показателям
A2: Показатель | D2: =Центрум!I3 -> ТРК Центрум | G2: =График!B27 -> Свидовская София | J2: =График!B25 -> Корж Анастасия | M2: =График!B26 -> Козлова Валерия | P2: =График!B28 -> Сейтджелилова Алина
D3: Факт | F3: Прогноз | G3: Факт | I3: Прогноз | J3: Факт | L3: Прогноз | M3: Факт | O3: Прогноз | P3: Факт | R3: Прогноз
A4: Выручка | D4: =Центрум!K8 -> 0.45158263 | E4: =Центрум!J8 -> 844539 | F4: =Центрум!M8 -> 0.45158263 | G4: ='Свидовская С. А.'!K8 -> 0.54678117 | H4: ='Свидовская С. А.'!J8 -> 248592 | I4: ='Свидовская С. А.'!M8 -> 0.57304159 | J4: ='Корж А. А.'!K8 -> 0.5188328 | K4: ='Корж А. А.'!J8 -> 309495 | L4: ='Корж А. А.'!M8 -> 0.53771899 | M4: ='Козлова В. Э.'!K8 -> 0.26437681 | N4: ='Козлова В. Э.'!J8 -> 65640 | O4: ='Козлова В. Э.'!M8 -> 0.30839097 | P4: =ПК4!K8 -> 0 | Q4: =ПК4!J8 -> 0 | R4: =ПК4!M8 -> 0
A5: Кол-во изделий | D5: =Центрум!K9 -> 0.41149068 | E5: =Центрум!J9 -> 106 | F5: =Центрум!M9 -> 0.41149068 | G5: ='Свидовская С. А.'!K9 -> 0.52695916 | H5: ='Свидовская С. А.'!J9 -> 33 | I5: ='Свидовская С. А.'!M9 -> 0.5339265 | J5: ='Корж А. А.'!K9 -> 0.35294611 | K5: ='Корж А. А.'!J9 -> 29 | L5: ='Корж А. А.'!M9 -> 0.35656212 | M5: ='Козлова В. Э.'!K9 -> 0.23392756 | N5: ='Козлова В. Э.'!J9 -> 8 | O5: ='Козлова В. Э.'!M9 -> 0.27287245 | P5: =ПК4!K9 -> 0 | Q5: =ПК4!J9 -> 0 | R5: =ПК4!M9
A6: Средний чек | D6: =Центрум!K10 -> 0.91625462 | E6: =Центрум!J10 -> 12239.696 | F6: =Центрум!M10 -> 0.91625462 | G6: ='Свидовская С. А.'!K10 -> 0.80910497 | H6: ='Свидовская С. А.'!J10 -> 10808.348 | I6: ='Свидовская С. А.'!M10 -> 0.80910497 | J6: ='Корж А. А.'!K10 -> 1.2871427 | K6: ='Корж А. А.'!J10 -> 17194.167 | L6: ='Корж А. А.'!M10 -> 1.2871427 | M6: ='Козлова В. Э.'!K10 -> 0.81896035 | N6: ='Козлова В. Э.'!J10 -> 10940 | O6: ='Козлова В. Э.'!M10 -> 0.81896035 | P6: =ПК4!K10 | Q6: =ПК4!J10 | R6: =ПК4!M10
A7: Средняя стоимость изделия | D7: =Центрум!K11 -> 1.097431 | E7: =Центрум!J11 -> 7967.3491 | F7: =Центрум!M11 -> 1.097431 | G7: ='Свидовская С. А.'!K11 -> 1.0376158 | H7: ='Свидовская С. А.'!J11 -> 7533.0909 | I7: ='Свидовская С. А.'!M11 -> 1.0376158 | J7: ='Корж А. А.'!K11 -> 1.4700057 | K7: ='Корж А. А.'!J11 -> 10672.241 | L7: ='Корж А. А.'!M11 -> 1.4700057 | M7: ='Козлова В. Э.'!K11 -> 1.1301653 | N7: ='Козлова В. Э.'!J11 -> 8205 | O7: ='Козлова В. Э.'!M11 -> 1.1301653 | P7: =ПК4!K11 | Q7: =ПК4!J11 | R7: =ПК4!M11
A8: Длина чека | D8: =Центрум!K12 -> 0.83490863 | E8: =Центрум!J12 -> 1.5362319 | F8: =Центрум!M12 -> 0.83490863 | G8: ='Свидовская С. А.'!K12 -> 0.77977316 | H8: ='Свидовская С. А.'!J12 -> 1.4347826 | I8: ='Свидовская С. А.'!M12 -> 0.77977316 | J8: ='Корж А. А.'!K12 -> 0.87560386 | K8: ='Корж А. А.'!J12 -> 1.6111111 | L8: ='Корж А. А.'!M12 -> 0.87560386 | M8: ='Козлова В. Э.'!K12 -> 0.72463768 | N8: ='Козлова В. Э.'!J12 -> 1.3333333 | O8: ='Козлова В. Э.'!M12 -> 0.72463768 | P8: =ПК4!K12 | Q8: =ПК4!J12 | R8: =ПК4!M12
A9: Кол-во чеков | D9: =Центрум!K13 -> 0.49285714 | E9: =Центрум!J13 -> 69 | F9: =Центрум!M13 -> 0.49285714 | G9: ='Свидовская С. А.'!K13 -> 0.67578521 | H9: ='Свидовская С. А.'!J13 -> 23 | I9: ='Свидовская С. А.'!M13 -> 0.68828385 | J9: ='Корж А. А.'!K13 -> 0.4030888 | K9: ='Корж А. А.'!J13 -> 18 | L9: ='Корж А. А.'!M13 -> 0.40882705 | M9: ='Козлова В. Э.'!K13 -> 0.32282004 | N9: ='Козлова В. Э.'!J13 -> 6 | O9: ='Козлова В. Э.'!M13 -> 0.37656398 | P9: =ПК4!K13 -> 0 | Q9: =ПК4!J13 -> 0 | R9: =ПК4!M13
A10: Кол-во смен план/отработано | D10: =Центрум!K14 -> 1 | E10: =Центрум!J14 -> 28 | G10: ='Свидовская С. А.'!K14 -> 1 | H10: ='Свидовская С. А.'!J14 -> 13 | J10: ='Корж А. А.'!K14 -> 1 | K10: ='Корж А. А.'!J14 -> 17 | M10: ='Козлова В. Э.'!K14 -> 1 | N10: ='Козлова В. Э.'!J14 -> 7 | P10: =ПК4!K14 -> 0.25 | Q10: =ПК4!J14 -> 5
A11: Средние продажи в смену | D11: =Центрум!K15 -> 0.45158263 | E11: =Центрум!J15 -> 30162.107 | F11: =Центрум!M15 -> 0.45158263 | G11: ='Свидовская С. А.'!K15 -> 0.57259736 | H11: ='Свидовская С. А.'!J15 -> 19122.462 | I11: ='Свидовская С. А.'!M15 -> 0.57259736 | J11: ='Корж А. А.'!K15 -> 0.54514278 | K11: ='Корж А. А.'!J15 -> 18205.588 | L11: ='Корж А. А.'!M15 -> 0.54514278 | M11: ='Козлова В. Э.'!K15 -> 0.28078641 | N11: ='Козлова В. Э.'!J15 -> 9377.1429 | O11: ='Козлова В. Э.'!M15 -> 0.28078641 | P11: =ПК4!K15 -> 0 | Q11: =ПК4!J15 -> 0 | R11: =ПК4!M15
A12: Отставание/Перевыполнение | D12: =Центрум!J16 -> -1025637 | G12: ='Свидовская С. А.'!N8 -> -194115.03 | J12: ='Корж А. А.'!N8 -> -275760.63 | M12: ='Козлова В. Э.'!N8 -> -171714.06 | P12: =ПК4!N8

Sheet Справочник магазинов
A1: МЕГА Белая Дача
A2: Гагаринский
A3: Марфино

Sheet План на день
A1: Выручка | D1: =86000 -> 86000
A2: Кол-во изделий | D2: =D1/D4 -> 11.84573
A3: Средний чек | D3: =D4*D5 -> 13358.4
A4: Средняя стоимость изделия | D4: =Центрум!I11 -> 7260
A5: Длина чека | D5: =Центрум!I12 -> 1.84
A6: Кол-во чеков | D6: =IF(D5<>0,D2/D5,"") -> 6.4378968
A7: Конверсия | D7: =Центрум!I20 -> 0.1

Sheet Сейтджелилова А.Э.
B1: =TODAY()-1 -> 46171
B2: (отчетная дата) | J2: ЕЖЕДНЕВНЫЙ ОТЧЕТ О ПРОДАЖАХ
B3: Осталось до выполнения плана!!! | J3: =График!B28 -> Сейтджелилова Алина
C4: =I8-D49 -> 357334.12 | E4: =IF(I8<>0,C4/I8,0) -> 0.62610438
F6: Целевые показатели
F7: Показатель | I7: План | J7: Факт | K7: % выполнения | L7: Прогноз выполнения | M7: % выполнения по прогнозу | N7: Отклонение | O7: Факт аналогичного месяца прошлого года | P7: Отклонение LFL
F8: Выручка | I8: =Центрум!I8/График!AJ29*График!AJ28 -> 570726.12 | J8: =D49 -> 213392 | K8: =IF(AND(I8<>"",I8<>0,J8<>""),J8/I8,"") -> 0.37389562 | L8: =IF(SUMIF($D$25:$D$47,">=0",$V$25:$V$47)<>0,I8*D49/SUMIF($D$25:$D$47,">=0",$V$25:$V$47),0) -> 213392 | M8: =L8/I8 -> 0.37389562 | N8: =IF(AND(J8<>0,J8<>"",I8<>0,I8<>""),L8-I8,"") -> -357334.12 | P8: =IF(AND(O8<>"",O8<>0,L8<>"",L8<>0),-O8+L8,"") | Q8: =IF(AND(P8<>"",P8<>0,O8<>0,O8<>""),P8/O8,"")
F9: Кол-во изделий | I9: =I8/I11 -> 78.612414 | J9: =E49 -> 35 | K9: =IF(AND(I9<>"",I9<>0,J9<>""),J9/I9,"") -> 0.4452223 | L9: =IF(SUMIF($E$25:$E$47,">=0",$W$25:$W$47)<>0,I9*E49/SUMIF($E$25:$E$47,">=0",$W$25:$W$47),0) -> 35 | M9: =IF(AND(I9<>"",I9<>0,L9<>"",L9<>0),L9/I9,"") -> 0.4452223 | N9: =IF(AND(J9<>0,J9<>"",I9<>0,I9<>""),L9-I9,"") -> -43.612414 | O9: =O8/O11 -> #DIV/0! | P9: =IF(AND(O9<>"",O9<>0,L9<>"",L9<>0),-O9+L9,"") -> #DIV/0! | Q9: =IF(AND(P9<>"",P9<>0,O9<>0,O9<>""),P9/O9,"") -> #DIV/0!
F10: Средний чек | I10: =I11*I12 -> 13358.4 | J10: =H49 -> 9277.913 | K10: =IF(AND(I10<>"",I10<>0,J10<>""),J10/I10,"") -> 0.69453775 | L10: =J10 -> 9277.913 | M10: =IF(AND(I10<>"",I10<>0,L10<>"",L10<>0),L10/I10,"") -> 0.69453775 | N10: =IF(AND(J10<>0,J10<>"",I10<>0,I10<>""),L10-I10,"") -> -4080.487 | O10: =O11*O12 -> 0 | P10: =IF(AND(O10<>"",O10<>0,L10<>"",L10<>0),-O10+L10,"") | Q10: =IF(AND(P10<>"",P10<>0,O10<>0,O10<>""),P10/O10,"")
F11: Средняя стоимость изделия | I11: =Центрум!I11 -> 7260 | J11: =F49 -> 6096.9143 | K11: =IF(AND(I11<>"",I11<>0,J11<>""),J11/I11,"") -> 0.83979536 | L11: =J11 -> 6096.9143 | M11: =IF(AND(I11<>"",I11<>0,L11<>"",L11<>0),L11/I11,"") -> 0.83979536 | N11: =IF(AND(J11<>0,J11<>"",I11<>0,I11<>""),L11-I11,"") -> -1163.0857 | P11: =IF(AND(O11<>"",O11<>0,L11<>"",L11<>0),-O11+L11,"") | Q11: =IF(AND(P11<>"",P11<>0,O11<>0,O11<>""),P11/O11,"")
F12: Длина чека | I12: =Центрум!I12 -> 1.84 | J12: =J49 -> 1.5217391 | K12: =IF(AND(I12<>"",I12<>0,J12<>""),J12/I12,"") -> 0.82703214 | L12: =J12 -> 1.5217391 | M12: =IF(AND(I12<>"",I12<>0,L12<>"",L12<>0),L12/I12,"") -> 0.82703214 | N12: =IF(AND(J12<>0,J12<>"",I12<>0,I12<>""),L12-I12,"") -> -0.31826087 | P12: =IF(AND(O12<>"",O12<>0,L12<>"",L12<>0),-O12+L12,"") | Q12: =IF(AND(P12<>"",P12<>0,O12<>0,O12<>""),P12/O12,"")
F13: Кол-во чеков | I13: =IF(I12<>0,I9/I12,"") -> 42.724138 | J13: =G49 -> 23 | K13: =IF(AND(I13<>"",I13<>0,J13<>""),J13/I13,"") -> 0.53833737 | L13: =IF(SUMIF($G$25:$G$47,">=0",$X$25:$X$47)<>0,I13*G49/SUMIF($G$25:$G$47,">=0",$X$25:$X$47),"") -> 23 | M13: =IF(AND(I13<>"",I13<>0,L13<>"",L13<>0),L13/I13,"") -> 0.53833737 | N13: =IF(AND(J13<>0,J13<>"",I13<>0,I13<>""),L13-I13,"") -> -19.724138 | P13: =IF(AND(O13<>"",O13<>0,L13<>"",L13<>0),-O13+L13,"") | Q13: =IF(AND(P13<>"",P13<>0,O13<>0,O13<>""),P13/O13,"")
F14: Кол-во смен план/отработано | I14: =График!AI28 -> 20 | J14: 20 | K14: =IF(AND(I14<>"",I14<>0,J14<>""),J14/I14,"") -> 1 | L14: =IF(SUMIF($D$25:$D$47,">=0",$V$25:$V$47),I49*I8/SUMIF($D$25:$D$47,">=0",$V$25:$V$47),"") -> 280 | N14: =IF(AND(J14<>0,J14<>"",I14<>0,I14<>""),L14-I14,"") -> 260 | P14: =IF(AND(O14<>"",O14<>0,L14<>"",L14<>0),-O14+L14,"") | Q14: =IF(AND(P14<>"",P14<>0,O14<>0,O14<>""),P14/O14,"")
F15: Средние продажи в смену | I15: =Центрум!I15/2 -> 33396 | J15: =J8/J14 -> 10669.6 | K15: =IF(AND(I15<>"",I15<>0,J15<>""),J15/I15,"") -> 0.31948736 | L15: =J15 -> 10669.6 | M15: =IF(AND(I15<>"",I15<>0,L15<>"",L15<>0),L15/I15,"") -> 0.31948736 | N15: =IF(AND(J15<>0,J15<>"",I15<>0,I15<>""),L15-I15,"") -> -22726.4 | P15: =IF(AND(O15<>"",O15<>0,L15<>"",L15<>0),-O15+L15,"") | Q15: =IF(AND(P15<>"",P15<>0,O15<>0,O15<>""),P15/O15,"")
F16: Отставание/Перевыполнение | J16: =J8-I15*J14 -> -454528 | K16: =IF(AND(I16<>"",I16<>0,J16<>""),J16/I16,"") | L16: =J16 -> -454528 | M16: =IF(AND(I16<>"",I16<>0,L16<>"",L16<>0),L16/I16,"") | N16: =IF(AND(J16<>0,J16<>"",I16<>0,I16<>""),L16-I16,"") | P16: =IF(AND(O16<>"",O16<>0,L16<>"",L16<>0),-O16+L16,"") | Q16: =IF(AND(P16<>"",P16<>0,O16<>0,O16<>""),P16/O16,"") | U16: Подарочные сертификаты
F17: Трафик | I17: =Центрум!I17/График!AJ29*График!AJ23 -> 0 | J17: =I49 -> 280 | K17: =IF(AND(I17<>"",I17<>0,J17<>""),J17/I17,"") | L17: =J17/J14*I14 -> 280 | M17: =IF(AND(I17<>"",I17<>0,L17<>"",L17<>0),L17/I17,"") | N17: =IF(AND(J17<>0,J17<>"",I17<>0,I17<>""),L17-I17,"") | P17: =IF(AND(O17<>"",O17<>0,L17<>"",L17<>0),-O17+L17,"") | Q17: =IF(AND(P17<>"",P17<>0,O17<>0,O17<>""),P17/O17,"")
K18: =IF(AND(I18<>"",I18<>0,J18<>""),J18/I18,"") | L18: =J18 -> 0 | M18: =IF(AND(I18<>"",I18<>0,L18<>"",L18<>0),L18/I18,"") | N18: =IF(AND(J18<>0,J18<>"",I18<>0,I18<>""),L18-I18,"") | O18: 0 | P18: =IF(AND(O18<>"",O18<>0,L18<>"",L18<>0),-O18+L18,"") | Q18: =IF(AND(P18<>"",P18<>0,O18<>0,O18<>""),P18/O18,"")
J19: =P49 -> 0 | K19: =IF(AND(I19<>"",I19<>0,J19<>""),J19/I19,"") | L19: =J19 -> 0 | M19: =IF(AND(I19<>"",I19<>0,L19<>"",L19<>0),L19/I19,"") | N19: =IF(AND(J19<>0,J19<>"",I19<>0,I19<>""),L19-I19,"") | O19: 0 | P19: =IF(AND(O19<>"",O19<>0,L19<>"",L19<>0),-O19+L19,"") | Q19: =IF(AND(P19<>"",P19<>0,O19<>0,O19<>""),P19/O19,"") | U19: =U18/I16 -> #DIV/0!
F20: Конверсия план/факт | I20: =Центрум!I20 -> 0.1 | J20: =T49 -> 0.082142857 | K20: =J20/I20 -> 0.82142857 | L20: =IF(AND(K8<>0,I14<>0,I49<>0),(I49*T49+(I49/K8-I49)*I20)/(I49/K8),0) -> 0.093323292 | M20: =IF(AND(I20<>"",I20<>0,L20<>"",L20<>0),L20/I20,"") -> 0.93323292 | N20: =IF(AND(J20<>0,J20<>"",I20<>0,I20<>""),L20-I20,"") -> -0.0066767076 | P20: =IF(AND(O20<>"",O20<>0,L20<>"",L20<>0),-O20+L20,"") | Q20: =IF(AND(P20<>"",P20<>0,O20<>0,O20<>""),P20/O20,"")
B22: Факт продаж за месяц | U22: % выполнения дневного плана | V22: Раcпределение плана по дням
B23: Дата | C23: День недели | D23: Выручка (руб) | E23: Кол-во единиц (шт.) | F23: Средняя стоимость изделия (руб.) | G23: Количество чеков (шт.) | H23: Средняя сумма чека (руб.) | I23: Трафик | J23: Длина чека (шт.) | K23: UNOde50 | L23: IS | M23: Agafi | N23: Kalliope | O23: Raganella | P23: CC/MP | Q23: Eva Rites | R23: Antura | S23: SALE | T23: Конверсия (%) | V23: выручка, план | W23: кол-во ед, план | X23: Кол-во чеков, план | Y23: выручка, скорректир.план | Z23: кол-во ед, скорр. план | AA23: кол-во чеков, скорр. план | AB23: Коэфф. Дня Недели | AC23: Специфика месяца
B24: 1 | C24: 2 | D24: 3 | E24: в | F24: 5 | G24: 6 | H24: 7 | I24: 8 | J24: 9 | K24: 10 | L24: 11 | M24: 12 | N24: 13 | O24: 14 | P24: 15 | Q24: 16 | R24: 17 | T24: 18 | V24: 1 | W24: 2 | X24: 3 | Y24: 4 | Z24: 5 | AA24: 6 | AB24: 10 | AC24: 11
A25: 1 | B25: 46054 | C25: вс | D25: =-10892+28117+7503 -> 24728 | E25: 6 | F25: =IF(AND(E25<>"",E25<>0),D25/E25,"") -> 4121.3333 | G25: 4 | H25: =IF(AND(G25<>"",G25<>0),D25/G25,"") -> 6182 | I25: 28 | J25: =IF(AND(G25<>"",G25<>0),E25/G25,"") -> 1.5 | L25: 7503 | M25: 8592 | T25: =IF(AND(I25<>"",I25<>0),G25/I25,"") -> 0.14285714 | U25: =D25/V25 -> 0.77989071 | V25: =$I$8*AB25*AC25/SUMPRODUCT($AC$25:$AC$56,$AB$25:$AB$56) -> 31707.007 | W25: =$I$9*AB25*AC25/SUMPRODUCT($AC$25:$AC$56,$AB$25:$AB$56) -> 4.3673563 | X25: =IF($I$12="","",W25/$I$12) -> 2.3735632 | Y25: =IF(AC25<>"",IF(D25<>"",D25,($I$8-SUM($Y24:Y$25))*AB25*AC25/SUMPRODUCT($AC25:$AC$56,$AB25:$AB$56)),"") -> 24728 | Z25: =IF(AC25<>"",IF(E25<>"",E25,($I$9-SUM($Z24:Z$25))*AB25*AC25/SUMPRODUCT($AC25:$AC$56,$AB25:$AB$56)),"") -> 6 | AA25: =IF(AC25<>"",IF($I$12<>"",IF(G25<>"",G25,($I$9/$I$12-SUM($AA24:AA$25))*AB25*AC25/SUMPRODUCT($AC25:$AC$56,$AB25:$AB$56)),""),"") -> 4 | AB25: 1 | AC25: 1
A26: 2 | B26: 46055 | C26: пн | D26: 0 | E26: 0 | F26: =IF(AND(E26<>"",E26<>0),D26/E26,"") | G26: 0 | H26: =IF(AND(G26<>"",G26<>0),D26/G26,"") | I26: 17 | J26: =IF(AND(G26<>"",G26<>0),E26/G26,"") | T26: =IF(AND(I26<>"",I26<>0),G26/I26,"") -> 0 | U26: =D26/V26 -> 0 | V26: =$I$8*AB26*AC26/SUMPRODUCT($AC$25:$AC$56,$AB$25:$AB$56) -> 31707.007 | W26: =$I$9*AB26*AC26/SUMPRODUCT($AC$25:$AC$56,$AB$25:$AB$56) -> 4.3673563 | X26: =IF($I$12="","",W26/$I$12) -> 2.3735632 | Y26: =IF(AC26<>"",IF(D26<>"",D26,($I$8-SUM($Y25:Y$25))*AB26*AC26/SUMPRODUCT($AC26:$AC$56,$AB26:$AB$56)),"") -> 0 | Z26: =IF(AC26<>"",IF(E26<>"",E26,($I$9-SUM($Z25:Z$25))*AB26*AC26/SUMPRODUCT($AC26:$AC$56,$AB26:$AB$56)),"") -> 0 | AA26: =IF(AC26<>"",IF($I$12<>"",IF(G26<>"",G26,($I$9/$I$12-SUM($AA25:AA$25))*AB26*AC26/SUMPRODUCT($AC26:$AC$56,$AB26:$AB$56)),""),"") -> 0 | AB26: 1 | AC26: 1
A27: 3 | B27: 46056 | C27: вт | D27: 30122 | E27: 5 | F27: =IF(AND(E27<>"",E27<>0),D27/E27,"") -> 6024.4 | G27: 3 | H27: =IF(AND(G27<>"",G27<>0),D27/G27,"") -> 10040.667 | I27: 18 | J27: =IF(AND(G27<>"",G27<>0),E27/G27,"") -> 1.6666667 | M27: 23903 | S27: 6219 | T27: =IF(AND(I27<>"",I27<>0),G27/I27,"") -> 0.16666667 | U27: =D27/V27 -> 0.95001083 | V27: =$I$8*AB27*AC27/SUMPRODUCT($AC$25:$AC$56,$AB$25:$AB$56) -> 31707.007 | W27: =$I$9*AB27*AC27/SUMPRODUCT($AC$25:$AC$56,$AB$25:$AB$56) -> 4.3673563 | X27: =IF($I$12="","",W27/$I$12) -> 2.3735632 | Y27: =IF(AC27<>"",IF(D27<>"",D27,($I$8-SUM($Y$25:Y26))*AB27*AC27/SUMPRODUCT($AC27:$AC$56,$AB27:$AB$56)),"") -> 30122 | Z27: =IF(AC27<>"",IF(E27<>"",E27,($I$9-SUM($Z$25:Z26))*AB27*AC27/SUMPRODUCT($AC27:$AC$56,$AB27:$AB$56)),"") -> 5 | AA27: =IF(AC27<>"",IF($I$12<>"",IF(G27<>"",G27,($I$9/$I$12-SUM($AA$25:AA26))*AB27*AC27/SUMPRODUCT($AC27:$AC$56,$AB27:$AB$56)),""),"") -> 3 | AB27: 1 | AC27: 1
A28: 4 | B28: 46059 | C28: пт | D28: 0 | E28: 0 | F28: =IF(AND(E28<>"",E28<>0),D28/E28,"") | G28: 0 | H28: =IF(AND(G28<>"",G28<>0),D28/G28,"") | I28: 25 | J28: =IF(AND(G28<>"",G28<>0),E28/G28,"") | T28: =IF(AND(I28<>"",I28<>0),G28/I28,"") -> 0 | U28: =D28/V28 -> 0 | V28: =$I$8*AB28*AC28/SUMPRODUCT($AC$25:$AC$56,$AB$25:$AB$56) -> 31707.007 | W28: =$I$9*AB28*AC28/SUMPRODUCT($AC$25:$AC$56,$AB$25:$AB$56) -> 4.3673563 | X28: =IF($I$12="","",W28/$I$12) -> 2.3735632 | Y28: =IF(AC28<>"",IF(D28<>"",D28,($I$8-SUM($Y$25:Y27))*AB28*AC28/SUMPRODUCT($AC28:$AC$56,$AB28:$AB$56)),"") -> 0 | Z28: =IF(AC28<>"",IF(E28<>"",E28,($I$9-SUM($Z$25:Z27))*AB28*AC28/SUMPRODUCT($AC28:$AC$56,$AB28:$AB$56)),"") -> 0 | AA28: =IF(AC28<>"",IF($I$12<>"",IF(G28<>"",G28,($I$9/$I$12-SUM($AA$25:AA27))*AB28*AC28/SUMPRODUCT($AC28:$AC$56,$AB28:$AB$56)),""),"") -> 0 | AB28: 1 | AC28: 1
A29: 5 | B29: 46060 | C29: сб | D29: 30068 | E29: 4 | F29: =IF(AND(E29<>"",E29<>0),D29/E29,"") -> 7517 | G29: 2 | H29: =IF(AND(G29<>"",G29<>0),D29/G29,"") -> 15034 | I29: 28 | J29: =IF(AND(G29<>"",G29<>0),E29/G29,"") -> 2 | M29: 15984 | T29: =IF(AND(I29<>"",I29<>0),G29/I29,"") -> 0.071428571 | U29: =D29/V29 -> 0.94830774 | V29: =$I$8*AB29*AC29/SUMPRODUCT($AC$25:$AC$56,$AB$25:$AB$56) -> 31707.007 | W29: =$I$9*AB29*AC29/SUMPRODUCT($AC$25:$AC$56,$AB$25:$AB$56) -> 4.3673563 | X29: =IF($I$12="","",W29/$I$12) -> 2.3735632 | Y29: =IF(AC29<>"",IF(D29<>"",D29,($I$8-SUM($Y$25:Y28))*AB29*AC29/SUMPRODUCT($AC29:$AC$56,$AB29:$AB$56)),"") -> 30068 | Z29: =IF(AC29<>"",IF(E29<>"",E29,($I$9-SUM($Z$25:Z28))*AB29*AC29/SUMPRODUCT($AC29:$AC$56,$AB29:$AB$56)),"") -> 4 | AA29: =IF(AC29<>"",IF($I$12<>"",IF(G29<>"",G29,($I$9/$I$12-SUM($AA$25:AA28))*AB29*AC29/SUMPRODUCT($AC29:$AC$56,$AB29:$AB$56)),""),"") -> 2 | AB29: 1 | AC29: 1
A30: 6 | B30: 46061 | C30: вс | D30: 31503 | E30: 5 | F30: =IF(AND(E30<>"",E30<>0),D30/E30,"") -> 6300.6 | G30: 3 | H30: =IF(AND(G30<>"",G30<>0),D30/G30,"") -> 10501 | I30: 30 | J30: =IF(AND(G30<>"",G30<>0),E30/G30,"") -> 1.6666667 | T30: =IF(AND(I30<>"",I30<>0),G30/I30,"") -> 0.1 | U30: =D30/V30 -> 0.99356587 | V30: =$I$8*AB30*AC30/SUMPRODUCT($AC$25:$AC$56,$AB$25:$AB$56) -> 31707.007 | W30: =$I$9*AB30*AC30/SUMPRODUCT($AC$25:$AC$56,$AB$25:$AB$56) -> 4.3673563 | X30: =IF($I$12="","",W30/$I$12) -> 2.3735632 | Y30: =IF(AC30<>"",IF(D30<>"",D30,($I$8-SUM($Y$25:Y29))*AB30*AC30/SUMPRODUCT($AC30:$AC$56,$AB30:$AB$56)),"") -> 31503 | Z30: =IF(AC30<>"",IF(E30<>"",E30,($I$9-SUM($Z$25:Z29))*AB30*AC30/SUMPRODUCT($AC30:$AC$56,$AB30:$AB$56)),"") -> 5 | AA30: =IF(AC30<>"",IF($I$12<>"",IF(G30<>"",G30,($I$9/$I$12-SUM($AA$25:AA29))*AB30*AC30/SUMPRODUCT($AC30:$AC$56,$AB30:$AB$56)),""),"") -> 3 | AB30: 1 | AC30: 1
A31: 7 | B31: 46063 | C31: вт | D31: 5098 | E31: 1 | F31: =IF(AND(E31<>"",E31<>0),D31/E31,"") -> 5098 | G31: 1 | H31: =IF(AND(G31<>"",G31<>0),D31/G31,"") -> 5098 | I31: 25 | J31: =IF(AND(G31<>"",G31<>0),E31/G31,"") -> 1 | T31: =IF(AND(I31<>"",I31<>0),G31/I31,"") -> 0.04 | U31: =D31/V31 -> 0.16078465 | V31: =$I$8*AB31*AC31/SUMPRODUCT($AC$25:$AC$56,$AB$25:$AB$56) -> 31707.007 | W31: =$I$9*AB31*AC31/SUMPRODUCT($AC$25:$AC$56,$AB$25:$AB$56) -> 4.3673563 | X31: =IF($I$12="","",W31/$I$12) -> 2.3735632 | Y31: =IF(AC31<>"",IF(D31<>"",D31,($I$8-SUM($Y$25:Y30))*AB31*AC31/SUMPRODUCT($AC31:$AC$56,$AB31:$AB$56)),"") -> 5098 | Z31: =IF(AC31<>"",IF(E31<>"",E31,($I$9-SUM($Z$25:Z30))*AB31*AC31/SUMPRODUCT($AC31:$AC$56,$AB31:$AB$56)),"") -> 1 | AA31: =IF(AC31<>"",IF($I$12<>"",IF(G31<>"",G31,($I$9/$I$12-SUM($AA$25:AA30))*AB31*AC31/SUMPRODUCT($AC31:$AC$56,$AB31:$AB$56)),""),"") -> 1 | AB31: 1 | AC31: 1
A32: 8 | B32: 46064 | C32: ср | D32: 5692 | E32: 1 | F32: =IF(AND(E32<>"",E32<>0),D32/E32,"") -> 5692 | G32: 1 | H32: =IF(AND(G32<>"",G32<>0),D32/G32,"") -> 5692 | I32: 27 | J32: =IF(AND(G32<>"",G32<>0),E32/G32,"") -> 1 | T32: =IF(AND(I32<>"",I32<>0),G32/I32,"") -> 0.037037037 | U32: =D32/V32 -> 0.17951868 | V32: =$I$8*AB32*AC32/SUMPRODUCT($AC$25:$AC$56,$AB$25:$AB$56) -> 31707.007 | W32: =$I$9*AB32*AC32/SUMPRODUCT($AC$25:$AC$56,$AB$25:$AB$56) -> 4.3673563 | X32: =IF($I$12="","",W32/$I$12) -> 2.3735632 | Y32: =IF(AC32<>"",IF(D32<>"",D32,($I$8-SUM($Y$25:Y31))*AB32*AC32/SUMPRODUCT($AC32:$AC$56,$AB32:$AB$56)),"") -> 5692 | Z32: =IF(AC32<>"",IF(E32<>"",E32,($I$9-SUM($Z$25:Z31))*AB32*AC32/SUMPRODUCT($AC32:$AC$56,$AB32:$AB$56)),"") -> 1 | AA32: =IF(AC32<>"",IF($I$12<>"",IF(G32<>"",G32,($I$9/$I$12-SUM($AA$25:AA31))*AB32*AC32/SUMPRODUCT($AC32:$AC$56,$AB32:$AB$56)),""),"") -> 1 | AB32: 1 | AC32: 1
A33: 9 | B33: 46067 | C33: сб | D33: 26506 | E33: 2 | F33: =IF(AND(E33<>"",E33<>0),D33/E33,"") -> 13253 | G33: 1 | H33: =IF(AND(G33<>"",G33<>0),D33/G33,"") -> 26506 | I33: 25 | J33: =IF(AND(G33<>"",G33<>0),E33/G33,"") -> 2 | T33: =IF(AND(I33<>"",I33<>0),G33/I33,"") -> 0.04 | U33: =D33/V33 -> 0.83596664 | V33: =$I$8*AB33*AC33/SUMPRODUCT($AC$25:$AC$56,$AB$25:$AB$56) -> 31707.007 | W33: =$I$9*AB33*AC33/SUMPRODUCT($AC$25:$AC$56,$AB$25:$AB$56) -> 4.3673563 | X33: =IF($I$12="","",W33/$I$12) -> 2.3735632 | Y33: =IF(AC33<>"",IF(D33<>"",D33,($I$8-SUM($Y$25:Y32))*AB33*AC33/SUMPRODUCT($AC33:$AC$56,$AB33:$AB$56)),"") -> 26506 | Z33: =IF(AC33<>"",IF(E33<>"",E33,($I$9-SUM($Z$25:Z32))*AB33*AC33/SUMPRODUCT($AC33:$AC$56,$AB33:$AB$56)),"") -> 2 | AA33: =IF(AC33<>"",IF($I$12<>"",IF(G33<>"",G33,($I$9/$I$12-SUM($AA$25:AA32))*AB33*AC33/SUMPRODUCT($AC33:$AC$56,$AB33:$AB$56)),""),"") -> 1 | AB33: 1 | AC33: 1
A34: 10 | B34: 46068 | C34: вс | D34: 0 | E34: 0 | F34: =IF(AND(E34<>"",E34<>0),D34/E34,"") | G34: 0 | H34: =IF(AND(G34<>"",G34<>0),D34/G34,"") | I34: 33 | J34: =IF(AND(G34<>"",G34<>0),E34/G34,"") | T34: =IF(AND(I34<>"",I34<>0),G34/I34,"") -> 0 | U34: =D34/V34 -> 0 | V34: =$I$8*AB34*AC34/SUMPRODUCT($AC$25:$AC$56,$AB$25:$AB$56) -> 31707.007 | W34: =$I$9*AB34*AC34/SUMPRODUCT($AC$25:$AC$56,$AB$25:$AB$56) -> 4.3673563 | X34: =IF($I$12="","",W34/$I$12) -> 2.3735632 | Y34: =IF(AC34<>"",IF(D34<>"",D34,($I$8-SUM($Y$25:Y33))*AB34*AC34/SUMPRODUCT($AC34:$AC$56,$AB34:$AB$56)),"") -> 0 | Z34: =IF(AC34<>"",IF(E34<>"",E34,($I$9-SUM($Z$25:Z33))*AB34*AC34/SUMPRODUCT($AC34:$AC$56,$AB34:$AB$56)),"") -> 0 | AA34: =IF(AC34<>"",IF($I$12<>"",IF(G34<>"",G34,($I$9/$I$12-SUM($AA$25:AA33))*AB34*AC34/SUMPRODUCT($AC34:$AC$56,$AB34:$AB$56)),""),"") -> 0 | AB34: 1 | AC34: 1
A35: 11 | B35: 46069 | C35: пн | D35: 0 | E35: 0 | F35: =IF(AND(E35<>"",E35<>0),D35/E35,"") | G35: 0 | H35: =IF(AND(G35<>"",G35<>0),D35/G35,"") | I35: 21 | J35: =IF(AND(G35<>"",G35<>0),E35/G35,"") | T35: =IF(AND(I35<>"",I35<>0),G35/I35,"") -> 0 | U35: =D35/V35 -> 0 | V35: =$I$8*AB35*AC35/SUMPRODUCT($AC$25:$AC$56,$AB$25:$AB$56) -> 31707.007 | W35: =$I$9*AB35*AC35/SUMPRODUCT($AC$25:$AC$56,$AB$25:$AB$56) -> 4.3673563 | X35: =IF($I$12="","",W35/$I$12) -> 2.3735632 | Y35: =IF(AC35<>"",IF(D35<>"",D35,($I$8-SUM($Y$25:Y34))*AB35*AC35/SUMPRODUCT($AC35:$AC$56,$AB35:$AB$56)),"") -> 0 | Z35: =IF(AC35<>"",IF(E35<>"",E35,($I$9-SUM($Z$25:Z34))*AB35*AC35/SUMPRODUCT($AC35:$AC$56,$AB35:$AB$56)),"") -> 0 | AA35: =IF(AC35<>"",IF($I$12<>"",IF(G35<>"",G35,($I$9/$I$12-SUM($AA$25:AA34))*AB35*AC35/SUMPRODUCT($AC35:$AC$56,$AB35:$AB$56)),""),"") -> 0 | AB35: 1 | AC35: 1
A36: 12 | B36: 46070 | C36: вт | D36: 0 | E36: 0 | F36: =IF(AND(E36<>"",E36<>0),D36/E36,"") | G36: 0 | H36: =IF(AND(G36<>"",G36<>0),D36/G36,"") | I36: 17 | J36: =IF(AND(G36<>"",G36<>0),E36/G36,"") | T36: =IF(AND(I36<>"",I36<>0),G36/I36,"") -> 0 | U36: =D36/V36 -> 0 | V36: =$I$8*AB36*AC36/SUMPRODUCT($AC$25:$AC$56,$AB$25:$AB$56) -> 31707.007 | W36: =$I$9*AB36*AC36/SUMPRODUCT($AC$25:$AC$56,$AB$25:$AB$56) -> 4.3673563 | X36: =IF($I$12="","",W36/$I$12) -> 2.3735632 | Y36: =IF(AC36<>"",IF(D36<>"",D36,($I$8-SUM($Y$25:Y35))*AB36*AC36/SUMPRODUCT($AC36:$AC$56,$AB36:$AB$56)),"") -> 0 | Z36: =IF(AC36<>"",IF(E36<>"",E36,($I$9-SUM($Z$25:Z35))*AB36*AC36/SUMPRODUCT($AC36:$AC$56,$AB36:$AB$56)),"") -> 0 | AA36: =IF(AC36<>"",IF($I$12<>"",IF(G36<>"",G36,($I$9/$I$12-SUM($AA$25:AA35))*AB36*AC36/SUMPRODUCT($AC36:$AC$56,$AB36:$AB$56)),""),"") -> 0 | AB36: 1 | AC36: 1
A37: 13 | B37: 46073 | C37: пт | D37: =11384+5690 -> 17074 | E37: 3 | F37: =IF(AND(E37<>"",E37<>0),D37/E37,"") -> 5691.3333 | G37: 2 | H37: =IF(AND(G37<>"",G37<>0),D37/G37,"") -> 8537 | I37: 31 | J37: =IF(AND(G37<>"",G37<>0),E37/G37,"") -> 1.5 | T37: =IF(AND(I37<>"",I37<>0),G37/I37,"") -> 0.064516129 | U37: =D37/V37 -> 0.53849296 | V37: =$I$8*AB37*AC37/SUMPRODUCT($AC$25:$AC$56,$AB$25:$AB$56) -> 31707.007 | W37: =$I$9*AB37*AC37/SUMPRODUCT($AC$25:$AC$56,$AB$25:$AB$56) -> 4.3673563 | X37: =IF($I$12="","",W37/$I$12) -> 2.3735632 | Y37: =IF(AC37<>"",IF(D37<>"",D37,($I$8-SUM($Y$25:Y36))*AB37*AC37/SUMPRODUCT($AC37:$AC$56,$AB37:$AB$56)),"") -> 17074 | Z37: =IF(AC37<>"",IF(E37<>"",E37,($I$9-SUM($Z$25:Z36))*AB37*AC37/SUMPRODUCT($AC37:$AC$56,$AB37:$AB$56)),"") -> 3 | AA37: =IF(AC37<>"",IF($I$12<>"",IF(G37<>"",G37,($I$9/$I$12-SUM($AA$25:AA36))*AB37*AC37/SUMPRODUCT($AC37:$AC$56,$AB37:$AB$56)),""),"") -> 2 | AB37: 1 | AC37: 1
A38: 14 | B38: 46074 | C38: сб | D38: 2147 | E38: 1 | F38: =IF(AND(E38<>"",E38<>0),D38/E38,"") -> 2147 | G38: 1 | H38: =IF(AND(G38<>"",G38<>0),D38/G38,"") -> 2147 | I38: 25 | J38: =IF(AND(G38<>"",G38<>0),E38/G38,"") -> 1 | S38: 2147 | T38: =IF(AND(I38<>"",I38<>0),G38/I38,"") -> 0.04 | U38: =D38/V38 -> 0.067713739 | V38: =$I$8*AB38*AC38/SUMPRODUCT($AC$25:$AC$46,$AB$25:$AB$46) -> 31707.007 | W38: =$I$9*AB38*AC38/SUMPRODUCT($AC$25:$AC$46,$AB$25:$AB$46) -> 4.3673563 | X38: =IF($I$12="","",W38/$I$12) -> 2.3735632 | Y38: =IF(AC38<>"",IF(D38<>"",D38,($I$8-SUM($Y$25:Y37))*AB38*AC38/SUMPRODUCT($AC38:$AC$56,$AB38:$AB$56)),"") -> 2147 | Z38: =IF(AC38<>"",IF(E38<>"",E38,($I$9-SUM($Z$25:Z37))*AB38*AC38/SUMPRODUCT($AC38:$AC$56,$AB38:$AB$56)),"") -> 1 | AA38: =IF(AC38<>"",IF($I$12<>"",IF(G38<>"",G38,($I$9/$I$12-SUM($AA$25:AA37))*AB38*AC38/SUMPRODUCT($AC38:$AC$56,$AB38:$AB$56)),""),"") -> 1 | AB38: 1 | AC38: 1
A39: 15 | B39: 46075 | C39: вс | D39: 7491 | E39: 2 | F39: =IF(AND(E39<>"",E39<>0),D39/E39,"") -> 3745.5 | G39: 1 | H39: =IF(AND(G39<>"",G39<>0),D39/G39,"") -> 7491 | J39: =IF(AND(G39<>"",G39<>0),E39/G39,"") -> 2 | T39: =IF(AND(I39<>"",I39<>0),G39/I39,"") | U39: =D39/V39 -> 0.23625693 | V39: =$I$8*AB39*AC39/SUMPRODUCT($AC$25:$AC$46,$AB$25:$AB$46) -> 31707.007 | W39: =$I$9*AB39*AC39/SUMPRODUCT($AC$25:$AC$46,$AB$25:$AB$46) -> 4.3673563 | X39: =IF($I$12="","",W39/$I$12) -> 2.3735632 | Y39: =IF(AC39<>"",IF(D39<>"",D39,($I$8-SUM($Y$25:Y38))*AB39*AC39/SUMPRODUCT($AC39:$AC$56,$AB39:$AB$56)),"") -> 7491 | Z39: =IF(AC39<>"",IF(E39<>"",E39,($I$9-SUM($Z$25:Z38))*AB39*AC39/SUMPRODUCT($AC39:$AC$56,$AB39:$AB$56)),"") -> 2 | AA39: =IF(AC39<>"",IF($I$12<>"",IF(G39<>"",G39,($I$9/$I$12-SUM($AA$25:AA38))*AB39*AC39/SUMPRODUCT($AC39:$AC$56,$AB39:$AB$56)),""),"") -> 1 | AB39: 1 | AC39: 1
A40: 16 | B40: 46076 | C40: пн | D40: 0 | E40: 0 | F40: =IF(AND(E40<>"",E40<>0),D40/E40,"") | G40: 0 | H40: =IF(AND(G40<>"",G40<>0),D40/G40,"") | J40: =IF(AND(G40<>"",G40<>0),E40/G40,"") | T40: =IF(AND(I40<>"",I40<>0),G40/I40,"") | U40: =D40/V40 -> 0 | V40: =$I$8*AB40*AC40/SUMPRODUCT($AC$25:$AC$46,$AB$25:$AB$46) -> 31707.007 | W40: =$I$9*AB40*AC40/SUMPRODUCT($AC$25:$AC$46,$AB$25:$AB$46) -> 4.3673563 | X40: =IF($I$12="","",W40/$I$12) -> 2.3735632 | Y40: =IF(AC40<>"",IF(D40<>"",D40,($I$8-SUM($Y$25:Y39))*AB40*AC40/SUMPRODUCT($AC40:$AC$56,$AB40:$AB$56)),"") -> 0 | Z40: =IF(AC40<>"",IF(E40<>"",E40,($I$9-SUM($Z$25:Z39))*AB40*AC40/SUMPRODUCT($AC40:$AC$56,$AB40:$AB$56)),"") -> 0 | AA40: =IF(AC40<>"",IF($I$12<>"",IF(G40<>"",G40,($I$9/$I$12-SUM($AA$25:AA39))*AB40*AC40/SUMPRODUCT($AC40:$AC$56,$AB40:$AB$56)),""),"") -> 0 | AB40: 1 | AC40: 1
A41: 17 | B41: 46077 | C41: вт | D41: 0 | E41: 0 | F41: =IF(AND(E41<>"",E41<>0),D41/E41,"") | G41: 0 | H41: =IF(AND(G41<>"",G41<>0),D41/G41,"") | J41: =IF(AND(G41<>"",G41<>0),E41/G41,"") | T41: =IF(AND(I41<>"",I41<>0),G41/I41,"") | U41: =D41/V41 -> 0 | V41: =$I$8*AB41*AC41/SUMPRODUCT($AC$25:$AC$46,$AB$25:$AB$46) -> 31707.007 | W41: =$I$9*AB41*AC41/SUMPRODUCT($AC$25:$AC$46,$AB$25:$AB$46) -> 4.3673563 | X41: =IF($I$12="","",W41/$I$12) -> 2.3735632 | Y41: =IF(AC41<>"",IF(D41<>"",D41,($I$8-SUM($Y$25:Y40))*AB41*AC41/SUMPRODUCT($AC41:$AC$56,$AB41:$AB$56)),"") -> 0 | Z41: =IF(AC41<>"",IF(E41<>"",E41,($I$9-SUM($Z$25:Z40))*AB41*AC41/SUMPRODUCT($AC41:$AC$56,$AB41:$AB$56)),"") -> 0 | AA41: =IF(AC41<>"",IF($I$12<>"",IF(G41<>"",G41,($I$9/$I$12-SUM($AA$25:AA40))*AB41*AC41/SUMPRODUCT($AC41:$AC$56,$AB41:$AB$56)),""),"") -> 0 | AB41: 1 | AC41: 1
A42: 18 | B42: 46079 | C42: чт | D42: 0 | E42: 0 | F42: =IF(AND(E42<>"",E42<>0),D42/E42,"") | G42: 0 | H42: =IF(AND(G42<>"",G42<>0),D42/G42,"") | J42: =IF(AND(G42<>"",G42<>0),E42/G42,"") | T42: =IF(AND(I42<>"",I42<>0),G42/I42,"") | U42: =D42/V42 -> 0 | V42: =$I$8*AB42*AC42/SUMPRODUCT($AC$25:$AC$46,$AB$25:$AB$46) -> 31707.007 | W42: =$I$9*AB42*AC42/SUMPRODUCT($AC$25:$AC$46,$AB$25:$AB$46) -> 4.3673563 | X42: =IF($I$12="","",W42/$I$12) -> 2.3735632 | Y42: =IF(AC42<>"",IF(D42<>"",D42,($I$8-SUM($Y$25:Y41))*AB42*AC42/SUMPRODUCT($AC42:$AC$56,$AB42:$AB$56)),"") -> 0 | Z42: =IF(AC42<>"",IF(E42<>"",E42,($I$9-SUM($Z$25:Z41))*AB42*AC42/SUMPRODUCT($AC42:$AC$56,$AB42:$AB$56)),"") -> 0 | AA42: =IF(AC42<>"",IF($I$12<>"",IF(G42<>"",G42,($I$9/$I$12-SUM($AA$25:AA41))*AB42*AC42/SUMPRODUCT($AC42:$AC$56,$AB42:$AB$56)),""),"") -> 0 | AB42: 1 | AC42: 1
A43: 19 | B43: 46080 | C43: пт | D43: 4693 | E43: 1 | F43: =IF(AND(E43<>"",E43<>0),D43/E43,"") -> 4693 | G43: 1 | H43: =IF(AND(G43<>"",G43<>0),D43/G43,"") -> 4693 | J43: =IF(AND(G43<>"",G43<>0),E43/G43,"") -> 1 | O43: 10993 | T43: =IF(AND(I43<>"",I43<>0),G43/I43,"") | U43: =D43/V43 -> #DIV/0! | V43: =$I$8*AB43*AC43/SUMPRODUCT($AC$25:$AC$46,$AB$25:$AB$46) -> 0 | W43: =$I$9*AB43*AC43/SUMPRODUCT($AC$25:$AC$46,$AB$25:$AB$46) -> 0 | X43: =IF($I$12="","",W43/$I$12) -> 0 | Y43: =IF(AC43<>"",IF(D43<>"",D43,($I$8-SUM($Y$25:Y42))*AB43*AC43/SUMPRODUCT($AC43:$AC$56,$AB43:$AB$56)),"") | Z43: =IF(AC43<>"",IF(E43<>"",E43,($I$9-SUM($Z$25:Z42))*AB43*AC43/SUMPRODUCT($AC43:$AC$56,$AB43:$AB$56)),"") | AA43: =IF(AC43<>"",IF($I$12<>"",IF(G43<>"",G43,($I$9/$I$12-SUM($AA$25:AA42))*AB43*AC43/SUMPRODUCT($AC43:$AC$56,$AB43:$AB$56)),""),"")
A44: 20 | B44: 46081 | C44: сб | D44: 28270 | E44: 4 | F44: =IF(AND(E44<>"",E44<>0),D44/E44,"") -> 7067.5 | G44: 3 | H44: =IF(AND(G44<>"",G44<>0),D44/G44,"") -> 9423.3333 | J44: =IF(AND(G44<>"",G44<>0),E44/G44,"") -> 1.3333333 | T44: =IF(AND(I44<>"",I44<>0),G44/I44,"") | U44: =D44/V44 -> #DIV/0! | V44: =$I$8*AB44*AC44/SUMPRODUCT($AC$25:$AC$46,$AB$25:$AB$46) -> 0 | W44: =$I$9*AB44*AC44/SUMPRODUCT($AC$25:$AC$46,$AB$25:$AB$46) -> 0 | X44: =IF($I$12="","",W44/$I$12) -> 0 | Y44: =IF(AC44<>"",IF(D44<>"",D44,($I$8-SUM($Y$25:Y43))*AB44*AC44/SUMPRODUCT($AC44:$AC$56,$AB44:$AB$56)),"") | Z44: =IF(AC44<>"",IF(E44<>"",E44,($I$9-SUM($Z$25:Z43))*AB44*AC44/SUMPRODUCT($AC44:$AC$56,$AB44:$AB$56)),"") | AA44: =IF(AC44<>"",IF($I$12<>"",IF(G44<>"",G44,($I$9/$I$12-SUM($AA$25:AA43))*AB44*AC44/SUMPRODUCT($AC44:$AC$56,$AB44:$AB$56)),""),"")
F45: =IF(AND(E45<>"",E45<>0),D45/E45,"") | H45: =IF(AND(G45<>"",G45<>0),D45/G45,"") | J45: =IF(AND(G45<>"",G45<>0),E45/G45,"") | T45: =IF(AND(I45<>"",I45<>0),G45/I45,"") | U45: =D45/V45 -> #DIV/0! | V45: =$I$8*AB45*AC45/SUMPRODUCT($AC$25:$AC$46,$AB$25:$AB$46) -> 0 | W45: =$I$9*AB45*AC45/SUMPRODUCT($AC$25:$AC$46,$AB$25:$AB$46) -> 0 | X45: =IF($I$12="","",W45/$I$12) -> 0 | Y45: =IF(AC45<>"",IF(D45<>"",D45,($I$8-SUM($Y$25:Y44))*AB45*AC45/SUMPRODUCT($AC45:$AC$56,$AB45:$AB$56)),"") | Z45: =IF(AC45<>"",IF(E45<>"",E45,($I$9-SUM($Z$25:Z44))*AB45*AC45/SUMPRODUCT($AC45:$AC$56,$AB45:$AB$56)),"") | AA45: =IF(AC45<>"",IF($I$12<>"",IF(G45<>"",G45,($I$9/$I$12-SUM($AA$25:AA44))*AB45*AC45/SUMPRODUCT($AC45:$AC$56,$AB45:$AB$56)),""),"")
F46: =IF(AND(E46<>"",E46<>0),D46/E46,"") | H46: =IF(AND(G46<>"",G46<>0),D46/G46,"") | J46: =IF(AND(G46<>"",G46<>0),E46/G46,"") | T46: =IF(AND(I46<>"",I46<>0),G46/I46,"") | U46: =D46/V46 -> #DIV/0! | V46: =$I$8*AB46*AC46/SUMPRODUCT($AC$25:$AC$46,$AB$25:$AB$46) -> 0 | W46: =$I$9*AB46*AC46/SUMPRODUCT($AC$25:$AC$46,$AB$25:$AB$46) -> 0 | X46: =IF($I$12="","",W46/$I$12) -> 0 | Y46: =IF(AC46<>"",IF(D46<>"",D46,($I$8-SUM($Y$25:Y45))*AB46*AC46/SUMPRODUCT($AC46:$AC$56,$AB46:$AB$56)),"") | Z46: =IF(AC46<>"",IF(E46<>"",E46,($I$9-SUM($Z$25:Z45))*AB46*AC46/SUMPRODUCT($AC46:$AC$56,$AB46:$AB$56)),"") | AA46: =IF(AC46<>"",IF($I$12<>"",IF(G46<>"",G46,($I$9/$I$12-SUM($AA$25:AA45))*AB46*AC46/SUMPRODUCT($AC46:$AC$56,$AB46:$AB$56)),""),"")
F47: =IF(AND(E47<>"",E47<>0),D47/E47,"") | H47: =IF(AND(G47<>"",G47<>0),D47/G47,"") | J47: =IF(AND(G47<>"",G47<>0),E47/G47,"") | T47: =IF(AND(I47<>"",I47<>0),G47/I47,"") | U47: =D47/V47 -> #DIV/0! | V47: =$I$8*AB47*AC47/SUMPRODUCT($AC$25:$AC$46,$AB$25:$AB$46) -> 0 | W47: =$I$9*AB47*AC47/SUMPRODUCT($AC$25:$AC$46,$AB$25:$AB$46) -> 0 | X47: =IF($I$12="","",W47/$I$12) -> 0 | Y47: =IF(AC47<>"",IF(D47<>"",D47,($I$8-SUM($Y$25:Y46))*AB47*AC47/SUMPRODUCT($AC47:$AC$56,$AB47:$AB$56)),"") | Z47: =IF(AC47<>"",IF(E47<>"",E47,($I$9-SUM($Z$25:Z46))*AB47*AC47/SUMPRODUCT($AC47:$AC$56,$AB47:$AB$56)),"") | AA47: =IF(AC47<>"",IF($I$12<>"",IF(G47<>"",G47,($I$9/$I$12-SUM($AA$25:AA46))*AB47*AC47/SUMPRODUCT($AC47:$AC$56,$AB47:$AB$56)),""),"")
F48: =IF(AND(E48<>"",E48<>0),D48/E48,"") | H48: =IF(AND(G48<>"",G48<>0),D48/G48,"") | J48: =IF(AND(G48<>"",G48<>0),E48/G48,"") | T48: =IF(AND(I48<>"",I48<>0),G48/I48,"") | U48: =D48/V48 -> #DIV/0! | V48: =$I$8*AB48*AC48/SUMPRODUCT($AC$25:$AC$46,$AB$25:$AB$46) -> 0 | W48: =$I$9*AB48*AC48/SUMPRODUCT($AC$25:$AC$46,$AB$25:$AB$46) -> 0 | X48: =IF($I$12="","",W48/$I$12) -> 0 | Y48: =IF(AC48<>"",IF(D48<>"",D48,($I$8-SUM($Y$25:Y47))*AB48*AC48/SUMPRODUCT($AC48:$AC$56,$AB48:$AB$56)),"") | Z48: =IF(AC48<>"",IF(E48<>"",E48,($I$9-SUM($Z$25:Z47))*AB48*AC48/SUMPRODUCT($AC48:$AC$56,$AB48:$AB$56)),"") | AA48: =IF(AC48<>"",IF($I$12<>"",IF(G48<>"",G48,($I$9/$I$12-SUM($AA$25:AA47))*AB48*AC48/SUMPRODUCT($AC48:$AC$56,$AB48:$AB$56)),""),"")
B49: итого | D49: =SUM(D25:D47) -> 213392 | E49: =SUM(E25:E47) -> 35 | F49: =IF(AND(E49<>"",E49<>0),D49/E49,"") -> 6096.9143 | G49: =SUM(G25:G47) -> 23 | H49: =IF(AND(G49<>"",G49<>0),D49/G49,"") -> 9277.913 | I49: =SUM(I25:I47)*0.8 -> 280 | J49: =IF(AND(G49<>"",G49<>0),E49/G49,"") -> 1.5217391 | K49: =SUM(K25:K48) -> 0 | L49: =SUM(L25:L48) -> 7503 | M49: =SUM(M25:M48) -> 48479 | N49: =SUM(N25:N48) -> 0 | O49: =SUM(O25:O48) -> 10993 | P49: =SUM(P25:P48) -> 0 | Q49: =SUM(Q25:Q48) -> 0 | R49: =SUM(R25:R48) -> 0 | S49: =SUM(S25:S48) -> 8366 | T49: =IF(AND(I49<>"",I49<>0),G49/I49,"") -> 0.082142857 | U49: =D49/V49 -> 0.37389562 | V49: =SUM(V25:V47) -> 570726.12 | W49: =SUM(W25:W47) -> 78.612414 | X49: =SUM(X25:X47) -> 42.724138 | Y49: =SUM(Y25:Y47) -> 180429 | Z49: =SUM(Z25:Z47) -> 30 | AA49: =SUM(AA25:AA47) -> 19
D50: =SUMIF(D25:D47,"",V25:V47)+D49 -> 213392

Sheet Корж А. А.
B1: =TODAY()-1 -> 46171
B2: (отчетная дата) | J2: ЕЖЕДНЕВНЫЙ ОТЧЕТ О ПРОДАЖАХ
B3: Осталось до выполнения плана!!! | J3: =График!B25 -> Корж Анастасия
C4: =I8-D48 -> 287026.66 | E4: =IF(I8<>0,C4/I8,0) -> 0.4811672
F6: Целевые показатели
F7: Показатель | I7: План | J7: Факт | K7: % выполнения | L7: Прогноз выполнения | M7: % выполнения по прогнозу | N7: Отклонение | O7: Факт аналогичного месяца прошлого года | P7: Отклонение LFL
F8: Выручка | I8: =Центрум!I8/График!AJ29*График!AJ25 -> 596521.66 | J8: =D48 -> 309495 | K8: =IF(AND(I8<>"",I8<>0,J8<>""),J8/I8,"") -> 0.5188328 | L8: =IF(SUMIF($D$25:$D$47,">=0",$V$25:$V$47)<>0,I8*D48/SUMIF($D$25:$D$47,">=0",$V$25:$V$47),0) -> 320761.02 | M8: =L8/I8 -> 0.53771899 | N8: =IF(AND(J8<>0,J8<>"",I8<>0,I8<>""),L8-I8,"") -> -275760.63 | P8: =IF(AND(O8<>"",O8<>0,L8<>"",L8<>0),-O8+L8,"") | Q8: =IF(AND(P8<>"",P8<>0,O8<>0,O8<>""),P8/O8,"")
F9: Кол-во изделий | I9: =I8/I11 -> 82.165517 | J9: =E48 -> 29 | K9: =IF(AND(I9<>"",I9<>0,J9<>""),J9/I9,"") -> 0.35294611 | L9: =IF(SUMIF($E$25:$E$47,">=0",$W$25:$W$47)<>0,I9*E48/SUMIF($E$25:$E$47,">=0",$W$25:$W$47),0) -> 29.297111 | M9: =IF(AND(I9<>"",I9<>0,L9<>"",L9<>0),L9/I9,"") -> 0.35656212 | N9: =IF(AND(J9<>0,J9<>"",I9<>0,I9<>""),L9-I9,"") -> -52.868406 | O9: =O8/O11 -> #DIV/0! | P9: =IF(AND(O9<>"",O9<>0,L9<>"",L9<>0),-O9+L9,"") -> #DIV/0! | Q9: =IF(AND(P9<>"",P9<>0,O9<>0,O9<>""),P9/O9,"") -> #DIV/0!
F10: Средний чек | I10: =I11*I12 -> 13358.4 | J10: =H48 -> 17194.167 | K10: =IF(AND(I10<>"",I10<>0,J10<>""),J10/I10,"") -> 1.2871427 | L10: =J10 -> 17194.167 | M10: =IF(AND(I10<>"",I10<>0,L10<>"",L10<>0),L10/I10,"") -> 1.2871427 | N10: =IF(AND(J10<>0,J10<>"",I10<>0,I10<>""),L10-I10,"") -> 3835.7667 | O10: =O11*O12 -> 0 | P10: =IF(AND(O10<>"",O10<>0,L10<>"",L10<>0),-O10+L10,"") | Q10: =IF(AND(P10<>"",P10<>0,O10<>0,O10<>""),P10/O10,"")
F11: Средняя стоимость изделия | I11: =Центрум!I11 -> 7260 | J11: =F48 -> 10672.241 | K11: =IF(AND(I11<>"",I11<>0,J11<>""),J11/I11,"") -> 1.4700057 | L11: =J11 -> 10672.241 | M11: =IF(AND(I11<>"",I11<>0,L11<>"",L11<>0),L11/I11,"") -> 1.4700057 | N11: =IF(AND(J11<>0,J11<>"",I11<>0,I11<>""),L11-I11,"") -> 3412.2414 | P11: =IF(AND(O11<>"",O11<>0,L11<>"",L11<>0),-O11+L11,"") | Q11: =IF(AND(P11<>"",P11<>0,O11<>0,O11<>""),P11/O11,"")
F12: Длина чека | I12: =Центрум!I12 -> 1.84 | J12: =J48 -> 1.6111111 | K12: =IF(AND(I12<>"",I12<>0,J12<>""),J12/I12,"") -> 0.87560386 | L12: =J12 -> 1.6111111 | M12: =IF(AND(I12<>"",I12<>0,L12<>"",L12<>0),L12/I12,"") -> 0.87560386 | N12: =IF(AND(J12<>0,J12<>"",I12<>0,I12<>""),L12-I12,"") -> -0.22888889 | P12: =IF(AND(O12<>"",O12<>0,L12<>"",L12<>0),-O12+L12,"") | Q12: =IF(AND(P12<>"",P12<>0,O12<>0,O12<>""),P12/O12,"")
F13: Кол-во чеков | I13: =IF(I12<>0,I9/I12,"") -> 44.655172 | J13: =G48 -> 18 | K13: =IF(AND(I13<>"",I13<>0,J13<>""),J13/I13,"") -> 0.4030888 | L13: =IF(SUMIF($G$25:$G$47,">=0",$X$25:$X$47)<>0,I13*G48/SUMIF($G$25:$G$47,">=0",$X$25:$X$47),"") -> 18.256243 | M13: =IF(AND(I13<>"",I13<>0,L13<>"",L13<>0),L13/I13,"") -> 0.40882705 | N13: =IF(AND(J13<>0,J13<>"",I13<>0,I13<>""),L13-I13,"") -> -26.39893 | P13: =IF(AND(O13<>"",O13<>0,L13<>"",L13<>0),-O13+L13,"") | Q13: =IF(AND(P13<>"",P13<>0,O13<>0,O13<>""),P13/O13,"")
F14: Кол-во смен план/отработано | I14: =График!AI25 -> 17 | J14: 17 | K14: =IF(AND(I14<>"",I14<>0,J14<>""),J14/I14,"") -> 1 | L14: =IF(SUMIF($D$25:$D$47,">=0",$V$25:$V$47),I48*I8/SUMIF($D$25:$D$47,">=0",$V$25:$V$47),"") -> 232.98302 | N14: =IF(AND(J14<>0,J14<>"",I14<>0,I14<>""),L14-I14,"") -> 215.98302 | P14: =IF(AND(O14<>"",O14<>0,L14<>"",L14<>0),-O14+L14,"") | Q14: =IF(AND(P14<>"",P14<>0,O14<>0,O14<>""),P14/O14,"")
F15: Средние продажи в смену | I15: =Центрум!I15/2 -> 33396 | J15: =J8/J14 -> 18205.588 | K15: =IF(AND(I15<>"",I15<>0,J15<>""),J15/I15,"") -> 0.54514278 | L15: =J15 -> 18205.588 | M15: =IF(AND(I15<>"",I15<>0,L15<>"",L15<>0),L15/I15,"") -> 0.54514278 | N15: =IF(AND(J15<>0,J15<>"",I15<>0,I15<>""),L15-I15,"") -> -15190.412 | P15: =IF(AND(O15<>"",O15<>0,L15<>"",L15<>0),-O15+L15,"") | Q15: =IF(AND(P15<>"",P15<>0,O15<>0,O15<>""),P15/O15,"")
F16: Отставание/Перевыполнение | J16: =J8-I15*J14 -> -258237 | K16: =IF(AND(I16<>"",I16<>0,J16<>""),J16/I16,"") | L16: =J16 -> -258237 | M16: =IF(AND(I16<>"",I16<>0,L16<>"",L16<>0),L16/I16,"") | N16: =IF(AND(J16<>0,J16<>"",I16<>0,I16<>""),L16-I16,"") | P16: =IF(AND(O16<>"",O16<>0,L16<>"",L16<>0),-O16+L16,"") | Q16: =IF(AND(P16<>"",P16<>0,O16<>0,O16<>""),P16/O16,"") | V16: Подарочные сертификаты
F17: Трафик | I17: =Центрум!I17/График!AJ29*График!AJ25 -> 446.55172 | J17: =I48 -> 224.8 | K17: =IF(AND(I17<>"",I17<>0,J17<>""),J17/I17,"") -> 0.50341313 | L17: =J17/J14*I14 -> 224.8 | M17: =IF(AND(I17<>"",I17<>0,L17<>"",L17<>0),L17/I17,"") -> 0.50341313 | N17: =IF(AND(J17<>0,J17<>"",I17<>0,I17<>""),L17-I17,"") -> -221.75172 | P17: =IF(AND(O17<>"",O17<>0,L17<>"",L17<>0),-O17+L17,"") | Q17: =IF(AND(P17<>"",P17<>0,O17<>0,O17<>""),P17/O17,"")
K18: =IF(AND(I18<>"",I18<>0,J18<>""),J18/I18,"") | L18: =J18 -> 0 | M18: =IF(AND(I18<>"",I18<>0,L18<>"",L18<>0),L18/I18,"") | N18: =IF(AND(J18<>0,J18<>"",I18<>0,I18<>""),L18-I18,"") | O18: 0 | P18: =IF(AND(O18<>"",O18<>0,L18<>"",L18<>0),-O18+L18,"") | Q18: =IF(AND(P18<>"",P18<>0,O18<>0,O18<>""),P18/O18,"")
J19: =P48 -> 0 | K19: =IF(AND(I19<>"",I19<>0,J19<>""),J19/I19,"") | L19: =J19 -> 0 | M19: =IF(AND(I19<>"",I19<>0,L19<>"",L19<>0),L19/I19,"") | N19: =IF(AND(J19<>0,J19<>"",I19<>0,I19<>""),L19-I19,"") | O19: 0 | P19: =IF(AND(O19<>"",O19<>0,L19<>"",L19<>0),-O19+L19,"") | Q19: =IF(AND(P19<>"",P19<>0,O19<>0,O19<>""),P19/O19,"") | V19: =V18/I16 -> #DIV/0!
F20: Конверсия план/факт | I20: =Центрум!I20 -> 0.1 | J20: =T48 -> 0.080071174 | K20: =J20/I20 -> 0.80071174 | L20: =IF(AND(K8<>0,I14<>0,I48<>0),(I48*T48+(I48/K8-I48)*I20)/(I48/K8),0) -> 0.089660272 | M20: =IF(AND(I20<>"",I20<>0,L20<>"",L20<>0),L20/I20,"") -> 0.89660272 | N20: =IF(AND(J20<>0,J20<>"",I20<>0,I20<>""),L20-I20,"") -> -0.010339728 | P20: =IF(AND(O20<>"",O20<>0,L20<>"",L20<>0),-O20+L20,"") | Q20: =IF(AND(P20<>"",P20<>0,O20<>0,O20<>""),P20/O20,"")
B22: Факт продаж за месяц | U22: % выполнения дневного плана | V22: Раcпределение плана по дням
B23: Дата | C23: День недели | D23: Выручка (руб) | E23: Кол-во единиц (шт.) | F23: Средняя стоимость изделия (руб.) | G23: Количество чеков (шт.) | H23: Средняя сумма чека (руб.) | I23: Трафик | J23: Длина чека (шт.) | K23: UNOde50 | L23: IS | M23: Agafi | N23: Kalliope | O23: Raganella | P23: CC/MP | Q23: Eva Rites | R23: Antura | S23: SALE | T23: Конверсия (%) | V23: выручка, план | W23: кол-во ед, план | X23: Кол-во чеков, план | Y23: выручка, скорректир.план | Z23: кол-во ед, скорр. план | AA23: кол-во чеков, скорр. план | AB23: Коэфф. Дня Недели | AC23: Специфика месяца
B24: 1 | C24: 2 | D24: 3 | E24: в | F24: 5 | G24: 6 | H24: 7 | I24: 8 | J24: 9 | K24: 10 | L24: 11 | M24: 12 | N24: 13 | O24: 14 | P24: 15 | Q24: 16 | R24: 17 | T24: 18 | V24: 1 | W24: 2 | X24: 3 | Y24: 4 | Z24: 5 | AA24: 6 | AB24: 10 | AC24: 11
A25: 1 | B25: 46056 | C25: вт | D25: 0 | E25: 0 | G25: 0 | H25: =IF(AND(G25<>"",G25<>0),D25/G25,"") | I25: 18 | J25: =IF(AND(G25<>"",G25<>0),E25/G25,"") | T25: =IF(AND(I25<>"",I25<>0),G25/I25,"") -> 0 | U25: =D25/V25 -> 0 | V25: =$I$8*AB25*AC25/SUMPRODUCT($AC$25:$AC$55,$AB$25:$AB$55) -> 35089.509 | W25: =$I$9*AB25*AC25/SUMPRODUCT($AC$25:$AC$55,$AB$25:$AB$55) -> 4.8332657 | X25: =IF($I$12="","",W25/$I$12) -> 2.6267748 | Y25: =IF(AC25<>"",IF(D25<>"",D25,($I$8-SUM($Y24:Y$25))*AB25*AC25/SUMPRODUCT($AC25:$AC$55,$AB25:$AB$55)),"") -> 0 | Z25: =IF(AC25<>"",IF(E25<>"",E25,($I$9-SUM($Z24:Z$25))*AB25*AC25/SUMPRODUCT($AC25:$AC$55,$AB25:$AB$55)),"") -> 0 | AA25: =IF(AC25<>"",IF($I$12<>"",IF(G25<>"",G25,($I$9/$I$12-SUM($AA24:AA$25))*AB25*AC25/SUMPRODUCT($AC25:$AC$55,$AB25:$AB$55)),""),"") -> 0 | AB25: 1 | AC25: 1
A26: 2 | B26: 46057 | C26: ср | D26: 22340 | E26: 2 | F26: =IF(AND(E26<>"",E26<>0),D26/E26,"") -> 11170 | G26: 2 | H26: =IF(AND(G26<>"",G26<>0),D26/G26,"") -> 11170 | I26: 18 | J26: =IF(AND(G26<>"",G26<>0),E26/G26,"") -> 1 | R26: 14445 | T26: =IF(AND(I26<>"",I26<>0),G26/I26,"") -> 0.11111111 | U26: =D26/V26 -> 0.63665752 | V26: =$I$8*AB26*AC26/SUMPRODUCT($AC$25:$AC$55,$AB$25:$AB$55) -> 35089.509 | W26: =$I$9*AB26*AC26/SUMPRODUCT($AC$25:$AC$55,$AB$25:$AB$55) -> 4.8332657 | X26: =IF($I$12="","",W26/$I$12) -> 2.6267748 | Y26: =IF(AC26<>"",IF(D26<>"",D26,($I$8-SUM($Y$25:Y25))*AB26*AC26/SUMPRODUCT($AC26:$AC$55,$AB26:$AB$55)),"") -> 22340 | Z26: =IF(AC26<>"",IF(E26<>"",E26,($I$9-SUM($Z$25:Z25))*AB26*AC26/SUMPRODUCT($AC26:$AC$55,$AB26:$AB$55)),"") -> 2 | AA26: =IF(AC26<>"",IF($I$12<>"",IF(G26<>"",G26,($I$9/$I$12-SUM($AA$25:AA25))*AB26*AC26/SUMPRODUCT($AC26:$AC$55,$AB26:$AB$55)),""),"") -> 2 | AB26: 1 | AC26: 1
A27: 3 | B27: 46058 | C27: чт | D27: 3390 | E27: 1 | F27: =IF(AND(E27<>"",E27<>0),D27/E27,"") -> 3390 | G27: 1 | H27: =IF(AND(G27<>"",G27<>0),D27/G27,"") -> 3390 | I27: 17 | J27: =IF(AND(G27<>"",G27<>0),E27/G27,"") -> 1 | T27: =IF(AND(I27<>"",I27<>0),G27/I27,"") -> 0.058823529 | U27: =D27/V27 -> 0.23977932 | V27: 14138 | W27: 4 | X27: 2 | Y27: 16611 | Z27: 3 | AA27: 3 | AB27: 1 | AC27: 1
A28: 4 | B28: 46059 | C28: пт | D28: 4529 | E28: 1 | F28: =IF(AND(E28<>"",E28<>0),D28/E28,"") -> 4529 | G28: 1 | H28: =IF(AND(G28<>"",G28<>0),D28/G28,"") -> 4529 | I28: 25 | J28: =IF(AND(G28<>"",G28<>0),E28/G28,"") -> 1 | T28: =IF(AND(I28<>"",I28<>0),G28/I28,"") -> 0.04 | U28: =D28/V28 -> 0.12906992 | V28: =$I$8*AB28*AC28/SUMPRODUCT($AC$25:$AC$55,$AB$25:$AB$55) -> 35089.509 | W28: =$I$9*AB28*AC28/SUMPRODUCT($AC$25:$AC$55,$AB$25:$AB$55) -> 4.8332657 | X28: =IF($I$12="","",W28/$I$12) -> 2.6267748 | Y28: =IF(AC28<>"",IF(D28<>"",D28,($I$8-SUM($Y$25:Y27))*AB28*AC28/SUMPRODUCT($AC28:$AC$55,$AB28:$AB$55)),"") -> 4529 | Z28: =IF(AC28<>"",IF(E28<>"",E28,($I$9-SUM($Z$25:Z27))*AB28*AC28/SUMPRODUCT($AC28:$AC$55,$AB28:$AB$55)),"") -> 1 | AA28: =IF(AC28<>"",IF($I$12<>"",IF(G28<>"",G28,($I$9/$I$12-SUM($AA$25:AA27))*AB28*AC28/SUMPRODUCT($AC28:$AC$55,$AB28:$AB$55)),""),"") -> 1 | AB28: 1 | AC28: 1
A29: 5 | B29: 46062 | C29: пн | D29: 0 | E29: 0 | F29: =IF(AND(E29<>"",E29<>0),D29/E29,"") | G29: 0 | H29: =IF(AND(G29<>"",G29<>0),D29/G29,"") | I29: 19 | J29: =IF(AND(G29<>"",G29<>0),E29/G29,"") | T29: =IF(AND(I29<>"",I29<>0),G29/I29,"") -> 0 | U29: =D29/V29 -> 0 | V29: =$I$8*AB29*AC29/SUMPRODUCT($AC$25:$AC$55,$AB$25:$AB$55) -> 35089.509 | W29: =$I$9*AB29*AC29/SUMPRODUCT($AC$25:$AC$55,$AB$25:$AB$55) -> 4.8332657 | X29: =IF($I$12="","",W29/$I$12) -> 2.6267748 | Y29: =IF(AC29<>"",IF(D29<>"",D29,($I$8-SUM($Y$25:Y28))*AB29*AC29/SUMPRODUCT($AC29:$AC$55,$AB29:$AB$55)),"") -> 0 | Z29: =IF(AC29<>"",IF(E29<>"",E29,($I$9-SUM($Z$25:Z28))*AB29*AC29/SUMPRODUCT($AC29:$AC$55,$AB29:$AB$55)),"") -> 0 | AA29: =IF(AC29<>"",IF($I$12<>"",IF(G29<>"",G29,($I$9/$I$12-SUM($AA$25:AA28))*AB29*AC29/SUMPRODUCT($AC29:$AC$55,$AB29:$AB$55)),""),"") -> 0 | AB29: 1 | AC29: 1
A30: 6 | B30: 46065 | C30: чт | D30: 185851 | E30: 11 | F30: =IF(AND(E30<>"",E30<>0),D30/E30,"") -> 16895.545 | G30: 2 | H30: =IF(AND(G30<>"",G30<>0),D30/G30,"") -> 92925.5 | I30: 20 | J30: =IF(AND(G30<>"",G30<>0),E30/G30,"") -> 5.5 | K30: 62658 | M30: 23181 | R30: 79315 | T30: =IF(AND(I30<>"",I30<>0),G30/I30,"") -> 0.1 | U30: =D30/V30 -> 5.2964833 | V30: =$I$8*AB30*AC30/SUMPRODUCT($AC$25:$AC$55,$AB$25:$AB$55) -> 35089.509 | W30: =$I$9*AB30*AC30/SUMPRODUCT($AC$25:$AC$55,$AB$25:$AB$55) -> 4.8332657 | X30: =IF($I$12="","",W30/$I$12) -> 2.6267748 | Y30: =IF(AC30<>"",IF(D30<>"",D30,($I$8-SUM($Y$25:Y29))*AB30*AC30/SUMPRODUCT($AC30:$AC$55,$AB30:$AB$55)),"") -> 185851 | Z30: =IF(AC30<>"",IF(E30<>"",E30,($I$9-SUM($Z$25:Z29))*AB30*AC30/SUMPRODUCT($AC30:$AC$55,$AB30:$AB$55)),"") -> 11 | AA30: =IF(AC30<>"",IF($I$12<>"",IF(G30<>"",G30,($I$9/$I$12-SUM($AA$25:AA29))*AB30*AC30/SUMPRODUCT($AC30:$AC$55,$AB30:$AB$55)),""),"") -> 2 | AB30: 1 | AC30: 1
A31: 7 | B31: 46066 | C31: пт | D31: 15735 | E31: 2 | F31: =IF(AND(E31<>"",E31<>0),D31/E31,"") -> 7867.5 | G31: 2 | H31: =IF(AND(G31<>"",G31<>0),D31/G31,"") -> 7867.5 | I31: 35 | J31: =IF(AND(G31<>"",G31<>0),E31/G31,"") -> 1 | M31: 10982 | T31: =IF(AND(I31<>"",I31<>0),G31/I31,"") -> 0.057142857 | U31: =D31/V31 -> 0.44842463 | V31: =$I$8*AB31*AC31/SUMPRODUCT($AC$25:$AC$55,$AB$25:$AB$55) -> 35089.509 | W31: =$I$9*AB31*AC31/SUMPRODUCT($AC$25:$AC$55,$AB$25:$AB$55) -> 4.8332657 | X31: =IF($I$12="","",W31/$I$12) -> 2.6267748 | Y31: =IF(AC31<>"",IF(D31<>"",D31,($I$8-SUM($Y$25:Y30))*AB31*AC31/SUMPRODUCT($AC31:$AC$55,$AB31:$AB$55)),"") -> 15735 | Z31: =IF(AC31<>"",IF(E31<>"",E31,($I$9-SUM($Z$25:Z30))*AB31*AC31/SUMPRODUCT($AC31:$AC$55,$AB31:$AB$55)),"") -> 2 | AA31: =IF(AC31<>"",IF($I$12<>"",IF(G31<>"",G31,($I$9/$I$12-SUM($AA$25:AA30))*AB31*AC31/SUMPRODUCT($AC31:$AC$55,$AB31:$AB$55)),""),"") -> 2 | AB31: 1 | AC31: 1
A32: 8 | B32: 46067 | C32: сб | D32: 12083 | E32: 2 | F32: =IF(AND(E32<>"",E32<>0),D32/E32,"") -> 6041.5 | G32: 2 | H32: =IF(AND(G32<>"",G32<>0),D32/G32,"") -> 6041.5 | I32: 25 | J32: =IF(AND(G32<>"",G32<>0),E32/G32,"") -> 1 | T32: =IF(AND(I32<>"",I32<>0),G32/I32,"") -> 0.08 | U32: =D32/V32 -> 0.34434793 | V32: =$I$8*AB32*AC32/SUMPRODUCT($AC$25:$AC$55,$AB$25:$AB$55) -> 35089.509 | W32: =$I$9*AB32*AC32/SUMPRODUCT($AC$25:$AC$55,$AB$25:$AB$55) -> 4.8332657 | X32: =IF($I$12="","",W32/$I$12) -> 2.6267748 | Y32: =IF(AC32<>"",IF(D32<>"",D32,($I$8-SUM($Y$25:Y31))*AB32*AC32/SUMPRODUCT($AC32:$AC$55,$AB32:$AB$55)),"") -> 12083 | Z32: =IF(AC32<>"",IF(E32<>"",E32,($I$9-SUM($Z$25:Z31))*AB32*AC32/SUMPRODUCT($AC32:$AC$55,$AB32:$AB$55)),"") -> 2 | AA32: =IF(AC32<>"",IF($I$12<>"",IF(G32<>"",G32,($I$9/$I$12-SUM($AA$25:AA31))*AB32*AC32/SUMPRODUCT($AC32:$AC$55,$AB32:$AB$55)),""),"") -> 2 | AB32: 1 | AC32: 1
A33: 9 | B33: 46068 | C33: вс | D33: 3193 | E33: 1 | F33: =IF(AND(E33<>"",E33<>0),D33/E33,"") -> 3193 | G33: 1 | H33: =IF(AND(G33<>"",G33<>0),D33/G33,"") -> 3193 | I33: 33 | J33: =IF(AND(G33<>"",G33<>0),E33/G33,"") -> 1 | T33: =IF(AND(I33<>"",I33<>0),G33/I33,"") -> 0.03030303 | U33: =D33/V33 -> 0.090995858 | V33: =$I$8*AB33*AC33/SUMPRODUCT($AC$25:$AC$55,$AB$25:$AB$55) -> 35089.509 | W33: =$I$9*AB33*AC33/SUMPRODUCT($AC$25:$AC$55,$AB$25:$AB$55) -> 4.8332657 | X33: =IF($I$12="","",W33/$I$12) -> 2.6267748 | Y33: =IF(AC33<>"",IF(D33<>"",D33,($I$8-SUM($Y$25:Y32))*AB33*AC33/SUMPRODUCT($AC33:$AC$55,$AB33:$AB$55)),"") -> 3193 | Z33: =IF(AC33<>"",IF(E33<>"",E33,($I$9-SUM($Z$25:Z32))*AB33*AC33/SUMPRODUCT($AC33:$AC$55,$AB33:$AB$55)),"") -> 1 | AA33: =IF(AC33<>"",IF($I$12<>"",IF(G33<>"",G33,($I$9/$I$12-SUM($AA$25:AA32))*AB33*AC33/SUMPRODUCT($AC33:$AC$55,$AB33:$AB$55)),""),"") -> 1 | AB33: 1 | AC33: 1
A34: 10 | B34: 46071 | C34: ср | D34: 0 | E34: 0 | F34: =IF(AND(E34<>"",E34<>0),D34/E34,"") | G34: 0 | H34: =IF(AND(G34<>"",G34<>0),D34/G34,"") | I34: 24 | J34: =IF(AND(G34<>"",G34<>0),E34/G34,"") | T34: =IF(AND(I34<>"",I34<>0),G34/I34,"") -> 0 | U34: =D34/V34 -> 0 | V34: =$I$8*AB34*AC34/SUMPRODUCT($AC$25:$AC$55,$AB$25:$AB$55) -> 35089.509 | W34: =$I$9*AB34*AC34/SUMPRODUCT($AC$25:$AC$55,$AB$25:$AB$55) -> 4.8332657 | X34: =IF($I$12="","",W34/$I$12) -> 2.6267748 | Y34: =IF(AC34<>"",IF(D34<>"",D34,($I$8-SUM($Y$25:Y33))*AB34*AC34/SUMPRODUCT($AC34:$AC$55,$AB34:$AB$55)),"") -> 0 | Z34: =IF(AC34<>"",IF(E34<>"",E34,($I$9-SUM($Z$25:Z33))*AB34*AC34/SUMPRODUCT($AC34:$AC$55,$AB34:$AB$55)),"") -> 0 | AA34: =IF(AC34<>"",IF($I$12<>"",IF(G34<>"",G34,($I$9/$I$12-SUM($AA$25:AA33))*AB34*AC34/SUMPRODUCT($AC34:$AC$55,$AB34:$AB$55)),""),"") -> 0 | AB34: 1 | AC34: 1
A35: 11 | B35: 46072 | C35: чт | D35: 0 | E35: 0 | F35: =IF(AND(E35<>"",E35<>0),D35/E35,"") | G35: 0 | H35: =IF(AND(G35<>"",G35<>0),D35/G35,"") | I35: 16 | J35: =IF(AND(G35<>"",G35<>0),E35/G35,"") | T35: =IF(AND(I35<>"",I35<>0),G35/I35,"") -> 0 | U35: =D35/V35 -> 0 | V35: =$I$8*AB35*AC35/SUMPRODUCT($AC$25:$AC$55,$AB$25:$AB$55) -> 35089.509 | W35: =$I$9*AB35*AC35/SUMPRODUCT($AC$25:$AC$55,$AB$25:$AB$55) -> 4.8332657 | X35: =IF($I$12="","",W35/$I$12) -> 2.6267748 | Y35: =IF(AC35<>"",IF(D35<>"",D35,($I$8-SUM($Y$25:Y34))*AB35*AC35/SUMPRODUCT($AC35:$AC$55,$AB35:$AB$55)),"") -> 0 | Z35: =IF(AC35<>"",IF(E35<>"",E35,($I$9-SUM($Z$25:Z34))*AB35*AC35/SUMPRODUCT($AC35:$AC$55,$AB35:$AB$55)),"") -> 0 | AA35: =IF(AC35<>"",IF($I$12<>"",IF(G35<>"",G35,($I$9/$I$12-SUM($AA$25:AA34))*AB35*AC35/SUMPRODUCT($AC35:$AC$55,$AB35:$AB$55)),""),"") -> 0 | AB35: 1 | AC35: 1
A36: 12 | B36: 46073 | C36: пт | D36: 9387 | E36: 2 | F36: =IF(AND(E36<>"",E36<>0),D36/E36,"") -> 4693.5 | G36: 1 | H36: =IF(AND(G36<>"",G36<>0),D36/G36,"") -> 9387 | I36: 31 | J36: =IF(AND(G36<>"",G36<>0),E36/G36,"") -> 2 | T36: =IF(AND(I36<>"",I36<>0),G36/I36,"") -> 0.032258065 | U36: =D36/V36 -> 0.26751585 | V36: =$I$8*AB36*AC36/SUMPRODUCT($AC$25:$AC$55,$AB$25:$AB$55) -> 35089.509 | W36: =$I$9*AB36*AC36/SUMPRODUCT($AC$25:$AC$55,$AB$25:$AB$55) -> 4.8332657 | X36: =IF($I$12="","",W36/$I$12) -> 2.6267748 | Y36: =IF(AC36<>"",IF(D36<>"",D36,($I$8-SUM($Y$25:Y35))*AB36*AC36/SUMPRODUCT($AC36:$AC$55,$AB36:$AB$55)),"") -> 9387 | Z36: =IF(AC36<>"",IF(E36<>"",E36,($I$9-SUM($Z$25:Z35))*AB36*AC36/SUMPRODUCT($AC36:$AC$55,$AB36:$AB$55)),"") -> 2 | AA36: =IF(AC36<>"",IF($I$12<>"",IF(G36<>"",G36,($I$9/$I$12-SUM($AA$25:AA35))*AB36*AC36/SUMPRODUCT($AC36:$AC$55,$AB36:$AB$55)),""),"") -> 1 | AB36: 1 | AC36: 1
A37: 13 | B37: 46074 | C37: сб | D37: 25795 | E37: 2 | F37: =IF(AND(E37<>"",E37<>0),D37/E37,"") -> 12897.5 | G37: 2 | H37: =IF(AND(G37<>"",G37<>0),D37/G37,"") -> 12897.5 | J37: =IF(AND(G37<>"",G37<>0),E37/G37,"") -> 1 | T37: =IF(AND(I37<>"",I37<>0),G37/I37,"") | U37: =D37/V37 -> 0.73512 | V37: =$I$8*AB37*AC37/SUMPRODUCT($AC$25:$AC$55,$AB$25:$AB$55) -> 35089.509 | W37: =$I$9*AB37*AC37/SUMPRODUCT($AC$25:$AC$55,$AB$25:$AB$55) -> 4.8332657 | X37: =IF($I$12="","",W37/$I$12) -> 2.6267748 | Y37: =IF(AC37<>"",IF(D37<>"",D37,($I$8-SUM($Y$25:Y36))*AB37*AC37/SUMPRODUCT($AC37:$AC$55,$AB37:$AB$55)),"") -> 25795 | Z37: =IF(AC37<>"",IF(E37<>"",E37,($I$9-SUM($Z$25:Z36))*AB37*AC37/SUMPRODUCT($AC37:$AC$55,$AB37:$AB$55)),"") -> 2 | AA37: =IF(AC37<>"",IF($I$12<>"",IF(G37<>"",G37,($I$9/$I$12-SUM($AA$25:AA36))*AB37*AC37/SUMPRODUCT($AC37:$AC$55,$AB37:$AB$55)),""),"") -> 2 | AB37: 1 | AC37: 1
A38: 14 | B38: 46077 | C38: вт | D38: 0 | E38: 0 | F38: =IF(AND(E38<>"",E38<>0),D38/E38,"") | G38: 0 | H38: =IF(AND(G38<>"",G38<>0),D38/G38,"") | J38: =IF(AND(G38<>"",G38<>0),E38/G38,"") | T38: =IF(AND(I38<>"",I38<>0),G38/I38,"") | U38: =D38/V38 -> 0 | V38: =$I$8*AB38*AC38/SUMPRODUCT($AC$25:$AC$55,$AB$25:$AB$55) -> 35089.509 | W38: =$I$9*AB38*AC38/SUMPRODUCT($AC$25:$AC$55,$AB$25:$AB$55) -> 4.8332657 | X38: =IF($I$12="","",W38/$I$12) -> 2.6267748 | Y38: =IF(AC38<>"",IF(D38<>"",D38,($I$8-SUM($Y$25:Y37))*AB38*AC38/SUMPRODUCT($AC38:$AC$55,$AB38:$AB$55)),"") -> 0 | Z38: =IF(AC38<>"",IF(E38<>"",E38,($I$9-SUM($Z$25:Z37))*AB38*AC38/SUMPRODUCT($AC38:$AC$55,$AB38:$AB$55)),"") -> 0 | AA38: =IF(AC38<>"",IF($I$12<>"",IF(G38<>"",G38,($I$9/$I$12-SUM($AA$25:AA37))*AB38*AC38/SUMPRODUCT($AC38:$AC$55,$AB38:$AB$55)),""),"") -> 0 | AB38: 1 | AC38: 1
A39: 15 | B39: 46078 | C39: ср | D39: 0 | E39: 0 | F39: =IF(AND(E39<>"",E39<>0),D39/E39,"") | G39: 0 | H39: =IF(AND(G39<>"",G39<>0),D39/G39,"") | J39: =IF(AND(G39<>"",G39<>0),E39/G39,"") | T39: =IF(AND(I39<>"",I39<>0),G39/I39,"") | U39: =D39/V39 -> 0 | V39: =$I$8*AB39*AC39/SUMPRODUCT($AC$25:$AC$55,$AB$25:$AB$55) -> 35089.509 | W39: =$I$9*AB39*AC39/SUMPRODUCT($AC$25:$AC$55,$AB$25:$AB$55) -> 4.8332657 | X39: =IF($I$12="","",W39/$I$12) -> 2.6267748 | Y39: =IF(AC39<>"",IF(D39<>"",D39,($I$8-SUM($Y$25:Y38))*AB39*AC39/SUMPRODUCT($AC39:$AC$55,$AB39:$AB$55)),"") -> 0 | Z39: =IF(AC39<>"",IF(E39<>"",E39,($I$9-SUM($Z$25:Z38))*AB39*AC39/SUMPRODUCT($AC39:$AC$55,$AB39:$AB$55)),"") -> 0 | AA39: =IF(AC39<>"",IF($I$12<>"",IF(G39<>"",G39,($I$9/$I$12-SUM($AA$25:AA38))*AB39*AC39/SUMPRODUCT($AC39:$AC$55,$AB39:$AB$55)),""),"") -> 0 | AB39: 1 | AC39: 1
A40: 16 | B40: 46079 | C40: чт | D40: 10002 | E40: 2 | F40: =IF(AND(E40<>"",E40<>0),D40/E40,"") -> 5001 | G40: 2 | H40: =IF(AND(G40<>"",G40<>0),D40/G40,"") -> 5001 | J40: =IF(AND(G40<>"",G40<>0),E40/G40,"") -> 1 | T40: =IF(AND(I40<>"",I40<>0),G40/I40,"") | U40: =D40/V40 -> 0.28504246 | V40: =$I$8*AB40*AC40/SUMPRODUCT($AC$25:$AC$55,$AB$25:$AB$55) -> 35089.509 | W40: =$I$9*AB40*AC40/SUMPRODUCT($AC$25:$AC$55,$AB$25:$AB$55) -> 4.8332657 | X40: =IF($I$12="","",W40/$I$12) -> 2.6267748 | Y40: =IF(AC40<>"",IF(D40<>"",D40,($I$8-SUM($Y$25:Y39))*AB40*AC40/SUMPRODUCT($AC40:$AC$55,$AB40:$AB$55)),"") -> 10002 | Z40: =IF(AC40<>"",IF(E40<>"",E40,($I$9-SUM($Z$25:Z39))*AB40*AC40/SUMPRODUCT($AC40:$AC$55,$AB40:$AB$55)),"") -> 2 | AA40: =IF(AC40<>"",IF($I$12<>"",IF(G40<>"",G40,($I$9/$I$12-SUM($AA$25:AA39))*AB40*AC40/SUMPRODUCT($AC40:$AC$55,$AB40:$AB$55)),""),"") -> 2 | AB40: 1 | AC40: 1
A41: 17 | B41: 46080 | C41: пт | D41: 4506 | E41: 1 | F41: =IF(AND(E41<>"",E41<>0),D41/E41,"") -> 4506 | G41: 1 | H41: =IF(AND(G41<>"",G41<>0),D41/G41,"") -> 4506 | J41: =IF(AND(G41<>"",G41<>0),E41/G41,"") -> 1 | T41: =IF(AND(I41<>"",I41<>0),G41/I41,"") | U41: =D41/V41 -> 0.12841445 | V41: =$I$8*AB41*AC41/SUMPRODUCT($AC$25:$AC$55,$AB$25:$AB$55) -> 35089.509 | W41: =$I$9*AB41*AC41/SUMPRODUCT($AC$25:$AC$55,$AB$25:$AB$55) -> 4.8332657 | X41: =IF($I$12="","",W41/$I$12) -> 2.6267748 | Y41: =IF(AC41<>"",IF(D41<>"",D41,($I$8-SUM($Y$25:Y40))*AB41*AC41/SUMPRODUCT($AC41:$AC$55,$AB41:$AB$55)),"") -> 4506 | Z41: =IF(AC41<>"",IF(E41<>"",E41,($I$9-SUM($Z$25:Z40))*AB41*AC41/SUMPRODUCT($AC41:$AC$55,$AB41:$AB$55)),"") -> 1 | AA41: =IF(AC41<>"",IF($I$12<>"",IF(G41<>"",G41,($I$9/$I$12-SUM($AA$25:AA40))*AB41*AC41/SUMPRODUCT($AC41:$AC$55,$AB41:$AB$55)),""),"") -> 1 | AB41: 1 | AC41: 1
A42: 18 | F42: =IF(AND(E42<>"",E42<>0),D42/E42,"") | H42: =IF(AND(G42<>"",G42<>0),D42/G42,"") | J42: =IF(AND(G42<>"",G42<>0),E42/G42,"") | T42: =IF(AND(I42<>"",I42<>0),G42/I42,"") | U42: =D42/V42 -> #DIV/0! | V42: =$I$8*AB42*AC42/SUMPRODUCT($AC$25:$AC$55,$AB$25:$AB$55) -> 0 | W42: =$I$9*AB42*AC42/SUMPRODUCT($AC$25:$AC$55,$AB$25:$AB$55) -> 0 | X42: =IF($I$12="","",W42/$I$12) -> 0 | Y42: =IF(AC42<>"",IF(D42<>"",D42,($I$8-SUM($Y$25:Y41))*AB42*AC42/SUMPRODUCT($AC42:$AC$55,$AB42:$AB$55)),"") | Z42: =IF(AC42<>"",IF(E42<>"",E42,($I$9-SUM($Z$25:Z41))*AB42*AC42/SUMPRODUCT($AC42:$AC$55,$AB42:$AB$55)),"") | AA42: =IF(AC42<>"",IF($I$12<>"",IF(G42<>"",G42,($I$9/$I$12-SUM($AA$25:AA41))*AB42*AC42/SUMPRODUCT($AC42:$AC$55,$AB42:$AB$55)),""),"")
A43: 19 | F43: =IF(AND(E43<>"",E43<>0),D43/E43,"") | H43: =IF(AND(G43<>"",G43<>0),D43/G43,"") | J43: =IF(AND(G43<>"",G43<>0),E43/G43,"") | T43: =IF(AND(I43<>"",I43<>0),G43/I43,"") | U43: =D43/V43 -> #DIV/0! | V43: =$I$8*AB43*AC43/SUMPRODUCT($AC$25:$AC$55,$AB$25:$AB$55) -> 0 | W43: =$I$9*AB43*AC43/SUMPRODUCT($AC$25:$AC$55,$AB$25:$AB$55) -> 0 | X43: =IF($I$12="","",W43/$I$12) -> 0 | Y43: =IF(AC43<>"",IF(D43<>"",D43,($I$8-SUM($Y$25:Y42))*AB43*AC43/SUMPRODUCT($AC43:$AC$55,$AB43:$AB$55)),"") | Z43: =IF(AC43<>"",IF(E43<>"",E43,($I$9-SUM($Z$25:Z42))*AB43*AC43/SUMPRODUCT($AC43:$AC$55,$AB43:$AB$55)),"") | AA43: =IF(AC43<>"",IF($I$12<>"",IF(G43<>"",G43,($I$9/$I$12-SUM($AA$25:AA42))*AB43*AC43/SUMPRODUCT($AC43:$AC$55,$AB43:$AB$55)),""),"")
F44: =IF(AND(E44<>"",E44<>0),D44/E44,"") | H44: =IF(AND(G44<>"",G44<>0),D44/G44,"") | J44: =IF(AND(G44<>"",G44<>0),E44/G44,"") | T44: =IF(AND(I44<>"",I44<>0),G44/I44,"") | U44: =D44/V44 -> #DIV/0! | V44: =$I$8*AB44*AC44/SUMPRODUCT($AC$25:$AC$55,$AB$25:$AB$55) -> 0 | W44: =$I$9*AB44*AC44/SUMPRODUCT($AC$25:$AC$55,$AB$25:$AB$55) -> 0 | X44: =IF($I$12="","",W44/$I$12) -> 0 | Y44: =IF(AC44<>"",IF(D44<>"",D44,($I$8-SUM($Y$25:Y43))*AB44*AC44/SUMPRODUCT($AC44:$AC$55,$AB44:$AB$55)),"") | Z44: =IF(AC44<>"",IF(E44<>"",E44,($I$9-SUM($Z$25:Z43))*AB44*AC44/SUMPRODUCT($AC44:$AC$55,$AB44:$AB$55)),"") | AA44: =IF(AC44<>"",IF($I$12<>"",IF(G44<>"",G44,($I$9/$I$12-SUM($AA$25:AA43))*AB44*AC44/SUMPRODUCT($AC44:$AC$55,$AB44:$AB$55)),""),"")
F45: =IF(AND(E45<>"",E45<>0),D45/E45,"") | H45: =IF(AND(G45<>"",G45<>0),D45/G45,"") | J45: =IF(AND(G45<>"",G45<>0),E45/G45,"") | T45: =IF(AND(I45<>"",I45<>0),G45/I45,"") | U45: =D45/V45 -> #DIV/0! | V45: =$I$8*AB45*AC45/SUMPRODUCT($AC$25:$AC$55,$AB$25:$AB$55) -> 0 | W45: =$I$9*AB45*AC45/SUMPRODUCT($AC$25:$AC$55,$AB$25:$AB$55) -> 0 | X45: =IF($I$12="","",W45/$I$12) -> 0 | Y45: =IF(AC45<>"",IF(D45<>"",D45,($I$8-SUM($Y$25:Y44))*AB45*AC45/SUMPRODUCT($AC45:$AC$55,$AB45:$AB$55)),"") | Z45: =IF(AC45<>"",IF(E45<>"",E45,($I$9-SUM($Z$25:Z44))*AB45*AC45/SUMPRODUCT($AC45:$AC$55,$AB45:$AB$55)),"") | AA45: =IF(AC45<>"",IF($I$12<>"",IF(G45<>"",G45,($I$9/$I$12-SUM($AA$25:AA44))*AB45*AC45/SUMPRODUCT($AC45:$AC$55,$AB45:$AB$55)),""),"")
F46: =IF(AND(E46<>"",E46<>0),D46/E46,"") | H46: =IF(AND(G46<>"",G46<>0),D46/G46,"") | J46: =IF(AND(G46<>"",G46<>0),E46/G46,"") | T46: =IF(AND(I46<>"",I46<>0),G46/I46,"") | U46: =D46/V46 -> #DIV/0! | V46: =$I$8*AB46*AC46/SUMPRODUCT($AC$25:$AC$46,$AB$25:$AB$46) -> 0 | W46: =$I$9*AB46*AC46/SUMPRODUCT($AC$25:$AC$46,$AB$25:$AB$46) -> 0 | X46: =IF($I$12="","",W46/$I$12) -> 0 | Y46: =IF(AC46<>"",IF(D46<>"",D46,($I$8-SUM($Y$25:Y45))*AB46*AC46/SUMPRODUCT($AC46:$AC$46,$AB46:$AB$46)),"") | Z46: =IF(AC46<>"",IF(E46<>"",E46,($I$9-SUM($Z$25:Z39))*AB46*AC46/SUMPRODUCT($AC46:$AC$46,$AB46:$AB$46)),"") | AA46: =IF(AC46<>"",IF($I$12<>"",IF(G46<>"",G46,($I$9/$I$12-SUM($AA$25:AA39))*AB46*AC46/SUMPRODUCT($AC46:$AC$46,$AB46:$AB$46)),""),"")
B47: 46060 | C47: сб | D47: 12684 | E47: 2 | F47: =IF(AND(E47<>"",E47<>0),D47/E47,"") -> 6342 | G47: 1 | H47: =IF(AND(G47<>"",G47<>0),D47/G47,"") -> 12684 | J47: =IF(AND(G47<>"",G47<>0),E47/G47,"") -> 2 | T47: =IF(AND(I47<>"",I47<>0),G47/I47,"") | U47: =D47/V47 -> #DIV/0! | V47: =$I$8*AB47*AC47/SUMPRODUCT($AC$25:$AC$46,$AB$25:$AB$46) -> 0 | W47: =$I$9*AB47*AC47/SUMPRODUCT($AC$25:$AC$46,$AB$25:$AB$46) -> 0 | X47: =IF($I$12="","",W47/$I$12) -> 0 | Y47: =IF(AC47<>"",IF(D47<>"",D47,($I$8-SUM($Y$25:Y46))*AB47*AC47/SUMPRODUCT($AC$47:$AC47,$AB$47:$AB47)),"") | Z47: =IF(AC47<>"",IF(E47<>"",E47,($I$9-SUM(#REF!))*AB47*AC47/SUMPRODUCT($AC$47:$AC47,$AB$47:$AB47)),"") | AA47: =IF(AC47<>"",IF($I$12<>"",IF(G47<>"",G47,($I$9/$I$12-SUM(#REF!))*AB47*AC47/SUMPRODUCT($AC$47:$AC47,$AB$47:$AB47)),""),"")
B48: итого | D48: =SUM(D25:D47) -> 309495 | E48: =SUM(E25:E47) -> 29 | F48: =IF(AND(E48<>"",E48<>0),D48/E48,"") -> 10672.241 | G48: =SUM(G25:G47) -> 18 | H48: =IF(AND(G48<>"",G48<>0),D48/G48,"") -> 17194.167 | I48: =SUM(I25:I47)*0.8 -> 224.8 | J48: =IF(AND(G48<>"",G48<>0),E48/G48,"") -> 1.6111111 | K48: =SUM(K25:K47) -> 62658 | L48: =SUM(L25:L47) -> 0 | M48: =SUM(M25:M47) -> 34163 | N48: =SUM(N25:N47) -> 0 | O48: =SUM(O25:O47) -> 0 | P48: =SUM(P25:P47) -> 0 | Q48: =SUM(Q25:Q47) -> 0 | R48: =SUM(R25:R47) -> 93760 | T48: =IF(AND(I48<>"",I48<>0),G48/I48,"") -> 0.080071174 | U48: =D48/V48 -> 0.53771899 | V48: =SUM(V25:V47) -> 575570.15 | W48: =SUM(W25:W47) -> 81.332252 | X48: =SUM(X25:X47) -> 44.028398 | Y48: =SUM(Y25:Y47) -> 310032 | Z48: =SUM(Z25:Z47) -> 29 | AA48: =SUM(AA25:AA47) -> 19
D49: =SUMIF(D25:D47,"",V25:V47)+D48 -> 309495

Sheet Свидовская С. А.
B1: =TODAY()-1 -> 46171
B2: (отчетная дата) | J2: ЕЖЕДНЕВНЫЙ ОТЧЕТ О ПРОДАЖАХ
B3: Осталось до выполнения плана!!! | J3: =График!B27 -> Свидовская София
C4: =I8-D48 -> 206054.23 | E4: =IF(I8<>0,C4/I8,0) -> 0.45321883
F6: Целевые показатели
F7: Показатель | I7: План | J7: Факт | K7: % выполнения | L7: Прогноз выполнения | M7: % выполнения по прогнозу | N7: Отклонение | O7: Факт аналогичного месяца прошлого года | P7: Отклонение LFL
F8: Выручка | I8: =Центрум!I8/График!AJ29*График!AJ27 -> 454646.23 | J8: =D48 -> 248592 | K8: =IF(AND(I8<>"",I8<>0,J8<>""),J8/I8,"") -> 0.54678117 | L8: =IF(SUMIF($D$25:$D$47,">=0",$V$25:$V$47)<>0,I8*D48/SUMIF($D$25:$D$47,">=0",$V$25:$V$47),0) -> 260531.2 | M8: =L8/I8 -> 0.57304159 | N8: =IF(AND(J8<>0,J8<>"",I8<>0,I8<>""),L8-I8,"") -> -194115.03 | P8: =IF(AND(O8<>"",O8<>0,L8<>"",L8<>0),-O8+L8,"") | Q8: =IF(AND(P8<>"",P8<>0,O8<>0,O8<>""),P8/O8,"")
F9: Кол-во изделий | I9: =I8/I11 -> 62.623448 | J9: =E48 -> 33 | K9: =IF(AND(I9<>"",I9<>0,J9<>""),J9/I9,"") -> 0.52695916 | L9: =IF(SUMIF($E$25:$E$47,">=0",$W$25:$W$47)<>0,I9*E48/SUMIF($E$25:$E$47,">=0",$W$25:$W$47),0) -> 33.436319 | M9: =IF(AND(I9<>"",I9<>0,L9<>"",L9<>0),L9/I9,"") -> 0.5339265 | N9: =IF(AND(J9<>0,J9<>"",I9<>0,I9<>""),L9-I9,"") -> -29.18713 | O9: =O8/O11 -> #DIV/0! | P9: =IF(AND(O9<>"",O9<>0,L9<>"",L9<>0),-O9+L9,"") -> #DIV/0! | Q9: =IF(AND(P9<>"",P9<>0,O9<>0,O9<>""),P9/O9,"") -> #DIV/0!
F10: Средний чек | I10: =I11*I12 -> 13358.4 | J10: =H48 -> 10808.348 | K10: =IF(AND(I10<>"",I10<>0,J10<>""),J10/I10,"") -> 0.80910497 | L10: =J10 -> 10808.348 | M10: =IF(AND(I10<>"",I10<>0,L10<>"",L10<>0),L10/I10,"") -> 0.80910497 | N10: =IF(AND(J10<>0,J10<>"",I10<>0,I10<>""),L10-I10,"") -> -2550.0522 | O10: =O11*O12 -> 0 | P10: =IF(AND(O10<>"",O10<>0,L10<>"",L10<>0),-O10+L10,"") | Q10: =IF(AND(P10<>"",P10<>0,O10<>0,O10<>""),P10/O10,"")
F11: Средняя стоимость изделия | I11: =Центрум!I11 -> 7260 | J11: =F48 -> 7533.0909 | K11: =IF(AND(I11<>"",I11<>0,J11<>""),J11/I11,"") -> 1.0376158 | L11: =J11 -> 7533.0909 | M11: =IF(AND(I11<>"",I11<>0,L11<>"",L11<>0),L11/I11,"") -> 1.0376158 | N11: =IF(AND(J11<>0,J11<>"",I11<>0,I11<>""),L11-I11,"") -> 273.09091 | P11: =IF(AND(O11<>"",O11<>0,L11<>"",L11<>0),-O11+L11,"") | Q11: =IF(AND(P11<>"",P11<>0,O11<>0,O11<>""),P11/O11,"")
F12: Длина чека | I12: =Центрум!I12 -> 1.84 | J12: =J48 -> 1.4347826 | K12: =IF(AND(I12<>"",I12<>0,J12<>""),J12/I12,"") -> 0.77977316 | L12: =J12 -> 1.4347826 | M12: =IF(AND(I12<>"",I12<>0,L12<>"",L12<>0),L12/I12,"") -> 0.77977316 | N12: =IF(AND(J12<>0,J12<>"",I12<>0,I12<>""),L12-I12,"") -> -0.40521739 | P12: =IF(AND(O12<>"",O12<>0,L12<>"",L12<>0),-O12+L12,"") | Q12: =IF(AND(P12<>"",P12<>0,O12<>0,O12<>""),P12/O12,"")
F13: Кол-во чеков | I13: =IF(I12<>0,I9/I12,"") -> 34.034483 | J13: =G48 -> 23 | K13: =IF(AND(I13<>"",I13<>0,J13<>""),J13/I13,"") -> 0.67578521 | L13: =IF(SUMIF($G$25:$G$47,">=0",$X$25:$X$47)<>0,I13*G48/SUMIF($G$25:$G$47,">=0",$X$25:$X$47),"") -> 23.425385 | M13: =IF(AND(I13<>"",I13<>0,L13<>"",L13<>0),L13/I13,"") -> 0.68828385 | N13: =IF(AND(J13<>0,J13<>"",I13<>0,I13<>""),L13-I13,"") -> -10.609098 | P13: =IF(AND(O13<>"",O13<>0,L13<>"",L13<>0),-O13+L13,"") | Q13: =IF(AND(P13<>"",P13<>0,O13<>0,O13<>""),P13/O13,"")
F14: Кол-во смен план/отработано | I14: =График!AI27 -> 13 | J14: 13 | K14: =IF(AND(I14<>"",I14<>0,J14<>""),J14/I14,"") -> 1 | L14: =IF(SUMIF($D$25:$D$47,">=0",$V$25:$V$47),I48*I8/SUMIF($D$25:$D$47,">=0",$V$25:$V$47),"") -> 176.06858 | N14: =IF(AND(J14<>0,J14<>"",I14<>0,I14<>""),L14-I14,"") -> 163.06858 | P14: =IF(AND(O14<>"",O14<>0,L14<>"",L14<>0),-O14+L14,"") | Q14: =IF(AND(P14<>"",P14<>0,O14<>0,O14<>""),P14/O14,"")
F15: Средние продажи в смену | I15: =Центрум!I15/2 -> 33396 | J15: =J8/J14 -> 19122.462 | K15: =IF(AND(I15<>"",I15<>0,J15<>""),J15/I15,"") -> 0.57259736 | L15: =J15 -> 19122.462 | M15: =IF(AND(I15<>"",I15<>0,L15<>"",L15<>0),L15/I15,"") -> 0.57259736 | N15: =IF(AND(J15<>0,J15<>"",I15<>0,I15<>""),L15-I15,"") -> -14273.538 | P15: =IF(AND(O15<>"",O15<>0,L15<>"",L15<>0),-O15+L15,"") | Q15: =IF(AND(P15<>"",P15<>0,O15<>0,O15<>""),P15/O15,"")
F16: Отставание/Перевыполнение | J16: =J8-I15*J14 -> -185556 | K16: =IF(AND(I16<>"",I16<>0,J16<>""),J16/I16,"") | L16: =J16 -> -185556 | M16: =IF(AND(I16<>"",I16<>0,L16<>"",L16<>0),L16/I16,"") | N16: =IF(AND(J16<>0,J16<>"",I16<>0,I16<>""),L16-I16,"") | P16: =IF(AND(O16<>"",O16<>0,L16<>"",L16<>0),-O16+L16,"") | Q16: =IF(AND(P16<>"",P16<>0,O16<>0,O16<>""),P16/O16,"") | V16: Подарочные сертификаты
F17: Трафик | I17: =Центрум!I17/График!AJ29*График!AJ27 -> 340.34483 | J17: =I48 -> 168 | K17: =IF(AND(I17<>"",I17<>0,J17<>""),J17/I17,"") -> 0.49361702 | L17: =J17/J14*I14 -> 168 | M17: =IF(AND(I17<>"",I17<>0,L17<>"",L17<>0),L17/I17,"") -> 0.49361702 | N17: =IF(AND(J17<>0,J17<>"",I17<>0,I17<>""),L17-I17,"") -> -172.34483 | P17: =IF(AND(O17<>"",O17<>0,L17<>"",L17<>0),-O17+L17,"") | Q17: =IF(AND(P17<>"",P17<>0,O17<>0,O17<>""),P17/O17,"")
K18: =IF(AND(I18<>"",I18<>0,J18<>""),J18/I18,"") | L18: =J18 -> 0 | M18: =IF(AND(I18<>"",I18<>0,L18<>"",L18<>0),L18/I18,"") | N18: =IF(AND(J18<>0,J18<>"",I18<>0,I18<>""),L18-I18,"") | O18: 0 | P18: =IF(AND(O18<>"",O18<>0,L18<>"",L18<>0),-O18+L18,"") | Q18: =IF(AND(P18<>"",P18<>0,O18<>0,O18<>""),P18/O18,"")
K19: =IF(AND(I19<>"",I19<>0,J19<>""),J19/I19,"") | L19: =J19 -> 0 | M19: =IF(AND(I19<>"",I19<>0,L19<>"",L19<>0),L19/I19,"") | N19: =IF(AND(J19<>0,J19<>"",I19<>0,I19<>""),L19-I19,"") | O19: 0 | P19: =IF(AND(O19<>"",O19<>0,L19<>"",L19<>0),-O19+L19,"") | Q19: =IF(AND(P19<>"",P19<>0,O19<>0,O19<>""),P19/O19,"") | V19: =V18/I16 -> #DIV/0!
F20: Конверсия план/факт | I20: =Центрум!I20 -> 0.1 | J20: =T48 -> 0.13690476 | K20: =J20/I20 -> 1.3690476 | L20: =IF(AND(K8<>0,I14<>0,I48<>0),(I48*T48+(I48/K8-I48)*I20)/(I48/K8),0) -> 0.12017883 | M20: =IF(AND(I20<>"",I20<>0,L20<>"",L20<>0),L20/I20,"") -> 1.2017883 | N20: =IF(AND(J20<>0,J20<>"",I20<>0,I20<>""),L20-I20,"") -> 0.020178829 | P20: =IF(AND(O20<>"",O20<>0,L20<>"",L20<>0),-O20+L20,"") | Q20: =IF(AND(P20<>"",P20<>0,O20<>0,O20<>""),P20/O20,"")
B22: Факт продаж за месяц | U22: % выполнения дневного плана | V22: Раcпределение плана по дням
B23: Дата | C23: День недели | D23: Выручка (руб) | E23: Кол-во единиц (шт.) | F23: Средняя стоимость изделия (руб.) | G23: Количество чеков (шт.) | H23: Средняя сумма чека (руб.) | I23: Трафик | J23: Длина чека (шт.) | K23: UNOde50 | L23: IS | M23: Agafi | N23: Kalliope | O23: Raganella | P23: CC/MP | Q23: Eva Rites | R23: Antura | S23: SALE | T23: Конверсия (%) | V23: выручка, план | W23: кол-во ед, план | X23: Кол-во чеков, план | Y23: выручка, скорректир.план | Z23: кол-во ед, скорр. план | AA23: кол-во чеков, скорр. план | AB23: Коэфф. Дня Недели | AC23: Специфика месяца
B24: 1 | C24: 2 | D24: 3 | E24: в | F24: 5 | G24: 6 | H24: 7 | I24: 8 | J24: 9 | K24: 10 | L24: 11 | M24: 12 | N24: 13 | O24: 14 | P24: 15 | Q24: 16 | R24: 17 | T24: 18 | V24: 1 | W24: 2 | X24: 3 | Y24: 4 | Z24: 5 | AA24: 6 | AB24: 10 | AC24: 11
A25: 1 | B25: 46063 | C25: вт | D25: 39452 | E25: 5 | F25: =IF(AND(E25<>"",E25<>0),D25/E25,"") -> 7890.4 | G25: 3 | H25: =IF(AND(G25<>"",G25<>0),D25/G25,"") -> 13150.667 | I25: 25 | J25: =IF(AND(G25<>"",G25<>0),E25/G25,"") -> 1.6666667 | Q25: 9777 | T25: =IF(AND(I25<>"",I25<>0),G25/I25,"") -> 0.12 | U25: =D25/V25 -> 1.1280771 | V25: =$I$8*AB25*AC25/SUMPRODUCT($AC$25:$AC$55,$AB$25:$AB$55) -> 34972.787 | W25: =$I$9*AB25*AC25/SUMPRODUCT($AC$25:$AC$55,$AB$25:$AB$55) -> 4.8171883 | X25: =IF($I$12="","",W25/$I$12) -> 2.6180371 | Y25: =IF(AC25<>"",IF(D25<>"",D25,($I$8-SUM($Y24:Y$25))*AB25*AC25/SUMPRODUCT($AC25:$AC$55,$AB25:$AB$55)),"") -> 39452 | Z25: =IF(AC25<>"",IF(E25<>"",E25,($I$9-SUM($Z24:Z$25))*AB25*AC25/SUMPRODUCT($AC25:$AC$55,$AB25:$AB$55)),"") -> 5 | AA25: =IF(AC25<>"",IF($I$12<>"",IF(G25<>"",G25,($I$9/$I$12-SUM($AA24:AA$25))*AB25*AC25/SUMPRODUCT($AC25:$AC$55,$AB25:$AB$55)),""),"") -> 3 | AB25: 1 | AC25: 1
A26: 2 | B26: 46064 | C26: ср | D26: 4741 | E26: 1 | F26: =IF(AND(E26<>"",E26<>0),D26/E26,"") -> 4741 | G26: 1 | H26: =IF(AND(G26<>"",G26<>0),D26/G26,"") -> 4741 | I26: 27 | J26: =IF(AND(G26<>"",G26<>0),E26/G26,"") -> 1 | T26: =IF(AND(I26<>"",I26<>0),G26/I26,"") -> 0.037037037 | U26: =D26/V26 -> 0.13556254 | V26: =$I$8*AB26*AC26/SUMPRODUCT($AC$25:$AC$55,$AB$25:$AB$55) -> 34972.787 | W26: =$I$9*AB26*AC26/SUMPRODUCT($AC$25:$AC$55,$AB$25:$AB$55) -> 4.8171883 | X26: =IF($I$12="","",W26/$I$12) -> 2.6180371 | Y26: =IF(AC26<>"",IF(D26<>"",D26,($I$8-SUM($Y$25:Y25))*AB26*AC26/SUMPRODUCT($AC26:$AC$55,$AB26:$AB$55)),"") -> 4741 | Z26: =IF(AC26<>"",IF(E26<>"",E26,($I$9-SUM($Z$25:Z25))*AB26*AC26/SUMPRODUCT($AC26:$AC$55,$AB26:$AB$55)),"") -> 1 | AA26: =IF(AC26<>"",IF($I$12<>"",IF(G26<>"",G26,($I$9/$I$12-SUM($AA$25:AA25))*AB26*AC26/SUMPRODUCT($AC26:$AC$55,$AB26:$AB$55)),""),"") -> 1 | AB26: 1 | AC26: 1
A27: 3 | B27: 46065 | C27: чт | D27: 22549 | E27: 3 | F27: =IF(AND(E27<>"",E27<>0),D27/E27,"") -> 7516.3333 | G27: 2 | H27: =IF(AND(G27<>"",G27<>0),D27/G27,"") -> 11274.5 | I27: 20 | J27: =IF(AND(G27<>"",G27<>0),E27/G27,"") -> 1.5 | L27: 15902 | S27: 1647 | T27: =IF(AND(I27<>"",I27<>0),G27/I27,"") -> 0.1 | U27: =D27/V27 -> 1.5949215 | V27: 14138 | W27: 4 | X27: 2 | Y27: 16611 | Z27: 3 | AA27: 3 | AB27: 1 | AC27: 1
A28: 4 | B28: 46066 | C28: пт | D28: 44222 | E28: 7 | F28: =IF(AND(E28<>"",E28<>0),D28/E28,"") -> 6317.4286 | G28: 4 | H28: =IF(AND(G28<>"",G28<>0),D28/G28,"") -> 11055.5 | I28: 35 | J28: =IF(AND(G28<>"",G28<>0),E28/G28,"") -> 1.75 | T28: =IF(AND(I28<>"",I28<>0),G28/I28,"") -> 0.11428571 | U28: =D28/V28 -> 1.2644688 | V28: =$I$8*AB28*AC28/SUMPRODUCT($AC$25:$AC$55,$AB$25:$AB$55) -> 34972.787 | W28: =$I$9*AB28*AC28/SUMPRODUCT($AC$25:$AC$55,$AB$25:$AB$55) -> 4.8171883 | X28: =IF($I$12="","",W28/$I$12) -> 2.6180371 | Y28: =IF(AC28<>"",IF(D28<>"",D28,($I$8-SUM($Y$25:Y27))*AB28*AC28/SUMPRODUCT($AC28:$AC$55,$AB28:$AB$55)),"") -> 44222 | Z28: =IF(AC28<>"",IF(E28<>"",E28,($I$9-SUM($Z$25:Z27))*AB28*AC28/SUMPRODUCT($AC28:$AC$55,$AB28:$AB$55)),"") -> 7 | AA28: =IF(AC28<>"",IF($I$12<>"",IF(G28<>"",G28,($I$9/$I$12-SUM($AA$25:AA27))*AB28*AC28/SUMPRODUCT($AC28:$AC$55,$AB28:$AB$55)),""),"") -> 4 | AB28: 1 | AC28: 1
A29: 5 | B29: 46069 | C29: пн | D29: 32673 | E29: 3 | F29: =IF(AND(E29<>"",E29<>0),D29/E29,"") -> 10891 | G29: 2 | H29: =IF(AND(G29<>"",G29<>0),D29/G29,"") -> 16336.5 | I29: 21 | J29: =IF(AND(G29<>"",G29<>0),E29/G29,"") -> 1.5 | M29: 27672 | T29: =IF(AND(I29<>"",I29<>0),G29/I29,"") -> 0.095238095 | U29: =D29/V29 -> 0.93424066 | V29: =$I$8*AB29*AC29/SUMPRODUCT($AC$25:$AC$55,$AB$25:$AB$55) -> 34972.787 | W29: =$I$9*AB29*AC29/SUMPRODUCT($AC$25:$AC$55,$AB$25:$AB$55) -> 4.8171883 | X29: =IF($I$12="","",W29/$I$12) -> 2.6180371 | Y29: =IF(AC29<>"",IF(D29<>"",D29,($I$8-SUM($Y$25:Y28))*AB29*AC29/SUMPRODUCT($AC29:$AC$55,$AB29:$AB$55)),"") -> 32673 | Z29: =IF(AC29<>"",IF(E29<>"",E29,($I$9-SUM($Z$25:Z28))*AB29*AC29/SUMPRODUCT($AC29:$AC$55,$AB29:$AB$55)),"") -> 3 | AA29: =IF(AC29<>"",IF($I$12<>"",IF(G29<>"",G29,($I$9/$I$12-SUM($AA$25:AA28))*AB29*AC29/SUMPRODUCT($AC29:$AC$55,$AB29:$AB$55)),""),"") -> 2 | AB29: 1 | AC29: 1
A30: 6 | B30: 46070 | C30: вт | D30: 21121 | E30: 3 | F30: =IF(AND(E30<>"",E30<>0),D30/E30,"") -> 7040.3333 | G30: 2 | H30: =IF(AND(G30<>"",G30<>0),D30/G30,"") -> 10560.5 | I30: 17 | J30: =IF(AND(G30<>"",G30<>0),E30/G30,"") -> 1.5 | Q30: 7605 | T30: =IF(AND(I30<>"",I30<>0),G30/I30,"") -> 0.11764706 | U30: =D30/V30 -> 0.6039267 | V30: =$I$8*AB30*AC30/SUMPRODUCT($AC$25:$AC$55,$AB$25:$AB$55) -> 34972.787 | W30: =$I$9*AB30*AC30/SUMPRODUCT($AC$25:$AC$55,$AB$25:$AB$55) -> 4.8171883 | X30: =IF($I$12="","",W30/$I$12) -> 2.6180371 | Y30: =IF(AC30<>"",IF(D30<>"",D30,($I$8-SUM($Y$25:Y29))*AB30*AC30/SUMPRODUCT($AC30:$AC$55,$AB30:$AB$55)),"") -> 21121 | Z30: =IF(AC30<>"",IF(E30<>"",E30,($I$9-SUM($Z$25:Z29))*AB30*AC30/SUMPRODUCT($AC30:$AC$55,$AB30:$AB$55)),"") -> 3 | AA30: =IF(AC30<>"",IF($I$12<>"",IF(G30<>"",G30,($I$9/$I$12-SUM($AA$25:AA29))*AB30*AC30/SUMPRODUCT($AC30:$AC$55,$AB30:$AB$55)),""),"") -> 2 | AB30: 1 | AC30: 1
A31: 7 | B31: 46071 | C31: ср | D31: 0 | E31: 0 | F31: =IF(AND(E31<>"",E31<>0),D31/E31,"") | G31: 0 | H31: =IF(AND(G31<>"",G31<>0),D31/G31,"") | I31: 24 | J31: =IF(AND(G31<>"",G31<>0),E31/G31,"") | T31: =IF(AND(I31<>"",I31<>0),G31/I31,"") -> 0 | U31: =D31/V31 -> 0 | V31: =$I$8*AB31*AC31/SUMPRODUCT($AC$25:$AC$55,$AB$25:$AB$55) -> 34972.787 | W31: =$I$9*AB31*AC31/SUMPRODUCT($AC$25:$AC$55,$AB$25:$AB$55) -> 4.8171883 | X31: =IF($I$12="","",W31/$I$12) -> 2.6180371 | Y31: =IF(AC31<>"",IF(D31<>"",D31,($I$8-SUM($Y$25:Y30))*AB31*AC31/SUMPRODUCT($AC31:$AC$55,$AB31:$AB$55)),"") -> 0 | Z31: =IF(AC31<>"",IF(E31<>"",E31,($I$9-SUM($Z$25:Z30))*AB31*AC31/SUMPRODUCT($AC31:$AC$55,$AB31:$AB$55)),"") -> 0 | AA31: =IF(AC31<>"",IF($I$12<>"",IF(G31<>"",G31,($I$9/$I$12-SUM($AA$25:AA30))*AB31*AC31/SUMPRODUCT($AC31:$AC$55,$AB31:$AB$55)),""),"") -> 0 | AB31: 1 | AC31: 1
A32: 8 | B32: 46072 | C32: чт | D32: =8883+7139 -> 16022 | E32: 3 | F32: =IF(AND(E32<>"",E32<>0),D32/E32,"") -> 5340.6667 | G32: 2 | H32: =IF(AND(G32<>"",G32<>0),D32/G32,"") -> 8011 | I32: 16 | J32: =IF(AND(G32<>"",G32<>0),E32/G32,"") -> 1.5 | T32: =IF(AND(I32<>"",I32<>0),G32/I32,"") -> 0.125 | U32: =D32/V32 -> 0.45812763 | V32: =$I$8*AB32*AC32/SUMPRODUCT($AC$25:$AC$55,$AB$25:$AB$55) -> 34972.787 | W32: =$I$9*AB32*AC32/SUMPRODUCT($AC$25:$AC$55,$AB$25:$AB$55) -> 4.8171883 | X32: =IF($I$12="","",W32/$I$12) -> 2.6180371 | Y32: =IF(AC32<>"",IF(D32<>"",D32,($I$8-SUM($Y$25:Y31))*AB32*AC32/SUMPRODUCT($AC32:$AC$55,$AB32:$AB$55)),"") -> 16022 | Z32: =IF(AC32<>"",IF(E32<>"",E32,($I$9-SUM($Z$25:Z31))*AB32*AC32/SUMPRODUCT($AC32:$AC$55,$AB32:$AB$55)),"") -> 3 | AA32: =IF(AC32<>"",IF($I$12<>"",IF(G32<>"",G32,($I$9/$I$12-SUM($AA$25:AA31))*AB32*AC32/SUMPRODUCT($AC32:$AC$55,$AB32:$AB$55)),""),"") -> 2 | AB32: 1 | AC32: 1
A33: 9 | B33: 46075 | C33: вс | D33: 20365 | E33: 3 | F33: =IF(AND(E33<>"",E33<>0),D33/E33,"") -> 6788.3333 | G33: 2 | H33: =IF(AND(G33<>"",G33<>0),D33/G33,"") -> 10182.5 | I33: 25 | J33: =IF(AND(G33<>"",G33<>0),E33/G33,"") -> 1.5 | T33: =IF(AND(I33<>"",I33<>0),G33/I33,"") -> 0.08 | U33: =D33/V33 -> 0.58230989 | V33: =$I$8*AB33*AC33/SUMPRODUCT($AC$25:$AC$55,$AB$25:$AB$55) -> 34972.787 | W33: =$I$9*AB33*AC33/SUMPRODUCT($AC$25:$AC$55,$AB$25:$AB$55) -> 4.8171883 | X33: =IF($I$12="","",W33/$I$12) -> 2.6180371 | Y33: =IF(AC33<>"",IF(D33<>"",D33,($I$8-SUM($Y$25:Y32))*AB33*AC33/SUMPRODUCT($AC33:$AC$55,$AB33:$AB$55)),"") -> 20365 | Z33: =IF(AC33<>"",IF(E33<>"",E33,($I$9-SUM($Z$25:Z32))*AB33*AC33/SUMPRODUCT($AC33:$AC$55,$AB33:$AB$55)),"") -> 3 | AA33: =IF(AC33<>"",IF($I$12<>"",IF(G33<>"",G33,($I$9/$I$12-SUM($AA$25:AA32))*AB33*AC33/SUMPRODUCT($AC33:$AC$55,$AB33:$AB$55)),""),"") -> 2 | AB33: 1 | AC33: 1
A34: 10 | B34: 46076 | C34: пн | D34: 18806 | E34: 2 | F34: =IF(AND(E34<>"",E34<>0),D34/E34,"") -> 9403 | G34: 2 | H34: =IF(AND(G34<>"",G34<>0),D34/G34,"") -> 9403 | J34: =IF(AND(G34<>"",G34<>0),E34/G34,"") -> 1 | M34: 10903 | T34: =IF(AND(I34<>"",I34<>0),G34/I34,"") | U34: =D34/V34 -> 0.53773238 | V34: =$I$8*AB34*AC34/SUMPRODUCT($AC$25:$AC$55,$AB$25:$AB$55) -> 34972.787 | W34: =$I$9*AB34*AC34/SUMPRODUCT($AC$25:$AC$55,$AB$25:$AB$55) -> 4.8171883 | X34: =IF($I$12="","",W34/$I$12) -> 2.6180371 | Y34: =IF(AC34<>"",IF(D34<>"",D34,($I$8-SUM($Y$25:Y33))*AB34*AC34/SUMPRODUCT($AC34:$AC$55,$AB34:$AB$55)),"") -> 18806 | Z34: =IF(AC34<>"",IF(E34<>"",E34,($I$9-SUM($Z$25:Z33))*AB34*AC34/SUMPRODUCT($AC34:$AC$55,$AB34:$AB$55)),"") -> 2 | AA34: =IF(AC34<>"",IF($I$12<>"",IF(G34<>"",G34,($I$9/$I$12-SUM($AA$25:AA33))*AB34*AC34/SUMPRODUCT($AC34:$AC$55,$AB34:$AB$55)),""),"") -> 2 | AB34: 1 | AC34: 1
A35: 11 | B35: 46077 | C35: вт | D35: 16803 | E35: 1 | F35: =IF(AND(E35<>"",E35<>0),D35/E35,"") -> 16803 | G35: 1 | H35: =IF(AND(G35<>"",G35<>0),D35/G35,"") -> 16803 | J35: =IF(AND(G35<>"",G35<>0),E35/G35,"") -> 1 | T35: =IF(AND(I35<>"",I35<>0),G35/I35,"") | U35: =D35/V35 -> 0.48045927 | V35: =$I$8*AB35*AC35/SUMPRODUCT($AC$25:$AC$55,$AB$25:$AB$55) -> 34972.787 | W35: =$I$9*AB35*AC35/SUMPRODUCT($AC$25:$AC$55,$AB$25:$AB$55) -> 4.8171883 | X35: =IF($I$12="","",W35/$I$12) -> 2.6180371 | Y35: =IF(AC35<>"",IF(D35<>"",D35,($I$8-SUM($Y$25:Y34))*AB35*AC35/SUMPRODUCT($AC35:$AC$55,$AB35:$AB$55)),"") -> 16803 | Z35: =IF(AC35<>"",IF(E35<>"",E35,($I$9-SUM($Z$25:Z34))*AB35*AC35/SUMPRODUCT($AC35:$AC$55,$AB35:$AB$55)),"") -> 1 | AA35: =IF(AC35<>"",IF($I$12<>"",IF(G35<>"",G35,($I$9/$I$12-SUM($AA$25:AA34))*AB35*AC35/SUMPRODUCT($AC35:$AC$55,$AB35:$AB$55)),""),"") -> 1 | AB35: 1 | AC35: 1
A36: 12 | B36: 46078 | C36: ср | D36: 0 | E36: 0 | F36: =IF(AND(E36<>"",E36<>0),D36/E36,"") | G36: 0 | H36: =IF(AND(G36<>"",G36<>0),D36/G36,"") | J36: =IF(AND(G36<>"",G36<>0),E36/G36,"") | T36: =IF(AND(I36<>"",I36<>0),G36/I36,"") | U36: =D36/V36 -> 0 | V36: =$I$8*AB36*AC36/SUMPRODUCT($AC$25:$AC$55,$AB$25:$AB$55) -> 34972.787 | W36: =$I$9*AB36*AC36/SUMPRODUCT($AC$25:$AC$55,$AB$25:$AB$55) -> 4.8171883 | X36: =IF($I$12="","",W36/$I$12) -> 2.6180371 | Y36: =IF(AC36<>"",IF(D36<>"",D36,($I$8-SUM($Y$25:Y35))*AB36*AC36/SUMPRODUCT($AC36:$AC$55,$AB36:$AB$55)),"") -> 0 | Z36: =IF(AC36<>"",IF(E36<>"",E36,($I$9-SUM($Z$25:Z35))*AB36*AC36/SUMPRODUCT($AC36:$AC$55,$AB36:$AB$55)),"") -> 0 | AA36: =IF(AC36<>"",IF($I$12<>"",IF(G36<>"",G36,($I$9/$I$12-SUM($AA$25:AA35))*AB36*AC36/SUMPRODUCT($AC36:$AC$55,$AB36:$AB$55)),""),"") -> 0 | AB36: 1 | AC36: 1
A37: 13 | B37: 46081 | C37: сб | D37: 8593 | E37: 1 | F37: =IF(AND(E37<>"",E37<>0),D37/E37,"") -> 8593 | G37: 1 | H37: =IF(AND(G37<>"",G37<>0),D37/G37,"") -> 8593 | J37: =IF(AND(G37<>"",G37<>0),E37/G37,"") -> 1 | T37: =IF(AND(I37<>"",I37<>0),G37/I37,"") | U37: =D37/V37 -> 0.24570532 | V37: =$I$8*AB37*AC37/SUMPRODUCT($AC$25:$AC$55,$AB$25:$AB$55) -> 34972.787 | W37: =$I$9*AB37*AC37/SUMPRODUCT($AC$25:$AC$55,$AB$25:$AB$55) -> 4.8171883 | X37: =IF($I$12="","",W37/$I$12) -> 2.6180371 | Y37: =IF(AC37<>"",IF(D37<>"",D37,($I$8-SUM($Y$25:Y36))*AB37*AC37/SUMPRODUCT($AC37:$AC$55,$AB37:$AB$55)),"") -> 8593 | Z37: =IF(AC37<>"",IF(E37<>"",E37,($I$9-SUM($Z$25:Z36))*AB37*AC37/SUMPRODUCT($AC37:$AC$55,$AB37:$AB$55)),"") -> 1 | AA37: =IF(AC37<>"",IF($I$12<>"",IF(G37<>"",G37,($I$9/$I$12-SUM($AA$25:AA36))*AB37*AC37/SUMPRODUCT($AC37:$AC$55,$AB37:$AB$55)),""),"") -> 1 | AB37: 1 | AC37: 1
A38: 14 | F38: =IF(AND(E38<>"",E38<>0),D38/E38,"") | H38: =IF(AND(G38<>"",G38<>0),D38/G38,"") | J38: =IF(AND(G38<>"",G38<>0),E38/G38,"") | T38: =IF(AND(I38<>"",I38<>0),G38/I38,"") | U38: =D38/V38 -> #DIV/0! | V38: =$I$8*AB38*AC38/SUMPRODUCT($AC$25:$AC$46,$AB$25:$AB$46) -> 0 | W38: =$I$9*AB38*AC38/SUMPRODUCT($AC$25:$AC$46,$AB$25:$AB$46) -> 0 | X38: =IF($I$12="","",W38/$I$12) -> 0 | Y38: =IF(AC38<>"",IF(D38<>"",D38,($I$8-SUM($Y$25:Y37))*AB38*AC38/SUMPRODUCT($AC38:$AC$55,$AB38:$AB$55)),"") | Z38: =IF(AC38<>"",IF(E38<>"",E38,($I$9-SUM($Z$25:Z37))*AB38*AC38/SUMPRODUCT($AC38:$AC$55,$AB38:$AB$55)),"") | AA38: =IF(AC38<>"",IF($I$12<>"",IF(G38<>"",G38,($I$9/$I$12-SUM($AA$25:AA37))*AB38*AC38/SUMPRODUCT($AC38:$AC$55,$AB38:$AB$55)),""),"")
A39: 15 | F39: =IF(AND(E39<>"",E39<>0),D39/E39,"") | H39: =IF(AND(G39<>"",G39<>0),D39/G39,"") | J39: =IF(AND(G39<>"",G39<>0),E39/G39,"") | T39: =IF(AND(I39<>"",I39<>0),G39/I39,"") | U39: =D39/V39 -> #DIV/0! | V39: =$I$8*AB39*AC39/SUMPRODUCT($AC$25:$AC$46,$AB$25:$AB$46) -> 0 | W39: =$I$9*AB39*AC39/SUMPRODUCT($AC$25:$AC$46,$AB$25:$AB$46) -> 0 | X39: =IF($I$12="","",W39/$I$12) -> 0 | Y39: =IF(AC39<>"",IF(D39<>"",D39,($I$8-SUM($Y$25:Y38))*AB39*AC39/SUMPRODUCT($AC39:$AC$55,$AB39:$AB$55)),"") | Z39: =IF(AC39<>"",IF(E39<>"",E39,($I$9-SUM($Z$25:Z38))*AB39*AC39/SUMPRODUCT($AC39:$AC$55,$AB39:$AB$55)),"") | AA39: =IF(AC39<>"",IF($I$12<>"",IF(G39<>"",G39,($I$9/$I$12-SUM($AA$25:AA38))*AB39*AC39/SUMPRODUCT($AC39:$AC$55,$AB39:$AB$55)),""),"")
A40: 16 | F40: =IF(AND(E40<>"",E40<>0),D40/E40,"") | H40: =IF(AND(G40<>"",G40<>0),D40/G40,"") | J40: =IF(AND(G40<>"",G40<>0),E40/G40,"") | T40: =IF(AND(I40<>"",I40<>0),G40/I40,"") | U40: =D40/V40 -> #DIV/0! | V40: =$I$8*AB40*AC40/SUMPRODUCT($AC$25:$AC$46,$AB$25:$AB$46) -> 0 | W40: =$I$9*AB40*AC40/SUMPRODUCT($AC$25:$AC$46,$AB$25:$AB$46) -> 0 | X40: =IF($I$12="","",W40/$I$12) -> 0 | Y40: =IF(AC40<>"",IF(D40<>"",D40,($I$8-SUM($Y$25:Y39))*AB40*AC40/SUMPRODUCT($AC40:$AC$55,$AB40:$AB$55)),"") | Z40: =IF(AC40<>"",IF(E40<>"",E40,($I$9-SUM($Z$25:Z39))*AB40*AC40/SUMPRODUCT($AC40:$AC$55,$AB40:$AB$55)),"") | AA40: =IF(AC40<>"",IF($I$12<>"",IF(G40<>"",G40,($I$9/$I$12-SUM($AA$25:AA39))*AB40*AC40/SUMPRODUCT($AC40:$AC$55,$AB40:$AB$55)),""),"")
A41: 17 | F41: =IF(AND(E41<>"",E41<>0),D41/E41,"") | H41: =IF(AND(G41<>"",G41<>0),D41/G41,"") | J41: =IF(AND(G41<>"",G41<>0),E41/G41,"") | T41: =IF(AND(I41<>"",I41<>0),G41/I41,"") | U41: =D41/V41 -> #DIV/0! | V41: =$I$8*AB41*AC41/SUMPRODUCT($AC$25:$AC$46,$AB$25:$AB$46) -> 0 | W41: =$I$9*AB41*AC41/SUMPRODUCT($AC$25:$AC$46,$AB$25:$AB$46) -> 0 | X41: =IF($I$12="","",W41/$I$12) -> 0 | Y41: =IF(AC41<>"",IF(D41<>"",D41,($I$8-SUM($Y$25:Y40))*AB41*AC41/SUMPRODUCT($AC41:$AC$55,$AB41:$AB$55)),"") | Z41: =IF(AC41<>"",IF(E41<>"",E41,($I$9-SUM($Z$25:Z40))*AB41*AC41/SUMPRODUCT($AC41:$AC$55,$AB41:$AB$55)),"") | AA41: =IF(AC41<>"",IF($I$12<>"",IF(G41<>"",G41,($I$9/$I$12-SUM($AA$25:AA40))*AB41*AC41/SUMPRODUCT($AC41:$AC$55,$AB41:$AB$55)),""),"")
A42: 18 | F42: =IF(AND(E42<>"",E42<>0),D42/E42,"") | H42: =IF(AND(G42<>"",G42<>0),D42/G42,"") | J42: =IF(AND(G42<>"",G42<>0),E42/G42,"") | T42: =IF(AND(I42<>"",I42<>0),G42/I42,"") | U42: =D42/V42 -> #DIV/0! | V42: =$I$8*AB42*AC42/SUMPRODUCT($AC$25:$AC$46,$AB$25:$AB$46) -> 0 | W42: =$I$9*AB42*AC42/SUMPRODUCT($AC$25:$AC$46,$AB$25:$AB$46) -> 0 | X42: =IF($I$12="","",W42/$I$12) -> 0 | Y42: =IF(AC42<>"",IF(D42<>"",D42,($I$8-SUM($Y$25:Y41))*AB42*AC42/SUMPRODUCT($AC42:$AC$55,$AB42:$AB$55)),"") | Z42: =IF(AC42<>"",IF(E42<>"",E42,($I$9-SUM($Z$25:Z41))*AB42*AC42/SUMPRODUCT($AC42:$AC$55,$AB42:$AB$55)),"") | AA42: =IF(AC42<>"",IF($I$12<>"",IF(G42<>"",G42,($I$9/$I$12-SUM($AA$25:AA41))*AB42*AC42/SUMPRODUCT($AC42:$AC$55,$AB42:$AB$55)),""),"")
A43: 19 | F43: =IF(AND(E43<>"",E43<>0),D43/E43,"") | H43: =IF(AND(G43<>"",G43<>0),D43/G43,"") | J43: =IF(AND(G43<>"",G43<>0),E43/G43,"") | T43: =IF(AND(I43<>"",I43<>0),G43/I43,"") | U43: =D43/V43 -> #DIV/0! | V43: =$I$8*AB43*AC43/SUMPRODUCT($AC$25:$AC$46,$AB$25:$AB$46) -> 0 | W43: =$I$9*AB43*AC43/SUMPRODUCT($AC$25:$AC$46,$AB$25:$AB$46) -> 0 | X43: =IF($I$12="","",W43/$I$12) -> 0 | Y43: =IF(AC43<>"",IF(D43<>"",D43,($I$8-SUM($Y$25:Y42))*AB43*AC43/SUMPRODUCT($AC43:$AC$55,$AB43:$AB$55)),"") | Z43: =IF(AC43<>"",IF(E43<>"",E43,($I$9-SUM($Z$25:Z42))*AB43*AC43/SUMPRODUCT($AC43:$AC$46,$AB43:$AB$46)),"") | AA43: =IF(AC43<>"",IF($I$12<>"",IF(G43<>"",G43,($I$9/$I$12-SUM($AA$25:AA42))*AB43*AC43/SUMPRODUCT($AC43:$AC$46,$AB43:$AB$46)),""),"")
F44: =IF(AND(E44<>"",E44<>0),D44/E44,"") | H44: =IF(AND(G44<>"",G44<>0),D44/G44,"") | J44: =IF(AND(G44<>"",G44<>0),E44/G44,"") | T44: =IF(AND(I44<>"",I44<>0),G44/I44,"") | U44: =D44/V44 -> #DIV/0! | V44: =$I$8*AB44*AC44/SUMPRODUCT($AC$25:$AC$46,$AB$25:$AB$46) -> 0 | W44: =$I$9*AB44*AC44/SUMPRODUCT($AC$25:$AC$46,$AB$25:$AB$46) -> 0 | X44: =IF($I$12="","",W44/$I$12) -> 0 | Y44: =IF(AC44<>"",IF(D44<>"",D44,($I$8-SUM($Y$25:Y43))*AB44*AC44/SUMPRODUCT($AC44:$AC$46,$AB44:$AB$46)),"") | Z44: =IF(AC44<>"",IF(E44<>"",E44,($I$9-SUM($Z$25:Z43))*AB44*AC44/SUMPRODUCT($AC44:$AC$46,$AB44:$AB$46)),"") | AA44: =IF(AC44<>"",IF($I$12<>"",IF(G44<>"",G44,($I$9/$I$12-SUM($AA$25:AA43))*AB44*AC44/SUMPRODUCT($AC44:$AC$46,$AB44:$AB$46)),""),"")
B45: 46080 | C45: пт | D45: 3245 | E45: 1 | G45: 1 | J45: =IF(AND(G45<>"",G45<>0),E45/G45,"") -> 1 | T45: =IF(AND(I45<>"",I45<>0),G45/I45,"") | U45: =D45/V45 -> #DIV/0! | V45: =$I$8*AB45*AC45/SUMPRODUCT($AC$25:$AC$46,$AB$25:$AB$46) -> 0 | W45: =$I$9*AB45*AC45/SUMPRODUCT($AC$25:$AC$46,$AB$25:$AB$46) -> 0 | X45: =IF($I$12="","",W45/$I$12) -> 0 | Y45: =IF(AC45<>"",IF(D45<>"",D45,($I$8-SUM($Y$25:Y44))*AB45*AC45/SUMPRODUCT($AC45:$AC$46,$AB45:$AB$46)),"") | Z45: =IF(AC45<>"",IF(E45<>"",E45,($I$9-SUM($Z$25:Z44))*AB45*AC45/SUMPRODUCT($AC45:$AC$46,$AB45:$AB$46)),"") | AA45: =IF(AC45<>"",IF($I$12<>"",IF(G45<>"",G45,($I$9/$I$12-SUM($AA$25:AA44))*AB45*AC45/SUMPRODUCT($AC45:$AC$46,$AB45:$AB$46)),""),"")
F46: =IF(AND(E46<>"",E46<>0),D46/E46,"") | H46: =IF(AND(G46<>"",G46<>0),D46/G46,"") | J46: =IF(AND(G46<>"",G46<>0),E46/G46,"") | T46: =IF(AND(I46<>"",I46<>0),G46/I46,"") | U46: =D46/V46 -> #DIV/0! | V46: =$I$8*AB46*AC46/SUMPRODUCT($AC$25:$AC$46,$AB$25:$AB$46) -> 0 | W46: =$I$9*AB46*AC46/SUMPRODUCT($AC$25:$AC$46,$AB$25:$AB$46) -> 0 | X46: =IF($I$12="","",W46/$I$12) -> 0 | Y46: =IF(AC46<>"",IF(D46<>"",D46,($I$8-SUM($Y$25:Y45))*AB46*AC46/SUMPRODUCT($AC46:$AC$46,$AB46:$AB$46)),"") | Z46: =IF(AC46<>"",IF(E46<>"",E46,($I$9-SUM($Z$25:Z39))*AB46*AC46/SUMPRODUCT($AC46:$AC$46,$AB46:$AB$46)),"") | AA46: =IF(AC46<>"",IF($I$12<>"",IF(G46<>"",G46,($I$9/$I$12-SUM($AA$25:AA39))*AB46*AC46/SUMPRODUCT($AC46:$AC$46,$AB46:$AB$46)),""),"")
F47: =IF(AND(E47<>"",E47<>0),D47/E47,"") | H47: =IF(AND(G47<>"",G47<>0),D47/G47,"") | J47: =IF(AND(G47<>"",G47<>0),E47/G47,"") | T47: =IF(AND(I47<>"",I47<>0),G47/I47,"") | U47: =D47/V47 -> #DIV/0! | V47: =$I$8*AB47*AC47/SUMPRODUCT($AC$25:$AC$46,$AB$25:$AB$46) -> 0 | W47: =$I$9*AB47*AC47/SUMPRODUCT($AC$25:$AC$46,$AB$25:$AB$46) -> 0 | X47: =IF($I$12="","",W47/$I$12) -> 0 | Y47: =IF(AC47<>"",IF(D47<>"",D47,($I$8-SUM($Y$25:Y46))*AB47*AC47/SUMPRODUCT($AC$46:$AC47,$AB$46:$AB47)),"") | Z47: =IF(AC47<>"",IF(E47<>"",E47,($I$9-SUM($Z$25:Z40))*AB47*AC47/SUMPRODUCT($AC$46:$AC47,$AB$46:$AB47)),"") | AA47: =IF(AC47<>"",IF($I$12<>"",IF(G47<>"",G47,($I$9/$I$12-SUM($AA$25:AA40))*AB47*AC47/SUMPRODUCT($AC$46:$AC47,$AB$46:$AB47)),""),"")
D48: =SUM(D25:D47) -> 248592 | E48: =SUM(E25:E47) -> 33 | F48: =IF(AND(E48<>"",E48<>0),D48/E48,"") -> 7533.0909 | G48: =SUM(G25:G47) -> 23 | H48: =IF(AND(G48<>"",G48<>0),D48/G48,"") -> 10808.348 | I48: =SUM(I25:I47)*0.8 -> 168 | J48: =IF(AND(G48<>"",G48<>0),E48/G48,"") -> 1.4347826 | K48: =SUM(K25:K47) -> 0 | L48: =SUM(L25:L47) -> 15902 | M48: =SUM(M25:M47) -> 38575 | N48: =SUM(N25:N47) -> 0 | O48: =SUM(O25:O47) -> 0 | P48: =SUM(P25:P47) -> 0 | Q48: =SUM(Q25:Q47) -> 17382 | R48: =SUM(R25:R47) -> 0 | S48: =SUM(S25:S47) -> 1647 | T48: =IF(AND(I48<>"",I48<>0),G48/I48,"") -> 0.13690476 | U48: =D48/V48 -> 0.57304159 | V48: =SUM(V25:V47) -> 433811.45 | W48: =SUM(W25:W47) -> 61.80626 | X48: =SUM(X25:X47) -> 33.416446 | Y48: =SUM(Y25:Y47) -> 239409 | Z48: =SUM(Z25:Z47) -> 32 | AA48: =SUM(AA25:AA47) -> 23
B49: итого | D49: =SUMIF(D25:D47,"",V25:V47)+D48 -> 248592

Sheet Доп сотрудник
B1: =TODAY()-1 -> 46171
B2: (отчетная дата) | J2: ЕЖЕДНЕВНЫЙ ОТЧЕТ О ПРОДАЖАХ
B3: Осталось до выполнения плана!!! | J3: =График!B24 -> 0
C4: =I8-D48 -> -7420 | E4: =IF(I8<>0,C4/I8,0) -> 0
F6: Целевые показатели
F7: Показатель | I7: План | J7: Факт | K7: % выполнения | L7: Прогноз выполнения | M7: % выполнения по прогнозу | N7: Отклонение | O7: Факт аналогичного месяца прошлого года | P7: Отклонение LFL
F8: Выручка | I8: =Центрум!I8/График!AJ29*График!AJ24 -> 0 | J8: =D48 -> 7420 | K8: =IF(AND(I8<>"",I8<>0,J8<>""),J8/I8,"") | L8: =IF(SUMIF($D$25:$D$47,">=0",$U$25:$U$47)<>0,I8*D48/SUMIF($D$25:$D$47,">=0",$U$25:$U$47),0) -> #DIV/0! | M8: =L8/I8 -> #DIV/0! | N8: =IF(AND(J8<>0,J8<>"",I8<>0,I8<>""),L8-I8,"") | P8: =IF(AND(O8<>"",O8<>0,L8<>"",L8<>0),-O8+L8,"") -> #DIV/0! | Q8: =IF(AND(P8<>"",P8<>0,O8<>0,O8<>""),P8/O8,"") -> #DIV/0!
F9: Кол-во изделий | I9: =I8/I11 -> 0 | J9: =E48 -> 1 | K9: =IF(AND(I9<>"",I9<>0,J9<>""),J9/I9,"") | L9: =IF(SUMIF($E$25:$E$47,">=0",$V$25:$V$47)<>0,I9*E48/SUMIF($E$25:$E$47,">=0",$V$25:$V$47),0) -> #DIV/0! | M9: =IF(AND(I9<>"",I9<>0,L9<>"",L9<>0),L9/I9,"") -> #DIV/0! | N9: =IF(AND(J9<>0,J9<>"",I9<>0,I9<>""),L9-I9,"") | P9: =IF(AND(O9<>"",O9<>0,L9<>"",L9<>0),-O9+L9,"") -> #DIV/0! | Q9: =IF(AND(P9<>"",P9<>0,O9<>0,O9<>""),P9/O9,"") -> #DIV/0!
F10: Средний чек | I10: =I11*I12 -> 13358.4 | J10: =H48 -> 7420 | K10: =IF(AND(I10<>"",I10<>0,J10<>""),J10/I10,"") -> 0.55545574 | L10: =J10 -> 7420 | M10: =IF(AND(I10<>"",I10<>0,L10<>"",L10<>0),L10/I10,"") -> 0.55545574 | N10: =IF(AND(J10<>0,J10<>"",I10<>0,I10<>""),L10-I10,"") -> -5938.4 | O10: =O11*O12 -> 0 | P10: =IF(AND(O10<>"",O10<>0,L10<>"",L10<>0),-O10+L10,"") | Q10: =IF(AND(P10<>"",P10<>0,O10<>0,O10<>""),P10/O10,"")
F11: Средняя стоимость изделия | I11: =Центрум!I11 -> 7260 | J11: =F48 -> 7420 | K11: =IF(AND(I11<>"",I11<>0,J11<>""),J11/I11,"") -> 1.0220386 | L11: =IF(L9>0,L8/L9,"") -> #DIV/0! | M11: =IF(AND(I11<>"",I11<>0,L11<>"",L11<>0),L11/I11,"") -> #DIV/0! | N11: =IF(AND(J11<>0,J11<>"",I11<>0,I11<>""),L11-I11,"") -> #DIV/0! | P11: =IF(AND(O11<>"",O11<>0,L11<>"",L11<>0),-O11+L11,"") -> #DIV/0! | Q11: =IF(AND(P11<>"",P11<>0,O11<>0,O11<>""),P11/O11,"") -> #DIV/0!
F12: Длина чека | I12: =Центрум!I12 -> 1.84 | J12: =J48 -> 1 | K12: =IF(AND(I12<>"",I12<>0,J12<>""),J12/I12,"") -> 0.54347826 | L12: =J12 -> 1 | M12: =IF(AND(I12<>"",I12<>0,L12<>"",L12<>0),L12/I12,"") -> 0.54347826 | N12: =IF(AND(J12<>0,J12<>"",I12<>0,I12<>""),L12-I12,"") -> -0.84 | P12: =IF(AND(O12<>"",O12<>0,L12<>"",L12<>0),-O12+L12,"") | Q12: =IF(AND(P12<>"",P12<>0,O12<>0,O12<>""),P12/O12,"")
F13: Кол-во чеков | I13: =IF(I12<>0,I9/I12,"") -> 0 | J13: =G48 -> 1 | K13: =IF(AND(I13<>"",I13<>0,J13<>""),J13/I13,"") | L13: =IF(SUMIF($G$25:$G$47,">=0",$W$25:$W$47)<>0,I13*G48/SUMIF($G$25:$G$47,">=0",$W$25:$W$47),"") -> #DIV/0! | M13: =IF(AND(I13<>"",I13<>0,L13<>"",L13<>0),L13/I13,"") -> #DIV/0! | N13: =IF(AND(J13<>0,J13<>"",I13<>0,I13<>""),L13-I13,"") | P13: =IF(AND(O13<>"",O13<>0,L13<>"",L13<>0),-O13+L13,"") -> #DIV/0! | Q13: =IF(AND(P13<>"",P13<>0,O13<>0,O13<>""),P13/O13,"") -> #DIV/0!
F14: Кол-во смен план/отработано | I14: =График!AI24 -> 0 | K14: =IF(AND(I14<>"",I14<>0,J14<>""),J14/I14,"") | L14: =IF(SUMIF($D$25:$D$47,">=0",$U$25:$U$47),I48*I8/SUMIF($D$25:$D$47,">=0",$U$25:$U$47),"") -> #DIV/0! | M14: =IF(AND(I14<>"",I14<>0,L14<>"",L14<>0),L14/I14,"") -> #DIV/0! | N14: =IF(AND(J14<>0,J14<>"",I14<>0,I14<>""),L14-I14,"") | P14: =IF(AND(O14<>"",O14<>0,L14<>"",L14<>0),-O14+L14,"") -> #DIV/0! | Q14: =IF(AND(P14<>"",P14<>0,O14<>0,O14<>""),P14/O14,"") -> #DIV/0!
F15: Средние продажи в смену | I15: =Центрум!I15 -> 66792 | J15: =J8/J14 -> #DIV/0! | K15: =IF(AND(I15<>"",I15<>0,J15<>""),J15/I15,"") -> #DIV/0! | L15: =J15 -> #DIV/0! | M15: =IF(AND(I15<>"",I15<>0,L15<>"",L15<>0),L15/I15,"") -> #DIV/0! | N15: =IF(AND(J15<>0,J15<>"",I15<>0,I15<>""),L15-I15,"") -> #DIV/0! | P15: =IF(AND(O15<>"",O15<>0,L15<>"",L15<>0),-O15+L15,"") -> #DIV/0! | Q15: =IF(AND(P15<>"",P15<>0,O15<>0,O15<>""),P15/O15,"") -> #DIV/0!
F16: Отставание/Перевыполнение | J16: =J8-I15*J14 -> 7420 | K16: =IF(AND(I16<>"",I16<>0,J16<>""),J16/I16,"") | L16: =J16 -> 7420 | M16: =IF(AND(I16<>"",I16<>0,L16<>"",L16<>0),L16/I16,"") | N16: =IF(AND(J16<>0,J16<>"",I16<>0,I16<>""),L16-I16,"") | P16: =IF(AND(O16<>"",O16<>0,L16<>"",L16<>0),-O16+L16,"") | Q16: =IF(AND(P16<>"",P16<>0,O16<>0,O16<>""),P16/O16,"") | T16: Подарочные сертификаты
F17: Трафик | I17: =Центрум!I17/График!AJ29*График!AJ24 -> 0 | J17: =I48 -> 0 | K17: =IF(AND(I17<>"",I17<>0,J17<>""),J17/I17,"") | L17: =J17/J14*I14 -> #DIV/0! | M17: =IF(AND(I17<>"",I17<>0,L17<>"",L17<>0),L17/I17,"") -> #DIV/0! | N17: =IF(AND(J17<>0,J17<>"",I17<>0,I17<>""),L17-I17,"") | P17: =IF(AND(O17<>"",O17<>0,L17<>"",L17<>0),-O17+L17,"") -> #DIV/0! | Q17: =IF(AND(P17<>"",P17<>0,O17<>0,O17<>""),P17/O17,"") -> #DIV/0!
K18: =IF(AND(I18<>"",I18<>0,J18<>""),J18/I18,"") | L18: =J18 -> 0 | M18: =IF(AND(I18<>"",I18<>0,L18<>"",L18<>0),L18/I18,"") | N18: =IF(AND(J18<>0,J18<>"",I18<>0,I18<>""),L18-I18,"") | O18: 0 | P18: =IF(AND(O18<>"",O18<>0,L18<>"",L18<>0),-O18+L18,"") | Q18: =IF(AND(P18<>"",P18<>0,O18<>0,O18<>""),P18/O18,"")
J19: =Q48 -> 0 | K19: =IF(AND(I19<>"",I19<>0,J19<>""),J19/I19,"") | L19: =J19 -> 0 | M19: =IF(AND(I19<>"",I19<>0,L19<>"",L19<>0),L19/I19,"") | N19: =IF(AND(J19<>0,J19<>"",I19<>0,I19<>""),L19-I19,"") | O19: 0 | P19: =IF(AND(O19<>"",O19<>0,L19<>"",L19<>0),-O19+L19,"") | Q19: =IF(AND(P19<>"",P19<>0,O19<>0,O19<>""),P19/O19,"") | T19: =T18/I16 -> #DIV/0!
F20: Конверсия план/факт | I20: =Центрум!I20 -> 0.1 | J20: =S48 | K20: =J20/I20 -> #VALUE! | L20: =IF(AND(K8<>0,I14<>0,I48<>0),(I48*S48+(I48/K8-I48)*I20)/(I48/K8),0) -> 0 | M20: =IF(AND(I20<>"",I20<>0,L20<>"",L20<>0),L20/I20,"") | N20: =IF(AND(J20<>0,J20<>"",I20<>0,I20<>""),L20-I20,"") | P20: =IF(AND(O20<>"",O20<>0,L20<>"",L20<>0),-O20+L20,"") | Q20: =IF(AND(P20<>"",P20<>0,O20<>0,O20<>""),P20/O20,"")
B22: Факт продаж за месяц | T22: % выполнения дневного плана | U22: Раcпределение плана по дням
B23: Дата | C23: День недели | D23: Выручка (руб) | E23: Кол-во единиц (шт.) | F23: Средняя стоимость изделия (руб.) | G23: Количество чеков (шт.) | H23: Средняя сумма чека (руб.) | I23: Трафик | J23: Длина чека (шт.) | K23: UNOde50 | L23: IS | M23: Agafi | N23: Kalliope | O23: Raganella | P23: CC/MP | Q23: Eva Rites | R23: Antura | S23: Конверсия (%) | U23: выручка, план | V23: кол-во ед, план | W23: Кол-во чеков, план | X23: выручка, скорректир.план | Y23: кол-во ед, скорр. план | Z23: кол-во чеков, скорр. план | AA23: Коэфф. Дня Недели | AB23: Специфика месяца
B24: 1 | C24: 2 | D24: 3 | E24: в | F24: 5 | G24: 6 | H24: 7 | I24: 8 | J24: 9 | K24: 10 | L24: 11 | M24: 12 | N24: 13 | O24: 14 | P24: 15 | Q24: 16 | R24: 17 | S24: 18 | U24: 1 | V24: 2 | W24: 3 | X24: 4 | Y24: 5 | Z24: 6 | AA24: 10 | AB24: 11
A25: 1 | J25: =IF(AND(G25<>"",G25<>0),E25/G25,"") | S25: =IF(AND(I25<>"",I25<>0),G25/I25,"") | T25: =D25/U25 -> #DIV/0! | U25: =$I$8*AA25*AB25/SUMPRODUCT($AB$25:$AB$55,$AA$25:$AA$55) -> #DIV/0! | V25: =$I$9*AA25*AB25/SUMPRODUCT($AB$25:$AB$55,$AA$25:$AA$55) -> #DIV/0! | W25: =IF($I$12="","",V25/$I$12) -> #DIV/0! | X25: =IF(AB25<>"",IF(D25<>"",D25,($I$8-SUM($X24:X$25))*AA25*AB25/SUMPRODUCT($AB25:$AB$55,$AA25:$AA$55)),"") | Y25: =IF(AB25<>"",IF(E25<>"",E25,($I$9-SUM($Y24:Y$25))*AA25*AB25/SUMPRODUCT($AB25:$AB$55,$AA25:$AA$55)),"") | Z25: =IF(AB25<>"",IF($I$12<>"",IF(G25<>"",G25,($I$9/$I$12-SUM($Z24:Z$25))*AA25*AB25/SUMPRODUCT($AB25:$AB$55,$AA25:$AA$55)),""),"")
A26: 2 | J26: =IF(AND(G26<>"",G26<>0),E26/G26,"") | S26: =IF(AND(I26<>"",I26<>0),G26/I26,"") | T26: =D26/U26 -> #DIV/0! | U26: =$I$8*AA26*AB26/SUMPRODUCT($AB$25:$AB$55,$AA$25:$AA$55) -> #DIV/0! | V26: =$I$9*AA26*AB26/SUMPRODUCT($AB$25:$AB$55,$AA$25:$AA$55) -> #DIV/0! | W26: =IF($I$12="","",V26/$I$12) -> #DIV/0! | X26: =IF(AB26<>"",IF(D26<>"",D26,($I$8-SUM($X$25:X25))*AA26*AB26/SUMPRODUCT($AB26:$AB$55,$AA26:$AA$55)),"") | Y26: =IF(AB26<>"",IF(E26<>"",E26,($I$9-SUM($Y$25:Y25))*AA26*AB26/SUMPRODUCT($AB26:$AB$55,$AA26:$AA$55)),"") | Z26: =IF(AB26<>"",IF($I$12<>"",IF(G26<>"",G26,($I$9/$I$12-SUM($Z$25:Z25))*AA26*AB26/SUMPRODUCT($AB26:$AB$55,$AA26:$AA$55)),""),"")
A27: 3 | E27: 0 | G27: 0 | J27: =IF(AND(G27<>"",G27<>0),E27/G27,"") | S27: =IF(AND(I27<>"",I27<>0),G27/I27,"") | T27: =D27/U27 -> #DIV/0! | U27: =$I$8*AA27*AB27/SUMPRODUCT($AB$25:$AB$55,$AA$25:$AA$55) -> #DIV/0! | V27: =$I$9*AA27*AB27/SUMPRODUCT($AB$25:$AB$55,$AA$25:$AA$55) -> #DIV/0! | W27: =IF($I$12="","",V27/$I$12) -> #DIV/0! | X27: =IF(AB27<>"",IF(D27<>"",D27,($I$8-SUM($X$25:X26))*AA27*AB27/SUMPRODUCT($AB27:$AB$55,$AA27:$AA$55)),"") | Y27: =IF(AB27<>"",IF(E27<>"",E27,($I$9-SUM($Y$25:Y26))*AA27*AB27/SUMPRODUCT($AB27:$AB$55,$AA27:$AA$55)),"") | Z27: =IF(AB27<>"",IF($I$12<>"",IF(G27<>"",G27,($I$9/$I$12-SUM($Z$25:Z26))*AA27*AB27/SUMPRODUCT($AB27:$AB$55,$AA27:$AA$55)),""),"")
A28: 4 | J28: =IF(AND(G28<>"",G28<>0),E28/G28,"") | S28: =IF(AND(I28<>"",I28<>0),G28/I28,"") | T28: =D28/U28 -> #DIV/0! | U28: =$I$8*AA28*AB28/SUMPRODUCT($AB$25:$AB$55,$AA$25:$AA$55) -> #DIV/0! | V28: =$I$9*AA28*AB28/SUMPRODUCT($AB$25:$AB$55,$AA$25:$AA$55) -> #DIV/0! | W28: =IF($I$12="","",V28/$I$12) -> #DIV/0! | X28: =IF(AB28<>"",IF(D28<>"",D28,($I$8-SUM($X$25:X27))*AA28*AB28/SUMPRODUCT($AB28:$AB$55,$AA28:$AA$55)),"") | Y28: =IF(AB28<>"",IF(E27<>"",E27,($I$9-SUM($Y$25:Y27))*AA28*AB28/SUMPRODUCT($AB28:$AB$55,$AA28:$AA$55)),"") | Z28: =IF(AB28<>"",IF($I$12<>"",IF(G28<>"",G28,($I$9/$I$12-SUM($Z$25:Z27))*AA28*AB28/SUMPRODUCT($AB28:$AB$55,$AA28:$AA$55)),""),"")
A29: 5 | J29: =IF(AND(G29<>"",G29<>0),E29/G29,"") | S29: =IF(AND(I29<>"",I29<>0),G29/I29,"") | T29: =D29/U29 -> #DIV/0! | U29: =$I$8*AA29*AB29/SUMPRODUCT($AB$25:$AB$55,$AA$25:$AA$55) -> #DIV/0! | V29: =$I$9*AA29*AB29/SUMPRODUCT($AB$25:$AB$55,$AA$25:$AA$55) -> #DIV/0! | W29: =IF($I$12="","",V29/$I$12) -> #DIV/0! | X29: =IF(AB29<>"",IF(D29<>"",D29,($I$8-SUM($X$25:X28))*AA29*AB29/SUMPRODUCT($AB29:$AB$55,$AA29:$AA$55)),"") | Y29: =IF(AB29<>"",IF(E29<>"",E29,($I$9-SUM($Y$25:Y28))*AA29*AB29/SUMPRODUCT($AB29:$AB$55,$AA29:$AA$55)),"") | Z29: =IF(AB29<>"",IF($I$12<>"",IF(G29<>"",G29,($I$9/$I$12-SUM($Z$25:Z28))*AA29*AB29/SUMPRODUCT($AB29:$AB$55,$AA29:$AA$55)),""),"")
J30: =IF(AND(G30<>"",G30<>0),E30/G30,"") | S30: =IF(AND(I30<>"",I30<>0),G30/I30,"") | T30: =D30/U30 -> #DIV/0! | U30: =$I$8*AA30*AB30/SUMPRODUCT($AB$25:$AB$55,$AA$25:$AA$55) -> #DIV/0! | V30: =$I$9*AA30*AB30/SUMPRODUCT($AB$25:$AB$55,$AA$25:$AA$55) -> #DIV/0! | W30: =IF($I$12="","",V30/$I$12) -> #DIV/0! | X30: =IF(AB30<>"",IF(D30<>"",D30,($I$8-SUM($X$25:X29))*AA30*AB30/SUMPRODUCT($AB30:$AB$55,$AA30:$AA$55)),"") | Y30: =IF(AB30<>"",IF(E30<>"",E30,($I$9-SUM($Y$25:Y29))*AA30*AB30/SUMPRODUCT($AB30:$AB$55,$AA30:$AA$55)),"") | Z30: =IF(AB30<>"",IF($I$12<>"",IF(G30<>"",G30,($I$9/$I$12-SUM($Z$25:Z29))*AA30*AB30/SUMPRODUCT($AB30:$AB$55,$AA30:$AA$55)),""),"")
J31: =IF(AND(G31<>"",G31<>0),E31/G31,"") | S31: =IF(AND(I31<>"",I31<>0),G31/I31,"") | T31: =D31/U31 -> #DIV/0! | U31: =$I$8*AA31*AB31/SUMPRODUCT($AB$25:$AB$55,$AA$25:$AA$55) -> #DIV/0! | V31: =$I$9*AA31*AB31/SUMPRODUCT($AB$25:$AB$55,$AA$25:$AA$55) -> #DIV/0! | W31: =IF($I$12="","",V31/$I$12) -> #DIV/0! | X31: =IF(AB31<>"",IF(D31<>"",D31,($I$8-SUM($X$25:X30))*AA31*AB31/SUMPRODUCT($AB31:$AB$55,$AA31:$AA$55)),"") | Y31: =IF(AB31<>"",IF(E31<>"",E31,($I$9-SUM($Y$25:Y30))*AA31*AB31/SUMPRODUCT($AB31:$AB$55,$AA31:$AA$55)),"") | Z31: =IF(AB31<>"",IF($I$12<>"",IF(G31<>"",G31,($I$9/$I$12-SUM($Z$25:Z30))*AA31*AB31/SUMPRODUCT($AB31:$AB$55,$AA31:$AA$55)),""),"")
J32: =IF(AND(G32<>"",G32<>0),E32/G32,"") | S32: =IF(AND(I32<>"",I32<>0),G32/I32,"") | T32: =D32/U32 -> #DIV/0! | U32: =$I$8*AA32*AB32/SUMPRODUCT($AB$25:$AB$55,$AA$25:$AA$55) -> #DIV/0! | V32: =$I$9*AA32*AB32/SUMPRODUCT($AB$25:$AB$55,$AA$25:$AA$55) -> #DIV/0! | W32: =IF($I$12="","",V32/$I$12) -> #DIV/0! | X32: =IF(AB32<>"",IF(D32<>"",D32,($I$8-SUM($X$25:X31))*AA32*AB32/SUMPRODUCT($AB32:$AB$55,$AA32:$AA$55)),"") | Y32: =IF(AB32<>"",IF(E32<>"",E32,($I$9-SUM($Y$25:Y31))*AA32*AB32/SUMPRODUCT($AB32:$AB$55,$AA32:$AA$55)),"") | Z32: =IF(AB32<>"",IF($I$12<>"",IF(G32<>"",G32,($I$9/$I$12-SUM($Z$25:Z31))*AA32*AB32/SUMPRODUCT($AB32:$AB$55,$AA32:$AA$55)),""),"")
J33: =IF(AND(G33<>"",G33<>0),E33/G33,"") | S33: =IF(AND(I33<>"",I33<>0),G33/I33,"") | T33: =D33/U33 -> #DIV/0! | U33: =$I$8*AA33*AB33/SUMPRODUCT($AB$25:$AB$55,$AA$25:$AA$55) -> #DIV/0! | V33: =$I$9*AA33*AB33/SUMPRODUCT($AB$25:$AB$55,$AA$25:$AA$55) -> #DIV/0! | W33: =IF($I$12="","",V33/$I$12) -> #DIV/0! | X33: =IF(AB33<>"",IF(D33<>"",D33,($I$8-SUM($X$25:X32))*AA33*AB33/SUMPRODUCT($AB33:$AB$55,$AA33:$AA$55)),"") | Y33: =IF(AB33<>"",IF(E33<>"",E33,($I$9-SUM($Y$25:Y32))*AA33*AB33/SUMPRODUCT($AB33:$AB$55,$AA33:$AA$55)),"") | Z33: =IF(AB33<>"",IF($I$12<>"",IF(G33<>"",G33,($I$9/$I$12-SUM($Z$25:Z32))*AA33*AB33/SUMPRODUCT($AB33:$AB$55,$AA33:$AA$55)),""),"")
J34: =IF(AND(G34<>"",G34<>0),E34/G34,"") | S34: =IF(AND(I34<>"",I34<>0),G34/I34,"") | T34: =D34/U34 -> #DIV/0! | U34: =$I$8*AA34*AB34/SUMPRODUCT($AB$25:$AB$55,$AA$25:$AA$55) -> #DIV/0! | V34: =$I$9*AA34*AB34/SUMPRODUCT($AB$25:$AB$55,$AA$25:$AA$55) -> #DIV/0! | W34: =IF($I$12="","",V34/$I$12) -> #DIV/0! | X34: =IF(AB34<>"",IF(D34<>"",D34,($I$8-SUM($X$25:X33))*AA34*AB34/SUMPRODUCT($AB34:$AB$55,$AA34:$AA$55)),"") | Y34: =IF(AB34<>"",IF(E34<>"",E34,($I$9-SUM($Y$25:Y33))*AA34*AB34/SUMPRODUCT($AB34:$AB$55,$AA34:$AA$55)),"") | Z34: =IF(AB34<>"",IF($I$12<>"",IF(G34<>"",G34,($I$9/$I$12-SUM($Z$25:Z33))*AA34*AB34/SUMPRODUCT($AB34:$AB$55,$AA34:$AA$55)),""),"")
J35: =IF(AND(G35<>"",G35<>0),E35/G35,"") | S35: =IF(AND(I35<>"",I35<>0),G35/I35,"") | T35: =D35/U35 -> #DIV/0! | U35: =$I$8*AA35*AB35/SUMPRODUCT($AB$25:$AB$55,$AA$25:$AA$55) -> #DIV/0! | V35: =$I$9*AA35*AB35/SUMPRODUCT($AB$25:$AB$55,$AA$25:$AA$55) -> #DIV/0! | W35: =IF($I$12="","",V35/$I$12) -> #DIV/0! | X35: =IF(AB35<>"",IF(D35<>"",D35,($I$8-SUM($X$25:X34))*AA35*AB35/SUMPRODUCT($AB35:$AB$55,$AA35:$AA$55)),"") | Y35: =IF(AB34<>"",IF(E34<>"",E34,($I$9-SUM($Y$25:Y33))*AA34*AB34/SUMPRODUCT($AB34:$AB$55,$AA34:$AA$55)),"") | Z35: =IF(AB34<>"",IF($I$12<>"",IF(G34<>"",G34,($I$9/$I$12-SUM($Z$25:Z33))*AA34*AB34/SUMPRODUCT($AB34:$AB$55,$AA34:$AA$55)),""),"")
J36: =IF(AND(G36<>"",G36<>0),E36/G36,"") | S36: =IF(AND(I36<>"",I36<>0),G36/I36,"") | T36: =D36/U36 -> #DIV/0! | U36: =$I$8*AA36*AB36/SUMPRODUCT($AB$25:$AB$55,$AA$25:$AA$55) -> #DIV/0! | V36: =$I$9*AA36*AB36/SUMPRODUCT($AB$25:$AB$55,$AA$25:$AA$55) -> #DIV/0! | W36: =IF($I$12="","",V36/$I$12) -> #DIV/0! | X36: =IF(AB36<>"",IF(D36<>"",D36,($I$8-SUM($X$25:X35))*AA36*AB36/SUMPRODUCT($AB36:$AB$55,$AA36:$AA$55)),"") | Y36: =IF(AB36<>"",IF(E36<>"",E36,($I$9-SUM($Y$25:Y35))*AA36*AB36/SUMPRODUCT($AB36:$AB$55,$AA36:$AA$55)),"") | Z36: =IF(AB36<>"",IF($I$12<>"",IF(G36<>"",G36,($I$9/$I$12-SUM($Z$25:Z35))*AA36*AB36/SUMPRODUCT($AB36:$AB$55,$AA36:$AA$55)),""),"")
J37: =IF(AND(G37<>"",G37<>0),E37/G37,"") | S37: =IF(AND(I37<>"",I37<>0),G37/I37,"") | T37: =D37/U37 -> #DIV/0! | U37: =$I$8*AA37*AB37/SUMPRODUCT($AB$25:$AB$55,$AA$25:$AA$55) -> #DIV/0! | V37: =$I$9*AA37*AB37/SUMPRODUCT($AB$25:$AB$55,$AA$25:$AA$55) -> #DIV/0! | W37: =IF($I$12="","",V37/$I$12) -> #DIV/0! | X37: =IF(AB37<>"",IF(D37<>"",D37,($I$8-SUM($X$25:X36))*AA37*AB37/SUMPRODUCT($AB37:$AB$55,$AA37:$AA$55)),"") | Y37: =IF(AB37<>"",IF(E37<>"",E37,($I$9-SUM($Y$25:Y36))*AA37*AB37/SUMPRODUCT($AB37:$AB$55,$AA37:$AA$55)),"") | Z37: =IF(AB37<>"",IF($I$12<>"",IF(G37<>"",G37,($I$9/$I$12-SUM($Z$25:Z36))*AA37*AB37/SUMPRODUCT($AB37:$AB$55,$AA37:$AA$55)),""),"")
J38: =IF(AND(G38<>"",G38<>0),E38/G38,"") | S38: =IF(AND(I38<>"",I38<>0),G38/I38,"") | T38: =D38/U38 -> #DIV/0! | U38: =$I$8*AA38*AB38/SUMPRODUCT($AB$25:$AB$46,$AA$25:$AA$46) -> #DIV/0! | V38: =$I$9*AA38*AB38/SUMPRODUCT($AB$25:$AB$46,$AA$25:$AA$46) -> #DIV/0! | W38: =IF($I$12="","",V38/$I$12) -> #DIV/0! | X38: =IF(AB38<>"",IF(D38<>"",D38,($I$8-SUM($X$25:X37))*AA38*AB38/SUMPRODUCT($AB38:$AB$55,$AA38:$AA$55)),"") | Y38: =IF(AB38<>"",IF(E38<>"",E38,($I$9-SUM($Y$25:Y37))*AA38*AB38/SUMPRODUCT($AB38:$AB$55,$AA38:$AA$55)),"") | Z38: =IF(AB38<>"",IF($I$12<>"",IF(G38<>"",G38,($I$9/$I$12-SUM($Z$25:Z37))*AA38*AB38/SUMPRODUCT($AB38:$AB$55,$AA38:$AA$55)),""),"")
J39: =IF(AND(G39<>"",G39<>0),E39/G39,"") | S39: =IF(AND(I39<>"",I39<>0),G39/I39,"") | T39: =D39/U39 -> #DIV/0! | U39: =$I$8*AA39*AB39/SUMPRODUCT($AB$25:$AB$46,$AA$25:$AA$46) -> #DIV/0! | V39: =$I$9*AA39*AB39/SUMPRODUCT($AB$25:$AB$46,$AA$25:$AA$46) -> #DIV/0! | W39: =IF($I$12="","",V39/$I$12) -> #DIV/0! | X39: =IF(AB39<>"",IF(D39<>"",D39,($I$8-SUM($X$25:X38))*AA39*AB39/SUMPRODUCT($AB39:$AB$47,$AA39:$AA$47)),"") | Y39: =IF(AB39<>"",IF(E39<>"",E39,($I$9-SUM($Y$25:Y38))*AA39*AB39/SUMPRODUCT($AB39:$AB$55,$AA39:$AA$55)),"") | Z39: =IF(AB39<>"",IF($I$12<>"",IF(G39<>"",G39,($I$9/$I$12-SUM($Z$25:Z38))*AA39*AB39/SUMPRODUCT($AB39:$AB$55,$AA39:$AA$55)),""),"")
J40: =IF(AND(G40<>"",G40<>0),E40/G40,"") | S40: =IF(AND(I40<>"",I40<>0),G40/I40,"") | T40: =D40/U40 -> #DIV/0! | U40: =$I$8*AA40*AB40/SUMPRODUCT($AB$25:$AB$46,$AA$25:$AA$46) -> #DIV/0! | V40: =$I$9*AA40*AB40/SUMPRODUCT($AB$25:$AB$46,$AA$25:$AA$46) -> #DIV/0! | W40: =IF($I$12="","",V40/$I$12) -> #DIV/0! | X40: =IF(AB40<>"",IF(D40<>"",D40,($I$8-SUM($X$25:X39))*AA40*AB40/SUMPRODUCT($AB40:$AB$46,$AA40:$AA$46)),"") | Y40: =IF(AB40<>"",IF(E40<>"",E40,($I$9-SUM($Y$25:Y39))*AA40*AB40/SUMPRODUCT($AB40:$AB$46,$AA40:$AA$46)),"") | Z40: =IF(AB40<>"",IF($I$12<>"",IF(G40<>"",G40,($I$9/$I$12-SUM($Z$25:Z39))*AA40*AB40/SUMPRODUCT($AB40:$AB$55,$AA40:$AA$55)),""),"")
B41: 46079 | C41: чт | D41: 7420 | E41: 1 | F41: =IF(AND(E41<>"",E41<>0),D41/E41,"") -> 7420 | G41: 1 | H41: =IF(AND(G41<>"",G41<>0),D41/G41,"") -> 7420 | J41: =IF(AND(G41<>"",G41<>0),E41/G41,"") -> 1 | S41: =IF(AND(I41<>"",I41<>0),G41/I41,"") | T41: =D41/U41 -> #DIV/0! | U41: =$I$8*AA41*AB41/SUMPRODUCT($AB$25:$AB$46,$AA$25:$AA$46) -> #DIV/0! | V41: =$I$9*AA41*AB41/SUMPRODUCT($AB$25:$AB$46,$AA$25:$AA$46) -> #DIV/0! | W41: =IF($I$12="","",V41/$I$12) -> #DIV/0! | X41: =IF(AB41<>"",IF(D41<>"",D41,($I$8-SUM($X$25:X40))*AA41*AB41/SUMPRODUCT($AB41:$AB$46,$AA41:$AA$46)),"") | Y41: =IF(AB41<>"",IF(E41<>"",E41,($I$9-SUM($Y$25:Y40))*AA41*AB41/SUMPRODUCT($AB41:$AB$46,$AA41:$AA$46)),"") | Z41: =IF(AB41<>"",IF($I$12<>"",IF(G41<>"",G41,($I$9/$I$12-SUM($Z$25:Z40))*AA41*AB41/SUMPRODUCT($AB41:$AB$55,$AA41:$AA$55)),""),"")
F42: =IF(AND(E42<>"",E42<>0),D42/E42,"") | H42: =IF(AND(G42<>"",G42<>0),D42/G42,"") | J42: =IF(AND(G42<>"",G42<>0),E42/G42,"") | S42: =IF(AND(I42<>"",I42<>0),G42/I42,"") | T42: =D42/U42 -> #DIV/0! | U42: =$I$8*AA42*AB42/SUMPRODUCT($AB$25:$AB$46,$AA$25:$AA$46) -> #DIV/0! | V42: =$I$9*AA42*AB42/SUMPRODUCT($AB$25:$AB$46,$AA$25:$AA$46) -> #DIV/0! | W42: =IF($I$12="","",V42/$I$12) -> #DIV/0! | X42: =IF(AB42<>"",IF(D42<>"",D42,($I$8-SUM($X$25:X41))*AA42*AB42/SUMPRODUCT($AB42:$AB$46,$AA42:$AA$46)),"") | Y42: =IF(AB42<>"",IF(E42<>"",E42,($I$9-SUM($Y$25:Y41))*AA42*AB42/SUMPRODUCT($AB42:$AB$46,$AA42:$AA$46)),"") | Z42: =IF(AB42<>"",IF($I$12<>"",IF(G42<>"",G42,($I$9/$I$12-SUM($Z$25:Z41))*AA42*AB42/SUMPRODUCT($AB42:$AB$46,$AA42:$AA$46)),""),"")
F43: =IF(AND(E43<>"",E43<>0),D43/E43,"") | H43: =IF(AND(G43<>"",G43<>0),D43/G43,"") | J43: =IF(AND(G43<>"",G43<>0),E43/G43,"") | S43: =IF(AND(I43<>"",I43<>0),G43/I43,"") | T43: =D43/U43 -> #DIV/0! | U43: =$I$8*AA43*AB43/SUMPRODUCT($AB$25:$AB$46,$AA$25:$AA$46) -> #DIV/0! | V43: =$I$9*AA43*AB43/SUMPRODUCT($AB$25:$AB$46,$AA$25:$AA$46) -> #DIV/0! | W43: =IF($I$12="","",V43/$I$12) -> #DIV/0! | X43: =IF(AB43<>"",IF(D43<>"",D43,($I$8-SUM($X$25:X42))*AA43*AB43/SUMPRODUCT($AB43:$AB$46,$AA43:$AA$46)),"") | Y43: =IF(AB43<>"",IF(E43<>"",E43,($I$9-SUM($Y$25:Y42))*AA43*AB43/SUMPRODUCT($AB43:$AB$46,$AA43:$AA$46)),"") | Z43: =IF(AB43<>"",IF($I$12<>"",IF(G43<>"",G43,($I$9/$I$12-SUM($Z$25:Z42))*AA43*AB43/SUMPRODUCT($AB43:$AB$46,$AA43:$AA$46)),""),"")
F44: =IF(AND(E44<>"",E44<>0),D44/E44,"") | H44: =IF(AND(G44<>"",G44<>0),D44/G44,"") | J44: =IF(AND(G44<>"",G44<>0),E44/G44,"") | S44: =IF(AND(I44<>"",I44<>0),G44/I44,"") | T44: =D44/U44 -> #DIV/0! | U44: =$I$8*AA44*AB44/SUMPRODUCT($AB$25:$AB$46,$AA$25:$AA$46) -> #DIV/0! | V44: =$I$9*AA44*AB44/SUMPRODUCT($AB$25:$AB$46,$AA$25:$AA$46) -> #DIV/0! | W44: =IF($I$12="","",V44/$I$12) -> #DIV/0! | X44: =IF(AB44<>"",IF(D44<>"",D44,($I$8-SUM($X$25:X43))*AA44*AB44/SUMPRODUCT($AB44:$AB$46,$AA44:$AA$46)),"") | Y44: =IF(AB44<>"",IF(E44<>"",E44,($I$9-SUM($Y$25:Y43))*AA44*AB44/SUMPRODUCT($AB44:$AB$46,$AA44:$AA$46)),"") | Z44: =IF(AB44<>"",IF($I$12<>"",IF(G44<>"",G44,($I$9/$I$12-SUM($Z$25:Z43))*AA44*AB44/SUMPRODUCT($AB44:$AB$46,$AA44:$AA$46)),""),"")
F45: =IF(AND(E45<>"",E45<>0),D45/E45,"") | H45: =IF(AND(G45<>"",G45<>0),D45/G45,"") | J45: =IF(AND(G45<>"",G45<>0),E45/G45,"") | S45: =IF(AND(I45<>"",I45<>0),G45/I45,"") | T45: =D45/U45 -> #DIV/0! | U45: =$I$8*AA45*AB45/SUMPRODUCT($AB$25:$AB$46,$AA$25:$AA$46) -> #DIV/0! | V45: =$I$9*AA45*AB45/SUMPRODUCT($AB$25:$AB$46,$AA$25:$AA$46) -> #DIV/0! | W45: =IF($I$12="","",V45/$I$12) -> #DIV/0! | X45: =IF(AB45<>"",IF(D45<>"",D45,($I$8-SUM($X$25:X44))*AA45*AB45/SUMPRODUCT($AB45:$AB$46,$AA45:$AA$46)),"") | Y45: =IF(AB45<>"",IF(E45<>"",E45,($I$9-SUM($Y$25:Y44))*AA45*AB45/SUMPRODUCT($AB45:$AB$46,$AA45:$AA$46)),"") | Z45: =IF(AB45<>"",IF($I$12<>"",IF(G45<>"",G45,($I$9/$I$12-SUM($Z$25:Z44))*AA45*AB45/SUMPRODUCT($AB45:$AB$46,$AA45:$AA$46)),""),"")
J46: =IF(AND(G46<>"",G46<>0),E46/G46,"") | S46: =IF(AND(I46<>"",I46<>0),G46/I46,"") | T46: =D46/U46 -> #DIV/0! | U46: =$I$8*AA46*AB46/SUMPRODUCT($AB$25:$AB$46,$AA$25:$AA$46) -> #DIV/0! | V46: =$I$9*AA46*AB46/SUMPRODUCT($AB$25:$AB$46,$AA$25:$AA$46) -> #DIV/0! | W46: =IF($I$12="","",V46/$I$12) -> #DIV/0! | X46: =IF(AB46<>"",IF(D46<>"",D46,($I$8-SUM($X$25:X45))*AA46*AB46/SUMPRODUCT($AB46:$AB$46,$AA46:$AA$46)),"") | Y46: =IF(AB46<>"",IF(E46<>"",E46,($I$9-SUM($Y$25:Y39))*AA46*AB46/SUMPRODUCT($AB46:$AB$46,$AA46:$AA$46)),"") | Z46: =IF(AB46<>"",IF($I$12<>"",IF(G46<>"",G46,($I$9/$I$12-SUM($Z$25:Z39))*AA46*AB46/SUMPRODUCT($AB46:$AB$46,$AA46:$AA$46)),""),"")
J47: =IF(AND(G47<>"",G47<>0),E47/G47,"") | S47: =IF(AND(I47<>"",I47<>0),G47/I47,"") | T47: =D47/U47 -> #DIV/0! | U47: =$I$8*AA47*AB47/SUMPRODUCT($AB$25:$AB$46,$AA$25:$AA$46) -> #DIV/0! | V47: =$I$9*AA47*AB47/SUMPRODUCT($AB$25:$AB$46,$AA$25:$AA$46) -> #DIV/0! | W47: =IF($I$12="","",V47/$I$12) -> #DIV/0! | X47: =IF(AB47<>"",IF(D47<>"",D47,($I$8-SUM($X$25:X46))*AA47*AB47/SUMPRODUCT($AB$47:$AB47,$AA$47:$AA47)),"") | Y47: =IF(AB47<>"",IF(E47<>"",E47,($I$9-SUM(#REF!))*AA47*AB47/SUMPRODUCT($AB$47:$AB47,$AA$47:$AA47)),"") | Z47: =IF(AB47<>"",IF($I$12<>"",IF(G47<>"",G47,($I$9/$I$12-SUM(#REF!))*AA47*AB47/SUMPRODUCT($AB$47:$AB47,$AA$47:$AA47)),""),"")
B48: итого | D48: =SUM(D25:D47) -> 7420 | E48: =SUM(E25:E47) -> 1 | F48: =IF(AND(E48<>"",E48<>0),D48/E48,"") -> 7420 | G48: =SUM(G25:G47) -> 1 | H48: =IF(AND(G48<>"",G48<>0),D48/G48,"") -> 7420 | I48: =SUM(I25:I47)*0.8 -> 0 | J48: =IF(AND(G48<>"",G48<>0),E48/G48,"") -> 1 | K48: =SUM(K25:K47) -> 0 | L48: =SUM(L25:L47) -> 0 | M48: =SUM(M25:M47) -> 0 | N48: =SUM(N25:N47) -> 0 | O48: =SUM(O25:O47) -> 0 | P48: =SUM(P25:P47) -> 0 | Q48: =SUM(Q25:Q47) -> 0 | R48: =SUM(R25:R47) -> 0 | S48: =IF(AND(I48<>"",I48<>0),G48/I48,"") | T48: =D48/U48 -> #DIV/0! | U48: =SUM(U25:U47) -> #DIV/0! | V48: =SUM(V25:V47) -> #DIV/0! | W48: =SUM(W25:W47) -> #DIV/0! | X48: =SUM(X25:X47) -> 0 | Y48: =SUM(Y25:Y47) -> 0 | Z48: =SUM(Z25:Z47) -> 0
D49: =SUMIF(D25:D47,"",U25:U47)+D48 -> #DIV/0!

Sheet Козлова В. Э.
B1: =TODAY()-1 -> 46171
B2: (отчетная дата) | J2: ЕЖЕДНЕВНЫЙ ОТЧЕТ О ПРОДАЖАХ
B3: Осталось до выполнения плана!!! | J3: =График!B26 -> Козлова Валерия
C4: =I8-D49 -> 182641.99 | E4: =IF(I8<>0,C4/I8,0) -> 0.73562319
F6: Целевые показатели
F7: Показатель | I7: План | J7: Факт | K7: % выполнения | L7: Прогноз выполнения | M7: % выполнения по прогнозу | N7: Отклонение | O7: Факт аналогичного месяца прошлого года | P7: Отклонение LFL
F8: Выручка | I8: =Центрум!I8/График!AJ29*График!AJ26 -> 248281.99 | J8: =D49 -> 65640 | K8: =IF(AND(I8<>"",I8<>0,J8<>""),J8/I8,"") -> 0.26437681 | L8: =IF(SUMIF($D$25:$D$47,">=0",$V$25:$V$47)<>0,I8*D49/SUMIF($D$25:$D$47,">=0",$V$25:$V$47),0) -> 76567.924 | M8: =L8/I8 -> 0.30839097 | N8: =IF(AND(J8<>0,J8<>"",I8<>0,I8<>""),L8-I8,"") -> -171714.06 | P8: =IF(AND(O8<>"",O8<>0,L8<>"",L8<>0),-O8+L8,"") | Q8: =IF(AND(P8<>"",P8<>0,O8<>0,O8<>""),P8/O8,"")
F9: Кол-во изделий | I9: =I8/I11 -> 34.198621 | J9: =E49 -> 8 | K9: =IF(AND(I9<>"",I9<>0,J9<>""),J9/I9,"") -> 0.23392756 | L9: =IF(SUMIF($E$25:$E$47,">=0",$W$25:$W$47)<>0,I9*E49/SUMIF($E$25:$E$47,">=0",$W$25:$W$47),0) -> 9.3318615 | M9: =IF(AND(I9<>"",I9<>0,L9<>"",L9<>0),L9/I9,"") -> 0.27287245 | N9: =IF(AND(J9<>0,J9<>"",I9<>0,I9<>""),L9-I9,"") -> -24.866759 | O9: =O8/O11 -> #DIV/0! | P9: =IF(AND(O9<>"",O9<>0,L9<>"",L9<>0),-O9+L9,"") -> #DIV/0! | Q9: =IF(AND(P9<>"",P9<>0,O9<>0,O9<>""),P9/O9,"") -> #DIV/0!
F10: Средний чек | I10: =I11*I12 -> 13358.4 | J10: =H49 -> 10940 | K10: =IF(AND(I10<>"",I10<>0,J10<>""),J10/I10,"") -> 0.81896035 | L10: =J10 -> 10940 | M10: =IF(AND(I10<>"",I10<>0,L10<>"",L10<>0),L10/I10,"") -> 0.81896035 | N10: =IF(AND(J10<>0,J10<>"",I10<>0,I10<>""),L10-I10,"") -> -2418.4 | O10: =O11*O12 -> 0 | P10: =IF(AND(O10<>"",O10<>0,L10<>"",L10<>0),-O10+L10,"") | Q10: =IF(AND(P10<>"",P10<>0,O10<>0,O10<>""),P10/O10,"")
F11: Средняя стоимость изделия | I11: =Центрум!I11 -> 7260 | J11: =F49 -> 8205 | K11: =IF(AND(I11<>"",I11<>0,J11<>""),J11/I11,"") -> 1.1301653 | L11: =J11 -> 8205 | M11: =IF(AND(I11<>"",I11<>0,L11<>"",L11<>0),L11/I11,"") -> 1.1301653 | N11: =IF(AND(J11<>0,J11<>"",I11<>0,I11<>""),L11-I11,"") -> 945 | P11: =IF(AND(O11<>"",O11<>0,L11<>"",L11<>0),-O11+L11,"") | Q11: =IF(AND(P11<>"",P11<>0,O11<>0,O11<>""),P11/O11,"")
F12: Длина чека | I12: =Центрум!I12 -> 1.84 | J12: =J49 -> 1.3333333 | K12: =IF(AND(I12<>"",I12<>0,J12<>""),J12/I12,"") -> 0.72463768 | L12: =J12 -> 1.3333333 | M12: =IF(AND(I12<>"",I12<>0,L12<>"",L12<>0),L12/I12,"") -> 0.72463768 | N12: =IF(AND(J12<>0,J12<>"",I12<>0,I12<>""),L12-I12,"") -> -0.50666667 | P12: =IF(AND(O12<>"",O12<>0,L12<>"",L12<>0),-O12+L12,"") | Q12: =IF(AND(P12<>"",P12<>0,O12<>0,O12<>""),P12/O12,"")
F13: Кол-во чеков | I13: =IF(I12<>0,I9/I12,"") -> 18.586207 | J13: =G49 -> 6 | K13: =IF(AND(I13<>"",I13<>0,J13<>""),J13/I13,"") -> 0.32282004 | L13: =IF(SUMIF($G$25:$G$47,">=0",$X$25:$X$47)<>0,I13*G49/SUMIF($G$25:$G$47,">=0",$X$25:$X$47),"") -> 6.9988961 | M13: =IF(AND(I13<>"",I13<>0,L13<>"",L13<>0),L13/I13,"") -> 0.37656398 | N13: =IF(AND(J13<>0,J13<>"",I13<>0,I13<>""),L13-I13,"") -> -11.587311 | P13: =IF(AND(O13<>"",O13<>0,L13<>"",L13<>0),-O13+L13,"") | Q13: =IF(AND(P13<>"",P13<>0,O13<>0,O13<>""),P13/O13,"")
F14: Кол-во смен план/отработано | I14: =График!AI26 -> 7 | J14: 7 | K14: =IF(AND(I14<>"",I14<>0,J14<>""),J14/I14,"") -> 1 | L14: =IF(SUMIF($D$25:$D$47,">=0",$V$25:$V$47),I49*I8/SUMIF($D$25:$D$47,">=0",$V$25:$V$47),"") -> 146.51023 | N14: =IF(AND(J14<>0,J14<>"",I14<>0,I14<>""),L14-I14,"") -> 139.51023 | P14: =IF(AND(O14<>"",O14<>0,L14<>"",L14<>0),-O14+L14,"") | Q14: =IF(AND(P14<>"",P14<>0,O14<>0,O14<>""),P14/O14,"")
F15: Средние продажи в смену | I15: =Центрум!I15/2 -> 33396 | J15: =J8/J14 -> 9377.1429 | K15: =IF(AND(I15<>"",I15<>0,J15<>""),J15/I15,"") -> 0.28078641 | L15: =J15 -> 9377.1429 | M15: =IF(AND(I15<>"",I15<>0,L15<>"",L15<>0),L15/I15,"") -> 0.28078641 | N15: =IF(AND(J15<>0,J15<>"",I15<>0,I15<>""),L15-I15,"") -> -24018.857 | P15: =IF(AND(O15<>"",O15<>0,L15<>"",L15<>0),-O15+L15,"") | Q15: =IF(AND(P15<>"",P15<>0,O15<>0,O15<>""),P15/O15,"")
F16: Отставание/Перевыполнение | J16: =J8-I15*J14 -> -168132 | K16: =IF(AND(I16<>"",I16<>0,J16<>""),J16/I16,"") | L16: =J16 -> -168132 | M16: =IF(AND(I16<>"",I16<>0,L16<>"",L16<>0),L16/I16,"") | N16: =IF(AND(J16<>0,J16<>"",I16<>0,I16<>""),L16-I16,"") | P16: =IF(AND(O16<>"",O16<>0,L16<>"",L16<>0),-O16+L16,"") | Q16: =IF(AND(P16<>"",P16<>0,O16<>0,O16<>""),P16/O16,"") | U16: Подарочные сертификаты
F17: Трафик | I17: =Центрум!I17/График!AJ29*График!AJ26 -> 185.86207 | J17: =I49 -> 125.6 | K17: =IF(AND(I17<>"",I17<>0,J17<>""),J17/I17,"") -> 0.67576994 | L17: =J17/J14*I14 -> 125.6 | M17: =IF(AND(I17<>"",I17<>0,L17<>"",L17<>0),L17/I17,"") -> 0.67576994 | N17: =IF(AND(J17<>0,J17<>"",I17<>0,I17<>""),L17-I17,"") -> -60.262069 | P17: =IF(AND(O17<>"",O17<>0,L17<>"",L17<>0),-O17+L17,"") | Q17: =IF(AND(P17<>"",P17<>0,O17<>0,O17<>""),P17/O17,"")
K18: =IF(AND(I18<>"",I18<>0,J18<>""),J18/I18,"") | L18: =J18 -> 0 | M18: =IF(AND(I18<>"",I18<>0,L18<>"",L18<>0),L18/I18,"") | N18: =IF(AND(J18<>0,J18<>"",I18<>0,I18<>""),L18-I18,"") | O18: 0 | P18: =IF(AND(O18<>"",O18<>0,L18<>"",L18<>0),-O18+L18,"") | Q18: =IF(AND(P18<>"",P18<>0,O18<>0,O18<>""),P18/O18,"")
J19: =P49 -> 0 | K19: =IF(AND(I19<>"",I19<>0,J19<>""),J19/I19,"") | L19: =J19 -> 0 | M19: =IF(AND(I19<>"",I19<>0,L19<>"",L19<>0),L19/I19,"") | N19: =IF(AND(J19<>0,J19<>"",I19<>0,I19<>""),L19-I19,"") | O19: 0 | P19: =IF(AND(O19<>"",O19<>0,L19<>"",L19<>0),-O19+L19,"") | Q19: =IF(AND(P19<>"",P19<>0,O19<>0,O19<>""),P19/O19,"") | U19: =U18/I16 -> #DIV/0!
F20: Конверсия план/факт | I20: =Центрум!I20 -> 0.1 | J20: =T49 -> 0.047770701 | K20: =J20/I20 -> 0.47770701 | L20: =IF(AND(K8<>0,I14<>0,I49<>0),(I49*T49+(I49/K8-I49)*I20)/(I49/K8),0) -> 0.086191784 | M20: =IF(AND(I20<>"",I20<>0,L20<>"",L20<>0),L20/I20,"") -> 0.86191784 | N20: =IF(AND(J20<>0,J20<>"",I20<>0,I20<>""),L20-I20,"") -> -0.013808216 | P20: =IF(AND(O20<>"",O20<>0,L20<>"",L20<>0),-O20+L20,"") | Q20: =IF(AND(P20<>"",P20<>0,O20<>0,O20<>""),P20/O20,"")
B22: Факт продаж за месяц | U22: % выполнения дневного плана | V22: Раcпределение плана по дням
B23: Дата | C23: День недели | D23: Выручка (руб) | E23: Кол-во единиц (шт.) | F23: Средняя стоимость изделия (руб.) | G23: Количество чеков (шт.) | H23: Средняя сумма чека (руб.) | I23: Трафик | J23: Длина чека (шт.) | K23: UNOde50 | L23: IS | M23: Agafi | N23: Kalliope | O23: Raganella | P23: CC/MP | Q23: Eva Rites | R23: Antura | S23: SALE | T23: Конверсия (%) | V23: выручка, план | W23: кол-во ед, план | X23: Кол-во чеков, план | Y23: выручка, скорректир.план | Z23: кол-во ед, скорр. план | AA23: кол-во чеков, скорр. план | AB23: Коэфф. Дня Недели | AC23: Специфика месяца
B24: 1 | C24: 2 | D24: 3 | E24: в | F24: 5 | G24: 6 | H24: 7 | I24: 8 | J24: 9 | K24: 10 | L24: 11 | M24: 12 | N24: 13 | O24: 14 | P24: 15 | Q24: 16 | R24: 17 | T24: 18 | V24: 1 | W24: 2 | X24: 3 | Y24: 4 | Z24: 5 | AA24: 6 | AB24: 10 | AC24: 11
A25: 1 | B25: 46054 | C25: вс | D25: 14786 | E25: 2 | F25: =IF(AND(E25<>"",E25<>0),D25/E25,"") -> 7393 | G25: 2 | H25: =IF(AND(G25<>"",G25<>0),D25/G25,"") -> 7393 | I25: 28 | J25: =IF(AND(G25<>"",G25<>0),E25/G25,"") -> 1 | T25: =IF(AND(I25<>"",I25<>0),G25/I25,"") -> 0.071428571 | U25: =D25/V25 -> 440.51541 | V25: =$I$8*AB25*AC25/SUMPRODUCT($AB$25:$AB$55,$AA$25:$AA$55) -> 33.565227 | W25: =$I$9*AB25*AC25/SUMPRODUCT($AB$25:$AB$55,$AA$25:$AA$55) -> 0.0046233095 | X25: =IF($I$12="","",W25/$I$12) -> 0.0025126682 | Y25: =IF(AC25<>"",IF(E25<>"",E25,($I$8-SUM($X24:Y$25))*AB25*AC25/SUMPRODUCT($AB25:$AB$48,$AA25:$AA$48)),"") -> 2 | Z25: =IF(AC25<>"",IF(F25<>"",F25,($I$9-SUM($Y24:Z$25))*AB25*AC25/SUMPRODUCT($AB25:$AB$55,$AA25:$AA$55)),"") -> 7393 | AA25: =IF(AC25<>"",IF($I$12<>"",IF(H25<>"",H25,($I$9/$I$12-SUM($Z24:AA$25))*AB25*AC25/SUMPRODUCT($AB25:$AB$55,$AA25:$AA$55)),""),"") -> 7393 | AB25: 1 | AC25: 1
A26: 2 | B26: 46055 | C26: пн | D26: 6492 | E26: 1 | F26: =IF(AND(E26<>"",E26<>0),D26/E26,"") -> 6492 | G26: 1 | H26: =IF(AND(G26<>"",G26<>0),D26/G26,"") -> 6492 | I26: 17 | J26: =IF(AND(G26<>"",G26<>0),E26/G26,"") -> 1 | T26: =IF(AND(I26<>"",I26<>0),G26/I26,"") -> 0.058823529 | U26: =D26/V26 -> 0.18303382 | V26: =$I$8*AB26*AC26/SUMPRODUCT($AC$25:$AC$56,$AB$25:$AB$56) -> 35468.855 | W26: =$I$9*AB26*AC26/SUMPRODUCT($AC$25:$AC$56,$AB$25:$AB$56) -> 4.8855172 | X26: =IF($I$12="","",W26/$I$12) -> 2.6551724 | Y26: =IF(AC26<>"",IF(D26<>"",D26,($I$8-SUM($Y$25:Y25))*AB26*AC26/SUMPRODUCT($AC26:$AC$56,$AB26:$AB$56)),"") -> 6492 | Z26: =IF(AC26<>"",IF(E26<>"",E26,($I$9-SUM($Z$25:Z25))*AB26*AC26/SUMPRODUCT($AC26:$AC$56,$AB26:$AB$56)),"") -> 1 | AA26: =IF(AC26<>"",IF($I$12<>"",IF(G26<>"",G26,($I$9/$I$12-SUM($AA$25:AA25))*AB26*AC26/SUMPRODUCT($AC26:$AC$56,$AB26:$AB$56)),""),"") -> 1 | AB26: 1 | AC26: 1
A27: 3 | B27: 46057 | C27: ср | D27: 39419 | E27: 4 | F27: =IF(AND(E27<>"",E27<>0),D27/E27,"") -> 9854.75 | G27: 2 | H27: =IF(AND(G27<>"",G27<>0),D27/G27,"") -> 19709.5 | I27: 18 | J27: =IF(AND(G27<>"",G27<>0),E27/G27,"") -> 2 | R27: 35593 | T27: =IF(AND(I27<>"",I27<>0),G27/I27,"") -> 0.11111111 | U27: =D27/V27 -> 1.1113694 | V27: =$I$8*AB27*AC27/SUMPRODUCT($AC$25:$AC$56,$AB$25:$AB$56) -> 35468.855 | W27: =$I$9*AB27*AC27/SUMPRODUCT($AC$25:$AC$56,$AB$25:$AB$56) -> 4.8855172 | X27: =IF($I$12="","",W27/$I$12) -> 2.6551724 | Y27: =IF(AC27<>"",IF(D27<>"",D27,($I$8-SUM($Y$25:Y26))*AB27*AC27/SUMPRODUCT($AC27:$AC$56,$AB27:$AB$56)),"") -> 39419 | Z27: =IF(AC27<>"",IF(E27<>"",E27,($I$9-SUM($Z$25:Z26))*AB27*AC27/SUMPRODUCT($AC27:$AC$56,$AB27:$AB$56)),"") -> 4 | AA27: =IF(AC27<>"",IF($I$12<>"",IF(G27<>"",G27,($I$9/$I$12-SUM($AA$25:AA26))*AB27*AC27/SUMPRODUCT($AC27:$AC$56,$AB27:$AB$56)),""),"") -> 2 | AB27: 1 | AC27: 1
A28: 4 | B28: 46058 | C28: чт | D28: 4943 | E28: 1 | F28: =IF(AND(E28<>"",E28<>0),D28/E28,"") -> 4943 | G28: 1 | H28: =IF(AND(G28<>"",G28<>0),D28/G28,"") -> 4943 | I28: 17 | J28: =IF(AND(G28<>"",G28<>0),E28/G28,"") -> 1 | T28: =IF(AND(I28<>"",I28<>0),G28/I28,"") -> 0.058823529 | U28: =D28/V28 -> 0.1393617 | V28: =$I$8*AB28*AC28/SUMPRODUCT($AC$25:$AC$56,$AB$25:$AB$56) -> 35468.855 | W28: =$I$9*AB28*AC28/SUMPRODUCT($AC$25:$AC$56,$AB$25:$AB$56) -> 4.8855172 | X28: =IF($I$12="","",W28/$I$12) -> 2.6551724 | Y28: =IF(AC28<>"",IF(D28<>"",D28,($I$8-SUM($Y$25:Y27))*AB28*AC28/SUMPRODUCT($AC28:$AC$56,$AB28:$AB$56)),"") -> 4943 | Z28: =IF(AC28<>"",IF(E28<>"",E28,($I$9-SUM($Z$25:Z27))*AB28*AC28/SUMPRODUCT($AC28:$AC$56,$AB28:$AB$56)),"") -> 1 | AA28: =IF(AC28<>"",IF($I$12<>"",IF(G28<>"",G28,($I$9/$I$12-SUM($AA$25:AA27))*AB28*AC28/SUMPRODUCT($AC28:$AC$56,$AB28:$AB$56)),""),"") -> 1 | AB28: 1 | AC28: 1
A29: 5 | B29: 46060 | C29: сб | D29: 0 | E29: 0 | F29: =IF(AND(E29<>"",E29<>0),D29/E29,"") | G29: 0 | H29: =IF(AND(G29<>"",G29<>0),D29/G29,"") | I29: 28 | J29: =IF(AND(G29<>"",G29<>0),E29/G29,"") | T29: =IF(AND(I29<>"",I29<>0),G29/I29,"") -> 0 | U29: =D29/V29 -> 0 | V29: =$I$8*AB29*AC29/SUMPRODUCT($AC$25:$AC$56,$AB$25:$AB$56) -> 35468.855 | W29: =$I$9*AB29*AC29/SUMPRODUCT($AC$25:$AC$56,$AB$25:$AB$56) -> 4.8855172 | X29: =IF($I$12="","",W29/$I$12) -> 2.6551724 | Y29: =IF(AC29<>"",IF(D29<>"",D29,($I$8-SUM($Y$25:Y28))*AB29*AC29/SUMPRODUCT($AC29:$AC$56,$AB29:$AB$56)),"") -> 0 | Z29: =IF(AC29<>"",IF(E29<>"",E29,($I$9-SUM($Z$25:Z28))*AB29*AC29/SUMPRODUCT($AC29:$AC$56,$AB29:$AB$56)),"") -> 0 | AA29: =IF(AC29<>"",IF($I$12<>"",IF(G29<>"",G29,($I$9/$I$12-SUM($AA$25:AA28))*AB29*AC29/SUMPRODUCT($AC29:$AC$56,$AB29:$AB$56)),""),"") -> 0 | AB29: 1 | AC29: 1
A30: 6 | B30: 46061 | C30: вс | D30: 0 | E30: 0 | F30: =IF(AND(E30<>"",E30<>0),D30/E30,"") | G30: 0 | H30: =IF(AND(G30<>"",G30<>0),D30/G30,"") | I30: 30 | J30: =IF(AND(G30<>"",G30<>0),E30/G30,"") | T30: =IF(AND(I30<>"",I30<>0),G30/I30,"") -> 0 | U30: =D30/V30 -> 0 | V30: =$I$8*AB30*AC30/SUMPRODUCT($AC$25:$AC$56,$AB$25:$AB$56) -> 35468.855 | W30: =$I$9*AB30*AC30/SUMPRODUCT($AC$25:$AC$56,$AB$25:$AB$56) -> 4.8855172 | X30: =IF($I$12="","",W30/$I$12) -> 2.6551724 | Y30: =IF(AC30<>"",IF(D30<>"",D30,($I$8-SUM($Y$25:Y29))*AB30*AC30/SUMPRODUCT($AC30:$AC$56,$AB30:$AB$56)),"") -> 0 | Z30: =IF(AC30<>"",IF(E30<>"",E30,($I$9-SUM($Z$25:Z29))*AB30*AC30/SUMPRODUCT($AC30:$AC$56,$AB30:$AB$56)),"") -> 0 | AA30: =IF(AC30<>"",IF($I$12<>"",IF(G30<>"",G30,($I$9/$I$12-SUM($AA$25:AA29))*AB30*AC30/SUMPRODUCT($AC30:$AC$56,$AB30:$AB$56)),""),"") -> 0 | AB30: 1 | AC30: 1
A31: 7 | B31: 46062 | C31: пн | D31: 0 | E31: 0 | F31: =IF(AND(E31<>"",E31<>0),D31/E31,"") | G31: 0 | H31: =IF(AND(G31<>"",G31<>0),D31/G31,"") | I31: 19 | J31: =IF(AND(G31<>"",G31<>0),E31/G31,"") | T31: =IF(AND(I31<>"",I31<>0),G31/I31,"") -> 0 | U31: =D31/V31 -> 0 | V31: =$I$8*AB31*AC31/SUMPRODUCT($AC$25:$AC$56,$AB$25:$AB$56) -> 35468.855 | W31: =$I$9*AB31*AC31/SUMPRODUCT($AC$25:$AC$56,$AB$25:$AB$56) -> 4.8855172 | X31: =IF($I$12="","",W31/$I$12) -> 2.6551724 | Y31: =IF(AC31<>"",IF(D31<>"",D31,($I$8-SUM($Y$25:Y30))*AB31*AC31/SUMPRODUCT($AC31:$AC$56,$AB31:$AB$56)),"") -> 0 | Z31: =IF(AC31<>"",IF(E31<>"",E31,($I$9-SUM($Z$25:Z30))*AB31*AC31/SUMPRODUCT($AC31:$AC$56,$AB31:$AB$56)),"") -> 0 | AA31: =IF(AC31<>"",IF($I$12<>"",IF(G31<>"",G31,($I$9/$I$12-SUM($AA$25:AA30))*AB31*AC31/SUMPRODUCT($AC31:$AC$56,$AB31:$AB$56)),""),"") -> 0 | AB31: 1 | AC31: 1
A32: 8 | F32: =IF(AND(E32<>"",E32<>0),D32/E32,"") | H32: =IF(AND(G32<>"",G32<>0),D32/G32,"") | J32: =IF(AND(G32<>"",G32<>0),E32/G32,"") | T32: =IF(AND(I32<>"",I32<>0),G32/I32,"") | U32: =D32/V32 -> #DIV/0! | V32: =$I$8*AB32*AC32/SUMPRODUCT($AC$25:$AC$56,$AB$25:$AB$56) -> 0 | W32: =$I$9*AB32*AC32/SUMPRODUCT($AC$25:$AC$56,$AB$25:$AB$56) -> 0 | X32: =IF($I$12="","",W32/$I$12) -> 0 | Y32: =IF(AC32<>"",IF(D32<>"",D32,($I$8-SUM($Y$25:Y31))*AB32*AC32/SUMPRODUCT($AC32:$AC$56,$AB32:$AB$56)),"") | Z32: =IF(AC32<>"",IF(E32<>"",E32,($I$9-SUM($Z$25:Z31))*AB32*AC32/SUMPRODUCT($AC32:$AC$56,$AB32:$AB$56)),"") | AA32: =IF(AC32<>"",IF($I$12<>"",IF(G32<>"",G32,($I$9/$I$12-SUM($AA$25:AA31))*AB32*AC32/SUMPRODUCT($AC32:$AC$56,$AB32:$AB$56)),""),"")
A33: 9 | F33: =IF(AND(E33<>"",E33<>0),D33/E33,"") | H33: =IF(AND(G33<>"",G33<>0),D33/G33,"") | J33: =IF(AND(G33<>"",G33<>0),E33/G33,"") | T33: =IF(AND(I33<>"",I33<>0),G33/I33,"") | U33: =D33/V33 -> #DIV/0! | V33: =$I$8*AB33*AC33/SUMPRODUCT($AC$25:$AC$56,$AB$25:$AB$56) -> 0 | W33: =$I$9*AB33*AC33/SUMPRODUCT($AC$25:$AC$56,$AB$25:$AB$56) -> 0 | X33: =IF($I$12="","",W33/$I$12) -> 0 | Y33: =IF(AC33<>"",IF(D33<>"",D33,($I$8-SUM($Y$25:Y32))*AB33*AC33/SUMPRODUCT($AC33:$AC$56,$AB33:$AB$56)),"") | Z33: =IF(AC33<>"",IF(E33<>"",E33,($I$9-SUM($Z$25:Z32))*AB33*AC33/SUMPRODUCT($AC33:$AC$56,$AB33:$AB$56)),"") | AA33: =IF(AC33<>"",IF($I$12<>"",IF(G33<>"",G33,($I$9/$I$12-SUM($AA$25:AA32))*AB33*AC33/SUMPRODUCT($AC33:$AC$56,$AB33:$AB$56)),""),"")
A34: 10 | F34: =IF(AND(E34<>"",E34<>0),D34/E34,"") | H34: =IF(AND(G34<>"",G34<>0),D34/G34,"") | J34: =IF(AND(G34<>"",G34<>0),E34/G34,"") | T34: =IF(AND(I34<>"",I34<>0),G34/I34,"") | U34: =D34/V34 -> #DIV/0! | V34: =$I$8*AB34*AC34/SUMPRODUCT($AC$25:$AC$56,$AB$25:$AB$56) -> 0 | W34: =$I$9*AB34*AC34/SUMPRODUCT($AC$25:$AC$56,$AB$25:$AB$56) -> 0 | X34: =IF($I$12="","",W34/$I$12) -> 0 | Y34: =IF(AC34<>"",IF(D34<>"",D34,($I$8-SUM($Y$25:Y33))*AB34*AC34/SUMPRODUCT($AC34:$AC$56,$AB34:$AB$56)),"") | Z34: =IF(AC34<>"",IF(E34<>"",E34,($I$9-SUM($Z$25:Z33))*AB34*AC34/SUMPRODUCT($AC34:$AC$56,$AB34:$AB$56)),"") | AA34: =IF(AC34<>"",IF($I$12<>"",IF(G34<>"",G34,($I$9/$I$12-SUM($AA$25:AA33))*AB34*AC34/SUMPRODUCT($AC34:$AC$56,$AB34:$AB$56)),""),"")
A35: 11 | F35: =IF(AND(E35<>"",E35<>0),D35/E35,"") | H35: =IF(AND(G35<>"",G35<>0),D35/G35,"") | J35: =IF(AND(G35<>"",G35<>0),E35/G35,"") | T35: =IF(AND(I35<>"",I35<>0),G35/I35,"") | U35: =D35/V35 -> #DIV/0! | V35: =$I$8*AB35*AC35/SUMPRODUCT($AC$25:$AC$56,$AB$25:$AB$56) -> 0 | W35: =$I$9*AB35*AC35/SUMPRODUCT($AC$25:$AC$56,$AB$25:$AB$56) -> 0 | X35: =IF($I$12="","",W35/$I$12) -> 0 | Y35: =IF(AC35<>"",IF(D35<>"",D35,($I$8-SUM($Y$25:Y34))*AB35*AC35/SUMPRODUCT($AC35:$AC$56,$AB35:$AB$56)),"") | Z35: =IF(AC35<>"",IF(E35<>"",E35,($I$9-SUM($Z$25:Z34))*AB35*AC35/SUMPRODUCT($AC35:$AC$56,$AB35:$AB$56)),"") | AA35: =IF(AC35<>"",IF($I$12<>"",IF(G35<>"",G35,($I$9/$I$12-SUM($AA$25:AA34))*AB35*AC35/SUMPRODUCT($AC35:$AC$56,$AB35:$AB$56)),""),"")
A36: 12 | F36: =IF(AND(E36<>"",E36<>0),D36/E36,"") | H36: =IF(AND(G36<>"",G36<>0),D36/G36,"") | J36: =IF(AND(G36<>"",G36<>0),E36/G36,"") | T36: =IF(AND(I36<>"",I36<>0),G36/I36,"") | U36: =D36/V36 -> #DIV/0! | V36: =$I$8*AB36*AC36/SUMPRODUCT($AC$25:$AC$56,$AB$25:$AB$56) -> 0 | W36: =$I$9*AB36*AC36/SUMPRODUCT($AC$25:$AC$56,$AB$25:$AB$56) -> 0 | X36: =IF($I$12="","",W36/$I$12) -> 0 | Y36: =IF(AC36<>"",IF(D36<>"",D36,($I$8-SUM($Y$25:Y35))*AB36*AC36/SUMPRODUCT($AC36:$AC$56,$AB36:$AB$56)),"") | Z36: =IF(AC36<>"",IF(E36<>"",E36,($I$9-SUM($Z$25:Z35))*AB36*AC36/SUMPRODUCT($AC36:$AC$56,$AB36:$AB$56)),"") | AA36: =IF(AC36<>"",IF($I$12<>"",IF(G36<>"",G36,($I$9/$I$12-SUM($AA$25:AA35))*AB36*AC36/SUMPRODUCT($AC36:$AC$56,$AB36:$AB$56)),""),"")
A37: 13 | F37: =IF(AND(E37<>"",E37<>0),D37/E37,"") | H37: =IF(AND(G37<>"",G37<>0),D37/G37,"") | J37: =IF(AND(G37<>"",G37<>0),E37/G37,"") | T37: =IF(AND(I37<>"",I37<>0),G37/I37,"") | U37: =D37/V37 -> #DIV/0! | V37: =$I$8*AB37*AC37/SUMPRODUCT($AC$25:$AC$56,$AB$25:$AB$56) -> 0 | W37: =$I$9*AB37*AC37/SUMPRODUCT($AC$25:$AC$56,$AB$25:$AB$56) -> 0 | X37: =IF($I$12="","",W37/$I$12) -> 0 | Y37: =IF(AC37<>"",IF(D37<>"",D37,($I$8-SUM($Y$25:Y36))*AB37*AC37/SUMPRODUCT($AC37:$AC$56,$AB37:$AB$56)),"") | Z37: =IF(AC37<>"",IF(E37<>"",E37,($I$9-SUM($Z$25:Z36))*AB37*AC37/SUMPRODUCT($AC37:$AC$56,$AB37:$AB$56)),"") | AA37: =IF(AC37<>"",IF($I$12<>"",IF(G37<>"",G37,($I$9/$I$12-SUM($AA$25:AA36))*AB37*AC37/SUMPRODUCT($AC37:$AC$56,$AB37:$AB$56)),""),"")
A38: 14 | F38: =IF(AND(E38<>"",E38<>0),D38/E38,"") | H38: =IF(AND(G38<>"",G38<>0),D38/G38,"") | J38: =IF(AND(G38<>"",G38<>0),E38/G38,"") | T38: =IF(AND(I38<>"",I38<>0),G38/I38,"") | U38: =D38/V38 -> #DIV/0! | V38: =$I$8*AB38*AC38/SUMPRODUCT($AC$25:$AC$46,$AB$25:$AB$46) -> 0 | W38: =$I$9*AB38*AC38/SUMPRODUCT($AC$25:$AC$46,$AB$25:$AB$46) -> 0 | X38: =IF($I$12="","",W38/$I$12) -> 0 | Y38: =IF(AC38<>"",IF(D38<>"",D38,($I$8-SUM($Y$25:Y37))*AB38*AC38/SUMPRODUCT($AC38:$AC$56,$AB38:$AB$56)),"") | Z38: =IF(AC38<>"",IF(E38<>"",E38,($I$9-SUM($Z$25:Z37))*AB38*AC38/SUMPRODUCT($AC38:$AC$56,$AB38:$AB$56)),"") | AA38: =IF(AC38<>"",IF($I$12<>"",IF(G38<>"",G38,($I$9/$I$12-SUM($AA$25:AA37))*AB38*AC38/SUMPRODUCT($AC38:$AC$56,$AB38:$AB$56)),""),"")
A39: 15 | F39: =IF(AND(E39<>"",E39<>0),D39/E39,"") | H39: =IF(AND(G39<>"",G39<>0),D39/G39,"") | J39: =IF(AND(G39<>"",G39<>0),E39/G39,"") | T39: =IF(AND(I39<>"",I39<>0),G39/I39,"") | U39: =D39/V39 -> #DIV/0! | V39: =$I$8*AB39*AC39/SUMPRODUCT($AC$25:$AC$46,$AB$25:$AB$46) -> 0 | W39: =$I$9*AB39*AC39/SUMPRODUCT($AC$25:$AC$46,$AB$25:$AB$46) -> 0 | X39: =IF($I$12="","",W39/$I$12) -> 0 | Y39: =IF(AC39<>"",IF(D39<>"",D39,($I$8-SUM($Y$25:Y38))*AB39*AC39/SUMPRODUCT($AC39:$AC$56,$AB39:$AB$56)),"") | Z39: =IF(AC39<>"",IF(E39<>"",E39,($I$9-SUM($Z$25:Z38))*AB39*AC39/SUMPRODUCT($AC39:$AC$56,$AB39:$AB$56)),"") | AA39: =IF(AC39<>"",IF($I$12<>"",IF(G39<>"",G39,($I$9/$I$12-SUM($AA$25:AA38))*AB39*AC39/SUMPRODUCT($AC39:$AC$56,$AB39:$AB$56)),""),"")
A40: 16 | F40: =IF(AND(E40<>"",E40<>0),D40/E40,"") | H40: =IF(AND(G40<>"",G40<>0),D40/G40,"") | J40: =IF(AND(G40<>"",G40<>0),E40/G40,"") | T40: =IF(AND(I40<>"",I40<>0),G40/I40,"") | U40: =D40/V40 -> #DIV/0! | V40: =$I$8*AB40*AC40/SUMPRODUCT($AC$25:$AC$46,$AB$25:$AB$46) -> 0 | W40: =$I$9*AB40*AC40/SUMPRODUCT($AC$25:$AC$46,$AB$25:$AB$46) -> 0 | X40: =IF($I$12="","",W40/$I$12) -> 0 | Y40: =IF(AC40<>"",IF(D40<>"",D40,($I$8-SUM($Y$25:Y39))*AB40*AC40/SUMPRODUCT($AC40:$AC$56,$AB40:$AB$56)),"") | Z40: =IF(AC40<>"",IF(E40<>"",E40,($I$9-SUM($Z$25:Z39))*AB40*AC40/SUMPRODUCT($AC40:$AC$56,$AB40:$AB$56)),"") | AA40: =IF(AC40<>"",IF($I$12<>"",IF(G40<>"",G40,($I$9/$I$12-SUM($AA$25:AA39))*AB40*AC40/SUMPRODUCT($AC40:$AC$56,$AB40:$AB$56)),""),"")
A41: 17 | F41: =IF(AND(E41<>"",E41<>0),D41/E41,"") | H41: =IF(AND(G41<>"",G41<>0),D41/G41,"") | J41: =IF(AND(G41<>"",G41<>0),E41/G41,"") | T41: =IF(AND(I41<>"",I41<>0),G41/I41,"") | U41: =D41/V41 -> #DIV/0! | V41: =$I$8*AB41*AC41/SUMPRODUCT($AC$25:$AC$46,$AB$25:$AB$46) -> 0 | W41: =$I$9*AB41*AC41/SUMPRODUCT($AC$25:$AC$46,$AB$25:$AB$46) -> 0 | X41: =IF($I$12="","",W41/$I$12) -> 0 | Y41: =IF(AC41<>"",IF(D41<>"",D41,($I$8-SUM($Y$25:Y40))*AB41*AC41/SUMPRODUCT($AC41:$AC$56,$AB41:$AB$56)),"") | Z41: =IF(AC41<>"",IF(E41<>"",E41,($I$9-SUM($Z$25:Z40))*AB41*AC41/SUMPRODUCT($AC41:$AC$56,$AB41:$AB$56)),"") | AA41: =IF(AC41<>"",IF($I$12<>"",IF(G41<>"",G41,($I$9/$I$12-SUM($AA$25:AA40))*AB41*AC41/SUMPRODUCT($AC41:$AC$56,$AB41:$AB$56)),""),"")
A42: 18 | F42: =IF(AND(E42<>"",E42<>0),D42/E42,"") | H42: =IF(AND(G42<>"",G42<>0),D42/G42,"") | J42: =IF(AND(G42<>"",G42<>0),E42/G42,"") | T42: =IF(AND(I42<>"",I42<>0),G42/I42,"") | U42: =D42/V42 -> #DIV/0! | V42: =$I$8*AB42*AC42/SUMPRODUCT($AC$25:$AC$46,$AB$25:$AB$46) -> 0 | W42: =$I$9*AB42*AC42/SUMPRODUCT($AC$25:$AC$46,$AB$25:$AB$46) -> 0 | X42: =IF($I$12="","",W42/$I$12) -> 0 | Y42: =IF(AC42<>"",IF(D42<>"",D42,($I$8-SUM($Y$25:Y41))*AB42*AC42/SUMPRODUCT($AC42:$AC$56,$AB42:$AB$56)),"") | Z42: =IF(AC42<>"",IF(E42<>"",E42,($I$9-SUM($Z$25:Z41))*AB42*AC42/SUMPRODUCT($AC42:$AC$56,$AB42:$AB$56)),"") | AA42: =IF(AC42<>"",IF($I$12<>"",IF(G42<>"",G42,($I$9/$I$12-SUM($AA$25:AA41))*AB42*AC42/SUMPRODUCT($AC42:$AC$56,$AB42:$AB$56)),""),"")
A43: 19 | F43: =IF(AND(E43<>"",E43<>0),D43/E43,"") | H43: =IF(AND(G43<>"",G43<>0),D43/G43,"") | J43: =IF(AND(G43<>"",G43<>0),E43/G43,"") | T43: =IF(AND(I43<>"",I43<>0),G43/I43,"") | U43: =D43/V43 -> #DIV/0! | V43: =$I$8*AB43*AC43/SUMPRODUCT($AC$25:$AC$46,$AB$25:$AB$46) -> 0 | W43: =$I$9*AB43*AC43/SUMPRODUCT($AC$25:$AC$46,$AB$25:$AB$46) -> 0 | X43: =IF($I$12="","",W43/$I$12) -> 0 | Y43: =IF(AC43<>"",IF(D43<>"",D43,($I$8-SUM($Y$25:Y42))*AB43*AC43/SUMPRODUCT($AC43:$AC$56,$AB43:$AB$56)),"") | Z43: =IF(AC43<>"",IF(E43<>"",E43,($I$9-SUM($Z$25:Z42))*AB43*AC43/SUMPRODUCT($AC43:$AC$56,$AB43:$AB$56)),"") | AA43: =IF(AC43<>"",IF($I$12<>"",IF(G43<>"",G43,($I$9/$I$12-SUM($AA$25:AA42))*AB43*AC43/SUMPRODUCT($AC43:$AC$56,$AB43:$AB$56)),""),"")
F44: =IF(AND(E44<>"",E44<>0),D44/E44,"") | H44: =IF(AND(G44<>"",G44<>0),D44/G44,"") | J44: =IF(AND(G44<>"",G44<>0),E44/G44,"") | T44: =IF(AND(I44<>"",I44<>0),G44/I44,"") | U44: =D44/V44 -> #DIV/0! | V44: =$I$8*AB44*AC44/SUMPRODUCT($AC$25:$AC$46,$AB$25:$AB$46) -> 0 | W44: =$I$9*AB44*AC44/SUMPRODUCT($AC$25:$AC$46,$AB$25:$AB$46) -> 0 | X44: =IF($I$12="","",W44/$I$12) -> 0 | Y44: =IF(AC44<>"",IF(D44<>"",D44,($I$8-SUM($Y$25:Y43))*AB44*AC44/SUMPRODUCT($AC44:$AC$56,$AB44:$AB$56)),"") | Z44: =IF(AC44<>"",IF(E44<>"",E44,($I$9-SUM($Z$25:Z43))*AB44*AC44/SUMPRODUCT($AC44:$AC$56,$AB44:$AB$56)),"") | AA44: =IF(AC44<>"",IF($I$12<>"",IF(G44<>"",G44,($I$9/$I$12-SUM($AA$25:AA43))*AB44*AC44/SUMPRODUCT($AC44:$AC$56,$AB44:$AB$56)),""),"")
F45: =IF(AND(E45<>"",E45<>0),D45/E45,"") | H45: =IF(AND(G45<>"",G45<>0),D45/G45,"") | J45: =IF(AND(G45<>"",G45<>0),E45/G45,"") | T45: =IF(AND(I45<>"",I45<>0),G45/I45,"") | U45: =D45/V45 -> #DIV/0! | V45: =$I$8*AB45*AC45/SUMPRODUCT($AC$25:$AC$46,$AB$25:$AB$46) -> 0 | W45: =$I$9*AB45*AC45/SUMPRODUCT($AC$25:$AC$46,$AB$25:$AB$46) -> 0 | X45: =IF($I$12="","",W45/$I$12) -> 0 | Y45: =IF(AC45<>"",IF(D45<>"",D45,($I$8-SUM($Y$25:Y44))*AB45*AC45/SUMPRODUCT($AC45:$AC$56,$AB45:$AB$56)),"") | Z45: =IF(AC45<>"",IF(E45<>"",E45,($I$9-SUM($Z$25:Z44))*AB45*AC45/SUMPRODUCT($AC45:$AC$56,$AB45:$AB$56)),"") | AA45: =IF(AC45<>"",IF($I$12<>"",IF(G45<>"",G45,($I$9/$I$12-SUM($AA$25:AA44))*AB45*AC45/SUMPRODUCT($AC45:$AC$56,$AB45:$AB$56)),""),"")
F46: =IF(AND(E46<>"",E46<>0),D46/E46,"") | H46: =IF(AND(G46<>"",G46<>0),D46/G46,"") | J46: =IF(AND(G46<>"",G46<>0),E46/G46,"") | T46: =IF(AND(I46<>"",I46<>0),G46/I46,"") | U46: =D46/V46 -> #DIV/0! | V46: =$I$8*AB46*AC46/SUMPRODUCT($AC$25:$AC$46,$AB$25:$AB$46) -> 0 | W46: =$I$9*AB46*AC46/SUMPRODUCT($AC$25:$AC$46,$AB$25:$AB$46) -> 0 | X46: =IF($I$12="","",W46/$I$12) -> 0 | Y46: =IF(AC46<>"",IF(D46<>"",D46,($I$8-SUM($Y$25:Y45))*AB46*AC46/SUMPRODUCT($AC46:$AC$56,$AB46:$AB$56)),"") | Z46: =IF(AC46<>"",IF(E46<>"",E46,($I$9-SUM($Z$25:Z45))*AB46*AC46/SUMPRODUCT($AC46:$AC$56,$AB46:$AB$56)),"") | AA46: =IF(AC46<>"",IF($I$12<>"",IF(G46<>"",G46,($I$9/$I$12-SUM($AA$25:AA45))*AB46*AC46/SUMPRODUCT($AC46:$AC$56,$AB46:$AB$56)),""),"")
F47: =IF(AND(E47<>"",E47<>0),D47/E47,"") | H47: =IF(AND(G47<>"",G47<>0),D47/G47,"") | J47: =IF(AND(G47<>"",G47<>0),E47/G47,"") | T47: =IF(AND(I47<>"",I47<>0),G47/I47,"") | U47: =D47/V47 -> #DIV/0! | V47: =$I$8*AB47*AC47/SUMPRODUCT($AC$25:$AC$46,$AB$25:$AB$46) -> 0 | W47: =$I$9*AB47*AC47/SUMPRODUCT($AC$25:$AC$46,$AB$25:$AB$46) -> 0 | X47: =IF($I$12="","",W47/$I$12) -> 0 | Y47: =IF(AC47<>"",IF(D47<>"",D47,($I$8-SUM($Y$25:Y46))*AB47*AC47/SUMPRODUCT($AC47:$AC$56,$AB47:$AB$56)),"") | Z47: =IF(AC47<>"",IF(E47<>"",E47,($I$9-SUM($Z$25:Z46))*AB47*AC47/SUMPRODUCT($AC47:$AC$56,$AB47:$AB$56)),"") | AA47: =IF(AC47<>"",IF($I$12<>"",IF(G47<>"",G47,($I$9/$I$12-SUM($AA$25:AA46))*AB47*AC47/SUMPRODUCT($AC47:$AC$56,$AB47:$AB$56)),""),"")
F48: =IF(AND(E48<>"",E48<>0),D48/E48,"") | H48: =IF(AND(G48<>"",G48<>0),D48/G48,"") | J48: =IF(AND(G48<>"",G48<>0),E48/G48,"") | T48: =IF(AND(I48<>"",I48<>0),G48/I48,"") | U48: =D48/V48 -> #DIV/0! | V48: =$I$8*AB48*AC48/SUMPRODUCT($AC$25:$AC$46,$AB$25:$AB$46) -> 0 | W48: =$I$9*AB48*AC48/SUMPRODUCT($AC$25:$AC$46,$AB$25:$AB$46) -> 0 | X48: =IF($I$12="","",W48/$I$12) -> 0 | Y48: =IF(AC48<>"",IF(D48<>"",D48,($I$8-SUM($Y$25:Y47))*AB48*AC48/SUMPRODUCT($AC48:$AC$56,$AB48:$AB$56)),"") | Z48: =IF(AC48<>"",IF(E48<>"",E48,($I$9-SUM($Z$25:Z47))*AB48*AC48/SUMPRODUCT($AC48:$AC$56,$AB48:$AB$56)),"") | AA48: =IF(AC48<>"",IF($I$12<>"",IF(G48<>"",G48,($I$9/$I$12-SUM($AA$25:AA47))*AB48*AC48/SUMPRODUCT($AC48:$AC$56,$AB48:$AB$56)),""),"")
B49: итого | D49: =SUM(D25:D47) -> 65640 | E49: =SUM(E25:E47) -> 8 | F49: =IF(AND(E49<>"",E49<>0),D49/E49,"") -> 8205 | G49: =SUM(G25:G47) -> 6 | H49: =IF(AND(G49<>"",G49<>0),D49/G49,"") -> 10940 | I49: =SUM(I25:I47)*0.8 -> 125.6 | J49: =IF(AND(G49<>"",G49<>0),E49/G49,"") -> 1.3333333 | K49: =SUM(K25:K48) -> 0 | L49: =SUM(L25:L48) -> 0 | M49: =SUM(M25:M48) -> 0 | N49: =SUM(N25:N48) -> 0 | O49: =SUM(O25:O48) -> 0 | P49: =SUM(P25:P48) -> 0 | Q49: =SUM(Q25:Q48) -> 0 | R49: =SUM(R25:R48) -> 35593 | S49: =SUM(S25:S48) -> 0 | T49: =IF(AND(I49<>"",I49<>0),G49/I49,"") -> 0.047770701 | U49: =D49/V49 -> 0.30839097 | V49: =SUM(V25:V47) -> 212846.7 | W49: =SUM(W25:W47) -> 29.317727 | X49: =SUM(X25:X47) -> 15.933547 | Y49: =SUM(Y25:Y47) -> 50856 | Z49: =SUM(Z25:Z47) -> 7399 | AA49: =SUM(AA25:AA47) -> 7397
D50: =SUMIF(D25:D47,"",V25:V47)+D49 -> 65640

Sheet Вед-ть Свидовская
A1: =График!B1 -> Февраль, 2026
A2: =График!B3 -> ул. Севастопольская, 62 | D2: =График!B4 -> GL-0004
A3: Сотрудник | D3: Выплачено на карту | E3: Выплачено наличными по платежной ведомости | F3: Дополнительные начисления, доплаты | G3: Оклад | H3: Бонусная часть от личных продаж | I3: Бонусная часть от общих продаж | J3: Базовый бонус за выполнение плана | K3: Итого: | L3: Вычеты | M3: Итого к выдаче с учетом авансов и вычетов | N3: Подпись
A4: =График!B27 -> Свидовская София | D4: =6264+15164.58 -> 21428.58 | F4: =H8+H9 -> 0 | G4: =D13 -> 14100 | H4: =D20 -> 9943.68 | I4: =M20 -> 4106.2069 | J4: =M13 -> 0 | K4: =H4+J4+G4+F4+I4 -> 28149.887 | L4: =C8+C9+C10+C11 -> 3203 | M4: =K4-L4-D4-E4 -> 3518.3069
B6: Вычеты | G6: Доп начисления
B7: Дата | C7: Сумма | D7: Описание | G7: Дата | H7: Сумма | J7: Описание
B8: 46081 | C8: =936+2267 -> 3203 | D8: НДФЛ
A13: Оклад: | D13: =G17+G18 -> 14100 | I13: Базовый бонус | M13: =K17+K18 -> 0
B15: Оклад: | I15: Базовый бонус за выполнение плана
B16: Дней | C16: Магазин | D16: Должность | E16: Зачислено часов | F16: Ставка за час, руб | G16: Начислено за день, руб | I16: Магазин | J16: КВП | K16: Начисленный ББ
B17: =График!AI27 -> 13 | C17: =A2 -> ул. Севастопольская, 62 | D17: ПК | E17: =График!AJ27 -> 141 | F17: 100 | G17: =E17*F17 -> 14100 | I17: =C17 -> ул. Севастопольская, 62 | J17: =Центрум!K8 -> 0.45158263
A20: БонуснаяЧасть | D20: =G25+G26 -> 9943.68 | I20: Бонусная часть от общих продаж | M20: =N25+N26 -> 4106.2069
B23: Бонус от личных продаж по категории товара | I23: Бонус от общих продаж
B24: Сотрудник | C24: Магазин | E24: Процент от продажи | F24: Продано на сумму, руб | G24: Начисленный бонус от продаж, руб | I24: Сотрудник | J24: Магазин | K24: Кол-во отработанных личных часов | L24: Кол-во отработанных общих часов | M24: Процент от продажи | N24: Начисленный бонус от продаж, руб
B25: =A4 -> Свидовская София | C25: =A2 -> ул. Севастопольская, 62 | E25: 0.04 | F25: ='Свидовская С. А.'!J8 -> 248592 | G25: =F25*E25 -> 9943.68 | I25: =B25 -> Свидовская София | J25: =C25 -> ул. Севастопольская, 62 | K25: =E17 -> 141 | L25: =График!AJ29 -> 580 | M25: 0.02 | N25: =Центрум!J8*M25*K25/L25 -> 4106.2069

Sheet Вед-ть Корж
A1: =График!B1 -> Февраль, 2026
A2: =График!B3 -> ул. Севастопольская, 62 | D2: =График!B4 -> GL-0004
A3: Сотрудник | D3: Выплачено на карту | E3: Выплачено наличными по платежной ведомости | F3: Дополнительные начисления, доплаты | G3: Оклад | H3: Бонусная часть от личных продаж | I3: Бонусная часть от общих продаж | J3: Базовый бонус за выполнение плана | K3: Итого: | L3: Вычеты | M3: Итого к выдаче с учетом авансов и вычетов | N3: Подпись
A4: =График!B25 -> Корж Анастасия | D4: =15660+10714.8 -> 26374.8 | F4: =H8+H9 -> 0 | G4: =D13 -> 18500 | H4: =D21 -> 12379.8 | I4: =M21 -> 5387.5764 | J4: =M13 -> 0 | K4: =H4+J4+G4+F4+I4 -> 36267.376 | L4: =C8+C9+C10+C11 -> 3941 | M4: =K4-L4-D4-E4 -> 5951.5764
B6: Вычеты | G6: Доп начисления
B7: Дата | C7: Сумма | D7: Описание | G7: Дата | H7: Сумма | J7: Описание
B8: 46081 | C8: =2340+1601 -> 3941 | D8: НДФЛ
A13: Оклад: | D13: =G17+G19+G18 -> 18500 | I13: Базовый бонус | M13: =K17+K19+K18 -> 0
B15: Оклад: | I15: Базовый бонус за выполнение плана
B16: Дней | C16: Магазин | D16: Должность | E16: Зачислено часов | F16: Ставка за час, руб | G16: Начислено за день, руб | I16: Магазин | J16: КВП | K16: Начисленный ББ
B17: =График!AI25 -> 17 | C17: =A2 -> ул. Севастопольская, 62 | D17: ПК | E17: =График!AJ25 -> 185 | F17: 100 | G17: =E17*F17 -> 18500 | I17: =C17 -> ул. Севастопольская, 62 | J17: =Центрум!K8 -> 0.45158263
A21: БонуснаяЧасть | D21: =G26+G27+G28 -> 12379.8 | I21: Бонусная часть от общих продаж | M21: =N26+N27+N28 -> 5387.5764
B24: Бонус от личных продаж по категории товара | I24: Бонус от общих продаж
B25: Сотрудник | C25: Магазин | E25: Процент от продажи | F25: Продано на сумму, руб | G25: Начисленный бонус от продаж, руб | I25: Сотрудник | J25: Магазин | K25: Кол-во отработанных личных часов | L25: Кол-во отработанных общих часов | M25: Процент от продажи | N25: Начисленный бонус от продаж, руб
B26: =A4 -> Корж Анастасия | C26: =A2 -> ул. Севастопольская, 62 | E26: 0.04 | F26: ='Корж А. А.'!J8 -> 309495 | G26: =F26*E26 -> 12379.8 | I26: =B26 -> Корж Анастасия | J26: =C26 -> ул. Севастопольская, 62 | K26: =E17 -> 185 | L26: =График!AJ29 -> 580 | M26: 0.02 | N26: =Центрум!J8*M26*K26/L26 -> 5387.5764

Sheet Вед-ть Сейтджелилова
A1: =График!B1 -> Февраль, 2026
A2: =График!B3 -> ул. Севастопольская, 62 | D2: =График!B4 -> GL-0004
A3: Сотрудник | D3: Выплачено на карту | E3: Выплачено наличными по платежной ведомости | F3: Дополнительные начисления, доплаты | G3: Оклад | H3: Бонусная часть от личных продаж | I3: Бонусная часть от общих продаж | J3: Базовый бонус за выполнение плана | K3: Итого: | L3: Вычеты | M3: Итого к выдаче с учетом авансов и вычетов | N3: Подпись
A4: =График!B28 -> Сейтджелилова Алина | D4: =19140+13095.63 -> 32235.63 | F4: =H8+H9 -> 8445.39 | G4: =D13 -> 17700 | H4: =D20 -> 8535.68 | I4: =M20 -> 5154.6001 | J4: =M13 -> 0 | K4: =H4+J4+G4+F4+I4 -> 39835.67 | L4: =C8+C9+C10+C11 -> 4817 | M4: =K4-L4-D4-E4 -> 2783.0401
B6: Вычеты | G6: Доп начисления
B7: Дата | C7: Сумма | D7: Описание | G7: Дата | H7: Сумма | J7: Описание
B8: 46081 | C8: =2860+1957 -> 4817 | D8: НДФЛ | G8: 46081 | H8: =Центрум!J8*0.01 -> 8445.39 | J8: Административный %
G9: 46081 | H9: 0 | J9: % наличного оборота < 60%
A13: Оклад: | D13: =G17+G18 -> 17700 | I13: Базовый бонус | M13: =K17+K18 -> 0
B15: Оклад: | I15: Базовый бонус за выполнение плана
B16: Дней | C16: Магазин | D16: Должность | E16: Зачислено часов | F16: Ставка за час, руб | G16: Начислено за день, руб | I16: Магазин | J16: КВП | K16: Начисленный ББ
B17: =График!AI28 -> 20 | C17: =A2 -> ул. Севастопольская, 62 | D17: УМ | E17: =График!AJ28 -> 177 | F17: 100 | G17: =E17*F17 -> 17700 | I17: =C17 -> ул. Севастопольская, 62 | J17: =Центрум!K8 -> 0.45158263
A20: БонуснаяЧасть | D20: =G25+G26 -> 8535.68 | I20: Бонусная часть от общих продаж | M20: =N25+N26 -> 5154.6001
B23: Бонус от личных продаж по категории товара | I23: Бонус от общих продаж
B24: Сотрудник | C24: Магазин | E24: Процент от продажи | F24: Продано на сумму, руб | G24: Начисленный бонус от продаж, руб | I24: Сотрудник | J24: Магазин | K24: Кол-во отработанных личных часов | L24: Кол-во отработанных общих часов | M24: Процент от продажи | N24: Начисленный бонус от продаж, руб
B25: =A4 -> Сейтджелилова Алина | C25: =A2 -> ул. Севастопольская, 62 | E25: 0.04 | F25: ='Сейтджелилова А.Э.'!J8 -> 213392 | G25: =F25*E25 -> 8535.68 | I25: =B25 -> Сейтджелилова Алина | J25: =C25 -> ул. Севастопольская, 62 | K25: =E17 -> 177 | L25: =График!AJ29 -> 580 | M25: 0.02 | N25: =Центрум!J8*M25*K25/L25 -> 5154.6001

Sheet График
B1: Февраль, 2026
B2: г. Симферополь
B3: ул. Севастопольская, 62
B4: GL-0004
B5: 10.00-21.00
B6: ФОТ | C6: Кол-во дней в месяц | AK6: 30
C7: Премия Директора, грн.
D8: вс | E8: пн | F8: вт | G8: ср | H8: чт | I8: пт | J8: сб | K8: вс | L8: пн | M8: вт | N8: ср | O8: чт | P8: пт | Q8: сб | R8: вс | S8: пн | T8: вт | U8: ср | V8: чт | W8: пт | X8: сб | Y8: вс | Z8: пн | AA8: вт | AB8: ср | AC8: чт | AD8: пт | AE8: сб | AJ8: Часы | AK8: Выходные | AL8: Отпуск | AM8: Больничный (официальный) | AN8: Дни стажировки
A10: № | B10: ФИО | C10: Должность | D10: 1 | E10: 2 | F10: 3 | G10: 4 | H10: 5 | I10: 6 | J10: 7 | K10: 8 | L10: 9 | M10: 10 | N10: 11 | O10: 12 | P10: 13 | Q10: 14 | R10: 15 | S10: 16 | T10: 17 | U10: 18 | V10: 19 | W10: 20 | X10: 21 | Y10: 22 | Z10: 23 | AA10: 24 | AB10: 25 | AC10: 26 | AD10: 27 | AE10: 28 | AI10: Дни
A11: 18 | AI11: =COUNTIF(D11:AH11,">0") -> 0 | AJ11: =SUMIF(D11:AH11,">0") -> 0 | AK11: 0 | AL11: 0 | AM11: 0 | AN11: 0
A12: 17 | AI12: =COUNTIF(D12:AH12,">0") -> 0 | AJ12: =SUMIF(D12:AH12,">0") -> 0 | AK12: =COUNTIF(D12:AH12,"В") -> 0 | AL12: 0 | AM12: 0 | AN12: 0
A13: 16 | AI13: =COUNTIF(D13:AH13,">0") -> 0 | AJ13: =SUMIF(D13:AH13,">0") -> 0 | AK13: =COUNTIF(D13:AH13,"В") -> 0 | AL13: 0 | AM13: 0 | AN13: 0
A14: 15 | AI14: =COUNTIF(D14:AH14,">0") -> 0 | AJ14: =SUMIF(D14:AH14,">0") -> 0 | AK14: =COUNTIF(D14:AH14,"В") -> 0 | AL14: 0 | AM14: 0 | AN14: 0
A15: 14 | AI15: =COUNTIF(D15:AH15,">0") -> 0 | AJ15: =SUMIF(D15:AH15,">0") -> 0 | AK15: =COUNTIF(D15:AH15,"В") -> 0 | AL15: 0 | AM15: 0 | AN15: 0
A16: 13 | AI16: =COUNTIF(D16:AH16,">0") -> 0 | AJ16: =SUMIF(D16:AH16,">0") -> 0 | AK16: =COUNTIF(D16:AH16,"В") -> 0 | AL16: 0 | AM16: 0 | AN16: 0
A17: 12 | AI17: =COUNTIF(D17:AH17,">0") -> 0 | AJ17: =SUMIF(D17:AH17,">0") -> 0 | AK17: =COUNTIF(D17:AH17,"В") -> 0 | AL17: 0 | AM17: 0 | AN17: 0
A18: 11 | AI18: =COUNTIF(D18:AH18,">0") -> 0 | AJ18: =SUMIF(D18:AH18,">0") -> 0 | AK18: =COUNTIF(D18:AH18,"В") -> 0 | AL18: 0 | AM18: 0 | AN18: 0
A19: 10 | AI19: =COUNTIF(D19:AH19,">0") -> 0 | AJ19: =SUMIF(D19:AH19,">0") -> 0 | AK19: =COUNTIF(D19:AH19,"В") -> 0 | AL19: 0 | AM19: 0 | AN19: 0
A20: 9 | AI20: =COUNTIF(D20:AH20,">0") -> 0 | AJ20: =SUMIF(D20:AH20,">0") -> 0 | AK20: =COUNTIF(D20:AH20,"В") -> 0 | AL20: 0 | AM20: 0 | AN20: 0
A21: 8 | AI21: =COUNTIF(D21:AH21,">0") -> 0 | AJ21: =SUMIF(D21:AH21,">0") -> 0 | AK21: =COUNTIF(D21:AH21,"В") -> 0 | AL21: 0 | AM21: 0 | AN21: 0
A22: 7 | AI22: =COUNTIF(D22:AH22,">0") -> 0 | AJ22: =SUMIF(D22:AH22,">0") -> 0 | AK22: =COUNTIF(D22:AH22,"В") -> 0 | AL22: 0 | AM22: 0 | AN22: 0
A23: 6 | AI23: =COUNTIF(D23:AH23,">0") -> 0 | AJ23: =SUMIF(D23:AH23,">0") -> 0 | AK23: =COUNTIF(D23:AH23,"В") -> 0 | AL23: 0 | AM23: 0 | AN23: 0
A24: 5 | AI24: =COUNTIF(D24:AH24,">0") -> 0 | AJ24: =SUMIF(D24:AH24,">0") -> 0 | AK24: =COUNTIF(D24:AH24,"В") -> 0 | AL24: 0 | AM24: 0 | AN24: 0
A25: 4 | B25: Корж Анастасия | C25: ПК | D25: в | E25: в | F25: 11 | G25: 11 | H25: 11 | I25: 11 | J25: в | K25: в | L25: 11 | M25: в | N25: в | O25: 11 | P25: 11 | Q25: 11 | R25: 11 | S25: в | T25: в | U25: 11 | V25: 11 | W25: 11 | X25: 9 | Y25: в | Z25: в | AA25: 11 | AB25: 11 | AC25: 11 | AD25: 11 | AE25: в | AI25: =COUNTIF(D25:AH25,">0") -> 17 | AJ25: =SUMIF(D25:AH25,">0") -> 185 | AK25: =COUNTIF(D25:AH25,"В") -> 11 | AL25: 0 | AM25: 0 | AN25: 0
A26: 3 | B26: Козлова Валерия | C26: ПК | D26: 11 | E26: 11 | F26: в | G26: 11 | H26: 11 | I26: в | J26: 11 | K26: 11 | L26: 11 | M26: у | N26: у | O26: у | P26: у | Q26: у | R26: у | S26: у | T26: у | U26: у | V26: у | W26: у | X26: у | Y26: у | Z26: у | AA26: у | AB26: у | AC26: у | AD26: у | AE26: у | AI26: =COUNTIF(D26:AH26,">0") -> 7 | AJ26: =SUMIF(D26:AH26,">0") -> 77 | AK26: =COUNTIF(D26:AH26,"В") -> 2 | AL26: 0 | AM26: 0 | AN26: 0
A27: 2 | B27: Свидовская София | C27: ПК | D27: о | E27: о | F27: о | G27: о | H27: о | I27: о | J27: о | K27: о | L27: о | M27: 11 | N27: 11 | O27: 11 | P27: 9 | Q27: в | R27: в | S27: 11 | T27: 11 | U27: 11 | V27: 11 | W27: в | X27: в | Y27: 11 | Z27: 11 | AA27: 11 | AB27: 11 | AC27: в | AD27: в | AE27: 11 | AI27: =COUNTIF(D27:AH27,">0") -> 13 | AJ27: =SUMIF(D27:AH27,">0") -> 141 | AK27: =COUNTIF(D27:AH27,"В") -> 6 | AL27: 0 | AM27: 0 | AN27: 0
A28: 1 | B28: Сейтджелилова Алина | C28: УМ | D28: 9 | E28: 9 | F28: 9 | G28: в | H28: в | I28: 9 | J28: 9 | K28: 9 | L28: в | M28: 9 | N28: 9 | O28: в | P28: в | Q28: 9 | R28: 9 | S28: 9 | T28: 9 | U28: в | V28: в | W28: 9 | X28: 11 | Y28: 9 | Z28: 8 | AA28: 5 | AB28: в | AC28: 9 | AD28: 9 | AE28: 9 | AI28: =COUNTIF(D28:AH28,">0") -> 20 | AJ28: =SUMIF(D28:AH28,">0") -> 177 | AK28: =COUNTIF(D28:AH28,"В") -> 8 | AL28: =COUNTIF(E28:AI28,"о") -> 0 | AM28: =COUNTIF(F28:AJ28,"б") -> 0 | AN28: 0
B29: Итого магазин | D29: =COUNTIF(D11:D28,">0") -> 2 | E29: =COUNTIF(E11:E28,">0") -> 2 | F29: =COUNTIF(F11:F28,">0") -> 2 | G29: =COUNTIF(G11:G28,">0") -> 2 | H29: =COUNTIF(H11:H28,">0") -> 2 | I29: =COUNTIF(I11:I28,">0") -> 2 | J29: =COUNTIF(J11:J28,">0") -> 2 | K29: =COUNTIF(K11:K28,">0") -> 2 | ... AH29: =COUNTIF(AH11:AH28,">0") -> 0 | AI29: =SUM(AI11:AI28) -> 57 | AJ29: =SUM(AJ11:AJ28) -> 580 | AK29: =SUM(AK11:AK28) -> 27 | AL29: =SUM(AL11:AL28) -> 0 | AM29: =SUM(AM11:AM28) -> 0 | AN29: =SUM(AN11:AN28) -> 0
T32: .
Q54: .

Sheet Вед-ть Доп сотрудник
A1: =График!B1 -> Февраль, 2026
A2: =График!B3 -> ул. Севастопольская, 62 | D2: =График!B4 -> GL-0004
A3: Сотрудник | D3: Выплачено на карту | E3: Выплачено наличными по платежной ведомости | F3: Дополнительные начисления, доплаты | G3: Оклад | H3: Бонусная часть от личных продаж | I3: Бонусная часть от общих продаж | J3: Базовый бонус за выполнение плана | K3: Итого: | L3: Вычеты | M3: Итого к выдаче с учетом авансов и вычетов | N3: Подпись
A4: =График!B24 -> 0 | F4: =H8+H9 -> 0 | G4: =D13 -> 0 | H4: =D20 -> 88.35 | I4: =M20 -> 0 | J4: =M13 -> 0 | K4: =H4+J4+G4+F4+I4 -> 88.35 | L4: =C8+C9+C10+C11 -> 200 | M4: =K4-L4-D4-E4 -> -111.65
B6: Вычеты | G6: Доп начисления
B7: Дата | C7: Сумма | D7: Описание | G7: Дата | H7: Сумма | J7: Описание
B8: 46031 | C8: 200 | D8: Вычет по инвентаризационной ведомости от 09.01 | G8: 46053 | H8: =Центрум!D62*1%/2 -> 0 | J8: Администартивный %
A13: Оклад: | D13: =G17+G18 -> 0 | I13: Базовый бонус | M13: =K17+K18 -> 0
B15: Оклад: | I15: Базовый бонус за выполнение плана
B16: Дней | C16: Магазин | D16: Должность | E16: Зачислено часов | F16: Ставка за час, руб | G16: Начислено за день, руб | I16: Магазин | J16: КВП | K16: Начисленный ББ
B17: =График!AI24 -> 0 | C17: =A2 -> ул. Севастопольская, 62 | D17: УМ | E17: =График!AJ24 -> 0 | F17: 200 | G17: =E17*F17 -> 0 | I17: =C17 -> ул. Севастопольская, 62 | J17: =Центрум!K8 -> 0.45158263
A20: БонуснаяЧасть | D20: =G25+G26 -> 88.35 | I20: Бонусная часть от общих продаж | M20: =N25+N26 -> 0
B23: Бонус от личных продаж по категории товара | I23: Бонус от общих продаж
B24: Сотрудник | C24: Магазин | E24: Процент от продажи | F24: Продано на сумму, руб | G24: Начисленный бонус от продаж, руб | I24: Сотрудник | J24: Магазин | K24: Кол-во отработанных личных часов | L24: Кол-во отработанных общих часов | M24: Процент от продажи | N24: Начисленный бонус от продаж, руб
B25: =A4 -> 0 | C25: =A2 -> ул. Севастопольская, 62 | E25: 0.05 | F25: ='Доп сотрудник'!J8-5653 -> 1767 | G25: =F25*E25 -> 88.35 | I25: =B25 -> 0 | J25: =C25 -> ул. Севастопольская, 62 | K25: =E17 -> 0 | L25: =График!AJ29 -> 580 | M25: 0.02 | N25: =Центрум!J8*M25*K25/L25 -> 0

Sheet Вед-ть Козлова
A1: =График!B1 -> Февраль, 2026
A2: =График!B3 -> ул. Севастопольская, 62 | D2: =График!B4 -> GL-0004
A3: Сотрудник | D3: Выплачено на карту | E3: Выплачено наличными по платежной ведомости | F3: Дополнительные начисления, доплаты | G3: Оклад | H3: Бонусная часть от личных продаж | I3: Бонусная часть от общих продаж | J3: Базовый бонус за выполнение плана | K3: Итого: | L3: Вычеты | M3: Итого к выдаче с учетом авансов и вычетов | N3: Подпись
A4: =График!B26 -> Козлова Валерия | D4: 17373.11 | F4: =H8+H9 -> 8600.69 | G4: =D13 -> 7700 | H4: =D21 -> 2625.6 | I4: =M21 -> 2242.3967 | J4: =M13 -> 0 | K4: =H4+J4+G4+F4+I4 -> 21168.687 | L4: =C8+C9 -> 2596 | M4: =K4-L4-D4-E4 -> 1199.5767
B6: Вычеты | G6: Доп начисления
B7: Дата | C7: Сумма | D7: Описание | G7: Дата | H7: Сумма | J7: Описание
B8: 46062 | C8: 2596 | D8: НДФЛ | G8: 46062 | H8: 8600.69 | J8: Компенсация, неиспользованный отпуск
A13: Оклад: | D13: =G17+G19+G18 -> 7700 | I13: Базовый бонус | M13: =K17+K19+K18 -> 0
B15: Оклад: | I15: Базовый бонус за выполнение плана
B16: Дней | C16: Магазин | D16: Должность | E16: Зачислено часов | F16: Ставка за час, руб | G16: Начислено за день, руб | I16: Магазин | J16: КВП | K16: Начисленный ББ
B17: =График!AI26 -> 7 | C17: =A2 -> ул. Севастопольская, 62 | D17: ПК | E17: =График!AJ26 -> 77 | F17: 100 | G17: =E17*F17 -> 7700 | I17: =C17 -> ул. Севастопольская, 62 | J17: =Центрум!K8 -> 0.45158263
G18: =E18*F18 -> 0
A21: БонуснаяЧасть | D21: =G26+G27+G28 -> 2625.6 | I21: Бонусная часть от общих продаж | M21: =N26+N27+N28 -> 2242.3967
B24: Бонус от личных продаж по категории товара | I24: Бонус от общих продаж
B25: Сотрудник | C25: Магазин | E25: Процент от продажи | F25: Продано на сумму, руб | G25: Начисленный бонус от продаж, руб | I25: Сотрудник | J25: Магазин | K25: Кол-во отработанных личных часов | L25: Кол-во отработанных общих часов | M25: Процент от продажи | N25: Начисленный бонус от продаж, руб
B26: =A4 -> Козлова Валерия | C26: =A2 -> ул. Севастопольская, 62 | E26: 0.04 | F26: ='Козлова В. Э.'!J8 -> 65640 | G26: =F26*E26 -> 2625.6 | I26: =B26 -> Козлова Валерия | J26: =C26 -> ул. Севастопольская, 62 | K26: =E17 -> 77 | L26: =График!AJ29 -> 580 | M26: 0.02 | N26: =Центрум!J8*M26*K26/L26 -> 2242.3967

Sheet ПК4
B1: =TODAY()-1 -> 46171
B2: (отчетная дата) | J2: ЕЖЕДНЕВНЫЙ ОТЧЕТ О ПРОДАЖАХ
B3: Осталось до выполнения плана!!! | J3: =График!B28 -> Сейтджелилова Алина
C4: =I8-D50 -> 570726.12 | E4: =IF(I8<>0,C4/I8,0) -> 1
F6: Целевые показатели
F7: Показатель | I7: План | J7: Факт | K7: % выполнения | L7: Прогноз выполнения | M7: % выполнения по прогнозу | N7: Отклонение | O7: Факт аналогичного месяца прошлого года | P7: Отклонение LFL
F8: Выручка | I8: =Центрум!I8/График!AJ29*График!AJ28 -> 570726.12 | J8: =D50 -> 0 | K8: =IF(AND(I8<>"",I8<>0,J8<>""),J8/I8,"") -> 0 | L8: =IF(SUMIF($D$25:$D$49,">=0",$T$25:$T$49)<>0,I8*D50/SUMIF($D$25:$D$49,">=0",$T$25:$T$49),0) -> 0 | M8: =L8/I8 -> 0 | N8: =IF(AND(J8<>0,J8<>"",I8<>0,I8<>""),L8-I8,"") | P8: =IF(AND(O8<>"",O8<>0,L8<>"",L8<>0),-O8+L8,"") | Q8: =IF(AND(P8<>"",P8<>0,O8<>0,O8<>""),P8/O8,"")
F9: Кол-во изделий | I9: =I8/I11 -> 78.612414 | J9: =E50 -> 0 | K9: =IF(AND(I9<>"",I9<>0,J9<>""),J9/I9,"") -> 0 | L9: =IF(SUMIF($E$25:$E$49,">=0",$U$25:$U$49)<>0,I9*E50/SUMIF($E$25:$E$49,">=0",$U$25:$U$49),0) -> 0 | M9: =IF(AND(I9<>"",I9<>0,L9<>"",L9<>0),L9/I9,"") | N9: =IF(AND(J9<>0,J9<>"",I9<>0,I9<>""),L9-I9,"") | O9: =O8/O11 -> #DIV/0! | P9: =IF(AND(O9<>"",O9<>0,L9<>"",L9<>0),-O9+L9,"") -> #DIV/0! | Q9: =IF(AND(P9<>"",P9<>0,O9<>0,O9<>""),P9/O9,"") -> #DIV/0!
F10: Средний чек | I10: =I11*I12 -> 13358.4 | J10: =H50 | K10: =IF(AND(I10<>"",I10<>0,J10<>""),J10/I10,"") | L10: =J10 | M10: =IF(AND(I10<>"",I10<>0,L10<>"",L10<>0),L10/I10,"") | N10: =IF(AND(J10<>0,J10<>"",I10<>0,I10<>""),L10-I10,"") | O10: =O11*O12 -> 0 | P10: =IF(AND(O10<>"",O10<>0,L10<>"",L10<>0),-O10+L10,"") | Q10: =IF(AND(P10<>"",P10<>0,O10<>0,O10<>""),P10/O10,"")
F11: Средняя стоимость изделия | I11: =Центрум!I11 -> 7260 | J11: =F50 | K11: =IF(AND(I11<>"",I11<>0,J11<>""),J11/I11,"") | L11: =J11 | M11: =IF(AND(I11<>"",I11<>0,L11<>"",L11<>0),L11/I11,"") | N11: =IF(AND(J11<>0,J11<>"",I11<>0,I11<>""),L11-I11,"") | P11: =IF(AND(O11<>"",O11<>0,L11<>"",L11<>0),-O11+L11,"") | Q11: =IF(AND(P11<>"",P11<>0,O11<>0,O11<>""),P11/O11,"")
F12: Длина чека | I12: =Центрум!I12 -> 1.84 | J12: =J50 | K12: =IF(AND(I12<>"",I12<>0,J12<>""),J12/I12,"") | L12: =J12 | M12: =IF(AND(I12<>"",I12<>0,L12<>"",L12<>0),L12/I12,"") | N12: =IF(AND(J12<>0,J12<>"",I12<>0,I12<>""),L12-I12,"") | P12: =IF(AND(O12<>"",O12<>0,L12<>"",L12<>0),-O12+L12,"") | Q12: =IF(AND(P12<>"",P12<>0,O12<>0,O12<>""),P12/O12,"")
F13: Кол-во чеков | I13: =IF(I12<>0,I9/I12,"") -> 42.724138 | J13: =G50 -> 0 | K13: =IF(AND(I13<>"",I13<>0,J13<>""),J13/I13,"") -> 0 | L13: =IF(SUMIF($G$25:$G$49,">=0",$V$25:$V$49)<>0,I13*G50/SUMIF($G$25:$G$49,">=0",$V$25:$V$49),"") | M13: =IF(AND(I13<>"",I13<>0,L13<>"",L13<>0),L13/I13,"") | N13: =IF(AND(J13<>0,J13<>"",I13<>0,I13<>""),L13-I13,"") | P13: =IF(AND(O13<>"",O13<>0,L13<>"",L13<>0),-O13+L13,"") | Q13: =IF(AND(P13<>"",P13<>0,O13<>0,O13<>""),P13/O13,"")
F14: Кол-во смен план/отработано | I14: =График!AI28 -> 20 | J14: 5 | K14: =IF(AND(I14<>"",I14<>0,J14<>""),J14/I14,"") -> 0.25 | L14: =IF(SUMIF($D$25:$D$49,">=0",$T$25:$T$49),I50*I8/SUMIF($D$25:$D$49,">=0",$T$25:$T$49),"") | N14: =IF(AND(J14<>0,J14<>"",I14<>0,I14<>""),L14-I14,"") -> #VALUE! | P14: =IF(AND(O14<>"",O14<>0,L14<>"",L14<>0),-O14+L14,"") | Q14: =IF(AND(P14<>"",P14<>0,O14<>0,O14<>""),P14/O14,"")
F15: Средние продажи в смену | I15: =Центрум!I15 -> 66792 | J15: =J8/J14 -> 0 | K15: =IF(AND(I15<>"",I15<>0,J15<>""),J15/I15,"") -> 0 | L15: =J15 -> 0 | M15: =IF(AND(I15<>"",I15<>0,L15<>"",L15<>0),L15/I15,"") | N15: =IF(AND(J15<>0,J15<>"",I15<>0,I15<>""),L15-I15,"") | P15: =IF(AND(O15<>"",O15<>0,L15<>"",L15<>0),-O15+L15,"") | Q15: =IF(AND(P15<>"",P15<>0,O15<>0,O15<>""),P15/O15,"")
F16: Отставание/Перевыполнение | J16: =J8-I15*J14 -> -333960 | K16: =IF(AND(I16<>"",I16<>0,J16<>""),J16/I16,"") | L16: =J16 -> -333960 | M16: =IF(AND(I16<>"",I16<>0,L16<>"",L16<>0),L16/I16,"") | N16: =IF(AND(J16<>0,J16<>"",I16<>0,I16<>""),L16-I16,"") | P16: =IF(AND(O16<>"",O16<>0,L16<>"",L16<>0),-O16+L16,"") | Q16: =IF(AND(P16<>"",P16<>0,O16<>0,O16<>""),P16/O16,"") | S16: Подарочные сертификаты
F17: Трафик | I17: =Центрум!I17/График!AJ29*График!AJ28 -> 427.24138 | J17: =I50 -> 0 | K17: =IF(AND(I17<>"",I17<>0,J17<>""),J17/I17,"") -> 0 | L17: =J17/J14*I14 -> 0 | M17: =IF(AND(I17<>"",I17<>0,L17<>"",L17<>0),L17/I17,"") | N17: =IF(AND(J17<>0,J17<>"",I17<>0,I17<>""),L17-I17,"") | P17: =IF(AND(O17<>"",O17<>0,L17<>"",L17<>0),-O17+L17,"") | Q17: =IF(AND(P17<>"",P17<>0,O17<>0,O17<>""),P17/O17,"")
K18: =IF(AND(I18<>"",I18<>0,J18<>""),J18/I18,"") | L18: =J18 -> 0 | M18: =IF(AND(I18<>"",I18<>0,L18<>"",L18<>0),L18/I18,"") | N18: =IF(AND(J18<>0,J18<>"",I18<>0,I18<>""),L18-I18,"") | O18: 0 | P18: =IF(AND(O18<>"",O18<>0,L18<>"",L18<>0),-O18+L18,"") | Q18: =IF(AND(P18<>"",P18<>0,O18<>0,O18<>""),P18/O18,"")
J19: =P50 -> 0 | K19: =IF(AND(I19<>"",I19<>0,J19<>""),J19/I19,"") | L19: =J19 -> 0 | M19: =IF(AND(I19<>"",I19<>0,L19<>"",L19<>0),L19/I19,"") | N19: =IF(AND(J19<>0,J19<>"",I19<>0,I19<>""),L19-I19,"") | O19: 0 | P19: =IF(AND(O19<>"",O19<>0,L19<>"",L19<>0),-O19+L19,"") | Q19: =IF(AND(P19<>"",P19<>0,O19<>0,O19<>""),P19/O19,"") | S19: =S18/I16 -> #DIV/0!
F20: Конверсия план/факт | I20: =Центрум!I20 -> 0.1 | J20: =R50 | K20: =J20/I20 -> #VALUE! | L20: =IF(AND(K8<>0,I14<>0,I50<>0),(I50*R50+(I50/K8-I50)*I20)/(I50/K8),0) -> 0 | M20: =IF(AND(I20<>"",I20<>0,L20<>"",L20<>0),L20/I20,"") | N20: =IF(AND(J20<>0,J20<>"",I20<>0,I20<>""),L20-I20,"") | P20: =IF(AND(O20<>"",O20<>0,L20<>"",L20<>0),-O20+L20,"") | Q20: =IF(AND(P20<>"",P20<>0,O20<>0,O20<>""),P20/O20,"")
B22: Факт продаж за месяц | S22: % выполнения дневного плана | T22: Раcпределение плана по дням
B23: Дата | C23: День недели | D23: Выручка (руб) | E23: Кол-во единиц (шт.) | F23: Средняя стоимость изделия (руб.) | G23: Количество чеков (шт.) | H23: Средняя сумма чека (руб.) | I23: Трафик | J23: Длина чека (шт.) | K23: UNOde50 | L23: IS | M23: Agafi | N23: Kalliope | O23: Raganella | P23: CC/MP | Q23: Eva Rites | R23: Конверсия (%) | T23: выручка, план | U23: кол-во ед, план | V23: Кол-во чеков, план | W23: выручка, скорректир.план | X23: кол-во ед, скорр. план | Y23: кол-во чеков, скорр. план | Z23: Коэфф. Дня Недели | AA23: Специфика месяца
B24: 1 | C24: 2 | D24: 3 | E24: в | F24: 5 | G24: 6 | H24: 7 | I24: 8 | J24: 9 | K24: 10 | L24: 11 | M24: 12 | N24: 13 | O24: 14 | P24: 15 | R24: 16 | T24: 1 | U24: 2 | V24: 3 | W24: 4 | X24: 5 | Y24: 6 | Z24: 10 | AA24: 11
A25: 1 | H25: =IF(AND(G25<>"",G25<>0),D25/G25,"") | J25: =IF(AND(G25<>"",G25<>0),E25/G25,"") | R25: =IF(AND(I25<>"",I25<>0),G25/I25,"") | S25: =D25/T25 -> 0 | T25: =$I$8*Z25*AA25/SUMPRODUCT($AA$25:$AA$57,$Z$25:$Z$57) -> 21192.404 | U25: =$I$9*Z25*AA25/SUMPRODUCT($AA$25:$AA$57,$Z$25:$Z$57) -> 2.9190639 | V25: =IF($I$12="","",U25/$I$12) -> 1.5864478 | W25: =IF(AA25<>"",IF(D25<>"",D25,($I$8-SUM($W24:W$25))*Z25*AA25/SUMPRODUCT($AA25:$AA$57,$Z25:$Z$57)),"") -> #REF! | X25: =IF(AA25<>"",IF(E25<>"",E25,($I$9-SUM($X24:X$25))*Z25*AA25/SUMPRODUCT($AA25:$AA$57,$Z25:$Z$57)),"") -> #REF! | Y25: =IF(AA25<>"",IF($I$12<>"",IF(G25<>"",G25,($I$9/$I$12-SUM($Y24:Y$25))*Z25*AA25/SUMPRODUCT($AA25:$AA$57,$Z25:$Z$57)),""),"") -> #REF! | Z25: 1 | AA25: 1
A26: 2 | H26: =IF(AND(G26<>"",G26<>0),D26/G26,"") | J26: =IF(AND(G26<>"",G26<>0),E26/G26,"") | R26: =IF(AND(I26<>"",I26<>0),G26/I26,"") | S26: =D26/T26 -> 0 | T26: =$I$8*Z26*AA26/SUMPRODUCT($AA$25:$AA$57,$Z$25:$Z$57) -> 15423.484 | U26: =$I$9*Z26*AA26/SUMPRODUCT($AA$25:$AA$57,$Z$25:$Z$57) -> 2.1244468 | V26: =IF($I$12="","",U26/$I$12) -> 1.1545907 | W26: =IF(AA26<>"",IF(D26<>"",D26,($I$8-SUM($W$25:W25))*Z26*AA26/SUMPRODUCT($AA26:$AA$57,$Z26:$Z$57)),"") -> #REF! | X26: =IF(AA26<>"",IF(E26<>"",E26,($I$9-SUM($X$25:X25))*Z26*AA26/SUMPRODUCT($AA26:$AA$57,$Z26:$Z$57)),"") -> #REF! | Y26: =IF(AA26<>"",IF($I$12<>"",IF(G26<>"",G26,($I$9/$I$12-SUM($Y$25:Y25))*Z26*AA26/SUMPRODUCT($AA26:$AA$57,$Z26:$Z$57)),""),"") -> #REF! | Z26: 0.85310234 | AA26: 0.85310234
A27: 3 | H27: =IF(AND(G27<>"",G27<>0),D27/G27,"") | J27: =IF(AND(G27<>"",G27<>0),E27/G27,"") | R27: =IF(AND(I27<>"",I27<>0),G27/I27,"") | S27: =D27/T27 -> 0 | T27: 14138 | U27: 4 | V27: 2 | W27: 16611 | X27: 3 | Y27: 3 | Z27: 0.94 | AA27: 0.94
A28: 4 | H28: =IF(AND(G28<>"",G28<>0),D28/G28,"") | J28: =IF(AND(G28<>"",G28<>0),E28/G28,"") | R28: =IF(AND(I28<>"",I28<>0),G28/I28,"") | S28: =D28/T28 -> 0 | T28: =$I$8*Z28*AA28/SUMPRODUCT($AA$25:$AA$57,$Z$25:$Z$57) -> 23720.863 | U28: =$I$9*Z28*AA28/SUMPRODUCT($AA$25:$AA$57,$Z$25:$Z$57) -> 3.2673365 | V28: =IF($I$12="","",U28/$I$12) -> 1.7757264 | W28: =IF(AA28<>"",IF(D28<>"",D28,($I$8-SUM($W$25:W27))*Z28*AA28/SUMPRODUCT($AA28:$AA$57,$Z28:$Z$57)),"") -> #REF! | X28: =IF(AA28<>"",IF(E28<>"",E28,($I$9-SUM($X$25:X27))*Z28*AA28/SUMPRODUCT($AA28:$AA$57,$Z28:$Z$57)),"") -> #REF! | Y28: =IF(AA28<>"",IF($I$12<>"",IF(G28<>"",G28,($I$9/$I$12-SUM($Y$25:Y27))*Z28*AA28/SUMPRODUCT($AA28:$AA$57,$Z28:$Z$57)),""),"") -> #REF! | Z28: 1.0579743 | AA28: 1.0579743
A29: 5 | H29: =IF(AND(G29<>"",G29<>0),D29/G29,"") | J29: =IF(AND(G29<>"",G29<>0),E29/G29,"") | R29: =IF(AND(I29<>"",I29<>0),G29/I29,"") | S29: =D29/T29 -> 0 | T29: =$I$8*Z29*AA29/SUMPRODUCT($AA$25:$AA$57,$Z$25:$Z$57) -> 21192.404 | U29: =$I$9*Z29*AA29/SUMPRODUCT($AA$25:$AA$57,$Z$25:$Z$57) -> 2.9190639 | V29: =IF($I$12="","",U29/$I$12) -> 1.5864478 | W29: =IF(AA29<>"",IF(D29<>"",D29,($I$8-SUM($W$25:W28))*Z29*AA29/SUMPRODUCT($AA29:$AA$57,$Z29:$Z$57)),"") -> #REF! | X29: =IF(AA29<>"",IF(E29<>"",E29,($I$9-SUM($X$25:X28))*Z29*AA29/SUMPRODUCT($AA29:$AA$57,$Z29:$Z$57)),"") -> #REF! | Y29: =IF(AA29<>"",IF($I$12<>"",IF(G29<>"",G29,($I$9/$I$12-SUM($Y$25:Y28))*Z29*AA29/SUMPRODUCT($AA29:$AA$57,$Z29:$Z$57)),""),"") -> #REF! | Z29: 1 | AA29: 1
