Workbook
Name маг: NA()

Sheet Центрум
B1: =TODAY()-1 -> 46031
B2: (отчетная дата) | J2: ЕЖЕДНЕВНЫЙ ОТЧЕТ О ПРОДАЖАХ
C3: Осталось до выполнения плана!!! | I3: ТРК Центрум
C4: =I8-D56 -> 3005284.9 | E4: =IF(I8<>0,C4/I8,0) -> 0.49327017
F6: Целевые показатели
F7: Показатель | I7: План | J7: Факт | K7: % выполнения | L7: Прогноз выполнения | M7: % выполнения по прогнозу | N7: Отклонение | O7: Факт аналогичного месяца прошлого года | P7: Отклонение LFL
F8: Выручка | I8: =I13*I10 -> 6092573.8 | J8: =D56 -> 3087288.9 | K8: =IF(AND(I8<>"",I8<>0,J8<>""),J8/I8,"") -> 0.50672983 | L8: =IF(SUMIF($D$25:$D$55,">=0",$T$25:$T$55)<>0,I8*D56/SUMIF($D$25:$D$55,">=0",$T$25:$T$55),0) -> 3087288.9 | M8: =L8/I8 -> 0.50672983 | N8: =IF(AND(J8<>0,J8<>"",I8<>0,I8<>""),L8-I8,"") -> -3005284.9 | O8: 343307.22 | P8: =IF(AND(O8<>"",O8<>0,L8<>"",L8<>0),-O8+L8,"") -> 2743981.7 | R8: =IF(AND(P8<>"",P8<>0,O8<>0,O8<>""),P8/O8,"") -> 7.9927875
F9: Кол-во изделий | I9: =I8/I11 -> 743.904 | J9: =E56 -> 398 | K9: =IF(AND(I9<>"",I9<>0,J9<>""),J9/I9,"") -> 0.53501527 | L9: =IF(SUMIF($E$25:$E$55,">=0",$U$25:$U$55)<>0,I9*E56/SUMIF($E$25:$E$55,">=0",$U$25:$U$55),0) -> 398 | M9: =IF(AND(I9<>"",I9<>0,L9<>"",L9<>0),L9/I9,"") -> 0.53501527 | N9: =IF(AND(J9<>0,J9<>"",I9<>0,I9<>""),L9-I9,"") -> -345.904 | O9: 104 | P9: =IF(AND(O9<>"",O9<>0,L9<>"",L9<>0),-O9+L9,"") -> 294 | R9: =IF(AND(P9<>"",P9<>0,O9<>0,O9<>""),P9/O9,"") -> 2.8269231
F10: Средний чек | I10: =I11*I12 -> 13759.2 | J10: =H56 -> 12251.146 | K10: =IF(AND(I10<>"",I10<>0,J10<>""),J10/I10,"") -> 0.89039671 | L10: =J10 -> 12251.146 | M10: =IF(AND(I10<>"",I10<>0,L10<>"",L10<>0),L10/I10,"") -> 0.89039671 | N10: =IF(AND(J10<>0,J10<>"",I10<>0,I10<>""),L10-I10,"") -> -1508.0536 | O10: 4702.8386 | P10: =IF(AND(O10<>"",O10<>0,L10<>"",L10<>0),-O10+L10,"") -> 7548.3078 | R10: =IF(AND(P10<>"",P10<>0,O10<>0,O10<>""),P10/O10,"") -> 1.6050535
F11: Средняя стоимость изделия | I11: 8190 | J11: =F56 -> 7757.0073 | K11: =IF(AND(I11<>"",I11<>0,J11<>""),J11/I11,"") -> 0.94713153 | L11: =IF(L9>0,L8/L9,"") -> 7757.0073 | M11: =IF(AND(I11<>"",I11<>0,L11<>"",L11<>0),L11/I11,"") -> 0.94713153 | N11: =IF(AND(J11<>0,J11<>"",I11<>0,I11<>""),L11-I11,"") -> -432.99274 | O11: 3301.031 | P11: =IF(AND(O11<>"",O11<>0,L11<>"",L11<>0),-O11+L11,"") -> 4455.9763 | R11: =IF(AND(P11<>"",P11<>0,O11<>0,O11<>""),P11/O11,"") -> 1.3498741
F12: Длина чека | I12: 1.68 | J12: =J56 -> 1.5793651 | K12: =IF(AND(I12<>"",I12<>0,J12<>""),J12/I12,"") -> 0.94009826 | L12: =J12 -> 1.5793651 | M12: =IF(AND(I12<>"",I12<>0,L12<>"",L12<>0),L12/I12,"") -> 0.94009826 | N12: =IF(AND(J12<>0,J12<>"",I12<>0,I12<>""),L12-I12,"") -> -0.10063492 | O12: 1.4246575 | P12: =IF(AND(O12<>"",O12<>0,L12<>"",L12<>0),-O12+L12,"") -> 0.15470755 | R12: =IF(AND(P12<>"",P12<>0,O12<>0,O12<>""),P12/O12,"") -> 0.1085928
F13: Кол-во чеков | I13: =I17*I20 -> 442.8 | J13: =G56 -> 252 | K13: =IF(AND(I13<>"",I13<>0,J13<>""),J13/I13,"") -> 0.56910569 | L13: =IF(SUMIF($G$25:$G$55,">=0",$V$25:$V$55)<>0,I13*G56/SUMIF($G$25:$G$55,">=0",$V$25:$V$55),"") -> 252 | M13: =IF(AND(I13<>"",I13<>0,L13<>"",L13<>0),L13/I13,"") -> 0.56910569 | N13: =IF(AND(J13<>0,J13<>"",I13<>0,I13<>""),L13-I13,"") -> -190.8 | O13: 73 | P13: =IF(AND(O13<>"",O13<>0,L13<>"",L13<>0),-O13+L13,"") -> 179 | R13: =IF(AND(P13<>"",P13<>0,O13<>0,O13<>""),P13/O13,"") -> 2.4520548
F14: Кол-во смен | I14: 31 | J14: 31 | K14: =IF(AND(I14<>"",I14<>0,J14<>""),J14/I14,"") -> 1 | L14: =IF(SUMIF($D$25:$D$55,">=0",$T$25:$T$55),I56*I8/SUMIF($D$25:$D$55,">=0",$T$25:$T$55),"") -> 2859.3 | N14: =IF(AND(J14<>0,J14<>"",I14<>0,I14<>""),L14-I14,"") -> 2828.3 | O14: 31 | P14: =IF(AND(O14<>"",O14<>0,L14<>"",L14<>0),-O14+L14,"") -> 2828.3 | R14: =IF(AND(P14<>"",P14<>0,O14<>0,O14<>""),P14/O14,"") -> 91.235484
F15: Средние продажи в смену | I15: =I8/I14 -> 196534.64 | J15: =J8/J14 -> 99589.964 | K15: =IF(AND(I15<>"",I15<>0,J15<>""),J15/I15,"") -> 0.50672983 | L15: =J15 -> 99589.964 | M15: =IF(AND(I15<>"",I15<>0,L15<>"",L15<>0),L15/I15,"") -> 0.50672983 | N15: =IF(AND(J15<>0,J15<>"",I15<>0,I15<>""),L15-I15,"") -> -96944.673 | O15: 11074.426 | P15: =IF(AND(O15<>"",O15<>0,L15<>"",L15<>0),-O15+L15,"") -> 88515.538 | R15: =IF(AND(P15<>"",P15<>0,O15<>0,O15<>""),P15/O15,"") -> 7.9927875
F16: Отставание/Перевыполнение | J16: =J8-I15*J14 -> -3005284.9 | K16: =IF(AND(I16<>"",I16<>0,J16<>""),J16/I16,"") | L16: =J16 -> -3005284.9 | M16: =IF(AND(I16<>"",I16<>0,L16<>"",L16<>0),L16/I16,"") | N16: =IF(AND(J16<>0,J16<>"",I16<>0,I16<>""),L16-I16,"") | O16: -182714.47 | P16: =IF(AND(O16<>"",O16<>0,L16<>"",L16<>0),-O16+L16,"") -> -2822570.4 | R16: =IF(AND(P16<>"",P16<>0,O16<>0,O16<>""),P16/O16,"") -> 15.447985 | V16: Подарочные сертификаты
F17: Трафик | I17: 3600 | J17: =I56 -> 2859.3 | K17: =IF(AND(I17<>"",I17<>0,J17<>""),J17/I17,"") -> 0.79425 | L17: =J17/J14*I14 -> 2859.3 | M17: =IF(AND(I17<>"",I17<>0,L17<>"",L17<>0),L17/I17,"") -> 0.79425 | N17: =IF(AND(J17<>0,J17<>"",I17<>0,I17<>""),L17-I17,"") -> -740.7 | O17: 381 | P17: =IF(AND(O17<>"",O17<>0,L17<>"",L17<>0),-O17+L17,"") -> 2478.3 | R17: =IF(AND(P17<>"",P17<>0,O17<>0,O17<>""),P17/O17,"") -> 6.5047244
K18: =IF(AND(I18<>"",I18<>0,J18<>""),J18/I18,"") | L18: =J18 -> 0 | M18: =IF(AND(I18<>"",I18<>0,L18<>"",L18<>0),L18/I18,"") | N18: =IF(AND(J18<>0,J18<>"",I18<>0,I18<>""),L18-I18,"") | P18: =IF(AND(O18<>"",O18<>0,L18<>"",L18<>0),-O18+L18,"") | R18: =IF(AND(P18<>"",P18<>0,O18<>0,O18<>""),P18/O18,"")
K19: =IF(AND(I19<>"",I19<>0,J19<>""),J19/I19,"") | L19: =J19 -> 0 | M19: =IF(AND(I19<>"",I19<>0,L19<>"",L19<>0),L19/I19,"") | N19: =IF(AND(J19<>0,J19<>"",I19<>0,I19<>""),L19-I19,"") | O19: 0 | P19: =IF(AND(O19<>"",O19<>0,L19<>"",L19<>0),-O19+L19,"") | R19: =IF(AND(P19<>"",P19<>0,O19<>0,O19<>""),P19/O19,"") | V19: =V18/I16 -> #DIV/0!
F20: Конверсия | I20: 0.123 | J20: =R56 -> 0.088133459 | K20: =J20/I20 -> 0.71653219 | L20: =J20/I20 -> 0.71653219 | M20: =J20/I20 -> 0.71653219 | N20: =IF(AND(J20<>0,J20<>"",I20<>0,I20<>""),L20-I20,"") -> 0.59353219 | O20: 0.19160105 | P20: =IF(AND(O20<>"",O20<>0,L20<>"",L20<>0),-O20+L20,"") -> 0.52493114 | R20: =IF(AND(P20<>"",P20<>0,O20<>0,O20<>""),P20/O20,"") -> 2.7397091
A22: Факт продаж за месяц | T22: Раcпределение плана по дням
A23: Сотрудник | B23: Дата | C23: День недели | D23: Выручка (руб) | E23: Кол-во единиц (шт.) | F23: Средняя стоимость изделия (руб.) | G23: Количество чеков (шт.) | H23: Средняя сумма чека (руб.) | I23: Трафик | J23: Длина чека (шт.) | K23: UNOde50 | L23: IS | M23: Agafi | N23: Kalliope | O23: Raganella | P23: CC/MP | Q23: Eva Rites | R23: Конверсия (%) | S23: % выполнения дневного плана | T23: выручка, план | U23: кол-во ед, план | V23: Кол-во чеков, план | W23: выручка, скорректир.план | X23: кол-во ед, скорр. план | Y23: кол-во чеков, скорр. план | Z23: Коэфф. Дня Недели | AA23: Специфика месяца
B24: 1 | C24: 2 | D24: 3 | E24: 4 | F24: 5 | G24: 6 | H24: 7 | I24: 8 | J24: 9 | K24: 10 | L24: 11 | M24: 12 | N24: 13 | O24: 14 | P24: 15 | Q24: 16 | R24: 13 | T24: 1 | U24: 2 | V24: 3 | W24: 4 | X24: 5 | Y24: 6 | Z24: 10 | AA24: 11
A25: Рогалевич, Козлова | B25: 45992 | C25: пн | D25: 13572 | E25: 2 | F25: =IF(AND(E25<>"",E25<>0),D25/E25,"") -> 6786 | G25: 1 | H25: =IF(AND(G25<>"",G25<>0),D25/G25,"") -> 13572 | I25: 64 | J25: =IF(AND(G25<>"",G25<>0),E25/G25,"") -> 2 | R25: =IF(AND(I25<>"",I25<>0),G25/I25,"") -> 0.015625 | S25: =D25/T25 -> 0.07091956 | T25: =$I$8*Z25*AA25/SUMPRODUCT($AA$25:$AA$55,$Z$25:$Z$55) -> 191371.75 | U25: =$I$9*Z25*AA25/SUMPRODUCT($AA$25:$AA$55,$Z$25:$Z$55) -> 23.366514 | V25: =IF($I$12="","",U25/$I$12) -> 13.908639 | W25: =IF(D25<>"",D25,T25) -> 13572 | X25: =IF(E25<>"",E25,U25) -> 2 | Y25: =IF(G25<>"",G25,V25) -> 1 | Z25: 0.9414554 | AA25: 0.9414554
A26: Рогалевич,Свидовская, Стекольщикова | B26: 45993 | C26: вт | D26: 88382 | E26: 10 | F26: =IF(AND(E26<>"",E26<>0),D26/E26,"") -> 8838.2 | G26: 6 | H26: =IF(AND(G26<>"",G26<>0),D26/G26,"") -> 14730.333 | I26: 103 | J26: =IF(AND(G26<>"",G26<>0),E26/G26,"") -> 1.6666667 | K26: 30744 | M26: =17684 -> 17684 | P26: 8593 | R26: =IF(AND(I26<>"",I26<>0),G26/I26,"") -> 0.058252427 | S26: =D26/T26 -> 0.56244912 | T26: =$I$8*Z26*AA26/SUMPRODUCT($AA$25:$AA$55,$Z$25:$Z$55) -> 157137.77 | U26: =$I$9*Z26*AA26/SUMPRODUCT($AA$25:$AA$55,$Z$25:$Z$55) -> 19.186541 | V26: =IF($I$12="","",U26/$I$12) -> 11.42056 | W26: =IF(AA26<>"",IF(D26<>"",D26,($I$8-SUM($W$25:W25))*Z26*AA26/SUMPRODUCT($AA26:$AA$55,$Z26:$Z$55)),"") -> 88382 | X26: =IF(AA26<>"",IF(E26<>"",E26,($I$9-SUM($X$25:X25))*Z26*AA26/SUMPRODUCT($AA26:$AA$55,$Z26:$Z$55)),"") -> 10 | Y26: =IF(AA26<>"",IF($I$12<>"",IF(G26<>"",G26,($I$9/$I$12-SUM($Y$25:Y25))*Z26*AA26/SUMPRODUCT($AA26:$AA$55,$Z26:$Z$55)),""),"") -> 6 | Z26: 0.85310234 | AA26: 0.85310234
A27: Рогалевич, Стекольщикова, Свидовская, Корж | B27: 45994 | C27: ср | D27: 74261 | E27: 7 | F27: =IF(AND(E27<>"",E27<>0),D27/E27,"") -> 10608.714 | G27: 4 | H27: =IF(AND(G27<>"",G27<>0),D27/G27,"") -> 18565.25 | I27: 90 | J27: =IF(AND(G27<>"",G27<>0),E27/G27,"") -> 1.75 | M27: 15190 | N27: =27149+5307 -> 32456 | O27: 15390 | R27: =IF(AND(I27<>"",I27<>0),G27/I27,"") -> 0.044444444 | S27: =D27/T27 -> 0.4725853 | T27: =$I$8*Z27*AA27/SUMPRODUCT($AA$25:$AA$55,$Z$25:$Z$55) -> 157137.77 | U27: =$I$9*Z27*AA27/SUMPRODUCT($AA$25:$AA$55,$Z$25:$Z$55) -> 19.186541 | V27: =IF($I$12="","",U27/$I$12) -> 11.42056 | W27: =IF(AA27<>"",IF(D27<>"",D27,($I$8-SUM($W$25:W26))*Z27*AA27/SUMPRODUCT($AA27:$AA$55,$Z27:$Z$55)),"") -> 74261 | X27: =IF(AA27<>"",IF(E27<>"",E27,($I$9-SUM($X$25:X26))*Z27*AA27/SUMPRODUCT($AA27:$AA$55,$Z27:$Z$55)),"") -> 7 | Y27: =IF(AA27<>"",IF($I$12<>"",IF(G27<>"",G27,($I$9/$I$12-SUM($Y$25:Y26))*Z27*AA27/SUMPRODUCT($AA27:$AA$55,$Z27:$Z$55)),""),"") -> 4 | Z27: 0.85310234 | AA27: 0.85310234
A28: Рогалевич, Стекольщикова,Корж, Козлова | B28: 45995 | C28: чт | D28: 165232 | E28: 18 | F28: =IF(AND(E28<>"",E28<>0),D28/E28,"") -> 9179.5556 | G28: 13 | H28: =IF(AND(G28<>"",G28<>0),D28/G28,"") -> 12710.154 | I28: 87 | J28: =IF(AND(G28<>"",G28<>0),E28/G28,"") -> 1.3846154 | K28: =32375+11493 -> 43868 | M28: =8699+10892+14992 -> 34583 | N28: 21370 | R28: =IF(AND(I28<>"",I28<>0),G28/I28,"") -> 0.14942529 | S28: =D28/T28 -> 1.0515104 | T28: =$I$8*Z28*AA28/SUMPRODUCT($AA$25:$AA$55,$Z$25:$Z$55) -> 157137.77 | U28: =$I$9*Z28*AA28/SUMPRODUCT($AA$25:$AA$55,$Z$25:$Z$55) -> 19.186541 | V28: =IF($I$12="","",U28/$I$12) -> 11.42056 | W28: =IF(AA28<>"",IF(D28<>"",D28,($I$8-SUM($W$25:W27))*Z28*AA28/SUMPRODUCT($AA28:$AA$55,$Z28:$Z$55)),"") -> 165232 | X28: =IF(AA28<>"",IF(E28<>"",E28,($I$9-SUM($X$25:X27))*Z28*AA28/SUMPRODUCT($AA28:$AA$55,$Z28:$Z$55)),"") -> 18 | Y28: =IF(AA28<>"",IF($I$12<>"",IF(G28<>"",G28,($I$9/$I$12-SUM($Y$25:Y27))*Z28*AA28/SUMPRODUCT($AA28:$AA$55,$Z28:$Z$55)),""),"") -> 13 | Z28: 0.85310234 | AA28: 0.85310234
A29: Рогалевич, Стекольщикова, Козлова | B29: 45996 | C29: пт | D29: 77191 | E29: 11 | F29: =IF(AND(E29<>"",E29<>0),D29/E29,"") -> 7017.3636 | G29: 9 | H29: =IF(AND(G29<>"",G29<>0),D29/G29,"") -> 8576.7778 | I29: 117 | J29: =IF(AND(G29<>"",G29<>0),E29/G29,"") -> 1.2222222 | M29: =15922+7493 -> 23415 | N29: 13290 | R29: =IF(AND(I29<>"",I29<>0),G29/I29,"") -> 0.076923077 | S29: =D29/T29 -> 0.49482371 | T29: =$I$8*Z29*AA29/SUMPRODUCT($AA$25:$AA$55,$Z$25:$Z$55) -> 155996.97 | U29: =$I$9*Z29*AA29/SUMPRODUCT($AA$25:$AA$55,$Z$25:$Z$55) -> 19.047249 | V29: =IF($I$12="","",U29/$I$12) -> 11.337648 | W29: =IF(AA29<>"",IF(D29<>"",D29,($I$8-SUM($W$25:W28))*Z29*AA29/SUMPRODUCT($AA29:$AA$55,$Z29:$Z$55)),"") -> 77191 | X29: =IF(AA29<>"",IF(E29<>"",E29,($I$9-SUM($X$25:X28))*Z29*AA29/SUMPRODUCT($AA29:$AA$55,$Z29:$Z$55)),"") -> 11 | Y29: =IF(AA29<>"",IF($I$12<>"",IF(G29<>"",G29,($I$9/$I$12-SUM($Y$25:Y28))*Z29*AA29/SUMPRODUCT($AA29:$AA$55,$Z29:$Z$55)),""),"") -> 9 | Z29: 0.85 | AA29: 0.85
A30: Рогалевич, Стекольщикова, Козлова, свидовская | B30: 45997 | C30: сб | D30: 165526 | E30: 20 | F30: =IF(AND(E30<>"",E30<>0),D30/E30,"") -> 8276.3 | G30: 12 | H30: =IF(AND(G30<>"",G30<>0),D30/G30,"") -> 13793.833 | I30: 144 | J30: =IF(AND(G30<>"",G30<>0),E30/G30,"") -> 1.6666667 | K30: 18990 | M30: 8082 | O30: =13390+8990 -> 22380 | P30: 19680 | R30: =IF(AND(I30<>"",I30<>0),G30/I30,"") -> 0.083333333 | S30: =D30/T30 -> 0.76663369 | T30: =$I$8*Z30*AA30/SUMPRODUCT($AA$25:$AA$55,$Z$25:$Z$55) -> 215912.76 | U30: =$I$9*Z30*AA30/SUMPRODUCT($AA$25:$AA$55,$Z$25:$Z$55) -> 26.362975 | V30: =IF($I$12="","",U30/$I$12) -> 15.692247 | W30: =IF(AA30<>"",IF(D30<>"",D30,($I$8-SUM($W$25:W29))*Z30*AA30/SUMPRODUCT($AA30:$AA$55,$Z30:$Z$55)),"") -> 165526 | X30: =IF(AA30<>"",IF(E30<>"",E30,($I$9-SUM($X$25:X29))*Z30*AA30/SUMPRODUCT($AA30:$AA$55,$Z30:$Z$55)),"") -> 20 | Y30: =IF(AA30<>"",IF($I$12<>"",IF(G30<>"",G30,($I$9/$I$12-SUM($Y$25:Y29))*Z30*AA30/SUMPRODUCT($AA30:$AA$55,$Z30:$Z$55)),""),"") -> 12 | Z30: 1 | AA30: 1
A31: Рогалевич, Корж, Свидовская | B31: 45998 | C31: вс | D31: 72565 | E31: 10 | F31: =IF(AND(E31<>"",E31<>0),D31/E31,"") -> 7256.5 | G31: 7 | H31: =IF(AND(G31<>"",G31<>0),D31/G31,"") -> 10366.429 | I31: 108 | J31: =IF(AND(G31<>"",G31<>0),E31/G31,"") -> 1.4285714 | N31: =17272+24082 -> 41354 | R31: =IF(AND(I31<>"",I31<>0),G31/I31,"") -> 0.064814815 | S31: =D31/T31 -> 0.33608481 | T31: =$I$8*Z31*AA31/SUMPRODUCT($AA$25:$AA$55,$Z$25:$Z$55) -> 215912.76 | U31: =$I$9*Z31*AA31/SUMPRODUCT($AA$25:$AA$55,$Z$25:$Z$55) -> 26.362975 | V31: =IF($I$12="","",U31/$I$12) -> 15.692247 | W31: =IF(AA31<>"",IF(D31<>"",D31,($I$8-SUM($W$25:W30))*Z31*AA31/SUMPRODUCT($AA31:$AA$55,$Z31:$Z$55)),"") -> 72565 | X31: =IF(AA31<>"",IF(E31<>"",E31,($I$9-SUM($X$25:X30))*Z31*AA31/SUMPRODUCT($AA31:$AA$55,$Z31:$Z$55)),"") -> 10 | Y31: =IF(AA31<>"",IF($I$12<>"",IF(G31<>"",G31,($I$9/$I$12-SUM($Y$25:Y30))*Z31*AA31/SUMPRODUCT($AA31:$AA$55,$Z31:$Z$55)),""),"") -> 7 | Z31: 1 | AA31: 1
A32: Свидовская, Корж | B32: 45999 | C32: пн | D32: 35971 | E32: 7 | F32: =IF(AND(E32<>"",E32<>0),D32/E32,"") -> 5138.7143 | G32: 5 | H32: =IF(AND(G32<>"",G32<>0),D32/G32,"") -> 7194.2 | I32: 80 | J32: =IF(AND(G32<>"",G32<>0),E32/G32,"") -> 1.4 | O32: 5993 | R32: =IF(AND(I32<>"",I32<>0),G32/I32,"") -> 0.0625 | S32: =D32/T32 -> 0.22891378 | T32: =$I$8*Z32*AA32/SUMPRODUCT($AA$25:$AA$55,$Z$25:$Z$55) -> 157137.77 | U32: =$I$9*Z32*AA32/SUMPRODUCT($AA$25:$AA$55,$Z$25:$Z$55) -> 19.186541 | V32: =IF($I$12="","",U32/$I$12) -> 11.42056 | W32: =IF(AA32<>"",IF(D32<>"",D32,($I$8-SUM($W$25:W31))*Z32*AA32/SUMPRODUCT($AA32:$AA$55,$Z32:$Z$55)),"") -> 35971 | X32: =IF(AA32<>"",IF(E32<>"",E32,($I$9-SUM($X$25:X31))*Z32*AA32/SUMPRODUCT($AA32:$AA$55,$Z32:$Z$55)),"") -> 7 | Y32: =IF(AA32<>"",IF($I$12<>"",IF(G32<>"",G32,($I$9/$I$12-SUM($Y$25:Y31))*Z32*AA32/SUMPRODUCT($AA32:$AA$55,$Z32:$Z$55)),""),"") -> 5 | Z32: 0.85310234 | AA32: 0.85310234
A33: Стекольщикова, Свидовская, Козлова | B33: 46000 | C33: вт | D33: 95353 | E33: 10 | F33: =IF(AND(E33<>"",E33<>0),D33/E33,"") -> 9535.3 | G33: 4 | H33: =IF(AND(G33<>"",G33<>0),D33/G33,"") -> 23838.25 | I33: 68 | J33: =IF(AND(G33<>"",G33<>0),E33/G33,"") -> 2.5 | K33: 13990 | M33: 9782 | N33: 33744 | O33: 33446 | R33: =IF(AND(I33<>"",I33<>0),G33/I33,"") -> 0.058823529 | S33: =D33/T33 -> 0.60681147 | T33: =$I$8*Z33*AA33/SUMPRODUCT($AA$25:$AA$55,$Z$25:$Z$55) -> 157137.77 | U33: =$I$9*Z33*AA33/SUMPRODUCT($AA$25:$AA$55,$Z$25:$Z$55) -> 19.186541 | V33: =IF($I$12="","",U33/$I$12) -> 11.42056 | W33: =IF(AA33<>"",IF(D33<>"",D33,($I$8-SUM($W$25:W32))*Z33*AA33/SUMPRODUCT($AA33:$AA$55,$Z33:$Z$55)),"") -> 95353 | X33: =IF(AA33<>"",IF(E33<>"",E33,($I$9-SUM($X$25:X32))*Z33*AA33/SUMPRODUCT($AA33:$AA$55,$Z33:$Z$55)),"") -> 10 | Y33: =IF(AA33<>"",IF($I$12<>"",IF(G33<>"",G33,($I$9/$I$12-SUM($Y$25:Y32))*Z33*AA33/SUMPRODUCT($AA33:$AA$55,$Z33:$Z$55)),""),"") -> 4 | Z33: 0.85310234 | AA33: 0.85310234
A34: Стекольщикова, Козлова, Корж | B34: 46001 | C34: ср | D34: 31725 | E34: 5 | F34: =IF(AND(E34<>"",E34<>0),D34/E34,"") -> 6345 | G34: 4 | H34: =IF(AND(G34<>"",G34<>0),D34/G34,"") -> 7931.25 | I34: 81 | J34: =IF(AND(G34<>"",G34<>0),E34/G34,"") -> 1.25 | P34: 15084 | R34: =IF(AND(I34<>"",I34<>0),G34/I34,"") -> 0.049382716 | S34: =D34/T34 -> 0.37675472 | T34: =$I$8*Z34*AA34/SUMPRODUCT($AA$25:$AA$55,$Z$25:$Z$55) -> 84205.978 | U34: =$I$9*Z34*AA34/SUMPRODUCT($AA$25:$AA$55,$Z$25:$Z$55) -> 10.28156 | V34: =IF($I$12="","",U34/$I$12) -> 6.1199763 | W34: =IF(AA34<>"",IF(D34<>"",D34,($I$8-SUM($W$25:W33))*Z34*AA34/SUMPRODUCT($AA34:$AA$55,$Z34:$Z$55)),"") -> 31725 | X34: =IF(AA34<>"",IF(E34<>"",E34,($I$9-SUM($X$25:X33))*Z34*AA34/SUMPRODUCT($AA34:$AA$55,$Z34:$Z$55)),"") -> 5 | Y34: =IF(AA34<>"",IF($I$12<>"",IF(G34<>"",G34,($I$9/$I$12-SUM($Y$25:Y33))*Z34*AA34/SUMPRODUCT($AA34:$AA$55,$Z34:$Z$55)),""),"") -> 4 | Z34: 0.65 | AA34: 0.6
A35: Стекольщикова, Козлова, Корж | B35: 46002 | C35: чт | D35: 17930 | E35: 3 | F35: =IF(AND(E35<>"",E35<>0),D35/E35,"") -> 5976.6667 | G35: 2 | H35: =IF(AND(G35<>"",G35<>0),D35/G35,"") -> 8965 | I35: 84 | J35: =IF(AND(G35<>"",G35<>0),E35/G35,"") -> 1.5 | M35: 14437 | R35: =IF(AND(I35<>"",I35<>0),G35/I35,"") -> 0.023809524 | S35: =D35/T35 -> 0.15817676 | T35: =$I$8*Z35*AA35/SUMPRODUCT($AA$25:$AA$55,$Z$25:$Z$55) -> 113354.2 | U35: =$I$9*Z35*AA35/SUMPRODUCT($AA$25:$AA$55,$Z$25:$Z$55) -> 13.840562 | V35: =IF($I$12="","",U35/$I$12) -> 8.2384297 | W35: =IF(AA35<>"",IF(D35<>"",D35,($I$8-SUM($W$25:W34))*Z35*AA35/SUMPRODUCT($AA35:$AA$55,$Z35:$Z$55)),"") -> 17930 | X35: =IF(AA35<>"",IF(E35<>"",E35,($I$9-SUM($X$25:X34))*Z35*AA35/SUMPRODUCT($AA35:$AA$55,$Z35:$Z$55)),"") -> 3 | Y35: =IF(AA35<>"",IF($I$12<>"",IF(G35<>"",G35,($I$9/$I$12-SUM($Y$25:Y34))*Z35*AA35/SUMPRODUCT($AA35:$AA$55,$Z35:$Z$55)),""),"") -> 2 | Z35: 0.75 | AA35: 0.7
A36: Стекольщикова, Свидовская, Козлова | B36: 46003 | C36: пт | D36: 31850 | E36: 5 | F36: =IF(AND(E36<>"",E36<>0),D36/E36,"") -> 6370 | G36: 5 | H36: =IF(AND(G36<>"",G36<>0),D36/G36,"") -> 6370 | I36: 92 | J36: =IF(AND(G36<>"",G36<>0),E36/G36,"") -> 1 | N36: 4390 | R36: =IF(AND(I36<>"",I36<>0),G36/I36,"") -> 0.054347826 | S36: =D36/T36 -> 0.20417063 | T36: =$I$8*Z36*AA36/SUMPRODUCT($AA$25:$AA$55,$Z$25:$Z$55) -> 155996.97 | U36: =$I$9*Z36*AA36/SUMPRODUCT($AA$25:$AA$55,$Z$25:$Z$55) -> 19.047249 | V36: =IF($I$12="","",U36/$I$12) -> 11.337648 | W36: =IF(AA36<>"",IF(D36<>"",D36,($I$8-SUM($W$25:W35))*Z36*AA36/SUMPRODUCT($AA36:$AA$55,$Z36:$Z$55)),"") -> 31850 | X36: =IF(AA36<>"",IF(E35<>"",E35,($I$9-SUM($X$25:X35))*Z36*AA36/SUMPRODUCT($AA36:$AA$55,$Z36:$Z$55)),"") -> 3 | Y36: =IF(AA36<>"",IF($I$12<>"",IF(G36<>"",G36,($I$9/$I$12-SUM($Y$25:Y35))*Z36*AA36/SUMPRODUCT($AA36:$AA$55,$Z36:$Z$55)),""),"") -> 5 | Z36: 0.85 | AA36: 0.85
A37: Стекольщикова, Свидовская, Корж | B37: 46004 | C37: сб | D37: 144713 | E37: 24 | F37: =IF(AND(E37<>"",E37<>0),D37/E37,"") -> 6029.7083 | G37: 12 | H37: =IF(AND(G37<>"",G37<>0),D37/G37,"") -> 12059.417 | I37: 136 | J37: =IF(AND(G37<>"",G37<>0),E37/G37,"") -> 2 | K37: =15493+13357 -> 28850 | L37: 6004.01 | N37: 7490 | O37: 11993 | P37: 6493 | R37: =IF(AND(I37<>"",I37<>0),G37/I37,"") -> 0.088235294 | S37: =D37/T37 -> 0.74264629 | T37: =$I$8*Z37*AA37/SUMPRODUCT($AA$25:$AA$55,$Z$25:$Z$55) -> 194861.27 | U37: =$I$9*Z37*AA37/SUMPRODUCT($AA$25:$AA$55,$Z$25:$Z$55) -> 23.792585 | V37: =IF($I$12="","",U37/$I$12) -> 14.162253 | W37: =IF(AA37<>"",IF(D37<>"",D37,($I$8-SUM($W$25:W36))*Z37*AA37/SUMPRODUCT($AA37:$AA$55,$Z37:$Z$55)),"") -> 144713 | X37: =IF(AA37<>"",IF(E37<>"",E37,($I$9-SUM($X$25:X36))*Z37*AA37/SUMPRODUCT($AA37:$AA$55,$Z37:$Z$55)),"") -> 24 | Y37: =IF(AA37<>"",IF($I$12<>"",IF(G37<>"",G37,($I$9/$I$12-SUM($Y$25:Y36))*Z37*AA37/SUMPRODUCT($AA37:$AA$55,$Z37:$Z$55)),""),"") -> 12 | Z37: 0.95 | AA37: 0.95
A38: Свидовская, Корж, Козлова | B38: 46005 | C38: вс | D38: 31461 | E38: 6 | F38: =IF(AND(E38<>"",E38<>0),D38/E38,"") -> 5243.5 | G38: 4 | H38: =IF(AND(G38<>"",G38<>0),D38/G38,"") -> 7865.25 | I38: 118 | J38: =IF(AND(G38<>"",G38<>0),E38/G38,"") -> 1.5 | N38: 8190 | R38: =IF(AND(I38<>"",I38<>0),G38/I38,"") -> 0.033898305 | S38: =D38/T38 -> 0.16145333 | T38: =$I$8*Z38*AA38/SUMPRODUCT($AA$25:$AA$55,$Z$25:$Z$55) -> 194861.27 | U38: =$I$9*Z38*AA38/SUMPRODUCT($AA$25:$AA$55,$Z$25:$Z$55) -> 23.792585 | V38: =IF($I$12="","",U38/$I$12) -> 14.162253 | W38: =IF(AA38<>"",IF(D38<>"",D38,($I$8-SUM($W$25:W37))*Z38*AA38/SUMPRODUCT($AA38:$AA$55,$Z38:$Z$55)),"") -> 31461 | X38: =IF(AA38<>"",IF(E38<>"",E38,($I$9-SUM($X$25:X37))*Z38*AA38/SUMPRODUCT($AA38:$AA$55,$Z38:$Z$55)),"") -> 6 | Y38: =IF(AA38<>"",IF($I$12<>"",IF(G38<>"",G38,($I$9/$I$12-SUM($Y$25:Y37))*Z38*AA38/SUMPRODUCT($AA38:$AA$55,$Z38:$Z$55)),""),"") -> 4 | Z38: 0.95 | AA38: 0.95
A39: Свидовская, Козлова | B39: 46006 | C39: пн | D39: 20868 | E39: 4 | F39: =IF(AND(E39<>"",E39<>0),D39/E39,"") -> 5217 | G39: 2 | H39: =IF(AND(G39<>"",G39<>0),D39/G39,"") -> 10434 | I39: 88 | J39: =IF(AND(G39<>"",G39<>0),E39/G39,"") -> 2 | R39: =IF(AND(I39<>"",I39<>0),G39/I39,"") -> 0.022727273 | S39: =D39/T39 -> 0.22875774 | T39: =$I$8*Z39*AA39/SUMPRODUCT($AA$25:$AA$55,$Z$25:$Z$55) -> 91223.143 | U39: =$I$9*Z39*AA39/SUMPRODUCT($AA$25:$AA$55,$Z$25:$Z$55) -> 11.138357 | V39: =IF($I$12="","",U39/$I$12) -> 6.6299743 | W39: =IF(AA39<>"",IF(D39<>"",D39,($I$8-SUM($W$25:W38))*Z39*AA39/SUMPRODUCT($AA39:$AA$55,$Z39:$Z$55)),"") -> 20868 | X39: =IF(AA39<>"",IF(E39<>"",E39,($I$9-SUM($X$25:X38))*Z39*AA39/SUMPRODUCT($AA39:$AA$55,$Z39:$Z$55)),"") -> 4 | Y39: =IF(AA39<>"",IF($I$12<>"",IF(G39<>"",G39,($I$9/$I$12-SUM($Y$25:Y38))*Z39*AA39/SUMPRODUCT($AA39:$AA$55,$Z39:$Z$55)),""),"") -> 2 | Z39: 0.65 | AA39: 0.65
A40: Стекольщикова, Козлова, Корж | B40: 46007 | C40: вт | D40: 58894 | E40: 8 | F40: =IF(AND(E40<>"",E40<>0),D40/E40,"") -> 7361.75 | G40: 6 | H40: =IF(AND(G40<>"",G40<>0),D40/G40,"") -> 9815.6667 | I40: 78 | J40: =IF(AND(G40<>"",G40<>0),E40/G40,"") -> 1.3333333 | M40: 22184 | R40: =IF(AND(I40<>"",I40<>0),G40/I40,"") -> 0.076923077 | S40: =D40/T40 -> 0.48492012 | T40: =$I$8*Z40*AA40/SUMPRODUCT($AA$25:$AA$55,$Z$25:$Z$55) -> 121450.93 | U40: =$I$9*Z40*AA40/SUMPRODUCT($AA$25:$AA$55,$Z$25:$Z$55) -> 14.829173 | V40: =IF($I$12="","",U40/$I$12) -> 8.8268889 | W40: =IF(AA40<>"",IF(D40<>"",D40,($I$8-SUM($W$25:W39))*Z40*AA40/SUMPRODUCT($AA40:$AA$55,$Z40:$Z$55)),"") -> 58894 | X40: =IF(AA40<>"",IF(E40<>"",E40,($I$9-SUM($X$25:X39))*Z40*AA40/SUMPRODUCT($AA40:$AA$55,$Z40:$Z$55)),"") -> 8 | Y40: =IF(AA40<>"",IF($I$12<>"",IF(G40<>"",G40,($I$9/$I$12-SUM($Y$25:Y39))*Z40*AA40/SUMPRODUCT($AA40:$AA$55,$Z40:$Z$55)),""),"") -> 6 | Z40: 0.75 | AA40: 0.75
A41: Стекольщикова, Козлова, Корж | B41: 46008 | C41: ср | D41: 84716 | E41: 9 | F41: =IF(AND(E41<>"",E41<>0),D41/E41,"") -> 9412.8889 | G41: 5 | H41: =IF(AND(G41<>"",G41<>0),D41/G41,"") -> 16943.2 | I41: 122 | J41: =IF(AND(G41<>"",G41<>0),E41/G41,"") -> 1.8 | O41: 41473 | R41: =IF(AND(I41<>"",I41<>0),G41/I41,"") -> 0.040983607 | S41: =D41/T41 -> 0.54306182 | T41: =$I$8*Z41*AA41/SUMPRODUCT($AA$25:$AA$55,$Z$25:$Z$55) -> 155996.97 | U41: =$I$9*Z41*AA41/SUMPRODUCT($AA$25:$AA$55,$Z$25:$Z$55) -> 19.047249 | V41: =IF($I$12="","",U41/$I$12) -> 11.337648 | W41: =IF(AA41<>"",IF(D41<>"",D41,($I$8-SUM($W$25:W40))*Z41*AA41/SUMPRODUCT($AA41:$AA$55,$Z41:$Z$55)),"") -> 84716 | X41: =IF(AA41<>"",IF(E41<>"",E41,($I$9-SUM($X$25:X40))*Z41*AA41/SUMPRODUCT($AA41:$AA$55,$Z41:$Z$55)),"") -> 9 | Y41: =IF(AA41<>"",IF($I$12<>"",IF(G41<>"",G41,($I$9/$I$12-SUM($Y$25:Y40))*Z41*AA41/SUMPRODUCT($AA41:$AA$55,$Z41:$Z$55)),""),"") -> 5 | Z41: 0.85 | AA41: 0.85
A42: Стекольщикова, Корж, Свидовская | B42: 46009 | C42: чт | D42: 70243.02 | E42: 11 | F42: =IF(AND(E42<>"",E42<>0),D42/E42,"") -> 6385.7291 | G42: 7 | H42: =IF(AND(G42<>"",G42<>0),D42/G42,"") -> 10034.717 | I42: 88 | J42: =IF(AND(G42<>"",G42<>0),E42/G42,"") -> 1.5714286 | O42: 15066 | R42: =IF(AND(I42<>"",I42<>0),G42/I42,"") -> 0.079545455 | S42: =D42/T42 -> 0.40164266 | T42: =$I$8*Z42*AA42/SUMPRODUCT($AA$25:$AA$55,$Z$25:$Z$55) -> 174889.34 | U42: =$I$9*Z42*AA42/SUMPRODUCT($AA$25:$AA$55,$Z$25:$Z$55) -> 21.35401 | V42: =IF($I$12="","",U42/$I$12) -> 12.71072 | W42: =IF(AA42<>"",IF(D42<>"",D42,($I$8-SUM($W$25:W41))*Z42*AA42/SUMPRODUCT($AA42:$AA$55,$Z42:$Z$55)),"") -> 70243.02 | X42: =IF(AA42<>"",IF(E42<>"",E42,($I$9-SUM($X$25:X41))*Z42*AA42/SUMPRODUCT($AA42:$AA$55,$Z42:$Z$55)),"") -> 11 | Y42: =IF(AA42<>"",IF($I$12<>"",IF(G42<>"",G42,($I$9/$I$12-SUM($Y$25:Y41))*Z42*AA42/SUMPRODUCT($AA42:$AA$55,$Z42:$Z$55)),""),"") -> 7 | Z42: 0.9 | AA42: 0.9
A43: Стекольщикова, Рогалевич, Козлова, Свидовская | B43: 46010 | C43: пт | D43: 176827 | E43: 21 | F43: =IF(AND(E43<>"",E43<>0),D43/E43,"") -> 8420.3333 | G43: 10 | H43: =IF(AND(G43<>"",G43<>0),D43/G43,"") -> 17682.7 | I43: 89 | J43: =IF(AND(G43<>"",G43<>0),E43/G43,"") -> 2.1 | K43: ='Доп сотрудник'!K32 -> 43070 | M43: 25272 | N43: ='Козлова В. Э.'!N37+'Стекольщикова А. А.'!N38 -> 20397 | O43: ='Стекольщикова А. А.'!O38 -> 22172 | R43: =IF(AND(I43<>"",I43<>0),G43/I43,"") -> 0.11235955 | S43: =D43/T43 -> 1.0110794 | T43: =$I$8*Z43*AA43/SUMPRODUCT($AA$25:$AA$55,$Z$25:$Z$55) -> 174889.34 | U43: =$I$9*Z43*AA43/SUMPRODUCT($AA$25:$AA$55,$Z$25:$Z$55) -> 21.35401 | V43: =IF($I$12="","",U43/$I$12) -> 12.71072 | W43: =IF(AA43<>"",IF(D43<>"",D43,($I$8-SUM($W$25:W42))*Z43*AA43/SUMPRODUCT($AA43:$AA$55,$Z43:$Z$55)),"") -> 176827 | X43: =IF(AA43<>"",IF(E43<>"",E43,($I$9-SUM($X$25:X42))*Z43*AA43/SUMPRODUCT($AA43:$AA$55,$Z43:$Z$55)),"") -> 21 | Y43: =IF(AA43<>"",IF($I$12<>"",IF(G43<>"",G43,($I$9/$I$12-SUM($Y$25:Y42))*Z43*AA43/SUMPRODUCT($AA43:$AA$55,$Z43:$Z$55)),""),"") -> 10 | Z43: 0.9 | AA43: 0.9
A44: Стекольщикова, Рогалевич, Козлова, Свидовская | B44: 46011 | C44: сб | D44: 362391 | E44: 50 | F44: =IF(AND(E44<>"",E44<>0),D44/E44,"") -> 7247.82 | G44: 25 | H44: =IF(AND(G44<>"",G44<>0),D44/G44,"") -> 14495.64 | I44: 245 | J44: =IF(AND(G44<>"",G44<>0),E44/G44,"") -> 2 | K44: ='Стекольщикова А. А.'!K39+'Доп сотрудник'!K33 -> 27250 | L44: ='Свидовская С. А.'!L37 -> 10903 | M44: ='Свидовская С. А.'!M37 -> 16470 | O44: ='Стекольщикова А. А.'!O39 -> 25611 | R44: =IF(AND(I44<>"",I44<>0),G44/I44,"") -> 0.10204082 | S44: =D44/T44 -> 1.678414 | T44: =$I$8*Z44*AA44/SUMPRODUCT($AA$25:$AA$55,$Z$25:$Z$55) -> 215912.76 | U44: =$I$9*Z44*AA44/SUMPRODUCT($AA$25:$AA$55,$Z$25:$Z$55) -> 26.362975 | V44: =IF($I$12="","",U44/$I$12) -> 15.692247 | W44: =IF(AA44<>"",IF(D44<>"",D44,($I$8-SUM($W$25:W43))*Z44*AA44/SUMPRODUCT($AA44:$AA$55,$Z44:$Z$55)),"") -> 362391 | X44: =IF(AA44<>"",IF(E44<>"",E44,($I$9-SUM($X$25:X43))*Z44*AA44/SUMPRODUCT($AA44:$AA$55,$Z44:$Z$55)),"") -> 50 | Y44: =IF(AA44<>"",IF($I$12<>"",IF(G44<>"",G44,($I$9/$I$12-SUM($Y$25:Y43))*Z44*AA44/SUMPRODUCT($AA44:$AA$55,$Z44:$Z$55)),""),"") -> 25 | Z44: 1 | AA44: 1
A45: Стекольщикова, Рогалевич, Корж | B45: 46012 | C45: вс | D45: 51540 | E45: 6 | F45: =IF(AND(E45<>"",E45<>0),D45/E45,"") -> 8590 | G45: 3 | H45: =IF(AND(G45<>"",G45<>0),D45/G45,"") -> 17180 | I45: 101 | J45: =IF(AND(G45<>"",G45<>0),E45/G45,"") -> 2 | K45: 24172 | R45: =IF(AND(I45<>"",I45<>0),G45/I45,"") -> 0.02970297 | S45: =D45/T45 -> 0.23870752 | T45: =$I$8*Z45*AA45/SUMPRODUCT($AA$25:$AA$55,$Z$25:$Z$55) -> 215912.76 | U45: =$I$9*Z45*AA45/SUMPRODUCT($AA$25:$AA$55,$Z$25:$Z$55) -> 26.362975 | V45: =IF($I$12="","",U45/$I$12) -> 15.692247 | W45: =IF(AA45<>"",IF(D45<>"",D45,($I$8-SUM($W$25:W44))*Z45*AA45/SUMPRODUCT($AA45:$AA$55,$Z45:$Z$55)),"") -> 51540 | X45: =IF(AA45<>"",IF(E45<>"",E45,($I$9-SUM($X$25:X44))*Z45*AA45/SUMPRODUCT($AA45:$AA$55,$Z45:$Z$55)),"") -> 6 | Y45: =IF(AA45<>"",IF($I$12<>"",IF(G45<>"",G45,($I$9/$I$12-SUM($Y$25:Y44))*Z45*AA45/SUMPRODUCT($AA45:$AA$55,$Z45:$Z$55)),""),"") -> 3 | Z45: 1 | AA45: 1
A46: Рогалевич, Козлова, Свидовская | B46: 46013 | C46: пн | D46: 101508 | E46: 17 | F46: =IF(AND(E46<>"",E46<>0),D46/E46,"") -> 5971.0588 | G46: 10 | H46: =IF(AND(G46<>"",G46<>0),D46/G46,"") -> 10150.8 | I46: 92 | J46: =IF(AND(G46<>"",G46<>0),E46/G46,"") -> 1.7 | Q46: ='Доп сотрудник'!P35 -> 20889 | R46: =IF(AND(I46<>"",I46<>0),G46/I46,"") -> 0.10869565 | S46: =D46/T46 -> 0.47013432 | T46: =$I$8*Z46*AA46/SUMPRODUCT($AA$25:$AA$55,$Z$25:$Z$55) -> 215912.76 | U46: =$I$9*Z46*AA46/SUMPRODUCT($AA$25:$AA$55,$Z$25:$Z$55) -> 26.362975 | V46: =IF($I$12="","",U46/$I$12) -> 15.692247 | W46: =IF(AA46<>"",IF(D46<>"",D46,($I$8-SUM($W$25:W45))*Z46*AA46/SUMPRODUCT($AA46:$AA$55,$Z46:$Z$55)),"") -> 101508 | X46: =IF(AA45<>"",IF(E45<>"",E45,($I$9-SUM($X$25:X44))*Z45*AA45/SUMPRODUCT($AA45:$AA$55,$Z45:$Z$55)),"") -> 6 | Y46: =IF(AA45<>"",IF($I$12<>"",IF(G45<>"",G45,($I$9/$I$12-SUM($Y$25:Y44))*Z45*AA45/SUMPRODUCT($AA45:$AA$55,$Z45:$Z$55)),""),"") -> 3 | Z46: 1 | AA46: 1
A47: Стекольщикова,Корж, Козлова | B47: 46014 | C47: вт | D47: 60335.5 | E47: 10 | F47: =IF(AND(E47<>"",E47<>0),D47/E47,"") -> 6033.55 | G47: 6 | H47: =IF(AND(G47<>"",G47<>0),D47/G47,"") -> 10055.917 | I47: 83 | J47: =IF(AND(G47<>"",G47<>0),E47/G47,"") -> 1.6666667 | O47: ='Козлова В. Э.'!N40 -> 7490 | R47: =IF(AND(I47<>"",I47<>0),G47/I47,"") -> 0.072289157 | S47: =D47/T47 -> 0.27944388 | T47: =$I$8*Z47*AA47/SUMPRODUCT($AA$25:$AA$55,$Z$25:$Z$55) -> 215912.76 | U47: =$I$9*Z47*AA47/SUMPRODUCT($AA$25:$AA$55,$Z$25:$Z$55) -> 26.362975 | V47: =IF($I$12="","",U47/$I$12) -> 15.692247 | W47: =IF(AA47<>"",IF(D47<>"",D47,($I$8-SUM($W$25:W46))*Z47*AA47/SUMPRODUCT($AA47:$AA$55,$Z47:$Z$55)),"") -> 60335.5 | X47: =IF(AA47<>"",IF(E47<>"",E47,($I$9-SUM($X$25:X46))*Z47*AA47/SUMPRODUCT($AA47:$AA$55,$Z47:$Z$55)),"") -> 10 | Y47: =IF(AA47<>"",IF($I$12<>"",IF(G47<>"",G47,($I$9/$I$12-SUM($Y$25:Y46))*Z47*AA47/SUMPRODUCT($AA47:$AA$55,$Z47:$Z$55)),""),"") -> 6 | Z47: 1 | AA47: 1
A48: Стекольщикова, Рогалевич, Корж, Козлова | B48: 46015 | C48: ср | D48: 108323 | E48: 9 | F48: =IF(AND(E48<>"",E48<>0),D48/E48,"") -> 12035.889 | G48: 7 | H48: =IF(AND(G48<>"",G48<>0),D48/G48,"") -> 15474.714 | I48: 80 | J48: =IF(AND(G48<>"",G48<>0),E48/G48,"") -> 1.2857143 | R48: =IF(AND(I48<>"",I48<>0),G48/I48,"") -> 0.0875 | S48: =D48/T48 -> 0.50169799 | T48: =$I$8*Z48*AA48/SUMPRODUCT($AA$25:$AA$55,$Z$25:$Z$55) -> 215912.76 | U48: =$I$9*Z48*AA48/SUMPRODUCT($AA$25:$AA$55,$Z$25:$Z$55) -> 26.362975 | V48: =IF($I$12="","",U48/$I$12) -> 15.692247 | W48: =IF(AA48<>"",IF(D48<>"",D48,($I$8-SUM($W$25:W47))*Z48*AA48/SUMPRODUCT($AA48:$AA$55,$Z48:$Z$55)),"") -> 108323 | X48: =IF(AA48<>"",IF(E48<>"",E48,($I$9-SUM($X$25:X47))*Z48*AA48/SUMPRODUCT($AA48:$AA$55,$Z48:$Z$55)),"") -> 9 | Y48: =IF(AA48<>"",IF($I$12<>"",IF(G48<>"",G48,($I$9/$I$12-SUM($Y$25:Y47))*Z48*AA48/SUMPRODUCT($AA48:$AA$55,$Z48:$Z$55)),""),"") -> 7 | Z48: 1 | AA48: 1
A49: Стекольщикова, Рогалевич, Свидовская, Корж | B49: 46016 | C49: чт | D49: 71891 | E49: 9 | F49: =IF(AND(E49<>"",E49<>0),D49/E49,"") -> 7987.8889 | G49: 7 | H49: =IF(AND(G49<>"",G49<>0),D49/G49,"") -> 10270.143 | I49: 102 | J49: =IF(AND(G49<>"",G49<>0),E49/G49,"") -> 1.2857143 | R49: =IF(AND(I49<>"",I49<>0),G49/I49,"") -> 0.068627451 | S49: =D49/T49 -> 0.33296318 | T49: =$I$8*Z49*AA49/SUMPRODUCT($AA$25:$AA$55,$Z$25:$Z$55) -> 215912.76 | U49: =$I$9*Z49*AA49/SUMPRODUCT($AA$25:$AA$55,$Z$25:$Z$55) -> 26.362975 | V49: =IF($I$12="","",U49/$I$12) -> 15.692247 | W49: =IF(AA49<>"",IF(D49<>"",D49,($I$8-SUM($W$25:W48))*Z49*AA49/SUMPRODUCT($AA49:$AA$55,$Z49:$Z$55)),"") -> 71891 | X49: =IF(AA49<>"",IF(E49<>"",E49,($I$9-SUM($X$25:X48))*Z49*AA49/SUMPRODUCT($AA49:$AA$55,$Z49:$Z$55)),"") -> 9 | Y49: =IF(AA49<>"",IF($I$12<>"",IF(G49<>"",G49,($I$9/$I$12-SUM($Y$25:Y48))*Z49*AA49/SUMPRODUCT($AA49:$AA$55,$Z49:$Z$55)),""),"") -> 7 | Z49: 1 | AA49: 1
A50: Стекольщикова, Рогалевич, Свидовская, Корж | B50: 46017 | C50: пт | D50: 98940.37 | E50: 12 | F50: =IF(AND(E50<>"",E50<>0),D50/E50,"") -> 8245.0308 | G50: 9 | H50: =IF(AND(G50<>"",G50<>0),D50/G50,"") -> 10993.374 | I50: 100 | J50: =IF(AND(G50<>"",G50<>0),E50/G50,"") -> 1.3333333 | K50: ='Корж А. А.'!K40+'Доп сотрудник'!K38 -> 38465 | O50: ='Свидовская С. А.'!O41 -> 6027.5 | Q50: ='Стекольщикова А. А.'!Q43 -> 9602 | R50: =IF(AND(I50<>"",I50<>0),G50/I50,"") -> 0.09 | S50: =D50/T50 -> 0.31822385 | T50: =$I$8*Z50*AA50/SUMPRODUCT($AA$25:$AA$55,$Z$25:$Z$55) -> 310914.38 | U50: =$I$9*Z50*AA50/SUMPRODUCT($AA$25:$AA$55,$Z$25:$Z$55) -> 37.962684 | V50: =IF($I$12="","",U50/$I$12) -> 22.596836 | W50: =IF(AA50<>"",IF(D50<>"",D50,($I$8-SUM($W$25:W49))*Z50*AA50/SUMPRODUCT($AA50:$AA$55,$Z50:$Z$55)),"") -> 98940.37 | X50: =IF(AA50<>"",IF(E50<>"",E50,($I$9-SUM($X$25:X49))*Z50*AA50/SUMPRODUCT($AA50:$AA$55,$Z50:$Z$55)),"") -> 12 | Y50: =IF(AA50<>"",IF($I$12<>"",IF(G50<>"",G50,($I$9/$I$12-SUM($Y$25:Y49))*Z50*AA50/SUMPRODUCT($AA50:$AA$55,$Z50:$Z$55)),""),"") -> 9 | Z50: 1.2 | AA50: 1.2
A51: Стекольщикова, Рогалевич,Корж, Козлова | B51: 46018 | C51: сб | D51: 159218 | E51: 16 | F51: =IF(AND(E51<>"",E51<>0),D51/E51,"") -> 9951.125 | G51: 16 | H51: =IF(AND(G51<>"",G51<>0),D51/G51,"") -> 9951.125 | I51: 113 | J51: =IF(AND(G51<>"",G51<>0),E51/G51,"") -> 1 | R51: =IF(AND(I51<>"",I51<>0),G51/I51,"") -> 0.14159292 | S51: =D51/T51 -> 0.51209597 | T51: =$I$8*Z51*AA51/SUMPRODUCT($AA$25:$AA$55,$Z$25:$Z$55) -> 310914.38 | U51: =$I$9*Z51*AA51/SUMPRODUCT($AA$25:$AA$55,$Z$25:$Z$55) -> 37.962684 | V51: =IF($I$12="","",U51/$I$12) -> 22.596836 | W51: =IF(AA51<>"",IF(D51<>"",D51,($I$8-SUM($W$25:W50))*Z51*AA51/SUMPRODUCT($AA51:$AA$55,$Z51:$Z$55)),"") -> 159218 | X51: =IF(AA51<>"",IF(E51<>"",E51,($I$9-SUM($X$25:X50))*Z51*AA51/SUMPRODUCT($AA51:$AA$55,$Z51:$Z$55)),"") -> 16 | Y51: =IF(AA51<>"",IF($I$12<>"",IF(G51<>"",G51,($I$9/$I$12-SUM($Y$25:Y50))*Z51*AA51/SUMPRODUCT($AA51:$AA$55,$Z51:$Z$55)),""),"") -> 16 | Z51: 1.2 | AA51: 1.2
A52: Стекольщикова, Рогалевич, Корж, Свидовская | B52: 46019 | C52: вс | D52: 151582 | E52: 21 | F52: =IF(AND(E52<>"",E52<>0),D52/E52,"") -> 7218.1905 | G52: 13 | H52: =IF(AND(G52<>"",G52<>0),D52/G52,"") -> 11660.154 | I52: 137 | J52: =IF(AND(G52<>"",G52<>0),E52/G52,"") -> 1.6153846 | K52: ='Стекольщикова А. А.'!K46+'Доп сотрудник'!K40 -> 39573 | M52: ='Доп сотрудник'!M40 -> 16293 | Q52: ='Доп сотрудник'!P40 -> 7093 | R52: =IF(AND(I52<>"",I52<>0),G52/I52,"") -> 0.094890511 | S52: =D52/T52 -> 0.48753615 | T52: =$I$8*Z52*AA52/SUMPRODUCT($AA$25:$AA$55,$Z$25:$Z$55) -> 310914.38 | U52: =$I$9*Z52*AA52/SUMPRODUCT($AA$25:$AA$55,$Z$25:$Z$55) -> 37.962684 | V52: =IF($I$12="","",U52/$I$12) -> 22.596836 | W52: =IF(AA52<>"",IF(D52<>"",D52,($I$8-SUM($W$25:W51))*Z52*AA52/SUMPRODUCT($AA52:$AA$55,$Z52:$Z$55)),"") -> 151582 | X52: =IF(AA52<>"",IF(E52<>"",E52,($I$9-SUM($X$25:X51))*Z52*AA52/SUMPRODUCT($AA52:$AA$55,$Z52:$Z$55)),"") -> 21 | Y52: =IF(AA52<>"",IF($I$12<>"",IF(G52<>"",G52,($I$9/$I$12-SUM($Y$25:Y51))*Z52*AA52/SUMPRODUCT($AA52:$AA$55,$Z52:$Z$55)),""),"") -> 13 | Z52: 1.2 | AA52: 1.2
A53: Стекольщикова,Свидовская,Козлова, Корж | B53: 46020 | C53: пн | D53: =162656+6203 -> 168859 | E53: 25 | F53: =IF(AND(E53<>"",E53<>0),D53/E53,"") -> 6754.36 | G53: 14 | H53: =IF(AND(G53<>"",G53<>0),D53/G53,"") -> 12061.357 | I53: 102 | J53: =IF(AND(G53<>"",G53<>0),E53/G53,"") -> 1.7857143 | L53: 6203 | R53: =IF(AND(I53<>"",I53<>0),G53/I53,"") -> 0.1372549 | S53: =D53/T53 -> 0.5431045 | T53: =$I$8*Z53*AA53/SUMPRODUCT($AA$25:$AA$55,$Z$25:$Z$55) -> 310914.38 | U53: =$I$9*Z53*AA53/SUMPRODUCT($AA$25:$AA$55,$Z$25:$Z$55) -> 37.962684 | V53: =IF($I$12="","",U53/$I$12) -> 22.596836 | W53: =IF(AA53<>"",IF(D53<>"",D53,($I$8-SUM($W$25:W52))*Z53*AA53/SUMPRODUCT($AA53:$AA$55,$Z53:$Z$55)),"") -> 168859 | X53: =IF(AA53<>"",IF(E53<>"",E53,($I$9-SUM($X$25:X52))*Z53*AA53/SUMPRODUCT($AA53:$AA$55,$Z53:$Z$55)),"") -> 25 | Y53: =IF(AA53<>"",IF($I$12<>"",IF(G53<>"",G53,($I$9/$I$12-SUM($Y$25:Y52))*Z53*AA53/SUMPRODUCT($AA53:$AA$55,$Z53:$Z$55)),""),"") -> 14 | Z53: 1.2 | AA53: 1.2
A54: Стекольщикова,Свидовская,Козлова, Корж | B54: 46021 | C54: вт | D54: 237382 | E54: 25 | F54: =IF(AND(E54<>"",E54<>0),D54/E54,"") -> 9495.28 | G54: 17 | H54: =IF(AND(G54<>"",G54<>0),D54/G54,"") -> 13963.647 | I54: 93 | J54: =IF(AND(G54<>"",G54<>0),E54/G54,"") -> 1.4705882 | K54: ='Свидовская С. А.'!K44+'Стекольщикова А. А.'!K48 -> 125557 | Q54: ='Козлова В. Э.'!Q44 -> 7785 | R54: =IF(AND(I54<>"",I54<>0),G54/I54,"") -> 0.1827957 | S54: =D54/T54 -> 0.76349637 | T54: =$I$8*Z54*AA54/SUMPRODUCT($AA$25:$AA$55,$Z$25:$Z$55) -> 310914.38 | U54: =$I$9*Z54*AA54/SUMPRODUCT($AA$25:$AA$55,$Z$25:$Z$55) -> 37.962684 | V54: =IF($I$12="","",U54/$I$12) -> 22.596836 | W54: =IF(AA54<>"",IF(D54<>"",D54,($I$8-SUM($W$25:W53))*Z54*AA54/SUMPRODUCT($AA54:$AA$55,$Z54:$Z$55)),"") -> 237382 | X54: =IF(AA54<>"",IF(E54<>"",E54,($I$9-SUM($X$25:X53))*Z54*AA54/SUMPRODUCT($AA54:$AA$55,$Z54:$Z$55)),"") -> 25 | Y54: =IF(AA54<>"",IF($I$12<>"",IF(G54<>"",G54,($I$9/$I$12-SUM($Y$25:Y53))*Z54*AA54/SUMPRODUCT($AA54:$AA$55,$Z54:$Z$55)),""),"") -> 17 | Z54: 1.2 | AA54: 1.2
A55: Стекольщикова,Свидовская,Козлова, Корж | B55: 46022 | C55: ср | D55: 58039 | E55: 7 | F55: =IF(AND(E55<>"",E55<>0),D55/E55,"") -> 8291.2857 | G55: 7 | H55: =IF(AND(G55<>"",G55<>0),D55/G55,"") -> 8291.2857 | I55: 92 | J55: =IF(AND(G55<>"",G55<>0),E55/G55,"") -> 1 | R55: =IF(AND(I55<>"",I55<>0),G55/I55,"") -> 0.076086957 | S55: =D55/T55 -> 0.26880764 | T55: =$I$8*Z55*AA55/SUMPRODUCT($AA$25:$AA$55,$Z$25:$Z$55) -> 215912.76 | U55: =$I$9*Z55*AA55/SUMPRODUCT($AA$25:$AA$55,$Z$25:$Z$55) -> 26.362975 | V55: =IF($I$12="","",U55/$I$12) -> 15.692247 | W55: =IF(AA55<>"",IF(D55<>"",D55,($I$8-SUM($W$25:W54))*Z55*AA55/SUMPRODUCT($AA55:$AA$55,$Z55:$Z$55)),"") -> 58039 | X55: =IF(AA55<>"",IF(E55<>"",E55,($I$9-SUM($X$25:X54))*Z55*AA55/SUMPRODUCT($AA55:$AA$55,$Z55:$Z$55)),"") -> 7 | Y55: =IF(AA55<>"",IF($I$12<>"",IF(G55<>"",G55,($I$9/$I$12-SUM($Y$25:Y54))*Z55*AA55/SUMPRODUCT($AA55:$AA$55,$Z55:$Z$55)),""),"") -> 7 | Z55: 1 | AA55: 1
B56: итого | D56: =SUM(D25:D55) -> 3087288.9 | E56: =SUM(E25:E55) -> 398 | F56: =IF(AND(E56<>"", E56<>0), D56/E56, "") -> 7757.0073 | G56: =SUM(G25:G55) -> 252 | H56: =IF(AND(G56<>"", G56<>0), D56/G56, "") -> 12251.146 | I56: =SUM(I25:I55)*0.9 -> 2859.3 | J56: =E56/G56 -> 1.5793651 | K56: =SUM(K25:K55) -> 434529 | L56: =SUM(L25:L55) -> 23110.01 | M56: =SUM(M25:M55) -> 203392 | N56: =SUM(N25:N55) -> 182681 | O56: =SUM(O25:O55) -> 207041.5 | P56: =SUM(P25:P55) -> 49850 | R56: =IF(AND(I56<>"",I56<>0),G56/I56,"") -> 0.088133459 | S56: =D56/T56 -> 0.50672983 | T56: =SUM(T25:T55) -> 6092573.8 | U56: =SUM(U25:U55) -> 743.904 | V56: =SUM(V25:V55) -> 442.8 | W56: =SUM(W25:W55) -> 3087288.9 | X56: =SUM(X25:X55) -> 385 | Y56: =SUM(Y25:Y55) -> 245
D57: =SUMIF(D25:D55,"",T25:T55)+D56 -> 3087288.9
D58: ='Доп сотрудник'!D48+'Свидовская С. А.'!J8+'Корж А. А.'!J8+'Козлова В. Э.'!J8+'Стекольщикова А. А.'!J8 -> 3087288.9 | I58: ='Козлова В. Э.'!I49+'Корж А. А.'!I48+'Свидовская С. А.'!I48+'Стекольщикова А. А.'!I50+'Доп сотрудник'!I48 -> 2748
D59: =SUM(D25:D31) -> 656729
D60: =SUM(D43:D46) -> 692266
D61: =SUM(D48:D52) -> 589954.37
D62: =D59+D60+D61 -> 1938949.4 | E62: =D58-D62 -> 1148339.5

Sheet Конкурс
A1: Личный ежедневный КВП, %
A3: Сотруник | B3: 45282 | C3: 45283 | D3: 45284 | E3: 45285 | F3: 45286 | G3: 45287 | H3: 45288 | I3: 45289 | J3: 45290 | K3: 45291 | L3: Итого:
A4: Доп сотрудник | B4: ='Доп сотрудник'!S35 -> 0.65039442 | D4: 0.27 | E4: 0.57 | F4: 0.73 | G4: 0.88 | H4: 0.98
A5: Стекольщикова Алла | C5: 0.25 | D5: 0.79 | E5: 0.33 | F5: 0.13 | G5: 0.75 | H5: 0.67 | I5: 0.74 | J5: 1.72 | K5: 0.33
A6: Свидовская София | B6: ='Свидовская С. А.'!R39 -> 0.64951176 | E6: 0.25 | F6: 0.25 | H6: 0.38 | I6: 1.11 | J6: 1.17 | K6: 0.34
A7: Корж Анастасия | C7: 0.33 | D7: 0.57 | E7: 0.08 | F7: 0.45 | G7: 0.4 | H7: 0.24 | I7: 0.25 | J7: 0.28 | K7: 0.23
A8: Козлова Валерия | B8: ='Козлова В. Э.'!S39 -> 0.42155461 | C8: 0.52 | D8: 0.31 | G8: 0.29 | I8: 0.49 | J8: 0.23 | K8: 0.1
A10: Личный КВП, баллы
A12: Сотруник | B12: 45282 | C12: 45283 | D12: 45284 | E12: 45285 | F12: 45286 | G12: 45287 | H12: 45288 | I12: 45289 | J12: 45290 | K12: 45291 | L12: Итого:
A13: Доп сотрудник | B13: 0 | D13: 0 | E13: 1 | F13: 1 | G13: 1 | H13: 1 | L13: =SUM(B13:K13) -> 4
A14: Стекольщикова Алла | C14: 0 | D14: 1 | E14: 0 | F14: 0 | G14: 0 | H14: 0 | I14: 0 | J14: 2 | K14: 0 | L14: =SUM(B14:K14) -> 3
A15: Свидовская София | B15: 1 | E15: 0 | F15: 0 | H15: 0 | I15: 2 | J15: 1 | K15: 1 | L15: =SUM(B15:K15) -> 5
A16: Корж Анастасия | C16: 0 | D16: 0 | E16: 0 | F16: 0 | G16: 0 | H16: 0 | I16: 0 | J16: 0 | K16: 0 | L16: =SUM(B16:K16) -> 0
A17: Козлова Валерия | B17: 0 | C17: 1 | D17: 0 | G17: 0 | I17: 0 | J17: 0 | K17: 0 | L17: =SUM(B17:K17) -> 1

Sheet Сводная
A1: Сводная по показателям
A2: Показатель | D2: =Центрум!I3 -> ТРК Центрум | G2: =График!B27 -> Свидовская София | J2: =График!B25 -> Корж Анастасия | M2: =График!B26 -> Козлова Валерия | P2: =График!B28 -> Стекольщикова Алла
D3: Факт | F3: Прогноз | G3: Факт | I3: Прогноз | J3: Факт | L3: Прогноз | M3: Факт | O3: Прогноз | P3: Факт | R3: Прогноз
A4: Выручка | D4: =Центрум!K8 -> 0.50672983 | E4: =Центрум!J8 -> 3087288.9 | F4: =Центрум!M8 -> 0.50672983 | G4: ='Свидовская С. А.'!K8 -> 0.5356874 | H4: ='Свидовская С. А.'!J8 -> 657954.52 | I4: ='Свидовская С. А.'!M8 -> 0.5528889 | J4: ='Корж А. А.'!K8 -> 0.36611769 | K4: ='Корж А. А.'!J8 -> 460812.37 | L4: ='Корж А. А.'!M8 -> 0.37639353 | M4: ='Козлова В. Э.'!K8 -> 0.35464809 | N4: ='Козлова В. Э.'!J8 -> 439907 | O4: ='Козлова В. Э.'!M8 -> 0.36559716 | P4: ='Стекольщикова А. А.'!K8 -> 0.61807695 | Q4: ='Стекольщикова А. А.'!J8 -> 875652 | R4: ='Стекольщикова А. А.'!M8 -> 0.62541458
A5: Кол-во изделий | D5: =Центрум!K9 -> 0.53501527 | E5: =Центрум!J9 -> 398 | F5: =Центрум!M9 -> 0.53501527 | G5: ='Свидовская С. А.'!K9 -> 0.58678922 | H5: ='Свидовская С. А.'!J9 -> 88 | I5: ='Свидовская С. А.'!M9 -> 0.59630055 | J5: ='Корж А. А.'!K9 -> 0.42295468 | K5: ='Корж А. А.'!J9 -> 65 | L5: ='Корж А. А.'!M9 -> 0.42831094 | M5: ='Козлова В. Э.'!K9 -> 0.3829558 | N5: ='Козлова В. Э.'!J9 -> 58 | O5: ='Козлова В. Э.'!M9 -> 0.3887622 | P5: ='Стекольщикова А. А.'!K9 -> 0.57230837 | Q5: ='Стекольщикова А. А.'!J9 -> 99 | R5: ='Стекольщикова А. А.'!M9 -> 0.57150148
A6: Средний чек | D6: =Центрум!K10 -> 0.89039671 | E6: =Центрум!J10 -> 12251.146 | F6: =Центрум!M10 -> 0.89039671 | G6: ='Свидовская С. А.'!K10 -> 0.85391504 | H6: ='Свидовская С. А.'!J10 -> 11749.188 | I6: ='Свидовская С. А.'!M10 -> 0.85391504 | J6: ='Корж А. А.'!K10 -> 0.81685898 | K6: ='Корж А. А.'!J10 -> 11239.326 | L6: ='Корж А. А.'!M10 -> 0.81685898 | M6: ='Козлова В. Э.'!K10 -> 0.81979088 | N6: ='Козлова В. Э.'!J10 -> 11279.667 | O6: ='Козлова В. Э.'!M10 -> 0.81979088 | P6: ='Стекольщикова А. А.'!K10 -> 0.9359 | Q6: ='Стекольщикова А. А.'!J10 -> 12877.235 | R6: ='Стекольщикова А. А.'!M10 -> 0.9359
A7: Средняя стоимость изделия | D7: =Центрум!K11 -> 0.94713153 | E7: =Центрум!J11 -> 7757.0073 | F7: =Центрум!M11 -> 0.94713153 | G7: ='Свидовская С. А.'!K11 -> 0.91291281 | H7: ='Свидовская С. А.'!J11 -> 7476.7559 | I7: ='Свидовская С. А.'!M11 -> 0.91291281 | J7: ='Корж А. А.'!K11 -> 0.86561918 | K7: ='Корж А. А.'!J11 -> 7089.4211 | L7: ='Корж А. А.'!M11 -> 0.86561918 | M7: ='Козлова В. Э.'!K11 -> 0.92608101 | N7: ='Козлова В. Э.'!J11 -> 7584.6034 | O7: ='Козлова В. Э.'!M11 -> 0.92608101 | P7: ='Стекольщикова А. А.'!K11 -> 1.0799719 | Q7: ='Стекольщикова А. А.'!J11 -> 8844.9697 | R7: ='Стекольщикова А. А.'!M11 -> 1.0799719
A8: Длина чека | D8: =Центрум!K12 -> 0.94009826 | E8: =Центрум!J12 -> 1.5793651 | F8: =Центрум!M12 -> 0.94009826 | G8: ='Свидовская С. А.'!K12 -> 0.93537415 | H8: ='Свидовская С. А.'!J12 -> 1.5714286 | I8: ='Свидовская С. А.'!M12 -> 0.93537415 | J8: ='Корж А. А.'!K12 -> 0.94367015 | K8: ='Корж А. А.'!J12 -> 1.5853659 | L8: ='Корж А. А.'!M12 -> 0.94367015 | M8: ='Козлова В. Э.'!K12 -> 0.88522589 | N8: ='Козлова В. Э.'!J12 -> 1.4871795 | O8: ='Козлова В. Э.'!M12 -> 0.88522589 | P8: ='Стекольщикова А. А.'!K12 -> 0.86659664 | Q8: ='Стекольщикова А. А.'!J12 -> 1.4558824 | R8: ='Стекольщикова А. А.'!M12 -> 0.86659664
A9: Кол-во чеков | D9: =Центрум!K13 -> 0.56910569 | E9: =Центрум!J13 -> 252 | F9: =Центрум!M13 -> 0.56910569 | G9: ='Свидовская С. А.'!K13 -> 0.62733103 | H9: ='Свидовская С. А.'!J13 -> 56 | I9: ='Свидовская С. А.'!M13 -> 0.6402762 | J9: ='Корж А. А.'!K13 -> 0.44820183 | K9: ='Корж А. А.'!J13 -> 41 | L9: ='Корж А. А.'!M13 -> 0.45580001 | M9: ='Козлова В. Э.'!K13 -> 0.432608 | N9: ='Козлова В. Э.'!J13 -> 39 | O9: ='Козлова В. Э.'!M13 -> 0.44105928 | P9: ='Стекольщикова А. А.'!K13 -> 0.66040918 | Q9: ='Стекольщикова А. А.'!J13 -> 68 | R9: ='Стекольщикова А. А.'!M13 -> 0.66192359
A10: Кол-во смен план/отработано | D10: =Центрум!K14 -> 1 | E10: =Центрум!J14 -> 31 | G10: ='Свидовская С. А.'!K14 -> 1 | H10: ='Свидовская С. А.'!J14 -> 21 | J10: ='Корж А. А.'!K14 -> 1 | K10: ='Корж А. А.'!J14 -> 21 | M10: ='Козлова В. Э.'!K14 -> 1 | N10: ='Козлова В. Э.'!J14 -> 21 | P10: ='Стекольщикова А. А.'!K14 -> 1 | Q10: ='Стекольщикова А. А.'!J14 -> 25
A11: Средние продажи в смену | D11: =Центрум!K15 -> 0.50672983 | E11: =Центрум!J15 -> 99589.964 | F11: =Центрум!M15 -> 0.50672983 | G11: ='Свидовская С. А.'!K15 -> 0.15941804 | H11: ='Свидовская С. А.'!J15 -> 31331.168 | I11: ='Свидовская С. А.'!M15 -> 0.15941804 | J11: ='Корж А. А.'!K15 -> 0.1116518 | K11: ='Корж А. А.'!J15 -> 21943.446 | L11: ='Корж А. А.'!M15 -> 0.1116518 | M11: ='Козлова В. Э.'!K15 -> 0.10658657 | N11: ='Козлова В. Э.'!J15 -> 20947.952 | O11: ='Козлова В. Э.'!M15 -> 0.10658657 | P11: ='Стекольщикова А. А.'!K15 -> 0.17821836 | Q11: ='Стекольщикова А. А.'!J15 -> 35026.08 | R11: ='Стекольщикова А. А.'!M15 -> 0.17821836
A12: Отставание/Перевыполнение | D12: =Центрум!J16 -> -3005284.9 | G12: ='Свидовская С. А.'!N8 -> -549161.26 | J12: ='Корж А. А.'!N8 -> -784899.46 | M12: ='Козлова В. Э.'!N8 -> -786915.97 | P12: ='Стекольщикова А. А.'!N8 -> -530688.73

Sheet Справочник магазинов
A1: МЕГА Белая Дача
A2: Гагаринский
A3: Марфино

Sheet План на день
A1: Выручка | D1: =681244 -> 681244
A2: Кол-во изделий | D2: =D1/D4 -> 83.179976
A3: Средний чек | D3: =D4*D5 -> 13759.2
A4: Средняя стоимость изделия | D4: =Центрум!I11 -> 8190
A5: Длина чека | D5: =Центрум!I12 -> 1.68
A6: Кол-во чеков | D6: =IF(D5<>0,D2/D5,"") -> 49.51189
A7: Конверсия | D7: =Центрум!I20 -> 0.123

Sheet Козлова В. Э.
B1: =TODAY()-1 -> 46031
B2: (отчетная дата) | J2: ЕЖЕДНЕВНЫЙ ОТЧЕТ О ПРОДАЖАХ
B3: Осталось до выполнения плана!!! | J3: =График!B26 -> Козлова Валерия
C4: =I8-D49 -> 800497.24 | E4: =IF(I8<>0,C4/I8,0) -> 0.64535191
F6: Целевые показатели
F7: Показатель | I7: План | J7: Факт | K7: % выполнения | L7: Прогноз выполнения | M7: % выполнения по прогнозу | N7: Отклонение | O7: Факт аналогичного месяца прошлого года | P7: Отклонение LFL
F8: Выручка | I8: =Центрум!I8/График!AJ29*График!AJ26 -> 1240404.2 | J8: =D49 -> 439907 | K8: =IF(AND(I8<>"",I8<>0,J8<>""),J8/I8,"") -> 0.35464809 | L8: =IF(SUMIF($D$25:$D$47,">=0",$T$25:$T$47)<>0,I8*D49/SUMIF($D$25:$D$47,">=0",$T$25:$T$47),0) -> 453488.27 | M8: =L8/I8 -> 0.36559716 | N8: =IF(AND(J8<>0,J8<>"",I8<>0,I8<>""),L8-I8,"") -> -786915.97 | P8: =IF(AND(O8<>"",O8<>0,L8<>"",L8<>0),-O8+L8,"") | Q8: =IF(AND(P8<>"",P8<>0,O8<>0,O8<>""),P8/O8,"")
F9: Кол-во изделий | I9: =I8/I11 -> 151.45351 | J9: =E49 -> 58 | K9: =IF(AND(I9<>"",I9<>0,J9<>""),J9/I9,"") -> 0.3829558 | L9: =IF(SUMIF($E$25:$E$47,">=0",$U$25:$U$47)<>0,I9*E49/SUMIF($E$25:$E$47,">=0",$U$25:$U$47),0) -> 58.879399 | M9: =IF(AND(I9<>"",I9<>0,L9<>"",L9<>0),L9/I9,"") -> 0.3887622 | N9: =IF(AND(J9<>0,J9<>"",I9<>0,I9<>""),L9-I9,"") -> -92.57411 | O9: =O8/O11 -> #DIV/0! | P9: =IF(AND(O9<>"",O9<>0,L9<>"",L9<>0),-O9+L9,"") -> #DIV/0! | Q9: =IF(AND(P9<>"",P9<>0,O9<>0,O9<>""),P9/O9,"") -> #DIV/0!
F10: Средний чек | I10: =I11*I12 -> 13759.2 | J10: =H49 -> 11279.667 | K10: =IF(AND(I10<>"",I10<>0,J10<>""),J10/I10,"") -> 0.81979088 | L10: =J10 -> 11279.667 | M10: =IF(AND(I10<>"",I10<>0,L10<>"",L10<>0),L10/I10,"") -> 0.81979088 | N10: =IF(AND(J10<>0,J10<>"",I10<>0,I10<>""),L10-I10,"") -> -2479.5333 | O10: =O11*O12 -> 0 | P10: =IF(AND(O10<>"",O10<>0,L10<>"",L10<>0),-O10+L10,"") | Q10: =IF(AND(P10<>"",P10<>0,O10<>0,O10<>""),P10/O10,"")
F11: Средняя стоимость изделия | I11: =Центрум!I11 -> 8190 | J11: =F49 -> 7584.6034 | K11: =IF(AND(I11<>"",I11<>0,J11<>""),J11/I11,"") -> 0.92608101 | L11: =J11 -> 7584.6034 | M11: =IF(AND(I11<>"",I11<>0,L11<>"",L11<>0),L11/I11,"") -> 0.92608101 | N11: =IF(AND(J11<>0,J11<>"",I11<>0,I11<>""),L11-I11,"") -> -605.39655 | P11: =IF(AND(O11<>"",O11<>0,L11<>"",L11<>0),-O11+L11,"") | Q11: =IF(AND(P11<>"",P11<>0,O11<>0,O11<>""),P11/O11,"")
F12: Длина чека | I12: =Центрум!I12 -> 1.68 | J12: =J49 -> 1.4871795 | K12: =IF(AND(I12<>"",I12<>0,J12<>""),J12/I12,"") -> 0.88522589 | L12: =J12 -> 1.4871795 | M12: =IF(AND(I12<>"",I12<>0,L12<>"",L12<>0),L12/I12,"") -> 0.88522589 | N12: =IF(AND(J12<>0,J12<>"",I12<>0,I12<>""),L12-I12,"") -> -0.19282051 | P12: =IF(AND(O12<>"",O12<>0,L12<>"",L12<>0),-O12+L12,"") | Q12: =IF(AND(P12<>"",P12<>0,O12<>0,O12<>""),P12/O12,"")
F13: Кол-во чеков | I13: =IF(I12<>0,I9/I12,"") -> 90.150898 | J13: =G49 -> 39 | K13: =IF(AND(I13<>"",I13<>0,J13<>""),J13/I13,"") -> 0.432608 | L13: =IF(SUMIF($G$25:$G$47,">=0",$V$25:$V$47)<>0,I13*G49/SUMIF($G$25:$G$47,">=0",$V$25:$V$47),"") -> 39.76189 | M13: =IF(AND(I13<>"",I13<>0,L13<>"",L13<>0),L13/I13,"") -> 0.44105928 | N13: =IF(AND(J13<>0,J13<>"",I13<>0,I13<>""),L13-I13,"") -> -50.389008 | P13: =IF(AND(O13<>"",O13<>0,L13<>"",L13<>0),-O13+L13,"") | Q13: =IF(AND(P13<>"",P13<>0,O13<>0,O13<>""),P13/O13,"")
F14: Кол-во смен план/отработано | I14: =График!AI26 -> 21 | J14: 21 | K14: =IF(AND(I14<>"",I14<>0,J14<>""),J14/I14,"") -> 1 | L14: =IF(SUMIF($D$25:$D$47,">=0",$T$25:$T$47),I49*I8/SUMIF($D$25:$D$47,">=0",$T$25:$T$47),"") -> 598.93724 | N14: =IF(AND(J14<>0,J14<>"",I14<>0,I14<>""),L14-I14,"") -> 577.93724 | P14: =IF(AND(O14<>"",O14<>0,L14<>"",L14<>0),-O14+L14,"") | Q14: =IF(AND(P14<>"",P14<>0,O14<>0,O14<>""),P14/O14,"")
F15: Средние продажи в смену | I15: =Центрум!I15 -> 196534.64 | J15: =J8/J14 -> 20947.952 | K15: =IF(AND(I15<>"",I15<>0,J15<>""),J15/I15,"") -> 0.10658657 | L15: =J15 -> 20947.952 | M15: =IF(AND(I15<>"",I15<>0,L15<>"",L15<>0),L15/I15,"") -> 0.10658657 | N15: =IF(AND(J15<>0,J15<>"",I15<>0,I15<>""),L15-I15,"") -> -175586.69 | P15: =IF(AND(O15<>"",O15<>0,L15<>"",L15<>0),-O15+L15,"") | Q15: =IF(AND(P15<>"",P15<>0,O15<>0,O15<>""),P15/O15,"")
F16: Отставание/Перевыполнение | J16: =J8-I15*J14 -> -3687320.4 | K16: =IF(AND(I16<>"",I16<>0,J16<>""),J16/I16,"") | L16: =J16 -> -3687320.4 | M16: =IF(AND(I16<>"",I16<>0,L16<>"",L16<>0),L16/I16,"") | N16: =IF(AND(J16<>0,J16<>"",I16<>0,I16<>""),L16-I16,"") | P16: =IF(AND(O16<>"",O16<>0,L16<>"",L16<>0),-O16+L16,"") | Q16: =IF(AND(P16<>"",P16<>0,O16<>0,O16<>""),P16/O16,"") | S16: Подарочные сертификаты
F17: Трафик | I17: =Центрум!I17/График!AJ29*График!AJ26 -> 732.93413 | J17: =I49 -> 581 | K17: =IF(AND(I17<>"",I17<>0,J17<>""),J17/I17,"") -> 0.79270425 | L17: =J17/J14*I14 -> 581 | M17: =IF(AND(I17<>"",I17<>0,L17<>"",L17<>0),L17/I17,"") -> 0.79270425 | N17: =IF(AND(J17<>0,J17<>"",I17<>0,I17<>""),L17-I17,"") -> -151.93413 | P17: =IF(AND(O17<>"",O17<>0,L17<>"",L17<>0),-O17+L17,"") | Q17: =IF(AND(P17<>"",P17<>0,O17<>0,O17<>""),P17/O17,"")
K18: =IF(AND(I18<>"",I18<>0,J18<>""),J18/I18,"") | L18: =J18 -> 0 | M18: =IF(AND(I18<>"",I18<>0,L18<>"",L18<>0),L18/I18,"") | N18: =IF(AND(J18<>0,J18<>"",I18<>0,I18<>""),L18-I18,"") | O18: 0 | P18: =IF(AND(O18<>"",O18<>0,L18<>"",L18<>0),-O18+L18,"") | Q18: =IF(AND(P18<>"",P18<>0,O18<>0,O18<>""),P18/O18,"")
J19: =P49 -> 0 | K19: =IF(AND(I19<>"",I19<>0,J19<>""),J19/I19,"") | L19: =J19 -> 0 | M19: =IF(AND(I19<>"",I19<>0,L19<>"",L19<>0),L19/I19,"") | N19: =IF(AND(J19<>0,J19<>"",I19<>0,I19<>""),L19-I19,"") | O19: 0 | P19: =IF(AND(O19<>"",O19<>0,L19<>"",L19<>0),-O19+L19,"") | Q19: =IF(AND(P19<>"",P19<>0,O19<>0,O19<>""),P19/O19,"") | S19: =S18/I16 -> #DIV/0!
F20: Конверсия план/факт | I20: =Центрум!I20 -> 0.123 | J20: =R49 -> 0.067125645 | K20: =J20/I20 -> 0.54573695 | L20: =IF(AND(K8<>0,I14<>0,I49<>0),(I49*R49+(I49/K8-I49)*I20)/(I49/K8),0) -> 0.10318427 | M20: =IF(AND(I20<>"",I20<>0,L20<>"",L20<>0),L20/I20,"") -> 0.83889648 | N20: =IF(AND(J20<>0,J20<>"",I20<>0,I20<>""),L20-I20,"") -> -0.019815733 | P20: =IF(AND(O20<>"",O20<>0,L20<>"",L20<>0),-O20+L20,"") | Q20: =IF(AND(P20<>"",P20<>0,O20<>0,O20<>""),P20/O20,"")
B22: Факт продаж за месяц | S22: % выполнения дневного плана | T22: Раcпределение плана по дням
B23: Дата | C23: День недели | D23: Выручка (руб) | E23: Кол-во единиц (шт.) | F23: Средняя стоимость изделия (руб.) | G23: Количество чеков (шт.) | H23: Средняя сумма чека (руб.) | I23: Трафик | J23: Длина чека (шт.) | K23: UNOde50 | L23: IS | M23: Agafi | N23: Kalliope | O23: Raganella | P23: CC/MP | Q23: Eva Rites | R23: Конверсия (%) | T23: выручка, план | U23: кол-во ед, план | V23: Кол-во чеков, план | W23: выручка, скорректир.план | X23: кол-во ед, скорр. план | Y23: кол-во чеков, скорр. план | Z23: Коэфф. Дня Недели | AA23: Специфика месяца
B24: 1 | C24: 2 | D24: 3 | E24: в | F24: 5 | G24: 6 | H24: 7 | I24: 8 | J24: 9 | K24: 10 | L24: 11 | M24: 12 | N24: 13 | O24: 14 | P24: 15 | R24: 13 | T24: 1 | U24: 2 | V24: 3 | W24: 4 | X24: 5 | Y24: 6 | Z24: 10 | AA24: 11
A25: 1 | B25: 45992 | C25: пн | D25: 13572 | E25: 2 | F25: =IF(AND(E25<>"",E25<>0),D25/E25,"") -> 6786 | G25: 1 | H25: =IF(AND(G25<>"",G25<>0),D25/G25,"") -> 13572 | I25: 32 | J25: =IF(AND(G25<>"",G25<>0),E25/G25,"") -> 2 | R25: =IF(AND(I25<>"",I25<>0),G25/I25,"") -> 0.03125 | S25: =D25/T25 -> 0.23382946 | T25: =$I$8*Z25*AA25/SUMPRODUCT($AA$25:$AA$56,$Z$25:$Z$56) -> 58042.302 | U25: =$I$9*Z25*AA25/SUMPRODUCT($AA$25:$AA$56,$Z$25:$Z$56) -> 7.0869722 | V25: =IF($I$12="","",U25/$I$12) -> 4.2184358 | W25: =IF(AA25<>"",IF(D25<>"",D25,($I$8-SUM($W24:W$25))*Z25*AA25/SUMPRODUCT($AA25:$AA$56,$Z25:$Z$56)),"") -> 13572 | X25: =IF(AA25<>"",IF(E25<>"",E25,($I$9-SUM($X24:X$25))*Z25*AA25/SUMPRODUCT($AA25:$AA$56,$Z25:$Z$56)),"") -> 2 | Y25: =IF(AA25<>"",IF($I$12<>"",IF(G25<>"",G25,($I$9/$I$12-SUM($Y24:Y$25))*Z25*AA25/SUMPRODUCT($AA25:$AA$56,$Z25:$Z$56)),""),"") -> 1 | Z25: 1 | AA25: 1
A26: 2 | B26: 45995 | C26: чт | D26: 11892 | E26: 2 | F26: =IF(AND(E26<>"",E26<>0),D26/E26,"") -> 5946 | G26: 2 | H26: =IF(AND(G26<>"",G26<>0),D26/G26,"") -> 5946 | I26: 21 | J26: =IF(AND(G26<>"",G26<>0),E26/G26,"") -> 1 | M26: 8699 | R26: =IF(AND(I26<>"",I26<>0),G26/I26,"") -> 0.095238095 | S26: =D26/T26 -> 0.28151919 | T26: =$I$8*Z26*AA26/SUMPRODUCT($AA$25:$AA$56,$Z$25:$Z$56) -> 42242.235 | U26: =$I$9*Z26*AA26/SUMPRODUCT($AA$25:$AA$56,$Z$25:$Z$56) -> 5.1577821 | V26: =IF($I$12="","",U26/$I$12) -> 3.0701084 | W26: =IF(AA26<>"",IF(D26<>"",D26,($I$8-SUM($W$25:W25))*Z26*AA26/SUMPRODUCT($AA26:$AA$56,$Z26:$Z$56)),"") -> 11892 | X26: =IF(AA26<>"",IF(E26<>"",E26,($I$9-SUM($X$25:X25))*Z26*AA26/SUMPRODUCT($AA26:$AA$56,$Z26:$Z$56)),"") -> 2 | Y26: =IF(AA26<>"",IF($I$12<>"",IF(G26<>"",G26,($I$9/$I$12-SUM($Y$25:Y25))*Z26*AA26/SUMPRODUCT($AA26:$AA$56,$Z26:$Z$56)),""),"") -> 2 | Z26: 0.85310234 | AA26: 0.85310234
A27: 3 | B27: 45996 | C27: пт | D27: 27997 | E27: 3 | F27: =IF(AND(E27<>"",E27<>0),D27/E27,"") -> 9332.3333 | G27: 3 | H27: =IF(AND(G27<>"",G27<>0),D27/G27,"") -> 9332.3333 | I27: 39 | J27: =IF(AND(G27<>"",G27<>0),E27/G27,"") -> 1 | M27: 15922 | R27: =IF(AND(I27<>"",I27<>0),G27/I27,"") -> 0.076923077 | S27: =D27/T27 -> 1.9802659 | T27: 14138 | U27: 4 | V27: 2 | W27: 16611 | X27: 3 | Y27: 3 | Z27: 0.94 | AA27: 0.94
A28: 4 | B28: 45997 | C28: сб | D28: 16020 | E28: 3 | F28: =IF(AND(E28<>"",E28<>0),D28/E28,"") -> 5340 | G28: 2 | H28: =IF(AND(G28<>"",G28<>0),D28/G28,"") -> 8010 | I28: 36 | J28: =IF(AND(G28<>"",G28<>0),E28/G28,"") -> 1.5 | R28: =IF(AND(I28<>"",I28<>0),G28/I28,"") -> 0.055555556 | S28: =D28/T28 -> 0.24658554 | T28: =$I$8*Z28*AA28/SUMPRODUCT($AA$25:$AA$56,$Z$25:$Z$56) -> 64967.312 | U28: =$I$9*Z28*AA28/SUMPRODUCT($AA$25:$AA$56,$Z$25:$Z$56) -> 7.9325167 | V28: =IF($I$12="","",U28/$I$12) -> 4.7217361 | W28: =IF(AA28<>"",IF(D28<>"",D28,($I$8-SUM($W$25:W27))*Z28*AA28/SUMPRODUCT($AA28:$AA$56,$Z28:$Z$56)),"") -> 16020 | X28: =IF(AA28<>"",IF(E28<>"",E28,($I$9-SUM($X$25:X27))*Z28*AA28/SUMPRODUCT($AA28:$AA$56,$Z28:$Z$56)),"") -> 3 | Y28: =IF(AA28<>"",IF($I$12<>"",IF(G28<>"",G28,($I$9/$I$12-SUM($Y$25:Y27))*Z28*AA28/SUMPRODUCT($AA28:$AA$56,$Z28:$Z$56)),""),"") -> 2 | Z28: 1.0579743 | AA28: 1.0579743
A29: 5 | B29: 46000 | C29: вт | D29: 47734 | E29: 5 | F29: =IF(AND(E29<>"",E29<>0),D29/E29,"") -> 9546.8 | G29: 1 | H29: =IF(AND(G29<>"",G29<>0),D29/G29,"") -> 47734 | I29: 22 | J29: =IF(AND(G29<>"",G29<>0),E29/G29,"") -> 5 | K29: 13990 | M29: 9782 | N29: 33744 | R29: =IF(AND(I29<>"",I29<>0),G29/I29,"") -> 0.045454545 | S29: =D29/T29 -> 0.82240018 | T29: =$I$8*Z29*AA29/SUMPRODUCT($AA$25:$AA$56,$Z$25:$Z$56) -> 58042.302 | U29: =$I$9*Z29*AA29/SUMPRODUCT($AA$25:$AA$56,$Z$25:$Z$56) -> 7.0869722 | V29: =IF($I$12="","",U29/$I$12) -> 4.2184358 | W29: =IF(AA29<>"",IF(D29<>"",D29,($I$8-SUM($W$25:W28))*Z29*AA29/SUMPRODUCT($AA29:$AA$56,$Z29:$Z$56)),"") -> 47734 | X29: =IF(AA29<>"",IF(E29<>"",E29,($I$9-SUM($X$25:X28))*Z29*AA29/SUMPRODUCT($AA29:$AA$56,$Z29:$Z$56)),"") -> 5 | Y29: =IF(AA29<>"",IF($I$12<>"",IF(G29<>"",G29,($I$9/$I$12-SUM($Y$25:Y28))*Z29*AA29/SUMPRODUCT($AA29:$AA$56,$Z29:$Z$56)),""),"") -> 1 | Z29: 1 | AA29: 1
A30: 6 | B30: 46001 | C30: ср | D30: 0 | E30: 0 | F30: =IF(AND(E30<>"",E30<>0),D30/E30,"") | G30: 0 | H30: =IF(AND(G30<>"",G30<>0),D30/G30,"") | I30: 27 | J30: =IF(AND(G30<>"",G30<>0),E30/G30,"") | R30: =IF(AND(I30<>"",I30<>0),G30/I30,"") -> 0 | S30: =D30/T30 -> 0 | T30: =$I$8*Z30*AA30/SUMPRODUCT($AA$25:$AA$56,$Z$25:$Z$56) -> 58042.302 | U30: =$I$9*Z30*AA30/SUMPRODUCT($AA$25:$AA$56,$Z$25:$Z$56) -> 7.0869722 | V30: =IF($I$12="","",U30/$I$12) -> 4.2184358 | W30: =IF(AA30<>"",IF(D30<>"",D30,($I$8-SUM($W$25:W29))*Z30*AA30/SUMPRODUCT($AA30:$AA$56,$Z30:$Z$56)),"") -> 0 | X30: =IF(AA30<>"",IF(E30<>"",E30,($I$9-SUM($X$25:X29))*Z30*AA30/SUMPRODUCT($AA30:$AA$56,$Z30:$Z$56)),"") -> 0 | Y30: =IF(AA30<>"",IF($I$12<>"",IF(G30<>"",G30,($I$9/$I$12-SUM($Y$25:Y29))*Z30*AA30/SUMPRODUCT($AA30:$AA$56,$Z30:$Z$56)),""),"") -> 0 | Z30: 1 | AA30: 1
A31: 7 | B31: 46002 | C31: чт | D31: 17930 | E31: 3 | F31: =IF(AND(E31<>"",E31<>0),D31/E31,"") -> 5976.6667 | G31: 2 | H31: =IF(AND(G31<>"",G31<>0),D31/G31,"") -> 8965 | I31: 28 | J31: =IF(AND(G31<>"",G31<>0),E31/G31,"") -> 1.5 | M31: 14437 | R31: =IF(AND(I31<>"",I31<>0),G31/I31,"") -> 0.071428571 | S31: =D31/T31 -> 0.30891263 | T31: =$I$8*Z31*AA31/SUMPRODUCT($AA$25:$AA$56,$Z$25:$Z$56) -> 58042.302 | U31: =$I$9*Z31*AA31/SUMPRODUCT($AA$25:$AA$56,$Z$25:$Z$56) -> 7.0869722 | V31: =IF($I$12="","",U31/$I$12) -> 4.2184358 | W31: =IF(AA31<>"",IF(D31<>"",D31,($I$8-SUM($W$25:W30))*Z31*AA31/SUMPRODUCT($AA31:$AA$56,$Z31:$Z$56)),"") -> 17930 | X31: =IF(AA31<>"",IF(E31<>"",E31,($I$9-SUM($X$25:X30))*Z31*AA31/SUMPRODUCT($AA31:$AA$56,$Z31:$Z$56)),"") -> 3 | Y31: =IF(AA31<>"",IF($I$12<>"",IF(G31<>"",G31,($I$9/$I$12-SUM($Y$25:Y30))*Z31*AA31/SUMPRODUCT($AA31:$AA$56,$Z31:$Z$56)),""),"") -> 2 | Z31: 1 | AA31: 1
A32: 8 | B32: 46003 | C32: пт | D32: 0 | E32: 0 | F32: =IF(AND(E32<>"",E32<>0),D32/E32,"") | G32: 0 | H32: =IF(AND(G32<>"",G32<>0),D32/G32,"") | I32: 31 | J32: =IF(AND(G32<>"",G32<>0),E32/G32,"") | R32: =IF(AND(I32<>"",I32<>0),G32/I32,"") -> 0 | S32: =D32/T32 -> 0 | T32: =$I$8*Z32*AA32/SUMPRODUCT($AA$25:$AA$56,$Z$25:$Z$56) -> 58042.302 | U32: =$I$9*Z32*AA32/SUMPRODUCT($AA$25:$AA$56,$Z$25:$Z$56) -> 7.0869722 | V32: =IF($I$12="","",U32/$I$12) -> 4.2184358 | W32: =IF(AA32<>"",IF(D32<>"",D32,($I$8-SUM($W$25:W31))*Z32*AA32/SUMPRODUCT($AA32:$AA$56,$Z32:$Z$56)),"") -> 0 | X32: =IF(AA32<>"",IF(E32<>"",E32,($I$9-SUM($X$25:X31))*Z32*AA32/SUMPRODUCT($AA32:$AA$56,$Z32:$Z$56)),"") -> 0 | Y32: =IF(AA32<>"",IF($I$12<>"",IF(G32<>"",G32,($I$9/$I$12-SUM($Y$25:Y31))*Z32*AA32/SUMPRODUCT($AA32:$AA$56,$Z32:$Z$56)),""),"") -> 0 | Z32: 1 | AA32: 1
A33: 9 | B33: 46005 | C33: вс | D33: 10120 | E33: 2 | F33: =IF(AND(E33<>"",E33<>0),D33/E33,"") -> 5060 | G33: 1 | H33: =IF(AND(G33<>"",G33<>0),D33/G33,"") -> 10120 | I33: 40 | J33: =IF(AND(G33<>"",G33<>0),E33/G33,"") -> 2 | R33: =IF(AND(I33<>"",I33<>0),G33/I33,"") -> 0.025 | S33: =D33/T33 -> 0.17435559 | T33: =$I$8*Z33*AA33/SUMPRODUCT($AA$25:$AA$56,$Z$25:$Z$56) -> 58042.302 | U33: =$I$9*Z33*AA33/SUMPRODUCT($AA$25:$AA$56,$Z$25:$Z$56) -> 7.0869722 | V33: =IF($I$12="","",U33/$I$12) -> 4.2184358 | W33: =IF(AA33<>"",IF(D33<>"",D33,($I$8-SUM($W$25:W32))*Z33*AA33/SUMPRODUCT($AA33:$AA$56,$Z33:$Z$56)),"") -> 10120 | X33: =IF(AA33<>"",IF(E33<>"",E33,($I$9-SUM($X$25:X32))*Z33*AA33/SUMPRODUCT($AA33:$AA$56,$Z33:$Z$56)),"") -> 2 | Y33: =IF(AA33<>"",IF($I$12<>"",IF(G33<>"",G33,($I$9/$I$12-SUM($Y$25:Y32))*Z33*AA33/SUMPRODUCT($AA33:$AA$56,$Z33:$Z$56)),""),"") -> 1 | Z33: 1 | AA33: 1
A34: 10 | B34: 46006 | C34: пн | D34: 0 | E34: 0 | F34: =IF(AND(E34<>"",E34<>0),D34/E34,"") | G34: 0 | H34: =IF(AND(G34<>"",G34<>0),D34/G34,"") | I34: 44 | J34: =IF(AND(G34<>"",G34<>0),E34/G34,"") | R34: =IF(AND(I34<>"",I34<>0),G34/I34,"") -> 0 | S34: =D34/T34 -> 0 | T34: =$I$8*Z34*AA34/SUMPRODUCT($AA$25:$AA$56,$Z$25:$Z$56) -> 58042.302 | U34: =$I$9*Z34*AA34/SUMPRODUCT($AA$25:$AA$56,$Z$25:$Z$56) -> 7.0869722 | V34: =IF($I$12="","",U34/$I$12) -> 4.2184358 | W34: =IF(AA34<>"",IF(D34<>"",D34,($I$8-SUM($W$25:W33))*Z34*AA34/SUMPRODUCT($AA34:$AA$56,$Z34:$Z$56)),"") -> 0 | X34: =IF(AA34<>"",IF(E34<>"",E34,($I$9-SUM($X$25:X33))*Z34*AA34/SUMPRODUCT($AA34:$AA$56,$Z34:$Z$56)),"") -> 0 | Y34: =IF(AA34<>"",IF($I$12<>"",IF(G34<>"",G34,($I$9/$I$12-SUM($Y$25:Y33))*Z34*AA34/SUMPRODUCT($AA34:$AA$56,$Z34:$Z$56)),""),"") -> 0 | Z34: 1 | AA34: 1
A35: 11 | B35: 46007 | C35: вт | D35: 6982 | E35: 1 | F35: =IF(AND(E35<>"",E35<>0),D35/E35,"") -> 6982 | G35: 1 | H35: =IF(AND(G35<>"",G35<>0),D35/G35,"") -> 6982 | I35: 26 | J35: =IF(AND(G35<>"",G35<>0),E35/G35,"") -> 1 | R35: =IF(AND(I35<>"",I35<>0),G35/I35,"") -> 0.038461538 | S35: =D35/T35 -> 0.12029158 | T35: =$I$8*Z35*AA35/SUMPRODUCT($AA$25:$AA$56,$Z$25:$Z$56) -> 58042.302 | U35: =$I$9*Z35*AA35/SUMPRODUCT($AA$25:$AA$56,$Z$25:$Z$56) -> 7.0869722 | V35: =IF($I$12="","",U35/$I$12) -> 4.2184358 | W35: =IF(AA35<>"",IF(D35<>"",D35,($I$8-SUM($W$25:W34))*Z35*AA35/SUMPRODUCT($AA35:$AA$56,$Z35:$Z$56)),"") -> 6982 | X35: =IF(AA35<>"",IF(E35<>"",E35,($I$9-SUM($X$25:X34))*Z35*AA35/SUMPRODUCT($AA35:$AA$56,$Z35:$Z$56)),"") -> 1 | Y35: =IF(AA35<>"",IF($I$12<>"",IF(G35<>"",G35,($I$9/$I$12-SUM($Y$25:Y34))*Z35*AA35/SUMPRODUCT($AA35:$AA$56,$Z35:$Z$56)),""),"") -> 1 | Z35: 1 | AA35: 1
A36: 12 | B36: 46008 | C36: ср | D36: =41473+14185+7493 -> 63151 | E36: 6 | F36: =IF(AND(E36<>"",E36<>0),D36/E36,"") -> 10525.167 | G36: 3 | H36: =IF(AND(G36<>"",G36<>0),D36/G36,"") -> 21050.333 | I36: 40 | J36: =IF(AND(G36<>"",G36<>0),E36/G36,"") -> 2 | O36: 41473 | R36: =IF(AND(I36<>"",I36<>0),G36/I36,"") -> 0.075 | S36: =D36/T36 -> 1.0880168 | T36: =$I$8*Z36*AA36/SUMPRODUCT($AA$25:$AA$56,$Z$25:$Z$56) -> 58042.302 | U36: =$I$9*Z36*AA36/SUMPRODUCT($AA$25:$AA$56,$Z$25:$Z$56) -> 7.0869722 | V36: =IF($I$12="","",U36/$I$12) -> 4.2184358 | W36: =IF(AA36<>"",IF(D36<>"",D36,($I$8-SUM($W$25:W35))*Z36*AA36/SUMPRODUCT($AA36:$AA$56,$Z36:$Z$56)),"") -> 63151 | X36: =IF(AA36<>"",IF(E36<>"",E36,($I$9-SUM($X$25:X35))*Z36*AA36/SUMPRODUCT($AA36:$AA$56,$Z36:$Z$56)),"") -> 6 | Y36: =IF(AA36<>"",IF($I$12<>"",IF(G36<>"",G36,($I$9/$I$12-SUM($Y$25:Y35))*Z36*AA36/SUMPRODUCT($AA36:$AA$56,$Z36:$Z$56)),""),"") -> 3 | Z36: 1 | AA36: 1
A37: 13 | B37: 46010 | C37: пт | D37: 16056 | E37: 3 | F37: =IF(AND(E37<>"",E37<>0),D37/E37,"") -> 5352 | G37: 2 | H37: =IF(AND(G37<>"",G37<>0),D37/G37,"") -> 8028 | I37: 22 | J37: =IF(AND(G37<>"",G37<>0),E37/G37,"") -> 1.5 | N37: 14707 | R37: =IF(AND(I37<>"",I37<>0),G37/I37,"") -> 0.090909091 | S37: =D37/T37 -> 0.27662583 | T37: =$I$8*Z37*AA37/SUMPRODUCT($AA$25:$AA$56,$Z$25:$Z$56) -> 58042.302 | U37: =$I$9*Z37*AA37/SUMPRODUCT($AA$25:$AA$56,$Z$25:$Z$56) -> 7.0869722 | V37: =IF($I$12="","",U37/$I$12) -> 4.2184358 | W37: =IF(AA37<>"",IF(D37<>"",D37,($I$8-SUM($W$25:W36))*Z37*AA37/SUMPRODUCT($AA37:$AA$56,$Z37:$Z$56)),"") -> 16056 | X37: =IF(AA37<>"",IF(E37<>"",E37,($I$9-SUM($X$25:X36))*Z37*AA37/SUMPRODUCT($AA37:$AA$56,$Z37:$Z$56)),"") -> 3 | Y37: =IF(AA37<>"",IF($I$12<>"",IF(G37<>"",G37,($I$9/$I$12-SUM($Y$25:Y36))*Z37*AA37/SUMPRODUCT($AA37:$AA$56,$Z37:$Z$56)),""),"") -> 2 | Z37: 1 | AA37: 1
A38: 14 | B38: 46011 | C38: сб | D38: =6298+6589+12354+5894+24676+12482 -> 68293 | E38: =1+1+2+1+3+1 -> 9 | F38: =IF(AND(E38<>"",E38<>0),D38/E38,"") -> 7588.1111 | G38: 6 | H38: =IF(AND(G38<>"",G38<>0),D38/G38,"") -> 11382.167 | I38: 62 | J38: =IF(AND(G38<>"",G38<>0),E38/G38,"") -> 1.5 | R38: =IF(AND(I38<>"",I38<>0),G38/I38,"") -> 0.096774194 | S38: =D38/T38 -> 1.1766074 | T38: =$I$8*Z38*AA38/SUMPRODUCT($AA$25:$AA$46,$Z$25:$Z$46) -> 58042.302 | U38: =$I$9*Z38*AA38/SUMPRODUCT($AA$25:$AA$46,$Z$25:$Z$46) -> 7.0869722 | V38: =IF($I$12="","",U38/$I$12) -> 4.2184358 | W38: =IF(AA38<>"",IF(D38<>"",D38,($I$8-SUM($W$25:W37))*Z38*AA38/SUMPRODUCT($AA38:$AA$56,$Z38:$Z$56)),"") -> 68293 | X38: =IF(AA38<>"",IF(E38<>"",E38,($I$9-SUM($X$25:X37))*Z38*AA38/SUMPRODUCT($AA38:$AA$56,$Z38:$Z$56)),"") -> 9 | Y38: =IF(AA38<>"",IF($I$12<>"",IF(G38<>"",G38,($I$9/$I$12-SUM($Y$25:Y37))*Z38*AA38/SUMPRODUCT($AA38:$AA$56,$Z38:$Z$56)),""),"") -> 6 | Z38: 1 | AA38: 1
A39: 15 | B39: 46013 | C39: пн | D39: =10684+13784 -> 24468 | E39: =2 -> 2 | F39: =IF(AND(E39<>"",E39<>0),D39/E39,"") -> 12234 | G39: 1 | H39: =IF(AND(G39<>"",G39<>0),D39/G39,"") -> 24468 | I39: 40 | J39: =IF(AND(G39<>"",G39<>0),E39/G39,"") -> 2 | R39: =IF(AND(I39<>"",I39<>0),G39/I39,"") -> 0.025 | S39: =D39/T39 -> 0.42155461 | T39: =$I$8*Z39*AA39/SUMPRODUCT($AA$25:$AA$46,$Z$25:$Z$46) -> 58042.302 | U39: =$I$9*Z39*AA39/SUMPRODUCT($AA$25:$AA$46,$Z$25:$Z$46) -> 7.0869722 | V39: =IF($I$12="","",U39/$I$12) -> 4.2184358 | W39: =IF(AA39<>"",IF(D39<>"",D39,($I$8-SUM($W$25:W38))*Z39*AA39/SUMPRODUCT($AA39:$AA$56,$Z39:$Z$56)),"") -> 24468 | X39: =IF(AA39<>"",IF(E39<>"",E39,($I$9-SUM($X$25:X38))*Z39*AA39/SUMPRODUCT($AA39:$AA$56,$Z39:$Z$56)),"") -> 2 | Y39: =IF(AA39<>"",IF($I$12<>"",IF(G39<>"",G39,($I$9/$I$12-SUM($Y$25:Y38))*Z39*AA39/SUMPRODUCT($AA39:$AA$56,$Z39:$Z$56)),""),"") -> 1 | Z39: 1 | AA39: 1
A40: 16 | B40: 46014 | C40: вт | D40: =13784+4593+10974 -> 29351 | E40: 5 | F40: =IF(AND(E40<>"",E40<>0),D40/E40,"") -> 5870.2 | G40: 3 | H40: =IF(AND(G40<>"",G40<>0),D40/G40,"") -> 9783.6667 | I40: 23 | J40: =IF(AND(G40<>"",G40<>0),E40/G40,"") -> 1.6666667 | N40: 7490 | R40: =IF(AND(I40<>"",I40<>0),G40/I40,"") -> 0.13043478 | S40: =D40/T40 -> 0.50568291 | T40: =$I$8*Z40*AA40/SUMPRODUCT($AA$25:$AA$46,$Z$25:$Z$46) -> 58042.302 | U40: =$I$9*Z40*AA40/SUMPRODUCT($AA$25:$AA$46,$Z$25:$Z$46) -> 7.0869722 | V40: =IF($I$12="","",U40/$I$12) -> 4.2184358 | W40: =IF(AA40<>"",IF(D40<>"",D40,($I$8-SUM($W$25:W39))*Z40*AA40/SUMPRODUCT($AA40:$AA$56,$Z40:$Z$56)),"") -> 29351 | X40: =IF(AA40<>"",IF(E40<>"",E40,($I$9-SUM($X$25:X39))*Z40*AA40/SUMPRODUCT($AA40:$AA$56,$Z40:$Z$56)),"") -> 5 | Y40: =IF(AA40<>"",IF($I$12<>"",IF(G40<>"",G40,($I$9/$I$12-SUM($Y$25:Y39))*Z40*AA40/SUMPRODUCT($AA40:$AA$56,$Z40:$Z$56)),""),"") -> 3 | Z40: 1 | AA40: 1
A41: 17 | B41: 46015 | C41: ср | D41: =4693+13084 -> 17777 | E41: =1+2 -> 3 | F41: =IF(AND(E41<>"",E41<>0),D41/E41,"") -> 5925.6667 | G41: 2 | H41: =IF(AND(G41<>"",G41<>0),D41/G41,"") -> 8888.5 | I41: 20 | J41: =IF(AND(G41<>"",G41<>0),E41/G41,"") -> 1.5 | R41: =IF(AND(I41<>"",I41<>0),G41/I41,"") -> 0.1 | S41: =D41/T41 -> 0.30627662 | T41: =$I$8*Z41*AA41/SUMPRODUCT($AA$25:$AA$46,$Z$25:$Z$46) -> 58042.302 | U41: =$I$9*Z41*AA41/SUMPRODUCT($AA$25:$AA$46,$Z$25:$Z$46) -> 7.0869722 | V41: =IF($I$12="","",U41/$I$12) -> 4.2184358 | W41: =IF(AA41<>"",IF(D41<>"",D41,($I$8-SUM($W$25:W40))*Z41*AA41/SUMPRODUCT($AA41:$AA$56,$Z41:$Z$56)),"") -> 17777 | X41: =IF(AA41<>"",IF(E41<>"",E41,($I$9-SUM($X$25:X40))*Z41*AA41/SUMPRODUCT($AA41:$AA$56,$Z41:$Z$56)),"") -> 3 | Y41: =IF(AA41<>"",IF($I$12<>"",IF(G41<>"",G41,($I$9/$I$12-SUM($Y$25:Y40))*Z41*AA41/SUMPRODUCT($AA41:$AA$56,$Z41:$Z$56)),""),"") -> 2 | Z41: 1 | AA41: 1
A42: 18 | B42: 46018 | C42: сб | D42: =10482+6074 -> 16556 | E42: 2 | F42: =IF(AND(E42<>"",E42<>0),D42/E42,"") -> 8278 | G42: 2 | H42: =IF(AND(G42<>"",G42<>0),D42/G42,"") -> 8278 | I42: 28 | J42: =IF(AND(G42<>"",G42<>0),E42/G42,"") -> 1 | M42: 10482 | R42: =IF(AND(I42<>"",I42<>0),G42/I42,"") -> 0.071428571 | S42: =D42/T42 -> 0.28524024 | T42: =$I$8*Z42*AA42/SUMPRODUCT($AA$25:$AA$46,$Z$25:$Z$46) -> 58042.302 | U42: =$I$9*Z42*AA42/SUMPRODUCT($AA$25:$AA$46,$Z$25:$Z$46) -> 7.0869722 | V42: =IF($I$12="","",U42/$I$12) -> 4.2184358 | W42: =IF(AA42<>"",IF(D42<>"",D42,($I$8-SUM($W$25:W41))*Z42*AA42/SUMPRODUCT($AA42:$AA$56,$Z42:$Z$56)),"") -> 16556 | X42: =IF(AA42<>"",IF(E42<>"",E42,($I$9-SUM($X$25:X41))*Z42*AA42/SUMPRODUCT($AA42:$AA$56,$Z42:$Z$56)),"") -> 2 | Y42: =IF(AA42<>"",IF($I$12<>"",IF(G42<>"",G42,($I$9/$I$12-SUM($Y$25:Y41))*Z42*AA42/SUMPRODUCT($AA42:$AA$56,$Z42:$Z$56)),""),"") -> 2 | Z42: 1 | AA42: 1
A43: 19 | B43: 46020 | C43: пн | D43: =4193+5001+4582+14184 -> 27960 | E43: 4 | F43: =IF(AND(E43<>"",E43<>0),D43/E43,"") -> 6990 | G43: 4 | H43: =IF(AND(G43<>"",G43<>0),D43/G43,"") -> 6990 | J43: =IF(AND(G43<>"",G43<>0),E43/G43,"") -> 1 | R43: =IF(AND(I43<>"",I43<>0),G43/I43,"") | S43: =D43/T43 -> 0.48171763 | T43: =$I$8*Z43*AA43/SUMPRODUCT($AA$25:$AA$46,$Z$25:$Z$46) -> 58042.302 | U43: =$I$9*Z43*AA43/SUMPRODUCT($AA$25:$AA$46,$Z$25:$Z$46) -> 7.0869722 | V43: =IF($I$12="","",U43/$I$12) -> 4.2184358 | W43: =IF(AA43<>"",IF(D43<>"",D43,($I$8-SUM($W$25:W42))*Z43*AA43/SUMPRODUCT($AA43:$AA$56,$Z43:$Z$56)),"") -> 27960 | X43: =IF(AA43<>"",IF(E43<>"",E43,($I$9-SUM($X$25:X42))*Z43*AA43/SUMPRODUCT($AA43:$AA$56,$Z43:$Z$56)),"") -> 4 | Y43: =IF(AA43<>"",IF($I$12<>"",IF(G43<>"",G43,($I$9/$I$12-SUM($Y$25:Y42))*Z43*AA43/SUMPRODUCT($AA43:$AA$56,$Z43:$Z$56)),""),"") -> 4 | Z43: 1 | AA43: 1
A44: 20 | B44: 46021 | C44: вт | D44: =8081+7785 -> 15866 | E44: 2 | F44: =IF(AND(E44<>"",E44<>0),D44/E44,"") -> 7933 | G44: 2 | H44: =IF(AND(G44<>"",G44<>0),D44/G44,"") -> 7933 | J44: =IF(AND(G44<>"",G44<>0),E44/G44,"") -> 1 | Q44: 7785 | R44: =IF(AND(I44<>"",I44<>0),G44/I44,"") | S44: =D44/T44 -> 0.22779363 | T44: =$I$8*Z44*AA44/SUMPRODUCT($AA$25:$AA$46,$Z$25:$Z$46) -> 69650.763 | U44: =$I$9*Z44*AA44/SUMPRODUCT($AA$25:$AA$46,$Z$25:$Z$46) -> 8.5043666 | V44: =IF($I$12="","",U44/$I$12) -> 5.062123 | W44: =IF(AA44<>"",IF(D44<>"",D44,($I$8-SUM($W$25:W43))*Z44*AA44/SUMPRODUCT($AA44:$AA$56,$Z44:$Z$56)),"") -> 15866 | X44: =IF(AA44<>"",IF(E44<>"",E44,($I$9-SUM($X$25:X43))*Z44*AA44/SUMPRODUCT($AA44:$AA$56,$Z44:$Z$56)),"") -> 2 | Y44: =IF(AA44<>"",IF($I$12<>"",IF(G44<>"",G44,($I$9/$I$12-SUM($Y$25:Y43))*Z44*AA44/SUMPRODUCT($AA44:$AA$56,$Z44:$Z$56)),""),"") -> 2 | Z44: 1.2 | AA44: 1
A45: 21 | B45: 46022 | C45: ср | D45: =8182 -> 8182 | E45: 1 | F45: =IF(AND(E45<>"",E45<>0),D45/E45,"") -> 8182 | G45: 1 | H45: =IF(AND(G45<>"",G45<>0),D45/G45,"") -> 8182 | J45: =IF(AND(G45<>"",G45<>0),E45/G45,"") -> 1 | R45: =IF(AND(I45<>"",I45<>0),G45/I45,"") | S45: =D45/T45 -> 0.097893161 | T45: =$I$8*Z45*AA45/SUMPRODUCT($AA$25:$AA$46,$Z$25:$Z$46) -> 83580.915 | U45: =$I$9*Z45*AA45/SUMPRODUCT($AA$25:$AA$46,$Z$25:$Z$46) -> 10.20524 | V45: =IF($I$12="","",U45/$I$12) -> 6.0745476 | W45: =IF(AA45<>"",IF(D45<>"",D45,($I$8-SUM($W$25:W44))*Z45*AA45/SUMPRODUCT($AA45:$AA$56,$Z45:$Z$56)),"") -> 8182 | X45: =IF(AA45<>"",IF(E45<>"",E45,($I$9-SUM($X$25:X44))*Z45*AA45/SUMPRODUCT($AA45:$AA$56,$Z45:$Z$56)),"") -> 1 | Y45: =IF(AA45<>"",IF($I$12<>"",IF(G45<>"",G45,($I$9/$I$12-SUM($Y$25:Y44))*Z45*AA45/SUMPRODUCT($AA45:$AA$56,$Z45:$Z$56)),""),"") -> 1 | Z45: 1.2 | AA45: 1.2
F46: =IF(AND(E46<>"",E46<>0),D46/E46,"") | H46: =IF(AND(G46<>"",G46<>0),D46/G46,"") | J46: =IF(AND(G46<>"",G46<>0),E46/G46,"") | R46: =IF(AND(I46<>"",I46<>0),G46/I46,"") | S46: =D46/T46 -> #DIV/0! | T46: =$I$8*Z46*AA46/SUMPRODUCT($AA$25:$AA$46,$Z$25:$Z$46) -> 0 | U46: =$I$9*Z46*AA46/SUMPRODUCT($AA$25:$AA$46,$Z$25:$Z$46) -> 0 | V46: =IF($I$12="","",U46/$I$12) -> 0 | W46: =IF(AA46<>"",IF(D46<>"",D46,($I$8-SUM($W$25:W45))*Z46*AA46/SUMPRODUCT($AA46:$AA$56,$Z46:$Z$56)),"") | X46: =IF(AA46<>"",IF(E46<>"",E46,($I$9-SUM($X$25:X45))*Z46*AA46/SUMPRODUCT($AA46:$AA$56,$Z46:$Z$56)),"") | Y46: =IF(AA46<>"",IF($I$12<>"",IF(G46<>"",G46,($I$9/$I$12-SUM($Y$25:Y45))*Z46*AA46/SUMPRODUCT($AA46:$AA$56,$Z46:$Z$56)),""),"")
F47: =IF(AND(E47<>"",E47<>0),D47/E47,"") | H47: =IF(AND(G47<>"",G47<>0),D47/G47,"") | J47: =IF(AND(G47<>"",G47<>0),E47/G47,"") | R47: =IF(AND(I47<>"",I47<>0),G47/I47,"") | S47: =D47/T47 -> #DIV/0! | T47: =$I$8*Z47*AA47/SUMPRODUCT($AA$25:$AA$46,$Z$25:$Z$46) -> 0 | U47: =$I$9*Z47*AA47/SUMPRODUCT($AA$25:$AA$46,$Z$25:$Z$46) -> 0 | V47: =IF($I$12="","",U47/$I$12) -> 0 | W47: =IF(AA47<>"",IF(D47<>"",D47,($I$8-SUM($W$25:W46))*Z47*AA47/SUMPRODUCT($AA47:$AA$56,$Z47:$Z$56)),"") | X47: =IF(AA47<>"",IF(E47<>"",E47,($I$9-SUM($X$25:X46))*Z47*AA47/SUMPRODUCT($AA47:$AA$56,$Z47:$Z$56)),"") | Y47: =IF(AA47<>"",IF($I$12<>"",IF(G47<>"",G47,($I$9/$I$12-SUM($Y$25:Y46))*Z47*AA47/SUMPRODUCT($AA47:$AA$56,$Z47:$Z$56)),""),"")
F48: =IF(AND(E48<>"",E48<>0),D48/E48,"") | H48: =IF(AND(G48<>"",G48<>0),D48/G48,"") | J48: =IF(AND(G48<>"",G48<>0),E48/G48,"") | R48: =IF(AND(I48<>"",I48<>0),G48/I48,"") | S48: =D48/T48 -> #DIV/0! | T48: =$I$8*Z48*AA48/SUMPRODUCT($AA$25:$AA$46,$Z$25:$Z$46) -> 0 | U48: =$I$9*Z48*AA48/SUMPRODUCT($AA$25:$AA$46,$Z$25:$Z$46) -> 0 | V48: =IF($I$12="","",U48/$I$12) -> 0 | W48: =IF(AA48<>"",IF(D48<>"",D48,($I$8-SUM($W$25:W47))*Z48*AA48/SUMPRODUCT($AA48:$AA$56,$Z48:$Z$56)),"") | X48: =IF(AA48<>"",IF(E48<>"",E48,($I$9-SUM($X$25:X47))*Z48*AA48/SUMPRODUCT($AA48:$AA$56,$Z48:$Z$56)),"") | Y48: =IF(AA48<>"",IF($I$12<>"",IF(G48<>"",G48,($I$9/$I$12-SUM($Y$25:Y47))*Z48*AA48/SUMPRODUCT($AA48:$AA$56,$Z48:$Z$56)),""),"")
B49: итого | D49: =SUM(D25:D47) -> 439907 | E49: =SUM(E25:E47) -> 58 | F49: =IF(AND(E49<>"",E49<>0),D49/E49,"") -> 7584.6034 | G49: =SUM(G25:G47) -> 39 | H49: =IF(AND(G49<>"",G49<>0),D49/G49,"") -> 11279.667 | I49: =SUM(I25:I47) -> 581 | J49: =IF(AND(G49<>"",G49<>0),E49/G49,"") -> 1.4871795 | K49: =SUM(K25:K47) -> 13990 | O49: =SUM(O25:O47) -> 41473 | P49: =SUM(P25:P47) -> 0 | Q49: =SUM(Q25:Q47) -> 7785 | R49: =IF(AND(I49<>"",I49<>0),G49/I49,"") -> 0.067125645 | S49: =D49/T49 -> 0.36559716 | T49: =SUM(T25:T47) -> 1203256.1 | U49: =SUM(U25:U47) -> 149.19146 | V49: =SUM(V25:V47) -> 88.423488 | W49: =SUM(W25:W47) -> 428521 | X49: =SUM(X25:X47) -> 58 | Y49: =SUM(Y25:Y47) -> 39
D50: =SUMIF(D25:D47,"",T25:T47)+D49 -> 439907

Sheet Корж А. А.
B1: =TODAY()-1 -> 46031
B2: (отчетная дата) | J2: ЕЖЕДНЕВНЫЙ ОТЧЕТ О ПРОДАЖАХ
B3: Осталось до выполнения плана!!! | J3: =График!B25 -> Корж Анастасия
C4: =I8-D48 -> 797833.11 | E4: =IF(I8<>0,C4/I8,0) -> 0.63388231
F6: Целевые показатели
F7: Показатель | I7: План | J7: Факт | K7: % выполнения | L7: Прогноз выполнения | M7: % выполнения по прогнозу | N7: Отклонение | O7: Факт аналогичного месяца прошлого года | P7: Отклонение LFL
F8: Выручка | I8: =Центрум!I8/График!AJ29*График!AJ25 -> 1258645.5 | J8: =D48 -> 460812.37 | K8: =IF(AND(I8<>"",I8<>0,J8<>""),J8/I8,"") -> 0.36611769 | L8: =IF(SUMIF($D$25:$D$47,">=0",$S$25:$S$47)<>0,I8*D48/SUMIF($D$25:$D$47,">=0",$S$25:$S$47),0) -> 473746.01 | M8: =L8/I8 -> 0.37639353 | N8: =IF(AND(J8<>0,J8<>"",I8<>0,I8<>""),L8-I8,"") -> -784899.46 | P8: =IF(AND(O8<>"",O8<>0,L8<>"",L8<>0),-O8+L8,"") | Q8: =IF(AND(P8<>"",P8<>0,O8<>0,O8<>""),P8/O8,"")
F9: Кол-во изделий | I9: =I8/I11 -> 153.68077 | J9: =E48 -> 65 | K9: =IF(AND(I9<>"",I9<>0,J9<>""),J9/I9,"") -> 0.42295468 | L9: =IF(SUMIF($E$25:$E$47,">=0",$T$25:$T$47)<>0,I9*E48/SUMIF($E$25:$E$47,">=0",$T$25:$T$47),0) -> 65.823153 | M9: =IF(AND(I9<>"",I9<>0,L9<>"",L9<>0),L9/I9,"") -> 0.42831094 | N9: =IF(AND(J9<>0,J9<>"",I9<>0,I9<>""),L9-I9,"") -> -87.857613 | O9: =O8/O11 -> #DIV/0! | P9: =IF(AND(O9<>"",O9<>0,L9<>"",L9<>0),-O9+L9,"") -> #DIV/0! | Q9: =IF(AND(P9<>"",P9<>0,O9<>0,O9<>""),P9/O9,"") -> #DIV/0!
F10: Средний чек | I10: =I11*I12 -> 13759.2 | J10: =H48 -> 11239.326 | K10: =IF(AND(I10<>"",I10<>0,J10<>""),J10/I10,"") -> 0.81685898 | L10: =J10 -> 11239.326 | M10: =IF(AND(I10<>"",I10<>0,L10<>"",L10<>0),L10/I10,"") -> 0.81685898 | N10: =IF(AND(J10<>0,J10<>"",I10<>0,I10<>""),L10-I10,"") -> -2519.8739 | O10: =O11*O12 -> 0 | P10: =IF(AND(O10<>"",O10<>0,L10<>"",L10<>0),-O10+L10,"") | Q10: =IF(AND(P10<>"",P10<>0,O10<>0,O10<>""),P10/O10,"")
F11: Средняя стоимость изделия | I11: =Центрум!I11 -> 8190 | J11: =F48 -> 7089.4211 | K11: =IF(AND(I11<>"",I11<>0,J11<>""),J11/I11,"") -> 0.86561918 | L11: =J11 -> 7089.4211 | M11: =IF(AND(I11<>"",I11<>0,L11<>"",L11<>0),L11/I11,"") -> 0.86561918 | N11: =IF(AND(J11<>0,J11<>"",I11<>0,I11<>""),L11-I11,"") -> -1100.5789 | P11: =IF(AND(O11<>"",O11<>0,L11<>"",L11<>0),-O11+L11,"") | Q11: =IF(AND(P11<>"",P11<>0,O11<>0,O11<>""),P11/O11,"")
F12: Длина чека | I12: =Центрум!I12 -> 1.68 | J12: =J48 -> 1.5853659 | K12: =IF(AND(I12<>"",I12<>0,J12<>""),J12/I12,"") -> 0.94367015 | L12: =J12 -> 1.5853659 | M12: =IF(AND(I12<>"",I12<>0,L12<>"",L12<>0),L12/I12,"") -> 0.94367015 | N12: =IF(AND(J12<>0,J12<>"",I12<>0,I12<>""),L12-I12,"") -> -0.094634146 | P12: =IF(AND(O12<>"",O12<>0,L12<>"",L12<>0),-O12+L12,"") | Q12: =IF(AND(P12<>"",P12<>0,O12<>0,O12<>""),P12/O12,"")
F13: Кол-во чеков | I13: =IF(I12<>0,I9/I12,"") -> 91.476647 | J13: =G48 -> 41 | K13: =IF(AND(I13<>"",I13<>0,J13<>""),J13/I13,"") -> 0.44820183 | L13: =IF(SUMIF($G$25:$G$47,">=0",$U$25:$U$47)<>0,I13*G48/SUMIF($G$25:$G$47,">=0",$U$25:$U$47),"") -> 41.695057 | M13: =IF(AND(I13<>"",I13<>0,L13<>"",L13<>0),L13/I13,"") -> 0.45580001 | N13: =IF(AND(J13<>0,J13<>"",I13<>0,I13<>""),L13-I13,"") -> -49.78159 | P13: =IF(AND(O13<>"",O13<>0,L13<>"",L13<>0),-O13+L13,"") | Q13: =IF(AND(P13<>"",P13<>0,O13<>0,O13<>""),P13/O13,"")
F14: Кол-во смен план/отработано | I14: =График!AI25 -> 21 | J14: 21 | K14: =IF(AND(I14<>"",I14<>0,J14<>""),J14/I14,"") -> 1 | L14: =IF(SUMIF($D$25:$D$47,">=0",$S$25:$S$47),I48*I8/SUMIF($D$25:$D$47,">=0",$S$25:$S$47),"") -> 538.70713 | N14: =IF(AND(J14<>0,J14<>"",I14<>0,I14<>""),L14-I14,"") -> 517.70713 | P14: =IF(AND(O14<>"",O14<>0,L14<>"",L14<>0),-O14+L14,"") | Q14: =IF(AND(P14<>"",P14<>0,O14<>0,O14<>""),P14/O14,"")
F15: Средние продажи в смену | I15: =Центрум!I15 -> 196534.64 | J15: =J8/J14 -> 21943.446 | K15: =IF(AND(I15<>"",I15<>0,J15<>""),J15/I15,"") -> 0.1116518 | L15: =J15 -> 21943.446 | M15: =IF(AND(I15<>"",I15<>0,L15<>"",L15<>0),L15/I15,"") -> 0.1116518 | N15: =IF(AND(J15<>0,J15<>"",I15<>0,I15<>""),L15-I15,"") -> -174591.19 | P15: =IF(AND(O15<>"",O15<>0,L15<>"",L15<>0),-O15+L15,"") | Q15: =IF(AND(P15<>"",P15<>0,O15<>0,O15<>""),P15/O15,"")
F16: Отставание/Перевыполнение | J16: =J8-I15*J14 -> -3666415 | K16: =IF(AND(I16<>"",I16<>0,J16<>""),J16/I16,"") | L16: =J16 -> -3666415 | M16: =IF(AND(I16<>"",I16<>0,L16<>"",L16<>0),L16/I16,"") | N16: =IF(AND(J16<>0,J16<>"",I16<>0,I16<>""),L16-I16,"") | P16: =IF(AND(O16<>"",O16<>0,L16<>"",L16<>0),-O16+L16,"") | Q16: =IF(AND(P16<>"",P16<>0,O16<>0,O16<>""),P16/O16,"") | S16: Подарочные сертификаты
F17: Трафик | I17: =Центрум!I17/График!AJ29*График!AJ25 -> 743.71257 | J17: =I48 -> 524 | K17: =IF(AND(I17<>"",I17<>0,J17<>""),J17/I17,"") -> 0.70457327 | L17: =J17/J14*I14 -> 524 | M17: =IF(AND(I17<>"",I17<>0,L17<>"",L17<>0),L17/I17,"") -> 0.70457327 | N17: =IF(AND(J17<>0,J17<>"",I17<>0,I17<>""),L17-I17,"") -> -219.71257 | P17: =IF(AND(O17<>"",O17<>0,L17<>"",L17<>0),-O17+L17,"") | Q17: =IF(AND(P17<>"",P17<>0,O17<>0,O17<>""),P17/O17,"")
K18: =IF(AND(I18<>"",I18<>0,J18<>""),J18/I18,"") | L18: =J18 -> 0 | M18: =IF(AND(I18<>"",I18<>0,L18<>"",L18<>0),L18/I18,"") | N18: =IF(AND(J18<>0,J18<>"",I18<>0,I18<>""),L18-I18,"") | O18: 0 | P18: =IF(AND(O18<>"",O18<>0,L18<>"",L18<>0),-O18+L18,"") | Q18: =IF(AND(P18<>"",P18<>0,O18<>0,O18<>""),P18/O18,"")
J19: =P48 -> 0 | K19: =IF(AND(I19<>"",I19<>0,J19<>""),J19/I19,"") | L19: =J19 -> 0 | M19: =IF(AND(I19<>"",I19<>0,L19<>"",L19<>0),L19/I19,"") | N19: =IF(AND(J19<>0,J19<>"",I19<>0,I19<>""),L19-I19,"") | O19: 0 | P19: =IF(AND(O19<>"",O19<>0,L19<>"",L19<>0),-O19+L19,"") | Q19: =IF(AND(P19<>"",P19<>0,O19<>0,O19<>""),P19/O19,"") | S19: =S18/I16 -> #DIV/0!
F20: Конверсия план/факт | I20: =Центрум!I20 -> 0.123 | J20: =Q48 -> 0.078244275 | K20: =J20/I20 -> 0.63613232 | L20: =IF(AND(K8<>0,I14<>0,I48<>0),(I48*Q48+(I48/K8-I48)*I20)/(I48/K8),0) -> 0.10661414 | M20: =IF(AND(I20<>"",I20<>0,L20<>"",L20<>0),L20/I20,"") -> 0.86678161 | N20: =IF(AND(J20<>0,J20<>"",I20<>0,I20<>""),L20-I20,"") -> -0.016385863 | P20: =IF(AND(O20<>"",O20<>0,L20<>"",L20<>0),-O20+L20,"") | Q20: =IF(AND(P20<>"",P20<>0,O20<>0,O20<>""),P20/O20,"")
B22: Факт продаж за месяц | R22: % выполнения дневного плана | S22: Раcпределение плана по дням
B23: Дата | C23: День недели | D23: Выручка (руб) | E23: Кол-во единиц (шт.) | F23: Средняя стоимость изделия (руб.) | G23: Количество чеков (шт.) | H23: Средняя сумма чека (руб.) | I23: Трафик | J23: Длина чека (шт.) | K23: UNOde50 | L23: IS | M23: Agafi | N23: Kalliope | O23: Raganella | P23: CC/MP | Q23: Конверсия (%) | S23: выручка, план | T23: кол-во ед, план | U23: Кол-во чеков, план | V23: выручка, скорректир.план | W23: кол-во ед, скорр. план | X23: кол-во чеков, скорр. план | Y23: Коэфф. Дня Недели | Z23: Специфика месяца
B24: 1 | C24: 2 | D24: 3 | E24: в | F24: 5 | G24: 6 | H24: 7 | I24: 8 | J24: 9 | K24: 10 | L24: 11 | M24: 12 | N24: 13 | O24: 14 | P24: 15 | Q24: 13 | S24: 1 | T24: 2 | U24: 3 | V24: 4 | W24: 5 | X24: 6 | Y24: 10 | Z24: 11
A25: 1 | B25: 45994 | C25: ср | D25: 6330 | E25: 1 | F25: =IF(AND(E25<>"",E25<>0),D25/E25,"") -> 6330 | G25: 1 | H25: =IF(AND(G25<>"",G25<>0),D25/G25,"") -> 6330 | I25: 22 | J25: =IF(AND(G25<>"",G25<>0),E25/G25,"") -> 1 | Q25: =IF(AND(I25<>"",I25<>0),G25/I25,"") -> 0.045454545 | R25: =D25/S25 -> 0.11532341 | S25: =$I$8*Y25*Z25/SUMPRODUCT($Z$25:$Z$55,$Y$25:$Y$55) -> 54889.116 | T25: =$I$9*Y25*Z25/SUMPRODUCT($Z$25:$Z$55,$Y$25:$Y$55) -> 6.7019677 | U25: =IF($I$12="","",T25/$I$12) -> 3.9892665 | V25: =IF(Z25<>"",IF(D25<>"",D25,($I$8-SUM($V24:V$25))*Y25*Z25/SUMPRODUCT($Z25:$Z$55,$Y25:$Y$55)),"") -> 6330 | W25: =IF(Z25<>"",IF(E25<>"",E25,($I$9-SUM($W24:W$25))*Y25*Z25/SUMPRODUCT($Z25:$Z$55,$Y25:$Y$55)),"") -> 1 | X25: =IF(Z25<>"",IF($I$12<>"",IF(G25<>"",G25,($I$9/$I$12-SUM($X24:X$25))*Y25*Z25/SUMPRODUCT($Z25:$Z$55,$Y25:$Y$55)),""),"") -> 1 | Y25: 1 | Z25: 1
A26: 2 | B26: 45995 | C26: чт | D26: 87372 | E26: 10 | F26: =IF(AND(E26<>"",E26<>0),D26/E26,"") -> 8737.2 | G26: 5 | H26: =IF(AND(G26<>"",G26<>0),D26/G26,"") -> 17474.4 | I26: 23 | J26: =IF(AND(G26<>"",G26<>0),E26/G26,"") -> 2 | K26: 32375 | M26: =10892+14992 -> 25884 | N26: 21370 | Q26: =IF(AND(I26<>"",I26<>0),G26/I26,"") -> 0.2173913 | R26: =D26/S26 -> 2.1871762 | S26: =$I$8*Y26*Z26/SUMPRODUCT($Z$25:$Z$55,$Y$25:$Y$55) -> 39947.398 | T26: =$I$9*Y26*Z26/SUMPRODUCT($Z$25:$Z$55,$Y$25:$Y$55) -> 4.8775822 | U26: =IF($I$12="","",T26/$I$12) -> 2.9033227 | V26: =IF(Z26<>"",IF(D26<>"",D26,($I$8-SUM($V$25:V25))*Y26*Z26/SUMPRODUCT($Z26:$Z$55,$Y26:$Y$55)),"") -> 87372 | W26: =IF(Z26<>"",IF(E26<>"",E26,($I$9-SUM($W$25:W25))*Y26*Z26/SUMPRODUCT($Z26:$Z$55,$Y26:$Y$55)),"") -> 10 | X26: =IF(Z26<>"",IF($I$12<>"",IF(G26<>"",G26,($I$9/$I$12-SUM($X$25:X25))*Y26*Z26/SUMPRODUCT($Z26:$Z$55,$Y26:$Y$55)),""),"") -> 5 | Y26: 0.85310234 | Z26: 0.85310234
A27: 3 | B27: 45998 | C27: вс | D27: 28013 | E27: 4 | F27: =IF(AND(E27<>"",E27<>0),D27/E27,"") -> 7003.25 | G27: 3 | H27: =IF(AND(G27<>"",G27<>0),D27/G27,"") -> 9337.6667 | I27: 36 | J27: =IF(AND(G27<>"",G27<>0),E27/G27,"") -> 1.3333333 | N27: 17272 | Q27: =IF(AND(I27<>"",I27<>0),G27/I27,"") -> 0.083333333 | R27: =D27/S27 -> 1.9813977 | S27: 14138 | T27: 4 | U27: 2 | V27: 16611 | W27: 3 | X27: 3 | Y27: 0.94 | Z27: 0.94
A28: 4 | B28: 45999 | C28: пн | D28: 24325 | E28: 5 | F28: =IF(AND(E28<>"",E28<>0),D28/E28,"") -> 4865 | G28: 3 | H28: =IF(AND(G28<>"",G28<>0),D28/G28,"") -> 8108.3333 | I28: 40 | J28: =IF(AND(G28<>"",G28<>0),E28/G28,"") -> 1.6666667 | Q28: =IF(AND(I28<>"",I28<>0),G28/I28,"") -> 0.075 | R28: =D28/S28 -> 0.39592812 | S28: =$I$8*Y28*Z28/SUMPRODUCT($Z$25:$Z$55,$Y$25:$Y$55) -> 61437.92 | T28: =$I$9*Y28*Z28/SUMPRODUCT($Z$25:$Z$55,$Y$25:$Y$55) -> 7.5015775 | U28: =IF($I$12="","",T28/$I$12) -> 4.4652247 | V28: =IF(Z28<>"",IF(D28<>"",D28,($I$8-SUM($V$25:V27))*Y28*Z28/SUMPRODUCT($Z28:$Z$55,$Y28:$Y$55)),"") -> 24325 | W28: =IF(Z28<>"",IF(E28<>"",E28,($I$9-SUM($W$25:W27))*Y28*Z28/SUMPRODUCT($Z28:$Z$55,$Y28:$Y$55)),"") -> 5 | X28: =IF(Z28<>"",IF($I$12<>"",IF(G28<>"",G28,($I$9/$I$12-SUM($X$25:X27))*Y28*Z28/SUMPRODUCT($Z28:$Z$55,$Y28:$Y$55)),""),"") -> 3 | Y28: 1.0579743 | Z28: 1.0579743
A29: 5 | B29: 46001 | C29: ср | D29: 6293 | E29: 1 | F29: =IF(AND(E29<>"",E29<>0),D29/E29,"") -> 6293 | G29: 1 | H29: =IF(AND(G29<>"",G29<>0),D29/G29,"") -> 6293 | I29: 27 | J29: =IF(AND(G29<>"",G29<>0),E29/G29,"") -> 1 | Q29: =IF(AND(I29<>"",I29<>0),G29/I29,"") -> 0.037037037 | R29: =D29/S29 -> 0.11464932 | S29: =$I$8*Y29*Z29/SUMPRODUCT($Z$25:$Z$55,$Y$25:$Y$55) -> 54889.116 | T29: =$I$9*Y29*Z29/SUMPRODUCT($Z$25:$Z$55,$Y$25:$Y$55) -> 6.7019677 | U29: =IF($I$12="","",T29/$I$12) -> 3.9892665 | V29: =IF(Z29<>"",IF(D29<>"",D29,($I$8-SUM($V$25:V28))*Y29*Z29/SUMPRODUCT($Z29:$Z$55,$Y29:$Y$55)),"") -> 6293 | W29: =IF(Z29<>"",IF(E29<>"",E29,($I$9-SUM($W$25:W28))*Y29*Z29/SUMPRODUCT($Z29:$Z$55,$Y29:$Y$55)),"") -> 1 | X29: =IF(Z29<>"",IF($I$12<>"",IF(G29<>"",G29,($I$9/$I$12-SUM($X$25:X28))*Y29*Z29/SUMPRODUCT($Z29:$Z$55,$Y29:$Y$55)),""),"") -> 1 | Y29: 1 | Z29: 1
A30: 6 | B30: 46002 | C30: чт | D30: 0 | E30: 0 | F30: =IF(AND(E30<>"",E30<>0),D30/E30,"") | G30: 0 | H30: =IF(AND(G30<>"",G30<>0),D30/G30,"") | I30: 28 | J30: =IF(AND(G30<>"",G30<>0),E30/G30,"") | Q30: =IF(AND(I30<>"",I30<>0),G30/I30,"") -> 0 | R30: =D30/S30 -> 0 | S30: =$I$8*Y30*Z30/SUMPRODUCT($Z$25:$Z$55,$Y$25:$Y$55) -> 54889.116 | T30: =$I$9*Y30*Z30/SUMPRODUCT($Z$25:$Z$55,$Y$25:$Y$55) -> 6.7019677 | U30: =IF($I$12="","",T30/$I$12) -> 3.9892665 | V30: =IF(Z30<>"",IF(D30<>"",D30,($I$8-SUM($V$25:V29))*Y30*Z30/SUMPRODUCT($Z30:$Z$55,$Y30:$Y$55)),"") -> 0 | W30: =IF(Z30<>"",IF(E30<>"",E30,($I$9-SUM($W$25:W29))*Y30*Z30/SUMPRODUCT($Z30:$Z$55,$Y30:$Y$55)),"") -> 0 | X30: =IF(Z30<>"",IF($I$12<>"",IF(G30<>"",G30,($I$9/$I$12-SUM($X$25:X29))*Y30*Z30/SUMPRODUCT($Z30:$Z$55,$Y30:$Y$55)),""),"") -> 0 | Y30: 1 | Z30: 1
A31: 7 | B31: 46004 | C31: сб | D31: 39129 | E31: 6 | F31: =IF(AND(E31<>"",E31<>0),D31/E31,"") -> 6521.5 | G31: 3 | H31: =IF(AND(G31<>"",G31<>0),D31/G31,"") -> 13043 | I31: 45 | J31: =IF(AND(G31<>"",G31<>0),E31/G31,"") -> 2 | L31: 6004 | Q31: =IF(AND(I31<>"",I31<>0),G31/I31,"") -> 0.066666667 | R31: =D31/S31 -> 0.71287357 | S31: =$I$8*Y31*Z31/SUMPRODUCT($Z$25:$Z$55,$Y$25:$Y$55) -> 54889.116 | T31: =$I$9*Y31*Z31/SUMPRODUCT($Z$25:$Z$55,$Y$25:$Y$55) -> 6.7019677 | U31: =IF($I$12="","",T31/$I$12) -> 3.9892665 | V31: =IF(Z31<>"",IF(D31<>"",D31,($I$8-SUM($V$25:V30))*Y31*Z31/SUMPRODUCT($Z31:$Z$55,$Y31:$Y$55)),"") -> 39129 | W31: =IF(Z31<>"",IF(E31<>"",E31,($I$9-SUM($W$25:W30))*Y31*Z31/SUMPRODUCT($Z31:$Z$55,$Y31:$Y$55)),"") -> 6 | X31: =IF(Z31<>"",IF($I$12<>"",IF(G31<>"",G31,($I$9/$I$12-SUM($X$25:X30))*Y31*Z31/SUMPRODUCT($Z31:$Z$55,$Y31:$Y$55)),""),"") -> 3 | Y31: 1 | Z31: 1
A32: 8 | B32: 46005 | C32: вс | D32: 0 | E32: 0 | F32: =IF(AND(E32<>"",E32<>0),D32/E32,"") | G32: 0 | H32: =IF(AND(G32<>"",G32<>0),D32/G32,"") | I32: 40 | J32: =IF(AND(G32<>"",G32<>0),E32/G32,"") | Q32: =IF(AND(I32<>"",I32<>0),G32/I32,"") -> 0 | R32: =D32/S32 -> 0 | S32: =$I$8*Y32*Z32/SUMPRODUCT($Z$25:$Z$55,$Y$25:$Y$55) -> 54889.116 | T32: =$I$9*Y32*Z32/SUMPRODUCT($Z$25:$Z$55,$Y$25:$Y$55) -> 6.7019677 | U32: =IF($I$12="","",T32/$I$12) -> 3.9892665 | V32: =IF(Z32<>"",IF(D32<>"",D32,($I$8-SUM($V$25:V31))*Y32*Z32/SUMPRODUCT($Z32:$Z$55,$Y32:$Y$55)),"") -> 0 | W32: =IF(Z32<>"",IF(E32<>"",E32,($I$9-SUM($W$25:W31))*Y32*Z32/SUMPRODUCT($Z32:$Z$55,$Y32:$Y$55)),"") -> 0 | X32: =IF(Z32<>"",IF($I$12<>"",IF(G32<>"",G32,($I$9/$I$12-SUM($X$25:X31))*Y32*Z32/SUMPRODUCT($Z32:$Z$55,$Y32:$Y$55)),""),"") -> 0 | Y32: 1 | Z32: 1
A33: 9 | B33: 46007 | C33: вт | D33: 27841 | E33: 3 | F33: =IF(AND(E33<>"",E33<>0),D33/E33,"") -> 9280.3333 | G33: 2 | H33: =IF(AND(G33<>"",G33<>0),D33/G33,"") -> 13920.5 | I33: 26 | J33: =IF(AND(G33<>"",G33<>0),E33/G33,"") -> 1.5 | M33: 22184 | Q33: =IF(AND(I33<>"",I33<>0),G33/I33,"") -> 0.076923077 | R33: =D33/S33 -> 0.5072226 | S33: =$I$8*Y33*Z33/SUMPRODUCT($Z$25:$Z$55,$Y$25:$Y$55) -> 54889.116 | T33: =$I$9*Y33*Z33/SUMPRODUCT($Z$25:$Z$55,$Y$25:$Y$55) -> 6.7019677 | U33: =IF($I$12="","",T33/$I$12) -> 3.9892665 | V33: =IF(Z33<>"",IF(D33<>"",D33,($I$8-SUM($V$25:V32))*Y33*Z33/SUMPRODUCT($Z33:$Z$55,$Y33:$Y$55)),"") -> 27841 | W33: =IF(Z33<>"",IF(E33<>"",E33,($I$9-SUM($W$25:W32))*Y33*Z33/SUMPRODUCT($Z33:$Z$55,$Y33:$Y$55)),"") -> 3 | X33: =IF(Z33<>"",IF($I$12<>"",IF(G33<>"",G33,($I$9/$I$12-SUM($X$25:X32))*Y33*Z33/SUMPRODUCT($Z33:$Z$55,$Y33:$Y$55)),""),"") -> 2 | Y33: 1 | Z33: 1
A34: 10 | B34: 46008 | C34: ср | D34: 15672 | E34: 2 | F34: =IF(AND(E34<>"",E34<>0),D34/E34,"") -> 7836 | G34: 1 | H34: =IF(AND(G34<>"",G34<>0),D34/G34,"") -> 15672 | I34: 42 | J34: =IF(AND(G34<>"",G34<>0),E34/G34,"") -> 2 | Q34: =IF(AND(I34<>"",I34<>0),G34/I34,"") -> 0.023809524 | R34: =D34/S34 -> 0.28552109 | S34: =$I$8*Y34*Z34/SUMPRODUCT($Z$25:$Z$55,$Y$25:$Y$55) -> 54889.116 | T34: =$I$9*Y34*Z34/SUMPRODUCT($Z$25:$Z$55,$Y$25:$Y$55) -> 6.7019677 | U34: =IF($I$12="","",T34/$I$12) -> 3.9892665 | V34: =IF(Z34<>"",IF(D34<>"",D34,($I$8-SUM($V$25:V33))*Y34*Z34/SUMPRODUCT($Z34:$Z$55,$Y34:$Y$55)),"") -> 15672 | W34: =IF(Z34<>"",IF(E34<>"",E34,($I$9-SUM($W$25:W33))*Y34*Z34/SUMPRODUCT($Z34:$Z$55,$Y34:$Y$55)),"") -> 2 | X34: =IF(Z34<>"",IF($I$12<>"",IF(G34<>"",G34,($I$9/$I$12-SUM($X$25:X33))*Y34*Z34/SUMPRODUCT($Z34:$Z$55,$Y34:$Y$55)),""),"") -> 1 | Y34: 1 | Z34: 1
A35: 11 | B35: 46009 | C35: чт | D35: 7488 | E35: 2 | F35: =IF(AND(E35<>"",E35<>0),D35/E35,"") -> 3744 | G35: 2 | H35: =IF(AND(G35<>"",G35<>0),D35/G35,"") -> 3744 | I35: 31 | J35: =IF(AND(G35<>"",G35<>0),E35/G35,"") -> 1 | Q35: =IF(AND(I35<>"",I35<>0),G35/I35,"") -> 0.064516129 | R35: =D35/S35 -> 0.13642049 | S35: =$I$8*Y35*Z35/SUMPRODUCT($Z$25:$Z$55,$Y$25:$Y$55) -> 54889.116 | T35: =$I$9*Y35*Z35/SUMPRODUCT($Z$25:$Z$55,$Y$25:$Y$55) -> 6.7019677 | U35: =IF($I$12="","",T35/$I$12) -> 3.9892665 | V35: =IF(Z35<>"",IF(D35<>"",D35,($I$8-SUM($V$25:V34))*Y35*Z35/SUMPRODUCT($Z35:$Z$55,$Y35:$Y$55)),"") -> 7488 | W35: =IF(Z35<>"",IF(E35<>"",E35,($I$9-SUM($W$25:W34))*Y35*Z35/SUMPRODUCT($Z35:$Z$55,$Y35:$Y$55)),"") -> 2 | X35: =IF(Z35<>"",IF($I$12<>"",IF(G35<>"",G35,($I$9/$I$12-SUM($X$25:X34))*Y35*Z35/SUMPRODUCT($Z35:$Z$55,$Y35:$Y$55)),""),"") -> 2 | Y35: 1 | Z35: 1
A36: 12 | B36: 46012 | C36: вс | D36: 4693 | E36: 1 | F36: =IF(AND(E36<>"",E36<>0),D36/E36,"") -> 4693 | G36: 1 | H36: =IF(AND(G36<>"",G36<>0),D36/G36,"") -> 4693 | I36: 33 | J36: =IF(AND(G36<>"",G36<>0),E36/G36,"") -> 1 | Q36: =IF(AND(I36<>"",I36<>0),G36/I36,"") -> 0.03030303 | R36: =D36/S36 -> 0.085499647 | S36: =$I$8*Y36*Z36/SUMPRODUCT($Z$25:$Z$55,$Y$25:$Y$55) -> 54889.116 | T36: =$I$9*Y36*Z36/SUMPRODUCT($Z$25:$Z$55,$Y$25:$Y$55) -> 6.7019677 | U36: =IF($I$12="","",T36/$I$12) -> 3.9892665 | V36: =IF(Z36<>"",IF(D36<>"",D36,($I$8-SUM($V$25:V35))*Y36*Z36/SUMPRODUCT($Z36:$Z$55,$Y36:$Y$55)),"") -> 4693 | W36: =IF(Z36<>"",IF(E36<>"",E36,($I$9-SUM($W$25:W35))*Y36*Z36/SUMPRODUCT($Z36:$Z$55,$Y36:$Y$55)),"") -> 1 | X36: =IF(Z36<>"",IF($I$12<>"",IF(G36<>"",G36,($I$9/$I$12-SUM($X$25:X35))*Y36*Z36/SUMPRODUCT($Z36:$Z$55,$Y36:$Y$55)),""),"") -> 1 | Y36: 1 | Z36: 1
A37: 13 | B37: 46014 | C37: вт | D37: 17878.5 | E37: 3 | F37: =IF(AND(E37<>"",E37<>0),D37/E37,"") -> 5959.5 | G37: 1 | H37: =IF(AND(G37<>"",G37<>0),D37/G37,"") -> 17878.5 | I37: 30 | J37: =IF(AND(G37<>"",G37<>0),E37/G37,"") -> 3 | Q37: =IF(AND(I37<>"",I37<>0),G37/I37,"") -> 0.033333333 | R37: =D37/S37 -> 0.32572031 | S37: =$I$8*Y37*Z37/SUMPRODUCT($Z$25:$Z$55,$Y$25:$Y$55) -> 54889.116 | T37: =$I$9*Y37*Z37/SUMPRODUCT($Z$25:$Z$55,$Y$25:$Y$55) -> 6.7019677 | U37: =IF($I$12="","",T37/$I$12) -> 3.9892665 | V37: =IF(Z37<>"",IF(D37<>"",D37,($I$8-SUM($V$25:V36))*Y37*Z37/SUMPRODUCT($Z37:$Z$55,$Y37:$Y$55)),"") -> 17878.5 | W37: =IF(Z37<>"",IF(E37<>"",E37,($I$9-SUM($W$25:W36))*Y37*Z37/SUMPRODUCT($Z37:$Z$55,$Y37:$Y$55)),"") -> 3 | X37: =IF(Z37<>"",IF($I$12<>"",IF(G37<>"",G37,($I$9/$I$12-SUM($X$25:X36))*Y37*Z37/SUMPRODUCT($Z37:$Z$55,$Y37:$Y$55)),""),"") -> 1 | Y37: 1 | Z37: 1
A38: 14 | B38: 46015 | C38: ср | D38: =9991+21385 -> 31376 | E38: 2 | F38: =IF(AND(E38<>"",E38<>0),D38/E38,"") -> 15688 | G38: 2 | H38: =IF(AND(G38<>"",G38<>0),D38/G38,"") -> 15688 | I38: 20 | J38: =IF(AND(G38<>"",G38<>0),E38/G38,"") -> 1 | K38: 13490 | Q38: =IF(AND(I38<>"",I38<>0),G38/I38,"") -> 0.1 | R38: =D38/S38 -> 0.57162517 | S38: =$I$8*Y38*Z38/SUMPRODUCT($Z$25:$Z$55,$Y$25:$Y$55) -> 54889.116 | T38: =$I$9*Y38*Z38/SUMPRODUCT($Z$25:$Z$55,$Y$25:$Y$55) -> 6.7019677 | U38: =IF($I$12="","",T38/$I$12) -> 3.9892665 | V38: =IF(Z38<>"",IF(D38<>"",D38,($I$8-SUM($V$25:V37))*Y38*Z38/SUMPRODUCT($Z38:$Z$55,$Y38:$Y$55)),"") -> 31376 | W38: =IF(Z38<>"",IF(E38<>"",E38,($I$9-SUM($W$25:W37))*Y38*Z38/SUMPRODUCT($Z38:$Z$55,$Y38:$Y$55)),"") -> 2 | X38: =IF(Z38<>"",IF($I$12<>"",IF(G38<>"",G38,($I$9/$I$12-SUM($X$25:X37))*Y38*Z38/SUMPRODUCT($Z38:$Z$55,$Y38:$Y$55)),""),"") -> 2 | Y38: 1 | Z38: 1
A39: 15 | B39: 46016 | C39: чт | D39: 4393 | E39: 1 | F39: =IF(AND(E39<>"",E39<>0),D39/E39,"") -> 4393 | G39: 1 | H39: =IF(AND(G39<>"",G39<>0),D39/G39,"") -> 4393 | I39: 25 | J39: =IF(AND(G39<>"",G39<>0),E39/G39,"") -> 1 | Q39: =IF(AND(I39<>"",I39<>0),G39/I39,"") -> 0.04 | R39: =D39/S39 -> 0.080034082 | S39: =$I$8*Y39*Z39/SUMPRODUCT($Z$25:$Z$55,$Y$25:$Y$55) -> 54889.116 | T39: =$I$9*Y39*Z39/SUMPRODUCT($Z$25:$Z$55,$Y$25:$Y$55) -> 6.7019677 | U39: =IF($I$12="","",T39/$I$12) -> 3.9892665 | V39: =IF(Z39<>"",IF(D39<>"",D39,($I$8-SUM($V$25:V38))*Y39*Z39/SUMPRODUCT($Z39:$Z$55,$Y39:$Y$55)),"") -> 4393 | W39: =IF(Z39<>"",IF(E39<>"",E39,($I$9-SUM($W$25:W38))*Y39*Z39/SUMPRODUCT($Z39:$Z$55,$Y39:$Y$55)),"") -> 1 | X39: =IF(Z39<>"",IF($I$12<>"",IF(G39<>"",G39,($I$9/$I$12-SUM($X$25:X38))*Y39*Z39/SUMPRODUCT($Z39:$Z$55,$Y39:$Y$55)),""),"") -> 1 | Y39: 1 | Z39: 1
A40: 16 | B40: 46017 | C40: пт | D40: 34891.87 | E40: 4 | F40: =IF(AND(E40<>"",E40<>0),D40/E40,"") -> 8722.9675 | G40: 3 | H40: =IF(AND(G40<>"",G40<>0),D40/G40,"") -> 11630.623 | I40: 25 | J40: =IF(AND(G40<>"",G40<>0),E40/G40,"") -> 1.3333333 | K40: 12481 | Q40: =IF(AND(I40<>"",I40<>0),G40/I40,"") -> 0.12 | R40: =D40/S40 -> 0.4414439 | S40: =$I$8*Y40*Z40/SUMPRODUCT($Z$25:$Z$55,$Y$25:$Y$55) -> 79040.327 | T40: =$I$9*Y40*Z40/SUMPRODUCT($Z$25:$Z$55,$Y$25:$Y$55) -> 9.6508335 | U40: =IF($I$12="","",T40/$I$12) -> 5.7445438 | V40: =IF(Z40<>"",IF(D40<>"",D40,($I$8-SUM($V$25:V39))*Y40*Z40/SUMPRODUCT($Z40:$Z$55,$Y40:$Y$55)),"") -> 34891.87 | W40: =IF(Z40<>"",IF(E40<>"",E40,($I$9-SUM($W$25:W39))*Y40*Z40/SUMPRODUCT($Z40:$Z$55,$Y40:$Y$55)),"") -> 4 | X40: =IF(Z40<>"",IF($I$12<>"",IF(G40<>"",G40,($I$9/$I$12-SUM($X$25:X39))*Y40*Z40/SUMPRODUCT($Z40:$Z$55,$Y40:$Y$55)),""),"") -> 3 | Y40: 1.2 | Z40: 1.2
A41: 17 | B41: 46018 | C41: сб | D41: =6893+500+23672 -> 31065 | E41: 3 | F41: =IF(AND(E41<>"",E41<>0),D41/E41,"") -> 10355 | G41: 2 | H41: =IF(AND(G41<>"",G41<>0),D41/G41,"") -> 15532.5 | I41: 29 | J41: =IF(AND(G41<>"",G41<>0),E41/G41,"") -> 1.5 | K41: 23672 | Q41: =IF(AND(I41<>"",I41<>0),G41/I41,"") -> 0.068965517 | R41: =D41/S41 -> 0.39302722 | S41: =$I$8*Y41*Z41/SUMPRODUCT($Z$25:$Z$55,$Y$25:$Y$55) -> 79040.327 | T41: =$I$9*Y41*Z41/SUMPRODUCT($Z$25:$Z$55,$Y$25:$Y$55) -> 9.6508335 | U41: =IF($I$12="","",T41/$I$12) -> 5.7445438 | V41: =IF(Z41<>"",IF(D41<>"",D41,($I$8-SUM($V$25:V40))*Y41*Z41/SUMPRODUCT($Z41:$Z$55,$Y41:$Y$55)),"") -> 31065 | W41: =IF(Z41<>"",IF(E41<>"",E41,($I$9-SUM($W$25:W40))*Y41*Z41/SUMPRODUCT($Z41:$Z$55,$Y41:$Y$55)),"") -> 3 | X41: =IF(Z41<>"",IF($I$12<>"",IF(G41<>"",G41,($I$9/$I$12-SUM($X$25:X40))*Y41*Z41/SUMPRODUCT($Z41:$Z$55,$Y41:$Y$55)),""),"") -> 2 | Y41: 1.2 | Z41: 1.2
A42: 18 | B42: 46019 | C42: вс | D42: 18462 | E42: 3 | F42: =IF(AND(E42<>"",E42<>0),D42/E42,"") -> 6154 | G42: 1 | H42: =IF(AND(G42<>"",G42<>0),D42/G42,"") -> 18462 | J42: =IF(AND(G42<>"",G42<>0),E42/G42,"") -> 3 | Q42: =IF(AND(I42<>"",I42<>0),G42/I42,"") | R42: =D42/S42 -> 0.23357697 | S42: =$I$8*Y42*Z42/SUMPRODUCT($Z$25:$Z$55,$Y$25:$Y$55) -> 79040.327 | T42: =$I$9*Y42*Z42/SUMPRODUCT($Z$25:$Z$55,$Y$25:$Y$55) -> 9.6508335 | U42: =IF($I$12="","",T42/$I$12) -> 5.7445438 | V42: =IF(Z42<>"",IF(D42<>"",D42,($I$8-SUM($V$25:V41))*Y42*Z42/SUMPRODUCT($Z42:$Z$55,$Y42:$Y$55)),"") -> 18462 | W42: =IF(Z42<>"",IF(E42<>"",E42,($I$9-SUM($W$25:W41))*Y42*Z42/SUMPRODUCT($Z42:$Z$55,$Y42:$Y$55)),"") -> 3 | X42: =IF(Z42<>"",IF($I$12<>"",IF(G42<>"",G42,($I$9/$I$12-SUM($X$25:X41))*Y42*Z42/SUMPRODUCT($Z42:$Z$55,$Y42:$Y$55)),""),"") -> 1 | Y42: 1.2 | Z42: 1.2
A43: 19 | B43: 46020 | C43: пн | D43: =3293+5793+10282 -> 19368 | E43: 3 | F43: =IF(AND(E43<>"",E43<>0),D43/E43,"") -> 6456 | G43: 3 | H43: =IF(AND(G43<>"",G43<>0),D43/G43,"") -> 6456 | J43: =IF(AND(G43<>"",G43<>0),E43/G43,"") -> 1 | Q43: =IF(AND(I43<>"",I43<>0),G43/I43,"") | R43: =D43/S43 -> 0.24503947 | S43: =$I$8*Y43*Z43/SUMPRODUCT($Z$25:$Z$55,$Y$25:$Y$55) -> 79040.327 | T43: =$I$9*Y43*Z43/SUMPRODUCT($Z$25:$Z$55,$Y$25:$Y$55) -> 9.6508335 | U43: =IF($I$12="","",T43/$I$12) -> 5.7445438 | V43: =IF(Z43<>"",IF(D43<>"",D43,($I$8-SUM($V$25:V42))*Y43*Z43/SUMPRODUCT($Z43:$Z$55,$Y43:$Y$55)),"") -> 19368 | W43: =IF(Z43<>"",IF(E43<>"",E43,($I$9-SUM($W$25:W42))*Y43*Z43/SUMPRODUCT($Z43:$Z$55,$Y43:$Y$55)),"") -> 3 | X43: =IF(Z43<>"",IF($I$12<>"",IF(G43<>"",G43,($I$9/$I$12-SUM($X$25:X42))*Y43*Z43/SUMPRODUCT($Z43:$Z$55,$Y43:$Y$55)),""),"") -> 3 | Y43: 1.2 | Z43: 1.2
A44: 20 | B44: 46021 | C44: вт | D44: =2793+19377 -> 22170 | E44: 4 | F44: =IF(AND(E44<>"",E44<>0),D44/E44,"") -> 5542.5 | G44: 2 | H44: =IF(AND(G44<>"",G44<>0),D44/G44,"") -> 11085 | J44: =IF(AND(G44<>"",G44<>0),E44/G44,"") -> 2 | Q44: =IF(AND(I44<>"",I44<>0),G44/I44,"") | R44: =D44/S44 -> 0.28048973 | S44: =$I$8*Y44*Z44/SUMPRODUCT($Z$25:$Z$55,$Y$25:$Y$55) -> 79040.327 | T44: =$I$9*Y44*Z44/SUMPRODUCT($Z$25:$Z$55,$Y$25:$Y$55) -> 9.6508335 | U44: =IF($I$12="","",T44/$I$12) -> 5.7445438 | V44: =IF(Z44<>"",IF(D44<>"",D44,($I$8-SUM($V$25:V43))*Y44*Z44/SUMPRODUCT($Z44:$Z$55,$Y44:$Y$55)),"") -> 22170 | W44: =IF(Z44<>"",IF(E44<>"",E44,($I$9-SUM($W$25:W43))*Y44*Z44/SUMPRODUCT($Z44:$Z$55,$Y44:$Y$55)),"") -> 4 | X44: =IF(Z44<>"",IF($I$12<>"",IF(G44<>"",G44,($I$9/$I$12-SUM($X$25:X43))*Y44*Z44/SUMPRODUCT($Z44:$Z$55,$Y44:$Y$55)),""),"") -> 2 | Y44: 1.2 | Z44: 1.2
A45: 21 | B45: 46022 | C45: ср | D45: =7293+5293 -> 12586 | E45: 2 | F45: =IF(AND(E45<>"",E45<>0),D45/E45,"") -> 6293 | G45: 2 | H45: =IF(AND(G45<>"",G45<>0),D45/G45,"") -> 6293 | J45: =IF(AND(G45<>"",G45<>0),E45/G45,"") -> 1 | Q45: =IF(AND(I45<>"",I45<>0),G45/I45,"") | R45: =D45/S45 -> 0.22929865 | S45: =$I$8*Y45*Z45/SUMPRODUCT($Z$25:$Z$55,$Y$25:$Y$55) -> 54889.116 | T45: =$I$9*Y45*Z45/SUMPRODUCT($Z$25:$Z$55,$Y$25:$Y$55) -> 6.7019677 | U45: =IF($I$12="","",T45/$I$12) -> 3.9892665 | V45: =IF(Z45<>"",IF(D45<>"",D45,($I$8-SUM($V$25:V44))*Y45*Z45/SUMPRODUCT($Z45:$Z$55,$Y45:$Y$55)),"") -> 12586 | W45: =IF(Z45<>"",IF(E45<>"",E45,($I$9-SUM($W$25:W44))*Y45*Z45/SUMPRODUCT($Z45:$Z$55,$Y45:$Y$55)),"") -> 2 | X45: =IF(Z45<>"",IF($I$12<>"",IF(G45<>"",G45,($I$9/$I$12-SUM($X$25:X44))*Y45*Z45/SUMPRODUCT($Z45:$Z$55,$Y45:$Y$55)),""),"") -> 2 | Y45: 1 | Z45: 1
B46: 46006 | C46: пн | D46: 17075 | E46: 3 | F46: =IF(AND(E46<>"",E46<>0),D46/E46,"") -> 5691.6667 | G46: 1 | H46: =IF(AND(G46<>"",G46<>0),D46/G46,"") -> 17075 | I46: 1 | J46: =IF(AND(G46<>"",G46<>0),E46/G46,"") -> 3 | Q46: =IF(AND(I46<>"",I46<>0),G46/I46,"") -> 1 | R46: =D46/S46 -> #DIV/0! | S46: =$I$8*Y46*Z46/SUMPRODUCT($Z$25:$Z$46,$Y$25:$Y$46) -> 0 | T46: =$I$9*Y46*Z46/SUMPRODUCT($Z$25:$Z$46,$Y$25:$Y$46) -> 0 | U46: =IF($I$12="","",T46/$I$12) -> 0 | V46: =IF(Z46<>"",IF(D46<>"",D46,($I$8-SUM($V$25:V45))*Y46*Z46/SUMPRODUCT($Z46:$Z$46,$Y46:$Y$46)),"") | W46: =IF(Z46<>"",IF(E46<>"",E46,($I$9-SUM($W$25:W39))*Y46*Z46/SUMPRODUCT($Z46:$Z$46,$Y46:$Y$46)),"") | X46: =IF(Z46<>"",IF($I$12<>"",IF(G46<>"",G46,($I$9/$I$12-SUM($X$25:X39))*Y46*Z46/SUMPRODUCT($Z46:$Z$46,$Y46:$Y$46)),""),"")
B47: 46000 | C47: вт | D47: 4391 | E47: 2 | F47: =IF(AND(E47<>"",E47<>0),D47/E47,"") -> 2195.5 | G47: 1 | H47: =IF(AND(G47<>"",G47<>0),D47/G47,"") -> 4391 | I47: 1 | J47: =IF(AND(G47<>"",G47<>0),E47/G47,"") -> 2 | Q47: =IF(AND(I47<>"",I47<>0),G47/I47,"") -> 1 | R47: =D47/S47 -> #DIV/0! | S47: =$I$8*Y47*Z47/SUMPRODUCT($Z$25:$Z$46,$Y$25:$Y$46) -> 0 | T47: =$I$9*Y47*Z47/SUMPRODUCT($Z$25:$Z$46,$Y$25:$Y$46) -> 0 | U47: =IF($I$12="","",T47/$I$12) -> 0 | V47: =IF(Z47<>"",IF(D47<>"",D47,($I$8-SUM($V$25:V46))*Y47*Z47/SUMPRODUCT($Z$47:$Z47,$Y$47:$Y47)),"") | W47: =IF(Z47<>"",IF(E47<>"",E47,($I$9-SUM(#REF!))*Y47*Z47/SUMPRODUCT($Z$47:$Z47,$Y$47:$Y47)),"") | X47: =IF(Z47<>"",IF($I$12<>"",IF(G47<>"",G47,($I$9/$I$12-SUM(#REF!))*Y47*Z47/SUMPRODUCT($Z$47:$Z47,$Y$47:$Y47)),""),"")
B48: итого | D48: =SUM(D25:D47) -> 460812.37 | E48: =SUM(E25:E47) -> 65 | F48: =IF(AND(E48<>"",E48<>0),D48/E48,"") -> 7089.4211 | G48: =SUM(G25:G47) -> 41 | H48: =IF(AND(G48<>"",G48<>0),D48/G48,"") -> 11239.326 | I48: =SUM(I25:I47) -> 524 | J48: =IF(AND(G48<>"",G48<>0),E48/G48,"") -> 1.5853659 | K48: =SUM(K25:K47) -> 82018 | O48: =SUM(O25:O47) -> 0 | P48: =SUM(P25:P47) -> 0 | Q48: =IF(AND(I48<>"",I48<>0),G48/I48,"") -> 0.078244275 | R48: =D48/S48 -> 0.37639353 | S48: =SUM(S25:S47) -> 1224283.5 | T48: =SUM(T25:T47) -> 151.75891 | U48: =SUM(U25:U47) -> 89.951731 | V48: =SUM(V25:V47) -> 427944.37 | W48: =SUM(W25:W47) -> 59 | X48: =SUM(X25:X47) -> 39
D49: =SUMIF(D25:D47,"",S25:S47)+D48 -> 460812.37

Sheet Свидовская С. А.
B1: =TODAY()-1 -> 46031
B2: (отчетная дата) | J2: ЕЖЕДНЕВНЫЙ ОТЧЕТ О ПРОДАЖАХ
B3: Осталось до выполнения плана!!! | J3: =График!B27 -> Свидовская София
C4: =I8-D48 -> 570288.89 | E4: =IF(I8<>0,C4/I8,0) -> 0.4643126
F6: Целевые показатели
F7: Показатель | I7: План | J7: Факт | K7: % выполнения | L7: Прогноз выполнения | M7: % выполнения по прогнозу | N7: Отклонение | O7: Факт аналогичного месяца прошлого года | P7: Отклонение LFL
F8: Выручка | I8: =Центрум!I8/График!AJ29*График!AJ27 -> 1228243.4 | J8: =D48 -> 657954.52 | K8: =IF(AND(I8<>"",I8<>0,J8<>""),J8/I8,"") -> 0.5356874 | L8: =IF(SUMIF($D$25:$D$47,">=0",$S$25:$S$47)<>0,I8*D48/SUMIF($D$25:$D$47,">=0",$S$25:$S$47),0) -> 679082.15 | M8: =L8/I8 -> 0.5528889 | N8: =IF(AND(J8<>0,J8<>"",I8<>0,I8<>""),L8-I8,"") -> -549161.26 | P8: =IF(AND(O8<>"",O8<>0,L8<>"",L8<>0),-O8+L8,"") | Q8: =IF(AND(P8<>"",P8<>0,O8<>0,O8<>""),P8/O8,"")
F9: Кол-во изделий | I9: =I8/I11 -> 149.96867 | J9: =E48 -> 88 | K9: =IF(AND(I9<>"",I9<>0,J9<>""),J9/I9,"") -> 0.58678922 | L9: =IF(SUMIF($E$25:$E$47,">=0",$T$25:$T$47)<>0,I9*E48/SUMIF($E$25:$E$47,">=0",$T$25:$T$47),0) -> 89.426401 | M9: =IF(AND(I9<>"",I9<>0,L9<>"",L9<>0),L9/I9,"") -> 0.59630055 | N9: =IF(AND(J9<>0,J9<>"",I9<>0,I9<>""),L9-I9,"") -> -60.54227 | O9: =O8/O11 -> #DIV/0! | P9: =IF(AND(O9<>"",O9<>0,L9<>"",L9<>0),-O9+L9,"") -> #DIV/0! | Q9: =IF(AND(P9<>"",P9<>0,O9<>0,O9<>""),P9/O9,"") -> #DIV/0!
F10: Средний чек | I10: =I11*I12 -> 13759.2 | J10: =H48 -> 11749.188 | K10: =IF(AND(I10<>"",I10<>0,J10<>""),J10/I10,"") -> 0.85391504 | L10: =J10 -> 11749.188 | M10: =IF(AND(I10<>"",I10<>0,L10<>"",L10<>0),L10/I10,"") -> 0.85391504 | N10: =IF(AND(J10<>0,J10<>"",I10<>0,I10<>""),L10-I10,"") -> -2010.0121 | O10: =O11*O12 -> 0 | P10: =IF(AND(O10<>"",O10<>0,L10<>"",L10<>0),-O10+L10,"") | Q10: =IF(AND(P10<>"",P10<>0,O10<>0,O10<>""),P10/O10,"")
F11: Средняя стоимость изделия | I11: =Центрум!I11 -> 8190 | J11: =F48 -> 7476.7559 | K11: =IF(AND(I11<>"",I11<>0,J11<>""),J11/I11,"") -> 0.91291281 | L11: =J11 -> 7476.7559 | M11: =IF(AND(I11<>"",I11<>0,L11<>"",L11<>0),L11/I11,"") -> 0.91291281 | N11: =IF(AND(J11<>0,J11<>"",I11<>0,I11<>""),L11-I11,"") -> -713.24409 | P11: =IF(AND(O11<>"",O11<>0,L11<>"",L11<>0),-O11+L11,"") | Q11: =IF(AND(P11<>"",P11<>0,O11<>0,O11<>""),P11/O11,"")
F12: Длина чека | I12: =Центрум!I12 -> 1.68 | J12: =J48 -> 1.5714286 | K12: =IF(AND(I12<>"",I12<>0,J12<>""),J12/I12,"") -> 0.93537415 | L12: =J12 -> 1.5714286 | M12: =IF(AND(I12<>"",I12<>0,L12<>"",L12<>0),L12/I12,"") -> 0.93537415 | N12: =IF(AND(J12<>0,J12<>"",I12<>0,I12<>""),L12-I12,"") -> -0.10857143 | P12: =IF(AND(O12<>"",O12<>0,L12<>"",L12<>0),-O12+L12,"") | Q12: =IF(AND(P12<>"",P12<>0,O12<>0,O12<>""),P12/O12,"")
F13: Кол-во чеков | I13: =IF(I12<>0,I9/I12,"") -> 89.267066 | J13: =G48 -> 56 | K13: =IF(AND(I13<>"",I13<>0,J13<>""),J13/I13,"") -> 0.62733103 | L13: =IF(SUMIF($G$25:$G$47,">=0",$U$25:$U$47)<>0,I13*G48/SUMIF($G$25:$G$47,">=0",$U$25:$U$47),"") -> 57.155578 | M13: =IF(AND(I13<>"",I13<>0,L13<>"",L13<>0),L13/I13,"") -> 0.6402762 | N13: =IF(AND(J13<>0,J13<>"",I13<>0,I13<>""),L13-I13,"") -> -32.111488 | P13: =IF(AND(O13<>"",O13<>0,L13<>"",L13<>0),-O13+L13,"") | Q13: =IF(AND(P13<>"",P13<>0,O13<>0,O13<>""),P13/O13,"")
F14: Кол-во смен план/отработано | I14: =График!AI27 -> 21 | J14: 21 | K14: =IF(AND(I14<>"",I14<>0,J14<>""),J14/I14,"") -> 1 | L14: =IF(SUMIF($D$25:$D$47,">=0",$S$25:$S$47),I48*I8/SUMIF($D$25:$D$47,">=0",$S$25:$S$47),"") -> 551.14732 | N14: =IF(AND(J14<>0,J14<>"",I14<>0,I14<>""),L14-I14,"") -> 530.14732 | P14: =IF(AND(O14<>"",O14<>0,L14<>"",L14<>0),-O14+L14,"") | Q14: =IF(AND(P14<>"",P14<>0,O14<>0,O14<>""),P14/O14,"")
F15: Средние продажи в смену | I15: =Центрум!I15 -> 196534.64 | J15: =J8/J14 -> 31331.168 | K15: =IF(AND(I15<>"",I15<>0,J15<>""),J15/I15,"") -> 0.15941804 | L15: =J15 -> 31331.168 | M15: =IF(AND(I15<>"",I15<>0,L15<>"",L15<>0),L15/I15,"") -> 0.15941804 | N15: =IF(AND(J15<>0,J15<>"",I15<>0,I15<>""),L15-I15,"") -> -165203.47 | P15: =IF(AND(O15<>"",O15<>0,L15<>"",L15<>0),-O15+L15,"") | Q15: =IF(AND(P15<>"",P15<>0,O15<>0,O15<>""),P15/O15,"")
F16: Отставание/Перевыполнение | J16: =J8-I15*J14 -> -3469272.9 | K16: =IF(AND(I16<>"",I16<>0,J16<>""),J16/I16,"") | L16: =J16 -> -3469272.9 | M16: =IF(AND(I16<>"",I16<>0,L16<>"",L16<>0),L16/I16,"") | N16: =IF(AND(J16<>0,J16<>"",I16<>0,I16<>""),L16-I16,"") | P16: =IF(AND(O16<>"",O16<>0,L16<>"",L16<>0),-O16+L16,"") | Q16: =IF(AND(P16<>"",P16<>0,O16<>0,O16<>""),P16/O16,"") | S16: Подарочные сертификаты
F17: Трафик | I17: =Центрум!I17/График!AJ29*График!AJ27 -> 725.7485 | J17: =I48 -> 534 | K17: =IF(AND(I17<>"",I17<>0,J17<>""),J17/I17,"") -> 0.73579208 | L17: =J17/J14*I14 -> 534 | M17: =IF(AND(I17<>"",I17<>0,L17<>"",L17<>0),L17/I17,"") -> 0.73579208 | N17: =IF(AND(J17<>0,J17<>"",I17<>0,I17<>""),L17-I17,"") -> -191.7485 | P17: =IF(AND(O17<>"",O17<>0,L17<>"",L17<>0),-O17+L17,"") | Q17: =IF(AND(P17<>"",P17<>0,O17<>0,O17<>""),P17/O17,"")
K18: =IF(AND(I18<>"",I18<>0,J18<>""),J18/I18,"") | L18: =J18 -> 0 | M18: =IF(AND(I18<>"",I18<>0,L18<>"",L18<>0),L18/I18,"") | N18: =IF(AND(J18<>0,J18<>"",I18<>0,I18<>""),L18-I18,"") | O18: 0 | P18: =IF(AND(O18<>"",O18<>0,L18<>"",L18<>0),-O18+L18,"") | Q18: =IF(AND(P18<>"",P18<>0,O18<>0,O18<>""),P18/O18,"")
K19: =IF(AND(I19<>"",I19<>0,J19<>""),J19/I19,"") | L19: =J19 -> 0 | M19: =IF(AND(I19<>"",I19<>0,L19<>"",L19<>0),L19/I19,"") | N19: =IF(AND(J19<>0,J19<>"",I19<>0,I19<>""),L19-I19,"") | O19: 0 | P19: =IF(AND(O19<>"",O19<>0,L19<>"",L19<>0),-O19+L19,"") | Q19: =IF(AND(P19<>"",P19<>0,O19<>0,O19<>""),P19/O19,"") | S19: =S18/I16 -> #DIV/0!
F20: Конверсия план/факт | I20: =Центрум!I20 -> 0.123 | J20: =Q48 -> 0.10486891 | K20: =J20/I20 -> 0.8525928 | L20: =IF(AND(K8<>0,I14<>0,I48<>0),(I48*Q48+(I48/K8-I48)*I20)/(I48/K8),0) -> 0.11328741 | M20: =IF(AND(I20<>"",I20<>0,L20<>"",L20<>0),L20/I20,"") -> 0.92103582 | N20: =IF(AND(J20<>0,J20<>"",I20<>0,I20<>""),L20-I20,"") -> -0.0097125944 | P20: =IF(AND(O20<>"",O20<>0,L20<>"",L20<>0),-O20+L20,"") | Q20: =IF(AND(P20<>"",P20<>0,O20<>0,O20<>""),P20/O20,"")
B22: Факт продаж за месяц | R22: % выполнения дневного плана | S22: Раcпределение плана по дням
B23: Дата | C23: День недели | D23: Выручка (руб) | E23: Кол-во единиц (шт.) | F23: Средняя стоимость изделия (руб.) | G23: Количество чеков (шт.) | H23: Средняя сумма чека (руб.) | I23: Трафик | J23: Длина чека (шт.) | K23: UNOde50 | L23: IS | M23: Agafi | N23: Kalliope | O23: Raganella | P23: CC/MP | Q23: Конверсия (%) | S23: выручка, план | T23: кол-во ед, план | U23: Кол-во чеков, план | V23: выручка, скорректир.план | W23: кол-во ед, скорр. план | X23: кол-во чеков, скорр. план | Y23: Коэфф. Дня Недели | Z23: Специфика месяца
B24: 1 | C24: 2 | D24: 3 | E24: в | F24: 5 | G24: 6 | H24: 7 | I24: 8 | J24: 9 | K24: 10 | L24: 11 | M24: 12 | N24: 13 | O24: 14 | P24: 15 | S24: 1 | T24: 2 | U24: 3 | V24: 4 | W24: 5 | X24: 6 | Y24: 10 | Z24: 11
A25: 1 | B25: 45993 | C25: вт | D25: 66305 | E25: 7 | F25: =IF(AND(E25<>"",E25<>0),D25/E25,"") -> 9472.1429 | G25: 4 | H25: =IF(AND(G25<>"",G25<>0),D25/G25,"") -> 16576.25 | I25: 35 | J25: =IF(AND(G25<>"",G25<>0),E25/G25,"") -> 1.75 | K25: 30744 | M25: =17684 -> 17684 | Q25: =IF(AND(I25<>"",I25<>0),G25/I25,"") -> 0.11428571 | R25: =D25/S25 -> 1.1191174 | S25: =$I$8*Y25*Z25/SUMPRODUCT($Z$25:$Z$55,$Y$25:$Y$55) -> 59247.58 | T25: =$I$9*Y25*Z25/SUMPRODUCT($Z$25:$Z$55,$Y$25:$Y$55) -> 7.2341368 | U25: =IF($I$12="","",T25/$I$12) -> 4.3060338 | V25: =IF(Z25<>"",IF(D25<>"",D25,($I$8-SUM($V24:V$25))*Y25*Z25/SUMPRODUCT($Z25:$Z$55,$Y25:$Y$55)),"") -> 66305 | W25: =IF(Z25<>"",IF(E25<>"",E25,($I$9-SUM($W24:W$25))*Y25*Z25/SUMPRODUCT($Z25:$Z$55,$Y25:$Y$55)),"") -> 7 | X25: =IF(Z25<>"",IF($I$12<>"",IF(G25<>"",G25,($I$9/$I$12-SUM($X24:X$25))*Y25*Z25/SUMPRODUCT($Z25:$Z$55,$Y25:$Y$55)),""),"") -> 4 | Y25: 1 | Z25: 1
A26: 2 | B26: 45994 | C26: ср | D26: 0 | E26: 0 | F26: =IF(AND(E26<>"",E26<>0),D26/E26,"") | G26: 0 | H26: =IF(AND(G26<>"",G26<>0),D26/G26,"") | I26: 22 | J26: =IF(AND(G26<>"",G26<>0),E26/G26,"") | Q26: =IF(AND(I26<>"",I26<>0),G26/I26,"") -> 0 | R26: =D26/S26 -> 0 | S26: =$I$8*Y26*Z26/SUMPRODUCT($Z$25:$Z$55,$Y$25:$Y$55) -> 43119.417 | T26: =$I$9*Y26*Z26/SUMPRODUCT($Z$25:$Z$55,$Y$25:$Y$55) -> 5.2648861 | U26: =IF($I$12="","",T26/$I$12) -> 3.1338608 | V26: =IF(Z26<>"",IF(D26<>"",D26,($I$8-SUM($V$25:V25))*Y26*Z26/SUMPRODUCT($Z26:$Z$55,$Y26:$Y$55)),"") -> 0 | W26: =IF(Z26<>"",IF(E26<>"",E26,($I$9-SUM($W$25:W25))*Y26*Z26/SUMPRODUCT($Z26:$Z$55,$Y26:$Y$55)),"") -> 0 | X26: =IF(Z26<>"",IF($I$12<>"",IF(G26<>"",G26,($I$9/$I$12-SUM($X$25:X25))*Y26*Z26/SUMPRODUCT($Z26:$Z$55,$Y26:$Y$55)),""),"") -> 0 | Y26: 0.85310234 | Z26: 0.85310234
A27: 3 | B27: 45997 | C27: сб | D27: 60986 | E27: 8 | F27: =IF(AND(E27<>"",E27<>0),D27/E27,"") -> 7623.25 | G27: 4 | H27: =IF(AND(G27<>"",G27<>0),D27/G27,"") -> 15246.5 | I27: 36 | J27: =IF(AND(G27<>"",G27<>0),E27/G27,"") -> 2 | O27: =13390+8990 -> 22380 | Q27: =IF(AND(I27<>"",I27<>0),G27/I27,"") -> 0.11111111 | R27: =D27/S27 -> 4.3136229 | S27: 14138 | T27: 4 | U27: 2 | V27: 16611 | W27: 3 | X27: 3 | Y27: 0.94 | Z27: 0.94
A28: 4 | B28: 45998 | C28: вс | D28: 33266 | E28: 4 | F28: =IF(AND(E28<>"",E28<>0),D28/E28,"") -> 8316.5 | G28: 2 | H28: =IF(AND(G28<>"",G28<>0),D28/G28,"") -> 16633 | I28: 36 | J28: =IF(AND(G28<>"",G28<>0),E28/G28,"") -> 2 | N28: 24082 | Q28: =IF(AND(I28<>"",I28<>0),G28/I28,"") -> 0.055555556 | R28: =D28/S28 -> 0.50162561 | S28: =$I$8*Y28*Z28/SUMPRODUCT($Z$25:$Z$55,$Y$25:$Y$55) -> 66316.391 | T28: =$I$9*Y28*Z28/SUMPRODUCT($Z$25:$Z$55,$Y$25:$Y$55) -> 8.0972395 | U28: =IF($I$12="","",T28/$I$12) -> 4.8197854 | V28: =IF(Z28<>"",IF(D28<>"",D28,($I$8-SUM($V$25:V27))*Y28*Z28/SUMPRODUCT($Z28:$Z$55,$Y28:$Y$55)),"") -> 33266 | W28: =IF(Z28<>"",IF(E28<>"",E28,($I$9-SUM($W$25:W27))*Y28*Z28/SUMPRODUCT($Z28:$Z$55,$Y28:$Y$55)),"") -> 4 | X28: =IF(Z28<>"",IF($I$12<>"",IF(G28<>"",G28,($I$9/$I$12-SUM($X$25:X27))*Y28*Z28/SUMPRODUCT($Z28:$Z$55,$Y28:$Y$55)),""),"") -> 2 | Y28: 1.0579743 | Z28: 1.0579743
A29: 5 | B29: 45999 | C29: пн | D29: 5993 | E29: 1 | F29: =IF(AND(E29<>"",E29<>0),D29/E29,"") -> 5993 | G29: 1 | H29: =IF(AND(G29<>"",G29<>0),D29/G29,"") -> 5993 | I29: 40 | J29: =IF(AND(G29<>"",G29<>0),E29/G29,"") -> 1 | O29: 5993 | Q29: =IF(AND(I29<>"",I29<>0),G29/I29,"") -> 0.025 | R29: =D29/S29 -> 0.10115181 | S29: =$I$8*Y29*Z29/SUMPRODUCT($Z$25:$Z$55,$Y$25:$Y$55) -> 59247.58 | T29: =$I$9*Y29*Z29/SUMPRODUCT($Z$25:$Z$55,$Y$25:$Y$55) -> 7.2341368 | U29: =IF($I$12="","",T29/$I$12) -> 4.3060338 | V29: =IF(Z29<>"",IF(D29<>"",D29,($I$8-SUM($V$25:V28))*Y29*Z29/SUMPRODUCT($Z29:$Z$55,$Y29:$Y$55)),"") -> 5993 | W29: =IF(Z29<>"",IF(E29<>"",E29,($I$9-SUM($W$25:W28))*Y29*Z29/SUMPRODUCT($Z29:$Z$55,$Y29:$Y$55)),"") -> 1 | X29: =IF(Z29<>"",IF($I$12<>"",IF(G29<>"",G29,($I$9/$I$12-SUM($X$25:X28))*Y29*Z29/SUMPRODUCT($Z29:$Z$55,$Y29:$Y$55)),""),"") -> 1 | Y29: 1 | Z29: 1
A30: 6 | B30: 46000 | C30: вт | D30: 9782 | E30: 1 | F30: =IF(AND(E30<>"",E30<>0),D30/E30,"") -> 9782 | G30: 1 | H30: =IF(AND(G30<>"",G30<>0),D30/G30,"") -> 9782 | I30: 23 | J30: =IF(AND(G30<>"",G30<>0),E30/G30,"") -> 1 | Q30: =IF(AND(I30<>"",I30<>0),G30/I30,"") -> 0.043478261 | R30: =D30/S30 -> 0.16510379 | S30: =$I$8*Y30*Z30/SUMPRODUCT($Z$25:$Z$55,$Y$25:$Y$55) -> 59247.58 | T30: =$I$9*Y30*Z30/SUMPRODUCT($Z$25:$Z$55,$Y$25:$Y$55) -> 7.2341368 | U30: =IF($I$12="","",T30/$I$12) -> 4.3060338 | V30: =IF(Z30<>"",IF(D30<>"",D30,($I$8-SUM($V$25:V29))*Y30*Z30/SUMPRODUCT($Z30:$Z$55,$Y30:$Y$55)),"") -> 9782 | W30: =IF(Z30<>"",IF(E30<>"",E30,($I$9-SUM($W$25:W29))*Y30*Z30/SUMPRODUCT($Z30:$Z$55,$Y30:$Y$55)),"") -> 1 | X30: =IF(Z30<>"",IF($I$12<>"",IF(G30<>"",G30,($I$9/$I$12-SUM($X$25:X29))*Y30*Z30/SUMPRODUCT($Z30:$Z$55,$Y30:$Y$55)),""),"") -> 1 | Y30: 1 | Z30: 1
A31: 7 | B31: 46003 | C31: пт | D31: 17354 | E31: 4 | F31: =IF(AND(E31<>"",E31<>0),D31/E31,"") -> 4338.5 | G31: 4 | H31: =IF(AND(G31<>"",G31<>0),D31/G31,"") -> 4338.5 | I31: 31 | J31: =IF(AND(G31<>"",G31<>0),E31/G31,"") -> 1 | Q31: =IF(AND(I31<>"",I31<>0),G31/I31,"") -> 0.12903226 | R31: =D31/S31 -> 0.29290648 | S31: =$I$8*Y31*Z31/SUMPRODUCT($Z$25:$Z$55,$Y$25:$Y$55) -> 59247.58 | T31: =$I$9*Y31*Z31/SUMPRODUCT($Z$25:$Z$55,$Y$25:$Y$55) -> 7.2341368 | U31: =IF($I$12="","",T31/$I$12) -> 4.3060338 | V31: =IF(Z31<>"",IF(D31<>"",D31,($I$8-SUM($V$25:V30))*Y31*Z31/SUMPRODUCT($Z31:$Z$55,$Y31:$Y$55)),"") -> 17354 | W31: =IF(Z31<>"",IF(E31<>"",E31,($I$9-SUM($W$25:W30))*Y31*Z31/SUMPRODUCT($Z31:$Z$55,$Y31:$Y$55)),"") -> 4 | X31: =IF(Z31<>"",IF($I$12<>"",IF(G31<>"",G31,($I$9/$I$12-SUM($X$25:X30))*Y31*Z31/SUMPRODUCT($Z31:$Z$55,$Y31:$Y$55)),""),"") -> 4 | Y31: 1 | Z31: 1
A32: 8 | B32: 46004 | C32: сб | D32: 66110 | E32: 7 | F32: =IF(AND(E32<>"",E32<>0),D32/E32,"") -> 9444.2857 | G32: 5 | H32: =IF(AND(G32<>"",G32<>0),D32/G32,"") -> 13222 | I32: 47 | J32: =IF(AND(G32<>"",G32<>0),E32/G32,"") -> 1.4 | K32: =15493+13357 -> 28850 | N32: 7490 | O32: 11993 | P32: 6493 | Q32: =IF(AND(I32<>"",I32<>0),G32/I32,"") -> 0.10638298 | R32: =D32/S32 -> 1.1158262 | S32: =$I$8*Y32*Z32/SUMPRODUCT($Z$25:$Z$55,$Y$25:$Y$55) -> 59247.58 | T32: =$I$9*Y32*Z32/SUMPRODUCT($Z$25:$Z$55,$Y$25:$Y$55) -> 7.2341368 | U32: =IF($I$12="","",T32/$I$12) -> 4.3060338 | V32: =IF(Z32<>"",IF(D32<>"",D32,($I$8-SUM($V$25:V31))*Y32*Z32/SUMPRODUCT($Z32:$Z$55,$Y32:$Y$55)),"") -> 66110 | W32: =IF(Z32<>"",IF(E32<>"",E32,($I$9-SUM($W$25:W31))*Y32*Z32/SUMPRODUCT($Z32:$Z$55,$Y32:$Y$55)),"") -> 7 | X32: =IF(Z32<>"",IF($I$12<>"",IF(G32<>"",G32,($I$9/$I$12-SUM($X$25:X31))*Y32*Z32/SUMPRODUCT($Z32:$Z$55,$Y32:$Y$55)),""),"") -> 5 | Y32: 1 | Z32: 1
A33: 9 | B33: 46005 | C33: вс | D33: 21341 | E33: 4 | F33: =IF(AND(E33<>"",E33<>0),D33/E33,"") -> 5335.25 | G33: 3 | H33: =IF(AND(G33<>"",G33<>0),D33/G33,"") -> 7113.6667 | I33: 41 | J33: =IF(AND(G33<>"",G33<>0),E33/G33,"") -> 1.3333333 | N33: 8190 | Q33: =IF(AND(I33<>"",I33<>0),G33/I33,"") -> 0.073170732 | R33: =D33/S33 -> 0.36020037 | S33: =$I$8*Y33*Z33/SUMPRODUCT($Z$25:$Z$55,$Y$25:$Y$55) -> 59247.58 | T33: =$I$9*Y33*Z33/SUMPRODUCT($Z$25:$Z$55,$Y$25:$Y$55) -> 7.2341368 | U33: =IF($I$12="","",T33/$I$12) -> 4.3060338 | V33: =IF(Z33<>"",IF(D33<>"",D33,($I$8-SUM($V$25:V32))*Y33*Z33/SUMPRODUCT($Z33:$Z$55,$Y33:$Y$55)),"") -> 21341 | W33: =IF(Z33<>"",IF(E33<>"",E33,($I$9-SUM($W$25:W32))*Y33*Z33/SUMPRODUCT($Z33:$Z$55,$Y33:$Y$55)),"") -> 4 | X33: =IF(Z33<>"",IF($I$12<>"",IF(G33<>"",G33,($I$9/$I$12-SUM($X$25:X32))*Y33*Z33/SUMPRODUCT($Z33:$Z$55,$Y33:$Y$55)),""),"") -> 3 | Y33: 1 | Z33: 1
A34: 10 | B34: 46006 | C34: пн | D34: 3793 | E34: 1 | F34: =IF(AND(E34<>"",E34<>0),D34/E34,"") -> 3793 | G34: 2 | H34: =IF(AND(G34<>"",G34<>0),D34/G34,"") -> 1896.5 | I34: 44 | J34: =IF(AND(G34<>"",G34<>0),E34/G34,"") -> 0.5 | Q34: =IF(AND(I34<>"",I34<>0),G34/I34,"") -> 0.045454545 | R34: =D34/S34 -> 0.064019492 | S34: =$I$8*Y34*Z34/SUMPRODUCT($Z$25:$Z$55,$Y$25:$Y$55) -> 59247.58 | T34: =$I$9*Y34*Z34/SUMPRODUCT($Z$25:$Z$55,$Y$25:$Y$55) -> 7.2341368 | U34: =IF($I$12="","",T34/$I$12) -> 4.3060338 | V34: =IF(Z34<>"",IF(D34<>"",D34,($I$8-SUM($V$25:V33))*Y34*Z34/SUMPRODUCT($Z34:$Z$55,$Y34:$Y$55)),"") -> 3793 | W34: =IF(Z34<>"",IF(E34<>"",E34,($I$9-SUM($W$25:W33))*Y34*Z34/SUMPRODUCT($Z34:$Z$55,$Y34:$Y$55)),"") -> 1 | X34: =IF(Z34<>"",IF($I$12<>"",IF(G34<>"",G34,($I$9/$I$12-SUM($X$25:X33))*Y34*Z34/SUMPRODUCT($Z34:$Z$55,$Y34:$Y$55)),""),"") -> 2 | Y34: 1 | Z34: 1
A35: 11 | B35: 46009 | C35: чт | D35: 39090.02 | E35: 7 | F35: =IF(AND(E35<>"",E35<>0),D35/E35,"") -> 5584.2886 | G35: 3 | H35: =IF(AND(G35<>"",G35<>0),D35/G35,"") -> 13030.007 | I35: 30 | J35: =IF(AND(G35<>"",G35<>0),E35/G35,"") -> 2.3333333 | Q35: =IF(AND(I35<>"",I35<>0),G35/I35,"") -> 0.1 | R35: =D35/S35 -> 0.65977412 | S35: =$I$8*Y35*Z35/SUMPRODUCT($Z$25:$Z$55,$Y$25:$Y$55) -> 59247.58 | T35: =$I$9*Y35*Z35/SUMPRODUCT($Z$25:$Z$55,$Y$25:$Y$55) -> 7.2341368 | U35: =IF($I$12="","",T35/$I$12) -> 4.3060338 | V35: =IF(Z35<>"",IF(D35<>"",D35,($I$8-SUM($V$25:V34))*Y35*Z35/SUMPRODUCT($Z35:$Z$55,$Y35:$Y$55)),"") -> 39090.02 | W35: =IF(Z35<>"",IF(E35<>"",E35,($I$9-SUM($W$25:W34))*Y35*Z35/SUMPRODUCT($Z35:$Z$55,$Y35:$Y$55)),"") -> 7 | X35: =IF(Z35<>"",IF($I$12<>"",IF(G35<>"",G35,($I$9/$I$12-SUM($X$25:X34))*Y35*Z35/SUMPRODUCT($Z35:$Z$55,$Y35:$Y$55)),""),"") -> 3 | Y35: 1 | Z35: 1
A36: 12 | B36: 46010 | C36: пт | D36: 0 | E36: 0 | F36: =IF(AND(E36<>"",E36<>0),D36/E36,"") | G36: 0 | H36: =IF(AND(G36<>"",G36<>0),D36/G36,"") | I36: 22 | J36: =IF(AND(G36<>"",G36<>0),E36/G36,"") | Q36: =IF(AND(I36<>"",I36<>0),G36/I36,"") -> 0 | R36: =D36/S36 -> 0 | S36: =$I$8*Y36*Z36/SUMPRODUCT($Z$25:$Z$55,$Y$25:$Y$55) -> 59247.58 | T36: =$I$9*Y36*Z36/SUMPRODUCT($Z$25:$Z$55,$Y$25:$Y$55) -> 7.2341368 | U36: =IF($I$12="","",T36/$I$12) -> 4.3060338 | V36: =IF(Z36<>"",IF(D36<>"",D36,($I$8-SUM($V$25:V35))*Y36*Z36/SUMPRODUCT($Z36:$Z$55,$Y36:$Y$55)),"") -> 0 | W36: =IF(Z36<>"",IF(E36<>"",E36,($I$9-SUM($W$25:W35))*Y36*Z36/SUMPRODUCT($Z36:$Z$55,$Y36:$Y$55)),"") -> 0 | X36: =IF(Z36<>"",IF($I$12<>"",IF(G36<>"",G36,($I$9/$I$12-SUM($X$25:X35))*Y36*Z36/SUMPRODUCT($Z36:$Z$55,$Y36:$Y$55)),""),"") -> 0 | Y36: 1 | Z36: 1
A37: 13 | B37: 46011 | C37: сб | D37: =28768+7466+31590+4493+12633+10903 -> 95853 | E37: =4+1+4+1+2+1 -> 13 | F37: =IF(AND(E37<>"",E37<>0),D37/E37,"") -> 7373.3077 | G37: 5 | H37: =IF(AND(G37<>"",G37<>0),D37/G37,"") -> 19170.6 | I37: 62 | J37: =IF(AND(G37<>"",G37<>0),E37/G37,"") -> 2.6 | L37: 10903 | M37: 16470 | Q37: =IF(AND(I37<>"",I37<>0),G37/I37,"") -> 0.080645161 | R37: =D37/S37 -> 1.6178382 | S37: =$I$8*Y37*Z37/SUMPRODUCT($Z$25:$Z$55,$Y$25:$Y$55) -> 59247.58 | T37: =$I$9*Y37*Z37/SUMPRODUCT($Z$25:$Z$55,$Y$25:$Y$55) -> 7.2341368 | U37: =IF($I$12="","",T37/$I$12) -> 4.3060338 | V37: =IF(Z37<>"",IF(D37<>"",D37,($I$8-SUM($V$25:V36))*Y37*Z37/SUMPRODUCT($Z37:$Z$55,$Y37:$Y$55)),"") -> 95853 | W37: =IF(Z37<>"",IF(E37<>"",E37,($I$9-SUM($W$25:W36))*Y37*Z37/SUMPRODUCT($Z37:$Z$55,$Y37:$Y$55)),"") -> 13 | X37: =IF(Z37<>"",IF($I$12<>"",IF(G37<>"",G37,($I$9/$I$12-SUM($X$25:X36))*Y37*Z37/SUMPRODUCT($Z37:$Z$55,$Y37:$Y$55)),""),"") -> 5 | Y37: 1 | Z37: 1
A38: 14 | B38: 46012 | C38: вс | D38: 0 | E38: 0 | F38: =IF(AND(E38<>"",E38<>0),D38/E38,"") | G38: 0 | H38: =IF(AND(G38<>"",G38<>0),D38/G38,"") | I38: 2 | J38: =IF(AND(G38<>"",G38<>0),E38/G38,"") | Q38: =IF(AND(I38<>"",I38<>0),G38/I38,"") -> 0 | R38: =D38/S38 -> 0 | S38: =$I$8*Y38*Z38/SUMPRODUCT($Z$25:$Z$46,$Y$25:$Y$46) -> 59247.58 | T38: =$I$9*Y38*Z38/SUMPRODUCT($Z$25:$Z$46,$Y$25:$Y$46) -> 7.2341368 | U38: =IF($I$12="","",T38/$I$12) -> 4.3060338 | V38: =IF(Z38<>"",IF(D38<>"",D38,($I$8-SUM($V$25:V37))*Y38*Z38/SUMPRODUCT($Z38:$Z$55,$Y38:$Y$55)),"") -> 0 | W38: =IF(Z38<>"",IF(E38<>"",E38,($I$9-SUM($W$25:W37))*Y38*Z38/SUMPRODUCT($Z38:$Z$55,$Y38:$Y$55)),"") -> 0 | X38: =IF(Z38<>"",IF($I$12<>"",IF(G38<>"",G38,($I$9/$I$12-SUM($X$25:X37))*Y38*Z38/SUMPRODUCT($Z38:$Z$55,$Y38:$Y$55)),""),"") -> 0 | Y38: 1 | Z38: 1
A39: 15 | B39: 46013 | C39: пн | D39: =7893+11132+5382+14075 -> 38482 | E39: =4+3 -> 7 | F39: =IF(AND(E39<>"",E39<>0),D39/E39,"") -> 5497.4286 | G39: 4 | H39: =IF(AND(G39<>"",G39<>0),D39/G39,"") -> 9620.5 | I39: 12 | J39: =IF(AND(G39<>"",G39<>0),E39/G39,"") -> 1.75 | Q39: =IF(AND(I39<>"",I39<>0),G39/I39,"") -> 0.33333333 | R39: =D39/S39 -> 0.64951176 | S39: =$I$8*Y39*Z39/SUMPRODUCT($Z$25:$Z$46,$Y$25:$Y$46) -> 59247.58 | T39: =$I$9*Y39*Z39/SUMPRODUCT($Z$25:$Z$46,$Y$25:$Y$46) -> 7.2341368 | U39: =IF($I$12="","",T39/$I$12) -> 4.3060338 | V39: =IF(Z39<>"",IF(D39<>"",D39,($I$8-SUM($V$25:V38))*Y39*Z39/SUMPRODUCT($Z39:$Z$55,$Y39:$Y$55)),"") -> 38482 | W39: =IF(Z39<>"",IF(E39<>"",E39,($I$9-SUM($W$25:W38))*Y39*Z39/SUMPRODUCT($Z39:$Z$55,$Y39:$Y$55)),"") -> 7 | X39: =IF(Z39<>"",IF($I$12<>"",IF(G39<>"",G39,($I$9/$I$12-SUM($X$25:X38))*Y39*Z39/SUMPRODUCT($Z39:$Z$55,$Y39:$Y$55)),""),"") -> 4 | Y39: 1 | Z39: 1
A40: 16 | B40: 46016 | C40: чт | D40: =10562+4193 -> 14755 | E40: 2 | F40: =IF(AND(E40<>"",E40<>0),D40/E40,"") -> 7377.5 | G40: 2 | H40: =IF(AND(G40<>"",G40<>0),D40/G40,"") -> 7377.5 | I40: 26 | Q40: =IF(AND(I40<>"",I40<>0),G40/I40,"") -> 0.076923077 | R40: =D40/S40 -> 0.24903971 | S40: =$I$8*Y40*Z40/SUMPRODUCT($Z$25:$Z$46,$Y$25:$Y$46) -> 59247.58 | T40: =$I$9*Y40*Z40/SUMPRODUCT($Z$25:$Z$46,$Y$25:$Y$46) -> 7.2341368 | U40: =IF($I$12="","",T40/$I$12) -> 4.3060338 | V40: =IF(Z40<>"",IF(D40<>"",D40,($I$8-SUM($V$25:V39))*Y40*Z40/SUMPRODUCT($Z40:$Z$55,$Y40:$Y$55)),"") -> 14755 | W40: =IF(Z40<>"",IF(E40<>"",E40,($I$9-SUM($W$25:W39))*Y40*Z40/SUMPRODUCT($Z40:$Z$55,$Y40:$Y$55)),"") -> 2 | X40: =IF(Z40<>"",IF($I$12<>"",IF(G40<>"",G40,($I$9/$I$12-SUM($X$25:X39))*Y40*Z40/SUMPRODUCT($Z40:$Z$55,$Y40:$Y$55)),""),"") -> 2 | Y40: 1 | Z40: 1
A41: 17 | B41: 46017 | C41: пт | D41: 9685.5 | E41: 2 | F41: =IF(AND(E41<>"",E41<>0),D41/E41,"") -> 4842.75 | G41: 2 | H41: =IF(AND(G41<>"",G41<>0),D41/G41,"") -> 4842.75 | I41: 25 | O41: 6027.5 | Q41: =IF(AND(I41<>"",I41<>0),G41/I41,"") -> 0.08 | S41: =$I$8*Y41*Z41/SUMPRODUCT($Z$25:$Z$46,$Y$25:$Y$46) -> 59247.58 | T41: =$I$9*Y41*Z41/SUMPRODUCT($Z$25:$Z$46,$Y$25:$Y$46) -> 7.2341368 | U41: =IF($I$12="","",T41/$I$12) -> 4.3060338 | V41: =IF(Z41<>"",IF(D41<>"",D41,($I$8-SUM($V$25:V40))*Y41*Z41/SUMPRODUCT($Z41:$Z$55,$Y41:$Y$55)),"") -> 9685.5 | W41: =IF(Z41<>"",IF(E41<>"",E41,($I$9-SUM($W$25:W40))*Y41*Z41/SUMPRODUCT($Z41:$Z$55,$Y41:$Y$55)),"") -> 2 | X41: =IF(Z41<>"",IF($I$12<>"",IF(G41<>"",G41,($I$9/$I$12-SUM($X$25:X40))*Y41*Z41/SUMPRODUCT($Z41:$Z$55,$Y41:$Y$55)),""),"") -> 2 | Y41: 1 | Z41: 1
A42: 18 | B42: 46019 | C42: вс | D42: =4571+11184+6294 -> 22049 | E42: 4 | F42: =IF(AND(E42<>"",E42<>0),D42/E42,"") -> 5512.25 | G42: 3 | H42: =IF(AND(G42<>"",G42<>0),D42/G42,"") -> 7349.6667 | J42: =IF(AND(G42<>"",G42<>0),E42/G42,"") -> 1.3333333 | Q42: =IF(AND(I42<>"",I42<>0),G42/I42,"") | R42: =D42/S42 -> 0.37215022 | S42: =$I$8*Y42*Z42/SUMPRODUCT($Z$25:$Z$46,$Y$25:$Y$46) -> 59247.58 | T42: =$I$9*Y42*Z42/SUMPRODUCT($Z$25:$Z$46,$Y$25:$Y$46) -> 7.2341368 | U42: =IF($I$12="","",T42/$I$12) -> 4.3060338 | V42: =IF(Z42<>"",IF(D42<>"",D42,($I$8-SUM($V$25:V41))*Y42*Z42/SUMPRODUCT($Z42:$Z$55,$Y42:$Y$55)),"") -> 22049 | W42: =IF(Z42<>"",IF(E42<>"",E42,($I$9-SUM($W$25:W41))*Y42*Z42/SUMPRODUCT($Z42:$Z$55,$Y42:$Y$55)),"") -> 4 | X42: =IF(Z42<>"",IF($I$12<>"",IF(G42<>"",G42,($I$9/$I$12-SUM($X$25:X41))*Y42*Z42/SUMPRODUCT($Z42:$Z$55,$Y42:$Y$55)),""),"") -> 3 | Y42: 1 | Z42: 1
A43: 19 | B43: 46020 | C43: пн | D43: =5182+34712+6293+18727 -> 64914 | E43: 8 | F43: =IF(AND(E43<>"",E43<>0),D43/E43,"") -> 8114.25 | G43: 4 | H43: =IF(AND(G43<>"",G43<>0),D43/G43,"") -> 16228.5 | J43: =IF(AND(G43<>"",G43<>0),E43/G43,"") -> 2 | K43: 25490 | Q43: =IF(AND(I43<>"",I43<>0),G43/I43,"") | R43: =D43/S43 -> 1.0956397 | S43: =$I$8*Y43*Z43/SUMPRODUCT($Z$25:$Z$46,$Y$25:$Y$46) -> 59247.58 | T43: =$I$9*Y43*Z43/SUMPRODUCT($Z$25:$Z$46,$Y$25:$Y$46) -> 7.2341368 | U43: =IF($I$12="","",T43/$I$12) -> 4.3060338 | V43: =IF(Z43<>"",IF(D43<>"",D43,($I$8-SUM($V$25:V42))*Y43*Z43/SUMPRODUCT($Z43:$Z$55,$Y43:$Y$55)),"") -> 64914 | W43: =IF(Z43<>"",IF(E43<>"",E43,($I$9-SUM($W$25:W42))*Y43*Z43/SUMPRODUCT($Z43:$Z$46,$Y43:$Y$46)),"") -> 8 | X43: =IF(Z43<>"",IF($I$12<>"",IF(G43<>"",G43,($I$9/$I$12-SUM($X$25:X42))*Y43*Z43/SUMPRODUCT($Z43:$Z$46,$Y43:$Y$46)),""),"") -> 4 | Y43: 1 | Z43: 1
A44: 20 | B44: 46021 | C44: вт | D44: =6482+13072+8393+35262+5193 -> 68402 | E44: 7 | F44: =IF(AND(E44<>"",E44<>0),D44/E44,"") -> 9771.7143 | G44: 5 | H44: =IF(AND(G44<>"",G44<>0),D44/G44,"") -> 13680.4 | J44: =IF(AND(G44<>"",G44<>0),E44/G44,"") -> 1.4 | K44: 35262 | Q44: =IF(AND(L44<>"",L44<>0),J44/L44,"") | R44: =D44/S44 -> 1.1545113 | S44: =$I$8*Y44*Z44/SUMPRODUCT($Z$25:$Z$46,$Y$25:$Y$46) -> 59247.58 | T44: =$I$9*Y44*Z44/SUMPRODUCT($Z$25:$Z$46,$Y$25:$Y$46) -> 7.2341368 | U44: =IF($I$12="","",T44/$I$12) -> 4.3060338 | V44: =IF(Z44<>"",IF(D44<>"",D44,($I$8-SUM($V$25:V43))*Y44*Z44/SUMPRODUCT($Z44:$Z$46,$Y44:$Y$46)),"") -> 68402 | W44: =IF(Z44<>"",IF(E44<>"",E44,($I$9-SUM($W$25:W43))*Y44*Z44/SUMPRODUCT($Z44:$Z$46,$Y44:$Y$46)),"") -> 7 | X44: =IF(Z44<>"",IF($I$12<>"",IF(G44<>"",G44,($I$9/$I$12-SUM($X$25:X43))*Y44*Z44/SUMPRODUCT($Z44:$Z$46,$Y44:$Y$46)),""),"") -> 5 | Y44: 1 | Z44: 1
A45: 21 | B45: 46022 | C45: ср | D45: =15001+4793 -> 19794 | E45: 1 | F45: =IF(AND(E45<>"",E45<>0),D45/E45,"") -> 19794 | G45: 2 | H45: =IF(AND(G45<>"",G45<>0),D45/G45,"") -> 9897 | J45: =IF(AND(G45<>"",G45<>0),E45/G45,"") -> 0.5 | Q45: =IF(AND(L45<>"",L45<>0),J45/L45,"") | R45: =D45/S45 -> 0.33408959 | S45: =$I$8*Y45*Z45/SUMPRODUCT($Z$25:$Z$46,$Y$25:$Y$46) -> 59247.58 | T45: =$I$9*Y45*Z45/SUMPRODUCT($Z$25:$Z$46,$Y$25:$Y$46) -> 7.2341368 | U45: =IF($I$12="","",T45/$I$12) -> 4.3060338 | V45: =IF(Z45<>"",IF(D45<>"",D45,($I$8-SUM($V$25:V44))*Y45*Z45/SUMPRODUCT($Z45:$Z$46,$Y45:$Y$46)),"") -> 19794 | W45: =IF(Z45<>"",IF(E45<>"",E45,($I$9-SUM($W$25:W44))*Y45*Z45/SUMPRODUCT($Z45:$Z$46,$Y45:$Y$46)),"") -> 1 | X45: =IF(Z45<>"",IF($I$12<>"",IF(G45<>"",G45,($I$9/$I$12-SUM($X$25:X44))*Y45*Z45/SUMPRODUCT($Z45:$Z$46,$Y45:$Y$46)),""),"") -> 2 | Y45: 1 | Z45: 1
F46: =IF(AND(E46<>"",E46<>0),D46/E46,"") | H46: =IF(AND(G46<>"",G46<>0),D46/G46,"") | J46: =IF(AND(G46<>"",G46<>0),E46/G46,"") | Q46: =IF(AND(L46<>"",L46<>0),J46/L46,"") | R46: =D46/S46 -> #DIV/0! | S46: =$I$8*Y46*Z46/SUMPRODUCT($Z$25:$Z$46,$Y$25:$Y$46) -> 0 | T46: =$I$9*Y46*Z46/SUMPRODUCT($Z$25:$Z$46,$Y$25:$Y$46) -> 0 | U46: =IF($I$12="","",T46/$I$12) -> 0 | V46: =IF(Z46<>"",IF(D46<>"",D46,($I$8-SUM($V$25:V45))*Y46*Z46/SUMPRODUCT($Z46:$Z$46,$Y46:$Y$46)),"") | W46: =IF(Z46<>"",IF(E46<>"",E46,($I$9-SUM($W$25:W39))*Y46*Z46/SUMPRODUCT($Z46:$Z$46,$Y46:$Y$46)),"") | X46: =IF(Z46<>"",IF($I$12<>"",IF(G46<>"",G46,($I$9/$I$12-SUM($X$25:X39))*Y46*Z46/SUMPRODUCT($Z46:$Z$46,$Y46:$Y$46)),""),"")
F47: =IF(AND(E47<>"",E47<>0),D47/E47,"") | H47: =IF(AND(G47<>"",G47<>0),D47/G47,"") | J47: =IF(AND(G47<>"",G47<>0),E47/G47,"") | Q47: =IF(AND(L47<>"",L47<>0),J47/L47,"") | R47: =D47/S47 -> #DIV/0! | S47: =$I$8*Y47*Z47/SUMPRODUCT($Z$25:$Z$46,$Y$25:$Y$46) -> 0 | T47: =$I$9*Y47*Z47/SUMPRODUCT($Z$25:$Z$46,$Y$25:$Y$46) -> 0 | U47: =IF($I$12="","",T47/$I$12) -> 0 | V47: =IF(Z47<>"",IF(D47<>"",D47,($I$8-SUM($V$25:V46))*Y47*Z47/SUMPRODUCT($Z$46:$Z47,$Y$46:$Y47)),"") | W47: =IF(Z47<>"",IF(E47<>"",E47,($I$9-SUM($W$25:W40))*Y47*Z47/SUMPRODUCT($Z$46:$Z47,$Y$46:$Y47)),"") | X47: =IF(Z47<>"",IF($I$12<>"",IF(G47<>"",G47,($I$9/$I$12-SUM($X$25:X40))*Y47*Z47/SUMPRODUCT($Z$46:$Z47,$Y$46:$Y47)),""),"")
B48: итого | D48: =SUM(D25:D47) -> 657954.52 | E48: =SUM(E25:E47) -> 88 | F48: =IF(AND(E48<>"",E48<>0),D48/E48,"") -> 7476.7559 | G48: =SUM(G25:G47) -> 56 | H48: =IF(AND(G48<>"",G48<>0),D48/G48,"") -> 11749.188 | I48: =SUM(I25:I47) -> 534 | J48: =IF(AND(G48<>"",G48<>0),E48/G48,"") -> 1.5714286 | K48: =SUM(K25:K47) -> 120346 | P48: =SUM(P25:P47) -> 6493 | Q48: =IF(AND(I48<>"",I48<>0),G48/I48,"") -> 0.10486891 | R48: =D48/S48 -> 0.5528889 | S48: =SUM(S25:S47) -> 1190030.3 | T48: =SUM(T25:T47) -> 147.57659 | U48: =SUM(U25:U47) -> 87.462254 | V48: =SUM(V25:V47) -> 613579.52 | W48: =SUM(W25:W47) -> 83 | X48: =SUM(X25:X47) -> 55
D49: =SUMIF(D25:D47,"",S25:S47)+D48 -> 657954.52

Sheet Стекольщикова А. А.
B1: =TODAY()-1 -> 46031
B2: (отчетная дата) | J2: ЕЖЕДНЕВНЫЙ ОТЧЕТ О ПРОДАЖАХ
B3: Осталось до выполнения плана!!! | J3: =График!B28 -> Стекольщикова Алла
C4: =I8-D50 -> 541084.21 | E4: =IF(I8<>0,C4/I8,0) -> 0.38192305
F6: Целевые показатели
F7: Показатель | I7: План | J7: Факт | K7: % выполнения | L7: Прогноз выполнения | M7: % выполнения по прогнозу | N7: Отклонение | O7: Факт аналогичного месяца прошлого года | P7: Отклонение LFL
F8: Выручка | I8: =Центрум!I8/График!AJ29*График!AJ28 -> 1416736.2 | J8: =D50 -> 875652 | K8: =IF(AND(I8<>"",I8<>0,J8<>""),J8/I8,"") -> 0.61807695 | L8: =IF(SUMIF($D$25:$D$49,">=0",$T$25:$T$49)<>0,I8*D50/SUMIF($D$25:$D$49,">=0",$T$25:$T$49),0) -> 886047.48 | M8: =L8/I8 -> 0.62541458 | N8: =IF(AND(J8<>0,J8<>"",I8<>0,I8<>""),L8-I8,"") -> -530688.73 | P8: =IF(AND(O8<>"",O8<>0,L8<>"",L8<>0),-O8+L8,"") | Q8: =IF(AND(P8<>"",P8<>0,O8<>0,O8<>""),P8/O8,"")
F9: Кол-во изделий | I9: =I8/I11 -> 172.98366 | J9: =E50 -> 99 | K9: =IF(AND(I9<>"",I9<>0,J9<>""),J9/I9,"") -> 0.57230837 | L9: =IF(SUMIF($E$25:$E$49,">=0",$U$25:$U$49)<>0,I9*E50/SUMIF($E$25:$E$49,">=0",$U$25:$U$49),0) -> 98.860421 | M9: =IF(AND(I9<>"",I9<>0,L9<>"",L9<>0),L9/I9,"") -> 0.57150148 | N9: =IF(AND(J9<>0,J9<>"",I9<>0,I9<>""),L9-I9,"") -> -74.123243 | O9: =O8/O11 -> #DIV/0! | P9: =IF(AND(O9<>"",O9<>0,L9<>"",L9<>0),-O9+L9,"") -> #DIV/0! | Q9: =IF(AND(P9<>"",P9<>0,O9<>0,O9<>""),P9/O9,"") -> #DIV/0!
F10: Средний чек | I10: =I11*I12 -> 13759.2 | J10: =H50 -> 12877.235 | K10: =IF(AND(I10<>"",I10<>0,J10<>""),J10/I10,"") -> 0.9359 | L10: =J10 -> 12877.235 | M10: =IF(AND(I10<>"",I10<>0,L10<>"",L10<>0),L10/I10,"") -> 0.9359 | N10: =IF(AND(J10<>0,J10<>"",I10<>0,I10<>""),L10-I10,"") -> -881.96471 | O10: =O11*O12 -> 0 | P10: =IF(AND(O10<>"",O10<>0,L10<>"",L10<>0),-O10+L10,"") | Q10: =IF(AND(P10<>"",P10<>0,O10<>0,O10<>""),P10/O10,"")
F11: Средняя стоимость изделия | I11: =Центрум!I11 -> 8190 | J11: =F50 -> 8844.9697 | K11: =IF(AND(I11<>"",I11<>0,J11<>""),J11/I11,"") -> 1.0799719 | L11: =J11 -> 8844.9697 | M11: =IF(AND(I11<>"",I11<>0,L11<>"",L11<>0),L11/I11,"") -> 1.0799719 | N11: =IF(AND(J11<>0,J11<>"",I11<>0,I11<>""),L11-I11,"") -> 654.9697 | P11: =IF(AND(O11<>"",O11<>0,L11<>"",L11<>0),-O11+L11,"") | Q11: =IF(AND(P11<>"",P11<>0,O11<>0,O11<>""),P11/O11,"")
F12: Длина чека | I12: =Центрум!I12 -> 1.68 | J12: =J50 -> 1.4558824 | K12: =IF(AND(I12<>"",I12<>0,J12<>""),J12/I12,"") -> 0.86659664 | L12: =J12 -> 1.4558824 | M12: =IF(AND(I12<>"",I12<>0,L12<>"",L12<>0),L12/I12,"") -> 0.86659664 | N12: =IF(AND(J12<>0,J12<>"",I12<>0,I12<>""),L12-I12,"") -> -0.22411765 | P12: =IF(AND(O12<>"",O12<>0,L12<>"",L12<>0),-O12+L12,"") | Q12: =IF(AND(P12<>"",P12<>0,O12<>0,O12<>""),P12/O12,"")
F13: Кол-во чеков | I13: =IF(I12<>0,I9/I12,"") -> 102.96647 | J13: =G50 -> 68 | K13: =IF(AND(I13<>"",I13<>0,J13<>""),J13/I13,"") -> 0.66040918 | L13: =IF(SUMIF($G$25:$G$49,">=0",$V$25:$V$49)<>0,I13*G50/SUMIF($G$25:$G$49,">=0",$V$25:$V$49),"") -> 68.155934 | M13: =IF(AND(I13<>"",I13<>0,L13<>"",L13<>0),L13/I13,"") -> 0.66192359 | N13: =IF(AND(J13<>0,J13<>"",I13<>0,I13<>""),L13-I13,"") -> -34.810534 | P13: =IF(AND(O13<>"",O13<>0,L13<>"",L13<>0),-O13+L13,"") | Q13: =IF(AND(P13<>"",P13<>0,O13<>0,O13<>""),P13/O13,"")
F14: Кол-во смен план/отработано | I14: =График!AI28 -> 25 | J14: 25 | K14: =IF(AND(I14<>"",I14<>0,J14<>""),J14/I14,"") -> 1 | L14: =IF(SUMIF($D$25:$D$49,">=0",$T$25:$T$49),I50*I8/SUMIF($D$25:$D$49,">=0",$T$25:$T$49),"") -> 634.44356 | N14: =IF(AND(J14<>0,J14<>"",I14<>0,I14<>""),L14-I14,"") -> 609.44356 | P14: =IF(AND(O14<>"",O14<>0,L14<>"",L14<>0),-O14+L14,"") | Q14: =IF(AND(P14<>"",P14<>0,O14<>0,O14<>""),P14/O14,"")
F15: Средние продажи в смену | I15: =Центрум!I15 -> 196534.64 | J15: =J8/J14 -> 35026.08 | K15: =IF(AND(I15<>"",I15<>0,J15<>""),J15/I15,"") -> 0.17821836 | L15: =J15 -> 35026.08 | M15: =IF(AND(I15<>"",I15<>0,L15<>"",L15<>0),L15/I15,"") -> 0.17821836 | N15: =IF(AND(J15<>0,J15<>"",I15<>0,I15<>""),L15-I15,"") -> -161508.56 | P15: =IF(AND(O15<>"",O15<>0,L15<>"",L15<>0),-O15+L15,"") | Q15: =IF(AND(P15<>"",P15<>0,O15<>0,O15<>""),P15/O15,"")
F16: Отставание/Перевыполнение | J16: =J8-I15*J14 -> -4037713.9 | K16: =IF(AND(I16<>"",I16<>0,J16<>""),J16/I16,"") | L16: =J16 -> -4037713.9 | M16: =IF(AND(I16<>"",I16<>0,L16<>"",L16<>0),L16/I16,"") | N16: =IF(AND(J16<>0,J16<>"",I16<>0,I16<>""),L16-I16,"") | P16: =IF(AND(O16<>"",O16<>0,L16<>"",L16<>0),-O16+L16,"") | Q16: =IF(AND(P16<>"",P16<>0,O16<>0,O16<>""),P16/O16,"") | S16: Подарочные сертификаты
F17: Трафик | I17: =Центрум!I17/График!AJ29*График!AJ28 -> 837.12575 | J17: =I50 -> 627 | K17: =IF(AND(I17<>"",I17<>0,J17<>""),J17/I17,"") -> 0.74899142 | L17: =J17/J14*I14 -> 627 | M17: =IF(AND(I17<>"",I17<>0,L17<>"",L17<>0),L17/I17,"") -> 0.74899142 | N17: =IF(AND(J17<>0,J17<>"",I17<>0,I17<>""),L17-I17,"") -> -210.12575 | P17: =IF(AND(O17<>"",O17<>0,L17<>"",L17<>0),-O17+L17,"") | Q17: =IF(AND(P17<>"",P17<>0,O17<>0,O17<>""),P17/O17,"")
K18: =IF(AND(I18<>"",I18<>0,J18<>""),J18/I18,"") | L18: =J18 -> 0 | M18: =IF(AND(I18<>"",I18<>0,L18<>"",L18<>0),L18/I18,"") | N18: =IF(AND(J18<>0,J18<>"",I18<>0,I18<>""),L18-I18,"") | O18: 0 | P18: =IF(AND(O18<>"",O18<>0,L18<>"",L18<>0),-O18+L18,"") | Q18: =IF(AND(P18<>"",P18<>0,O18<>0,O18<>""),P18/O18,"")
J19: =P50 -> 41508 | K19: =IF(AND(I19<>"",I19<>0,J19<>""),J19/I19,"") | L19: =J19 -> 41508 | M19: =IF(AND(I19<>"",I19<>0,L19<>"",L19<>0),L19/I19,"") | N19: =IF(AND(J19<>0,J19<>"",I19<>0,I19<>""),L19-I19,"") | O19: 0 | P19: =IF(AND(O19<>"",O19<>0,L19<>"",L19<>0),-O19+L19,"") | Q19: =IF(AND(P19<>"",P19<>0,O19<>0,O19<>""),P19/O19,"") | S19: =S18/I16 -> #DIV/0!
F20: Конверсия план/факт | I20: =Центрум!I20 -> 0.123 | J20: =R50 -> 0.10845295 | K20: =J20/I20 -> 0.88173131 | L20: =IF(AND(K8<>0,I14<>0,I50<>0),(I50*R50+(I50/K8-I50)*I20)/(I50/K8),0) -> 0.1140088 | M20: =IF(AND(I20<>"",I20<>0,L20<>"",L20<>0),L20/I20,"") -> 0.92690085 | N20: =IF(AND(J20<>0,J20<>"",I20<>0,I20<>""),L20-I20,"") -> -0.008991196 | P20: =IF(AND(O20<>"",O20<>0,L20<>"",L20<>0),-O20+L20,"") | Q20: =IF(AND(P20<>"",P20<>0,O20<>0,O20<>""),P20/O20,"")
B22: Факт продаж за месяц | S22: % выполнения дневного плана | T22: Раcпределение плана по дням
B23: Дата | C23: День недели | D23: Выручка (руб) | E23: Кол-во единиц (шт.) | F23: Средняя стоимость изделия (руб.) | G23: Количество чеков (шт.) | H23: Средняя сумма чека (руб.) | I23: Трафик | J23: Длина чека (шт.) | K23: UNOde50 | L23: IS | M23: Agafi | N23: Kalliope | O23: Raganella | P23: CC/MP | Q23: Eva Rites | R23: Конверсия (%) | T23: выручка, план | U23: кол-во ед, план | V23: Кол-во чеков, план | W23: выручка, скорректир.план | X23: кол-во ед, скорр. план | Y23: кол-во чеков, скорр. план | Z23: Коэфф. Дня Недели | AA23: Специфика месяца
B24: 1 | C24: 2 | D24: 3 | E24: в | F24: 5 | G24: 6 | H24: 7 | I24: 8 | J24: 9 | K24: 10 | L24: 11 | M24: 12 | N24: 13 | O24: 14 | P24: 15 | R24: 16 | T24: 1 | U24: 2 | V24: 3 | W24: 4 | X24: 5 | Y24: 6 | Z24: 10 | AA24: 11
A25: 1 | B25: 45993 | C25: вт | D25: 0 | E25: 0 | F25: =IF(AND(E25<>"",E25<>0),D25/E25,"") | G25: 0 | H25: =IF(AND(G25<>"",G25<>0),D25/G25,"") | I25: 33 | J25: =IF(AND(G25<>"",G25<>0),E25/G25,"") | R25: =IF(AND(I25<>"",I25<>0),G25/I25,"") -> 0 | S25: =D25/T25 -> 0 | T25: =$I$8*Z25*AA25/SUMPRODUCT($AA$25:$AA$57,$Z$25:$Z$57) -> 52606.749 | U25: =$I$9*Z25*AA25/SUMPRODUCT($AA$25:$AA$57,$Z$25:$Z$57) -> 6.4232904 | V25: =IF($I$12="","",U25/$I$12) -> 3.8233872 | W25: =IF(AA25<>"",IF(D25<>"",D25,($I$8-SUM($W24:W$25))*Z25*AA25/SUMPRODUCT($AA25:$AA$57,$Z25:$Z$57)),"") -> 0 | X25: =IF(AA25<>"",IF(E25<>"",E25,($I$9-SUM($X24:X$25))*Z25*AA25/SUMPRODUCT($AA25:$AA$57,$Z25:$Z$57)),"") -> 0 | Y25: =IF(AA25<>"",IF($I$12<>"",IF(G25<>"",G25,($I$9/$I$12-SUM($Y24:Y$25))*Z25*AA25/SUMPRODUCT($AA25:$AA$57,$Z25:$Z$57)),""),"") -> 0 | Z25: 1 | AA25: 1
A26: 2 | B26: 45994 | C26: ср | D26: 0 | E26: 0 | F26: =IF(AND(E26<>"",E26<>0),D26/E26,"") | G26: 0 | H26: =IF(AND(G26<>"",G26<>0),D26/G26,"") | I26: 22 | J26: =IF(AND(G26<>"",G26<>0),E26/G26,"") | R26: =IF(AND(I26<>"",I26<>0),G26/I26,"") -> 0 | S26: =D26/T26 -> 0 | T26: =$I$8*Z26*AA26/SUMPRODUCT($AA$25:$AA$57,$Z$25:$Z$57) -> 38286.329 | U26: =$I$9*Z26*AA26/SUMPRODUCT($AA$25:$AA$57,$Z$25:$Z$57) -> 4.6747654 | V26: =IF($I$12="","",U26/$I$12) -> 2.7825985 | W26: =IF(AA26<>"",IF(D26<>"",D26,($I$8-SUM($W$25:W25))*Z26*AA26/SUMPRODUCT($AA26:$AA$57,$Z26:$Z$57)),"") -> 0 | X26: =IF(AA26<>"",IF(E26<>"",E26,($I$9-SUM($X$25:X25))*Z26*AA26/SUMPRODUCT($AA26:$AA$57,$Z26:$Z$57)),"") -> 0 | Y26: =IF(AA26<>"",IF($I$12<>"",IF(G26<>"",G26,($I$9/$I$12-SUM($Y$25:Y25))*Z26*AA26/SUMPRODUCT($AA26:$AA$57,$Z26:$Z$57)),""),"") -> 0 | Z26: 0.85310234 | AA26: 0.85310234
A27: 3 | B27: 45995 | C27: чт | D27: 48596 | E27: 2 | F27: =IF(AND(E27<>"",E27<>0),D27/E27,"") -> 24298 | G27: 3 | H27: =IF(AND(G27<>"",G27<>0),D27/G27,"") -> 16198.667 | I27: 13 | J27: =IF(AND(G27<>"",G27<>0),E27/G27,"") -> 0.66666667 | R27: =IF(AND(I27<>"",I27<>0),G27/I27,"") -> 0.23076923 | S27: =D27/T27 -> 3.4372613 | T27: 14138 | U27: 4 | V27: 2 | W27: 16611 | X27: 3 | Y27: 3 | Z27: 0.94 | AA27: 0.94
A28: 4 | B28: 45996 | C28: пт | D28: 16579 | E28: 3 | F28: =IF(AND(E28<>"",E28<>0),D28/E28,"") -> 5526.3333 | G28: 3 | H28: =IF(AND(G28<>"",G28<>0),D28/G28,"") -> 5526.3333 | I28: 39 | J28: =IF(AND(G28<>"",G28<>0),E28/G28,"") -> 1 | M28: 7493 | R28: =IF(AND(I28<>"",I28<>0),G28/I28,"") -> 0.076923077 | S28: =D28/T28 -> 0.28155718 | T28: =$I$8*Z28*AA28/SUMPRODUCT($AA$25:$AA$57,$Z$25:$Z$57) -> 58883.244 | U28: =$I$9*Z28*AA28/SUMPRODUCT($AA$25:$AA$57,$Z$25:$Z$57) -> 7.1896513 | V28: =IF($I$12="","",U28/$I$12) -> 4.2795543 | W28: =IF(AA28<>"",IF(D28<>"",D28,($I$8-SUM($W$25:W27))*Z28*AA28/SUMPRODUCT($AA28:$AA$57,$Z28:$Z$57)),"") -> 16579 | X28: =IF(AA28<>"",IF(E28<>"",E28,($I$9-SUM($X$25:X27))*Z28*AA28/SUMPRODUCT($AA28:$AA$57,$Z28:$Z$57)),"") -> 3 | Y28: =IF(AA28<>"",IF($I$12<>"",IF(G28<>"",G28,($I$9/$I$12-SUM($Y$25:Y27))*Z28*AA28/SUMPRODUCT($AA28:$AA$57,$Z28:$Z$57)),""),"") -> 3 | Z28: 1.0579743 | AA28: 1.0579743
A29: 5 | B29: 45997 | C29: сб | D29: 73034 | E29: 7 | F29: =IF(AND(E29<>"",E29<>0),D29/E29,"") -> 10433.429 | G29: 4 | H29: =IF(AND(G29<>"",G29<>0),D29/G29,"") -> 18258.5 | I29: 36 | J29: =IF(AND(G29<>"",G29<>0),E29/G29,"") -> 1.75 | K29: 18990 | M29: 8082 | P29: 19680 | R29: =IF(AND(I29<>"",I29<>0),G29/I29,"") -> 0.11111111 | S29: =D29/T29 -> 1.388301 | T29: =$I$8*Z29*AA29/SUMPRODUCT($AA$25:$AA$57,$Z$25:$Z$57) -> 52606.749 | U29: =$I$9*Z29*AA29/SUMPRODUCT($AA$25:$AA$57,$Z$25:$Z$57) -> 6.4232904 | V29: =IF($I$12="","",U29/$I$12) -> 3.8233872 | W29: =IF(AA29<>"",IF(D29<>"",D29,($I$8-SUM($W$25:W28))*Z29*AA29/SUMPRODUCT($AA29:$AA$57,$Z29:$Z$57)),"") -> 73034 | X29: =IF(AA29<>"",IF(E29<>"",E29,($I$9-SUM($X$25:X28))*Z29*AA29/SUMPRODUCT($AA29:$AA$57,$Z29:$Z$57)),"") -> 7 | Y29: =IF(AA29<>"",IF($I$12<>"",IF(G29<>"",G29,($I$9/$I$12-SUM($Y$25:Y28))*Z29*AA29/SUMPRODUCT($AA29:$AA$57,$Z29:$Z$57)),""),"") -> 4 | Z29: 1 | AA29: 1
A30: 6 | B30: 46000 | C30: вт | D30: 33446 | E30: 2 | F30: =IF(AND(E30<>"",E30<>0),D30/E30,"") -> 16723 | G30: 1 | H30: =IF(AND(G30<>"",G30<>0),D30/G30,"") -> 33446 | I30: 22 | J30: =IF(AND(G30<>"",G30<>0),E30/G30,"") -> 2 | O30: 33446 | R30: =IF(AND(I30<>"",I30<>0),G30/I30,"") -> 0.045454545 | S30: =D30/T30 -> 0.63577394 | T30: =$I$8*Z30*AA30/SUMPRODUCT($AA$25:$AA$57,$Z$25:$Z$57) -> 52606.749 | U30: =$I$9*Z30*AA30/SUMPRODUCT($AA$25:$AA$57,$Z$25:$Z$57) -> 6.4232904 | V30: =IF($I$12="","",U30/$I$12) -> 3.8233872 | W30: =IF(AA30<>"",IF(D30<>"",D30,($I$8-SUM($W$25:W29))*Z30*AA30/SUMPRODUCT($AA30:$AA$57,$Z30:$Z$57)),"") -> 33446 | X30: =IF(AA30<>"",IF(E30<>"",E30,($I$9-SUM($X$25:X29))*Z30*AA30/SUMPRODUCT($AA30:$AA$57,$Z30:$Z$57)),"") -> 2 | Y30: =IF(AA30<>"",IF($I$12<>"",IF(G30<>"",G30,($I$9/$I$12-SUM($Y$25:Y29))*Z30*AA30/SUMPRODUCT($AA30:$AA$57,$Z30:$Z$57)),""),"") -> 1 | Z30: 1 | AA30: 1
A31: 7 | B31: 46001 | C31: ср | D31: 25432 | E31: 4 | F31: =IF(AND(E31<>"",E31<>0),D31/E31,"") -> 6358 | G31: 3 | H31: =IF(AND(G31<>"",G31<>0),D31/G31,"") -> 8477.3333 | I31: 27 | J31: =IF(AND(G31<>"",G31<>0),E31/G31,"") -> 1.3333333 | P31: 15084 | R31: =IF(AND(I31<>"",I31<>0),G31/I31,"") -> 0.11111111 | S31: =D31/T31 -> 0.48343607 | T31: =$I$8*Z31*AA31/SUMPRODUCT($AA$25:$AA$57,$Z$25:$Z$57) -> 52606.749 | U31: =$I$9*Z31*AA31/SUMPRODUCT($AA$25:$AA$57,$Z$25:$Z$57) -> 6.4232904 | V31: =IF($I$12="","",U31/$I$12) -> 3.8233872 | W31: =IF(AA31<>"",IF(D31<>"",D31,($I$8-SUM($W$25:W30))*Z31*AA31/SUMPRODUCT($AA31:$AA$57,$Z31:$Z$57)),"") -> 25432 | X31: =IF(AA31<>"",IF(E31<>"",E31,($I$9-SUM($X$25:X30))*Z31*AA31/SUMPRODUCT($AA31:$AA$57,$Z31:$Z$57)),"") -> 4 | Y31: =IF(AA31<>"",IF($I$12<>"",IF(G31<>"",G31,($I$9/$I$12-SUM($Y$25:Y30))*Z31*AA31/SUMPRODUCT($AA31:$AA$57,$Z31:$Z$57)),""),"") -> 3 | Z31: 1 | AA31: 1
A32: 8 | B32: 46002 | C32: чт | D32: 0 | E32: 0 | F32: =IF(AND(E32<>"",E32<>0),D32/E32,"") | G32: 0 | H32: =IF(AND(G32<>"",G32<>0),D32/G32,"") | I32: 28 | J32: =IF(AND(G32<>"",G32<>0),E32/G32,"") | R32: =IF(AND(I32<>"",I32<>0),G32/I32,"") -> 0 | S32: =D32/T32 -> 0 | T32: =$I$8*Z32*AA32/SUMPRODUCT($AA$25:$AA$57,$Z$25:$Z$57) -> 52606.749 | U32: =$I$9*Z32*AA32/SUMPRODUCT($AA$25:$AA$57,$Z$25:$Z$57) -> 6.4232904 | V32: =IF($I$12="","",U32/$I$12) -> 3.8233872 | W32: =IF(AA32<>"",IF(D32<>"",D32,($I$8-SUM($W$25:W31))*Z32*AA32/SUMPRODUCT($AA32:$AA$57,$Z32:$Z$57)),"") -> 0 | X32: =IF(AA32<>"",IF(E32<>"",E32,($I$9-SUM($X$25:X31))*Z32*AA32/SUMPRODUCT($AA32:$AA$57,$Z32:$Z$57)),"") -> 0 | Y32: =IF(AA32<>"",IF($I$12<>"",IF(G32<>"",G32,($I$9/$I$12-SUM($Y$25:Y31))*Z32*AA32/SUMPRODUCT($AA32:$AA$57,$Z32:$Z$57)),""),"") -> 0 | Z32: 1 | AA32: 1
A33: 9 | B33: 46003 | C33: пт | D33: 14496 | E33: 2 | F33: =IF(AND(E33<>"",E33<>0),D33/E33,"") -> 7248 | G33: 2 | H33: =IF(AND(G33<>"",G33<>0),D33/G33,"") -> 7248 | I33: 32 | J33: =IF(AND(G33<>"",G33<>0),E33/G33,"") -> 1 | R33: =IF(AND(I33<>"",I33<>0),G33/I33,"") -> 0.0625 | S33: =D33/T33 -> 0.275554 | T33: =$I$8*Z33*AA33/SUMPRODUCT($AA$25:$AA$57,$Z$25:$Z$57) -> 52606.749 | U33: =$I$9*Z33*AA33/SUMPRODUCT($AA$25:$AA$57,$Z$25:$Z$57) -> 6.4232904 | V33: =IF($I$12="","",U33/$I$12) -> 3.8233872 | W33: =IF(AA33<>"",IF(D33<>"",D33,($I$8-SUM($W$25:W32))*Z33*AA33/SUMPRODUCT($AA33:$AA$57,$Z33:$Z$57)),"") -> 14496 | X33: =IF(AA33<>"",IF(E33<>"",E33,($I$9-SUM($X$25:X32))*Z33*AA33/SUMPRODUCT($AA33:$AA$57,$Z33:$Z$57)),"") -> 2 | Y33: =IF(AA33<>"",IF($I$12<>"",IF(G33<>"",G33,($I$9/$I$12-SUM($Y$25:Y32))*Z33*AA33/SUMPRODUCT($AA33:$AA$57,$Z33:$Z$57)),""),"") -> 2 | Z33: 1 | AA33: 1
A34: 10 | B34: 46004 | C34: сб | D34: 39474 | E34: 8 | F34: =IF(AND(E34<>"",E34<>0),D34/E34,"") -> 4934.25 | G34: 4 | H34: =IF(AND(G34<>"",G34<>0),D34/G34,"") -> 9868.5 | I34: 45 | J34: =IF(AND(G34<>"",G34<>0),E34/G34,"") -> 2 | R34: =IF(AND(I34<>"",I34<>0),G34/I34,"") -> 0.088888889 | S34: =D34/T34 -> 0.75036 | T34: =$I$8*Z34*AA34/SUMPRODUCT($AA$25:$AA$57,$Z$25:$Z$57) -> 52606.749 | U34: =$I$9*Z34*AA34/SUMPRODUCT($AA$25:$AA$57,$Z$25:$Z$57) -> 6.4232904 | V34: =IF($I$12="","",U34/$I$12) -> 3.8233872 | W34: =IF(AA34<>"",IF(D34<>"",D34,($I$8-SUM($W$25:W33))*Z34*AA34/SUMPRODUCT($AA34:$AA$57,$Z34:$Z$57)),"") -> 39474 | X34: =IF(AA34<>"",IF(E34<>"",E34,($I$9-SUM($X$25:X33))*Z34*AA34/SUMPRODUCT($AA34:$AA$57,$Z34:$Z$57)),"") -> 8 | Y34: =IF(AA34<>"",IF($I$12<>"",IF(G34<>"",G34,($I$9/$I$12-SUM($Y$25:Y33))*Z34*AA34/SUMPRODUCT($AA34:$AA$57,$Z34:$Z$57)),""),"") -> 4 | Z34: 1 | AA34: 1
A35: 11 | B35: 46007 | C35: вт | D35: 24071 | E35: 4 | F35: =IF(AND(E35<>"",E35<>0),D35/E35,"") -> 6017.75 | G35: 3 | H35: =IF(AND(G35<>"",G35<>0),D35/G35,"") -> 8023.6667 | I35: 26 | J35: =IF(AND(G35<>"",G35<>0),E35/G35,"") -> 1.3333333 | R35: =IF(AND(I35<>"",I35<>0),G35/I35,"") -> 0.11538462 | S35: =D35/T35 -> 0.45756487 | T35: =$I$8*Z35*AA35/SUMPRODUCT($AA$25:$AA$57,$Z$25:$Z$57) -> 52606.749 | U35: =$I$9*Z35*AA35/SUMPRODUCT($AA$25:$AA$57,$Z$25:$Z$57) -> 6.4232904 | V35: =IF($I$12="","",U35/$I$12) -> 3.8233872 | W35: =IF(AA35<>"",IF(D35<>"",D35,($I$8-SUM($W$25:W34))*Z35*AA35/SUMPRODUCT($AA35:$AA$57,$Z35:$Z$57)),"") -> 24071 | X35: =IF(AA35<>"",IF(E35<>"",E35,($I$9-SUM($X$25:X34))*Z35*AA35/SUMPRODUCT($AA35:$AA$57,$Z35:$Z$57)),"") -> 4 | Y35: =IF(AA35<>"",IF($I$12<>"",IF(G35<>"",G35,($I$9/$I$12-SUM($Y$25:Y34))*Z35*AA35/SUMPRODUCT($AA35:$AA$57,$Z35:$Z$57)),""),"") -> 3 | Z35: 1 | AA35: 1
A36: 12 | B36: 46008 | C36: ср | D36: 5893 | E36: 1 | F36: =IF(AND(E36<>"",E36<>0),D36/E36,"") -> 5893 | G36: 1 | H36: =IF(AND(G36<>"",G36<>0),D36/G36,"") -> 5893 | I36: 40 | J36: =IF(AND(G36<>"",G36<>0),E36/G36,"") -> 1 | R36: =IF(AND(I36<>"",I36<>0),G36/I36,"") -> 0.025 | S36: =D36/T36 -> 0.11201985 | T36: =$I$8*Z36*AA36/SUMPRODUCT($AA$25:$AA$57,$Z$25:$Z$57) -> 52606.749 | U36: =$I$9*Z36*AA36/SUMPRODUCT($AA$25:$AA$57,$Z$25:$Z$57) -> 6.4232904 | V36: =IF($I$12="","",U36/$I$12) -> 3.8233872 | W36: =IF(AA36<>"",IF(D36<>"",D36,($I$8-SUM($W$25:W35))*Z36*AA36/SUMPRODUCT($AA36:$AA$57,$Z36:$Z$57)),"") -> 5893 | X36: =IF(AA36<>"",IF(E36<>"",E36,($I$9-SUM($X$25:X35))*Z36*AA36/SUMPRODUCT($AA36:$AA$57,$Z36:$Z$57)),"") -> 1 | Y36: =IF(AA36<>"",IF($I$12<>"",IF(G36<>"",G36,($I$9/$I$12-SUM($Y$25:Y35))*Z36*AA36/SUMPRODUCT($AA36:$AA$57,$Z36:$Z$57)),""),"") -> 1 | Z36: 1 | AA36: 1
A37: 13 | B37: 46009 | C37: чт | D37: 23665 | E37: 2 | F37: =IF(AND(E37<>"",E37<>0),D37/E37,"") -> 11832.5 | G37: 2 | H37: =IF(AND(G37<>"",G37<>0),D37/G37,"") -> 11832.5 | I37: 30 | J37: =IF(AND(G37<>"",G37<>0),E37/G37,"") -> 1 | O37: 15066 | R37: =IF(AND(I37<>"",I37<>0),G37/I37,"") -> 0.066666667 | S37: =D37/T37 -> 0.44984723 | T37: =$I$8*Z37*AA37/SUMPRODUCT($AA$25:$AA$57,$Z$25:$Z$57) -> 52606.749 | U37: =$I$9*Z37*AA37/SUMPRODUCT($AA$25:$AA$57,$Z$25:$Z$57) -> 6.4232904 | V37: =IF($I$12="","",U37/$I$12) -> 3.8233872 | W37: =IF(AA37<>"",IF(D37<>"",D37,($I$8-SUM($W$25:W36))*Z37*AA37/SUMPRODUCT($AA37:$AA$57,$Z37:$Z$57)),"") -> 23665 | X37: =IF(AA37<>"",IF(E37<>"",E37,($I$9-SUM($X$25:X36))*Z37*AA37/SUMPRODUCT($AA37:$AA$57,$Z37:$Z$57)),"") -> 2 | Y37: =IF(AA37<>"",IF($I$12<>"",IF(G37<>"",G37,($I$9/$I$12-SUM($Y$25:Y36))*Z37*AA37/SUMPRODUCT($AA37:$AA$57,$Z37:$Z$57)),""),"") -> 2 | Z37: 1 | AA37: 1
A38: 14 | B38: 46010 | C38: пт | D38: 89483 | E38: 10 | F38: =IF(AND(E38<>"",E38<>0),D38/E38,"") -> 8948.3 | G38: 5 | H38: =IF(AND(G38<>"",G38<>0),D38/G38,"") -> 17896.6 | I38: 20 | J38: =IF(AND(G38<>"",G38<>0),E38/G38,"") -> 2 | M38: 25272 | N38: 5690 | O38: 22172 | R38: =IF(AND(I38<>"",I38<>0),G38/I38,"") -> 0.25 | S38: =D38/T38 -> 1.5468657 | T38: =$I$8*Z38*AA38/SUMPRODUCT($AA$25:$AA$47,$Z$25:$Z$47) -> 57847.942 | U38: =$I$9*Z38*AA38/SUMPRODUCT($AA$25:$AA$47,$Z$25:$Z$47) -> 7.0632408 | V38: =IF($I$12="","",U38/$I$12) -> 4.20431 | W38: =IF(AA38<>"",IF(D38<>"",D38,($I$8-SUM($W$25:W37))*Z38*AA38/SUMPRODUCT($AA38:$AA$57,$Z38:$Z$57)),"") -> 89483 | X38: =IF(AA38<>"",IF(E38<>"",E38,($I$9-SUM($X$25:X37))*Z38*AA38/SUMPRODUCT($AA38:$AA$57,$Z38:$Z$57)),"") -> 10 | Y38: =IF(AA38<>"",IF($I$12<>"",IF(G38<>"",G38,($I$9/$I$12-SUM($Y$25:Y37))*Z38*AA38/SUMPRODUCT($AA38:$AA$57,$Z38:$Z$57)),""),"") -> 5 | Z38: 1 | AA38: 1
A39: 15 | B39: 46011 | C39: сб | D39: =23979+6744+11298+8036+7983+5494 -> 63534 | E39: =2+1+1+2+1+1 -> 8 | F39: =IF(AND(E39<>"",E39<>0),D39/E39,"") -> 7941.75 | G39: 6 | H39: =IF(AND(G39<>"",G39<>0),D39/G39,"") -> 10589 | I39: 60 | J39: =IF(AND(G39<>"",G39<>0),E39/G39,"") -> 1.3333333 | K39: 7983 | O39: =14313+11298 -> 25611 | P39: 6744 | R39: =IF(AND(I39<>"",I39<>0),G39/I39,"") -> 0.1 | S39: =D39/T39 -> 1.0982932 | T39: =$I$8*Z39*AA39/SUMPRODUCT($AA$25:$AA$47,$Z$25:$Z$47) -> 57847.942 | U39: =$I$9*Z39*AA39/SUMPRODUCT($AA$25:$AA$47,$Z$25:$Z$47) -> 7.0632408 | V39: =IF($I$12="","",U39/$I$12) -> 4.20431 | W39: =IF(AA39<>"",IF(D39<>"",D39,($I$8-SUM($W$25:W38))*Z39*AA39/SUMPRODUCT($AA39:$AA$57,$Z39:$Z$57)),"") -> 63534 | X39: =IF(AA39<>"",IF(E39<>"",E39,($I$9-SUM($X$25:X38))*Z39*AA39/SUMPRODUCT($AA39:$AA$57,$Z39:$Z$57)),"") -> 8 | Y39: =IF(AA39<>"",IF($I$12<>"",IF(G39<>"",G39,($I$9/$I$12-SUM($Y$25:Y38))*Z39*AA39/SUMPRODUCT($AA39:$AA$57,$Z39:$Z$57)),""),"") -> 6 | Z39: 1 | AA39: 1
A40: 16 | B40: 46012 | C40: вс | D40: 22675 | E40: 3 | F40: =IF(AND(E40<>"",E40<>0),D40/E40,"") -> 7558.3333 | G40: 1 | H40: =IF(AND(G40<>"",G40<>0),D40/G40,"") -> 22675 | I40: 29 | J40: =IF(AND(G40<>"",G40<>0),E40/G40,"") -> 3 | R40: =IF(AND(I40<>"",I40<>0),G40/I40,"") -> 0.034482759 | S40: =D40/T40 -> 0.39197591 | T40: =$I$8*Z40*AA40/SUMPRODUCT($AA$25:$AA$47,$Z$25:$Z$47) -> 57847.942 | U40: =$I$9*Z40*AA40/SUMPRODUCT($AA$25:$AA$47,$Z$25:$Z$47) -> 7.0632408 | V40: =IF($I$12="","",U40/$I$12) -> 4.20431 | W40: =IF(AA40<>"",IF(D40<>"",D40,($I$8-SUM($W$25:W39))*Z40*AA40/SUMPRODUCT($AA40:$AA$57,$Z40:$Z$57)),"") -> 22675 | X40: =IF(AA40<>"",IF(E40<>"",E40,($I$9-SUM($X$25:X39))*Z40*AA40/SUMPRODUCT($AA40:$AA$57,$Z40:$Z$57)),"") -> 3 | Y40: =IF(AA40<>"",IF($I$12<>"",IF(G40<>"",G40,($I$9/$I$12-SUM($Y$25:Y39))*Z40*AA40/SUMPRODUCT($AA40:$AA$57,$Z40:$Z$57)),""),"") -> 1 | Z40: 1 | AA40: 1
A41: 17 | B41: 46014 | C41: вт | D41: =5824+7282 -> 13106 | E41: 2 | F41: =IF(AND(E41<>"",E41<>0),D41/E41,"") -> 6553 | G41: 2 | H41: =IF(AND(G41<>"",G41<>0),D41/G41,"") -> 6553 | I41: 27 | J41: =IF(AND(G41<>"",G41<>0),E41/G41,"") -> 1 | R41: =IF(AND(I41<>"",I41<>0),G41/I41,"") -> 0.074074074 | S41: =D41/T41 -> 0.24913153 | T41: =$I$8*Z41*AA41/SUMPRODUCT($AA$25:$AA$55,$Z$25:$Z$55) -> 52606.749 | U41: =$I$9*Z41*AA41/SUMPRODUCT($AA$25:$AA$55,$Z$25:$Z$55) -> 6.4232904 | V41: =IF($I$12="","",U41/$I$12) -> 3.8233872 | W41: =IF(AA41<>"",IF(D41<>"",D41,($I$8-SUM($W$25:W40))*Z41*AA41/SUMPRODUCT($AA41:$AA$55,$Z41:$Z$55)),"") -> 13106 | X41: =IF(AA41<>"",IF(E41<>"",E41,($I$9-SUM($X$25:X40))*Z41*AA41/SUMPRODUCT($AA41:$AA$55,$Z41:$Z$55)),"") -> 2 | Y41: =IF(AA41<>"",IF($I$12<>"",IF(G41<>"",G41,($I$9/$I$12-SUM($Y$25:Y40))*Z41*AA41/SUMPRODUCT($AA41:$AA$55,$Z41:$Z$55)),""),"") -> 2 | Z41: 1 | AA41: 1
A42: 18 | B42: 46015 | C42: ср | D42: =42185 -> 42185 | E42: =2 -> 2 | F42: =IF(AND(E42<>"",E42<>0),D42/E42,"") -> 21092.5 | G42: 1 | H42: =IF(AND(G42<>"",G42<>0),D42/G42,"") -> 42185 | I42: 20 | J42: =IF(AND(G42<>"",G42<>0),E42/G42,"") -> 2 | K42: 25495 | O42: 16690 | R42: =IF(AND(I42<>"",I42<>0),G42/I42,"") -> 0.05 | S42: =D42/T42 -> 0.80189331 | T42: =$I$8*Z42*AA42/SUMPRODUCT($AA$25:$AA$55,$Z$25:$Z$55) -> 52606.749 | U42: =$I$9*Z42*AA42/SUMPRODUCT($AA$25:$AA$55,$Z$25:$Z$55) -> 6.4232904 | V42: =IF($I$12="","",U42/$I$12) -> 3.8233872 | W42: =IF(AA42<>"",IF(D42<>"",D42,($I$8-SUM($W$25:W41))*Z42*AA42/SUMPRODUCT($AA42:$AA$55,$Z42:$Z$55)),"") -> 42185 | X42: =IF(AA42<>"",IF(E42<>"",E42,($I$9-SUM($X$25:X41))*Z42*AA42/SUMPRODUCT($AA42:$AA$55,$Z42:$Z$55)),"") -> 2 | Y42: =IF(AA42<>"",IF($I$12<>"",IF(G42<>"",G42,($I$9/$I$12-SUM($Y$25:Y41))*Z42*AA42/SUMPRODUCT($AA42:$AA$55,$Z42:$Z$55)),""),"") -> 1 | Z42: 1 | AA42: 1
A43: 19 | B43: 46016 | C43: чт | D43: =890+16484 -> 17374 | E43: 2 | F43: =IF(AND(E43<>"",E43<>0),D43/E43,"") -> 8687 | G43: 2 | H43: =IF(AND(G43<>"",G43<>0),D43/G43,"") -> 8687 | I43: 25 | J43: =IF(AND(G43<>"",G43<>0),E43/G43,"") -> 1 | Q43: 9602 | R43: =IF(AND(I43<>"",I43<>0),G43/I43,"") -> 0.08 | S43: =D43/T43 -> 0.33026181 | T43: =$I$8*Z43*AA43/SUMPRODUCT($AA$25:$AA$55,$Z$25:$Z$55) -> 52606.749 | U43: =$I$9*Z43*AA43/SUMPRODUCT($AA$25:$AA$55,$Z$25:$Z$55) -> 6.4232904 | V43: =IF($I$12="","",U43/$I$12) -> 3.8233872 | W43: =IF(AA43<>"",IF(D43<>"",D43,($I$8-SUM($W$25:W42))*Z43*AA43/SUMPRODUCT($AA43:$AA$55,$Z43:$Z$55)),"") -> 17374 | X43: =IF(AA43<>"",IF(E43<>"",E43,($I$9-SUM($X$25:X42))*Z43*AA43/SUMPRODUCT($AA43:$AA$55,$Z43:$Z$55)),"") -> 2 | Y43: =IF(AA43<>"",IF($I$12<>"",IF(G43<>"",G43,($I$9/$I$12-SUM($Y$25:Y42))*Z43*AA43/SUMPRODUCT($AA43:$AA$55,$Z43:$Z$55)),""),"") -> 2 | Z43: 1 | AA43: 1
A44: 20 | B44: 46017 | C44: пт | D44: 9602 | E44: 1 | F44: =IF(AND(E44<>"",E44<>0),D44/E44,"") -> 9602 | G44: 1 | H44: =IF(AND(G44<>"",G44<>0),D44/G44,"") -> 9602 | I44: 25 | J44: =IF(AND(G44<>"",G44<>0),E44/G44,"") -> 1 | R44: =IF(AND(I44<>"",I44<>0),G44/I44,"") -> 0.04 | S44: =D44/T44 -> 0.12675285 | T44: =$I$8*Z44*AA44/SUMPRODUCT($AA$25:$AA$55,$Z$25:$Z$55) -> 75753.718 | U44: =$I$9*Z44*AA44/SUMPRODUCT($AA$25:$AA$55,$Z$25:$Z$55) -> 9.2495382 | V44: =IF($I$12="","",U44/$I$12) -> 5.5056775 | W44: =IF(AA44<>"",IF(D44<>"",D44,($I$8-SUM($W$25:W43))*Z44*AA44/SUMPRODUCT($AA44:$AA$55,$Z44:$Z$55)),"") -> 9602 | X44: =IF(AA44<>"",IF(E44<>"",E44,($I$9-SUM($X$25:X43))*Z44*AA44/SUMPRODUCT($AA44:$AA$55,$Z44:$Z$55)),"") -> 1 | Y44: =IF(AA44<>"",IF($I$12<>"",IF(G44<>"",G44,($I$9/$I$12-SUM($Y$25:Y43))*Z44*AA44/SUMPRODUCT($AA44:$AA$55,$Z44:$Z$55)),""),"") -> 1 | Z44: 1.2 | AA44: 1.2
A45: 21 | B45: 46018 | C45: сб | D45: =8082+6893+7864+5001+5001+13547+890+10000 -> 57278 | E45: 5 | F45: =IF(AND(E45<>"",E45<>0),D45/E45,"") -> 11455.6 | G45: 8 | H45: =IF(AND(G45<>"",G45<>0),D45/G45,"") -> 7159.75 | I45: 28 | J45: =IF(AND(G45<>"",G45<>0),E45/G45,"") -> 0.625 | M45: 8082 | R45: =IF(AND(I45<>"",I45<>0),G45/I45,"") -> 0.28571429 | S45: =D45/T45 -> 0.7561081 | T45: =$I$8*Z45*AA45/SUMPRODUCT($AA$25:$AA$55,$Z$25:$Z$55) -> 75753.718 | U45: =$I$9*Z45*AA45/SUMPRODUCT($AA$25:$AA$55,$Z$25:$Z$55) -> 9.2495382 | V45: =IF($I$12="","",U45/$I$12) -> 5.5056775 | W45: =IF(AA45<>"",IF(D45<>"",D45,($I$8-SUM($W$25:W44))*Z45*AA45/SUMPRODUCT($AA45:$AA$55,$Z45:$Z$55)),"") -> 57278 | X45: =IF(AA45<>"",IF(E45<>"",E45,($I$9-SUM($X$25:X44))*Z45*AA45/SUMPRODUCT($AA45:$AA$55,$Z45:$Z$55)),"") -> 5 | Y45: =IF(AA45<>"",IF($I$12<>"",IF(G45<>"",G45,($I$9/$I$12-SUM($Y$25:Y44))*Z45*AA45/SUMPRODUCT($AA45:$AA$55,$Z45:$Z$55)),""),"") -> 8 | Z45: 1.2 | AA45: 1.2
A46: 22 | B46: 46019 | C46: вс | D46: =20490+5001+11216+13984 -> 50691 | E46: 7 | F46: =IF(AND(E46<>"",E46<>0),D46/E46,"") -> 7241.5714 | G46: 3 | H46: =IF(AND(G46<>"",G46<>0),D46/G46,"") -> 16897 | J46: =IF(AND(G46<>"",G46<>0),E46/G46,"") -> 2.3333333 | K46: 14093 | R46: =IF(AND(I46<>"",I46<>0),G46/I46,"") | S46: =D46/T46 -> 0.66915527 | T46: =$I$8*Z46*AA46/SUMPRODUCT($AA$25:$AA$55,$Z$25:$Z$55) -> 75753.718 | U46: =$I$9*Z46*AA46/SUMPRODUCT($AA$25:$AA$55,$Z$25:$Z$55) -> 9.2495382 | V46: =IF($I$12="","",U46/$I$12) -> 5.5056775 | W46: =IF(AA46<>"",IF(D46<>"",D46,($I$8-SUM($W$25:W45))*Z46*AA46/SUMPRODUCT($AA46:$AA$55,$Z46:$Z$55)),"") -> 50691 | X46: =IF(AA46<>"",IF(E46<>"",E46,($I$9-SUM($X$25:X45))*Z46*AA46/SUMPRODUCT($AA46:$AA$55,$Z46:$Z$55)),"") -> 7 | Y46: =IF(AA46<>"",IF($I$12<>"",IF(G46<>"",G46,($I$9/$I$12-SUM($Y$25:Y45))*Z46*AA46/SUMPRODUCT($AA46:$AA$55,$Z46:$Z$55)),""),"") -> 3 | Z46: 1.2 | AA46: 1.2
A47: 23 | B47: 46020 | C47: пн | D47: =8882+41532+6203 -> 56617 | E47: 9 | F47: =IF(AND(E47<>"",E47<>0),D47/E47,"") -> 6290.7778 | G47: 3 | H47: =IF(AND(G47<>"",G47<>0),D47/G47,"") -> 18872.333 | J47: =IF(AND(G47<>"",G47<>0),E47/G47,"") -> 3 | L47: 6203 | M47: 7990 | R47: =IF(AND(I47<>"",I47<>0),G47/I47,"") | S47: =D47/T47 -> 0.74738246 | T47: =$I$8*Z47*AA47/SUMPRODUCT($AA$25:$AA$55,$Z$25:$Z$55) -> 75753.718 | U47: =$I$9*Z47*AA47/SUMPRODUCT($AA$25:$AA$55,$Z$25:$Z$55) -> 9.2495382 | V47: =IF($I$12="","",U47/$I$12) -> 5.5056775 | W47: =IF(AA47<>"",IF(D47<>"",D47,($I$8-SUM($W$25:W46))*Z47*AA47/SUMPRODUCT($AA47:$AA$55,$Z47:$Z$55)),"") -> 56617 | X47: =IF(AA47<>"",IF(E47<>"",E47,($I$9-SUM($X$25:X46))*Z47*AA47/SUMPRODUCT($AA47:$AA$55,$Z47:$Z$55)),"") -> 9 | Y47: =IF(AA47<>"",IF($I$12<>"",IF(G47<>"",G47,($I$9/$I$12-SUM($Y$25:Y46))*Z47*AA47/SUMPRODUCT($AA47:$AA$55,$Z47:$Z$55)),""),"") -> 3 | Z47: 1.2 | AA47: 1.2
A48: 24 | B48: 46021 | C48: вт | D48: =5001+48897+30916+10684+11584+2097+11283+10482 -> 130944 | E48: 12 | F48: =IF(AND(E48<>"",E48<>0),D48/E48,"") -> 10912 | G48: 8 | H48: =IF(AND(G48<>"",G48<>0),D48/G48,"") -> 16368 | J48: =IF(AND(G48<>"",G48<>0),E48/G48,"") -> 1.5 | K48: =30916+48897+10482 -> 90295 | R48: =IF(AND(I48<>"",I48<>0),G48/I48,"") | S48: =D48/T48 -> 1.7285488 | T48: =$I$8*Z48*AA48/SUMPRODUCT($AA$25:$AA$55,$Z$25:$Z$55) -> 75753.718 | U48: =$I$9*Z48*AA48/SUMPRODUCT($AA$25:$AA$55,$Z$25:$Z$55) -> 9.2495382 | V48: =IF($I$12="","",U48/$I$12) -> 5.5056775 | W48: =IF(AA48<>"",IF(D48<>"",D48,($I$8-SUM($W$25:W47))*Z48*AA48/SUMPRODUCT($AA48:$AA$55,$Z48:$Z$55)),"") -> 130944 | X48: =IF(AA48<>"",IF(E48<>"",E48,($I$9-SUM($X$25:X47))*Z48*AA48/SUMPRODUCT($AA48:$AA$55,$Z48:$Z$55)),"") -> 12 | Y48: =IF(AA48<>"",IF($I$12<>"",IF(G48<>"",G48,($I$9/$I$12-SUM($Y$25:Y47))*Z48*AA48/SUMPRODUCT($AA48:$AA$55,$Z48:$Z$55)),""),"") -> 8 | Z48: 1.2 | AA48: 1.2
A49: 25 | B49: 46022 | C49: ср | D49: =5693+11784 -> 17477 | E49: 3 | F49: =IF(AND(E49<>"",E49<>0),D49/E49,"") -> 5825.6667 | G49: 2 | H49: =IF(AND(G49<>"",G49<>0),D49/G49,"") -> 8738.5 | J49: =IF(AND(G49<>"",G49<>0),E49/G49,"") -> 1.5 | R49: =IF(AND(I49<>"",I49<>0),G49/I49,"") | S49: =D49/T49 -> 0.33221973 | T49: =$I$8*Z49*AA49/SUMPRODUCT($AA$25:$AA$55,$Z$25:$Z$55) -> 52606.749 | U49: =$I$9*Z49*AA49/SUMPRODUCT($AA$25:$AA$55,$Z$25:$Z$55) -> 6.4232904 | V49: =IF($I$12="","",U49/$I$12) -> 3.8233872 | W49: =IF(AA49<>"",IF(D49<>"",D49,($I$8-SUM($W$25:W48))*Z49*AA49/SUMPRODUCT($AA49:$AA$55,$Z49:$Z$55)),"") -> 17477 | X49: =IF(AA49<>"",IF(E49<>"",E49,($I$9-SUM($X$25:X48))*Z49*AA49/SUMPRODUCT($AA49:$AA$55,$Z49:$Z$55)),"") -> 3 | Y49: =IF(AA49<>"",IF($I$12<>"",IF(G49<>"",G49,($I$9/$I$12-SUM($Y$25:Y48))*Z49*AA49/SUMPRODUCT($AA49:$AA$55,$Z49:$Z$55)),""),"") -> 2 | Z49: 1 | AA49: 1
B50: итого | D50: =SUM(D25:D49) -> 875652 | E50: =SUM(E25:E49) -> 99 | F50: =IF(AND(E50<>"",E50<>0),D50/E50,"") -> 8844.9697 | G50: =SUM(G25:G49) -> 68 | H50: =IF(AND(G50<>"",G50<>0),D50/G50,"") -> 12877.235 | I50: =SUM(I25:I49) -> 627 | J50: =IF(AND(G50<>"",G50<>0),E50/G50,"") -> 1.4558824 | K50: =SUM(K25:K49) -> 156856 | L50: =SUM(L25:L49) -> 6203 | M50: =SUM(M25:M49) -> 56919 | N50: =SUM(N25:N49) -> 5690 | O50: =SUM(O25:O49) -> 112985 | P50: =SUM(P25:P49) -> 41508 | Q50: =SUM(Q25:Q49) -> 9602 | R50: =IF(AND(I50<>"",I50<>0),G50/I50,"") -> 0.10845295 | S50: =D50/T50 -> 0.62541458 | T50: =SUM(T25:T49) -> 1400114.5 | U50: =SUM(U25:U49) -> 173.2279 | V50: =SUM(V25:V49) -> 102.73089 | W50: =SUM(W25:W49) -> 843667 | X50: =SUM(X25:X49) -> 100 | Y50: =SUM(Y25:Y49) -> 68
D51: =SUMIF(D25:D49,"",T25:T49)+D50 -> 875652

Sheet Доп сотрудник
B1: =TODAY()-1 -> 46031
B2: (отчетная дата) | J2: ЕЖЕДНЕВНЫЙ ОТЧЕТ О ПРОДАЖАХ
B3: Осталось до выполнения плана!!! | J3: =График!B24 -> Рогалевич Ирина
C4: =I8-D48 -> 295581.42 | E4: =IF(I8<>0,C4/I8,0) -> 0.31161579
F6: Целевые показатели
F7: Показатель | I7: План | J7: Факт | K7: % выполнения | L7: Прогноз выполнения | M7: % выполнения по прогнозу | N7: Отклонение | O7: Факт аналогичного месяца прошлого года | P7: Отклонение LFL
F8: Выручка | I8: =Центрум!I8/График!AJ29*График!AJ24 -> 948544.42 | J8: =D48 -> 652963 | K8: =IF(AND(I8<>"",I8<>0,J8<>""),J8/I8,"") -> 0.68838421 | L8: =IF(SUMIF($D$25:$D$47,">=0",$T$25:$T$47)<>0,I8*D48/SUMIF($D$25:$D$47,">=0",$T$25:$T$47),0) -> 652963 | M8: =L8/I8 -> 0.68838421 | N8: =IF(AND(J8<>0,J8<>"",I8<>0,I8<>""),L8-I8,"") -> -295581.42 | P8: =IF(AND(O8<>"",O8<>0,L8<>"",L8<>0),-O8+L8,"") | Q8: =IF(AND(P8<>"",P8<>0,O8<>0,O8<>""),P8/O8,"")
F9: Кол-во изделий | I9: =I8/I11 -> 115.81739 | J9: =E48 -> 82 | K9: =IF(AND(I9<>"",I9<>0,J9<>""),J9/I9,"") -> 0.70801112 | L9: =IF(SUMIF($E$25:$E$47,">=0",$U$25:$U$47)<>0,I9*E48/SUMIF($E$25:$E$47,">=0",$U$25:$U$47),0) -> 82 | M9: =IF(AND(I9<>"",I9<>0,L9<>"",L9<>0),L9/I9,"") -> 0.70801112 | N9: =IF(AND(J9<>0,J9<>"",I9<>0,I9<>""),L9-I9,"") -> -33.817389 | O9: =O8/O11 -> #DIV/0! | P9: =IF(AND(O9<>"",O9<>0,L9<>"",L9<>0),-O9+L9,"") -> #DIV/0! | Q9: =IF(AND(P9<>"",P9<>0,O9<>0,O9<>""),P9/O9,"") -> #DIV/0!
F10: Средний чек | I10: =I11*I12 -> 13759.2 | J10: =H48 -> 14510.289 | K10: =IF(AND(I10<>"",I10<>0,J10<>""),J10/I10,"") -> 1.0545881 | L10: =J10 -> 14510.289 | M10: =IF(AND(I10<>"",I10<>0,L10<>"",L10<>0),L10/I10,"") -> 1.0545881 | N10: =IF(AND(J10<>0,J10<>"",I10<>0,I10<>""),L10-I10,"") -> 751.08889 | O10: =O11*O12 -> 0 | P10: =IF(AND(O10<>"",O10<>0,L10<>"",L10<>0),-O10+L10,"") | Q10: =IF(AND(P10<>"",P10<>0,O10<>0,O10<>""),P10/O10,"")
F11: Средняя стоимость изделия | I11: =Центрум!I11 -> 8190 | J11: =F48 -> 7962.9634 | K11: =IF(AND(I11<>"",I11<>0,J11<>""),J11/I11,"") -> 0.97227881 | L11: =IF(L9>0,L8/L9,"") -> 7962.9634 | M11: =IF(AND(I11<>"",I11<>0,L11<>"",L11<>0),L11/I11,"") -> 0.97227881 | N11: =IF(AND(J11<>0,J11<>"",I11<>0,I11<>""),L11-I11,"") -> -227.03659 | P11: =IF(AND(O11<>"",O11<>0,L11<>"",L11<>0),-O11+L11,"") | Q11: =IF(AND(P11<>"",P11<>0,O11<>0,O11<>""),P11/O11,"")
F12: Длина чека | I12: =Центрум!I12 -> 1.68 | J12: =J48 -> 1.8222222 | K12: =IF(AND(I12<>"",I12<>0,J12<>""),J12/I12,"") -> 1.0846561 | L12: =J12 -> 1.8222222 | M12: =IF(AND(I12<>"",I12<>0,L12<>"",L12<>0),L12/I12,"") -> 1.0846561 | N12: =IF(AND(J12<>0,J12<>"",I12<>0,I12<>""),L12-I12,"") -> 0.14222222 | P12: =IF(AND(O12<>"",O12<>0,L12<>"",L12<>0),-O12+L12,"") | Q12: =IF(AND(P12<>"",P12<>0,O12<>0,O12<>""),P12/O12,"")
F13: Кол-во чеков | I13: =IF(I12<>0,I9/I12,"") -> 68.938922 | J13: =G48 -> 45 | K13: =IF(AND(I13<>"",I13<>0,J13<>""),J13/I13,"") -> 0.65275172 | L13: =IF(SUMIF($G$25:$G$47,">=0",$V$25:$V$47)<>0,I13*G48/SUMIF($G$25:$G$47,">=0",$V$25:$V$47),"") -> 45 | M13: =IF(AND(I13<>"",I13<>0,L13<>"",L13<>0),L13/I13,"") -> 0.65275172 | N13: =IF(AND(J13<>0,J13<>"",I13<>0,I13<>""),L13-I13,"") -> -23.938922 | P13: =IF(AND(O13<>"",O13<>0,L13<>"",L13<>0),-O13+L13,"") | Q13: =IF(AND(P13<>"",P13<>0,O13<>0,O13<>""),P13/O13,"")
F14: Кол-во смен план/отработано | I14: =График!AI24 -> 16 | J14: 16 | K14: =IF(AND(I14<>"",I14<>0,J14<>""),J14/I14,"") -> 1 | L14: =IF(SUMIF($D$25:$D$47,">=0",$T$25:$T$47),I48*I8/SUMIF($D$25:$D$47,">=0",$T$25:$T$47),"") -> 482 | M14: =IF(AND(I14<>"",I14<>0,L14<>"",L14<>0),L14/I14,"") -> 30.125 | N14: =IF(AND(J14<>0,J14<>"",I14<>0,I14<>""),L14-I14,"") -> 466 | P14: =IF(AND(O14<>"",O14<>0,L14<>"",L14<>0),-O14+L14,"") | Q14: =IF(AND(P14<>"",P14<>0,O14<>0,O14<>""),P14/O14,"")
F15: Средние продажи в смену | I15: =Центрум!I15 -> 196534.64 | J15: =J8/J14 -> 40810.188 | K15: =IF(AND(I15<>"",I15<>0,J15<>""),J15/I15,"") -> 0.20764883 | L15: =J15 -> 40810.188 | M15: =IF(AND(I15<>"",I15<>0,L15<>"",L15<>0),L15/I15,"") -> 0.20764883 | N15: =IF(AND(J15<>0,J15<>"",I15<>0,I15<>""),L15-I15,"") -> -155724.45 | P15: =IF(AND(O15<>"",O15<>0,L15<>"",L15<>0),-O15+L15,"") | Q15: =IF(AND(P15<>"",P15<>0,O15<>0,O15<>""),P15/O15,"")
F16: Отставание/Перевыполнение | J16: =J8-I15*J14 -> -2491591.2 | K16: =IF(AND(I16<>"",I16<>0,J16<>""),J16/I16,"") | L16: =J16 -> -2491591.2 | M16: =IF(AND(I16<>"",I16<>0,L16<>"",L16<>0),L16/I16,"") | N16: =IF(AND(J16<>0,J16<>"",I16<>0,I16<>""),L16-I16,"") | P16: =IF(AND(O16<>"",O16<>0,L16<>"",L16<>0),-O16+L16,"") | Q16: =IF(AND(P16<>"",P16<>0,O16<>0,O16<>""),P16/O16,"") | S16: Подарочные сертификаты
F17: Трафик | I17: =Центрум!I17/График!AJ29*График!AJ24 -> 560.47904 | J17: =I48 -> 482 | K17: =IF(AND(I17<>"",I17<>0,J17<>""),J17/I17,"") -> 0.85997863 | L17: =J17/J14*I14 -> 482 | M17: =IF(AND(I17<>"",I17<>0,L17<>"",L17<>0),L17/I17,"") -> 0.85997863 | N17: =IF(AND(J17<>0,J17<>"",I17<>0,I17<>""),L17-I17,"") -> -78.479042 | P17: =IF(AND(O17<>"",O17<>0,L17<>"",L17<>0),-O17+L17,"") | Q17: =IF(AND(P17<>"",P17<>0,O17<>0,O17<>""),P17/O17,"")
K18: =IF(AND(I18<>"",I18<>0,J18<>""),J18/I18,"") | L18: =J18 -> 0 | M18: =IF(AND(I18<>"",I18<>0,L18<>"",L18<>0),L18/I18,"") | N18: =IF(AND(J18<>0,J18<>"",I18<>0,I18<>""),L18-I18,"") | O18: 0 | P18: =IF(AND(O18<>"",O18<>0,L18<>"",L18<>0),-O18+L18,"") | Q18: =IF(AND(P18<>"",P18<>0,O18<>0,O18<>""),P18/O18,"")
J19: =Q48 -> 8593 | K19: =IF(AND(I19<>"",I19<>0,J19<>""),J19/I19,"") | L19: =J19 -> 8593 | M19: =IF(AND(I19<>"",I19<>0,L19<>"",L19<>0),L19/I19,"") | N19: =IF(AND(J19<>0,J19<>"",I19<>0,I19<>""),L19-I19,"") | O19: 0 | P19: =IF(AND(O19<>"",O19<>0,L19<>"",L19<>0),-O19+L19,"") | Q19: =IF(AND(P19<>"",P19<>0,O19<>0,O19<>""),P19/O19,"") | S19: =S18/I16 -> #DIV/0!
F20: Конверсия план/факт | I20: =Центрум!I20 -> 0.123 | J20: =R48 -> 0.093360996 | K20: =J20/I20 -> 0.75903249 | L20: =IF(AND(K8<>0,I14<>0,I48<>0),(I48*R48+(I48/K8-I48)*I20)/(I48/K8),0) -> 0.10259698 | M20: =IF(AND(I20<>"",I20<>0,L20<>"",L20<>0),L20/I20,"") -> 0.83412177 | N20: =IF(AND(J20<>0,J20<>"",I20<>0,I20<>""),L20-I20,"") -> -0.020403022 | P20: =IF(AND(O20<>"",O20<>0,L20<>"",L20<>0),-O20+L20,"") | Q20: =IF(AND(P20<>"",P20<>0,O20<>0,O20<>""),P20/O20,"")
B22: Факт продаж за месяц | S22: % выполнения дневного плана | T22: Раcпределение плана по дням
B23: Дата | C23: День недели | D23: Выручка (руб) | E23: Кол-во единиц (шт.) | F23: Средняя стоимость изделия (руб.) | G23: Количество чеков (шт.) | H23: Средняя сумма чека (руб.) | I23: Трафик | J23: Длина чека (шт.) | K23: UNOde50 | L23: IS | M23: Agafi | N23: Kalliope | O23: Raganella | P23: Eva Rites | Q23: CC/MP | R23: Конверсия (%) | T23: выручка, план | U23: кол-во ед, план | V23: Кол-во чеков, план | W23: выручка, скорректир.план | X23: кол-во ед, скорр. план | Y23: кол-во чеков, скорр. план | Z23: Коэфф. Дня Недели | AA23: Специфика месяца
B24: 1 | C24: 2 | D24: 3 | E24: в | F24: 5 | G24: 6 | H24: 7 | I24: 8 | J24: 9 | K24: 10 | L24: 11 | M24: 12 | N24: 13 | O24: 14 | P24: 15 | Q24: 16 | R24: 17 | T24: 1 | U24: 2 | V24: 3 | W24: 4 | X24: 5 | Y24: 6 | Z24: 10 | AA24: 11
A25: 1 | B25: 45992 | C25: пн | D25: 0 | E25: 0 | F25: =IF(AND(E25<>"",E25<>0),D25/E25,"") | G25: 0 | H25: =IF(AND(G25<>"",G25<>0),D25/G25,"") | I25: 32 | J25: =IF(AND(G25<>"",G25<>0),E25/G25,"") | R25: =IF(AND(I25<>"",I25<>0),G25/I25,"") -> 0 | S25: =D25/T25 -> 0 | T25: =$I$8*Z25*AA25/SUMPRODUCT($AA$25:$AA$55,$Z$25:$Z$55) -> 59284.026 | U25: =$I$9*Z25*AA25/SUMPRODUCT($AA$25:$AA$55,$Z$25:$Z$55) -> 7.2385868 | V25: =IF($I$12="","",U25/$I$12) -> 4.3086826 | W25: =IF(AA25<>"",IF(D25<>"",D25,($I$8-SUM($W24:W$25))*Z25*AA25/SUMPRODUCT($AA25:$AA$55,$Z25:$Z$55)),"") -> 0 | X25: =IF(AA25<>"",IF(E25<>"",E25,($I$9-SUM($X24:X$25))*Z25*AA25/SUMPRODUCT($AA25:$AA$55,$Z25:$Z$55)),"") -> 0 | Y25: =IF(AA25<>"",IF($I$12<>"",IF(G25<>"",G25,($I$9/$I$12-SUM($Y24:Y$25))*Z25*AA25/SUMPRODUCT($AA25:$AA$55,$Z25:$Z$55)),""),"") -> 0 | Z25: 1 | AA25: 1
A26: 2 | B26: 45993 | C26: вт | D26: 22077 | E26: 3 | F26: =IF(AND(E26<>"",E26<>0),D26/E26,"") -> 7359 | G26: 2 | H26: =IF(AND(G26<>"",G26<>0),D26/G26,"") -> 11038.5 | I26: 35 | J26: =IF(AND(G26<>"",G26<>0),E26/G26,"") -> 1.5 | Q26: 8593 | R26: =IF(AND(I26<>"",I26<>0),G26/I26,"") -> 0.057142857 | S26: =D26/T26 -> 0.37239374 | T26: =$I$8*Z26*AA26/SUMPRODUCT($AA$25:$AA$55,$Z$25:$Z$55) -> 59284.026 | U26: =$I$9*Z26*AA26/SUMPRODUCT($AA$25:$AA$55,$Z$25:$Z$55) -> 7.2385868 | V26: =IF($I$12="","",U26/$I$12) -> 4.3086826 | W26: =IF(AA26<>"",IF(D26<>"",D26,($I$8-SUM($W$25:W25))*Z26*AA26/SUMPRODUCT($AA26:$AA$55,$Z26:$Z$55)),"") -> 22077 | X26: =IF(AA26<>"",IF(E26<>"",E26,($I$9-SUM($X$25:X25))*Z26*AA26/SUMPRODUCT($AA26:$AA$55,$Z26:$Z$55)),"") -> 3 | Y26: =IF(AA26<>"",IF($I$12<>"",IF(G26<>"",G26,($I$9/$I$12-SUM($Y$25:Y25))*Z26*AA26/SUMPRODUCT($AA26:$AA$55,$Z26:$Z$55)),""),"") -> 2 | Z26: 1 | AA26: 1
A27: 3 | B27: 45994 | C27: ср | D27: 67931 | E27: 6 | F27: =IF(AND(E27<>"",E27<>0),D27/E27,"") -> 11321.833 | G27: 3 | H27: =IF(AND(G27<>"",G27<>0),D27/G27,"") -> 22643.667 | I27: 24 | J27: =IF(AND(G27<>"",G27<>0),E27/G27,"") -> 2 | M27: 15190 | N27: =27149+5307 -> 32456 | O27: 15390 | R27: =IF(AND(I27<>"",I27<>0),G27/I27,"") -> 0.125 | S27: =D27/T27 -> 1.1458567 | T27: =$I$8*Z27*AA27/SUMPRODUCT($AA$25:$AA$55,$Z$25:$Z$55) -> 59284.026 | U27: =$I$9*Z27*AA27/SUMPRODUCT($AA$25:$AA$55,$Z$25:$Z$55) -> 7.2385868 | V27: =IF($I$12="","",U27/$I$12) -> 4.3086826 | W27: =IF(AA27<>"",IF(D27<>"",D27,($I$8-SUM($W$25:W26))*Z27*AA27/SUMPRODUCT($AA27:$AA$55,$Z27:$Z$55)),"") -> 67931 | X27: =IF(AA27<>"",IF(E27<>"",E27,($I$9-SUM($X$25:X26))*Z27*AA27/SUMPRODUCT($AA27:$AA$55,$Z27:$Z$55)),"") -> 6 | Y27: =IF(AA27<>"",IF($I$12<>"",IF(G27<>"",G27,($I$9/$I$12-SUM($Y$25:Y26))*Z27*AA27/SUMPRODUCT($AA27:$AA$55,$Z27:$Z$55)),""),"") -> 3 | Z27: 1 | AA27: 1
A28: 4 | B28: 45995 | C28: чт | D28: 17372 | E28: 2 | F28: =IF(AND(E28<>"",E28<>0),D28/E28,"") -> 8686 | G28: 2 | H28: =IF(AND(G28<>"",G28<>0),D28/G28,"") -> 8686 | I28: 22 | J28: =IF(AND(G28<>"",G28<>0),E28/G28,"") -> 1 | K28: 11493 | R28: =IF(AND(I28<>"",I28<>0),G28/I28,"") -> 0.090909091 | S28: =D28/T28 -> 0.29303003 | T28: =$I$8*Z28*AA28/SUMPRODUCT($AA$25:$AA$55,$Z$25:$Z$55) -> 59284.026 | U28: =$I$9*Z28*AA28/SUMPRODUCT($AA$25:$AA$55,$Z$25:$Z$55) -> 7.2385868 | V28: =IF($I$12="","",U28/$I$12) -> 4.3086826 | W28: =IF(AA28<>"",IF(D28<>"",D28,($I$8-SUM($W$25:W27))*Z28*AA28/SUMPRODUCT($AA28:$AA$55,$Z28:$Z$55)),"") -> 17372 | X28: =IF(AA28<>"",IF(E27<>"",E27,($I$9-SUM($X$25:X27))*Z28*AA28/SUMPRODUCT($AA28:$AA$55,$Z28:$Z$55)),"") -> 6 | Y28: =IF(AA28<>"",IF($I$12<>"",IF(G28<>"",G28,($I$9/$I$12-SUM($Y$25:Y27))*Z28*AA28/SUMPRODUCT($AA28:$AA$55,$Z28:$Z$55)),""),"") -> 2 | Z28: 1 | AA28: 1
A29: 5 | B29: 45996 | C29: пт | D29: 32615 | E29: 5 | F29: =IF(AND(E29<>"",E29<>0),D29/E29,"") -> 6523 | G29: 3 | H29: =IF(AND(G29<>"",G29<>0),D29/G29,"") -> 10871.667 | I29: 39 | J29: =IF(AND(G29<>"",G29<>0),E29/G29,"") -> 1.6666667 | M29: 15922 | R29: =IF(AND(I29<>"",I29<>0),G29/I29,"") -> 0.076923077 | S29: =D29/T29 -> 0.5501482 | T29: =$I$8*Z29*AA29/SUMPRODUCT($AA$25:$AA$55,$Z$25:$Z$55) -> 59284.026 | U29: =$I$9*Z29*AA29/SUMPRODUCT($AA$25:$AA$55,$Z$25:$Z$55) -> 7.2385868 | V29: =IF($I$12="","",U29/$I$12) -> 4.3086826 | W29: =IF(AA29<>"",IF(D29<>"",D29,($I$8-SUM($W$25:W28))*Z29*AA29/SUMPRODUCT($AA29:$AA$55,$Z29:$Z$55)),"") -> 32615 | X29: =IF(AA29<>"",IF(E29<>"",E29,($I$9-SUM($X$25:X28))*Z29*AA29/SUMPRODUCT($AA29:$AA$55,$Z29:$Z$55)),"") -> 5 | Y29: =IF(AA29<>"",IF($I$12<>"",IF(G29<>"",G29,($I$9/$I$12-SUM($Y$25:Y28))*Z29*AA29/SUMPRODUCT($AA29:$AA$55,$Z29:$Z$55)),""),"") -> 3 | Z29: 1 | AA29: 1
A30: 6 | B30: 45997 | C30: сб | D30: 15486 | E30: 2 | F30: =IF(AND(E30<>"",E30<>0),D30/E30,"") -> 7743 | G30: 2 | H30: =IF(AND(G30<>"",G30<>0),D30/G30,"") -> 7743 | I30: 36 | J30: =IF(AND(G30<>"",G30<>0),E30/G30,"") -> 1 | R30: =IF(AND(I30<>"",I30<>0),G30/I30,"") -> 0.055555556 | S30: =D30/T30 -> 0.26121708 | T30: =$I$8*Z30*AA30/SUMPRODUCT($AA$25:$AA$55,$Z$25:$Z$55) -> 59284.026 | U30: =$I$9*Z30*AA30/SUMPRODUCT($AA$25:$AA$55,$Z$25:$Z$55) -> 7.2385868 | V30: =IF($I$12="","",U30/$I$12) -> 4.3086826 | W30: =IF(AA30<>"",IF(D30<>"",D30,($I$8-SUM($W$25:W29))*Z30*AA30/SUMPRODUCT($AA30:$AA$55,$Z30:$Z$55)),"") -> 15486 | X30: =IF(AA30<>"",IF(E30<>"",E30,($I$9-SUM($X$25:X29))*Z30*AA30/SUMPRODUCT($AA30:$AA$55,$Z30:$Z$55)),"") -> 2 | Y30: =IF(AA30<>"",IF($I$12<>"",IF(G30<>"",G30,($I$9/$I$12-SUM($Y$25:Y29))*Z30*AA30/SUMPRODUCT($AA30:$AA$55,$Z30:$Z$55)),""),"") -> 2 | Z30: 1 | AA30: 1
A31: 7 | B31: 45998 | C31: вс | D31: 11286 | E31: 2 | F31: =IF(AND(E31<>"",E31<>0),D31/E31,"") -> 5643 | G31: 2 | H31: =IF(AND(G31<>"",G31<>0),D31/G31,"") -> 5643 | I31: 36 | J31: =IF(AND(G31<>"",G31<>0),E31/G31,"") -> 1 | R31: =IF(AND(I31<>"",I31<>0),G31/I31,"") -> 0.055555556 | S31: =D31/T31 -> 0.19037169 | T31: =$I$8*Z31*AA31/SUMPRODUCT($AA$25:$AA$55,$Z$25:$Z$55) -> 59284.026 | U31: =$I$9*Z31*AA31/SUMPRODUCT($AA$25:$AA$55,$Z$25:$Z$55) -> 7.2385868 | V31: =IF($I$12="","",U31/$I$12) -> 4.3086826 | W31: =IF(AA31<>"",IF(D31<>"",D31,($I$8-SUM($W$25:W30))*Z31*AA31/SUMPRODUCT($AA31:$AA$55,$Z31:$Z$55)),"") -> 11286 | X31: =IF(AA31<>"",IF(E31<>"",E31,($I$9-SUM($X$25:X30))*Z31*AA31/SUMPRODUCT($AA31:$AA$55,$Z31:$Z$55)),"") -> 2 | Y31: =IF(AA31<>"",IF($I$12<>"",IF(G31<>"",G31,($I$9/$I$12-SUM($Y$25:Y30))*Z31*AA31/SUMPRODUCT($AA31:$AA$55,$Z31:$Z$55)),""),"") -> 2 | Z31: 1 | AA31: 1
A32: 8 | B32: 46010 | C32: пт | D32: 71288 | E32: 8 | F32: =IF(AND(E32<>"",E32<>0),D32/E32,"") -> 8911 | G32: 3 | H32: =IF(AND(G32<>"",G32<>0),D32/G32,"") -> 23762.667 | I32: 22 | J32: =IF(AND(G32<>"",G32<>0),E32/G32,"") -> 2.6666667 | K32: 43070 | R32: =IF(AND(I32<>"",I32<>0),G32/I32,"") -> 0.13636364 | S32: =D32/T32 -> 1.2024824 | T32: =$I$8*Z32*AA32/SUMPRODUCT($AA$25:$AA$55,$Z$25:$Z$55) -> 59284.026 | U32: =$I$9*Z32*AA32/SUMPRODUCT($AA$25:$AA$55,$Z$25:$Z$55) -> 7.2385868 | V32: =IF($I$12="","",U32/$I$12) -> 4.3086826 | W32: =IF(AA32<>"",IF(D32<>"",D32,($I$8-SUM($W$25:W31))*Z32*AA32/SUMPRODUCT($AA32:$AA$55,$Z32:$Z$55)),"") -> 71288 | X32: =IF(AA32<>"",IF(E32<>"",E32,($I$9-SUM($X$25:X31))*Z32*AA32/SUMPRODUCT($AA32:$AA$55,$Z32:$Z$55)),"") -> 8 | Y32: =IF(AA32<>"",IF($I$12<>"",IF(G32<>"",G32,($I$9/$I$12-SUM($Y$25:Y31))*Z32*AA32/SUMPRODUCT($AA32:$AA$55,$Z32:$Z$55)),""),"") -> 3 | Z32: 1 | AA32: 1
A33: 9 | B33: 46011 | C33: сб | D33: =13098+18113+13374+38720+14785+5029+31592 -> 134711 | E33: 21 | F33: =IF(AND(E33<>"",E33<>0),D33/E33,"") -> 6414.8095 | G33: 7 | H33: =IF(AND(G33<>"",G33<>0),D33/G33,"") -> 19244.429 | I33: 62 | J33: =IF(AND(G33<>"",G33<>0),E33/G33,"") -> 3 | K33: 19267 | R33: =IF(AND(I33<>"",I33<>0),G33/I33,"") -> 0.11290323 | S33: =D33/T33 -> 2.2722984 | T33: =$I$8*Z33*AA33/SUMPRODUCT($AA$25:$AA$55,$Z$25:$Z$55) -> 59284.026 | U33: =$I$9*Z33*AA33/SUMPRODUCT($AA$25:$AA$55,$Z$25:$Z$55) -> 7.2385868 | V33: =IF($I$12="","",U33/$I$12) -> 4.3086826 | W33: =IF(AA33<>"",IF(D33<>"",D33,($I$8-SUM($W$25:W32))*Z33*AA33/SUMPRODUCT($AA33:$AA$55,$Z33:$Z$55)),"") -> 134711 | X33: =IF(AA33<>"",IF(E33<>"",E33,($I$9-SUM($X$25:X32))*Z33*AA33/SUMPRODUCT($AA33:$AA$55,$Z33:$Z$55)),"") -> 21 | Y33: =IF(AA33<>"",IF($I$12<>"",IF(G33<>"",G33,($I$9/$I$12-SUM($Y$25:Y32))*Z33*AA33/SUMPRODUCT($AA33:$AA$55,$Z33:$Z$55)),""),"") -> 7 | Z33: 1 | AA33: 1
A34: 10 | B34: 46012 | C34: вс | D34: 24172 | E34: 2 | F34: =IF(AND(E34<>"",E34<>0),D34/E34,"") -> 12086 | G34: 1 | H34: =IF(AND(G34<>"",G34<>0),D34/G34,"") -> 24172 | I34: 33 | J34: =IF(AND(G34<>"",G34<>0),E34/G34,"") -> 2 | K34: 24172 | R34: =IF(AND(I34<>"",I34<>0),G34/I34,"") -> 0.03030303 | S34: =D34/T34 -> 0.40773209 | T34: =$I$8*Z34*AA34/SUMPRODUCT($AA$25:$AA$55,$Z$25:$Z$55) -> 59284.026 | U34: =$I$9*Z34*AA34/SUMPRODUCT($AA$25:$AA$55,$Z$25:$Z$55) -> 7.2385868 | V34: =IF($I$12="","",U34/$I$12) -> 4.3086826 | W34: =IF(AA34<>"",IF(D34<>"",D34,($I$8-SUM($W$25:W33))*Z34*AA34/SUMPRODUCT($AA34:$AA$55,$Z34:$Z$55)),"") -> 24172 | X34: =IF(AA34<>"",IF(E34<>"",E34,($I$9-SUM($X$25:X33))*Z34*AA34/SUMPRODUCT($AA34:$AA$55,$Z34:$Z$55)),"") -> 2 | Y34: =IF(AA34<>"",IF($I$12<>"",IF(G34<>"",G34,($I$9/$I$12-SUM($Y$25:Y33))*Z34*AA34/SUMPRODUCT($AA34:$AA$55,$Z34:$Z$55)),""),"") -> 1 | Z34: 1 | AA34: 1
A35: 11 | B35: 46013 | C35: пн | D35: =6382+6395+20889+4892 -> 38558 | E35: 6 | F35: =IF(AND(E35<>"",E35<>0),D35/E35,"") -> 6426.3333 | G35: 4 | H35: =IF(AND(G35<>"",G35<>0),D35/G35,"") -> 9639.5 | I35: 40 | J35: =IF(AND(G35<>"",G35<>0),E35/G35,"") -> 1.5 | P35: 20889 | R35: =IF(AND(I35<>"",I35<>0),G35/I35,"") -> 0.1 | S35: =D35/T35 -> 0.65039442 | T35: =$I$8*Z35*AA35/SUMPRODUCT($AA$25:$AA$55,$Z$25:$Z$55) -> 59284.026 | U35: =$I$9*Z35*AA35/SUMPRODUCT($AA$25:$AA$55,$Z$25:$Z$55) -> 7.2385868 | V35: =IF($I$12="","",U35/$I$12) -> 4.3086826 | W35: =IF(AA35<>"",IF(D35<>"",D35,($I$8-SUM($W$25:W34))*Z35*AA35/SUMPRODUCT($AA35:$AA$55,$Z35:$Z$55)),"") -> 38558 | X35: =IF(AA34<>"",IF(E34<>"",E34,($I$9-SUM($X$25:X33))*Z34*AA34/SUMPRODUCT($AA34:$AA$55,$Z34:$Z$55)),"") -> 2 | Y35: =IF(AA34<>"",IF($I$12<>"",IF(G34<>"",G34,($I$9/$I$12-SUM($Y$25:Y33))*Z34*AA34/SUMPRODUCT($AA34:$AA$55,$Z34:$Z$55)),""),"") -> 1 | Z35: 1 | AA35: 1
A36: 12 | B36: 46015 | C36: ср | D36: =11984+5001 -> 16985 | E36: =2 -> 2 | F36: =IF(AND(E36<>"",E36<>0),D36/E36,"") -> 8492.5 | G36: 2 | H36: =IF(AND(G36<>"",G36<>0),D36/G36,"") -> 8492.5 | I36: 20 | J36: =IF(AND(G36<>"",G36<>0),E36/G36,"") -> 1 | R36: =IF(AND(I36<>"",I36<>0),G36/I36,"") -> 0.1 | S36: =D36/T36 -> 0.28650213 | T36: =$I$8*Z36*AA36/SUMPRODUCT($AA$25:$AA$55,$Z$25:$Z$55) -> 59284.026 | U36: =$I$9*Z36*AA36/SUMPRODUCT($AA$25:$AA$55,$Z$25:$Z$55) -> 7.2385868 | V36: =IF($I$12="","",U36/$I$12) -> 4.3086826 | W36: =IF(AA36<>"",IF(D36<>"",D36,($I$8-SUM($W$25:W35))*Z36*AA36/SUMPRODUCT($AA36:$AA$55,$Z36:$Z$55)),"") -> 16985 | X36: =IF(AA36<>"",IF(E36<>"",E36,($I$9-SUM($X$25:X35))*Z36*AA36/SUMPRODUCT($AA36:$AA$55,$Z36:$Z$55)),"") -> 2 | Y36: =IF(AA36<>"",IF($I$12<>"",IF(G36<>"",G36,($I$9/$I$12-SUM($Y$25:Y35))*Z36*AA36/SUMPRODUCT($AA36:$AA$55,$Z36:$Z$55)),""),"") -> 2 | Z36: 1 | AA36: 1
A37: 13 | B37: 46016 | C37: чт | D37: =25368+10001 -> 35369 | E37: 4 | F37: =IF(AND(E37<>"",E37<>0),D37/E37,"") -> 8842.25 | G37: 2 | H37: =IF(AND(G37<>"",G37<>0),D37/G37,"") -> 17684.5 | I37: 26 | J37: =IF(AND(G37<>"",G37<>0),E37/G37,"") -> 2 | R37: =IF(AND(I37<>"",I37<>0),G37/I37,"") -> 0.076923077 | S37: =D37/T37 -> 0.59660253 | T37: =$I$8*Z37*AA37/SUMPRODUCT($AA$25:$AA$55,$Z$25:$Z$55) -> 59284.026 | U37: =$I$9*Z37*AA37/SUMPRODUCT($AA$25:$AA$55,$Z$25:$Z$55) -> 7.2385868 | V37: =IF($I$12="","",U37/$I$12) -> 4.3086826 | W37: =IF(AA37<>"",IF(D37<>"",D37,($I$8-SUM($W$25:W36))*Z37*AA37/SUMPRODUCT($AA37:$AA$55,$Z37:$Z$55)),"") -> 35369 | X37: =IF(AA37<>"",IF(E37<>"",E37,($I$9-SUM($X$25:X36))*Z37*AA37/SUMPRODUCT($AA37:$AA$55,$Z37:$Z$55)),"") -> 4 | Y37: =IF(AA37<>"",IF($I$12<>"",IF(G37<>"",G37,($I$9/$I$12-SUM($Y$25:Y36))*Z37*AA37/SUMPRODUCT($AA37:$AA$55,$Z37:$Z$55)),""),"") -> 2 | Z37: 1 | AA37: 1
A38: 14 | B38: 46017 | C38: пт | D38: 44761 | E38: 5 | F38: =IF(AND(E38<>"",E38<>0),D38/E38,"") -> 8952.2 | G38: 3 | H38: =IF(AND(G38<>"",G38<>0),D38/G38,"") -> 14920.333 | I38: 25 | J38: =IF(AND(G38<>"",G38<>0),E38/G38,"") -> 1.6666667 | K38: 25984 | R38: =IF(AND(I38<>"",I38<>0),G38/I38,"") -> 0.12 | S38: =D38/T38 -> 0.75502632 | T38: =$I$8*Z38*AA38/SUMPRODUCT($AA$25:$AA$46,$Z$25:$Z$46) -> 59284.026 | U38: =$I$9*Z38*AA38/SUMPRODUCT($AA$25:$AA$46,$Z$25:$Z$46) -> 7.2385868 | V38: =IF($I$12="","",U38/$I$12) -> 4.3086826 | W38: =IF(AA38<>"",IF(D38<>"",D38,($I$8-SUM($W$25:W37))*Z38*AA38/SUMPRODUCT($AA38:$AA$55,$Z38:$Z$55)),"") -> 44761 | X38: =IF(AA38<>"",IF(E38<>"",E38,($I$9-SUM($X$25:X37))*Z38*AA38/SUMPRODUCT($AA38:$AA$55,$Z38:$Z$55)),"") -> 5 | Y38: =IF(AA38<>"",IF($I$12<>"",IF(G38<>"",G38,($I$9/$I$12-SUM($Y$25:Y37))*Z38*AA38/SUMPRODUCT($AA38:$AA$55,$Z38:$Z$55)),""),"") -> 3 | Z38: 1 | AA38: 1
A39: 15 | B39: 46018 | C39: сб | D39: =13665+18785+11868+10001 -> 54319 | E39: 6 | F39: =IF(AND(E39<>"",E39<>0),D39/E39,"") -> 9053.1667 | G39: 3 | H39: =IF(AND(G39<>"",G39<>0),D39/G39,"") -> 18106.333 | I39: 29 | J39: =IF(AND(G39<>"",G39<>0),E39/G39,"") -> 2 | K39: 11990 | M39: 7090 | R39: =IF(AND(I39<>"",I39<>0),G39/I39,"") -> 0.10344828 | S39: =D39/T39 -> 0.91625019 | T39: =$I$8*Z39*AA39/SUMPRODUCT($AA$25:$AA$46,$Z$25:$Z$46) -> 59284.026 | U39: =$I$9*Z39*AA39/SUMPRODUCT($AA$25:$AA$46,$Z$25:$Z$46) -> 7.2385868 | V39: =IF($I$12="","",U39/$I$12) -> 4.3086826 | W39: =IF(AA39<>"",IF(D39<>"",D39,($I$8-SUM($W$25:W38))*Z39*AA39/SUMPRODUCT($AA39:$AA$47,$Z39:$Z$47)),"") -> 54319 | X39: =IF(AA39<>"",IF(E39<>"",E39,($I$9-SUM($X$25:X38))*Z39*AA39/SUMPRODUCT($AA39:$AA$55,$Z39:$Z$55)),"") -> 6 | Y39: =IF(AA39<>"",IF($I$12<>"",IF(G39<>"",G39,($I$9/$I$12-SUM($Y$25:Y38))*Z39*AA39/SUMPRODUCT($AA39:$AA$55,$Z39:$Z$55)),""),"") -> 3 | Z39: 1 | AA39: 1
A40: 16 | B40: 46019 | C40: вс | D40: =16293+7093+28876+3425+4693 -> 60380 | E40: 7 | F40: =IF(AND(E40<>"",E40<>0),D40/E40,"") -> 8625.7143 | G40: 5 | H40: =IF(AND(G40<>"",G40<>0),D40/G40,"") -> 12076 | J40: =IF(AND(G40<>"",G40<>0),E40/G40,"") -> 1.4 | K40: =11990+13490 -> 25480 | M40: 16293 | P40: 7093 | R40: =IF(AND(I40<>"",I40<>0),G40/I40,"") | S40: =D40/T40 -> 1.0184868 | T40: =$I$8*Z40*AA40/SUMPRODUCT($AA$25:$AA$46,$Z$25:$Z$46) -> 59284.026 | U40: =$I$9*Z40*AA40/SUMPRODUCT($AA$25:$AA$46,$Z$25:$Z$46) -> 7.2385868 | V40: =IF($I$12="","",U40/$I$12) -> 4.3086826 | W40: =IF(AA40<>"",IF(D40<>"",D40,($I$8-SUM($W$25:W39))*Z40*AA40/SUMPRODUCT($AA40:$AA$46,$Z40:$Z$46)),"") -> 60380 | X40: =IF(AA40<>"",IF(E40<>"",E40,($I$9-SUM($X$25:X39))*Z40*AA40/SUMPRODUCT($AA40:$AA$46,$Z40:$Z$46)),"") -> 7 | Y40: =IF(AA40<>"",IF($I$12<>"",IF(G40<>"",G40,($I$9/$I$12-SUM($Y$25:Y39))*Z40*AA40/SUMPRODUCT($AA40:$AA$55,$Z40:$Z$55)),""),"") -> 5 | Z40: 1 | AA40: 1
F41: =IF(AND(E41<>"",E41<>0),D41/E41,"") | H41: =IF(AND(G41<>"",G41<>0),D41/G41,"") | J41: =IF(AND(G41<>"",G41<>0),E41/G41,"") | R41: =IF(AND(I41<>"",I41<>0),G41/I41,"") | S41: =D41/T41 -> #DIV/0! | T41: =$I$8*Z41*AA41/SUMPRODUCT($AA$25:$AA$46,$Z$25:$Z$46) -> 0 | U41: =$I$9*Z41*AA41/SUMPRODUCT($AA$25:$AA$46,$Z$25:$Z$46) -> 0 | V41: =IF($I$12="","",U41/$I$12) -> 0 | W41: =IF(AA41<>"",IF(D41<>"",D41,($I$8-SUM($W$25:W40))*Z41*AA41/SUMPRODUCT($AA41:$AA$46,$Z41:$Z$46)),"") | X41: =IF(AA41<>"",IF(E41<>"",E41,($I$9-SUM($X$25:X40))*Z41*AA41/SUMPRODUCT($AA41:$AA$46,$Z41:$Z$46)),"") | Y41: =IF(AA41<>"",IF($I$12<>"",IF(G41<>"",G41,($I$9/$I$12-SUM($Y$25:Y40))*Z41*AA41/SUMPRODUCT($AA41:$AA$55,$Z41:$Z$55)),""),"")
F42: =IF(AND(E42<>"",E42<>0),D42/E42,"") | H42: =IF(AND(G42<>"",G42<>0),D42/G42,"") | J42: =IF(AND(G42<>"",G42<>0),E42/G42,"") | R42: =IF(AND(I42<>"",I42<>0),G42/I42,"") | S42: =D42/T42 -> #DIV/0! | T42: =$I$8*Z42*AA42/SUMPRODUCT($AA$25:$AA$46,$Z$25:$Z$46) -> 0 | U42: =$I$9*Z42*AA42/SUMPRODUCT($AA$25:$AA$46,$Z$25:$Z$46) -> 0 | V42: =IF($I$12="","",U42/$I$12) -> 0 | W42: =IF(AA42<>"",IF(D42<>"",D42,($I$8-SUM($W$25:W41))*Z42*AA42/SUMPRODUCT($AA42:$AA$46,$Z42:$Z$46)),"") | X42: =IF(AA42<>"",IF(E42<>"",E42,($I$9-SUM($X$25:X41))*Z42*AA42/SUMPRODUCT($AA42:$AA$46,$Z42:$Z$46)),"") | Y42: =IF(AA42<>"",IF($I$12<>"",IF(G42<>"",G42,($I$9/$I$12-SUM($Y$25:Y41))*Z42*AA42/SUMPRODUCT($AA42:$AA$46,$Z42:$Z$46)),""),"")
F43: =IF(AND(E43<>"",E43<>0),D43/E43,"") | H43: =IF(AND(G43<>"",G43<>0),D43/G43,"") | J43: =IF(AND(G43<>"",G43<>0),E43/G43,"") | R43: =IF(AND(I43<>"",I43<>0),G43/I43,"") | S43: =D43/T43 -> #DIV/0! | T43: =$I$8*Z43*AA43/SUMPRODUCT($AA$25:$AA$46,$Z$25:$Z$46) -> 0 | U43: =$I$9*Z43*AA43/SUMPRODUCT($AA$25:$AA$46,$Z$25:$Z$46) -> 0 | V43: =IF($I$12="","",U43/$I$12) -> 0 | W43: =IF(AA43<>"",IF(D43<>"",D43,($I$8-SUM($W$25:W42))*Z43*AA43/SUMPRODUCT($AA43:$AA$46,$Z43:$Z$46)),"") | X43: =IF(AA43<>"",IF(E43<>"",E43,($I$9-SUM($X$25:X42))*Z43*AA43/SUMPRODUCT($AA43:$AA$46,$Z43:$Z$46)),"") | Y43: =IF(AA43<>"",IF($I$12<>"",IF(G43<>"",G43,($I$9/$I$12-SUM($Y$25:Y42))*Z43*AA43/SUMPRODUCT($AA43:$AA$46,$Z43:$Z$46)),""),"")
F44: =IF(AND(E44<>"",E44<>0),D44/E44,"") | H44: =IF(AND(G44<>"",G44<>0),D44/G44,"") | J44: =IF(AND(G44<>"",G44<>0),E44/G44,"") | R44: =IF(AND(I44<>"",I44<>0),G44/I44,"") | S44: =D44/T44 -> #DIV/0! | T44: =$I$8*Z44*AA44/SUMPRODUCT($AA$25:$AA$46,$Z$25:$Z$46) -> 0 | U44: =$I$9*Z44*AA44/SUMPRODUCT($AA$25:$AA$46,$Z$25:$Z$46) -> 0 | V44: =IF($I$12="","",U44/$I$12) -> 0 | W44: =IF(AA44<>"",IF(D44<>"",D44,($I$8-SUM($W$25:W43))*Z44*AA44/SUMPRODUCT($AA44:$AA$46,$Z44:$Z$46)),"") | X44: =IF(AA44<>"",IF(E44<>"",E44,($I$9-SUM($X$25:X43))*Z44*AA44/SUMPRODUCT($AA44:$AA$46,$Z44:$Z$46)),"") | Y44: =IF(AA44<>"",IF($I$12<>"",IF(G44<>"",G44,($I$9/$I$12-SUM($Y$25:Y43))*Z44*AA44/SUMPRODUCT($AA44:$AA$46,$Z44:$Z$46)),""),"")
F45: =IF(AND(E45<>"",E45<>0),D45/E45,"") | H45: =IF(AND(G45<>"",G45<>0),D45/G45,"") | J45: =IF(AND(G45<>"",G45<>0),E45/G45,"") | R45: =IF(AND(I45<>"",I45<>0),G45/I45,"") | S45: =D45/T45 -> #DIV/0! | T45: =$I$8*Z45*AA45/SUMPRODUCT($AA$25:$AA$46,$Z$25:$Z$46) -> 0 | U45: =$I$9*Z45*AA45/SUMPRODUCT($AA$25:$AA$46,$Z$25:$Z$46) -> 0 | V45: =IF($I$12="","",U45/$I$12) -> 0 | W45: =IF(AA45<>"",IF(D45<>"",D45,($I$8-SUM($W$25:W44))*Z45*AA45/SUMPRODUCT($AA45:$AA$46,$Z45:$Z$46)),"") | X45: =IF(AA45<>"",IF(E45<>"",E45,($I$9-SUM($X$25:X44))*Z45*AA45/SUMPRODUCT($AA45:$AA$46,$Z45:$Z$46)),"") | Y45: =IF(AA45<>"",IF($I$12<>"",IF(G45<>"",G45,($I$9/$I$12-SUM($Y$25:Y44))*Z45*AA45/SUMPRODUCT($AA45:$AA$46,$Z45:$Z$46)),""),"")
F46: =IF(AND(E46<>"",E46<>0),D46/E46,"") | H46: =IF(AND(G46<>"",G46<>0),D46/G46,"") | J46: =IF(AND(G46<>"",G46<>0),E46/G46,"") | R46: =IF(AND(I46<>"",I46<>0),G46/I46,"") | S46: =D46/T46 -> #DIV/0! | T46: =$I$8*Z46*AA46/SUMPRODUCT($AA$25:$AA$46,$Z$25:$Z$46) -> 0 | U46: =$I$9*Z46*AA46/SUMPRODUCT($AA$25:$AA$46,$Z$25:$Z$46) -> 0 | V46: =IF($I$12="","",U46/$I$12) -> 0 | W46: =IF(AA46<>"",IF(D46<>"",D46,($I$8-SUM($W$25:W45))*Z46*AA46/SUMPRODUCT($AA46:$AA$46,$Z46:$Z$46)),"") | X46: =IF(AA46<>"",IF(E46<>"",E46,($I$9-SUM($X$25:X39))*Z46*AA46/SUMPRODUCT($AA46:$AA$46,$Z46:$Z$46)),"") | Y46: =IF(AA46<>"",IF($I$12<>"",IF(G46<>"",G46,($I$9/$I$12-SUM($Y$25:Y39))*Z46*AA46/SUMPRODUCT($AA46:$AA$46,$Z46:$Z$46)),""),"")
A47: Андруневчина | B47: 45999 | C47: пн | D47: 5653 | E47: 1 | F47: =IF(AND(E47<>"",E47<>0),D47/E47,"") -> 5653 | G47: 1 | H47: =IF(AND(G47<>"",G47<>0),D47/G47,"") -> 5653 | I47: 1 | J47: =IF(AND(G47<>"",G47<>0),E47/G47,"") -> 1 | R47: =IF(AND(I47<>"",I47<>0),G47/I47,"") -> 1 | S47: =D47/T47 -> #DIV/0! | T47: =$I$8*Z47*AA47/SUMPRODUCT($AA$25:$AA$46,$Z$25:$Z$46) -> 0 | U47: =$I$9*Z47*AA47/SUMPRODUCT($AA$25:$AA$46,$Z$25:$Z$46) -> 0 | V47: =IF($I$12="","",U47/$I$12) -> 0 | W47: =IF(AA47<>"",IF(D47<>"",D47,($I$8-SUM($W$25:W46))*Z47*AA47/SUMPRODUCT($AA$47:$AA47,$Z$47:$Z47)),"") | X47: =IF(AA47<>"",IF(E47<>"",E47,($I$9-SUM(#REF!))*Z47*AA47/SUMPRODUCT($AA$47:$AA47,$Z$47:$Z47)),"") | Y47: =IF(AA47<>"",IF($I$12<>"",IF(G47<>"",G47,($I$9/$I$12-SUM(#REF!))*Z47*AA47/SUMPRODUCT($AA$47:$AA47,$Z$47:$Z47)),""),"")
B48: итого | D48: =SUM(D25:D47) -> 652963 | E48: =SUM(E25:E47) -> 82 | F48: =IF(AND(E48<>"",E48<>0),D48/E48,"") -> 7962.9634 | G48: =SUM(G25:G47) -> 45 | H48: =IF(AND(G48<>"",G48<>0),D48/G48,"") -> 14510.289 | I48: =SUM(I25:I47) -> 482 | J48: =IF(AND(G48<>"",G48<>0),E48/G48,"") -> 1.8222222 | K48: =SUM(K25:K47) -> 161456 | L48: =SUM(L25:L47) -> 0 | M48: =SUM(M25:M47) -> 54495 | N48: =SUM(N25:N47) -> 32456 | O48: =SUM(O25:O47) -> 15390 | Q48: =SUM(Q25:Q47) -> 8593 | R48: =IF(AND(I48<>"",I48<>0),G48/I48,"") -> 0.093360996 | S48: =D48/T48 -> 0.68838421 | T48: =SUM(T25:T47) -> 948544.42 | U48: =SUM(U25:U47) -> 115.81739 | V48: =SUM(V25:V47) -> 68.938922 | W48: =SUM(W25:W47) -> 647310 | X48: =SUM(X25:X47) -> 81 | Y48: =SUM(Y25:Y47) -> 41
D49: =SUMIF(D25:D47,"",T25:T47)+D48 -> 652963

Sheet Вед-ть УМ
A1: =График!B1 -> Декабрь, 2025
A2: =График!B3 -> ул. Севастопольская, 62 | D2: =График!B4 -> GL-0004
A3: Сотрудник | D3: Выплачено на карту | E3: Выплачено наличными по платежной ведомости | F3: Дополнительные начисления, доплаты | G3: Оклад | H3: Бонусная часть от личных продаж | I3: Бонусная часть от общих продаж | J3: Базовый бонус за выполнение плана | K3: Итого: | L3: Вычеты | M3: Итого к выдаче с учетом авансов и вычетов | N3: Подпись
A4: =График!B28 -> Стекольщикова Алла | D4: =44000-C8 -> 38280 | F4: =H8+H9 -> 21178.145 | G4: =D13 -> 23300 | H4: =D20 -> 43782.6 | I4: =M20 -> 14358.05 | J4: =M13 -> 12705 | K4: =H4+J4+G4+F4+I4 -> 115323.8 | L4: =C8+C9+C10+C11 -> 5920 | M4: =K4-L4-D4-E4 -> 71123.795
B6: Вычеты | G6: Доп начисления
B7: Дата | C7: Сумма | D7: Описание | G7: Дата | H7: Сумма | J7: Описание
B8: 46022 | C8: 5720 | D8: НДФЛ декабрь 2025 | G8: 46022 | H8: =Центрум!E62*1%+9694.75 -> 21178.145 | J8: Администартивный %
B9: 46031 | C9: 200 | D9: Вычет по инвентаризационной ведомости от 09.01 | G9: 46022 | H9: 0 | J9: Чек-лист декабрь 2025
G10: 46022 | H10: 0 | J10: % наличного оборота < 60%
A13: Оклад: | D13: =G17+G18 -> 23300 | I13: Базовый бонус | M13: =K17+K18 -> 12705
B15: Оклад: | I15: Базовый бонус за выполнение плана
B16: Дней | C16: Магазин | D16: Должность | E16: Зачислено часов | F16: Ставка за час, руб | G16: Начислено за день, руб | I16: Магазин | J16: КВП | K16: Начисленный ББ
B17: =График!AI28 -> 25 | C17: =A2 -> ул. Севастопольская, 62 | D17: УМ | E17: =График!AJ28 -> 233 | F17: 100 | G17: =E17*F17 -> 23300 | I17: =C17 -> ул. Севастопольская, 62 | J17: 1 | K17: 12705
A20: БонуснаяЧасть | D20: =G25+G26 -> 43782.6 | I20: Бонусная часть от общих продаж | M20: =N25+N26 -> 14358.05
B23: Бонус от личных продаж по категории товара | I23: Бонус от общих продаж
B24: Сотрудник | C24: Магазин | E24: Процент от продажи | F24: Продано на сумму, руб | G24: Начисленный бонус от продаж, руб | I24: Сотрудник | J24: Магазин | K24: Кол-во отработанных личных часов | L24: Кол-во отработанных общих часов | M24: Процент от продажи | N24: Начисленный бонус от продаж, руб
B25: =A4 -> Стекольщикова Алла | C25: =A2 -> ул. Севастопольская, 62 | E25: 0.05 | F25: ='Стекольщикова А. А.'!J8 -> 875652 | G25: =F25*E25 -> 43782.6 | I25: =B25 -> Стекольщикова Алла | J25: =C25 -> ул. Севастопольская, 62 | K25: =E17 -> 233 | L25: =График!AJ29 -> 1002 | M25: 0.02 | N25: =Центрум!J8*M25*K25/L25 -> 14358.05

Sheet Вед-ть Козлова
A1: =График!B1 -> Декабрь, 2025
A2: =График!B3 -> ул. Севастопольская, 62 | D2: =График!B4 -> GL-0004
A3: Сотрудник | D3: Выплачено на карту | E3: Выплачено наличными по платежной ведомости | F3: Дополнительные начисления, доплаты | G3: Оклад | H3: Бонусная часть от личных продаж | I3: Бонусная часть от общих продаж | J3: Базовый бонус за выполнение плана | K3: Итого: | L3: Вычеты | M3: Итого к выдаче с учетом авансов и вычетов | N3: Подпись
A4: =График!B26 -> Козлова Валерия | D4: =36000-C8 -> 31320 | F4: =H8+H9 -> 0 | G4: =D13 -> 21500 | H4: =D21 -> 21995.35 | I4: =M21 -> 13955.547 | J4: =M13 -> 11220 | K4: =H4+J4+G4+F4+I4 -> 68670.897 | L4: =C8+C9 -> 4880 | M4: =K4-L4-D4-E4 -> 32470.897
B6: Вычеты | G6: Доп начисления
B7: Дата | C7: Сумма | D7: Описание | G7: Дата | H7: Сумма | J7: Описание
B8: 46022 | C8: 4680 | D8: НДФЛ декабрь 2025
B9: 46031 | C9: 200 | D9: Вычет по инвентаризационной ведомости от 09.01
A13: Оклад: | D13: =G17+G19+G18 -> 21500 | I13: Базовый бонус | M13: =K17+K19+K18 -> 11220
B15: Оклад: | I15: Базовый бонус за выполнение плана
B16: Дней | C16: Магазин | D16: Должность | E16: Зачислено часов | F16: Ставка за час, руб | G16: Начислено за день, руб | I16: Магазин | J16: КВП | K16: Начисленный ББ
B17: =График!AI26 -> 21 | C17: =A2 -> ул. Севастопольская, 62 | D17: ПК | E17: =График!AJ26 -> 204 | F17: 100 | G17: =E17*F17 -> 20400 | I17: =C17 -> ул. Севастопольская, 62 | J17: 1 | K17: =G17*55% -> 11220
B18: 1 | C18: ул. Евпаторийское шоссе, 8 | D18: ПК | E18: 11 | F18: 100 | G18: =E18*F18 -> 1100 | I18: =C18 -> ул. Евпаторийское шоссе, 8 | J18: 0.5593 | K18: 0
A21: БонуснаяЧасть | D21: =G26+G27+G28 -> 21995.35 | I21: Бонусная часть от общих продаж | M21: =N26+N27+N28 -> 13955.547
B24: Бонус от личных продаж по категории товара | I24: Бонус от общих продаж
B25: Сотрудник | C25: Магазин | E25: Процент от продажи | F25: Продано на сумму, руб | G25: Начисленный бонус от продаж, руб | I25: Сотрудник | J25: Магазин | K25: Кол-во отработанных личных часов | L25: Кол-во отработанных общих часов | M25: Процент от продажи | N25: Начисленный бонус от продаж, руб
B26: =A4 -> Козлова Валерия | C26: =A2 -> ул. Севастопольская, 62 | E26: 0.05 | F26: ='Козлова В. Э.'!J8 -> 439907 | G26: =F26*E26 -> 21995.35 | I26: =B26 -> Козлова Валерия | J26: =C26 -> ул. Севастопольская, 62 | K26: =E17 -> 204 | L26: =График!AJ29 -> 1002 | M26: 0.02 | N26: =Центрум!J8*M26*K26/L26 -> 12570.997
B27: =A4 -> Козлова Валерия | C27: =C18 -> ул. Евпаторийское шоссе, 8 | E27: 0.055 | F27: 0 | G27: =F27*E27 -> 0 | I27: =B27 -> Козлова Валерия | J27: =C18 -> ул. Евпаторийское шоссе, 8 | K27: =E18 -> 11 | L27: 465 | M27: 0.04 | N27: =1463218*M27*K27/L27 -> 1384.5504

Sheet Вед-ть Свидовская
A1: =График!B1 -> Декабрь, 2025
A2: =График!B3 -> ул. Севастопольская, 62 | D2: =График!B4 -> GL-0004
A3: Сотрудник | D3: Выплачено на карту | E3: Выплачено наличными по платежной ведомости | F3: Дополнительные начисления, доплаты | G3: Оклад | H3: Бонусная часть от личных продаж | I3: Бонусная часть от общих продаж | J3: Базовый бонус за выполнение плана | K3: Итого: | L3: Вычеты | M3: Итого к выдаче с учетом авансов и вычетов | N3: Подпись
A4: =График!B27 -> Свидовская София | D4: =36000-C8 -> 31320 | F4: =H8+H9 -> 0 | G4: =D13 -> 20200 | H4: =D20 -> 32897.726 | I4: =M20 -> 12447.752 | J4: =M13 -> 11110 | K4: =H4+J4+G4+F4+I4 -> 76655.478 | L4: =C8+C9+C10+C11 -> 4880 | M4: =K4-L4-D4-E4 -> 40455.478
B6: Вычеты | G6: Доп начисления
B7: Дата | C7: Сумма | D7: Описание | G7: Дата | H7: Сумма | J7: Описание
B8: 46022 | C8: 4680 | D8: НДФЛ декабрь 2025
B9: 46031 | C9: 200 | D9: Вычет по инвентаризационной ведомости от 09.01
A13: Оклад: | D13: =G17+G18 -> 20200 | I13: Базовый бонус | M13: =K17+K18 -> 11110
B15: Оклад: | I15: Базовый бонус за выполнение плана
B16: Дней | C16: Магазин | D16: Должность | E16: Зачислено часов | F16: Ставка за час, руб | G16: Начислено за день, руб | I16: Магазин | J16: КВП | K16: Начисленный ББ
B17: =График!AI27 -> 21 | C17: =A2 -> ул. Севастопольская, 62 | D17: ПК | E17: =График!AJ27 -> 202 | F17: 100 | G17: =E17*F17 -> 20200 | I17: =C17 -> ул. Севастопольская, 62 | J17: 1 | K17: =G17*55% -> 11110
A20: БонуснаяЧасть | D20: =G25+G26 -> 32897.726 | I20: Бонусная часть от общих продаж | M20: =N25+N26 -> 12447.752
B23: Бонус от личных продаж по категории товара | I23: Бонус от общих продаж
B24: Сотрудник | C24: Магазин | E24: Процент от продажи | F24: Продано на сумму, руб | G24: Начисленный бонус от продаж, руб | I24: Сотрудник | J24: Магазин | K24: Кол-во отработанных личных часов | L24: Кол-во отработанных общих часов | M24: Процент от продажи | N24: Начисленный бонус от продаж, руб
B25: =A4 -> Свидовская София | C25: =A2 -> ул. Севастопольская, 62 | E25: 0.05 | F25: ='Свидовская С. А.'!J8 -> 657954.52 | G25: =F25*E25 -> 32897.726 | I25: =B25 -> Свидовская София | J25: =C25 -> ул. Севастопольская, 62 | K25: =E17 -> 202 | L25: =График!AJ29 -> 1002 | M25: 0.02 | N25: =Центрум!J8*M25*K25/L25 -> 12447.752

Sheet Вед-ть Корж
A1: =График!B1 -> Декабрь, 2025
A2: =График!B3 -> ул. Севастопольская, 62 | D2: =График!B4 -> GL-0004
A3: Сотрудник | D3: Выплачено на карту | E3: Выплачено наличными по платежной ведомости | F3: Дополнительные начисления, доплаты | G3: Оклад | H3: Бонусная часть от личных продаж | I3: Бонусная часть от общих продаж | J3: Базовый бонус за выполнение плана | K3: Итого: | L3: Вычеты | M3: Итого к выдаче с учетом авансов и вычетов | N3: Подпись
A4: =График!B25 -> Корж Анастасия | D4: =36000-C8 -> 31320 | F4: =H8+H9 -> 0 | G4: =D13 -> 20700 | H4: =D21 -> 23040.619 | I4: =M21 -> 12755.864 | J4: =M13 -> 11385 | K4: =H4+J4+G4+F4+I4 -> 67881.483 | L4: =C8+C9+C10+C11 -> 4880 | M4: =K4-L4-D4-E4 -> 31681.483
B6: Вычеты | G6: Доп начисления
B7: Дата | C7: Сумма | D7: Описание | G7: Дата | H7: Сумма | J7: Описание
B8: 46022 | C8: 4680 | D8: НДФЛ декабрь 2025
B9: 46031 | C9: 200 | D9: Вычет по инвентаризационной ведомости от 09.01
A13: Оклад: | D13: =G17+G19+G18 -> 20700 | I13: Базовый бонус | M13: =K17+K19+K18 -> 11385
B15: Оклад: | I15: Базовый бонус за выполнение плана
B16: Дней | C16: Магазин | D16: Должность | E16: Зачислено часов | F16: Ставка за час, руб | G16: Начислено за день, руб | I16: Магазин | J16: КВП | K16: Начисленный ББ
B17: =График!AI25 -> 21 | C17: =A2 -> ул. Севастопольская, 62 | D17: ПК | E17: =График!AJ25 -> 207 | F17: 100 | G17: =E17*F17 -> 20700 | I17: =C17 -> ул. Севастопольская, 62 | J17: 1 | K17: =G17*55% -> 11385
A21: БонуснаяЧасть | D21: =G26+G27+G28 -> 23040.619 | I21: Бонусная часть от общих продаж | M21: =N26+N27+N28 -> 12755.864
B24: Бонус от личных продаж по категории товара | I24: Бонус от общих продаж
B25: Сотрудник | C25: Магазин | E25: Процент от продажи | F25: Продано на сумму, руб | G25: Начисленный бонус от продаж, руб | I25: Сотрудник | J25: Магазин | K25: Кол-во отработанных личных часов | L25: Кол-во отработанных общих часов | M25: Процент от продажи | N25: Начисленный бонус от продаж, руб
B26: =A4 -> Корж Анастасия | C26: =A2 -> ул. Севастопольская, 62 | E26: 0.05 | F26: ='Корж А. А.'!J8 -> 460812.37 | G26: =F26*E26 -> 23040.619 | I26: =B26 -> Корж Анастасия | J26: =C26 -> ул. Севастопольская, 62 | K26: =E17 -> 207 | L26: =График!AJ29 -> 1002 | M26: 0.02 | N26: =Центрум!J8*M26*K26/L26 -> 12755.864

Sheet Вед-ть Доп сотрудник
A1: =График!B1 -> Декабрь, 2025
A2: =График!B3 -> ул. Севастопольская, 62 | D2: =График!B4 -> GL-0004
A3: Сотрудник | D3: Выплачено на карту | E3: Выплачено наличными по платежной ведомости | F3: Дополнительные начисления, доплаты | G3: Оклад | H3: Бонусная часть от личных продаж | I3: Бонусная часть от общих продаж | J3: Базовый бонус за выполнение плана | K3: Итого: | L3: Вычеты | M3: Итого к выдаче с учетом авансов и вычетов | N3: Подпись
A4: =График!B24 -> Рогалевич Ирина | F4: =H8+H9 -> 9694.7469 | G4: =D13 -> 31200 | H4: =D20 -> 32365.5 | I4: =M20 -> 9613.1151 | J4: =M13 -> 9680 | K4: =H4+J4+G4+F4+I4 -> 92553.362 | L4: =C8+C9+C10+C11 -> 200 | M4: =K4-L4-D4-E4 -> 92353.362
B6: Вычеты | G6: Доп начисления
B7: Дата | C7: Сумма | D7: Описание | G7: Дата | H7: Сумма | J7: Описание
B8: 46031 | C8: 200 | D8: Вычет по инвентаризационной ведомости от 09.01 | G8: 46022 | H8: =Центрум!D62*1%/2 -> 9694.7469 | J8: Администартивный %
A13: Оклад: | D13: =G17+G18 -> 31200 | I13: Базовый бонус | M13: =K17+K18 -> 9680
B15: Оклад: | I15: Базовый бонус за выполнение плана
B16: Дней | C16: Магазин | D16: Должность | E16: Зачислено часов | F16: Ставка за час, руб | G16: Начислено за день, руб | I16: Магазин | J16: КВП | K16: Начисленный ББ
B17: =График!AI24 -> 16 | C17: =A2 -> ул. Севастопольская, 62 | D17: УМ | E17: =График!AJ24 -> 156 | F17: 200 | G17: =E17*F17 -> 31200 | I17: =C17 -> ул. Севастопольская, 62 | J17: 1 | K17: 9680
A20: БонуснаяЧасть | D20: =G25+G26 -> 32365.5 | I20: Бонусная часть от общих продаж | M20: =N25+N26 -> 9613.1151
B23: Бонус от личных продаж по категории товара | I23: Бонус от общих продаж
B24: Сотрудник | C24: Магазин | E24: Процент от продажи | F24: Продано на сумму, руб | G24: Начисленный бонус от продаж, руб | I24: Сотрудник | J24: Магазин | K24: Кол-во отработанных личных часов | L24: Кол-во отработанных общих часов | M24: Процент от продажи | N24: Начисленный бонус от продаж, руб
B25: =A4 -> Рогалевич Ирина | C25: =A2 -> ул. Севастопольская, 62 | E25: 0.05 | F25: ='Доп сотрудник'!J8-5653 -> 647310 | G25: =F25*E25 -> 32365.5 | I25: =B25 -> Рогалевич Ирина | J25: =C25 -> ул. Севастопольская, 62 | K25: =E17 -> 156 | L25: =График!AJ29 -> 1002 | M25: 0.02 | N25: =Центрум!J8*M25*K25/L25 -> 9613.1151

Sheet График
B1: Декабрь, 2025
B2: г. Симферополь
B3: ул. Севастопольская, 62
B4: GL-0004
B5: 10.00-21.00
B6: ФОТ | C6: Кол-во дней в месяц | AK6: 30
C7: Премия Директора, грн.
D8: пн | E8: вт | F8: ср | G8: чт | H8: пт | I8: сб | J8: вс | K8: пн | L8: вт | M8: ср | N8: чт | O8: пт | P8: сб | Q8: вс | R8: пн | S8: вт | T8: ср | U8: чт | V8: пт | W8: сб | X8: вс | Y8: пн | Z8: вт | AA8: ср | AB8: чт | AC8: пт | AD8: сб | AE8: вс | AF8: пн | AG8: вт | AH8: ср | AJ8: Часы | AK8: Выходные | AL8: Отпуск | AM8: Больничный (официальный) | AN8: Дни стажировки
A10: № | B10: ФИО | C10: Должность | D10: 1 | E10: 2 | F10: 3 | G10: 4 | H10: 5 | I10: 6 | J10: 7 | K10: 8 | L10: 9 | M10: 10 | N10: 11 | O10: 12 | P10: 13 | Q10: 14 | R10: 15 | S10: 16 | T10: 17 | U10: 18 | V10: 19 | W10: 20 | X10: 21 | Y10: 22 | Z10: 23 | AA10: 24 | AB10: 25 | AC10: 26 | AD10: 27 | AE10: 28 | AF10: 29 | AG10: 30 | AH10: 31 | AI10: Дни
A11: 18 | AI11: =COUNTIF(D11:AH11,">0") -> 0 | AJ11: 0 | AK11: 0 | AL11: 0 | AM11: 0 | AN11: 0
A12: 17 | AI12: =COUNTIF(D12:AH12,">0") -> 0 | AJ12: 0 | AK12: 0 | AL12: 0 | AM12: 0 | AN12: 0
A13: 16 | AI13: =COUNTIF(D13:AH13,">0") -> 0 | AJ13: 0 | AK13: 0 | AL13: 0 | AM13: 0 | AN13: 0
A14: 15 | AI14: =COUNTIF(D14:AH14,">0") -> 0 | AJ14: 0 | AK14: 0 | AL14: 0 | AM14: 0 | AN14: 0
A15: 14 | AI15: =COUNTIF(D15:AH15,">0") -> 0 | AJ15: 0 | AK15: 0 | AL15: 0 | AM15: 0 | AN15: 0
A16: 13 | AI16: =COUNTIF(D16:AH16,">0") -> 0 | AJ16: 0 | AK16: 0 | AL16: 0 | AM16: 0 | AN16: 0
A17: 12 | AI17: =COUNTIF(D17:AH17,">0") -> 0 | AJ17: 0 | AK17: 0 | AL17: 0 | AM17: 0 | AN17: 0
A18: 11 | AI18: =COUNTIF(D18:AH18,">0") -> 0 | AJ18: 0 | AK18: 0 | AL18: 0 | AM18: 0 | AN18: 0
A19: 10 | AI19: =COUNTIF(D19:AH19,">0") -> 0 | AJ19: 0 | AK19: 0 | AL19: 0 | AM19: 0 | AN19: 0
A20: 9 | AI20: =COUNTIF(D20:AH20,">0") -> 0 | AJ20: 0 | AK20: 0 | AL20: 0 | AM20: 0 | AN20: 0
A21: 8 | AI21: =COUNTIF(D21:AH21,">0") -> 0 | AJ21: 0 | AK21: 0 | AL21: 0 | AM21: 0 | AN21: 0
A22: 7 | AI22: =COUNTIF(D22:AH22,">0") -> 0 | AJ22: 0 | AK22: 0 | AL22: 0 | AM22: 0 | AN22: 0
A23: 6 | AI23: =COUNTIF(D23:AH23,">0") -> 0 | AJ23: 0 | AK23: 0 | AL23: 0 | AM23: 0 | AN23: 0
A24: 5 | B24: Рогалевич Ирина | C24: УМ | D24: 11 | E24: 11 | F24: 9 | G24: 9 | H24: 9 | I24: 11 | J24: 11 | V24: 10 | W24: 11 | X24: 9 | Y24: 11 | AA24: 9 | AB24: 9 | AC24: 9 | AD24: 9 | AE24: 8 | AI24: =COUNTIF(D24:AH24,">0") -> 16 | AJ24: =SUMIF(D24:AH24,">0") -> 156 | AK24: 0 | AL24: 0 | AM24: 0 | AN24: 0
A25: 4 | B25: Корж Анастасия | C25: ПК | D25: в | E25: в | F25: 9 | G25: 9 | H25: в | I25: в | J25: 9 | K25: 11 | L25: в | M25: 11 | N25: 9 | O25: в | P25: 9 | Q25: 9 | R25: в | S25: 11 | T25: 11 | U25: 11 | V25: в | W25: в | X25: 9 | Y25: в | Z25: 11 | AA25: 9 | AB25: 9 | AC25: 9 | AD25: 11 | AE25: 11 | AF25: 9 | AG25: 11 | AH25: 9 | AI25: =COUNTIF(D25:AH25,">0") -> 21 | AJ25: =SUMIF(D25:AH25,">0") -> 207 | AK25: =COUNTIF(D25:AH25,"В") -> 10 | AL25: 0 | AM25: 0 | AN25: 0
